Workbook

Sheet Commencer ici
B2: Calculateur de faisabilité financière de mini-réseau
B3: Hybride solaire PV + batterie + diesel | modèle annuel sur 20 ans | édition accès à l'énergie
B5: À QUELLE QUESTION RÉPOND CET OUTIL
B6: Ce mini-réseau est-il financièrement viable, peut-il supporter de la dette, et quelle subvention (grant / RBF) comble le déficit ?
B8: MODE D'EMPLOI (10 minutes)
B9: 1. Allez dans « Hypothèses ». Modifiez UNIQUEMENT les cellules jaunes à texte bleu. Toutes les autres cellules sont des formules.
B10: 2. Saisissez vos segments de clientèle (ménages, usagers productifs, commerces, institutions).
B11: 3. Vérifiez le dimensionnement automatique dans « Hypothèses » (PV, batterie, diesel). Saisissez une valeur dans la colonne Forçage pour imposer votre propre conception.
B12: 4. Saisissez les coûts unitaires, les coûts d'exploitation et la structure de financement (grant, RBF par raccordement, dette).
B13: 5. Lisez le « Tableau de bord » : TRI, VAN, LCOE, DSCR, délai de récupération et déficit de viabilité (subvention nécessaire pour atteindre votre taux de rendement minimal).
B14: 6. Utilisez les leviers de scénario dans « Hypothèses » (multiplicateurs de tarif, demande, CAPEX) pour tester la résistance du projet.
B16: LÉGENDE DES COULEURS
... B37: Licence : un utilisateur / une organisation. Revente et redistribution interdites.

Sheet Hypothèses
A1: HYPOTHÈSES
A2: Ne modifiez que les cellules jaunes. Les valeurs d'exemple sont illustratives et ne sont pas des références.
A5: 1. PROJET
A6: Nom du projet | C6: Mini-réseau villageois (exemple)
A7: Pays / site | C7: Site exemple
A8: Libellé de la devise | C8: USD | H8: Libellé uniquement. Tous les montants doivent être saisis dans cette devise.
A9: Première année d'exploitation | C9: 2027 | D9: année
A10: Durée de vie du projet | C10: 20 | D10: ans | H10: Maximum 20. Les flux au-delà de cette année sont nuls.
A11: Taux d'actualisation / taux de rendement minimal (projet) | C11: 0.1 | H11: Utilisé pour la VAN, le LCOE et le déficit de viabilité.
A12: TRI cible des fonds propres | C12: 0.15
A13: DSCR minimum exigé par le prêteur | C13: 1.3
A14: Indexation du tarif | C14: 0.03 | D14: par an
A15: Indexation des coûts (OPEX, carburant) | C15: 0.03 | D15: par an
A16: Taux d'impôt sur les sociétés | C16: 0.25
A17: Durée d'amortissement fiscal | C17: 15 | D17: ans | H17: Linéaire sur le CAPEX total.
A19: 2. LEVIERS DE SCÉNARIO (1,00 = cas de base)
A20: Multiplicateur de tarif | C20: 1
A21: Multiplicateur de demande | C21: 1
A22: Multiplicateur de CAPEX | C22: 1
A23: Multiplicateur d'OPEX | C23: 1
A25: 3. CLIENTS & DEMANDE
A26: Segment | B26: Clients | C26: kWh / mois | D26: Tarif /kWh | E26: Frais de racc. | F26: Facture mensuelle
A27: Ménages | B27: 800 | C27: 15 | D27: 0.4 | E27: 10 | F27: =C27*D27 -> 6
A28: Usagers productifs (moulins, soudure, chambres froides) | B28: 60 | C28: 250 | D28: 0.35 | E28: 25 | F28: =C28*D28 -> 87.5
A29: Commerces (boutiques, bars, kiosques) | B29: 100 | C29: 50 | D29: 0.4 | E29: 15 | F29: =C29*D29 -> 20
A30: Institutions (centre de santé, école, eau) | B30: 10 | C30: 300 | D30: 0.35 | E30: 50 | F30: =C30*D30 -> 105
A31: Autre / personnalisé | B31: 0 | C31: 0 | D31: 0 | E31: 0 | F31: =C31*D31 -> 0
A32: Total / moyenne pondérée | B32: =SUM(B27:B31) -> 970 | C32: =IFERROR(SUMPRODUCT(B27:B31,C27:C31)/B32,0) -> 36.082474 | D32: =IFERROR(SUMPRODUCT(B27:B31,C27:C31,D27:D31)/SUMPRODUCT(B27:B31,C27:C31),0) -> 0.37428571
A34: Montée en charge des raccordements - année 1 (% des clients raccordés) | C34: 0.6
A35: Montée en charge des raccordements - année 2 | C35: 0.85
A36: Montée en charge des raccordements - année 3 et suivantes | C36: 1
A37: Croissance annuelle de la consommation par client | C37: 0.03 | D37: par an
A38: Taux de recouvrement (part des factures effectivement payées) | C38: 0.92
A40: 4. CONCEPTION TECHNIQUE & DIMENSIONNEMENT AUTOMATIQUE
A41: Productible spécifique PV | C41: 1500 | D41: kWh/kWc/an | H41: Utilisez PVGIS ou votre étude de conception pour le site.
A42: Dégradation PV | C42: 0.005 | D42: par an
A43: Pertes de distribution et de conversion | C43: 0.12 | H43: Énergie produite par rapport à l'énergie vendue.
A44: Fraction solaire cible (part max de la production issue du PV) | C44: 0.9 | H44: Plafond lié au stockage ; le reste provient du diesel.
A45: Facteur de surdimensionnement PV | C45: 1.15 | H45: Marge pour la météo, l'écrêtage et la croissance.
A46: Part de l'énergie journalière consommée la nuit | C46: 0.45
A47: Profondeur de décharge utile de la batterie | C47: 0.8
A48: Ratio charge de pointe / charge moyenne | C48: 2.5
A49: Rendement du groupe diesel | C49: 3 | D49: kWh/litre
A50: Prix du diesel en année 1 | C50: 1.2 | D50: par litre
A52: Composant | B52: Auto-dimensionné | C52: Forçage | D52: Retenu | E52: Unité
A53: Énergie vendue de conception (année 3, raccordement complet) | B53: =(Seg1_N*Seg1_kWh+Seg2_N*Seg2_kWh+Seg3_N*Seg3_kWh+Seg4_N*Seg4_kWh+Seg5_N*Seg5_kWh)*12*LevDemand*Ramp3*(1+DemandGrowth)^2 -> 445578 | E53: kWh/an
A54: Production de conception (pertes incluses) | B54: =DesignEnergy/(1-Losses) -> 506338.64 | E54: kWh/an
A55: Champ PV | B55: =DesignGen*SolarFraction/SpecYield*PVOversize -> 349.37366 | D55: =IF(ISNUMBER(C55),C55,B55) -> 349.37366 | E55: kWc
A56: Stockage batterie (base utile -> nominale) | B56: =DesignGen/365*NightShare/DoD -> 780.31639 | D56: =IF(ISNUMBER(C56),C56,B56) -> 780.31639 | E56: kWh
A57: Groupe diesel (secours, couvre la pointe) | B57: =DesignGen/8760*PeakRatio -> 144.50304 | D57: =IF(ISNUMBER(C57),C57,B57) -> 144.50304 | E57: kW
A58: Laissez Forçage vide pour utiliser l'auto-dimensionnement. C'est une règle empirique de présélection, pas une conception d'ingénierie (utilisez HOMER ou équivalent pour la conception finale).
A60: 5. CAPEX (coûts unitaires, année 0)
A61: Modules PV, structures et onduleurs | C61: 700 | D61: par kWc
A62: Système de stockage par batterie | C62: 350 | D62: par kWh
A63: Groupe diesel | C63: 400 | D63: par kW
A64: Réseau de distribution | C64: 450 | D64: par raccordement
A65: Compteurs intelligents et branchements | C65: 80 | D65: par raccordement
A66: Local technique, BOS, génie civil (forfait) | C66: 60000
A67: Coûts de développement (études, permis, communauté) | C67: 0.08 | D67: du CAPEX direct
A68: Imprévus | C68: 0.07 | D68: du CAPEX direct
A69: Durée de vie des batteries | C69: 8 | D69: ans
A70: Coût de remplacement des batteries | C70: 250 | D70: par kWh | H70: En termes réels de l'année 0, indexé avec les coûts.
A71: Financer les remplacements via une réserve de maintenance ? (1 = oui, 0 = non) | C71: 1 | H71: 1 = des dotations annuelles à la réserve lissent le remplacement des batteries dans le CFADS (pratique des prêteurs).
A73: CAPEX direct | C73: =(PV_kWp*C_PV+BESS_kWh*C_BESS+Diesel_kW*C_Diesel+TotalCustomers*(C_Network+C_Meter)+C_BOS)*LevCapex -> 1149573.5
A74: CAPEX TOTAL | C74: =HardCapex*(1+C_DevPct+C_ContPct) -> 1322009.5
A75: CAPEX par raccordement | C75: =IFERROR(TotalCapex/TotalCustomers,0) -> 1362.8964
A77: 6. OPEX (valeurs année 1, indexées)
A78: Exploitation et maintenance fixes | C78: 0.025 | D78: du CAPEX direct / an
A79: Personnel local et opérateur | C79: 18000 | D79: par an
A80: Assurance | C80: 0.005 | D80: du CAPEX total / an
A81: Licences, foncier, redevances réglementaires | C81: 3000 | D81: par an
A82: Maintenance du groupe diesel | C82: 0.03 | D82: par kWh diesel
A83: Gestion clientèle, frais de mobile money | C83: 0.03 | D83: du chiffre d'affaires
A85: 7. FINANCEMENT & SUBVENTIONS
A86: Subvention d'investissement initiale | C86: 680000 | H86: Subvention d'investissement reçue en année 0.
A87: RBF par nouveau raccordement | C87: 250 | D87: par raccordement | H87: Versé l'année où le raccordement est réalisé (et vérifié).
A88: Délai de vérification du RBF | C88: 0 | D88: ans | H88: 0 = payé la même année, 1 = payé l'année suivante.
A89: Part de dette dans le CAPEX net de subvention | C89: 0.3
A90: Taux d'intérêt | C90: 0.09
A91: Durée du prêt (différé inclus) | C91: 10 | D91: ans
A92: Différé (intérêts seuls) | C92: 1 | D92: ans
A94: Montant de la dette | C94: =MAX(0,(TotalCapex-Grant))*DebtPct -> 192602.86
A95: Montant des fonds propres | C95: =MAX(0,TotalCapex-Grant-DebtAmt) -> 449406.68
A98: 8. IMPACT
A99: Facteur d'émission CO2 du diesel | C99: 2.68 | D99: kgCO2/litre | H99: Facteur de combustion couramment utilisé pour le diesel ; à vérifier selon la norme de votre bailleur.

Sheet Tableau de bord
B1: ="TABLEAU DE BORD - "&ProjectName -> TABLEAU DE BORD - Mini-réseau villageois (exemple)
B2: =Site&" | "&TotalCustomers&" clients | "&FIXED(PV_kWp,0)&" kWc PV / "&FIXED(BESS_kWh,0)&" kWh batterie / "&FIXED(Diesel_kW,0)&" kW diesel | montants en "&Currency -> Site exemple | 970 clients | 349 kWc PV / 780 kWh batterie / 145 kW diesel | montants en USD | F2: ="Contrôles du modèle : "&ChecksOverall -> Contrôles du modèle : TOUT OK
B4: ÉCONOMIE DU PROJET | E4: FINANCEMENT & BANCABILITÉ
B5: CAPEX total | C5: =TotalCapex -> 1322009.5 | E5: Montant de la dette | F5: =DebtAmt -> 192602.86
B6: CAPEX par raccordement | C6: =CapexPerConn -> 1362.8964 | E6: Montant des fonds propres | F6: =EquityAmt -> 449406.68
B7: TRI du projet - avant subventions | C7: =IFERROR(IRR('Flux de trésorerie'!$C$82:$W$82),"n.d.") -> -0.03238788 | E7: Total des subventions (grant + RBF, nominal) | F7: =Grant+'Flux de trésorerie'!$B$64 -> 922500
B8: TRI du projet - après subventions | C8: =IFERROR(IRR('Flux de trésorerie'!$C$83:$W$83),"n.d.") -> 0.10900568 | E8: Part des subventions dans le CAPEX | F8: =IFERROR(TotalSubsidy/TotalCapex,0) -> 0.69780132
B9: VAN du projet au taux minimal - avant subventions | C9: ='Flux de trésorerie'!$B$82 -> -862669.04 | E9: DSCR minimum | F9: =IF(DebtAmt>0,MIN('Flux de trésorerie'!$D$85:$W$85),"pas de dette") -> 1.6011342
B10: VAN du projet au taux minimal - après subventions | C10: ='Flux de trésorerie'!$B$83 -> 27036.068 | E10: DSCR moyen | F10: =IF(DebtAmt>0,AVERAGE('Flux de trésorerie'!$D$85:$W$85),"pas de dette") -> 2.655189
B11: LCOE (coût par kWh vendu) | C11: =IFERROR('Flux de trésorerie'!$B$90/'Flux de trésorerie'!$B$91,0) -> 0.62815496 | E11: TRI des fonds propres | F11: =IFERROR(IRR('Flux de trésorerie'!$C$86:$W$86),"n.d.") -> 0.086270354
B12: Tarif moyen facturé (pondéré, année 1) | C12: =IFERROR('Flux de trésorerie'!D42/'Flux de trésorerie'!D26,0) -> 0.37428571 | E12: Délai de récupération des fonds propres (ans) | F12: =IFERROR(MATCH(TRUE(),INDEX('Flux de trésorerie'!$C$87:$W$87>=0,0),0)-1,"> durée de vie") -> 11
B13: Recette encaissée actualisée par kWh | C13: =IFERROR('Flux de trésorerie'!$B$92/'Flux de trésorerie'!$B$91,0) -> 0.43839149 | E13: CO2 évité sur la durée de vie vs tout-diesel (tCO2) | F13: ='Flux de trésorerie'!$B$31/DieselEff*CO2perL/1000 -> 8426.7681
B14: Marge d'EBE année 1 | C14: ='Flux de trésorerie'!D58 -> 0.23700334 | E14: Énergie totale vendue sur la durée de vie (MWh) | F14: ='Flux de trésorerie'!$B$26/1000 -> 11052.667
B15: Fraction solaire moyenne (durée de vie) | C15: =IFERROR('Flux de trésorerie'!$B$31/'Flux de trésorerie'!$B$29,0) -> 0.75104002
B17: DÉFICIT DE VIABILITÉ & VERDICT DE BANCABILITÉ
B18: Déficit de viabilité : subvention initiale nécessaire pour VAN = 0 au taux minimal | C18: =MAX(0,-NPV_Pre) -> 862669.04 | E18: Viable commercialement sans subvention ? | F18: =IF(NPV_Pre>=0,"OUI","NON - subvention nécessaire") -> NON - subvention nécessaire
B19: Déficit de viabilité par raccordement | C19: =IFERROR(VGF/TotalCustomers,0) -> 889.34953 | E19: Viable au taux minimal après subventions prévues ? | F19: =IF(NPV_Post>=0,"OUI","NON - déficit restant") -> OUI
B20: Subventions déjà prévues (VA du grant + RBF au taux minimal) | C20: =NPV_Post-NPV_Pre -> 889705.11 | E20: Covenant de dette respecté (DSCR min >= exigé) ? | F20: =IF(DebtAmt=0,"Pas de dette",IF(DSCR_Min>=MinDSCR,"OUI","NON - redimensionner la dette")) -> OUI
B21: Déficit restant après subventions prévues | C21: =MAX(0,VGF-SubsidyPV) -> 0 | E21: TRI des fonds propres conforme à la cible ? | F21: =IF(ISNUMBER(IRR_Eq),IF(IRR_Eq>=TargetEqIRR,"OUI","NON"),"n.d.") -> NON
E22: Le tarif encaissé couvre-t-il le LCOE ? | F22: =IF(LevRev>=LCOE,"OUI","NON - tarif inférieur au coût") -> NON - tarif inférieur au coût
B24: Le déficit de viabilité utilise le flux du projet avant subventions actualisé au taux minimal. C'est la subvention initiale minimale en valeur actuelle ; un RBF versé plus tard doit être plus élevé en nominal.
B27: Les données des graphiques sont liées à « Flux de trésorerie » (colonnes L-R).
L28: Année | M28: Recettes | N28: OPEX | O28: CFADS | P28: Service de la dette | Q28: kWh solaire | R28: kWh diesel
L29: ='Flux de trésorerie'!D5 -> 2027 | M29: ='Flux de trésorerie'!D45 -> 93674.4 | N29: ='Flux de trésorerie'!D55 -> 71473.254 | O29: ='Flux de trésorerie'!D84 -> 137710.81 | P29: ='Flux de trésorerie'!D79 -> 17334.258 | Q29: ='Flux de trésorerie'!D31 -> 257727.27 | R29: ='Flux de trésorerie'!D32 -> 28636.364
L30: ='Flux de trésorerie'!E5 -> 2028 | M30: ='Flux de trésorerie'!E45 -> 133291.86 | N30: ='Flux de trésorerie'!E55 -> 80545.3 | O30: ='Flux de trésorerie'!E84 -> 83381.226 | P30: ='Flux de trésorerie'!E79 -> 32125.927 | Q30: ='Flux de trésorerie'!E31 -> 376067.05 | R30: ='Flux de trésorerie'!E32 -> 41785.227
L31: ='Flux de trésorerie'!F5 -> 2029 | M31: ='Flux de trésorerie'!F45 -> 164500.59 | N31: ='Flux de trésorerie'!F55 -> 87814.591 | O31: ='Flux de trésorerie'!F84 -> 83070.66 | P31: ='Flux de trésorerie'!F79 -> 32125.927 | Q31: ='Flux de trésorerie'!F31 -> 455704.77 | R31: ='Flux de trésorerie'!F32 -> 50633.864
L32: ='Flux de trésorerie'!G5 -> 2030 | M32: ='Flux de trésorerie'!G45 -> 172688.62 | N32: ='Flux de trésorerie'!G55 -> 91260.363 | O32: ='Flux de trésorerie'!G84 -> 51437.921 | P32: ='Flux de trésorerie'!G79 -> 32125.927 | Q32: ='Flux de trésorerie'!G31 -> 469375.92 | R32: ='Flux de trésorerie'!G32 -> 52152.88
L33: ='Flux de trésorerie'!H5 -> 2031 | M33: ='Flux de trésorerie'!H45 -> 183205.36 | N33: ='Flux de trésorerie'!H55 -> 94915.467 | O33: ='Flux de trésorerie'!H84 -> 58299.553 | P33: ='Flux de trésorerie'!H79 -> 32125.927 | Q33: ='Flux de trésorerie'!H31 -> 483457.19 | R33: ='Flux de trésorerie'!H32 -> 53717.466
L34: ='Flux de trésorerie'!I5 -> 2032 | M34: ='Flux de trésorerie'!I45 -> 194362.56 | N34: ='Flux de trésorerie'!I55 -> 98736.088 | O34: ='Flux de trésorerie'!I84 -> 65636.139 | P34: ='Flux de trésorerie'!I79 -> 32125.927 | Q34: ='Flux de trésorerie'!I31 -> 497960.91 | R34: ='Flux de trésorerie'!I32 -> 55328.99
L35: ='Flux de trésorerie'!J5 -> 2033 | M35: ='Flux de trésorerie'!J45 -> 206199.24 | N35: ='Flux de trésorerie'!J55 -> 104972.2 | O35: ='Flux de trésorerie'!J84 -> 70305.214 | P35: ='Flux de trésorerie'!J79 -> 32125.927 | Q35: ='Flux de trésorerie'!J31 -> 508533.89 | R35: ='Flux de trésorerie'!J32 -> 61354.705
L36: ='Flux de trésorerie'!K5 -> 2034 | M36: ='Flux de trésorerie'!K45 -> 218756.78 | N36: ='Flux de trésorerie'!K55 -> 118698.69 | O36: ='Flux de trésorerie'!K84 -> 68916.425 | P36: ='Flux de trésorerie'!K79 -> 32125.927 | Q36: ='Flux de trésorerie'!K31 -> 505991.22 | R36: ='Flux de trésorerie'!K32 -> 80994.032
L37: ='Flux de trésorerie'!L5 -> 2035 | M37: ='Flux de trésorerie'!L45 -> 232079.06 | N37: ='Flux de trésorerie'!L55 -> 133432.66 | O37: ='Flux de trésorerie'!L84 -> 59298.983 | P37: ='Flux de trésorerie'!L79 -> 32125.927 | Q37: ='Flux de trésorerie'!L31 -> 503461.27 | R37: ='Flux de trésorerie'!L32 -> 101133.55
L38: ='Flux de trésorerie'!M5 -> 2036 | M38: ='Flux de trésorerie'!M45 -> 246212.68 | N38: ='Flux de trésorerie'!M55 -> 149239.4 | O38: ='Flux de trésorerie'!M84 -> 57435.744 | P38: ='Flux de trésorerie'!M79 -> 32125.927 | Q38: ='Flux de trésorerie'!M31 -> 500943.96 | R38: ='Flux de trésorerie'!M32 -> 121788.7
L39: ='Flux de trésorerie'!N5 -> 2037 | M39: ='Flux de trésorerie'!N45 -> 261207.03 | N39: ='Flux de trésorerie'!N55 -> 166188.27 | O39: ='Flux de trésorerie'!N84 -> 55306.701 | P39: ='Flux de trésorerie'!N79 -> 0 | Q39: ='Flux de trésorerie'!N31 -> 498439.24 | R39: ='Flux de trésorerie'!N32 -> 142975.4
L40: ='Flux de trésorerie'!O5 -> 2038 | M40: ='Flux de trésorerie'!O45 -> 277114.54 | N40: ='Flux de trésorerie'!O55 -> 184352.96 | O40: ='Flux de trésorerie'!O84 -> 53613.816 | P40: ='Flux de trésorerie'!O79 -> 0 | Q40: ='Flux de trésorerie'!O31 -> 495947.04 | R40: ='Flux de trésorerie'!O32 -> 164710.03
L41: ='Flux de trésorerie'!P5 -> 2039 | M41: ='Flux de trésorerie'!P45 -> 293990.81 | N41: ='Flux de trésorerie'!P55 -> 203811.72 | O41: ='Flux de trésorerie'!P84 -> 51676.955 | P41: ='Flux de trésorerie'!P79 -> 0 | Q41: ='Flux de trésorerie'!P31 -> 493467.31 | R41: ='Flux de trésorerie'!P32 -> 187009.48
L42: ='Flux de trésorerie'!Q5 -> 2040 | M42: ='Flux de trésorerie'!Q45 -> 311894.86 | N42: ='Flux de trésorerie'!Q55 -> 224647.66 | O42: ='Flux de trésorerie'!Q84 -> 49256.339 | P42: ='Flux de trésorerie'!Q79 -> 0 | Q42: ='Flux de trésorerie'!Q31 -> 490999.97 | R42: ='Flux de trésorerie'!Q32 -> 209891.12
L43: ='Flux de trésorerie'!R5 -> 2041 | M43: ='Flux de trésorerie'!R45 -> 330889.25 | N43: ='Flux de trésorerie'!R55 -> 246949.05 | O43: ='Flux de trésorerie'!R84 -> 45949.341 | P43: ='Flux de trésorerie'!R79 -> 0 | Q43: ='Flux de trésorerie'!R31 -> 488544.97 | R43: ='Flux de trésorerie'!R32 -> 233372.85
L44: ='Flux de trésorerie'!S5 -> 2042 | M44: ='Flux de trésorerie'!S45 -> 351040.41 | N44: ='Flux de trésorerie'!S55 -> 270809.65 | O44: ='Flux de trésorerie'!S84 -> 22182.21 | P44: ='Flux de trésorerie'!S79 -> 0 | Q44: ='Flux de trésorerie'!S31 -> 486102.25 | R44: ='Flux de trésorerie'!S32 -> 257473.11
L45: ='Flux de trésorerie'!T5 -> 2043 | M45: ='Flux de trésorerie'!T45 -> 372418.77 | N45: ='Flux de trésorerie'!T55 -> 296329 | O45: ='Flux de trésorerie'!T84 -> 57067.325 | P45: ='Flux de trésorerie'!T79 -> 0 | Q45: ='Flux de trésorerie'!T31 -> 483671.74 | R45: ='Flux de trésorerie'!T32 -> 282210.88
L46: ='Flux de trésorerie'!U5 -> 2044 | M46: ='Flux de trésorerie'!U45 -> 395099.07 | N46: ='Flux de trésorerie'!U55 -> 323612.84 | O46: ='Flux de trésorerie'!U84 -> 53614.676 | P46: ='Flux de trésorerie'!U79 -> 0 | Q46: ='Flux de trésorerie'!U31 -> 481253.38 | R46: ='Flux de trésorerie'!U32 -> 307605.72
L47: ='Flux de trésorerie'!V5 -> 2045 | M47: ='Flux de trésorerie'!V45 -> 419160.6 | N47: ='Flux de trésorerie'!V55 -> 352773.42 | O47: ='Flux de trésorerie'!V84 -> 49790.391 | P47: ='Flux de trésorerie'!V79 -> 0 | Q47: ='Flux de trésorerie'!V31 -> 478847.11 | R47: ='Flux de trésorerie'!V32 -> 333677.76
L48: ='Flux de trésorerie'!W5 -> 2046 | M48: ='Flux de trésorerie'!W45 -> 444687.49 | N48: ='Flux de trésorerie'!W55 -> 383929.95 | O48: ='Flux de trésorerie'!W84 -> 45568.151 | P48: ='Flux de trésorerie'!W79 -> 0 | Q48: ='Flux de trésorerie'!W31 -> 476452.87 | R48: ='Flux de trésorerie'!W32 -> 360447.74

Sheet Flux de trésorerie
A1: MOTEUR DE FLUX DE TRÉSORERIE (annuel, nominal)
A2: Toutes les cellules sont des formules. Colonne B = total ou VAN selon le cas.
A4: Année du projet | B4: Total / VAN | C4: 0 | D4: 1 | E4: 2 | F4: 3 | G4: 4 | H4: 5 | I4: 6 | J4: 7 | K4: 8 | L4: 9 | M4: 10 | N4: 11 | O4: 12 | P4: 13 | Q4: 14 | R4: 15 | S4: 16 | T4: 17 | U4: 18 | V4: 19 | W4: 20
A5: Année civile | C5: =StartYear-1+C4 -> 2026 | D5: =StartYear-1+D4 -> 2027 | E5: =StartYear-1+E4 -> 2028 | F5: =StartYear-1+F4 -> 2029 | G5: =StartYear-1+G4 -> 2030 | H5: =StartYear-1+H4 -> 2031 | I5: =StartYear-1+I4 -> 2032 | J5: =StartYear-1+J4 -> 2033 | ... W5: =StartYear-1+W4 -> 2046
A6: Indicateur d'exploitation | C6: =IF(AND(C4>=1,C4<=Life),1,0) -> 0 | D6: =IF(AND(D4>=1,D4<=Life),1,0) -> 1 | E6: =IF(AND(E4>=1,E4<=Life),1,0) -> 1 | F6: =IF(AND(F4>=1,F4<=Life),1,0) -> 1 | G6: =IF(AND(G4>=1,G4<=Life),1,0) -> 1 | H6: =IF(AND(H4>=1,H4<=Life),1,0) -> 1 | I6: =IF(AND(I4>=1,I4<=Life),1,0) -> 1 | J6: =IF(AND(J4>=1,J4<=Life),1,0) -> 1 | ... W6: =IF(AND(W4>=1,W4<=Life),1,0) -> 1
A7: Montée en charge des raccordements | C7: 0 | D7: =IF(D4=1,Ramp1,IF(D4=2,Ramp2,Ramp3))*D6 -> 0.6 | E7: =IF(E4=1,Ramp1,IF(E4=2,Ramp2,Ramp3))*E6 -> 0.85 | F7: =IF(F4=1,Ramp1,IF(F4=2,Ramp2,Ramp3))*F6 -> 1 | G7: =IF(G4=1,Ramp1,IF(G4=2,Ramp2,Ramp3))*G6 -> 1 | H7: =IF(H4=1,Ramp1,IF(H4=2,Ramp2,Ramp3))*H6 -> 1 | I7: =IF(I4=1,Ramp1,IF(I4=2,Ramp2,Ramp3))*I6 -> 1 | J7: =IF(J4=1,Ramp1,IF(J4=2,Ramp2,Ramp3))*J6 -> 1 | K7: =IF(K4=1,Ramp1,IF(K4=2,Ramp2,Ramp3))*K6 -> 1 | ... W7: =IF(W4=1,Ramp1,IF(W4=2,Ramp2,Ramp3))*W6 -> 1
A8: Indice tarifaire | C8: 0 | D8: =(1+TariffEsc)^(D4-1) -> 1 | E8: =(1+TariffEsc)^(E4-1) -> 1.03 | F8: =(1+TariffEsc)^(F4-1) -> 1.0609 | G8: =(1+TariffEsc)^(G4-1) -> 1.092727 | H8: =(1+TariffEsc)^(H4-1) -> 1.1255088 | I8: =(1+TariffEsc)^(I4-1) -> 1.1592741 | J8: =(1+TariffEsc)^(J4-1) -> 1.1940523 | K8: =(1+TariffEsc)^(K4-1) -> 1.2298739 | ... W8: =(1+TariffEsc)^(W4-1) -> 1.7535061
A9: Indice des coûts | C9: 0 | D9: =(1+CostEsc)^(D4-1) -> 1 | E9: =(1+CostEsc)^(E4-1) -> 1.03 | F9: =(1+CostEsc)^(F4-1) -> 1.0609 | G9: =(1+CostEsc)^(G4-1) -> 1.092727 | H9: =(1+CostEsc)^(H4-1) -> 1.1255088 | I9: =(1+CostEsc)^(I4-1) -> 1.1592741 | J9: =(1+CostEsc)^(J4-1) -> 1.1940523 | K9: =(1+CostEsc)^(K4-1) -> 1.2298739 | ... W9: =(1+CostEsc)^(W4-1) -> 1.7535061
A10: Indice de croissance de la consommation | C10: 0 | D10: =(1+DemandGrowth)^(D4-1)*LevDemand -> 1 | E10: =(1+DemandGrowth)^(E4-1)*LevDemand -> 1.03 | F10: =(1+DemandGrowth)^(F4-1)*LevDemand -> 1.0609 | G10: =(1+DemandGrowth)^(G4-1)*LevDemand -> 1.092727 | H10: =(1+DemandGrowth)^(H4-1)*LevDemand -> 1.1255088 | I10: =(1+DemandGrowth)^(I4-1)*LevDemand -> 1.1592741 | J10: =(1+DemandGrowth)^(J4-1)*LevDemand -> 1.1940523 | K10: =(1+DemandGrowth)^(K4-1)*LevDemand -> 1.2298739 | ... W10: =(1+DemandGrowth)^(W4-1)*LevDemand -> 1.7535061
A12: DEMANDE & RACCORDEMENTS
A13: ="Raccordements - "&Seg1_Name -> Raccordements - Ménages | C13: 0 | D13: =Seg1_N*D7 -> 480 | E13: =Seg1_N*E7 -> 680 | F13: =Seg1_N*F7 -> 800 | G13: =Seg1_N*G7 -> 800 | H13: =Seg1_N*H7 -> 800 | I13: =Seg1_N*I7 -> 800 | J13: =Seg1_N*J7 -> 800 | K13: =Seg1_N*K7 -> 800 | ... W13: =Seg1_N*W7 -> 800
A14: ="Raccordements - "&Seg2_Name -> Raccordements - Usagers productifs (moulins, soudure, chambres froides) | C14: 0 | D14: =Seg2_N*D7 -> 36 | E14: =Seg2_N*E7 -> 51 | F14: =Seg2_N*F7 -> 60 | G14: =Seg2_N*G7 -> 60 | H14: =Seg2_N*H7 -> 60 | I14: =Seg2_N*I7 -> 60 | J14: =Seg2_N*J7 -> 60 | K14: =Seg2_N*K7 -> 60 | ... W14: =Seg2_N*W7 -> 60
A15: ="Raccordements - "&Seg3_Name -> Raccordements - Commerces (boutiques, bars, kiosques) | C15: 0 | D15: =Seg3_N*D7 -> 60 | E15: =Seg3_N*E7 -> 85 | F15: =Seg3_N*F7 -> 100 | G15: =Seg3_N*G7 -> 100 | H15: =Seg3_N*H7 -> 100 | I15: =Seg3_N*I7 -> 100 | J15: =Seg3_N*J7 -> 100 | K15: =Seg3_N*K7 -> 100 | ... W15: =Seg3_N*W7 -> 100
A16: ="Raccordements - "&Seg4_Name -> Raccordements - Institutions (centre de santé, école, eau) | C16: 0 | D16: =Seg4_N*D7 -> 6 | E16: =Seg4_N*E7 -> 8.5 | F16: =Seg4_N*F7 -> 10 | G16: =Seg4_N*G7 -> 10 | H16: =Seg4_N*H7 -> 10 | I16: =Seg4_N*I7 -> 10 | J16: =Seg4_N*J7 -> 10 | K16: =Seg4_N*K7 -> 10 | ... W16: =Seg4_N*W7 -> 10
A17: ="Raccordements - "&Seg5_Name -> Raccordements - Autre / personnalisé | C17: 0 | D17: =Seg5_N*D7 -> 0 | E17: =Seg5_N*E7 -> 0 | F17: =Seg5_N*F7 -> 0 | G17: =Seg5_N*G7 -> 0 | H17: =Seg5_N*H7 -> 0 | I17: =Seg5_N*I7 -> 0 | J17: =Seg5_N*J7 -> 0 | K17: =Seg5_N*K7 -> 0 | ... W17: =Seg5_N*W7 -> 0
A18: Total des raccordements | C18: =C13+C14+C15+C16+C17 -> 0 | D18: =D13+D14+D15+D16+D17 -> 582 | E18: =E13+E14+E15+E16+E17 -> 824.5 | F18: =F13+F14+F15+F16+F17 -> 970 | G18: =G13+G14+G15+G16+G17 -> 970 | H18: =H13+H14+H15+H16+H17 -> 970 | I18: =I13+I14+I15+I16+I17 -> 970 | J18: =J13+J14+J15+J16+J17 -> 970 | ... W18: =W13+W14+W15+W16+W17 -> 970
A19: Nouveaux raccordements de l'année | B19: =SUM(C19:W19) -> 970 | C19: 0 | D19: =MAX(0,D18-C18) -> 582 | E19: =MAX(0,E18-D18) -> 242.5 | F19: =MAX(0,F18-E18) -> 145.5 | G19: =MAX(0,G18-F18) -> 0 | H19: =MAX(0,H18-G18) -> 0 | I19: =MAX(0,I18-H18) -> 0 | J19: =MAX(0,J18-I18) -> 0 | K19: =MAX(0,K18-J18) -> 0 | ... W19: =MAX(0,W18-V18) -> 0
A21: ="Énergie vendue - "&Seg1_Name&" (kWh)" -> Énergie vendue - Ménages (kWh) | B21: =SUM(C21:W21) -> 3789485.9 | C21: 0 | D21: =D13*Seg1_kWh*12*D10 -> 86400 | E21: =E13*Seg1_kWh*12*E10 -> 126072 | F21: =F13*Seg1_kWh*12*F10 -> 152769.6 | G21: =G13*Seg1_kWh*12*G10 -> 157352.69 | H21: =H13*Seg1_kWh*12*H10 -> 162073.27 | I21: =I13*Seg1_kWh*12*I10 -> 166935.47 | J21: =J13*Seg1_kWh*12*J10 -> 171943.53 | K21: =K13*Seg1_kWh*12*K10 -> 177101.84 | ... W21: =W13*Seg1_kWh*12*W10 -> 252504.87
A22: ="Énergie vendue - "&Seg2_Name&" (kWh)" -> Énergie vendue - Usagers productifs (moulins, soudure, chambres froides) (kWh) | B22: =SUM(C22:W22) -> 4736857.4 | C22: 0 | D22: =D14*Seg2_kWh*12*D10 -> 108000 | E22: =E14*Seg2_kWh*12*E10 -> 157590 | F22: =F14*Seg2_kWh*12*F10 -> 190962 | G22: =G14*Seg2_kWh*12*G10 -> 196690.86 | H22: =H14*Seg2_kWh*12*H10 -> 202591.59 | I22: =I14*Seg2_kWh*12*I10 -> 208669.33 | J22: =J14*Seg2_kWh*12*J10 -> 214929.41 | K22: =K14*Seg2_kWh*12*K10 -> 221377.3 | ... W22: =W14*Seg2_kWh*12*W10 -> 315631.09
A23: ="Énergie vendue - "&Seg3_Name&" (kWh)" -> Énergie vendue - Commerces (boutiques, bars, kiosques) (kWh) | B23: =SUM(C23:W23) -> 1578952.5 | C23: 0 | D23: =D15*Seg3_kWh*12*D10 -> 36000 | E23: =E15*Seg3_kWh*12*E10 -> 52530 | F23: =F15*Seg3_kWh*12*F10 -> 63654 | G23: =G15*Seg3_kWh*12*G10 -> 65563.62 | H23: =H15*Seg3_kWh*12*H10 -> 67530.529 | I23: =I15*Seg3_kWh*12*I10 -> 69556.444 | J23: =J15*Seg3_kWh*12*J10 -> 71643.138 | K23: =K15*Seg3_kWh*12*K10 -> 73792.432 | ... W23: =W15*Seg3_kWh*12*W10 -> 105210.36
A24: ="Énergie vendue - "&Seg4_Name&" (kWh)" -> Énergie vendue - Institutions (centre de santé, école, eau) (kWh) | B24: =SUM(C24:W24) -> 947371.48 | C24: 0 | D24: =D16*Seg4_kWh*12*D10 -> 21600 | E24: =E16*Seg4_kWh*12*E10 -> 31518 | F24: =F16*Seg4_kWh*12*F10 -> 38192.4 | G24: =G16*Seg4_kWh*12*G10 -> 39338.172 | H24: =H16*Seg4_kWh*12*H10 -> 40518.317 | I24: =I16*Seg4_kWh*12*I10 -> 41733.867 | J24: =J16*Seg4_kWh*12*J10 -> 42985.883 | K24: =K16*Seg4_kWh*12*K10 -> 44275.459 | ... W24: =W16*Seg4_kWh*12*W10 -> 63126.218
A25: ="Énergie vendue - "&Seg5_Name&" (kWh)" -> Énergie vendue - Autre / personnalisé (kWh) | B25: =SUM(C25:W25) -> 0 | C25: 0 | D25: =D17*Seg5_kWh*12*D10 -> 0 | E25: =E17*Seg5_kWh*12*E10 -> 0 | F25: =F17*Seg5_kWh*12*F10 -> 0 | G25: =G17*Seg5_kWh*12*G10 -> 0 | H25: =H17*Seg5_kWh*12*H10 -> 0 | I25: =I17*Seg5_kWh*12*I10 -> 0 | J25: =J17*Seg5_kWh*12*J10 -> 0 | K25: =K17*Seg5_kWh*12*K10 -> 0 | ... W25: =W17*Seg5_kWh*12*W10 -> 0
A26: Énergie totale vendue (kWh) | B26: =SUM(C26:W26) -> 11052667 | C26: =C21+C22+C23+C24+C25 -> 0 | D26: =D21+D22+D23+D24+D25 -> 252000 | E26: =E21+E22+E23+E24+E25 -> 367710 | F26: =F21+F22+F23+F24+F25 -> 445578 | G26: =G21+G22+G23+G24+G25 -> 458945.34 | H26: =H21+H22+H23+H24+H25 -> 472713.7 | I26: =I21+I22+I23+I24+I25 -> 486895.11 | J26: =J21+J22+J23+J24+J25 -> 501501.96 | ... W26: =W21+W22+W23+W24+W25 -> 736472.54
A28: MIX DE PRODUCTION
A29: Production brute nécessaire (kWh) | B29: =SUM(C29:W29) -> 12559849 | C29: 0 | D29: =D26/(1-Losses) -> 286363.64 | E29: =E26/(1-Losses) -> 417852.27 | F29: =F26/(1-Losses) -> 506338.64 | G29: =G26/(1-Losses) -> 521528.8 | H29: =H26/(1-Losses) -> 537174.66 | I29: =I26/(1-Losses) -> 553289.9 | J29: =J26/(1-Losses) -> 569888.6 | K29: =K26/(1-Losses) -> 586985.25 | ... W29: =W26/(1-Losses) -> 836900.62
A30: Énergie PV disponible (kWh) | B30: =SUM(C30:W30) -> 9997975.7 | C30: 0 | D30: =PV_kWp*SpecYield*(1-Degradation)^(D4-1)*D6 -> 524060.49 | E30: =PV_kWp*SpecYield*(1-Degradation)^(E4-1)*E6 -> 521440.19 | F30: =PV_kWp*SpecYield*(1-Degradation)^(F4-1)*F6 -> 518832.99 | G30: =PV_kWp*SpecYield*(1-Degradation)^(G4-1)*G6 -> 516238.82 | H30: =PV_kWp*SpecYield*(1-Degradation)^(H4-1)*H6 -> 513657.63 | I30: =PV_kWp*SpecYield*(1-Degradation)^(I4-1)*I6 -> 511089.34 | J30: =PV_kWp*SpecYield*(1-Degradation)^(J4-1)*J6 -> 508533.89 | K30: =PV_kWp*SpecYield*(1-Degradation)^(K4-1)*K6 -> 505991.22 | ... W30: =PV_kWp*SpecYield*(1-Degradation)^(W4-1)*W6 -> 476452.87
A31: Énergie solaire livrée (kWh) | B31: =SUM(C31:W31) -> 9432949.3 | C31: 0 | D31: =MIN(D30,D29*SolarFraction) -> 257727.27 | E31: =MIN(E30,E29*SolarFraction) -> 376067.05 | F31: =MIN(F30,F29*SolarFraction) -> 455704.77 | G31: =MIN(G30,G29*SolarFraction) -> 469375.92 | H31: =MIN(H30,H29*SolarFraction) -> 483457.19 | I31: =MIN(I30,I29*SolarFraction) -> 497960.91 | J31: =MIN(J30,J29*SolarFraction) -> 508533.89 | K31: =MIN(K30,K29*SolarFraction) -> 505991.22 | ... W31: =MIN(W30,W29*SolarFraction) -> 476452.87
A32: Énergie diesel livrée (kWh) | B32: =SUM(C32:W32) -> 3126899.9 | C32: 0 | D32: =D29-D31 -> 28636.364 | E32: =E29-E31 -> 41785.227 | F32: =F29-F31 -> 50633.864 | G32: =G29-G31 -> 52152.88 | H32: =H29-H31 -> 53717.466 | I32: =I29-I31 -> 55328.99 | J32: =J29-J31 -> 61354.705 | K32: =K29-K31 -> 80994.032 | ... W32: =W29-W31 -> 360447.74
A33: Fraction solaire effective | C33: 0 | D33: =IFERROR(D31/D29,0) -> 0.9 | E33: =IFERROR(E31/E29,0) -> 0.9 | F33: =IFERROR(F31/F29,0) -> 0.9 | G33: =IFERROR(G31/G29,0) -> 0.9 | H33: =IFERROR(H31/H29,0) -> 0.9 | I33: =IFERROR(I31/I29,0) -> 0.9 | J33: =IFERROR(J31/J29,0) -> 0.89233913 | K33: =IFERROR(K31/K29,0) -> 0.86201692 | ... W33: =IFERROR(W31/W29,0) -> 0.5693064
A34: Diesel consommé (litres) | B34: =SUM(C34:W34) -> 1042300 | C34: 0 | D34: =D32/DieselEff -> 9545.4545 | E34: =E32/DieselEff -> 13928.409 | F34: =F32/DieselEff -> 16877.955 | G34: =G32/DieselEff -> 17384.293 | H34: =H32/DieselEff -> 17905.822 | I34: =I32/DieselEff -> 18442.997 | J34: =J32/DieselEff -> 20451.568 | K34: =K32/DieselEff -> 26998.011 | ... W34: =W32/DieselEff -> 120149.25
A36: RECETTES
A37: ="Recettes facturées - "&Seg1_Name -> Recettes facturées - Ménages | B37: =SUM(C37:W37) -> 2107258.1 | C37: 0 | D37: =D21*Seg1_Tariff*LevTariff*D8 -> 34560 | E37: =E21*Seg1_Tariff*LevTariff*E8 -> 51941.664 | F37: =F21*Seg1_Tariff*LevTariff*F8 -> 64829.307 | G37: =G21*Seg1_Tariff*LevTariff*G8 -> 68777.412 | H37: =H21*Seg1_Tariff*LevTariff*H8 -> 72965.957 | I37: =I21*Seg1_Tariff*LevTariff*I8 -> 77409.583 | J37: =J21*Seg1_Tariff*LevTariff*J8 -> 82123.827 | K37: =K21*Seg1_Tariff*LevTariff*K8 -> 87125.168 | ... W37: =W21*Seg1_Tariff*LevTariff*W8 -> 177107.53
A38: ="Recettes facturées - "&Seg2_Name -> Recettes facturées - Usagers productifs (moulins, soudure, chambres froides) | B38: =SUM(C38:W38) -> 2304813.6 | C38: 0 | D38: =D22*Seg2_Tariff*LevTariff*D8 -> 37800 | E38: =E22*Seg2_Tariff*LevTariff*E8 -> 56811.195 | F38: =F22*Seg2_Tariff*LevTariff*F8 -> 70907.055 | G38: =G22*Seg2_Tariff*LevTariff*G8 -> 75225.295 | H38: =H22*Seg2_Tariff*LevTariff*H8 -> 79806.515 | I38: =I22*Seg2_Tariff*LevTariff*I8 -> 84666.732 | J38: =J22*Seg2_Tariff*LevTariff*J8 -> 89822.936 | K38: =K22*Seg2_Tariff*LevTariff*K8 -> 95293.153 | ... W38: =W22*Seg2_Tariff*LevTariff*W8 -> 193711.36
A39: ="Recettes facturées - "&Seg3_Name -> Recettes facturées - Commerces (boutiques, bars, kiosques) | B39: =SUM(C39:W39) -> 878024.22 | C39: 0 | D39: =D23*Seg3_Tariff*LevTariff*D8 -> 14400 | E39: =E23*Seg3_Tariff*LevTariff*E8 -> 21642.36 | F39: =F23*Seg3_Tariff*LevTariff*F8 -> 27012.211 | G39: =G23*Seg3_Tariff*LevTariff*G8 -> 28657.255 | H39: =H23*Seg3_Tariff*LevTariff*H8 -> 30402.482 | I39: =I23*Seg3_Tariff*LevTariff*I8 -> 32253.993 | J39: =J23*Seg3_Tariff*LevTariff*J8 -> 34218.261 | K39: =K23*Seg3_Tariff*LevTariff*K8 -> 36302.153 | ... W39: =W23*Seg3_Tariff*LevTariff*W8 -> 73794.803
A40: ="Recettes facturées - "&Seg4_Name -> Recettes facturées - Institutions (centre de santé, école, eau) | B40: =SUM(C40:W40) -> 460962.72 | C40: 0 | D40: =D24*Seg4_Tariff*LevTariff*D8 -> 7560 | E40: =E24*Seg4_Tariff*LevTariff*E8 -> 11362.239 | F40: =F24*Seg4_Tariff*LevTariff*F8 -> 14181.411 | G40: =G24*Seg4_Tariff*LevTariff*G8 -> 15045.059 | H40: =H24*Seg4_Tariff*LevTariff*H8 -> 15961.303 | I40: =I24*Seg4_Tariff*LevTariff*I8 -> 16933.346 | J40: =J24*Seg4_Tariff*LevTariff*J8 -> 17964.587 | K40: =K24*Seg4_Tariff*LevTariff*K8 -> 19058.631 | ... W40: =W24*Seg4_Tariff*LevTariff*W8 -> 38742.272
A41: ="Recettes facturées - "&Seg5_Name -> Recettes facturées - Autre / personnalisé | B41: =SUM(C41:W41) -> 0 | C41: 0 | D41: =D25*Seg5_Tariff*LevTariff*D8 -> 0 | E41: =E25*Seg5_Tariff*LevTariff*E8 -> 0 | F41: =F25*Seg5_Tariff*LevTariff*F8 -> 0 | G41: =G25*Seg5_Tariff*LevTariff*G8 -> 0 | H41: =H25*Seg5_Tariff*LevTariff*H8 -> 0 | I41: =I25*Seg5_Tariff*LevTariff*I8 -> 0 | J41: =J25*Seg5_Tariff*LevTariff*J8 -> 0 | K41: =K25*Seg5_Tariff*LevTariff*K8 -> 0 | ... W41: =W25*Seg5_Tariff*LevTariff*W8 -> 0
A42: Total des recettes d'énergie facturées | B42: =SUM(C42:W42) -> 5751058.7 | C42: =C37+C38+C39+C40+C41 -> 0 | D42: =D37+D38+D39+D40+D41 -> 94320 | E42: =E37+E38+E39+E40+E41 -> 141757.46 | F42: =F37+F38+F39+F40+F41 -> 176929.98 | G42: =G37+G38+G39+G40+G41 -> 187705.02 | H42: =H37+H38+H39+H40+H41 -> 199136.26 | I42: =I37+I38+I39+I40+I41 -> 211263.65 | J42: =J37+J38+J39+J40+J41 -> 224129.61 | ... W42: =W37+W38+W39+W40+W41 -> 483355.96
A43: Recettes d'énergie encaissées | B43: =SUM(C43:W43) -> 5290974 | C43: 0 | D43: =D42*Collection -> 86774.4 | E43: =E42*Collection -> 130416.86 | F43: =F42*Collection -> 162775.59 | G43: =G42*Collection -> 172688.62 | H43: =H42*Collection -> 183205.36 | I43: =I42*Collection -> 194362.56 | J43: =J42*Collection -> 206199.24 | K43: =K42*Collection -> 218756.78 | ... W43: =W42*Collection -> 444687.49
A44: Frais de raccordement | B44: =SUM(C44:W44) -> 11500 | C44: 0 | D44: =MAX(0,D13-C13)*Seg1_Fee+MAX(0,D14-C14)*Seg2_Fee+MAX(0,D15-C15)*Seg3_Fee+MAX(0,D16-C16)*Seg4_Fee+MAX(0,D17-C17)*Seg5_Fee -> 6900 | E44: =MAX(0,E13-D13)*Seg1_Fee+MAX(0,E14-D14)*Seg2_Fee+MAX(0,E15-D15)*Seg3_Fee+MAX(0,E16-D16)*Seg4_Fee+MAX(0,E17-D17)*Seg5_Fee -> 2875 | F44: =MAX(0,F13-E13)*Seg1_Fee+MAX(0,F14-E14)*Seg2_Fee+MAX(0,F15-E15)*Seg3_Fee+MAX(0,F16-E16)*Seg4_Fee+MAX(0,F17-E17)*Seg5_Fee -> 1725 | G44: =MAX(0,G13-F13)*Seg1_Fee+MAX(0,G14-F14)*Seg2_Fee+MAX(0,G15-F15)*Seg3_Fee+MAX(0,G16-F16)*Seg4_Fee+MAX(0,G17-F17)*Seg5_Fee -> 0 | H44: =MAX(0,H13-G13)*Seg1_Fee+MAX(0,H14-G14)*Seg2_Fee+MAX(0,H15-G15)*Seg3_Fee+MAX(0,H16-G16)*Seg4_Fee+MAX(0,H17-G17)*Seg5_Fee -> 0 | I44: =MAX(0,I13-H13)*Seg1_Fee+MAX(0,I14-H14)*Seg2_Fee+MAX(0,I15-H15)*Seg3_Fee+MAX(0,I16-H16)*Seg4_Fee+MAX(0,I17-H17)*Seg5_Fee -> 0 | J44: =MAX(0,J13-I13)*Seg1_Fee+MAX(0,J14-I14)*Seg2_Fee+MAX(0,J15-I15)*Seg3_Fee+MAX(0,J16-I16)*Seg4_Fee+MAX(0,J17-I17)*Seg5_Fee -> 0 | K44: =MAX(0,K13-J13)*Seg1_Fee+MAX(0,K14-J14)*Seg2_Fee+MAX(0,K15-J15)*Seg3_Fee+MAX(0,K16-J16)*Seg4_Fee+MAX(0,K17-J17)*Seg5_Fee -> 0 | ... W44: =MAX(0,W13-V13)*Seg1_Fee+MAX(0,W14-V14)*Seg2_Fee+MAX(0,W15-V15)*Seg3_Fee+MAX(0,W16-V16)*Seg4_Fee+MAX(0,W17-V17)*Seg5_Fee -> 0
A45: TOTAL DES RECETTES D'EXPLOITATION [B = VAN] | B45: =C45+NPV(Hurdle,D45:W45) -> 1843667.6 | C45: =C43+C44 -> 0 | D45: =D43+D44 -> 93674.4 | E45: =E43+E44 -> 133291.86 | F45: =F43+F44 -> 164500.59 | G45: =G43+G44 -> 172688.62 | H45: =H43+H44 -> 183205.36 | I45: =I43+I44 -> 194362.56 | J45: =J43+J44 -> 206199.24 | ... W45: =W43+W44 -> 444687.49
A47: COÛTS D'EXPLOITATION
A48: Exploitation et maintenance fixes | B48: =SUM(C48:W48) -> 772236.77 | C48: 0 | D48: =HardCapex*O_FixedPct*D9*LevOpex*D6 -> 28739.338 | E48: =HardCapex*O_FixedPct*E9*LevOpex*E6 -> 29601.518 | F48: =HardCapex*O_FixedPct*F9*LevOpex*F6 -> 30489.563 | G48: =HardCapex*O_FixedPct*G9*LevOpex*G6 -> 31404.25 | H48: =HardCapex*O_FixedPct*H9*LevOpex*H6 -> 32346.378 | I48: =HardCapex*O_FixedPct*I9*LevOpex*I6 -> 33316.769 | J48: =HardCapex*O_FixedPct*J9*LevOpex*J6 -> 34316.272 | K48: =HardCapex*O_FixedPct*K9*LevOpex*K6 -> 35345.76 | ... W48: =HardCapex*O_FixedPct*W9*LevOpex*W6 -> 50394.603
A49: Personnel et opérateur | B49: =SUM(C49:W49) -> 483666.74 | C49: 0 | D49: =O_Staff*D9*LevOpex*D6 -> 18000 | E49: =O_Staff*E9*LevOpex*E6 -> 18540 | F49: =O_Staff*F9*LevOpex*F6 -> 19096.2 | G49: =O_Staff*G9*LevOpex*G6 -> 19669.086 | H49: =O_Staff*H9*LevOpex*H6 -> 20259.159 | I49: =O_Staff*I9*LevOpex*I6 -> 20866.933 | J49: =O_Staff*J9*LevOpex*J6 -> 21492.941 | K49: =O_Staff*K9*LevOpex*K6 -> 22137.73 | ... W49: =O_Staff*W9*LevOpex*W6 -> 31563.109
A50: Assurance | B50: =SUM(C50:W50) -> 177614.46 | C50: 0 | D50: =TotalCapex*O_InsPct*D9*LevOpex*D6 -> 6610.0477 | E50: =TotalCapex*O_InsPct*E9*LevOpex*E6 -> 6808.3491 | F50: =TotalCapex*O_InsPct*F9*LevOpex*F6 -> 7012.5996 | G50: =TotalCapex*O_InsPct*G9*LevOpex*G6 -> 7222.9776 | H50: =TotalCapex*O_InsPct*H9*LevOpex*H6 -> 7439.6669 | I50: =TotalCapex*O_InsPct*I9*LevOpex*I6 -> 7662.8569 | J50: =TotalCapex*O_InsPct*J9*LevOpex*J6 -> 7892.7426 | K50: =TotalCapex*O_InsPct*K9*LevOpex*K6 -> 8129.5249 | ... W50: =TotalCapex*O_InsPct*W9*LevOpex*W6 -> 11590.759
A51: Licences et redevances | B51: =SUM(C51:W51) -> 80611.123 | C51: 0 | D51: =O_Fees*D9*LevOpex*D6 -> 3000 | E51: =O_Fees*E9*LevOpex*E6 -> 3090 | F51: =O_Fees*F9*LevOpex*F6 -> 3182.7 | G51: =O_Fees*G9*LevOpex*G6 -> 3278.181 | H51: =O_Fees*H9*LevOpex*H6 -> 3376.5264 | I51: =O_Fees*I9*LevOpex*I6 -> 3477.8222 | J51: =O_Fees*J9*LevOpex*J6 -> 3582.1569 | K51: =O_Fees*K9*LevOpex*K6 -> 3689.6216 | ... W51: =O_Fees*W9*LevOpex*W6 -> 5260.5182
A52: Gestion clientèle | B52: =SUM(C52:W52) -> 159074.22 | C52: 0 | D52: =D45*O_CustPct -> 2810.232 | E52: =E45*O_CustPct -> 3998.7558 | F52: =F45*O_CustPct -> 4935.0176 | G52: =G45*O_CustPct -> 5180.6586 | H52: =H45*O_CustPct -> 5496.1607 | I52: =I45*O_CustPct -> 5830.8769 | J52: =J45*O_CustPct -> 6185.9773 | K52: =K45*O_CustPct -> 6562.7033 | ... W52: =W45*O_CustPct -> 13340.625
A53: Maintenance diesel | B53: =SUM(C53:W53) -> 140322.5 | C53: 0 | D53: =D32*O_DieselOM*D9*LevOpex -> 859.09091 | E53: =E32*O_DieselOM*E9*LevOpex -> 1291.1635 | F53: =F32*O_DieselOM*F9*LevOpex -> 1611.524 | G53: =G32*O_DieselOM*G9*LevOpex -> 1709.6658 | H53: =H32*O_DieselOM*H9*LevOpex -> 1813.7844 | I53: =I32*O_DieselOM*I9*LevOpex -> 1924.2439 | J53: =J32*O_DieselOM*J9*LevOpex -> 2197.8218 | K53: =K32*O_DieselOM*K9*LevOpex -> 2988.3733 | ... W53: =W32*O_DieselOM*W9*LevOpex -> 18961.419
A54: Carburant diesel | B54: =SUM(C54:W54) -> 1870966.7 | C54: 0 | D54: =D34*FuelPrice*D9 -> 11454.545 | E54: =E34*FuelPrice*E9 -> 17215.514 | F54: =F34*FuelPrice*F9 -> 21486.986 | G54: =G34*FuelPrice*G9 -> 22795.544 | H54: =H34*FuelPrice*H9 -> 24183.792 | I54: =I34*FuelPrice*I9 -> 25656.585 | J54: =J34*FuelPrice*J9 -> 29304.29 | K54: =K34*FuelPrice*K9 -> 39844.977 | ... W54: =W34*FuelPrice*W9 -> 252818.92
A55: TOTAL OPEX [B = VAN] | B55: =C55+NPV(Hurdle,D55:W55) -> 1182705.1 | C55: =C48+C49+C50+C51+C52+C53+C54 -> 0 | D55: =D48+D49+D50+D51+D52+D53+D54 -> 71473.254 | E55: =E48+E49+E50+E51+E52+E53+E54 -> 80545.3 | F55: =F48+F49+F50+F51+F52+F53+F54 -> 87814.591 | G55: =G48+G49+G50+G51+G52+G53+G54 -> 91260.363 | H55: =H48+H49+H50+H51+H52+H53+H54 -> 94915.467 | I55: =I48+I49+I50+I51+I52+I53+I54 -> 98736.088 | J55: =J48+J49+J50+J51+J52+J53+J54 -> 104972.2 | ... W55: =W48+W49+W50+W51+W52+W53+W54 -> 383929.95
A57: EBE | B57: =SUM(C57:W57) -> 1617981.5 | C57: =C45-C55 -> 0 | D57: =D45-D55 -> 22201.146 | E57: =E45-E55 -> 52746.561 | F57: =F45-F55 -> 76685.995 | G57: =G45-G55 -> 81428.256 | H57: =H45-H55 -> 88289.889 | I57: =I45-I55 -> 95626.475 | J57: =J45-J55 -> 101227.04 | ... W57: =W45-W55 -> 60757.535
A58: Marge d'EBE | C58: 0 | D58: =IFERROR(D57/D45,0) -> 0.23700334 | E58: =IFERROR(E57/E45,0) -> 0.39572229 | F58: =IFERROR(F57/F45,0) -> 0.4661746 | G58: =IFERROR(G57/G45,0) -> 0.47153227 | H58: =IFERROR(H57/H45,0) -> 0.48191762 | I58: =IFERROR(I57/I45,0) -> 0.49200048 | J58: =IFERROR(J57/J45,0) -> 0.49091858 | K58: =IFERROR(K57/K45,0) -> 0.45739422 | ... W58: =IFERROR(W57/W45,0) -> 0.13662974
A60: CAPEX, REMPLACEMENTS & SUBVENTIONS
A61: CAPEX initial [B = VAN] | B61: =C61+NPV(Hurdle,D61:W61) -> 1322009.5 | C61: =TotalCapex -> 1322009.5 | D61: =0 -> 0 | E61: =0 -> 0 | F61: =0 -> 0 | G61: =0 -> 0 | H61: =0 -> 0 | I61: =0 -> 0 | J61: =0 -> 0 | K61: =0 -> 0 | ... W61: =0 -> 0
A62: Remplacement des batteries [B = VAN] | B62: =C62+NPV(Hurdle,D62:W62) -> 178069.05 | C62: 0 | D62: =IF(AND(D6=1,MOD(D4,BattLife)=0,D4<Life),BESS_kWh*C_BattRepl*LevCapex*D9,0) -> 0 | E62: =IF(AND(E6=1,MOD(E4,BattLife)=0,E4<Life),BESS_kWh*C_BattRepl*LevCapex*E9,0) -> 0 | F62: =IF(AND(F6=1,MOD(F4,BattLife)=0,F4<Life),BESS_kWh*C_BattRepl*LevCapex*F9,0) -> 0 | G62: =IF(AND(G6=1,MOD(G4,BattLife)=0,G4<Life),BESS_kWh*C_BattRepl*LevCapex*G9,0) -> 0 | H62: =IF(AND(H6=1,MOD(H4,BattLife)=0,H4<Life),BESS_kWh*C_BattRepl*LevCapex*H9,0) -> 0 | I62: =IF(AND(I6=1,MOD(I4,BattLife)=0,I4<Life),BESS_kWh*C_BattRepl*LevCapex*I9,0) -> 0 | J62: =IF(AND(J6=1,MOD(J4,BattLife)=0,J4<Life),BESS_kWh*C_BattRepl*LevCapex*J9,0) -> 0 | K62: =IF(AND(K6=1,MOD(K4,BattLife)=0,K4<Life),BESS_kWh*C_BattRepl*LevCapex*K9,0) -> 239922.68 | ... W62: =IF(AND(W6=1,MOD(W4,BattLife)=0,W4<Life),BESS_kWh*C_BattRepl*LevCapex*W9,0) -> 0
A63: Subvention d'investissement reçue | B63: =SUM(C63:W63) -> 680000 | C63: =Grant -> 680000 | D63: =0 -> 0 | E63: =0 -> 0 | F63: =0 -> 0 | G63: =0 -> 0 | H63: =0 -> 0 | I63: =0 -> 0 | J63: =0 -> 0 | K63: =0 -> 0 | ... W63: =0 -> 0
A64: RBF reçu | B64: =SUM(C64:W64) -> 242500 | C64: 0 | D64: =IF(D4-RBFLag>=1,INDEX($C$19:$W$19,1,D4-RBFLag+1)*RBFperConn,0) -> 145500 | E64: =IF(E4-RBFLag>=1,INDEX($C$19:$W$19,1,E4-RBFLag+1)*RBFperConn,0) -> 60625 | F64: =IF(F4-RBFLag>=1,INDEX($C$19:$W$19,1,F4-RBFLag+1)*RBFperConn,0) -> 36375 | G64: =IF(G4-RBFLag>=1,INDEX($C$19:$W$19,1,G4-RBFLag+1)*RBFperConn,0) -> 0 | H64: =IF(H4-RBFLag>=1,INDEX($C$19:$W$19,1,H4-RBFLag+1)*RBFperConn,0) -> 0 | I64: =IF(I4-RBFLag>=1,INDEX($C$19:$W$19,1,I4-RBFLag+1)*RBFperConn,0) -> 0 | J64: =IF(J4-RBFLag>=1,INDEX($C$19:$W$19,1,J4-RBFLag+1)*RBFperConn,0) -> 0 | K64: =IF(K4-RBFLag>=1,INDEX($C$19:$W$19,1,K4-RBFLag+1)*RBFperConn,0) -> 0 | ... W64: =IF(W4-RBFLag>=1,INDEX($C$19:$W$19,1,W4-RBFLag+1)*RBFperConn,0) -> 0
A65: Dotation à la réserve de maintenance (batteries) | B65: =SUM(C65:W65) -> 543849.56 | C65: 0 | D65: =IF(AND(UseMRA=1,D6=1,CEILING(D4,BattLife)<Life),BESS_kWh*C_BattRepl*LevCapex*(1+CostEsc)^(CEILING(D4,BattLife)-1)/BattLife,0) -> 29990.336 | E65: =IF(AND(UseMRA=1,E6=1,CEILING(E4,BattLife)<Life),BESS_kWh*C_BattRepl*LevCapex*(1+CostEsc)^(CEILING(E4,BattLife)-1)/BattLife,0) -> 29990.336 | F65: =IF(AND(UseMRA=1,F6=1,CEILING(F4,BattLife)<Life),BESS_kWh*C_BattRepl*LevCapex*(1+CostEsc)^(CEILING(F4,BattLife)-1)/BattLife,0) -> 29990.336 | G65: =IF(AND(UseMRA=1,G6=1,CEILING(G4,BattLife)<Life),BESS_kWh*C_BattRepl*LevCapex*(1+CostEsc)^(CEILING(G4,BattLife)-1)/BattLife,0) -> 29990.336 | H65: =IF(AND(UseMRA=1,H6=1,CEILING(H4,BattLife)<Life),BESS_kWh*C_BattRepl*LevCapex*(1+CostEsc)^(CEILING(H4,BattLife)-1)/BattLife,0) -> 29990.336 | I65: =IF(AND(UseMRA=1,I6=1,CEILING(I4,BattLife)<Life),BESS_kWh*C_BattRepl*LevCapex*(1+CostEsc)^(CEILING(I4,BattLife)-1)/BattLife,0) -> 29990.336 | J65: =IF(AND(UseMRA=1,J6=1,CEILING(J4,BattLife)<Life),BESS_kWh*C_BattRepl*LevCapex*(1+CostEsc)^(CEILING(J4,BattLife)-1)/BattLife,0) -> 29990.336 | K65: =IF(AND(UseMRA=1,K6=1,CEILING(K4,BattLife)<Life),BESS_kWh*C_BattRepl*LevCapex*(1+CostEsc)^(CEILING(K4,BattLife)-1)/BattLife,0) -> 29990.336 | ... W65: =IF(AND(UseMRA=1,W6=1,CEILING(W4,BattLife)<Life),BESS_kWh*C_BattRepl*LevCapex*(1+CostEsc)^(CEILING(W4,BattLife)-1)/BattLife,0) -> 0
A66: Coût de remplacement imputé au CFADS | B66: =SUM(C66:W66) -> 543849.56 | C66: 0 | D66: =IF(UseMRA=1,D65,D62) -> 29990.336 | E66: =IF(UseMRA=1,E65,E62) -> 29990.336 | F66: =IF(UseMRA=1,F65,F62) -> 29990.336 | G66: =IF(UseMRA=1,G65,G62) -> 29990.336 | H66: =IF(UseMRA=1,H65,H62) -> 29990.336 | I66: =IF(UseMRA=1,I65,I62) -> 29990.336 | J66: =IF(UseMRA=1,J65,J62) -> 29990.336 | K66: =IF(UseMRA=1,K65,K62) -> 29990.336 | ... W66: =IF(UseMRA=1,W65,W62) -> 0
A68: IMPÔT (simplifié)
A69: Amortissement fiscal | B69: =SUM(C69:W69) -> 1322009.5 | C69: 0 | D69: =IF(D4<=MIN(DepYears,Life),TotalCapex/DepYears,0) -> 88133.969 | E69: =IF(E4<=MIN(DepYears,Life),TotalCapex/DepYears,0) -> 88133.969 | F69: =IF(F4<=MIN(DepYears,Life),TotalCapex/DepYears,0) -> 88133.969 | G69: =IF(G4<=MIN(DepYears,Life),TotalCapex/DepYears,0) -> 88133.969 | H69: =IF(H4<=MIN(DepYears,Life),TotalCapex/DepYears,0) -> 88133.969 | I69: =IF(I4<=MIN(DepYears,Life),TotalCapex/DepYears,0) -> 88133.969 | J69: =IF(J4<=MIN(DepYears,Life),TotalCapex/DepYears,0) -> 88133.969 | K69: =IF(K4<=MIN(DepYears,Life),TotalCapex/DepYears,0) -> 88133.969 | ... W69: =IF(W4<=MIN(DepYears,Life),TotalCapex/DepYears,0) -> 0
A70: Impôt - hors dette (pour le TRI projet) | B70: =SUM(C70:W70) -> 105131.59 | C70: 0 | D70: =MAX(0,D57-D69)*TaxRate -> 0 | E70: =MAX(0,E57-E69)*TaxRate -> 0 | F70: =MAX(0,F57-F69)*TaxRate -> 0 | G70: =MAX(0,G57-G69)*TaxRate -> 0 | H70: =MAX(0,H57-H69)*TaxRate -> 38.979882 | I70: =MAX(0,I57-I69)*TaxRate -> 1873.1263 | J70: =MAX(0,J57-J69)*TaxRate -> 3273.2676 | K70: =MAX(0,K57-K69)*TaxRate -> 2981.0292 | ... W70: =MAX(0,W57-W69)*TaxRate -> 15189.384
A71: Impôt - avec dette (après intérêts) | B71: =SUM(C71:W71) -> 97113.311 | C71: 0 | D71: =MAX(0,D57-D69-D76)*TaxRate -> 0 | E71: =MAX(0,E57-E69-E76)*TaxRate -> 0 | F71: =MAX(0,F57-F69-F76)*TaxRate -> 0 | G71: =MAX(0,G57-G69-G76)*TaxRate -> 0 | H71: =MAX(0,H57-H69-H76)*TaxRate -> 0 | I71: =MAX(0,I57-I69-I76)*TaxRate -> 0 | J71: =MAX(0,J57-J69-J76)*TaxRate -> 931.49007 | K71: =MAX(0,K57-K69-K76)*TaxRate -> 1151.325 | ... W71: =MAX(0,W57-W69-W76)*TaxRate -> 15189.384
A73: DETTE SENIOR
A74: Solde d'ouverture | C74: 0 | D74: =C78 -> 192602.86 | E74: =D78 -> 192602.86 | F74: =E78 -> 177811.19 | G74: =F78 -> 161688.27 | H74: =G78 -> 144114.29 | I74: =H78 -> 124958.65 | J74: =I78 -> 104079 | K74: =J78 -> 81320.187 | ... W74: =V78 -> 0
A75: Tirage | B75: =SUM(C75:W75) -> 192602.86 | C75: =DebtAmt -> 192602.86 | D75: =0 -> 0 | E75: =0 -> 0 | F75: =0 -> 0 | G75: =0 -> 0 | H75: =0 -> 0 | I75: =0 -> 0 | J75: =0 -> 0 | K75: =0 -> 0 | ... W75: =0 -> 0
A76: Intérêts | B76: =SUM(C76:W76) -> 113864.74 | C76: 0 | D76: =D74*IntRate -> 17334.258 | E76: =E74*IntRate -> 17334.258 | F76: =F74*IntRate -> 16003.007 | G76: =G74*IntRate -> 14551.945 | H76: =H74*IntRate -> 12970.286 | I76: =I74*IntRate -> 11246.279 | J76: =J74*IntRate -> 9367.1103 | K76: =K74*IntRate -> 7318.8168 | ... W76: =W74*IntRate -> 0
A77: Remboursement du principal | B77: =SUM(C77:W77) -> 192602.86 | C77: 0 | D77: =IF(AND(D4>Grace,D4<=Tenor),PMT(IntRate,Tenor-Grace,-DebtAmt)-D76,0) -> 0 | E77: =IF(AND(E4>Grace,E4<=Tenor),PMT(IntRate,Tenor-Grace,-DebtAmt)-E76,0) -> 14791.669 | F77: =IF(AND(F4>Grace,F4<=Tenor),PMT(IntRate,Tenor-Grace,-DebtAmt)-F76,0) -> 16122.919 | G77: =IF(AND(G4>Grace,G4<=Tenor),PMT(IntRate,Tenor-Grace,-DebtAmt)-G76,0) -> 17573.982 | H77: =IF(AND(H4>Grace,H4<=Tenor),PMT(IntRate,Tenor-Grace,-DebtAmt)-H76,0) -> 19155.64 | I77: =IF(AND(I4>Grace,I4<=Tenor),PMT(IntRate,Tenor-Grace,-DebtAmt)-I76,0) -> 20879.648 | J77: =IF(AND(J4>Grace,J4<=Tenor),PMT(IntRate,Tenor-Grace,-DebtAmt)-J76,0) -> 22758.816 | K77: =IF(AND(K4>Grace,K4<=Tenor),PMT(IntRate,Tenor-Grace,-DebtAmt)-K76,0) -> 24807.11 | ... W77: =IF(AND(W4>Grace,W4<=Tenor),PMT(IntRate,Tenor-Grace,-DebtAmt)-W76,0) -> 0
A78: Solde de clôture | C78: =0+C75-0 -> 192602.86 | D78: =D74+D75-D77 -> 192602.86 | E78: =E74+E75-E77 -> 177811.19 | F78: =F74+F75-F77 -> 161688.27 | G78: =G74+G75-G77 -> 144114.29 | H78: =H74+H75-H77 -> 124958.65 | I78: =I74+I75-I77 -> 104079 | J78: =J74+J75-J77 -> 81320.187 | K78: =K74+K75-K77 -> 56513.077 | ... W78: =W74+W75-W77 -> 0
A79: Service total de la dette | B79: =SUM(C79:W79) -> 306467.6 | C79: 0 | D79: =D76+D77 -> 17334.258 | E79: =E76+E77 -> 32125.927 | F79: =F76+F77 -> 32125.927 | G79: =G76+G77 -> 32125.927 | H79: =H76+H77 -> 32125.927 | I79: =I76+I77 -> 32125.927 | J79: =J76+J77 -> 32125.927 | K79: =K76+K77 -> 32125.927 | ... W79: =W76+W77 -> 0
A81: FLUX DE TRÉSORERIE
A82: Flux du projet AVANT subventions (hors dette) [B = VAN] | B82: =C82+NPV(Hurdle,D82:W82) -> -862669.04 | C82: =-C61+C57-C62-C70 -> -1322009.5 | D82: =-D61+D57-D62-D70 -> 22201.146 | E82: =-E61+E57-E62-E70 -> 52746.561 | F82: =-F61+F57-F62-F70 -> 76685.995 | G82: =-G61+G57-G62-G70 -> 81428.256 | H82: =-H61+H57-H62-H70 -> 88250.909 | I82: =-I61+I57-I62-I70 -> 93753.348 | J82: =-J61+J57-J62-J70 -> 97953.772 | ... W82: =-W61+W57-W62-W70 -> 45568.151
A83: Flux du projet APRÈS subventions (hors dette) [B = VAN] | B83: =C83+NPV(Hurdle,D83:W83) -> 27036.068 | C83: =C82+C63+C64 -> -642009.54 | D83: =D82+D63+D64 -> 167701.15 | E83: =E82+E63+E64 -> 113371.56 | F83: =F82+F63+F64 -> 113061 | G83: =G82+G63+G64 -> 81428.256 | H83: =H82+H63+H64 -> 88250.909 | I83: =I82+I63+I64 -> 93753.348 | J83: =J82+J63+J64 -> 97953.772 | ... W83: =W82+W63+W64 -> 45568.151
A84: CFADS (flux disponible pour le service de la dette) | B84: =SUM(C84:W84) -> 1219518.6 | C84: 0 | D84: =D57-D66-D71+D64 -> 137710.81 | E84: =E57-E66-E71+E64 -> 83381.226 | F84: =F57-F66-F71+F64 -> 83070.66 | G84: =G57-G66-G71+G64 -> 51437.921 | H84: =H57-H66-H71+H64 -> 58299.553 | I84: =I57-I66-I71+I64 -> 65636.139 | J84: =J57-J66-J71+J64 -> 70305.214 | K84: =K57-K66-K71+K64 -> 68916.425 | ... W84: =W57-W66-W71+W64 -> 45568.151
A85: DSCR | C85: 0 | D85: =IF(D79>0,D84/D79,"") -> 7.9444309 | E85: =IF(E79>0,E84/E79,"") -> 2.5954497 | F85: =IF(F79>0,F84/F79,"") -> 2.5857825 | G85: =IF(G79>0,G84/G79,"") -> 1.6011342 | H85: =IF(H79>0,H84/H79,"") -> 1.8147197 | I85: =IF(I79>0,I84/I79,"") -> 2.0430894 | J85: =IF(J79>0,J84/J79,"") -> 2.188426 | K85: =IF(K79>0,K84/K79,"") -> 2.1451965 | ... W85: =IF(W79>0,W84/W79,"")
A86: Flux des fonds propres [B = VAN] | B86: =C86+NPV(Hurdle,D86:W86) -> -36860.436 | C86: =-EquityAmt -> -449406.68 | D86: =D84-D79 -> 120376.55 | E86: =E84-E79 -> 51255.299 | F86: =F84-F79 -> 50944.733 | G86: =G84-G79 -> 19311.994 | H86: =H84-H79 -> 26173.627 | I86: =I84-I79 -> 33510.212 | J86: =J84-J79 -> 38179.288 | K86: =K84-K79 -> 36790.499 | ... W86: =W84-W79 -> 45568.151
A87: Flux cumulé des fonds propres | C87: =C86 -> -449406.68 | D87: =C87+D86 -> -329030.12 | E87: =D87+E86 -> -277774.83 | F87: =E87+F86 -> -226830.09 | G87: =F87+G86 -> -207518.1 | H87: =G87+H86 -> -181344.47 | I87: =H87+I86 -> -147834.26 | J87: =I87+J86 -> -109654.97 | K87: =J87+K86 -> -72864.473 | ... W87: =V87+W86 -> 463644.31
A89: ÉLÉMENTS DU LCOE (actualisés au taux minimal)
A90: Coût sur le cycle de vie (CAPEX + OPEX + remplacements) [B = VAN] | B90: =C90+NPV(Hurdle,D90:W90) -> 2627473.6 | C90: =C61+C55-C52+C62 -> 1322009.5 | D90: =D61+D55-D52+D62 -> 68663.022 | E90: =E61+E55-E52+E62 -> 76546.544 | F90: =F61+F55-F52+F62 -> 82879.573 | G90: =G61+G55-G52+G62 -> 86079.705 | H90: =H61+H55-H52+H62 -> 89419.307 | I90: =I61+I55-I52+I62 -> 92905.211 | J90: =J61+J55-J52+J62 -> 98786.225 | ... W90: =W61+W55-W52+W62 -> 370589.33
A91: Énergie vendue (kWh) [B = VAN] | B91: =C91+NPV(Hurdle,D91:W91) -> 4182843.1 | C91: =C26 -> 0 | D91: =D26 -> 252000 | E91: =E26 -> 367710 | F91: =F26 -> 445578 | G91: =G26 -> 458945.34 | H91: =H26 -> 472713.7 | I91: =I26 -> 486895.11 | J91: =J26 -> 501501.96 | ... W91: =W26 -> 736472.54
A92: Recettes d'énergie encaissées [B = VAN] | B92: =C92+NPV(Hurdle,D92:W92) -> 1833722.8 | C92: =C43 -> 0 | D92: =D43 -> 86774.4 | E92: =E43 -> 130416.86 | F92: =F43 -> 162775.59 | G92: =G43 -> 172688.62 | H92: =H43 -> 183205.36 | I92: =I43 -> 194362.56 | J92: =J43 -> 206199.24 | ... W92: =W43 -> 444687.49

Sheet Contrôles
A1: CONTRÔLES D'INTÉGRITÉ
A3: Ressources = emplois en année 0 (grant + dette + fonds propres = CAPEX) | B3: =IF(ABS(Grant+DebtAmt+EquityAmt-MAX(TotalCapex,Grant))<1,"OK","À VÉRIFIER") -> OK
A4: Dette entièrement remboursée à l'échéance | B4: =IF(ABS(INDEX('Flux de trésorerie'!$C$78:$W$78,1,MIN(Tenor,20)+1))<1,"OK","À VÉRIFIER") -> OK
A5: Durée de vie dans l'horizon modélisé | B5: =IF(AND(Life>=1,Life<=20),"OK","À VÉRIFIER") -> OK
A6: Durée du prêt dans la durée de vie | B6: =IF(Tenor<=Life,"OK","À VÉRIFIER") -> OK
A7: Différé plus court que la durée | B7: =IF(Grace<Tenor,"OK","À VÉRIFIER") -> OK
A8: Dotations à la réserve = remplacements (si réserve utilisée) | B8: =IF(OR(UseMRA=0,ABS('Flux de trésorerie'!$B$65-SUM('Flux de trésorerie'!$C$62:$W$62))<1),"OK","À VÉRIFIER") -> OK
A9: Pourcentages de montée en charge entre 0 et 100 % | B9: =IF(AND(Ramp1>=0,Ramp1<=1,Ramp2>=0,Ramp2<=1,Ramp3>=0,Ramp3<=1),"OK","À VÉRIFIER") -> OK
A10: Bilan énergétique : solaire + diesel = production | B10: =IF(ABS('Flux de trésorerie'!$B$31+'Flux de trésorerie'!$B$32-'Flux de trésorerie'!$B$29)<1,"OK","À VÉRIFIER") -> OK
A11: Au moins un client saisi | B11: =IF(TotalCustomers>0,"OK","À VÉRIFIER") -> OK
A13: GLOBAL | B13: =IF(COUNTIF(B3:B11,"OK")=9,"TOUT OK","À REVOIR") -> TOUT OK
