Workbook

Sheet COVER
B8: AFRICA ENERGY FINANCE | MODÈLES ÉCONOMIQUES ET FINANCIERS
B10: MODEL 7
B12: MODÈLE DE DÉVELOPPEMENT ET FINANCEMENT
B13: DE L'HYDROÉLECTRICITÉ
B15: De la rivière au bouclage financier
B16: Un cadre pour développeurs, prêteurs et États appliqué aux projets hydroélectriques en Afrique
B18: LE HYDRO READINESS FRAMEWORK™ : 8 questions · 23 portes · 1 décision de bouclage financier
B19: DÉVELOPPEUR · PRÊTEUR · ÉTAT
B21: Accompagne le Livre 7, Développement et financement de l'hydroélectricité, et MANUAL 7. Version 1.0, release candidate 1.
B22: Cas de référence : Kasiri River Hydro, PIE au fil de l'eau de 60 MW, République de Navaria (fictive). Toutes les données sont illustratives.
B24: STATUT ACTUEL
B25: Décision de bouclage financier (23 portes) | D25: ='30A_CLOSE_READINESS'!$C$34 -> STOP : une porte critique n'est pas franchie
B26: Portes franchies | D26: ='30A_CLOSE_READINESS'!$C$29&" sur 23" -> 6 sur 23
B27: Filtre de développement (9 portes) | D27: ='30_BANKABILITY'!$C$58 -> NOT BANKABLE : lacune(s) critique(s) à combler
B28: Filtre budgétaire | D28: ='26_DEBT_SUSTAINABILITY'!$C$35 -> LOW : faible pression budgétaire supplémentaire
B29: Contrôles d'intégrité du modèle (33_CHECKS) | D29: ='33_CHECKS'!$C$19 -> ALL OK
B30: Cohérence avec le livre (35_BOOK_CHECK) | D30: ='35_BOOK_CHECK'!E32 -> ALL PASS
B32: COMMENCER ICI
B33: 00_README | C33: Rôle du modèle, code couleur, versions
B34: 01_CONTROL_PANEL | C34: Cas, structure, stress et cas prêteurs
B35: 32_DASHBOARD | C35: Résultats : projet, financement, développeur, compagnie d'électricité, finances publiques
B36: 30A_CLOSE_READINESS | C36: Les 23 portes du bouclage financier et la décision
B37: 34_FRAMEWORK_MAP | C37: Cadre du Livre 7 relié au modèle
B38: 33_CHECKS | C38: Contrôles d'intégrité
B41: Auteur et conception : Emmanuel Boujieka Kamga
B43: Outil d'aide à la décision ; pas un conseil en investissement, juridique, fiscal ou comptable. Remplacer chaque donnée d'entrée par les données du projet avant usage.
B44: Police bleue = donnée d'entrée ; noire = formule ; verte = lien ; cellule sur fond vert = résultat clé. Pas de macros, pas de références circulaires.

Sheet 00_README
A1: MODEL 7 — Modèle de développement et de financement de l'hydroélectricité (v1.0 release candidate 1)
A2: Ce projet peut-il fournir une électricité bancable SANS créer de passifs publics insoutenables ?
A4: Objet | B4: Un moteur intégré reliant RESSOURCE HYDRAULIQUE → CENTRALE → TRANSPORT → RÉSEAU → DEMANDE → COMPAGNIE D'ÉLECTRICITÉ → RÉGULATION → CAE → FINANCEMENT → PPP/PIE → SOUTIEN DE L'ÉTAT → EXPOSITION BUDGÉTAIRE → BANCABILITÉ.
A5: Principe de base | B5: La faisabilité technique n'est pas la bancabilité financière. La bancabilité financière n'est pas la viabilité des finances publiques.
A6: Projet de référence | B6: Kasiri River Hydro (PIE au fil de l'eau de 60 MW), République de Navaria, ENTIÈREMENT FICTIF. Accompagne le Livre 7, Développement et financement de l'hydroélectricité. Toutes les données sont illustratives et doivent être remplacées par les données du projet.
A7: Utilisateurs | B7: Développeur, investisseur, prêteur, ministère des Finances / cellule PPP, compagnie d'électricité, IFD, conseiller de transaction — même moteur, lectures différentes (voir le manuel d'utilisation).
A8: Mode d'emploi | B8: 1) Choisir cas, structure et stress dans 01_CONTROL_PANEL. 2) Remplacer les données bleues des feuilles 02-17A, 21-26. 3) Lire 32_DASHBOARD et 30_BANKABILITY. 4) Vérifier que 33_CHECKS = ALL OK.
A9: Code couleur | B9: Police bleue = donnée saisie ; fond jaune = levier clé ; noire = formule ; verte = lien vers une autre feuille ; cellule sur fond vert = résultat clé.
A10: Unités | B10: Millions USD nominaux sauf mention contraire ; énergie en GWh ; puissance en MW ; données réelles en USD 2026.
A11: Calendrier | B11: Annuel, 40 périodes à partir de l'année de départ du modèle. Construction + concession doivent tenir en 40 ans (contrôlé).
A12: Circularité | B12: Aucune (contrôlé avec tools/model/check_cycles.py). Les intérêts intercalaires (IDC) et commissions sont financés par la dette dans la limite du gearing via des facteurs analytiques ; le DSRA est financé par fonds propres ; la dette commerciale est sculptée sur un CFADS du cas prêteurs avec impôt non levier. Simplifications documentées.
A13: Scénarios | B13: Trois cas exclusifs (Base/Bas/Haut) + neuf stress combinables + cinq variations de sensibilité. Instantanés du moteur complet : python tools/run_snapshots.py.
A14: Structures | B14: Cinq structures dans 17A_STRUCTURES évaluées par le moteur complet (choix dans le panneau de contrôle) et par une comparaison analytique en direct.
A15: Deux niveaux de portes | B15: Filtre de développement : 9 portes de bancabilité (30_BANKABILITY), maillon le plus faible avec seuils explicites, utilisées pour décider de poursuivre le développement. Maturité pour le bouclage : 23 portes de preuve (30A_CLOSE_READINESS) regroupées sous les huit questions du Hydro Readiness Framework du Livre 7, donnant STOP / NOT READY / CONDITIONAL GO / GO. 34_FRAMEWORK_MAP relie les deux et le livre.
... A21: Plan du classeur | B21: COVER | 00 README | 01 Contrôle, 01A Développement | 02-07 Projet, 05A Contrats | 08-10 Système électrique | 11-12 Acheteur/compagnie | 13-16 Régulation, CAE, tarif, revenus | 17-21 Financement, 17A Structures | 22-26 Finances publiques | 27-28 Scénarios/sensibilité | 29 Répartition des risques | 30 Filtre à 9 portes, 30A Maturité à 23 portes | 31 Étude de cas | 32 Tableau de bord | 33 Contrôles | 34 Carte du cadre | 35 Contrôle livre

Sheet 01_CONTROL_PANEL
A1: 01 PANNEAU DE CONTRÔLE — Choix du scénario, de la structure et du cas
A2: Bleu = donnée d'entrée. Jaune = levier clé. Chaque stress peut être combiné avec tous les autres.
A4: A. CHOIX DU CAS ET DE LA PRODUCTION
A5: Cas du modèle (1=Base, 2=Bas, 3=Haut) | B5: 1-3 | C5: 1 | D5: Multiplicateurs des cas dans 27_SCENARIOS
A6: Cas de production des flux (1=P50, 2=P75, 3=P90) | B6: 1-3 | C6: 1 | D6: Cas FP / promoteur : souvent P50
A7: Cas de production pour la dette (1=P50, 2=P75, 3=P90 à un an, 4=P90 à dix ans) | B7: 1-4 | C7: 4 | D7: Les prêteurs dimensionnent souvent la dette sur un P90 (à un an) : vérifier avec le conseiller technique des prêteurs
A8: B. STRUCTURE DE LA TRANSACTION
A9: Structure de financement / PPP (1-5, voir 17A_STRUCTURES) | B9: 1-5 | C9: 2 | D9: 1 Public | 2 PIE | 3 PPP | 4 Hybride | 5 Financement mixte
A10: Structure choisie | C10: ='17A_STRUCTURES'!$C$5 -> PIE (BOOT privé)
A11: Mode de dimensionnement de la dette (1=sculptée dans le modèle, 2=montants figés) | B11: 1-2 | C11: 1 | D11: Choisir 2 pour stresser une dette FIGÉE (coller les montants du cas de base dans 18_DEBT)
A12: Garantie budgétaire de l'État sur le déficit CAE de la compagnie (1=oui, 0=non) | B12: 0/1 | C12: 1 | D12: 1 : le déficit devient un coût budgétaire. 0 : le déficit devient un appel de garantie ou des arriérés envers le PIE
A13: Part du déficit couverte par la garantie budgétaire | B13: % | C13: 1 | D13: Le reste va à la garantie CAE, puis aux arriérés
A14: C. STRESS (1 = ACTIF). Paramètres dans 27_SCENARIOS
A15: Sécheresse | B15: 0/1 | C15: 0
A16: Dépassement du CAPEX | B16: 0/1 | C16: 0
A17: Retard de construction | B17: 0/1 | C17: 0
A18: Demande faible | B18: 0/1 | C18: 0
A19: Stress de l'acheteur | B19: 0/1 | C19: 0
A20: Dépréciation change | B20: 0/1 | C20: 0
A21: Taux d'intérêt élevé | B21: 0/1 | C21: 0
A22: Retard du transport | B22: 0/1 | C22: 0
A23: Tendance climat. débits | B23: 0/1 | C23: 0
A24: D. VARIATIONS DE SENSIBILITÉ (en plus du cas et des stress)
A25: Variation CAPEX | B25: % | C25: 0 | D25: e.g. 0.10 = +10%
A26: Variation production | B26: % | C26: 0
A27: Variation tarif CAE | B27: % | C27: 0
A28: Variation OPEX | B28: % | C28: 0
A29: Variation du taux commercial (absolue) | B29: % | C29: 0 | D29: ex. 0,01 = +100 pb
A30: E. LECTURE DU SCÉNARIO ACTIF
A31: Nombre de stress actifs | B31: # | C31: =SUM('01_CONTROL_PANEL'!$C$15,'01_CONTROL_PANEL'!$C$16,'01_CONTROL_PANEL'!$C$17,'01_CONTROL_PANEL'!$C$18,'01_CONTROL_PANEL'!$C$19,'01_CONTROL_PANEL'!$C$20,'01_CONTROL_PANEL'!$C$21,'01_CONTROL_PANEL'!$C$22,'01_CONTROL_PANEL'!$C$23) -> 0
A32: TRI du projet (après impôt, sans levier) | B32: % | C32: ='17_PROJECT_FINANCE'!$C$31 -> 0.11218248
A33: TRI FP privés | B33: % | C33: ='17_PROJECT_FINANCE'!$C$33 -> 0.1375812
A34: DSCR minimum (cas réel) | B34: x | C34: ='17_PROJECT_FINANCE'!$C$37 -> 1.5272063
A35: Besoin non couvert | B35: M USD | C35: ='17_PROJECT_FINANCE'!$C$27 -> 4.0543507
A36: VAN budgétaire pour l'État (négatif = coût net) | B36: M USD | C36: ='25_FISCAL_IMPACT'!$C$20 -> 34.788022
A37: VAN budgétaire consolidée, compagnie publique incluse | B37: M USD | C37: ='25_FISCAL_IMPACT'!$C$21 -> -27.580964
A38: TRI développeur (succès) | B38: % | C38: ='01A_DEVELOPMENT'!$C$72 -> 0.15957204
A39: Décision de bouclage financier (23 portes) | C39: ='30A_CLOSE_READINESS'!$C$34 -> STOP : une porte critique n'est pas franchie
A40: Verdict global de bancabilité | C40: ='30_BANKABILITY'!$C$58 -> NOT BANKABLE : lacune(s) critique(s) à combler
A41: Contrôles d'intégrité | C41: ='33_CHECKS'!$C$19 -> ALL OK

Sheet 01A_DEVELOPMENT
A1: 01A DÉVELOPPEMENT — Du site au bouclage financier : budget, attrition et rendements du développeur
A2: Les années de développement précèdent le départ du modèle (bouclage financier). Les probabilités sont des jugements de l'utilisateur éclairés par le dossier de recherche, pas des statistiques calibrées.
A4: A. ÉTAPES DE DÉVELOPPEMENT (données)
A5: Étape | B5: Financeur (type) | C5: Durée (mois) | D5: Budget (M USD réels) | E5: P(succès étape suiv.)
A6: 1. Identification du site et reconnaissance | B6: FP du développeur | C6: 6 | D6: 0.1 | E6: 0.6
A7: 2. Préfaisabilité et début du jaugeage | B7: Fonds propres du développeur / subvention de préparation | C7: 12 | D7: 0.6 | E7: 0.6
A8: 3. Faisabilité, EIES, études géotechniques et réseau | B8: FP de dévelop., facilité de préparation | C8: 18 | D8: 4.5 | E8: 0.7
A9: 4. Licences, droits d'eau, foncier et permis | B9: FP de développement | C9: 12 | D9: 0.8 | E9: 0.85
A10: 5. CAE, convention de mise en œuvre et homologation du tarif | B10: FP de développement | C10: 12 | D10: 0.8 | E10: 0.8
A11: 6. Financement : conseillers des prêteurs, juridique, assurances, bouclage | B11: FP de dévelop., co-développeur | C11: 12 | D11: 2.2 | E11: 0.85
A12: Budget total de développement (réel) | B12: M USD | C12: =SUM(D6:D11) -> 9
A13: Durée de développement | B13: ans | C13: =SUM(C6:C11)/12 -> 6
A14: Probabilité d'atteindre le bouclage depuis la reconnaissance | B14: % | C14: =PRODUCT(E6:E11) -> 0.145656
A15: Budget dévelop. / CAPEX centrale | B15: % | C15: ='01A_DEVELOPMENT'!$C$12/'06_CONSTRUCTION'!$C$9 -> 0.057376004
A17: B. CONDITIONS DÉVELOPPEUR (données)
A18: Prime de développement versée au bouclage (% du CAPEX centrale) | B18: % | C18: 0.03 | D18: Négociée ; vérifier par rapport au dossier de recherche avant usage
A19: Prime de développement | B19: M USD | C19: ='01A_DEVELOPMENT'!$C$18*'06_CONSTRUCTION'!$C$9 -> 4.7058
A20: Part du développeur dans les fonds propres privés après bouclage | B20: % | C20: 0.4 | D20: Le reste par un co-investisseur ou un fonds
A21: Taux d'actualisation du développeur pour les flux de développement | B21: % | C21: 0.25 | D21: Capital à haut risque ; hypothèse
A22: Taux d'actualisation des fonds propres au bouclage (risque de construction) | B22: % | C22: 0.15 | D22: Hypothèse
A23: Taux d'actualisation des fonds propres à la COD (actif en exploitation) | B23: % | C23: 0.11 | D23: Hypothèse
A25: C. FLUX DE DÉVELOPPEMENT SUR LE SCÉNARIO DE SUCCÈS (M USD nominaux ; colonnes = années de développement, dernière = année avant bouclage)
A26: Année de dévelop. | F26: ='02_PROJECT_INPUTS'!$C$10-10+0 -> 2017 | G26: ='02_PROJECT_INPUTS'!$C$10-10+1 -> 2018 | H26: ='02_PROJECT_INPUTS'!$C$10-10+2 -> 2019 | I26: ='02_PROJECT_INPUTS'!$C$10-10+3 -> 2020 | J26: ='02_PROJECT_INPUTS'!$C$10-10+4 -> 2021 | K26: ='02_PROJECT_INPUTS'!$C$10-10+5 -> 2022 | L26: ='02_PROJECT_INPUTS'!$C$10-10+6 -> 2023 | M26: ='02_PROJECT_INPUTS'!$C$10-10+7 -> 2024 | N26: ='02_PROJECT_INPUTS'!$C$10-10+8 -> 2025 | O26: ='02_PROJECT_INPUTS'!$C$10-10+9 -> 2026
A27: Dépense : étape 1 | F27: =IF($C$6>0,MAX(0,MIN(SUM('01A_DEVELOPMENT'!$C$6:$C$11)-12*(10-1-0)-0,SUM($C$6:$C$6))-MAX(SUM('01A_DEVELOPMENT'!$C$6:$C$11)-12*(10-0),SUM($C$6:$C$6)-$C$6))/$C$6*$D$6,0)*(1+'02_PROJECT_INPUTS'!$C$18)^(F$26-'02_PROJECT_INPUTS'!$C$11) -> 0 | G27: =IF($C$6>0,MAX(0,MIN(SUM('01A_DEVELOPMENT'!$C$6:$C$11)-12*(10-1-1)-0,SUM($C$6:$C$6))-MAX(SUM('01A_DEVELOPMENT'!$C$6:$C$11)-12*(10-1),SUM($C$6:$C$6)-$C$6))/$C$6*$D$6,0)*(1+'02_PROJECT_INPUTS'!$C$18)^(G$26-'02_PROJECT_INPUTS'!$C$11) -> 0 | H27: =IF($C$6>0,MAX(0,MIN(SUM('01A_DEVELOPMENT'!$C$6:$C$11)-12*(10-1-2)-0,SUM($C$6:$C$6))-MAX(SUM('01A_DEVELOPMENT'!$C$6:$C$11)-12*(10-2),SUM($C$6:$C$6)-$C$6))/$C$6*$D$6,0)*(1+'02_PROJECT_INPUTS'!$C$18)^(H$26-'02_PROJECT_INPUTS'!$C$11) -> 0 | I27: =IF($C$6>0,MAX(0,MIN(SUM('01A_DEVELOPMENT'!$C$6:$C$11)-12*(10-1-3)-0,SUM($C$6:$C$6))-MAX(SUM('01A_DEVELOPMENT'!$C$6:$C$11)-12*(10-3),SUM($C$6:$C$6)-$C$6))/$C$6*$D$6,0)*(1+'02_PROJECT_INPUTS'!$C$18)^(I$26-'02_PROJECT_INPUTS'!$C$11) -> 0 | J27: =IF($C$6>0,MAX(0,MIN(SUM('01A_DEVELOPMENT'!$C$6:$C$11)-12*(10-1-4)-0,SUM($C$6:$C$6))-MAX(SUM('01A_DEVELOPMENT'!$C$6:$C$11)-12*(10-4),SUM($C$6:$C$6)-$C$6))/$C$6*$D$6,0)*(1+'02_PROJECT_INPUTS'!$C$18)^(J$26-'02_PROJECT_INPUTS'!$C$11) -> 0.090573081 | K27: =IF($C$6>0,MAX(0,MIN(SUM('01A_DEVELOPMENT'!$C$6:$C$11)-12*(10-1-5)-0,SUM($C$6:$C$6))-MAX(SUM('01A_DEVELOPMENT'!$C$6:$C$11)-12*(10-5),SUM($C$6:$C$6)-$C$6))/$C$6*$D$6,0)*(1+'02_PROJECT_INPUTS'!$C$18)^(K$26-'02_PROJECT_INPUTS'!$C$11) -> 0 | L27: =IF($C$6>0,MAX(0,MIN(SUM('01A_DEVELOPMENT'!$C$6:$C$11)-12*(10-1-6)-0,SUM($C$6:$C$6))-MAX(SUM('01A_DEVELOPMENT'!$C$6:$C$11)-12*(10-6),SUM($C$6:$C$6)-$C$6))/$C$6*$D$6,0)*(1+'02_PROJECT_INPUTS'!$C$18)^(L$26-'02_PROJECT_INPUTS'!$C$11) -> 0 | M27: =IF($C$6>0,MAX(0,MIN(SUM('01A_DEVELOPMENT'!$C$6:$C$11)-12*(10-1-7)-0,SUM($C$6:$C$6))-MAX(SUM('01A_DEVELOPMENT'!$C$6:$C$11)-12*(10-7),SUM($C$6:$C$6)-$C$6))/$C$6*$D$6,0)*(1+'02_PROJECT_INPUTS'!$C$18)^(M$26-'02_PROJECT_INPUTS'!$C$11) -> 0 | N27: =IF($C$6>0,MAX(0,MIN(SUM('01A_DEVELOPMENT'!$C$6:$C$11)-12*(10-1-8)-0,SUM($C$6:$C$6))-MAX(SUM('01A_DEVELOPMENT'!$C$6:$C$11)-12*(10-8),SUM($C$6:$C$6)-$C$6))/$C$6*$D$6,0)*(1+'02_PROJECT_INPUTS'!$C$18)^(N$26-'02_PROJECT_INPUTS'!$C$11) -> 0 | O27: =IF($C$6>0,MAX(0,MIN(SUM('01A_DEVELOPMENT'!$C$6:$C$11)-12*(10-1-9)-0,SUM($C$6:$C$6))-MAX(SUM('01A_DEVELOPMENT'!$C$6:$C$11)-12*(10-9),SUM($C$6:$C$6)-$C$6))/$C$6*$D$6,0)*(1+'02_PROJECT_INPUTS'!$C$18)^(O$26-'02_PROJECT_INPUTS'!$C$11) -> 0
A28: Dépense : étape 2 | F28: =IF($C$7>0,MAX(0,MIN(SUM('01A_DEVELOPMENT'!$C$6:$C$11)-12*(10-1-0)-0,SUM($C$6:$C$7))-MAX(SUM('01A_DEVELOPMENT'!$C$6:$C$11)-12*(10-0),SUM($C$6:$C$7)-$C$7))/$C$7*$D$7,0)*(1+'02_PROJECT_INPUTS'!$C$18)^(F$26-'02_PROJECT_INPUTS'!$C$11) -> 0 | G28: =IF($C$7>0,MAX(0,MIN(SUM('01A_DEVELOPMENT'!$C$6:$C$11)-12*(10-1-1)-0,SUM($C$6:$C$7))-MAX(SUM('01A_DEVELOPMENT'!$C$6:$C$11)-12*(10-1),SUM($C$6:$C$7)-$C$7))/$C$7*$D$7,0)*(1+'02_PROJECT_INPUTS'!$C$18)^(G$26-'02_PROJECT_INPUTS'!$C$11) -> 0 | H28: =IF($C$7>0,MAX(0,MIN(SUM('01A_DEVELOPMENT'!$C$6:$C$11)-12*(10-1-2)-0,SUM($C$6:$C$7))-MAX(SUM('01A_DEVELOPMENT'!$C$6:$C$11)-12*(10-2),SUM($C$6:$C$7)-$C$7))/$C$7*$D$7,0)*(1+'02_PROJECT_INPUTS'!$C$18)^(H$26-'02_PROJECT_INPUTS'!$C$11) -> 0 | I28: =IF($C$7>0,MAX(0,MIN(SUM('01A_DEVELOPMENT'!$C$6:$C$11)-12*(10-1-3)-0,SUM($C$6:$C$7))-MAX(SUM('01A_DEVELOPMENT'!$C$6:$C$11)-12*(10-3),SUM($C$6:$C$7)-$C$7))/$C$7*$D$7,0)*(1+'02_PROJECT_INPUTS'!$C$18)^(I$26-'02_PROJECT_INPUTS'!$C$11) -> 0 | J28: =IF($C$7>0,MAX(0,MIN(SUM('01A_DEVELOPMENT'!$C$6:$C$11)-12*(10-1-4)-0,SUM($C$6:$C$7))-MAX(SUM('01A_DEVELOPMENT'!$C$6:$C$11)-12*(10-4),SUM($C$6:$C$7)-$C$7))/$C$7*$D$7,0)*(1+'02_PROJECT_INPUTS'!$C$18)^(J$26-'02_PROJECT_INPUTS'!$C$11) -> 0.27171924 | K28: =IF($C$7>0,MAX(0,MIN(SUM('01A_DEVELOPMENT'!$C$6:$C$11)-12*(10-1-5)-0,SUM($C$6:$C$7))-MAX(SUM('01A_DEVELOPMENT'!$C$6:$C$11)-12*(10-5),SUM($C$6:$C$7)-$C$7))/$C$7*$D$7,0)*(1+'02_PROJECT_INPUTS'!$C$18)^(K$26-'02_PROJECT_INPUTS'!$C$11) -> 0.27715363 | L28: =IF($C$7>0,MAX(0,MIN(SUM('01A_DEVELOPMENT'!$C$6:$C$11)-12*(10-1-6)-0,SUM($C$6:$C$7))-MAX(SUM('01A_DEVELOPMENT'!$C$6:$C$11)-12*(10-6),SUM($C$6:$C$7)-$C$7))/$C$7*$D$7,0)*(1+'02_PROJECT_INPUTS'!$C$18)^(L$26-'02_PROJECT_INPUTS'!$C$11) -> 0 | M28: =IF($C$7>0,MAX(0,MIN(SUM('01A_DEVELOPMENT'!$C$6:$C$11)-12*(10-1-7)-0,SUM($C$6:$C$7))-MAX(SUM('01A_DEVELOPMENT'!$C$6:$C$11)-12*(10-7),SUM($C$6:$C$7)-$C$7))/$C$7*$D$7,0)*(1+'02_PROJECT_INPUTS'!$C$18)^(M$26-'02_PROJECT_INPUTS'!$C$11) -> 0 | N28: =IF($C$7>0,MAX(0,MIN(SUM('01A_DEVELOPMENT'!$C$6:$C$11)-12*(10-1-8)-0,SUM($C$6:$C$7))-MAX(SUM('01A_DEVELOPMENT'!$C$6:$C$11)-12*(10-8),SUM($C$6:$C$7)-$C$7))/$C$7*$D$7,0)*(1+'02_PROJECT_INPUTS'!$C$18)^(N$26-'02_PROJECT_INPUTS'!$C$11) -> 0 | O28: =IF($C$7>0,MAX(0,MIN(SUM('01A_DEVELOPMENT'!$C$6:$C$11)-12*(10-1-9)-0,SUM($C$6:$C$7))-MAX(SUM('01A_DEVELOPMENT'!$C$6:$C$11)-12*(10-9),SUM($C$6:$C$7)-$C$7))/$C$7*$D$7,0)*(1+'02_PROJECT_INPUTS'!$C$18)^(O$26-'02_PROJECT_INPUTS'!$C$11) -> 0
A29: Dépense : étape 3 | F29: =IF($C$8>0,MAX(0,MIN(SUM('01A_DEVELOPMENT'!$C$6:$C$11)-12*(10-1-0)-0,SUM($C$6:$C$8))-MAX(SUM('01A_DEVELOPMENT'!$C$6:$C$11)-12*(10-0),SUM($C$6:$C$8)-$C$8))/$C$8*$D$8,0)*(1+'02_PROJECT_INPUTS'!$C$18)^(F$26-'02_PROJECT_INPUTS'!$C$11) -> 0 | G29: =IF($C$8>0,MAX(0,MIN(SUM('01A_DEVELOPMENT'!$C$6:$C$11)-12*(10-1-1)-0,SUM($C$6:$C$8))-MAX(SUM('01A_DEVELOPMENT'!$C$6:$C$11)-12*(10-1),SUM($C$6:$C$8)-$C$8))/$C$8*$D$8,0)*(1+'02_PROJECT_INPUTS'!$C$18)^(G$26-'02_PROJECT_INPUTS'!$C$11) -> 0 | H29: =IF($C$8>0,MAX(0,MIN(SUM('01A_DEVELOPMENT'!$C$6:$C$11)-12*(10-1-2)-0,SUM($C$6:$C$8))-MAX(SUM('01A_DEVELOPMENT'!$C$6:$C$11)-12*(10-2),SUM($C$6:$C$8)-$C$8))/$C$8*$D$8,0)*(1+'02_PROJECT_INPUTS'!$C$18)^(H$26-'02_PROJECT_INPUTS'!$C$11) -> 0 | I29: =IF($C$8>0,MAX(0,MIN(SUM('01A_DEVELOPMENT'!$C$6:$C$11)-12*(10-1-3)-0,SUM($C$6:$C$8))-MAX(SUM('01A_DEVELOPMENT'!$C$6:$C$11)-12*(10-3),SUM($C$6:$C$8)-$C$8))/$C$8*$D$8,0)*(1+'02_PROJECT_INPUTS'!$C$18)^(I$26-'02_PROJECT_INPUTS'!$C$11) -> 0 | J29: =IF($C$8>0,MAX(0,MIN(SUM('01A_DEVELOPMENT'!$C$6:$C$11)-12*(10-1-4)-0,SUM($C$6:$C$8))-MAX(SUM('01A_DEVELOPMENT'!$C$6:$C$11)-12*(10-4),SUM($C$6:$C$8)-$C$8))/$C$8*$D$8,0)*(1+'02_PROJECT_INPUTS'!$C$18)^(J$26-'02_PROJECT_INPUTS'!$C$11) -> 0 | K29: =IF($C$8>0,MAX(0,MIN(SUM('01A_DEVELOPMENT'!$C$6:$C$11)-12*(10-1-5)-0,SUM($C$6:$C$8))-MAX(SUM('01A_DEVELOPMENT'!$C$6:$C$11)-12*(10-5),SUM($C$6:$C$8)-$C$8))/$C$8*$D$8,0)*(1+'02_PROJECT_INPUTS'!$C$18)^(K$26-'02_PROJECT_INPUTS'!$C$11) -> 1.3857681 | L29: =IF($C$8>0,MAX(0,MIN(SUM('01A_DEVELOPMENT'!$C$6:$C$11)-12*(10-1-6)-0,SUM($C$6:$C$8))-MAX(SUM('01A_DEVELOPMENT'!$C$6:$C$11)-12*(10-6),SUM($C$6:$C$8)-$C$8))/$C$8*$D$8,0)*(1+'02_PROJECT_INPUTS'!$C$18)^(L$26-'02_PROJECT_INPUTS'!$C$11) -> 2.826967 | M29: =IF($C$8>0,MAX(0,MIN(SUM('01A_DEVELOPMENT'!$C$6:$C$11)-12*(10-1-7)-0,SUM($C$6:$C$8))-MAX(SUM('01A_DEVELOPMENT'!$C$6:$C$11)-12*(10-7),SUM($C$6:$C$8)-$C$8))/$C$8*$D$8,0)*(1+'02_PROJECT_INPUTS'!$C$18)^(M$26-'02_PROJECT_INPUTS'!$C$11) -> 0 | N29: =IF($C$8>0,MAX(0,MIN(SUM('01A_DEVELOPMENT'!$C$6:$C$11)-12*(10-1-8)-0,SUM($C$6:$C$8))-MAX(SUM('01A_DEVELOPMENT'!$C$6:$C$11)-12*(10-8),SUM($C$6:$C$8)-$C$8))/$C$8*$D$8,0)*(1+'02_PROJECT_INPUTS'!$C$18)^(N$26-'02_PROJECT_INPUTS'!$C$11) -> 0 | O29: =IF($C$8>0,MAX(0,MIN(SUM('01A_DEVELOPMENT'!$C$6:$C$11)-12*(10-1-9)-0,SUM($C$6:$C$8))-MAX(SUM('01A_DEVELOPMENT'!$C$6:$C$11)-12*(10-9),SUM($C$6:$C$8)-$C$8))/$C$8*$D$8,0)*(1+'02_PROJECT_INPUTS'!$C$18)^(O$26-'02_PROJECT_INPUTS'!$C$11) -> 0
A30: Dépense : étape 4 | F30: =IF($C$9>0,MAX(0,MIN(SUM('01A_DEVELOPMENT'!$C$6:$C$11)-12*(10-1-0)-0,SUM($C$6:$C$9))-MAX(SUM('01A_DEVELOPMENT'!$C$6:$C$11)-12*(10-0),SUM($C$6:$C$9)-$C$9))/$C$9*$D$9,0)*(1+'02_PROJECT_INPUTS'!$C$18)^(F$26-'02_PROJECT_INPUTS'!$C$11) -> 0 | G30: =IF($C$9>0,MAX(0,MIN(SUM('01A_DEVELOPMENT'!$C$6:$C$11)-12*(10-1-1)-0,SUM($C$6:$C$9))-MAX(SUM('01A_DEVELOPMENT'!$C$6:$C$11)-12*(10-1),SUM($C$6:$C$9)-$C$9))/$C$9*$D$9,0)*(1+'02_PROJECT_INPUTS'!$C$18)^(G$26-'02_PROJECT_INPUTS'!$C$11) -> 0 | H30: =IF($C$9>0,MAX(0,MIN(SUM('01A_DEVELOPMENT'!$C$6:$C$11)-12*(10-1-2)-0,SUM($C$6:$C$9))-MAX(SUM('01A_DEVELOPMENT'!$C$6:$C$11)-12*(10-2),SUM($C$6:$C$9)-$C$9))/$C$9*$D$9,0)*(1+'02_PROJECT_INPUTS'!$C$18)^(H$26-'02_PROJECT_INPUTS'!$C$11) -> 0 | I30: =IF($C$9>0,MAX(0,MIN(SUM('01A_DEVELOPMENT'!$C$6:$C$11)-12*(10-1-3)-0,SUM($C$6:$C$9))-MAX(SUM('01A_DEVELOPMENT'!$C$6:$C$11)-12*(10-3),SUM($C$6:$C$9)-$C$9))/$C$9*$D$9,0)*(1+'02_PROJECT_INPUTS'!$C$18)^(I$26-'02_PROJECT_INPUTS'!$C$11) -> 0 | J30: =IF($C$9>0,MAX(0,MIN(SUM('01A_DEVELOPMENT'!$C$6:$C$11)-12*(10-1-4)-0,SUM($C$6:$C$9))-MAX(SUM('01A_DEVELOPMENT'!$C$6:$C$11)-12*(10-4),SUM($C$6:$C$9)-$C$9))/$C$9*$D$9,0)*(1+'02_PROJECT_INPUTS'!$C$18)^(J$26-'02_PROJECT_INPUTS'!$C$11) -> 0 | K30: =IF($C$9>0,MAX(0,MIN(SUM('01A_DEVELOPMENT'!$C$6:$C$11)-12*(10-1-5)-0,SUM($C$6:$C$9))-MAX(SUM('01A_DEVELOPMENT'!$C$6:$C$11)-12*(10-5),SUM($C$6:$C$9)-$C$9))/$C$9*$D$9,0)*(1+'02_PROJECT_INPUTS'!$C$18)^(K$26-'02_PROJECT_INPUTS'!$C$11) -> 0 | L30: =IF($C$9>0,MAX(0,MIN(SUM('01A_DEVELOPMENT'!$C$6:$C$11)-12*(10-1-6)-0,SUM($C$6:$C$9))-MAX(SUM('01A_DEVELOPMENT'!$C$6:$C$11)-12*(10-6),SUM($C$6:$C$9)-$C$9))/$C$9*$D$9,0)*(1+'02_PROJECT_INPUTS'!$C$18)^(L$26-'02_PROJECT_INPUTS'!$C$11) -> 0 | M30: =IF($C$9>0,MAX(0,MIN(SUM('01A_DEVELOPMENT'!$C$6:$C$11)-12*(10-1-7)-0,SUM($C$6:$C$9))-MAX(SUM('01A_DEVELOPMENT'!$C$6:$C$11)-12*(10-7),SUM($C$6:$C$9)-$C$9))/$C$9*$D$9,0)*(1+'02_PROJECT_INPUTS'!$C$18)^(M$26-'02_PROJECT_INPUTS'!$C$11) -> 0.76893502 | N30: =IF($C$9>0,MAX(0,MIN(SUM('01A_DEVELOPMENT'!$C$6:$C$11)-12*(10-1-8)-0,SUM($C$6:$C$9))-MAX(SUM('01A_DEVELOPMENT'!$C$6:$C$11)-12*(10-8),SUM($C$6:$C$9)-$C$9))/$C$9*$D$9,0)*(1+'02_PROJECT_INPUTS'!$C$18)^(N$26-'02_PROJECT_INPUTS'!$C$11) -> 0 | O30: =IF($C$9>0,MAX(0,MIN(SUM('01A_DEVELOPMENT'!$C$6:$C$11)-12*(10-1-9)-0,SUM($C$6:$C$9))-MAX(SUM('01A_DEVELOPMENT'!$C$6:$C$11)-12*(10-9),SUM($C$6:$C$9)-$C$9))/$C$9*$D$9,0)*(1+'02_PROJECT_INPUTS'!$C$18)^(O$26-'02_PROJECT_INPUTS'!$C$11) -> 0
A31: Dépense : étape 5 | F31: =IF($C$10>0,MAX(0,MIN(SUM('01A_DEVELOPMENT'!$C$6:$C$11)-12*(10-1-0)-0,SUM($C$6:$C$10))-MAX(SUM('01A_DEVELOPMENT'!$C$6:$C$11)-12*(10-0),SUM($C$6:$C$10)-$C$10))/$C$10*$D$10,0)*(1+'02_PROJECT_INPUTS'!$C$18)^(F$26-'02_PROJECT_INPUTS'!$C$11) -> 0 | G31: =IF($C$10>0,MAX(0,MIN(SUM('01A_DEVELOPMENT'!$C$6:$C$11)-12*(10-1-1)-0,SUM($C$6:$C$10))-MAX(SUM('01A_DEVELOPMENT'!$C$6:$C$11)-12*(10-1),SUM($C$6:$C$10)-$C$10))/$C$10*$D$10,0)*(1+'02_PROJECT_INPUTS'!$C$18)^(G$26-'02_PROJECT_INPUTS'!$C$11) -> 0 | H31: =IF($C$10>0,MAX(0,MIN(SUM('01A_DEVELOPMENT'!$C$6:$C$11)-12*(10-1-2)-0,SUM($C$6:$C$10))-MAX(SUM('01A_DEVELOPMENT'!$C$6:$C$11)-12*(10-2),SUM($C$6:$C$10)-$C$10))/$C$10*$D$10,0)*(1+'02_PROJECT_INPUTS'!$C$18)^(H$26-'02_PROJECT_INPUTS'!$C$11) -> 0 | I31: =IF($C$10>0,MAX(0,MIN(SUM('01A_DEVELOPMENT'!$C$6:$C$11)-12*(10-1-3)-0,SUM($C$6:$C$10))-MAX(SUM('01A_DEVELOPMENT'!$C$6:$C$11)-12*(10-3),SUM($C$6:$C$10)-$C$10))/$C$10*$D$10,0)*(1+'02_PROJECT_INPUTS'!$C$18)^(I$26-'02_PROJECT_INPUTS'!$C$11) -> 0 | J31: =IF($C$10>0,MAX(0,MIN(SUM('01A_DEVELOPMENT'!$C$6:$C$11)-12*(10-1-4)-0,SUM($C$6:$C$10))-MAX(SUM('01A_DEVELOPMENT'!$C$6:$C$11)-12*(10-4),SUM($C$6:$C$10)-$C$10))/$C$10*$D$10,0)*(1+'02_PROJECT_INPUTS'!$C$18)^(J$26-'02_PROJECT_INPUTS'!$C$11) -> 0 | K31: =IF($C$10>0,MAX(0,MIN(SUM('01A_DEVELOPMENT'!$C$6:$C$11)-12*(10-1-5)-0,SUM($C$6:$C$10))-MAX(SUM('01A_DEVELOPMENT'!$C$6:$C$11)-12*(10-5),SUM($C$6:$C$10)-$C$10))/$C$10*$D$10,0)*(1+'02_PROJECT_INPUTS'!$C$18)^(K$26-'02_PROJECT_INPUTS'!$C$11) -> 0 | L31: =IF($C$10>0,MAX(0,MIN(SUM('01A_DEVELOPMENT'!$C$6:$C$11)-12*(10-1-6)-0,SUM($C$6:$C$10))-MAX(SUM('01A_DEVELOPMENT'!$C$6:$C$11)-12*(10-6),SUM($C$6:$C$10)-$C$10))/$C$10*$D$10,0)*(1+'02_PROJECT_INPUTS'!$C$18)^(L$26-'02_PROJECT_INPUTS'!$C$11) -> 0 | M31: =IF($C$10>0,MAX(0,MIN(SUM('01A_DEVELOPMENT'!$C$6:$C$11)-12*(10-1-7)-0,SUM($C$6:$C$10))-MAX(SUM('01A_DEVELOPMENT'!$C$6:$C$11)-12*(10-7),SUM($C$6:$C$10)-$C$10))/$C$10*$D$10,0)*(1+'02_PROJECT_INPUTS'!$C$18)^(M$26-'02_PROJECT_INPUTS'!$C$11) -> 0 | N31: =IF($C$10>0,MAX(0,MIN(SUM('01A_DEVELOPMENT'!$C$6:$C$11)-12*(10-1-8)-0,SUM($C$6:$C$10))-MAX(SUM('01A_DEVELOPMENT'!$C$6:$C$11)-12*(10-8),SUM($C$6:$C$10)-$C$10))/$C$10*$D$10,0)*(1+'02_PROJECT_INPUTS'!$C$18)^(N$26-'02_PROJECT_INPUTS'!$C$11) -> 0.78431373 | O31: =IF($C$10>0,MAX(0,MIN(SUM('01A_DEVELOPMENT'!$C$6:$C$11)-12*(10-1-9)-0,SUM($C$6:$C$10))-MAX(SUM('01A_DEVELOPMENT'!$C$6:$C$11)-12*(10-9),SUM($C$6:$C$10)-$C$10))/$C$10*$D$10,0)*(1+'02_PROJECT_INPUTS'!$C$18)^(O$26-'02_PROJECT_INPUTS'!$C$11) -> 0
A32: Dépense : étape 6 | F32: =IF($C$11>0,MAX(0,MIN(SUM('01A_DEVELOPMENT'!$C$6:$C$11)-12*(10-1-0)-0,SUM($C$6:$C$11))-MAX(SUM('01A_DEVELOPMENT'!$C$6:$C$11)-12*(10-0),SUM($C$6:$C$11)-$C$11))/$C$11*$D$11,0)*(1+'02_PROJECT_INPUTS'!$C$18)^(F$26-'02_PROJECT_INPUTS'!$C$11) -> 0 | G32: =IF($C$11>0,MAX(0,MIN(SUM('01A_DEVELOPMENT'!$C$6:$C$11)-12*(10-1-1)-0,SUM($C$6:$C$11))-MAX(SUM('01A_DEVELOPMENT'!$C$6:$C$11)-12*(10-1),SUM($C$6:$C$11)-$C$11))/$C$11*$D$11,0)*(1+'02_PROJECT_INPUTS'!$C$18)^(G$26-'02_PROJECT_INPUTS'!$C$11) -> 0 | H32: =IF($C$11>0,MAX(0,MIN(SUM('01A_DEVELOPMENT'!$C$6:$C$11)-12*(10-1-2)-0,SUM($C$6:$C$11))-MAX(SUM('01A_DEVELOPMENT'!$C$6:$C$11)-12*(10-2),SUM($C$6:$C$11)-$C$11))/$C$11*$D$11,0)*(1+'02_PROJECT_INPUTS'!$C$18)^(H$26-'02_PROJECT_INPUTS'!$C$11) -> 0 | I32: =IF($C$11>0,MAX(0,MIN(SUM('01A_DEVELOPMENT'!$C$6:$C$11)-12*(10-1-3)-0,SUM($C$6:$C$11))-MAX(SUM('01A_DEVELOPMENT'!$C$6:$C$11)-12*(10-3),SUM($C$6:$C$11)-$C$11))/$C$11*$D$11,0)*(1+'02_PROJECT_INPUTS'!$C$18)^(I$26-'02_PROJECT_INPUTS'!$C$11) -> 0 | J32: =IF($C$11>0,MAX(0,MIN(SUM('01A_DEVELOPMENT'!$C$6:$C$11)-12*(10-1-4)-0,SUM($C$6:$C$11))-MAX(SUM('01A_DEVELOPMENT'!$C$6:$C$11)-12*(10-4),SUM($C$6:$C$11)-$C$11))/$C$11*$D$11,0)*(1+'02_PROJECT_INPUTS'!$C$18)^(J$26-'02_PROJECT_INPUTS'!$C$11) -> 0 | K32: =IF($C$11>0,MAX(0,MIN(SUM('01A_DEVELOPMENT'!$C$6:$C$11)-12*(10-1-5)-0,SUM($C$6:$C$11))-MAX(SUM('01A_DEVELOPMENT'!$C$6:$C$11)-12*(10-5),SUM($C$6:$C$11)-$C$11))/$C$11*$D$11,0)*(1+'02_PROJECT_INPUTS'!$C$18)^(K$26-'02_PROJECT_INPUTS'!$C$11) -> 0 | L32: =IF($C$11>0,MAX(0,MIN(SUM('01A_DEVELOPMENT'!$C$6:$C$11)-12*(10-1-6)-0,SUM($C$6:$C$11))-MAX(SUM('01A_DEVELOPMENT'!$C$6:$C$11)-12*(10-6),SUM($C$6:$C$11)-$C$11))/$C$11*$D$11,0)*(1+'02_PROJECT_INPUTS'!$C$18)^(L$26-'02_PROJECT_INPUTS'!$C$11) -> 0 | M32: =IF($C$11>0,MAX(0,MIN(SUM('01A_DEVELOPMENT'!$C$6:$C$11)-12*(10-1-7)-0,SUM($C$6:$C$11))-MAX(SUM('01A_DEVELOPMENT'!$C$6:$C$11)-12*(10-7),SUM($C$6:$C$11)-$C$11))/$C$11*$D$11,0)*(1+'02_PROJECT_INPUTS'!$C$18)^(M$26-'02_PROJECT_INPUTS'!$C$11) -> 0 | N32: =IF($C$11>0,MAX(0,MIN(SUM('01A_DEVELOPMENT'!$C$6:$C$11)-12*(10-1-8)-0,SUM($C$6:$C$11))-MAX(SUM('01A_DEVELOPMENT'!$C$6:$C$11)-12*(10-8),SUM($C$6:$C$11)-$C$11))/$C$11*$D$11,0)*(1+'02_PROJECT_INPUTS'!$C$18)^(N$26-'02_PROJECT_INPUTS'!$C$11) -> 0 | O32: =IF($C$11>0,MAX(0,MIN(SUM('01A_DEVELOPMENT'!$C$6:$C$11)-12*(10-1-9)-0,SUM($C$6:$C$11))-MAX(SUM('01A_DEVELOPMENT'!$C$6:$C$11)-12*(10-9),SUM($C$6:$C$11)-$C$11))/$C$11*$D$11,0)*(1+'02_PROJECT_INPUTS'!$C$18)^(O$26-'02_PROJECT_INPUTS'!$C$11) -> 2.2
A33: Dépense totale de dévelop. | C33: =SUM(F33:O33) -> 8.6054298 | F33: =SUM(F27:F32) -> 0 | G33: =SUM(G27:G32) -> 0 | H33: =SUM(H27:H32) -> 0 | I33: =SUM(I27:I32) -> 0 | J33: =SUM(J27:J32) -> 0.36229232 | K33: =SUM(K27:K32) -> 1.6629218 | L33: =SUM(L27:L32) -> 2.826967 | M33: =SUM(M27:M32) -> 0.76893502 | ... O33: =SUM(O27:O32) -> 2.2
A34: Probabilité que le projet soit encore en vie au moment de la dépense | F34: =IF(F33>0,(F27*PRODUCT($E$6:$E$6)/$E$6+F28*PRODUCT($E$6:$E$7)/$E$7+F29*PRODUCT($E$6:$E$8)/$E$8+F30*PRODUCT($E$6:$E$9)/$E$9+F31*PRODUCT($E$6:$E$10)/$E$10+F32*PRODUCT($E$6:$E$11)/$E$11)/F33,0) -> 0 | G34: =IF(G33>0,(G27*PRODUCT($E$6:$E$6)/$E$6+G28*PRODUCT($E$6:$E$7)/$E$7+G29*PRODUCT($E$6:$E$8)/$E$8+G30*PRODUCT($E$6:$E$9)/$E$9+G31*PRODUCT($E$6:$E$10)/$E$10+G32*PRODUCT($E$6:$E$11)/$E$11)/G33,0) -> 0 | H34: =IF(H33>0,(H27*PRODUCT($E$6:$E$6)/$E$6+H28*PRODUCT($E$6:$E$7)/$E$7+H29*PRODUCT($E$6:$E$8)/$E$8+H30*PRODUCT($E$6:$E$9)/$E$9+H31*PRODUCT($E$6:$E$10)/$E$10+H32*PRODUCT($E$6:$E$11)/$E$11)/H33,0) -> 0 | I34: =IF(I33>0,(I27*PRODUCT($E$6:$E$6)/$E$6+I28*PRODUCT($E$6:$E$7)/$E$7+I29*PRODUCT($E$6:$E$8)/$E$8+I30*PRODUCT($E$6:$E$9)/$E$9+I31*PRODUCT($E$6:$E$10)/$E$10+I32*PRODUCT($E$6:$E$11)/$E$11)/I33,0) -> 0 | J34: =IF(J33>0,(J27*PRODUCT($E$6:$E$6)/$E$6+J28*PRODUCT($E$6:$E$7)/$E$7+J29*PRODUCT($E$6:$E$8)/$E$8+J30*PRODUCT($E$6:$E$9)/$E$9+J31*PRODUCT($E$6:$E$10)/$E$10+J32*PRODUCT($E$6:$E$11)/$E$11)/J33,0) -> 0.7 | K34: =IF(K33>0,(K27*PRODUCT($E$6:$E$6)/$E$6+K28*PRODUCT($E$6:$E$7)/$E$7+K29*PRODUCT($E$6:$E$8)/$E$8+K30*PRODUCT($E$6:$E$9)/$E$9+K31*PRODUCT($E$6:$E$10)/$E$10+K32*PRODUCT($E$6:$E$11)/$E$11)/K33,0) -> 0.4 | L34: =IF(L33>0,(L27*PRODUCT($E$6:$E$6)/$E$6+L28*PRODUCT($E$6:$E$7)/$E$7+L29*PRODUCT($E$6:$E$8)/$E$8+L30*PRODUCT($E$6:$E$9)/$E$9+L31*PRODUCT($E$6:$E$10)/$E$10+L32*PRODUCT($E$6:$E$11)/$E$11)/L33,0) -> 0.36 | M34: =IF(M33>0,(M27*PRODUCT($E$6:$E$6)/$E$6+M28*PRODUCT($E$6:$E$7)/$E$7+M29*PRODUCT($E$6:$E$8)/$E$8+M30*PRODUCT($E$6:$E$9)/$E$9+M31*PRODUCT($E$6:$E$10)/$E$10+M32*PRODUCT($E$6:$E$11)/$E$11)/M33,0) -> 0.252 | ... O34: =IF(O33>0,(O27*PRODUCT($E$6:$E$6)/$E$6+O28*PRODUCT($E$6:$E$7)/$E$7+O29*PRODUCT($E$6:$E$8)/$E$8+O30*PRODUCT($E$6:$E$9)/$E$9+O31*PRODUCT($E$6:$E$10)/$E$10+O32*PRODUCT($E$6:$E$11)/$E$11)/O33,0) -> 0.17136
A36: D. RENDEMENTS DÉVELOPPEUR
A37: Coûts de développement remboursés par le projet au bouclage (nominal) | B37: M USD | C37: =C33 -> 8.6054298
A38: Participation du développeur : VAN au bouclage de sa part des flux des fonds propres privés, au taux du bouclage | B38: M USD | C38: ='01A_DEVELOPMENT'!$C$20*NPV('01A_DEVELOPMENT'!$C$22,'20_CASH_FLOW'!$E$41:$AR$41) -> -2.0389683
A39: Valeur reçue au bouclage sur le scénario de succès (remboursement + prime + VAN fonds propres) | B39: M USD | C39: ='01A_DEVELOPMENT'!$C$37+'01A_DEVELOPMENT'!$C$19+'01A_DEVELOPMENT'!$C$38 -> 11.272262
A40: VA au début du développement des dépenses sur le scénario de succès | B40: M USD | C40: =NPV('01A_DEVELOPMENT'!$C$21,F33:O33)*(1+'01A_DEVELOPMENT'!$C$21)^(10-SUM('01A_DEVELOPMENT'!$C$6:$C$11)/12) -> 3.9501874
A41: VA des dépenses pondérées par le risque (chaque étape pondérée par sa probabilité d'être atteinte) | B41: M USD | C41: =SUMPRODUCT(F33:O33,F34:O34,1/(1+'01A_DEVELOPMENT'!$C$21)^(COLUMN(F33:O33)-COLUMN(F33)+1))*(1+'01A_DEVELOPMENT'!$C$21)^(10-SUM('01A_DEVELOPMENT'!$C$6:$C$11)/12) -> 1.3829035
A42: VA au début du développement de la valeur reçue au bouclage | B42: M USD | C42: ='01A_DEVELOPMENT'!$C$39/(1+'01A_DEVELOPMENT'!$C$21)^(SUM('01A_DEVELOPMENT'!$C$6:$C$11)/12) -> 2.9549557
A43: VAN du développeur si le projet atteint le bouclage | B43: M USD | C43: ='01A_DEVELOPMENT'!$C$42-'01A_DEVELOPMENT'!$C$40 -> -0.99523167
A44: VAN DU DÉVELOPPEUR PONDÉRÉE PAR LE RISQUE (espérée, depuis la reconnaissance) | B44: M USD | C44: ='01A_DEVELOPMENT'!$C$14*'01A_DEVELOPMENT'!$C$42-'01A_DEVELOPMENT'!$C$41 -> -0.95249649
A45: Prime de développement qui annule la VAN pondérée par le risque, au premier ordre (coût de la centrale et fonds propres fixes ; la valeur du moteur complet est dans l'instantané) | B45: M USD | C45: =MAX(0,'01A_DEVELOPMENT'!$C$19-'01A_DEVELOPMENT'!$C$44*(1+'01A_DEVELOPMENT'!$C$21)^(SUM('01A_DEVELOPMENT'!$C$6:$C$11)/12)/'01A_DEVELOPMENT'!$C$14) -> 29.651465
A46: en % du CAPEX centrale | B46: % | C46: ='01A_DEVELOPMENT'!$C$45/'06_CONSTRUCTION'!$C$9 -> 0.1890314
A47: Probabilité d'atteindre le bouclage au point mort, à la prime actuelle (indicatif : pondérations des dépenses fixes ; n/a si le projet perd de la valeur même sur le scénario de succès) | B47: % | C47: =IF('01A_DEVELOPMENT'!$C$43<=0,"n/a : négative sur le scénario de succès",'01A_DEVELOPMENT'!$C$41/'01A_DEVELOPMENT'!$C$42) -> n/a : négative sur le scénario de succès
A49: D2. VALEUR DE LA POSITION DE DÉVELOPPEMENT AU DÉBUT DE CHAQUE ÉTAPE (pondérée par le risque, réelle, 100 %)
A50: Étape à venir | B50: P(bouclage) d'ici | C50: VA valeur au bouclage | D50: VA des dépenses restantes | E50: Valeur pondérée risque
A51: 1. Identification du site et reconnaissance | B51: =PRODUCT($E$6:$E$11) -> 0.145656 | C51: =B51*'01A_DEVELOPMENT'!$C$39/(1+'01A_DEVELOPMENT'!$C$21)^((SUM('01A_DEVELOPMENT'!$C$6:$C$11)-(SUM($C$6:$C$6)-$C$6))/12) -> 0.43040703 | D51: =$D$6*1/(1+'01A_DEVELOPMENT'!$C$21)^(((SUM($C$6:$C$6)-$C$6)-(SUM($C$6:$C$6)-$C$6)+0.5*$C$6)/12)+$D$7*PRODUCT($E$6:$E$6)/(1+'01A_DEVELOPMENT'!$C$21)^(((SUM($C$6:$C$7)-$C$7)-(SUM($C$6:$C$6)-$C$6)+0.5*$C$7)/12)+$D$8*PRODUCT($E$6:$E$7)/(1+'01A_DEVELOPMENT'!$C$21)^(((SUM($C$6:$C$8)-$C$8)-(SUM($C$6:$C$6)-$C$6)+0.5*$C$8)/12)+$D$9*PRODUCT($E$6:$E$8)/(1+'01A_DEVELOPMENT'!$C$21)^(((SUM($C$6:$C$9)-$C$9)-(SUM($C$6:$C$6)-$C$6)+0.5*$C$9)/12)+$D$10*PRODUCT($E$6:$E$9)/(1+'01A_DEVELOPMENT'!$C$21)^(((SUM($C$6:$C$10)-$C$10)-(SUM($C$6:$C$6)-$C$6)+0.5*$C$10)/12)+$D$11*PRODUCT($E$6:$E$10)/(1+'01A_DEVELOPMENT'!$C$21)^(((SUM($C$6:$C$11)-$C$11)-(SUM($C$6:$C$6)-$C$6)+0.5*$C$11)/12) -> 1.6287112 | E51: =C51-D51 -> -1.1983041
A52: 2. Préfaisabilité et début du jaugeage | B52: =PRODUCT($E$7:$E$11) -> 0.24276 | C52: =B52*'01A_DEVELOPMENT'!$C$39/(1+'01A_DEVELOPMENT'!$C$21)^((SUM('01A_DEVELOPMENT'!$C$6:$C$11)-(SUM($C$6:$C$7)-$C$7))/12) -> 0.80201615 | D52: =$D$7*1/(1+'01A_DEVELOPMENT'!$C$21)^(((SUM($C$6:$C$7)-$C$7)-(SUM($C$6:$C$7)-$C$7)+0.5*$C$7)/12)+$D$8*PRODUCT($E$7:$E$7)/(1+'01A_DEVELOPMENT'!$C$21)^(((SUM($C$6:$C$8)-$C$8)-(SUM($C$6:$C$7)-$C$7)+0.5*$C$8)/12)+$D$9*PRODUCT($E$7:$E$8)/(1+'01A_DEVELOPMENT'!$C$21)^(((SUM($C$6:$C$9)-$C$9)-(SUM($C$6:$C$7)-$C$7)+0.5*$C$9)/12)+$D$10*PRODUCT($E$7:$E$9)/(1+'01A_DEVELOPMENT'!$C$21)^(((SUM($C$6:$C$10)-$C$10)-(SUM($C$6:$C$7)-$C$7)+0.5*$C$10)/12)+$D$11*PRODUCT($E$7:$E$10)/(1+'01A_DEVELOPMENT'!$C$21)^(((SUM($C$6:$C$11)-$C$11)-(SUM($C$6:$C$7)-$C$7)+0.5*$C$11)/12) -> 2.8586955 | E52: =C52-D52 -> -2.0566794
A53: 3. Faisabilité, EIES, études géotechniques et réseau | B53: =PRODUCT($E$8:$E$11) -> 0.4046 | C53: =B53*'01A_DEVELOPMENT'!$C$39/(1+'01A_DEVELOPMENT'!$C$21)^((SUM('01A_DEVELOPMENT'!$C$6:$C$11)-(SUM($C$6:$C$8)-$C$8))/12) -> 1.670867 | D53: =$D$8*1/(1+'01A_DEVELOPMENT'!$C$21)^(((SUM($C$6:$C$8)-$C$8)-(SUM($C$6:$C$8)-$C$8)+0.5*$C$8)/12)+$D$9*PRODUCT($E$8:$E$8)/(1+'01A_DEVELOPMENT'!$C$21)^(((SUM($C$6:$C$9)-$C$9)-(SUM($C$6:$C$8)-$C$8)+0.5*$C$9)/12)+$D$10*PRODUCT($E$8:$E$9)/(1+'01A_DEVELOPMENT'!$C$21)^(((SUM($C$6:$C$10)-$C$10)-(SUM($C$6:$C$8)-$C$8)+0.5*$C$10)/12)+$D$11*PRODUCT($E$8:$E$10)/(1+'01A_DEVELOPMENT'!$C$21)^(((SUM($C$6:$C$11)-$C$11)-(SUM($C$6:$C$8)-$C$8)+0.5*$C$11)/12) -> 4.8375817 | E53: =C53-D53 -> -3.1667147
A54: 4. Licences, droits d'eau, foncier et permis | B54: =PRODUCT($E$9:$E$11) -> 0.578 | C54: =B54*'01A_DEVELOPMENT'!$C$39/(1+'01A_DEVELOPMENT'!$C$21)^((SUM('01A_DEVELOPMENT'!$C$6:$C$11)-(SUM($C$6:$C$9)-$C$9))/12) -> 3.335868 | D54: =$D$9*1/(1+'01A_DEVELOPMENT'!$C$21)^(((SUM($C$6:$C$9)-$C$9)-(SUM($C$6:$C$9)-$C$9)+0.5*$C$9)/12)+$D$10*PRODUCT($E$9:$E$9)/(1+'01A_DEVELOPMENT'!$C$21)^(((SUM($C$6:$C$10)-$C$10)-(SUM($C$6:$C$9)-$C$9)+0.5*$C$10)/12)+$D$11*PRODUCT($E$9:$E$10)/(1+'01A_DEVELOPMENT'!$C$21)^(((SUM($C$6:$C$11)-$C$11)-(SUM($C$6:$C$9)-$C$9)+0.5*$C$11)/12) -> 2.0584705 | E54: =C54-D54 -> 1.2773975
A55: 5. CAE, convention de mise en œuvre et homologation du tarif | B55: =PRODUCT($E$10:$E$11) -> 0.68 | C55: =B55*'01A_DEVELOPMENT'!$C$39/(1+'01A_DEVELOPMENT'!$C$21)^((SUM('01A_DEVELOPMENT'!$C$6:$C$11)-(SUM($C$6:$C$10)-$C$10))/12) -> 4.9056882 | D55: =$D$10*1/(1+'01A_DEVELOPMENT'!$C$21)^(((SUM($C$6:$C$10)-$C$10)-(SUM($C$6:$C$10)-$C$10)+0.5*$C$10)/12)+$D$11*PRODUCT($E$10:$E$10)/(1+'01A_DEVELOPMENT'!$C$21)^(((SUM($C$6:$C$11)-$C$11)-(SUM($C$6:$C$10)-$C$10)+0.5*$C$11)/12) -> 1.9748952 | E55: =C55-D55 -> 2.930793
A56: 6. Financement : conseillers des prêteurs, juridique, assurances, bouclage | B56: =PRODUCT($E$11:$E$11) -> 0.85 | C56: =B56*'01A_DEVELOPMENT'!$C$39/(1+'01A_DEVELOPMENT'!$C$21)^((SUM('01A_DEVELOPMENT'!$C$6:$C$11)-(SUM($C$6:$C$11)-$C$11))/12) -> 7.6651379 | D56: =$D$11*1/(1+'01A_DEVELOPMENT'!$C$21)^(((SUM($C$6:$C$11)-$C$11)-(SUM($C$6:$C$11)-$C$11)+0.5*$C$11)/12) -> 1.9677398 | E56: =C56-D56 -> 5.697398
A57: Lecture : la valeur pondérée par le risque est ce que vaut toute la position de développement, avant le début de l'étape, pour un acheteur appliquant le taux d'actualisation du développeur. C'est le point de départ pour fixer le prix d'entrée d'un co-développeur.
A59: E. REVALORISATIONS (fonds propres privés, 100 %)
A60: Fonds propres privés apportés (nominal) | B60: M USD | C60: ='20_CASH_FLOW'!$C$12 -> 69.608201
A61: Valeur des fonds propres privés au bouclage (VAN de tous les flux au taux du bouclage, plus apports en VA) | B61: M USD | C61: =NPV('01A_DEVELOPMENT'!$C$22,'20_CASH_FLOW'!$E$41:$AR$41)+NPV('01A_DEVELOPMENT'!$C$22,'20_CASH_FLOW'!$E$12:$AR$12) -> 45.809309
A62: Valeur des fonds propres privés à la COD (flux d'exploitation seuls, au taux COD, actualisés au bouclage) | B62: M USD | C62: =SUMPRODUCT('06_CONSTRUCTION'!$E$14:$AR$14,'20_CASH_FLOW'!$E$41:$AR$41,1/(1+'01A_DEVELOPMENT'!$C$23)^('06_CONSTRUCTION'!$E$12:$AR$12-'06_CONSTRUCTION'!$C$7))/(1+'01A_DEVELOPMENT'!$C$22)^'06_CONSTRUCTION'!$C$7 -> 64.09734
A63: Valeur créée au bouclage (valeur au bouclage moins VA des apports) | B63: M USD | C63: =NPV('01A_DEVELOPMENT'!$C$22,'20_CASH_FLOW'!$E$41:$AR$41) -> -5.0974207
A64: Revalorisation par réduction du risque, du bouclage à la COD (en VA) | B64: M USD | C64: ='01A_DEVELOPMENT'!$C$62-SUMPRODUCT('06_CONSTRUCTION'!$E$14:$AR$14,'20_CASH_FLOW'!$E$41:$AR$41,1/(1+'01A_DEVELOPMENT'!$C$22)^'06_CONSTRUCTION'!$E$12:$AR$12) -> 18.288031
A66: F. FLUX DU DÉVELOPPEUR SUR LE SCÉNARIO DE SUCCÈS, AVEC CESSION PARTIELLE À LA COD
A67: Part de la participation du développeur cédée à la COD | B67: % | C67: 0.5 | D67: Cession à la valeur COD des fonds propres en exploitation (taux de la section E)
A68: Valeur de 100 % des fonds propres privés à la COD (fin de construction), au taux COD | B68: M USD | C68: =SUMPRODUCT('06_CONSTRUCTION'!$E$14:$AR$14,'20_CASH_FLOW'!$E$41:$AR$41,1/(1+'01A_DEVELOPMENT'!$C$23)^('06_CONSTRUCTION'!$E$12:$AR$12-'06_CONSTRUCTION'!$C$7)) -> 97.484042
A69: Produit de cession pour le développeur | B69: M USD | C69: ='01A_DEVELOPMENT'!$C$67*'01A_DEVELOPMENT'!$C$20*'01A_DEVELOPMENT'!$C$68 -> 19.496808
A70: Année | F70: ='02_PROJECT_INPUTS'!$C$10-10+0 -> 2017 | G70: ='02_PROJECT_INPUTS'!$C$10-10+1 -> 2018 | H70: ='02_PROJECT_INPUTS'!$C$10-10+2 -> 2019 | I70: ='02_PROJECT_INPUTS'!$C$10-10+3 -> 2020 | J70: ='02_PROJECT_INPUTS'!$C$10-10+4 -> 2021 | K70: ='02_PROJECT_INPUTS'!$C$10-10+5 -> 2022 | L70: ='02_PROJECT_INPUTS'!$C$10-10+6 -> 2023 | M70: ='02_PROJECT_INPUTS'!$C$10-10+7 -> 2024 | N70: ='02_PROJECT_INPUTS'!$C$10-10+8 -> 2025 | O70: ='02_PROJECT_INPUTS'!$C$10-10+9 -> 2026 | P70: ='02_PROJECT_INPUTS'!$C$10-10+10 -> 2027 | Q70: ='02_PROJECT_INPUTS'!$C$10-10+11 -> 2028 | R70: ='02_PROJECT_INPUTS'!$C$10-10+12 -> 2029 | S70: ='02_PROJECT_INPUTS'!$C$10-10+13 -> 2030 | T70: ='02_PROJECT_INPUTS'!$C$10-10+14 -> 2031 | U70: ='02_PROJECT_INPUTS'!$C$10-10+15 -> 2032 | V70: ='02_PROJECT_INPUTS'!$C$10-10+16 -> 2033 | W70: ='02_PROJECT_INPUTS'!$C$10-10+17 -> 2034 | X70: ='02_PROJECT_INPUTS'!$C$10-10+18 -> 2035 | Y70: ='02_PROJECT_INPUTS'!$C$10-10+19 -> 2036 | Z70: ='02_PROJECT_INPUTS'!$C$10-10+20 -> 2037 | AA70: ='02_PROJECT_INPUTS'!$C$10-10+21 -> 2038 | AB70: ='02_PROJECT_INPUTS'!$C$10-10+22 -> 2039 | AC70: ='02_PROJECT_INPUTS'!$C$10-10+23 -> 2040 | AD70: ='02_PROJECT_INPUTS'!$C$10-10+24 -> 2041 | AE70: ='02_PROJECT_INPUTS'!$C$10-10+25 -> 2042 | AF70: ='02_PROJECT_INPUTS'!$C$10-10+26 -> 2043 | AG70: ='02_PROJECT_INPUTS'!$C$10-10+27 -> 2044 | AH70: ='02_PROJECT_INPUTS'!$C$10-10+28 -> 2045 | AI70: ='02_PROJECT_INPUTS'!$C$10-10+29 -> 2046 | AJ70: ='02_PROJECT_INPUTS'!$C$10-10+30 -> 2047 | AK70: ='02_PROJECT_INPUTS'!$C$10-10+31 -> 2048 | AL70: ='02_PROJECT_INPUTS'!$C$10-10+32 -> 2049 | AM70: ='02_PROJECT_INPUTS'!$C$10-10+33 -> 2050 | AN70: ='02_PROJECT_INPUTS'!$C$10-10+34 -> 2051 | AO70: ='02_PROJECT_INPUTS'!$C$10-10+35 -> 2052 | AP70: ='02_PROJECT_INPUTS'!$C$10-10+36 -> 2053 | AQ70: ='02_PROJECT_INPUTS'!$C$10-10+37 -> 2054 | AR70: ='02_PROJECT_INPUTS'!$C$10-10+38 -> 2055 | AS70: ='02_PROJECT_INPUTS'!$C$10-10+39 -> 2056 | AT70: ='02_PROJECT_INPUTS'!$C$10-10+40 -> 2057 | AU70: ='02_PROJECT_INPUTS'!$C$10-10+41 -> 2058 | AV70: ='02_PROJECT_INPUTS'!$C$10-10+42 -> 2059 | AW70: ='02_PROJECT_INPUTS'!$C$10-10+43 -> 2060 | AX70: ='02_PROJECT_INPUTS'!$C$10-10+44 -> 2061 | AY70: ='02_PROJECT_INPUTS'!$C$10-10+45 -> 2062 | AZ70: ='02_PROJECT_INPUTS'!$C$10-10+46 -> 2063 | BA70: ='02_PROJECT_INPUTS'!$C$10-10+47 -> 2064 | BB70: ='02_PROJECT_INPUTS'!$C$10-10+48 -> 2065 | BC70: ='02_PROJECT_INPUTS'!$C$10-10+49 -> 2066
A71: Flux du développeur (M USD) | F71: =-F33 -> 0 | G71: =-G33 -> 0 | H71: =-H33 -> 0 | I71: =-I33 -> 0 | J71: =-J33 -> -0.36229232 | K71: =-K33 -> -1.6629218 | L71: =-L33 -> -2.826967 | M71: =-M33 -> -0.76893502 | ... O71: =-O33 -> -2.2 | P71: =IF(1=1,'01A_DEVELOPMENT'!$C$37+'01A_DEVELOPMENT'!$C$19,0)+'01A_DEVELOPMENT'!$C$20*'20_CASH_FLOW'!E41*IF('06_CONSTRUCTION'!E14=1,1-'01A_DEVELOPMENT'!$C$67,1)+IF('06_CONSTRUCTION'!E15=1,'01A_DEVELOPMENT'!$C$69,0) -> 8.141755 | Q71: =IF(2=1,'01A_DEVELOPMENT'!$C$37+'01A_DEVELOPMENT'!$C$19,0)+'01A_DEVELOPMENT'!$C$20*'20_CASH_FLOW'!F41*IF('06_CONSTRUCTION'!F14=1,1-'01A_DEVELOPMENT'!$C$67,1)+IF('06_CONSTRUCTION'!F15=1,'01A_DEVELOPMENT'!$C$69,0) -> -9.7244869 | R71: =IF(3=1,'01A_DEVELOPMENT'!$C$37+'01A_DEVELOPMENT'!$C$19,0)+'01A_DEVELOPMENT'!$C$20*'20_CASH_FLOW'!G41*IF('06_CONSTRUCTION'!G14=1,1-'01A_DEVELOPMENT'!$C$67,1)+IF('06_CONSTRUCTION'!G15=1,'01A_DEVELOPMENT'!$C$69,0) -> 6.5474897 | S71: =IF(4=1,'01A_DEVELOPMENT'!$C$37+'01A_DEVELOPMENT'!$C$19,0)+'01A_DEVELOPMENT'!$C$20*'20_CASH_FLOW'!H41*IF('06_CONSTRUCTION'!H14=1,1-'01A_DEVELOPMENT'!$C$67,1)+IF('06_CONSTRUCTION'!H15=1,'01A_DEVELOPMENT'!$C$69,0) -> 1.2159489 | T71: =IF(5=1,'01A_DEVELOPMENT'!$C$37+'01A_DEVELOPMENT'!$C$19,0)+'01A_DEVELOPMENT'!$C$20*'20_CASH_FLOW'!I41*IF('06_CONSTRUCTION'!I14=1,1-'01A_DEVELOPMENT'!$C$67,1)+IF('06_CONSTRUCTION'!I15=1,'01A_DEVELOPMENT'!$C$69,0) -> 1.8913233 | U71: =IF(6=1,'01A_DEVELOPMENT'!$C$37+'01A_DEVELOPMENT'!$C$19,0)+'01A_DEVELOPMENT'!$C$20*'20_CASH_FLOW'!J41*IF('06_CONSTRUCTION'!J14=1,1-'01A_DEVELOPMENT'!$C$67,1)+IF('06_CONSTRUCTION'!J15=1,'01A_DEVELOPMENT'!$C$69,0) -> 1.9074004 | V71: =IF(7=1,'01A_DEVELOPMENT'!$C$37+'01A_DEVELOPMENT'!$C$19,0)+'01A_DEVELOPMENT'!$C$20*'20_CASH_FLOW'!K41*IF('06_CONSTRUCTION'!K14=1,1-'01A_DEVELOPMENT'!$C$67,1)+IF('06_CONSTRUCTION'!K15=1,'01A_DEVELOPMENT'!$C$69,0) -> 1.923799 | W71: =IF(8=1,'01A_DEVELOPMENT'!$C$37+'01A_DEVELOPMENT'!$C$19,0)+'01A_DEVELOPMENT'!$C$20*'20_CASH_FLOW'!L41*IF('06_CONSTRUCTION'!L14=1,1-'01A_DEVELOPMENT'!$C$67,1)+IF('06_CONSTRUCTION'!L15=1,'01A_DEVELOPMENT'!$C$69,0) -> 2.2957024 | X71: =IF(9=1,'01A_DEVELOPMENT'!$C$37+'01A_DEVELOPMENT'!$C$19,0)+'01A_DEVELOPMENT'!$C$20*'20_CASH_FLOW'!M41*IF('06_CONSTRUCTION'!M14=1,1-'01A_DEVELOPMENT'!$C$67,1)+IF('06_CONSTRUCTION'!M15=1,'01A_DEVELOPMENT'!$C$69,0) -> 2.1183075 | Y71: =IF(10=1,'01A_DEVELOPMENT'!$C$37+'01A_DEVELOPMENT'!$C$19,0)+'01A_DEVELOPMENT'!$C$20*'20_CASH_FLOW'!N41*IF('06_CONSTRUCTION'!N14=1,1-'01A_DEVELOPMENT'!$C$67,1)+IF('06_CONSTRUCTION'!N15=1,'01A_DEVELOPMENT'!$C$69,0) -> 2.100714 | Z71: =IF(11=1,'01A_DEVELOPMENT'!$C$37+'01A_DEVELOPMENT'!$C$19,0)+'01A_DEVELOPMENT'!$C$20*'20_CASH_FLOW'!O41*IF('06_CONSTRUCTION'!O14=1,1-'01A_DEVELOPMENT'!$C$67,1)+IF('06_CONSTRUCTION'!O15=1,'01A_DEVELOPMENT'!$C$69,0) -> 2.0804634 | AA71: =IF(12=1,'01A_DEVELOPMENT'!$C$37+'01A_DEVELOPMENT'!$C$19,0)+'01A_DEVELOPMENT'!$C$20*'20_CASH_FLOW'!P41*IF('06_CONSTRUCTION'!P14=1,1-'01A_DEVELOPMENT'!$C$67,1)+IF('06_CONSTRUCTION'!P15=1,'01A_DEVELOPMENT'!$C$69,0) -> 2.0573182 | AB71: =IF(13=1,'01A_DEVELOPMENT'!$C$37+'01A_DEVELOPMENT'!$C$19,0)+'01A_DEVELOPMENT'!$C$20*'20_CASH_FLOW'!Q41*IF('06_CONSTRUCTION'!Q14=1,1-'01A_DEVELOPMENT'!$C$67,1)+IF('06_CONSTRUCTION'!Q15=1,'01A_DEVELOPMENT'!$C$69,0) -> 2.0310214 | AC71: =IF(14=1,'01A_DEVELOPMENT'!$C$37+'01A_DEVELOPMENT'!$C$19,0)+'01A_DEVELOPMENT'!$C$20*'20_CASH_FLOW'!R41*IF('06_CONSTRUCTION'!R14=1,1-'01A_DEVELOPMENT'!$C$67,1)+IF('06_CONSTRUCTION'!R15=1,'01A_DEVELOPMENT'!$C$69,0) -> 2.0012946 | AD71: =IF(15=1,'01A_DEVELOPMENT'!$C$37+'01A_DEVELOPMENT'!$C$19,0)+'01A_DEVELOPMENT'!$C$20*'20_CASH_FLOW'!S41*IF('06_CONSTRUCTION'!S14=1,1-'01A_DEVELOPMENT'!$C$67,1)+IF('06_CONSTRUCTION'!S15=1,'01A_DEVELOPMENT'!$C$69,0) -> 1.9678372 | AE71: =IF(16=1,'01A_DEVELOPMENT'!$C$37+'01A_DEVELOPMENT'!$C$19,0)+'01A_DEVELOPMENT'!$C$20*'20_CASH_FLOW'!T41*IF('06_CONSTRUCTION'!T14=1,1-'01A_DEVELOPMENT'!$C$67,1)+IF('06_CONSTRUCTION'!T15=1,'01A_DEVELOPMENT'!$C$69,0) -> 1.9303235 | AF71: =IF(17=1,'01A_DEVELOPMENT'!$C$37+'01A_DEVELOPMENT'!$C$19,0)+'01A_DEVELOPMENT'!$C$20*'20_CASH_FLOW'!U41*IF('06_CONSTRUCTION'!U14=1,1-'01A_DEVELOPMENT'!$C$67,1)+IF('06_CONSTRUCTION'!U15=1,'01A_DEVELOPMENT'!$C$69,0) -> 1.8884015 | AG71: =IF(18=1,'01A_DEVELOPMENT'!$C$37+'01A_DEVELOPMENT'!$C$19,0)+'01A_DEVELOPMENT'!$C$20*'20_CASH_FLOW'!V41*IF('06_CONSTRUCTION'!V14=1,1-'01A_DEVELOPMENT'!$C$67,1)+IF('06_CONSTRUCTION'!V15=1,'01A_DEVELOPMENT'!$C$69,0) -> 1.8416903 | AH71: =IF(19=1,'01A_DEVELOPMENT'!$C$37+'01A_DEVELOPMENT'!$C$19,0)+'01A_DEVELOPMENT'!$C$20*'20_CASH_FLOW'!W41*IF('06_CONSTRUCTION'!W14=1,1-'01A_DEVELOPMENT'!$C$67,1)+IF('06_CONSTRUCTION'!W15=1,'01A_DEVELOPMENT'!$C$69,0) -> 3.4321278 | AI71: =IF(20=1,'01A_DEVELOPMENT'!$C$37+'01A_DEVELOPMENT'!$C$19,0)+'01A_DEVELOPMENT'!$C$20*'20_CASH_FLOW'!X41*IF('06_CONSTRUCTION'!X14=1,1-'01A_DEVELOPMENT'!$C$67,1)+IF('06_CONSTRUCTION'!X15=1,'01A_DEVELOPMENT'!$C$69,0) -> 5.0303551 | AJ71: =IF(21=1,'01A_DEVELOPMENT'!$C$37+'01A_DEVELOPMENT'!$C$19,0)+'01A_DEVELOPMENT'!$C$20*'20_CASH_FLOW'!Y41*IF('06_CONSTRUCTION'!Y14=1,1-'01A_DEVELOPMENT'!$C$67,1)+IF('06_CONSTRUCTION'!Y15=1,'01A_DEVELOPMENT'!$C$69,0) -> 5.0726424 | AK71: =IF(22=1,'01A_DEVELOPMENT'!$C$37+'01A_DEVELOPMENT'!$C$19,0)+'01A_DEVELOPMENT'!$C$20*'20_CASH_FLOW'!Z41*IF('06_CONSTRUCTION'!Z14=1,1-'01A_DEVELOPMENT'!$C$67,1)+IF('06_CONSTRUCTION'!Z15=1,'01A_DEVELOPMENT'!$C$69,0) -> 5.1157754 | AL71: =IF(23=1,'01A_DEVELOPMENT'!$C$37+'01A_DEVELOPMENT'!$C$19,0)+'01A_DEVELOPMENT'!$C$20*'20_CASH_FLOW'!AA41*IF('06_CONSTRUCTION'!AA14=1,1-'01A_DEVELOPMENT'!$C$67,1)+IF('06_CONSTRUCTION'!AA15=1,'01A_DEVELOPMENT'!$C$69,0) -> 5.1597711 | AM71: =IF(24=1,'01A_DEVELOPMENT'!$C$37+'01A_DEVELOPMENT'!$C$19,0)+'01A_DEVELOPMENT'!$C$20*'20_CASH_FLOW'!AB41*IF('06_CONSTRUCTION'!AB14=1,1-'01A_DEVELOPMENT'!$C$67,1)+IF('06_CONSTRUCTION'!AB15=1,'01A_DEVELOPMENT'!$C$69,0) -> 4.5817086 | AN71: =IF(25=1,'01A_DEVELOPMENT'!$C$37+'01A_DEVELOPMENT'!$C$19,0)+'01A_DEVELOPMENT'!$C$20*'20_CASH_FLOW'!AC41*IF('06_CONSTRUCTION'!AC14=1,1-'01A_DEVELOPMENT'!$C$67,1)+IF('06_CONSTRUCTION'!AC15=1,'01A_DEVELOPMENT'!$C$69,0) -> 4.6274817 | AO71: =IF(26=1,'01A_DEVELOPMENT'!$C$37+'01A_DEVELOPMENT'!$C$19,0)+'01A_DEVELOPMENT'!$C$20*'20_CASH_FLOW'!AD41*IF('06_CONSTRUCTION'!AD14=1,1-'01A_DEVELOPMENT'!$C$67,1)+IF('06_CONSTRUCTION'!AD15=1,'01A_DEVELOPMENT'!$C$69,0) -> 4.6741702 | AP71: =IF(27=1,'01A_DEVELOPMENT'!$C$37+'01A_DEVELOPMENT'!$C$19,0)+'01A_DEVELOPMENT'!$C$20*'20_CASH_FLOW'!AE41*IF('06_CONSTRUCTION'!AE14=1,1-'01A_DEVELOPMENT'!$C$67,1)+IF('06_CONSTRUCTION'!AE15=1,'01A_DEVELOPMENT'!$C$69,0) -> 4.7217925 | AQ71: =IF(28=1,'01A_DEVELOPMENT'!$C$37+'01A_DEVELOPMENT'!$C$19,0)+'01A_DEVELOPMENT'!$C$20*'20_CASH_FLOW'!AF41*IF('06_CONSTRUCTION'!AF14=1,1-'01A_DEVELOPMENT'!$C$67,1)+IF('06_CONSTRUCTION'!AF15=1,'01A_DEVELOPMENT'!$C$69,0) -> 4.7703673 | AR71: =IF(29=1,'01A_DEVELOPMENT'!$C$37+'01A_DEVELOPMENT'!$C$19,0)+'01A_DEVELOPMENT'!$C$20*'20_CASH_FLOW'!AG41*IF('06_CONSTRUCTION'!AG14=1,1-'01A_DEVELOPMENT'!$C$67,1)+IF('06_CONSTRUCTION'!AG15=1,'01A_DEVELOPMENT'!$C$69,0) -> 0 | AS71: =IF(30=1,'01A_DEVELOPMENT'!$C$37+'01A_DEVELOPMENT'!$C$19,0)+'01A_DEVELOPMENT'!$C$20*'20_CASH_FLOW'!AH41*IF('06_CONSTRUCTION'!AH14=1,1-'01A_DEVELOPMENT'!$C$67,1)+IF('06_CONSTRUCTION'!AH15=1,'01A_DEVELOPMENT'!$C$69,0) -> 0 | AT71: =IF(31=1,'01A_DEVELOPMENT'!$C$37+'01A_DEVELOPMENT'!$C$19,0)+'01A_DEVELOPMENT'!$C$20*'20_CASH_FLOW'!AI41*IF('06_CONSTRUCTION'!AI14=1,1-'01A_DEVELOPMENT'!$C$67,1)+IF('06_CONSTRUCTION'!AI15=1,'01A_DEVELOPMENT'!$C$69,0) -> 0 | AU71: =IF(32=1,'01A_DEVELOPMENT'!$C$37+'01A_DEVELOPMENT'!$C$19,0)+'01A_DEVELOPMENT'!$C$20*'20_CASH_FLOW'!AJ41*IF('06_CONSTRUCTION'!AJ14=1,1-'01A_DEVELOPMENT'!$C$67,1)+IF('06_CONSTRUCTION'!AJ15=1,'01A_DEVELOPMENT'!$C$69,0) -> 0 | AV71: =IF(33=1,'01A_DEVELOPMENT'!$C$37+'01A_DEVELOPMENT'!$C$19,0)+'01A_DEVELOPMENT'!$C$20*'20_CASH_FLOW'!AK41*IF('06_CONSTRUCTION'!AK14=1,1-'01A_DEVELOPMENT'!$C$67,1)+IF('06_CONSTRUCTION'!AK15=1,'01A_DEVELOPMENT'!$C$69,0) -> 0 | AW71: =IF(34=1,'01A_DEVELOPMENT'!$C$37+'01A_DEVELOPMENT'!$C$19,0)+'01A_DEVELOPMENT'!$C$20*'20_CASH_FLOW'!AL41*IF('06_CONSTRUCTION'!AL14=1,1-'01A_DEVELOPMENT'!$C$67,1)+IF('06_CONSTRUCTION'!AL15=1,'01A_DEVELOPMENT'!$C$69,0) -> 0 | AX71: =IF(35=1,'01A_DEVELOPMENT'!$C$37+'01A_DEVELOPMENT'!$C$19,0)+'01A_DEVELOPMENT'!$C$20*'20_CASH_FLOW'!AM41*IF('06_CONSTRUCTION'!AM14=1,1-'01A_DEVELOPMENT'!$C$67,1)+IF('06_CONSTRUCTION'!AM15=1,'01A_DEVELOPMENT'!$C$69,0) -> 0 | AY71: =IF(36=1,'01A_DEVELOPMENT'!$C$37+'01A_DEVELOPMENT'!$C$19,0)+'01A_DEVELOPMENT'!$C$20*'20_CASH_FLOW'!AN41*IF('06_CONSTRUCTION'!AN14=1,1-'01A_DEVELOPMENT'!$C$67,1)+IF('06_CONSTRUCTION'!AN15=1,'01A_DEVELOPMENT'!$C$69,0) -> 0 | AZ71: =IF(37=1,'01A_DEVELOPMENT'!$C$37+'01A_DEVELOPMENT'!$C$19,0)+'01A_DEVELOPMENT'!$C$20*'20_CASH_FLOW'!AO41*IF('06_CONSTRUCTION'!AO14=1,1-'01A_DEVELOPMENT'!$C$67,1)+IF('06_CONSTRUCTION'!AO15=1,'01A_DEVELOPMENT'!$C$69,0) -> 0 | BA71: =IF(38=1,'01A_DEVELOPMENT'!$C$37+'01A_DEVELOPMENT'!$C$19,0)+'01A_DEVELOPMENT'!$C$20*'20_CASH_FLOW'!AP41*IF('06_CONSTRUCTION'!AP14=1,1-'01A_DEVELOPMENT'!$C$67,1)+IF('06_CONSTRUCTION'!AP15=1,'01A_DEVELOPMENT'!$C$69,0) -> 0 | BB71: =IF(39=1,'01A_DEVELOPMENT'!$C$37+'01A_DEVELOPMENT'!$C$19,0)+'01A_DEVELOPMENT'!$C$20*'20_CASH_FLOW'!AQ41*IF('06_CONSTRUCTION'!AQ14=1,1-'01A_DEVELOPMENT'!$C$67,1)+IF('06_CONSTRUCTION'!AQ15=1,'01A_DEVELOPMENT'!$C$69,0) -> 0 | BC71: =IF(40=1,'01A_DEVELOPMENT'!$C$37+'01A_DEVELOPMENT'!$C$19,0)+'01A_DEVELOPMENT'!$C$20*'20_CASH_FLOW'!AR41*IF('06_CONSTRUCTION'!AR14=1,1-'01A_DEVELOPMENT'!$C$67,1)+IF('06_CONSTRUCTION'!AR15=1,'01A_DEVELOPMENT'!$C$69,0) -> 0
A72: TRI DU DÉVELOPPEUR sur le scénario de succès (des dépenses de développement à la dernière distribution) | B72: % | C72: =IF(ISNUMBER(IRR('01A_DEVELOPMENT'!$F$71:$BC$71,0.15)),IF(ABS(IRR('01A_DEVELOPMENT'!$F$71:$BC$71,0.15))<1,IRR('01A_DEVELOPMENT'!$F$71:$BC$71,0.15),IF(ISNUMBER(IRR('01A_DEVELOPMENT'!$F$71:$BC$71,0.05)),IF(ABS(IRR('01A_DEVELOPMENT'!$F$71:$BC$71,0.05))<1,IRR('01A_DEVELOPMENT'!$F$71:$BC$71,0.05),IF(ISNUMBER(IRR('01A_DEVELOPMENT'!$F$71:$BC$71,-0.05)),IF(ABS(IRR('01A_DEVELOPMENT'!$F$71:$BC$71,-0.05))<1,IRR('01A_DEVELOPMENT'!$F$71:$BC$71,-0.05),-1),-1)),IF(ISNUMBER(IRR('01A_DEVELOPMENT'!$F$71:$BC$71,-0.05)),IF(ABS(IRR('01A_DEVELOPMENT'!$F$71:$BC$71,-0.05))<1,IRR('01A_DEVELOPMENT'!$F$71:$BC$71,-0.05),-1),-1))),IF(ISNUMBER(IRR('01A_DEVELOPMENT'!$F$71:$BC$71,0.05)),IF(ABS(IRR('01A_DEVELOPMENT'!$F$71:$BC$71,0.05))<1,IRR('01A_DEVELOPMENT'!$F$71:$BC$71,0.05),IF(ISNUMBER(IRR('01A_DEVELOPMENT'!$F$71:$BC$71,-0.05)),IF(ABS(IRR('01A_DEVELOPMENT'!$F$71:$BC$71,-0.05))<1,IRR('01A_DEVELOPMENT'!$F$71:$BC$71,-0.05),-1),-1)),IF(ISNUMBER(IRR('01A_DEVELOPMENT'!$F$71:$BC$71,-0.05)),IF(ABS(IRR('01A_DEVELOPMENT'!$F$71:$BC$71,-0.05))<1,IRR('01A_DEVELOPMENT'!$F$71:$BC$71,-0.05),-1),-1))) -> 0.15957204
A73: Multiple de trésorerie du développeur (entrées / sorties) | B73: x | C73: =IFERROR(SUMIF('01A_DEVELOPMENT'!$F$71:$BC$71,">0")/-SUMIF('01A_DEVELOPMENT'!$F$71:$BC$71,"<0"),0) -> 4.9714892
A74: Trésorerie cumulée maximale à risque du développeur | B74: M USD | C74: =-MIN(0,MIN(SUM($F$71:F$71),SUM($F$71:G$71),SUM($F$71:H$71),SUM($F$71:I$71),SUM($F$71:J$71),SUM($F$71:K$71),SUM($F$71:L$71),SUM($F$71:M$71),SUM($F$71:N$71),SUM($F$71:O$71),SUM($F$71:P$71),SUM($F$71:Q$71),SUM($F$71:R$71),SUM($F$71:S$71),SUM($F$71:T$71),SUM($F$71:U$71),SUM($F$71:V$71),SUM($F$71:W$71))) -> 10.188162
A76: Lecture : la VAN pondérée par le risque indique si un développeur doit se lancer ; le TRI et le multiple sur le scénario de succès indiquent ce qu'il gagne s'il boucle ; les revalorisations montrent où la valeur se crée entre le bouclage et la COD. Les promotes et le carried interest ne sont pas modélisés.

Sheet 02_PROJECT_INPUTS
A1: 02 DONNÉES DU PROJET — Projet de référence fictif : Kasiri River Hydro (PIE privé de 60 MW)
A2: Toutes les données sont FICTIVES, construites pour la formation. Aucune donnée de projet confidentielle.
A4: A. IDENTITÉ DU PROJET
A5: Nom du projet | C5: Kasiri River Hydro (KRH) | D5: PIE privé fictif de 60 MW
A6: Pays | C6: République de Navaria | D6: Pays fictif d'Afrique subsaharienne
A7: Rivière / bassin | C7: Rivière Kasiri | D7: Fictif ; régime tropical bimodal, bassin versant à forte pente
A8: Type d'aménagement | C8: Au fil de l'eau avec petite retenue journalière
A9: B. CALENDRIER
A10: Année de départ du modèle / bouclage financier (t=1) | B10: année | C10: 2027
A11: Année de base des prix réels | B11: année | C11: 2026 | D11: Toutes les données « réelles » en USD 2026
A12: Durée de construction de base | B12: ans | C12: 3 | D12: IFC 2015 : jusqu'à environ 4 ans pour les grands ouvrages ; petite hydro en ASS observée à 19-29 mois [hydro_development_evidence]
A13: Durée d'exploitation concession / CAE | B13: ans | C13: 25 | D13: CAE de 20 ans plus une prolongation supposée de 5 ans au même tarif (hypothèse)
A14: C. CENTRALE
A15: Puissance installée | B15: MW | C15: 60 | D15: 3 groupes Francis de 20 MW (fictif)
A16: Nombre de groupes | B16: # | C16: 3
A17: D. MACRO (modèle en USD, compagnie en monnaie locale)
A18: IPC américain (indexation USD) | B18: % p.a. | C18: 0.02 | D18: Hypothèse
A19: IPC local (lire navarienne, NVL) | B19: % p.a. | C19: 0.08 | D19: Hypothèse
A20: Taux de change année de base | B20: NVL/USD | C20: 20 | D20: Fictif
A21: Dépréciation nominale NVL/USD (cas de base) | B21: % p.a. | C21: 0.06 | D21: Environ l'écart d'inflation (PPA) — hypothèse
A22: Indexation du CAPEX pendant la construction | B22: % p.a. | C22: 0.025
A23: Taux d'actualisation du projet (USD nominal) pour VAN/LCOE | B23: % | C23: 0.1 | D23: Hypothèse ; remplacer par le CMPC du promoteur
A24: Taux d'actualisation État (VA budgétaire) | B24: % | C24: 0.08 | D24: Approximation : coût d'emprunt souverain en USD — hypothèse

Sheet 03_HYDROLOGY
A1: 03 HYDROLOGIE — Débit, chute, rendement → énergie mensuelle et annuelle ; P50/P75/P90
A2: Énergie installée, disponible, attendue et contractuelle restent distinctes (voir 04_GENERATION)
A4: A. PARAMÈTRES HYDRAULIQUES
A5: Débit d'équipement des turbines | B5: m3/s | C5: 57 | D5: Fictif
A6: Chute nette nominale | B6: m | C6: 120 | D6: Fictif
A7: Rendement des turbines | B7: % | C7: 0.92 | D7: Hypothèse (sans source)
A8: Rendement alternateur et transformateur | B8: % | C8: 0.98 | D8: Hypothèse
A9: Débit réservé | B9: m3/s | C9: 4 | D9: Fixé par l'EIES / le permis d'eau
A10: Disponibilité (arrêts planifiés + fortuits) | B10: % | C10: 0.95 | D10: Hypothèse
A11: Disponibilité de la 1re année (montée en charge) | B11: x | C11: 0.85
A12: Masse volumique de l'eau | B12: kg/m3 | C12: 1000 | D12: Constante physique
A13: Gravité | B13: m/s2 | C13: 9.81 | D13: Constante physique
A14: B. INCERTITUDE HYDROLOGIQUE
A15: Coefficient de variation interannuel de l'énergie | B15: % | C15: 0.15 | D15: Petit bassin à forte pente : plus variable qu'un grand fleuve (hypothèse)
A16: Score z normal pour P75 | C16: 0.6745 | D16: Approximation normale ; remplacer par la distribution empirique si disponible
A17: Score z normal pour P90 | C17: 1.2816
A18: Durée de la série de débits fiable | B18: ans | C18: 12 | D18: Jaugeage commencé en préfaisabilité plus corrélation régionale (fictif)
A19: Maturité de l'étude hydrologique (1=bureau, 2=niveau EF, 3=revue indépendante) | B19: 1-3 | C19: 2 | D19: Test GATE 1
A21: C. DÉBIT MOYEN MENSUEL (moyenne de long terme, régime bimodal fictif)
A22: Mois | C22: Annuel | E22: Janv. | F22: Févr. | G22: Mars | H22: Avr. | I22: Mai | J22: Juin | K22: Juil. | L22: Août | M22: Sept. | N22: Oct. | O22: Nov. | P22: Déc.
A23: Jours par mois | B23: jours | E23: 31 | F23: 28.25 | G23: 31 | H23: 30 | I23: 31 | J23: 30 | K23: 31 | L23: 31 | M23: 30 | N23: 31 | O23: 30 | P23: 31
A24: Débit moyen rivière | B24: m3/s | C24: =SUMPRODUCT(E24:P24,E23:P23)/SUM(E23:P23) -> 37.894593 | E24: 24 | F24: 20 | G24: 28 | H24: 52 | I24: 70 | J24: 58 | K24: 40 | L24: 28 | M24: 22 | N24: 30 | O24: 46 | P24: 36
A25: Débit turbinable = MIN(MAX(Q - débit réservé,0), Q équipement) | B25: m3/s | E25: =MIN(MAX(E24-'03_HYDROLOGY'!$C$9,0),'03_HYDROLOGY'!$C$5) -> 20 | F25: =MIN(MAX(F24-'03_HYDROLOGY'!$C$9,0),'03_HYDROLOGY'!$C$5) -> 16 | G25: =MIN(MAX(G24-'03_HYDROLOGY'!$C$9,0),'03_HYDROLOGY'!$C$5) -> 24 | H25: =MIN(MAX(H24-'03_HYDROLOGY'!$C$9,0),'03_HYDROLOGY'!$C$5) -> 48 | I25: =MIN(MAX(I24-'03_HYDROLOGY'!$C$9,0),'03_HYDROLOGY'!$C$5) -> 57 | J25: =MIN(MAX(J24-'03_HYDROLOGY'!$C$9,0),'03_HYDROLOGY'!$C$5) -> 54 | K25: =MIN(MAX(K24-'03_HYDROLOGY'!$C$9,0),'03_HYDROLOGY'!$C$5) -> 36 | L25: =MIN(MAX(L24-'03_HYDROLOGY'!$C$9,0),'03_HYDROLOGY'!$C$5) -> 24 | ... P25: =MIN(MAX(P24-'03_HYDROLOGY'!$C$9,0),'03_HYDROLOGY'!$C$5) -> 32
A26: Puissance moyenne = MIN(rho*g*Q*H*eta/1e6, installée) | B26: MW | C26: =SUMPRODUCT(E26:P26,E23:P23)/SUM(E23:P23) -> 35.121508 | E26: =MIN('03_HYDROLOGY'!$C$12*'03_HYDROLOGY'!$C$13*E25*'03_HYDROLOGY'!$C$6*'03_HYDROLOGY'!$C$7*'03_HYDROLOGY'!$C$8/1000000,'02_PROJECT_INPUTS'!$C$15) -> 21.22727 | F26: =MIN('03_HYDROLOGY'!$C$12*'03_HYDROLOGY'!$C$13*F25*'03_HYDROLOGY'!$C$6*'03_HYDROLOGY'!$C$7*'03_HYDROLOGY'!$C$8/1000000,'02_PROJECT_INPUTS'!$C$15) -> 16.981816 | G26: =MIN('03_HYDROLOGY'!$C$12*'03_HYDROLOGY'!$C$13*G25*'03_HYDROLOGY'!$C$6*'03_HYDROLOGY'!$C$7*'03_HYDROLOGY'!$C$8/1000000,'02_PROJECT_INPUTS'!$C$15) -> 25.472724 | H26: =MIN('03_HYDROLOGY'!$C$12*'03_HYDROLOGY'!$C$13*H25*'03_HYDROLOGY'!$C$6*'03_HYDROLOGY'!$C$7*'03_HYDROLOGY'!$C$8/1000000,'02_PROJECT_INPUTS'!$C$15) -> 50.945449 | I26: =MIN('03_HYDROLOGY'!$C$12*'03_HYDROLOGY'!$C$13*I25*'03_HYDROLOGY'!$C$6*'03_HYDROLOGY'!$C$7*'03_HYDROLOGY'!$C$8/1000000,'02_PROJECT_INPUTS'!$C$15) -> 60 | J26: =MIN('03_HYDROLOGY'!$C$12*'03_HYDROLOGY'!$C$13*J25*'03_HYDROLOGY'!$C$6*'03_HYDROLOGY'!$C$7*'03_HYDROLOGY'!$C$8/1000000,'02_PROJECT_INPUTS'!$C$15) -> 57.31363 | K26: =MIN('03_HYDROLOGY'!$C$12*'03_HYDROLOGY'!$C$13*K25*'03_HYDROLOGY'!$C$6*'03_HYDROLOGY'!$C$7*'03_HYDROLOGY'!$C$8/1000000,'02_PROJECT_INPUTS'!$C$15) -> 38.209087 | L26: =MIN('03_HYDROLOGY'!$C$12*'03_HYDROLOGY'!$C$13*L25*'03_HYDROLOGY'!$C$6*'03_HYDROLOGY'!$C$7*'03_HYDROLOGY'!$C$8/1000000,'02_PROJECT_INPUTS'!$C$15) -> 25.472724 | ... P26: =MIN('03_HYDROLOGY'!$C$12*'03_HYDROLOGY'!$C$13*P25*'03_HYDROLOGY'!$C$6*'03_HYDROLOGY'!$C$7*'03_HYDROLOGY'!$C$8/1000000,'02_PROJECT_INPUTS'!$C$15) -> 33.963633
A27: Énergie à 100 % de disponibilité | B27: GWh | C27: =SUM(E27:P27) -> 307.87513 | E27: =E26*E23*24/1000 -> 15.793089 | F27: =F26*F23*24/1000 -> 11.513671 | G27: =G26*G23*24/1000 -> 18.951707 | H27: =H26*H23*24/1000 -> 36.680723 | I27: =I26*I23*24/1000 -> 44.64 | J27: =J26*J23*24/1000 -> 41.265814 | K27: =K26*K23*24/1000 -> 28.427561 | L27: =L26*L23*24/1000 -> 18.951707 | ... P27: =P26*P23*24/1000 -> 25.268943
A28: Énergie attendue (x disponibilité) | B28: GWh | C28: =SUM(E28:P28) -> 292.48138 | E28: =E27*'03_HYDROLOGY'!$C$10 -> 15.003435 | F28: =F27*'03_HYDROLOGY'!$C$10 -> 10.937988 | G28: =G27*'03_HYDROLOGY'!$C$10 -> 18.004122 | H28: =H27*'03_HYDROLOGY'!$C$10 -> 34.846687 | I28: =I27*'03_HYDROLOGY'!$C$10 -> 42.408 | J28: =J27*'03_HYDROLOGY'!$C$10 -> 39.202523 | K28: =K27*'03_HYDROLOGY'!$C$10 -> 27.006182 | L28: =L27*'03_HYDROLOGY'!$C$10 -> 18.004122 | ... P28: =P27*'03_HYDROLOGY'!$C$10 -> 24.005496
A29: Débit déversé (> débit d'équip.) | B29: m3/s | E29: =MAX(E24-'03_HYDROLOGY'!$C$9-'03_HYDROLOGY'!$C$5,0) -> 0 | F29: =MAX(F24-'03_HYDROLOGY'!$C$9-'03_HYDROLOGY'!$C$5,0) -> 0 | G29: =MAX(G24-'03_HYDROLOGY'!$C$9-'03_HYDROLOGY'!$C$5,0) -> 0 | H29: =MAX(H24-'03_HYDROLOGY'!$C$9-'03_HYDROLOGY'!$C$5,0) -> 0 | I29: =MAX(I24-'03_HYDROLOGY'!$C$9-'03_HYDROLOGY'!$C$5,0) -> 9 | J29: =MAX(J24-'03_HYDROLOGY'!$C$9-'03_HYDROLOGY'!$C$5,0) -> 0 | K29: =MAX(K24-'03_HYDROLOGY'!$C$9-'03_HYDROLOGY'!$C$5,0) -> 0 | L29: =MAX(L24-'03_HYDROLOGY'!$C$9-'03_HYDROLOGY'!$C$5,0) -> 0 | ... P29: =MAX(P24-'03_HYDROLOGY'!$C$9-'03_HYDROLOGY'!$C$5,0) -> 0
A30: Note de méthode : l'énergie calculée sur les débits mensuels moyens de long terme surestime l'énergie quand les débits dépassent le débit d'équipement certaines années (inégalité de Jensen). Remplacer par une simulation journalière ou mensuelle sur toute la série quand elle est disponible.
A32: D. STATISTIQUES D'ÉNERGIE ANNUELLE
A33: Énergie annuelle P50 (attendue, long terme) | B33: GWh | C33: =C28 -> 292.48138
A34: Énergie annuelle P75 | B34: GWh | C34: ='03_HYDROLOGY'!$C$33*(1-'03_HYDROLOGY'!$C$16*'03_HYDROLOGY'!$C$15) -> 262.88957
A35: Énergie annuelle P90 (à un an) | B35: GWh | C35: ='03_HYDROLOGY'!$C$33*(1-'03_HYDROLOGY'!$C$17*'03_HYDROLOGY'!$C$15) -> 236.25476
A36: Corrélation interannuelle de l'énergie (persistance des années sèches) | C36: 0.3 | D36: Hypothèse ; estimer à partir de la série de débits
A37: P90 de l'énergie moyenne sur 10 ans (avec persistance) | B37: GWh | C37: ='03_HYDROLOGY'!$C$33*(1-'03_HYDROLOGY'!$C$17*'03_HYDROLOGY'!$C$15*SQRT((1+'03_HYDROLOGY'!$C$36)/(1-'03_HYDROLOGY'!$C$36)/10)) -> 268.25075
A38: Facteur de charge au P50 | B38: % | C38: ='03_HYDROLOGY'!$C$33/('02_PROJECT_INPUTS'!$C$15*8.76) -> 0.55647142
A39: Puissance disponible (installée x disponibilité) | B39: MW | C39: ='02_PROJECT_INPUTS'!$C$15*'03_HYDROLOGY'!$C$10 -> 57
A40: Production moyenne au P50 | B40: MW | C40: ='03_HYDROLOGY'!$C$33/8.76 -> 33.388285
A41: Puissance garantie saison sèche (mois min.) | B41: MW | C41: =MIN(E26:P26)*'03_HYDROLOGY'!$C$10 -> 16.132726
A42: Ratio P90 / P50 | B42: x | C42: ='03_HYDROLOGY'!$C$35/'03_HYDROLOGY'!$C$33 -> 0.80776
A43: Contrôle : puissance théorique au débit d'équip. | B43: MW | C43: ='03_HYDROLOGY'!$C$12*'03_HYDROLOGY'!$C$13*'03_HYDROLOGY'!$C$5*'03_HYDROLOGY'!$C$6*'03_HYDROLOGY'!$C$7*'03_HYDROLOGY'!$C$8/1000000 -> 60.497721 | D43: Doit être ≥ puissance installée

Sheet 04_GENERATION
A1: 04 PRODUCTION — Installée, disponible, attendue, évacuée, livrée, contractuelle
A2: Cas hydrologique, fenêtre de sécheresse et tendance climatique appliqués ici
A6: Énergie du cas de production choisi (P50/P75/P90) | B6: GWh | C6: =CHOOSE('01_CONTROL_PANEL'!$C$6,'03_HYDROLOGY'!$C$33,'03_HYDROLOGY'!$C$34,'03_HYDROLOGY'!$C$35) -> 292.48138
A7: Énergie cas prêteurs | B7: GWh | C7: =CHOOSE('01_CONTROL_PANEL'!$C$7,'03_HYDROLOGY'!$C$33,'03_HYDROLOGY'!$C$34,'03_HYDROLOGY'!$C$35,'03_HYDROLOGY'!$C$37) -> 268.25075
A8: A. PUISSANCE
A9: Puissance installée | B9: MW | E9: ='06_CONSTRUCTION'!E14*'02_PROJECT_INPUTS'!$C$15 -> 0 | F9: ='06_CONSTRUCTION'!F14*'02_PROJECT_INPUTS'!$C$15 -> 0 | G9: ='06_CONSTRUCTION'!G14*'02_PROJECT_INPUTS'!$C$15 -> 0 | H9: ='06_CONSTRUCTION'!H14*'02_PROJECT_INPUTS'!$C$15 -> 60 | I9: ='06_CONSTRUCTION'!I14*'02_PROJECT_INPUTS'!$C$15 -> 60 | J9: ='06_CONSTRUCTION'!J14*'02_PROJECT_INPUTS'!$C$15 -> 60 | K9: ='06_CONSTRUCTION'!K14*'02_PROJECT_INPUTS'!$C$15 -> 60 | L9: ='06_CONSTRUCTION'!L14*'02_PROJECT_INPUTS'!$C$15 -> 60 | ... AR9: ='06_CONSTRUCTION'!AR14*'02_PROJECT_INPUTS'!$C$15 -> 0
A10: Puissance disponible (x disponibilité) | B10: MW | E10: ='06_CONSTRUCTION'!E14*'03_HYDROLOGY'!$C$39 -> 0 | F10: ='06_CONSTRUCTION'!F14*'03_HYDROLOGY'!$C$39 -> 0 | G10: ='06_CONSTRUCTION'!G14*'03_HYDROLOGY'!$C$39 -> 0 | H10: ='06_CONSTRUCTION'!H14*'03_HYDROLOGY'!$C$39 -> 57 | I10: ='06_CONSTRUCTION'!I14*'03_HYDROLOGY'!$C$39 -> 57 | J10: ='06_CONSTRUCTION'!J14*'03_HYDROLOGY'!$C$39 -> 57 | K10: ='06_CONSTRUCTION'!K14*'03_HYDROLOGY'!$C$39 -> 57 | L10: ='06_CONSTRUCTION'!L14*'03_HYDROLOGY'!$C$39 -> 57 | ... AR10: ='06_CONSTRUCTION'!AR14*'03_HYDROLOGY'!$C$39 -> 0
A11: B. FACTEURS HYDROLOGIQUES
A12: Facteur sécheresse | B12: x | E12: =IF(AND('01_CONTROL_PANEL'!$C$15=1,'06_CONSTRUCTION'!E5>='27_SCENARIOS'!$C$12,'06_CONSTRUCTION'!E5<'27_SCENARIOS'!$C$12+'27_SCENARIOS'!$C$13),'27_SCENARIOS'!$C$11,1) -> 1 | F12: =IF(AND('01_CONTROL_PANEL'!$C$15=1,'06_CONSTRUCTION'!F5>='27_SCENARIOS'!$C$12,'06_CONSTRUCTION'!F5<'27_SCENARIOS'!$C$12+'27_SCENARIOS'!$C$13),'27_SCENARIOS'!$C$11,1) -> 1 | G12: =IF(AND('01_CONTROL_PANEL'!$C$15=1,'06_CONSTRUCTION'!G5>='27_SCENARIOS'!$C$12,'06_CONSTRUCTION'!G5<'27_SCENARIOS'!$C$12+'27_SCENARIOS'!$C$13),'27_SCENARIOS'!$C$11,1) -> 1 | H12: =IF(AND('01_CONTROL_PANEL'!$C$15=1,'06_CONSTRUCTION'!H5>='27_SCENARIOS'!$C$12,'06_CONSTRUCTION'!H5<'27_SCENARIOS'!$C$12+'27_SCENARIOS'!$C$13),'27_SCENARIOS'!$C$11,1) -> 1 | I12: =IF(AND('01_CONTROL_PANEL'!$C$15=1,'06_CONSTRUCTION'!I5>='27_SCENARIOS'!$C$12,'06_CONSTRUCTION'!I5<'27_SCENARIOS'!$C$12+'27_SCENARIOS'!$C$13),'27_SCENARIOS'!$C$11,1) -> 1 | J12: =IF(AND('01_CONTROL_PANEL'!$C$15=1,'06_CONSTRUCTION'!J5>='27_SCENARIOS'!$C$12,'06_CONSTRUCTION'!J5<'27_SCENARIOS'!$C$12+'27_SCENARIOS'!$C$13),'27_SCENARIOS'!$C$11,1) -> 1 | K12: =IF(AND('01_CONTROL_PANEL'!$C$15=1,'06_CONSTRUCTION'!K5>='27_SCENARIOS'!$C$12,'06_CONSTRUCTION'!K5<'27_SCENARIOS'!$C$12+'27_SCENARIOS'!$C$13),'27_SCENARIOS'!$C$11,1) -> 1 | L12: =IF(AND('01_CONTROL_PANEL'!$C$15=1,'06_CONSTRUCTION'!L5>='27_SCENARIOS'!$C$12,'06_CONSTRUCTION'!L5<'27_SCENARIOS'!$C$12+'27_SCENARIOS'!$C$13),'27_SCENARIOS'!$C$11,1) -> 1 | ... AR12: =IF(AND('01_CONTROL_PANEL'!$C$15=1,'06_CONSTRUCTION'!AR5>='27_SCENARIOS'!$C$12,'06_CONSTRUCTION'!AR5<'27_SCENARIOS'!$C$12+'27_SCENARIOS'!$C$13),'27_SCENARIOS'!$C$11,1) -> 1
A13: Facteur tendance clim. | B13: x | E13: =(1+'27_SCENARIOS'!$C$38)^(('06_CONSTRUCTION'!E4-'02_PROJECT_INPUTS'!$C$11)/10) -> 1 | F13: =(1+'27_SCENARIOS'!$C$38)^(('06_CONSTRUCTION'!F4-'02_PROJECT_INPUTS'!$C$11)/10) -> 1 | G13: =(1+'27_SCENARIOS'!$C$38)^(('06_CONSTRUCTION'!G4-'02_PROJECT_INPUTS'!$C$11)/10) -> 1 | H13: =(1+'27_SCENARIOS'!$C$38)^(('06_CONSTRUCTION'!H4-'02_PROJECT_INPUTS'!$C$11)/10) -> 1 | I13: =(1+'27_SCENARIOS'!$C$38)^(('06_CONSTRUCTION'!I4-'02_PROJECT_INPUTS'!$C$11)/10) -> 1 | J13: =(1+'27_SCENARIOS'!$C$38)^(('06_CONSTRUCTION'!J4-'02_PROJECT_INPUTS'!$C$11)/10) -> 1 | K13: =(1+'27_SCENARIOS'!$C$38)^(('06_CONSTRUCTION'!K4-'02_PROJECT_INPUTS'!$C$11)/10) -> 1 | L13: =(1+'27_SCENARIOS'!$C$38)^(('06_CONSTRUCTION'!L4-'02_PROJECT_INPUTS'!$C$11)/10) -> 1 | ... AR13: =(1+'27_SCENARIOS'!$C$38)^(('06_CONSTRUCTION'!AR4-'02_PROJECT_INPUTS'!$C$11)/10) -> 1
A14: Facteur de montée en charge | B14: x | E14: =IF('06_CONSTRUCTION'!E5=1,'03_HYDROLOGY'!$C$11,1) -> 1 | F14: =IF('06_CONSTRUCTION'!F5=1,'03_HYDROLOGY'!$C$11,1) -> 1 | G14: =IF('06_CONSTRUCTION'!G5=1,'03_HYDROLOGY'!$C$11,1) -> 1 | H14: =IF('06_CONSTRUCTION'!H5=1,'03_HYDROLOGY'!$C$11,1) -> 0.85 | I14: =IF('06_CONSTRUCTION'!I5=1,'03_HYDROLOGY'!$C$11,1) -> 1 | J14: =IF('06_CONSTRUCTION'!J5=1,'03_HYDROLOGY'!$C$11,1) -> 1 | K14: =IF('06_CONSTRUCTION'!K5=1,'03_HYDROLOGY'!$C$11,1) -> 1 | L14: =IF('06_CONSTRUCTION'!L5=1,'03_HYDROLOGY'!$C$11,1) -> 1 | ... AR14: =IF('06_CONSTRUCTION'!AR5=1,'03_HYDROLOGY'!$C$11,1) -> 1
A15: C. ÉNERGIE (GWh)
A16: Production attendue, P50 (référence) | B16: GWh | C16: =SUM('04_GENERATION'!$E$16:$AR$16) -> 7268.1622 | E16: ='06_CONSTRUCTION'!E14*'03_HYDROLOGY'!$C$33*'27_SCENARIOS'!$C$26*'04_GENERATION'!E13*'04_GENERATION'!E14 -> 0 | F16: ='06_CONSTRUCTION'!F14*'03_HYDROLOGY'!$C$33*'27_SCENARIOS'!$C$26*'04_GENERATION'!F13*'04_GENERATION'!F14 -> 0 | G16: ='06_CONSTRUCTION'!G14*'03_HYDROLOGY'!$C$33*'27_SCENARIOS'!$C$26*'04_GENERATION'!G13*'04_GENERATION'!G14 -> 0 | H16: ='06_CONSTRUCTION'!H14*'03_HYDROLOGY'!$C$33*'27_SCENARIOS'!$C$26*'04_GENERATION'!H13*'04_GENERATION'!H14 -> 248.60917 | I16: ='06_CONSTRUCTION'!I14*'03_HYDROLOGY'!$C$33*'27_SCENARIOS'!$C$26*'04_GENERATION'!I13*'04_GENERATION'!I14 -> 292.48138 | J16: ='06_CONSTRUCTION'!J14*'03_HYDROLOGY'!$C$33*'27_SCENARIOS'!$C$26*'04_GENERATION'!J13*'04_GENERATION'!J14 -> 292.48138 | K16: ='06_CONSTRUCTION'!K14*'03_HYDROLOGY'!$C$33*'27_SCENARIOS'!$C$26*'04_GENERATION'!K13*'04_GENERATION'!K14 -> 292.48138 | L16: ='06_CONSTRUCTION'!L14*'03_HYDROLOGY'!$C$33*'27_SCENARIOS'!$C$26*'04_GENERATION'!L13*'04_GENERATION'!L14 -> 292.48138 | ... AR16: ='06_CONSTRUCTION'!AR14*'03_HYDROLOGY'!$C$33*'27_SCENARIOS'!$C$26*'04_GENERATION'!AR13*'04_GENERATION'!AR14 -> 0
A17: Production — cas choisi | B17: GWh | C17: =SUM('04_GENERATION'!$E$17:$AR$17) -> 7268.1622 | E17: ='06_CONSTRUCTION'!E14*'04_GENERATION'!$C$6*'27_SCENARIOS'!$C$26*'04_GENERATION'!E12*'04_GENERATION'!E13*'04_GENERATION'!E14 -> 0 | F17: ='06_CONSTRUCTION'!F14*'04_GENERATION'!$C$6*'27_SCENARIOS'!$C$26*'04_GENERATION'!F12*'04_GENERATION'!F13*'04_GENERATION'!F14 -> 0 | G17: ='06_CONSTRUCTION'!G14*'04_GENERATION'!$C$6*'27_SCENARIOS'!$C$26*'04_GENERATION'!G12*'04_GENERATION'!G13*'04_GENERATION'!G14 -> 0 | H17: ='06_CONSTRUCTION'!H14*'04_GENERATION'!$C$6*'27_SCENARIOS'!$C$26*'04_GENERATION'!H12*'04_GENERATION'!H13*'04_GENERATION'!H14 -> 248.60917 | I17: ='06_CONSTRUCTION'!I14*'04_GENERATION'!$C$6*'27_SCENARIOS'!$C$26*'04_GENERATION'!I12*'04_GENERATION'!I13*'04_GENERATION'!I14 -> 292.48138 | J17: ='06_CONSTRUCTION'!J14*'04_GENERATION'!$C$6*'27_SCENARIOS'!$C$26*'04_GENERATION'!J12*'04_GENERATION'!J13*'04_GENERATION'!J14 -> 292.48138 | K17: ='06_CONSTRUCTION'!K14*'04_GENERATION'!$C$6*'27_SCENARIOS'!$C$26*'04_GENERATION'!K12*'04_GENERATION'!K13*'04_GENERATION'!K14 -> 292.48138 | L17: ='06_CONSTRUCTION'!L14*'04_GENERATION'!$C$6*'27_SCENARIOS'!$C$26*'04_GENERATION'!L12*'04_GENERATION'!L13*'04_GENERATION'!L14 -> 292.48138 | ... AR17: ='06_CONSTRUCTION'!AR14*'04_GENERATION'!$C$6*'27_SCENARIOS'!$C$26*'04_GENERATION'!AR12*'04_GENERATION'!AR13*'04_GENERATION'!AR14 -> 0
A18: Énergie évacuable (x taux d'évacuation) | B18: GWh | C18: =SUM('04_GENERATION'!$E$18:$AR$18) -> 7268.1622 | E18: ='04_GENERATION'!E17*'09_GRID'!E17 -> 0 | F18: ='04_GENERATION'!F17*'09_GRID'!F17 -> 0 | G18: ='04_GENERATION'!G17*'09_GRID'!G17 -> 0 | H18: ='04_GENERATION'!H17*'09_GRID'!H17 -> 248.60917 | I18: ='04_GENERATION'!I17*'09_GRID'!I17 -> 292.48138 | J18: ='04_GENERATION'!J17*'09_GRID'!J17 -> 292.48138 | K18: ='04_GENERATION'!K17*'09_GRID'!K17 -> 292.48138 | L18: ='04_GENERATION'!L17*'09_GRID'!L17 -> 292.48138 | ... AR18: ='04_GENERATION'!AR17*'09_GRID'!AR17 -> 0
A19: Écrêtement — transport / réseau | B19: GWh | C19: =SUM('04_GENERATION'!$E$19:$AR$19) -> 0 | E19: ='04_GENERATION'!E17-'04_GENERATION'!E18 -> 0 | F19: ='04_GENERATION'!F17-'04_GENERATION'!F18 -> 0 | G19: ='04_GENERATION'!G17-'04_GENERATION'!G18 -> 0 | H19: ='04_GENERATION'!H17-'04_GENERATION'!H18 -> 0 | I19: ='04_GENERATION'!I17-'04_GENERATION'!I18 -> 0 | J19: ='04_GENERATION'!J17-'04_GENERATION'!J18 -> 0 | K19: ='04_GENERATION'!K17-'04_GENERATION'!K18 -> 0 | L19: ='04_GENERATION'!L17-'04_GENERATION'!L18 -> 0 | ... AR19: ='04_GENERATION'!AR17-'04_GENERATION'!AR18 -> 0
A20: Énergie livrée (absorbée par la demande) | B20: GWh | C20: =SUM('04_GENERATION'!$E$20:$AR$20) -> 7268.1622 | E20: =MIN('04_GENERATION'!E18,'10_DEMAND'!E33) -> 0 | F20: =MIN('04_GENERATION'!F18,'10_DEMAND'!F33) -> 0 | G20: =MIN('04_GENERATION'!G18,'10_DEMAND'!G33) -> 0 | H20: =MIN('04_GENERATION'!H18,'10_DEMAND'!H33) -> 248.60917 | I20: =MIN('04_GENERATION'!I18,'10_DEMAND'!I33) -> 292.48138 | J20: =MIN('04_GENERATION'!J18,'10_DEMAND'!J33) -> 292.48138 | K20: =MIN('04_GENERATION'!K18,'10_DEMAND'!K33) -> 292.48138 | L20: =MIN('04_GENERATION'!L18,'10_DEMAND'!L33) -> 292.48138 | ... AR20: =MIN('04_GENERATION'!AR18,'10_DEMAND'!AR33) -> 0
A21: Écrêtement — demande insuffisante | B21: GWh | C21: =SUM('04_GENERATION'!$E$21:$AR$21) -> 0 | E21: ='04_GENERATION'!E18-'04_GENERATION'!E20 -> 0 | F21: ='04_GENERATION'!F18-'04_GENERATION'!F20 -> 0 | G21: ='04_GENERATION'!G18-'04_GENERATION'!G20 -> 0 | H21: ='04_GENERATION'!H18-'04_GENERATION'!H20 -> 0 | I21: ='04_GENERATION'!I18-'04_GENERATION'!I20 -> 0 | J21: ='04_GENERATION'!J18-'04_GENERATION'!J20 -> 0 | K21: ='04_GENERATION'!K18-'04_GENERATION'!K20 -> 0 | L21: ='04_GENERATION'!L18-'04_GENERATION'!L20 -> 0 | ... AR21: ='04_GENERATION'!AR18-'04_GENERATION'!AR20 -> 0
A22: Énergie contractuelle (référence P50) | B22: GWh | C22: =SUM('04_GENERATION'!$E$22:$AR$22) -> 7268.1622 | E22: ='04_GENERATION'!E16 -> 0 | F22: ='04_GENERATION'!F16 -> 0 | G22: ='04_GENERATION'!G16 -> 0 | H22: ='04_GENERATION'!H16 -> 248.60917 | I22: ='04_GENERATION'!I16 -> 292.48138 | J22: ='04_GENERATION'!J16 -> 292.48138 | K22: ='04_GENERATION'!K16 -> 292.48138 | L22: ='04_GENERATION'!L16 -> 292.48138 | ... AR22: ='04_GENERATION'!AR16 -> 0
A23: Production du cas prêteurs | B23: GWh | C23: =SUM('04_GENERATION'!$E$23:$AR$23) -> 6666.0312 | E23: ='06_CONSTRUCTION'!E14*'04_GENERATION'!$C$7*'27_SCENARIOS'!$C$26*'04_GENERATION'!E13*'04_GENERATION'!E14 -> 0 | F23: ='06_CONSTRUCTION'!F14*'04_GENERATION'!$C$7*'27_SCENARIOS'!$C$26*'04_GENERATION'!F13*'04_GENERATION'!F14 -> 0 | G23: ='06_CONSTRUCTION'!G14*'04_GENERATION'!$C$7*'27_SCENARIOS'!$C$26*'04_GENERATION'!G13*'04_GENERATION'!G14 -> 0 | H23: ='06_CONSTRUCTION'!H14*'04_GENERATION'!$C$7*'27_SCENARIOS'!$C$26*'04_GENERATION'!H13*'04_GENERATION'!H14 -> 228.01314 | I23: ='06_CONSTRUCTION'!I14*'04_GENERATION'!$C$7*'27_SCENARIOS'!$C$26*'04_GENERATION'!I13*'04_GENERATION'!I14 -> 268.25075 | J23: ='06_CONSTRUCTION'!J14*'04_GENERATION'!$C$7*'27_SCENARIOS'!$C$26*'04_GENERATION'!J13*'04_GENERATION'!J14 -> 268.25075 | K23: ='06_CONSTRUCTION'!K14*'04_GENERATION'!$C$7*'27_SCENARIOS'!$C$26*'04_GENERATION'!K13*'04_GENERATION'!K14 -> 268.25075 | L23: ='06_CONSTRUCTION'!L14*'04_GENERATION'!$C$7*'27_SCENARIOS'!$C$26*'04_GENERATION'!L13*'04_GENERATION'!L14 -> 268.25075 | ... AR23: ='06_CONSTRUCTION'!AR14*'04_GENERATION'!$C$7*'27_SCENARIOS'!$C$26*'04_GENERATION'!AR13*'04_GENERATION'!AR14 -> 0
A24: Facteur de charge (cas choisi) | B24: % | E24: =IF('06_CONSTRUCTION'!E14=1,'04_GENERATION'!E17/('02_PROJECT_INPUTS'!$C$15*8.76),0) -> 0 | F24: =IF('06_CONSTRUCTION'!F14=1,'04_GENERATION'!F17/('02_PROJECT_INPUTS'!$C$15*8.76),0) -> 0 | G24: =IF('06_CONSTRUCTION'!G14=1,'04_GENERATION'!G17/('02_PROJECT_INPUTS'!$C$15*8.76),0) -> 0 | H24: =IF('06_CONSTRUCTION'!H14=1,'04_GENERATION'!H17/('02_PROJECT_INPUTS'!$C$15*8.76),0) -> 0.47300071 | I24: =IF('06_CONSTRUCTION'!I14=1,'04_GENERATION'!I17/('02_PROJECT_INPUTS'!$C$15*8.76),0) -> 0.55647142 | J24: =IF('06_CONSTRUCTION'!J14=1,'04_GENERATION'!J17/('02_PROJECT_INPUTS'!$C$15*8.76),0) -> 0.55647142 | K24: =IF('06_CONSTRUCTION'!K14=1,'04_GENERATION'!K17/('02_PROJECT_INPUTS'!$C$15*8.76),0) -> 0.55647142 | L24: =IF('06_CONSTRUCTION'!L14=1,'04_GENERATION'!L17/('02_PROJECT_INPUTS'!$C$15*8.76),0) -> 0.55647142 | ... AR24: =IF('06_CONSTRUCTION'!AR14=1,'04_GENERATION'!AR17/('02_PROJECT_INPUTS'!$C$15*8.76),0) -> 0

Sheet 05_PLANT_CAPEX
A1: 05 CAPEX CENTRALE — USD réels 2026, avant indexation
A2: Estimation fictive ; comparer aux fourchettes de référence (base de sources)
A4: A. VENTILATION DES COÛTS (M USD réels 2026)
A5: Génie civil (seuil, prise d'eau, galerie d'amenée, conduite forcée, centrale) | B5: M USD | C5: 68 | D5: Fictif
A6: Équipements hydromécaniques (vannes, blindage) | B6: M USD | C6: 9 | D6: Fictif
A7: Électromécanique (turbines, alternateurs, poste) | B7: M USD | C7: 33 | D7: Fictif
A8: Environnemental et social (PAR, moyens de subsistance, compensations) | B8: M USD | C8: 5 | D8: Fictif
A9: Ingénierie, supervision, ingénieur du maître d'ouvrage | B9: M USD | C9: 8 | D9: Fictif
A10: Coûts maître d'ouvrage (construction) | B10: M USD | C10: 4 | D10: Fictif
A11: Coûts de développement remboursés au bouclage (de 01A_DEVELOPMENT) | B11: M USD | C11: ='01A_DEVELOPMENT'!$C$12 -> 9
A12: Prime de risque de l'entrepreneur sur génie civil, hydromécanique et électromécanique (de 05A_CONTRACTING) | B12: M USD | C12: =('05_PLANT_CAPEX'!$C$5+'05_PLANT_CAPEX'!$C$6+'05_PLANT_CAPEX'!$C$7)*'05A_CONTRACTING'!$C$7 -> 6.6
A13: Sous-total avant aléas | B13: M USD | C13: =SUM(C5:C12) -> 142.6
A14: Aléas physiques | B14: % | C14: 0.1 | D14: IFC 2015 : provision médiane de 9,8 % du coût total de la centrale (5,4-12,6 %)
A15: CAPEX de base centrale (réel 2026) | B15: M USD | C15: ='05_PLANT_CAPEX'!$C$13*(1+'05_PLANT_CAPEX'!$C$14) -> 156.86
A16: CAPEX unitaire | B16: USD/kW | C16: ='05_PLANT_CAPEX'!$C$15/'02_PROJECT_INPUTS'!$C$15*1000 -> 2614.3333
A17: Surcoût par année de retard (réclamations, coûts du maître d'ouvrage, indexation) | B17: % par an | C17: 0.04 | D17: Hypothèse
A18: Maturité de la faisabilité (1=pré-EF, 2=EF, 3=EF bancable + revue LTA) | B18: 1-3 | C18: 2 | D18: Test GATE 3
A19: B. RÉFÉRENCE (voir research/source_database.md)
A20: CAPEX unitaire de référence — central | B20: USD/kW | C20: 2515 | D20: IRENA RPGC 2024 tableau 6.3 : grande hydro en Afrique, moyenne pondérée 2018-24 = 2 515 (USD 2024/kW) ; fourchette 2 330-3 290 [HY-01, PF-11]. Écart d'année de prix avec 2026 non corrigé
A21: CAPEX unitaire / référence | B21: x | C21: ='05_PLANT_CAPEX'!$C$16/'05_PLANT_CAPEX'!$C$20 -> 1.0394964

Sheet 05A_CONTRACTING
A1: 05A CONTRATS — Qui porte le risque de construction, et à quel prix
A2: Paramètres indicatifs pour comparer les structures ; remplacer par les offres. Le risque géologique reste en général au maître d'ouvrage, quel que soit l'intitulé.
A4: Structure contractuelle (1=EPC clés en main forfaitaire, 2=lots séparés génie civil + électromécanique, 3=multicontrats, intégration par le maître d'ouvrage) | B4: 1-3 | C4: 2
A6: Paramètre | B6: Unité | C6: CHOISI | E6: 1 EPC clés en main | F6: 2 Lots séparés | G6: 3 Multicontrats
A7: Prime de risque de l'entrepreneur sur génie civil, HM et électromécanique | B7: % | C7: =INDEX(E7:G7,'05A_CONTRACTING'!$C$4) -> 0.06 | E7: 0.12 | F7: 0.06 | G7: 0
A8: Part d'un dépassement portée par le MOA | B8: % | C8: =INDEX(E8:G8,'05A_CONTRACTING'!$C$4) -> 0.55 | E8: 0.3 | F8: 0.55 | G8: 0.9
A9: Part du coût de retard portée par le maître d'ouvrage (après pénalités forfaitaires) | B9: % | C9: =INDEX(E9:G9,'05A_CONTRACTING'!$C$4) -> 0.6 | E9: 0.35 | F9: 0.6 | G9: 0.9
A10: Risque d'interface (qualitatif, 1 faible à 3 élevé) | B10: 1-3 | C10: =INDEX(E10:G10,'05A_CONTRACTING'!$C$4) -> 2 | E10: 1 | F10: 2 | G10: 3
A12: L'EPC clés en main achète la certitude de prix et de délai moyennant une prime, mais les conditions géologiques imprévues sont souvent exclues ou plafonnées ; le Livre Émeraude de la FIDIC (2019) répartit le risque du sous-sol au moyen d'un rapport géotechnique de référence. Le multicontrat est moins cher sur le papier et laisse le risque d'interface et de dépassement au maître d'ouvrage.

Sheet 06_CONSTRUCTION
A1: 06 CONSTRUCTION — Calendrier maître, indices d'indexation et de change, phasage du CAPEX
A2: Les indicateurs pilotent toutes les séries
A4: Année civile | E4: ='02_PROJECT_INPUTS'!$C$10+1-1 -> 2027 | F4: ='02_PROJECT_INPUTS'!$C$10+2-1 -> 2028 | G4: ='02_PROJECT_INPUTS'!$C$10+3-1 -> 2029 | H4: ='02_PROJECT_INPUTS'!$C$10+4-1 -> 2030 | I4: ='02_PROJECT_INPUTS'!$C$10+5-1 -> 2031 | J4: ='02_PROJECT_INPUTS'!$C$10+6-1 -> 2032 | K4: ='02_PROJECT_INPUTS'!$C$10+7-1 -> 2033 | L4: ='02_PROJECT_INPUTS'!$C$10+8-1 -> 2034 | M4: ='02_PROJECT_INPUTS'!$C$10+9-1 -> 2035 | N4: ='02_PROJECT_INPUTS'!$C$10+10-1 -> 2036 | O4: ='02_PROJECT_INPUTS'!$C$10+11-1 -> 2037 | P4: ='02_PROJECT_INPUTS'!$C$10+12-1 -> 2038 | Q4: ='02_PROJECT_INPUTS'!$C$10+13-1 -> 2039 | R4: ='02_PROJECT_INPUTS'!$C$10+14-1 -> 2040 | S4: ='02_PROJECT_INPUTS'!$C$10+15-1 -> 2041 | T4: ='02_PROJECT_INPUTS'!$C$10+16-1 -> 2042 | U4: ='02_PROJECT_INPUTS'!$C$10+17-1 -> 2043 | V4: ='02_PROJECT_INPUTS'!$C$10+18-1 -> 2044 | W4: ='02_PROJECT_INPUTS'!$C$10+19-1 -> 2045 | X4: ='02_PROJECT_INPUTS'!$C$10+20-1 -> 2046 | Y4: ='02_PROJECT_INPUTS'!$C$10+21-1 -> 2047 | Z4: ='02_PROJECT_INPUTS'!$C$10+22-1 -> 2048 | AA4: ='02_PROJECT_INPUTS'!$C$10+23-1 -> 2049 | AB4: ='02_PROJECT_INPUTS'!$C$10+24-1 -> 2050 | AC4: ='02_PROJECT_INPUTS'!$C$10+25-1 -> 2051 | AD4: ='02_PROJECT_INPUTS'!$C$10+26-1 -> 2052 | AE4: ='02_PROJECT_INPUTS'!$C$10+27-1 -> 2053 | AF4: ='02_PROJECT_INPUTS'!$C$10+28-1 -> 2054 | AG4: ='02_PROJECT_INPUTS'!$C$10+29-1 -> 2055 | AH4: ='02_PROJECT_INPUTS'!$C$10+30-1 -> 2056 | AI4: ='02_PROJECT_INPUTS'!$C$10+31-1 -> 2057 | AJ4: ='02_PROJECT_INPUTS'!$C$10+32-1 -> 2058 | AK4: ='02_PROJECT_INPUTS'!$C$10+33-1 -> 2059 | AL4: ='02_PROJECT_INPUTS'!$C$10+34-1 -> 2060 | AM4: ='02_PROJECT_INPUTS'!$C$10+35-1 -> 2061 | AN4: ='02_PROJECT_INPUTS'!$C$10+36-1 -> 2062 | AO4: ='02_PROJECT_INPUTS'!$C$10+37-1 -> 2063 | AP4: ='02_PROJECT_INPUTS'!$C$10+38-1 -> 2064 | AQ4: ='02_PROJECT_INPUTS'!$C$10+39-1 -> 2065 | AR4: ='02_PROJECT_INPUTS'!$C$10+40-1 -> 2066
A5: Année d'exploit. | B5: # | E5: =IF('06_CONSTRUCTION'!E14=1,1-'06_CONSTRUCTION'!$C$7,0) -> 0 | F5: =IF('06_CONSTRUCTION'!F14=1,2-'06_CONSTRUCTION'!$C$7,0) -> 0 | G5: =IF('06_CONSTRUCTION'!G14=1,3-'06_CONSTRUCTION'!$C$7,0) -> 0 | H5: =IF('06_CONSTRUCTION'!H14=1,4-'06_CONSTRUCTION'!$C$7,0) -> 1 | I5: =IF('06_CONSTRUCTION'!I14=1,5-'06_CONSTRUCTION'!$C$7,0) -> 2 | J5: =IF('06_CONSTRUCTION'!J14=1,6-'06_CONSTRUCTION'!$C$7,0) -> 3 | K5: =IF('06_CONSTRUCTION'!K14=1,7-'06_CONSTRUCTION'!$C$7,0) -> 4 | L5: =IF('06_CONSTRUCTION'!L14=1,8-'06_CONSTRUCTION'!$C$7,0) -> 5 | M5: =IF('06_CONSTRUCTION'!M14=1,9-'06_CONSTRUCTION'!$C$7,0) -> 6 | N5: =IF('06_CONSTRUCTION'!N14=1,10-'06_CONSTRUCTION'!$C$7,0) -> 7 | O5: =IF('06_CONSTRUCTION'!O14=1,11-'06_CONSTRUCTION'!$C$7,0) -> 8 | P5: =IF('06_CONSTRUCTION'!P14=1,12-'06_CONSTRUCTION'!$C$7,0) -> 9 | Q5: =IF('06_CONSTRUCTION'!Q14=1,13-'06_CONSTRUCTION'!$C$7,0) -> 10 | R5: =IF('06_CONSTRUCTION'!R14=1,14-'06_CONSTRUCTION'!$C$7,0) -> 11 | S5: =IF('06_CONSTRUCTION'!S14=1,15-'06_CONSTRUCTION'!$C$7,0) -> 12 | T5: =IF('06_CONSTRUCTION'!T14=1,16-'06_CONSTRUCTION'!$C$7,0) -> 13 | U5: =IF('06_CONSTRUCTION'!U14=1,17-'06_CONSTRUCTION'!$C$7,0) -> 14 | V5: =IF('06_CONSTRUCTION'!V14=1,18-'06_CONSTRUCTION'!$C$7,0) -> 15 | W5: =IF('06_CONSTRUCTION'!W14=1,19-'06_CONSTRUCTION'!$C$7,0) -> 16 | X5: =IF('06_CONSTRUCTION'!X14=1,20-'06_CONSTRUCTION'!$C$7,0) -> 17 | Y5: =IF('06_CONSTRUCTION'!Y14=1,21-'06_CONSTRUCTION'!$C$7,0) -> 18 | Z5: =IF('06_CONSTRUCTION'!Z14=1,22-'06_CONSTRUCTION'!$C$7,0) -> 19 | AA5: =IF('06_CONSTRUCTION'!AA14=1,23-'06_CONSTRUCTION'!$C$7,0) -> 20 | AB5: =IF('06_CONSTRUCTION'!AB14=1,24-'06_CONSTRUCTION'!$C$7,0) -> 21 | AC5: =IF('06_CONSTRUCTION'!AC14=1,25-'06_CONSTRUCTION'!$C$7,0) -> 22 | AD5: =IF('06_CONSTRUCTION'!AD14=1,26-'06_CONSTRUCTION'!$C$7,0) -> 23 | AE5: =IF('06_CONSTRUCTION'!AE14=1,27-'06_CONSTRUCTION'!$C$7,0) -> 24 | AF5: =IF('06_CONSTRUCTION'!AF14=1,28-'06_CONSTRUCTION'!$C$7,0) -> 25 | AG5: =IF('06_CONSTRUCTION'!AG14=1,29-'06_CONSTRUCTION'!$C$7,0) -> 0 | AH5: =IF('06_CONSTRUCTION'!AH14=1,30-'06_CONSTRUCTION'!$C$7,0) -> 0 | AI5: =IF('06_CONSTRUCTION'!AI14=1,31-'06_CONSTRUCTION'!$C$7,0) -> 0 | AJ5: =IF('06_CONSTRUCTION'!AJ14=1,32-'06_CONSTRUCTION'!$C$7,0) -> 0 | AK5: =IF('06_CONSTRUCTION'!AK14=1,33-'06_CONSTRUCTION'!$C$7,0) -> 0 | AL5: =IF('06_CONSTRUCTION'!AL14=1,34-'06_CONSTRUCTION'!$C$7,0) -> 0 | AM5: =IF('06_CONSTRUCTION'!AM14=1,35-'06_CONSTRUCTION'!$C$7,0) -> 0 | AN5: =IF('06_CONSTRUCTION'!AN14=1,36-'06_CONSTRUCTION'!$C$7,0) -> 0 | AO5: =IF('06_CONSTRUCTION'!AO14=1,37-'06_CONSTRUCTION'!$C$7,0) -> 0 | AP5: =IF('06_CONSTRUCTION'!AP14=1,38-'06_CONSTRUCTION'!$C$7,0) -> 0 | AQ5: =IF('06_CONSTRUCTION'!AQ14=1,39-'06_CONSTRUCTION'!$C$7,0) -> 0 | AR5: =IF('06_CONSTRUCTION'!AR14=1,40-'06_CONSTRUCTION'!$C$7,0) -> 0
A7: Durée effective de construction | B7: ans | C7: ='02_PROJECT_INPUTS'!$C$12+'27_SCENARIOS'!$C$28 -> 3
A8: Date de mise en service commerciale (1re année pleine) | B8: année | C8: ='02_PROJECT_INPUTS'!$C$10+'06_CONSTRUCTION'!$C$7 -> 2030
A9: CAPEX centrale (réel 2026), y c. cas, dépassement et coûts de retard | B9: M USD | C9: ='05_PLANT_CAPEX'!$C$15*'27_SCENARIOS'!$C$27*(1+'05_PLANT_CAPEX'!$C$17*'27_SCENARIOS'!$C$28*'05A_CONTRACTING'!$C$9) -> 156.86
A11: INDICATEURS
A12: Indice de période t | B12: # | E12: =1 -> 1 | F12: =2 -> 2 | G12: =3 -> 3 | H12: =4 -> 4 | I12: =5 -> 5 | J12: =6 -> 6 | K12: =7 -> 7 | L12: =8 -> 8 | M12: =9 -> 9 | N12: =10 -> 10 | O12: =11 -> 11 | P12: =12 -> 12 | Q12: =13 -> 13 | R12: =14 -> 14 | S12: =15 -> 15 | T12: =16 -> 16 | U12: =17 -> 17 | V12: =18 -> 18 | W12: =19 -> 19 | X12: =20 -> 20 | Y12: =21 -> 21 | Z12: =22 -> 22 | AA12: =23 -> 23 | AB12: =24 -> 24 | AC12: =25 -> 25 | AD12: =26 -> 26 | AE12: =27 -> 27 | AF12: =28 -> 28 | AG12: =29 -> 29 | AH12: =30 -> 30 | AI12: =31 -> 31 | AJ12: =32 -> 32 | AK12: =33 -> 33 | AL12: =34 -> 34 | AM12: =35 -> 35 | AN12: =36 -> 36 | AO12: =37 -> 37 | AP12: =38 -> 38 | AQ12: =39 -> 39 | AR12: =40 -> 40
A13: Indic. construction | B13: indic. | E13: =IF(1<='06_CONSTRUCTION'!$C$7,1,0) -> 1 | F13: =IF(2<='06_CONSTRUCTION'!$C$7,1,0) -> 1 | G13: =IF(3<='06_CONSTRUCTION'!$C$7,1,0) -> 1 | H13: =IF(4<='06_CONSTRUCTION'!$C$7,1,0) -> 0 | I13: =IF(5<='06_CONSTRUCTION'!$C$7,1,0) -> 0 | J13: =IF(6<='06_CONSTRUCTION'!$C$7,1,0) -> 0 | K13: =IF(7<='06_CONSTRUCTION'!$C$7,1,0) -> 0 | L13: =IF(8<='06_CONSTRUCTION'!$C$7,1,0) -> 0 | M13: =IF(9<='06_CONSTRUCTION'!$C$7,1,0) -> 0 | N13: =IF(10<='06_CONSTRUCTION'!$C$7,1,0) -> 0 | O13: =IF(11<='06_CONSTRUCTION'!$C$7,1,0) -> 0 | P13: =IF(12<='06_CONSTRUCTION'!$C$7,1,0) -> 0 | Q13: =IF(13<='06_CONSTRUCTION'!$C$7,1,0) -> 0 | R13: =IF(14<='06_CONSTRUCTION'!$C$7,1,0) -> 0 | S13: =IF(15<='06_CONSTRUCTION'!$C$7,1,0) -> 0 | T13: =IF(16<='06_CONSTRUCTION'!$C$7,1,0) -> 0 | U13: =IF(17<='06_CONSTRUCTION'!$C$7,1,0) -> 0 | V13: =IF(18<='06_CONSTRUCTION'!$C$7,1,0) -> 0 | W13: =IF(19<='06_CONSTRUCTION'!$C$7,1,0) -> 0 | X13: =IF(20<='06_CONSTRUCTION'!$C$7,1,0) -> 0 | Y13: =IF(21<='06_CONSTRUCTION'!$C$7,1,0) -> 0 | Z13: =IF(22<='06_CONSTRUCTION'!$C$7,1,0) -> 0 | AA13: =IF(23<='06_CONSTRUCTION'!$C$7,1,0) -> 0 | AB13: =IF(24<='06_CONSTRUCTION'!$C$7,1,0) -> 0 | AC13: =IF(25<='06_CONSTRUCTION'!$C$7,1,0) -> 0 | AD13: =IF(26<='06_CONSTRUCTION'!$C$7,1,0) -> 0 | AE13: =IF(27<='06_CONSTRUCTION'!$C$7,1,0) -> 0 | AF13: =IF(28<='06_CONSTRUCTION'!$C$7,1,0) -> 0 | AG13: =IF(29<='06_CONSTRUCTION'!$C$7,1,0) -> 0 | AH13: =IF(30<='06_CONSTRUCTION'!$C$7,1,0) -> 0 | AI13: =IF(31<='06_CONSTRUCTION'!$C$7,1,0) -> 0 | AJ13: =IF(32<='06_CONSTRUCTION'!$C$7,1,0) -> 0 | AK13: =IF(33<='06_CONSTRUCTION'!$C$7,1,0) -> 0 | AL13: =IF(34<='06_CONSTRUCTION'!$C$7,1,0) -> 0 | AM13: =IF(35<='06_CONSTRUCTION'!$C$7,1,0) -> 0 | AN13: =IF(36<='06_CONSTRUCTION'!$C$7,1,0) -> 0 | AO13: =IF(37<='06_CONSTRUCTION'!$C$7,1,0) -> 0 | AP13: =IF(38<='06_CONSTRUCTION'!$C$7,1,0) -> 0 | AQ13: =IF(39<='06_CONSTRUCTION'!$C$7,1,0) -> 0 | AR13: =IF(40<='06_CONSTRUCTION'!$C$7,1,0) -> 0
A14: Indic. exploitation | B14: indic. | C14: =SUM('06_CONSTRUCTION'!$E$14:$AR$14) -> 25 | E14: =IF(AND(1>'06_CONSTRUCTION'!$C$7,1<='06_CONSTRUCTION'!$C$7+'02_PROJECT_INPUTS'!$C$13),1,0) -> 0 | F14: =IF(AND(2>'06_CONSTRUCTION'!$C$7,2<='06_CONSTRUCTION'!$C$7+'02_PROJECT_INPUTS'!$C$13),1,0) -> 0 | G14: =IF(AND(3>'06_CONSTRUCTION'!$C$7,3<='06_CONSTRUCTION'!$C$7+'02_PROJECT_INPUTS'!$C$13),1,0) -> 0 | H14: =IF(AND(4>'06_CONSTRUCTION'!$C$7,4<='06_CONSTRUCTION'!$C$7+'02_PROJECT_INPUTS'!$C$13),1,0) -> 1 | I14: =IF(AND(5>'06_CONSTRUCTION'!$C$7,5<='06_CONSTRUCTION'!$C$7+'02_PROJECT_INPUTS'!$C$13),1,0) -> 1 | J14: =IF(AND(6>'06_CONSTRUCTION'!$C$7,6<='06_CONSTRUCTION'!$C$7+'02_PROJECT_INPUTS'!$C$13),1,0) -> 1 | K14: =IF(AND(7>'06_CONSTRUCTION'!$C$7,7<='06_CONSTRUCTION'!$C$7+'02_PROJECT_INPUTS'!$C$13),1,0) -> 1 | L14: =IF(AND(8>'06_CONSTRUCTION'!$C$7,8<='06_CONSTRUCTION'!$C$7+'02_PROJECT_INPUTS'!$C$13),1,0) -> 1 | M14: =IF(AND(9>'06_CONSTRUCTION'!$C$7,9<='06_CONSTRUCTION'!$C$7+'02_PROJECT_INPUTS'!$C$13),1,0) -> 1 | N14: =IF(AND(10>'06_CONSTRUCTION'!$C$7,10<='06_CONSTRUCTION'!$C$7+'02_PROJECT_INPUTS'!$C$13),1,0) -> 1 | O14: =IF(AND(11>'06_CONSTRUCTION'!$C$7,11<='06_CONSTRUCTION'!$C$7+'02_PROJECT_INPUTS'!$C$13),1,0) -> 1 | P14: =IF(AND(12>'06_CONSTRUCTION'!$C$7,12<='06_CONSTRUCTION'!$C$7+'02_PROJECT_INPUTS'!$C$13),1,0) -> 1 | Q14: =IF(AND(13>'06_CONSTRUCTION'!$C$7,13<='06_CONSTRUCTION'!$C$7+'02_PROJECT_INPUTS'!$C$13),1,0) -> 1 | R14: =IF(AND(14>'06_CONSTRUCTION'!$C$7,14<='06_CONSTRUCTION'!$C$7+'02_PROJECT_INPUTS'!$C$13),1,0) -> 1 | S14: =IF(AND(15>'06_CONSTRUCTION'!$C$7,15<='06_CONSTRUCTION'!$C$7+'02_PROJECT_INPUTS'!$C$13),1,0) -> 1 | T14: =IF(AND(16>'06_CONSTRUCTION'!$C$7,16<='06_CONSTRUCTION'!$C$7+'02_PROJECT_INPUTS'!$C$13),1,0) -> 1 | U14: =IF(AND(17>'06_CONSTRUCTION'!$C$7,17<='06_CONSTRUCTION'!$C$7+'02_PROJECT_INPUTS'!$C$13),1,0) -> 1 | V14: =IF(AND(18>'06_CONSTRUCTION'!$C$7,18<='06_CONSTRUCTION'!$C$7+'02_PROJECT_INPUTS'!$C$13),1,0) -> 1 | W14: =IF(AND(19>'06_CONSTRUCTION'!$C$7,19<='06_CONSTRUCTION'!$C$7+'02_PROJECT_INPUTS'!$C$13),1,0) -> 1 | X14: =IF(AND(20>'06_CONSTRUCTION'!$C$7,20<='06_CONSTRUCTION'!$C$7+'02_PROJECT_INPUTS'!$C$13),1,0) -> 1 | Y14: =IF(AND(21>'06_CONSTRUCTION'!$C$7,21<='06_CONSTRUCTION'!$C$7+'02_PROJECT_INPUTS'!$C$13),1,0) -> 1 | Z14: =IF(AND(22>'06_CONSTRUCTION'!$C$7,22<='06_CONSTRUCTION'!$C$7+'02_PROJECT_INPUTS'!$C$13),1,0) -> 1 | AA14: =IF(AND(23>'06_CONSTRUCTION'!$C$7,23<='06_CONSTRUCTION'!$C$7+'02_PROJECT_INPUTS'!$C$13),1,0) -> 1 | AB14: =IF(AND(24>'06_CONSTRUCTION'!$C$7,24<='06_CONSTRUCTION'!$C$7+'02_PROJECT_INPUTS'!$C$13),1,0) -> 1 | AC14: =IF(AND(25>'06_CONSTRUCTION'!$C$7,25<='06_CONSTRUCTION'!$C$7+'02_PROJECT_INPUTS'!$C$13),1,0) -> 1 | AD14: =IF(AND(26>'06_CONSTRUCTION'!$C$7,26<='06_CONSTRUCTION'!$C$7+'02_PROJECT_INPUTS'!$C$13),1,0) -> 1 | AE14: =IF(AND(27>'06_CONSTRUCTION'!$C$7,27<='06_CONSTRUCTION'!$C$7+'02_PROJECT_INPUTS'!$C$13),1,0) -> 1 | AF14: =IF(AND(28>'06_CONSTRUCTION'!$C$7,28<='06_CONSTRUCTION'!$C$7+'02_PROJECT_INPUTS'!$C$13),1,0) -> 1 | AG14: =IF(AND(29>'06_CONSTRUCTION'!$C$7,29<='06_CONSTRUCTION'!$C$7+'02_PROJECT_INPUTS'!$C$13),1,0) -> 0 | AH14: =IF(AND(30>'06_CONSTRUCTION'!$C$7,30<='06_CONSTRUCTION'!$C$7+'02_PROJECT_INPUTS'!$C$13),1,0) -> 0 | AI14: =IF(AND(31>'06_CONSTRUCTION'!$C$7,31<='06_CONSTRUCTION'!$C$7+'02_PROJECT_INPUTS'!$C$13),1,0) -> 0 | AJ14: =IF(AND(32>'06_CONSTRUCTION'!$C$7,32<='06_CONSTRUCTION'!$C$7+'02_PROJECT_INPUTS'!$C$13),1,0) -> 0 | AK14: =IF(AND(33>'06_CONSTRUCTION'!$C$7,33<='06_CONSTRUCTION'!$C$7+'02_PROJECT_INPUTS'!$C$13),1,0) -> 0 | AL14: =IF(AND(34>'06_CONSTRUCTION'!$C$7,34<='06_CONSTRUCTION'!$C$7+'02_PROJECT_INPUTS'!$C$13),1,0) -> 0 | AM14: =IF(AND(35>'06_CONSTRUCTION'!$C$7,35<='06_CONSTRUCTION'!$C$7+'02_PROJECT_INPUTS'!$C$13),1,0) -> 0 | AN14: =IF(AND(36>'06_CONSTRUCTION'!$C$7,36<='06_CONSTRUCTION'!$C$7+'02_PROJECT_INPUTS'!$C$13),1,0) -> 0 | AO14: =IF(AND(37>'06_CONSTRUCTION'!$C$7,37<='06_CONSTRUCTION'!$C$7+'02_PROJECT_INPUTS'!$C$13),1,0) -> 0 | AP14: =IF(AND(38>'06_CONSTRUCTION'!$C$7,38<='06_CONSTRUCTION'!$C$7+'02_PROJECT_INPUTS'!$C$13),1,0) -> 0 | AQ14: =IF(AND(39>'06_CONSTRUCTION'!$C$7,39<='06_CONSTRUCTION'!$C$7+'02_PROJECT_INPUTS'!$C$13),1,0) -> 0 | AR14: =IF(AND(40>'06_CONSTRUCTION'!$C$7,40<='06_CONSTRUCTION'!$C$7+'02_PROJECT_INPUTS'!$C$13),1,0) -> 0
A15: Indic. dernière année constr. | B15: indic. | E15: =IF(1='06_CONSTRUCTION'!$C$7,1,0) -> 0 | F15: =IF(2='06_CONSTRUCTION'!$C$7,1,0) -> 0 | G15: =IF(3='06_CONSTRUCTION'!$C$7,1,0) -> 1 | H15: =IF(4='06_CONSTRUCTION'!$C$7,1,0) -> 0 | I15: =IF(5='06_CONSTRUCTION'!$C$7,1,0) -> 0 | J15: =IF(6='06_CONSTRUCTION'!$C$7,1,0) -> 0 | K15: =IF(7='06_CONSTRUCTION'!$C$7,1,0) -> 0 | L15: =IF(8='06_CONSTRUCTION'!$C$7,1,0) -> 0 | M15: =IF(9='06_CONSTRUCTION'!$C$7,1,0) -> 0 | N15: =IF(10='06_CONSTRUCTION'!$C$7,1,0) -> 0 | O15: =IF(11='06_CONSTRUCTION'!$C$7,1,0) -> 0 | P15: =IF(12='06_CONSTRUCTION'!$C$7,1,0) -> 0 | Q15: =IF(13='06_CONSTRUCTION'!$C$7,1,0) -> 0 | R15: =IF(14='06_CONSTRUCTION'!$C$7,1,0) -> 0 | S15: =IF(15='06_CONSTRUCTION'!$C$7,1,0) -> 0 | T15: =IF(16='06_CONSTRUCTION'!$C$7,1,0) -> 0 | U15: =IF(17='06_CONSTRUCTION'!$C$7,1,0) -> 0 | V15: =IF(18='06_CONSTRUCTION'!$C$7,1,0) -> 0 | W15: =IF(19='06_CONSTRUCTION'!$C$7,1,0) -> 0 | X15: =IF(20='06_CONSTRUCTION'!$C$7,1,0) -> 0 | Y15: =IF(21='06_CONSTRUCTION'!$C$7,1,0) -> 0 | Z15: =IF(22='06_CONSTRUCTION'!$C$7,1,0) -> 0 | AA15: =IF(23='06_CONSTRUCTION'!$C$7,1,0) -> 0 | AB15: =IF(24='06_CONSTRUCTION'!$C$7,1,0) -> 0 | AC15: =IF(25='06_CONSTRUCTION'!$C$7,1,0) -> 0 | AD15: =IF(26='06_CONSTRUCTION'!$C$7,1,0) -> 0 | AE15: =IF(27='06_CONSTRUCTION'!$C$7,1,0) -> 0 | AF15: =IF(28='06_CONSTRUCTION'!$C$7,1,0) -> 0 | AG15: =IF(29='06_CONSTRUCTION'!$C$7,1,0) -> 0 | AH15: =IF(30='06_CONSTRUCTION'!$C$7,1,0) -> 0 | AI15: =IF(31='06_CONSTRUCTION'!$C$7,1,0) -> 0 | AJ15: =IF(32='06_CONSTRUCTION'!$C$7,1,0) -> 0 | AK15: =IF(33='06_CONSTRUCTION'!$C$7,1,0) -> 0 | AL15: =IF(34='06_CONSTRUCTION'!$C$7,1,0) -> 0 | AM15: =IF(35='06_CONSTRUCTION'!$C$7,1,0) -> 0 | AN15: =IF(36='06_CONSTRUCTION'!$C$7,1,0) -> 0 | AO15: =IF(37='06_CONSTRUCTION'!$C$7,1,0) -> 0 | AP15: =IF(38='06_CONSTRUCTION'!$C$7,1,0) -> 0 | AQ15: =IF(39='06_CONSTRUCTION'!$C$7,1,0) -> 0 | AR15: =IF(40='06_CONSTRUCTION'!$C$7,1,0) -> 0
A16: INDICES
A17: Indice IPC US (2026 = 1) | B17: x | E17: =(1+'02_PROJECT_INPUTS'!$C$18)^('06_CONSTRUCTION'!E4-'02_PROJECT_INPUTS'!$C$11) -> 1.02 | F17: =(1+'02_PROJECT_INPUTS'!$C$18)^('06_CONSTRUCTION'!F4-'02_PROJECT_INPUTS'!$C$11) -> 1.0404 | G17: =(1+'02_PROJECT_INPUTS'!$C$18)^('06_CONSTRUCTION'!G4-'02_PROJECT_INPUTS'!$C$11) -> 1.061208 | H17: =(1+'02_PROJECT_INPUTS'!$C$18)^('06_CONSTRUCTION'!H4-'02_PROJECT_INPUTS'!$C$11) -> 1.0824322 | I17: =(1+'02_PROJECT_INPUTS'!$C$18)^('06_CONSTRUCTION'!I4-'02_PROJECT_INPUTS'!$C$11) -> 1.1040808 | J17: =(1+'02_PROJECT_INPUTS'!$C$18)^('06_CONSTRUCTION'!J4-'02_PROJECT_INPUTS'!$C$11) -> 1.1261624 | K17: =(1+'02_PROJECT_INPUTS'!$C$18)^('06_CONSTRUCTION'!K4-'02_PROJECT_INPUTS'!$C$11) -> 1.1486857 | L17: =(1+'02_PROJECT_INPUTS'!$C$18)^('06_CONSTRUCTION'!L4-'02_PROJECT_INPUTS'!$C$11) -> 1.1716594 | ... AR17: =(1+'02_PROJECT_INPUTS'!$C$18)^('06_CONSTRUCTION'!AR4-'02_PROJECT_INPUTS'!$C$11) -> 2.2080397
A18: Indice IPC local (2026 = 1) | B18: x | E18: =(1+'02_PROJECT_INPUTS'!$C$19)^('06_CONSTRUCTION'!E4-'02_PROJECT_INPUTS'!$C$11) -> 1.08 | F18: =(1+'02_PROJECT_INPUTS'!$C$19)^('06_CONSTRUCTION'!F4-'02_PROJECT_INPUTS'!$C$11) -> 1.1664 | G18: =(1+'02_PROJECT_INPUTS'!$C$19)^('06_CONSTRUCTION'!G4-'02_PROJECT_INPUTS'!$C$11) -> 1.259712 | H18: =(1+'02_PROJECT_INPUTS'!$C$19)^('06_CONSTRUCTION'!H4-'02_PROJECT_INPUTS'!$C$11) -> 1.360489 | I18: =(1+'02_PROJECT_INPUTS'!$C$19)^('06_CONSTRUCTION'!I4-'02_PROJECT_INPUTS'!$C$11) -> 1.4693281 | J18: =(1+'02_PROJECT_INPUTS'!$C$19)^('06_CONSTRUCTION'!J4-'02_PROJECT_INPUTS'!$C$11) -> 1.5868743 | K18: =(1+'02_PROJECT_INPUTS'!$C$19)^('06_CONSTRUCTION'!K4-'02_PROJECT_INPUTS'!$C$11) -> 1.7138243 | L18: =(1+'02_PROJECT_INPUTS'!$C$19)^('06_CONSTRUCTION'!L4-'02_PROJECT_INPUTS'!$C$11) -> 1.8509302 | ... AR18: =(1+'02_PROJECT_INPUTS'!$C$19)^('06_CONSTRUCTION'!AR4-'02_PROJECT_INPUTS'!$C$11) -> 21.724521
A19: Taux de change | B19: NVL/USD | E19: ='02_PROJECT_INPUTS'!$C$20*(1+'27_SCENARIOS'!$C$34)^('06_CONSTRUCTION'!E4-'02_PROJECT_INPUTS'!$C$11)*IF('06_CONSTRUCTION'!E4>='06_CONSTRUCTION'!$C$8,1+'27_SCENARIOS'!$C$35,1) -> 21.2 | F19: ='02_PROJECT_INPUTS'!$C$20*(1+'27_SCENARIOS'!$C$34)^('06_CONSTRUCTION'!F4-'02_PROJECT_INPUTS'!$C$11)*IF('06_CONSTRUCTION'!F4>='06_CONSTRUCTION'!$C$8,1+'27_SCENARIOS'!$C$35,1) -> 22.472 | G19: ='02_PROJECT_INPUTS'!$C$20*(1+'27_SCENARIOS'!$C$34)^('06_CONSTRUCTION'!G4-'02_PROJECT_INPUTS'!$C$11)*IF('06_CONSTRUCTION'!G4>='06_CONSTRUCTION'!$C$8,1+'27_SCENARIOS'!$C$35,1) -> 23.82032 | H19: ='02_PROJECT_INPUTS'!$C$20*(1+'27_SCENARIOS'!$C$34)^('06_CONSTRUCTION'!H4-'02_PROJECT_INPUTS'!$C$11)*IF('06_CONSTRUCTION'!H4>='06_CONSTRUCTION'!$C$8,1+'27_SCENARIOS'!$C$35,1) -> 25.249539 | I19: ='02_PROJECT_INPUTS'!$C$20*(1+'27_SCENARIOS'!$C$34)^('06_CONSTRUCTION'!I4-'02_PROJECT_INPUTS'!$C$11)*IF('06_CONSTRUCTION'!I4>='06_CONSTRUCTION'!$C$8,1+'27_SCENARIOS'!$C$35,1) -> 26.764512 | J19: ='02_PROJECT_INPUTS'!$C$20*(1+'27_SCENARIOS'!$C$34)^('06_CONSTRUCTION'!J4-'02_PROJECT_INPUTS'!$C$11)*IF('06_CONSTRUCTION'!J4>='06_CONSTRUCTION'!$C$8,1+'27_SCENARIOS'!$C$35,1) -> 28.370382 | K19: ='02_PROJECT_INPUTS'!$C$20*(1+'27_SCENARIOS'!$C$34)^('06_CONSTRUCTION'!K4-'02_PROJECT_INPUTS'!$C$11)*IF('06_CONSTRUCTION'!K4>='06_CONSTRUCTION'!$C$8,1+'27_SCENARIOS'!$C$35,1) -> 30.072605 | L19: ='02_PROJECT_INPUTS'!$C$20*(1+'27_SCENARIOS'!$C$34)^('06_CONSTRUCTION'!L4-'02_PROJECT_INPUTS'!$C$11)*IF('06_CONSTRUCTION'!L4>='06_CONSTRUCTION'!$C$8,1+'27_SCENARIOS'!$C$35,1) -> 31.876961 | ... AR19: ='02_PROJECT_INPUTS'!$C$20*(1+'27_SCENARIOS'!$C$34)^('06_CONSTRUCTION'!AR4-'02_PROJECT_INPUTS'!$C$11)*IF('06_CONSTRUCTION'!AR4>='06_CONSTRUCTION'!$C$8,1+'27_SCENARIOS'!$C$35,1) -> 205.71436
A20: Indice de change (2026 = 1) | B20: x | E20: ='06_CONSTRUCTION'!E19/'02_PROJECT_INPUTS'!$C$20 -> 1.06 | F20: ='06_CONSTRUCTION'!F19/'02_PROJECT_INPUTS'!$C$20 -> 1.1236 | G20: ='06_CONSTRUCTION'!G19/'02_PROJECT_INPUTS'!$C$20 -> 1.191016 | H20: ='06_CONSTRUCTION'!H19/'02_PROJECT_INPUTS'!$C$20 -> 1.262477 | I20: ='06_CONSTRUCTION'!I19/'02_PROJECT_INPUTS'!$C$20 -> 1.3382256 | J20: ='06_CONSTRUCTION'!J19/'02_PROJECT_INPUTS'!$C$20 -> 1.4185191 | K20: ='06_CONSTRUCTION'!K19/'02_PROJECT_INPUTS'!$C$20 -> 1.5036303 | L20: ='06_CONSTRUCTION'!L19/'02_PROJECT_INPUTS'!$C$20 -> 1.5938481 | ... AR20: ='06_CONSTRUCTION'!AR19/'02_PROJECT_INPUTS'!$C$20 -> 10.285718
A21: Indice d'indexation du CAPEX | B21: x | E21: =(1+'02_PROJECT_INPUTS'!$C$22)^('06_CONSTRUCTION'!E4-'02_PROJECT_INPUTS'!$C$11) -> 1.025 | F21: =(1+'02_PROJECT_INPUTS'!$C$22)^('06_CONSTRUCTION'!F4-'02_PROJECT_INPUTS'!$C$11) -> 1.050625 | G21: =(1+'02_PROJECT_INPUTS'!$C$22)^('06_CONSTRUCTION'!G4-'02_PROJECT_INPUTS'!$C$11) -> 1.0768906 | H21: =(1+'02_PROJECT_INPUTS'!$C$22)^('06_CONSTRUCTION'!H4-'02_PROJECT_INPUTS'!$C$11) -> 1.1038129 | I21: =(1+'02_PROJECT_INPUTS'!$C$22)^('06_CONSTRUCTION'!I4-'02_PROJECT_INPUTS'!$C$11) -> 1.1314082 | J21: =(1+'02_PROJECT_INPUTS'!$C$22)^('06_CONSTRUCTION'!J4-'02_PROJECT_INPUTS'!$C$11) -> 1.1596934 | K21: =(1+'02_PROJECT_INPUTS'!$C$22)^('06_CONSTRUCTION'!K4-'02_PROJECT_INPUTS'!$C$11) -> 1.1886858 | L21: =(1+'02_PROJECT_INPUTS'!$C$22)^('06_CONSTRUCTION'!L4-'02_PROJECT_INPUTS'!$C$11) -> 1.2184029 | ... AR21: =(1+'02_PROJECT_INPUTS'!$C$22)^('06_CONSTRUCTION'!AR4-'02_PROJECT_INPUTS'!$C$11) -> 2.6850638
A22: PHASAGE DU CAPEX CENTRALE (courbe en S sinusoïdale sur la durée effective)
A23: Part du CAPEX (somme = 100 %) | B23: % | C23: =SUM('06_CONSTRUCTION'!$E$23:$AR$23) -> 1 | E23: =IF('06_CONSTRUCTION'!E13=1,SIN(PI()*(1-0.5)/'06_CONSTRUCTION'!$C$7)*SIN(PI()/(2*'06_CONSTRUCTION'!$C$7)),0) -> 0.25 | F23: =IF('06_CONSTRUCTION'!F13=1,SIN(PI()*(2-0.5)/'06_CONSTRUCTION'!$C$7)*SIN(PI()/(2*'06_CONSTRUCTION'!$C$7)),0) -> 0.5 | G23: =IF('06_CONSTRUCTION'!G13=1,SIN(PI()*(3-0.5)/'06_CONSTRUCTION'!$C$7)*SIN(PI()/(2*'06_CONSTRUCTION'!$C$7)),0) -> 0.25 | H23: =IF('06_CONSTRUCTION'!H13=1,SIN(PI()*(4-0.5)/'06_CONSTRUCTION'!$C$7)*SIN(PI()/(2*'06_CONSTRUCTION'!$C$7)),0) -> 0 | I23: =IF('06_CONSTRUCTION'!I13=1,SIN(PI()*(5-0.5)/'06_CONSTRUCTION'!$C$7)*SIN(PI()/(2*'06_CONSTRUCTION'!$C$7)),0) -> 0 | J23: =IF('06_CONSTRUCTION'!J13=1,SIN(PI()*(6-0.5)/'06_CONSTRUCTION'!$C$7)*SIN(PI()/(2*'06_CONSTRUCTION'!$C$7)),0) -> 0 | K23: =IF('06_CONSTRUCTION'!K13=1,SIN(PI()*(7-0.5)/'06_CONSTRUCTION'!$C$7)*SIN(PI()/(2*'06_CONSTRUCTION'!$C$7)),0) -> 0 | L23: =IF('06_CONSTRUCTION'!L13=1,SIN(PI()*(8-0.5)/'06_CONSTRUCTION'!$C$7)*SIN(PI()/(2*'06_CONSTRUCTION'!$C$7)),0) -> 0 | M23: =IF('06_CONSTRUCTION'!M13=1,SIN(PI()*(9-0.5)/'06_CONSTRUCTION'!$C$7)*SIN(PI()/(2*'06_CONSTRUCTION'!$C$7)),0) -> 0 | N23: =IF('06_CONSTRUCTION'!N13=1,SIN(PI()*(10-0.5)/'06_CONSTRUCTION'!$C$7)*SIN(PI()/(2*'06_CONSTRUCTION'!$C$7)),0) -> 0 | O23: =IF('06_CONSTRUCTION'!O13=1,SIN(PI()*(11-0.5)/'06_CONSTRUCTION'!$C$7)*SIN(PI()/(2*'06_CONSTRUCTION'!$C$7)),0) -> 0 | P23: =IF('06_CONSTRUCTION'!P13=1,SIN(PI()*(12-0.5)/'06_CONSTRUCTION'!$C$7)*SIN(PI()/(2*'06_CONSTRUCTION'!$C$7)),0) -> 0 | Q23: =IF('06_CONSTRUCTION'!Q13=1,SIN(PI()*(13-0.5)/'06_CONSTRUCTION'!$C$7)*SIN(PI()/(2*'06_CONSTRUCTION'!$C$7)),0) -> 0 | R23: =IF('06_CONSTRUCTION'!R13=1,SIN(PI()*(14-0.5)/'06_CONSTRUCTION'!$C$7)*SIN(PI()/(2*'06_CONSTRUCTION'!$C$7)),0) -> 0 | S23: =IF('06_CONSTRUCTION'!S13=1,SIN(PI()*(15-0.5)/'06_CONSTRUCTION'!$C$7)*SIN(PI()/(2*'06_CONSTRUCTION'!$C$7)),0) -> 0 | T23: =IF('06_CONSTRUCTION'!T13=1,SIN(PI()*(16-0.5)/'06_CONSTRUCTION'!$C$7)*SIN(PI()/(2*'06_CONSTRUCTION'!$C$7)),0) -> 0 | U23: =IF('06_CONSTRUCTION'!U13=1,SIN(PI()*(17-0.5)/'06_CONSTRUCTION'!$C$7)*SIN(PI()/(2*'06_CONSTRUCTION'!$C$7)),0) -> 0 | V23: =IF('06_CONSTRUCTION'!V13=1,SIN(PI()*(18-0.5)/'06_CONSTRUCTION'!$C$7)*SIN(PI()/(2*'06_CONSTRUCTION'!$C$7)),0) -> 0 | W23: =IF('06_CONSTRUCTION'!W13=1,SIN(PI()*(19-0.5)/'06_CONSTRUCTION'!$C$7)*SIN(PI()/(2*'06_CONSTRUCTION'!$C$7)),0) -> 0 | X23: =IF('06_CONSTRUCTION'!X13=1,SIN(PI()*(20-0.5)/'06_CONSTRUCTION'!$C$7)*SIN(PI()/(2*'06_CONSTRUCTION'!$C$7)),0) -> 0 | Y23: =IF('06_CONSTRUCTION'!Y13=1,SIN(PI()*(21-0.5)/'06_CONSTRUCTION'!$C$7)*SIN(PI()/(2*'06_CONSTRUCTION'!$C$7)),0) -> 0 | Z23: =IF('06_CONSTRUCTION'!Z13=1,SIN(PI()*(22-0.5)/'06_CONSTRUCTION'!$C$7)*SIN(PI()/(2*'06_CONSTRUCTION'!$C$7)),0) -> 0 | AA23: =IF('06_CONSTRUCTION'!AA13=1,SIN(PI()*(23-0.5)/'06_CONSTRUCTION'!$C$7)*SIN(PI()/(2*'06_CONSTRUCTION'!$C$7)),0) -> 0 | AB23: =IF('06_CONSTRUCTION'!AB13=1,SIN(PI()*(24-0.5)/'06_CONSTRUCTION'!$C$7)*SIN(PI()/(2*'06_CONSTRUCTION'!$C$7)),0) -> 0 | AC23: =IF('06_CONSTRUCTION'!AC13=1,SIN(PI()*(25-0.5)/'06_CONSTRUCTION'!$C$7)*SIN(PI()/(2*'06_CONSTRUCTION'!$C$7)),0) -> 0 | AD23: =IF('06_CONSTRUCTION'!AD13=1,SIN(PI()*(26-0.5)/'06_CONSTRUCTION'!$C$7)*SIN(PI()/(2*'06_CONSTRUCTION'!$C$7)),0) -> 0 | AE23: =IF('06_CONSTRUCTION'!AE13=1,SIN(PI()*(27-0.5)/'06_CONSTRUCTION'!$C$7)*SIN(PI()/(2*'06_CONSTRUCTION'!$C$7)),0) -> 0 | AF23: =IF('06_CONSTRUCTION'!AF13=1,SIN(PI()*(28-0.5)/'06_CONSTRUCTION'!$C$7)*SIN(PI()/(2*'06_CONSTRUCTION'!$C$7)),0) -> 0 | AG23: =IF('06_CONSTRUCTION'!AG13=1,SIN(PI()*(29-0.5)/'06_CONSTRUCTION'!$C$7)*SIN(PI()/(2*'06_CONSTRUCTION'!$C$7)),0) -> 0 | AH23: =IF('06_CONSTRUCTION'!AH13=1,SIN(PI()*(30-0.5)/'06_CONSTRUCTION'!$C$7)*SIN(PI()/(2*'06_CONSTRUCTION'!$C$7)),0) -> 0 | AI23: =IF('06_CONSTRUCTION'!AI13=1,SIN(PI()*(31-0.5)/'06_CONSTRUCTION'!$C$7)*SIN(PI()/(2*'06_CONSTRUCTION'!$C$7)),0) -> 0 | AJ23: =IF('06_CONSTRUCTION'!AJ13=1,SIN(PI()*(32-0.5)/'06_CONSTRUCTION'!$C$7)*SIN(PI()/(2*'06_CONSTRUCTION'!$C$7)),0) -> 0 | AK23: =IF('06_CONSTRUCTION'!AK13=1,SIN(PI()*(33-0.5)/'06_CONSTRUCTION'!$C$7)*SIN(PI()/(2*'06_CONSTRUCTION'!$C$7)),0) -> 0 | AL23: =IF('06_CONSTRUCTION'!AL13=1,SIN(PI()*(34-0.5)/'06_CONSTRUCTION'!$C$7)*SIN(PI()/(2*'06_CONSTRUCTION'!$C$7)),0) -> 0 | AM23: =IF('06_CONSTRUCTION'!AM13=1,SIN(PI()*(35-0.5)/'06_CONSTRUCTION'!$C$7)*SIN(PI()/(2*'06_CONSTRUCTION'!$C$7)),0) -> 0 | AN23: =IF('06_CONSTRUCTION'!AN13=1,SIN(PI()*(36-0.5)/'06_CONSTRUCTION'!$C$7)*SIN(PI()/(2*'06_CONSTRUCTION'!$C$7)),0) -> 0 | AO23: =IF('06_CONSTRUCTION'!AO13=1,SIN(PI()*(37-0.5)/'06_CONSTRUCTION'!$C$7)*SIN(PI()/(2*'06_CONSTRUCTION'!$C$7)),0) -> 0 | AP23: =IF('06_CONSTRUCTION'!AP13=1,SIN(PI()*(38-0.5)/'06_CONSTRUCTION'!$C$7)*SIN(PI()/(2*'06_CONSTRUCTION'!$C$7)),0) -> 0 | AQ23: =IF('06_CONSTRUCTION'!AQ13=1,SIN(PI()*(39-0.5)/'06_CONSTRUCTION'!$C$7)*SIN(PI()/(2*'06_CONSTRUCTION'!$C$7)),0) -> 0 | AR23: =IF('06_CONSTRUCTION'!AR13=1,SIN(PI()*(40-0.5)/'06_CONSTRUCTION'!$C$7)*SIN(PI()/(2*'06_CONSTRUCTION'!$C$7)),0) -> 0
A24: Part cumulée du CAPEX | B24: % | E24: ='06_CONSTRUCTION'!D24+'06_CONSTRUCTION'!E23 -> 0.25 | F24: ='06_CONSTRUCTION'!E24+'06_CONSTRUCTION'!F23 -> 0.75 | G24: ='06_CONSTRUCTION'!F24+'06_CONSTRUCTION'!G23 -> 1 | H24: ='06_CONSTRUCTION'!G24+'06_CONSTRUCTION'!H23 -> 1 | I24: ='06_CONSTRUCTION'!H24+'06_CONSTRUCTION'!I23 -> 1 | J24: ='06_CONSTRUCTION'!I24+'06_CONSTRUCTION'!J23 -> 1 | K24: ='06_CONSTRUCTION'!J24+'06_CONSTRUCTION'!K23 -> 1 | L24: ='06_CONSTRUCTION'!K24+'06_CONSTRUCTION'!L23 -> 1 | ... AR24: ='06_CONSTRUCTION'!AQ24+'06_CONSTRUCTION'!AR23 -> 1
A25: CAPEX centrale, nominal | B25: M USD | C25: =SUM('06_CONSTRUCTION'!$E$25:$AR$25) -> 164.82616 | E25: ='06_CONSTRUCTION'!$C$9*'06_CONSTRUCTION'!E23*'06_CONSTRUCTION'!E21 -> 40.195375 | F25: ='06_CONSTRUCTION'!$C$9*'06_CONSTRUCTION'!F23*'06_CONSTRUCTION'!F21 -> 82.400519 | G25: ='06_CONSTRUCTION'!$C$9*'06_CONSTRUCTION'!G23*'06_CONSTRUCTION'!G21 -> 42.230266 | H25: ='06_CONSTRUCTION'!$C$9*'06_CONSTRUCTION'!H23*'06_CONSTRUCTION'!H21 -> 0 | I25: ='06_CONSTRUCTION'!$C$9*'06_CONSTRUCTION'!I23*'06_CONSTRUCTION'!I21 -> 0 | J25: ='06_CONSTRUCTION'!$C$9*'06_CONSTRUCTION'!J23*'06_CONSTRUCTION'!J21 -> 0 | K25: ='06_CONSTRUCTION'!$C$9*'06_CONSTRUCTION'!K23*'06_CONSTRUCTION'!K21 -> 0 | L25: ='06_CONSTRUCTION'!$C$9*'06_CONSTRUCTION'!L23*'06_CONSTRUCTION'!L21 -> 0 | ... AR25: ='06_CONSTRUCTION'!$C$9*'06_CONSTRUCTION'!AR23*'06_CONSTRUCTION'!AR21 -> 0
A27: Poids de la courbe en S_t = sin(pi(t-0.5)/N)·sin(pi/2N) — forme analytique dont la somme vaut exactement 1 pour tout N. Remplacer par l'échéancier de paiement EPC quand il est disponible.

Sheet 07_OPEX
A1: 07 OPEX — Coûts d'exploitation de la centrale et paiements à l'État
A2: Données réelles 2026 indexées IPC US
A6: A. DONNÉES
A7: O&M fixe (personnel, contrats de maintenance) | B7: M USD/an réels | C7: 3.2 | D7: Environ 1,6 % du CAPEX ; fourchette IFC 1-4 % [hydro_development_evidence]
A8: O&M variable | B8: USD/MWh réels | C8: 1
A9: Assurance | B9: % du CAPEX par an | C9: 0.0035
A10: Dotation à la réserve de gros entretien | B10: % du CAPEX par an | C10: 0.0025
A11: Frais généraux, suivi E&S, programmes communautaires | B11: M USD/an réels | C11: 0.8
A12: Redevance d'eau / redevance sur la ressource à l'État | B12: USD/MWh réels | C12: 2.5 | D12: Recette budgétaire
A13: B. CALCULS (M USD nominaux)
A14: O&M fixe | B14: M USD | C14: =SUM('07_OPEX'!$E$14:$AR$14) -> 110.946 | E14: ='06_CONSTRUCTION'!E14*'07_OPEX'!$C$7*'27_SCENARIOS'!$C$39*'06_CONSTRUCTION'!E17 -> 0 | F14: ='06_CONSTRUCTION'!F14*'07_OPEX'!$C$7*'27_SCENARIOS'!$C$39*'06_CONSTRUCTION'!F17 -> 0 | G14: ='06_CONSTRUCTION'!G14*'07_OPEX'!$C$7*'27_SCENARIOS'!$C$39*'06_CONSTRUCTION'!G17 -> 0 | H14: ='06_CONSTRUCTION'!H14*'07_OPEX'!$C$7*'27_SCENARIOS'!$C$39*'06_CONSTRUCTION'!H17 -> 3.4637829 | I14: ='06_CONSTRUCTION'!I14*'07_OPEX'!$C$7*'27_SCENARIOS'!$C$39*'06_CONSTRUCTION'!I17 -> 3.5330586 | J14: ='06_CONSTRUCTION'!J14*'07_OPEX'!$C$7*'27_SCENARIOS'!$C$39*'06_CONSTRUCTION'!J17 -> 3.6037197 | K14: ='06_CONSTRUCTION'!K14*'07_OPEX'!$C$7*'27_SCENARIOS'!$C$39*'06_CONSTRUCTION'!K17 -> 3.6757941 | L14: ='06_CONSTRUCTION'!L14*'07_OPEX'!$C$7*'27_SCENARIOS'!$C$39*'06_CONSTRUCTION'!L17 -> 3.74931 | ... AR14: ='06_CONSTRUCTION'!AR14*'07_OPEX'!$C$7*'27_SCENARIOS'!$C$39*'06_CONSTRUCTION'!AR17 -> 0
A15: O&M variable | B15: M USD | C15: =SUM('07_OPEX'!$E$15:$AR$15) -> 10.093024 | E15: ='04_GENERATION'!E17*'07_OPEX'!$C$8*'27_SCENARIOS'!$C$39*'06_CONSTRUCTION'!E17/1000 -> 0 | F15: ='04_GENERATION'!F17*'07_OPEX'!$C$8*'27_SCENARIOS'!$C$39*'06_CONSTRUCTION'!F17/1000 -> 0 | G15: ='04_GENERATION'!G17*'07_OPEX'!$C$8*'27_SCENARIOS'!$C$39*'06_CONSTRUCTION'!G17/1000 -> 0 | H15: ='04_GENERATION'!H17*'07_OPEX'!$C$8*'27_SCENARIOS'!$C$39*'06_CONSTRUCTION'!H17/1000 -> 0.26910256 | I15: ='04_GENERATION'!I17*'07_OPEX'!$C$8*'27_SCENARIOS'!$C$39*'06_CONSTRUCTION'!I17/1000 -> 0.32292307 | J15: ='04_GENERATION'!J17*'07_OPEX'!$C$8*'27_SCENARIOS'!$C$39*'06_CONSTRUCTION'!J17/1000 -> 0.32938154 | K15: ='04_GENERATION'!K17*'07_OPEX'!$C$8*'27_SCENARIOS'!$C$39*'06_CONSTRUCTION'!K17/1000 -> 0.33596917 | L15: ='04_GENERATION'!L17*'07_OPEX'!$C$8*'27_SCENARIOS'!$C$39*'06_CONSTRUCTION'!L17/1000 -> 0.34268855 | ... AR15: ='04_GENERATION'!AR17*'07_OPEX'!$C$8*'27_SCENARIOS'!$C$39*'06_CONSTRUCTION'!AR17/1000 -> 0
A16: Assurance | B16: M USD | C16: =SUM('07_OPEX'!$E$16:$AR$16) -> 19.034521 | E16: ='06_CONSTRUCTION'!E14*'06_CONSTRUCTION'!$C$9*'07_OPEX'!$C$9*'06_CONSTRUCTION'!E17 -> 0 | F16: ='06_CONSTRUCTION'!F14*'06_CONSTRUCTION'!$C$9*'07_OPEX'!$C$9*'06_CONSTRUCTION'!F17 -> 0 | G16: ='06_CONSTRUCTION'!G14*'06_CONSTRUCTION'!$C$9*'07_OPEX'!$C$9*'06_CONSTRUCTION'!G17 -> 0 | H16: ='06_CONSTRUCTION'!H14*'06_CONSTRUCTION'!$C$9*'07_OPEX'!$C$9*'06_CONSTRUCTION'!H17 -> 0.59426608 | I16: ='06_CONSTRUCTION'!I14*'06_CONSTRUCTION'!$C$9*'07_OPEX'!$C$9*'06_CONSTRUCTION'!I17 -> 0.6061514 | J16: ='06_CONSTRUCTION'!J14*'06_CONSTRUCTION'!$C$9*'07_OPEX'!$C$9*'06_CONSTRUCTION'!J17 -> 0.61827443 | K16: ='06_CONSTRUCTION'!K14*'06_CONSTRUCTION'!$C$9*'07_OPEX'!$C$9*'06_CONSTRUCTION'!K17 -> 0.63063992 | L16: ='06_CONSTRUCTION'!L14*'06_CONSTRUCTION'!$C$9*'07_OPEX'!$C$9*'06_CONSTRUCTION'!L17 -> 0.64325272 | ... AR16: ='06_CONSTRUCTION'!AR14*'06_CONSTRUCTION'!$C$9*'07_OPEX'!$C$9*'06_CONSTRUCTION'!AR17 -> 0
A17: Réserve de gros entretien | B17: M USD | C17: =SUM('07_OPEX'!$E$17:$AR$17) -> 13.596086 | E17: ='06_CONSTRUCTION'!E14*'06_CONSTRUCTION'!$C$9*'07_OPEX'!$C$10*'06_CONSTRUCTION'!E17 -> 0 | F17: ='06_CONSTRUCTION'!F14*'06_CONSTRUCTION'!$C$9*'07_OPEX'!$C$10*'06_CONSTRUCTION'!F17 -> 0 | G17: ='06_CONSTRUCTION'!G14*'06_CONSTRUCTION'!$C$9*'07_OPEX'!$C$10*'06_CONSTRUCTION'!G17 -> 0 | H17: ='06_CONSTRUCTION'!H14*'06_CONSTRUCTION'!$C$9*'07_OPEX'!$C$10*'06_CONSTRUCTION'!H17 -> 0.42447577 | I17: ='06_CONSTRUCTION'!I14*'06_CONSTRUCTION'!$C$9*'07_OPEX'!$C$10*'06_CONSTRUCTION'!I17 -> 0.43296529 | J17: ='06_CONSTRUCTION'!J14*'06_CONSTRUCTION'!$C$9*'07_OPEX'!$C$10*'06_CONSTRUCTION'!J17 -> 0.44162459 | K17: ='06_CONSTRUCTION'!K14*'06_CONSTRUCTION'!$C$9*'07_OPEX'!$C$10*'06_CONSTRUCTION'!K17 -> 0.45045708 | L17: ='06_CONSTRUCTION'!L14*'06_CONSTRUCTION'!$C$9*'07_OPEX'!$C$10*'06_CONSTRUCTION'!L17 -> 0.45946623 | ... AR17: ='06_CONSTRUCTION'!AR14*'06_CONSTRUCTION'!$C$9*'07_OPEX'!$C$10*'06_CONSTRUCTION'!AR17 -> 0
A18: Frais généraux / E&S / communautés | B18: M USD | C18: =SUM('07_OPEX'!$E$18:$AR$18) -> 27.736501 | E18: ='06_CONSTRUCTION'!E14*'07_OPEX'!$C$11*'27_SCENARIOS'!$C$39*'06_CONSTRUCTION'!E17 -> 0 | F18: ='06_CONSTRUCTION'!F14*'07_OPEX'!$C$11*'27_SCENARIOS'!$C$39*'06_CONSTRUCTION'!F17 -> 0 | G18: ='06_CONSTRUCTION'!G14*'07_OPEX'!$C$11*'27_SCENARIOS'!$C$39*'06_CONSTRUCTION'!G17 -> 0 | H18: ='06_CONSTRUCTION'!H14*'07_OPEX'!$C$11*'27_SCENARIOS'!$C$39*'06_CONSTRUCTION'!H17 -> 0.86594573 | I18: ='06_CONSTRUCTION'!I14*'07_OPEX'!$C$11*'27_SCENARIOS'!$C$39*'06_CONSTRUCTION'!I17 -> 0.88326464 | J18: ='06_CONSTRUCTION'!J14*'07_OPEX'!$C$11*'27_SCENARIOS'!$C$39*'06_CONSTRUCTION'!J17 -> 0.90092994 | K18: ='06_CONSTRUCTION'!K14*'07_OPEX'!$C$11*'27_SCENARIOS'!$C$39*'06_CONSTRUCTION'!K17 -> 0.91894853 | L18: ='06_CONSTRUCTION'!L14*'07_OPEX'!$C$11*'27_SCENARIOS'!$C$39*'06_CONSTRUCTION'!L17 -> 0.9373275 | ... AR18: ='06_CONSTRUCTION'!AR14*'07_OPEX'!$C$11*'27_SCENARIOS'!$C$39*'06_CONSTRUCTION'!AR17 -> 0
A19: O&M transport et transit (si détenu par le projet) | B19: M USD | C19: =SUM('07_OPEX'!$E$19:$AR$19) -> 8.6849919 | E19: =IF('08_TRANSMISSION'!$C$17=2,'08_TRANSMISSION'!E34,0)+'08_TRANSMISSION'!E36 -> 0 | F19: =IF('08_TRANSMISSION'!$C$17=2,'08_TRANSMISSION'!F34,0)+'08_TRANSMISSION'!F36 -> 0 | G19: =IF('08_TRANSMISSION'!$C$17=2,'08_TRANSMISSION'!G34,0)+'08_TRANSMISSION'!G36 -> 0 | H19: =IF('08_TRANSMISSION'!$C$17=2,'08_TRANSMISSION'!H34,0)+'08_TRANSMISSION'!H36 -> 0.27114926 | I19: =IF('08_TRANSMISSION'!$C$17=2,'08_TRANSMISSION'!I34,0)+'08_TRANSMISSION'!I36 -> 0.27657224 | J19: =IF('08_TRANSMISSION'!$C$17=2,'08_TRANSMISSION'!J34,0)+'08_TRANSMISSION'!J36 -> 0.28210369 | K19: =IF('08_TRANSMISSION'!$C$17=2,'08_TRANSMISSION'!K34,0)+'08_TRANSMISSION'!K36 -> 0.28774576 | L19: =IF('08_TRANSMISSION'!$C$17=2,'08_TRANSMISSION'!L34,0)+'08_TRANSMISSION'!L36 -> 0.29350067 | ... AR19: =IF('08_TRANSMISSION'!$C$17=2,'08_TRANSMISSION'!AR34,0)+'08_TRANSMISSION'!AR36 -> 0
A20: OPEX total | B20: M USD | C20: =SUM('07_OPEX'!$E$20:$AR$20) -> 190.09113 | E20: ='07_OPEX'!E14+'07_OPEX'!E15+'07_OPEX'!E16+'07_OPEX'!E17+'07_OPEX'!E18+'07_OPEX'!E19 -> 0 | F20: ='07_OPEX'!F14+'07_OPEX'!F15+'07_OPEX'!F16+'07_OPEX'!F17+'07_OPEX'!F18+'07_OPEX'!F19 -> 0 | G20: ='07_OPEX'!G14+'07_OPEX'!G15+'07_OPEX'!G16+'07_OPEX'!G17+'07_OPEX'!G18+'07_OPEX'!G19 -> 0 | H20: ='07_OPEX'!H14+'07_OPEX'!H15+'07_OPEX'!H16+'07_OPEX'!H17+'07_OPEX'!H18+'07_OPEX'!H19 -> 5.8887223 | I20: ='07_OPEX'!I14+'07_OPEX'!I15+'07_OPEX'!I16+'07_OPEX'!I17+'07_OPEX'!I18+'07_OPEX'!I19 -> 6.0549352 | J20: ='07_OPEX'!J14+'07_OPEX'!J15+'07_OPEX'!J16+'07_OPEX'!J17+'07_OPEX'!J18+'07_OPEX'!J19 -> 6.1760339 | K20: ='07_OPEX'!K14+'07_OPEX'!K15+'07_OPEX'!K16+'07_OPEX'!K17+'07_OPEX'!K18+'07_OPEX'!K19 -> 6.2995546 | L20: ='07_OPEX'!L14+'07_OPEX'!L15+'07_OPEX'!L16+'07_OPEX'!L17+'07_OPEX'!L18+'07_OPEX'!L19 -> 6.4255457 | ... AR20: ='07_OPEX'!AR14+'07_OPEX'!AR15+'07_OPEX'!AR16+'07_OPEX'!AR17+'07_OPEX'!AR18+'07_OPEX'!AR19 -> 0
A21: Redevance d'eau (à l'État) | B21: M USD | C21: =SUM('07_OPEX'!$E$21:$AR$21) -> 25.23256 | E21: ='04_GENERATION'!E20*'07_OPEX'!$C$12*'06_CONSTRUCTION'!E17/1000 -> 0 | F21: ='04_GENERATION'!F20*'07_OPEX'!$C$12*'06_CONSTRUCTION'!F17/1000 -> 0 | G21: ='04_GENERATION'!G20*'07_OPEX'!$C$12*'06_CONSTRUCTION'!G17/1000 -> 0 | H21: ='04_GENERATION'!H20*'07_OPEX'!$C$12*'06_CONSTRUCTION'!H17/1000 -> 0.67275641 | I21: ='04_GENERATION'!I20*'07_OPEX'!$C$12*'06_CONSTRUCTION'!I17/1000 -> 0.80730769 | J21: ='04_GENERATION'!J20*'07_OPEX'!$C$12*'06_CONSTRUCTION'!J17/1000 -> 0.82345384 | K21: ='04_GENERATION'!K20*'07_OPEX'!$C$12*'06_CONSTRUCTION'!K17/1000 -> 0.83992292 | L21: ='04_GENERATION'!L20*'07_OPEX'!$C$12*'06_CONSTRUCTION'!L17/1000 -> 0.85672138 | ... AR21: ='04_GENERATION'!AR20*'07_OPEX'!$C$12*'06_CONSTRUCTION'!AR17/1000 -> 0
A22: Redevance d'eau — cas prêteurs | B22: M USD | C22: =SUM('07_OPEX'!$E$22:$AR$22) -> 23.142168 | E22: ='04_GENERATION'!E23*'07_OPEX'!$C$12*'06_CONSTRUCTION'!E17/1000 -> 0 | F22: ='04_GENERATION'!F23*'07_OPEX'!$C$12*'06_CONSTRUCTION'!F17/1000 -> 0 | G22: ='04_GENERATION'!G23*'07_OPEX'!$C$12*'06_CONSTRUCTION'!G17/1000 -> 0 | H22: ='04_GENERATION'!H23*'07_OPEX'!$C$12*'06_CONSTRUCTION'!H17/1000 -> 0.61702189 | I22: ='04_GENERATION'!I23*'07_OPEX'!$C$12*'06_CONSTRUCTION'!I17/1000 -> 0.74042626 | J22: ='04_GENERATION'!J23*'07_OPEX'!$C$12*'06_CONSTRUCTION'!J17/1000 -> 0.75523479 | K22: ='04_GENERATION'!K23*'07_OPEX'!$C$12*'06_CONSTRUCTION'!K17/1000 -> 0.77033949 | L22: ='04_GENERATION'!L23*'07_OPEX'!$C$12*'06_CONSTRUCTION'!L17/1000 -> 0.78574628 | ... AR22: ='04_GENERATION'!AR23*'07_OPEX'!$C$12*'06_CONSTRUCTION'!AR17/1000 -> 0

Sheet 08_TRANSMISSION
A1: 08 TRANSPORT — Ligne d'évacuation, postes, renforcement, écart de préparation
A2: Question : la centrale peut-elle évacuer l'électricité qu'elle produit ?
A6: A. DONNÉES
A7: Point de raccord. | C7: Poste 400 kV de Kabanga (fictif)
A8: Longueur de ligne | B8: km | C8: 35
A9: Tension | B9: kV | C9: 132
A10: Capacité de transit thermique / stabilité de la ligne | B10: MW | C10: 120 | D10: Confirmer par étude de répartition
A11: Coût de ligne par km (réel 2026) | B11: M USD/km | C11: 0.22 | D11: Hypothèse pour un terne 132 kV ; EAPP 2014 donne 0,27-0,63 M USD(2012)/km en 220 kV [TX-04]
A12: Postes et extension du poste d'évacuation | B12: M USD | C12: 6 | D12: Fictif
A13: Renforcement du réseau en aval | B13: M USD | C13: 3 | D13: Fictif ; issu de l'étude d'impact réseau
A14: Durée de construction du transport | B14: ans | C14: 2
A15: Pertes jusqu'au centre de charge | B15: % | C15: 0.02 | D15: Hypothèse
A16: O&M du transport | B16: % capex par an | C16: 0.015 | D16: Hypothèse
A17: Qui construit et finance le transport (1=État/compagnie, 2=société de projet) | B17: 1-2 | C17: 2 | D17: Le projet construit l'interconnexion et la transfère à la compagnie à la COD
A18: COD prévue du transport par rapport à la COD centrale (ans, + = retard) | B18: ans | C18: 0
A19: Évacuation provisoire par le réseau existant | B19: MW | C19: 0 | D19: Si ligne non prête
A20: Frais de transit / d'utilisation du réseau à la charge du projet | B20: USD/MWh | C20: 0 | D20: Mettre >0 si ventes tiers/export
A21: Financement du transport obtenu (1=oui, 0=non) | B21: 0/1 | C21: 1 | D21: Inclus dans le financement du projet
A22: B. CALCULS
A23: CAPEX transport (réel 2026, y c. cas et dépassement) | B23: M USD | C23: =('08_TRANSMISSION'!$C$8*'08_TRANSMISSION'!$C$11+'08_TRANSMISSION'!$C$12+'08_TRANSMISSION'!$C$13)*'27_SCENARIOS'!$C$27 -> 16.7
A24: COD prévue du transport (année) | B24: année | C24: ='02_PROJECT_INPUTS'!$C$10+'02_PROJECT_INPUTS'!$C$12+'08_TRANSMISSION'!$C$18 -> 2030
A25: COD effective du transport (année) | B25: année | C25: ='08_TRANSMISSION'!$C$24+'27_SCENARIOS'!$C$37 -> 2030
A26: Écart de préparation du transport — délai | B26: ans | C26: ='08_TRANSMISSION'!$C$25-'06_CONSTRUCTION'!$C$8 -> 0
A27: Écart de préparation du transport — capacité à la COD | B27: MW | C27: =MAX(0,'02_PROJECT_INPUTS'!$C$15-'09_GRID'!$C$20) -> 0
A28: Coût de raccordement par kW de centrale | B28: USD/kW | C28: ='08_TRANSMISSION'!$C$23/'02_PROJECT_INPUTS'!$C$15*1000 -> 278.33333
A30: Indicateur ligne en service | B30: indic. | E30: =IF('06_CONSTRUCTION'!E4>='08_TRANSMISSION'!$C$25,1,0) -> 0 | F30: =IF('06_CONSTRUCTION'!F4>='08_TRANSMISSION'!$C$25,1,0) -> 0 | G30: =IF('06_CONSTRUCTION'!G4>='08_TRANSMISSION'!$C$25,1,0) -> 0 | H30: =IF('06_CONSTRUCTION'!H4>='08_TRANSMISSION'!$C$25,1,0) -> 1 | I30: =IF('06_CONSTRUCTION'!I4>='08_TRANSMISSION'!$C$25,1,0) -> 1 | J30: =IF('06_CONSTRUCTION'!J4>='08_TRANSMISSION'!$C$25,1,0) -> 1 | K30: =IF('06_CONSTRUCTION'!K4>='08_TRANSMISSION'!$C$25,1,0) -> 1 | L30: =IF('06_CONSTRUCTION'!L4>='08_TRANSMISSION'!$C$25,1,0) -> 1 | ... AR30: =IF('06_CONSTRUCTION'!AR4>='08_TRANSMISSION'!$C$25,1,0) -> 1
A31: CAPEX transport, nominal | B31: M USD | C31: =SUM('08_TRANSMISSION'!$E$31:$AR$31) -> 17.764755 | E31: =IF(AND('06_CONSTRUCTION'!E4>='08_TRANSMISSION'!$C$24-'08_TRANSMISSION'!$C$14,'06_CONSTRUCTION'!E4<'08_TRANSMISSION'!$C$25),'08_TRANSMISSION'!$C$23*(1+'05_PLANT_CAPEX'!$C$17*'27_SCENARIOS'!$C$37)/('08_TRANSMISSION'!$C$14+'27_SCENARIOS'!$C$37)*'06_CONSTRUCTION'!E21,0) -> 0 | F31: =IF(AND('06_CONSTRUCTION'!F4>='08_TRANSMISSION'!$C$24-'08_TRANSMISSION'!$C$14,'06_CONSTRUCTION'!F4<'08_TRANSMISSION'!$C$25),'08_TRANSMISSION'!$C$23*(1+'05_PLANT_CAPEX'!$C$17*'27_SCENARIOS'!$C$37)/('08_TRANSMISSION'!$C$14+'27_SCENARIOS'!$C$37)*'06_CONSTRUCTION'!F21,0) -> 8.7727187 | G31: =IF(AND('06_CONSTRUCTION'!G4>='08_TRANSMISSION'!$C$24-'08_TRANSMISSION'!$C$14,'06_CONSTRUCTION'!G4<'08_TRANSMISSION'!$C$25),'08_TRANSMISSION'!$C$23*(1+'05_PLANT_CAPEX'!$C$17*'27_SCENARIOS'!$C$37)/('08_TRANSMISSION'!$C$14+'27_SCENARIOS'!$C$37)*'06_CONSTRUCTION'!G21,0) -> 8.9920367 | H31: =IF(AND('06_CONSTRUCTION'!H4>='08_TRANSMISSION'!$C$24-'08_TRANSMISSION'!$C$14,'06_CONSTRUCTION'!H4<'08_TRANSMISSION'!$C$25),'08_TRANSMISSION'!$C$23*(1+'05_PLANT_CAPEX'!$C$17*'27_SCENARIOS'!$C$37)/('08_TRANSMISSION'!$C$14+'27_SCENARIOS'!$C$37)*'06_CONSTRUCTION'!H21,0) -> 0 | I31: =IF(AND('06_CONSTRUCTION'!I4>='08_TRANSMISSION'!$C$24-'08_TRANSMISSION'!$C$14,'06_CONSTRUCTION'!I4<'08_TRANSMISSION'!$C$25),'08_TRANSMISSION'!$C$23*(1+'05_PLANT_CAPEX'!$C$17*'27_SCENARIOS'!$C$37)/('08_TRANSMISSION'!$C$14+'27_SCENARIOS'!$C$37)*'06_CONSTRUCTION'!I21,0) -> 0 | J31: =IF(AND('06_CONSTRUCTION'!J4>='08_TRANSMISSION'!$C$24-'08_TRANSMISSION'!$C$14,'06_CONSTRUCTION'!J4<'08_TRANSMISSION'!$C$25),'08_TRANSMISSION'!$C$23*(1+'05_PLANT_CAPEX'!$C$17*'27_SCENARIOS'!$C$37)/('08_TRANSMISSION'!$C$14+'27_SCENARIOS'!$C$37)*'06_CONSTRUCTION'!J21,0) -> 0 | K31: =IF(AND('06_CONSTRUCTION'!K4>='08_TRANSMISSION'!$C$24-'08_TRANSMISSION'!$C$14,'06_CONSTRUCTION'!K4<'08_TRANSMISSION'!$C$25),'08_TRANSMISSION'!$C$23*(1+'05_PLANT_CAPEX'!$C$17*'27_SCENARIOS'!$C$37)/('08_TRANSMISSION'!$C$14+'27_SCENARIOS'!$C$37)*'06_CONSTRUCTION'!K21,0) -> 0 | L31: =IF(AND('06_CONSTRUCTION'!L4>='08_TRANSMISSION'!$C$24-'08_TRANSMISSION'!$C$14,'06_CONSTRUCTION'!L4<'08_TRANSMISSION'!$C$25),'08_TRANSMISSION'!$C$23*(1+'05_PLANT_CAPEX'!$C$17*'27_SCENARIOS'!$C$37)/('08_TRANSMISSION'!$C$14+'27_SCENARIOS'!$C$37)*'06_CONSTRUCTION'!L21,0) -> 0 | ... AR31: =IF(AND('06_CONSTRUCTION'!AR4>='08_TRANSMISSION'!$C$24-'08_TRANSMISSION'!$C$14,'06_CONSTRUCTION'!AR4<'08_TRANSMISSION'!$C$25),'08_TRANSMISSION'!$C$23*(1+'05_PLANT_CAPEX'!$C$17*'27_SCENARIOS'!$C$37)/('08_TRANSMISSION'!$C$14+'27_SCENARIOS'!$C$37)*'06_CONSTRUCTION'!AR21,0) -> 0
A32: dont public (État/compagnie) | B32: M USD | C32: =SUM('08_TRANSMISSION'!$E$32:$AR$32) -> 0 | E32: =IF('08_TRANSMISSION'!$C$17=1,'08_TRANSMISSION'!E31,0) -> 0 | F32: =IF('08_TRANSMISSION'!$C$17=1,'08_TRANSMISSION'!F31,0) -> 0 | G32: =IF('08_TRANSMISSION'!$C$17=1,'08_TRANSMISSION'!G31,0) -> 0 | H32: =IF('08_TRANSMISSION'!$C$17=1,'08_TRANSMISSION'!H31,0) -> 0 | I32: =IF('08_TRANSMISSION'!$C$17=1,'08_TRANSMISSION'!I31,0) -> 0 | J32: =IF('08_TRANSMISSION'!$C$17=1,'08_TRANSMISSION'!J31,0) -> 0 | K32: =IF('08_TRANSMISSION'!$C$17=1,'08_TRANSMISSION'!K31,0) -> 0 | L32: =IF('08_TRANSMISSION'!$C$17=1,'08_TRANSMISSION'!L31,0) -> 0 | ... AR32: =IF('08_TRANSMISSION'!$C$17=1,'08_TRANSMISSION'!AR31,0) -> 0
A33: dont société de projet | B33: M USD | C33: =SUM('08_TRANSMISSION'!$E$33:$AR$33) -> 17.764755 | E33: =IF('08_TRANSMISSION'!$C$17=2,'08_TRANSMISSION'!E31,0) -> 0 | F33: =IF('08_TRANSMISSION'!$C$17=2,'08_TRANSMISSION'!F31,0) -> 8.7727187 | G33: =IF('08_TRANSMISSION'!$C$17=2,'08_TRANSMISSION'!G31,0) -> 8.9920367 | H33: =IF('08_TRANSMISSION'!$C$17=2,'08_TRANSMISSION'!H31,0) -> 0 | I33: =IF('08_TRANSMISSION'!$C$17=2,'08_TRANSMISSION'!I31,0) -> 0 | J33: =IF('08_TRANSMISSION'!$C$17=2,'08_TRANSMISSION'!J31,0) -> 0 | K33: =IF('08_TRANSMISSION'!$C$17=2,'08_TRANSMISSION'!K31,0) -> 0 | L33: =IF('08_TRANSMISSION'!$C$17=2,'08_TRANSMISSION'!L31,0) -> 0 | ... AR33: =IF('08_TRANSMISSION'!$C$17=2,'08_TRANSMISSION'!AR31,0) -> 0
A34: O&M du transport (une fois en service) | B34: M USD | C34: =SUM('08_TRANSMISSION'!$E$34:$AR$34) -> 8.6849919 | E34: ='08_TRANSMISSION'!E30*'06_CONSTRUCTION'!E14*'08_TRANSMISSION'!$C$23*'08_TRANSMISSION'!$C$16*'06_CONSTRUCTION'!E17 -> 0 | F34: ='08_TRANSMISSION'!F30*'06_CONSTRUCTION'!F14*'08_TRANSMISSION'!$C$23*'08_TRANSMISSION'!$C$16*'06_CONSTRUCTION'!F17 -> 0 | G34: ='08_TRANSMISSION'!G30*'06_CONSTRUCTION'!G14*'08_TRANSMISSION'!$C$23*'08_TRANSMISSION'!$C$16*'06_CONSTRUCTION'!G17 -> 0 | H34: ='08_TRANSMISSION'!H30*'06_CONSTRUCTION'!H14*'08_TRANSMISSION'!$C$23*'08_TRANSMISSION'!$C$16*'06_CONSTRUCTION'!H17 -> 0.27114926 | I34: ='08_TRANSMISSION'!I30*'06_CONSTRUCTION'!I14*'08_TRANSMISSION'!$C$23*'08_TRANSMISSION'!$C$16*'06_CONSTRUCTION'!I17 -> 0.27657224 | J34: ='08_TRANSMISSION'!J30*'06_CONSTRUCTION'!J14*'08_TRANSMISSION'!$C$23*'08_TRANSMISSION'!$C$16*'06_CONSTRUCTION'!J17 -> 0.28210369 | K34: ='08_TRANSMISSION'!K30*'06_CONSTRUCTION'!K14*'08_TRANSMISSION'!$C$23*'08_TRANSMISSION'!$C$16*'06_CONSTRUCTION'!K17 -> 0.28774576 | L34: ='08_TRANSMISSION'!L30*'06_CONSTRUCTION'!L14*'08_TRANSMISSION'!$C$23*'08_TRANSMISSION'!$C$16*'06_CONSTRUCTION'!L17 -> 0.29350067 | ... AR34: ='08_TRANSMISSION'!AR30*'06_CONSTRUCTION'!AR14*'08_TRANSMISSION'!$C$23*'08_TRANSMISSION'!$C$16*'06_CONSTRUCTION'!AR17 -> 0
A35: Pertes de transport sur l'énergie livrée | B35: GWh | C35: =SUM('08_TRANSMISSION'!$E$35:$AR$35) -> 145.36324 | E35: ='04_GENERATION'!E20*'08_TRANSMISSION'!$C$15 -> 0 | F35: ='04_GENERATION'!F20*'08_TRANSMISSION'!$C$15 -> 0 | G35: ='04_GENERATION'!G20*'08_TRANSMISSION'!$C$15 -> 0 | H35: ='04_GENERATION'!H20*'08_TRANSMISSION'!$C$15 -> 4.9721834 | I35: ='04_GENERATION'!I20*'08_TRANSMISSION'!$C$15 -> 5.8496276 | J35: ='04_GENERATION'!J20*'08_TRANSMISSION'!$C$15 -> 5.8496276 | K35: ='04_GENERATION'!K20*'08_TRANSMISSION'!$C$15 -> 5.8496276 | L35: ='04_GENERATION'!L20*'08_TRANSMISSION'!$C$15 -> 5.8496276 | ... AR35: ='04_GENERATION'!AR20*'08_TRANSMISSION'!$C$15 -> 0
A36: Frais de transit payés par le projet | B36: M USD | C36: =SUM('08_TRANSMISSION'!$E$36:$AR$36) -> 0 | E36: ='04_GENERATION'!E20*'08_TRANSMISSION'!$C$20*'06_CONSTRUCTION'!E17/1000 -> 0 | F36: ='04_GENERATION'!F20*'08_TRANSMISSION'!$C$20*'06_CONSTRUCTION'!F17/1000 -> 0 | G36: ='04_GENERATION'!G20*'08_TRANSMISSION'!$C$20*'06_CONSTRUCTION'!G17/1000 -> 0 | H36: ='04_GENERATION'!H20*'08_TRANSMISSION'!$C$20*'06_CONSTRUCTION'!H17/1000 -> 0 | I36: ='04_GENERATION'!I20*'08_TRANSMISSION'!$C$20*'06_CONSTRUCTION'!I17/1000 -> 0 | J36: ='04_GENERATION'!J20*'08_TRANSMISSION'!$C$20*'06_CONSTRUCTION'!J17/1000 -> 0 | K36: ='04_GENERATION'!K20*'08_TRANSMISSION'!$C$20*'06_CONSTRUCTION'!K17/1000 -> 0 | L36: ='04_GENERATION'!L20*'08_TRANSMISSION'!$C$20*'06_CONSTRUCTION'!L17/1000 -> 0 | ... AR36: ='04_GENERATION'!AR20*'08_TRANSMISSION'!$C$20*'06_CONSTRUCTION'!AR17/1000 -> 0

Sheet 09_GRID
A1: 09 RÉSEAU — Taille du système, limite d'absorption, part du projet dans la pointe
A2: Filtre simplifié — ne remplace pas les études de répartition des charges / de stabilité
A6: A. DONNÉES
A7: Pointe du système (2026) | B7: MW | C7: 1450 | D7: Fictif
A8: Charge min. en % de la pointe | B8: % | C8: 0.6
A9: Production fatale à la charge minimale | B9: MW | C9: 300 | D9: Base existante / fil de l'eau
A10: Capacité d'interconnexion à l'export | B10: MW | C10: 100
A11: Puissance installée existante | B11: MW | C11: 2100
A12: B. CALCULS
A13: Pointe du système | B13: MW | E13: ='09_GRID'!$C$7*'10_DEMAND'!E27/'10_DEMAND'!$C$99 -> 1539.3836 | F13: ='09_GRID'!$C$7*'10_DEMAND'!F27/'10_DEMAND'!$C$99 -> 1634.4698 | G13: ='09_GRID'!$C$7*'10_DEMAND'!G27/'10_DEMAND'!$C$99 -> 1735.6357 | H13: ='09_GRID'!$C$7*'10_DEMAND'!H27/'10_DEMAND'!$C$99 -> 1843.2842 | I13: ='09_GRID'!$C$7*'10_DEMAND'!I27/'10_DEMAND'!$C$99 -> 1957.846 | J13: ='09_GRID'!$C$7*'10_DEMAND'!J27/'10_DEMAND'!$C$99 -> 2079.7815 | K13: ='09_GRID'!$C$7*'10_DEMAND'!K27/'10_DEMAND'!$C$99 -> 2209.5828 | L13: ='09_GRID'!$C$7*'10_DEMAND'!L27/'10_DEMAND'!$C$99 -> 2347.7766 | ... AR13: ='09_GRID'!$C$7*'10_DEMAND'!AR27/'10_DEMAND'!$C$99 -> 17615.145
A14: Limite d'absorption à charge min. | B14: MW | E14: =MAX(0,'09_GRID'!E13*'09_GRID'!$C$8-'09_GRID'!$C$9)+'09_GRID'!$C$10 -> 723.63014 | F14: =MAX(0,'09_GRID'!F13*'09_GRID'!$C$8-'09_GRID'!$C$9)+'09_GRID'!$C$10 -> 780.68188 | G14: =MAX(0,'09_GRID'!G13*'09_GRID'!$C$8-'09_GRID'!$C$9)+'09_GRID'!$C$10 -> 841.38143 | H14: =MAX(0,'09_GRID'!H13*'09_GRID'!$C$8-'09_GRID'!$C$9)+'09_GRID'!$C$10 -> 905.97055 | I14: =MAX(0,'09_GRID'!I13*'09_GRID'!$C$8-'09_GRID'!$C$9)+'09_GRID'!$C$10 -> 974.70762 | J14: =MAX(0,'09_GRID'!J13*'09_GRID'!$C$8-'09_GRID'!$C$9)+'09_GRID'!$C$10 -> 1047.8689 | K14: =MAX(0,'09_GRID'!K13*'09_GRID'!$C$8-'09_GRID'!$C$9)+'09_GRID'!$C$10 -> 1125.7497 | L14: =MAX(0,'09_GRID'!L13*'09_GRID'!$C$8-'09_GRID'!$C$9)+'09_GRID'!$C$10 -> 1208.6659 | ... AR14: =MAX(0,'09_GRID'!AR13*'09_GRID'!$C$8-'09_GRID'!$C$9)+'09_GRID'!$C$10 -> 10369.087
A15: Capacité de ligne disponible pour le projet | B15: MW | E15: =IF('08_TRANSMISSION'!E30=1,'08_TRANSMISSION'!$C$10,'08_TRANSMISSION'!$C$19) -> 0 | F15: =IF('08_TRANSMISSION'!F30=1,'08_TRANSMISSION'!$C$10,'08_TRANSMISSION'!$C$19) -> 0 | G15: =IF('08_TRANSMISSION'!G30=1,'08_TRANSMISSION'!$C$10,'08_TRANSMISSION'!$C$19) -> 0 | H15: =IF('08_TRANSMISSION'!H30=1,'08_TRANSMISSION'!$C$10,'08_TRANSMISSION'!$C$19) -> 120 | I15: =IF('08_TRANSMISSION'!I30=1,'08_TRANSMISSION'!$C$10,'08_TRANSMISSION'!$C$19) -> 120 | J15: =IF('08_TRANSMISSION'!J30=1,'08_TRANSMISSION'!$C$10,'08_TRANSMISSION'!$C$19) -> 120 | K15: =IF('08_TRANSMISSION'!K30=1,'08_TRANSMISSION'!$C$10,'08_TRANSMISSION'!$C$19) -> 120 | L15: =IF('08_TRANSMISSION'!L30=1,'08_TRANSMISSION'!$C$10,'08_TRANSMISSION'!$C$19) -> 120 | ... AR15: =IF('08_TRANSMISSION'!AR30=1,'08_TRANSMISSION'!$C$10,'08_TRANSMISSION'!$C$19) -> 120
A16: Capacité d'évacuation effective = MIN(ligne, absorption) | B16: MW | E16: =MIN('09_GRID'!E15,'09_GRID'!E14) -> 0 | F16: =MIN('09_GRID'!F15,'09_GRID'!F14) -> 0 | G16: =MIN('09_GRID'!G15,'09_GRID'!G14) -> 0 | H16: =MIN('09_GRID'!H15,'09_GRID'!H14) -> 120 | I16: =MIN('09_GRID'!I15,'09_GRID'!I14) -> 120 | J16: =MIN('09_GRID'!J15,'09_GRID'!J14) -> 120 | K16: =MIN('09_GRID'!K15,'09_GRID'!K14) -> 120 | L16: =MIN('09_GRID'!L15,'09_GRID'!L14) -> 120 | ... AR16: =MIN('09_GRID'!AR15,'09_GRID'!AR14) -> 120
A17: Taux d'évacuation (plafonné à 1) | B17: x | E17: =MIN(1,'09_GRID'!E16/'02_PROJECT_INPUTS'!$C$15) -> 0 | F17: =MIN(1,'09_GRID'!F16/'02_PROJECT_INPUTS'!$C$15) -> 0 | G17: =MIN(1,'09_GRID'!G16/'02_PROJECT_INPUTS'!$C$15) -> 0 | H17: =MIN(1,'09_GRID'!H16/'02_PROJECT_INPUTS'!$C$15) -> 1 | I17: =MIN(1,'09_GRID'!I16/'02_PROJECT_INPUTS'!$C$15) -> 1 | J17: =MIN(1,'09_GRID'!J16/'02_PROJECT_INPUTS'!$C$15) -> 1 | K17: =MIN(1,'09_GRID'!K16/'02_PROJECT_INPUTS'!$C$15) -> 1 | L17: =MIN(1,'09_GRID'!L16/'02_PROJECT_INPUTS'!$C$15) -> 1 | ... AR17: =MIN(1,'09_GRID'!AR16/'02_PROJECT_INPUTS'!$C$15) -> 1
A18: Part projet dans la pointe | B18: % | E18: ='06_CONSTRUCTION'!E14*'02_PROJECT_INPUTS'!$C$15/'09_GRID'!E13 -> 0 | F18: ='06_CONSTRUCTION'!F14*'02_PROJECT_INPUTS'!$C$15/'09_GRID'!F13 -> 0 | G18: ='06_CONSTRUCTION'!G14*'02_PROJECT_INPUTS'!$C$15/'09_GRID'!G13 -> 0 | H18: ='06_CONSTRUCTION'!H14*'02_PROJECT_INPUTS'!$C$15/'09_GRID'!H13 -> 0.032550596 | I18: ='06_CONSTRUCTION'!I14*'02_PROJECT_INPUTS'!$C$15/'09_GRID'!I13 -> 0.030645924 | J18: ='06_CONSTRUCTION'!J14*'02_PROJECT_INPUTS'!$C$15/'09_GRID'!J13 -> 0.028849185 | K18: ='06_CONSTRUCTION'!K14*'02_PROJECT_INPUTS'!$C$15/'09_GRID'!K13 -> 0.027154447 | L18: ='06_CONSTRUCTION'!L14*'02_PROJECT_INPUTS'!$C$15/'09_GRID'!L13 -> 0.025556094 | ... AR18: ='06_CONSTRUCTION'!AR14*'02_PROJECT_INPUTS'!$C$15/'09_GRID'!AR13 -> 0
A19: Marge de réserve, projet inclus | B19: % | E19: =('09_GRID'!$C$11+'02_PROJECT_INPUTS'!$C$15*'06_CONSTRUCTION'!E14-'09_GRID'!E13)/'09_GRID'!E13 -> 0.36418242 | F19: =('09_GRID'!$C$11+'02_PROJECT_INPUTS'!$C$15*'06_CONSTRUCTION'!F14-'09_GRID'!F13)/'09_GRID'!F13 -> 0.28482032 | G19: =('09_GRID'!$C$11+'02_PROJECT_INPUTS'!$C$15*'06_CONSTRUCTION'!G14-'09_GRID'!G13)/'09_GRID'!G13 -> 0.20993131 | H19: =('09_GRID'!$C$11+'02_PROJECT_INPUTS'!$C$15*'06_CONSTRUCTION'!H14-'09_GRID'!H13)/'09_GRID'!H13 -> 0.17182144 | I19: =('09_GRID'!$C$11+'02_PROJECT_INPUTS'!$C$15*'06_CONSTRUCTION'!I14-'09_GRID'!I13)/'09_GRID'!I13 -> 0.10325325 | J19: =('09_GRID'!$C$11+'02_PROJECT_INPUTS'!$C$15*'06_CONSTRUCTION'!J14-'09_GRID'!J13)/'09_GRID'!J13 -> 0.038570652 | K19: =('09_GRID'!$C$11+'02_PROJECT_INPUTS'!$C$15*'06_CONSTRUCTION'!K14-'09_GRID'!K13)/'09_GRID'!K13 -> -0.022439909 | L19: =('09_GRID'!$C$11+'02_PROJECT_INPUTS'!$C$15*'06_CONSTRUCTION'!L14-'09_GRID'!L13)/'09_GRID'!L13 -> -0.079980599 | ... AR19: =('09_GRID'!$C$11+'02_PROJECT_INPUTS'!$C$15*'06_CONSTRUCTION'!AR14-'09_GRID'!AR13)/'09_GRID'!AR13 -> -0.8807844
A20: Capacité d'évacuation la 1re année d'exploitation | B20: MW | C20: =SUM('09_GRID'!$E$20:$AR$20) -> 120 | E20: =IF('06_CONSTRUCTION'!E5=1,'09_GRID'!E16,0) -> 0 | F20: =IF('06_CONSTRUCTION'!F5=1,'09_GRID'!F16,0) -> 0 | G20: =IF('06_CONSTRUCTION'!G5=1,'09_GRID'!G16,0) -> 0 | H20: =IF('06_CONSTRUCTION'!H5=1,'09_GRID'!H16,0) -> 120 | I20: =IF('06_CONSTRUCTION'!I5=1,'09_GRID'!I16,0) -> 0 | J20: =IF('06_CONSTRUCTION'!J5=1,'09_GRID'!J16,0) -> 0 | K20: =IF('06_CONSTRUCTION'!K5=1,'09_GRID'!K16,0) -> 0 | L20: =IF('06_CONSTRUCTION'!L5=1,'09_GRID'!L16,0) -> 0 | ... AR20: =IF('06_CONSTRUCTION'!AR5=1,'09_GRID'!AR16,0) -> 0
A21: Part du projet dans la pointe la 1re année d'exploitation | B21: % | C21: =SUM('09_GRID'!$E$21:$AR$21) -> 0.032550596 | E21: =IF('06_CONSTRUCTION'!E5=1,'09_GRID'!E18,0) -> 0 | F21: =IF('06_CONSTRUCTION'!F5=1,'09_GRID'!F18,0) -> 0 | G21: =IF('06_CONSTRUCTION'!G5=1,'09_GRID'!G18,0) -> 0 | H21: =IF('06_CONSTRUCTION'!H5=1,'09_GRID'!H18,0) -> 0.032550596 | I21: =IF('06_CONSTRUCTION'!I5=1,'09_GRID'!I18,0) -> 0 | J21: =IF('06_CONSTRUCTION'!J5=1,'09_GRID'!J18,0) -> 0 | K21: =IF('06_CONSTRUCTION'!K5=1,'09_GRID'!K18,0) -> 0 | L21: =IF('06_CONSTRUCTION'!L5=1,'09_GRID'!L18,0) -> 0 | ... AR21: =IF('06_CONSTRUCTION'!AR5=1,'09_GRID'!AR18,0) -> 0
A23: Simplification d'écrêtement proportionnel : livré = production x MIN(1, MW évacuables / MW installés). Prudent pour les centrales de pointe avec retenue ; remplacer par une simulation de dispatching si disponible.

Sheet 10_DEMAND
A1: 10 DEMANDE — Demande potentielle, commerciale, contractuelle et bancable
A2: Croissance par segment selon le cas ; « bancable » = contractuelle ET absorbable par une demande solvable
A6: A. DONNÉES PAR SEGMENT (année de base 2026)
A7: Segment | B7: GWh 2026 | C7: Croiss. base | E7: Croiss. basse | F7: Croiss. haute | G7: Part commerciale
A8: Résidentiel | B8: 2600 | C8: 0.07 | E8: 0.05 | F8: 0.085 | G8: 0.75
A9: Commercial | B9: 1400 | C9: 0.06 | E9: 0.045 | F9: 0.075 | G9: 0.92
A10: Industriel | B10: 1500 | C10: 0.05 | E10: 0.03 | F10: 0.065 | G10: 0.95
A11: Mines | B11: 1100 | C11: 0.06 | E11: 0.02 | F11: 0.09 | G11: 0.98
A12: Usages productifs (agro-transformation, etc.) | B12: 250 | C12: 0.1 | E12: 0.06 | F12: 0.14 | G12: 0.7
A13: Secteur public | B13: 450 | C13: 0.04 | E13: 0.03 | F13: 0.05 | G13: 0.65
A14: Valeurs fictives. Part commerciale = part de la demande du segment issue de clients capables et disposés à payer des tarifs reflétant les coûts (hypothèse).
A15: Potentiel d'export via le pool énergétique régional | B15: GWh/an | C15: 600 | D15: Potentiel seulement
A16: Ventes à l'export contractées (signées) | B16: GWh/an | C16: 0
A17: Offre intérieure garantie existante (2026) | B17: GWh/an | C17: 8600 | D17: Y c. centrales engagées ; fictif
A18: Croissance des autres sources disponibles pour la compagnie (engagées + prévues) | B18: % p.a. | C18: 0.045 | D18: Plafonne les ventes : la demande au-delà de l'offre disponible n'est pas servie
A19: Production thermique existante substituable | B19: GWh/an | C19: 500 | D19: Diesel/fioul que l'hydro peut remplacer
A20: B. PROJECTION DE LA DEMANDE (GWh)
A21: Résidentiel | B21: GWh | E21: =$B$8*(1+CHOOSE('01_CONTROL_PANEL'!$C$5,$C$8,$E$8,$F$8)+'27_SCENARIOS'!$C$29)^('06_CONSTRUCTION'!E4-'02_PROJECT_INPUTS'!$C$11)*IF('06_CONSTRUCTION'!E4>='06_CONSTRUCTION'!$C$8,'27_SCENARIOS'!$C$30,1) -> 2782 | F21: =$B$8*(1+CHOOSE('01_CONTROL_PANEL'!$C$5,$C$8,$E$8,$F$8)+'27_SCENARIOS'!$C$29)^('06_CONSTRUCTION'!F4-'02_PROJECT_INPUTS'!$C$11)*IF('06_CONSTRUCTION'!F4>='06_CONSTRUCTION'!$C$8,'27_SCENARIOS'!$C$30,1) -> 2976.74 | G21: =$B$8*(1+CHOOSE('01_CONTROL_PANEL'!$C$5,$C$8,$E$8,$F$8)+'27_SCENARIOS'!$C$29)^('06_CONSTRUCTION'!G4-'02_PROJECT_INPUTS'!$C$11)*IF('06_CONSTRUCTION'!G4>='06_CONSTRUCTION'!$C$8,'27_SCENARIOS'!$C$30,1) -> 3185.1118 | H21: =$B$8*(1+CHOOSE('01_CONTROL_PANEL'!$C$5,$C$8,$E$8,$F$8)+'27_SCENARIOS'!$C$29)^('06_CONSTRUCTION'!H4-'02_PROJECT_INPUTS'!$C$11)*IF('06_CONSTRUCTION'!H4>='06_CONSTRUCTION'!$C$8,'27_SCENARIOS'!$C$30,1) -> 3408.0696 | I21: =$B$8*(1+CHOOSE('01_CONTROL_PANEL'!$C$5,$C$8,$E$8,$F$8)+'27_SCENARIOS'!$C$29)^('06_CONSTRUCTION'!I4-'02_PROJECT_INPUTS'!$C$11)*IF('06_CONSTRUCTION'!I4>='06_CONSTRUCTION'!$C$8,'27_SCENARIOS'!$C$30,1) -> 3646.6345 | J21: =$B$8*(1+CHOOSE('01_CONTROL_PANEL'!$C$5,$C$8,$E$8,$F$8)+'27_SCENARIOS'!$C$29)^('06_CONSTRUCTION'!J4-'02_PROJECT_INPUTS'!$C$11)*IF('06_CONSTRUCTION'!J4>='06_CONSTRUCTION'!$C$8,'27_SCENARIOS'!$C$30,1) -> 3901.8989 | K21: =$B$8*(1+CHOOSE('01_CONTROL_PANEL'!$C$5,$C$8,$E$8,$F$8)+'27_SCENARIOS'!$C$29)^('06_CONSTRUCTION'!K4-'02_PROJECT_INPUTS'!$C$11)*IF('06_CONSTRUCTION'!K4>='06_CONSTRUCTION'!$C$8,'27_SCENARIOS'!$C$30,1) -> 4175.0318 | L21: =$B$8*(1+CHOOSE('01_CONTROL_PANEL'!$C$5,$C$8,$E$8,$F$8)+'27_SCENARIOS'!$C$29)^('06_CONSTRUCTION'!L4-'02_PROJECT_INPUTS'!$C$11)*IF('06_CONSTRUCTION'!L4>='06_CONSTRUCTION'!$C$8,'27_SCENARIOS'!$C$30,1) -> 4467.2841 | ... AR21: =$B$8*(1+CHOOSE('01_CONTROL_PANEL'!$C$5,$C$8,$E$8,$F$8)+'27_SCENARIOS'!$C$29)^('06_CONSTRUCTION'!AR4-'02_PROJECT_INPUTS'!$C$11)*IF('06_CONSTRUCTION'!AR4>='06_CONSTRUCTION'!$C$8,'27_SCENARIOS'!$C$30,1) -> 38933.59
A22: Commercial | B22: GWh | E22: =$B$9*(1+CHOOSE('01_CONTROL_PANEL'!$C$5,$C$9,$E$9,$F$9)+'27_SCENARIOS'!$C$29)^('06_CONSTRUCTION'!E4-'02_PROJECT_INPUTS'!$C$11)*IF('06_CONSTRUCTION'!E4>='06_CONSTRUCTION'!$C$8,'27_SCENARIOS'!$C$30,1) -> 1484 | F22: =$B$9*(1+CHOOSE('01_CONTROL_PANEL'!$C$5,$C$9,$E$9,$F$9)+'27_SCENARIOS'!$C$29)^('06_CONSTRUCTION'!F4-'02_PROJECT_INPUTS'!$C$11)*IF('06_CONSTRUCTION'!F4>='06_CONSTRUCTION'!$C$8,'27_SCENARIOS'!$C$30,1) -> 1573.04 | G22: =$B$9*(1+CHOOSE('01_CONTROL_PANEL'!$C$5,$C$9,$E$9,$F$9)+'27_SCENARIOS'!$C$29)^('06_CONSTRUCTION'!G4-'02_PROJECT_INPUTS'!$C$11)*IF('06_CONSTRUCTION'!G4>='06_CONSTRUCTION'!$C$8,'27_SCENARIOS'!$C$30,1) -> 1667.4224 | H22: =$B$9*(1+CHOOSE('01_CONTROL_PANEL'!$C$5,$C$9,$E$9,$F$9)+'27_SCENARIOS'!$C$29)^('06_CONSTRUCTION'!H4-'02_PROJECT_INPUTS'!$C$11)*IF('06_CONSTRUCTION'!H4>='06_CONSTRUCTION'!$C$8,'27_SCENARIOS'!$C$30,1) -> 1767.4677 | I22: =$B$9*(1+CHOOSE('01_CONTROL_PANEL'!$C$5,$C$9,$E$9,$F$9)+'27_SCENARIOS'!$C$29)^('06_CONSTRUCTION'!I4-'02_PROJECT_INPUTS'!$C$11)*IF('06_CONSTRUCTION'!I4>='06_CONSTRUCTION'!$C$8,'27_SCENARIOS'!$C$30,1) -> 1873.5158 | J22: =$B$9*(1+CHOOSE('01_CONTROL_PANEL'!$C$5,$C$9,$E$9,$F$9)+'27_SCENARIOS'!$C$29)^('06_CONSTRUCTION'!J4-'02_PROJECT_INPUTS'!$C$11)*IF('06_CONSTRUCTION'!J4>='06_CONSTRUCTION'!$C$8,'27_SCENARIOS'!$C$30,1) -> 1985.9268 | K22: =$B$9*(1+CHOOSE('01_CONTROL_PANEL'!$C$5,$C$9,$E$9,$F$9)+'27_SCENARIOS'!$C$29)^('06_CONSTRUCTION'!K4-'02_PROJECT_INPUTS'!$C$11)*IF('06_CONSTRUCTION'!K4>='06_CONSTRUCTION'!$C$8,'27_SCENARIOS'!$C$30,1) -> 2105.0824 | L22: =$B$9*(1+CHOOSE('01_CONTROL_PANEL'!$C$5,$C$9,$E$9,$F$9)+'27_SCENARIOS'!$C$29)^('06_CONSTRUCTION'!L4-'02_PROJECT_INPUTS'!$C$11)*IF('06_CONSTRUCTION'!L4>='06_CONSTRUCTION'!$C$8,'27_SCENARIOS'!$C$30,1) -> 2231.3873 | ... AR22: =$B$9*(1+CHOOSE('01_CONTROL_PANEL'!$C$5,$C$9,$E$9,$F$9)+'27_SCENARIOS'!$C$29)^('06_CONSTRUCTION'!AR4-'02_PROJECT_INPUTS'!$C$11)*IF('06_CONSTRUCTION'!AR4>='06_CONSTRUCTION'!$C$8,'27_SCENARIOS'!$C$30,1) -> 14400.005
A23: Industriel | B23: GWh | E23: =$B$10*(1+CHOOSE('01_CONTROL_PANEL'!$C$5,$C$10,$E$10,$F$10)+'27_SCENARIOS'!$C$29)^('06_CONSTRUCTION'!E4-'02_PROJECT_INPUTS'!$C$11)*IF('06_CONSTRUCTION'!E4>='06_CONSTRUCTION'!$C$8,'27_SCENARIOS'!$C$30,1) -> 1575 | F23: =$B$10*(1+CHOOSE('01_CONTROL_PANEL'!$C$5,$C$10,$E$10,$F$10)+'27_SCENARIOS'!$C$29)^('06_CONSTRUCTION'!F4-'02_PROJECT_INPUTS'!$C$11)*IF('06_CONSTRUCTION'!F4>='06_CONSTRUCTION'!$C$8,'27_SCENARIOS'!$C$30,1) -> 1653.75 | G23: =$B$10*(1+CHOOSE('01_CONTROL_PANEL'!$C$5,$C$10,$E$10,$F$10)+'27_SCENARIOS'!$C$29)^('06_CONSTRUCTION'!G4-'02_PROJECT_INPUTS'!$C$11)*IF('06_CONSTRUCTION'!G4>='06_CONSTRUCTION'!$C$8,'27_SCENARIOS'!$C$30,1) -> 1736.4375 | H23: =$B$10*(1+CHOOSE('01_CONTROL_PANEL'!$C$5,$C$10,$E$10,$F$10)+'27_SCENARIOS'!$C$29)^('06_CONSTRUCTION'!H4-'02_PROJECT_INPUTS'!$C$11)*IF('06_CONSTRUCTION'!H4>='06_CONSTRUCTION'!$C$8,'27_SCENARIOS'!$C$30,1) -> 1823.2594 | I23: =$B$10*(1+CHOOSE('01_CONTROL_PANEL'!$C$5,$C$10,$E$10,$F$10)+'27_SCENARIOS'!$C$29)^('06_CONSTRUCTION'!I4-'02_PROJECT_INPUTS'!$C$11)*IF('06_CONSTRUCTION'!I4>='06_CONSTRUCTION'!$C$8,'27_SCENARIOS'!$C$30,1) -> 1914.4223 | J23: =$B$10*(1+CHOOSE('01_CONTROL_PANEL'!$C$5,$C$10,$E$10,$F$10)+'27_SCENARIOS'!$C$29)^('06_CONSTRUCTION'!J4-'02_PROJECT_INPUTS'!$C$11)*IF('06_CONSTRUCTION'!J4>='06_CONSTRUCTION'!$C$8,'27_SCENARIOS'!$C$30,1) -> 2010.1435 | K23: =$B$10*(1+CHOOSE('01_CONTROL_PANEL'!$C$5,$C$10,$E$10,$F$10)+'27_SCENARIOS'!$C$29)^('06_CONSTRUCTION'!K4-'02_PROJECT_INPUTS'!$C$11)*IF('06_CONSTRUCTION'!K4>='06_CONSTRUCTION'!$C$8,'27_SCENARIOS'!$C$30,1) -> 2110.6506 | L23: =$B$10*(1+CHOOSE('01_CONTROL_PANEL'!$C$5,$C$10,$E$10,$F$10)+'27_SCENARIOS'!$C$29)^('06_CONSTRUCTION'!L4-'02_PROJECT_INPUTS'!$C$11)*IF('06_CONSTRUCTION'!L4>='06_CONSTRUCTION'!$C$8,'27_SCENARIOS'!$C$30,1) -> 2216.1832 | ... AR23: =$B$10*(1+CHOOSE('01_CONTROL_PANEL'!$C$5,$C$10,$E$10,$F$10)+'27_SCENARIOS'!$C$29)^('06_CONSTRUCTION'!AR4-'02_PROJECT_INPUTS'!$C$11)*IF('06_CONSTRUCTION'!AR4>='06_CONSTRUCTION'!$C$8,'27_SCENARIOS'!$C$30,1) -> 10559.983
A24: Mines | B24: GWh | E24: =$B$11*(1+CHOOSE('01_CONTROL_PANEL'!$C$5,$C$11,$E$11,$F$11)+'27_SCENARIOS'!$C$29)^('06_CONSTRUCTION'!E4-'02_PROJECT_INPUTS'!$C$11)*IF('06_CONSTRUCTION'!E4>='06_CONSTRUCTION'!$C$8,'27_SCENARIOS'!$C$30,1) -> 1166 | F24: =$B$11*(1+CHOOSE('01_CONTROL_PANEL'!$C$5,$C$11,$E$11,$F$11)+'27_SCENARIOS'!$C$29)^('06_CONSTRUCTION'!F4-'02_PROJECT_INPUTS'!$C$11)*IF('06_CONSTRUCTION'!F4>='06_CONSTRUCTION'!$C$8,'27_SCENARIOS'!$C$30,1) -> 1235.96 | G24: =$B$11*(1+CHOOSE('01_CONTROL_PANEL'!$C$5,$C$11,$E$11,$F$11)+'27_SCENARIOS'!$C$29)^('06_CONSTRUCTION'!G4-'02_PROJECT_INPUTS'!$C$11)*IF('06_CONSTRUCTION'!G4>='06_CONSTRUCTION'!$C$8,'27_SCENARIOS'!$C$30,1) -> 1310.1176 | H24: =$B$11*(1+CHOOSE('01_CONTROL_PANEL'!$C$5,$C$11,$E$11,$F$11)+'27_SCENARIOS'!$C$29)^('06_CONSTRUCTION'!H4-'02_PROJECT_INPUTS'!$C$11)*IF('06_CONSTRUCTION'!H4>='06_CONSTRUCTION'!$C$8,'27_SCENARIOS'!$C$30,1) -> 1388.7247 | I24: =$B$11*(1+CHOOSE('01_CONTROL_PANEL'!$C$5,$C$11,$E$11,$F$11)+'27_SCENARIOS'!$C$29)^('06_CONSTRUCTION'!I4-'02_PROJECT_INPUTS'!$C$11)*IF('06_CONSTRUCTION'!I4>='06_CONSTRUCTION'!$C$8,'27_SCENARIOS'!$C$30,1) -> 1472.0481 | J24: =$B$11*(1+CHOOSE('01_CONTROL_PANEL'!$C$5,$C$11,$E$11,$F$11)+'27_SCENARIOS'!$C$29)^('06_CONSTRUCTION'!J4-'02_PROJECT_INPUTS'!$C$11)*IF('06_CONSTRUCTION'!J4>='06_CONSTRUCTION'!$C$8,'27_SCENARIOS'!$C$30,1) -> 1560.371 | K24: =$B$11*(1+CHOOSE('01_CONTROL_PANEL'!$C$5,$C$11,$E$11,$F$11)+'27_SCENARIOS'!$C$29)^('06_CONSTRUCTION'!K4-'02_PROJECT_INPUTS'!$C$11)*IF('06_CONSTRUCTION'!K4>='06_CONSTRUCTION'!$C$8,'27_SCENARIOS'!$C$30,1) -> 1653.9933 | L24: =$B$11*(1+CHOOSE('01_CONTROL_PANEL'!$C$5,$C$11,$E$11,$F$11)+'27_SCENARIOS'!$C$29)^('06_CONSTRUCTION'!L4-'02_PROJECT_INPUTS'!$C$11)*IF('06_CONSTRUCTION'!L4>='06_CONSTRUCTION'!$C$8,'27_SCENARIOS'!$C$30,1) -> 1753.2329 | ... AR24: =$B$11*(1+CHOOSE('01_CONTROL_PANEL'!$C$5,$C$11,$E$11,$F$11)+'27_SCENARIOS'!$C$29)^('06_CONSTRUCTION'!AR4-'02_PROJECT_INPUTS'!$C$11)*IF('06_CONSTRUCTION'!AR4>='06_CONSTRUCTION'!$C$8,'27_SCENARIOS'!$C$30,1) -> 11314.29
A25: Usages productifs (agro-transformation, etc.) | B25: GWh | E25: =$B$12*(1+CHOOSE('01_CONTROL_PANEL'!$C$5,$C$12,$E$12,$F$12)+'27_SCENARIOS'!$C$29)^('06_CONSTRUCTION'!E4-'02_PROJECT_INPUTS'!$C$11)*IF('06_CONSTRUCTION'!E4>='06_CONSTRUCTION'!$C$8,'27_SCENARIOS'!$C$30,1) -> 275 | F25: =$B$12*(1+CHOOSE('01_CONTROL_PANEL'!$C$5,$C$12,$E$12,$F$12)+'27_SCENARIOS'!$C$29)^('06_CONSTRUCTION'!F4-'02_PROJECT_INPUTS'!$C$11)*IF('06_CONSTRUCTION'!F4>='06_CONSTRUCTION'!$C$8,'27_SCENARIOS'!$C$30,1) -> 302.5 | G25: =$B$12*(1+CHOOSE('01_CONTROL_PANEL'!$C$5,$C$12,$E$12,$F$12)+'27_SCENARIOS'!$C$29)^('06_CONSTRUCTION'!G4-'02_PROJECT_INPUTS'!$C$11)*IF('06_CONSTRUCTION'!G4>='06_CONSTRUCTION'!$C$8,'27_SCENARIOS'!$C$30,1) -> 332.75 | H25: =$B$12*(1+CHOOSE('01_CONTROL_PANEL'!$C$5,$C$12,$E$12,$F$12)+'27_SCENARIOS'!$C$29)^('06_CONSTRUCTION'!H4-'02_PROJECT_INPUTS'!$C$11)*IF('06_CONSTRUCTION'!H4>='06_CONSTRUCTION'!$C$8,'27_SCENARIOS'!$C$30,1) -> 366.025 | I25: =$B$12*(1+CHOOSE('01_CONTROL_PANEL'!$C$5,$C$12,$E$12,$F$12)+'27_SCENARIOS'!$C$29)^('06_CONSTRUCTION'!I4-'02_PROJECT_INPUTS'!$C$11)*IF('06_CONSTRUCTION'!I4>='06_CONSTRUCTION'!$C$8,'27_SCENARIOS'!$C$30,1) -> 402.6275 | J25: =$B$12*(1+CHOOSE('01_CONTROL_PANEL'!$C$5,$C$12,$E$12,$F$12)+'27_SCENARIOS'!$C$29)^('06_CONSTRUCTION'!J4-'02_PROJECT_INPUTS'!$C$11)*IF('06_CONSTRUCTION'!J4>='06_CONSTRUCTION'!$C$8,'27_SCENARIOS'!$C$30,1) -> 442.89025 | K25: =$B$12*(1+CHOOSE('01_CONTROL_PANEL'!$C$5,$C$12,$E$12,$F$12)+'27_SCENARIOS'!$C$29)^('06_CONSTRUCTION'!K4-'02_PROJECT_INPUTS'!$C$11)*IF('06_CONSTRUCTION'!K4>='06_CONSTRUCTION'!$C$8,'27_SCENARIOS'!$C$30,1) -> 487.17928 | L25: =$B$12*(1+CHOOSE('01_CONTROL_PANEL'!$C$5,$C$12,$E$12,$F$12)+'27_SCENARIOS'!$C$29)^('06_CONSTRUCTION'!L4-'02_PROJECT_INPUTS'!$C$11)*IF('06_CONSTRUCTION'!L4>='06_CONSTRUCTION'!$C$8,'27_SCENARIOS'!$C$30,1) -> 535.8972 | ... AR25: =$B$12*(1+CHOOSE('01_CONTROL_PANEL'!$C$5,$C$12,$E$12,$F$12)+'27_SCENARIOS'!$C$29)^('06_CONSTRUCTION'!AR4-'02_PROJECT_INPUTS'!$C$11)*IF('06_CONSTRUCTION'!AR4>='06_CONSTRUCTION'!$C$8,'27_SCENARIOS'!$C$30,1) -> 11314.814
A26: Secteur public | B26: GWh | E26: =$B$13*(1+CHOOSE('01_CONTROL_PANEL'!$C$5,$C$13,$E$13,$F$13)+'27_SCENARIOS'!$C$29)^('06_CONSTRUCTION'!E4-'02_PROJECT_INPUTS'!$C$11)*IF('06_CONSTRUCTION'!E4>='06_CONSTRUCTION'!$C$8,'27_SCENARIOS'!$C$30,1) -> 468 | F26: =$B$13*(1+CHOOSE('01_CONTROL_PANEL'!$C$5,$C$13,$E$13,$F$13)+'27_SCENARIOS'!$C$29)^('06_CONSTRUCTION'!F4-'02_PROJECT_INPUTS'!$C$11)*IF('06_CONSTRUCTION'!F4>='06_CONSTRUCTION'!$C$8,'27_SCENARIOS'!$C$30,1) -> 486.72 | G26: =$B$13*(1+CHOOSE('01_CONTROL_PANEL'!$C$5,$C$13,$E$13,$F$13)+'27_SCENARIOS'!$C$29)^('06_CONSTRUCTION'!G4-'02_PROJECT_INPUTS'!$C$11)*IF('06_CONSTRUCTION'!G4>='06_CONSTRUCTION'!$C$8,'27_SCENARIOS'!$C$30,1) -> 506.1888 | H26: =$B$13*(1+CHOOSE('01_CONTROL_PANEL'!$C$5,$C$13,$E$13,$F$13)+'27_SCENARIOS'!$C$29)^('06_CONSTRUCTION'!H4-'02_PROJECT_INPUTS'!$C$11)*IF('06_CONSTRUCTION'!H4>='06_CONSTRUCTION'!$C$8,'27_SCENARIOS'!$C$30,1) -> 526.43635 | I26: =$B$13*(1+CHOOSE('01_CONTROL_PANEL'!$C$5,$C$13,$E$13,$F$13)+'27_SCENARIOS'!$C$29)^('06_CONSTRUCTION'!I4-'02_PROJECT_INPUTS'!$C$11)*IF('06_CONSTRUCTION'!I4>='06_CONSTRUCTION'!$C$8,'27_SCENARIOS'!$C$30,1) -> 547.49381 | J26: =$B$13*(1+CHOOSE('01_CONTROL_PANEL'!$C$5,$C$13,$E$13,$F$13)+'27_SCENARIOS'!$C$29)^('06_CONSTRUCTION'!J4-'02_PROJECT_INPUTS'!$C$11)*IF('06_CONSTRUCTION'!J4>='06_CONSTRUCTION'!$C$8,'27_SCENARIOS'!$C$30,1) -> 569.39356 | K26: =$B$13*(1+CHOOSE('01_CONTROL_PANEL'!$C$5,$C$13,$E$13,$F$13)+'27_SCENARIOS'!$C$29)^('06_CONSTRUCTION'!K4-'02_PROJECT_INPUTS'!$C$11)*IF('06_CONSTRUCTION'!K4>='06_CONSTRUCTION'!$C$8,'27_SCENARIOS'!$C$30,1) -> 592.1693 | L26: =$B$13*(1+CHOOSE('01_CONTROL_PANEL'!$C$5,$C$13,$E$13,$F$13)+'27_SCENARIOS'!$C$29)^('06_CONSTRUCTION'!L4-'02_PROJECT_INPUTS'!$C$11)*IF('06_CONSTRUCTION'!L4>='06_CONSTRUCTION'!$C$8,'27_SCENARIOS'!$C$30,1) -> 615.85607 | ... AR26: =$B$13*(1+CHOOSE('01_CONTROL_PANEL'!$C$5,$C$13,$E$13,$F$13)+'27_SCENARIOS'!$C$29)^('06_CONSTRUCTION'!AR4-'02_PROJECT_INPUTS'!$C$11)*IF('06_CONSTRUCTION'!AR4>='06_CONSTRUCTION'!$C$8,'27_SCENARIOS'!$C$30,1) -> 2160.4593
A27: Demande intérieure totale (potentielle, au compteur client) | B27: GWh | E27: ='10_DEMAND'!E21+'10_DEMAND'!E22+'10_DEMAND'!E23+'10_DEMAND'!E24+'10_DEMAND'!E25+'10_DEMAND'!E26 -> 7750 | F27: ='10_DEMAND'!F21+'10_DEMAND'!F22+'10_DEMAND'!F23+'10_DEMAND'!F24+'10_DEMAND'!F25+'10_DEMAND'!F26 -> 8228.71 | G27: ='10_DEMAND'!G21+'10_DEMAND'!G22+'10_DEMAND'!G23+'10_DEMAND'!G24+'10_DEMAND'!G25+'10_DEMAND'!G26 -> 8738.0281 | H27: ='10_DEMAND'!H21+'10_DEMAND'!H22+'10_DEMAND'!H23+'10_DEMAND'!H24+'10_DEMAND'!H25+'10_DEMAND'!H26 -> 9279.9828 | I27: ='10_DEMAND'!I21+'10_DEMAND'!I22+'10_DEMAND'!I23+'10_DEMAND'!I24+'10_DEMAND'!I25+'10_DEMAND'!I26 -> 9856.7421 | J27: ='10_DEMAND'!J21+'10_DEMAND'!J22+'10_DEMAND'!J23+'10_DEMAND'!J24+'10_DEMAND'!J25+'10_DEMAND'!J26 -> 10470.624 | K27: ='10_DEMAND'!K21+'10_DEMAND'!K22+'10_DEMAND'!K23+'10_DEMAND'!K24+'10_DEMAND'!K25+'10_DEMAND'!K26 -> 11124.107 | L27: ='10_DEMAND'!L21+'10_DEMAND'!L22+'10_DEMAND'!L23+'10_DEMAND'!L24+'10_DEMAND'!L25+'10_DEMAND'!L26 -> 11819.841 | ... AR27: ='10_DEMAND'!AR21+'10_DEMAND'!AR22+'10_DEMAND'!AR23+'10_DEMAND'!AR24+'10_DEMAND'!AR25+'10_DEMAND'!AR26 -> 88683.141
A28: Demande POTENTIELLE, export potentiel inclus | B28: GWh | E28: ='10_DEMAND'!E27+'10_DEMAND'!$C$15 -> 8350 | F28: ='10_DEMAND'!F27+'10_DEMAND'!$C$15 -> 8828.71 | G28: ='10_DEMAND'!G27+'10_DEMAND'!$C$15 -> 9338.0281 | H28: ='10_DEMAND'!H27+'10_DEMAND'!$C$15 -> 9879.9828 | I28: ='10_DEMAND'!I27+'10_DEMAND'!$C$15 -> 10456.742 | J28: ='10_DEMAND'!J27+'10_DEMAND'!$C$15 -> 11070.624 | K28: ='10_DEMAND'!K27+'10_DEMAND'!$C$15 -> 11724.107 | L28: ='10_DEMAND'!L27+'10_DEMAND'!$C$15 -> 12419.841 | ... AR28: ='10_DEMAND'!AR27+'10_DEMAND'!$C$15 -> 89283.141
A29: Demande COMMERCIALE (pondérée par la capacité de payer) | B29: GWh | E29: ='10_DEMAND'!E21*'10_DEMAND'!$G$8+'10_DEMAND'!E22*'10_DEMAND'!$G$9+'10_DEMAND'!E23*'10_DEMAND'!$G$10+'10_DEMAND'!E24*'10_DEMAND'!$G$11+'10_DEMAND'!E25*'10_DEMAND'!$G$12+'10_DEMAND'!E26*'10_DEMAND'!$G$13+'10_DEMAND'!$C$16 -> 6587.41 | F29: ='10_DEMAND'!F21*'10_DEMAND'!$G$8+'10_DEMAND'!F22*'10_DEMAND'!$G$9+'10_DEMAND'!F23*'10_DEMAND'!$G$10+'10_DEMAND'!F24*'10_DEMAND'!$G$11+'10_DEMAND'!F25*'10_DEMAND'!$G$12+'10_DEMAND'!F26*'10_DEMAND'!$G$13+'10_DEMAND'!$C$16 -> 6990.1731 | G29: ='10_DEMAND'!G21*'10_DEMAND'!$G$8+'10_DEMAND'!G22*'10_DEMAND'!$G$9+'10_DEMAND'!G23*'10_DEMAND'!$G$10+'10_DEMAND'!G24*'10_DEMAND'!$G$11+'10_DEMAND'!G25*'10_DEMAND'!$G$12+'10_DEMAND'!G26*'10_DEMAND'!$G$13+'10_DEMAND'!$C$16 -> 7418.3411 | H29: ='10_DEMAND'!H21*'10_DEMAND'!$G$8+'10_DEMAND'!H22*'10_DEMAND'!$G$9+'10_DEMAND'!H23*'10_DEMAND'!$G$10+'10_DEMAND'!H24*'10_DEMAND'!$G$11+'10_DEMAND'!H25*'10_DEMAND'!$G$12+'10_DEMAND'!H26*'10_DEMAND'!$G$13+'10_DEMAND'!$C$16 -> 7873.5702 | I29: ='10_DEMAND'!I21*'10_DEMAND'!$G$8+'10_DEMAND'!I22*'10_DEMAND'!$G$9+'10_DEMAND'!I23*'10_DEMAND'!$G$10+'10_DEMAND'!I24*'10_DEMAND'!$G$11+'10_DEMAND'!I25*'10_DEMAND'!$G$12+'10_DEMAND'!I26*'10_DEMAND'!$G$13+'10_DEMAND'!$C$16 -> 8357.629 | J29: ='10_DEMAND'!J21*'10_DEMAND'!$G$8+'10_DEMAND'!J22*'10_DEMAND'!$G$9+'10_DEMAND'!J23*'10_DEMAND'!$G$10+'10_DEMAND'!J24*'10_DEMAND'!$G$11+'10_DEMAND'!J25*'10_DEMAND'!$G$12+'10_DEMAND'!J26*'10_DEMAND'!$G$13+'10_DEMAND'!$C$16 -> 8872.4057 | K29: ='10_DEMAND'!K21*'10_DEMAND'!$G$8+'10_DEMAND'!K22*'10_DEMAND'!$G$9+'10_DEMAND'!K23*'10_DEMAND'!$G$10+'10_DEMAND'!K24*'10_DEMAND'!$G$11+'10_DEMAND'!K25*'10_DEMAND'!$G$12+'10_DEMAND'!K26*'10_DEMAND'!$G$13+'10_DEMAND'!$C$16 -> 9419.9167 | L29: ='10_DEMAND'!L21*'10_DEMAND'!$G$8+'10_DEMAND'!L22*'10_DEMAND'!$G$9+'10_DEMAND'!L23*'10_DEMAND'!$G$10+'10_DEMAND'!L24*'10_DEMAND'!$G$11+'10_DEMAND'!L25*'10_DEMAND'!$G$12+'10_DEMAND'!L26*'10_DEMAND'!$G$13+'10_DEMAND'!$C$16 -> 10002.316 | ... AR29: ='10_DEMAND'!AR21*'10_DEMAND'!$G$8+'10_DEMAND'!AR22*'10_DEMAND'!$G$9+'10_DEMAND'!AR23*'10_DEMAND'!$G$10+'10_DEMAND'!AR24*'10_DEMAND'!$G$11+'10_DEMAND'!AR25*'10_DEMAND'!$G$12+'10_DEMAND'!AR26*'10_DEMAND'!$G$13+'10_DEMAND'!$C$16 -> 72892.854
A30: Offre injectée requise (majorée des pertes de la compagnie) | B30: GWh | E30: ='10_DEMAND'!E27/(1-'12_UTILITY'!$C$11-'12_UTILITY'!$C$12) -> 9935.8974 | F30: ='10_DEMAND'!F27/(1-'12_UTILITY'!$C$11-'12_UTILITY'!$C$12) -> 10549.628 | G30: ='10_DEMAND'!G27/(1-'12_UTILITY'!$C$11-'12_UTILITY'!$C$12) -> 11202.6 | H30: ='10_DEMAND'!H27/(1-'12_UTILITY'!$C$11-'12_UTILITY'!$C$12) -> 11897.414 | I30: ='10_DEMAND'!I27/(1-'12_UTILITY'!$C$11-'12_UTILITY'!$C$12) -> 12636.849 | J30: ='10_DEMAND'!J27/(1-'12_UTILITY'!$C$11-'12_UTILITY'!$C$12) -> 13423.877 | K30: ='10_DEMAND'!K27/(1-'12_UTILITY'!$C$11-'12_UTILITY'!$C$12) -> 14261.675 | L30: ='10_DEMAND'!L27/(1-'12_UTILITY'!$C$11-'12_UTILITY'!$C$12) -> 15153.642 | ... AR30: ='10_DEMAND'!AR27/(1-'12_UTILITY'!$C$11-'12_UTILITY'!$C$12) -> 113696.34
A31: Autres sources engagées | B31: GWh | E31: ='10_DEMAND'!$C$17*(1+'10_DEMAND'!$C$18)^('06_CONSTRUCTION'!E4-'02_PROJECT_INPUTS'!$C$11) -> 8987 | F31: ='10_DEMAND'!$C$17*(1+'10_DEMAND'!$C$18)^('06_CONSTRUCTION'!F4-'02_PROJECT_INPUTS'!$C$11) -> 9391.415 | G31: ='10_DEMAND'!$C$17*(1+'10_DEMAND'!$C$18)^('06_CONSTRUCTION'!G4-'02_PROJECT_INPUTS'!$C$11) -> 9814.0287 | H31: ='10_DEMAND'!$C$17*(1+'10_DEMAND'!$C$18)^('06_CONSTRUCTION'!H4-'02_PROJECT_INPUTS'!$C$11) -> 10255.66 | I31: ='10_DEMAND'!$C$17*(1+'10_DEMAND'!$C$18)^('06_CONSTRUCTION'!I4-'02_PROJECT_INPUTS'!$C$11) -> 10717.165 | J31: ='10_DEMAND'!$C$17*(1+'10_DEMAND'!$C$18)^('06_CONSTRUCTION'!J4-'02_PROJECT_INPUTS'!$C$11) -> 11199.437 | K31: ='10_DEMAND'!$C$17*(1+'10_DEMAND'!$C$18)^('06_CONSTRUCTION'!K4-'02_PROJECT_INPUTS'!$C$11) -> 11703.412 | L31: ='10_DEMAND'!$C$17*(1+'10_DEMAND'!$C$18)^('06_CONSTRUCTION'!L4-'02_PROJECT_INPUTS'!$C$11) -> 12230.065 | ... AR31: ='10_DEMAND'!$C$17*(1+'10_DEMAND'!$C$18)^('06_CONSTRUCTION'!AR4-'02_PROJECT_INPUTS'!$C$11) -> 50020.735
A32: Déficit d'offre avant projet | B32: GWh | E32: =MAX(0,'10_DEMAND'!E30-'10_DEMAND'!E31) -> 948.89744 | F32: =MAX(0,'10_DEMAND'!F30-'10_DEMAND'!F31) -> 1158.2132 | G32: =MAX(0,'10_DEMAND'!G30-'10_DEMAND'!G31) -> 1388.5715 | H32: =MAX(0,'10_DEMAND'!H30-'10_DEMAND'!H31) -> 1641.7538 | I32: =MAX(0,'10_DEMAND'!I30-'10_DEMAND'!I31) -> 1919.6842 | J32: =MAX(0,'10_DEMAND'!J30-'10_DEMAND'!J31) -> 2224.4398 | K32: =MAX(0,'10_DEMAND'!K30-'10_DEMAND'!K31) -> 2558.2635 | L32: =MAX(0,'10_DEMAND'!L30-'10_DEMAND'!L31) -> 2923.5766 | ... AR32: =MAX(0,'10_DEMAND'!AR30-'10_DEMAND'!AR31) -> 63675.6
A33: Énergie du projet absorbable (déficit + substitution thermique + contrats export) | B33: GWh | E33: ='10_DEMAND'!E32+'10_DEMAND'!$C$19+'10_DEMAND'!$C$16 -> 1448.8974 | F33: ='10_DEMAND'!F32+'10_DEMAND'!$C$19+'10_DEMAND'!$C$16 -> 1658.2132 | G33: ='10_DEMAND'!G32+'10_DEMAND'!$C$19+'10_DEMAND'!$C$16 -> 1888.5715 | H33: ='10_DEMAND'!H32+'10_DEMAND'!$C$19+'10_DEMAND'!$C$16 -> 2141.7538 | I33: ='10_DEMAND'!I32+'10_DEMAND'!$C$19+'10_DEMAND'!$C$16 -> 2419.6842 | J33: ='10_DEMAND'!J32+'10_DEMAND'!$C$19+'10_DEMAND'!$C$16 -> 2724.4398 | K33: ='10_DEMAND'!K32+'10_DEMAND'!$C$19+'10_DEMAND'!$C$16 -> 3058.2635 | L33: ='10_DEMAND'!L32+'10_DEMAND'!$C$19+'10_DEMAND'!$C$16 -> 3423.5766 | ... AR33: ='10_DEMAND'!AR32+'10_DEMAND'!$C$19+'10_DEMAND'!$C$16 -> 64175.6
A34: Demande CONTRACTUELLE (énergie contractée au CAE, P50) | B34: GWh | E34: ='06_CONSTRUCTION'!E14*'03_HYDROLOGY'!$C$33 -> 0 | F34: ='06_CONSTRUCTION'!F14*'03_HYDROLOGY'!$C$33 -> 0 | G34: ='06_CONSTRUCTION'!G14*'03_HYDROLOGY'!$C$33 -> 0 | H34: ='06_CONSTRUCTION'!H14*'03_HYDROLOGY'!$C$33 -> 292.48138 | I34: ='06_CONSTRUCTION'!I14*'03_HYDROLOGY'!$C$33 -> 292.48138 | J34: ='06_CONSTRUCTION'!J14*'03_HYDROLOGY'!$C$33 -> 292.48138 | K34: ='06_CONSTRUCTION'!K14*'03_HYDROLOGY'!$C$33 -> 292.48138 | L34: ='06_CONSTRUCTION'!L14*'03_HYDROLOGY'!$C$33 -> 292.48138 | ... AR34: ='06_CONSTRUCTION'!AR14*'03_HYDROLOGY'!$C$33 -> 0
A35: Demande BANCABLE = MIN(contractuelle, absorbable x ratio commercial) | B35: GWh | E35: ='06_CONSTRUCTION'!E14*MIN('10_DEMAND'!E34,'10_DEMAND'!E33*'10_DEMAND'!E29/('10_DEMAND'!E27+'10_DEMAND'!$C$16)) -> 0 | F35: ='06_CONSTRUCTION'!F14*MIN('10_DEMAND'!F34,'10_DEMAND'!F33*'10_DEMAND'!F29/('10_DEMAND'!F27+'10_DEMAND'!$C$16)) -> 0 | G35: ='06_CONSTRUCTION'!G14*MIN('10_DEMAND'!G34,'10_DEMAND'!G33*'10_DEMAND'!G29/('10_DEMAND'!G27+'10_DEMAND'!$C$16)) -> 0 | H35: ='06_CONSTRUCTION'!H14*MIN('10_DEMAND'!H34,'10_DEMAND'!H33*'10_DEMAND'!H29/('10_DEMAND'!H27+'10_DEMAND'!$C$16)) -> 292.48138 | I35: ='06_CONSTRUCTION'!I14*MIN('10_DEMAND'!I34,'10_DEMAND'!I33*'10_DEMAND'!I29/('10_DEMAND'!I27+'10_DEMAND'!$C$16)) -> 292.48138 | J35: ='06_CONSTRUCTION'!J14*MIN('10_DEMAND'!J34,'10_DEMAND'!J33*'10_DEMAND'!J29/('10_DEMAND'!J27+'10_DEMAND'!$C$16)) -> 292.48138 | K35: ='06_CONSTRUCTION'!K14*MIN('10_DEMAND'!K34,'10_DEMAND'!K33*'10_DEMAND'!K29/('10_DEMAND'!K27+'10_DEMAND'!$C$16)) -> 292.48138 | L35: ='06_CONSTRUCTION'!L14*MIN('10_DEMAND'!L34,'10_DEMAND'!L33*'10_DEMAND'!L29/('10_DEMAND'!L27+'10_DEMAND'!$C$16)) -> 292.48138 | ... AR35: ='06_CONSTRUCTION'!AR14*MIN('10_DEMAND'!AR34,'10_DEMAND'!AR33*'10_DEMAND'!AR29/('10_DEMAND'!AR27+'10_DEMAND'!$C$16)) -> 0
A36: Bancable / contractuelle | B36: x | E36: =IF('10_DEMAND'!E34>0,'10_DEMAND'!E35/'10_DEMAND'!E34,"") | F36: =IF('10_DEMAND'!F34>0,'10_DEMAND'!F35/'10_DEMAND'!F34,"") | G36: =IF('10_DEMAND'!G34>0,'10_DEMAND'!G35/'10_DEMAND'!G34,"") | H36: =IF('10_DEMAND'!H34>0,'10_DEMAND'!H35/'10_DEMAND'!H34,"") -> 1 | I36: =IF('10_DEMAND'!I34>0,'10_DEMAND'!I35/'10_DEMAND'!I34,"") -> 1 | J36: =IF('10_DEMAND'!J34>0,'10_DEMAND'!J35/'10_DEMAND'!J34,"") -> 1 | K36: =IF('10_DEMAND'!K34>0,'10_DEMAND'!K35/'10_DEMAND'!K34,"") -> 1 | L36: =IF('10_DEMAND'!L34>0,'10_DEMAND'!L35/'10_DEMAND'!L34,"") -> 1 | ... AR36: =IF('10_DEMAND'!AR34>0,'10_DEMAND'!AR35/'10_DEMAND'!AR34,"")
A37: Ratio 5 premières années | B37: x | C37: =IF(COUNT('10_DEMAND'!$E$37:$AR$37)=0,99,MIN('10_DEMAND'!$E$37:$AR$37)) -> 1 | E37: =IF(AND('06_CONSTRUCTION'!E5>=1,'06_CONSTRUCTION'!E5<=5),'10_DEMAND'!E36,"") | F37: =IF(AND('06_CONSTRUCTION'!F5>=1,'06_CONSTRUCTION'!F5<=5),'10_DEMAND'!F36,"") | G37: =IF(AND('06_CONSTRUCTION'!G5>=1,'06_CONSTRUCTION'!G5<=5),'10_DEMAND'!G36,"") | H37: =IF(AND('06_CONSTRUCTION'!H5>=1,'06_CONSTRUCTION'!H5<=5),'10_DEMAND'!H36,"") -> 1 | I37: =IF(AND('06_CONSTRUCTION'!I5>=1,'06_CONSTRUCTION'!I5<=5),'10_DEMAND'!I36,"") -> 1 | J37: =IF(AND('06_CONSTRUCTION'!J5>=1,'06_CONSTRUCTION'!J5<=5),'10_DEMAND'!J36,"") -> 1 | K37: =IF(AND('06_CONSTRUCTION'!K5>=1,'06_CONSTRUCTION'!K5<=5),'10_DEMAND'!K36,"") -> 1 | L37: =IF(AND('06_CONSTRUCTION'!L5>=1,'06_CONSTRUCTION'!L5<=5),'10_DEMAND'!L36,"") -> 1 | ... AR37: =IF(AND('06_CONSTRUCTION'!AR5>=1,'06_CONSTRUCTION'!AR5<=5),'10_DEMAND'!AR36,"")
A99: Demande intérieure 2026 | C99: =$B$8+$B$9+$B$10+$B$11+$B$12+$B$13 -> 7300

Sheet 11_OFFTAKER
A1: 11 ACHETEUR — Répartition des ventes, qualité de crédit et garantie de paiement
A2: Données qualitatives pour GATE 5
A4: Acheteur principal | C4: Navaria Electricity Company (NEC) — intégrée verticalement, publique | D4: Fictif
A5: Qualité de crédit de l'acheteur | C5: Non notée ; souverain noté B- (fictif)
A6: Part de la production vendue à la compagnie | B6: % | C6: 1
A7: Part vendue à l'acheteur minier (bilatéral, USD, via transit) | B7: % | C7: =1-'11_OFFTAKER'!$C$6 -> 0
A8: Garantie de paiement : couverture par lettre de crédit / séquestre | B8: mois de facturation CAE | C8: 3 | D8: Test de porte ; 6 mois est le seuil READY (hypothèse)
A9: Retards de paiement historiques de la compagnie envers les PIE existants | B9: jours | C9: 120 | D9: Fictif
A10: Montant de LC requis (1re année pleine d'exploitation) | B10: M USD | C10: ='11_OFFTAKER'!$C$8/12*'16_REVENUE'!$C$16 -> 8.6156623

Sheet 12_UTILITY
A1: 12 COMPAGNIE — Modèle de trésorerie simplifié et PAIEMENT CAE MAXIMAL SOUTENABLE
A2: Le modèle ne suppose pas que l'acheteur peut payer ; il le teste. Équivalents USD des flux en monnaie locale.
A6: A. DONNÉES (2026)
A7: Clients | B7: # | C7: 1350000 | D7: Fictif
A8: Croissance clients | B8: % p.a. | C8: 0.05
A9: Tarif de détail moyen | B9: NVL/kWh | C9: 2.7 | D9: Soit 0,135 USD/kWh à 20 NVL/USD (fictif)
A10: Ajustement tarifaire : répercussion de l'inflation locale | B10: % | C10: 1 | D10: 1,0 = indexation totale au cas de base ; le stress acheteur gèle le tarif
A11: Pertes techniques | B11: % de l'injecté | C11: 0.14
A12: Pertes commerciales (non techniques) | B12: % de l'injecté | C12: 0.08
A13: Taux de recouvrement | B13: % de la facturation | C13: 0.88
A14: Coût des autres sources (production propre + autres PIE) | B14: USD/MWh 2026 | C14: 55
A15: Part liée à l'USD du coût des autres sources | B15: % | C15: 0.5
A16: OPEX compagnie (T&D, commercial, frais gén.) | B16: M USD 2026 | C16: 190 | D16: Monnaie locale ; 50 % fixe, 50 % proportionnel aux ventes
A17: Transferts d'exploitation / subventions de l'État | B17: M USD 2026 | C17: 80 | D17: Monnaie locale
A18: Service dette existante compagnie | B18: M USD/an | C18: 85 | D18: Libellé en USD, constant
A19: Créances d'ouverture | B19: M USD | C19: 180
A20: Passage en perte annuel des créances anciennes | B20: % du stock | C20: 0.3
A21: Couverture trésorerie requise nouveaux CAE | B21: x | C21: 1.2 | D21: Marge prudentielle — hypothèse
A22: B. BILAN ÉNERGÉTIQUE (GWh)
A23: Demande de la compagnie (intérieure, hors charge minière servie directement par le projet) | B23: GWh | E23: =MAX(0,'10_DEMAND'!E27-'04_GENERATION'!E20*'11_OFFTAKER'!$C$7) -> 7750 | F23: =MAX(0,'10_DEMAND'!F27-'04_GENERATION'!F20*'11_OFFTAKER'!$C$7) -> 8228.71 | G23: =MAX(0,'10_DEMAND'!G27-'04_GENERATION'!G20*'11_OFFTAKER'!$C$7) -> 8738.0281 | H23: =MAX(0,'10_DEMAND'!H27-'04_GENERATION'!H20*'11_OFFTAKER'!$C$7) -> 9279.9828 | I23: =MAX(0,'10_DEMAND'!I27-'04_GENERATION'!I20*'11_OFFTAKER'!$C$7) -> 9856.7421 | J23: =MAX(0,'10_DEMAND'!J27-'04_GENERATION'!J20*'11_OFFTAKER'!$C$7) -> 10470.624 | K23: =MAX(0,'10_DEMAND'!K27-'04_GENERATION'!K20*'11_OFFTAKER'!$C$7) -> 11124.107 | L23: =MAX(0,'10_DEMAND'!L27-'04_GENERATION'!L20*'11_OFFTAKER'!$C$7) -> 11819.841 | ... AR23: =MAX(0,'10_DEMAND'!AR27-'04_GENERATION'!AR20*'11_OFFTAKER'!$C$7) -> 88683.141
A24: Énergie injectée requise pour la demande de la compagnie | B24: GWh | E24: ='12_UTILITY'!E23/(1-'12_UTILITY'!$C$11-'12_UTILITY'!$C$12) -> 9935.8974 | F24: ='12_UTILITY'!F23/(1-'12_UTILITY'!$C$11-'12_UTILITY'!$C$12) -> 10549.628 | G24: ='12_UTILITY'!G23/(1-'12_UTILITY'!$C$11-'12_UTILITY'!$C$12) -> 11202.6 | H24: ='12_UTILITY'!H23/(1-'12_UTILITY'!$C$11-'12_UTILITY'!$C$12) -> 11897.414 | I24: ='12_UTILITY'!I23/(1-'12_UTILITY'!$C$11-'12_UTILITY'!$C$12) -> 12636.849 | J24: ='12_UTILITY'!J23/(1-'12_UTILITY'!$C$11-'12_UTILITY'!$C$12) -> 13423.877 | K24: ='12_UTILITY'!K23/(1-'12_UTILITY'!$C$11-'12_UTILITY'!$C$12) -> 14261.675 | L24: ='12_UTILITY'!L23/(1-'12_UTILITY'!$C$11-'12_UTILITY'!$C$12) -> 15153.642 | ... AR24: ='12_UTILITY'!AR23/(1-'12_UTILITY'!$C$11-'12_UTILITY'!$C$12) -> 113696.34
A25: du projet (part compagnie, nette des pertes de transport) | B25: GWh | E25: =MIN('04_GENERATION'!E20*'11_OFFTAKER'!$C$6*(1-'08_TRANSMISSION'!$C$15),'12_UTILITY'!E24) -> 0 | F25: =MIN('04_GENERATION'!F20*'11_OFFTAKER'!$C$6*(1-'08_TRANSMISSION'!$C$15),'12_UTILITY'!F24) -> 0 | G25: =MIN('04_GENERATION'!G20*'11_OFFTAKER'!$C$6*(1-'08_TRANSMISSION'!$C$15),'12_UTILITY'!G24) -> 0 | H25: =MIN('04_GENERATION'!H20*'11_OFFTAKER'!$C$6*(1-'08_TRANSMISSION'!$C$15),'12_UTILITY'!H24) -> 243.63699 | I25: =MIN('04_GENERATION'!I20*'11_OFFTAKER'!$C$6*(1-'08_TRANSMISSION'!$C$15),'12_UTILITY'!I24) -> 286.63175 | J25: =MIN('04_GENERATION'!J20*'11_OFFTAKER'!$C$6*(1-'08_TRANSMISSION'!$C$15),'12_UTILITY'!J24) -> 286.63175 | K25: =MIN('04_GENERATION'!K20*'11_OFFTAKER'!$C$6*(1-'08_TRANSMISSION'!$C$15),'12_UTILITY'!K24) -> 286.63175 | L25: =MIN('04_GENERATION'!L20*'11_OFFTAKER'!$C$6*(1-'08_TRANSMISSION'!$C$15),'12_UTILITY'!L24) -> 286.63175 | ... AR25: =MIN('04_GENERATION'!AR20*'11_OFFTAKER'!$C$6*(1-'08_TRANSMISSION'!$C$15),'12_UTILITY'!AR24) -> 0
A26: des autres sources (plafonné à l'offre disponible) | B26: GWh | E26: =MIN('12_UTILITY'!E24-'12_UTILITY'!E25,'10_DEMAND'!E31) -> 8987 | F26: =MIN('12_UTILITY'!F24-'12_UTILITY'!F25,'10_DEMAND'!F31) -> 9391.415 | G26: =MIN('12_UTILITY'!G24-'12_UTILITY'!G25,'10_DEMAND'!G31) -> 9814.0287 | H26: =MIN('12_UTILITY'!H24-'12_UTILITY'!H25,'10_DEMAND'!H31) -> 10255.66 | I26: =MIN('12_UTILITY'!I24-'12_UTILITY'!I25,'10_DEMAND'!I31) -> 10717.165 | J26: =MIN('12_UTILITY'!J24-'12_UTILITY'!J25,'10_DEMAND'!J31) -> 11199.437 | K26: =MIN('12_UTILITY'!K24-'12_UTILITY'!K25,'10_DEMAND'!K31) -> 11703.412 | L26: =MIN('12_UTILITY'!L24-'12_UTILITY'!L25,'10_DEMAND'!L31) -> 12230.065 | ... AR26: =MIN('12_UTILITY'!AR24-'12_UTILITY'!AR25,'10_DEMAND'!AR31) -> 50020.735
A27: Énergie achetée / injectée | B27: GWh | E27: ='12_UTILITY'!E25+'12_UTILITY'!E26 -> 8987 | F27: ='12_UTILITY'!F25+'12_UTILITY'!F26 -> 9391.415 | G27: ='12_UTILITY'!G25+'12_UTILITY'!G26 -> 9814.0287 | H27: ='12_UTILITY'!H25+'12_UTILITY'!H26 -> 10499.297 | I27: ='12_UTILITY'!I25+'12_UTILITY'!I26 -> 11003.796 | J27: ='12_UTILITY'!J25+'12_UTILITY'!J26 -> 11486.069 | K27: ='12_UTILITY'!K25+'12_UTILITY'!K26 -> 11990.043 | L27: ='12_UTILITY'!L25+'12_UTILITY'!L26 -> 12516.697 | ... AR27: ='12_UTILITY'!AR25+'12_UTILITY'!AR26 -> 50020.735
A28: Ventes d'électricité (demande servie) | B28: GWh | E28: ='12_UTILITY'!E27*(1-'12_UTILITY'!$C$11-'12_UTILITY'!$C$12) -> 7009.86 | F28: ='12_UTILITY'!F27*(1-'12_UTILITY'!$C$11-'12_UTILITY'!$C$12) -> 7325.3037 | G28: ='12_UTILITY'!G27*(1-'12_UTILITY'!$C$11-'12_UTILITY'!$C$12) -> 7654.9424 | H28: ='12_UTILITY'!H27*(1-'12_UTILITY'!$C$11-'12_UTILITY'!$C$12) -> 8189.4516 | I28: ='12_UTILITY'!I27*(1-'12_UTILITY'!$C$11-'12_UTILITY'!$C$12) -> 8582.9612 | J28: ='12_UTILITY'!J27*(1-'12_UTILITY'!$C$11-'12_UTILITY'!$C$12) -> 8959.1337 | K28: ='12_UTILITY'!K27*(1-'12_UTILITY'!$C$11-'12_UTILITY'!$C$12) -> 9352.2339 | L28: ='12_UTILITY'!L27*(1-'12_UTILITY'!$C$11-'12_UTILITY'!$C$12) -> 9763.0237 | ... AR28: ='12_UTILITY'!AR27*(1-'12_UTILITY'!$C$11-'12_UTILITY'!$C$12) -> 39016.173
A29: Demande non servie (délestage) | B29: GWh | C29: =SUM('12_UTILITY'!$E$29:$AR$29) -> 566125.27 | E29: ='12_UTILITY'!E23-'12_UTILITY'!E28 -> 740.14 | F29: ='12_UTILITY'!F23-'12_UTILITY'!F28 -> 903.4063 | G29: ='12_UTILITY'!G23-'12_UTILITY'!G28 -> 1083.0857 | H29: ='12_UTILITY'!H23-'12_UTILITY'!H28 -> 1090.5311 | I29: ='12_UTILITY'!I23-'12_UTILITY'!I28 -> 1273.7809 | J29: ='12_UTILITY'!J23-'12_UTILITY'!J28 -> 1511.4903 | K29: ='12_UTILITY'!K23-'12_UTILITY'!K28 -> 1771.8728 | L29: ='12_UTILITY'!L23-'12_UTILITY'!L28 -> 2056.817 | ... AR29: ='12_UTILITY'!AR23-'12_UTILITY'!AR28 -> 49666.968
A30: C. RÉSULTAT ET TRÉSORERIE (équivalent M USD)
A31: Tarif de détail moyen | B31: NVL/kWh | E31: =IF(1=1,'12_UTILITY'!$C$9,'12_UTILITY'!D31)*(1+'02_PROJECT_INPUTS'!$C$19*IF(AND('06_CONSTRUCTION'!E5>=1,'06_CONSTRUCTION'!E5<='27_SCENARIOS'!$C$33),0,'12_UTILITY'!$C$10)) -> 2.916 | F31: =IF(2=1,'12_UTILITY'!$C$9,'12_UTILITY'!E31)*(1+'02_PROJECT_INPUTS'!$C$19*IF(AND('06_CONSTRUCTION'!F5>=1,'06_CONSTRUCTION'!F5<='27_SCENARIOS'!$C$33),0,'12_UTILITY'!$C$10)) -> 3.14928 | G31: =IF(3=1,'12_UTILITY'!$C$9,'12_UTILITY'!F31)*(1+'02_PROJECT_INPUTS'!$C$19*IF(AND('06_CONSTRUCTION'!G5>=1,'06_CONSTRUCTION'!G5<='27_SCENARIOS'!$C$33),0,'12_UTILITY'!$C$10)) -> 3.4012224 | H31: =IF(4=1,'12_UTILITY'!$C$9,'12_UTILITY'!G31)*(1+'02_PROJECT_INPUTS'!$C$19*IF(AND('06_CONSTRUCTION'!H5>=1,'06_CONSTRUCTION'!H5<='27_SCENARIOS'!$C$33),0,'12_UTILITY'!$C$10)) -> 3.6733202 | I31: =IF(5=1,'12_UTILITY'!$C$9,'12_UTILITY'!H31)*(1+'02_PROJECT_INPUTS'!$C$19*IF(AND('06_CONSTRUCTION'!I5>=1,'06_CONSTRUCTION'!I5<='27_SCENARIOS'!$C$33),0,'12_UTILITY'!$C$10)) -> 3.9671858 | J31: =IF(6=1,'12_UTILITY'!$C$9,'12_UTILITY'!I31)*(1+'02_PROJECT_INPUTS'!$C$19*IF(AND('06_CONSTRUCTION'!J5>=1,'06_CONSTRUCTION'!J5<='27_SCENARIOS'!$C$33),0,'12_UTILITY'!$C$10)) -> 4.2845607 | K31: =IF(7=1,'12_UTILITY'!$C$9,'12_UTILITY'!J31)*(1+'02_PROJECT_INPUTS'!$C$19*IF(AND('06_CONSTRUCTION'!K5>=1,'06_CONSTRUCTION'!K5<='27_SCENARIOS'!$C$33),0,'12_UTILITY'!$C$10)) -> 4.6273255 | L31: =IF(8=1,'12_UTILITY'!$C$9,'12_UTILITY'!K31)*(1+'02_PROJECT_INPUTS'!$C$19*IF(AND('06_CONSTRUCTION'!L5>=1,'06_CONSTRUCTION'!L5<='27_SCENARIOS'!$C$33),0,'12_UTILITY'!$C$10)) -> 4.9975116 | M31: =IF(9=1,'12_UTILITY'!$C$9,'12_UTILITY'!L31)*(1+'02_PROJECT_INPUTS'!$C$19*IF(AND('06_CONSTRUCTION'!M5>=1,'06_CONSTRUCTION'!M5<='27_SCENARIOS'!$C$33),0,'12_UTILITY'!$C$10)) -> 5.3973125 | N31: =IF(10=1,'12_UTILITY'!$C$9,'12_UTILITY'!M31)*(1+'02_PROJECT_INPUTS'!$C$19*IF(AND('06_CONSTRUCTION'!N5>=1,'06_CONSTRUCTION'!N5<='27_SCENARIOS'!$C$33),0,'12_UTILITY'!$C$10)) -> 5.8290975 | O31: =IF(11=1,'12_UTILITY'!$C$9,'12_UTILITY'!N31)*(1+'02_PROJECT_INPUTS'!$C$19*IF(AND('06_CONSTRUCTION'!O5>=1,'06_CONSTRUCTION'!O5<='27_SCENARIOS'!$C$33),0,'12_UTILITY'!$C$10)) -> 6.2954253 | P31: =IF(12=1,'12_UTILITY'!$C$9,'12_UTILITY'!O31)*(1+'02_PROJECT_INPUTS'!$C$19*IF(AND('06_CONSTRUCTION'!P5>=1,'06_CONSTRUCTION'!P5<='27_SCENARIOS'!$C$33),0,'12_UTILITY'!$C$10)) -> 6.7990593 | Q31: =IF(13=1,'12_UTILITY'!$C$9,'12_UTILITY'!P31)*(1+'02_PROJECT_INPUTS'!$C$19*IF(AND('06_CONSTRUCTION'!Q5>=1,'06_CONSTRUCTION'!Q5<='27_SCENARIOS'!$C$33),0,'12_UTILITY'!$C$10)) -> 7.3429841 | R31: =IF(14=1,'12_UTILITY'!$C$9,'12_UTILITY'!Q31)*(1+'02_PROJECT_INPUTS'!$C$19*IF(AND('06_CONSTRUCTION'!R5>=1,'06_CONSTRUCTION'!R5<='27_SCENARIOS'!$C$33),0,'12_UTILITY'!$C$10)) -> 7.9304228 | S31: =IF(15=1,'12_UTILITY'!$C$9,'12_UTILITY'!R31)*(1+'02_PROJECT_INPUTS'!$C$19*IF(AND('06_CONSTRUCTION'!S5>=1,'06_CONSTRUCTION'!S5<='27_SCENARIOS'!$C$33),0,'12_UTILITY'!$C$10)) -> 8.5648566 | T31: =IF(16=1,'12_UTILITY'!$C$9,'12_UTILITY'!S31)*(1+'02_PROJECT_INPUTS'!$C$19*IF(AND('06_CONSTRUCTION'!T5>=1,'06_CONSTRUCTION'!T5<='27_SCENARIOS'!$C$33),0,'12_UTILITY'!$C$10)) -> 9.2500451 | U31: =IF(17=1,'12_UTILITY'!$C$9,'12_UTILITY'!T31)*(1+'02_PROJECT_INPUTS'!$C$19*IF(AND('06_CONSTRUCTION'!U5>=1,'06_CONSTRUCTION'!U5<='27_SCENARIOS'!$C$33),0,'12_UTILITY'!$C$10)) -> 9.9900487 | V31: =IF(18=1,'12_UTILITY'!$C$9,'12_UTILITY'!U31)*(1+'02_PROJECT_INPUTS'!$C$19*IF(AND('06_CONSTRUCTION'!V5>=1,'06_CONSTRUCTION'!V5<='27_SCENARIOS'!$C$33),0,'12_UTILITY'!$C$10)) -> 10.789253 | W31: =IF(19=1,'12_UTILITY'!$C$9,'12_UTILITY'!V31)*(1+'02_PROJECT_INPUTS'!$C$19*IF(AND('06_CONSTRUCTION'!W5>=1,'06_CONSTRUCTION'!W5<='27_SCENARIOS'!$C$33),0,'12_UTILITY'!$C$10)) -> 11.652393 | X31: =IF(20=1,'12_UTILITY'!$C$9,'12_UTILITY'!W31)*(1+'02_PROJECT_INPUTS'!$C$19*IF(AND('06_CONSTRUCTION'!X5>=1,'06_CONSTRUCTION'!X5<='27_SCENARIOS'!$C$33),0,'12_UTILITY'!$C$10)) -> 12.584584 | Y31: =IF(21=1,'12_UTILITY'!$C$9,'12_UTILITY'!X31)*(1+'02_PROJECT_INPUTS'!$C$19*IF(AND('06_CONSTRUCTION'!Y5>=1,'06_CONSTRUCTION'!Y5<='27_SCENARIOS'!$C$33),0,'12_UTILITY'!$C$10)) -> 13.591351 | Z31: =IF(22=1,'12_UTILITY'!$C$9,'12_UTILITY'!Y31)*(1+'02_PROJECT_INPUTS'!$C$19*IF(AND('06_CONSTRUCTION'!Z5>=1,'06_CONSTRUCTION'!Z5<='27_SCENARIOS'!$C$33),0,'12_UTILITY'!$C$10)) -> 14.678659 | AA31: =IF(23=1,'12_UTILITY'!$C$9,'12_UTILITY'!Z31)*(1+'02_PROJECT_INPUTS'!$C$19*IF(AND('06_CONSTRUCTION'!AA5>=1,'06_CONSTRUCTION'!AA5<='27_SCENARIOS'!$C$33),0,'12_UTILITY'!$C$10)) -> 15.852952 | AB31: =IF(24=1,'12_UTILITY'!$C$9,'12_UTILITY'!AA31)*(1+'02_PROJECT_INPUTS'!$C$19*IF(AND('06_CONSTRUCTION'!AB5>=1,'06_CONSTRUCTION'!AB5<='27_SCENARIOS'!$C$33),0,'12_UTILITY'!$C$10)) -> 17.121188 | AC31: =IF(25=1,'12_UTILITY'!$C$9,'12_UTILITY'!AB31)*(1+'02_PROJECT_INPUTS'!$C$19*IF(AND('06_CONSTRUCTION'!AC5>=1,'06_CONSTRUCTION'!AC5<='27_SCENARIOS'!$C$33),0,'12_UTILITY'!$C$10)) -> 18.490883 | AD31: =IF(26=1,'12_UTILITY'!$C$9,'12_UTILITY'!AC31)*(1+'02_PROJECT_INPUTS'!$C$19*IF(AND('06_CONSTRUCTION'!AD5>=1,'06_CONSTRUCTION'!AD5<='27_SCENARIOS'!$C$33),0,'12_UTILITY'!$C$10)) -> 19.970154 | AE31: =IF(27=1,'12_UTILITY'!$C$9,'12_UTILITY'!AD31)*(1+'02_PROJECT_INPUTS'!$C$19*IF(AND('06_CONSTRUCTION'!AE5>=1,'06_CONSTRUCTION'!AE5<='27_SCENARIOS'!$C$33),0,'12_UTILITY'!$C$10)) -> 21.567766 | AF31: =IF(28=1,'12_UTILITY'!$C$9,'12_UTILITY'!AE31)*(1+'02_PROJECT_INPUTS'!$C$19*IF(AND('06_CONSTRUCTION'!AF5>=1,'06_CONSTRUCTION'!AF5<='27_SCENARIOS'!$C$33),0,'12_UTILITY'!$C$10)) -> 23.293187 | AG31: =IF(29=1,'12_UTILITY'!$C$9,'12_UTILITY'!AF31)*(1+'02_PROJECT_INPUTS'!$C$19*IF(AND('06_CONSTRUCTION'!AG5>=1,'06_CONSTRUCTION'!AG5<='27_SCENARIOS'!$C$33),0,'12_UTILITY'!$C$10)) -> 25.156642 | AH31: =IF(30=1,'12_UTILITY'!$C$9,'12_UTILITY'!AG31)*(1+'02_PROJECT_INPUTS'!$C$19*IF(AND('06_CONSTRUCTION'!AH5>=1,'06_CONSTRUCTION'!AH5<='27_SCENARIOS'!$C$33),0,'12_UTILITY'!$C$10)) -> 27.169174 | AI31: =IF(31=1,'12_UTILITY'!$C$9,'12_UTILITY'!AH31)*(1+'02_PROJECT_INPUTS'!$C$19*IF(AND('06_CONSTRUCTION'!AI5>=1,'06_CONSTRUCTION'!AI5<='27_SCENARIOS'!$C$33),0,'12_UTILITY'!$C$10)) -> 29.342707 | AJ31: =IF(32=1,'12_UTILITY'!$C$9,'12_UTILITY'!AI31)*(1+'02_PROJECT_INPUTS'!$C$19*IF(AND('06_CONSTRUCTION'!AJ5>=1,'06_CONSTRUCTION'!AJ5<='27_SCENARIOS'!$C$33),0,'12_UTILITY'!$C$10)) -> 31.690124 | AK31: =IF(33=1,'12_UTILITY'!$C$9,'12_UTILITY'!AJ31)*(1+'02_PROJECT_INPUTS'!$C$19*IF(AND('06_CONSTRUCTION'!AK5>=1,'06_CONSTRUCTION'!AK5<='27_SCENARIOS'!$C$33),0,'12_UTILITY'!$C$10)) -> 34.225334 | AL31: =IF(34=1,'12_UTILITY'!$C$9,'12_UTILITY'!AK31)*(1+'02_PROJECT_INPUTS'!$C$19*IF(AND('06_CONSTRUCTION'!AL5>=1,'06_CONSTRUCTION'!AL5<='27_SCENARIOS'!$C$33),0,'12_UTILITY'!$C$10)) -> 36.963361 | AM31: =IF(35=1,'12_UTILITY'!$C$9,'12_UTILITY'!AL31)*(1+'02_PROJECT_INPUTS'!$C$19*IF(AND('06_CONSTRUCTION'!AM5>=1,'06_CONSTRUCTION'!AM5<='27_SCENARIOS'!$C$33),0,'12_UTILITY'!$C$10)) -> 39.92043 | AN31: =IF(36=1,'12_UTILITY'!$C$9,'12_UTILITY'!AM31)*(1+'02_PROJECT_INPUTS'!$C$19*IF(AND('06_CONSTRUCTION'!AN5>=1,'06_CONSTRUCTION'!AN5<='27_SCENARIOS'!$C$33),0,'12_UTILITY'!$C$10)) -> 43.114064 | AO31: =IF(37=1,'12_UTILITY'!$C$9,'12_UTILITY'!AN31)*(1+'02_PROJECT_INPUTS'!$C$19*IF(AND('06_CONSTRUCTION'!AO5>=1,'06_CONSTRUCTION'!AO5<='27_SCENARIOS'!$C$33),0,'12_UTILITY'!$C$10)) -> 46.563189 | AP31: =IF(38=1,'12_UTILITY'!$C$9,'12_UTILITY'!AO31)*(1+'02_PROJECT_INPUTS'!$C$19*IF(AND('06_CONSTRUCTION'!AP5>=1,'06_CONSTRUCTION'!AP5<='27_SCENARIOS'!$C$33),0,'12_UTILITY'!$C$10)) -> 50.288244 | AQ31: =IF(39=1,'12_UTILITY'!$C$9,'12_UTILITY'!AP31)*(1+'02_PROJECT_INPUTS'!$C$19*IF(AND('06_CONSTRUCTION'!AQ5>=1,'06_CONSTRUCTION'!AQ5<='27_SCENARIOS'!$C$33),0,'12_UTILITY'!$C$10)) -> 54.311304 | AR31: =IF(40=1,'12_UTILITY'!$C$9,'12_UTILITY'!AQ31)*(1+'02_PROJECT_INPUTS'!$C$19*IF(AND('06_CONSTRUCTION'!AR5>=1,'06_CONSTRUCTION'!AR5<='27_SCENARIOS'!$C$33),0,'12_UTILITY'!$C$10)) -> 58.656208
A32: Tarif de détail moyen (USD/MWh) | B32: USD/MWh | E32: ='12_UTILITY'!E31/'06_CONSTRUCTION'!E19*1000 -> 137.54717 | F32: ='12_UTILITY'!F31/'06_CONSTRUCTION'!F19*1000 -> 140.1424 | G32: ='12_UTILITY'!G31/'06_CONSTRUCTION'!G19*1000 -> 142.7866 | H32: ='12_UTILITY'!H31/'06_CONSTRUCTION'!H19*1000 -> 145.48068 | I32: ='12_UTILITY'!I31/'06_CONSTRUCTION'!I19*1000 -> 148.2256 | J32: ='12_UTILITY'!J31/'06_CONSTRUCTION'!J19*1000 -> 151.02231 | K32: ='12_UTILITY'!K31/'06_CONSTRUCTION'!K19*1000 -> 153.87179 | L32: ='12_UTILITY'!L31/'06_CONSTRUCTION'!L19*1000 -> 156.77503 | ... AR32: ='12_UTILITY'!AR31/'06_CONSTRUCTION'!AR19*1000 -> 285.13424
A33: CA facturé | B33: M USD | E33: ='12_UTILITY'!E28*'12_UTILITY'!E31/'06_CONSTRUCTION'!E19 -> 964.1864 | F33: ='12_UTILITY'!F28*'12_UTILITY'!F31/'06_CONSTRUCTION'!F19 -> 1026.5856 | G33: ='12_UTILITY'!G28*'12_UTILITY'!G31/'06_CONSTRUCTION'!G19 -> 1093.0232 | H33: ='12_UTILITY'!H28*'12_UTILITY'!H31/'06_CONSTRUCTION'!H19 -> 1191.407 | I33: ='12_UTILITY'!I28*'12_UTILITY'!I31/'06_CONSTRUCTION'!I19 -> 1272.2146 | J33: ='12_UTILITY'!J28*'12_UTILITY'!J31/'06_CONSTRUCTION'!J19 -> 1353.0291 | K33: ='12_UTILITY'!K28*'12_UTILITY'!K31/'06_CONSTRUCTION'!K19 -> 1439.045 | L33: ='12_UTILITY'!L28*'12_UTILITY'!L31/'06_CONSTRUCTION'!L19 -> 1530.5983 | ... AR33: ='12_UTILITY'!AR28*'12_UTILITY'!AR31/'06_CONSTRUCTION'!AR19 -> 11124.847
A34: Taux de recouvrement | B34: % | E34: =MAX(0,MIN(1,'12_UTILITY'!$C$13+IF('06_CONSTRUCTION'!E4>='06_CONSTRUCTION'!$C$8,'27_SCENARIOS'!$C$31,0))) -> 0.88 | F34: =MAX(0,MIN(1,'12_UTILITY'!$C$13+IF('06_CONSTRUCTION'!F4>='06_CONSTRUCTION'!$C$8,'27_SCENARIOS'!$C$31,0))) -> 0.88 | G34: =MAX(0,MIN(1,'12_UTILITY'!$C$13+IF('06_CONSTRUCTION'!G4>='06_CONSTRUCTION'!$C$8,'27_SCENARIOS'!$C$31,0))) -> 0.88 | H34: =MAX(0,MIN(1,'12_UTILITY'!$C$13+IF('06_CONSTRUCTION'!H4>='06_CONSTRUCTION'!$C$8,'27_SCENARIOS'!$C$31,0))) -> 0.88 | I34: =MAX(0,MIN(1,'12_UTILITY'!$C$13+IF('06_CONSTRUCTION'!I4>='06_CONSTRUCTION'!$C$8,'27_SCENARIOS'!$C$31,0))) -> 0.88 | J34: =MAX(0,MIN(1,'12_UTILITY'!$C$13+IF('06_CONSTRUCTION'!J4>='06_CONSTRUCTION'!$C$8,'27_SCENARIOS'!$C$31,0))) -> 0.88 | K34: =MAX(0,MIN(1,'12_UTILITY'!$C$13+IF('06_CONSTRUCTION'!K4>='06_CONSTRUCTION'!$C$8,'27_SCENARIOS'!$C$31,0))) -> 0.88 | L34: =MAX(0,MIN(1,'12_UTILITY'!$C$13+IF('06_CONSTRUCTION'!L4>='06_CONSTRUCTION'!$C$8,'27_SCENARIOS'!$C$31,0))) -> 0.88 | ... AR34: =MAX(0,MIN(1,'12_UTILITY'!$C$13+IF('06_CONSTRUCTION'!AR4>='06_CONSTRUCTION'!$C$8,'27_SCENARIOS'!$C$31,0))) -> 0.88
A35: Encaissements | B35: M USD | E35: ='12_UTILITY'!E33*'12_UTILITY'!E34 -> 848.48404 | F35: ='12_UTILITY'!F33*'12_UTILITY'!F34 -> 903.39536 | G35: ='12_UTILITY'!G33*'12_UTILITY'!G34 -> 961.86038 | H35: ='12_UTILITY'!H33*'12_UTILITY'!H34 -> 1048.4382 | I35: ='12_UTILITY'!I33*'12_UTILITY'!I34 -> 1119.5488 | J35: ='12_UTILITY'!J33*'12_UTILITY'!J34 -> 1190.6656 | K35: ='12_UTILITY'!K33*'12_UTILITY'!K34 -> 1266.3596 | L35: ='12_UTILITY'!L33*'12_UTILITY'!L34 -> 1346.9265 | ... AR35: ='12_UTILITY'!AR33*'12_UTILITY'!AR34 -> 9789.8654
A36: Transferts de l'État | B36: M USD | E36: ='12_UTILITY'!$C$17*IF('06_CONSTRUCTION'!E4>='06_CONSTRUCTION'!$C$8,'27_SCENARIOS'!$C$32,1)*'06_CONSTRUCTION'!E18/'06_CONSTRUCTION'!E20 -> 81.509434 | F36: ='12_UTILITY'!$C$17*IF('06_CONSTRUCTION'!F4>='06_CONSTRUCTION'!$C$8,'27_SCENARIOS'!$C$32,1)*'06_CONSTRUCTION'!F18/'06_CONSTRUCTION'!F20 -> 83.047348 | G36: ='12_UTILITY'!$C$17*IF('06_CONSTRUCTION'!G4>='06_CONSTRUCTION'!$C$8,'27_SCENARIOS'!$C$32,1)*'06_CONSTRUCTION'!G18/'06_CONSTRUCTION'!G20 -> 84.614279 | H36: ='12_UTILITY'!$C$17*IF('06_CONSTRUCTION'!H4>='06_CONSTRUCTION'!$C$8,'27_SCENARIOS'!$C$32,1)*'06_CONSTRUCTION'!H18/'06_CONSTRUCTION'!H20 -> 86.210775 | I36: ='12_UTILITY'!$C$17*IF('06_CONSTRUCTION'!I4>='06_CONSTRUCTION'!$C$8,'27_SCENARIOS'!$C$32,1)*'06_CONSTRUCTION'!I18/'06_CONSTRUCTION'!I20 -> 87.837393 | J36: ='12_UTILITY'!$C$17*IF('06_CONSTRUCTION'!J4>='06_CONSTRUCTION'!$C$8,'27_SCENARIOS'!$C$32,1)*'06_CONSTRUCTION'!J18/'06_CONSTRUCTION'!J20 -> 89.494702 | K36: ='12_UTILITY'!$C$17*IF('06_CONSTRUCTION'!K4>='06_CONSTRUCTION'!$C$8,'27_SCENARIOS'!$C$32,1)*'06_CONSTRUCTION'!K18/'06_CONSTRUCTION'!K20 -> 91.183282 | L36: ='12_UTILITY'!$C$17*IF('06_CONSTRUCTION'!L4>='06_CONSTRUCTION'!$C$8,'27_SCENARIOS'!$C$32,1)*'06_CONSTRUCTION'!L18/'06_CONSTRUCTION'!L20 -> 92.903721 | ... AR36: ='12_UTILITY'!$C$17*IF('06_CONSTRUCTION'!AR4>='06_CONSTRUCTION'!$C$8,'27_SCENARIOS'!$C$32,1)*'06_CONSTRUCTION'!AR18/'06_CONSTRUCTION'!AR20 -> 168.96844
A37: OPEX compagnie | B37: M USD | E37: =-'12_UTILITY'!$C$16*'06_CONSTRUCTION'!E18/'06_CONSTRUCTION'!E20*(0.5+0.5*'12_UTILITY'!E28/'10_DEMAND'!$C$99) -> -189.73787 | F37: =-'12_UTILITY'!$C$16*'06_CONSTRUCTION'!F18/'06_CONSTRUCTION'!F20*(0.5+0.5*'12_UTILITY'!F28/'10_DEMAND'!$C$99) -> -197.57929 | G37: =-'12_UTILITY'!$C$16*'06_CONSTRUCTION'!G18/'06_CONSTRUCTION'!G20*(0.5+0.5*'12_UTILITY'!G28/'10_DEMAND'!$C$99) -> -205.84445 | H37: =-'12_UTILITY'!$C$16*'06_CONSTRUCTION'!H18/'06_CONSTRUCTION'!H20*(0.5+0.5*'12_UTILITY'!H28/'10_DEMAND'!$C$99) -> -217.22427 | I37: =-'12_UTILITY'!$C$16*'06_CONSTRUCTION'!I18/'06_CONSTRUCTION'!I20*(0.5+0.5*'12_UTILITY'!I28/'10_DEMAND'!$C$99) -> -226.94555 | J37: =-'12_UTILITY'!$C$16*'06_CONSTRUCTION'!J18/'06_CONSTRUCTION'!J20*(0.5+0.5*'12_UTILITY'!J28/'10_DEMAND'!$C$99) -> -236.70394 | K37: =-'12_UTILITY'!$C$16*'06_CONSTRUCTION'!K18/'06_CONSTRUCTION'!K20*(0.5+0.5*'12_UTILITY'!K28/'10_DEMAND'!$C$99) -> -247.00087 | L37: =-'12_UTILITY'!$C$16*'06_CONSTRUCTION'!L18/'06_CONSTRUCTION'!L20*(0.5+0.5*'12_UTILITY'!L28/'10_DEMAND'!$C$99) -> -257.86943 | ... AR37: =-'12_UTILITY'!$C$16*'06_CONSTRUCTION'!AR18/'06_CONSTRUCTION'!AR20*(0.5+0.5*'12_UTILITY'!AR28/'10_DEMAND'!$C$99) -> -1273.0604
A38: Coût des autres sources | B38: M USD | E38: =-'12_UTILITY'!E26*'12_UTILITY'!$C$14*('12_UTILITY'!$C$15*'06_CONSTRUCTION'!E17+(1-'12_UTILITY'!$C$15)*'06_CONSTRUCTION'!E18/'06_CONSTRUCTION'!E20)/1000 -> -503.89092 | F38: =-'12_UTILITY'!F26*'12_UTILITY'!$C$14*('12_UTILITY'!$C$15*'06_CONSTRUCTION'!F17+(1-'12_UTILITY'!$C$15)*'06_CONSTRUCTION'!F18/'06_CONSTRUCTION'!F20)/1000 -> -536.79944 | G38: =-'12_UTILITY'!G26*'12_UTILITY'!$C$14*('12_UTILITY'!$C$15*'06_CONSTRUCTION'!G17+(1-'12_UTILITY'!$C$15)*'06_CONSTRUCTION'!G18/'06_CONSTRUCTION'!G20)/1000 -> -571.85735 | H38: =-'12_UTILITY'!H26*'12_UTILITY'!$C$14*('12_UTILITY'!$C$15*'06_CONSTRUCTION'!H17+(1-'12_UTILITY'!$C$15)*'06_CONSTRUCTION'!H18/'06_CONSTRUCTION'!H20)/1000 -> -609.20505 | I38: =-'12_UTILITY'!I26*'12_UTILITY'!$C$14*('12_UTILITY'!$C$15*'06_CONSTRUCTION'!I17+(1-'12_UTILITY'!$C$15)*'06_CONSTRUCTION'!I18/'06_CONSTRUCTION'!I20)/1000 -> -648.99212 | J38: =-'12_UTILITY'!J26*'12_UTILITY'!$C$14*('12_UTILITY'!$C$15*'06_CONSTRUCTION'!J17+(1-'12_UTILITY'!$C$15)*'06_CONSTRUCTION'!J18/'06_CONSTRUCTION'!J20)/1000 -> -691.37788 | K38: =-'12_UTILITY'!K26*'12_UTILITY'!$C$14*('12_UTILITY'!$C$15*'06_CONSTRUCTION'!K17+(1-'12_UTILITY'!$C$15)*'06_CONSTRUCTION'!K18/'06_CONSTRUCTION'!K20)/1000 -> -736.53209 | L38: =-'12_UTILITY'!L26*'12_UTILITY'!$C$14*('12_UTILITY'!$C$15*'06_CONSTRUCTION'!L17+(1-'12_UTILITY'!$C$15)*'06_CONSTRUCTION'!L18/'06_CONSTRUCTION'!L20)/1000 -> -784.63558 | ... AR38: =-'12_UTILITY'!AR26*'12_UTILITY'!$C$14*('12_UTILITY'!$C$15*'06_CONSTRUCTION'!AR17+(1-'12_UTILITY'!$C$15)*'06_CONSTRUCTION'!AR18/'06_CONSTRUCTION'!AR20)/1000 -> -5942.663
A39: Service dette existante | B39: M USD | E39: =-'12_UTILITY'!$C$18 -> -85 | F39: =-'12_UTILITY'!$C$18 -> -85 | G39: =-'12_UTILITY'!$C$18 -> -85 | H39: =-'12_UTILITY'!$C$18 -> -85 | I39: =-'12_UTILITY'!$C$18 -> -85 | J39: =-'12_UTILITY'!$C$18 -> -85 | K39: =-'12_UTILITY'!$C$18 -> -85 | L39: =-'12_UTILITY'!$C$18 -> -85 | ... AR39: =-'12_UTILITY'!$C$18 -> -85
A40: Trésorerie disponible après offre substituée, avant paiement du nouveau CAE | B40: M USD | E40: ='12_UTILITY'!E35+'12_UTILITY'!E36+'12_UTILITY'!E37+'12_UTILITY'!E38+'12_UTILITY'!E39 -> 151.36468 | F40: ='12_UTILITY'!F35+'12_UTILITY'!F36+'12_UTILITY'!F37+'12_UTILITY'!F38+'12_UTILITY'!F39 -> 167.06398 | G40: ='12_UTILITY'!G35+'12_UTILITY'!G36+'12_UTILITY'!G37+'12_UTILITY'!G38+'12_UTILITY'!G39 -> 183.77286 | H40: ='12_UTILITY'!H35+'12_UTILITY'!H36+'12_UTILITY'!H37+'12_UTILITY'!H38+'12_UTILITY'!H39 -> 223.21962 | I40: ='12_UTILITY'!I35+'12_UTILITY'!I36+'12_UTILITY'!I37+'12_UTILITY'!I38+'12_UTILITY'!I39 -> 246.44856 | J40: ='12_UTILITY'!J35+'12_UTILITY'!J36+'12_UTILITY'!J37+'12_UTILITY'!J38+'12_UTILITY'!J39 -> 267.07846 | K40: ='12_UTILITY'!K35+'12_UTILITY'!K36+'12_UTILITY'!K37+'12_UTILITY'!K38+'12_UTILITY'!K39 -> 289.00989 | L40: ='12_UTILITY'!L35+'12_UTILITY'!L36+'12_UTILITY'!L37+'12_UTILITY'!L38+'12_UTILITY'!L39 -> 312.32524 | ... AR40: ='12_UTILITY'!AR35+'12_UTILITY'!AR36+'12_UTILITY'!AR37+'12_UTILITY'!AR38+'12_UTILITY'!AR39 -> 2658.1104
A41: PAIEMENT CAE MAXIMAL SOUTENABLE | B41: M USD | E41: =MAX(0,'12_UTILITY'!E40)/'12_UTILITY'!$C$21 -> 126.13724 | F41: =MAX(0,'12_UTILITY'!F40)/'12_UTILITY'!$C$21 -> 139.21999 | G41: =MAX(0,'12_UTILITY'!G40)/'12_UTILITY'!$C$21 -> 153.14405 | H41: =MAX(0,'12_UTILITY'!H40)/'12_UTILITY'!$C$21 -> 186.01635 | I41: =MAX(0,'12_UTILITY'!I40)/'12_UTILITY'!$C$21 -> 205.3738 | J41: =MAX(0,'12_UTILITY'!J40)/'12_UTILITY'!$C$21 -> 222.56539 | K41: =MAX(0,'12_UTILITY'!K40)/'12_UTILITY'!$C$21 -> 240.84157 | L41: =MAX(0,'12_UTILITY'!L40)/'12_UTILITY'!$C$21 -> 260.27103 | ... AR41: =MAX(0,'12_UTILITY'!AR40)/'12_UTILITY'!$C$21 -> 2215.092
A42: Paiement CAE facturé par le projet (part compagnie) | B42: M USD | E42: ='16_REVENUE'!E15 -> 0 | F42: ='16_REVENUE'!F15 -> 0 | G42: ='16_REVENUE'!G15 -> 0 | H42: ='16_REVENUE'!H15 -> 28.991857 | I42: ='16_REVENUE'!I15 -> 34.462649 | J42: ='16_REVENUE'!J15 -> 34.824323 | K42: ='16_REVENUE'!K15 -> 35.193231 | L42: ='16_REVENUE'!L15 -> 35.569516 | ... AR42: ='16_REVENUE'!AR15 -> 0
A43: ÉCART DE CAPACITÉ DE PAIEMENT ACHETEUR | B43: M USD | C43: =SUM('12_UTILITY'!$E$43:$AR$43) -> 0 | E43: ='06_CONSTRUCTION'!E14*MAX(0,'12_UTILITY'!E42-'12_UTILITY'!E41) -> 0 | F43: ='06_CONSTRUCTION'!F14*MAX(0,'12_UTILITY'!F42-'12_UTILITY'!F41) -> 0 | G43: ='06_CONSTRUCTION'!G14*MAX(0,'12_UTILITY'!G42-'12_UTILITY'!G41) -> 0 | H43: ='06_CONSTRUCTION'!H14*MAX(0,'12_UTILITY'!H42-'12_UTILITY'!H41) -> 0 | I43: ='06_CONSTRUCTION'!I14*MAX(0,'12_UTILITY'!I42-'12_UTILITY'!I41) -> 0 | J43: ='06_CONSTRUCTION'!J14*MAX(0,'12_UTILITY'!J42-'12_UTILITY'!J41) -> 0 | K43: ='06_CONSTRUCTION'!K14*MAX(0,'12_UTILITY'!K42-'12_UTILITY'!K41) -> 0 | L43: ='06_CONSTRUCTION'!L14*MAX(0,'12_UTILITY'!L42-'12_UTILITY'!L41) -> 0 | ... AR43: ='06_CONSTRUCTION'!AR14*MAX(0,'12_UTILITY'!AR42-'12_UTILITY'!AR41) -> 0
A44: Capacité de paiement / paiement CAE | B44: x | E44: =IF('12_UTILITY'!E42>0,'12_UTILITY'!E41/'12_UTILITY'!E42,99) -> 99 | F44: =IF('12_UTILITY'!F42>0,'12_UTILITY'!F41/'12_UTILITY'!F42,99) -> 99 | G44: =IF('12_UTILITY'!G42>0,'12_UTILITY'!G41/'12_UTILITY'!G42,99) -> 99 | H44: =IF('12_UTILITY'!H42>0,'12_UTILITY'!H41/'12_UTILITY'!H42,99) -> 6.4161585 | I44: =IF('12_UTILITY'!I42>0,'12_UTILITY'!I41/'12_UTILITY'!I42,99) -> 5.9593154 | J44: =IF('12_UTILITY'!J42>0,'12_UTILITY'!J41/'12_UTILITY'!J42,99) -> 6.3910901 | K44: =IF('12_UTILITY'!K42>0,'12_UTILITY'!K41/'12_UTILITY'!K42,99) -> 6.8434062 | L44: =IF('12_UTILITY'!L42>0,'12_UTILITY'!L41/'12_UTILITY'!L42,99) -> 7.3172497 | ... AR44: =IF('12_UTILITY'!AR42>0,'12_UTILITY'!AR41/'12_UTILITY'!AR42,99) -> 99
A45: Ratio 10 premières années | B45: x | C45: =IF(COUNT('12_UTILITY'!$E$45:$AR$45)=0,99,MIN('12_UTILITY'!$E$45:$AR$45)) -> 5.9593154 | E45: =IF(AND('06_CONSTRUCTION'!E5>=1,'06_CONSTRUCTION'!E5<=10),'12_UTILITY'!E44,"") | F45: =IF(AND('06_CONSTRUCTION'!F5>=1,'06_CONSTRUCTION'!F5<=10),'12_UTILITY'!F44,"") | G45: =IF(AND('06_CONSTRUCTION'!G5>=1,'06_CONSTRUCTION'!G5<=10),'12_UTILITY'!G44,"") | H45: =IF(AND('06_CONSTRUCTION'!H5>=1,'06_CONSTRUCTION'!H5<=10),'12_UTILITY'!H44,"") -> 6.4161585 | I45: =IF(AND('06_CONSTRUCTION'!I5>=1,'06_CONSTRUCTION'!I5<=10),'12_UTILITY'!I44,"") -> 5.9593154 | J45: =IF(AND('06_CONSTRUCTION'!J5>=1,'06_CONSTRUCTION'!J5<=10),'12_UTILITY'!J44,"") -> 6.3910901 | K45: =IF(AND('06_CONSTRUCTION'!K5>=1,'06_CONSTRUCTION'!K5<=10),'12_UTILITY'!K44,"") -> 6.8434062 | L45: =IF(AND('06_CONSTRUCTION'!L5>=1,'06_CONSTRUCTION'!L5<=10),'12_UTILITY'!L44,"") -> 7.3172497 | ... AR45: =IF(AND('06_CONSTRUCTION'!AR5>=1,'06_CONSTRUCTION'!AR5<=10),'12_UTILITY'!AR44,"")
A46: Déficit de trésorerie préexistant de la compagnie (avant tout nouveau CAE) | B46: M USD | C46: =SUM('12_UTILITY'!$E$46:$AR$46) -> 0 | E46: =MAX(0,-'12_UTILITY'!E40) -> 0 | F46: =MAX(0,-'12_UTILITY'!F40) -> 0 | G46: =MAX(0,-'12_UTILITY'!G40) -> 0 | H46: =MAX(0,-'12_UTILITY'!H40) -> 0 | I46: =MAX(0,-'12_UTILITY'!I40) -> 0 | J46: =MAX(0,-'12_UTILITY'!J40) -> 0 | K46: =MAX(0,-'12_UTILITY'!K40) -> 0 | L46: =MAX(0,-'12_UTILITY'!L40) -> 0 | ... AR46: =MAX(0,-'12_UTILITY'!AR40) -> 0
A47: D. INDICATEURS
A48: EBITDA de la compagnie (hors transferts) | B48: M USD | E48: ='12_UTILITY'!E33+'12_UTILITY'!E37+'12_UTILITY'!E38-'12_UTILITY'!E42 -> 270.55762 | F48: ='12_UTILITY'!F33+'12_UTILITY'!F37+'12_UTILITY'!F38-'12_UTILITY'!F42 -> 292.20691 | G48: ='12_UTILITY'!G33+'12_UTILITY'!G37+'12_UTILITY'!G38-'12_UTILITY'!G42 -> 315.32136 | H48: ='12_UTILITY'!H33+'12_UTILITY'!H37+'12_UTILITY'!H38-'12_UTILITY'!H42 -> 335.98583 | I48: ='12_UTILITY'!I33+'12_UTILITY'!I37+'12_UTILITY'!I38-'12_UTILITY'!I42 -> 361.81427 | J48: ='12_UTILITY'!J33+'12_UTILITY'!J37+'12_UTILITY'!J38-'12_UTILITY'!J42 -> 390.12293 | K48: ='12_UTILITY'!K33+'12_UTILITY'!K37+'12_UTILITY'!K38-'12_UTILITY'!K42 -> 420.31877 | L48: ='12_UTILITY'!L33+'12_UTILITY'!L37+'12_UTILITY'!L38-'12_UTILITY'!L42 -> 452.5238 | ... AR48: ='12_UTILITY'!AR33+'12_UTILITY'!AR37+'12_UTILITY'!AR38-'12_UTILITY'!AR42 -> 3909.1236
A49: EBITDA de la compagnie, transferts de l'État inclus | B49: M USD | E49: ='12_UTILITY'!E48+'12_UTILITY'!E36 -> 352.06705 | F49: ='12_UTILITY'!F48+'12_UTILITY'!F36 -> 375.25426 | G49: ='12_UTILITY'!G48+'12_UTILITY'!G36 -> 399.93564 | H49: ='12_UTILITY'!H48+'12_UTILITY'!H36 -> 422.1966 | I49: ='12_UTILITY'!I48+'12_UTILITY'!I36 -> 449.65166 | J49: ='12_UTILITY'!J48+'12_UTILITY'!J36 -> 479.61763 | K49: ='12_UTILITY'!K48+'12_UTILITY'!K36 -> 511.50205 | L49: ='12_UTILITY'!L48+'12_UTILITY'!L36 -> 545.42752 | ... AR49: ='12_UTILITY'!AR48+'12_UTILITY'!AR36 -> 4078.092
A50: Marge d'exploitation (EBITDA / facturé) | B50: % | E50: =IF('12_UTILITY'!E33>0,'12_UTILITY'!E48/'12_UTILITY'!E33,0) -> 0.28060717 | F50: =IF('12_UTILITY'!F33>0,'12_UTILITY'!F48/'12_UTILITY'!F33,0) -> 0.28463959 | G50: =IF('12_UTILITY'!G33>0,'12_UTILITY'!G48/'12_UTILITY'!G33,0) -> 0.28848553 | H50: =IF('12_UTILITY'!H33>0,'12_UTILITY'!H48/'12_UTILITY'!H33,0) -> 0.2820076 | I50: =IF('12_UTILITY'!I33>0,'12_UTILITY'!I48/'12_UTILITY'!I33,0) -> 0.2843972 | J50: =IF('12_UTILITY'!J33>0,'12_UTILITY'!J48/'12_UTILITY'!J33,0) -> 0.288333 | K50: =IF('12_UTILITY'!K33>0,'12_UTILITY'!K48/'12_UTILITY'!K33,0) -> 0.29208175 | L50: =IF('12_UTILITY'!L33>0,'12_UTILITY'!L48/'12_UTILITY'!L33,0) -> 0.29565157 | ... AR50: =IF('12_UTILITY'!AR33>0,'12_UTILITY'!AR48/'12_UTILITY'!AR33,0) -> 0.35138673
A51: CAE payé sur trésorerie propre | B51: M USD | E51: ='12_UTILITY'!E42-'12_UTILITY'!E43 -> 0 | F51: ='12_UTILITY'!F42-'12_UTILITY'!F43 -> 0 | G51: ='12_UTILITY'!G42-'12_UTILITY'!G43 -> 0 | H51: ='12_UTILITY'!H42-'12_UTILITY'!H43 -> 28.991857 | I51: ='12_UTILITY'!I42-'12_UTILITY'!I43 -> 34.462649 | J51: ='12_UTILITY'!J42-'12_UTILITY'!J43 -> 34.824323 | K51: ='12_UTILITY'!K42-'12_UTILITY'!K43 -> 35.193231 | L51: ='12_UTILITY'!L42-'12_UTILITY'!L43 -> 35.569516 | ... AR51: ='12_UTILITY'!AR42-'12_UTILITY'!AR43 -> 0
A52: Trésorerie compagnie après CAE | B52: M USD | E52: ='12_UTILITY'!E40-'12_UTILITY'!E51 -> 151.36468 | F52: ='12_UTILITY'!F40-'12_UTILITY'!F51 -> 167.06398 | G52: ='12_UTILITY'!G40-'12_UTILITY'!G51 -> 183.77286 | H52: ='12_UTILITY'!H40-'12_UTILITY'!H51 -> 194.22776 | I52: ='12_UTILITY'!I40-'12_UTILITY'!I51 -> 211.98591 | J52: ='12_UTILITY'!J40-'12_UTILITY'!J51 -> 232.25414 | K52: ='12_UTILITY'!K40-'12_UTILITY'!K51 -> 253.81666 | L52: ='12_UTILITY'!L40-'12_UTILITY'!L51 -> 276.75572 | ... AR52: ='12_UTILITY'!AR40-'12_UTILITY'!AR51 -> 2658.1104
A53: DSCR compagnie, dette existante | B53: x | E53: =('12_UTILITY'!E40-'12_UTILITY'!E39-'12_UTILITY'!E51)/-'12_UTILITY'!E39 -> 2.780761 | F53: =('12_UTILITY'!F40-'12_UTILITY'!F39-'12_UTILITY'!F51)/-'12_UTILITY'!F39 -> 2.9654586 | G53: =('12_UTILITY'!G40-'12_UTILITY'!G39-'12_UTILITY'!G51)/-'12_UTILITY'!G39 -> 3.1620337 | H53: =('12_UTILITY'!H40-'12_UTILITY'!H39-'12_UTILITY'!H51)/-'12_UTILITY'!H39 -> 3.2850325 | I53: =('12_UTILITY'!I40-'12_UTILITY'!I39-'12_UTILITY'!I51)/-'12_UTILITY'!I39 -> 3.4939519 | J53: =('12_UTILITY'!J40-'12_UTILITY'!J39-'12_UTILITY'!J51)/-'12_UTILITY'!J39 -> 3.7324016 | K53: =('12_UTILITY'!K40-'12_UTILITY'!K39-'12_UTILITY'!K51)/-'12_UTILITY'!K39 -> 3.9860783 | L53: =('12_UTILITY'!L40-'12_UTILITY'!L39-'12_UTILITY'!L51)/-'12_UTILITY'!L39 -> 4.2559496 | ... AR53: =('12_UTILITY'!AR40-'12_UTILITY'!AR39-'12_UTILITY'!AR51)/-'12_UTILITY'!AR39 -> 32.271887
A54: Créances (clôture) | B54: M USD | E54: =IF(1=1,'12_UTILITY'!$C$19,'12_UTILITY'!D54)*(1-'12_UTILITY'!$C$20)+'12_UTILITY'!E33-'12_UTILITY'!E35 -> 241.70237 | F54: =IF(2=1,'12_UTILITY'!$C$19,'12_UTILITY'!E54)*(1-'12_UTILITY'!$C$20)+'12_UTILITY'!F33-'12_UTILITY'!F35 -> 292.38193 | G54: =IF(3=1,'12_UTILITY'!$C$19,'12_UTILITY'!F54)*(1-'12_UTILITY'!$C$20)+'12_UTILITY'!G33-'12_UTILITY'!G35 -> 335.83013 | H54: =IF(4=1,'12_UTILITY'!$C$19,'12_UTILITY'!G54)*(1-'12_UTILITY'!$C$20)+'12_UTILITY'!H33-'12_UTILITY'!H35 -> 378.04993 | I54: =IF(5=1,'12_UTILITY'!$C$19,'12_UTILITY'!H54)*(1-'12_UTILITY'!$C$20)+'12_UTILITY'!I33-'12_UTILITY'!I35 -> 417.3007 | J54: =IF(6=1,'12_UTILITY'!$C$19,'12_UTILITY'!I54)*(1-'12_UTILITY'!$C$20)+'12_UTILITY'!J33-'12_UTILITY'!J35 -> 454.47398 | K54: =IF(7=1,'12_UTILITY'!$C$19,'12_UTILITY'!J54)*(1-'12_UTILITY'!$C$20)+'12_UTILITY'!K33-'12_UTILITY'!K35 -> 490.81718 | L54: =IF(8=1,'12_UTILITY'!$C$19,'12_UTILITY'!K54)*(1-'12_UTILITY'!$C$20)+'12_UTILITY'!L33-'12_UTILITY'!L35 -> 527.24383 | M54: =IF(9=1,'12_UTILITY'!$C$19,'12_UTILITY'!L54)*(1-'12_UTILITY'!$C$20)+'12_UTILITY'!M33-'12_UTILITY'!M35 -> 564.43632 | N54: =IF(10=1,'12_UTILITY'!$C$19,'12_UTILITY'!M54)*(1-'12_UTILITY'!$C$20)+'12_UTILITY'!N33-'12_UTILITY'!N35 -> 602.91805 | O54: =IF(11=1,'12_UTILITY'!$C$19,'12_UTILITY'!N54)*(1-'12_UTILITY'!$C$20)+'12_UTILITY'!O33-'12_UTILITY'!O35 -> 643.10408 | P54: =IF(12=1,'12_UTILITY'!$C$19,'12_UTILITY'!O54)*(1-'12_UTILITY'!$C$20)+'12_UTILITY'!P33-'12_UTILITY'!P35 -> 685.33676 | Q54: =IF(13=1,'12_UTILITY'!$C$19,'12_UTILITY'!P54)*(1-'12_UTILITY'!$C$20)+'12_UTILITY'!Q33-'12_UTILITY'!Q35 -> 729.91092 | R54: =IF(14=1,'12_UTILITY'!$C$19,'12_UTILITY'!Q54)*(1-'12_UTILITY'!$C$20)+'12_UTILITY'!R33-'12_UTILITY'!R35 -> 777.09168 | S54: =IF(15=1,'12_UTILITY'!$C$19,'12_UTILITY'!R54)*(1-'12_UTILITY'!$C$20)+'12_UTILITY'!S33-'12_UTILITY'!S35 -> 827.12717 | T54: =IF(16=1,'12_UTILITY'!$C$19,'12_UTILITY'!S54)*(1-'12_UTILITY'!$C$20)+'12_UTILITY'!T33-'12_UTILITY'!T35 -> 880.25766 | U54: =IF(17=1,'12_UTILITY'!$C$19,'12_UTILITY'!T54)*(1-'12_UTILITY'!$C$20)+'12_UTILITY'!U33-'12_UTILITY'!U35 -> 936.72225 | V54: =IF(18=1,'12_UTILITY'!$C$19,'12_UTILITY'!U54)*(1-'12_UTILITY'!$C$20)+'12_UTILITY'!V33-'12_UTILITY'!V35 -> 996.76379 | W54: =IF(19=1,'12_UTILITY'!$C$19,'12_UTILITY'!V54)*(1-'12_UTILITY'!$C$20)+'12_UTILITY'!W33-'12_UTILITY'!W35 -> 1060.6326 | X54: =IF(20=1,'12_UTILITY'!$C$19,'12_UTILITY'!W54)*(1-'12_UTILITY'!$C$20)+'12_UTILITY'!X33-'12_UTILITY'!X35 -> 1128.5896 | Y54: =IF(21=1,'12_UTILITY'!$C$19,'12_UTILITY'!X54)*(1-'12_UTILITY'!$C$20)+'12_UTILITY'!Y33-'12_UTILITY'!Y35 -> 1200.9085 | Z54: =IF(22=1,'12_UTILITY'!$C$19,'12_UTILITY'!Y54)*(1-'12_UTILITY'!$C$20)+'12_UTILITY'!Z33-'12_UTILITY'!Z35 -> 1277.8777 | AA54: =IF(23=1,'12_UTILITY'!$C$19,'12_UTILITY'!Z54)*(1-'12_UTILITY'!$C$20)+'12_UTILITY'!AA33-'12_UTILITY'!AA35 -> 1359.8025 | AB54: =IF(24=1,'12_UTILITY'!$C$19,'12_UTILITY'!AA54)*(1-'12_UTILITY'!$C$20)+'12_UTILITY'!AB33-'12_UTILITY'!AB35 -> 1447.0068 | AC54: =IF(25=1,'12_UTILITY'!$C$19,'12_UTILITY'!AB54)*(1-'12_UTILITY'!$C$20)+'12_UTILITY'!AC33-'12_UTILITY'!AC35 -> 1539.8339 | AD54: =IF(26=1,'12_UTILITY'!$C$19,'12_UTILITY'!AC54)*(1-'12_UTILITY'!$C$20)+'12_UTILITY'!AD33-'12_UTILITY'!AD35 -> 1638.6492 | AE54: =IF(27=1,'12_UTILITY'!$C$19,'12_UTILITY'!AD54)*(1-'12_UTILITY'!$C$20)+'12_UTILITY'!AE33-'12_UTILITY'!AE35 -> 1743.841 | AF54: =IF(28=1,'12_UTILITY'!$C$19,'12_UTILITY'!AE54)*(1-'12_UTILITY'!$C$20)+'12_UTILITY'!AF33-'12_UTILITY'!AF35 -> 1855.8224 | AG54: =IF(29=1,'12_UTILITY'!$C$19,'12_UTILITY'!AF54)*(1-'12_UTILITY'!$C$20)+'12_UTILITY'!AG33-'12_UTILITY'!AG35 -> 1968.805 | AH54: =IF(30=1,'12_UTILITY'!$C$19,'12_UTILITY'!AG54)*(1-'12_UTILITY'!$C$20)+'12_UTILITY'!AH33-'12_UTILITY'!AH35 -> 2091.2357 | AI54: =IF(31=1,'12_UTILITY'!$C$19,'12_UTILITY'!AH54)*(1-'12_UTILITY'!$C$20)+'12_UTILITY'!AI33-'12_UTILITY'!AI35 -> 2223.085 | AJ54: =IF(32=1,'12_UTILITY'!$C$19,'12_UTILITY'!AI54)*(1-'12_UTILITY'!$C$20)+'12_UTILITY'!AJ33-'12_UTILITY'!AJ35 -> 2364.514 | AK54: =IF(33=1,'12_UTILITY'!$C$19,'12_UTILITY'!AJ54)*(1-'12_UTILITY'!$C$20)+'12_UTILITY'!AK33-'12_UTILITY'!AK35 -> 2515.8285 | AL54: =IF(34=1,'12_UTILITY'!$C$19,'12_UTILITY'!AK54)*(1-'12_UTILITY'!$C$20)+'12_UTILITY'!AL33-'12_UTILITY'!AL35 -> 2677.4486 | AM54: =IF(35=1,'12_UTILITY'!$C$19,'12_UTILITY'!AL54)*(1-'12_UTILITY'!$C$20)+'12_UTILITY'!AM33-'12_UTILITY'!AM35 -> 2849.8873 | AN54: =IF(36=1,'12_UTILITY'!$C$19,'12_UTILITY'!AM54)*(1-'12_UTILITY'!$C$20)+'12_UTILITY'!AN33-'12_UTILITY'!AN35 -> 3033.7369 | AO54: =IF(37=1,'12_UTILITY'!$C$19,'12_UTILITY'!AN54)*(1-'12_UTILITY'!$C$20)+'12_UTILITY'!AO33-'12_UTILITY'!AO35 -> 3229.6607 | AP54: =IF(38=1,'12_UTILITY'!$C$19,'12_UTILITY'!AO54)*(1-'12_UTILITY'!$C$20)+'12_UTILITY'!AP33-'12_UTILITY'!AP35 -> 3438.3873 | AQ54: =IF(39=1,'12_UTILITY'!$C$19,'12_UTILITY'!AP54)*(1-'12_UTILITY'!$C$20)+'12_UTILITY'!AQ33-'12_UTILITY'!AQ35 -> 3660.7082 | AR54: =IF(40=1,'12_UTILITY'!$C$19,'12_UTILITY'!AQ54)*(1-'12_UTILITY'!$C$20)+'12_UTILITY'!AR33-'12_UTILITY'!AR35 -> 3897.4774
A55: Jours de créances | B55: jours | E55: =IF('12_UTILITY'!E33>0,'12_UTILITY'!E54/'12_UTILITY'!E33*365,0) -> 91.498246 | F55: =IF('12_UTILITY'!F33>0,'12_UTILITY'!F54/'12_UTILITY'!F33*365,0) -> 103.95568 | G55: =IF('12_UTILITY'!G33>0,'12_UTILITY'!G54/'12_UTILITY'!G33*365,0) -> 112.14584 | H55: =IF('12_UTILITY'!H33>0,'12_UTILITY'!H54/'12_UTILITY'!H33*365,0) -> 115.81955 | I55: =IF('12_UTILITY'!I33>0,'12_UTILITY'!I54/'12_UTILITY'!I33*365,0) -> 119.72411 | J55: =IF('12_UTILITY'!J33>0,'12_UTILITY'!J54/'12_UTILITY'!J33*365,0) -> 122.60121 | K55: =IF('12_UTILITY'!K33>0,'12_UTILITY'!K54/'12_UTILITY'!K33*365,0) -> 124.49109 | L55: =IF('12_UTILITY'!L33>0,'12_UTILITY'!L54/'12_UTILITY'!L33*365,0) -> 125.73122 | ... AR55: =IF('12_UTILITY'!AR33>0,'12_UTILITY'!AR54/'12_UTILITY'!AR33*365,0) -> 127.87405
A56: Arriérés CAE impayés cumulés envers le projet | B56: M USD | E56: ='12_UTILITY'!D56+'16_REVENUE'!E24 -> 0 | F56: ='12_UTILITY'!E56+'16_REVENUE'!F24 -> 0 | G56: ='12_UTILITY'!F56+'16_REVENUE'!G24 -> 0 | H56: ='12_UTILITY'!G56+'16_REVENUE'!H24 -> 0 | I56: ='12_UTILITY'!H56+'16_REVENUE'!I24 -> 0 | J56: ='12_UTILITY'!I56+'16_REVENUE'!J24 -> 0 | K56: ='12_UTILITY'!J56+'16_REVENUE'!K24 -> 0 | L56: ='12_UTILITY'!K56+'16_REVENUE'!L24 -> 0 | ... AR56: ='12_UTILITY'!AQ56+'16_REVENUE'!AR24 -> 0
A57: Cas sans projet : achats aux autres sources | B57: GWh | E57: =MIN('12_UTILITY'!E24+'04_GENERATION'!E20*'11_OFFTAKER'!$C$7/(1-'12_UTILITY'!$C$11-'12_UTILITY'!$C$12)*'06_CONSTRUCTION'!E14,'10_DEMAND'!E31) -> 8987 | F57: =MIN('12_UTILITY'!F24+'04_GENERATION'!F20*'11_OFFTAKER'!$C$7/(1-'12_UTILITY'!$C$11-'12_UTILITY'!$C$12)*'06_CONSTRUCTION'!F14,'10_DEMAND'!F31) -> 9391.415 | G57: =MIN('12_UTILITY'!G24+'04_GENERATION'!G20*'11_OFFTAKER'!$C$7/(1-'12_UTILITY'!$C$11-'12_UTILITY'!$C$12)*'06_CONSTRUCTION'!G14,'10_DEMAND'!G31) -> 9814.0287 | H57: =MIN('12_UTILITY'!H24+'04_GENERATION'!H20*'11_OFFTAKER'!$C$7/(1-'12_UTILITY'!$C$11-'12_UTILITY'!$C$12)*'06_CONSTRUCTION'!H14,'10_DEMAND'!H31) -> 10255.66 | I57: =MIN('12_UTILITY'!I24+'04_GENERATION'!I20*'11_OFFTAKER'!$C$7/(1-'12_UTILITY'!$C$11-'12_UTILITY'!$C$12)*'06_CONSTRUCTION'!I14,'10_DEMAND'!I31) -> 10717.165 | J57: =MIN('12_UTILITY'!J24+'04_GENERATION'!J20*'11_OFFTAKER'!$C$7/(1-'12_UTILITY'!$C$11-'12_UTILITY'!$C$12)*'06_CONSTRUCTION'!J14,'10_DEMAND'!J31) -> 11199.437 | K57: =MIN('12_UTILITY'!K24+'04_GENERATION'!K20*'11_OFFTAKER'!$C$7/(1-'12_UTILITY'!$C$11-'12_UTILITY'!$C$12)*'06_CONSTRUCTION'!K14,'10_DEMAND'!K31) -> 11703.412 | L57: =MIN('12_UTILITY'!L24+'04_GENERATION'!L20*'11_OFFTAKER'!$C$7/(1-'12_UTILITY'!$C$11-'12_UTILITY'!$C$12)*'06_CONSTRUCTION'!L14,'10_DEMAND'!L31) -> 12230.065 | ... AR57: =MIN('12_UTILITY'!AR24+'04_GENERATION'!AR20*'11_OFFTAKER'!$C$7/(1-'12_UTILITY'!$C$11-'12_UTILITY'!$C$12)*'06_CONSTRUCTION'!AR14,'10_DEMAND'!AR31) -> 50020.735
A58: Cas sans projet : ventes | B58: GWh | E58: ='12_UTILITY'!E57*(1-'12_UTILITY'!$C$11-'12_UTILITY'!$C$12) -> 7009.86 | F58: ='12_UTILITY'!F57*(1-'12_UTILITY'!$C$11-'12_UTILITY'!$C$12) -> 7325.3037 | G58: ='12_UTILITY'!G57*(1-'12_UTILITY'!$C$11-'12_UTILITY'!$C$12) -> 7654.9424 | H58: ='12_UTILITY'!H57*(1-'12_UTILITY'!$C$11-'12_UTILITY'!$C$12) -> 7999.4148 | I58: ='12_UTILITY'!I57*(1-'12_UTILITY'!$C$11-'12_UTILITY'!$C$12) -> 8359.3884 | J58: ='12_UTILITY'!J57*(1-'12_UTILITY'!$C$11-'12_UTILITY'!$C$12) -> 8735.5609 | K58: ='12_UTILITY'!K57*(1-'12_UTILITY'!$C$11-'12_UTILITY'!$C$12) -> 9128.6612 | L58: ='12_UTILITY'!L57*(1-'12_UTILITY'!$C$11-'12_UTILITY'!$C$12) -> 9539.4509 | ... AR58: ='12_UTILITY'!AR57*(1-'12_UTILITY'!$C$11-'12_UTILITY'!$C$12) -> 39016.173
