Workbook

Sheet Cover
A1: AFRICA ENERGY FINANCE | Business & Financial Models
A2: Volume 2 - Solar Home Systems | PAYGo Company Financial & Investment Model
A4: Model | B4: SHS / PAYGo Company Financial & Investment Model - MTF Tiers 1-5
A5: Version | B5: v0.2 - development build, generated 2026-10-02
A6: Status | B6: Draft for expert review. Default inputs are illustrative, not benchmarks.
A7: Currency | B7: Model currency = LCY. Hardware, RBF and term debt in USD, converted at the Timeline FX path.
A8: Periodicity | B8: Monthly over 60 months; annual roll-ups on Annual, KPIs and Valuation.
A9: Master check | B9: =Checks!$C$18
A11: How to use
B12: 1. Inputs - scenario, macro, volumes, opex, RBF, financing, covenants, valuation (yellow = review first).
B13: 2. Products - five MTF tiers: specification, PAYGo price plan, cost to serve, credit risk, recovery, RBF, advance rate.
B14: 3. Scenarios - Base / Downside / Severe levers.
B15: 4. Read Investment_Summary, then Dashboard, KPIs, Valuation, Covenants and Unit_Economics.
B16: 5. Audit trail: FS -> Ops -> Cohort_T1..T5 -> Curves. Every number traces back to Inputs or Products.
B17: 6. The master check must read OK before any output is used.
A19: Sheet index
A20: Investment_Summary | B20: One-page investment committee / lender summary
A21: Inputs | B21: Global inputs
A22: Products | B22: Tiers 1-5: specification, price plans, risk
A23: Scenarios | B23: Stress levers
A24: Dashboard | B24: Charts
A25: KPIs | B25: Portfolio, financial and lender KPIs
A26: Valuation | B26: DCF and investor IRR / MOIC
A27: Covenants | B27: Monthly covenant tests
A28: Unit_Economics | B28: Per-unit economics by tier
A29: Sensitivity | B29: Static scenario & sensitivity snapshot
A30: Annual | B30: Annual statements
A31: FS | B31: Monthly statements
... A39: Checks | B39: Integrity checks
A41: Colour code
A42: 1,000 | B42: Blue = hard-coded input
A43: 1,000 | B43: Yellow fill = key assumption
A44: 1,000 | B44: Black = formula
A45: 1,000 | B45: Green = link from another sheet
A47: Disclaimer | B47: Decision-support tool. Not investment, legal, tax or accounting advice. Default inputs are illustrative. Accounting simplifications (revenue recognition, ECL without staging, tax, valuation) are listed in the user manual. Users are responsible for their inputs and conclusions.

Sheet Investment_Summary
A1: Investment summary
A2: One-page view for investment committees and lenders. Active scenario, LCY unless stated.
A4: Active scenario | B4: =Scenarios!$G$12 | D4: Model version | E4: v0.2
A5: Master check | B5: =Checks!$C$18 | D5: Currency | E5: =Inputs!$C$7
A7: 1. Operating & financial trajectory
A8: Metric | B8: Year 1 | C8: Year 2 | D8: Year 3 | E8: Year 4 | F8: Year 5
A9: Units sold | B9: =KPIs!E14 | C9: =KPIs!F14 | D9: =KPIs!G14 | E9: =KPIs!H14 | F9: =KPIs!I14
A10: Active PAYGo accounts (year end) | B10: =KPIs!E16 | C10: =KPIs!F16 | D10: =KPIs!G16 | E10: =KPIs!H16 | F10: =KPIs!I16
A11: Average cash price per unit (USD) | B11: =KPIs!E15 | C11: =KPIs!F15 | D11: =KPIs!G15 | E11: =KPIs!H15 | F11: =KPIs!I15
A12: Revenue (USD, average FX) | B12: =KPIs!E32 | C12: =KPIs!F32 | D12: =KPIs!G32 | E12: =KPIs!H32 | F12: =KPIs!I32
A13: Gross margin | B13: =KPIs!E33 | C13: =KPIs!F33 | D13: =KPIs!G33 | E13: =KPIs!H33 | F13: =KPIs!I33
A14: EBITDA margin | B14: =KPIs!E35 | C14: =KPIs!F35 | D14: =KPIs!G35 | E14: =KPIs!H35 | F14: =KPIs!I35
A15: Net income (LCY) | B15: =KPIs!E38 | C15: =KPIs!F38 | D15: =KPIs!G38 | E15: =KPIs!H38 | F15: =KPIs!I38
A16: Collection rate | B16: =KPIs!E19 | C16: =KPIs!F19 | D16: =KPIs!G19 | E16: =KPIs!H19 | F16: =KPIs!I19
A17: Receivables at risk / gross receivables | B17: =KPIs!E21 | C17: =KPIs!F21 | D17: =KPIs!G21 | E17: =KPIs!H21 | F17: =KPIs!I21
A18: Total debt (LCY, year end) | B18: =KPIs!E43 | C18: =KPIs!F43 | D18: =KPIs!G43 | E18: =KPIs!H43 | F18: =KPIs!I43
A19: DSCR | B19: =KPIs!E46 | C19: =KPIs!F46 | D19: =KPIs!G46 | E19: =KPIs!H46 | F19: =KPIs!I46
A21: 2. Funding requirement
A22: Peak equity requirement (USD, opening FX) | B22: =KPIs!$C$53
A23: Peak equity requirement (LCY) | B23: =KPIs!$C$52
A24: Peak total debt (LCY) | B24: =KPIs!$C$54
A25: Total RBF received (USD) | B25: =KPIs!$C$55
A26: First month with positive EBITDA | B26: =KPIs!$C$56
A27: First month with positive operating cash flow | B27: =KPIs!$C$57
A29: 3. Valuation & equity returns
A30: DCF enterprise value at start (USD) | B30: =Valuation!$C$28
A31: Terminal value share of EV | B31: =Valuation!$C$29
A32: Exit equity value, 100% (USD, end Year 5) | B32: =Valuation!$C$36
A33: Investor stake | B33: =Valuation!$C$38
A34: Investor IRR (USD) | B34: =Valuation!$C$39
A35: Investor MOIC (USD) | B35: =Valuation!$C$40
A37: 4. Lender view
A38: Lowest trailing-3-month collection rate | B38: =KPIs!$C$58
A39: Highest receivables-at-risk ratio | B39: =KPIs!$C$59
A40: Months with any covenant breach | B40: =KPIs!$C$60
A41: Years with DSCR below minimum | B41: =KPIs!$C$61
A42: Peak facility utilisation | B42: =Financing!$C$26
A44: 5. Unit economics by tier
A45: Metric | B45: Tier 1 | C45: Tier 2 | D45: Tier 3 | E45: Tier 4 | F45: Tier 5
A46: Cash price (LCY) | B46: =Unit_Economics!C5 | C46: =Unit_Economics!D5 | D46: =Unit_Economics!E5 | E46: =Unit_Economics!F5 | F46: =Unit_Economics!G5
A47: Implied APR | B47: =Unit_Economics!C7 | C47: =Unit_Economics!D7 | D47: =Unit_Economics!E7 | E47: =Unit_Economics!F7 | F47: =Unit_Economics!G7
A48: Expected loss rate | B48: =Unit_Economics!C11 | C48: =Unit_Economics!D11 | D48: =Unit_Economics!E11 | E48: =Unit_Economics!F11 | F48: =Unit_Economics!G11
A49: LTV / CAC | B49: =Unit_Economics!C21 | C49: =Unit_Economics!D21 | D49: =Unit_Economics!E21 | E49: =Unit_Economics!F21 | F49: =Unit_Economics!G21
A50: Cash payback (months) | B50: =Unit_Economics!C22 | C50: =Unit_Economics!D22 | D50: =Unit_Economics!E22 | E50: =Unit_Economics!F22 | F50: =Unit_Economics!G22
A51: Unit IRR | B51: =Unit_Economics!C23 | C51: =Unit_Economics!D23 | D51: =Unit_Economics!E23 | E51: =Unit_Economics!F23 | F51: =Unit_Economics!G23
A53: 6. Scenario snapshot (static, default inputs - see Sensitivity)
A54: Case | B54: Peak equity (USD m) | C54: Investor IRR | D54: MOIC | E54: Breach months
A55: =IF(Sensitivity!A6="","",Sensitivity!A6) | B55: =IF(Sensitivity!B6="","",Sensitivity!B6) | C55: =IF(Sensitivity!G6="","",Sensitivity!G6) | D55: =IF(Sensitivity!H6="","",Sensitivity!H6) | E55: =IF(Sensitivity!I6="","",Sensitivity!I6)
A56: =IF(Sensitivity!A7="","",Sensitivity!A7) | B56: =IF(Sensitivity!B7="","",Sensitivity!B7) | C56: =IF(Sensitivity!G7="","",Sensitivity!G7) | D56: =IF(Sensitivity!H7="","",Sensitivity!H7) | E56: =IF(Sensitivity!I7="","",Sensitivity!I7)
A57: =IF(Sensitivity!A8="","",Sensitivity!A8) | B57: =IF(Sensitivity!B8="","",Sensitivity!B8) | C57: =IF(Sensitivity!G8="","",Sensitivity!G8) | D57: =IF(Sensitivity!H8="","",Sensitivity!H8) | E57: =IF(Sensitivity!I8="","",Sensitivity!I8)
A59: All default inputs are illustrative. Not investment advice. See Cover for the disclaimer.

Sheet Inputs
A1: Inputs
A2: Blue = input. Yellow = key assumption to review first. All defaults illustrative.
A4: Scenario & settings
A5: Active scenario (1 = Base, 2 = Downside, 3 = Severe) | B5: # | C5: 1 | D5: Drives the levers on the Scenarios sheet.
A6: First model month (period end) | B6: date | C6: =DATE(2027,1,31) | D6: Period-end date of month 1.
A7: Local currency label | B7: text | C7: LCY | D7: Display only.
A9: Macro
A10: Opening FX rate | B10: LCY per USD | C10: 130 | D10: Illustrative placeholder - replace with company data.
A11: Local inflation (opex indexation) | B11: % p.a. | C11: 0.06 | D11: Illustrative placeholder - replace with company data.
A12: Corporate income tax rate | B12: % | C12: 0.3 | D12: Simplified: unlimited loss carry-forward, tax paid in the month it arises.
A13: Annual price increase on NEW PAYGo contracts | B13: % p.a. | C13: 0.05 | D13: Existing contracts keep their price plan.
A14: Pass-through of LCY depreciation into new-contract prices | B14: % | C14: 0.5 | D14: Share of cumulative FX depreciation passed into prices of NEW contracts (0% = none, 100% = USD-indexed).
A16: Sales volume - all tiers (Base, before scenario multiplier; split by Products mix)
A17: Units sold - Year 1 | B17: units | C17: 12000 | D17: Illustrative placeholder - replace with company data.
A18: Units sold - Year 2 | B18: units | C18: 24000 | D18: Illustrative placeholder - replace with company data.
A19: Units sold - Year 3 | B19: units | C19: 36000 | D19: Illustrative placeholder - replace with company data.
A20: Units sold - Year 4 | B20: units | C20: 45000 | D20: Illustrative placeholder - replace with company data.
A21: Units sold - Year 5 | B21: units | C21: 50000 | D21: Illustrative placeholder - replace with company data.
A23: Operating costs
A24: Mobile-money / payment processing fees | B24: % of cash collected | C24: 0.02 | D24: Illustrative placeholder - replace with company data.
A25: Customer service & collections cost | B25: LCY / active account / month | C25: 150 | D25: Illustrative placeholder - replace with company data.
A26: Staff costs (fixed, month-1 level) | B26: LCY / month | C26: 26000000 | D26: Illustrative placeholder - replace with company data.
A27: G&A, rent, IT, licences (fixed, month-1 level) | B27: LCY / month | C27: 10400000 | D27: Illustrative placeholder - replace with company data.
A28: Freight, duty & clearing on hardware | B28: % of USD FOB cost | C28: 0.2 | D28: Illustrative placeholder - replace with company data.
A30: Repossession & results-based financing (RBF)
A31: Months from default to resale of repossessed unit | B31: months | C31: 3 | D31: Illustrative placeholder - replace with company data.
A32: RBF programme active (1 = yes, 0 = no) | B32: switch | C32: 1 | D32: RBF per unit is set by tier on Products. Recognised as other income when received (cash basis).
A33: Months from sale to RBF disbursement (verification lag) | B33: months | C33: 6 | D33: Illustrative placeholder - replace with company data.
A35: Working capital & capex
A36: Inventory cover | B36: months of hardware COGS | C36: 2 | D36: Illustrative placeholder - replace with company data.
A37: Supplier credit on hardware | B37: days | C37: 60 | D37: Illustrative placeholder - replace with company data.
A38: Fixed capex (vehicles, IT, depots, month-1 level) | B38: LCY / month | C38: 900000 | D38: Illustrative placeholder - replace with company data.
A39: Depreciation life of fixed capex | B39: months | C39: 36 | D39: Illustrative placeholder - replace with company data.
A40: Minimum operating cash balance | B40: LCY | C40: 100000000 | D40: Any shortfall is covered by an automatic equity top-up = funding requirement.
A42: Financing
A43: Initial equity (month 1, all shareholders) | B43: LCY | C43: 1300000000 | D43: Illustrative placeholder - replace with company data.
A44: USD term loan - amount | B44: USD | C44: 5000000 | D44: Illustrative placeholder - replace with company data.
A45: USD term loan - drawdown month | B45: month # | C45: 6 | D45: Illustrative placeholder - replace with company data.
A46: USD term loan - interest rate | B46: % p.a. | C46: 0.1 | D46: Illustrative placeholder - replace with company data.
A47: USD term loan - grace period after drawdown | B47: months | C47: 12 | D47: Illustrative placeholder - replace with company data.
A48: USD term loan - amortisation period | B48: months | C48: 36 | D48: Illustrative placeholder - replace with company data.
A49: Receivables facility (LCY) - limit | B49: LCY | C49: 6500000000 | D49: Drawn as needed to hold minimum cash (cash sweep), capped at the borrowing base and the limit. Borrowing base = sum over tiers of advance rate x eligible receivables.
A50: Receivables facility - interest rate | B50: % p.a. | C50: 0.16 | D50: Illustrative placeholder - replace with company data.
A51: Receivables facility - first available month | B51: month # | C51: 7 | D51: Illustrative placeholder - replace with company data.
A53: Lender covenants (tested on Covenants sheet)
A54: Minimum trailing-3-month collection rate | B54: % | C54: 0.7 | D54: Illustrative placeholder - replace with company data.
A55: Maximum receivables at risk / gross receivables | B55: % | C55: 0.15 | D55: Illustrative placeholder - replace with company data.
A56: Maximum debt / book equity | B56: x | C56: 3 | D56: Illustrative placeholder - replace with company data.
A57: Minimum annual DSCR (years with debt service) | B57: x | C57: 1.2 | D57: Illustrative placeholder - replace with company data.
A58: Minimum liquidity: cash before equity top-up | B58: LCY | C58: 50000000 | D58: Illustrative placeholder - replace with company data.
A60: Valuation & transaction
A61: Discount rate for DCF (LCY, nominal) | B61: % p.a. | C61: 0.22 | D61: Should reflect LCY risk-free rate, country and company risk premia.
A62: Terminal growth rate (LCY, nominal) | B62: % p.a. | C62: 0.05 | D62: Illustrative placeholder - replace with company data.
A63: Investor ticket (part of initial equity) | B63: USD | C63: 4000000 | D63: Illustrative placeholder - replace with company data.
A64: Pre-money equity valuation | B64: USD | C64: 8000000 | D64: Illustrative placeholder - replace with company data.
A65: Exit valuation method (1 = EV/EBITDA, 2 = Price/Book) | B65: # | C65: 1 | D65: Illustrative placeholder - replace with company data.
A66: Exit EV / EBITDA multiple (end of Year 5) | B66: x | C66: 6 | D66: Illustrative placeholder - replace with company data.
A67: Exit price / book equity multiple (end of Year 5) | B67: x | C67: 1.5 | D67: Illustrative placeholder - replace with company data.

Sheet Products
A1: Product range & PAYGo price plans - MTF Tiers 1-5
A2: One column per tier. Tier labels follow the MTF capacity attribute only (indicative). Blue = input.
A4: Parameter | B4: Unit | C4: Tier 1 | D4: Tier 2 | E4: Tier 3 | F4: Tier 4 | G4: Tier 5 | H4: Notes
A5: Product specification
A6: Product name | B6: text | C6: Tier 1 - Pico solar kit | D6: Tier 2 - SHS with TV | E6: Tier 3 - Large SHS + DC fridge | F6: Tier 4 - Solar inverter + lithium (~1.2 kWp / 5 kWh) | G6: Tier 5 - Solar inverter + lithium (~3 kWp / 10 kWh) | H6: Illustrative placeholder - replace with company data.
A7: MTF capacity tier (indicative) | B7: tier | C7: 1 | D7: 2 | E7: 3 | F7: 4 | G7: 5 | H7: Capacity minimums: T1 ≥3 W and ≥12 Wh/day; T2 ≥50 W and ≥200 Wh/day; T3 ≥200 W and ≥1.0 kWh/day; T4 ≥800 W and ≥3.4 kWh/day; T5 ≥2 kW and ≥8.2 kWh/day (ESMAP MTF - verify).
A8: PV array size | B8: Wp | C8: 10 | D8: 80 | E8: 300 | F8: 1200 | G8: 3000 | H8: Illustrative placeholder - replace with company data.
A9: Battery capacity | B9: Wh | C9: 40 | D9: 300 | E9: 1500 | F9: 5000 | G9: 10000 | H9: Illustrative placeholder - replace with company data.
A10: Typical loads / appliances | B10: text | C10: 1-3 lamps, phone charging, radio | D10: 4-6 lamps, radio, phone, 24-32" DC TV | E10: Lighting, TV, DC fridge, fan | F10: AC loads: TV, fridge, fans, small tools | G10: Full household AC loads, freezer, productive-use equipment | H10: Illustrative placeholder - replace with company data.
A11: Target customer segment | B11: text | C11: Rural, low income, first-time PAYGo | D11: Rural / peri-urban households | E11: Peri-urban households, kiosks | F11: Urban households & SMEs with weak grid | G11: Upper-income households, SMEs, productive use | H11: Illustrative placeholder - replace with company data.
A12: PAYGo price plan
A13: Cash (list) price | B13: LCY | C13: 6500 | D13: 39000 | E13: 117000 | F13: 390000 | G13: 845000 | H13: Price if paid upfront. Basis of hardware revenue.
A14: Down payment (deposit) | B14: LCY | C14: 1000 | D14: 4000 | E14: 17550 | F14: 78000 | G14: 211250 | H14: Illustrative placeholder - replace with company data.
A15: PAYGo daily rate | B15: LCY / day | C15: 25 | D15: 77 | E15: 173 | F15: 445 | G15: 694 | H15: Illustrative placeholder - replace with company data.
A16: PAYGo tenor | B16: months | C16: 12 | D16: 24 | E16: 30 | F16: 36 | G16: 48 | H16: Maximum 60 months (horizon of the curves).
A17: Cost to serve & acquisition
A18: Hardware FOB cost | B18: USD / unit | C18: 25 | D18: 150 | E18: 450 | F18: 1400 | G18: 3200 | H18: Illustrative placeholder - replace with company data.
A19: Installation & last-mile logistics | B19: LCY / unit | C19: 0 | D19: 500 | E19: 2500 | F19: 15000 | G19: 30000 | H19: Indexed to local inflation.
A20: Agent / installer commission per sale | B20: LCY / unit | C20: 500 | D20: 2000 | E20: 5000 | F20: 12000 | G20: 20000 | H20: Indexed to local inflation.
A21: Marketing & other acquisition cost per sale | B21: LCY / unit | C21: 300 | D21: 1000 | E21: 2500 | F21: 6000 | G21: 10000 | H21: Indexed to local inflation.
A22: Warranty & after-sales provision | B22: % of landed HW cost | C22: 0.03 | D22: 0.05 | E22: 0.05 | F22: 0.06 | G22: 0.06 | H22: Illustrative placeholder - replace with company data.
A23: Sales mix | B23: % of units | C23: 0.3 | D23: 0.35 | E23: 0.2 | F23: 0.1 | G23: 0.05 | H23: Must sum to 100% (see Checks).
A24: Credit risk & recovery
A25: Base monthly default hazard | B25: % of paying accounts / month | C25: 0.035 | D25: 0.026 | E25: 0.019 | F25: 0.013 | G25: 0.01 | H25: Share of still-paying accounts that stop paying each month. Calibrate to the company's own cohort curves.
A26: Base collection rate on paying accounts | B26: % of instalment | C26: 0.88 | D26: 0.88 | E26: 0.9 | F26: 0.92 | G26: 0.93 | H26: Captures partial / late payment by accounts that keep paying.
A27: Repossession rate of defaulted units | B27: % of defaults | C27: 0 | D27: 0.2 | E27: 0.4 | F27: 0.6 | G27: 0.7 | H27: Illustrative placeholder - replace with company data.
A28: Net resale value of repossessed unit | B28: % of cash price | C28: 0.2 | D28: 0.25 | E28: 0.35 | F28: 0.45 | G28: 0.5 | H28: Net of retrieval and refurbishment. Recognised as a recovery against credit losses.
A29: Subsidy & funding
A30: RBF per unit sold | B30: USD / unit | C30: 5 | D30: 15 | E30: 25 | F30: 0 | G30: 0 | H30: Set to 0 for tiers outside the programme.
A31: Receivables facility advance rate | B31: % of eligible receivables | C31: 0.5 | D31: 0.7 | E31: 0.7 | F31: 0.75 | G31: 0.75 | H31: Lenders often apply different advance rates by product.
A32: Derived price-plan metrics (do not edit)
A33: Monthly instalment (daily rate x 365/12) | B33: LCY / month | C33: =Products!$C$15*365/12 | D33: =Products!$D$15*365/12 | E33: =Products!$E$15*365/12 | F33: =Products!$F$15*365/12 | G33: =Products!$G$15*365/12
A34: Total PAYGo contract value | B34: LCY | C34: =Products!$C$14+Products!$C$33*Products!$C$16 | D34: =Products!$D$14+Products!$D$33*Products!$D$16 | E34: =Products!$E$14+Products!$E$33*Products!$E$16 | F34: =Products!$F$14+Products!$F$33*Products!$F$16 | G34: =Products!$G$14+Products!$G$33*Products!$G$16
A35: PAYGo price premium over cash price | B35: LCY | C35: =Products!$C$34-Products!$C$13 | D35: =Products!$D$34-Products!$D$13 | E35: =Products!$E$34-Products!$E$13 | F35: =Products!$F$34-Products!$F$13 | G35: =Products!$G$34-Products!$G$13
A36: PAYGo premium as % of cash price | B36: % | C36: =IF(Products!$C$13=0,0,Products!$C$35/Products!$C$13) | D36: =IF(Products!$D$13=0,0,Products!$D$35/Products!$D$13) | E36: =IF(Products!$E$13=0,0,Products!$E$35/Products!$E$13) | F36: =IF(Products!$F$13=0,0,Products!$F$35/Products!$F$13) | G36: =IF(Products!$G$13=0,0,Products!$G$35/Products!$G$13)
A37: Down payment as % of cash price | B37: % | C37: =IF(Products!$C$13=0,0,Products!$C$14/Products!$C$13) | D37: =IF(Products!$D$13=0,0,Products!$D$14/Products!$D$13) | E37: =IF(Products!$E$13=0,0,Products!$E$14/Products!$E$13) | F37: =IF(Products!$F$13=0,0,Products!$F$14/Products!$F$13) | G37: =IF(Products!$G$13=0,0,Products!$G$14/Products!$G$13)
A38: Amount financed at sale (cash price - deposit) | B38: LCY | C38: =Products!$C$13-Products!$C$14 | D38: =Products!$D$13-Products!$D$14 | E38: =Products!$E$13-Products!$E$14 | F38: =Products!$F$13-Products!$F$14 | G38: =Products!$G$13-Products!$G$14
A39: Implied annual financing rate (nominal APR) | B39: % p.a. | C39: =IFERROR(RATE(Products!$C$16,-Products!$C$33,Products!$C$38)*12,0) | D39: =IFERROR(RATE(Products!$D$16,-Products!$D$33,Products!$D$38)*12,0) | E39: =IFERROR(RATE(Products!$E$16,-Products!$E$33,Products!$E$38)*12,0) | F39: =IFERROR(RATE(Products!$F$16,-Products!$F$33,Products!$F$38)*12,0) | G39: =IFERROR(RATE(Products!$G$16,-Products!$G$33,Products!$G$38)*12,0) | H39: Rate equating the financed amount with the instalment stream (consumer-protection disclosure).
A40: Cash price in USD at opening FX | B40: USD | C40: =Products!$C$13/Inputs!$C$10 | D40: =Products!$D$13/Inputs!$C$10 | E40: =Products!$E$13/Inputs!$C$10 | F40: =Products!$F$13/Inputs!$C$10 | G40: =Products!$G$13/Inputs!$C$10
A41: Scenario monthly default hazard | B41: % | C41: =Products!$C$25*Scenarios!$G$6 | D41: =Products!$D$25*Scenarios!$G$6 | E41: =Products!$E$25*Scenarios!$G$6 | F41: =Products!$F$25*Scenarios!$G$6 | G41: =Products!$G$25*Scenarios!$G$6
A42: Scenario collection rate on paying accounts | B42: % | C42: =MIN(1,Products!$C$26*Scenarios!$G$7) | D42: =MIN(1,Products!$D$26*Scenarios!$G$7) | E42: =MIN(1,Products!$E$26*Scenarios!$G$7) | F42: =MIN(1,Products!$F$26*Scenarios!$G$7) | G42: =MIN(1,Products!$G$26*Scenarios!$G$7)
A43: Landed hardware cost at opening FX (scenario) | B43: LCY / unit | C43: =Products!$C$18*(1+Inputs!$C$28)*Inputs!$C$10*Scenarios!$G$9 | D43: =Products!$D$18*(1+Inputs!$C$28)*Inputs!$C$10*Scenarios!$G$9 | E43: =Products!$E$18*(1+Inputs!$C$28)*Inputs!$C$10*Scenarios!$G$9 | F43: =Products!$F$18*(1+Inputs!$C$28)*Inputs!$C$10*Scenarios!$G$9 | G43: =Products!$G$18*(1+Inputs!$C$28)*Inputs!$C$10*Scenarios!$G$9
A44: Customer acquisition cost (commission + marketing) | B44: LCY / unit | C44: =Products!$C$20+Products!$C$21 | D44: =Products!$D$20+Products!$D$21 | E44: =Products!$E$20+Products!$E$21 | F44: =Products!$F$20+Products!$F$21 | G44: =Products!$G$20+Products!$G$21
A45: Hardware gross margin on cash price (month 1) | B45: % | C45: =IF(Products!$C$13=0,0,1-(Products!$C$43+Products!$C$19)/Products!$C$13) | D45: =IF(Products!$D$13=0,0,1-(Products!$D$43+Products!$D$19)/Products!$D$13) | E45: =IF(Products!$E$13=0,0,1-(Products!$E$43+Products!$E$19)/Products!$E$13) | F45: =IF(Products!$F$13=0,0,1-(Products!$F$43+Products!$F$19)/Products!$F$13) | G45: =IF(Products!$G$13=0,0,1-(Products!$G$43+Products!$G$19)/Products!$G$13)

Sheet Scenarios
A1: Scenario levers
A2: Multipliers / overrides on Base inputs. ACTIVE column follows the selector on Inputs.
A5: Lever | B5: Unit | C5: Base | D5: Downside | E5: Severe | G5: ACTIVE
A6: Default hazard multiplier | B6: x | C6: 1 | D6: 1.3 | E6: 1.75 | G6: =CHOOSE(Inputs!$C$5,C6,D6,E6)
A7: Collection-rate multiplier (paying accounts) | B7: x | C7: 1 | D7: 0.97 | E7: 0.92 | G7: =CHOOSE(Inputs!$C$5,C7,D7,E7)
A8: Sales volume multiplier | B8: x | C8: 1 | D8: 0.9 | E8: 0.75 | G8: =CHOOSE(Inputs!$C$5,C8,D8,E8)
A9: Hardware cost multiplier (USD) | B9: x | C9: 1 | D9: 1.05 | E9: 1.1 | G9: =CHOOSE(Inputs!$C$5,C9,D9,E9)
A10: LCY depreciation vs USD | B10: % p.a. | C10: 0.05 | D10: 0.12 | E10: 0.25 | G10: =CHOOSE(Inputs!$C$5,C10,D10,E10)
A12: Scenario name | C12: Base | D12: Downside | E12: Severe | G12: =CHOOSE(Inputs!$C$5,C12,D12,E12)
A14: Downside / Severe are illustrative stress settings. Calibrate to the company's cohort history and sector data.
A15: Context: ESMAP Off-Grid Solar Market Trends Report 2024 reports a sector PAYGo collection rate of about 62% in 2023 (source register S01, to verify).

Sheet Dashboard
A1: Dashboard
A2: Charts read from Annual and KPIs (active scenario).
A4: Active scenario | B4: =Scenarios!$G$12
A5: Master check | B5: =Checks!$C$18
A8: Series order: Revenue, EBITDA | Tier 1..5 | Collection, Write-off | Equity, Debt.

Sheet KPIs
A1: Key performance indicators
A2: PAYGo portfolio KPIs (PERFORM-style where noted), financial and lender KPIs.
E5: Year 1 | F5: Year 2 | G5: Year 3 | H5: Year 4 | I5: Year 5
E6: 1 | F6: 2 | G6: 3 | H6: 4 | I6: 5
A8: Sales & customers
A9: Units sold - Tier 1 - Pico solar kit | E9: =SUMIFS(Ops!$E$9:$BL$9,Timeline!$E$6:$BL$6,E$6) | F9: =SUMIFS(Ops!$E$9:$BL$9,Timeline!$E$6:$BL$6,F$6) | G9: =SUMIFS(Ops!$E$9:$BL$9,Timeline!$E$6:$BL$6,G$6) | H9: =SUMIFS(Ops!$E$9:$BL$9,Timeline!$E$6:$BL$6,H$6) | I9: =SUMIFS(Ops!$E$9:$BL$9,Timeline!$E$6:$BL$6,I$6)
A10: Units sold - Tier 2 - SHS with TV | E10: =SUMIFS(Ops!$E$34:$BL$34,Timeline!$E$6:$BL$6,E$6) | F10: =SUMIFS(Ops!$E$34:$BL$34,Timeline!$E$6:$BL$6,F$6) | G10: =SUMIFS(Ops!$E$34:$BL$34,Timeline!$E$6:$BL$6,G$6) | H10: =SUMIFS(Ops!$E$34:$BL$34,Timeline!$E$6:$BL$6,H$6) | I10: =SUMIFS(Ops!$E$34:$BL$34,Timeline!$E$6:$BL$6,I$6)
A11: Units sold - Tier 3 - Large SHS + DC fridge | E11: =SUMIFS(Ops!$E$59:$BL$59,Timeline!$E$6:$BL$6,E$6) | F11: =SUMIFS(Ops!$E$59:$BL$59,Timeline!$E$6:$BL$6,F$6) | G11: =SUMIFS(Ops!$E$59:$BL$59,Timeline!$E$6:$BL$6,G$6) | H11: =SUMIFS(Ops!$E$59:$BL$59,Timeline!$E$6:$BL$6,H$6) | I11: =SUMIFS(Ops!$E$59:$BL$59,Timeline!$E$6:$BL$6,I$6)
A12: Units sold - Tier 4 - Solar inverter + lithium (~1.2 kWp / 5 kWh) | E12: =SUMIFS(Ops!$E$84:$BL$84,Timeline!$E$6:$BL$6,E$6) | F12: =SUMIFS(Ops!$E$84:$BL$84,Timeline!$E$6:$BL$6,F$6) | G12: =SUMIFS(Ops!$E$84:$BL$84,Timeline!$E$6:$BL$6,G$6) | H12: =SUMIFS(Ops!$E$84:$BL$84,Timeline!$E$6:$BL$6,H$6) | I12: =SUMIFS(Ops!$E$84:$BL$84,Timeline!$E$6:$BL$6,I$6)
A13: Units sold - Tier 5 - Solar inverter + lithium (~3 kWp / 10 kWh) | E13: =SUMIFS(Ops!$E$109:$BL$109,Timeline!$E$6:$BL$6,E$6) | F13: =SUMIFS(Ops!$E$109:$BL$109,Timeline!$E$6:$BL$6,F$6) | G13: =SUMIFS(Ops!$E$109:$BL$109,Timeline!$E$6:$BL$6,G$6) | H13: =SUMIFS(Ops!$E$109:$BL$109,Timeline!$E$6:$BL$6,H$6) | I13: =SUMIFS(Ops!$E$109:$BL$109,Timeline!$E$6:$BL$6,I$6)
A14: Units sold - total | E14: =SUMIFS(Ops!$E$134:$BL$134,Timeline!$E$6:$BL$6,E$6) | F14: =SUMIFS(Ops!$E$134:$BL$134,Timeline!$E$6:$BL$6,F$6) | G14: =SUMIFS(Ops!$E$134:$BL$134,Timeline!$E$6:$BL$6,G$6) | H14: =SUMIFS(Ops!$E$134:$BL$134,Timeline!$E$6:$BL$6,H$6) | I14: =SUMIFS(Ops!$E$134:$BL$134,Timeline!$E$6:$BL$6,I$6)
A15: Average cash price per unit sold (USD, opening FX) | E15: =IFERROR(SUMIFS(Ops!$E$137:$BL$137,Timeline!$E$6:$BL$6,E$6)/SUMIFS(Ops!$E$134:$BL$134,Timeline!$E$6:$BL$6,E$6)/Inputs!$C$10,0) | F15: =IFERROR(SUMIFS(Ops!$E$137:$BL$137,Timeline!$E$6:$BL$6,F$6)/SUMIFS(Ops!$E$134:$BL$134,Timeline!$E$6:$BL$6,F$6)/Inputs!$C$10,0) | G15: =IFERROR(SUMIFS(Ops!$E$137:$BL$137,Timeline!$E$6:$BL$6,G$6)/SUMIFS(Ops!$E$134:$BL$134,Timeline!$E$6:$BL$6,G$6)/Inputs!$C$10,0) | H15: =IFERROR(SUMIFS(Ops!$E$137:$BL$137,Timeline!$E$6:$BL$6,H$6)/SUMIFS(Ops!$E$134:$BL$134,Timeline!$E$6:$BL$6,H$6)/Inputs!$C$10,0) | I15: =IFERROR(SUMIFS(Ops!$E$137:$BL$137,Timeline!$E$6:$BL$6,I$6)/SUMIFS(Ops!$E$134:$BL$134,Timeline!$E$6:$BL$6,I$6)/Inputs!$C$10,0)
A16: Active PAYGo accounts (year end) | E16: =INDEX(Ops!$E$146:$BL$146,1,E$6*12) | F16: =INDEX(Ops!$E$146:$BL$146,1,F$6*12) | G16: =INDEX(Ops!$E$146:$BL$146,1,G$6*12) | H16: =INDEX(Ops!$E$146:$BL$146,1,H$6*12) | I16: =INDEX(Ops!$E$146:$BL$146,1,I$6*12)
A17: Cumulative unlocked accounts (customer ownership) | E17: =INDEX(Ops!$E$158:$BL$158,1,E$6*12) | F17: =INDEX(Ops!$E$158:$BL$158,1,F$6*12) | G17: =INDEX(Ops!$E$158:$BL$158,1,G$6*12) | H17: =INDEX(Ops!$E$158:$BL$158,1,H$6*12) | I17: =INDEX(Ops!$E$158:$BL$158,1,I$6*12)
A18: Portfolio quality
A19: Collection rate (collected / due, excl. down payments) | E19: =IFERROR(SUMIFS(Ops!$E$140:$BL$140,Timeline!$E$6:$BL$6,E$6)/SUMIFS(Ops!$E$139:$BL$139,Timeline!$E$6:$BL$6,E$6),0) | F19: =IFERROR(SUMIFS(Ops!$E$140:$BL$140,Timeline!$E$6:$BL$6,F$6)/SUMIFS(Ops!$E$139:$BL$139,Timeline!$E$6:$BL$6,F$6),0) | G19: =IFERROR(SUMIFS(Ops!$E$140:$BL$140,Timeline!$E$6:$BL$6,G$6)/SUMIFS(Ops!$E$139:$BL$139,Timeline!$E$6:$BL$6,G$6),0) | H19: =IFERROR(SUMIFS(Ops!$E$140:$BL$140,Timeline!$E$6:$BL$6,H$6)/SUMIFS(Ops!$E$139:$BL$139,Timeline!$E$6:$BL$6,H$6),0) | I19: =IFERROR(SUMIFS(Ops!$E$140:$BL$140,Timeline!$E$6:$BL$6,I$6)/SUMIFS(Ops!$E$139:$BL$139,Timeline!$E$6:$BL$6,I$6),0)
A20: Write-off rate (missed / due) | E20: =IFERROR(SUMIFS(Ops!$E$141:$BL$141,Timeline!$E$6:$BL$6,E$6)/SUMIFS(Ops!$E$139:$BL$139,Timeline!$E$6:$BL$6,E$6),0) | F20: =IFERROR(SUMIFS(Ops!$E$141:$BL$141,Timeline!$E$6:$BL$6,F$6)/SUMIFS(Ops!$E$139:$BL$139,Timeline!$E$6:$BL$6,F$6),0) | G20: =IFERROR(SUMIFS(Ops!$E$141:$BL$141,Timeline!$E$6:$BL$6,G$6)/SUMIFS(Ops!$E$139:$BL$139,Timeline!$E$6:$BL$6,G$6),0) | H20: =IFERROR(SUMIFS(Ops!$E$141:$BL$141,Timeline!$E$6:$BL$6,H$6)/SUMIFS(Ops!$E$139:$BL$139,Timeline!$E$6:$BL$6,H$6),0) | I20: =IFERROR(SUMIFS(Ops!$E$141:$BL$141,Timeline!$E$6:$BL$6,I$6)/SUMIFS(Ops!$E$139:$BL$139,Timeline!$E$6:$BL$6,I$6),0)
A21: Receivables at risk / gross receivables (year end) | E21: =IFERROR(INDEX(Ops!$E$148:$BL$148,1,E$6*12)/INDEX(Ops!$E$149:$BL$149,1,E$6*12),0) | F21: =IFERROR(INDEX(Ops!$E$148:$BL$148,1,F$6*12)/INDEX(Ops!$E$149:$BL$149,1,F$6*12),0) | G21: =IFERROR(INDEX(Ops!$E$148:$BL$148,1,G$6*12)/INDEX(Ops!$E$149:$BL$149,1,G$6*12),0) | H21: =IFERROR(INDEX(Ops!$E$148:$BL$148,1,H$6*12)/INDEX(Ops!$E$149:$BL$149,1,H$6*12),0) | I21: =IFERROR(INDEX(Ops!$E$148:$BL$148,1,I$6*12)/INDEX(Ops!$E$149:$BL$149,1,I$6*12),0)
A22: Loss allowance coverage (allowance / gross receivables) | E22: =IFERROR(-INDEX(FS!$E$33:$BL$33,1,E$6*12)/INDEX(FS!$E$32:$BL$32,1,E$6*12),0) | F22: =IFERROR(-INDEX(FS!$E$33:$BL$33,1,F$6*12)/INDEX(FS!$E$32:$BL$32,1,F$6*12),0) | G22: =IFERROR(-INDEX(FS!$E$33:$BL$33,1,G$6*12)/INDEX(FS!$E$32:$BL$32,1,G$6*12),0) | H22: =IFERROR(-INDEX(FS!$E$33:$BL$33,1,H$6*12)/INDEX(FS!$E$32:$BL$32,1,H$6*12),0) | I22: =IFERROR(-INDEX(FS!$E$33:$BL$33,1,I$6*12)/INDEX(FS!$E$32:$BL$32,1,I$6*12),0)
A23: Recoveries / write-offs | E23: =IFERROR(SUMIFS(Ops!$E$144:$BL$144,Timeline!$E$6:$BL$6,E$6)/SUMIFS(Ops!$E$141:$BL$141,Timeline!$E$6:$BL$6,E$6),0) | F23: =IFERROR(SUMIFS(Ops!$E$144:$BL$144,Timeline!$E$6:$BL$6,F$6)/SUMIFS(Ops!$E$141:$BL$141,Timeline!$E$6:$BL$6,F$6),0) | G23: =IFERROR(SUMIFS(Ops!$E$144:$BL$144,Timeline!$E$6:$BL$6,G$6)/SUMIFS(Ops!$E$141:$BL$141,Timeline!$E$6:$BL$6,G$6),0) | H23: =IFERROR(SUMIFS(Ops!$E$144:$BL$144,Timeline!$E$6:$BL$6,H$6)/SUMIFS(Ops!$E$141:$BL$141,Timeline!$E$6:$BL$6,H$6),0) | I23: =IFERROR(SUMIFS(Ops!$E$144:$BL$144,Timeline!$E$6:$BL$6,I$6)/SUMIFS(Ops!$E$141:$BL$141,Timeline!$E$6:$BL$6,I$6),0)
A24: Revenue mix
A25: Revenue share - Tier 1 - Pico solar kit | E25: =IFERROR((SUMIFS(Ops!$E$12:$BL$12,Timeline!$E$6:$BL$6,E$6)+SUMIFS(Ops!$E$17:$BL$17,Timeline!$E$6:$BL$6,E$6))/SUMIFS(FS!$E$11:$BL$11,Timeline!$E$6:$BL$6,E$6),0) | F25: =IFERROR((SUMIFS(Ops!$E$12:$BL$12,Timeline!$E$6:$BL$6,F$6)+SUMIFS(Ops!$E$17:$BL$17,Timeline!$E$6:$BL$6,F$6))/SUMIFS(FS!$E$11:$BL$11,Timeline!$E$6:$BL$6,F$6),0) | G25: =IFERROR((SUMIFS(Ops!$E$12:$BL$12,Timeline!$E$6:$BL$6,G$6)+SUMIFS(Ops!$E$17:$BL$17,Timeline!$E$6:$BL$6,G$6))/SUMIFS(FS!$E$11:$BL$11,Timeline!$E$6:$BL$6,G$6),0) | H25: =IFERROR((SUMIFS(Ops!$E$12:$BL$12,Timeline!$E$6:$BL$6,H$6)+SUMIFS(Ops!$E$17:$BL$17,Timeline!$E$6:$BL$6,H$6))/SUMIFS(FS!$E$11:$BL$11,Timeline!$E$6:$BL$6,H$6),0) | I25: =IFERROR((SUMIFS(Ops!$E$12:$BL$12,Timeline!$E$6:$BL$6,I$6)+SUMIFS(Ops!$E$17:$BL$17,Timeline!$E$6:$BL$6,I$6))/SUMIFS(FS!$E$11:$BL$11,Timeline!$E$6:$BL$6,I$6),0)
A26: Revenue share - Tier 2 - SHS with TV | E26: =IFERROR((SUMIFS(Ops!$E$37:$BL$37,Timeline!$E$6:$BL$6,E$6)+SUMIFS(Ops!$E$42:$BL$42,Timeline!$E$6:$BL$6,E$6))/SUMIFS(FS!$E$11:$BL$11,Timeline!$E$6:$BL$6,E$6),0) | F26: =IFERROR((SUMIFS(Ops!$E$37:$BL$37,Timeline!$E$6:$BL$6,F$6)+SUMIFS(Ops!$E$42:$BL$42,Timeline!$E$6:$BL$6,F$6))/SUMIFS(FS!$E$11:$BL$11,Timeline!$E$6:$BL$6,F$6),0) | G26: =IFERROR((SUMIFS(Ops!$E$37:$BL$37,Timeline!$E$6:$BL$6,G$6)+SUMIFS(Ops!$E$42:$BL$42,Timeline!$E$6:$BL$6,G$6))/SUMIFS(FS!$E$11:$BL$11,Timeline!$E$6:$BL$6,G$6),0) | H26: =IFERROR((SUMIFS(Ops!$E$37:$BL$37,Timeline!$E$6:$BL$6,H$6)+SUMIFS(Ops!$E$42:$BL$42,Timeline!$E$6:$BL$6,H$6))/SUMIFS(FS!$E$11:$BL$11,Timeline!$E$6:$BL$6,H$6),0) | I26: =IFERROR((SUMIFS(Ops!$E$37:$BL$37,Timeline!$E$6:$BL$6,I$6)+SUMIFS(Ops!$E$42:$BL$42,Timeline!$E$6:$BL$6,I$6))/SUMIFS(FS!$E$11:$BL$11,Timeline!$E$6:$BL$6,I$6),0)
A27: Revenue share - Tier 3 - Large SHS + DC fridge | E27: =IFERROR((SUMIFS(Ops!$E$62:$BL$62,Timeline!$E$6:$BL$6,E$6)+SUMIFS(Ops!$E$67:$BL$67,Timeline!$E$6:$BL$6,E$6))/SUMIFS(FS!$E$11:$BL$11,Timeline!$E$6:$BL$6,E$6),0) | F27: =IFERROR((SUMIFS(Ops!$E$62:$BL$62,Timeline!$E$6:$BL$6,F$6)+SUMIFS(Ops!$E$67:$BL$67,Timeline!$E$6:$BL$6,F$6))/SUMIFS(FS!$E$11:$BL$11,Timeline!$E$6:$BL$6,F$6),0) | G27: =IFERROR((SUMIFS(Ops!$E$62:$BL$62,Timeline!$E$6:$BL$6,G$6)+SUMIFS(Ops!$E$67:$BL$67,Timeline!$E$6:$BL$6,G$6))/SUMIFS(FS!$E$11:$BL$11,Timeline!$E$6:$BL$6,G$6),0) | H27: =IFERROR((SUMIFS(Ops!$E$62:$BL$62,Timeline!$E$6:$BL$6,H$6)+SUMIFS(Ops!$E$67:$BL$67,Timeline!$E$6:$BL$6,H$6))/SUMIFS(FS!$E$11:$BL$11,Timeline!$E$6:$BL$6,H$6),0) | I27: =IFERROR((SUMIFS(Ops!$E$62:$BL$62,Timeline!$E$6:$BL$6,I$6)+SUMIFS(Ops!$E$67:$BL$67,Timeline!$E$6:$BL$6,I$6))/SUMIFS(FS!$E$11:$BL$11,Timeline!$E$6:$BL$6,I$6),0)
A28: Revenue share - Tier 4 - Solar inverter + lithium (~1.2 kWp / 5 kWh) | E28: =IFERROR((SUMIFS(Ops!$E$87:$BL$87,Timeline!$E$6:$BL$6,E$6)+SUMIFS(Ops!$E$92:$BL$92,Timeline!$E$6:$BL$6,E$6))/SUMIFS(FS!$E$11:$BL$11,Timeline!$E$6:$BL$6,E$6),0) | F28: =IFERROR((SUMIFS(Ops!$E$87:$BL$87,Timeline!$E$6:$BL$6,F$6)+SUMIFS(Ops!$E$92:$BL$92,Timeline!$E$6:$BL$6,F$6))/SUMIFS(FS!$E$11:$BL$11,Timeline!$E$6:$BL$6,F$6),0) | G28: =IFERROR((SUMIFS(Ops!$E$87:$BL$87,Timeline!$E$6:$BL$6,G$6)+SUMIFS(Ops!$E$92:$BL$92,Timeline!$E$6:$BL$6,G$6))/SUMIFS(FS!$E$11:$BL$11,Timeline!$E$6:$BL$6,G$6),0) | H28: =IFERROR((SUMIFS(Ops!$E$87:$BL$87,Timeline!$E$6:$BL$6,H$6)+SUMIFS(Ops!$E$92:$BL$92,Timeline!$E$6:$BL$6,H$6))/SUMIFS(FS!$E$11:$BL$11,Timeline!$E$6:$BL$6,H$6),0) | I28: =IFERROR((SUMIFS(Ops!$E$87:$BL$87,Timeline!$E$6:$BL$6,I$6)+SUMIFS(Ops!$E$92:$BL$92,Timeline!$E$6:$BL$6,I$6))/SUMIFS(FS!$E$11:$BL$11,Timeline!$E$6:$BL$6,I$6),0)
A29: Revenue share - Tier 5 - Solar inverter + lithium (~3 kWp / 10 kWh) | E29: =IFERROR((SUMIFS(Ops!$E$112:$BL$112,Timeline!$E$6:$BL$6,E$6)+SUMIFS(Ops!$E$117:$BL$117,Timeline!$E$6:$BL$6,E$6))/SUMIFS(FS!$E$11:$BL$11,Timeline!$E$6:$BL$6,E$6),0) | F29: =IFERROR((SUMIFS(Ops!$E$112:$BL$112,Timeline!$E$6:$BL$6,F$6)+SUMIFS(Ops!$E$117:$BL$117,Timeline!$E$6:$BL$6,F$6))/SUMIFS(FS!$E$11:$BL$11,Timeline!$E$6:$BL$6,F$6),0) | G29: =IFERROR((SUMIFS(Ops!$E$112:$BL$112,Timeline!$E$6:$BL$6,G$6)+SUMIFS(Ops!$E$117:$BL$117,Timeline!$E$6:$BL$6,G$6))/SUMIFS(FS!$E$11:$BL$11,Timeline!$E$6:$BL$6,G$6),0) | H29: =IFERROR((SUMIFS(Ops!$E$112:$BL$112,Timeline!$E$6:$BL$6,H$6)+SUMIFS(Ops!$E$117:$BL$117,Timeline!$E$6:$BL$6,H$6))/SUMIFS(FS!$E$11:$BL$11,Timeline!$E$6:$BL$6,H$6),0) | I29: =IFERROR((SUMIFS(Ops!$E$112:$BL$112,Timeline!$E$6:$BL$6,I$6)+SUMIFS(Ops!$E$117:$BL$117,Timeline!$E$6:$BL$6,I$6))/SUMIFS(FS!$E$11:$BL$11,Timeline!$E$6:$BL$6,I$6),0)
A30: Profitability
A31: Revenue (LCY) | E31: =SUMIFS(FS!$E$11:$BL$11,Timeline!$E$6:$BL$6,E$6) | F31: =SUMIFS(FS!$E$11:$BL$11,Timeline!$E$6:$BL$6,F$6) | G31: =SUMIFS(FS!$E$11:$BL$11,Timeline!$E$6:$BL$6,G$6) | H31: =SUMIFS(FS!$E$11:$BL$11,Timeline!$E$6:$BL$6,H$6) | I31: =SUMIFS(FS!$E$11:$BL$11,Timeline!$E$6:$BL$6,I$6)
A32: Revenue (USD, average FX) | E32: =IFERROR(SUMIFS(FS!$E$11:$BL$11,Timeline!$E$6:$BL$6,E$6)/AVERAGEIFS(Timeline!$E$8:$BL$8,Timeline!$E$6:$BL$6,E$6),0) | F32: =IFERROR(SUMIFS(FS!$E$11:$BL$11,Timeline!$E$6:$BL$6,F$6)/AVERAGEIFS(Timeline!$E$8:$BL$8,Timeline!$E$6:$BL$6,F$6),0) | G32: =IFERROR(SUMIFS(FS!$E$11:$BL$11,Timeline!$E$6:$BL$6,G$6)/AVERAGEIFS(Timeline!$E$8:$BL$8,Timeline!$E$6:$BL$6,G$6),0) | H32: =IFERROR(SUMIFS(FS!$E$11:$BL$11,Timeline!$E$6:$BL$6,H$6)/AVERAGEIFS(Timeline!$E$8:$BL$8,Timeline!$E$6:$BL$6,H$6),0) | I32: =IFERROR(SUMIFS(FS!$E$11:$BL$11,Timeline!$E$6:$BL$6,I$6)/AVERAGEIFS(Timeline!$E$8:$BL$8,Timeline!$E$6:$BL$6,I$6),0)
A33: Gross margin | E33: =IFERROR(SUMIFS(FS!$E$13:$BL$13,Timeline!$E$6:$BL$6,E$6)/SUMIFS(FS!$E$11:$BL$11,Timeline!$E$6:$BL$6,E$6),0) | F33: =IFERROR(SUMIFS(FS!$E$13:$BL$13,Timeline!$E$6:$BL$6,F$6)/SUMIFS(FS!$E$11:$BL$11,Timeline!$E$6:$BL$6,F$6),0) | G33: =IFERROR(SUMIFS(FS!$E$13:$BL$13,Timeline!$E$6:$BL$6,G$6)/SUMIFS(FS!$E$11:$BL$11,Timeline!$E$6:$BL$6,G$6),0) | H33: =IFERROR(SUMIFS(FS!$E$13:$BL$13,Timeline!$E$6:$BL$6,H$6)/SUMIFS(FS!$E$11:$BL$11,Timeline!$E$6:$BL$6,H$6),0) | I33: =IFERROR(SUMIFS(FS!$E$13:$BL$13,Timeline!$E$6:$BL$6,I$6)/SUMIFS(FS!$E$11:$BL$11,Timeline!$E$6:$BL$6,I$6),0)
A34: EBITDA (LCY) | E34: =SUMIFS(FS!$E$18:$BL$18,Timeline!$E$6:$BL$6,E$6) | F34: =SUMIFS(FS!$E$18:$BL$18,Timeline!$E$6:$BL$6,F$6) | G34: =SUMIFS(FS!$E$18:$BL$18,Timeline!$E$6:$BL$6,G$6) | H34: =SUMIFS(FS!$E$18:$BL$18,Timeline!$E$6:$BL$6,H$6) | I34: =SUMIFS(FS!$E$18:$BL$18,Timeline!$E$6:$BL$6,I$6)
A35: EBITDA margin | E35: =IFERROR(SUMIFS(FS!$E$18:$BL$18,Timeline!$E$6:$BL$6,E$6)/SUMIFS(FS!$E$11:$BL$11,Timeline!$E$6:$BL$6,E$6),0) | F35: =IFERROR(SUMIFS(FS!$E$18:$BL$18,Timeline!$E$6:$BL$6,F$6)/SUMIFS(FS!$E$11:$BL$11,Timeline!$E$6:$BL$6,F$6),0) | G35: =IFERROR(SUMIFS(FS!$E$18:$BL$18,Timeline!$E$6:$BL$6,G$6)/SUMIFS(FS!$E$11:$BL$11,Timeline!$E$6:$BL$6,G$6),0) | H35: =IFERROR(SUMIFS(FS!$E$18:$BL$18,Timeline!$E$6:$BL$6,H$6)/SUMIFS(FS!$E$11:$BL$11,Timeline!$E$6:$BL$6,H$6),0) | I35: =IFERROR(SUMIFS(FS!$E$18:$BL$18,Timeline!$E$6:$BL$6,I$6)/SUMIFS(FS!$E$11:$BL$11,Timeline!$E$6:$BL$6,I$6),0)
A36: Net credit losses / revenue | E36: =IFERROR(-(SUMIFS(FS!$E$16:$BL$16,Timeline!$E$6:$BL$6,E$6)+SUMIFS(FS!$E$17:$BL$17,Timeline!$E$6:$BL$6,E$6))/SUMIFS(FS!$E$11:$BL$11,Timeline!$E$6:$BL$6,E$6),0) | F36: =IFERROR(-(SUMIFS(FS!$E$16:$BL$16,Timeline!$E$6:$BL$6,F$6)+SUMIFS(FS!$E$17:$BL$17,Timeline!$E$6:$BL$6,F$6))/SUMIFS(FS!$E$11:$BL$11,Timeline!$E$6:$BL$6,F$6),0) | G36: =IFERROR(-(SUMIFS(FS!$E$16:$BL$16,Timeline!$E$6:$BL$6,G$6)+SUMIFS(FS!$E$17:$BL$17,Timeline!$E$6:$BL$6,G$6))/SUMIFS(FS!$E$11:$BL$11,Timeline!$E$6:$BL$6,G$6),0) | H36: =IFERROR(-(SUMIFS(FS!$E$16:$BL$16,Timeline!$E$6:$BL$6,H$6)+SUMIFS(FS!$E$17:$BL$17,Timeline!$E$6:$BL$6,H$6))/SUMIFS(FS!$E$11:$BL$11,Timeline!$E$6:$BL$6,H$6),0) | I36: =IFERROR(-(SUMIFS(FS!$E$16:$BL$16,Timeline!$E$6:$BL$6,I$6)+SUMIFS(FS!$E$17:$BL$17,Timeline!$E$6:$BL$6,I$6))/SUMIFS(FS!$E$11:$BL$11,Timeline!$E$6:$BL$6,I$6),0)
A37: RBF dependency (RBF income / revenue) | E37: =IFERROR(SUMIFS(FS!$E$14:$BL$14,Timeline!$E$6:$BL$6,E$6)/SUMIFS(FS!$E$11:$BL$11,Timeline!$E$6:$BL$6,E$6),0) | F37: =IFERROR(SUMIFS(FS!$E$14:$BL$14,Timeline!$E$6:$BL$6,F$6)/SUMIFS(FS!$E$11:$BL$11,Timeline!$E$6:$BL$6,F$6),0) | G37: =IFERROR(SUMIFS(FS!$E$14:$BL$14,Timeline!$E$6:$BL$6,G$6)/SUMIFS(FS!$E$11:$BL$11,Timeline!$E$6:$BL$6,G$6),0) | H37: =IFERROR(SUMIFS(FS!$E$14:$BL$14,Timeline!$E$6:$BL$6,H$6)/SUMIFS(FS!$E$11:$BL$11,Timeline!$E$6:$BL$6,H$6),0) | I37: =IFERROR(SUMIFS(FS!$E$14:$BL$14,Timeline!$E$6:$BL$6,I$6)/SUMIFS(FS!$E$11:$BL$11,Timeline!$E$6:$BL$6,I$6),0)
A38: Net income (LCY) | E38: =SUMIFS(FS!$E$28:$BL$28,Timeline!$E$6:$BL$6,E$6) | F38: =SUMIFS(FS!$E$28:$BL$28,Timeline!$E$6:$BL$6,F$6) | G38: =SUMIFS(FS!$E$28:$BL$28,Timeline!$E$6:$BL$6,G$6) | H38: =SUMIFS(FS!$E$28:$BL$28,Timeline!$E$6:$BL$6,H$6) | I38: =SUMIFS(FS!$E$28:$BL$28,Timeline!$E$6:$BL$6,I$6)
A39: Funding, leverage & coverage
A40: Closing cash (LCY) | E40: =INDEX(FS!$E$63:$BL$63,1,E$6*12) | F40: =INDEX(FS!$E$63:$BL$63,1,F$6*12) | G40: =INDEX(FS!$E$63:$BL$63,1,G$6*12) | H40: =INDEX(FS!$E$63:$BL$63,1,H$6*12) | I40: =INDEX(FS!$E$63:$BL$63,1,I$6*12)
A41: Cumulative equity invested (LCY) | E41: =INDEX(Financing!$E$11:$BL$11,1,E$6*12) | F41: =INDEX(Financing!$E$11:$BL$11,1,F$6*12) | G41: =INDEX(Financing!$E$11:$BL$11,1,G$6*12) | H41: =INDEX(Financing!$E$11:$BL$11,1,H$6*12) | I41: =INDEX(Financing!$E$11:$BL$11,1,I$6*12)
A42: Equity top-ups in year (funding gap, LCY) | E42: =SUMIFS(FS!$E$62:$BL$62,Timeline!$E$6:$BL$6,E$6) | F42: =SUMIFS(FS!$E$62:$BL$62,Timeline!$E$6:$BL$6,F$6) | G42: =SUMIFS(FS!$E$62:$BL$62,Timeline!$E$6:$BL$6,G$6) | H42: =SUMIFS(FS!$E$62:$BL$62,Timeline!$E$6:$BL$6,H$6) | I42: =SUMIFS(FS!$E$62:$BL$62,Timeline!$E$6:$BL$6,I$6)
A43: Total debt (year end, LCY) | E43: =INDEX(FS!$E$39:$BL$39,1,E$6*12)+INDEX(FS!$E$40:$BL$40,1,E$6*12) | F43: =INDEX(FS!$E$39:$BL$39,1,F$6*12)+INDEX(FS!$E$40:$BL$40,1,F$6*12) | G43: =INDEX(FS!$E$39:$BL$39,1,G$6*12)+INDEX(FS!$E$40:$BL$40,1,G$6*12) | H43: =INDEX(FS!$E$39:$BL$39,1,H$6*12)+INDEX(FS!$E$40:$BL$40,1,H$6*12) | I43: =INDEX(FS!$E$39:$BL$39,1,I$6*12)+INDEX(FS!$E$40:$BL$40,1,I$6*12)
A44: Debt / book equity | E44: =IFERROR((INDEX(FS!$E$39:$BL$39,1,E$6*12)+INDEX(FS!$E$40:$BL$40,1,E$6*12))/INDEX(FS!$E$44:$BL$44,1,E$6*12),0) | F44: =IFERROR((INDEX(FS!$E$39:$BL$39,1,F$6*12)+INDEX(FS!$E$40:$BL$40,1,F$6*12))/INDEX(FS!$E$44:$BL$44,1,F$6*12),0) | G44: =IFERROR((INDEX(FS!$E$39:$BL$39,1,G$6*12)+INDEX(FS!$E$40:$BL$40,1,G$6*12))/INDEX(FS!$E$44:$BL$44,1,G$6*12),0) | H44: =IFERROR((INDEX(FS!$E$39:$BL$39,1,H$6*12)+INDEX(FS!$E$40:$BL$40,1,H$6*12))/INDEX(FS!$E$44:$BL$44,1,H$6*12),0) | I44: =IFERROR((INDEX(FS!$E$39:$BL$39,1,I$6*12)+INDEX(FS!$E$40:$BL$40,1,I$6*12))/INDEX(FS!$E$44:$BL$44,1,I$6*12),0)
A45: Debt service (interest + term-loan principal, LCY) | E45: =SUMIFS(Financing!$E$16:$BL$16,Timeline!$E$6:$BL$6,E$6)+SUMIFS(Financing!$E$18:$BL$18,Timeline!$E$6:$BL$6,E$6)+SUMIFS(Financing!$E$25:$BL$25,Timeline!$E$6:$BL$6,E$6) | F45: =SUMIFS(Financing!$E$16:$BL$16,Timeline!$E$6:$BL$6,F$6)+SUMIFS(Financing!$E$18:$BL$18,Timeline!$E$6:$BL$6,F$6)+SUMIFS(Financing!$E$25:$BL$25,Timeline!$E$6:$BL$6,F$6) | G45: =SUMIFS(Financing!$E$16:$BL$16,Timeline!$E$6:$BL$6,G$6)+SUMIFS(Financing!$E$18:$BL$18,Timeline!$E$6:$BL$6,G$6)+SUMIFS(Financing!$E$25:$BL$25,Timeline!$E$6:$BL$6,G$6) | H45: =SUMIFS(Financing!$E$16:$BL$16,Timeline!$E$6:$BL$6,H$6)+SUMIFS(Financing!$E$18:$BL$18,Timeline!$E$6:$BL$6,H$6)+SUMIFS(Financing!$E$25:$BL$25,Timeline!$E$6:$BL$6,H$6) | I45: =SUMIFS(Financing!$E$16:$BL$16,Timeline!$E$6:$BL$6,I$6)+SUMIFS(Financing!$E$18:$BL$18,Timeline!$E$6:$BL$6,I$6)+SUMIFS(Financing!$E$25:$BL$25,Timeline!$E$6:$BL$6,I$6)
A46: DSCR ((CFO + interest) / debt service) | E46: =IFERROR((SUMIFS(FS!$E$55:$BL$55,Timeline!$E$6:$BL$6,E$6)-SUMIFS(FS!$E$21:$BL$21,Timeline!$E$6:$BL$6,E$6)-SUMIFS(FS!$E$22:$BL$22,Timeline!$E$6:$BL$6,E$6))/E45,0) | F46: =IFERROR((SUMIFS(FS!$E$55:$BL$55,Timeline!$E$6:$BL$6,F$6)-SUMIFS(FS!$E$21:$BL$21,Timeline!$E$6:$BL$6,F$6)-SUMIFS(FS!$E$22:$BL$22,Timeline!$E$6:$BL$6,F$6))/F45,0) | G46: =IFERROR((SUMIFS(FS!$E$55:$BL$55,Timeline!$E$6:$BL$6,G$6)-SUMIFS(FS!$E$21:$BL$21,Timeline!$E$6:$BL$6,G$6)-SUMIFS(FS!$E$22:$BL$22,Timeline!$E$6:$BL$6,G$6))/G45,0) | H46: =IFERROR((SUMIFS(FS!$E$55:$BL$55,Timeline!$E$6:$BL$6,H$6)-SUMIFS(FS!$E$21:$BL$21,Timeline!$E$6:$BL$6,H$6)-SUMIFS(FS!$E$22:$BL$22,Timeline!$E$6:$BL$6,H$6))/H45,0) | I46: =IFERROR((SUMIFS(FS!$E$55:$BL$55,Timeline!$E$6:$BL$6,I$6)-SUMIFS(FS!$E$21:$BL$21,Timeline!$E$6:$BL$6,I$6)-SUMIFS(FS!$E$22:$BL$22,Timeline!$E$6:$BL$6,I$6))/I45,0)
A47: Breach: DSCR below minimum (years with debt service) | E47: =IF(AND(E45>0,E46<Inputs!$C$57),1,0) | F47: =IF(AND(F45>0,F46<Inputs!$C$57),1,0) | G47: =IF(AND(G45>0,G46<Inputs!$C$57),1,0) | H47: =IF(AND(H45>0,H46<Inputs!$C$57),1,0) | I47: =IF(AND(I45>0,I46<Inputs!$C$57),1,0)
A48: Months with any monthly covenant breach | E48: =SUMIFS(Covenants!$E$17:$BL$17,Timeline!$E$6:$BL$6,E$6) | F48: =SUMIFS(Covenants!$E$17:$BL$17,Timeline!$E$6:$BL$6,F$6) | G48: =SUMIFS(Covenants!$E$17:$BL$17,Timeline!$E$6:$BL$6,G$6) | H48: =SUMIFS(Covenants!$E$17:$BL$17,Timeline!$E$6:$BL$6,H$6) | I48: =SUMIFS(Covenants!$E$17:$BL$17,Timeline!$E$6:$BL$6,I$6)
A49: FX rate (year end, LCY / USD) | E49: =INDEX(Timeline!$E$8:$BL$8,1,E$6*12) | F49: =INDEX(Timeline!$E$8:$BL$8,1,F$6*12) | G49: =INDEX(Timeline!$E$8:$BL$8,1,G$6*12) | H49: =INDEX(Timeline!$E$8:$BL$8,1,H$6*12) | I49: =INDEX(Timeline!$E$8:$BL$8,1,I$6*12)
A51: Headline metrics
A52: Peak cumulative equity requirement (LCY) | C52: =MAX(Financing!$E$11:$BL$11)
A53: Peak cumulative equity requirement (USD, opening FX) | C53: =C52/Inputs!$C$10
A54: Peak total debt (LCY) | C54: =MAX(Covenants!$E$12:$BL$12)
A55: Total RBF received (USD, opening FX) | C55: =SUM(Ops!$E$145:$BL$145)/Inputs!$C$10
A56: First month with positive EBITDA | C56: =IFERROR(MATCH(1,FS!$E$66:$BL$66,0),"Not reached")
A57: First month with positive operating cash flow | C57: =IFERROR(MATCH(1,FS!$E$67:$BL$67,0),"Not reached")
A58: Lowest trailing-3-month collection rate (from month 3) | C58: =MIN(Covenants!G8:BL8)
A59: Highest receivables-at-risk ratio | C59: =MAX(Ops!$E$161:$BL$161)
A60: Total months with a covenant breach | C60: =SUM(Covenants!$E$17:$BL$17)
A61: Years with DSCR below minimum | C61: =SUM(E47:I47)
A63: Receivables at risk approximates PAYGo PERFORM 'Receivables at Risk'. Covenant definitions are illustrative; use those in the actual facility agreement.

Sheet Valuation
A1: Valuation & investor returns
A2: DCF of unlevered free cash flow (LCY) and equity investor returns (USD).
D5: Year 0 | E5: Year 1 | F5: Year 2 | G5: Year 3 | H5: Year 4 | I5: Year 5
D6: 0 | E6: 1 | F6: 2 | G6: 3 | H6: 4 | I6: 5
A8: Unlevered free cash flow (LCY)
A9: EBITDA | E9: =SUMIFS(FS!$E$18:$BL$18,Timeline!$E$6:$BL$6,E$6) | F9: =SUMIFS(FS!$E$18:$BL$18,Timeline!$E$6:$BL$6,F$6) | G9: =SUMIFS(FS!$E$18:$BL$18,Timeline!$E$6:$BL$6,G$6) | H9: =SUMIFS(FS!$E$18:$BL$18,Timeline!$E$6:$BL$6,H$6) | I9: =SUMIFS(FS!$E$18:$BL$18,Timeline!$E$6:$BL$6,I$6)
A10: Less: income tax paid (levered tax - simplification) | E10: =SUMIFS(FS!$E$27:$BL$27,Timeline!$E$6:$BL$6,E$6) | F10: =SUMIFS(FS!$E$27:$BL$27,Timeline!$E$6:$BL$6,F$6) | G10: =SUMIFS(FS!$E$27:$BL$27,Timeline!$E$6:$BL$6,G$6) | H10: =SUMIFS(FS!$E$27:$BL$27,Timeline!$E$6:$BL$6,H$6) | I10: =SUMIFS(FS!$E$27:$BL$27,Timeline!$E$6:$BL$6,I$6)
A11: Less: capex | E11: =-SUMIFS(Costs!$E$25:$BL$25,Timeline!$E$6:$BL$6,E$6) | F11: =-SUMIFS(Costs!$E$25:$BL$25,Timeline!$E$6:$BL$6,F$6) | G11: =-SUMIFS(Costs!$E$25:$BL$25,Timeline!$E$6:$BL$6,G$6) | H11: =-SUMIFS(Costs!$E$25:$BL$25,Timeline!$E$6:$BL$6,H$6) | I11: =-SUMIFS(Costs!$E$25:$BL$25,Timeline!$E$6:$BL$6,I$6)
A12: Net working capital (net receivables + inventory - payables), year end | D12: 0 | E12: =INDEX(FS!$E$34:$BL$34,1,E$6*12)+INDEX(FS!$E$35:$BL$35,1,E$6*12)-INDEX(FS!$E$38:$BL$38,1,E$6*12) | F12: =INDEX(FS!$E$34:$BL$34,1,F$6*12)+INDEX(FS!$E$35:$BL$35,1,F$6*12)-INDEX(FS!$E$38:$BL$38,1,F$6*12) | G12: =INDEX(FS!$E$34:$BL$34,1,G$6*12)+INDEX(FS!$E$35:$BL$35,1,G$6*12)-INDEX(FS!$E$38:$BL$38,1,G$6*12) | H12: =INDEX(FS!$E$34:$BL$34,1,H$6*12)+INDEX(FS!$E$35:$BL$35,1,H$6*12)-INDEX(FS!$E$38:$BL$38,1,H$6*12) | I12: =INDEX(FS!$E$34:$BL$34,1,I$6*12)+INDEX(FS!$E$35:$BL$35,1,I$6*12)-INDEX(FS!$E$38:$BL$38,1,I$6*12)
A13: Less: increase in net working capital | E13: =-(E12-D12) | F13: =-(F12-E12) | G13: =-(G12-F12) | H13: =-(H12-G12) | I13: =-(I12-H12)
A14: Unlevered free cash flow (FCFF) | E14: =E9+E10+E11+E13 | F14: =F9+F10+F11+F13 | G14: =G9+G10+G11+G13 | H14: =H9+H10+H11+H13 | I14: =I9+I10+I11+I13
A15: Discount factor (mid-year) | E15: =1/(1+Inputs!$C$61)^(E$6-0.5) | F15: =1/(1+Inputs!$C$61)^(F$6-0.5) | G15: =1/(1+Inputs!$C$61)^(G$6-0.5) | H15: =1/(1+Inputs!$C$61)^(H$6-0.5) | I15: =1/(1+Inputs!$C$61)^(I$6-0.5)
A16: Present value of FCFF | E16: =E14*E15 | F16: =F14*F15 | G16: =G14*G15 | H16: =H14*H15 | I16: =I14*I15
A17: Equity investor (USD)
A18: Equity top-ups in year (LCY) | E18: =SUMIFS(FS!$E$62:$BL$62,Timeline!$E$6:$BL$6,E$6) | F18: =SUMIFS(FS!$E$62:$BL$62,Timeline!$E$6:$BL$6,F$6) | G18: =SUMIFS(FS!$E$62:$BL$62,Timeline!$E$6:$BL$6,G$6) | H18: =SUMIFS(FS!$E$62:$BL$62,Timeline!$E$6:$BL$6,H$6) | I18: =SUMIFS(FS!$E$62:$BL$62,Timeline!$E$6:$BL$6,I$6)
A19: Average FX in year (LCY / USD) | E19: =AVERAGEIFS(Timeline!$E$8:$BL$8,Timeline!$E$6:$BL$6,E$6) | F19: =AVERAGEIFS(Timeline!$E$8:$BL$8,Timeline!$E$6:$BL$6,F$6) | G19: =AVERAGEIFS(Timeline!$E$8:$BL$8,Timeline!$E$6:$BL$6,G$6) | H19: =AVERAGEIFS(Timeline!$E$8:$BL$8,Timeline!$E$6:$BL$6,H$6) | I19: =AVERAGEIFS(Timeline!$E$8:$BL$8,Timeline!$E$6:$BL$6,I$6)
A20: Investor cash flow (USD) | D20: =-Inputs!$C$63 | E20: =-C38*E18/E19 | F20: =-C38*F18/F19 | G20: =-C38*G18/G19 | H20: =-C38*H18/H19 | I20: =-C38*I18/I19+C38*C36
A22: Valuation summary
A23: Sum of PV of FCFF, Years 1-5 (LCY) | C23: =SUM(E16:I16)
A24: Normalised terminal FCFF: (EBITDA - tax - capex)_Y5 x (1+g) - g x NWC_Y5 (LCY) | C24: =(I9+I10+I11)*(1+Inputs!$C$62)-Inputs!$C$62*I12
A25: Terminal value at end of Year 5 (Gordon growth on normalised FCFF, LCY) | C25: =IF(Inputs!$C$61>Inputs!$C$62,C24/(Inputs!$C$61-Inputs!$C$62),0)
A26: PV of terminal value (LCY) | C26: =C25/(1+Inputs!$C$61)^5
A27: DCF enterprise value at model start (LCY) | C27: =C23+C26
A28: DCF enterprise value at model start (USD, opening FX) | C28: =C27/Inputs!$C$10
A29: Terminal value share of EV | C29: =IFERROR(C26/C27,0)
A31: Year 5 EBITDA (LCY) | C31: =I9
A32: Net debt at end of Year 5 (LCY) | C32: =INDEX(FS!$E$39:$BL$39,1,I$6*12)+INDEX(FS!$E$40:$BL$40,1,I$6*12)-INDEX(FS!$E$63:$BL$63,1,I$6*12)
A33: Book equity at end of Year 5 (LCY) | C33: =INDEX(FS!$E$44:$BL$44,1,I$6*12)
A34: Exit equity value, 100% (LCY) | C34: =MAX(0,IF(Inputs!$C$65=1,Inputs!$C$66*C31-C32,Inputs!$C$67*C33))
A35: FX at exit (LCY / USD) | C35: =INDEX(Timeline!$E$8:$BL$8,1,60)
A36: Exit equity value, 100% (USD) | C36: =C34/C35
A38: Investor stake (ticket / post-money) | C38: =IFERROR(Inputs!$C$63/(Inputs!$C$64+Inputs!$C$63),0)
A39: Investor IRR (USD) | C39: =IFERROR(IRR(D20:I20,0.1),"n/a")
A40: Investor MOIC (USD) | C40: =IFERROR(SUMIF(D20:I20,">0")/-SUMIF(D20:I20,"<0"),0)
A42: Investor funds its pro-rata share of any equity top-up and receives no dividends before exit. LCY flows are converted to USD at average FX for the year; exit at year-end FX.
A43: For PAYGo companies, growth of the receivables book is working capital, so FCFF is negative while the book grows. The terminal value therefore uses a normalised FCFF that reinvests only g x NWC (steady-state growth).

Sheet Covenants
A1: Lender covenant tests (monthly)
A2: Flags = 1 when a covenant is breached. Tested only while the relevant debt is outstanding.
A4: Month # | D4: Opening | E4: =Timeline!E4 | F4: =Timeline!F4 | G4: =Timeline!G4 | H4: =Timeline!H4 | I4: =Timeline!I4 | J4: =Timeline!J4 | K4: =Timeline!K4 | L4: =Timeline!L4 | ... BL4: =Timeline!BL4
A5: Period end | E5: =Timeline!E5 | F5: =Timeline!F5 | G5: =Timeline!G5 | H5: =Timeline!H5 | I5: =Timeline!I5 | J5: =Timeline!J5 | K5: =Timeline!K5 | L5: =Timeline!L5 | ... BL5: =Timeline!BL5
A6: Year # | E6: =Timeline!E6 | F6: =Timeline!F6 | G6: =Timeline!G6 | H6: =Timeline!H6 | I6: =Timeline!I6 | J6: =Timeline!J6 | K6: =Timeline!K6 | L6: =Timeline!L6 | ... BL6: =Timeline!BL6
A8: Trailing 3-month collection rate | C8: =MIN(E8:BL8) | E8: =IFERROR(SUM(Ops!E140:E140)/SUM(Ops!E139:E139),0) | F8: =IFERROR(SUM(Ops!E140:F140)/SUM(Ops!E139:F139),0) | G8: =IFERROR(SUM(Ops!E140:G140)/SUM(Ops!E139:G139),0) | H8: =IFERROR(SUM(Ops!F140:H140)/SUM(Ops!F139:H139),0) | I8: =IFERROR(SUM(Ops!G140:I140)/SUM(Ops!G139:I139),0) | J8: =IFERROR(SUM(Ops!H140:J140)/SUM(Ops!H139:J139),0) | K8: =IFERROR(SUM(Ops!I140:K140)/SUM(Ops!I139:K139),0) | L8: =IFERROR(SUM(Ops!J140:L140)/SUM(Ops!J139:L139),0) | M8: =IFERROR(SUM(Ops!K140:M140)/SUM(Ops!K139:M139),0) | N8: =IFERROR(SUM(Ops!L140:N140)/SUM(Ops!L139:N139),0) | ... BL8: =IFERROR(SUM(Ops!BJ140:BL140)/SUM(Ops!BJ139:BL139),0)
A9: Breach: collection rate below minimum | C9: =SUM(E9:BL9) | E9: =IF(AND(Financing!E$23>0,E8<Inputs!$C$54),1,0) | F9: =IF(AND(Financing!F$23>0,F8<Inputs!$C$54),1,0) | G9: =IF(AND(Financing!G$23>0,G8<Inputs!$C$54),1,0) | H9: =IF(AND(Financing!H$23>0,H8<Inputs!$C$54),1,0) | I9: =IF(AND(Financing!I$23>0,I8<Inputs!$C$54),1,0) | J9: =IF(AND(Financing!J$23>0,J8<Inputs!$C$54),1,0) | K9: =IF(AND(Financing!K$23>0,K8<Inputs!$C$54),1,0) | L9: =IF(AND(Financing!L$23>0,L8<Inputs!$C$54),1,0) | ... BL9: =IF(AND(Financing!BL$23>0,BL8<Inputs!$C$54),1,0)
A10: Receivables at risk / gross receivables | C10: =MAX(E10:BL10) | E10: =Ops!E$161 | F10: =Ops!F$161 | G10: =Ops!G$161 | H10: =Ops!H$161 | I10: =Ops!I$161 | J10: =Ops!J$161 | K10: =Ops!K$161 | L10: =Ops!L$161 | ... BL10: =Ops!BL$161
A11: Breach: receivables at risk above maximum | C11: =SUM(E11:BL11) | E11: =IF(AND(Financing!E$23>0,E10>Inputs!$C$55),1,0) | F11: =IF(AND(Financing!F$23>0,F10>Inputs!$C$55),1,0) | G11: =IF(AND(Financing!G$23>0,G10>Inputs!$C$55),1,0) | H11: =IF(AND(Financing!H$23>0,H10>Inputs!$C$55),1,0) | I11: =IF(AND(Financing!I$23>0,I10>Inputs!$C$55),1,0) | J11: =IF(AND(Financing!J$23>0,J10>Inputs!$C$55),1,0) | K11: =IF(AND(Financing!K$23>0,K10>Inputs!$C$55),1,0) | L11: =IF(AND(Financing!L$23>0,L10>Inputs!$C$55),1,0) | ... BL11: =IF(AND(Financing!BL$23>0,BL10>Inputs!$C$55),1,0)
A12: Total financial debt (LCY) | C12: =MAX(E12:BL12) | E12: =FS!E$39+FS!E$40 | F12: =FS!F$39+FS!F$40 | G12: =FS!G$39+FS!G$40 | H12: =FS!H$39+FS!H$40 | I12: =FS!I$39+FS!I$40 | J12: =FS!J$39+FS!J$40 | K12: =FS!K$39+FS!K$40 | L12: =FS!L$39+FS!L$40 | ... BL12: =FS!BL$39+FS!BL$40
A13: Debt / book equity | C13: =MAX(E13:BL13) | E13: =IF(FS!E$44<=0,99,E12/FS!E$44) | F13: =IF(FS!F$44<=0,99,F12/FS!F$44) | G13: =IF(FS!G$44<=0,99,G12/FS!G$44) | H13: =IF(FS!H$44<=0,99,H12/FS!H$44) | I13: =IF(FS!I$44<=0,99,I12/FS!I$44) | J13: =IF(FS!J$44<=0,99,J12/FS!J$44) | K13: =IF(FS!K$44<=0,99,K12/FS!K$44) | L13: =IF(FS!L$44<=0,99,L12/FS!L$44) | ... BL13: =IF(FS!BL$44<=0,99,BL12/FS!BL$44)
A14: Breach: leverage above maximum | C14: =SUM(E14:BL14) | E14: =IF(AND(E12>0,E13>Inputs!$C$56),1,0) | F14: =IF(AND(F12>0,F13>Inputs!$C$56),1,0) | G14: =IF(AND(G12>0,G13>Inputs!$C$56),1,0) | H14: =IF(AND(H12>0,H13>Inputs!$C$56),1,0) | I14: =IF(AND(I12>0,I13>Inputs!$C$56),1,0) | J14: =IF(AND(J12>0,J13>Inputs!$C$56),1,0) | K14: =IF(AND(K12>0,K13>Inputs!$C$56),1,0) | L14: =IF(AND(L12>0,L13>Inputs!$C$56),1,0) | ... BL14: =IF(AND(BL12>0,BL13>Inputs!$C$56),1,0)
A15: Cash before equity top-up (LCY) | C15: =MIN(E15:BL15) | E15: =FS!E$61 | F15: =FS!F$61 | G15: =FS!G$61 | H15: =FS!H$61 | I15: =FS!I$61 | J15: =FS!J$61 | K15: =FS!K$61 | L15: =FS!L$61 | ... BL15: =FS!BL$61
A16: Breach: liquidity below minimum (before new equity) | C16: =SUM(E16:BL16) | E16: =IF(AND(E12>0,E15<Inputs!$C$58),1,0) | F16: =IF(AND(F12>0,F15<Inputs!$C$58),1,0) | G16: =IF(AND(G12>0,G15<Inputs!$C$58),1,0) | H16: =IF(AND(H12>0,H15<Inputs!$C$58),1,0) | I16: =IF(AND(I12>0,I15<Inputs!$C$58),1,0) | J16: =IF(AND(J12>0,J15<Inputs!$C$58),1,0) | K16: =IF(AND(K12>0,K15<Inputs!$C$58),1,0) | L16: =IF(AND(L12>0,L15<Inputs!$C$58),1,0) | ... BL16: =IF(AND(BL12>0,BL15<Inputs!$C$58),1,0)
A17: Any covenant breached in month | C17: =SUM(E17:BL17) | E17: =MAX(E9,E11,E14,E16) | F17: =MAX(F9,F11,F14,F16) | G17: =MAX(G9,G11,G14,G16) | H17: =MAX(H9,H11,H14,H16) | I17: =MAX(I9,I11,I14,I16) | J17: =MAX(J9,J11,J14,J16) | K17: =MAX(K9,K11,K14,K16) | L17: =MAX(L9,L11,L14,L16) | ... BL17: =MAX(BL9,BL11,BL14,BL16)

Sheet Unit_Economics
A1: Unit economics by tier (per unit, month-1 prices, active scenario)
A2: Lifetime view of one PAYGo customer. Undiscounted unless stated.
A4: Metric | B4: Unit | C4: Tier 1 | D4: Tier 2 | E4: Tier 3 | F4: Tier 4 | G4: Tier 5
A5: Cash price | B5: LCY | C5: =Products!$C$13 | D5: =Products!$D$13 | E5: =Products!$E$13 | F5: =Products!$F$13 | G5: =Products!$G$13
A6: Total PAYGo contract value | B6: LCY | C6: =Products!$C$34 | D6: =Products!$D$34 | E6: =Products!$E$34 | F6: =Products!$F$34 | G6: =Products!$G$34
A7: Implied annual financing rate (nominal APR) | B7: % | C7: =Products!$C$39 | D7: =Products!$D$39 | E7: =Products!$E$39 | F7: =Products!$F$39 | G7: =Products!$G$39
A8: Down payment | B8: LCY | C8: =Products!$C$14 | D8: =Products!$D$14 | E8: =Products!$E$14 | F8: =Products!$F$14 | G8: =Products!$G$14
A9: Expected instalments collected | B9: LCY | C9: =Curves!$D$70 | D9: =Curves!$P$70 | E9: =Curves!$AB$70 | F9: =Curves!$AN$70 | G9: =Curves!$AZ$70
A10: Expected lifetime customer cash (down payment + instalments) | B10: LCY | C10: =C8+C9 | D10: =D8+D9 | E10: =E8+E9 | F10: =F8+F9 | G10: =G8+G9
A11: Expected loss rate (missed / scheduled instalments) | B11: % | C11: =IFERROR(Curves!$E$70/Curves!$C$70,0) | D11: =IFERROR(Curves!$Q$70/Curves!$O$70,0) | E11: =IFERROR(Curves!$AC$70/Curves!$AA$70,0) | F11: =IFERROR(Curves!$AO$70/Curves!$AM$70,0) | G11: =IFERROR(Curves!$BA$70/Curves!$AY$70,0)
A12: Lifetime collection rate (customer cash / contract value) | B12: % | C12: =IFERROR(C10/C6,0) | D12: =IFERROR(D10/D6,0) | E12: =IFERROR(E10/E6,0) | F12: =IFERROR(F10/F6,0) | G12: =IFERROR(G10/G6,0)
A13: Expected recoveries from repossession | B13: LCY | C13: =Curves!$I$70 | D13: =Curves!$U$70 | E13: =Curves!$AG$70 | F13: =Curves!$AS$70 | G13: =Curves!$BE$70
A14: RBF per unit (opening FX) | B14: LCY | C14: =Curves!$J$70 | D14: =Curves!$V$70 | E14: =Curves!$AH$70 | F14: =Curves!$AT$70 | G14: =Curves!$BF$70
A15: Landed hardware cost | B15: LCY | C15: =Products!$C$43 | D15: =Products!$D$43 | E15: =Products!$E$43 | F15: =Products!$F$43 | G15: =Products!$G$43
A16: Installation & logistics | B16: LCY | C16: =Products!$C$19 | D16: =Products!$D$19 | E16: =Products!$E$19 | F16: =Products!$F$19 | G16: =Products!$G$19
A17: Warranty provision | B17: LCY | C17: =Products!$C$43*Products!$C$22 | D17: =Products!$D$43*Products!$D$22 | E17: =Products!$E$43*Products!$E$22 | F17: =Products!$F$43*Products!$F$22 | G17: =Products!$G$43*Products!$G$22
A18: Customer acquisition cost (CAC) | B18: LCY | C18: =Products!$C$44 | D18: =Products!$D$44 | E18: =Products!$E$44 | F18: =Products!$F$44 | G18: =Products!$G$44
A19: Payment fees + servicing over life | B19: LCY | C19: =C10*Inputs!$C$24+Inputs!$C$25*(SUM(Curves!$G$8:$G$68)-1) | D19: =D10*Inputs!$C$24+Inputs!$C$25*(SUM(Curves!$S$8:$S$68)-1) | E19: =E10*Inputs!$C$24+Inputs!$C$25*(SUM(Curves!$AE$8:$AE$68)-1) | F19: =F10*Inputs!$C$24+Inputs!$C$25*(SUM(Curves!$AQ$8:$AQ$68)-1) | G19: =G10*Inputs!$C$24+Inputs!$C$25*(SUM(Curves!$BC$8:$BC$68)-1)
A20: Lifetime contribution per unit | B20: LCY | C20: =C10+C13+C14-C15-C16-C17-C18-C19 | D20: =D10+D13+D14-D15-D16-D17-D18-D19 | E20: =E10+E13+E14-E15-E16-E17-E18-E19 | F20: =F10+F13+F14-F15-F16-F17-F18-F19 | G20: =G10+G13+G14-G15-G16-G17-G18-G19
A21: LTV / CAC (contribution before CAC / CAC) | B21: x | C21: =IFERROR((C20+C18)/C18,0) | D21: =IFERROR((D20+D18)/D18,0) | E21: =IFERROR((E20+E18)/E18,0) | F21: =IFERROR((F20+F18)/F18,0) | G21: =IFERROR((G20+G18)/G18,0)
A22: Cash payback (months after sale) | B22: months | C22: =IF(COUNTIF(Curves!$L$8:$L$68,"<0")>60,"Not paid back",COUNTIF(Curves!$L$8:$L$68,"<0")) | D22: =IF(COUNTIF(Curves!$X$8:$X$68,"<0")>60,"Not paid back",COUNTIF(Curves!$X$8:$X$68,"<0")) | E22: =IF(COUNTIF(Curves!$AJ$8:$AJ$68,"<0")>60,"Not paid back",COUNTIF(Curves!$AJ$8:$AJ$68,"<0")) | F22: =IF(COUNTIF(Curves!$AV$8:$AV$68,"<0")>60,"Not paid back",COUNTIF(Curves!$AV$8:$AV$68,"<0")) | G22: =IF(COUNTIF(Curves!$BH$8:$BH$68,"<0")>60,"Not paid back",COUNTIF(Curves!$BH$8:$BH$68,"<0"))
A23: Unit IRR (annualised, unlevered) | B23: % | C23: =IFERROR((1+IRR(Curves!$K$8:$K$68,0.02))^12-1,"n/a") | D23: =IFERROR((1+IRR(Curves!$W$8:$W$68,0.02))^12-1,"n/a") | E23: =IFERROR((1+IRR(Curves!$AI$8:$AI$68,0.02))^12-1,"n/a") | F23: =IFERROR((1+IRR(Curves!$AU$8:$AU$68,0.02))^12-1,"n/a") | G23: =IFERROR((1+IRR(Curves!$BG$8:$BG$68,0.02))^12-1,"n/a")
A24: Unit NPV at the DCF discount rate | B24: LCY | C24: =NPV((1+Inputs!$C$61)^(1/12)-1,Curves!$K$8:$K$68)*(1+Inputs!$C$61)^(1/12) | D24: =NPV((1+Inputs!$C$61)^(1/12)-1,Curves!$W$8:$W$68)*(1+Inputs!$C$61)^(1/12) | E24: =NPV((1+Inputs!$C$61)^(1/12)-1,Curves!$AI$8:$AI$68)*(1+Inputs!$C$61)^(1/12) | F24: =NPV((1+Inputs!$C$61)^(1/12)-1,Curves!$AU$8:$AU$68)*(1+Inputs!$C$61)^(1/12) | G24: =NPV((1+Inputs!$C$61)^(1/12)-1,Curves!$BG$8:$BG$68)*(1+Inputs!$C$61)^(1/12)
A26: Servicing counts active months after the sale month. Payback counts months with negative cumulative cash flow (ages 0-60). Unit NPV discounts monthly at the DCF rate; age 0 undiscounted.

Sheet Sensitivity
A1: Scenario & sensitivity snapshot (static values)
A2: Generated by the verified Python twin (tools/shadow_shs.py) at DEFAULT inputs. Does NOT update when inputs change.
A5: Case | B5: Peak equity need (USD m) | C5: Year 5 revenue (USD m) | D5: Year 5 EBITDA margin | E5: Year 5 collection rate | F5: DCF EV (USD m) | G5: Investor IRR (USD) | H5: Investor MOIC | I5: Covenant-breach months
A6: Base | B6: 10 | C6: 68.45434 | D6: 0.22326977 | E6: 0.7326369 | F6: 16.930206 | G6: 0.47656549 | H6: 7.0188113 | I6: 0
A7: Downside | B7: 10 | C7: 52.677847 | D7: 0.081003105 | E7: 0.67067563 | F7: -6.6149778 | G7: -0.10720472 | H7: 0.56723031 | I7: 43
A8: Severe | B8: 44.691615 | C8: 33.645155 | D8: -0.17422086 | E8: 0.58753459 | F8: -78.959838 | G8: n/a | H8: 0 | I8: 48
A9: Base - default hazard x1.5 | B9: 10 | C9: 68.45434 | D9: 0.16624798 | E9: 0.66126112 | F9: 13.456695 | G9: 0.38464728 | H9: 5.0897422 | I9: 39
A10: Base - collection rate x0.95 | B10: 10 | C10: 68.45434 | D10: 0.18978266 | E10: 0.69600506 | F10: 11.825953 | G10: 0.4170139 | H10: 5.7130832 | I10: 24
A11: Base - sales volume -20% | B11: 10 | C11: 54.763472 | D11: 0.21052055 | E11: 0.7326369 | F11: 10.383791 | G11: 0.39054398 | H11: 5.1990459 | I11: 0
A12: Base - hardware cost +15% | B12: 10 | C12: 68.45434 | D12: 0.16077337 | E12: 0.7326369 | F12: 8.5082039 | G12: 0.31605684 | H12: 3.9479645 | I12: 36
A13: Base - LCY depreciation 20% p.a. | B13: 10 | C13: 49.519668 | D13: 0.088673426 | E13: 0.73741025 | F13: -5.4279205 | G13: -0.089388298 | H13: 0.62613234 | I13: 40
A14: Base - no price increase on new contracts | B14: 10 | C14: 55.941718 | D14: 0.11138163 | E14: 0.72910543 | F14: -1.58717 | G14: 0.11919778 | H14: 1.7560392 | I14: 33
A15: Base - RBF programme off | B15: 10 | C15: 68.45434 | D15: 0.21511129 | E15: 0.7326369 | F15: 15.250773 | G15: 0.46006723 | H15: 6.6353566 | I15: 0
A16: Base - higher Tier 4-5 mix (20% / 10%) | B16: 10 | C16: 111.77093 | D16: 0.25647682 | E16: 0.74586675 | F16: 39.711583 | G16: 0.6799077 | H16: 13.379106 | I16: 0
A17: Base - exit at 4.0x EBITDA | B17: 10 | C17: 68.45434 | D17: 0.22326977 | E17: 0.7326369 | F17: 16.930206 | G17: 0.35261312 | H17: 4.5275993 | I17: 0
A19: Snapshot generated 2026-10-02 at default inputs (tools/shs_defaults.py) by the Python twin, which reproduces the workbook exactly (QA in the volume README). Refresh: python tools/build_shs_model.py --snapshot

Sheet Annual
A1: Annual financial statements
A2: Flows summed by year; balances at year end. LCY.
E5: Year 1 | F5: Year 2 | G5: Year 3 | H5: Year 4 | I5: Year 5
E6: 1 | F6: 2 | G6: 3 | H6: 4 | I6: 5
A8: INCOME STATEMENT
A9: Hardware revenue (cash price) | E9: =SUMIFS(FS!$E$9:$BL$9,Timeline!$E$6:$BL$6,E$6) | F9: =SUMIFS(FS!$E$9:$BL$9,Timeline!$E$6:$BL$6,F$6) | G9: =SUMIFS(FS!$E$9:$BL$9,Timeline!$E$6:$BL$6,G$6) | H9: =SUMIFS(FS!$E$9:$BL$9,Timeline!$E$6:$BL$6,H$6) | I9: =SUMIFS(FS!$E$9:$BL$9,Timeline!$E$6:$BL$6,I$6)
A10: PAYGo financing income | E10: =SUMIFS(FS!$E$10:$BL$10,Timeline!$E$6:$BL$6,E$6) | F10: =SUMIFS(FS!$E$10:$BL$10,Timeline!$E$6:$BL$6,F$6) | G10: =SUMIFS(FS!$E$10:$BL$10,Timeline!$E$6:$BL$6,G$6) | H10: =SUMIFS(FS!$E$10:$BL$10,Timeline!$E$6:$BL$6,H$6) | I10: =SUMIFS(FS!$E$10:$BL$10,Timeline!$E$6:$BL$6,I$6)
A11: Total revenue | E11: =SUMIFS(FS!$E$11:$BL$11,Timeline!$E$6:$BL$6,E$6) | F11: =SUMIFS(FS!$E$11:$BL$11,Timeline!$E$6:$BL$6,F$6) | G11: =SUMIFS(FS!$E$11:$BL$11,Timeline!$E$6:$BL$6,G$6) | H11: =SUMIFS(FS!$E$11:$BL$11,Timeline!$E$6:$BL$6,H$6) | I11: =SUMIFS(FS!$E$11:$BL$11,Timeline!$E$6:$BL$6,I$6)
A12: Cost of sales (hardware, installation) | E12: =SUMIFS(FS!$E$12:$BL$12,Timeline!$E$6:$BL$6,E$6) | F12: =SUMIFS(FS!$E$12:$BL$12,Timeline!$E$6:$BL$6,F$6) | G12: =SUMIFS(FS!$E$12:$BL$12,Timeline!$E$6:$BL$6,G$6) | H12: =SUMIFS(FS!$E$12:$BL$12,Timeline!$E$6:$BL$6,H$6) | I12: =SUMIFS(FS!$E$12:$BL$12,Timeline!$E$6:$BL$6,I$6)
A13: Gross profit | E13: =SUMIFS(FS!$E$13:$BL$13,Timeline!$E$6:$BL$6,E$6) | F13: =SUMIFS(FS!$E$13:$BL$13,Timeline!$E$6:$BL$6,F$6) | G13: =SUMIFS(FS!$E$13:$BL$13,Timeline!$E$6:$BL$6,G$6) | H13: =SUMIFS(FS!$E$13:$BL$13,Timeline!$E$6:$BL$6,H$6) | I13: =SUMIFS(FS!$E$13:$BL$13,Timeline!$E$6:$BL$6,I$6)
A14: RBF / subsidy income | E14: =SUMIFS(FS!$E$14:$BL$14,Timeline!$E$6:$BL$6,E$6) | F14: =SUMIFS(FS!$E$14:$BL$14,Timeline!$E$6:$BL$6,F$6) | G14: =SUMIFS(FS!$E$14:$BL$14,Timeline!$E$6:$BL$6,G$6) | H14: =SUMIFS(FS!$E$14:$BL$14,Timeline!$E$6:$BL$6,H$6) | I14: =SUMIFS(FS!$E$14:$BL$14,Timeline!$E$6:$BL$6,I$6)
A15: Operating expenses | E15: =SUMIFS(FS!$E$15:$BL$15,Timeline!$E$6:$BL$6,E$6) | F15: =SUMIFS(FS!$E$15:$BL$15,Timeline!$E$6:$BL$6,F$6) | G15: =SUMIFS(FS!$E$15:$BL$15,Timeline!$E$6:$BL$6,G$6) | H15: =SUMIFS(FS!$E$15:$BL$15,Timeline!$E$6:$BL$6,H$6) | I15: =SUMIFS(FS!$E$15:$BL$15,Timeline!$E$6:$BL$6,I$6)
A16: Expected credit losses | E16: =SUMIFS(FS!$E$16:$BL$16,Timeline!$E$6:$BL$6,E$6) | F16: =SUMIFS(FS!$E$16:$BL$16,Timeline!$E$6:$BL$6,F$6) | G16: =SUMIFS(FS!$E$16:$BL$16,Timeline!$E$6:$BL$6,G$6) | H16: =SUMIFS(FS!$E$16:$BL$16,Timeline!$E$6:$BL$6,H$6) | I16: =SUMIFS(FS!$E$16:$BL$16,Timeline!$E$6:$BL$6,I$6)
A17: Recoveries on repossessed units | E17: =SUMIFS(FS!$E$17:$BL$17,Timeline!$E$6:$BL$6,E$6) | F17: =SUMIFS(FS!$E$17:$BL$17,Timeline!$E$6:$BL$6,F$6) | G17: =SUMIFS(FS!$E$17:$BL$17,Timeline!$E$6:$BL$6,G$6) | H17: =SUMIFS(FS!$E$17:$BL$17,Timeline!$E$6:$BL$6,H$6) | I17: =SUMIFS(FS!$E$17:$BL$17,Timeline!$E$6:$BL$6,I$6)
A18: EBITDA | E18: =SUMIFS(FS!$E$18:$BL$18,Timeline!$E$6:$BL$6,E$6) | F18: =SUMIFS(FS!$E$18:$BL$18,Timeline!$E$6:$BL$6,F$6) | G18: =SUMIFS(FS!$E$18:$BL$18,Timeline!$E$6:$BL$6,G$6) | H18: =SUMIFS(FS!$E$18:$BL$18,Timeline!$E$6:$BL$6,H$6) | I18: =SUMIFS(FS!$E$18:$BL$18,Timeline!$E$6:$BL$6,I$6)
A19: Depreciation | E19: =SUMIFS(FS!$E$19:$BL$19,Timeline!$E$6:$BL$6,E$6) | F19: =SUMIFS(FS!$E$19:$BL$19,Timeline!$E$6:$BL$6,F$6) | G19: =SUMIFS(FS!$E$19:$BL$19,Timeline!$E$6:$BL$6,G$6) | H19: =SUMIFS(FS!$E$19:$BL$19,Timeline!$E$6:$BL$6,H$6) | I19: =SUMIFS(FS!$E$19:$BL$19,Timeline!$E$6:$BL$6,I$6)
A20: EBIT | E20: =SUMIFS(FS!$E$20:$BL$20,Timeline!$E$6:$BL$6,E$6) | F20: =SUMIFS(FS!$E$20:$BL$20,Timeline!$E$6:$BL$6,F$6) | G20: =SUMIFS(FS!$E$20:$BL$20,Timeline!$E$6:$BL$6,G$6) | H20: =SUMIFS(FS!$E$20:$BL$20,Timeline!$E$6:$BL$6,H$6) | I20: =SUMIFS(FS!$E$20:$BL$20,Timeline!$E$6:$BL$6,I$6)
A21: Interest - USD term loan | E21: =SUMIFS(FS!$E$21:$BL$21,Timeline!$E$6:$BL$6,E$6) | F21: =SUMIFS(FS!$E$21:$BL$21,Timeline!$E$6:$BL$6,F$6) | G21: =SUMIFS(FS!$E$21:$BL$21,Timeline!$E$6:$BL$6,G$6) | H21: =SUMIFS(FS!$E$21:$BL$21,Timeline!$E$6:$BL$6,H$6) | I21: =SUMIFS(FS!$E$21:$BL$21,Timeline!$E$6:$BL$6,I$6)
A22: Interest - receivables facility | E22: =SUMIFS(FS!$E$22:$BL$22,Timeline!$E$6:$BL$6,E$6) | F22: =SUMIFS(FS!$E$22:$BL$22,Timeline!$E$6:$BL$6,F$6) | G22: =SUMIFS(FS!$E$22:$BL$22,Timeline!$E$6:$BL$6,G$6) | H22: =SUMIFS(FS!$E$22:$BL$22,Timeline!$E$6:$BL$6,H$6) | I22: =SUMIFS(FS!$E$22:$BL$22,Timeline!$E$6:$BL$6,I$6)
A23: FX (loss) / gain on USD debt | E23: =SUMIFS(FS!$E$23:$BL$23,Timeline!$E$6:$BL$6,E$6) | F23: =SUMIFS(FS!$E$23:$BL$23,Timeline!$E$6:$BL$6,F$6) | G23: =SUMIFS(FS!$E$23:$BL$23,Timeline!$E$6:$BL$6,G$6) | H23: =SUMIFS(FS!$E$23:$BL$23,Timeline!$E$6:$BL$6,H$6) | I23: =SUMIFS(FS!$E$23:$BL$23,Timeline!$E$6:$BL$6,I$6)
A24: Profit before tax | E24: =SUMIFS(FS!$E$24:$BL$24,Timeline!$E$6:$BL$6,E$6) | F24: =SUMIFS(FS!$E$24:$BL$24,Timeline!$E$6:$BL$6,F$6) | G24: =SUMIFS(FS!$E$24:$BL$24,Timeline!$E$6:$BL$6,G$6) | H24: =SUMIFS(FS!$E$24:$BL$24,Timeline!$E$6:$BL$6,H$6) | I24: =SUMIFS(FS!$E$24:$BL$24,Timeline!$E$6:$BL$6,I$6)
A25: Income tax | E25: =SUMIFS(FS!$E$27:$BL$27,Timeline!$E$6:$BL$6,E$6) | F25: =SUMIFS(FS!$E$27:$BL$27,Timeline!$E$6:$BL$6,F$6) | G25: =SUMIFS(FS!$E$27:$BL$27,Timeline!$E$6:$BL$6,G$6) | H25: =SUMIFS(FS!$E$27:$BL$27,Timeline!$E$6:$BL$6,H$6) | I25: =SUMIFS(FS!$E$27:$BL$27,Timeline!$E$6:$BL$6,I$6)
A26: Net income | E26: =SUMIFS(FS!$E$28:$BL$28,Timeline!$E$6:$BL$6,E$6) | F26: =SUMIFS(FS!$E$28:$BL$28,Timeline!$E$6:$BL$6,F$6) | G26: =SUMIFS(FS!$E$28:$BL$28,Timeline!$E$6:$BL$6,G$6) | H26: =SUMIFS(FS!$E$28:$BL$28,Timeline!$E$6:$BL$6,H$6) | I26: =SUMIFS(FS!$E$28:$BL$28,Timeline!$E$6:$BL$6,I$6)
A28: BALANCE SHEET
A29: Cash | E29: =INDEX(FS!$E$31:$BL$31,1,E$6*12) | F29: =INDEX(FS!$E$31:$BL$31,1,F$6*12) | G29: =INDEX(FS!$E$31:$BL$31,1,G$6*12) | H29: =INDEX(FS!$E$31:$BL$31,1,H$6*12) | I29: =INDEX(FS!$E$31:$BL$31,1,I$6*12)
A30: PAYGo receivables - gross | E30: =INDEX(FS!$E$32:$BL$32,1,E$6*12) | F30: =INDEX(FS!$E$32:$BL$32,1,F$6*12) | G30: =INDEX(FS!$E$32:$BL$32,1,G$6*12) | H30: =INDEX(FS!$E$32:$BL$32,1,H$6*12) | I30: =INDEX(FS!$E$32:$BL$32,1,I$6*12)
A31: Loss allowance (ECL) | E31: =INDEX(FS!$E$33:$BL$33,1,E$6*12) | F31: =INDEX(FS!$E$33:$BL$33,1,F$6*12) | G31: =INDEX(FS!$E$33:$BL$33,1,G$6*12) | H31: =INDEX(FS!$E$33:$BL$33,1,H$6*12) | I31: =INDEX(FS!$E$33:$BL$33,1,I$6*12)
A32: PAYGo receivables - net | E32: =INDEX(FS!$E$34:$BL$34,1,E$6*12) | F32: =INDEX(FS!$E$34:$BL$34,1,F$6*12) | G32: =INDEX(FS!$E$34:$BL$34,1,G$6*12) | H32: =INDEX(FS!$E$34:$BL$34,1,H$6*12) | I32: =INDEX(FS!$E$34:$BL$34,1,I$6*12)
A33: Inventory | E33: =INDEX(FS!$E$35:$BL$35,1,E$6*12) | F33: =INDEX(FS!$E$35:$BL$35,1,F$6*12) | G33: =INDEX(FS!$E$35:$BL$35,1,G$6*12) | H33: =INDEX(FS!$E$35:$BL$35,1,H$6*12) | I33: =INDEX(FS!$E$35:$BL$35,1,I$6*12)
A34: Net fixed assets | E34: =INDEX(FS!$E$36:$BL$36,1,E$6*12) | F34: =INDEX(FS!$E$36:$BL$36,1,F$6*12) | G34: =INDEX(FS!$E$36:$BL$36,1,G$6*12) | H34: =INDEX(FS!$E$36:$BL$36,1,H$6*12) | I34: =INDEX(FS!$E$36:$BL$36,1,I$6*12)
A35: Total assets | E35: =INDEX(FS!$E$37:$BL$37,1,E$6*12) | F35: =INDEX(FS!$E$37:$BL$37,1,F$6*12) | G35: =INDEX(FS!$E$37:$BL$37,1,G$6*12) | H35: =INDEX(FS!$E$37:$BL$37,1,H$6*12) | I35: =INDEX(FS!$E$37:$BL$37,1,I$6*12)
A36: Supplier payables | E36: =INDEX(FS!$E$38:$BL$38,1,E$6*12) | F36: =INDEX(FS!$E$38:$BL$38,1,F$6*12) | G36: =INDEX(FS!$E$38:$BL$38,1,G$6*12) | H36: =INDEX(FS!$E$38:$BL$38,1,H$6*12) | I36: =INDEX(FS!$E$38:$BL$38,1,I$6*12)
A37: USD term loan (in LCY) | E37: =INDEX(FS!$E$39:$BL$39,1,E$6*12) | F37: =INDEX(FS!$E$39:$BL$39,1,F$6*12) | G37: =INDEX(FS!$E$39:$BL$39,1,G$6*12) | H37: =INDEX(FS!$E$39:$BL$39,1,H$6*12) | I37: =INDEX(FS!$E$39:$BL$39,1,I$6*12)
A38: Receivables facility | E38: =INDEX(FS!$E$40:$BL$40,1,E$6*12) | F38: =INDEX(FS!$E$40:$BL$40,1,F$6*12) | G38: =INDEX(FS!$E$40:$BL$40,1,G$6*12) | H38: =INDEX(FS!$E$40:$BL$40,1,H$6*12) | I38: =INDEX(FS!$E$40:$BL$40,1,I$6*12)
A39: Total liabilities | E39: =INDEX(FS!$E$41:$BL$41,1,E$6*12) | F39: =INDEX(FS!$E$41:$BL$41,1,F$6*12) | G39: =INDEX(FS!$E$41:$BL$41,1,G$6*12) | H39: =INDEX(FS!$E$41:$BL$41,1,H$6*12) | I39: =INDEX(FS!$E$41:$BL$41,1,I$6*12)
A40: Share capital | E40: =INDEX(FS!$E$42:$BL$42,1,E$6*12) | F40: =INDEX(FS!$E$42:$BL$42,1,F$6*12) | G40: =INDEX(FS!$E$42:$BL$42,1,G$6*12) | H40: =INDEX(FS!$E$42:$BL$42,1,H$6*12) | I40: =INDEX(FS!$E$42:$BL$42,1,I$6*12)
A41: Retained earnings | E41: =INDEX(FS!$E$43:$BL$43,1,E$6*12) | F41: =INDEX(FS!$E$43:$BL$43,1,F$6*12) | G41: =INDEX(FS!$E$43:$BL$43,1,G$6*12) | H41: =INDEX(FS!$E$43:$BL$43,1,H$6*12) | I41: =INDEX(FS!$E$43:$BL$43,1,I$6*12)
A42: Total equity | E42: =INDEX(FS!$E$44:$BL$44,1,E$6*12) | F42: =INDEX(FS!$E$44:$BL$44,1,F$6*12) | G42: =INDEX(FS!$E$44:$BL$44,1,G$6*12) | H42: =INDEX(FS!$E$44:$BL$44,1,H$6*12) | I42: =INDEX(FS!$E$44:$BL$44,1,I$6*12)
A43: Total liabilities & equity | E43: =INDEX(FS!$E$45:$BL$45,1,E$6*12) | F43: =INDEX(FS!$E$45:$BL$45,1,F$6*12) | G43: =INDEX(FS!$E$45:$BL$45,1,G$6*12) | H43: =INDEX(FS!$E$45:$BL$45,1,H$6*12) | I43: =INDEX(FS!$E$45:$BL$45,1,I$6*12)
A44: Balance check (should be 0) | E44: =INDEX(FS!$E$46:$BL$46,1,E$6*12) | F44: =INDEX(FS!$E$46:$BL$46,1,F$6*12) | G44: =INDEX(FS!$E$46:$BL$46,1,G$6*12) | H44: =INDEX(FS!$E$46:$BL$46,1,H$6*12) | I44: =INDEX(FS!$E$46:$BL$46,1,I$6*12)
A46: CASH FLOW STATEMENT
A47: Net income | E47: =SUMIFS(FS!$E$49:$BL$49,Timeline!$E$6:$BL$6,E$6) | F47: =SUMIFS(FS!$E$49:$BL$49,Timeline!$E$6:$BL$6,F$6) | G47: =SUMIFS(FS!$E$49:$BL$49,Timeline!$E$6:$BL$6,G$6) | H47: =SUMIFS(FS!$E$49:$BL$49,Timeline!$E$6:$BL$6,H$6) | I47: =SUMIFS(FS!$E$49:$BL$49,Timeline!$E$6:$BL$6,I$6)
A48: Add back: depreciation | E48: =SUMIFS(FS!$E$50:$BL$50,Timeline!$E$6:$BL$6,E$6) | F48: =SUMIFS(FS!$E$50:$BL$50,Timeline!$E$6:$BL$6,F$6) | G48: =SUMIFS(FS!$E$50:$BL$50,Timeline!$E$6:$BL$6,G$6) | H48: =SUMIFS(FS!$E$50:$BL$50,Timeline!$E$6:$BL$6,H$6) | I48: =SUMIFS(FS!$E$50:$BL$50,Timeline!$E$6:$BL$6,I$6)
A49: Add back: unrealised FX loss | E49: =SUMIFS(FS!$E$51:$BL$51,Timeline!$E$6:$BL$6,E$6) | F49: =SUMIFS(FS!$E$51:$BL$51,Timeline!$E$6:$BL$6,F$6) | G49: =SUMIFS(FS!$E$51:$BL$51,Timeline!$E$6:$BL$6,G$6) | H49: =SUMIFS(FS!$E$51:$BL$51,Timeline!$E$6:$BL$6,H$6) | I49: =SUMIFS(FS!$E$51:$BL$51,Timeline!$E$6:$BL$6,I$6)
A50: (Increase) / decrease in net receivables | E50: =SUMIFS(FS!$E$52:$BL$52,Timeline!$E$6:$BL$6,E$6) | F50: =SUMIFS(FS!$E$52:$BL$52,Timeline!$E$6:$BL$6,F$6) | G50: =SUMIFS(FS!$E$52:$BL$52,Timeline!$E$6:$BL$6,G$6) | H50: =SUMIFS(FS!$E$52:$BL$52,Timeline!$E$6:$BL$6,H$6) | I50: =SUMIFS(FS!$E$52:$BL$52,Timeline!$E$6:$BL$6,I$6)
A51: (Increase) / decrease in inventory | E51: =SUMIFS(FS!$E$53:$BL$53,Timeline!$E$6:$BL$6,E$6) | F51: =SUMIFS(FS!$E$53:$BL$53,Timeline!$E$6:$BL$6,F$6) | G51: =SUMIFS(FS!$E$53:$BL$53,Timeline!$E$6:$BL$6,G$6) | H51: =SUMIFS(FS!$E$53:$BL$53,Timeline!$E$6:$BL$6,H$6) | I51: =SUMIFS(FS!$E$53:$BL$53,Timeline!$E$6:$BL$6,I$6)
A52: Increase / (decrease) in payables | E52: =SUMIFS(FS!$E$54:$BL$54,Timeline!$E$6:$BL$6,E$6) | F52: =SUMIFS(FS!$E$54:$BL$54,Timeline!$E$6:$BL$6,F$6) | G52: =SUMIFS(FS!$E$54:$BL$54,Timeline!$E$6:$BL$6,G$6) | H52: =SUMIFS(FS!$E$54:$BL$54,Timeline!$E$6:$BL$6,H$6) | I52: =SUMIFS(FS!$E$54:$BL$54,Timeline!$E$6:$BL$6,I$6)
A53: Cash flow from operations | E53: =SUMIFS(FS!$E$55:$BL$55,Timeline!$E$6:$BL$6,E$6) | F53: =SUMIFS(FS!$E$55:$BL$55,Timeline!$E$6:$BL$6,F$6) | G53: =SUMIFS(FS!$E$55:$BL$55,Timeline!$E$6:$BL$6,G$6) | H53: =SUMIFS(FS!$E$55:$BL$55,Timeline!$E$6:$BL$6,H$6) | I53: =SUMIFS(FS!$E$55:$BL$55,Timeline!$E$6:$BL$6,I$6)
A54: Cash flow from investing (capex) | E54: =SUMIFS(FS!$E$56:$BL$56,Timeline!$E$6:$BL$6,E$6) | F54: =SUMIFS(FS!$E$56:$BL$56,Timeline!$E$6:$BL$6,F$6) | G54: =SUMIFS(FS!$E$56:$BL$56,Timeline!$E$6:$BL$6,G$6) | H54: =SUMIFS(FS!$E$56:$BL$56,Timeline!$E$6:$BL$6,H$6) | I54: =SUMIFS(FS!$E$56:$BL$56,Timeline!$E$6:$BL$6,I$6)
A55: Term loan drawdown / (repayment) | E55: =SUMIFS(FS!$E$57:$BL$57,Timeline!$E$6:$BL$6,E$6) | F55: =SUMIFS(FS!$E$57:$BL$57,Timeline!$E$6:$BL$6,F$6) | G55: =SUMIFS(FS!$E$57:$BL$57,Timeline!$E$6:$BL$6,G$6) | H55: =SUMIFS(FS!$E$57:$BL$57,Timeline!$E$6:$BL$6,H$6) | I55: =SUMIFS(FS!$E$57:$BL$57,Timeline!$E$6:$BL$6,I$6)
A56: Receivables facility drawdown / (repayment) | E56: =SUMIFS(FS!$E$58:$BL$58,Timeline!$E$6:$BL$6,E$6) | F56: =SUMIFS(FS!$E$58:$BL$58,Timeline!$E$6:$BL$6,F$6) | G56: =SUMIFS(FS!$E$58:$BL$58,Timeline!$E$6:$BL$6,G$6) | H56: =SUMIFS(FS!$E$58:$BL$58,Timeline!$E$6:$BL$6,H$6) | I56: =SUMIFS(FS!$E$58:$BL$58,Timeline!$E$6:$BL$6,I$6)
A57: Equity - initial | E57: =SUMIFS(FS!$E$59:$BL$59,Timeline!$E$6:$BL$6,E$6) | F57: =SUMIFS(FS!$E$59:$BL$59,Timeline!$E$6:$BL$6,F$6) | G57: =SUMIFS(FS!$E$59:$BL$59,Timeline!$E$6:$BL$6,G$6) | H57: =SUMIFS(FS!$E$59:$BL$59,Timeline!$E$6:$BL$6,H$6) | I57: =SUMIFS(FS!$E$59:$BL$59,Timeline!$E$6:$BL$6,I$6)
A58: Cash before equity top-up | E58: =INDEX(FS!$E$61:$BL$61,1,E$6*12) | F58: =INDEX(FS!$E$61:$BL$61,1,F$6*12) | G58: =INDEX(FS!$E$61:$BL$61,1,G$6*12) | H58: =INDEX(FS!$E$61:$BL$61,1,H$6*12) | I58: =INDEX(FS!$E$61:$BL$61,1,I$6*12)
A59: Equity top-up to maintain minimum cash | E59: =SUMIFS(FS!$E$62:$BL$62,Timeline!$E$6:$BL$6,E$6) | F59: =SUMIFS(FS!$E$62:$BL$62,Timeline!$E$6:$BL$6,F$6) | G59: =SUMIFS(FS!$E$62:$BL$62,Timeline!$E$6:$BL$6,G$6) | H59: =SUMIFS(FS!$E$62:$BL$62,Timeline!$E$6:$BL$6,H$6) | I59: =SUMIFS(FS!$E$62:$BL$62,Timeline!$E$6:$BL$6,I$6)
A60: Closing cash | E60: =INDEX(FS!$E$63:$BL$63,1,E$6*12) | F60: =INDEX(FS!$E$63:$BL$63,1,F$6*12) | G60: =INDEX(FS!$E$63:$BL$63,1,G$6*12) | H60: =INDEX(FS!$E$63:$BL$63,1,H$6*12) | I60: =INDEX(FS!$E$63:$BL$63,1,I$6*12)

Sheet FS
A1: Financial statements (monthly)
A2: LCY. Simplified IFRS-style presentation; simplifications listed in the manual.
A4: Month # | D4: Opening | E4: =Timeline!E4 | F4: =Timeline!F4 | G4: =Timeline!G4 | H4: =Timeline!H4 | I4: =Timeline!I4 | J4: =Timeline!J4 | K4: =Timeline!K4 | L4: =Timeline!L4 | ... BL4: =Timeline!BL4
A5: Period end | E5: =Timeline!E5 | F5: =Timeline!F5 | G5: =Timeline!G5 | H5: =Timeline!H5 | I5: =Timeline!I5 | J5: =Timeline!J5 | K5: =Timeline!K5 | L5: =Timeline!L5 | ... BL5: =Timeline!BL5
A6: Year # | E6: =Timeline!E6 | F6: =Timeline!F6 | G6: =Timeline!G6 | H6: =Timeline!H6 | I6: =Timeline!I6 | J6: =Timeline!J6 | K6: =Timeline!K6 | L6: =Timeline!L6 | ... BL6: =Timeline!BL6
A8: INCOME STATEMENT
A9: Hardware revenue (cash price) | B9: LCY | C9: =SUM(E9:BL9) | E9: =Ops!E$137 | F9: =Ops!F$137 | G9: =Ops!G$137 | H9: =Ops!H$137 | I9: =Ops!I$137 | J9: =Ops!J$137 | K9: =Ops!K$137 | L9: =Ops!L$137 | ... BL9: =Ops!BL$137
A10: PAYGo financing income | B10: LCY | C10: =SUM(E10:BL10) | E10: =Ops!E$142 | F10: =Ops!F$142 | G10: =Ops!G$142 | H10: =Ops!H$142 | I10: =Ops!I$142 | J10: =Ops!J$142 | K10: =Ops!K$142 | L10: =Ops!L$142 | ... BL10: =Ops!BL$142
A11: Total revenue | B11: LCY | C11: =SUM(E11:BL11) | E11: =E9+E10 | F11: =F9+F10 | G11: =G9+G10 | H11: =H9+H10 | I11: =I9+I10 | J11: =J9+J10 | K11: =K9+K10 | L11: =L9+L10 | ... BL11: =BL9+BL10
A12: Cost of sales (hardware, installation) | B12: LCY | C12: =SUM(E12:BL12) | E12: =-Costs!E$10 | F12: =-Costs!F$10 | G12: =-Costs!G$10 | H12: =-Costs!H$10 | I12: =-Costs!I$10 | J12: =-Costs!J$10 | K12: =-Costs!K$10 | L12: =-Costs!L$10 | ... BL12: =-Costs!BL$10
A13: Gross profit | B13: LCY | C13: =SUM(E13:BL13) | E13: =E11+E12 | F13: =F11+F12 | G13: =G11+G12 | H13: =H11+H12 | I13: =I11+I12 | J13: =J11+J12 | K13: =K11+K12 | L13: =L11+L12 | ... BL13: =BL11+BL12
A14: RBF / subsidy income | B14: LCY | C14: =SUM(E14:BL14) | E14: =Ops!E$145 | F14: =Ops!F$145 | G14: =Ops!G$145 | H14: =Ops!H$145 | I14: =Ops!I$145 | J14: =Ops!J$145 | K14: =Ops!K$145 | L14: =Ops!L$145 | ... BL14: =Ops!BL$145
A15: Operating expenses | B15: LCY | C15: =SUM(E15:BL15) | E15: =-Costs!E$19 | F15: =-Costs!F$19 | G15: =-Costs!G$19 | H15: =-Costs!H$19 | I15: =-Costs!I$19 | J15: =-Costs!J$19 | K15: =-Costs!K$19 | L15: =-Costs!L$19 | ... BL15: =-Costs!BL$19
A16: Expected credit losses | B16: LCY | C16: =SUM(E16:BL16) | E16: =-Ops!E$143 | F16: =-Ops!F$143 | G16: =-Ops!G$143 | H16: =-Ops!H$143 | I16: =-Ops!I$143 | J16: =-Ops!J$143 | K16: =-Ops!K$143 | L16: =-Ops!L$143 | ... BL16: =-Ops!BL$143
A17: Recoveries on repossessed units | B17: LCY | C17: =SUM(E17:BL17) | E17: =Ops!E$144 | F17: =Ops!F$144 | G17: =Ops!G$144 | H17: =Ops!H$144 | I17: =Ops!I$144 | J17: =Ops!J$144 | K17: =Ops!K$144 | L17: =Ops!L$144 | ... BL17: =Ops!BL$144
A18: EBITDA | B18: LCY | C18: =SUM(E18:BL18) | E18: =E13+E14+E15+E16+E17 | F18: =F13+F14+F15+F16+F17 | G18: =G13+G14+G15+G16+G17 | H18: =H13+H14+H15+H16+H17 | I18: =I13+I14+I15+I16+I17 | J18: =J13+J14+J15+J16+J17 | K18: =K13+K14+K15+K16+K17 | L18: =L13+L14+L15+L16+L17 | ... BL18: =BL13+BL14+BL15+BL16+BL17
A19: Depreciation | B19: LCY | C19: =SUM(E19:BL19) | E19: =-Costs!E$26 | F19: =-Costs!F$26 | G19: =-Costs!G$26 | H19: =-Costs!H$26 | I19: =-Costs!I$26 | J19: =-Costs!J$26 | K19: =-Costs!K$26 | L19: =-Costs!L$26 | ... BL19: =-Costs!BL$26
A20: EBIT | B20: LCY | C20: =SUM(E20:BL20) | E20: =E18+E19 | F20: =F18+F19 | G20: =G18+G19 | H20: =H18+H19 | I20: =I18+I19 | J20: =J18+J19 | K20: =K18+K19 | L20: =L18+L19 | ... BL20: =BL18+BL19
A21: Interest - USD term loan | B21: LCY | C21: =SUM(E21:BL21) | E21: =-Financing!E$16 | F21: =-Financing!F$16 | G21: =-Financing!G$16 | H21: =-Financing!H$16 | I21: =-Financing!I$16 | J21: =-Financing!J$16 | K21: =-Financing!K$16 | L21: =-Financing!L$16 | ... BL21: =-Financing!BL$16
A22: Interest - receivables facility | B22: LCY | C22: =SUM(E22:BL22) | E22: =-Financing!E$25 | F22: =-Financing!F$25 | G22: =-Financing!G$25 | H22: =-Financing!H$25 | I22: =-Financing!I$25 | J22: =-Financing!J$25 | K22: =-Financing!K$25 | L22: =-Financing!L$25 | ... BL22: =-Financing!BL$25
A23: FX (loss) / gain on USD debt | B23: LCY | C23: =SUM(E23:BL23) | E23: =-Financing!E$20 | F23: =-Financing!F$20 | G23: =-Financing!G$20 | H23: =-Financing!H$20 | I23: =-Financing!I$20 | J23: =-Financing!J$20 | K23: =-Financing!K$20 | L23: =-Financing!L$20 | ... BL23: =-Financing!BL$20
A24: Profit before tax | B24: LCY | C24: =SUM(E24:BL24) | E24: =E20+E21+E22+E23 | F24: =F20+F21+F22+F23 | G24: =G20+G21+G22+G23 | H24: =H20+H21+H22+H23 | I24: =I20+I21+I22+I23 | J24: =J20+J21+J22+J23 | K24: =K20+K21+K22+K23 | L24: =L20+L21+L22+L23 | ... BL24: =BL20+BL21+BL22+BL23
A25: memo: cumulative PBT | B25: LCY | C25: =BL25 | E25: =D25+E24 | F25: =E25+F24 | G25: =F25+G24 | H25: =G25+H24 | I25: =H25+I24 | J25: =I25+J24 | K25: =J25+K24 | L25: =K25+L24 | ... BL25: =BK25+BL24
A26: memo: running maximum of cumulative PBT | B26: LCY | C26: =BL26 | E26: =MAX(D26,E25) | F26: =MAX(E26,F25) | G26: =MAX(F26,G25) | H26: =MAX(G26,H25) | I26: =MAX(H26,I25) | J26: =MAX(I26,J25) | K26: =MAX(J26,K25) | L26: =MAX(K26,L25) | ... BL26: =MAX(BK26,BL25)
A27: Income tax | B27: LCY | C27: =SUM(E27:BL27) | E27: =-Inputs!$C$12*(MAX(0,E26)-MAX(0,D26)) | F27: =-Inputs!$C$12*(MAX(0,F26)-MAX(0,E26)) | G27: =-Inputs!$C$12*(MAX(0,G26)-MAX(0,F26)) | H27: =-Inputs!$C$12*(MAX(0,H26)-MAX(0,G26)) | I27: =-Inputs!$C$12*(MAX(0,I26)-MAX(0,H26)) | J27: =-Inputs!$C$12*(MAX(0,J26)-MAX(0,I26)) | K27: =-Inputs!$C$12*(MAX(0,K26)-MAX(0,J26)) | L27: =-Inputs!$C$12*(MAX(0,L26)-MAX(0,K26)) | ... BL27: =-Inputs!$C$12*(MAX(0,BL26)-MAX(0,BK26))
A28: Net income | B28: LCY | C28: =SUM(E28:BL28) | E28: =E24+E27 | F28: =F24+F27 | G28: =G24+G27 | H28: =H24+H27 | I28: =I24+I27 | J28: =J24+J27 | K28: =K24+K27 | L28: =L24+L27 | ... BL28: =BL24+BL27
A30: BALANCE SHEET
A31: Cash | B31: LCY | C31: =BL31 | E31: =E63 | F31: =F63 | G31: =G63 | H31: =H63 | I31: =I63 | J31: =J63 | K31: =K63 | L31: =L63 | ... BL31: =BL63
A32: PAYGo receivables - gross | B32: LCY | C32: =BL32 | E32: =Ops!E$149 | F32: =Ops!F$149 | G32: =Ops!G$149 | H32: =Ops!H$149 | I32: =Ops!I$149 | J32: =Ops!J$149 | K32: =Ops!K$149 | L32: =Ops!L$149 | ... BL32: =Ops!BL$149
A33: Loss allowance (ECL) | B33: LCY | C33: =BL33 | E33: =D33-Ops!E$143+Ops!E$141 | F33: =E33-Ops!F$143+Ops!F$141 | G33: =F33-Ops!G$143+Ops!G$141 | H33: =G33-Ops!H$143+Ops!H$141 | I33: =H33-Ops!I$143+Ops!I$141 | J33: =I33-Ops!J$143+Ops!J$141 | K33: =J33-Ops!K$143+Ops!K$141 | L33: =K33-Ops!L$143+Ops!L$141 | ... BL33: =BK33-Ops!BL$143+Ops!BL$141
A34: PAYGo receivables - net | B34: LCY | C34: =BL34 | E34: =E32+E33 | F34: =F32+F33 | G34: =G32+G33 | H34: =H32+H33 | I34: =I32+I33 | J34: =J32+J33 | K34: =K32+K33 | L34: =L32+L33 | ... BL34: =BL32+BL33
A35: Inventory | B35: LCY | C35: =BL35 | E35: =Costs!E$21 | F35: =Costs!F$21 | G35: =Costs!G$21 | H35: =Costs!H$21 | I35: =Costs!I$21 | J35: =Costs!J$21 | K35: =Costs!K$21 | L35: =Costs!L$21 | ... BL35: =Costs!BL$21
A36: Net fixed assets | B36: LCY | C36: =BL36 | E36: =Costs!E$27 | F36: =Costs!F$27 | G36: =Costs!G$27 | H36: =Costs!H$27 | I36: =Costs!I$27 | J36: =Costs!J$27 | K36: =Costs!K$27 | L36: =Costs!L$27 | ... BL36: =Costs!BL$27
A37: Total assets | B37: LCY | C37: =BL37 | E37: =E31+E34+E35+E36 | F37: =F31+F34+F35+F36 | G37: =G31+G34+G35+G36 | H37: =H31+H34+H35+H36 | I37: =I31+I34+I35+I36 | J37: =J31+J34+J35+J36 | K37: =K31+K34+K35+K36 | L37: =L31+L34+L35+L36 | ... BL37: =BL31+BL34+BL35+BL36
A38: Supplier payables | B38: LCY | C38: =BL38 | E38: =Costs!E$23 | F38: =Costs!F$23 | G38: =Costs!G$23 | H38: =Costs!H$23 | I38: =Costs!I$23 | J38: =Costs!J$23 | K38: =Costs!K$23 | L38: =Costs!L$23 | ... BL38: =Costs!BL$23
A39: USD term loan (in LCY) | B39: LCY | C39: =BL39 | E39: =Financing!E$19 | F39: =Financing!F$19 | G39: =Financing!G$19 | H39: =Financing!H$19 | I39: =Financing!I$19 | J39: =Financing!J$19 | K39: =Financing!K$19 | L39: =Financing!L$19 | ... BL39: =Financing!BL$19
A40: Receivables facility | B40: LCY | C40: =BL40 | E40: =Financing!E$23 | F40: =Financing!F$23 | G40: =Financing!G$23 | H40: =Financing!H$23 | I40: =Financing!I$23 | J40: =Financing!J$23 | K40: =Financing!K$23 | L40: =Financing!L$23 | ... BL40: =Financing!BL$23
A41: Total liabilities | B41: LCY | C41: =BL41 | E41: =E38+E39+E40 | F41: =F38+F39+F40 | G41: =G38+G39+G40 | H41: =H38+H39+H40 | I41: =I38+I39+I40 | J41: =J38+J39+J40 | K41: =K38+K39+K40 | L41: =L38+L39+L40 | ... BL41: =BL38+BL39+BL40
A42: Share capital | B42: LCY | C42: =BL42 | E42: =Financing!E$11 | F42: =Financing!F$11 | G42: =Financing!G$11 | H42: =Financing!H$11 | I42: =Financing!I$11 | J42: =Financing!J$11 | K42: =Financing!K$11 | L42: =Financing!L$11 | ... BL42: =Financing!BL$11
A43: Retained earnings | B43: LCY | C43: =BL43 | E43: =D43+E28 | F43: =E43+F28 | G43: =F43+G28 | H43: =G43+H28 | I43: =H43+I28 | J43: =I43+J28 | K43: =J43+K28 | L43: =K43+L28 | ... BL43: =BK43+BL28
A44: Total equity | B44: LCY | C44: =BL44 | E44: =E42+E43 | F44: =F42+F43 | G44: =G42+G43 | H44: =H42+H43 | I44: =I42+I43 | J44: =J42+J43 | K44: =K42+K43 | L44: =L42+L43 | ... BL44: =BL42+BL43
A45: Total liabilities & equity | B45: LCY | C45: =BL45 | E45: =E41+E44 | F45: =F41+F44 | G45: =G41+G44 | H45: =H41+H44 | I45: =I41+I44 | J45: =J41+J44 | K45: =K41+K44 | L45: =L41+L44 | ... BL45: =BL41+BL44
A46: Balance check (should be 0) | B46: LCY | C46: =MAX(E46:BL46) | E46: =ROUND(E37-E45,0) | F46: =ROUND(F37-F45,0) | G46: =ROUND(G37-G45,0) | H46: =ROUND(H37-H45,0) | I46: =ROUND(I37-I45,0) | J46: =ROUND(J37-J45,0) | K46: =ROUND(K37-K45,0) | L46: =ROUND(L37-L45,0) | ... BL46: =ROUND(BL37-BL45,0)
A48: CASH FLOW STATEMENT
A49: Net income | B49: LCY | C49: =SUM(E49:BL49) | E49: =E28 | F49: =F28 | G49: =G28 | H49: =H28 | I49: =I28 | J49: =J28 | K49: =K28 | L49: =L28 | ... BL49: =BL28
A50: Add back: depreciation | B50: LCY | C50: =SUM(E50:BL50) | E50: =-E19 | F50: =-F19 | G50: =-G19 | H50: =-H19 | I50: =-I19 | J50: =-J19 | K50: =-K19 | L50: =-L19 | ... BL50: =-BL19
A51: Add back: unrealised FX loss | B51: LCY | C51: =SUM(E51:BL51) | E51: =-E23 | F51: =-F23 | G51: =-G23 | H51: =-H23 | I51: =-I23 | J51: =-J23 | K51: =-K23 | L51: =-L23 | ... BL51: =-BL23
A52: (Increase) / decrease in net receivables | B52: LCY | C52: =SUM(E52:BL52) | E52: =-(E34-D34) | F52: =-(F34-E34) | G52: =-(G34-F34) | H52: =-(H34-G34) | I52: =-(I34-H34) | J52: =-(J34-I34) | K52: =-(K34-J34) | L52: =-(L34-K34) | ... BL52: =-(BL34-BK34)
A53: (Increase) / decrease in inventory | B53: LCY | C53: =SUM(E53:BL53) | E53: =-(E35-D35) | F53: =-(F35-E35) | G53: =-(G35-F35) | H53: =-(H35-G35) | I53: =-(I35-H35) | J53: =-(J35-I35) | K53: =-(K35-J35) | L53: =-(L35-K35) | ... BL53: =-(BL35-BK35)
A54: Increase / (decrease) in payables | B54: LCY | C54: =SUM(E54:BL54) | E54: =E38-D38 | F54: =F38-E38 | G54: =G38-F38 | H54: =H38-G38 | I54: =I38-H38 | J54: =J38-I38 | K54: =K38-J38 | L54: =L38-K38 | ... BL54: =BL38-BK38
A55: Cash flow from operations | B55: LCY | C55: =SUM(E55:BL55) | E55: =SUM(E49:E54) | F55: =SUM(F49:F54) | G55: =SUM(G49:G54) | H55: =SUM(H49:H54) | I55: =SUM(I49:I54) | J55: =SUM(J49:J54) | K55: =SUM(K49:K54) | L55: =SUM(L49:L54) | ... BL55: =SUM(BL49:BL54)
A56: Cash flow from investing (capex) | B56: LCY | C56: =SUM(E56:BL56) | E56: =-Costs!E$25 | F56: =-Costs!F$25 | G56: =-Costs!G$25 | H56: =-Costs!H$25 | I56: =-Costs!I$25 | J56: =-Costs!J$25 | K56: =-Costs!K$25 | L56: =-Costs!L$25 | ... BL56: =-Costs!BL$25
A57: Term loan drawdown / (repayment) | B57: LCY | C57: =SUM(E57:BL57) | E57: =Financing!E$17-Financing!E$18 | F57: =Financing!F$17-Financing!F$18 | G57: =Financing!G$17-Financing!G$18 | H57: =Financing!H$17-Financing!H$18 | I57: =Financing!I$17-Financing!I$18 | J57: =Financing!J$17-Financing!J$18 | K57: =Financing!K$17-Financing!K$18 | L57: =Financing!L$17-Financing!L$18 | ... BL57: =Financing!BL$17-Financing!BL$18
A58: Receivables facility drawdown / (repayment) | B58: LCY | C58: =SUM(E58:BL58) | E58: =Financing!E$24 | F58: =Financing!F$24 | G58: =Financing!G$24 | H58: =Financing!H$24 | I58: =Financing!I$24 | J58: =Financing!J$24 | K58: =Financing!K$24 | L58: =Financing!L$24 | ... BL58: =Financing!BL$24
A59: Equity - initial | B59: LCY | C59: =SUM(E59:BL59) | E59: =Financing!E$9 | F59: =Financing!F$9 | G59: =Financing!G$9 | H59: =Financing!H$9 | I59: =Financing!I$9 | J59: =Financing!J$9 | K59: =Financing!K$9 | L59: =Financing!L$9 | ... BL59: =Financing!BL$9
A60: memo: cash before facility and equity top-up | B60: LCY | C60: =BL60 | E60: =D63+E55+E56+E57+E59 | F60: =E63+F55+F56+F57+F59 | G60: =F63+G55+G56+G57+G59 | H60: =G63+H55+H56+H57+H59 | I60: =H63+I55+I56+I57+I59 | J60: =I63+J55+J56+J57+J59 | K60: =J63+K55+K56+K57+K59 | L60: =K63+L55+L56+L57+L59 | ... BL60: =BK63+BL55+BL56+BL57+BL59
A61: Cash before equity top-up | B61: LCY | C61: =BL61 | E61: =E60+E58 | F61: =F60+F58 | G61: =G60+G58 | H61: =H60+H58 | I61: =I60+I58 | J61: =J60+J58 | K61: =K60+K58 | L61: =L60+L58 | ... BL61: =BL60+BL58
A62: Equity top-up to maintain minimum cash | B62: LCY | C62: =SUM(E62:BL62) | E62: =MAX(0,Inputs!$C$40-E61) | F62: =MAX(0,Inputs!$C$40-F61) | G62: =MAX(0,Inputs!$C$40-G61) | H62: =MAX(0,Inputs!$C$40-H61) | I62: =MAX(0,Inputs!$C$40-I61) | J62: =MAX(0,Inputs!$C$40-J61) | K62: =MAX(0,Inputs!$C$40-K61) | L62: =MAX(0,Inputs!$C$40-L61) | ... BL62: =MAX(0,Inputs!$C$40-BL61)
A63: Closing cash | B63: LCY | C63: =BL63 | E63: =E61+E62 | F63: =F61+F62 | G63: =G61+G62 | H63: =H61+H62 | I63: =I61+I62 | J63: =J61+J62 | K63: =K61+K62 | L63: =L61+L62 | ... BL63: =BL61+BL62
A65: MEMO
A66: EBITDA positive (1 = yes) | B66: flag | E66: =IF(E18>0,1,0) | F66: =IF(F18>0,1,0) | G66: =IF(G18>0,1,0) | H66: =IF(H18>0,1,0) | I66: =IF(I18>0,1,0) | J66: =IF(J18>0,1,0) | K66: =IF(K18>0,1,0) | L66: =IF(L18>0,1,0) | ... BL66: =IF(BL18>0,1,0)
A67: Operating cash flow positive (1 = yes) | B67: flag | E67: =IF(E55>0,1,0) | F67: =IF(F55>0,1,0) | G67: =IF(G55>0,1,0) | H67: =IF(H55>0,1,0) | I67: =IF(I55>0,1,0) | J67: =IF(J55>0,1,0) | K67: =IF(K55>0,1,0) | L67: =IF(L55>0,1,0) | ... BL67: =IF(BL55>0,1,0)

Sheet Ops
A1: Operations & PAYGo portfolio
A2: By tier, then total. LCY unless stated.
A4: Month # | D4: Opening | E4: =Timeline!E4 | F4: =Timeline!F4 | G4: =Timeline!G4 | H4: =Timeline!H4 | I4: =Timeline!I4 | J4: =Timeline!J4 | K4: =Timeline!K4 | L4: =Timeline!L4 | ... BL4: =Timeline!BL4
A5: Period end | E5: =Timeline!E5 | F5: =Timeline!F5 | G5: =Timeline!G5 | H5: =Timeline!H5 | I5: =Timeline!I5 | J5: =Timeline!J5 | K5: =Timeline!K5 | L5: =Timeline!L5 | ... BL5: =Timeline!BL5
A6: Year # | E6: =Timeline!E6 | F6: =Timeline!F6 | G6: =Timeline!G6 | H6: =Timeline!H6 | I6: =Timeline!I6 | J6: =Timeline!J6 | K6: =Timeline!K6 | L6: =Timeline!L6 | ... BL6: =Timeline!BL6
A8: =Products!$C$6
A9: Units sold | B9: units | C9: =SUM(E9:BL9) | E9: =Timeline!E$11*Products!$C$23 | F9: =Timeline!F$11*Products!$C$23 | G9: =Timeline!G$11*Products!$C$23 | H9: =Timeline!H$11*Products!$C$23 | I9: =Timeline!I$11*Products!$C$23 | J9: =Timeline!J$11*Products!$C$23 | K9: =Timeline!K$11*Products!$C$23 | L9: =Timeline!L$11*Products!$C$23 | ... BL9: =Timeline!BL$11*Products!$C$23
A10: Price-indexed units (units x price index) | B10: units | C10: =SUM(E10:BL10) | E10: =E9*Timeline!E$10 | F10: =F9*Timeline!F$10 | G10: =G9*Timeline!G$10 | H10: =H9*Timeline!H$10 | I10: =I9*Timeline!I$10 | J10: =J9*Timeline!J$10 | K10: =K9*Timeline!K$10 | L10: =L9*Timeline!L$10 | ... BL10: =BL9*Timeline!BL$10
A11: Down payments collected | B11: LCY | C11: =SUM(E11:BL11) | E11: =E10*Products!$C$14 | F11: =F10*Products!$C$14 | G11: =G10*Products!$C$14 | H11: =H10*Products!$C$14 | I11: =I10*Products!$C$14 | J11: =J10*Products!$C$14 | K11: =K10*Products!$C$14 | L11: =L10*Products!$C$14 | ... BL11: =BL10*Products!$C$14
A12: Hardware revenue (cash price) | B12: LCY | C12: =SUM(E12:BL12) | E12: =E10*Products!$C$13 | F12: =F10*Products!$C$13 | G12: =G10*Products!$C$13 | H12: =H10*Products!$C$13 | I12: =I10*Products!$C$13 | J12: =J10*Products!$C$13 | K12: =K10*Products!$C$13 | L12: =L10*Products!$C$13 | ... BL12: =BL10*Products!$C$13
A13: New PAYGo receivables originated | B13: LCY | C13: =SUM(E13:BL13) | E13: =E10*Products!$C$38 | F13: =F10*Products!$C$38 | G13: =G10*Products!$C$38 | H13: =H10*Products!$C$38 | I13: =I10*Products!$C$38 | J13: =J10*Products!$C$38 | K13: =K10*Products!$C$38 | L13: =L10*Products!$C$38 | ... BL13: =BL10*Products!$C$38
A14: Instalments due | B14: LCY | C14: =SUM(E14:BL14) | E14: =Products!$C$33*SUMIFS($E$10:$BL$10,Timeline!$E$4:$BL$4,">="&(E$4-Products!$C$16),Timeline!$E$4:$BL$4,"<="&(E$4-1)) | F14: =Products!$C$33*SUMIFS($E$10:$BL$10,Timeline!$E$4:$BL$4,">="&(F$4-Products!$C$16),Timeline!$E$4:$BL$4,"<="&(F$4-1)) | G14: =Products!$C$33*SUMIFS($E$10:$BL$10,Timeline!$E$4:$BL$4,">="&(G$4-Products!$C$16),Timeline!$E$4:$BL$4,"<="&(G$4-1)) | H14: =Products!$C$33*SUMIFS($E$10:$BL$10,Timeline!$E$4:$BL$4,">="&(H$4-Products!$C$16),Timeline!$E$4:$BL$4,"<="&(H$4-1)) | I14: =Products!$C$33*SUMIFS($E$10:$BL$10,Timeline!$E$4:$BL$4,">="&(I$4-Products!$C$16),Timeline!$E$4:$BL$4,"<="&(I$4-1)) | J14: =Products!$C$33*SUMIFS($E$10:$BL$10,Timeline!$E$4:$BL$4,">="&(J$4-Products!$C$16),Timeline!$E$4:$BL$4,"<="&(J$4-1)) | K14: =Products!$C$33*SUMIFS($E$10:$BL$10,Timeline!$E$4:$BL$4,">="&(K$4-Products!$C$16),Timeline!$E$4:$BL$4,"<="&(K$4-1)) | L14: =Products!$C$33*SUMIFS($E$10:$BL$10,Timeline!$E$4:$BL$4,">="&(L$4-Products!$C$16),Timeline!$E$4:$BL$4,"<="&(L$4-1)) | ... BL14: =Products!$C$33*SUMIFS($E$10:$BL$10,Timeline!$E$4:$BL$4,">="&(BL$4-Products!$C$16),Timeline!$E$4:$BL$4,"<="&(BL$4-1))
A15: Instalments collected | B15: LCY | C15: =SUM(E15:BL15) | E15: =Cohort_T1!E$9 | F15: =Cohort_T1!F$9 | G15: =Cohort_T1!G$9 | H15: =Cohort_T1!H$9 | I15: =Cohort_T1!I$9 | J15: =Cohort_T1!J$9 | K15: =Cohort_T1!K$9 | L15: =Cohort_T1!L$9 | ... BL15: =Cohort_T1!BL$9
A16: Missed instalments written off | B16: LCY | C16: =SUM(E16:BL16) | E16: =E14-E15 | F16: =F14-F15 | G16: =G14-G15 | H16: =H14-H15 | I16: =I14-I15 | J16: =J14-J15 | K16: =K14-K15 | L16: =L14-L15 | ... BL16: =BL14-BL15
A17: PAYGo financing income (straight-line over tenor) | B17: LCY | C17: =SUM(E17:BL17) | E17: =IF(Products!$C$16=0,0,Products!$C$35/Products!$C$16*SUMIFS($E$10:$BL$10,Timeline!$E$4:$BL$4,">="&(E$4-Products!$C$16),Timeline!$E$4:$BL$4,"<="&(E$4-1))) | F17: =IF(Products!$C$16=0,0,Products!$C$35/Products!$C$16*SUMIFS($E$10:$BL$10,Timeline!$E$4:$BL$4,">="&(F$4-Products!$C$16),Timeline!$E$4:$BL$4,"<="&(F$4-1))) | G17: =IF(Products!$C$16=0,0,Products!$C$35/Products!$C$16*SUMIFS($E$10:$BL$10,Timeline!$E$4:$BL$4,">="&(G$4-Products!$C$16),Timeline!$E$4:$BL$4,"<="&(G$4-1))) | H17: =IF(Products!$C$16=0,0,Products!$C$35/Products!$C$16*SUMIFS($E$10:$BL$10,Timeline!$E$4:$BL$4,">="&(H$4-Products!$C$16),Timeline!$E$4:$BL$4,"<="&(H$4-1))) | I17: =IF(Products!$C$16=0,0,Products!$C$35/Products!$C$16*SUMIFS($E$10:$BL$10,Timeline!$E$4:$BL$4,">="&(I$4-Products!$C$16),Timeline!$E$4:$BL$4,"<="&(I$4-1))) | J17: =IF(Products!$C$16=0,0,Products!$C$35/Products!$C$16*SUMIFS($E$10:$BL$10,Timeline!$E$4:$BL$4,">="&(J$4-Products!$C$16),Timeline!$E$4:$BL$4,"<="&(J$4-1))) | K17: =IF(Products!$C$16=0,0,Products!$C$35/Products!$C$16*SUMIFS($E$10:$BL$10,Timeline!$E$4:$BL$4,">="&(K$4-Products!$C$16),Timeline!$E$4:$BL$4,"<="&(K$4-1))) | L17: =IF(Products!$C$16=0,0,Products!$C$35/Products!$C$16*SUMIFS($E$10:$BL$10,Timeline!$E$4:$BL$4,">="&(L$4-Products!$C$16),Timeline!$E$4:$BL$4,"<="&(L$4-1))) | ... BL17: =IF(Products!$C$16=0,0,Products!$C$35/Products!$C$16*SUMIFS($E$10:$BL$10,Timeline!$E$4:$BL$4,">="&(BL$4-Products!$C$16),Timeline!$E$4:$BL$4,"<="&(BL$4-1)))
A18: Expected credit loss charged at origination | B18: LCY | C18: =SUM(E18:BL18) | E18: =E10*Curves!$E$70 | F18: =F10*Curves!$E$70 | G18: =G10*Curves!$E$70 | H18: =H10*Curves!$E$70 | I18: =I10*Curves!$E$70 | J18: =J10*Curves!$E$70 | K18: =K10*Curves!$E$70 | L18: =L10*Curves!$E$70 | ... BL18: =BL10*Curves!$E$70
A19: Recoveries from resale of repossessed units | B19: LCY | C19: =SUM(E19:BL19) | E19: =Cohort_T1!E$198 | F19: =Cohort_T1!F$198 | G19: =Cohort_T1!G$198 | H19: =Cohort_T1!H$198 | I19: =Cohort_T1!I$198 | J19: =Cohort_T1!J$198 | K19: =Cohort_T1!K$198 | L19: =Cohort_T1!L$198 | ... BL19: =Cohort_T1!BL$198
A20: RBF received | B20: LCY | C20: =SUM(E20:BL20) | E20: =IF(E$4-Inputs!$C$33>=1,INDEX($E$9:$BL$9,1,E$4-Inputs!$C$33),0)*Products!$C$30*Timeline!E$8*Inputs!$C$32 | F20: =IF(F$4-Inputs!$C$33>=1,INDEX($E$9:$BL$9,1,F$4-Inputs!$C$33),0)*Products!$C$30*Timeline!F$8*Inputs!$C$32 | G20: =IF(G$4-Inputs!$C$33>=1,INDEX($E$9:$BL$9,1,G$4-Inputs!$C$33),0)*Products!$C$30*Timeline!G$8*Inputs!$C$32 | H20: =IF(H$4-Inputs!$C$33>=1,INDEX($E$9:$BL$9,1,H$4-Inputs!$C$33),0)*Products!$C$30*Timeline!H$8*Inputs!$C$32 | I20: =IF(I$4-Inputs!$C$33>=1,INDEX($E$9:$BL$9,1,I$4-Inputs!$C$33),0)*Products!$C$30*Timeline!I$8*Inputs!$C$32 | J20: =IF(J$4-Inputs!$C$33>=1,INDEX($E$9:$BL$9,1,J$4-Inputs!$C$33),0)*Products!$C$30*Timeline!J$8*Inputs!$C$32 | K20: =IF(K$4-Inputs!$C$33>=1,INDEX($E$9:$BL$9,1,K$4-Inputs!$C$33),0)*Products!$C$30*Timeline!K$8*Inputs!$C$32 | L20: =IF(L$4-Inputs!$C$33>=1,INDEX($E$9:$BL$9,1,L$4-Inputs!$C$33),0)*Products!$C$30*Timeline!L$8*Inputs!$C$32 | ... BL20: =IF(BL$4-Inputs!$C$33>=1,INDEX($E$9:$BL$9,1,BL$4-Inputs!$C$33),0)*Products!$C$30*Timeline!BL$8*Inputs!$C$32
A21: Active (paying, in-tenor) accounts | B21: accounts | C21: =BL21 | E21: =Cohort_T1!E$72 | F21: =Cohort_T1!F$72 | G21: =Cohort_T1!G$72 | H21: =Cohort_T1!H$72 | I21: =Cohort_T1!I$72 | J21: =Cohort_T1!J$72 | K21: =Cohort_T1!K$72 | L21: =Cohort_T1!L$72 | ... BL21: =Cohort_T1!BL$72
A22: Accounts reaching end of tenor (unlocked) | B22: accounts | C22: =SUM(E22:BL22) | E22: =IF(E$4>Products!$C$16,INDEX($E$9:$BL$9,1,E$4-Products!$C$16)*INDEX(Curves!$B$8:$B$68,Products!$C$16+1),0) | F22: =IF(F$4>Products!$C$16,INDEX($E$9:$BL$9,1,F$4-Products!$C$16)*INDEX(Curves!$B$8:$B$68,Products!$C$16+1),0) | G22: =IF(G$4>Products!$C$16,INDEX($E$9:$BL$9,1,G$4-Products!$C$16)*INDEX(Curves!$B$8:$B$68,Products!$C$16+1),0) | H22: =IF(H$4>Products!$C$16,INDEX($E$9:$BL$9,1,H$4-Products!$C$16)*INDEX(Curves!$B$8:$B$68,Products!$C$16+1),0) | I22: =IF(I$4>Products!$C$16,INDEX($E$9:$BL$9,1,I$4-Products!$C$16)*INDEX(Curves!$B$8:$B$68,Products!$C$16+1),0) | J22: =IF(J$4>Products!$C$16,INDEX($E$9:$BL$9,1,J$4-Products!$C$16)*INDEX(Curves!$B$8:$B$68,Products!$C$16+1),0) | K22: =IF(K$4>Products!$C$16,INDEX($E$9:$BL$9,1,K$4-Products!$C$16)*INDEX(Curves!$B$8:$B$68,Products!$C$16+1),0) | L22: =IF(L$4>Products!$C$16,INDEX($E$9:$BL$9,1,L$4-Products!$C$16)*INDEX(Curves!$B$8:$B$68,Products!$C$16+1),0) | ... BL22: =IF(BL$4>Products!$C$16,INDEX($E$9:$BL$9,1,BL$4-Products!$C$16)*INDEX(Curves!$B$8:$B$68,Products!$C$16+1),0)
A23: Receivables at risk (carrying amount, accounts that stopped paying) | B23: LCY | C23: =BL23 | E23: =Cohort_T1!E$135 | F23: =Cohort_T1!F$135 | G23: =Cohort_T1!G$135 | H23: =Cohort_T1!H$135 | I23: =Cohort_T1!I$135 | J23: =Cohort_T1!J$135 | K23: =Cohort_T1!K$135 | L23: =Cohort_T1!L$135 | ... BL23: =Cohort_T1!BL$135
A24: Gross PAYGo receivables (closing) | B24: LCY | C24: =BL24 | E24: =D24+E13+E17-E15-E16 | F24: =E24+F13+F17-F15-F16 | G24: =F24+G13+G17-G15-G16 | H24: =G24+H13+H17-H15-H16 | I24: =H24+I13+I17-I15-I16 | J24: =I24+J13+J17-J15-J16 | K24: =J24+K13+K17-K15-K16 | L24: =K24+L13+L17-L15-L16 | ... BL24: =BK24+BL13+BL17-BL15-BL16
A25: Eligible receivables (gross - at risk) | B25: LCY | C25: =BL25 | E25: =MAX(0,E24-E23) | F25: =MAX(0,F24-F23) | G25: =MAX(0,G24-G23) | H25: =MAX(0,H24-H23) | I25: =MAX(0,I24-I23) | J25: =MAX(0,J24-J23) | K25: =MAX(0,K24-K23) | L25: =MAX(0,L24-L23) | ... BL25: =MAX(0,BL24-BL23)
A26: Borrowing-base contribution (advance rate x eligible) | B26: LCY | C26: =BL26 | E26: =E25*Products!$C$31 | F26: =F25*Products!$C$31 | G26: =G25*Products!$C$31 | H26: =H25*Products!$C$31 | I26: =I25*Products!$C$31 | J26: =J25*Products!$C$31 | K26: =K25*Products!$C$31 | L26: =L25*Products!$C$31 | ... BL26: =BL25*Products!$C$31
A27: Landed hardware cost of units sold | B27: LCY | C27: =SUM(E27:BL27) | E27: =E9*Products!$C$18*(1+Inputs!$C$28)*Timeline!E$8*Scenarios!$G$9 | F27: =F9*Products!$C$18*(1+Inputs!$C$28)*Timeline!F$8*Scenarios!$G$9 | G27: =G9*Products!$C$18*(1+Inputs!$C$28)*Timeline!G$8*Scenarios!$G$9 | H27: =H9*Products!$C$18*(1+Inputs!$C$28)*Timeline!H$8*Scenarios!$G$9 | I27: =I9*Products!$C$18*(1+Inputs!$C$28)*Timeline!I$8*Scenarios!$G$9 | J27: =J9*Products!$C$18*(1+Inputs!$C$28)*Timeline!J$8*Scenarios!$G$9 | K27: =K9*Products!$C$18*(1+Inputs!$C$28)*Timeline!K$8*Scenarios!$G$9 | L27: =L9*Products!$C$18*(1+Inputs!$C$28)*Timeline!L$8*Scenarios!$G$9 | ... BL27: =BL9*Products!$C$18*(1+Inputs!$C$28)*Timeline!BL$8*Scenarios!$G$9
A28: Installation & logistics | B28: LCY | C28: =SUM(E28:BL28) | E28: =E9*Products!$C$19*Timeline!E$9 | F28: =F9*Products!$C$19*Timeline!F$9 | G28: =G9*Products!$C$19*Timeline!G$9 | H28: =H9*Products!$C$19*Timeline!H$9 | I28: =I9*Products!$C$19*Timeline!I$9 | J28: =J9*Products!$C$19*Timeline!J$9 | K28: =K9*Products!$C$19*Timeline!K$9 | L28: =L9*Products!$C$19*Timeline!L$9 | ... BL28: =BL9*Products!$C$19*Timeline!BL$9
A29: Warranty & after-sales provision | B29: LCY | C29: =SUM(E29:BL29) | E29: =E27*Products!$C$22 | F29: =F27*Products!$C$22 | G29: =G27*Products!$C$22 | H29: =H27*Products!$C$22 | I29: =I27*Products!$C$22 | J29: =J27*Products!$C$22 | K29: =K27*Products!$C$22 | L29: =L27*Products!$C$22 | ... BL29: =BL27*Products!$C$22
A30: Commissions | B30: LCY | C30: =SUM(E30:BL30) | E30: =E9*Products!$C$20*Timeline!E$9 | F30: =F9*Products!$C$20*Timeline!F$9 | G30: =G9*Products!$C$20*Timeline!G$9 | H30: =H9*Products!$C$20*Timeline!H$9 | I30: =I9*Products!$C$20*Timeline!I$9 | J30: =J9*Products!$C$20*Timeline!J$9 | K30: =K9*Products!$C$20*Timeline!K$9 | L30: =L9*Products!$C$20*Timeline!L$9 | ... BL30: =BL9*Products!$C$20*Timeline!BL$9
A31: Marketing & acquisition | B31: LCY | C31: =SUM(E31:BL31) | E31: =E9*Products!$C$21*Timeline!E$9 | F31: =F9*Products!$C$21*Timeline!F$9 | G31: =G9*Products!$C$21*Timeline!G$9 | H31: =H9*Products!$C$21*Timeline!H$9 | I31: =I9*Products!$C$21*Timeline!I$9 | J31: =J9*Products!$C$21*Timeline!J$9 | K31: =K9*Products!$C$21*Timeline!K$9 | L31: =L9*Products!$C$21*Timeline!L$9 | ... BL31: =BL9*Products!$C$21*Timeline!BL$9
A33: =Products!$D$6
A34: Units sold | B34: units | C34: =SUM(E34:BL34) | E34: =Timeline!E$11*Products!$D$23 | F34: =Timeline!F$11*Products!$D$23 | G34: =Timeline!G$11*Products!$D$23 | H34: =Timeline!H$11*Products!$D$23 | I34: =Timeline!I$11*Products!$D$23 | J34: =Timeline!J$11*Products!$D$23 | K34: =Timeline!K$11*Products!$D$23 | L34: =Timeline!L$11*Products!$D$23 | ... BL34: =Timeline!BL$11*Products!$D$23
A35: Price-indexed units (units x price index) | B35: units | C35: =SUM(E35:BL35) | E35: =E34*Timeline!E$10 | F35: =F34*Timeline!F$10 | G35: =G34*Timeline!G$10 | H35: =H34*Timeline!H$10 | I35: =I34*Timeline!I$10 | J35: =J34*Timeline!J$10 | K35: =K34*Timeline!K$10 | L35: =L34*Timeline!L$10 | ... BL35: =BL34*Timeline!BL$10
A36: Down payments collected | B36: LCY | C36: =SUM(E36:BL36) | E36: =E35*Products!$D$14 | F36: =F35*Products!$D$14 | G36: =G35*Products!$D$14 | H36: =H35*Products!$D$14 | I36: =I35*Products!$D$14 | J36: =J35*Products!$D$14 | K36: =K35*Products!$D$14 | L36: =L35*Products!$D$14 | ... BL36: =BL35*Products!$D$14
A37: Hardware revenue (cash price) | B37: LCY | C37: =SUM(E37:BL37) | E37: =E35*Products!$D$13 | F37: =F35*Products!$D$13 | G37: =G35*Products!$D$13 | H37: =H35*Products!$D$13 | I37: =I35*Products!$D$13 | J37: =J35*Products!$D$13 | K37: =K35*Products!$D$13 | L37: =L35*Products!$D$13 | ... BL37: =BL35*Products!$D$13
A38: New PAYGo receivables originated | B38: LCY | C38: =SUM(E38:BL38) | E38: =E35*Products!$D$38 | F38: =F35*Products!$D$38 | G38: =G35*Products!$D$38 | H38: =H35*Products!$D$38 | I38: =I35*Products!$D$38 | J38: =J35*Products!$D$38 | K38: =K35*Products!$D$38 | L38: =L35*Products!$D$38 | ... BL38: =BL35*Products!$D$38
A39: Instalments due | B39: LCY | C39: =SUM(E39:BL39) | E39: =Products!$D$33*SUMIFS($E$35:$BL$35,Timeline!$E$4:$BL$4,">="&(E$4-Products!$D$16),Timeline!$E$4:$BL$4,"<="&(E$4-1)) | F39: =Products!$D$33*SUMIFS($E$35:$BL$35,Timeline!$E$4:$BL$4,">="&(F$4-Products!$D$16),Timeline!$E$4:$BL$4,"<="&(F$4-1)) | G39: =Products!$D$33*SUMIFS($E$35:$BL$35,Timeline!$E$4:$BL$4,">="&(G$4-Products!$D$16),Timeline!$E$4:$BL$4,"<="&(G$4-1)) | H39: =Products!$D$33*SUMIFS($E$35:$BL$35,Timeline!$E$4:$BL$4,">="&(H$4-Products!$D$16),Timeline!$E$4:$BL$4,"<="&(H$4-1)) | I39: =Products!$D$33*SUMIFS($E$35:$BL$35,Timeline!$E$4:$BL$4,">="&(I$4-Products!$D$16),Timeline!$E$4:$BL$4,"<="&(I$4-1)) | J39: =Products!$D$33*SUMIFS($E$35:$BL$35,Timeline!$E$4:$BL$4,">="&(J$4-Products!$D$16),Timeline!$E$4:$BL$4,"<="&(J$4-1)) | K39: =Products!$D$33*SUMIFS($E$35:$BL$35,Timeline!$E$4:$BL$4,">="&(K$4-Products!$D$16),Timeline!$E$4:$BL$4,"<="&(K$4-1)) | L39: =Products!$D$33*SUMIFS($E$35:$BL$35,Timeline!$E$4:$BL$4,">="&(L$4-Products!$D$16),Timeline!$E$4:$BL$4,"<="&(L$4-1)) | ... BL39: =Products!$D$33*SUMIFS($E$35:$BL$35,Timeline!$E$4:$BL$4,">="&(BL$4-Products!$D$16),Timeline!$E$4:$BL$4,"<="&(BL$4-1))
A40: Instalments collected | B40: LCY | C40: =SUM(E40:BL40) | E40: =Cohort_T2!E$9 | F40: =Cohort_T2!F$9 | G40: =Cohort_T2!G$9 | H40: =Cohort_T2!H$9 | I40: =Cohort_T2!I$9 | J40: =Cohort_T2!J$9 | K40: =Cohort_T2!K$9 | L40: =Cohort_T2!L$9 | ... BL40: =Cohort_T2!BL$9
A41: Missed instalments written off | B41: LCY | C41: =SUM(E41:BL41) | E41: =E39-E40 | F41: =F39-F40 | G41: =G39-G40 | H41: =H39-H40 | I41: =I39-I40 | J41: =J39-J40 | K41: =K39-K40 | L41: =L39-L40 | ... BL41: =BL39-BL40
A42: PAYGo financing income (straight-line over tenor) | B42: LCY | C42: =SUM(E42:BL42) | E42: =IF(Products!$D$16=0,0,Products!$D$35/Products!$D$16*SUMIFS($E$35:$BL$35,Timeline!$E$4:$BL$4,">="&(E$4-Products!$D$16),Timeline!$E$4:$BL$4,"<="&(E$4-1))) | F42: =IF(Products!$D$16=0,0,Products!$D$35/Products!$D$16*SUMIFS($E$35:$BL$35,Timeline!$E$4:$BL$4,">="&(F$4-Products!$D$16),Timeline!$E$4:$BL$4,"<="&(F$4-1))) | G42: =IF(Products!$D$16=0,0,Products!$D$35/Products!$D$16*SUMIFS($E$35:$BL$35,Timeline!$E$4:$BL$4,">="&(G$4-Products!$D$16),Timeline!$E$4:$BL$4,"<="&(G$4-1))) | H42: =IF(Products!$D$16=0,0,Products!$D$35/Products!$D$16*SUMIFS($E$35:$BL$35,Timeline!$E$4:$BL$4,">="&(H$4-Products!$D$16),Timeline!$E$4:$BL$4,"<="&(H$4-1))) | I42: =IF(Products!$D$16=0,0,Products!$D$35/Products!$D$16*SUMIFS($E$35:$BL$35,Timeline!$E$4:$BL$4,">="&(I$4-Products!$D$16),Timeline!$E$4:$BL$4,"<="&(I$4-1))) | J42: =IF(Products!$D$16=0,0,Products!$D$35/Products!$D$16*SUMIFS($E$35:$BL$35,Timeline!$E$4:$BL$4,">="&(J$4-Products!$D$16),Timeline!$E$4:$BL$4,"<="&(J$4-1))) | K42: =IF(Products!$D$16=0,0,Products!$D$35/Products!$D$16*SUMIFS($E$35:$BL$35,Timeline!$E$4:$BL$4,">="&(K$4-Products!$D$16),Timeline!$E$4:$BL$4,"<="&(K$4-1))) | L42: =IF(Products!$D$16=0,0,Products!$D$35/Products!$D$16*SUMIFS($E$35:$BL$35,Timeline!$E$4:$BL$4,">="&(L$4-Products!$D$16),Timeline!$E$4:$BL$4,"<="&(L$4-1))) | ... BL42: =IF(Products!$D$16=0,0,Products!$D$35/Products!$D$16*SUMIFS($E$35:$BL$35,Timeline!$E$4:$BL$4,">="&(BL$4-Products!$D$16),Timeline!$E$4:$BL$4,"<="&(BL$4-1)))
A43: Expected credit loss charged at origination | B43: LCY | C43: =SUM(E43:BL43) | E43: =E35*Curves!$Q$70 | F43: =F35*Curves!$Q$70 | G43: =G35*Curves!$Q$70 | H43: =H35*Curves!$Q$70 | I43: =I35*Curves!$Q$70 | J43: =J35*Curves!$Q$70 | K43: =K35*Curves!$Q$70 | L43: =L35*Curves!$Q$70 | ... BL43: =BL35*Curves!$Q$70
A44: Recoveries from resale of repossessed units | B44: LCY | C44: =SUM(E44:BL44) | E44: =Cohort_T2!E$198 | F44: =Cohort_T2!F$198 | G44: =Cohort_T2!G$198 | H44: =Cohort_T2!H$198 | I44: =Cohort_T2!I$198 | J44: =Cohort_T2!J$198 | K44: =Cohort_T2!K$198 | L44: =Cohort_T2!L$198 | ... BL44: =Cohort_T2!BL$198
A45: RBF received | B45: LCY | C45: =SUM(E45:BL45) | E45: =IF(E$4-Inputs!$C$33>=1,INDEX($E$34:$BL$34,1,E$4-Inputs!$C$33),0)*Products!$D$30*Timeline!E$8*Inputs!$C$32 | F45: =IF(F$4-Inputs!$C$33>=1,INDEX($E$34:$BL$34,1,F$4-Inputs!$C$33),0)*Products!$D$30*Timeline!F$8*Inputs!$C$32 | G45: =IF(G$4-Inputs!$C$33>=1,INDEX($E$34:$BL$34,1,G$4-Inputs!$C$33),0)*Products!$D$30*Timeline!G$8*Inputs!$C$32 | H45: =IF(H$4-Inputs!$C$33>=1,INDEX($E$34:$BL$34,1,H$4-Inputs!$C$33),0)*Products!$D$30*Timeline!H$8*Inputs!$C$32 | I45: =IF(I$4-Inputs!$C$33>=1,INDEX($E$34:$BL$34,1,I$4-Inputs!$C$33),0)*Products!$D$30*Timeline!I$8*Inputs!$C$32 | J45: =IF(J$4-Inputs!$C$33>=1,INDEX($E$34:$BL$34,1,J$4-Inputs!$C$33),0)*Products!$D$30*Timeline!J$8*Inputs!$C$32 | K45: =IF(K$4-Inputs!$C$33>=1,INDEX($E$34:$BL$34,1,K$4-Inputs!$C$33),0)*Products!$D$30*Timeline!K$8*Inputs!$C$32 | L45: =IF(L$4-Inputs!$C$33>=1,INDEX($E$34:$BL$34,1,L$4-Inputs!$C$33),0)*Products!$D$30*Timeline!L$8*Inputs!$C$32 | ... BL45: =IF(BL$4-Inputs!$C$33>=1,INDEX($E$34:$BL$34,1,BL$4-Inputs!$C$33),0)*Products!$D$30*Timeline!BL$8*Inputs!$C$32
A46: Active (paying, in-tenor) accounts | B46: accounts | C46: =BL46 | E46: =Cohort_T2!E$72 | F46: =Cohort_T2!F$72 | G46: =Cohort_T2!G$72 | H46: =Cohort_T2!H$72 | I46: =Cohort_T2!I$72 | J46: =Cohort_T2!J$72 | K46: =Cohort_T2!K$72 | L46: =Cohort_T2!L$72 | ... BL46: =Cohort_T2!BL$72
A47: Accounts reaching end of tenor (unlocked) | B47: accounts | C47: =SUM(E47:BL47) | E47: =IF(E$4>Products!$D$16,INDEX($E$34:$BL$34,1,E$4-Products!$D$16)*INDEX(Curves!$N$8:$N$68,Products!$D$16+1),0) | F47: =IF(F$4>Products!$D$16,INDEX($E$34:$BL$34,1,F$4-Products!$D$16)*INDEX(Curves!$N$8:$N$68,Products!$D$16+1),0) | G47: =IF(G$4>Products!$D$16,INDEX($E$34:$BL$34,1,G$4-Products!$D$16)*INDEX(Curves!$N$8:$N$68,Products!$D$16+1),0) | H47: =IF(H$4>Products!$D$16,INDEX($E$34:$BL$34,1,H$4-Products!$D$16)*INDEX(Curves!$N$8:$N$68,Products!$D$16+1),0) | I47: =IF(I$4>Products!$D$16,INDEX($E$34:$BL$34,1,I$4-Products!$D$16)*INDEX(Curves!$N$8:$N$68,Products!$D$16+1),0) | J47: =IF(J$4>Products!$D$16,INDEX($E$34:$BL$34,1,J$4-Products!$D$16)*INDEX(Curves!$N$8:$N$68,Products!$D$16+1),0) | K47: =IF(K$4>Products!$D$16,INDEX($E$34:$BL$34,1,K$4-Products!$D$16)*INDEX(Curves!$N$8:$N$68,Products!$D$16+1),0) | L47: =IF(L$4>Products!$D$16,INDEX($E$34:$BL$34,1,L$4-Products!$D$16)*INDEX(Curves!$N$8:$N$68,Products!$D$16+1),0) | ... BL47: =IF(BL$4>Products!$D$16,INDEX($E$34:$BL$34,1,BL$4-Products!$D$16)*INDEX(Curves!$N$8:$N$68,Products!$D$16+1),0)
A48: Receivables at risk (carrying amount, accounts that stopped paying) | B48: LCY | C48: =BL48 | E48: =Cohort_T2!E$135 | F48: =Cohort_T2!F$135 | G48: =Cohort_T2!G$135 | H48: =Cohort_T2!H$135 | I48: =Cohort_T2!I$135 | J48: =Cohort_T2!J$135 | K48: =Cohort_T2!K$135 | L48: =Cohort_T2!L$135 | ... BL48: =Cohort_T2!BL$135
A49: Gross PAYGo receivables (closing) | B49: LCY | C49: =BL49 | E49: =D49+E38+E42-E40-E41 | F49: =E49+F38+F42-F40-F41 | G49: =F49+G38+G42-G40-G41 | H49: =G49+H38+H42-H40-H41 | I49: =H49+I38+I42-I40-I41 | J49: =I49+J38+J42-J40-J41 | K49: =J49+K38+K42-K40-K41 | L49: =K49+L38+L42-L40-L41 | ... BL49: =BK49+BL38+BL42-BL40-BL41
A50: Eligible receivables (gross - at risk) | B50: LCY | C50: =BL50 | E50: =MAX(0,E49-E48) | F50: =MAX(0,F49-F48) | G50: =MAX(0,G49-G48) | H50: =MAX(0,H49-H48) | I50: =MAX(0,I49-I48) | J50: =MAX(0,J49-J48) | K50: =MAX(0,K49-K48) | L50: =MAX(0,L49-L48) | ... BL50: =MAX(0,BL49-BL48)
A51: Borrowing-base contribution (advance rate x eligible) | B51: LCY | C51: =BL51 | E51: =E50*Products!$D$31 | F51: =F50*Products!$D$31 | G51: =G50*Products!$D$31 | H51: =H50*Products!$D$31 | I51: =I50*Products!$D$31 | J51: =J50*Products!$D$31 | K51: =K50*Products!$D$31 | L51: =L50*Products!$D$31 | ... BL51: =BL50*Products!$D$31
A52: Landed hardware cost of units sold | B52: LCY | C52: =SUM(E52:BL52) | E52: =E34*Products!$D$18*(1+Inputs!$C$28)*Timeline!E$8*Scenarios!$G$9 | F52: =F34*Products!$D$18*(1+Inputs!$C$28)*Timeline!F$8*Scenarios!$G$9 | G52: =G34*Products!$D$18*(1+Inputs!$C$28)*Timeline!G$8*Scenarios!$G$9 | H52: =H34*Products!$D$18*(1+Inputs!$C$28)*Timeline!H$8*Scenarios!$G$9 | I52: =I34*Products!$D$18*(1+Inputs!$C$28)*Timeline!I$8*Scenarios!$G$9 | J52: =J34*Products!$D$18*(1+Inputs!$C$28)*Timeline!J$8*Scenarios!$G$9 | K52: =K34*Products!$D$18*(1+Inputs!$C$28)*Timeline!K$8*Scenarios!$G$9 | L52: =L34*Products!$D$18*(1+Inputs!$C$28)*Timeline!L$8*Scenarios!$G$9 | ... BL52: =BL34*Products!$D$18*(1+Inputs!$C$28)*Timeline!BL$8*Scenarios!$G$9
A53: Installation & logistics | B53: LCY | C53: =SUM(E53:BL53) | E53: =E34*Products!$D$19*Timeline!E$9 | F53: =F34*Products!$D$19*Timeline!F$9 | G53: =G34*Products!$D$19*Timeline!G$9 | H53: =H34*Products!$D$19*Timeline!H$9 | I53: =I34*Products!$D$19*Timeline!I$9 | J53: =J34*Products!$D$19*Timeline!J$9 | K53: =K34*Products!$D$19*Timeline!K$9 | L53: =L34*Products!$D$19*Timeline!L$9 | ... BL53: =BL34*Products!$D$19*Timeline!BL$9
A54: Warranty & after-sales provision | B54: LCY | C54: =SUM(E54:BL54) | E54: =E52*Products!$D$22 | F54: =F52*Products!$D$22 | G54: =G52*Products!$D$22 | H54: =H52*Products!$D$22 | I54: =I52*Products!$D$22 | J54: =J52*Products!$D$22 | K54: =K52*Products!$D$22 | L54: =L52*Products!$D$22 | ... BL54: =BL52*Products!$D$22
A55: Commissions | B55: LCY | C55: =SUM(E55:BL55) | E55: =E34*Products!$D$20*Timeline!E$9 | F55: =F34*Products!$D$20*Timeline!F$9 | G55: =G34*Products!$D$20*Timeline!G$9 | H55: =H34*Products!$D$20*Timeline!H$9 | I55: =I34*Products!$D$20*Timeline!I$9 | J55: =J34*Products!$D$20*Timeline!J$9 | K55: =K34*Products!$D$20*Timeline!K$9 | L55: =L34*Products!$D$20*Timeline!L$9 | ... BL55: =BL34*Products!$D$20*Timeline!BL$9
A56: Marketing & acquisition | B56: LCY | C56: =SUM(E56:BL56) | E56: =E34*Products!$D$21*Timeline!E$9 | F56: =F34*Products!$D$21*Timeline!F$9 | G56: =G34*Products!$D$21*Timeline!G$9 | H56: =H34*Products!$D$21*Timeline!H$9 | I56: =I34*Products!$D$21*Timeline!I$9 | J56: =J34*Products!$D$21*Timeline!J$9 | K56: =K34*Products!$D$21*Timeline!K$9 | L56: =L34*Products!$D$21*Timeline!L$9 | ... BL56: =BL34*Products!$D$21*Timeline!BL$9
A58: =Products!$E$6
A59: Units sold | B59: units | C59: =SUM(E59:BL59) | E59: =Timeline!E$11*Products!$E$23 | F59: =Timeline!F$11*Products!$E$23 | G59: =Timeline!G$11*Products!$E$23 | H59: =Timeline!H$11*Products!$E$23 | I59: =Timeline!I$11*Products!$E$23 | J59: =Timeline!J$11*Products!$E$23 | K59: =Timeline!K$11*Products!$E$23 | L59: =Timeline!L$11*Products!$E$23 | ... BL59: =Timeline!BL$11*Products!$E$23
A60: Price-indexed units (units x price index) | B60: units | C60: =SUM(E60:BL60) | E60: =E59*Timeline!E$10 | F60: =F59*Timeline!F$10 | G60: =G59*Timeline!G$10 | H60: =H59*Timeline!H$10 | I60: =I59*Timeline!I$10 | J60: =J59*Timeline!J$10 | K60: =K59*Timeline!K$10 | L60: =L59*Timeline!L$10 | ... BL60: =BL59*Timeline!BL$10
A61: Down payments collected | B61: LCY | C61: =SUM(E61:BL61) | E61: =E60*Products!$E$14 | F61: =F60*Products!$E$14 | G61: =G60*Products!$E$14 | H61: =H60*Products!$E$14 | I61: =I60*Products!$E$14 | J61: =J60*Products!$E$14 | K61: =K60*Products!$E$14 | L61: =L60*Products!$E$14 | ... BL61: =BL60*Products!$E$14
A62: Hardware revenue (cash price) | B62: LCY | C62: =SUM(E62:BL62) | E62: =E60*Products!$E$13 | F62: =F60*Products!$E$13 | G62: =G60*Products!$E$13 | H62: =H60*Products!$E$13 | I62: =I60*Products!$E$13 | J62: =J60*Products!$E$13 | K62: =K60*Products!$E$13 | L62: =L60*Products!$E$13 | ... BL62: =BL60*Products!$E$13
A63: New PAYGo receivables originated | B63: LCY | C63: =SUM(E63:BL63) | E63: =E60*Products!$E$38 | F63: =F60*Products!$E$38 | G63: =G60*Products!$E$38 | H63: =H60*Products!$E$38 | I63: =I60*Products!$E$38 | J63: =J60*Products!$E$38 | K63: =K60*Products!$E$38 | L63: =L60*Products!$E$38 | ... BL63: =BL60*Products!$E$38
A64: Instalments due | B64: LCY | C64: =SUM(E64:BL64) | E64: =Products!$E$33*SUMIFS($E$60:$BL$60,Timeline!$E$4:$BL$4,">="&(E$4-Products!$E$16),Timeline!$E$4:$BL$4,"<="&(E$4-1)) | F64: =Products!$E$33*SUMIFS($E$60:$BL$60,Timeline!$E$4:$BL$4,">="&(F$4-Products!$E$16),Timeline!$E$4:$BL$4,"<="&(F$4-1)) | G64: =Products!$E$33*SUMIFS($E$60:$BL$60,Timeline!$E$4:$BL$4,">="&(G$4-Products!$E$16),Timeline!$E$4:$BL$4,"<="&(G$4-1)) | H64: =Products!$E$33*SUMIFS($E$60:$BL$60,Timeline!$E$4:$BL$4,">="&(H$4-Products!$E$16),Timeline!$E$4:$BL$4,"<="&(H$4-1)) | I64: =Products!$E$33*SUMIFS($E$60:$BL$60,Timeline!$E$4:$BL$4,">="&(I$4-Products!$E$16),Timeline!$E$4:$BL$4,"<="&(I$4-1)) | J64: =Products!$E$33*SUMIFS($E$60:$BL$60,Timeline!$E$4:$BL$4,">="&(J$4-Products!$E$16),Timeline!$E$4:$BL$4,"<="&(J$4-1)) | K64: =Products!$E$33*SUMIFS($E$60:$BL$60,Timeline!$E$4:$BL$4,">="&(K$4-Products!$E$16),Timeline!$E$4:$BL$4,"<="&(K$4-1)) | L64: =Products!$E$33*SUMIFS($E$60:$BL$60,Timeline!$E$4:$BL$4,">="&(L$4-Products!$E$16),Timeline!$E$4:$BL$4,"<="&(L$4-1)) | ... BL64: =Products!$E$33*SUMIFS($E$60:$BL$60,Timeline!$E$4:$BL$4,">="&(BL$4-Products!$E$16),Timeline!$E$4:$BL$4,"<="&(BL$4-1))
A65: Instalments collected | B65: LCY | C65: =SUM(E65:BL65) | E65: =Cohort_T3!E$9 | F65: =Cohort_T3!F$9 | G65: =Cohort_T3!G$9 | H65: =Cohort_T3!H$9 | I65: =Cohort_T3!I$9 | J65: =Cohort_T3!J$9 | K65: =Cohort_T3!K$9 | L65: =Cohort_T3!L$9 | ... BL65: =Cohort_T3!BL$9
A66: Missed instalments written off | B66: LCY | C66: =SUM(E66:BL66) | E66: =E64-E65 | F66: =F64-F65 | G66: =G64-G65 | H66: =H64-H65 | I66: =I64-I65 | J66: =J64-J65 | K66: =K64-K65 | L66: =L64-L65 | ... BL66: =BL64-BL65
A67: PAYGo financing income (straight-line over tenor) | B67: LCY | C67: =SUM(E67:BL67) | E67: =IF(Products!$E$16=0,0,Products!$E$35/Products!$E$16*SUMIFS($E$60:$BL$60,Timeline!$E$4:$BL$4,">="&(E$4-Products!$E$16),Timeline!$E$4:$BL$4,"<="&(E$4-1))) | F67: =IF(Products!$E$16=0,0,Products!$E$35/Products!$E$16*SUMIFS($E$60:$BL$60,Timeline!$E$4:$BL$4,">="&(F$4-Products!$E$16),Timeline!$E$4:$BL$4,"<="&(F$4-1))) | G67: =IF(Products!$E$16=0,0,Products!$E$35/Products!$E$16*SUMIFS($E$60:$BL$60,Timeline!$E$4:$BL$4,">="&(G$4-Products!$E$16),Timeline!$E$4:$BL$4,"<="&(G$4-1))) | H67: =IF(Products!$E$16=0,0,Products!$E$35/Products!$E$16*SUMIFS($E$60:$BL$60,Timeline!$E$4:$BL$4,">="&(H$4-Products!$E$16),Timeline!$E$4:$BL$4,"<="&(H$4-1))) | I67: =IF(Products!$E$16=0,0,Products!$E$35/Products!$E$16*SUMIFS($E$60:$BL$60,Timeline!$E$4:$BL$4,">="&(I$4-Products!$E$16),Timeline!$E$4:$BL$4,"<="&(I$4-1))) | J67: =IF(Products!$E$16=0,0,Products!$E$35/Products!$E$16*SUMIFS($E$60:$BL$60,Timeline!$E$4:$BL$4,">="&(J$4-Products!$E$16),Timeline!$E$4:$BL$4,"<="&(J$4-1))) | K67: =IF(Products!$E$16=0,0,Products!$E$35/Products!$E$16*SUMIFS($E$60:$BL$60,Timeline!$E$4:$BL$4,">="&(K$4-Products!$E$16),Timeline!$E$4:$BL$4,"<="&(K$4-1))) | L67: =IF(Products!$E$16=0,0,Products!$E$35/Products!$E$16*SUMIFS($E$60:$BL$60,Timeline!$E$4:$BL$4,">="&(L$4-Products!$E$16),Timeline!$E$4:$BL$4,"<="&(L$4-1))) | ... BL67: =IF(Products!$E$16=0,0,Products!$E$35/Products!$E$16*SUMIFS($E$60:$BL$60,Timeline!$E$4:$BL$4,">="&(BL$4-Products!$E$16),Timeline!$E$4:$BL$4,"<="&(BL$4-1)))
A68: Expected credit loss charged at origination | B68: LCY | C68: =SUM(E68:BL68) | E68: =E60*Curves!$AC$70 | F68: =F60*Curves!$AC$70 | G68: =G60*Curves!$AC$70 | H68: =H60*Curves!$AC$70 | I68: =I60*Curves!$AC$70 | J68: =J60*Curves!$AC$70 | K68: =K60*Curves!$AC$70 | L68: =L60*Curves!$AC$70 | ... BL68: =BL60*Curves!$AC$70
A69: Recoveries from resale of repossessed units | B69: LCY | C69: =SUM(E69:BL69) | E69: =Cohort_T3!E$198 | F69: =Cohort_T3!F$198 | G69: =Cohort_T3!G$198 | H69: =Cohort_T3!H$198 | I69: =Cohort_T3!I$198 | J69: =Cohort_T3!J$198 | K69: =Cohort_T3!K$198 | L69: =Cohort_T3!L$198 | ... BL69: =Cohort_T3!BL$198
A70: RBF received | B70: LCY | C70: =SUM(E70:BL70) | E70: =IF(E$4-Inputs!$C$33>=1,INDEX($E$59:$BL$59,1,E$4-Inputs!$C$33),0)*Products!$E$30*Timeline!E$8*Inputs!$C$32 | F70: =IF(F$4-Inputs!$C$33>=1,INDEX($E$59:$BL$59,1,F$4-Inputs!$C$33),0)*Products!$E$30*Timeline!F$8*Inputs!$C$32 | G70: =IF(G$4-Inputs!$C$33>=1,INDEX($E$59:$BL$59,1,G$4-Inputs!$C$33),0)*Products!$E$30*Timeline!G$8*Inputs!$C$32 | H70: =IF(H$4-Inputs!$C$33>=1,INDEX($E$59:$BL$59,1,H$4-Inputs!$C$33),0)*Products!$E$30*Timeline!H$8*Inputs!$C$32 | I70: =IF(I$4-Inputs!$C$33>=1,INDEX($E$59:$BL$59,1,I$4-Inputs!$C$33),0)*Products!$E$30*Timeline!I$8*Inputs!$C$32 | J70: =IF(J$4-Inputs!$C$33>=1,INDEX($E$59:$BL$59,1,J$4-Inputs!$C$33),0)*Products!$E$30*Timeline!J$8*Inputs!$C$32 | K70: =IF(K$4-Inputs!$C$33>=1,INDEX($E$59:$BL$59,1,K$4-Inputs!$C$33),0)*Products!$E$30*Timeline!K$8*Inputs!$C$32 | L70: =IF(L$4-Inputs!$C$33>=1,INDEX($E$59:$BL$59,1,L$4-Inputs!$C$33),0)*Products!$E$30*Timeline!L$8*Inputs!$C$32 | ... BL70: =IF(BL$4-Inputs!$C$33>=1,INDEX($E$59:$BL$59,1,BL$4-Inputs!$C$33),0)*Products!$E$30*Timeline!BL$8*Inputs!$C$32
A71: Active (paying, in-tenor) accounts | B71: accounts | C71: =BL71 | E71: =Cohort_T3!E$72 | F71: =Cohort_T3!F$72 | G71: =Cohort_T3!G$72 | H71: =Cohort_T3!H$72 | I71: =Cohort_T3!I$72 | J71: =Cohort_T3!J$72 | K71: =Cohort_T3!K$72 | L71: =Cohort_T3!L$72 | ... BL71: =Cohort_T3!BL$72
A72: Accounts reaching end of tenor (unlocked) | B72: accounts | C72: =SUM(E72:BL72) | E72: =IF(E$4>Products!$E$16,INDEX($E$59:$BL$59,1,E$4-Products!$E$16)*INDEX(Curves!$Z$8:$Z$68,Products!$E$16+1),0) | F72: =IF(F$4>Products!$E$16,INDEX($E$59:$BL$59,1,F$4-Products!$E$16)*INDEX(Curves!$Z$8:$Z$68,Products!$E$16+1),0) | G72: =IF(G$4>Products!$E$16,INDEX($E$59:$BL$59,1,G$4-Products!$E$16)*INDEX(Curves!$Z$8:$Z$68,Products!$E$16+1),0) | H72: =IF(H$4>Products!$E$16,INDEX($E$59:$BL$59,1,H$4-Products!$E$16)*INDEX(Curves!$Z$8:$Z$68,Products!$E$16+1),0) | I72: =IF(I$4>Products!$E$16,INDEX($E$59:$BL$59,1,I$4-Products!$E$16)*INDEX(Curves!$Z$8:$Z$68,Products!$E$16+1),0) | J72: =IF(J$4>Products!$E$16,INDEX($E$59:$BL$59,1,J$4-Products!$E$16)*INDEX(Curves!$Z$8:$Z$68,Products!$E$16+1),0) | K72: =IF(K$4>Products!$E$16,INDEX($E$59:$BL$59,1,K$4-Products!$E$16)*INDEX(Curves!$Z$8:$Z$68,Products!$E$16+1),0) | L72: =IF(L$4>Products!$E$16,INDEX($E$59:$BL$59,1,L$4-Products!$E$16)*INDEX(Curves!$Z$8:$Z$68,Products!$E$16+1),0) | ... BL72: =IF(BL$4>Products!$E$16,INDEX($E$59:$BL$59,1,BL$4-Products!$E$16)*INDEX(Curves!$Z$8:$Z$68,Products!$E$16+1),0)
A73: Receivables at risk (carrying amount, accounts that stopped paying) | B73: LCY | C73: =BL73 | E73: =Cohort_T3!E$135 | F73: =Cohort_T3!F$135 | G73: =Cohort_T3!G$135 | H73: =Cohort_T3!H$135 | I73: =Cohort_T3!I$135 | J73: =Cohort_T3!J$135 | K73: =Cohort_T3!K$135 | L73: =Cohort_T3!L$135 | ... BL73: =Cohort_T3!BL$135
A74: Gross PAYGo receivables (closing) | B74: LCY | C74: =BL74 | E74: =D74+E63+E67-E65-E66 | F74: =E74+F63+F67-F65-F66 | G74: =F74+G63+G67-G65-G66 | H74: =G74+H63+H67-H65-H66 | I74: =H74+I63+I67-I65-I66 | J74: =I74+J63+J67-J65-J66 | K74: =J74+K63+K67-K65-K66 | L74: =K74+L63+L67-L65-L66 | ... BL74: =BK74+BL63+BL67-BL65-BL66
A75: Eligible receivables (gross - at risk) | B75: LCY | C75: =BL75 | E75: =MAX(0,E74-E73) | F75: =MAX(0,F74-F73) | G75: =MAX(0,G74-G73) | H75: =MAX(0,H74-H73) | I75: =MAX(0,I74-I73) | J75: =MAX(0,J74-J73) | K75: =MAX(0,K74-K73) | L75: =MAX(0,L74-L73) | ... BL75: =MAX(0,BL74-BL73)
A76: Borrowing-base contribution (advance rate x eligible) | B76: LCY | C76: =BL76 | E76: =E75*Products!$E$31 | F76: =F75*Products!$E$31 | G76: =G75*Products!$E$31 | H76: =H75*Products!$E$31 | I76: =I75*Products!$E$31 | J76: =J75*Products!$E$31 | K76: =K75*Products!$E$31 | L76: =L75*Products!$E$31 | ... BL76: =BL75*Products!$E$31
A77: Landed hardware cost of units sold | B77: LCY | C77: =SUM(E77:BL77) | E77: =E59*Products!$E$18*(1+Inputs!$C$28)*Timeline!E$8*Scenarios!$G$9 | F77: =F59*Products!$E$18*(1+Inputs!$C$28)*Timeline!F$8*Scenarios!$G$9 | G77: =G59*Products!$E$18*(1+Inputs!$C$28)*Timeline!G$8*Scenarios!$G$9 | H77: =H59*Products!$E$18*(1+Inputs!$C$28)*Timeline!H$8*Scenarios!$G$9 | I77: =I59*Products!$E$18*(1+Inputs!$C$28)*Timeline!I$8*Scenarios!$G$9 | J77: =J59*Products!$E$18*(1+Inputs!$C$28)*Timeline!J$8*Scenarios!$G$9 | K77: =K59*Products!$E$18*(1+Inputs!$C$28)*Timeline!K$8*Scenarios!$G$9 | L77: =L59*Products!$E$18*(1+Inputs!$C$28)*Timeline!L$8*Scenarios!$G$9 | ... BL77: =BL59*Products!$E$18*(1+Inputs!$C$28)*Timeline!BL$8*Scenarios!$G$9
A78: Installation & logistics | B78: LCY | C78: =SUM(E78:BL78) | E78: =E59*Products!$E$19*Timeline!E$9 | F78: =F59*Products!$E$19*Timeline!F$9 | G78: =G59*Products!$E$19*Timeline!G$9 | H78: =H59*Products!$E$19*Timeline!H$9 | I78: =I59*Products!$E$19*Timeline!I$9 | J78: =J59*Products!$E$19*Timeline!J$9 | K78: =K59*Products!$E$19*Timeline!K$9 | L78: =L59*Products!$E$19*Timeline!L$9 | ... BL78: =BL59*Products!$E$19*Timeline!BL$9
A79: Warranty & after-sales provision | B79: LCY | C79: =SUM(E79:BL79) | E79: =E77*Products!$E$22 | F79: =F77*Products!$E$22 | G79: =G77*Products!$E$22 | H79: =H77*Products!$E$22 | I79: =I77*Products!$E$22 | J79: =J77*Products!$E$22 | K79: =K77*Products!$E$22 | L79: =L77*Products!$E$22 | ... BL79: =BL77*Products!$E$22
A80: Commissions | B80: LCY | C80: =SUM(E80:BL80) | E80: =E59*Products!$E$20*Timeline!E$9 | F80: =F59*Products!$E$20*Timeline!F$9 | G80: =G59*Products!$E$20*Timeline!G$9 | H80: =H59*Products!$E$20*Timeline!H$9 | I80: =I59*Products!$E$20*Timeline!I$9 | J80: =J59*Products!$E$20*Timeline!J$9 | K80: =K59*Products!$E$20*Timeline!K$9 | L80: =L59*Products!$E$20*Timeline!L$9 | ... BL80: =BL59*Products!$E$20*Timeline!BL$9
A81: Marketing & acquisition | B81: LCY | C81: =SUM(E81:BL81) | E81: =E59*Products!$E$21*Timeline!E$9 | F81: =F59*Products!$E$21*Timeline!F$9 | G81: =G59*Products!$E$21*Timeline!G$9 | H81: =H59*Products!$E$21*Timeline!H$9 | I81: =I59*Products!$E$21*Timeline!I$9 | J81: =J59*Products!$E$21*Timeline!J$9 | K81: =K59*Products!$E$21*Timeline!K$9 | L81: =L59*Products!$E$21*Timeline!L$9 | ... BL81: =BL59*Products!$E$21*Timeline!BL$9
A83: =Products!$F$6
A84: Units sold | B84: units | C84: =SUM(E84:BL84) | E84: =Timeline!E$11*Products!$F$23 | F84: =Timeline!F$11*Products!$F$23 | G84: =Timeline!G$11*Products!$F$23 | H84: =Timeline!H$11*Products!$F$23 | I84: =Timeline!I$11*Products!$F$23 | J84: =Timeline!J$11*Products!$F$23 | K84: =Timeline!K$11*Products!$F$23 | L84: =Timeline!L$11*Products!$F$23 | ... BL84: =Timeline!BL$11*Products!$F$23
A85: Price-indexed units (units x price index) | B85: units | C85: =SUM(E85:BL85) | E85: =E84*Timeline!E$10 | F85: =F84*Timeline!F$10 | G85: =G84*Timeline!G$10 | H85: =H84*Timeline!H$10 | I85: =I84*Timeline!I$10 | J85: =J84*Timeline!J$10 | K85: =K84*Timeline!K$10 | L85: =L84*Timeline!L$10 | ... BL85: =BL84*Timeline!BL$10
A86: Down payments collected | B86: LCY | C86: =SUM(E86:BL86) | E86: =E85*Products!$F$14 | F86: =F85*Products!$F$14 | G86: =G85*Products!$F$14 | H86: =H85*Products!$F$14 | I86: =I85*Products!$F$14 | J86: =J85*Products!$F$14 | K86: =K85*Products!$F$14 | L86: =L85*Products!$F$14 | ... BL86: =BL85*Products!$F$14
A87: Hardware revenue (cash price) | B87: LCY | C87: =SUM(E87:BL87) | E87: =E85*Products!$F$13 | F87: =F85*Products!$F$13 | G87: =G85*Products!$F$13 | H87: =H85*Products!$F$13 | I87: =I85*Products!$F$13 | J87: =J85*Products!$F$13 | K87: =K85*Products!$F$13 | L87: =L85*Products!$F$13 | ... BL87: =BL85*Products!$F$13
A88: New PAYGo receivables originated | B88: LCY | C88: =SUM(E88:BL88) | E88: =E85*Products!$F$38 | F88: =F85*Products!$F$38 | G88: =G85*Products!$F$38 | H88: =H85*Products!$F$38 | I88: =I85*Products!$F$38 | J88: =J85*Products!$F$38 | K88: =K85*Products!$F$38 | L88: =L85*Products!$F$38 | ... BL88: =BL85*Products!$F$38
A89: Instalments due | B89: LCY | C89: =SUM(E89:BL89) | E89: =Products!$F$33*SUMIFS($E$85:$BL$85,Timeline!$E$4:$BL$4,">="&(E$4-Products!$F$16),Timeline!$E$4:$BL$4,"<="&(E$4-1)) | F89: =Products!$F$33*SUMIFS($E$85:$BL$85,Timeline!$E$4:$BL$4,">="&(F$4-Products!$F$16),Timeline!$E$4:$BL$4,"<="&(F$4-1)) | G89: =Products!$F$33*SUMIFS($E$85:$BL$85,Timeline!$E$4:$BL$4,">="&(G$4-Products!$F$16),Timeline!$E$4:$BL$4,"<="&(G$4-1)) | H89: =Products!$F$33*SUMIFS($E$85:$BL$85,Timeline!$E$4:$BL$4,">="&(H$4-Products!$F$16),Timeline!$E$4:$BL$4,"<="&(H$4-1)) | I89: =Products!$F$33*SUMIFS($E$85:$BL$85,Timeline!$E$4:$BL$4,">="&(I$4-Products!$F$16),Timeline!$E$4:$BL$4,"<="&(I$4-1)) | J89: =Products!$F$33*SUMIFS($E$85:$BL$85,Timeline!$E$4:$BL$4,">="&(J$4-Products!$F$16),Timeline!$E$4:$BL$4,"<="&(J$4-1)) | K89: =Products!$F$33*SUMIFS($E$85:$BL$85,Timeline!$E$4:$BL$4,">="&(K$4-Products!$F$16),Timeline!$E$4:$BL$4,"<="&(K$4-1)) | L89: =Products!$F$33*SUMIFS($E$85:$BL$85,Timeline!$E$4:$BL$4,">="&(L$4-Products!$F$16),Timeline!$E$4:$BL$4,"<="&(L$4-1)) | ... BL89: =Products!$F$33*SUMIFS($E$85:$BL$85,Timeline!$E$4:$BL$4,">="&(BL$4-Products!$F$16),Timeline!$E$4:$BL$4,"<="&(BL$4-1))
A90: Instalments collected | B90: LCY | C90: =SUM(E90:BL90) | E90: =Cohort_T4!E$9 | F90: =Cohort_T4!F$9 | G90: =Cohort_T4!G$9 | H90: =Cohort_T4!H$9 | I90: =Cohort_T4!I$9 | J90: =Cohort_T4!J$9 | K90: =Cohort_T4!K$9 | L90: =Cohort_T4!L$9 | ... BL90: =Cohort_T4!BL$9
A91: Missed instalments written off | B91: LCY | C91: =SUM(E91:BL91) | E91: =E89-E90 | F91: =F89-F90 | G91: =G89-G90 | H91: =H89-H90 | I91: =I89-I90 | J91: =J89-J90 | K91: =K89-K90 | L91: =L89-L90 | ... BL91: =BL89-BL90
A92: PAYGo financing income (straight-line over tenor) | B92: LCY | C92: =SUM(E92:BL92) | E92: =IF(Products!$F$16=0,0,Products!$F$35/Products!$F$16*SUMIFS($E$85:$BL$85,Timeline!$E$4:$BL$4,">="&(E$4-Products!$F$16),Timeline!$E$4:$BL$4,"<="&(E$4-1))) | F92: =IF(Products!$F$16=0,0,Products!$F$35/Products!$F$16*SUMIFS($E$85:$BL$85,Timeline!$E$4:$BL$4,">="&(F$4-Products!$F$16),Timeline!$E$4:$BL$4,"<="&(F$4-1))) | G92: =IF(Products!$F$16=0,0,Products!$F$35/Products!$F$16*SUMIFS($E$85:$BL$85,Timeline!$E$4:$BL$4,">="&(G$4-Products!$F$16),Timeline!$E$4:$BL$4,"<="&(G$4-1))) | H92: =IF(Products!$F$16=0,0,Products!$F$35/Products!$F$16*SUMIFS($E$85:$BL$85,Timeline!$E$4:$BL$4,">="&(H$4-Products!$F$16),Timeline!$E$4:$BL$4,"<="&(H$4-1))) | I92: =IF(Products!$F$16=0,0,Products!$F$35/Products!$F$16*SUMIFS($E$85:$BL$85,Timeline!$E$4:$BL$4,">="&(I$4-Products!$F$16),Timeline!$E$4:$BL$4,"<="&(I$4-1))) | J92: =IF(Products!$F$16=0,0,Products!$F$35/Products!$F$16*SUMIFS($E$85:$BL$85,Timeline!$E$4:$BL$4,">="&(J$4-Products!$F$16),Timeline!$E$4:$BL$4,"<="&(J$4-1))) | K92: =IF(Products!$F$16=0,0,Products!$F$35/Products!$F$16*SUMIFS($E$85:$BL$85,Timeline!$E$4:$BL$4,">="&(K$4-Products!$F$16),Timeline!$E$4:$BL$4,"<="&(K$4-1))) | L92: =IF(Products!$F$16=0,0,Products!$F$35/Products!$F$16*SUMIFS($E$85:$BL$85,Timeline!$E$4:$BL$4,">="&(L$4-Products!$F$16),Timeline!$E$4:$BL$4,"<="&(L$4-1))) | ... BL92: =IF(Products!$F$16=0,0,Products!$F$35/Products!$F$16*SUMIFS($E$85:$BL$85,Timeline!$E$4:$BL$4,">="&(BL$4-Products!$F$16),Timeline!$E$4:$BL$4,"<="&(BL$4-1)))
A93: Expected credit loss charged at origination | B93: LCY | C93: =SUM(E93:BL93) | E93: =E85*Curves!$AO$70 | F93: =F85*Curves!$AO$70 | G93: =G85*Curves!$AO$70 | H93: =H85*Curves!$AO$70 | I93: =I85*Curves!$AO$70 | J93: =J85*Curves!$AO$70 | K93: =K85*Curves!$AO$70 | L93: =L85*Curves!$AO$70 | ... BL93: =BL85*Curves!$AO$70
A94: Recoveries from resale of repossessed units | B94: LCY | C94: =SUM(E94:BL94) | E94: =Cohort_T4!E$198 | F94: =Cohort_T4!F$198 | G94: =Cohort_T4!G$198 | H94: =Cohort_T4!H$198 | I94: =Cohort_T4!I$198 | J94: =Cohort_T4!J$198 | K94: =Cohort_T4!K$198 | L94: =Cohort_T4!L$198 | ... BL94: =Cohort_T4!BL$198
A95: RBF received | B95: LCY | C95: =SUM(E95:BL95) | E95: =IF(E$4-Inputs!$C$33>=1,INDEX($E$84:$BL$84,1,E$4-Inputs!$C$33),0)*Products!$F$30*Timeline!E$8*Inputs!$C$32 | F95: =IF(F$4-Inputs!$C$33>=1,INDEX($E$84:$BL$84,1,F$4-Inputs!$C$33),0)*Products!$F$30*Timeline!F$8*Inputs!$C$32 | G95: =IF(G$4-Inputs!$C$33>=1,INDEX($E$84:$BL$84,1,G$4-Inputs!$C$33),0)*Products!$F$30*Timeline!G$8*Inputs!$C$32 | H95: =IF(H$4-Inputs!$C$33>=1,INDEX($E$84:$BL$84,1,H$4-Inputs!$C$33),0)*Products!$F$30*Timeline!H$8*Inputs!$C$32 | I95: =IF(I$4-Inputs!$C$33>=1,INDEX($E$84:$BL$84,1,I$4-Inputs!$C$33),0)*Products!$F$30*Timeline!I$8*Inputs!$C$32 | J95: =IF(J$4-Inputs!$C$33>=1,INDEX($E$84:$BL$84,1,J$4-Inputs!$C$33),0)*Products!$F$30*Timeline!J$8*Inputs!$C$32 | K95: =IF(K$4-Inputs!$C$33>=1,INDEX($E$84:$BL$84,1,K$4-Inputs!$C$33),0)*Products!$F$30*Timeline!K$8*Inputs!$C$32 | L95: =IF(L$4-Inputs!$C$33>=1,INDEX($E$84:$BL$84,1,L$4-Inputs!$C$33),0)*Products!$F$30*Timeline!L$8*Inputs!$C$32 | ... BL95: =IF(BL$4-Inputs!$C$33>=1,INDEX($E$84:$BL$84,1,BL$4-Inputs!$C$33),0)*Products!$F$30*Timeline!BL$8*Inputs!$C$32
A96: Active (paying, in-tenor) accounts | B96: accounts | C96: =BL96 | E96: =Cohort_T4!E$72 | F96: =Cohort_T4!F$72 | G96: =Cohort_T4!G$72 | H96: =Cohort_T4!H$72 | I96: =Cohort_T4!I$72 | J96: =Cohort_T4!J$72 | K96: =Cohort_T4!K$72 | L96: =Cohort_T4!L$72 | ... BL96: =Cohort_T4!BL$72
A97: Accounts reaching end of tenor (unlocked) | B97: accounts | C97: =SUM(E97:BL97) | E97: =IF(E$4>Products!$F$16,INDEX($E$84:$BL$84,1,E$4-Products!$F$16)*INDEX(Curves!$AL$8:$AL$68,Products!$F$16+1),0) | F97: =IF(F$4>Products!$F$16,INDEX($E$84:$BL$84,1,F$4-Products!$F$16)*INDEX(Curves!$AL$8:$AL$68,Products!$F$16+1),0) | G97: =IF(G$4>Products!$F$16,INDEX($E$84:$BL$84,1,G$4-Products!$F$16)*INDEX(Curves!$AL$8:$AL$68,Products!$F$16+1),0) | H97: =IF(H$4>Products!$F$16,INDEX($E$84:$BL$84,1,H$4-Products!$F$16)*INDEX(Curves!$AL$8:$AL$68,Products!$F$16+1),0) | I97: =IF(I$4>Products!$F$16,INDEX($E$84:$BL$84,1,I$4-Products!$F$16)*INDEX(Curves!$AL$8:$AL$68,Products!$F$16+1),0) | J97: =IF(J$4>Products!$F$16,INDEX($E$84:$BL$84,1,J$4-Products!$F$16)*INDEX(Curves!$AL$8:$AL$68,Products!$F$16+1),0) | K97: =IF(K$4>Products!$F$16,INDEX($E$84:$BL$84,1,K$4-Products!$F$16)*INDEX(Curves!$AL$8:$AL$68,Products!$F$16+1),0) | L97: =IF(L$4>Products!$F$16,INDEX($E$84:$BL$84,1,L$4-Products!$F$16)*INDEX(Curves!$AL$8:$AL$68,Products!$F$16+1),0) | ... BL97: =IF(BL$4>Products!$F$16,INDEX($E$84:$BL$84,1,BL$4-Products!$F$16)*INDEX(Curves!$AL$8:$AL$68,Products!$F$16+1),0)
A98: Receivables at risk (carrying amount, accounts that stopped paying) | B98: LCY | C98: =BL98 | E98: =Cohort_T4!E$135 | F98: =Cohort_T4!F$135 | G98: =Cohort_T4!G$135 | H98: =Cohort_T4!H$135 | I98: =Cohort_T4!I$135 | J98: =Cohort_T4!J$135 | K98: =Cohort_T4!K$135 | L98: =Cohort_T4!L$135 | ... BL98: =Cohort_T4!BL$135
A99: Gross PAYGo receivables (closing) | B99: LCY | C99: =BL99 | E99: =D99+E88+E92-E90-E91 | F99: =E99+F88+F92-F90-F91 | G99: =F99+G88+G92-G90-G91 | H99: =G99+H88+H92-H90-H91 | I99: =H99+I88+I92-I90-I91 | J99: =I99+J88+J92-J90-J91 | K99: =J99+K88+K92-K90-K91 | L99: =K99+L88+L92-L90-L91 | ... BL99: =BK99+BL88+BL92-BL90-BL91
A100: Eligible receivables (gross - at risk) | B100: LCY | C100: =BL100 | E100: =MAX(0,E99-E98) | F100: =MAX(0,F99-F98) | G100: =MAX(0,G99-G98) | H100: =MAX(0,H99-H98) | I100: =MAX(0,I99-I98) | J100: =MAX(0,J99-J98) | K100: =MAX(0,K99-K98) | L100: =MAX(0,L99-L98) | ... BL100: =MAX(0,BL99-BL98)
A101: Borrowing-base contribution (advance rate x eligible) | B101: LCY | C101: =BL101 | E101: =E100*Products!$F$31 | F101: =F100*Products!$F$31 | G101: =G100*Products!$F$31 | H101: =H100*Products!$F$31 | I101: =I100*Products!$F$31 | J101: =J100*Products!$F$31 | K101: =K100*Products!$F$31 | L101: =L100*Products!$F$31 | ... BL101: =BL100*Products!$F$31
A102: Landed hardware cost of units sold | B102: LCY | C102: =SUM(E102:BL102) | E102: =E84*Products!$F$18*(1+Inputs!$C$28)*Timeline!E$8*Scenarios!$G$9 | F102: =F84*Products!$F$18*(1+Inputs!$C$28)*Timeline!F$8*Scenarios!$G$9 | G102: =G84*Products!$F$18*(1+Inputs!$C$28)*Timeline!G$8*Scenarios!$G$9 | H102: =H84*Products!$F$18*(1+Inputs!$C$28)*Timeline!H$8*Scenarios!$G$9 | I102: =I84*Products!$F$18*(1+Inputs!$C$28)*Timeline!I$8*Scenarios!$G$9 | J102: =J84*Products!$F$18*(1+Inputs!$C$28)*Timeline!J$8*Scenarios!$G$9 | K102: =K84*Products!$F$18*(1+Inputs!$C$28)*Timeline!K$8*Scenarios!$G$9 | L102: =L84*Products!$F$18*(1+Inputs!$C$28)*Timeline!L$8*Scenarios!$G$9 | ... BL102: =BL84*Products!$F$18*(1+Inputs!$C$28)*Timeline!BL$8*Scenarios!$G$9
A103: Installation & logistics | B103: LCY | C103: =SUM(E103:BL103) | E103: =E84*Products!$F$19*Timeline!E$9 | F103: =F84*Products!$F$19*Timeline!F$9 | G103: =G84*Products!$F$19*Timeline!G$9 | H103: =H84*Products!$F$19*Timeline!H$9 | I103: =I84*Products!$F$19*Timeline!I$9 | J103: =J84*Products!$F$19*Timeline!J$9 | K103: =K84*Products!$F$19*Timeline!K$9 | L103: =L84*Products!$F$19*Timeline!L$9 | ... BL103: =BL84*Products!$F$19*Timeline!BL$9
A104: Warranty & after-sales provision | B104: LCY | C104: =SUM(E104:BL104) | E104: =E102*Products!$F$22 | F104: =F102*Products!$F$22 | G104: =G102*Products!$F$22 | H104: =H102*Products!$F$22 | I104: =I102*Products!$F$22 | J104: =J102*Products!$F$22 | K104: =K102*Products!$F$22 | L104: =L102*Products!$F$22 | ... BL104: =BL102*Products!$F$22
A105: Commissions | B105: LCY | C105: =SUM(E105:BL105) | E105: =E84*Products!$F$20*Timeline!E$9 | F105: =F84*Products!$F$20*Timeline!F$9 | G105: =G84*Products!$F$20*Timeline!G$9 | H105: =H84*Products!$F$20*Timeline!H$9 | I105: =I84*Products!$F$20*Timeline!I$9 | J105: =J84*Products!$F$20*Timeline!J$9 | K105: =K84*Products!$F$20*Timeline!K$9 | L105: =L84*Products!$F$20*Timeline!L$9 | ... BL105: =BL84*Products!$F$20*Timeline!BL$9
...

Sheet Costs
A1: Operating costs, working capital & capex
A2: LCY
A4: Month # | D4: Opening | E4: =Timeline!E4 | F4: =Timeline!F4 | G4: =Timeline!G4 | H4: =Timeline!H4 | I4: =Timeline!I4 | J4: =Timeline!J4 | K4: =Timeline!K4 | L4: =Timeline!L4 | ... BL4: =Timeline!BL4
A5: Period end | E5: =Timeline!E5 | F5: =Timeline!F5 | G5: =Timeline!G5 | H5: =Timeline!H5 | I5: =Timeline!I5 | J5: =Timeline!J5 | K5: =Timeline!K5 | L5: =Timeline!L5 | ... BL5: =Timeline!BL5
A6: Year # | E6: =Timeline!E6 | F6: =Timeline!F6 | G6: =Timeline!G6 | H6: =Timeline!H6 | I6: =Timeline!I6 | J6: =Timeline!J6 | K6: =Timeline!K6 | L6: =Timeline!L6 | ... BL6: =Timeline!BL6
A8: Landed hardware cost (COGS) | B8: LCY | C8: =SUM(E8:BL8) | E8: =Ops!E$152 | F8: =Ops!F$152 | G8: =Ops!G$152 | H8: =Ops!H$152 | I8: =Ops!I$152 | J8: =Ops!J$152 | K8: =Ops!K$152 | L8: =Ops!L$152 | ... BL8: =Ops!BL$152
A9: Installation & logistics (cost of sales) | B9: LCY | C9: =SUM(E9:BL9) | E9: =Ops!E$153 | F9: =Ops!F$153 | G9: =Ops!G$153 | H9: =Ops!H$153 | I9: =Ops!I$153 | J9: =Ops!J$153 | K9: =Ops!K$153 | L9: =Ops!L$153 | ... BL9: =Ops!BL$153
A10: Total cost of sales | B10: LCY | C10: =SUM(E10:BL10) | E10: =E8+E9 | F10: =F8+F9 | G10: =G8+G9 | H10: =H8+H9 | I10: =I8+I9 | J10: =J8+J9 | K10: =K8+K9 | L10: =L8+L9 | ... BL10: =BL8+BL9
A12: Warranty & after-sales | B12: LCY | C12: =SUM(E12:BL12) | E12: =Ops!E$154 | F12: =Ops!F$154 | G12: =Ops!G$154 | H12: =Ops!H$154 | I12: =Ops!I$154 | J12: =Ops!J$154 | K12: =Ops!K$154 | L12: =Ops!L$154 | ... BL12: =Ops!BL$154
A13: Agent / installer commissions | B13: LCY | C13: =SUM(E13:BL13) | E13: =Ops!E$155 | F13: =Ops!F$155 | G13: =Ops!G$155 | H13: =Ops!H$155 | I13: =Ops!I$155 | J13: =Ops!J$155 | K13: =Ops!K$155 | L13: =Ops!L$155 | ... BL13: =Ops!BL$155
A14: Marketing & acquisition | B14: LCY | C14: =SUM(E14:BL14) | E14: =Ops!E$156 | F14: =Ops!F$156 | G14: =Ops!G$156 | H14: =Ops!H$156 | I14: =Ops!I$156 | J14: =Ops!J$156 | K14: =Ops!K$156 | L14: =Ops!L$156 | ... BL14: =Ops!BL$156
A15: Payment processing fees | B15: LCY | C15: =SUM(E15:BL15) | E15: =(Ops!E$136+Ops!E$140)*Inputs!$C$24 | F15: =(Ops!F$136+Ops!F$140)*Inputs!$C$24 | G15: =(Ops!G$136+Ops!G$140)*Inputs!$C$24 | H15: =(Ops!H$136+Ops!H$140)*Inputs!$C$24 | I15: =(Ops!I$136+Ops!I$140)*Inputs!$C$24 | J15: =(Ops!J$136+Ops!J$140)*Inputs!$C$24 | K15: =(Ops!K$136+Ops!K$140)*Inputs!$C$24 | L15: =(Ops!L$136+Ops!L$140)*Inputs!$C$24 | ... BL15: =(Ops!BL$136+Ops!BL$140)*Inputs!$C$24
A16: Customer service & collections | B16: LCY | C16: =SUM(E16:BL16) | E16: =Ops!E$146*Inputs!$C$25*Timeline!E$9 | F16: =Ops!F$146*Inputs!$C$25*Timeline!F$9 | G16: =Ops!G$146*Inputs!$C$25*Timeline!G$9 | H16: =Ops!H$146*Inputs!$C$25*Timeline!H$9 | I16: =Ops!I$146*Inputs!$C$25*Timeline!I$9 | J16: =Ops!J$146*Inputs!$C$25*Timeline!J$9 | K16: =Ops!K$146*Inputs!$C$25*Timeline!K$9 | L16: =Ops!L$146*Inputs!$C$25*Timeline!L$9 | ... BL16: =Ops!BL$146*Inputs!$C$25*Timeline!BL$9
A17: Staff | B17: LCY | C17: =SUM(E17:BL17) | E17: =Inputs!$C$26*Timeline!E$9 | F17: =Inputs!$C$26*Timeline!F$9 | G17: =Inputs!$C$26*Timeline!G$9 | H17: =Inputs!$C$26*Timeline!H$9 | I17: =Inputs!$C$26*Timeline!I$9 | J17: =Inputs!$C$26*Timeline!J$9 | K17: =Inputs!$C$26*Timeline!K$9 | L17: =Inputs!$C$26*Timeline!L$9 | ... BL17: =Inputs!$C$26*Timeline!BL$9
A18: G&A, rent, IT | B18: LCY | C18: =SUM(E18:BL18) | E18: =Inputs!$C$27*Timeline!E$9 | F18: =Inputs!$C$27*Timeline!F$9 | G18: =Inputs!$C$27*Timeline!G$9 | H18: =Inputs!$C$27*Timeline!H$9 | I18: =Inputs!$C$27*Timeline!I$9 | J18: =Inputs!$C$27*Timeline!J$9 | K18: =Inputs!$C$27*Timeline!K$9 | L18: =Inputs!$C$27*Timeline!L$9 | ... BL18: =Inputs!$C$27*Timeline!BL$9
A19: Total operating expenses | B19: LCY | C19: =SUM(E19:BL19) | E19: =SUM(E12:E18) | F19: =SUM(F12:F18) | G19: =SUM(G12:G18) | H19: =SUM(H12:H18) | I19: =SUM(I12:I18) | J19: =SUM(J12:J18) | K19: =SUM(K12:K18) | L19: =SUM(L12:L18) | ... BL19: =SUM(BL12:BL18)
A21: Inventory (closing) | B21: LCY | C21: =BL21 | E21: =E8*Inputs!$C$36 | F21: =F8*Inputs!$C$36 | G21: =G8*Inputs!$C$36 | H21: =H8*Inputs!$C$36 | I21: =I8*Inputs!$C$36 | J21: =J8*Inputs!$C$36 | K21: =K8*Inputs!$C$36 | L21: =L8*Inputs!$C$36 | ... BL21: =BL8*Inputs!$C$36
A22: Hardware purchases | B22: LCY | C22: =SUM(E22:BL22) | E22: =E8+E21-D21 | F22: =F8+F21-E21 | G22: =G8+G21-F21 | H22: =H8+H21-G21 | I22: =I8+I21-H21 | J22: =J8+J21-I21 | K22: =K8+K21-J21 | L22: =L8+L21-K21 | ... BL22: =BL8+BL21-BK21
A23: Supplier payables (closing) | B23: LCY | C23: =BL23 | E23: =E22*Inputs!$C$37/(365/12) | F23: =F22*Inputs!$C$37/(365/12) | G23: =G22*Inputs!$C$37/(365/12) | H23: =H22*Inputs!$C$37/(365/12) | I23: =I22*Inputs!$C$37/(365/12) | J23: =J22*Inputs!$C$37/(365/12) | K23: =K22*Inputs!$C$37/(365/12) | L23: =L22*Inputs!$C$37/(365/12) | ... BL23: =BL22*Inputs!$C$37/(365/12)
A25: Fixed capex | B25: LCY | C25: =SUM(E25:BL25) | E25: =Inputs!$C$38*Timeline!E$9 | F25: =Inputs!$C$38*Timeline!F$9 | G25: =Inputs!$C$38*Timeline!G$9 | H25: =Inputs!$C$38*Timeline!H$9 | I25: =Inputs!$C$38*Timeline!I$9 | J25: =Inputs!$C$38*Timeline!J$9 | K25: =Inputs!$C$38*Timeline!K$9 | L25: =Inputs!$C$38*Timeline!L$9 | ... BL25: =Inputs!$C$38*Timeline!BL$9
A26: Depreciation (straight-line by vintage) | B26: LCY | C26: =SUM(E26:BL26) | E26: =SUMIFS($E25:E25,$E$4:E$4,">"&(E$4-Inputs!$C$39))/Inputs!$C$39 | F26: =SUMIFS($E25:F25,$E$4:F$4,">"&(F$4-Inputs!$C$39))/Inputs!$C$39 | G26: =SUMIFS($E25:G25,$E$4:G$4,">"&(G$4-Inputs!$C$39))/Inputs!$C$39 | H26: =SUMIFS($E25:H25,$E$4:H$4,">"&(H$4-Inputs!$C$39))/Inputs!$C$39 | I26: =SUMIFS($E25:I25,$E$4:I$4,">"&(I$4-Inputs!$C$39))/Inputs!$C$39 | J26: =SUMIFS($E25:J25,$E$4:J$4,">"&(J$4-Inputs!$C$39))/Inputs!$C$39 | K26: =SUMIFS($E25:K25,$E$4:K$4,">"&(K$4-Inputs!$C$39))/Inputs!$C$39 | L26: =SUMIFS($E25:L25,$E$4:L$4,">"&(L$4-Inputs!$C$39))/Inputs!$C$39 | ... BL26: =SUMIFS($E25:BL25,$E$4:BL$4,">"&(BL$4-Inputs!$C$39))/Inputs!$C$39
A27: Net fixed assets (closing) | B27: LCY | C27: =BL27 | E27: =D27+E25-E26 | F27: =E27+F25-F26 | G27: =F27+G25-G26 | H27: =G27+H25-H26 | I27: =H27+I25-I26 | J27: =I27+J25-J26 | K27: =J27+K25-K26 | L27: =K27+L25-L26 | ... BL27: =BK27+BL25-BL26

Sheet Financing
A1: Financing
A2: Equity, USD term loan with FX translation, receivables-backed facility
A4: Month # | D4: Opening | E4: =Timeline!E4 | F4: =Timeline!F4 | G4: =Timeline!G4 | H4: =Timeline!H4 | I4: =Timeline!I4 | J4: =Timeline!J4 | K4: =Timeline!K4 | L4: =Timeline!L4 | ... BL4: =Timeline!BL4
A5: Period end | E5: =Timeline!E5 | F5: =Timeline!F5 | G5: =Timeline!G5 | H5: =Timeline!H5 | I5: =Timeline!I5 | J5: =Timeline!J5 | K5: =Timeline!K5 | L5: =Timeline!L5 | ... BL5: =Timeline!BL5
A6: Year # | E6: =Timeline!E6 | F6: =Timeline!F6 | G6: =Timeline!G6 | H6: =Timeline!H6 | I6: =Timeline!I6 | J6: =Timeline!J6 | K6: =Timeline!K6 | L6: =Timeline!L6 | ... BL6: =Timeline!BL6
A8: EQUITY
A9: Initial equity injection | B9: LCY | C9: =SUM(E9:BL9) | E9: =IF(E$4=1,Inputs!$C$43,0) | F9: =IF(F$4=1,Inputs!$C$43,0) | G9: =IF(G$4=1,Inputs!$C$43,0) | H9: =IF(H$4=1,Inputs!$C$43,0) | I9: =IF(I$4=1,Inputs!$C$43,0) | J9: =IF(J$4=1,Inputs!$C$43,0) | K9: =IF(K$4=1,Inputs!$C$43,0) | L9: =IF(L$4=1,Inputs!$C$43,0) | ... BL9: =IF(BL$4=1,Inputs!$C$43,0)
A10: Automatic equity top-up (funding requirement) | B10: LCY | C10: =SUM(E10:BL10) | E10: =FS!E$62 | F10: =FS!F$62 | G10: =FS!G$62 | H10: =FS!H$62 | I10: =FS!I$62 | J10: =FS!J$62 | K10: =FS!K$62 | L10: =FS!L$62 | ... BL10: =FS!BL$62
A11: Cumulative equity invested | B11: LCY | C11: =BL11 | E11: =D11+E9+E10 | F11: =E11+F9+F10 | G11: =F11+G9+G10 | H11: =G11+H9+H10 | I11: =H11+I9+I10 | J11: =I11+J9+J10 | K11: =J11+K9+K10 | L11: =K11+L9+L10 | ... BL11: =BK11+BL9+BL10
A12: USD TERM LOAN
A13: Drawdown (USD) | B13: USD | C13: =SUM(E13:BL13) | E13: =IF(E$4=Inputs!$C$45,Inputs!$C$44,0) | F13: =IF(F$4=Inputs!$C$45,Inputs!$C$44,0) | G13: =IF(G$4=Inputs!$C$45,Inputs!$C$44,0) | H13: =IF(H$4=Inputs!$C$45,Inputs!$C$44,0) | I13: =IF(I$4=Inputs!$C$45,Inputs!$C$44,0) | J13: =IF(J$4=Inputs!$C$45,Inputs!$C$44,0) | K13: =IF(K$4=Inputs!$C$45,Inputs!$C$44,0) | L13: =IF(L$4=Inputs!$C$45,Inputs!$C$44,0) | ... BL13: =IF(BL$4=Inputs!$C$45,Inputs!$C$44,0)
A14: Repayment (USD) | B14: USD | C14: =SUM(E14:BL14) | E14: =IF(AND(E$4>Inputs!$C$45+Inputs!$C$47,E$4<=Inputs!$C$45+Inputs!$C$47+Inputs!$C$48),MIN(D15,Inputs!$C$44/Inputs!$C$48),0) | F14: =IF(AND(F$4>Inputs!$C$45+Inputs!$C$47,F$4<=Inputs!$C$45+Inputs!$C$47+Inputs!$C$48),MIN(E15,Inputs!$C$44/Inputs!$C$48),0) | G14: =IF(AND(G$4>Inputs!$C$45+Inputs!$C$47,G$4<=Inputs!$C$45+Inputs!$C$47+Inputs!$C$48),MIN(F15,Inputs!$C$44/Inputs!$C$48),0) | H14: =IF(AND(H$4>Inputs!$C$45+Inputs!$C$47,H$4<=Inputs!$C$45+Inputs!$C$47+Inputs!$C$48),MIN(G15,Inputs!$C$44/Inputs!$C$48),0) | I14: =IF(AND(I$4>Inputs!$C$45+Inputs!$C$47,I$4<=Inputs!$C$45+Inputs!$C$47+Inputs!$C$48),MIN(H15,Inputs!$C$44/Inputs!$C$48),0) | J14: =IF(AND(J$4>Inputs!$C$45+Inputs!$C$47,J$4<=Inputs!$C$45+Inputs!$C$47+Inputs!$C$48),MIN(I15,Inputs!$C$44/Inputs!$C$48),0) | K14: =IF(AND(K$4>Inputs!$C$45+Inputs!$C$47,K$4<=Inputs!$C$45+Inputs!$C$47+Inputs!$C$48),MIN(J15,Inputs!$C$44/Inputs!$C$48),0) | L14: =IF(AND(L$4>Inputs!$C$45+Inputs!$C$47,L$4<=Inputs!$C$45+Inputs!$C$47+Inputs!$C$48),MIN(K15,Inputs!$C$44/Inputs!$C$48),0) | ... BL14: =IF(AND(BL$4>Inputs!$C$45+Inputs!$C$47,BL$4<=Inputs!$C$45+Inputs!$C$47+Inputs!$C$48),MIN(BK15,Inputs!$C$44/Inputs!$C$48),0)
A15: Closing balance (USD) | B15: USD | C15: =BL15 | E15: =D15+E13-E14 | F15: =E15+F13-F14 | G15: =F15+G13-G14 | H15: =G15+H13-H14 | I15: =H15+I13-I14 | J15: =I15+J13-J14 | K15: =J15+K13-K14 | L15: =K15+L13-L14 | ... BL15: =BK15+BL13-BL14
A16: Interest (LCY) | B16: LCY | C16: =SUM(E16:BL16) | E16: =D15*Inputs!$C$46/12*Timeline!E$8 | F16: =E15*Inputs!$C$46/12*Timeline!F$8 | G16: =F15*Inputs!$C$46/12*Timeline!G$8 | H16: =G15*Inputs!$C$46/12*Timeline!H$8 | I16: =H15*Inputs!$C$46/12*Timeline!I$8 | J16: =I15*Inputs!$C$46/12*Timeline!J$8 | K16: =J15*Inputs!$C$46/12*Timeline!K$8 | L16: =K15*Inputs!$C$46/12*Timeline!L$8 | ... BL16: =BK15*Inputs!$C$46/12*Timeline!BL$8
A17: Drawdown (LCY) | B17: LCY | C17: =SUM(E17:BL17) | E17: =E13*Timeline!E$8 | F17: =F13*Timeline!F$8 | G17: =G13*Timeline!G$8 | H17: =H13*Timeline!H$8 | I17: =I13*Timeline!I$8 | J17: =J13*Timeline!J$8 | K17: =K13*Timeline!K$8 | L17: =L13*Timeline!L$8 | ... BL17: =BL13*Timeline!BL$8
A18: Repayment (LCY) | B18: LCY | C18: =SUM(E18:BL18) | E18: =E14*Timeline!E$8 | F18: =F14*Timeline!F$8 | G18: =G14*Timeline!G$8 | H18: =H14*Timeline!H$8 | I18: =I14*Timeline!I$8 | J18: =J14*Timeline!J$8 | K18: =K14*Timeline!K$8 | L18: =L14*Timeline!L$8 | ... BL18: =BL14*Timeline!BL$8
A19: Closing balance (LCY) | B19: LCY | C19: =BL19 | E19: =E15*Timeline!E$8 | F19: =F15*Timeline!F$8 | G19: =G15*Timeline!G$8 | H19: =H15*Timeline!H$8 | I19: =I15*Timeline!I$8 | J19: =J15*Timeline!J$8 | K19: =K15*Timeline!K$8 | L19: =L15*Timeline!L$8 | ... BL19: =BL15*Timeline!BL$8
A20: Unrealised FX loss / (gain) on USD debt (LCY) | B20: LCY | C20: =SUM(E20:BL20) | E20: =D15*(Timeline!E$8-Timeline!D$8) | F20: =E15*(Timeline!F$8-Timeline!E$8) | G20: =F15*(Timeline!G$8-Timeline!F$8) | H20: =G15*(Timeline!H$8-Timeline!G$8) | I20: =H15*(Timeline!I$8-Timeline!H$8) | J20: =I15*(Timeline!J$8-Timeline!I$8) | K20: =J15*(Timeline!K$8-Timeline!J$8) | L20: =K15*(Timeline!L$8-Timeline!K$8) | ... BL20: =BK15*(Timeline!BL$8-Timeline!BK$8)
A21: RECEIVABLES FACILITY (LCY)
A22: Borrowing base (sum of tier contributions) | B22: LCY | C22: =BL22 | E22: =Ops!E$151 | F22: =Ops!F$151 | G22: =Ops!G$151 | H22: =Ops!H$151 | I22: =Ops!I$151 | J22: =Ops!J$151 | K22: =Ops!K$151 | L22: =Ops!L$151 | ... BL22: =Ops!BL$151
A23: Facility drawn (closing; cash sweep within borrowing base) | B23: LCY | C23: =BL23 | E23: =IF(E$4>=Inputs!$C$51,MAX(0,MIN(Inputs!$C$49,E22,D23+Inputs!$C$40-FS!E$60)),0) | F23: =IF(F$4>=Inputs!$C$51,MAX(0,MIN(Inputs!$C$49,F22,E23+Inputs!$C$40-FS!F$60)),0) | G23: =IF(G$4>=Inputs!$C$51,MAX(0,MIN(Inputs!$C$49,G22,F23+Inputs!$C$40-FS!G$60)),0) | H23: =IF(H$4>=Inputs!$C$51,MAX(0,MIN(Inputs!$C$49,H22,G23+Inputs!$C$40-FS!H$60)),0) | I23: =IF(I$4>=Inputs!$C$51,MAX(0,MIN(Inputs!$C$49,I22,H23+Inputs!$C$40-FS!I$60)),0) | J23: =IF(J$4>=Inputs!$C$51,MAX(0,MIN(Inputs!$C$49,J22,I23+Inputs!$C$40-FS!J$60)),0) | K23: =IF(K$4>=Inputs!$C$51,MAX(0,MIN(Inputs!$C$49,K22,J23+Inputs!$C$40-FS!K$60)),0) | L23: =IF(L$4>=Inputs!$C$51,MAX(0,MIN(Inputs!$C$49,L22,K23+Inputs!$C$40-FS!L$60)),0) | ... BL23: =IF(BL$4>=Inputs!$C$51,MAX(0,MIN(Inputs!$C$49,BL22,BK23+Inputs!$C$40-FS!BL$60)),0)
A24: Net drawdown / (repayment) | B24: LCY | C24: =SUM(E24:BL24) | E24: =E23-D23 | F24: =F23-E23 | G24: =G23-F23 | H24: =H23-G23 | I24: =I23-H23 | J24: =J23-I23 | K24: =K23-J23 | L24: =L23-K23 | ... BL24: =BL23-BK23
A25: Interest | B25: LCY | C25: =SUM(E25:BL25) | E25: =D23*Inputs!$C$50/12 | F25: =E23*Inputs!$C$50/12 | G25: =F23*Inputs!$C$50/12 | H25: =G23*Inputs!$C$50/12 | I25: =H23*Inputs!$C$50/12 | J25: =I23*Inputs!$C$50/12 | K25: =J23*Inputs!$C$50/12 | L25: =K23*Inputs!$C$50/12 | ... BL25: =BK23*Inputs!$C$50/12
A26: Utilisation of limit | B26: % | C26: =MAX(E26:BL26) | E26: =IF(Inputs!$C$49=0,0,E23/Inputs!$C$49) | F26: =IF(Inputs!$C$49=0,0,F23/Inputs!$C$49) | G26: =IF(Inputs!$C$49=0,0,G23/Inputs!$C$49) | H26: =IF(Inputs!$C$49=0,0,H23/Inputs!$C$49) | I26: =IF(Inputs!$C$49=0,0,I23/Inputs!$C$49) | J26: =IF(Inputs!$C$49=0,0,J23/Inputs!$C$49) | K26: =IF(Inputs!$C$49=0,0,K23/Inputs!$C$49) | L26: =IF(Inputs!$C$49=0,0,L23/Inputs!$C$49) | ... BL26: =IF(Inputs!$C$49=0,0,BL23/Inputs!$C$49)

Sheet Curves
A1: Per-unit PAYGo behaviour by account age
A2: Age 0 = month of sale. Per unit, month-1 prices; cohorts are scaled by the price index. RBF at opening FX.
B5: Tier 1 - Pico solar kit | N5: Tier 2 - SHS with TV | Z5: Tier 3 - Large SHS + DC fridge | AL5: Tier 4 - Solar inverter + lithium (~1.2 kWp / 5 kWh) | AX5: Tier 5 - Solar inverter + lithium (~3 kWp / 10 kWh)
A6: Age (m) | B6: Survival (still paying) | C6: Instalment due | D6: Collected | E6: Missed (written off) | F6: Receivable at risk | G6: Active account | H6: Defaults at this age | I6: Recovery (resale) | J6: RBF received | K6: Net cash flow / unit | L6: Cumulative cash flow | N6: Survival (still paying) | O6: Instalment due | P6: Collected | Q6: Missed (written off) | R6: Receivable at risk | S6: Active account | T6: Defaults at this age | U6: Recovery (resale) | V6: RBF received | W6: Net cash flow / unit | X6: Cumulative cash flow | Z6: Survival (still paying) | AA6: Instalment due | AB6: Collected | AC6: Missed (written off) | AD6: Receivable at risk | AE6: Active account | AF6: Defaults at this age | AG6: Recovery (resale) | AH6: RBF received | AI6: Net cash flow / unit | AJ6: Cumulative cash flow | AL6: Survival (still paying) | AM6: Instalment due | AN6: Collected | AO6: Missed (written off) | AP6: Receivable at risk | AQ6: Active account | AR6: Defaults at this age | AS6: Recovery (resale) | AT6: RBF received | AU6: Net cash flow / unit | AV6: Cumulative cash flow | AX6: Survival (still paying) | AY6: Instalment due | AZ6: Collected | BA6: Missed (written off) | BB6: Receivable at risk | BC6: Active account | BD6: Defaults at this age | BE6: Recovery (resale) | BF6: RBF received | BG6: Net cash flow / unit | BH6: Cumulative cash flow
A8: 0 | B8: =1 | C8: =IF(AND($A8>=1,$A8<=Products!$C$16),Products!$C$33,0) | D8: =C8*Products!$C$42*B8 | E8: =C8-D8 | F8: =(1-B8)*MAX(0,Products!$C$16-$A8)*(Products!$C$33-Products!$C$35/Products!$C$16) | G8: =IF($A8<=Products!$C$16,B8,0) | H8: =0 | I8: =IF(AND($A8-Inputs!$C$31>=1,$A8-Inputs!$C$31<=Products!$C$16),INDEX(Curves!$H$8:$H$68,$A8-Inputs!$C$31+1),0)*Products!$C$27*Products!$C$28*Products!$C$13 | J8: =IF($A8=Inputs!$C$33,Products!$C$30*Inputs!$C$10*Inputs!$C$32,0) | K8: =Products!$C$14*(1-Inputs!$C$24)-Products!$C$43*(1+Products!$C$22)-Products!$C$19-Products!$C$44+J8 | L8: =K8 | N8: =1 | O8: =IF(AND($A8>=1,$A8<=Products!$D$16),Products!$D$33,0) | P8: =O8*Products!$D$42*N8 | Q8: =O8-P8 | R8: =(1-N8)*MAX(0,Products!$D$16-$A8)*(Products!$D$33-Products!$D$35/Products!$D$16) | S8: =IF($A8<=Products!$D$16,N8,0) | T8: =0 | U8: =IF(AND($A8-Inputs!$C$31>=1,$A8-Inputs!$C$31<=Products!$D$16),INDEX(Curves!$T$8:$T$68,$A8-Inputs!$C$31+1),0)*Products!$D$27*Products!$D$28*Products!$D$13 | V8: =IF($A8=Inputs!$C$33,Products!$D$30*Inputs!$C$10*Inputs!$C$32,0) | W8: =Products!$D$14*(1-Inputs!$C$24)-Products!$D$43*(1+Products!$D$22)-Products!$D$19-Products!$D$44+V8 | X8: =W8 | Z8: =1 | AA8: =IF(AND($A8>=1,$A8<=Products!$E$16),Products!$E$33,0) | AB8: =AA8*Products!$E$42*Z8 | AC8: =AA8-AB8 | AD8: =(1-Z8)*MAX(0,Products!$E$16-$A8)*(Products!$E$33-Products!$E$35/Products!$E$16) | AE8: =IF($A8<=Products!$E$16,Z8,0) | AF8: =0 | AG8: =IF(AND($A8-Inputs!$C$31>=1,$A8-Inputs!$C$31<=Products!$E$16),INDEX(Curves!$AF$8:$AF$68,$A8-Inputs!$C$31+1),0)*Products!$E$27*Products!$E$28*Products!$E$13 | AH8: =IF($A8=Inputs!$C$33,Products!$E$30*Inputs!$C$10*Inputs!$C$32,0) | AI8: =Products!$E$14*(1-Inputs!$C$24)-Products!$E$43*(1+Products!$E$22)-Products!$E$19-Products!$E$44+AH8 | AJ8: =AI8 | AL8: =1 | AM8: =IF(AND($A8>=1,$A8<=Products!$F$16),Products!$F$33,0) | AN8: =AM8*Products!$F$42*AL8 | AO8: =AM8-AN8 | AP8: =(1-AL8)*MAX(0,Products!$F$16-$A8)*(Products!$F$33-Products!$F$35/Products!$F$16) | AQ8: =IF($A8<=Products!$F$16,AL8,0) | AR8: =0 | AS8: =IF(AND($A8-Inputs!$C$31>=1,$A8-Inputs!$C$31<=Products!$F$16),INDEX(Curves!$AR$8:$AR$68,$A8-Inputs!$C$31+1),0)*Products!$F$27*Products!$F$28*Products!$F$13 | AT8: =IF($A8=Inputs!$C$33,Products!$F$30*Inputs!$C$10*Inputs!$C$32,0) | AU8: =Products!$F$14*(1-Inputs!$C$24)-Products!$F$43*(1+Products!$F$22)-Products!$F$19-Products!$F$44+AT8 | AV8: =AU8 | AX8: =1 | AY8: =IF(AND($A8>=1,$A8<=Products!$G$16),Products!$G$33,0) | AZ8: =AY8*Products!$G$42*AX8 | BA8: =AY8-AZ8 | BB8: =(1-AX8)*MAX(0,Products!$G$16-$A8)*(Products!$G$33-Products!$G$35/Products!$G$16) | BC8: =IF($A8<=Products!$G$16,AX8,0) | BD8: =0 | BE8: =IF(AND($A8-Inputs!$C$31>=1,$A8-Inputs!$C$31<=Products!$G$16),INDEX(Curves!$BD$8:$BD$68,$A8-Inputs!$C$31+1),0)*Products!$G$27*Products!$G$28*Products!$G$13 | BF8: =IF($A8=Inputs!$C$33,Products!$G$30*Inputs!$C$10*Inputs!$C$32,0) | BG8: =Products!$G$14*(1-Inputs!$C$24)-Products!$G$43*(1+Products!$G$22)-Products!$G$19-Products!$G$44+BF8 | BH8: =BG8
A9: 1 | B9: =(1-Products!$C$41)^$A9 | C9: =IF(AND($A9>=1,$A9<=Products!$C$16),Products!$C$33,0) | D9: =C9*Products!$C$42*B9 | E9: =C9-D9 | F9: =(1-B9)*MAX(0,Products!$C$16-$A9)*(Products!$C$33-Products!$C$35/Products!$C$16) | G9: =IF($A9<=Products!$C$16,B9,0) | H9: =IF(AND($A9>=1,$A9<=Products!$C$16),B8-B9,0) | I9: =IF(AND($A9-Inputs!$C$31>=1,$A9-Inputs!$C$31<=Products!$C$16),INDEX(Curves!$H$8:$H$68,$A9-Inputs!$C$31+1),0)*Products!$C$27*Products!$C$28*Products!$C$13 | J9: =IF($A9=Inputs!$C$33,Products!$C$30*Inputs!$C$10*Inputs!$C$32,0) | K9: =D9*(1-Inputs!$C$24)-Inputs!$C$25*G9+I9+J9 | L9: =L8+K9 | N9: =(1-Products!$D$41)^$A9 | O9: =IF(AND($A9>=1,$A9<=Products!$D$16),Products!$D$33,0) | P9: =O9*Products!$D$42*N9 | Q9: =O9-P9 | R9: =(1-N9)*MAX(0,Products!$D$16-$A9)*(Products!$D$33-Products!$D$35/Products!$D$16) | S9: =IF($A9<=Products!$D$16,N9,0) | T9: =IF(AND($A9>=1,$A9<=Products!$D$16),N8-N9,0) | U9: =IF(AND($A9-Inputs!$C$31>=1,$A9-Inputs!$C$31<=Products!$D$16),INDEX(Curves!$T$8:$T$68,$A9-Inputs!$C$31+1),0)*Products!$D$27*Products!$D$28*Products!$D$13 | V9: =IF($A9=Inputs!$C$33,Products!$D$30*Inputs!$C$10*Inputs!$C$32,0) | W9: =P9*(1-Inputs!$C$24)-Inputs!$C$25*S9+U9+V9 | X9: =X8+W9 | Z9: =(1-Products!$E$41)^$A9 | AA9: =IF(AND($A9>=1,$A9<=Products!$E$16),Products!$E$33,0) | AB9: =AA9*Products!$E$42*Z9 | AC9: =AA9-AB9 | AD9: =(1-Z9)*MAX(0,Products!$E$16-$A9)*(Products!$E$33-Products!$E$35/Products!$E$16) | AE9: =IF($A9<=Products!$E$16,Z9,0) | AF9: =IF(AND($A9>=1,$A9<=Products!$E$16),Z8-Z9,0) | AG9: =IF(AND($A9-Inputs!$C$31>=1,$A9-Inputs!$C$31<=Products!$E$16),INDEX(Curves!$AF$8:$AF$68,$A9-Inputs!$C$31+1),0)*Products!$E$27*Products!$E$28*Products!$E$13 | AH9: =IF($A9=Inputs!$C$33,Products!$E$30*Inputs!$C$10*Inputs!$C$32,0) | AI9: =AB9*(1-Inputs!$C$24)-Inputs!$C$25*AE9+AG9+AH9 | AJ9: =AJ8+AI9 | AL9: =(1-Products!$F$41)^$A9 | AM9: =IF(AND($A9>=1,$A9<=Products!$F$16),Products!$F$33,0) | AN9: =AM9*Products!$F$42*AL9 | AO9: =AM9-AN9 | AP9: =(1-AL9)*MAX(0,Products!$F$16-$A9)*(Products!$F$33-Products!$F$35/Products!$F$16) | AQ9: =IF($A9<=Products!$F$16,AL9,0) | AR9: =IF(AND($A9>=1,$A9<=Products!$F$16),AL8-AL9,0) | AS9: =IF(AND($A9-Inputs!$C$31>=1,$A9-Inputs!$C$31<=Products!$F$16),INDEX(Curves!$AR$8:$AR$68,$A9-Inputs!$C$31+1),0)*Products!$F$27*Products!$F$28*Products!$F$13 | AT9: =IF($A9=Inputs!$C$33,Products!$F$30*Inputs!$C$10*Inputs!$C$32,0) | AU9: =AN9*(1-Inputs!$C$24)-Inputs!$C$25*AQ9+AS9+AT9 | AV9: =AV8+AU9 | AX9: =(1-Products!$G$41)^$A9 | AY9: =IF(AND($A9>=1,$A9<=Products!$G$16),Products!$G$33,0) | AZ9: =AY9*Products!$G$42*AX9 | BA9: =AY9-AZ9 | BB9: =(1-AX9)*MAX(0,Products!$G$16-$A9)*(Products!$G$33-Products!$G$35/Products!$G$16) | BC9: =IF($A9<=Products!$G$16,AX9,0) | BD9: =IF(AND($A9>=1,$A9<=Products!$G$16),AX8-AX9,0) | BE9: =IF(AND($A9-Inputs!$C$31>=1,$A9-Inputs!$C$31<=Products!$G$16),INDEX(Curves!$BD$8:$BD$68,$A9-Inputs!$C$31+1),0)*Products!$G$27*Products!$G$28*Products!$G$13 | BF9: =IF($A9=Inputs!$C$33,Products!$G$30*Inputs!$C$10*Inputs!$C$32,0) | BG9: =AZ9*(1-Inputs!$C$24)-Inputs!$C$25*BC9+BE9+BF9 | BH9: =BH8+BG9
A10: 2 | B10: =(1-Products!$C$41)^$A10 | C10: =IF(AND($A10>=1,$A10<=Products!$C$16),Products!$C$33,0) | D10: =C10*Products!$C$42*B10 | E10: =C10-D10 | F10: =(1-B10)*MAX(0,Products!$C$16-$A10)*(Products!$C$33-Products!$C$35/Products!$C$16) | G10: =IF($A10<=Products!$C$16,B10,0) | H10: =IF(AND($A10>=1,$A10<=Products!$C$16),B9-B10,0) | I10: =IF(AND($A10-Inputs!$C$31>=1,$A10-Inputs!$C$31<=Products!$C$16),INDEX(Curves!$H$8:$H$68,$A10-Inputs!$C$31+1),0)*Products!$C$27*Products!$C$28*Products!$C$13 | J10: =IF($A10=Inputs!$C$33,Products!$C$30*Inputs!$C$10*Inputs!$C$32,0) | K10: =D10*(1-Inputs!$C$24)-Inputs!$C$25*G10+I10+J10 | L10: =L9+K10 | N10: =(1-Products!$D$41)^$A10 | O10: =IF(AND($A10>=1,$A10<=Products!$D$16),Products!$D$33,0) | P10: =O10*Products!$D$42*N10 | Q10: =O10-P10 | R10: =(1-N10)*MAX(0,Products!$D$16-$A10)*(Products!$D$33-Products!$D$35/Products!$D$16) | S10: =IF($A10<=Products!$D$16,N10,0) | T10: =IF(AND($A10>=1,$A10<=Products!$D$16),N9-N10,0) | U10: =IF(AND($A10-Inputs!$C$31>=1,$A10-Inputs!$C$31<=Products!$D$16),INDEX(Curves!$T$8:$T$68,$A10-Inputs!$C$31+1),0)*Products!$D$27*Products!$D$28*Products!$D$13 | V10: =IF($A10=Inputs!$C$33,Products!$D$30*Inputs!$C$10*Inputs!$C$32,0) | W10: =P10*(1-Inputs!$C$24)-Inputs!$C$25*S10+U10+V10 | X10: =X9+W10 | Z10: =(1-Products!$E$41)^$A10 | AA10: =IF(AND($A10>=1,$A10<=Products!$E$16),Products!$E$33,0) | AB10: =AA10*Products!$E$42*Z10 | AC10: =AA10-AB10 | AD10: =(1-Z10)*MAX(0,Products!$E$16-$A10)*(Products!$E$33-Products!$E$35/Products!$E$16) | AE10: =IF($A10<=Products!$E$16,Z10,0) | AF10: =IF(AND($A10>=1,$A10<=Products!$E$16),Z9-Z10,0) | AG10: =IF(AND($A10-Inputs!$C$31>=1,$A10-Inputs!$C$31<=Products!$E$16),INDEX(Curves!$AF$8:$AF$68,$A10-Inputs!$C$31+1),0)*Products!$E$27*Products!$E$28*Products!$E$13 | AH10: =IF($A10=Inputs!$C$33,Products!$E$30*Inputs!$C$10*Inputs!$C$32,0) | AI10: =AB10*(1-Inputs!$C$24)-Inputs!$C$25*AE10+AG10+AH10 | AJ10: =AJ9+AI10 | AL10: =(1-Products!$F$41)^$A10 | AM10: =IF(AND($A10>=1,$A10<=Products!$F$16),Products!$F$33,0) | AN10: =AM10*Products!$F$42*AL10 | AO10: =AM10-AN10 | AP10: =(1-AL10)*MAX(0,Products!$F$16-$A10)*(Products!$F$33-Products!$F$35/Products!$F$16) | AQ10: =IF($A10<=Products!$F$16,AL10,0) | AR10: =IF(AND($A10>=1,$A10<=Products!$F$16),AL9-AL10,0) | AS10: =IF(AND($A10-Inputs!$C$31>=1,$A10-Inputs!$C$31<=Products!$F$16),INDEX(Curves!$AR$8:$AR$68,$A10-Inputs!$C$31+1),0)*Products!$F$27*Products!$F$28*Products!$F$13 | AT10: =IF($A10=Inputs!$C$33,Products!$F$30*Inputs!$C$10*Inputs!$C$32,0) | AU10: =AN10*(1-Inputs!$C$24)-Inputs!$C$25*AQ10+AS10+AT10 | AV10: =AV9+AU10 | AX10: =(1-Products!$G$41)^$A10 | AY10: =IF(AND($A10>=1,$A10<=Products!$G$16),Products!$G$33,0) | AZ10: =AY10*Products!$G$42*AX10 | BA10: =AY10-AZ10 | BB10: =(1-AX10)*MAX(0,Products!$G$16-$A10)*(Products!$G$33-Products!$G$35/Products!$G$16) | BC10: =IF($A10<=Products!$G$16,AX10,0) | BD10: =IF(AND($A10>=1,$A10<=Products!$G$16),AX9-AX10,0) | BE10: =IF(AND($A10-Inputs!$C$31>=1,$A10-Inputs!$C$31<=Products!$G$16),INDEX(Curves!$BD$8:$BD$68,$A10-Inputs!$C$31+1),0)*Products!$G$27*Products!$G$28*Products!$G$13 | BF10: =IF($A10=Inputs!$C$33,Products!$G$30*Inputs!$C$10*Inputs!$C$32,0) | BG10: =AZ10*(1-Inputs!$C$24)-Inputs!$C$25*BC10+BE10+BF10 | BH10: =BH9+BG10
A11: 3 | B11: =(1-Products!$C$41)^$A11 | C11: =IF(AND($A11>=1,$A11<=Products!$C$16),Products!$C$33,0) | D11: =C11*Products!$C$42*B11 | E11: =C11-D11 | F11: =(1-B11)*MAX(0,Products!$C$16-$A11)*(Products!$C$33-Products!$C$35/Products!$C$16) | G11: =IF($A11<=Products!$C$16,B11,0) | H11: =IF(AND($A11>=1,$A11<=Products!$C$16),B10-B11,0) | I11: =IF(AND($A11-Inputs!$C$31>=1,$A11-Inputs!$C$31<=Products!$C$16),INDEX(Curves!$H$8:$H$68,$A11-Inputs!$C$31+1),0)*Products!$C$27*Products!$C$28*Products!$C$13 | J11: =IF($A11=Inputs!$C$33,Products!$C$30*Inputs!$C$10*Inputs!$C$32,0) | K11: =D11*(1-Inputs!$C$24)-Inputs!$C$25*G11+I11+J11 | L11: =L10+K11 | N11: =(1-Products!$D$41)^$A11 | O11: =IF(AND($A11>=1,$A11<=Products!$D$16),Products!$D$33,0) | P11: =O11*Products!$D$42*N11 | Q11: =O11-P11 | R11: =(1-N11)*MAX(0,Products!$D$16-$A11)*(Products!$D$33-Products!$D$35/Products!$D$16) | S11: =IF($A11<=Products!$D$16,N11,0) | T11: =IF(AND($A11>=1,$A11<=Products!$D$16),N10-N11,0) | U11: =IF(AND($A11-Inputs!$C$31>=1,$A11-Inputs!$C$31<=Products!$D$16),INDEX(Curves!$T$8:$T$68,$A11-Inputs!$C$31+1),0)*Products!$D$27*Products!$D$28*Products!$D$13 | V11: =IF($A11=Inputs!$C$33,Products!$D$30*Inputs!$C$10*Inputs!$C$32,0) | W11: =P11*(1-Inputs!$C$24)-Inputs!$C$25*S11+U11+V11 | X11: =X10+W11 | Z11: =(1-Products!$E$41)^$A11 | AA11: =IF(AND($A11>=1,$A11<=Products!$E$16),Products!$E$33,0) | AB11: =AA11*Products!$E$42*Z11 | AC11: =AA11-AB11 | AD11: =(1-Z11)*MAX(0,Products!$E$16-$A11)*(Products!$E$33-Products!$E$35/Products!$E$16) | AE11: =IF($A11<=Products!$E$16,Z11,0) | AF11: =IF(AND($A11>=1,$A11<=Products!$E$16),Z10-Z11,0) | AG11: =IF(AND($A11-Inputs!$C$31>=1,$A11-Inputs!$C$31<=Products!$E$16),INDEX(Curves!$AF$8:$AF$68,$A11-Inputs!$C$31+1),0)*Products!$E$27*Products!$E$28*Products!$E$13 | AH11: =IF($A11=Inputs!$C$33,Products!$E$30*Inputs!$C$10*Inputs!$C$32,0) | AI11: =AB11*(1-Inputs!$C$24)-Inputs!$C$25*AE11+AG11+AH11 | AJ11: =AJ10+AI11 | AL11: =(1-Products!$F$41)^$A11 | AM11: =IF(AND($A11>=1,$A11<=Products!$F$16),Products!$F$33,0) | AN11: =AM11*Products!$F$42*AL11 | AO11: =AM11-AN11 | AP11: =(1-AL11)*MAX(0,Products!$F$16-$A11)*(Products!$F$33-Products!$F$35/Products!$F$16) | AQ11: =IF($A11<=Products!$F$16,AL11,0) | AR11: =IF(AND($A11>=1,$A11<=Products!$F$16),AL10-AL11,0) | AS11: =IF(AND($A11-Inputs!$C$31>=1,$A11-Inputs!$C$31<=Products!$F$16),INDEX(Curves!$AR$8:$AR$68,$A11-Inputs!$C$31+1),0)*Products!$F$27*Products!$F$28*Products!$F$13 | AT11: =IF($A11=Inputs!$C$33,Products!$F$30*Inputs!$C$10*Inputs!$C$32,0) | AU11: =AN11*(1-Inputs!$C$24)-Inputs!$C$25*AQ11+AS11+AT11 | AV11: =AV10+AU11 | AX11: =(1-Products!$G$41)^$A11 | AY11: =IF(AND($A11>=1,$A11<=Products!$G$16),Products!$G$33,0) | AZ11: =AY11*Products!$G$42*AX11 | BA11: =AY11-AZ11 | BB11: =(1-AX11)*MAX(0,Products!$G$16-$A11)*(Products!$G$33-Products!$G$35/Products!$G$16) | BC11: =IF($A11<=Products!$G$16,AX11,0) | BD11: =IF(AND($A11>=1,$A11<=Products!$G$16),AX10-AX11,0) | BE11: =IF(AND($A11-Inputs!$C$31>=1,$A11-Inputs!$C$31<=Products!$G$16),INDEX(Curves!$BD$8:$BD$68,$A11-Inputs!$C$31+1),0)*Products!$G$27*Products!$G$28*Products!$G$13 | BF11: =IF($A11=Inputs!$C$33,Products!$G$30*Inputs!$C$10*Inputs!$C$32,0) | BG11: =AZ11*(1-Inputs!$C$24)-Inputs!$C$25*BC11+BE11+BF11 | BH11: =BH10+BG11
A12: 4 | B12: =(1-Products!$C$41)^$A12 | C12: =IF(AND($A12>=1,$A12<=Products!$C$16),Products!$C$33,0) | D12: =C12*Products!$C$42*B12 | E12: =C12-D12 | F12: =(1-B12)*MAX(0,Products!$C$16-$A12)*(Products!$C$33-Products!$C$35/Products!$C$16) | G12: =IF($A12<=Products!$C$16,B12,0) | H12: =IF(AND($A12>=1,$A12<=Products!$C$16),B11-B12,0) | I12: =IF(AND($A12-Inputs!$C$31>=1,$A12-Inputs!$C$31<=Products!$C$16),INDEX(Curves!$H$8:$H$68,$A12-Inputs!$C$31+1),0)*Products!$C$27*Products!$C$28*Products!$C$13 | J12: =IF($A12=Inputs!$C$33,Products!$C$30*Inputs!$C$10*Inputs!$C$32,0) | K12: =D12*(1-Inputs!$C$24)-Inputs!$C$25*G12+I12+J12 | L12: =L11+K12 | N12: =(1-Products!$D$41)^$A12 | O12: =IF(AND($A12>=1,$A12<=Products!$D$16),Products!$D$33,0) | P12: =O12*Products!$D$42*N12 | Q12: =O12-P12 | R12: =(1-N12)*MAX(0,Products!$D$16-$A12)*(Products!$D$33-Products!$D$35/Products!$D$16) | S12: =IF($A12<=Products!$D$16,N12,0) | T12: =IF(AND($A12>=1,$A12<=Products!$D$16),N11-N12,0) | U12: =IF(AND($A12-Inputs!$C$31>=1,$A12-Inputs!$C$31<=Products!$D$16),INDEX(Curves!$T$8:$T$68,$A12-Inputs!$C$31+1),0)*Products!$D$27*Products!$D$28*Products!$D$13 | V12: =IF($A12=Inputs!$C$33,Products!$D$30*Inputs!$C$10*Inputs!$C$32,0) | W12: =P12*(1-Inputs!$C$24)-Inputs!$C$25*S12+U12+V12 | X12: =X11+W12 | Z12: =(1-Products!$E$41)^$A12 | AA12: =IF(AND($A12>=1,$A12<=Products!$E$16),Products!$E$33,0) | AB12: =AA12*Products!$E$42*Z12 | AC12: =AA12-AB12 | AD12: =(1-Z12)*MAX(0,Products!$E$16-$A12)*(Products!$E$33-Products!$E$35/Products!$E$16) | AE12: =IF($A12<=Products!$E$16,Z12,0) | AF12: =IF(AND($A12>=1,$A12<=Products!$E$16),Z11-Z12,0) | AG12: =IF(AND($A12-Inputs!$C$31>=1,$A12-Inputs!$C$31<=Products!$E$16),INDEX(Curves!$AF$8:$AF$68,$A12-Inputs!$C$31+1),0)*Products!$E$27*Products!$E$28*Products!$E$13 | AH12: =IF($A12=Inputs!$C$33,Products!$E$30*Inputs!$C$10*Inputs!$C$32,0) | AI12: =AB12*(1-Inputs!$C$24)-Inputs!$C$25*AE12+AG12+AH12 | AJ12: =AJ11+AI12 | AL12: =(1-Products!$F$41)^$A12 | AM12: =IF(AND($A12>=1,$A12<=Products!$F$16),Products!$F$33,0) | AN12: =AM12*Products!$F$42*AL12 | AO12: =AM12-AN12 | AP12: =(1-AL12)*MAX(0,Products!$F$16-$A12)*(Products!$F$33-Products!$F$35/Products!$F$16) | AQ12: =IF($A12<=Products!$F$16,AL12,0) | AR12: =IF(AND($A12>=1,$A12<=Products!$F$16),AL11-AL12,0) | AS12: =IF(AND($A12-Inputs!$C$31>=1,$A12-Inputs!$C$31<=Products!$F$16),INDEX(Curves!$AR$8:$AR$68,$A12-Inputs!$C$31+1),0)*Products!$F$27*Products!$F$28*Products!$F$13 | AT12: =IF($A12=Inputs!$C$33,Products!$F$30*Inputs!$C$10*Inputs!$C$32,0) | AU12: =AN12*(1-Inputs!$C$24)-Inputs!$C$25*AQ12+AS12+AT12 | AV12: =AV11+AU12 | AX12: =(1-Products!$G$41)^$A12 | AY12: =IF(AND($A12>=1,$A12<=Products!$G$16),Products!$G$33,0) | AZ12: =AY12*Products!$G$42*AX12 | BA12: =AY12-AZ12 | BB12: =(1-AX12)*MAX(0,Products!$G$16-$A12)*(Products!$G$33-Products!$G$35/Products!$G$16) | BC12: =IF($A12<=Products!$G$16,AX12,0) | BD12: =IF(AND($A12>=1,$A12<=Products!$G$16),AX11-AX12,0) | BE12: =IF(AND($A12-Inputs!$C$31>=1,$A12-Inputs!$C$31<=Products!$G$16),INDEX(Curves!$BD$8:$BD$68,$A12-Inputs!$C$31+1),0)*Products!$G$27*Products!$G$28*Products!$G$13 | BF12: =IF($A12=Inputs!$C$33,Products!$G$30*Inputs!$C$10*Inputs!$C$32,0) | BG12: =AZ12*(1-Inputs!$C$24)-Inputs!$C$25*BC12+BE12+BF12 | BH12: =BH11+BG12
A13: 5 | B13: =(1-Products!$C$41)^$A13 | C13: =IF(AND($A13>=1,$A13<=Products!$C$16),Products!$C$33,0) | D13: =C13*Products!$C$42*B13 | E13: =C13-D13 | F13: =(1-B13)*MAX(0,Products!$C$16-$A13)*(Products!$C$33-Products!$C$35/Products!$C$16) | G13: =IF($A13<=Products!$C$16,B13,0) | H13: =IF(AND($A13>=1,$A13<=Products!$C$16),B12-B13,0) | I13: =IF(AND($A13-Inputs!$C$31>=1,$A13-Inputs!$C$31<=Products!$C$16),INDEX(Curves!$H$8:$H$68,$A13-Inputs!$C$31+1),0)*Products!$C$27*Products!$C$28*Products!$C$13 | J13: =IF($A13=Inputs!$C$33,Products!$C$30*Inputs!$C$10*Inputs!$C$32,0) | K13: =D13*(1-Inputs!$C$24)-Inputs!$C$25*G13+I13+J13 | L13: =L12+K13 | N13: =(1-Products!$D$41)^$A13 | O13: =IF(AND($A13>=1,$A13<=Products!$D$16),Products!$D$33,0) | P13: =O13*Products!$D$42*N13 | Q13: =O13-P13 | R13: =(1-N13)*MAX(0,Products!$D$16-$A13)*(Products!$D$33-Products!$D$35/Products!$D$16) | S13: =IF($A13<=Products!$D$16,N13,0) | T13: =IF(AND($A13>=1,$A13<=Products!$D$16),N12-N13,0) | U13: =IF(AND($A13-Inputs!$C$31>=1,$A13-Inputs!$C$31<=Products!$D$16),INDEX(Curves!$T$8:$T$68,$A13-Inputs!$C$31+1),0)*Products!$D$27*Products!$D$28*Products!$D$13 | V13: =IF($A13=Inputs!$C$33,Products!$D$30*Inputs!$C$10*Inputs!$C$32,0) | W13: =P13*(1-Inputs!$C$24)-Inputs!$C$25*S13+U13+V13 | X13: =X12+W13 | Z13: =(1-Products!$E$41)^$A13 | AA13: =IF(AND($A13>=1,$A13<=Products!$E$16),Products!$E$33,0) | AB13: =AA13*Products!$E$42*Z13 | AC13: =AA13-AB13 | AD13: =(1-Z13)*MAX(0,Products!$E$16-$A13)*(Products!$E$33-Products!$E$35/Products!$E$16) | AE13: =IF($A13<=Products!$E$16,Z13,0) | AF13: =IF(AND($A13>=1,$A13<=Products!$E$16),Z12-Z13,0) | AG13: =IF(AND($A13-Inputs!$C$31>=1,$A13-Inputs!$C$31<=Products!$E$16),INDEX(Curves!$AF$8:$AF$68,$A13-Inputs!$C$31+1),0)*Products!$E$27*Products!$E$28*Products!$E$13 | AH13: =IF($A13=Inputs!$C$33,Products!$E$30*Inputs!$C$10*Inputs!$C$32,0) | AI13: =AB13*(1-Inputs!$C$24)-Inputs!$C$25*AE13+AG13+AH13 | AJ13: =AJ12+AI13 | AL13: =(1-Products!$F$41)^$A13 | AM13: =IF(AND($A13>=1,$A13<=Products!$F$16),Products!$F$33,0) | AN13: =AM13*Products!$F$42*AL13 | AO13: =AM13-AN13 | AP13: =(1-AL13)*MAX(0,Products!$F$16-$A13)*(Products!$F$33-Products!$F$35/Products!$F$16) | AQ13: =IF($A13<=Products!$F$16,AL13,0) | AR13: =IF(AND($A13>=1,$A13<=Products!$F$16),AL12-AL13,0) | AS13: =IF(AND($A13-Inputs!$C$31>=1,$A13-Inputs!$C$31<=Products!$F$16),INDEX(Curves!$AR$8:$AR$68,$A13-Inputs!$C$31+1),0)*Products!$F$27*Products!$F$28*Products!$F$13 | AT13: =IF($A13=Inputs!$C$33,Products!$F$30*Inputs!$C$10*Inputs!$C$32,0) | AU13: =AN13*(1-Inputs!$C$24)-Inputs!$C$25*AQ13+AS13+AT13 | AV13: =AV12+AU13 | AX13: =(1-Products!$G$41)^$A13 | AY13: =IF(AND($A13>=1,$A13<=Products!$G$16),Products!$G$33,0) | AZ13: =AY13*Products!$G$42*AX13 | BA13: =AY13-AZ13 | BB13: =(1-AX13)*MAX(0,Products!$G$16-$A13)*(Products!$G$33-Products!$G$35/Products!$G$16) | BC13: =IF($A13<=Products!$G$16,AX13,0) | BD13: =IF(AND($A13>=1,$A13<=Products!$G$16),AX12-AX13,0) | BE13: =IF(AND($A13-Inputs!$C$31>=1,$A13-Inputs!$C$31<=Products!$G$16),INDEX(Curves!$BD$8:$BD$68,$A13-Inputs!$C$31+1),0)*Products!$G$27*Products!$G$28*Products!$G$13 | BF13: =IF($A13=Inputs!$C$33,Products!$G$30*Inputs!$C$10*Inputs!$C$32,0) | BG13: =AZ13*(1-Inputs!$C$24)-Inputs!$C$25*BC13+BE13+BF13 | BH13: =BH12+BG13
A14: 6 | B14: =(1-Products!$C$41)^$A14 | C14: =IF(AND($A14>=1,$A14<=Products!$C$16),Products!$C$33,0) | D14: =C14*Products!$C$42*B14 | E14: =C14-D14 | F14: =(1-B14)*MAX(0,Products!$C$16-$A14)*(Products!$C$33-Products!$C$35/Products!$C$16) | G14: =IF($A14<=Products!$C$16,B14,0) | H14: =IF(AND($A14>=1,$A14<=Products!$C$16),B13-B14,0) | I14: =IF(AND($A14-Inputs!$C$31>=1,$A14-Inputs!$C$31<=Products!$C$16),INDEX(Curves!$H$8:$H$68,$A14-Inputs!$C$31+1),0)*Products!$C$27*Products!$C$28*Products!$C$13 | J14: =IF($A14=Inputs!$C$33,Products!$C$30*Inputs!$C$10*Inputs!$C$32,0) | K14: =D14*(1-Inputs!$C$24)-Inputs!$C$25*G14+I14+J14 | L14: =L13+K14 | N14: =(1-Products!$D$41)^$A14 | O14: =IF(AND($A14>=1,$A14<=Products!$D$16),Products!$D$33,0) | P14: =O14*Products!$D$42*N14 | Q14: =O14-P14 | R14: =(1-N14)*MAX(0,Products!$D$16-$A14)*(Products!$D$33-Products!$D$35/Products!$D$16) | S14: =IF($A14<=Products!$D$16,N14,0) | T14: =IF(AND($A14>=1,$A14<=Products!$D$16),N13-N14,0) | U14: =IF(AND($A14-Inputs!$C$31>=1,$A14-Inputs!$C$31<=Products!$D$16),INDEX(Curves!$T$8:$T$68,$A14-Inputs!$C$31+1),0)*Products!$D$27*Products!$D$28*Products!$D$13 | V14: =IF($A14=Inputs!$C$33,Products!$D$30*Inputs!$C$10*Inputs!$C$32,0) | W14: =P14*(1-Inputs!$C$24)-Inputs!$C$25*S14+U14+V14 | X14: =X13+W14 | Z14: =(1-Products!$E$41)^$A14 | AA14: =IF(AND($A14>=1,$A14<=Products!$E$16),Products!$E$33,0) | AB14: =AA14*Products!$E$42*Z14 | AC14: =AA14-AB14 | AD14: =(1-Z14)*MAX(0,Products!$E$16-$A14)*(Products!$E$33-Products!$E$35/Products!$E$16) | AE14: =IF($A14<=Products!$E$16,Z14,0) | AF14: =IF(AND($A14>=1,$A14<=Products!$E$16),Z13-Z14,0) | AG14: =IF(AND($A14-Inputs!$C$31>=1,$A14-Inputs!$C$31<=Products!$E$16),INDEX(Curves!$AF$8:$AF$68,$A14-Inputs!$C$31+1),0)*Products!$E$27*Products!$E$28*Products!$E$13 | AH14: =IF($A14=Inputs!$C$33,Products!$E$30*Inputs!$C$10*Inputs!$C$32,0) | AI14: =AB14*(1-Inputs!$C$24)-Inputs!$C$25*AE14+AG14+AH14 | AJ14: =AJ13+AI14 | AL14: =(1-Products!$F$41)^$A14 | AM14: =IF(AND($A14>=1,$A14<=Products!$F$16),Products!$F$33,0) | AN14: =AM14*Products!$F$42*AL14 | AO14: =AM14-AN14 | AP14: =(1-AL14)*MAX(0,Products!$F$16-$A14)*(Products!$F$33-Products!$F$35/Products!$F$16) | AQ14: =IF($A14<=Products!$F$16,AL14,0) | AR14: =IF(AND($A14>=1,$A14<=Products!$F$16),AL13-AL14,0) | AS14: =IF(AND($A14-Inputs!$C$31>=1,$A14-Inputs!$C$31<=Products!$F$16),INDEX(Curves!$AR$8:$AR$68,$A14-Inputs!$C$31+1),0)*Products!$F$27*Products!$F$28*Products!$F$13 | AT14: =IF($A14=Inputs!$C$33,Products!$F$30*Inputs!$C$10*Inputs!$C$32,0) | AU14: =AN14*(1-Inputs!$C$24)-Inputs!$C$25*AQ14+AS14+AT14 | AV14: =AV13+AU14 | AX14: =(1-Products!$G$41)^$A14 | AY14: =IF(AND($A14>=1,$A14<=Products!$G$16),Products!$G$33,0) | AZ14: =AY14*Products!$G$42*AX14 | BA14: =AY14-AZ14 | BB14: =(1-AX14)*MAX(0,Products!$G$16-$A14)*(Products!$G$33-Products!$G$35/Products!$G$16) | BC14: =IF($A14<=Products!$G$16,AX14,0) | BD14: =IF(AND($A14>=1,$A14<=Products!$G$16),AX13-AX14,0) | BE14: =IF(AND($A14-Inputs!$C$31>=1,$A14-Inputs!$C$31<=Products!$G$16),INDEX(Curves!$BD$8:$BD$68,$A14-Inputs!$C$31+1),0)*Products!$G$27*Products!$G$28*Products!$G$13 | BF14: =IF($A14=Inputs!$C$33,Products!$G$30*Inputs!$C$10*Inputs!$C$32,0) | BG14: =AZ14*(1-Inputs!$C$24)-Inputs!$C$25*BC14+BE14+BF14 | BH14: =BH13+BG14
A15: 7 | B15: =(1-Products!$C$41)^$A15 | C15: =IF(AND($A15>=1,$A15<=Products!$C$16),Products!$C$33,0) | D15: =C15*Products!$C$42*B15 | E15: =C15-D15 | F15: =(1-B15)*MAX(0,Products!$C$16-$A15)*(Products!$C$33-Products!$C$35/Products!$C$16) | G15: =IF($A15<=Products!$C$16,B15,0) | H15: =IF(AND($A15>=1,$A15<=Products!$C$16),B14-B15,0) | I15: =IF(AND($A15-Inputs!$C$31>=1,$A15-Inputs!$C$31<=Products!$C$16),INDEX(Curves!$H$8:$H$68,$A15-Inputs!$C$31+1),0)*Products!$C$27*Products!$C$28*Products!$C$13 | J15: =IF($A15=Inputs!$C$33,Products!$C$30*Inputs!$C$10*Inputs!$C$32,0) | K15: =D15*(1-Inputs!$C$24)-Inputs!$C$25*G15+I15+J15 | L15: =L14+K15 | N15: =(1-Products!$D$41)^$A15 | O15: =IF(AND($A15>=1,$A15<=Products!$D$16),Products!$D$33,0) | P15: =O15*Products!$D$42*N15 | Q15: =O15-P15 | R15: =(1-N15)*MAX(0,Products!$D$16-$A15)*(Products!$D$33-Products!$D$35/Products!$D$16) | S15: =IF($A15<=Products!$D$16,N15,0) | T15: =IF(AND($A15>=1,$A15<=Products!$D$16),N14-N15,0) | U15: =IF(AND($A15-Inputs!$C$31>=1,$A15-Inputs!$C$31<=Products!$D$16),INDEX(Curves!$T$8:$T$68,$A15-Inputs!$C$31+1),0)*Products!$D$27*Products!$D$28*Products!$D$13 | V15: =IF($A15=Inputs!$C$33,Products!$D$30*Inputs!$C$10*Inputs!$C$32,0) | W15: =P15*(1-Inputs!$C$24)-Inputs!$C$25*S15+U15+V15 | X15: =X14+W15 | Z15: =(1-Products!$E$41)^$A15 | AA15: =IF(AND($A15>=1,$A15<=Products!$E$16),Products!$E$33,0) | AB15: =AA15*Products!$E$42*Z15 | AC15: =AA15-AB15 | AD15: =(1-Z15)*MAX(0,Products!$E$16-$A15)*(Products!$E$33-Products!$E$35/Products!$E$16) | AE15: =IF($A15<=Products!$E$16,Z15,0) | AF15: =IF(AND($A15>=1,$A15<=Products!$E$16),Z14-Z15,0) | AG15: =IF(AND($A15-Inputs!$C$31>=1,$A15-Inputs!$C$31<=Products!$E$16),INDEX(Curves!$AF$8:$AF$68,$A15-Inputs!$C$31+1),0)*Products!$E$27*Products!$E$28*Products!$E$13 | AH15: =IF($A15=Inputs!$C$33,Products!$E$30*Inputs!$C$10*Inputs!$C$32,0) | AI15: =AB15*(1-Inputs!$C$24)-Inputs!$C$25*AE15+AG15+AH15 | AJ15: =AJ14+AI15 | AL15: =(1-Products!$F$41)^$A15 | AM15: =IF(AND($A15>=1,$A15<=Products!$F$16),Products!$F$33,0) | AN15: =AM15*Products!$F$42*AL15 | AO15: =AM15-AN15 | AP15: =(1-AL15)*MAX(0,Products!$F$16-$A15)*(Products!$F$33-Products!$F$35/Products!$F$16) | AQ15: =IF($A15<=Products!$F$16,AL15,0) | AR15: =IF(AND($A15>=1,$A15<=Products!$F$16),AL14-AL15,0) | AS15: =IF(AND($A15-Inputs!$C$31>=1,$A15-Inputs!$C$31<=Products!$F$16),INDEX(Curves!$AR$8:$AR$68,$A15-Inputs!$C$31+1),0)*Products!$F$27*Products!$F$28*Products!$F$13 | AT15: =IF($A15=Inputs!$C$33,Products!$F$30*Inputs!$C$10*Inputs!$C$32,0) | AU15: =AN15*(1-Inputs!$C$24)-Inputs!$C$25*AQ15+AS15+AT15 | AV15: =AV14+AU15 | AX15: =(1-Products!$G$41)^$A15 | AY15: =IF(AND($A15>=1,$A15<=Products!$G$16),Products!$G$33,0) | AZ15: =AY15*Products!$G$42*AX15 | BA15: =AY15-AZ15 | BB15: =(1-AX15)*MAX(0,Products!$G$16-$A15)*(Products!$G$33-Products!$G$35/Products!$G$16) | BC15: =IF($A15<=Products!$G$16,AX15,0) | BD15: =IF(AND($A15>=1,$A15<=Products!$G$16),AX14-AX15,0) | BE15: =IF(AND($A15-Inputs!$C$31>=1,$A15-Inputs!$C$31<=Products!$G$16),INDEX(Curves!$BD$8:$BD$68,$A15-Inputs!$C$31+1),0)*Products!$G$27*Products!$G$28*Products!$G$13 | BF15: =IF($A15=Inputs!$C$33,Products!$G$30*Inputs!$C$10*Inputs!$C$32,0) | BG15: =AZ15*(1-Inputs!$C$24)-Inputs!$C$25*BC15+BE15+BF15 | BH15: =BH14+BG15
A16: 8 | B16: =(1-Products!$C$41)^$A16 | C16: =IF(AND($A16>=1,$A16<=Products!$C$16),Products!$C$33,0) | D16: =C16*Products!$C$42*B16 | E16: =C16-D16 | F16: =(1-B16)*MAX(0,Products!$C$16-$A16)*(Products!$C$33-Products!$C$35/Products!$C$16) | G16: =IF($A16<=Products!$C$16,B16,0) | H16: =IF(AND($A16>=1,$A16<=Products!$C$16),B15-B16,0) | I16: =IF(AND($A16-Inputs!$C$31>=1,$A16-Inputs!$C$31<=Products!$C$16),INDEX(Curves!$H$8:$H$68,$A16-Inputs!$C$31+1),0)*Products!$C$27*Products!$C$28*Products!$C$13 | J16: =IF($A16=Inputs!$C$33,Products!$C$30*Inputs!$C$10*Inputs!$C$32,0) | K16: =D16*(1-Inputs!$C$24)-Inputs!$C$25*G16+I16+J16 | L16: =L15+K16 | N16: =(1-Products!$D$41)^$A16 | O16: =IF(AND($A16>=1,$A16<=Products!$D$16),Products!$D$33,0) | P16: =O16*Products!$D$42*N16 | Q16: =O16-P16 | R16: =(1-N16)*MAX(0,Products!$D$16-$A16)*(Products!$D$33-Products!$D$35/Products!$D$16) | S16: =IF($A16<=Products!$D$16,N16,0) | T16: =IF(AND($A16>=1,$A16<=Products!$D$16),N15-N16,0) | U16: =IF(AND($A16-Inputs!$C$31>=1,$A16-Inputs!$C$31<=Products!$D$16),INDEX(Curves!$T$8:$T$68,$A16-Inputs!$C$31+1),0)*Products!$D$27*Products!$D$28*Products!$D$13 | V16: =IF($A16=Inputs!$C$33,Products!$D$30*Inputs!$C$10*Inputs!$C$32,0) | W16: =P16*(1-Inputs!$C$24)-Inputs!$C$25*S16+U16+V16 | X16: =X15+W16 | Z16: =(1-Products!$E$41)^$A16 | AA16: =IF(AND($A16>=1,$A16<=Products!$E$16),Products!$E$33,0) | AB16: =AA16*Products!$E$42*Z16 | AC16: =AA16-AB16 | AD16: =(1-Z16)*MAX(0,Products!$E$16-$A16)*(Products!$E$33-Products!$E$35/Products!$E$16) | AE16: =IF($A16<=Products!$E$16,Z16,0) | AF16: =IF(AND($A16>=1,$A16<=Products!$E$16),Z15-Z16,0) | AG16: =IF(AND($A16-Inputs!$C$31>=1,$A16-Inputs!$C$31<=Products!$E$16),INDEX(Curves!$AF$8:$AF$68,$A16-Inputs!$C$31+1),0)*Products!$E$27*Products!$E$28*Products!$E$13 | AH16: =IF($A16=Inputs!$C$33,Products!$E$30*Inputs!$C$10*Inputs!$C$32,0) | AI16: =AB16*(1-Inputs!$C$24)-Inputs!$C$25*AE16+AG16+AH16 | AJ16: =AJ15+AI16 | AL16: =(1-Products!$F$41)^$A16 | AM16: =IF(AND($A16>=1,$A16<=Products!$F$16),Products!$F$33,0) | AN16: =AM16*Products!$F$42*AL16 | AO16: =AM16-AN16 | AP16: =(1-AL16)*MAX(0,Products!$F$16-$A16)*(Products!$F$33-Products!$F$35/Products!$F$16) | AQ16: =IF($A16<=Products!$F$16,AL16,0) | AR16: =IF(AND($A16>=1,$A16<=Products!$F$16),AL15-AL16,0) | AS16: =IF(AND($A16-Inputs!$C$31>=1,$A16-Inputs!$C$31<=Products!$F$16),INDEX(Curves!$AR$8:$AR$68,$A16-Inputs!$C$31+1),0)*Products!$F$27*Products!$F$28*Products!$F$13 | AT16: =IF($A16=Inputs!$C$33,Products!$F$30*Inputs!$C$10*Inputs!$C$32,0) | AU16: =AN16*(1-Inputs!$C$24)-Inputs!$C$25*AQ16+AS16+AT16 | AV16: =AV15+AU16 | AX16: =(1-Products!$G$41)^$A16 | AY16: =IF(AND($A16>=1,$A16<=Products!$G$16),Products!$G$33,0) | AZ16: =AY16*Products!$G$42*AX16 | BA16: =AY16-AZ16 | BB16: =(1-AX16)*MAX(0,Products!$G$16-$A16)*(Products!$G$33-Products!$G$35/Products!$G$16) | BC16: =IF($A16<=Products!$G$16,AX16,0) | BD16: =IF(AND($A16>=1,$A16<=Products!$G$16),AX15-AX16,0) | BE16: =IF(AND($A16-Inputs!$C$31>=1,$A16-Inputs!$C$31<=Products!$G$16),INDEX(Curves!$BD$8:$BD$68,$A16-Inputs!$C$31+1),0)*Products!$G$27*Products!$G$28*Products!$G$13 | BF16: =IF($A16=Inputs!$C$33,Products!$G$30*Inputs!$C$10*Inputs!$C$32,0) | BG16: =AZ16*(1-Inputs!$C$24)-Inputs!$C$25*BC16+BE16+BF16 | BH16: =BH15+BG16
A17: 9 | B17: =(1-Products!$C$41)^$A17 | C17: =IF(AND($A17>=1,$A17<=Products!$C$16),Products!$C$33,0) | D17: =C17*Products!$C$42*B17 | E17: =C17-D17 | F17: =(1-B17)*MAX(0,Products!$C$16-$A17)*(Products!$C$33-Products!$C$35/Products!$C$16) | G17: =IF($A17<=Products!$C$16,B17,0) | H17: =IF(AND($A17>=1,$A17<=Products!$C$16),B16-B17,0) | I17: =IF(AND($A17-Inputs!$C$31>=1,$A17-Inputs!$C$31<=Products!$C$16),INDEX(Curves!$H$8:$H$68,$A17-Inputs!$C$31+1),0)*Products!$C$27*Products!$C$28*Products!$C$13 | J17: =IF($A17=Inputs!$C$33,Products!$C$30*Inputs!$C$10*Inputs!$C$32,0) | K17: =D17*(1-Inputs!$C$24)-Inputs!$C$25*G17+I17+J17 | L17: =L16+K17 | N17: =(1-Products!$D$41)^$A17 | O17: =IF(AND($A17>=1,$A17<=Products!$D$16),Products!$D$33,0) | P17: =O17*Products!$D$42*N17 | Q17: =O17-P17 | R17: =(1-N17)*MAX(0,Products!$D$16-$A17)*(Products!$D$33-Products!$D$35/Products!$D$16) | S17: =IF($A17<=Products!$D$16,N17,0) | T17: =IF(AND($A17>=1,$A17<=Products!$D$16),N16-N17,0) | U17: =IF(AND($A17-Inputs!$C$31>=1,$A17-Inputs!$C$31<=Products!$D$16),INDEX(Curves!$T$8:$T$68,$A17-Inputs!$C$31+1),0)*Products!$D$27*Products!$D$28*Products!$D$13 | V17: =IF($A17=Inputs!$C$33,Products!$D$30*Inputs!$C$10*Inputs!$C$32,0) | W17: =P17*(1-Inputs!$C$24)-Inputs!$C$25*S17+U17+V17 | X17: =X16+W17 | Z17: =(1-Products!$E$41)^$A17 | AA17: =IF(AND($A17>=1,$A17<=Products!$E$16),Products!$E$33,0) | AB17: =AA17*Products!$E$42*Z17 | AC17: =AA17-AB17 | AD17: =(1-Z17)*MAX(0,Products!$E$16-$A17)*(Products!$E$33-Products!$E$35/Products!$E$16) | AE17: =IF($A17<=Products!$E$16,Z17,0) | AF17: =IF(AND($A17>=1,$A17<=Products!$E$16),Z16-Z17,0) | AG17: =IF(AND($A17-Inputs!$C$31>=1,$A17-Inputs!$C$31<=Products!$E$16),INDEX(Curves!$AF$8:$AF$68,$A17-Inputs!$C$31+1),0)*Products!$E$27*Products!$E$28*Products!$E$13 | AH17: =IF($A17=Inputs!$C$33,Products!$E$30*Inputs!$C$10*Inputs!$C$32,0) | AI17: =AB17*(1-Inputs!$C$24)-Inputs!$C$25*AE17+AG17+AH17 | AJ17: =AJ16+AI17 | AL17: =(1-Products!$F$41)^$A17 | AM17: =IF(AND($A17>=1,$A17<=Products!$F$16),Products!$F$33,0) | AN17: =AM17*Products!$F$42*AL17 | AO17: =AM17-AN17 | AP17: =(1-AL17)*MAX(0,Products!$F$16-$A17)*(Products!$F$33-Products!$F$35/Products!$F$16) | AQ17: =IF($A17<=Products!$F$16,AL17,0) | AR17: =IF(AND($A17>=1,$A17<=Products!$F$16),AL16-AL17,0) | AS17: =IF(AND($A17-Inputs!$C$31>=1,$A17-Inputs!$C$31<=Products!$F$16),INDEX(Curves!$AR$8:$AR$68,$A17-Inputs!$C$31+1),0)*Products!$F$27*Products!$F$28*Products!$F$13 | AT17: =IF($A17=Inputs!$C$33,Products!$F$30*Inputs!$C$10*Inputs!$C$32,0) | AU17: =AN17*(1-Inputs!$C$24)-Inputs!$C$25*AQ17+AS17+AT17 | AV17: =AV16+AU17 | AX17: =(1-Products!$G$41)^$A17 | AY17: =IF(AND($A17>=1,$A17<=Products!$G$16),Products!$G$33,0) | AZ17: =AY17*Products!$G$42*AX17 | BA17: =AY17-AZ17 | BB17: =(1-AX17)*MAX(0,Products!$G$16-$A17)*(Products!$G$33-Products!$G$35/Products!$G$16) | BC17: =IF($A17<=Products!$G$16,AX17,0) | BD17: =IF(AND($A17>=1,$A17<=Products!$G$16),AX16-AX17,0) | BE17: =IF(AND($A17-Inputs!$C$31>=1,$A17-Inputs!$C$31<=Products!$G$16),INDEX(Curves!$BD$8:$BD$68,$A17-Inputs!$C$31+1),0)*Products!$G$27*Products!$G$28*Products!$G$13 | BF17: =IF($A17=Inputs!$C$33,Products!$G$30*Inputs!$C$10*Inputs!$C$32,0) | BG17: =AZ17*(1-Inputs!$C$24)-Inputs!$C$25*BC17+BE17+BF17 | BH17: =BH16+BG17
A18: 10 | B18: =(1-Products!$C$41)^$A18 | C18: =IF(AND($A18>=1,$A18<=Products!$C$16),Products!$C$33,0) | D18: =C18*Products!$C$42*B18 | E18: =C18-D18 | F18: =(1-B18)*MAX(0,Products!$C$16-$A18)*(Products!$C$33-Products!$C$35/Products!$C$16) | G18: =IF($A18<=Products!$C$16,B18,0) | H18: =IF(AND($A18>=1,$A18<=Products!$C$16),B17-B18,0) | I18: =IF(AND($A18-Inputs!$C$31>=1,$A18-Inputs!$C$31<=Products!$C$16),INDEX(Curves!$H$8:$H$68,$A18-Inputs!$C$31+1),0)*Products!$C$27*Products!$C$28*Products!$C$13 | J18: =IF($A18=Inputs!$C$33,Products!$C$30*Inputs!$C$10*Inputs!$C$32,0) | K18: =D18*(1-Inputs!$C$24)-Inputs!$C$25*G18+I18+J18 | L18: =L17+K18 | N18: =(1-Products!$D$41)^$A18 | O18: =IF(AND($A18>=1,$A18<=Products!$D$16),Products!$D$33,0) | P18: =O18*Products!$D$42*N18 | Q18: =O18-P18 | R18: =(1-N18)*MAX(0,Products!$D$16-$A18)*(Products!$D$33-Products!$D$35/Products!$D$16) | S18: =IF($A18<=Products!$D$16,N18,0) | T18: =IF(AND($A18>=1,$A18<=Products!$D$16),N17-N18,0) | U18: =IF(AND($A18-Inputs!$C$31>=1,$A18-Inputs!$C$31<=Products!$D$16),INDEX(Curves!$T$8:$T$68,$A18-Inputs!$C$31+1),0)*Products!$D$27*Products!$D$28*Products!$D$13 | V18: =IF($A18=Inputs!$C$33,Products!$D$30*Inputs!$C$10*Inputs!$C$32,0) | W18: =P18*(1-Inputs!$C$24)-Inputs!$C$25*S18+U18+V18 | X18: =X17+W18 | Z18: =(1-Products!$E$41)^$A18 | AA18: =IF(AND($A18>=1,$A18<=Products!$E$16),Products!$E$33,0) | AB18: =AA18*Products!$E$42*Z18 | AC18: =AA18-AB18 | AD18: =(1-Z18)*MAX(0,Products!$E$16-$A18)*(Products!$E$33-Products!$E$35/Products!$E$16) | AE18: =IF($A18<=Products!$E$16,Z18,0) | AF18: =IF(AND($A18>=1,$A18<=Products!$E$16),Z17-Z18,0) | AG18: =IF(AND($A18-Inputs!$C$31>=1,$A18-Inputs!$C$31<=Products!$E$16),INDEX(Curves!$AF$8:$AF$68,$A18-Inputs!$C$31+1),0)*Products!$E$27*Products!$E$28*Products!$E$13 | AH18: =IF($A18=Inputs!$C$33,Products!$E$30*Inputs!$C$10*Inputs!$C$32,0) | AI18: =AB18*(1-Inputs!$C$24)-Inputs!$C$25*AE18+AG18+AH18 | AJ18: =AJ17+AI18 | AL18: =(1-Products!$F$41)^$A18 | AM18: =IF(AND($A18>=1,$A18<=Products!$F$16),Products!$F$33,0) | AN18: =AM18*Products!$F$42*AL18 | AO18: =AM18-AN18 | AP18: =(1-AL18)*MAX(0,Products!$F$16-$A18)*(Products!$F$33-Products!$F$35/Products!$F$16) | AQ18: =IF($A18<=Products!$F$16,AL18,0) | AR18: =IF(AND($A18>=1,$A18<=Products!$F$16),AL17-AL18,0) | AS18: =IF(AND($A18-Inputs!$C$31>=1,$A18-Inputs!$C$31<=Products!$F$16),INDEX(Curves!$AR$8:$AR$68,$A18-Inputs!$C$31+1),0)*Products!$F$27*Products!$F$28*Products!$F$13 | AT18: =IF($A18=Inputs!$C$33,Products!$F$30*Inputs!$C$10*Inputs!$C$32,0) | AU18: =AN18*(1-Inputs!$C$24)-Inputs!$C$25*AQ18+AS18+AT18 | AV18: =AV17+AU18 | AX18: =(1-Products!$G$41)^$A18 | AY18: =IF(AND($A18>=1,$A18<=Products!$G$16),Products!$G$33,0) | AZ18: =AY18*Products!$G$42*AX18 | BA18: =AY18-AZ18 | BB18: =(1-AX18)*MAX(0,Products!$G$16-$A18)*(Products!$G$33-Products!$G$35/Products!$G$16) | BC18: =IF($A18<=Products!$G$16,AX18,0) | BD18: =IF(AND($A18>=1,$A18<=Products!$G$16),AX17-AX18,0) | BE18: =IF(AND($A18-Inputs!$C$31>=1,$A18-Inputs!$C$31<=Products!$G$16),INDEX(Curves!$BD$8:$BD$68,$A18-Inputs!$C$31+1),0)*Products!$G$27*Products!$G$28*Products!$G$13 | BF18: =IF($A18=Inputs!$C$33,Products!$G$30*Inputs!$C$10*Inputs!$C$32,0) | BG18: =AZ18*(1-Inputs!$C$24)-Inputs!$C$25*BC18+BE18+BF18 | BH18: =BH17+BG18
A19: 11 | B19: =(1-Products!$C$41)^$A19 | C19: =IF(AND($A19>=1,$A19<=Products!$C$16),Products!$C$33,0) | D19: =C19*Products!$C$42*B19 | E19: =C19-D19 | F19: =(1-B19)*MAX(0,Products!$C$16-$A19)*(Products!$C$33-Products!$C$35/Products!$C$16) | G19: =IF($A19<=Products!$C$16,B19,0) | H19: =IF(AND($A19>=1,$A19<=Products!$C$16),B18-B19,0) | I19: =IF(AND($A19-Inputs!$C$31>=1,$A19-Inputs!$C$31<=Products!$C$16),INDEX(Curves!$H$8:$H$68,$A19-Inputs!$C$31+1),0)*Products!$C$27*Products!$C$28*Products!$C$13 | J19: =IF($A19=Inputs!$C$33,Products!$C$30*Inputs!$C$10*Inputs!$C$32,0) | K19: =D19*(1-Inputs!$C$24)-Inputs!$C$25*G19+I19+J19 | L19: =L18+K19 | N19: =(1-Products!$D$41)^$A19 | O19: =IF(AND($A19>=1,$A19<=Products!$D$16),Products!$D$33,0) | P19: =O19*Products!$D$42*N19 | Q19: =O19-P19 | R19: =(1-N19)*MAX(0,Products!$D$16-$A19)*(Products!$D$33-Products!$D$35/Products!$D$16) | S19: =IF($A19<=Products!$D$16,N19,0) | T19: =IF(AND($A19>=1,$A19<=Products!$D$16),N18-N19,0) | U19: =IF(AND($A19-Inputs!$C$31>=1,$A19-Inputs!$C$31<=Products!$D$16),INDEX(Curves!$T$8:$T$68,$A19-Inputs!$C$31+1),0)*Products!$D$27*Products!$D$28*Products!$D$13 | V19: =IF($A19=Inputs!$C$33,Products!$D$30*Inputs!$C$10*Inputs!$C$32,0) | W19: =P19*(1-Inputs!$C$24)-Inputs!$C$25*S19+U19+V19 | X19: =X18+W19 | Z19: =(1-Products!$E$41)^$A19 | AA19: =IF(AND($A19>=1,$A19<=Products!$E$16),Products!$E$33,0) | AB19: =AA19*Products!$E$42*Z19 | AC19: =AA19-AB19 | AD19: =(1-Z19)*MAX(0,Products!$E$16-$A19)*(Products!$E$33-Products!$E$35/Products!$E$16) | AE19: =IF($A19<=Products!$E$16,Z19,0) | AF19: =IF(AND($A19>=1,$A19<=Products!$E$16),Z18-Z19,0) | AG19: =IF(AND($A19-Inputs!$C$31>=1,$A19-Inputs!$C$31<=Products!$E$16),INDEX(Curves!$AF$8:$AF$68,$A19-Inputs!$C$31+1),0)*Products!$E$27*Products!$E$28*Products!$E$13 | AH19: =IF($A19=Inputs!$C$33,Products!$E$30*Inputs!$C$10*Inputs!$C$32,0) | AI19: =AB19*(1-Inputs!$C$24)-Inputs!$C$25*AE19+AG19+AH19 | AJ19: =AJ18+AI19 | AL19: =(1-Products!$F$41)^$A19 | AM19: =IF(AND($A19>=1,$A19<=Products!$F$16),Products!$F$33,0) | AN19: =AM19*Products!$F$42*AL19 | AO19: =AM19-AN19 | AP19: =(1-AL19)*MAX(0,Products!$F$16-$A19)*(Products!$F$33-Products!$F$35/Products!$F$16) | AQ19: =IF($A19<=Products!$F$16,AL19,0) | AR19: =IF(AND($A19>=1,$A19<=Products!$F$16),AL18-AL19,0) | AS19: =IF(AND($A19-Inputs!$C$31>=1,$A19-Inputs!$C$31<=Products!$F$16),INDEX(Curves!$AR$8:$AR$68,$A19-Inputs!$C$31+1),0)*Products!$F$27*Products!$F$28*Products!$F$13 | AT19: =IF($A19=Inputs!$C$33,Products!$F$30*Inputs!$C$10*Inputs!$C$32,0) | AU19: =AN19*(1-Inputs!$C$24)-Inputs!$C$25*AQ19+AS19+AT19 | AV19: =AV18+AU19 | AX19: =(1-Products!$G$41)^$A19 | AY19: =IF(AND($A19>=1,$A19<=Products!$G$16),Products!$G$33,0) | AZ19: =AY19*Products!$G$42*AX19 | BA19: =AY19-AZ19 | BB19: =(1-AX19)*MAX(0,Products!$G$16-$A19)*(Products!$G$33-Products!$G$35/Products!$G$16) | BC19: =IF($A19<=Products!$G$16,AX19,0) | BD19: =IF(AND($A19>=1,$A19<=Products!$G$16),AX18-AX19,0) | BE19: =IF(AND($A19-Inputs!$C$31>=1,$A19-Inputs!$C$31<=Products!$G$16),INDEX(Curves!$BD$8:$BD$68,$A19-Inputs!$C$31+1),0)*Products!$G$27*Products!$G$28*Products!$G$13 | BF19: =IF($A19=Inputs!$C$33,Products!$G$30*Inputs!$C$10*Inputs!$C$32,0) | BG19: =AZ19*(1-Inputs!$C$24)-Inputs!$C$25*BC19+BE19+BF19 | BH19: =BH18+BG19
A20: 12 | B20: =(1-Products!$C$41)^$A20 | C20: =IF(AND($A20>=1,$A20<=Products!$C$16),Products!$C$33,0) | D20: =C20*Products!$C$42*B20 | E20: =C20-D20 | F20: =(1-B20)*MAX(0,Products!$C$16-$A20)*(Products!$C$33-Products!$C$35/Products!$C$16) | G20: =IF($A20<=Products!$C$16,B20,0) | H20: =IF(AND($A20>=1,$A20<=Products!$C$16),B19-B20,0) | I20: =IF(AND($A20-Inputs!$C$31>=1,$A20-Inputs!$C$31<=Products!$C$16),INDEX(Curves!$H$8:$H$68,$A20-Inputs!$C$31+1),0)*Products!$C$27*Products!$C$28*Products!$C$13 | J20: =IF($A20=Inputs!$C$33,Products!$C$30*Inputs!$C$10*Inputs!$C$32,0) | K20: =D20*(1-Inputs!$C$24)-Inputs!$C$25*G20+I20+J20 | L20: =L19+K20 | N20: =(1-Products!$D$41)^$A20 | O20: =IF(AND($A20>=1,$A20<=Products!$D$16),Products!$D$33,0) | P20: =O20*Products!$D$42*N20 | Q20: =O20-P20 | R20: =(1-N20)*MAX(0,Products!$D$16-$A20)*(Products!$D$33-Products!$D$35/Products!$D$16) | S20: =IF($A20<=Products!$D$16,N20,0) | T20: =IF(AND($A20>=1,$A20<=Products!$D$16),N19-N20,0) | U20: =IF(AND($A20-Inputs!$C$31>=1,$A20-Inputs!$C$31<=Products!$D$16),INDEX(Curves!$T$8:$T$68,$A20-Inputs!$C$31+1),0)*Products!$D$27*Products!$D$28*Products!$D$13 | V20: =IF($A20=Inputs!$C$33,Products!$D$30*Inputs!$C$10*Inputs!$C$32,0) | W20: =P20*(1-Inputs!$C$24)-Inputs!$C$25*S20+U20+V20 | X20: =X19+W20 | Z20: =(1-Products!$E$41)^$A20 | AA20: =IF(AND($A20>=1,$A20<=Products!$E$16),Products!$E$33,0) | AB20: =AA20*Products!$E$42*Z20 | AC20: =AA20-AB20 | AD20: =(1-Z20)*MAX(0,Products!$E$16-$A20)*(Products!$E$33-Products!$E$35/Products!$E$16) | AE20: =IF($A20<=Products!$E$16,Z20,0) | AF20: =IF(AND($A20>=1,$A20<=Products!$E$16),Z19-Z20,0) | AG20: =IF(AND($A20-Inputs!$C$31>=1,$A20-Inputs!$C$31<=Products!$E$16),INDEX(Curves!$AF$8:$AF$68,$A20-Inputs!$C$31+1),0)*Products!$E$27*Products!$E$28*Products!$E$13 | AH20: =IF($A20=Inputs!$C$33,Products!$E$30*Inputs!$C$10*Inputs!$C$32,0) | AI20: =AB20*(1-Inputs!$C$24)-Inputs!$C$25*AE20+AG20+AH20 | AJ20: =AJ19+AI20 | AL20: =(1-Products!$F$41)^$A20 | AM20: =IF(AND($A20>=1,$A20<=Products!$F$16),Products!$F$33,0) | AN20: =AM20*Products!$F$42*AL20 | AO20: =AM20-AN20 | AP20: =(1-AL20)*MAX(0,Products!$F$16-$A20)*(Products!$F$33-Products!$F$35/Products!$F$16) | AQ20: =IF($A20<=Products!$F$16,AL20,0) | AR20: =IF(AND($A20>=1,$A20<=Products!$F$16),AL19-AL20,0) | AS20: =IF(AND($A20-Inputs!$C$31>=1,$A20-Inputs!$C$31<=Products!$F$16),INDEX(Curves!$AR$8:$AR$68,$A20-Inputs!$C$31+1),0)*Products!$F$27*Products!$F$28*Products!$F$13 | AT20: =IF($A20=Inputs!$C$33,Products!$F$30*Inputs!$C$10*Inputs!$C$32,0) | AU20: =AN20*(1-Inputs!$C$24)-Inputs!$C$25*AQ20+AS20+AT20 | AV20: =AV19+AU20 | AX20: =(1-Products!$G$41)^$A20 | AY20: =IF(AND($A20>=1,$A20<=Products!$G$16),Products!$G$33,0) | AZ20: =AY20*Products!$G$42*AX20 | BA20: =AY20-AZ20 | BB20: =(1-AX20)*MAX(0,Products!$G$16-$A20)*(Products!$G$33-Products!$G$35/Products!$G$16) | BC20: =IF($A20<=Products!$G$16,AX20,0) | BD20: =IF(AND($A20>=1,$A20<=Products!$G$16),AX19-AX20,0) | BE20: =IF(AND($A20-Inputs!$C$31>=1,$A20-Inputs!$C$31<=Products!$G$16),INDEX(Curves!$BD$8:$BD$68,$A20-Inputs!$C$31+1),0)*Products!$G$27*Products!$G$28*Products!$G$13 | BF20: =IF($A20=Inputs!$C$33,Products!$G$30*Inputs!$C$10*Inputs!$C$32,0) | BG20: =AZ20*(1-Inputs!$C$24)-Inputs!$C$25*BC20+BE20+BF20 | BH20: =BH19+BG20
... A68: 60 | B68: =(1-Products!$C$41)^$A68 | C68: =IF(AND($A68>=1,$A68<=Products!$C$16),Products!$C$33,0) | D68: =C68*Products!$C$42*B68 | E68: =C68-D68 | F68: =(1-B68)*MAX(0,Products!$C$16-$A68)*(Products!$C$33-Products!$C$35/Products!$C$16) | G68: =IF($A68<=Products!$C$16,B68,0) | H68: =IF(AND($A68>=1,$A68<=Products!$C$16),B67-B68,0) | I68: =IF(AND($A68-Inputs!$C$31>=1,$A68-Inputs!$C$31<=Products!$C$16),INDEX(Curves!$H$8:$H$68,$A68-Inputs!$C$31+1),0)*Products!$C$27*Products!$C$28*Products!$C$13 | J68: =IF($A68=Inputs!$C$33,Products!$C$30*Inputs!$C$10*Inputs!$C$32,0) | K68: =D68*(1-Inputs!$C$24)-Inputs!$C$25*G68+I68+J68 | L68: =L67+K68 | N68: =(1-Products!$D$41)^$A68 | O68: =IF(AND($A68>=1,$A68<=Products!$D$16),Products!$D$33,0) | P68: =O68*Products!$D$42*N68 | Q68: =O68-P68 | R68: =(1-N68)*MAX(0,Products!$D$16-$A68)*(Products!$D$33-Products!$D$35/Products!$D$16) | S68: =IF($A68<=Products!$D$16,N68,0) | T68: =IF(AND($A68>=1,$A68<=Products!$D$16),N67-N68,0) | U68: =IF(AND($A68-Inputs!$C$31>=1,$A68-Inputs!$C$31<=Products!$D$16),INDEX(Curves!$T$8:$T$68,$A68-Inputs!$C$31+1),0)*Products!$D$27*Products!$D$28*Products!$D$13 | V68: =IF($A68=Inputs!$C$33,Products!$D$30*Inputs!$C$10*Inputs!$C$32,0) | W68: =P68*(1-Inputs!$C$24)-Inputs!$C$25*S68+U68+V68 | X68: =X67+W68 | Z68: =(1-Products!$E$41)^$A68 | AA68: =IF(AND($A68>=1,$A68<=Products!$E$16),Products!$E$33,0) | AB68: =AA68*Products!$E$42*Z68 | AC68: =AA68-AB68 | AD68: =(1-Z68)*MAX(0,Products!$E$16-$A68)*(Products!$E$33-Products!$E$35/Products!$E$16) | AE68: =IF($A68<=Products!$E$16,Z68,0) | AF68: =IF(AND($A68>=1,$A68<=Products!$E$16),Z67-Z68,0) | AG68: =IF(AND($A68-Inputs!$C$31>=1,$A68-Inputs!$C$31<=Products!$E$16),INDEX(Curves!$AF$8:$AF$68,$A68-Inputs!$C$31+1),0)*Products!$E$27*Products!$E$28*Products!$E$13 | AH68: =IF($A68=Inputs!$C$33,Products!$E$30*Inputs!$C$10*Inputs!$C$32,0) | AI68: =AB68*(1-Inputs!$C$24)-Inputs!$C$25*AE68+AG68+AH68 | AJ68: =AJ67+AI68 | AL68: =(1-Products!$F$41)^$A68 | AM68: =IF(AND($A68>=1,$A68<=Products!$F$16),Products!$F$33,0) | AN68: =AM68*Products!$F$42*AL68 | AO68: =AM68-AN68 | AP68: =(1-AL68)*MAX(0,Products!$F$16-$A68)*(Products!$F$33-Products!$F$35/Products!$F$16) | AQ68: =IF($A68<=Products!$F$16,AL68,0) | AR68: =IF(AND($A68>=1,$A68<=Products!$F$16),AL67-AL68,0) | AS68: =IF(AND($A68-Inputs!$C$31>=1,$A68-Inputs!$C$31<=Products!$F$16),INDEX(Curves!$AR$8:$AR$68,$A68-Inputs!$C$31+1),0)*Products!$F$27*Products!$F$28*Products!$F$13 | AT68: =IF($A68=Inputs!$C$33,Products!$F$30*Inputs!$C$10*Inputs!$C$32,0) | AU68: =AN68*(1-Inputs!$C$24)-Inputs!$C$25*AQ68+AS68+AT68 | AV68: =AV67+AU68 | AX68: =(1-Products!$G$41)^$A68 | AY68: =IF(AND($A68>=1,$A68<=Products!$G$16),Products!$G$33,0) | AZ68: =AY68*Products!$G$42*AX68 | BA68: =AY68-AZ68 | BB68: =(1-AX68)*MAX(0,Products!$G$16-$A68)*(Products!$G$33-Products!$G$35/Products!$G$16) | BC68: =IF($A68<=Products!$G$16,AX68,0) | BD68: =IF(AND($A68>=1,$A68<=Products!$G$16),AX67-AX68,0) | BE68: =IF(AND($A68-Inputs!$C$31>=1,$A68-Inputs!$C$31<=Products!$G$16),INDEX(Curves!$BD$8:$BD$68,$A68-Inputs!$C$31+1),0)*Products!$G$27*Products!$G$28*Products!$G$13 | BF68: =IF($A68=Inputs!$C$33,Products!$G$30*Inputs!$C$10*Inputs!$C$32,0) | BG68: =AZ68*(1-Inputs!$C$24)-Inputs!$C$25*BC68+BE68+BF68 | BH68: =BH67+BG68
A70: Totals per unit | C70: =SUM(C8:C68) | D70: =SUM(D8:D68) | E70: =SUM(E8:E68) | I70: =SUM(I8:I68) | J70: =SUM(J8:J68) | O70: =SUM(O8:O68) | P70: =SUM(P8:P68) | Q70: =SUM(Q8:Q68) | U70: =SUM(U8:U68) | V70: =SUM(V8:V68) | AA70: =SUM(AA8:AA68) | AB70: =SUM(AB8:AB68) | AC70: =SUM(AC8:AC68) | AG70: =SUM(AG8:AG68) | AH70: =SUM(AH8:AH68) | AM70: =SUM(AM8:AM68) | AN70: =SUM(AN8:AN68) | AO70: =SUM(AO8:AO68) | AS70: =SUM(AS8:AS68) | AT70: =SUM(AT8:AT68) | AY70: =SUM(AY8:AY68) | AZ70: =SUM(AZ8:AZ68) | BA70: =SUM(BA8:BA68) | BE70: =SUM(BE8:BE68) | BF70: =SUM(BF8:BF68)

Sheet Cohort_T1
A1: Cohort (vintage) analysis - Tier 1 - Pico solar kit
A2: Rows = sales cohort (month of sale); columns = calendar month. Cohort size in column C.
A4: Month # | D4: Opening | E4: =Timeline!E4 | F4: =Timeline!F4 | G4: =Timeline!G4 | H4: =Timeline!H4 | I4: =Timeline!I4 | J4: =Timeline!J4 | K4: =Timeline!K4 | L4: =Timeline!L4 | ... BL4: =Timeline!BL4
A5: Period end | E5: =Timeline!E5 | F5: =Timeline!F5 | G5: =Timeline!G5 | H5: =Timeline!H5 | I5: =Timeline!I5 | J5: =Timeline!J5 | K5: =Timeline!K5 | L5: =Timeline!L5 | ... BL5: =Timeline!BL5
A6: Year # | E6: =Timeline!E6 | F6: =Timeline!F6 | G6: =Timeline!G6 | H6: =Timeline!H6 | I6: =Timeline!I6 | J6: =Timeline!J6 | K6: =Timeline!K6 | L6: =Timeline!L6 | ... BL6: =Timeline!BL6
A8: Instalments collected by cohort (LCY)
A9: Total | E9: =SUM(E10:E69) | F9: =SUM(F10:F69) | G9: =SUM(G10:G69) | H9: =SUM(H10:H69) | I9: =SUM(I10:I69) | J9: =SUM(J10:J69) | K9: =SUM(K10:K69) | L9: =SUM(L10:L69) | ... BL9: =SUM(BL10:BL69)
A10: Cohort month 1 | B10: 1 | C10: =INDEX(Ops!$E$10:$BL$10,1,$B10) | F10: =$C10*INDEX(Curves!$D$8:$D$68,F$4-$B10+1) | G10: =$C10*INDEX(Curves!$D$8:$D$68,G$4-$B10+1) | H10: =$C10*INDEX(Curves!$D$8:$D$68,H$4-$B10+1) | I10: =$C10*INDEX(Curves!$D$8:$D$68,I$4-$B10+1) | J10: =$C10*INDEX(Curves!$D$8:$D$68,J$4-$B10+1) | K10: =$C10*INDEX(Curves!$D$8:$D$68,K$4-$B10+1) | L10: =$C10*INDEX(Curves!$D$8:$D$68,L$4-$B10+1) | M10: =$C10*INDEX(Curves!$D$8:$D$68,M$4-$B10+1) | ... BL10: =$C10*INDEX(Curves!$D$8:$D$68,BL$4-$B10+1)
A11: Cohort month 2 | B11: 2 | C11: =INDEX(Ops!$E$10:$BL$10,1,$B11) | G11: =$C11*INDEX(Curves!$D$8:$D$68,G$4-$B11+1) | H11: =$C11*INDEX(Curves!$D$8:$D$68,H$4-$B11+1) | I11: =$C11*INDEX(Curves!$D$8:$D$68,I$4-$B11+1) | J11: =$C11*INDEX(Curves!$D$8:$D$68,J$4-$B11+1) | K11: =$C11*INDEX(Curves!$D$8:$D$68,K$4-$B11+1) | L11: =$C11*INDEX(Curves!$D$8:$D$68,L$4-$B11+1) | M11: =$C11*INDEX(Curves!$D$8:$D$68,M$4-$B11+1) | N11: =$C11*INDEX(Curves!$D$8:$D$68,N$4-$B11+1) | ... BL11: =$C11*INDEX(Curves!$D$8:$D$68,BL$4-$B11+1)
A12: Cohort month 3 | B12: 3 | C12: =INDEX(Ops!$E$10:$BL$10,1,$B12) | H12: =$C12*INDEX(Curves!$D$8:$D$68,H$4-$B12+1) | I12: =$C12*INDEX(Curves!$D$8:$D$68,I$4-$B12+1) | J12: =$C12*INDEX(Curves!$D$8:$D$68,J$4-$B12+1) | K12: =$C12*INDEX(Curves!$D$8:$D$68,K$4-$B12+1) | L12: =$C12*INDEX(Curves!$D$8:$D$68,L$4-$B12+1) | M12: =$C12*INDEX(Curves!$D$8:$D$68,M$4-$B12+1) | N12: =$C12*INDEX(Curves!$D$8:$D$68,N$4-$B12+1) | O12: =$C12*INDEX(Curves!$D$8:$D$68,O$4-$B12+1) | ... BL12: =$C12*INDEX(Curves!$D$8:$D$68,BL$4-$B12+1)
