Workbook

Sheet Start Here
B2: Energy Access Fund Manager Model - RBF & Portfolio Edition
B3: From funding to impact | Screen, score and allocate RBF and grant funding across an energy-access project pipeline
B5: THE QUESTION THIS MODEL ANSWERS
B6: Which projects should the fund support, with how much RBF and grant, and what portfolio of connections, impact, leverage and risk does that buy?
B8: WORKFLOW
B9: 1. Fund Parameters - envelope, costs, fund profile (RBF rates, grant share, caps, tranches), eligibility rules, scoring weights, limits.
B10: 2. Pipeline - one row per applicant project. Outputs of the Developer Edition (CAPEX, viability gap, CO2) can be pasted here.
B11: 3. Eligibility & Scoring - eligibility tests, maximum support, request, cost-effectiveness, leverage, additionality and weighted score.
B12: 4. Allocation - projects funded in rank order until the envelope is used, within project and country concentration limits.
B13: 5. Disbursements - grant at commissioning, RBF by tranche as connections are verified, adjusted for expected delivery by risk rating.
B14: 6. MRV Tracker - verified connections to date against targets, RBF earned and outstanding, status per project.
B15: 7. Portfolio Dashboard - commitments, disbursements, connections, people, CO2, leverage, cost per connection, concentration and risk.
... B34: Not investment, legal or tax advice. Licence: single user / single organisation. No resale or redistribution.

Sheet Fund Parameters
A1: FUND PARAMETERS
A2: Edit yellow cells only. All values are illustrative and do not describe any real fund.
A4: 1. FUND
A5: Fund name | B5: Example Energy Access Fund
A6: Fund manager | B6: Example Fund Manager
A7: Currency label | B7: USD | H7: Label only. Enter every amount in this currency.
A8: First fund year (calendar) | B8: 2027
A9: Total fund size | B9: 3000000
A10: Fund management & MRV costs | B10: 0.07 | H10: Share of fund size.
A11: Technical assistance window | B11: 0.08 | H11: Share of fund size, not allocated to projects.
A12: Funds available for project allocation | B12: =FundSize*(1-MgmtPct-TAPct) -> 2550000
A13: Over-commitment ratio | B13: 1 | H13: Commit above available funds to offset expected under-delivery of connections.
A14: Allocation envelope (commitment limit) | B14: =Available*Overcommit -> 2550000
A15: Allow partial funding of the marginal project? (1 = yes) | B15: 1
A16: Maximum share of the envelope per project | B16: 0.15
A17: Maximum share of the envelope per country | B17: 0.5
A18: Additionality tolerance above the viability gap | B18: 0.1 | H18: A request up to viability gap x (1 + tolerance) counts as additional.
A19: Average household size | B19: 5
A21: 2. FUND PROFILE (support rules)
A22: Active profile | B22: Capex grant + RBF | H22: Generic profiles. Configure 'Custom' to mirror a specific programme's published rules.
A24: Rule | B24: Active | C24: Per-connection RBF | D24: Capex grant + RBF | E24: Productive-use focus | F24: Custom
A25: RBF per household connection | B25: =INDEX(C25:F25,1,MATCH(ProfileName,$C$24:$F$24,0)) -> 100 | C25: 150 | D25: 100 | E25: 100 | F25: 150
A26: RBF per productive-use connection | B26: =INDEX(C26:F26,1,MATCH(ProfileName,$C$24:$F$24,0)) -> 300 | C26: 400 | D26: 300 | E26: 600 | F26: 400
A27: RBF per commercial connection | B27: =INDEX(C27:F27,1,MATCH(ProfileName,$C$24:$F$24,0)) -> 200 | C27: 250 | D27: 200 | E27: 250 | F27: 250
A28: RBF per institution connection | B28: =INDEX(C28:F28,1,MATCH(ProfileName,$C$24:$F$24,0)) -> 250 | C28: 300 | D28: 250 | E28: 300 | F28: 300
A29: CAPEX grant (share of project CAPEX) | B29: =INDEX(C29:F29,1,MATCH(ProfileName,$C$24:$F$24,0)) -> 0.25 | C29: 0 | D29: 0.25 | E29: 0.1 | F29: 0
A30: Maximum public support (share of CAPEX, all sources) | B30: =INDEX(C30:F30,1,MATCH(ProfileName,$C$24:$F$24,0)) -> 0.6 | C30: 0.5 | D30: 0.6 | E30: 0.55 | F30: 0.5
A31: Maximum support per project | B31: =INDEX(C31:F31,1,MATCH(ProfileName,$C$24:$F$24,0)) -> 750000 | C31: 600000 | D31: 750000 | E31: 700000 | F31: 600000
A32: RBF tranche paid at verification | B32: =INDEX(C32:F32,1,MATCH(ProfileName,$C$24:$F$24,0)) -> 0.7 | C32: 0.8 | D32: 0.7 | E32: 0.7 | F32: 0.8
A33: RBF verification lag (years) | B33: =INDEX(C33:F33,1,MATCH(ProfileName,$C$24:$F$24,0)) -> 0 | C33: 0 | D33: 0 | E33: 0 | F33: 0
A34: The remaining RBF tranche (1 - tranche at verification) is paid one year later, after a service-continuity check.
A35: Connections verified in commissioning year (share of target) | B35: 0.6
A36: Connections verified by end of the following year (cumulative) | B36: 0.9 | H36: The rest is verified in the third year.
A38: 3. ELIGIBILITY CRITERIA (1 = apply)
A39: Criterion | B39: Threshold | C39: Apply?
A40: Minimum number of connections | B40: 200 | C40: 1
A41: Maximum CAPEX per connection | B41: 2000 | C41: 1
A42: Minimum renewable share of generation | B42: 0.6 | C42: 1
A43: Minimum private co-finance (equity + debt) / CAPEX | B43: 0.2 | C43: 1
A44: Minimum readiness stage (1-5) | B44: 3 | C44: 1
A45: Maximum average tariff per kWh (affordability) | B45: 0.6 | C45: 1
A46: Minimum productive-use share of connections | B46: 0.04 | C46: 1
A47: Country must be listed as eligible (table below) | B47: - | C47: 1
A49: 4. ELIGIBLE COUNTRIES
A50: Country | B50: Eligible? (Y/N)
A51: Country A | B51: Y
A52: Country B | B52: Y
A53: Country C | B53: N
A54: Country D | B54: Y
A60: 5. SCORING WEIGHTS (must total 100%)
A61: Criterion | B61: Weight
A62: Cost-effectiveness (fund support per connection, lower is better) | B62: 0.25
A63: Leverage (private capital per $ of fund support) | B63: 0.15
A64: Productive-use share of connections | B64: 0.15
A65: Climate (lifetime CO2 avoided per $ of fund support) | B65: 0.1
A66: Readiness stage | B66: 0.1
A67: Developer track record | B67: 0.1
A68: Risk rating (lower risk is better) | B68: 0.05
A69: Additionality (request within viability gap) | B69: 0.1
A70: Total weights | B70: =SUM(B62:B69) -> 1
A72: 6. EXPECTED DELIVERY BY RISK RATING
A73: Risk rating | B73: Expected share of target connections delivered
A74: 1 | B74: 1
A75: 2 | B75: 0.95
A76: 3 | B76: 0.9
A77: 4 | B77: 0.8
A78: 5 | B78: 0.7
A79: 1 = lowest risk, 5 = highest. Calibrate on the fund's own delivery history where available.

Sheet Pipeline
A1: PROJECT PIPELINE
A2: One row per applicant. Projects and figures are illustrative. Paste CAPEX, viability gap and CO2 from the Developer Edition where available.
A3: Viability gap and amount requested are optional: leave blank if unknown. Technology is descriptive only.
A6: # | B6: Project | C6: Country | D6: Developer | E6: Technology | F6: Readiness (1-5) | G6: Track record (1-5) | H6: Risk rating (1-5) | I6: Commissioning (fund year) | J6: Household connections | K6: Productive-use connections | L6: Commercial connections | M6: Institution connections | N6: Project CAPEX | O6: Developer equity | P6: Debt secured | Q6: Other grants | R6: Average tariff per kWh | S6: Renewable share | T6: Lifetime CO2 avoided (tCO2) | U6: Viability gap (from Developer model) | V6: Amount requested (optional)
A7: 1 | B7: Project A - Lake village cluster | C7: Country A | D7: Developer 1 | E7: Mini-grid | F7: 4 | G7: 4 | H7: 2 | I7: 1 | J7: 900 | K7: 60 | L7: 110 | M7: 10 | N7: 1300000 | O7: 300000 | P7: 250000 | Q7: 0 | R7: 0.38 | S7: 0.75 | T7: 7000 | U7: 820000
A8: 2 | B8: Project B - River towns | C8: Country A | D8: Developer 2 | E8: Mini-grid | F8: 3 | G8: 3 | H8: 3 | I8: 2 | J8: 600 | K8: 30 | L8: 60 | M8: 6 | N8: 950000 | O8: 200000 | P8: 150000 | Q8: 0 | R8: 0.42 | S8: 0.85 | T8: 4500 | U8: 600000
A9: 3 | B9: Project C - Northern corridor | C9: Country B | D9: Developer 3 | E9: Mini-grid | F9: 5 | G9: 5 | H9: 1 | I9: 1 | J9: 1400 | K9: 120 | L9: 180 | M9: 14 | N9: 2000000 | O9: 500000 | P9: 500000 | Q9: 100000 | R9: 0.35 | S9: 0.9 | T9: 12000 | U9: 1100000
A10: 4 | B10: Project D - Island grids | C10: Country B | D10: Developer 1 | E10: Hybrid | F10: 2 | G10: 4 | H10: 3 | I10: 3 | J10: 500 | K10: 40 | L10: 50 | M10: 5 | N10: 900000 | O10: 150000 | P10: 100000 | Q10: 0 | R10: 0.45 | S10: 0.7 | T10: 3500
A11: 5 | B11: Project E - Highland villages | C11: Country C | D11: Developer 4 | E11: Mini-grid | F11: 4 | G11: 3 | H11: 3 | I11: 2 | J11: 700 | K11: 50 | L11: 70 | M11: 8 | N11: 1050000 | O11: 200000 | P11: 200000 | Q11: 0 | R11: 0.4 | S11: 0.8 | T11: 5200 | U11: 650000
A12: 6 | B12: Project F - Market towns | C12: Country A | D12: Developer 5 | E12: Hybrid | F12: 4 | G12: 2 | H12: 4 | I12: 2 | J12: 800 | K12: 60 | L12: 120 | M12: 8 | N12: 1100000 | O12: 250000 | P12: 200000 | Q12: 0 | R12: 0.36 | S12: 0.5 | T12: 3000
A13: 7 | B13: Project G - Remote valley | C13: Country D | D13: Developer 6 | E13: Mini-grid | F13: 3 | G13: 3 | H13: 4 | I13: 3 | J13: 300 | K13: 20 | L13: 30 | M13: 4 | N13: 900000 | O13: 150000 | P13: 50000 | Q13: 0 | R13: 0.55 | S13: 0.9 | T13: 2500 | U13: 700000
A14: 8 | B14: Project H - Agro-processing hub | C14: Country B | D14: Developer 2 | E14: Mini-grid | F14: 4 | G14: 3 | H14: 2 | I14: 2 | J14: 650 | K14: 140 | L14: 80 | M14: 6 | N14: 1200000 | O14: 300000 | P14: 300000 | Q14: 0 | R14: 0.33 | S14: 0.85 | T14: 6500 | U14: 550000
A15: 9 | B15: Project I - Fishing communities | C15: Country D | D15: Developer 7 | E15: Mini-grid | F15: 3 | G15: 2 | H15: 3 | I15: 2 | J15: 750 | K15: 70 | L15: 90 | M15: 7 | N15: 1150000 | O15: 200000 | P15: 150000 | Q15: 50000 | R15: 0.4 | S15: 0.8 | T15: 5000 | U15: 700000 | V15: 450000
A16: 10 | B16: Project J - Health and schools first | C16: Country A | D16: Developer 8 | E16: Mini-grid | F16: 4 | G16: 4 | H16: 2 | I16: 1 | J16: 550 | K16: 25 | L16: 50 | M16: 25 | N16: 900000 | O16: 200000 | P16: 150000 | Q16: 0 | R16: 0.39 | S16: 0.95 | T16: 4200 | U16: 520000
A17: 11 | B17: Project K - Peri-urban extension | C17: Country B | D17: Developer 9 | E17: Mini-grid | F17: 5 | G17: 4 | H17: 2 | I17: 1 | J17: 1200 | K17: 90 | L17: 160 | M17: 10 | N17: 1500000 | O17: 400000 | P17: 400000 | Q17: 0 | R17: 0.32 | S17: 0.8 | T17: 8000 | U17: 450000
A18: 12 | B18: Project L - Mining belt | C18: Country D | D18: Developer 3 | E18: Hybrid | F18: 3 | G18: 5 | H18: 3 | I18: 2 | J18: 1000 | K18: 150 | L18: 140 | M18: 8 | N18: 1700000 | O18: 400000 | P18: 300000 | Q18: 0 | R18: 0.41 | S18: 0.75 | T18: 7500 | U18: 900000
A19: 13 | B19: Project M - Small pilot | C19: Country A | D19: Developer 10 | E19: Mini-grid | F19: 3 | G19: 2 | H19: 4 | I19: 2 | J19: 150 | K19: 10 | L19: 20 | M19: 2 | N19: 300000 | O19: 50000 | P19: 0 | Q19: 0 | R19: 0.5 | S19: 0.9 | T19: 900
A20: 14 | B20: Project N - Lakeside expansion | C20: Country B | D20: Developer 1 | E20: Mini-grid | F20: 4 | G20: 4 | H20: 2 | I20: 2 | J20: 850 | K20: 55 | L20: 100 | M20: 9 | N20: 1250000 | O20: 300000 | P20: 250000 | Q20: 0 | R20: 0.37 | S20: 0.85 | T20: 6800 | U20: 750000
A21: 15
A22: 16
A23: 17
A24: 18
A25: 19
A26: 20
A27: 21
A28: 22
A29: 23
A30: 24
A31: 25

Sheet Eligibility & Scoring
A1: ELIGIBILITY & SCORING
A2: All cells are formulas. 1 = criterion met. Only eligible projects receive a score, a rank and an allocation.
G5: ELIGIBILITY TESTS
A6: # | B6: Project | C6: Total connections | D6: CAPEX per connection | E6: Private co-finance / CAPEX | F6: Productive-use share | G6: Min. connections | H6: Max. CAPEX / connection | I6: Min. renewable share | J6: Min. private co-finance | K6: Min. readiness | L6: Max. tariff | M6: Min. productive use | N6: Eligible country | O6: ELIGIBLE | P6: Eligibility status | Q6: RBF at profile rates | R6: CAPEX grant at profile rate | S6: Maximum support (after caps) | T6: Request considered | U6: RBF share of request | V6: Fund support per connection | W6: Leverage (private / fund) | X6: tCO2 per $1,000 of support | Y6: Additionality check | Z6: Score: cost-effectiveness | AA6: Score: leverage | AB6: Score: productive use | AC6: Score: climate | AD6: Score: readiness | AE6: Score: track record | AF6: Score: risk | AG6: Score: additionality | AH6: WEIGHTED SCORE | AI6: Rank key | AJ6: RANK | AK6: Allocated | AL6: Share of request funded | AM6: Allocation status | AN6: helper: 1 / support per connection | AO6: helper: leverage | AP6: helper: productive share | AQ6: helper: CO2 per $
A7: =1 -> 1 | B7: =IF(Pipeline!$B7<>"",Pipeline!$B7,"") -> Project A - Lake village cluster | C7: =SUM(Pipeline!$J7:$M7) -> 1080 | D7: =IFERROR(Pipeline!$N7/$C7,0) -> 1203.7037 | E7: =IFERROR((Pipeline!$O7+Pipeline!$P7)/Pipeline!$N7,0) -> 0.42307692 | F7: =IFERROR(Pipeline!$K7/$C7,0) -> 0.055555556 | G7: =IF(NOT(Pipeline!$B7<>""),0,IF(E_MinConn_On=1,IF($C7>=E_MinConn,1,0),1)) -> 1 | H7: =IF(NOT(Pipeline!$B7<>""),0,IF(E_MaxCapexConn_On=1,IF($D7<=E_MaxCapexConn,1,0),1)) -> 1 | I7: =IF(NOT(Pipeline!$B7<>""),0,IF(E_MinRE_On=1,IF(Pipeline!$S7>=E_MinRE,1,0),1)) -> 1 | J7: =IF(NOT(Pipeline!$B7<>""),0,IF(E_MinPrivate_On=1,IF($E7>=E_MinPrivate,1,0),1)) -> 1 | K7: =IF(NOT(Pipeline!$B7<>""),0,IF(E_MinReady_On=1,IF(Pipeline!$F7>=E_MinReady,1,0),1)) -> 1 | L7: =IF(NOT(Pipeline!$B7<>""),0,IF(E_MaxTariff_On=1,IF(Pipeline!$R7<=E_MaxTariff,1,0),1)) -> 1 | M7: =IF(NOT(Pipeline!$B7<>""),0,IF(E_MinPU_On=1,IF($F7>=E_MinPU,1,0),1)) -> 1 | N7: =IF(NOT(Pipeline!$B7<>""),0,IF(E_Country_On=1,IF(IFERROR(INDEX('Fund Parameters'!$B$51:$B$58,MATCH(Pipeline!$C7,'Fund Parameters'!$A$51:$A$58,0))="Y",FALSE()),1,0),1)) -> 1 | O7: =IF(AND(Pipeline!$B7<>"",$G7*$H7*$I7*$J7*$K7*$L7*$M7*$N7=1),1,0) -> 1 | P7: =IF(NOT(Pipeline!$B7<>""),"",IF($O7=1,"Eligible",IF($G7=0,"Too few connections",IF($H7=0,"CAPEX per connection too high",IF($I7=0,"Renewable share too low",IF($J7=0,"Private co-finance too low",IF($K7=0,"Not ready enough",IF($L7=0,"Tariff above cap",IF($M7=0,"Productive use too low",IF($N7=0,"Country not eligible","")))))))))) -> Eligible | Q7: =Pipeline!$J7*RBF_HH+Pipeline!$K7*RBF_PU+Pipeline!$L7*RBF_COM+Pipeline!$M7*RBF_INST -> 132500 | R7: =Pipeline!$N7*GrantPct -> 325000 | S7: =MAX(0,MIN($Q7+$R7,MaxSupportPct*Pipeline!$N7-Pipeline!$Q7,MaxPerProject,MaxProjShare*Envelope)) -> 382500 | T7: =IF($O7=1,IF(Pipeline!$V7>0,MIN(Pipeline!$V7,$S7),$S7),0) -> 382500 | U7: =IFERROR($Q7/($Q7+$R7),1) -> 0.28961749 | V7: =IFERROR($T7/$C7,0) -> 354.16667 | W7: =IFERROR((Pipeline!$O7+Pipeline!$P7)/$T7,0) -> 1.4379085 | X7: =IFERROR(Pipeline!$T7/$T7*1000,0) -> 18.300654 | Y7: =IF($O7=0,"",IF(NOT(ISNUMBER(Pipeline!$U7)),"No viability-gap data",IF(Pipeline!$U7<=0,"No viability-gap data",IF($T7<=Pipeline!$U7*(1+VGFTol),"Within viability gap","Above viability gap")))) -> Within viability gap | Z7: =IF($O7=1,IFERROR($AN7/MAX($AN$7:$AN$31)*100,0),0) -> 63.010502 | AA7: =IF($O7=1,IFERROR($AO7/MAX($AO$7:$AO$31)*100,0),0) -> 55 | AB7: =IF($O7=1,IFERROR($AP7/MAX($AP$7:$AP$31)*100,0),0) -> 34.761905 | AC7: =IF($O7=1,IFERROR($AQ7/MAX($AQ$7:$AQ$31)*100,0),0) -> 58.333333 | AD7: =IF($O7=1,Pipeline!$F7/5*100,0) -> 80 | AE7: =IF($O7=1,Pipeline!$G7/5*100,0) -> 80 | AF7: =IF($O7=1,(6-Pipeline!$H7)/5*100,0) -> 80 | AG7: =IF($O7=1,IF($Y7="Within viability gap",100,IF($Y7="Above viability gap",0,50)),0) -> 100 | AH7: =$Z7*W_Cost+$AA7*W_Lev+$AB7*W_PU+$AC7*W_CO2+$AD7*W_Ready+$AE7*W_Track+$AF7*W_Risk+$AG7*W_Add -> 65.050244 | AI7: =IF($O7=1,$AH7+(26-$A7)/1000000,-1) -> 65.050269 | AJ7: =IF($O7=1,COUNTIF($AI$7:$AI$31,">"&$AI7)+1,"") -> 5 | AK7: =SUMIF(Allocation!$B$7:$B$31,1,Allocation!$I$7:$I$31) -> 382500 | AL7: =IFERROR($AK7/$T7,0) -> 1 | AM7: =IF($O7=0,"",IF($AL7>=0.999,"Funded",IF($AK7>0,"Partially funded","Not funded"))) -> Funded | AN7: =IF(AND($O7=1,$V7>0),1/$V7,0) -> 0.0028235294 | AO7: =IF($O7=1,$W7,0) -> 1.4379085 | AP7: =IF($O7=1,$F7,0) -> 0.055555556 | AQ7: =IF(AND($O7=1,$T7>0),Pipeline!$T7/$T7,0) -> 0.018300654
A8: =2 -> 2 | B8: =IF(Pipeline!$B8<>"",Pipeline!$B8,"") -> Project B - River towns | C8: =SUM(Pipeline!$J8:$M8) -> 696 | D8: =IFERROR(Pipeline!$N8/$C8,0) -> 1364.9425 | E8: =IFERROR((Pipeline!$O8+Pipeline!$P8)/Pipeline!$N8,0) -> 0.36842105 | F8: =IFERROR(Pipeline!$K8/$C8,0) -> 0.043103448 | G8: =IF(NOT(Pipeline!$B8<>""),0,IF(E_MinConn_On=1,IF($C8>=E_MinConn,1,0),1)) -> 1 | H8: =IF(NOT(Pipeline!$B8<>""),0,IF(E_MaxCapexConn_On=1,IF($D8<=E_MaxCapexConn,1,0),1)) -> 1 | I8: =IF(NOT(Pipeline!$B8<>""),0,IF(E_MinRE_On=1,IF(Pipeline!$S8>=E_MinRE,1,0),1)) -> 1 | J8: =IF(NOT(Pipeline!$B8<>""),0,IF(E_MinPrivate_On=1,IF($E8>=E_MinPrivate,1,0),1)) -> 1 | K8: =IF(NOT(Pipeline!$B8<>""),0,IF(E_MinReady_On=1,IF(Pipeline!$F8>=E_MinReady,1,0),1)) -> 1 | L8: =IF(NOT(Pipeline!$B8<>""),0,IF(E_MaxTariff_On=1,IF(Pipeline!$R8<=E_MaxTariff,1,0),1)) -> 1 | M8: =IF(NOT(Pipeline!$B8<>""),0,IF(E_MinPU_On=1,IF($F8>=E_MinPU,1,0),1)) -> 1 | N8: =IF(NOT(Pipeline!$B8<>""),0,IF(E_Country_On=1,IF(IFERROR(INDEX('Fund Parameters'!$B$51:$B$58,MATCH(Pipeline!$C8,'Fund Parameters'!$A$51:$A$58,0))="Y",FALSE()),1,0),1)) -> 1 | O8: =IF(AND(Pipeline!$B8<>"",$G8*$H8*$I8*$J8*$K8*$L8*$M8*$N8=1),1,0) -> 1 | P8: =IF(NOT(Pipeline!$B8<>""),"",IF($O8=1,"Eligible",IF($G8=0,"Too few connections",IF($H8=0,"CAPEX per connection too high",IF($I8=0,"Renewable share too low",IF($J8=0,"Private co-finance too low",IF($K8=0,"Not ready enough",IF($L8=0,"Tariff above cap",IF($M8=0,"Productive use too low",IF($N8=0,"Country not eligible","")))))))))) -> Eligible | Q8: =Pipeline!$J8*RBF_HH+Pipeline!$K8*RBF_PU+Pipeline!$L8*RBF_COM+Pipeline!$M8*RBF_INST -> 82500 | R8: =Pipeline!$N8*GrantPct -> 237500 | S8: =MAX(0,MIN($Q8+$R8,MaxSupportPct*Pipeline!$N8-Pipeline!$Q8,MaxPerProject,MaxProjShare*Envelope)) -> 320000 | T8: =IF($O8=1,IF(Pipeline!$V8>0,MIN(Pipeline!$V8,$S8),$S8),0) -> 320000 | U8: =IFERROR($Q8/($Q8+$R8),1) -> 0.2578125 | V8: =IFERROR($T8/$C8,0) -> 459.77011 | W8: =IFERROR((Pipeline!$O8+Pipeline!$P8)/$T8,0) -> 1.09375 | X8: =IFERROR(Pipeline!$T8/$T8*1000,0) -> 14.0625 | Y8: =IF($O8=0,"",IF(NOT(ISNUMBER(Pipeline!$U8)),"No viability-gap data",IF(Pipeline!$U8<=0,"No viability-gap data",IF($T8<=Pipeline!$U8*(1+VGFTol),"Within viability gap","Above viability gap")))) -> Within viability gap | Z8: =IF($O8=1,IFERROR($AN8/MAX($AN$7:$AN$31)*100,0),0) -> 48.537777 | AA8: =IF($O8=1,IFERROR($AO8/MAX($AO$7:$AO$31)*100,0),0) -> 41.835938 | AB8: =IF($O8=1,IFERROR($AP8/MAX($AP$7:$AP$31)*100,0),0) -> 26.970443 | AC8: =IF($O8=1,IFERROR($AQ8/MAX($AQ$7:$AQ$31)*100,0),0) -> 44.824219 | AD8: =IF($O8=1,Pipeline!$F8/5*100,0) -> 60 | AE8: =IF($O8=1,Pipeline!$G8/5*100,0) -> 60 | AF8: =IF($O8=1,(6-Pipeline!$H8)/5*100,0) -> 60 | AG8: =IF($O8=1,IF($Y8="Within viability gap",100,IF($Y8="Above viability gap",0,50)),0) -> 100 | AH8: =$Z8*W_Cost+$AA8*W_Lev+$AB8*W_PU+$AC8*W_CO2+$AD8*W_Ready+$AE8*W_Track+$AF8*W_Risk+$AG8*W_Add -> 51.937823 | AI8: =IF($O8=1,$AH8+(26-$A8)/1000000,-1) -> 51.937847 | AJ8: =IF($O8=1,COUNTIF($AI$7:$AI$31,">"&$AI8)+1,"") -> 8 | AK8: =SUMIF(Allocation!$B$7:$B$31,2,Allocation!$I$7:$I$31) -> 127500 | AL8: =IFERROR($AK8/$T8,0) -> 0.3984375 | AM8: =IF($O8=0,"",IF($AL8>=0.999,"Funded",IF($AK8>0,"Partially funded","Not funded"))) -> Partially funded | AN8: =IF(AND($O8=1,$V8>0),1/$V8,0) -> 0.002175 | AO8: =IF($O8=1,$W8,0) -> 1.09375 | AP8: =IF($O8=1,$F8,0) -> 0.043103448 | AQ8: =IF(AND($O8=1,$T8>0),Pipeline!$T8/$T8,0) -> 0.0140625
A9: =3 -> 3 | B9: =IF(Pipeline!$B9<>"",Pipeline!$B9,"") -> Project C - Northern corridor | C9: =SUM(Pipeline!$J9:$M9) -> 1714 | D9: =IFERROR(Pipeline!$N9/$C9,0) -> 1166.8611 | E9: =IFERROR((Pipeline!$O9+Pipeline!$P9)/Pipeline!$N9,0) -> 0.5 | F9: =IFERROR(Pipeline!$K9/$C9,0) -> 0.070011669 | G9: =IF(NOT(Pipeline!$B9<>""),0,IF(E_MinConn_On=1,IF($C9>=E_MinConn,1,0),1)) -> 1 | H9: =IF(NOT(Pipeline!$B9<>""),0,IF(E_MaxCapexConn_On=1,IF($D9<=E_MaxCapexConn,1,0),1)) -> 1 | I9: =IF(NOT(Pipeline!$B9<>""),0,IF(E_MinRE_On=1,IF(Pipeline!$S9>=E_MinRE,1,0),1)) -> 1 | J9: =IF(NOT(Pipeline!$B9<>""),0,IF(E_MinPrivate_On=1,IF($E9>=E_MinPrivate,1,0),1)) -> 1 | K9: =IF(NOT(Pipeline!$B9<>""),0,IF(E_MinReady_On=1,IF(Pipeline!$F9>=E_MinReady,1,0),1)) -> 1 | L9: =IF(NOT(Pipeline!$B9<>""),0,IF(E_MaxTariff_On=1,IF(Pipeline!$R9<=E_MaxTariff,1,0),1)) -> 1 | M9: =IF(NOT(Pipeline!$B9<>""),0,IF(E_MinPU_On=1,IF($F9>=E_MinPU,1,0),1)) -> 1 | N9: =IF(NOT(Pipeline!$B9<>""),0,IF(E_Country_On=1,IF(IFERROR(INDEX('Fund Parameters'!$B$51:$B$58,MATCH(Pipeline!$C9,'Fund Parameters'!$A$51:$A$58,0))="Y",FALSE()),1,0),1)) -> 1 | O9: =IF(AND(Pipeline!$B9<>"",$G9*$H9*$I9*$J9*$K9*$L9*$M9*$N9=1),1,0) -> 1 | P9: =IF(NOT(Pipeline!$B9<>""),"",IF($O9=1,"Eligible",IF($G9=0,"Too few connections",IF($H9=0,"CAPEX per connection too high",IF($I9=0,"Renewable share too low",IF($J9=0,"Private co-finance too low",IF($K9=0,"Not ready enough",IF($L9=0,"Tariff above cap",IF($M9=0,"Productive use too low",IF($N9=0,"Country not eligible","")))))))))) -> Eligible | Q9: =Pipeline!$J9*RBF_HH+Pipeline!$K9*RBF_PU+Pipeline!$L9*RBF_COM+Pipeline!$M9*RBF_INST -> 215500 | R9: =Pipeline!$N9*GrantPct -> 500000 | S9: =MAX(0,MIN($Q9+$R9,MaxSupportPct*Pipeline!$N9-Pipeline!$Q9,MaxPerProject,MaxProjShare*Envelope)) -> 382500 | T9: =IF($O9=1,IF(Pipeline!$V9>0,MIN(Pipeline!$V9,$S9),$S9),0) -> 382500 | U9: =IFERROR($Q9/($Q9+$R9),1) -> 0.30118798 | V9: =IFERROR($T9/$C9,0) -> 223.16219 | W9: =IFERROR((Pipeline!$O9+Pipeline!$P9)/$T9,0) -> 2.6143791 | X9: =IFERROR(Pipeline!$T9/$T9*1000,0) -> 31.372549 | Y9: =IF($O9=0,"",IF(NOT(ISNUMBER(Pipeline!$U9)),"No viability-gap data",IF(Pipeline!$U9<=0,"No viability-gap data",IF($T9<=Pipeline!$U9*(1+VGFTol),"Within viability gap","Above viability gap")))) -> Within viability gap | Z9: =IF($O9=1,IFERROR($AN9/MAX($AN$7:$AN$31)*100,0),0) -> 100 | AA9: =IF($O9=1,IFERROR($AO9/MAX($AO$7:$AO$31)*100,0),0) -> 100 | AB9: =IF($O9=1,IFERROR($AP9/MAX($AP$7:$AP$31)*100,0),0) -> 43.807301 | AC9: =IF($O9=1,IFERROR($AQ9/MAX($AQ$7:$AQ$31)*100,0),0) -> 100 | AD9: =IF($O9=1,Pipeline!$F9/5*100,0) -> 100 | AE9: =IF($O9=1,Pipeline!$G9/5*100,0) -> 100 | AF9: =IF($O9=1,(6-Pipeline!$H9)/5*100,0) -> 100 | AG9: =IF($O9=1,IF($Y9="Within viability gap",100,IF($Y9="Above viability gap",0,50)),0) -> 100 | AH9: =$Z9*W_Cost+$AA9*W_Lev+$AB9*W_PU+$AC9*W_CO2+$AD9*W_Ready+$AE9*W_Track+$AF9*W_Risk+$AG9*W_Add -> 91.571095 | AI9: =IF($O9=1,$AH9+(26-$A9)/1000000,-1) -> 91.571118 | AJ9: =IF($O9=1,COUNTIF($AI$7:$AI$31,">"&$AI9)+1,"") -> 1 | AK9: =SUMIF(Allocation!$B$7:$B$31,3,Allocation!$I$7:$I$31) -> 382500 | AL9: =IFERROR($AK9/$T9,0) -> 1 | AM9: =IF($O9=0,"",IF($AL9>=0.999,"Funded",IF($AK9>0,"Partially funded","Not funded"))) -> Funded | AN9: =IF(AND($O9=1,$V9>0),1/$V9,0) -> 0.0044810458 | AO9: =IF($O9=1,$W9,0) -> 2.6143791 | AP9: =IF($O9=1,$F9,0) -> 0.070011669 | AQ9: =IF(AND($O9=1,$T9>0),Pipeline!$T9/$T9,0) -> 0.031372549
A10: =4 -> 4 | B10: =IF(Pipeline!$B10<>"",Pipeline!$B10,"") -> Project D - Island grids | C10: =SUM(Pipeline!$J10:$M10) -> 595 | D10: =IFERROR(Pipeline!$N10/$C10,0) -> 1512.605 | E10: =IFERROR((Pipeline!$O10+Pipeline!$P10)/Pipeline!$N10,0) -> 0.27777778 | F10: =IFERROR(Pipeline!$K10/$C10,0) -> 0.067226891 | G10: =IF(NOT(Pipeline!$B10<>""),0,IF(E_MinConn_On=1,IF($C10>=E_MinConn,1,0),1)) -> 1 | H10: =IF(NOT(Pipeline!$B10<>""),0,IF(E_MaxCapexConn_On=1,IF($D10<=E_MaxCapexConn,1,0),1)) -> 1 | I10: =IF(NOT(Pipeline!$B10<>""),0,IF(E_MinRE_On=1,IF(Pipeline!$S10>=E_MinRE,1,0),1)) -> 1 | J10: =IF(NOT(Pipeline!$B10<>""),0,IF(E_MinPrivate_On=1,IF($E10>=E_MinPrivate,1,0),1)) -> 1 | K10: =IF(NOT(Pipeline!$B10<>""),0,IF(E_MinReady_On=1,IF(Pipeline!$F10>=E_MinReady,1,0),1)) -> 0 | L10: =IF(NOT(Pipeline!$B10<>""),0,IF(E_MaxTariff_On=1,IF(Pipeline!$R10<=E_MaxTariff,1,0),1)) -> 1 | M10: =IF(NOT(Pipeline!$B10<>""),0,IF(E_MinPU_On=1,IF($F10>=E_MinPU,1,0),1)) -> 1 | N10: =IF(NOT(Pipeline!$B10<>""),0,IF(E_Country_On=1,IF(IFERROR(INDEX('Fund Parameters'!$B$51:$B$58,MATCH(Pipeline!$C10,'Fund Parameters'!$A$51:$A$58,0))="Y",FALSE()),1,0),1)) -> 1 | O10: =IF(AND(Pipeline!$B10<>"",$G10*$H10*$I10*$J10*$K10*$L10*$M10*$N10=1),1,0) -> 0 | P10: =IF(NOT(Pipeline!$B10<>""),"",IF($O10=1,"Eligible",IF($G10=0,"Too few connections",IF($H10=0,"CAPEX per connection too high",IF($I10=0,"Renewable share too low",IF($J10=0,"Private co-finance too low",IF($K10=0,"Not ready enough",IF($L10=0,"Tariff above cap",IF($M10=0,"Productive use too low",IF($N10=0,"Country not eligible","")))))))))) -> Not ready enough | Q10: =Pipeline!$J10*RBF_HH+Pipeline!$K10*RBF_PU+Pipeline!$L10*RBF_COM+Pipeline!$M10*RBF_INST -> 73250 | R10: =Pipeline!$N10*GrantPct -> 225000 | S10: =MAX(0,MIN($Q10+$R10,MaxSupportPct*Pipeline!$N10-Pipeline!$Q10,MaxPerProject,MaxProjShare*Envelope)) -> 298250 | T10: =IF($O10=1,IF(Pipeline!$V10>0,MIN(Pipeline!$V10,$S10),$S10),0) -> 0 | U10: =IFERROR($Q10/($Q10+$R10),1) -> 0.24559933 | V10: =IFERROR($T10/$C10,0) -> 0 | W10: =IFERROR((Pipeline!$O10+Pipeline!$P10)/$T10,0) -> 0 | X10: =IFERROR(Pipeline!$T10/$T10*1000,0) -> 0 | Y10: =IF($O10=0,"",IF(NOT(ISNUMBER(Pipeline!$U10)),"No viability-gap data",IF(Pipeline!$U10<=0,"No viability-gap data",IF($T10<=Pipeline!$U10*(1+VGFTol),"Within viability gap","Above viability gap")))) | Z10: =IF($O10=1,IFERROR($AN10/MAX($AN$7:$AN$31)*100,0),0) -> 0 | AA10: =IF($O10=1,IFERROR($AO10/MAX($AO$7:$AO$31)*100,0),0) -> 0 | AB10: =IF($O10=1,IFERROR($AP10/MAX($AP$7:$AP$31)*100,0),0) -> 0 | AC10: =IF($O10=1,IFERROR($AQ10/MAX($AQ$7:$AQ$31)*100,0),0) -> 0 | AD10: =IF($O10=1,Pipeline!$F10/5*100,0) -> 0 | AE10: =IF($O10=1,Pipeline!$G10/5*100,0) -> 0 | AF10: =IF($O10=1,(6-Pipeline!$H10)/5*100,0) -> 0 | AG10: =IF($O10=1,IF($Y10="Within viability gap",100,IF($Y10="Above viability gap",0,50)),0) -> 0 | AH10: =$Z10*W_Cost+$AA10*W_Lev+$AB10*W_PU+$AC10*W_CO2+$AD10*W_Ready+$AE10*W_Track+$AF10*W_Risk+$AG10*W_Add -> 0 | AI10: =IF($O10=1,$AH10+(26-$A10)/1000000,-1) -> -1 | AJ10: =IF($O10=1,COUNTIF($AI$7:$AI$31,">"&$AI10)+1,"") | AK10: =SUMIF(Allocation!$B$7:$B$31,4,Allocation!$I$7:$I$31) -> 0 | AL10: =IFERROR($AK10/$T10,0) -> 0 | AM10: =IF($O10=0,"",IF($AL10>=0.999,"Funded",IF($AK10>0,"Partially funded","Not funded"))) | AN10: =IF(AND($O10=1,$V10>0),1/$V10,0) -> 0 | AO10: =IF($O10=1,$W10,0) -> 0 | AP10: =IF($O10=1,$F10,0) -> 0 | AQ10: =IF(AND($O10=1,$T10>0),Pipeline!$T10/$T10,0) -> 0
A11: =5 -> 5 | B11: =IF(Pipeline!$B11<>"",Pipeline!$B11,"") -> Project E - Highland villages | C11: =SUM(Pipeline!$J11:$M11) -> 828 | D11: =IFERROR(Pipeline!$N11/$C11,0) -> 1268.1159 | E11: =IFERROR((Pipeline!$O11+Pipeline!$P11)/Pipeline!$N11,0) -> 0.38095238 | F11: =IFERROR(Pipeline!$K11/$C11,0) -> 0.060386473 | G11: =IF(NOT(Pipeline!$B11<>""),0,IF(E_MinConn_On=1,IF($C11>=E_MinConn,1,0),1)) -> 1 | H11: =IF(NOT(Pipeline!$B11<>""),0,IF(E_MaxCapexConn_On=1,IF($D11<=E_MaxCapexConn,1,0),1)) -> 1 | I11: =IF(NOT(Pipeline!$B11<>""),0,IF(E_MinRE_On=1,IF(Pipeline!$S11>=E_MinRE,1,0),1)) -> 1 | J11: =IF(NOT(Pipeline!$B11<>""),0,IF(E_MinPrivate_On=1,IF($E11>=E_MinPrivate,1,0),1)) -> 1 | K11: =IF(NOT(Pipeline!$B11<>""),0,IF(E_MinReady_On=1,IF(Pipeline!$F11>=E_MinReady,1,0),1)) -> 1 | L11: =IF(NOT(Pipeline!$B11<>""),0,IF(E_MaxTariff_On=1,IF(Pipeline!$R11<=E_MaxTariff,1,0),1)) -> 1 | M11: =IF(NOT(Pipeline!$B11<>""),0,IF(E_MinPU_On=1,IF($F11>=E_MinPU,1,0),1)) -> 1 | N11: =IF(NOT(Pipeline!$B11<>""),0,IF(E_Country_On=1,IF(IFERROR(INDEX('Fund Parameters'!$B$51:$B$58,MATCH(Pipeline!$C11,'Fund Parameters'!$A$51:$A$58,0))="Y",FALSE()),1,0),1)) -> 0 | O11: =IF(AND(Pipeline!$B11<>"",$G11*$H11*$I11*$J11*$K11*$L11*$M11*$N11=1),1,0) -> 0 | P11: =IF(NOT(Pipeline!$B11<>""),"",IF($O11=1,"Eligible",IF($G11=0,"Too few connections",IF($H11=0,"CAPEX per connection too high",IF($I11=0,"Renewable share too low",IF($J11=0,"Private co-finance too low",IF($K11=0,"Not ready enough",IF($L11=0,"Tariff above cap",IF($M11=0,"Productive use too low",IF($N11=0,"Country not eligible","")))))))))) -> Country not eligible | Q11: =Pipeline!$J11*RBF_HH+Pipeline!$K11*RBF_PU+Pipeline!$L11*RBF_COM+Pipeline!$M11*RBF_INST -> 101000 | R11: =Pipeline!$N11*GrantPct -> 262500 | S11: =MAX(0,MIN($Q11+$R11,MaxSupportPct*Pipeline!$N11-Pipeline!$Q11,MaxPerProject,MaxProjShare*Envelope)) -> 363500 | T11: =IF($O11=1,IF(Pipeline!$V11>0,MIN(Pipeline!$V11,$S11),$S11),0) -> 0 | U11: =IFERROR($Q11/($Q11+$R11),1) -> 0.2778542 | V11: =IFERROR($T11/$C11,0) -> 0 | W11: =IFERROR((Pipeline!$O11+Pipeline!$P11)/$T11,0) -> 0 | X11: =IFERROR(Pipeline!$T11/$T11*1000,0) -> 0 | Y11: =IF($O11=0,"",IF(NOT(ISNUMBER(Pipeline!$U11)),"No viability-gap data",IF(Pipeline!$U11<=0,"No viability-gap data",IF($T11<=Pipeline!$U11*(1+VGFTol),"Within viability gap","Above viability gap")))) | Z11: =IF($O11=1,IFERROR($AN11/MAX($AN$7:$AN$31)*100,0),0) -> 0 | AA11: =IF($O11=1,IFERROR($AO11/MAX($AO$7:$AO$31)*100,0),0) -> 0 | AB11: =IF($O11=1,IFERROR($AP11/MAX($AP$7:$AP$31)*100,0),0) -> 0 | AC11: =IF($O11=1,IFERROR($AQ11/MAX($AQ$7:$AQ$31)*100,0),0) -> 0 | AD11: =IF($O11=1,Pipeline!$F11/5*100,0) -> 0 | AE11: =IF($O11=1,Pipeline!$G11/5*100,0) -> 0 | AF11: =IF($O11=1,(6-Pipeline!$H11)/5*100,0) -> 0 | AG11: =IF($O11=1,IF($Y11="Within viability gap",100,IF($Y11="Above viability gap",0,50)),0) -> 0 | AH11: =$Z11*W_Cost+$AA11*W_Lev+$AB11*W_PU+$AC11*W_CO2+$AD11*W_Ready+$AE11*W_Track+$AF11*W_Risk+$AG11*W_Add -> 0 | AI11: =IF($O11=1,$AH11+(26-$A11)/1000000,-1) -> -1 | AJ11: =IF($O11=1,COUNTIF($AI$7:$AI$31,">"&$AI11)+1,"") | AK11: =SUMIF(Allocation!$B$7:$B$31,5,Allocation!$I$7:$I$31) -> 0 | AL11: =IFERROR($AK11/$T11,0) -> 0 | AM11: =IF($O11=0,"",IF($AL11>=0.999,"Funded",IF($AK11>0,"Partially funded","Not funded"))) | AN11: =IF(AND($O11=1,$V11>0),1/$V11,0) -> 0 | AO11: =IF($O11=1,$W11,0) -> 0 | AP11: =IF($O11=1,$F11,0) -> 0 | AQ11: =IF(AND($O11=1,$T11>0),Pipeline!$T11/$T11,0) -> 0
A12: =6 -> 6 | B12: =IF(Pipeline!$B12<>"",Pipeline!$B12,"") -> Project F - Market towns | C12: =SUM(Pipeline!$J12:$M12) -> 988 | D12: =IFERROR(Pipeline!$N12/$C12,0) -> 1113.3603 | E12: =IFERROR((Pipeline!$O12+Pipeline!$P12)/Pipeline!$N12,0) -> 0.40909091 | F12: =IFERROR(Pipeline!$K12/$C12,0) -> 0.060728745 | G12: =IF(NOT(Pipeline!$B12<>""),0,IF(E_MinConn_On=1,IF($C12>=E_MinConn,1,0),1)) -> 1 | H12: =IF(NOT(Pipeline!$B12<>""),0,IF(E_MaxCapexConn_On=1,IF($D12<=E_MaxCapexConn,1,0),1)) -> 1 | I12: =IF(NOT(Pipeline!$B12<>""),0,IF(E_MinRE_On=1,IF(Pipeline!$S12>=E_MinRE,1,0),1)) -> 0 | J12: =IF(NOT(Pipeline!$B12<>""),0,IF(E_MinPrivate_On=1,IF($E12>=E_MinPrivate,1,0),1)) -> 1 | K12: =IF(NOT(Pipeline!$B12<>""),0,IF(E_MinReady_On=1,IF(Pipeline!$F12>=E_MinReady,1,0),1)) -> 1 | L12: =IF(NOT(Pipeline!$B12<>""),0,IF(E_MaxTariff_On=1,IF(Pipeline!$R12<=E_MaxTariff,1,0),1)) -> 1 | M12: =IF(NOT(Pipeline!$B12<>""),0,IF(E_MinPU_On=1,IF($F12>=E_MinPU,1,0),1)) -> 1 | N12: =IF(NOT(Pipeline!$B12<>""),0,IF(E_Country_On=1,IF(IFERROR(INDEX('Fund Parameters'!$B$51:$B$58,MATCH(Pipeline!$C12,'Fund Parameters'!$A$51:$A$58,0))="Y",FALSE()),1,0),1)) -> 1 | O12: =IF(AND(Pipeline!$B12<>"",$G12*$H12*$I12*$J12*$K12*$L12*$M12*$N12=1),1,0) -> 0 | P12: =IF(NOT(Pipeline!$B12<>""),"",IF($O12=1,"Eligible",IF($G12=0,"Too few connections",IF($H12=0,"CAPEX per connection too high",IF($I12=0,"Renewable share too low",IF($J12=0,"Private co-finance too low",IF($K12=0,"Not ready enough",IF($L12=0,"Tariff above cap",IF($M12=0,"Productive use too low",IF($N12=0,"Country not eligible","")))))))))) -> Renewable share too low | Q12: =Pipeline!$J12*RBF_HH+Pipeline!$K12*RBF_PU+Pipeline!$L12*RBF_COM+Pipeline!$M12*RBF_INST -> 124000 | R12: =Pipeline!$N12*GrantPct -> 275000 | S12: =MAX(0,MIN($Q12+$R12,MaxSupportPct*Pipeline!$N12-Pipeline!$Q12,MaxPerProject,MaxProjShare*Envelope)) -> 382500 | T12: =IF($O12=1,IF(Pipeline!$V12>0,MIN(Pipeline!$V12,$S12),$S12),0) -> 0 | U12: =IFERROR($Q12/($Q12+$R12),1) -> 0.31077694 | V12: =IFERROR($T12/$C12,0) -> 0 | W12: =IFERROR((Pipeline!$O12+Pipeline!$P12)/$T12,0) -> 0 | X12: =IFERROR(Pipeline!$T12/$T12*1000,0) -> 0 | Y12: =IF($O12=0,"",IF(NOT(ISNUMBER(Pipeline!$U12)),"No viability-gap data",IF(Pipeline!$U12<=0,"No viability-gap data",IF($T12<=Pipeline!$U12*(1+VGFTol),"Within viability gap","Above viability gap")))) | Z12: =IF($O12=1,IFERROR($AN12/MAX($AN$7:$AN$31)*100,0),0) -> 0 | AA12: =IF($O12=1,IFERROR($AO12/MAX($AO$7:$AO$31)*100,0),0) -> 0 | AB12: =IF($O12=1,IFERROR($AP12/MAX($AP$7:$AP$31)*100,0),0) -> 0 | AC12: =IF($O12=1,IFERROR($AQ12/MAX($AQ$7:$AQ$31)*100,0),0) -> 0 | AD12: =IF($O12=1,Pipeline!$F12/5*100,0) -> 0 | AE12: =IF($O12=1,Pipeline!$G12/5*100,0) -> 0 | AF12: =IF($O12=1,(6-Pipeline!$H12)/5*100,0) -> 0 | AG12: =IF($O12=1,IF($Y12="Within viability gap",100,IF($Y12="Above viability gap",0,50)),0) -> 0 | AH12: =$Z12*W_Cost+$AA12*W_Lev+$AB12*W_PU+$AC12*W_CO2+$AD12*W_Ready+$AE12*W_Track+$AF12*W_Risk+$AG12*W_Add -> 0 | AI12: =IF($O12=1,$AH12+(26-$A12)/1000000,-1) -> -1 | AJ12: =IF($O12=1,COUNTIF($AI$7:$AI$31,">"&$AI12)+1,"") | AK12: =SUMIF(Allocation!$B$7:$B$31,6,Allocation!$I$7:$I$31) -> 0 | AL12: =IFERROR($AK12/$T12,0) -> 0 | AM12: =IF($O12=0,"",IF($AL12>=0.999,"Funded",IF($AK12>0,"Partially funded","Not funded"))) | AN12: =IF(AND($O12=1,$V12>0),1/$V12,0) -> 0 | AO12: =IF($O12=1,$W12,0) -> 0 | AP12: =IF($O12=1,$F12,0) -> 0 | AQ12: =IF(AND($O12=1,$T12>0),Pipeline!$T12/$T12,0) -> 0
A13: =7 -> 7 | B13: =IF(Pipeline!$B13<>"",Pipeline!$B13,"") -> Project G - Remote valley | C13: =SUM(Pipeline!$J13:$M13) -> 354 | D13: =IFERROR(Pipeline!$N13/$C13,0) -> 2542.3729 | E13: =IFERROR((Pipeline!$O13+Pipeline!$P13)/Pipeline!$N13,0) -> 0.22222222 | F13: =IFERROR(Pipeline!$K13/$C13,0) -> 0.056497175 | G13: =IF(NOT(Pipeline!$B13<>""),0,IF(E_MinConn_On=1,IF($C13>=E_MinConn,1,0),1)) -> 1 | H13: =IF(NOT(Pipeline!$B13<>""),0,IF(E_MaxCapexConn_On=1,IF($D13<=E_MaxCapexConn,1,0),1)) -> 0 | I13: =IF(NOT(Pipeline!$B13<>""),0,IF(E_MinRE_On=1,IF(Pipeline!$S13>=E_MinRE,1,0),1)) -> 1 | J13: =IF(NOT(Pipeline!$B13<>""),0,IF(E_MinPrivate_On=1,IF($E13>=E_MinPrivate,1,0),1)) -> 1 | K13: =IF(NOT(Pipeline!$B13<>""),0,IF(E_MinReady_On=1,IF(Pipeline!$F13>=E_MinReady,1,0),1)) -> 1 | L13: =IF(NOT(Pipeline!$B13<>""),0,IF(E_MaxTariff_On=1,IF(Pipeline!$R13<=E_MaxTariff,1,0),1)) -> 1 | M13: =IF(NOT(Pipeline!$B13<>""),0,IF(E_MinPU_On=1,IF($F13>=E_MinPU,1,0),1)) -> 1 | N13: =IF(NOT(Pipeline!$B13<>""),0,IF(E_Country_On=1,IF(IFERROR(INDEX('Fund Parameters'!$B$51:$B$58,MATCH(Pipeline!$C13,'Fund Parameters'!$A$51:$A$58,0))="Y",FALSE()),1,0),1)) -> 1 | O13: =IF(AND(Pipeline!$B13<>"",$G13*$H13*$I13*$J13*$K13*$L13*$M13*$N13=1),1,0) -> 0 | P13: =IF(NOT(Pipeline!$B13<>""),"",IF($O13=1,"Eligible",IF($G13=0,"Too few connections",IF($H13=0,"CAPEX per connection too high",IF($I13=0,"Renewable share too low",IF($J13=0,"Private co-finance too low",IF($K13=0,"Not ready enough",IF($L13=0,"Tariff above cap",IF($M13=0,"Productive use too low",IF($N13=0,"Country not eligible","")))))))))) -> CAPEX per connection too high | Q13: =Pipeline!$J13*RBF_HH+Pipeline!$K13*RBF_PU+Pipeline!$L13*RBF_COM+Pipeline!$M13*RBF_INST -> 43000 | R13: =Pipeline!$N13*GrantPct -> 225000 | S13: =MAX(0,MIN($Q13+$R13,MaxSupportPct*Pipeline!$N13-Pipeline!$Q13,MaxPerProject,MaxProjShare*Envelope)) -> 268000 | T13: =IF($O13=1,IF(Pipeline!$V13>0,MIN(Pipeline!$V13,$S13),$S13),0) -> 0 | U13: =IFERROR($Q13/($Q13+$R13),1) -> 0.16044776 | V13: =IFERROR($T13/$C13,0) -> 0 | W13: =IFERROR((Pipeline!$O13+Pipeline!$P13)/$T13,0) -> 0 | X13: =IFERROR(Pipeline!$T13/$T13*1000,0) -> 0 | Y13: =IF($O13=0,"",IF(NOT(ISNUMBER(Pipeline!$U13)),"No viability-gap data",IF(Pipeline!$U13<=0,"No viability-gap data",IF($T13<=Pipeline!$U13*(1+VGFTol),"Within viability gap","Above viability gap")))) | Z13: =IF($O13=1,IFERROR($AN13/MAX($AN$7:$AN$31)*100,0),0) -> 0 | AA13: =IF($O13=1,IFERROR($AO13/MAX($AO$7:$AO$31)*100,0),0) -> 0 | AB13: =IF($O13=1,IFERROR($AP13/MAX($AP$7:$AP$31)*100,0),0) -> 0 | AC13: =IF($O13=1,IFERROR($AQ13/MAX($AQ$7:$AQ$31)*100,0),0) -> 0 | AD13: =IF($O13=1,Pipeline!$F13/5*100,0) -> 0 | AE13: =IF($O13=1,Pipeline!$G13/5*100,0) -> 0 | AF13: =IF($O13=1,(6-Pipeline!$H13)/5*100,0) -> 0 | AG13: =IF($O13=1,IF($Y13="Within viability gap",100,IF($Y13="Above viability gap",0,50)),0) -> 0 | AH13: =$Z13*W_Cost+$AA13*W_Lev+$AB13*W_PU+$AC13*W_CO2+$AD13*W_Ready+$AE13*W_Track+$AF13*W_Risk+$AG13*W_Add -> 0 | AI13: =IF($O13=1,$AH13+(26-$A13)/1000000,-1) -> -1 | AJ13: =IF($O13=1,COUNTIF($AI$7:$AI$31,">"&$AI13)+1,"") | AK13: =SUMIF(Allocation!$B$7:$B$31,7,Allocation!$I$7:$I$31) -> 0 | AL13: =IFERROR($AK13/$T13,0) -> 0 | AM13: =IF($O13=0,"",IF($AL13>=0.999,"Funded",IF($AK13>0,"Partially funded","Not funded"))) | AN13: =IF(AND($O13=1,$V13>0),1/$V13,0) -> 0 | AO13: =IF($O13=1,$W13,0) -> 0 | AP13: =IF($O13=1,$F13,0) -> 0 | AQ13: =IF(AND($O13=1,$T13>0),Pipeline!$T13/$T13,0) -> 0
A14: =8 -> 8 | B14: =IF(Pipeline!$B14<>"",Pipeline!$B14,"") -> Project H - Agro-processing hub | C14: =SUM(Pipeline!$J14:$M14) -> 876 | D14: =IFERROR(Pipeline!$N14/$C14,0) -> 1369.863 | E14: =IFERROR((Pipeline!$O14+Pipeline!$P14)/Pipeline!$N14,0) -> 0.5 | F14: =IFERROR(Pipeline!$K14/$C14,0) -> 0.15981735 | G14: =IF(NOT(Pipeline!$B14<>""),0,IF(E_MinConn_On=1,IF($C14>=E_MinConn,1,0),1)) -> 1 | H14: =IF(NOT(Pipeline!$B14<>""),0,IF(E_MaxCapexConn_On=1,IF($D14<=E_MaxCapexConn,1,0),1)) -> 1 | I14: =IF(NOT(Pipeline!$B14<>""),0,IF(E_MinRE_On=1,IF(Pipeline!$S14>=E_MinRE,1,0),1)) -> 1 | J14: =IF(NOT(Pipeline!$B14<>""),0,IF(E_MinPrivate_On=1,IF($E14>=E_MinPrivate,1,0),1)) -> 1 | K14: =IF(NOT(Pipeline!$B14<>""),0,IF(E_MinReady_On=1,IF(Pipeline!$F14>=E_MinReady,1,0),1)) -> 1 | L14: =IF(NOT(Pipeline!$B14<>""),0,IF(E_MaxTariff_On=1,IF(Pipeline!$R14<=E_MaxTariff,1,0),1)) -> 1 | M14: =IF(NOT(Pipeline!$B14<>""),0,IF(E_MinPU_On=1,IF($F14>=E_MinPU,1,0),1)) -> 1 | N14: =IF(NOT(Pipeline!$B14<>""),0,IF(E_Country_On=1,IF(IFERROR(INDEX('Fund Parameters'!$B$51:$B$58,MATCH(Pipeline!$C14,'Fund Parameters'!$A$51:$A$58,0))="Y",FALSE()),1,0),1)) -> 1 | O14: =IF(AND(Pipeline!$B14<>"",$G14*$H14*$I14*$J14*$K14*$L14*$M14*$N14=1),1,0) -> 1 | P14: =IF(NOT(Pipeline!$B14<>""),"",IF($O14=1,"Eligible",IF($G14=0,"Too few connections",IF($H14=0,"CAPEX per connection too high",IF($I14=0,"Renewable share too low",IF($J14=0,"Private co-finance too low",IF($K14=0,"Not ready enough",IF($L14=0,"Tariff above cap",IF($M14=0,"Productive use too low",IF($N14=0,"Country not eligible","")))))))))) -> Eligible | Q14: =Pipeline!$J14*RBF_HH+Pipeline!$K14*RBF_PU+Pipeline!$L14*RBF_COM+Pipeline!$M14*RBF_INST -> 124500 | R14: =Pipeline!$N14*GrantPct -> 300000 | S14: =MAX(0,MIN($Q14+$R14,MaxSupportPct*Pipeline!$N14-Pipeline!$Q14,MaxPerProject,MaxProjShare*Envelope)) -> 382500 | T14: =IF($O14=1,IF(Pipeline!$V14>0,MIN(Pipeline!$V14,$S14),$S14),0) -> 382500 | U14: =IFERROR($Q14/($Q14+$R14),1) -> 0.29328622 | V14: =IFERROR($T14/$C14,0) -> 436.64384 | W14: =IFERROR((Pipeline!$O14+Pipeline!$P14)/$T14,0) -> 1.5686275 | X14: =IFERROR(Pipeline!$T14/$T14*1000,0) -> 16.993464 | Y14: =IF($O14=0,"",IF(NOT(ISNUMBER(Pipeline!$U14)),"No viability-gap data",IF(Pipeline!$U14<=0,"No viability-gap data",IF($T14<=Pipeline!$U14*(1+VGFTol),"Within viability gap","Above viability gap")))) -> Within viability gap | Z14: =IF($O14=1,IFERROR($AN14/MAX($AN$7:$AN$31)*100,0),0) -> 51.108518 | AA14: =IF($O14=1,IFERROR($AO14/MAX($AO$7:$AO$31)*100,0),0) -> 60 | AB14: =IF($O14=1,IFERROR($AP14/MAX($AP$7:$AP$31)*100,0),0) -> 100 | AC14: =IF($O14=1,IFERROR($AQ14/MAX($AQ$7:$AQ$31)*100,0),0) -> 54.166667 | AD14: =IF($O14=1,Pipeline!$F14/5*100,0) -> 80 | AE14: =IF($O14=1,Pipeline!$G14/5*100,0) -> 60 | AF14: =IF($O14=1,(6-Pipeline!$H14)/5*100,0) -> 80 | AG14: =IF($O14=1,IF($Y14="Within viability gap",100,IF($Y14="Above viability gap",0,50)),0) -> 100 | AH14: =$Z14*W_Cost+$AA14*W_Lev+$AB14*W_PU+$AC14*W_CO2+$AD14*W_Ready+$AE14*W_Track+$AF14*W_Risk+$AG14*W_Add -> 70.193796 | AI14: =IF($O14=1,$AH14+(26-$A14)/1000000,-1) -> 70.193814 | AJ14: =IF($O14=1,COUNTIF($AI$7:$AI$31,">"&$AI14)+1,"") -> 4 | AK14: =SUMIF(Allocation!$B$7:$B$31,8,Allocation!$I$7:$I$31) -> 382500 | AL14: =IFERROR($AK14/$T14,0) -> 1 | AM14: =IF($O14=0,"",IF($AL14>=0.999,"Funded",IF($AK14>0,"Partially funded","Not funded"))) -> Funded | AN14: =IF(AND($O14=1,$V14>0),1/$V14,0) -> 0.0022901961 | AO14: =IF($O14=1,$W14,0) -> 1.5686275 | AP14: =IF($O14=1,$F14,0) -> 0.15981735 | AQ14: =IF(AND($O14=1,$T14>0),Pipeline!$T14/$T14,0) -> 0.016993464
A15: =9 -> 9 | B15: =IF(Pipeline!$B15<>"",Pipeline!$B15,"") -> Project I - Fishing communities | C15: =SUM(Pipeline!$J15:$M15) -> 917 | D15: =IFERROR(Pipeline!$N15/$C15,0) -> 1254.0894 | E15: =IFERROR((Pipeline!$O15+Pipeline!$P15)/Pipeline!$N15,0) -> 0.30434783 | F15: =IFERROR(Pipeline!$K15/$C15,0) -> 0.076335878 | G15: =IF(NOT(Pipeline!$B15<>""),0,IF(E_MinConn_On=1,IF($C15>=E_MinConn,1,0),1)) -> 1 | H15: =IF(NOT(Pipeline!$B15<>""),0,IF(E_MaxCapexConn_On=1,IF($D15<=E_MaxCapexConn,1,0),1)) -> 1 | I15: =IF(NOT(Pipeline!$B15<>""),0,IF(E_MinRE_On=1,IF(Pipeline!$S15>=E_MinRE,1,0),1)) -> 1 | J15: =IF(NOT(Pipeline!$B15<>""),0,IF(E_MinPrivate_On=1,IF($E15>=E_MinPrivate,1,0),1)) -> 1 | K15: =IF(NOT(Pipeline!$B15<>""),0,IF(E_MinReady_On=1,IF(Pipeline!$F15>=E_MinReady,1,0),1)) -> 1 | L15: =IF(NOT(Pipeline!$B15<>""),0,IF(E_MaxTariff_On=1,IF(Pipeline!$R15<=E_MaxTariff,1,0),1)) -> 1 | M15: =IF(NOT(Pipeline!$B15<>""),0,IF(E_MinPU_On=1,IF($F15>=E_MinPU,1,0),1)) -> 1 | N15: =IF(NOT(Pipeline!$B15<>""),0,IF(E_Country_On=1,IF(IFERROR(INDEX('Fund Parameters'!$B$51:$B$58,MATCH(Pipeline!$C15,'Fund Parameters'!$A$51:$A$58,0))="Y",FALSE()),1,0),1)) -> 1 | O15: =IF(AND(Pipeline!$B15<>"",$G15*$H15*$I15*$J15*$K15*$L15*$M15*$N15=1),1,0) -> 1 | P15: =IF(NOT(Pipeline!$B15<>""),"",IF($O15=1,"Eligible",IF($G15=0,"Too few connections",IF($H15=0,"CAPEX per connection too high",IF($I15=0,"Renewable share too low",IF($J15=0,"Private co-finance too low",IF($K15=0,"Not ready enough",IF($L15=0,"Tariff above cap",IF($M15=0,"Productive use too low",IF($N15=0,"Country not eligible","")))))))))) -> Eligible | Q15: =Pipeline!$J15*RBF_HH+Pipeline!$K15*RBF_PU+Pipeline!$L15*RBF_COM+Pipeline!$M15*RBF_INST -> 115750 | R15: =Pipeline!$N15*GrantPct -> 287500 | S15: =MAX(0,MIN($Q15+$R15,MaxSupportPct*Pipeline!$N15-Pipeline!$Q15,MaxPerProject,MaxProjShare*Envelope)) -> 382500 | T15: =IF($O15=1,IF(Pipeline!$V15>0,MIN(Pipeline!$V15,$S15),$S15),0) -> 382500 | U15: =IFERROR($Q15/($Q15+$R15),1) -> 0.28704278 | V15: =IFERROR($T15/$C15,0) -> 417.12105 | W15: =IFERROR((Pipeline!$O15+Pipeline!$P15)/$T15,0) -> 0.91503268 | X15: =IFERROR(Pipeline!$T15/$T15*1000,0) -> 13.071895 | Y15: =IF($O15=0,"",IF(NOT(ISNUMBER(Pipeline!$U15)),"No viability-gap data",IF(Pipeline!$U15<=0,"No viability-gap data",IF($T15<=Pipeline!$U15*(1+VGFTol),"Within viability gap","Above viability gap")))) -> Within viability gap | Z15: =IF($O15=1,IFERROR($AN15/MAX($AN$7:$AN$31)*100,0),0) -> 53.500583 | AA15: =IF($O15=1,IFERROR($AO15/MAX($AO$7:$AO$31)*100,0),0) -> 35 | AB15: =IF($O15=1,IFERROR($AP15/MAX($AP$7:$AP$31)*100,0),0) -> 47.764449 | AC15: =IF($O15=1,IFERROR($AQ15/MAX($AQ$7:$AQ$31)*100,0),0) -> 41.666667 | AD15: =IF($O15=1,Pipeline!$F15/5*100,0) -> 60 | AE15: =IF($O15=1,Pipeline!$G15/5*100,0) -> 40 | AF15: =IF($O15=1,(6-Pipeline!$H15)/5*100,0) -> 60 | AG15: =IF($O15=1,IF($Y15="Within viability gap",100,IF($Y15="Above viability gap",0,50)),0) -> 100 | AH15: =$Z15*W_Cost+$AA15*W_Lev+$AB15*W_PU+$AC15*W_CO2+$AD15*W_Ready+$AE15*W_Track+$AF15*W_Risk+$AG15*W_Add -> 52.95648 | AI15: =IF($O15=1,$AH15+(26-$A15)/1000000,-1) -> 52.956497 | AJ15: =IF($O15=1,COUNTIF($AI$7:$AI$31,">"&$AI15)+1,"") -> 7 | AK15: =SUMIF(Allocation!$B$7:$B$31,9,Allocation!$I$7:$I$31) -> 382500 | AL15: =IFERROR($AK15/$T15,0) -> 1 | AM15: =IF($O15=0,"",IF($AL15>=0.999,"Funded",IF($AK15>0,"Partially funded","Not funded"))) -> Funded | AN15: =IF(AND($O15=1,$V15>0),1/$V15,0) -> 0.0023973856 | AO15: =IF($O15=1,$W15,0) -> 0.91503268 | AP15: =IF($O15=1,$F15,0) -> 0.076335878 | AQ15: =IF(AND($O15=1,$T15>0),Pipeline!$T15/$T15,0) -> 0.013071895
A16: =10 -> 10 | B16: =IF(Pipeline!$B16<>"",Pipeline!$B16,"") -> Project J - Health and schools first | C16: =SUM(Pipeline!$J16:$M16) -> 650 | D16: =IFERROR(Pipeline!$N16/$C16,0) -> 1384.6154 | E16: =IFERROR((Pipeline!$O16+Pipeline!$P16)/Pipeline!$N16,0) -> 0.38888889 | F16: =IFERROR(Pipeline!$K16/$C16,0) -> 0.038461538 | G16: =IF(NOT(Pipeline!$B16<>""),0,IF(E_MinConn_On=1,IF($C16>=E_MinConn,1,0),1)) -> 1 | H16: =IF(NOT(Pipeline!$B16<>""),0,IF(E_MaxCapexConn_On=1,IF($D16<=E_MaxCapexConn,1,0),1)) -> 1 | I16: =IF(NOT(Pipeline!$B16<>""),0,IF(E_MinRE_On=1,IF(Pipeline!$S16>=E_MinRE,1,0),1)) -> 1 | J16: =IF(NOT(Pipeline!$B16<>""),0,IF(E_MinPrivate_On=1,IF($E16>=E_MinPrivate,1,0),1)) -> 1 | K16: =IF(NOT(Pipeline!$B16<>""),0,IF(E_MinReady_On=1,IF(Pipeline!$F16>=E_MinReady,1,0),1)) -> 1 | L16: =IF(NOT(Pipeline!$B16<>""),0,IF(E_MaxTariff_On=1,IF(Pipeline!$R16<=E_MaxTariff,1,0),1)) -> 1 | M16: =IF(NOT(Pipeline!$B16<>""),0,IF(E_MinPU_On=1,IF($F16>=E_MinPU,1,0),1)) -> 0 | N16: =IF(NOT(Pipeline!$B16<>""),0,IF(E_Country_On=1,IF(IFERROR(INDEX('Fund Parameters'!$B$51:$B$58,MATCH(Pipeline!$C16,'Fund Parameters'!$A$51:$A$58,0))="Y",FALSE()),1,0),1)) -> 1 | O16: =IF(AND(Pipeline!$B16<>"",$G16*$H16*$I16*$J16*$K16*$L16*$M16*$N16=1),1,0) -> 0 | P16: =IF(NOT(Pipeline!$B16<>""),"",IF($O16=1,"Eligible",IF($G16=0,"Too few connections",IF($H16=0,"CAPEX per connection too high",IF($I16=0,"Renewable share too low",IF($J16=0,"Private co-finance too low",IF($K16=0,"Not ready enough",IF($L16=0,"Tariff above cap",IF($M16=0,"Productive use too low",IF($N16=0,"Country not eligible","")))))))))) -> Productive use too low | Q16: =Pipeline!$J16*RBF_HH+Pipeline!$K16*RBF_PU+Pipeline!$L16*RBF_COM+Pipeline!$M16*RBF_INST -> 78750 | R16: =Pipeline!$N16*GrantPct -> 225000 | S16: =MAX(0,MIN($Q16+$R16,MaxSupportPct*Pipeline!$N16-Pipeline!$Q16,MaxPerProject,MaxProjShare*Envelope)) -> 303750 | T16: =IF($O16=1,IF(Pipeline!$V16>0,MIN(Pipeline!$V16,$S16),$S16),0) -> 0 | U16: =IFERROR($Q16/($Q16+$R16),1) -> 0.25925926 | V16: =IFERROR($T16/$C16,0) -> 0 | W16: =IFERROR((Pipeline!$O16+Pipeline!$P16)/$T16,0) -> 0 | X16: =IFERROR(Pipeline!$T16/$T16*1000,0) -> 0 | Y16: =IF($O16=0,"",IF(NOT(ISNUMBER(Pipeline!$U16)),"No viability-gap data",IF(Pipeline!$U16<=0,"No viability-gap data",IF($T16<=Pipeline!$U16*(1+VGFTol),"Within viability gap","Above viability gap")))) | Z16: =IF($O16=1,IFERROR($AN16/MAX($AN$7:$AN$31)*100,0),0) -> 0 | AA16: =IF($O16=1,IFERROR($AO16/MAX($AO$7:$AO$31)*100,0),0) -> 0 | AB16: =IF($O16=1,IFERROR($AP16/MAX($AP$7:$AP$31)*100,0),0) -> 0 | AC16: =IF($O16=1,IFERROR($AQ16/MAX($AQ$7:$AQ$31)*100,0),0) -> 0 | AD16: =IF($O16=1,Pipeline!$F16/5*100,0) -> 0 | AE16: =IF($O16=1,Pipeline!$G16/5*100,0) -> 0 | AF16: =IF($O16=1,(6-Pipeline!$H16)/5*100,0) -> 0 | AG16: =IF($O16=1,IF($Y16="Within viability gap",100,IF($Y16="Above viability gap",0,50)),0) -> 0 | AH16: =$Z16*W_Cost+$AA16*W_Lev+$AB16*W_PU+$AC16*W_CO2+$AD16*W_Ready+$AE16*W_Track+$AF16*W_Risk+$AG16*W_Add -> 0 | AI16: =IF($O16=1,$AH16+(26-$A16)/1000000,-1) -> -1 | AJ16: =IF($O16=1,COUNTIF($AI$7:$AI$31,">"&$AI16)+1,"") | AK16: =SUMIF(Allocation!$B$7:$B$31,10,Allocation!$I$7:$I$31) -> 0 | AL16: =IFERROR($AK16/$T16,0) -> 0 | AM16: =IF($O16=0,"",IF($AL16>=0.999,"Funded",IF($AK16>0,"Partially funded","Not funded"))) | AN16: =IF(AND($O16=1,$V16>0),1/$V16,0) -> 0 | AO16: =IF($O16=1,$W16,0) -> 0 | AP16: =IF($O16=1,$F16,0) -> 0 | AQ16: =IF(AND($O16=1,$T16>0),Pipeline!$T16/$T16,0) -> 0
A17: =11 -> 11 | B17: =IF(Pipeline!$B17<>"",Pipeline!$B17,"") -> Project K - Peri-urban extension | C17: =SUM(Pipeline!$J17:$M17) -> 1460 | D17: =IFERROR(Pipeline!$N17/$C17,0) -> 1027.3973 | E17: =IFERROR((Pipeline!$O17+Pipeline!$P17)/Pipeline!$N17,0) -> 0.53333333 | F17: =IFERROR(Pipeline!$K17/$C17,0) -> 0.061643836 | G17: =IF(NOT(Pipeline!$B17<>""),0,IF(E_MinConn_On=1,IF($C17>=E_MinConn,1,0),1)) -> 1 | H17: =IF(NOT(Pipeline!$B17<>""),0,IF(E_MaxCapexConn_On=1,IF($D17<=E_MaxCapexConn,1,0),1)) -> 1 | I17: =IF(NOT(Pipeline!$B17<>""),0,IF(E_MinRE_On=1,IF(Pipeline!$S17>=E_MinRE,1,0),1)) -> 1 | J17: =IF(NOT(Pipeline!$B17<>""),0,IF(E_MinPrivate_On=1,IF($E17>=E_MinPrivate,1,0),1)) -> 1 | K17: =IF(NOT(Pipeline!$B17<>""),0,IF(E_MinReady_On=1,IF(Pipeline!$F17>=E_MinReady,1,0),1)) -> 1 | L17: =IF(NOT(Pipeline!$B17<>""),0,IF(E_MaxTariff_On=1,IF(Pipeline!$R17<=E_MaxTariff,1,0),1)) -> 1 | M17: =IF(NOT(Pipeline!$B17<>""),0,IF(E_MinPU_On=1,IF($F17>=E_MinPU,1,0),1)) -> 1 | N17: =IF(NOT(Pipeline!$B17<>""),0,IF(E_Country_On=1,IF(IFERROR(INDEX('Fund Parameters'!$B$51:$B$58,MATCH(Pipeline!$C17,'Fund Parameters'!$A$51:$A$58,0))="Y",FALSE()),1,0),1)) -> 1 | O17: =IF(AND(Pipeline!$B17<>"",$G17*$H17*$I17*$J17*$K17*$L17*$M17*$N17=1),1,0) -> 1 | P17: =IF(NOT(Pipeline!$B17<>""),"",IF($O17=1,"Eligible",IF($G17=0,"Too few connections",IF($H17=0,"CAPEX per connection too high",IF($I17=0,"Renewable share too low",IF($J17=0,"Private co-finance too low",IF($K17=0,"Not ready enough",IF($L17=0,"Tariff above cap",IF($M17=0,"Productive use too low",IF($N17=0,"Country not eligible","")))))))))) -> Eligible | Q17: =Pipeline!$J17*RBF_HH+Pipeline!$K17*RBF_PU+Pipeline!$L17*RBF_COM+Pipeline!$M17*RBF_INST -> 181500 | R17: =Pipeline!$N17*GrantPct -> 375000 | S17: =MAX(0,MIN($Q17+$R17,MaxSupportPct*Pipeline!$N17-Pipeline!$Q17,MaxPerProject,MaxProjShare*Envelope)) -> 382500 | T17: =IF($O17=1,IF(Pipeline!$V17>0,MIN(Pipeline!$V17,$S17),$S17),0) -> 382500 | U17: =IFERROR($Q17/($Q17+$R17),1) -> 0.32614555 | V17: =IFERROR($T17/$C17,0) -> 261.9863 | W17: =IFERROR((Pipeline!$O17+Pipeline!$P17)/$T17,0) -> 2.0915033 | X17: =IFERROR(Pipeline!$T17/$T17*1000,0) -> 20.915033 | Y17: =IF($O17=0,"",IF(NOT(ISNUMBER(Pipeline!$U17)),"No viability-gap data",IF(Pipeline!$U17<=0,"No viability-gap data",IF($T17<=Pipeline!$U17*(1+VGFTol),"Within viability gap","Above viability gap")))) -> Within viability gap | Z17: =IF($O17=1,IFERROR($AN17/MAX($AN$7:$AN$31)*100,0),0) -> 85.180863 | AA17: =IF($O17=1,IFERROR($AO17/MAX($AO$7:$AO$31)*100,0),0) -> 80 | AB17: =IF($O17=1,IFERROR($AP17/MAX($AP$7:$AP$31)*100,0),0) -> 38.571429 | AC17: =IF($O17=1,IFERROR($AQ17/MAX($AQ$7:$AQ$31)*100,0),0) -> 66.666667 | AD17: =IF($O17=1,Pipeline!$F17/5*100,0) -> 100 | AE17: =IF($O17=1,Pipeline!$G17/5*100,0) -> 80 | AF17: =IF($O17=1,(6-Pipeline!$H17)/5*100,0) -> 80 | AG17: =IF($O17=1,IF($Y17="Within viability gap",100,IF($Y17="Above viability gap",0,50)),0) -> 100 | AH17: =$Z17*W_Cost+$AA17*W_Lev+$AB17*W_PU+$AC17*W_CO2+$AD17*W_Ready+$AE17*W_Track+$AF17*W_Risk+$AG17*W_Add -> 77.747597 | AI17: =IF($O17=1,$AH17+(26-$A17)/1000000,-1) -> 77.747612 | AJ17: =IF($O17=1,COUNTIF($AI$7:$AI$31,">"&$AI17)+1,"") -> 2 | AK17: =SUMIF(Allocation!$B$7:$B$31,11,Allocation!$I$7:$I$31) -> 382500 | AL17: =IFERROR($AK17/$T17,0) -> 1 | AM17: =IF($O17=0,"",IF($AL17>=0.999,"Funded",IF($AK17>0,"Partially funded","Not funded"))) -> Funded | AN17: =IF(AND($O17=1,$V17>0),1/$V17,0) -> 0.0038169935 | AO17: =IF($O17=1,$W17,0) -> 2.0915033 | AP17: =IF($O17=1,$F17,0) -> 0.061643836 | AQ17: =IF(AND($O17=1,$T17>0),Pipeline!$T17/$T17,0) -> 0.020915033
A18: =12 -> 12 | B18: =IF(Pipeline!$B18<>"",Pipeline!$B18,"") -> Project L - Mining belt | C18: =SUM(Pipeline!$J18:$M18) -> 1298 | D18: =IFERROR(Pipeline!$N18/$C18,0) -> 1309.7072 | E18: =IFERROR((Pipeline!$O18+Pipeline!$P18)/Pipeline!$N18,0) -> 0.41176471 | F18: =IFERROR(Pipeline!$K18/$C18,0) -> 0.1155624 | G18: =IF(NOT(Pipeline!$B18<>""),0,IF(E_MinConn_On=1,IF($C18>=E_MinConn,1,0),1)) -> 1 | H18: =IF(NOT(Pipeline!$B18<>""),0,IF(E_MaxCapexConn_On=1,IF($D18<=E_MaxCapexConn,1,0),1)) -> 1 | I18: =IF(NOT(Pipeline!$B18<>""),0,IF(E_MinRE_On=1,IF(Pipeline!$S18>=E_MinRE,1,0),1)) -> 1 | J18: =IF(NOT(Pipeline!$B18<>""),0,IF(E_MinPrivate_On=1,IF($E18>=E_MinPrivate,1,0),1)) -> 1 | K18: =IF(NOT(Pipeline!$B18<>""),0,IF(E_MinReady_On=1,IF(Pipeline!$F18>=E_MinReady,1,0),1)) -> 1 | L18: =IF(NOT(Pipeline!$B18<>""),0,IF(E_MaxTariff_On=1,IF(Pipeline!$R18<=E_MaxTariff,1,0),1)) -> 1 | M18: =IF(NOT(Pipeline!$B18<>""),0,IF(E_MinPU_On=1,IF($F18>=E_MinPU,1,0),1)) -> 1 | N18: =IF(NOT(Pipeline!$B18<>""),0,IF(E_Country_On=1,IF(IFERROR(INDEX('Fund Parameters'!$B$51:$B$58,MATCH(Pipeline!$C18,'Fund Parameters'!$A$51:$A$58,0))="Y",FALSE()),1,0),1)) -> 1 | O18: =IF(AND(Pipeline!$B18<>"",$G18*$H18*$I18*$J18*$K18*$L18*$M18*$N18=1),1,0) -> 1 | P18: =IF(NOT(Pipeline!$B18<>""),"",IF($O18=1,"Eligible",IF($G18=0,"Too few connections",IF($H18=0,"CAPEX per connection too high",IF($I18=0,"Renewable share too low",IF($J18=0,"Private co-finance too low",IF($K18=0,"Not ready enough",IF($L18=0,"Tariff above cap",IF($M18=0,"Productive use too low",IF($N18=0,"Country not eligible","")))))))))) -> Eligible | Q18: =Pipeline!$J18*RBF_HH+Pipeline!$K18*RBF_PU+Pipeline!$L18*RBF_COM+Pipeline!$M18*RBF_INST -> 175000 | R18: =Pipeline!$N18*GrantPct -> 425000 | S18: =MAX(0,MIN($Q18+$R18,MaxSupportPct*Pipeline!$N18-Pipeline!$Q18,MaxPerProject,MaxProjShare*Envelope)) -> 382500 | T18: =IF($O18=1,IF(Pipeline!$V18>0,MIN(Pipeline!$V18,$S18),$S18),0) -> 382500 | U18: =IFERROR($Q18/($Q18+$R18),1) -> 0.29166667 | V18: =IFERROR($T18/$C18,0) -> 294.68413 | W18: =IFERROR((Pipeline!$O18+Pipeline!$P18)/$T18,0) -> 1.8300654 | X18: =IFERROR(Pipeline!$T18/$T18*1000,0) -> 19.607843 | Y18: =IF($O18=0,"",IF(NOT(ISNUMBER(Pipeline!$U18)),"No viability-gap data",IF(Pipeline!$U18<=0,"No viability-gap data",IF($T18<=Pipeline!$U18*(1+VGFTol),"Within viability gap","Above viability gap")))) -> Within viability gap | Z18: =IF($O18=1,IFERROR($AN18/MAX($AN$7:$AN$31)*100,0),0) -> 75.729288 | AA18: =IF($O18=1,IFERROR($AO18/MAX($AO$7:$AO$31)*100,0),0) -> 70 | AB18: =IF($O18=1,IFERROR($AP18/MAX($AP$7:$AP$31)*100,0),0) -> 72.309047 | AC18: =IF($O18=1,IFERROR($AQ18/MAX($AQ$7:$AQ$31)*100,0),0) -> 62.5 | AD18: =IF($O18=1,Pipeline!$F18/5*100,0) -> 60 | AE18: =IF($O18=1,Pipeline!$G18/5*100,0) -> 100 | AF18: =IF($O18=1,(6-Pipeline!$H18)/5*100,0) -> 60 | AG18: =IF($O18=1,IF($Y18="Within viability gap",100,IF($Y18="Above viability gap",0,50)),0) -> 100 | AH18: =$Z18*W_Cost+$AA18*W_Lev+$AB18*W_PU+$AC18*W_CO2+$AD18*W_Ready+$AE18*W_Track+$AF18*W_Risk+$AG18*W_Add -> 75.528679 | AI18: =IF($O18=1,$AH18+(26-$A18)/1000000,-1) -> 75.528693 | AJ18: =IF($O18=1,COUNTIF($AI$7:$AI$31,">"&$AI18)+1,"") -> 3 | AK18: =SUMIF(Allocation!$B$7:$B$31,12,Allocation!$I$7:$I$31) -> 382500 | AL18: =IFERROR($AK18/$T18,0) -> 1 | AM18: =IF($O18=0,"",IF($AL18>=0.999,"Funded",IF($AK18>0,"Partially funded","Not funded"))) -> Funded | AN18: =IF(AND($O18=1,$V18>0),1/$V18,0) -> 0.0033934641 | AO18: =IF($O18=1,$W18,0) -> 1.8300654 | AP18: =IF($O18=1,$F18,0) -> 0.1155624 | AQ18: =IF(AND($O18=1,$T18>0),Pipeline!$T18/$T18,0) -> 0.019607843
A19: =13 -> 13 | B19: =IF(Pipeline!$B19<>"",Pipeline!$B19,"") -> Project M - Small pilot | C19: =SUM(Pipeline!$J19:$M19) -> 182 | D19: =IFERROR(Pipeline!$N19/$C19,0) -> 1648.3516 | E19: =IFERROR((Pipeline!$O19+Pipeline!$P19)/Pipeline!$N19,0) -> 0.16666667 | F19: =IFERROR(Pipeline!$K19/$C19,0) -> 0.054945055 | G19: =IF(NOT(Pipeline!$B19<>""),0,IF(E_MinConn_On=1,IF($C19>=E_MinConn,1,0),1)) -> 0 | H19: =IF(NOT(Pipeline!$B19<>""),0,IF(E_MaxCapexConn_On=1,IF($D19<=E_MaxCapexConn,1,0),1)) -> 1 | I19: =IF(NOT(Pipeline!$B19<>""),0,IF(E_MinRE_On=1,IF(Pipeline!$S19>=E_MinRE,1,0),1)) -> 1 | J19: =IF(NOT(Pipeline!$B19<>""),0,IF(E_MinPrivate_On=1,IF($E19>=E_MinPrivate,1,0),1)) -> 0 | K19: =IF(NOT(Pipeline!$B19<>""),0,IF(E_MinReady_On=1,IF(Pipeline!$F19>=E_MinReady,1,0),1)) -> 1 | L19: =IF(NOT(Pipeline!$B19<>""),0,IF(E_MaxTariff_On=1,IF(Pipeline!$R19<=E_MaxTariff,1,0),1)) -> 1 | M19: =IF(NOT(Pipeline!$B19<>""),0,IF(E_MinPU_On=1,IF($F19>=E_MinPU,1,0),1)) -> 1 | N19: =IF(NOT(Pipeline!$B19<>""),0,IF(E_Country_On=1,IF(IFERROR(INDEX('Fund Parameters'!$B$51:$B$58,MATCH(Pipeline!$C19,'Fund Parameters'!$A$51:$A$58,0))="Y",FALSE()),1,0),1)) -> 1 | O19: =IF(AND(Pipeline!$B19<>"",$G19*$H19*$I19*$J19*$K19*$L19*$M19*$N19=1),1,0) -> 0 | P19: =IF(NOT(Pipeline!$B19<>""),"",IF($O19=1,"Eligible",IF($G19=0,"Too few connections",IF($H19=0,"CAPEX per connection too high",IF($I19=0,"Renewable share too low",IF($J19=0,"Private co-finance too low",IF($K19=0,"Not ready enough",IF($L19=0,"Tariff above cap",IF($M19=0,"Productive use too low",IF($N19=0,"Country not eligible","")))))))))) -> Too few connections | Q19: =Pipeline!$J19*RBF_HH+Pipeline!$K19*RBF_PU+Pipeline!$L19*RBF_COM+Pipeline!$M19*RBF_INST -> 22500 | R19: =Pipeline!$N19*GrantPct -> 75000 | S19: =MAX(0,MIN($Q19+$R19,MaxSupportPct*Pipeline!$N19-Pipeline!$Q19,MaxPerProject,MaxProjShare*Envelope)) -> 97500 | T19: =IF($O19=1,IF(Pipeline!$V19>0,MIN(Pipeline!$V19,$S19),$S19),0) -> 0 | U19: =IFERROR($Q19/($Q19+$R19),1) -> 0.23076923 | V19: =IFERROR($T19/$C19,0) -> 0 | W19: =IFERROR((Pipeline!$O19+Pipeline!$P19)/$T19,0) -> 0 | X19: =IFERROR(Pipeline!$T19/$T19*1000,0) -> 0 | Y19: =IF($O19=0,"",IF(NOT(ISNUMBER(Pipeline!$U19)),"No viability-gap data",IF(Pipeline!$U19<=0,"No viability-gap data",IF($T19<=Pipeline!$U19*(1+VGFTol),"Within viability gap","Above viability gap")))) | Z19: =IF($O19=1,IFERROR($AN19/MAX($AN$7:$AN$31)*100,0),0) -> 0 | AA19: =IF($O19=1,IFERROR($AO19/MAX($AO$7:$AO$31)*100,0),0) -> 0 | AB19: =IF($O19=1,IFERROR($AP19/MAX($AP$7:$AP$31)*100,0),0) -> 0 | AC19: =IF($O19=1,IFERROR($AQ19/MAX($AQ$7:$AQ$31)*100,0),0) -> 0 | AD19: =IF($O19=1,Pipeline!$F19/5*100,0) -> 0 | AE19: =IF($O19=1,Pipeline!$G19/5*100,0) -> 0 | AF19: =IF($O19=1,(6-Pipeline!$H19)/5*100,0) -> 0 | AG19: =IF($O19=1,IF($Y19="Within viability gap",100,IF($Y19="Above viability gap",0,50)),0) -> 0 | AH19: =$Z19*W_Cost+$AA19*W_Lev+$AB19*W_PU+$AC19*W_CO2+$AD19*W_Ready+$AE19*W_Track+$AF19*W_Risk+$AG19*W_Add -> 0 | AI19: =IF($O19=1,$AH19+(26-$A19)/1000000,-1) -> -1 | AJ19: =IF($O19=1,COUNTIF($AI$7:$AI$31,">"&$AI19)+1,"") | AK19: =SUMIF(Allocation!$B$7:$B$31,13,Allocation!$I$7:$I$31) -> 0 | AL19: =IFERROR($AK19/$T19,0) -> 0 | AM19: =IF($O19=0,"",IF($AL19>=0.999,"Funded",IF($AK19>0,"Partially funded","Not funded"))) | AN19: =IF(AND($O19=1,$V19>0),1/$V19,0) -> 0 | AO19: =IF($O19=1,$W19,0) -> 0 | AP19: =IF($O19=1,$F19,0) -> 0 | AQ19: =IF(AND($O19=1,$T19>0),Pipeline!$T19/$T19,0) -> 0
A20: =14 -> 14 | B20: =IF(Pipeline!$B20<>"",Pipeline!$B20,"") -> Project N - Lakeside expansion | C20: =SUM(Pipeline!$J20:$M20) -> 1014 | D20: =IFERROR(Pipeline!$N20/$C20,0) -> 1232.7416 | E20: =IFERROR((Pipeline!$O20+Pipeline!$P20)/Pipeline!$N20,0) -> 0.44 | F20: =IFERROR(Pipeline!$K20/$C20,0) -> 0.054240631 | G20: =IF(NOT(Pipeline!$B20<>""),0,IF(E_MinConn_On=1,IF($C20>=E_MinConn,1,0),1)) -> 1 | H20: =IF(NOT(Pipeline!$B20<>""),0,IF(E_MaxCapexConn_On=1,IF($D20<=E_MaxCapexConn,1,0),1)) -> 1 | I20: =IF(NOT(Pipeline!$B20<>""),0,IF(E_MinRE_On=1,IF(Pipeline!$S20>=E_MinRE,1,0),1)) -> 1 | J20: =IF(NOT(Pipeline!$B20<>""),0,IF(E_MinPrivate_On=1,IF($E20>=E_MinPrivate,1,0),1)) -> 1 | K20: =IF(NOT(Pipeline!$B20<>""),0,IF(E_MinReady_On=1,IF(Pipeline!$F20>=E_MinReady,1,0),1)) -> 1 | L20: =IF(NOT(Pipeline!$B20<>""),0,IF(E_MaxTariff_On=1,IF(Pipeline!$R20<=E_MaxTariff,1,0),1)) -> 1 | M20: =IF(NOT(Pipeline!$B20<>""),0,IF(E_MinPU_On=1,IF($F20>=E_MinPU,1,0),1)) -> 1 | N20: =IF(NOT(Pipeline!$B20<>""),0,IF(E_Country_On=1,IF(IFERROR(INDEX('Fund Parameters'!$B$51:$B$58,MATCH(Pipeline!$C20,'Fund Parameters'!$A$51:$A$58,0))="Y",FALSE()),1,0),1)) -> 1 | O20: =IF(AND(Pipeline!$B20<>"",$G20*$H20*$I20*$J20*$K20*$L20*$M20*$N20=1),1,0) -> 1 | P20: =IF(NOT(Pipeline!$B20<>""),"",IF($O20=1,"Eligible",IF($G20=0,"Too few connections",IF($H20=0,"CAPEX per connection too high",IF($I20=0,"Renewable share too low",IF($J20=0,"Private co-finance too low",IF($K20=0,"Not ready enough",IF($L20=0,"Tariff above cap",IF($M20=0,"Productive use too low",IF($N20=0,"Country not eligible","")))))))))) -> Eligible | Q20: =Pipeline!$J20*RBF_HH+Pipeline!$K20*RBF_PU+Pipeline!$L20*RBF_COM+Pipeline!$M20*RBF_INST -> 123750 | R20: =Pipeline!$N20*GrantPct -> 312500 | S20: =MAX(0,MIN($Q20+$R20,MaxSupportPct*Pipeline!$N20-Pipeline!$Q20,MaxPerProject,MaxProjShare*Envelope)) -> 382500 | T20: =IF($O20=1,IF(Pipeline!$V20>0,MIN(Pipeline!$V20,$S20),$S20),0) -> 382500 | U20: =IFERROR($Q20/($Q20+$R20),1) -> 0.28366762 | V20: =IFERROR($T20/$C20,0) -> 377.21893 | W20: =IFERROR((Pipeline!$O20+Pipeline!$P20)/$T20,0) -> 1.4379085 | X20: =IFERROR(Pipeline!$T20/$T20*1000,0) -> 17.777778 | Y20: =IF($O20=0,"",IF(NOT(ISNUMBER(Pipeline!$U20)),"No viability-gap data",IF(Pipeline!$U20<=0,"No viability-gap data",IF($T20<=Pipeline!$U20*(1+VGFTol),"Within viability gap","Above viability gap")))) -> Within viability gap | Z20: =IF($O20=1,IFERROR($AN20/MAX($AN$7:$AN$31)*100,0),0) -> 59.15986 | AA20: =IF($O20=1,IFERROR($AO20/MAX($AO$7:$AO$31)*100,0),0) -> 55 | AB20: =IF($O20=1,IFERROR($AP20/MAX($AP$7:$AP$31)*100,0),0) -> 33.939138 | AC20: =IF($O20=1,IFERROR($AQ20/MAX($AQ$7:$AQ$31)*100,0),0) -> 56.666667 | AD20: =IF($O20=1,Pipeline!$F20/5*100,0) -> 80 | AE20: =IF($O20=1,Pipeline!$G20/5*100,0) -> 80 | AF20: =IF($O20=1,(6-Pipeline!$H20)/5*100,0) -> 80 | AG20: =IF($O20=1,IF($Y20="Within viability gap",100,IF($Y20="Above viability gap",0,50)),0) -> 100 | AH20: =$Z20*W_Cost+$AA20*W_Lev+$AB20*W_PU+$AC20*W_CO2+$AD20*W_Ready+$AE20*W_Track+$AF20*W_Risk+$AG20*W_Add -> 63.797502 | AI20: =IF($O20=1,$AH20+(26-$A20)/1000000,-1) -> 63.797514 | AJ20: =IF($O20=1,COUNTIF($AI$7:$AI$31,">"&$AI20)+1,"") -> 6 | AK20: =SUMIF(Allocation!$B$7:$B$31,14,Allocation!$I$7:$I$31) -> 127500 | AL20: =IFERROR($AK20/$T20,0) -> 0.33333333 | AM20: =IF($O20=0,"",IF($AL20>=0.999,"Funded",IF($AK20>0,"Partially funded","Not funded"))) -> Partially funded | AN20: =IF(AND($O20=1,$V20>0),1/$V20,0) -> 0.0026509804 | AO20: =IF($O20=1,$W20,0) -> 1.4379085 | AP20: =IF($O20=1,$F20,0) -> 0.054240631 | AQ20: =IF(AND($O20=1,$T20>0),Pipeline!$T20/$T20,0) -> 0.017777778
A21: =15 -> 15 | B21: =IF(Pipeline!$B21<>"",Pipeline!$B21,"") | C21: =SUM(Pipeline!$J21:$M21) -> 0 | D21: =IFERROR(Pipeline!$N21/$C21,0) -> 0 | E21: =IFERROR((Pipeline!$O21+Pipeline!$P21)/Pipeline!$N21,0) -> 0 | F21: =IFERROR(Pipeline!$K21/$C21,0) -> 0 | G21: =IF(NOT(Pipeline!$B21<>""),0,IF(E_MinConn_On=1,IF($C21>=E_MinConn,1,0),1)) -> 0 | H21: =IF(NOT(Pipeline!$B21<>""),0,IF(E_MaxCapexConn_On=1,IF($D21<=E_MaxCapexConn,1,0),1)) -> 0 | I21: =IF(NOT(Pipeline!$B21<>""),0,IF(E_MinRE_On=1,IF(Pipeline!$S21>=E_MinRE,1,0),1)) -> 0 | J21: =IF(NOT(Pipeline!$B21<>""),0,IF(E_MinPrivate_On=1,IF($E21>=E_MinPrivate,1,0),1)) -> 0 | K21: =IF(NOT(Pipeline!$B21<>""),0,IF(E_MinReady_On=1,IF(Pipeline!$F21>=E_MinReady,1,0),1)) -> 0 | L21: =IF(NOT(Pipeline!$B21<>""),0,IF(E_MaxTariff_On=1,IF(Pipeline!$R21<=E_MaxTariff,1,0),1)) -> 0 | M21: =IF(NOT(Pipeline!$B21<>""),0,IF(E_MinPU_On=1,IF($F21>=E_MinPU,1,0),1)) -> 0 | N21: =IF(NOT(Pipeline!$B21<>""),0,IF(E_Country_On=1,IF(IFERROR(INDEX('Fund Parameters'!$B$51:$B$58,MATCH(Pipeline!$C21,'Fund Parameters'!$A$51:$A$58,0))="Y",FALSE()),1,0),1)) -> 0 | O21: =IF(AND(Pipeline!$B21<>"",$G21*$H21*$I21*$J21*$K21*$L21*$M21*$N21=1),1,0) -> 0 | P21: =IF(NOT(Pipeline!$B21<>""),"",IF($O21=1,"Eligible",IF($G21=0,"Too few connections",IF($H21=0,"CAPEX per connection too high",IF($I21=0,"Renewable share too low",IF($J21=0,"Private co-finance too low",IF($K21=0,"Not ready enough",IF($L21=0,"Tariff above cap",IF($M21=0,"Productive use too low",IF($N21=0,"Country not eligible","")))))))))) | Q21: =Pipeline!$J21*RBF_HH+Pipeline!$K21*RBF_PU+Pipeline!$L21*RBF_COM+Pipeline!$M21*RBF_INST -> 0 | R21: =Pipeline!$N21*GrantPct -> 0 | S21: =MAX(0,MIN($Q21+$R21,MaxSupportPct*Pipeline!$N21-Pipeline!$Q21,MaxPerProject,MaxProjShare*Envelope)) -> 0 | T21: =IF($O21=1,IF(Pipeline!$V21>0,MIN(Pipeline!$V21,$S21),$S21),0) -> 0 | U21: =IFERROR($Q21/($Q21+$R21),1) -> 1 | V21: =IFERROR($T21/$C21,0) -> 0 | W21: =IFERROR((Pipeline!$O21+Pipeline!$P21)/$T21,0) -> 0 | X21: =IFERROR(Pipeline!$T21/$T21*1000,0) -> 0 | Y21: =IF($O21=0,"",IF(NOT(ISNUMBER(Pipeline!$U21)),"No viability-gap data",IF(Pipeline!$U21<=0,"No viability-gap data",IF($T21<=Pipeline!$U21*(1+VGFTol),"Within viability gap","Above viability gap")))) | Z21: =IF($O21=1,IFERROR($AN21/MAX($AN$7:$AN$31)*100,0),0) -> 0 | AA21: =IF($O21=1,IFERROR($AO21/MAX($AO$7:$AO$31)*100,0),0) -> 0 | AB21: =IF($O21=1,IFERROR($AP21/MAX($AP$7:$AP$31)*100,0),0) -> 0 | AC21: =IF($O21=1,IFERROR($AQ21/MAX($AQ$7:$AQ$31)*100,0),0) -> 0 | AD21: =IF($O21=1,Pipeline!$F21/5*100,0) -> 0 | AE21: =IF($O21=1,Pipeline!$G21/5*100,0) -> 0 | AF21: =IF($O21=1,(6-Pipeline!$H21)/5*100,0) -> 0 | AG21: =IF($O21=1,IF($Y21="Within viability gap",100,IF($Y21="Above viability gap",0,50)),0) -> 0 | AH21: =$Z21*W_Cost+$AA21*W_Lev+$AB21*W_PU+$AC21*W_CO2+$AD21*W_Ready+$AE21*W_Track+$AF21*W_Risk+$AG21*W_Add -> 0 | AI21: =IF($O21=1,$AH21+(26-$A21)/1000000,-1) -> -1 | AJ21: =IF($O21=1,COUNTIF($AI$7:$AI$31,">"&$AI21)+1,"") | AK21: =SUMIF(Allocation!$B$7:$B$31,15,Allocation!$I$7:$I$31) -> 0 | AL21: =IFERROR($AK21/$T21,0) -> 0 | AM21: =IF($O21=0,"",IF($AL21>=0.999,"Funded",IF($AK21>0,"Partially funded","Not funded"))) | AN21: =IF(AND($O21=1,$V21>0),1/$V21,0) -> 0 | AO21: =IF($O21=1,$W21,0) -> 0 | AP21: =IF($O21=1,$F21,0) -> 0 | AQ21: =IF(AND($O21=1,$T21>0),Pipeline!$T21/$T21,0) -> 0
A22: =16 -> 16 | B22: =IF(Pipeline!$B22<>"",Pipeline!$B22,"") | C22: =SUM(Pipeline!$J22:$M22) -> 0 | D22: =IFERROR(Pipeline!$N22/$C22,0) -> 0 | E22: =IFERROR((Pipeline!$O22+Pipeline!$P22)/Pipeline!$N22,0) -> 0 | F22: =IFERROR(Pipeline!$K22/$C22,0) -> 0 | G22: =IF(NOT(Pipeline!$B22<>""),0,IF(E_MinConn_On=1,IF($C22>=E_MinConn,1,0),1)) -> 0 | H22: =IF(NOT(Pipeline!$B22<>""),0,IF(E_MaxCapexConn_On=1,IF($D22<=E_MaxCapexConn,1,0),1)) -> 0 | I22: =IF(NOT(Pipeline!$B22<>""),0,IF(E_MinRE_On=1,IF(Pipeline!$S22>=E_MinRE,1,0),1)) -> 0 | J22: =IF(NOT(Pipeline!$B22<>""),0,IF(E_MinPrivate_On=1,IF($E22>=E_MinPrivate,1,0),1)) -> 0 | K22: =IF(NOT(Pipeline!$B22<>""),0,IF(E_MinReady_On=1,IF(Pipeline!$F22>=E_MinReady,1,0),1)) -> 0 | L22: =IF(NOT(Pipeline!$B22<>""),0,IF(E_MaxTariff_On=1,IF(Pipeline!$R22<=E_MaxTariff,1,0),1)) -> 0 | M22: =IF(NOT(Pipeline!$B22<>""),0,IF(E_MinPU_On=1,IF($F22>=E_MinPU,1,0),1)) -> 0 | N22: =IF(NOT(Pipeline!$B22<>""),0,IF(E_Country_On=1,IF(IFERROR(INDEX('Fund Parameters'!$B$51:$B$58,MATCH(Pipeline!$C22,'Fund Parameters'!$A$51:$A$58,0))="Y",FALSE()),1,0),1)) -> 0 | O22: =IF(AND(Pipeline!$B22<>"",$G22*$H22*$I22*$J22*$K22*$L22*$M22*$N22=1),1,0) -> 0 | P22: =IF(NOT(Pipeline!$B22<>""),"",IF($O22=1,"Eligible",IF($G22=0,"Too few connections",IF($H22=0,"CAPEX per connection too high",IF($I22=0,"Renewable share too low",IF($J22=0,"Private co-finance too low",IF($K22=0,"Not ready enough",IF($L22=0,"Tariff above cap",IF($M22=0,"Productive use too low",IF($N22=0,"Country not eligible","")))))))))) | Q22: =Pipeline!$J22*RBF_HH+Pipeline!$K22*RBF_PU+Pipeline!$L22*RBF_COM+Pipeline!$M22*RBF_INST -> 0 | R22: =Pipeline!$N22*GrantPct -> 0 | S22: =MAX(0,MIN($Q22+$R22,MaxSupportPct*Pipeline!$N22-Pipeline!$Q22,MaxPerProject,MaxProjShare*Envelope)) -> 0 | T22: =IF($O22=1,IF(Pipeline!$V22>0,MIN(Pipeline!$V22,$S22),$S22),0) -> 0 | U22: =IFERROR($Q22/($Q22+$R22),1) -> 1 | V22: =IFERROR($T22/$C22,0) -> 0 | W22: =IFERROR((Pipeline!$O22+Pipeline!$P22)/$T22,0) -> 0 | X22: =IFERROR(Pipeline!$T22/$T22*1000,0) -> 0 | Y22: =IF($O22=0,"",IF(NOT(ISNUMBER(Pipeline!$U22)),"No viability-gap data",IF(Pipeline!$U22<=0,"No viability-gap data",IF($T22<=Pipeline!$U22*(1+VGFTol),"Within viability gap","Above viability gap")))) | Z22: =IF($O22=1,IFERROR($AN22/MAX($AN$7:$AN$31)*100,0),0) -> 0 | AA22: =IF($O22=1,IFERROR($AO22/MAX($AO$7:$AO$31)*100,0),0) -> 0 | AB22: =IF($O22=1,IFERROR($AP22/MAX($AP$7:$AP$31)*100,0),0) -> 0 | AC22: =IF($O22=1,IFERROR($AQ22/MAX($AQ$7:$AQ$31)*100,0),0) -> 0 | AD22: =IF($O22=1,Pipeline!$F22/5*100,0) -> 0 | AE22: =IF($O22=1,Pipeline!$G22/5*100,0) -> 0 | AF22: =IF($O22=1,(6-Pipeline!$H22)/5*100,0) -> 0 | AG22: =IF($O22=1,IF($Y22="Within viability gap",100,IF($Y22="Above viability gap",0,50)),0) -> 0 | AH22: =$Z22*W_Cost+$AA22*W_Lev+$AB22*W_PU+$AC22*W_CO2+$AD22*W_Ready+$AE22*W_Track+$AF22*W_Risk+$AG22*W_Add -> 0 | AI22: =IF($O22=1,$AH22+(26-$A22)/1000000,-1) -> -1 | AJ22: =IF($O22=1,COUNTIF($AI$7:$AI$31,">"&$AI22)+1,"") | AK22: =SUMIF(Allocation!$B$7:$B$31,16,Allocation!$I$7:$I$31) -> 0 | AL22: =IFERROR($AK22/$T22,0) -> 0 | AM22: =IF($O22=0,"",IF($AL22>=0.999,"Funded",IF($AK22>0,"Partially funded","Not funded"))) | AN22: =IF(AND($O22=1,$V22>0),1/$V22,0) -> 0 | AO22: =IF($O22=1,$W22,0) -> 0 | AP22: =IF($O22=1,$F22,0) -> 0 | AQ22: =IF(AND($O22=1,$T22>0),Pipeline!$T22/$T22,0) -> 0
A23: =17 -> 17 | B23: =IF(Pipeline!$B23<>"",Pipeline!$B23,"") | C23: =SUM(Pipeline!$J23:$M23) -> 0 | D23: =IFERROR(Pipeline!$N23/$C23,0) -> 0 | E23: =IFERROR((Pipeline!$O23+Pipeline!$P23)/Pipeline!$N23,0) -> 0 | F23: =IFERROR(Pipeline!$K23/$C23,0) -> 0 | G23: =IF(NOT(Pipeline!$B23<>""),0,IF(E_MinConn_On=1,IF($C23>=E_MinConn,1,0),1)) -> 0 | H23: =IF(NOT(Pipeline!$B23<>""),0,IF(E_MaxCapexConn_On=1,IF($D23<=E_MaxCapexConn,1,0),1)) -> 0 | I23: =IF(NOT(Pipeline!$B23<>""),0,IF(E_MinRE_On=1,IF(Pipeline!$S23>=E_MinRE,1,0),1)) -> 0 | J23: =IF(NOT(Pipeline!$B23<>""),0,IF(E_MinPrivate_On=1,IF($E23>=E_MinPrivate,1,0),1)) -> 0 | K23: =IF(NOT(Pipeline!$B23<>""),0,IF(E_MinReady_On=1,IF(Pipeline!$F23>=E_MinReady,1,0),1)) -> 0 | L23: =IF(NOT(Pipeline!$B23<>""),0,IF(E_MaxTariff_On=1,IF(Pipeline!$R23<=E_MaxTariff,1,0),1)) -> 0 | M23: =IF(NOT(Pipeline!$B23<>""),0,IF(E_MinPU_On=1,IF($F23>=E_MinPU,1,0),1)) -> 0 | N23: =IF(NOT(Pipeline!$B23<>""),0,IF(E_Country_On=1,IF(IFERROR(INDEX('Fund Parameters'!$B$51:$B$58,MATCH(Pipeline!$C23,'Fund Parameters'!$A$51:$A$58,0))="Y",FALSE()),1,0),1)) -> 0 | O23: =IF(AND(Pipeline!$B23<>"",$G23*$H23*$I23*$J23*$K23*$L23*$M23*$N23=1),1,0) -> 0 | P23: =IF(NOT(Pipeline!$B23<>""),"",IF($O23=1,"Eligible",IF($G23=0,"Too few connections",IF($H23=0,"CAPEX per connection too high",IF($I23=0,"Renewable share too low",IF($J23=0,"Private co-finance too low",IF($K23=0,"Not ready enough",IF($L23=0,"Tariff above cap",IF($M23=0,"Productive use too low",IF($N23=0,"Country not eligible","")))))))))) | Q23: =Pipeline!$J23*RBF_HH+Pipeline!$K23*RBF_PU+Pipeline!$L23*RBF_COM+Pipeline!$M23*RBF_INST -> 0 | R23: =Pipeline!$N23*GrantPct -> 0 | S23: =MAX(0,MIN($Q23+$R23,MaxSupportPct*Pipeline!$N23-Pipeline!$Q23,MaxPerProject,MaxProjShare*Envelope)) -> 0 | T23: =IF($O23=1,IF(Pipeline!$V23>0,MIN(Pipeline!$V23,$S23),$S23),0) -> 0 | U23: =IFERROR($Q23/($Q23+$R23),1) -> 1 | V23: =IFERROR($T23/$C23,0) -> 0 | W23: =IFERROR((Pipeline!$O23+Pipeline!$P23)/$T23,0) -> 0 | X23: =IFERROR(Pipeline!$T23/$T23*1000,0) -> 0 | Y23: =IF($O23=0,"",IF(NOT(ISNUMBER(Pipeline!$U23)),"No viability-gap data",IF(Pipeline!$U23<=0,"No viability-gap data",IF($T23<=Pipeline!$U23*(1+VGFTol),"Within viability gap","Above viability gap")))) | Z23: =IF($O23=1,IFERROR($AN23/MAX($AN$7:$AN$31)*100,0),0) -> 0 | AA23: =IF($O23=1,IFERROR($AO23/MAX($AO$7:$AO$31)*100,0),0) -> 0 | AB23: =IF($O23=1,IFERROR($AP23/MAX($AP$7:$AP$31)*100,0),0) -> 0 | AC23: =IF($O23=1,IFERROR($AQ23/MAX($AQ$7:$AQ$31)*100,0),0) -> 0 | AD23: =IF($O23=1,Pipeline!$F23/5*100,0) -> 0 | AE23: =IF($O23=1,Pipeline!$G23/5*100,0) -> 0 | AF23: =IF($O23=1,(6-Pipeline!$H23)/5*100,0) -> 0 | AG23: =IF($O23=1,IF($Y23="Within viability gap",100,IF($Y23="Above viability gap",0,50)),0) -> 0 | AH23: =$Z23*W_Cost+$AA23*W_Lev+$AB23*W_PU+$AC23*W_CO2+$AD23*W_Ready+$AE23*W_Track+$AF23*W_Risk+$AG23*W_Add -> 0 | AI23: =IF($O23=1,$AH23+(26-$A23)/1000000,-1) -> -1 | AJ23: =IF($O23=1,COUNTIF($AI$7:$AI$31,">"&$AI23)+1,"") | AK23: =SUMIF(Allocation!$B$7:$B$31,17,Allocation!$I$7:$I$31) -> 0 | AL23: =IFERROR($AK23/$T23,0) -> 0 | AM23: =IF($O23=0,"",IF($AL23>=0.999,"Funded",IF($AK23>0,"Partially funded","Not funded"))) | AN23: =IF(AND($O23=1,$V23>0),1/$V23,0) -> 0 | AO23: =IF($O23=1,$W23,0) -> 0 | AP23: =IF($O23=1,$F23,0) -> 0 | AQ23: =IF(AND($O23=1,$T23>0),Pipeline!$T23/$T23,0) -> 0
A24: =18 -> 18 | B24: =IF(Pipeline!$B24<>"",Pipeline!$B24,"") | C24: =SUM(Pipeline!$J24:$M24) -> 0 | D24: =IFERROR(Pipeline!$N24/$C24,0) -> 0 | E24: =IFERROR((Pipeline!$O24+Pipeline!$P24)/Pipeline!$N24,0) -> 0 | F24: =IFERROR(Pipeline!$K24/$C24,0) -> 0 | G24: =IF(NOT(Pipeline!$B24<>""),0,IF(E_MinConn_On=1,IF($C24>=E_MinConn,1,0),1)) -> 0 | H24: =IF(NOT(Pipeline!$B24<>""),0,IF(E_MaxCapexConn_On=1,IF($D24<=E_MaxCapexConn,1,0),1)) -> 0 | I24: =IF(NOT(Pipeline!$B24<>""),0,IF(E_MinRE_On=1,IF(Pipeline!$S24>=E_MinRE,1,0),1)) -> 0 | J24: =IF(NOT(Pipeline!$B24<>""),0,IF(E_MinPrivate_On=1,IF($E24>=E_MinPrivate,1,0),1)) -> 0 | K24: =IF(NOT(Pipeline!$B24<>""),0,IF(E_MinReady_On=1,IF(Pipeline!$F24>=E_MinReady,1,0),1)) -> 0 | L24: =IF(NOT(Pipeline!$B24<>""),0,IF(E_MaxTariff_On=1,IF(Pipeline!$R24<=E_MaxTariff,1,0),1)) -> 0 | M24: =IF(NOT(Pipeline!$B24<>""),0,IF(E_MinPU_On=1,IF($F24>=E_MinPU,1,0),1)) -> 0 | N24: =IF(NOT(Pipeline!$B24<>""),0,IF(E_Country_On=1,IF(IFERROR(INDEX('Fund Parameters'!$B$51:$B$58,MATCH(Pipeline!$C24,'Fund Parameters'!$A$51:$A$58,0))="Y",FALSE()),1,0),1)) -> 0 | O24: =IF(AND(Pipeline!$B24<>"",$G24*$H24*$I24*$J24*$K24*$L24*$M24*$N24=1),1,0) -> 0 | P24: =IF(NOT(Pipeline!$B24<>""),"",IF($O24=1,"Eligible",IF($G24=0,"Too few connections",IF($H24=0,"CAPEX per connection too high",IF($I24=0,"Renewable share too low",IF($J24=0,"Private co-finance too low",IF($K24=0,"Not ready enough",IF($L24=0,"Tariff above cap",IF($M24=0,"Productive use too low",IF($N24=0,"Country not eligible","")))))))))) | Q24: =Pipeline!$J24*RBF_HH+Pipeline!$K24*RBF_PU+Pipeline!$L24*RBF_COM+Pipeline!$M24*RBF_INST -> 0 | R24: =Pipeline!$N24*GrantPct -> 0 | S24: =MAX(0,MIN($Q24+$R24,MaxSupportPct*Pipeline!$N24-Pipeline!$Q24,MaxPerProject,MaxProjShare*Envelope)) -> 0 | T24: =IF($O24=1,IF(Pipeline!$V24>0,MIN(Pipeline!$V24,$S24),$S24),0) -> 0 | U24: =IFERROR($Q24/($Q24+$R24),1) -> 1 | V24: =IFERROR($T24/$C24,0) -> 0 | W24: =IFERROR((Pipeline!$O24+Pipeline!$P24)/$T24,0) -> 0 | X24: =IFERROR(Pipeline!$T24/$T24*1000,0) -> 0 | Y24: =IF($O24=0,"",IF(NOT(ISNUMBER(Pipeline!$U24)),"No viability-gap data",IF(Pipeline!$U24<=0,"No viability-gap data",IF($T24<=Pipeline!$U24*(1+VGFTol),"Within viability gap","Above viability gap")))) | Z24: =IF($O24=1,IFERROR($AN24/MAX($AN$7:$AN$31)*100,0),0) -> 0 | AA24: =IF($O24=1,IFERROR($AO24/MAX($AO$7:$AO$31)*100,0),0) -> 0 | AB24: =IF($O24=1,IFERROR($AP24/MAX($AP$7:$AP$31)*100,0),0) -> 0 | AC24: =IF($O24=1,IFERROR($AQ24/MAX($AQ$7:$AQ$31)*100,0),0) -> 0 | AD24: =IF($O24=1,Pipeline!$F24/5*100,0) -> 0 | AE24: =IF($O24=1,Pipeline!$G24/5*100,0) -> 0 | AF24: =IF($O24=1,(6-Pipeline!$H24)/5*100,0) -> 0 | AG24: =IF($O24=1,IF($Y24="Within viability gap",100,IF($Y24="Above viability gap",0,50)),0) -> 0 | AH24: =$Z24*W_Cost+$AA24*W_Lev+$AB24*W_PU+$AC24*W_CO2+$AD24*W_Ready+$AE24*W_Track+$AF24*W_Risk+$AG24*W_Add -> 0 | AI24: =IF($O24=1,$AH24+(26-$A24)/1000000,-1) -> -1 | AJ24: =IF($O24=1,COUNTIF($AI$7:$AI$31,">"&$AI24)+1,"") | AK24: =SUMIF(Allocation!$B$7:$B$31,18,Allocation!$I$7:$I$31) -> 0 | AL24: =IFERROR($AK24/$T24,0) -> 0 | AM24: =IF($O24=0,"",IF($AL24>=0.999,"Funded",IF($AK24>0,"Partially funded","Not funded"))) | AN24: =IF(AND($O24=1,$V24>0),1/$V24,0) -> 0 | AO24: =IF($O24=1,$W24,0) -> 0 | AP24: =IF($O24=1,$F24,0) -> 0 | AQ24: =IF(AND($O24=1,$T24>0),Pipeline!$T24/$T24,0) -> 0
A25: =19 -> 19 | B25: =IF(Pipeline!$B25<>"",Pipeline!$B25,"") | C25: =SUM(Pipeline!$J25:$M25) -> 0 | D25: =IFERROR(Pipeline!$N25/$C25,0) -> 0 | E25: =IFERROR((Pipeline!$O25+Pipeline!$P25)/Pipeline!$N25,0) -> 0 | F25: =IFERROR(Pipeline!$K25/$C25,0) -> 0 | G25: =IF(NOT(Pipeline!$B25<>""),0,IF(E_MinConn_On=1,IF($C25>=E_MinConn,1,0),1)) -> 0 | H25: =IF(NOT(Pipeline!$B25<>""),0,IF(E_MaxCapexConn_On=1,IF($D25<=E_MaxCapexConn,1,0),1)) -> 0 | I25: =IF(NOT(Pipeline!$B25<>""),0,IF(E_MinRE_On=1,IF(Pipeline!$S25>=E_MinRE,1,0),1)) -> 0 | J25: =IF(NOT(Pipeline!$B25<>""),0,IF(E_MinPrivate_On=1,IF($E25>=E_MinPrivate,1,0),1)) -> 0 | K25: =IF(NOT(Pipeline!$B25<>""),0,IF(E_MinReady_On=1,IF(Pipeline!$F25>=E_MinReady,1,0),1)) -> 0 | L25: =IF(NOT(Pipeline!$B25<>""),0,IF(E_MaxTariff_On=1,IF(Pipeline!$R25<=E_MaxTariff,1,0),1)) -> 0 | M25: =IF(NOT(Pipeline!$B25<>""),0,IF(E_MinPU_On=1,IF($F25>=E_MinPU,1,0),1)) -> 0 | N25: =IF(NOT(Pipeline!$B25<>""),0,IF(E_Country_On=1,IF(IFERROR(INDEX('Fund Parameters'!$B$51:$B$58,MATCH(Pipeline!$C25,'Fund Parameters'!$A$51:$A$58,0))="Y",FALSE()),1,0),1)) -> 0 | O25: =IF(AND(Pipeline!$B25<>"",$G25*$H25*$I25*$J25*$K25*$L25*$M25*$N25=1),1,0) -> 0 | P25: =IF(NOT(Pipeline!$B25<>""),"",IF($O25=1,"Eligible",IF($G25=0,"Too few connections",IF($H25=0,"CAPEX per connection too high",IF($I25=0,"Renewable share too low",IF($J25=0,"Private co-finance too low",IF($K25=0,"Not ready enough",IF($L25=0,"Tariff above cap",IF($M25=0,"Productive use too low",IF($N25=0,"Country not eligible","")))))))))) | Q25: =Pipeline!$J25*RBF_HH+Pipeline!$K25*RBF_PU+Pipeline!$L25*RBF_COM+Pipeline!$M25*RBF_INST -> 0 | R25: =Pipeline!$N25*GrantPct -> 0 | S25: =MAX(0,MIN($Q25+$R25,MaxSupportPct*Pipeline!$N25-Pipeline!$Q25,MaxPerProject,MaxProjShare*Envelope)) -> 0 | T25: =IF($O25=1,IF(Pipeline!$V25>0,MIN(Pipeline!$V25,$S25),$S25),0) -> 0 | U25: =IFERROR($Q25/($Q25+$R25),1) -> 1 | V25: =IFERROR($T25/$C25,0) -> 0 | W25: =IFERROR((Pipeline!$O25+Pipeline!$P25)/$T25,0) -> 0 | X25: =IFERROR(Pipeline!$T25/$T25*1000,0) -> 0 | Y25: =IF($O25=0,"",IF(NOT(ISNUMBER(Pipeline!$U25)),"No viability-gap data",IF(Pipeline!$U25<=0,"No viability-gap data",IF($T25<=Pipeline!$U25*(1+VGFTol),"Within viability gap","Above viability gap")))) | Z25: =IF($O25=1,IFERROR($AN25/MAX($AN$7:$AN$31)*100,0),0) -> 0 | AA25: =IF($O25=1,IFERROR($AO25/MAX($AO$7:$AO$31)*100,0),0) -> 0 | AB25: =IF($O25=1,IFERROR($AP25/MAX($AP$7:$AP$31)*100,0),0) -> 0 | AC25: =IF($O25=1,IFERROR($AQ25/MAX($AQ$7:$AQ$31)*100,0),0) -> 0 | AD25: =IF($O25=1,Pipeline!$F25/5*100,0) -> 0 | AE25: =IF($O25=1,Pipeline!$G25/5*100,0) -> 0 | AF25: =IF($O25=1,(6-Pipeline!$H25)/5*100,0) -> 0 | AG25: =IF($O25=1,IF($Y25="Within viability gap",100,IF($Y25="Above viability gap",0,50)),0) -> 0 | AH25: =$Z25*W_Cost+$AA25*W_Lev+$AB25*W_PU+$AC25*W_CO2+$AD25*W_Ready+$AE25*W_Track+$AF25*W_Risk+$AG25*W_Add -> 0 | AI25: =IF($O25=1,$AH25+(26-$A25)/1000000,-1) -> -1 | AJ25: =IF($O25=1,COUNTIF($AI$7:$AI$31,">"&$AI25)+1,"") | AK25: =SUMIF(Allocation!$B$7:$B$31,19,Allocation!$I$7:$I$31) -> 0 | AL25: =IFERROR($AK25/$T25,0) -> 0 | AM25: =IF($O25=0,"",IF($AL25>=0.999,"Funded",IF($AK25>0,"Partially funded","Not funded"))) | AN25: =IF(AND($O25=1,$V25>0),1/$V25,0) -> 0 | AO25: =IF($O25=1,$W25,0) -> 0 | AP25: =IF($O25=1,$F25,0) -> 0 | AQ25: =IF(AND($O25=1,$T25>0),Pipeline!$T25/$T25,0) -> 0
A26: =20 -> 20 | B26: =IF(Pipeline!$B26<>"",Pipeline!$B26,"") | C26: =SUM(Pipeline!$J26:$M26) -> 0 | D26: =IFERROR(Pipeline!$N26/$C26,0) -> 0 | E26: =IFERROR((Pipeline!$O26+Pipeline!$P26)/Pipeline!$N26,0) -> 0 | F26: =IFERROR(Pipeline!$K26/$C26,0) -> 0 | G26: =IF(NOT(Pipeline!$B26<>""),0,IF(E_MinConn_On=1,IF($C26>=E_MinConn,1,0),1)) -> 0 | H26: =IF(NOT(Pipeline!$B26<>""),0,IF(E_MaxCapexConn_On=1,IF($D26<=E_MaxCapexConn,1,0),1)) -> 0 | I26: =IF(NOT(Pipeline!$B26<>""),0,IF(E_MinRE_On=1,IF(Pipeline!$S26>=E_MinRE,1,0),1)) -> 0 | J26: =IF(NOT(Pipeline!$B26<>""),0,IF(E_MinPrivate_On=1,IF($E26>=E_MinPrivate,1,0),1)) -> 0 | K26: =IF(NOT(Pipeline!$B26<>""),0,IF(E_MinReady_On=1,IF(Pipeline!$F26>=E_MinReady,1,0),1)) -> 0 | L26: =IF(NOT(Pipeline!$B26<>""),0,IF(E_MaxTariff_On=1,IF(Pipeline!$R26<=E_MaxTariff,1,0),1)) -> 0 | M26: =IF(NOT(Pipeline!$B26<>""),0,IF(E_MinPU_On=1,IF($F26>=E_MinPU,1,0),1)) -> 0 | N26: =IF(NOT(Pipeline!$B26<>""),0,IF(E_Country_On=1,IF(IFERROR(INDEX('Fund Parameters'!$B$51:$B$58,MATCH(Pipeline!$C26,'Fund Parameters'!$A$51:$A$58,0))="Y",FALSE()),1,0),1)) -> 0 | O26: =IF(AND(Pipeline!$B26<>"",$G26*$H26*$I26*$J26*$K26*$L26*$M26*$N26=1),1,0) -> 0 | P26: =IF(NOT(Pipeline!$B26<>""),"",IF($O26=1,"Eligible",IF($G26=0,"Too few connections",IF($H26=0,"CAPEX per connection too high",IF($I26=0,"Renewable share too low",IF($J26=0,"Private co-finance too low",IF($K26=0,"Not ready enough",IF($L26=0,"Tariff above cap",IF($M26=0,"Productive use too low",IF($N26=0,"Country not eligible","")))))))))) | Q26: =Pipeline!$J26*RBF_HH+Pipeline!$K26*RBF_PU+Pipeline!$L26*RBF_COM+Pipeline!$M26*RBF_INST -> 0 | R26: =Pipeline!$N26*GrantPct -> 0 | S26: =MAX(0,MIN($Q26+$R26,MaxSupportPct*Pipeline!$N26-Pipeline!$Q26,MaxPerProject,MaxProjShare*Envelope)) -> 0 | T26: =IF($O26=1,IF(Pipeline!$V26>0,MIN(Pipeline!$V26,$S26),$S26),0) -> 0 | U26: =IFERROR($Q26/($Q26+$R26),1) -> 1 | V26: =IFERROR($T26/$C26,0) -> 0 | W26: =IFERROR((Pipeline!$O26+Pipeline!$P26)/$T26,0) -> 0 | X26: =IFERROR(Pipeline!$T26/$T26*1000,0) -> 0 | Y26: =IF($O26=0,"",IF(NOT(ISNUMBER(Pipeline!$U26)),"No viability-gap data",IF(Pipeline!$U26<=0,"No viability-gap data",IF($T26<=Pipeline!$U26*(1+VGFTol),"Within viability gap","Above viability gap")))) | Z26: =IF($O26=1,IFERROR($AN26/MAX($AN$7:$AN$31)*100,0),0) -> 0 | AA26: =IF($O26=1,IFERROR($AO26/MAX($AO$7:$AO$31)*100,0),0) -> 0 | AB26: =IF($O26=1,IFERROR($AP26/MAX($AP$7:$AP$31)*100,0),0) -> 0 | AC26: =IF($O26=1,IFERROR($AQ26/MAX($AQ$7:$AQ$31)*100,0),0) -> 0 | AD26: =IF($O26=1,Pipeline!$F26/5*100,0) -> 0 | AE26: =IF($O26=1,Pipeline!$G26/5*100,0) -> 0 | AF26: =IF($O26=1,(6-Pipeline!$H26)/5*100,0) -> 0 | AG26: =IF($O26=1,IF($Y26="Within viability gap",100,IF($Y26="Above viability gap",0,50)),0) -> 0 | AH26: =$Z26*W_Cost+$AA26*W_Lev+$AB26*W_PU+$AC26*W_CO2+$AD26*W_Ready+$AE26*W_Track+$AF26*W_Risk+$AG26*W_Add -> 0 | AI26: =IF($O26=1,$AH26+(26-$A26)/1000000,-1) -> -1 | AJ26: =IF($O26=1,COUNTIF($AI$7:$AI$31,">"&$AI26)+1,"") | AK26: =SUMIF(Allocation!$B$7:$B$31,20,Allocation!$I$7:$I$31) -> 0 | AL26: =IFERROR($AK26/$T26,0) -> 0 | AM26: =IF($O26=0,"",IF($AL26>=0.999,"Funded",IF($AK26>0,"Partially funded","Not funded"))) | AN26: =IF(AND($O26=1,$V26>0),1/$V26,0) -> 0 | AO26: =IF($O26=1,$W26,0) -> 0 | AP26: =IF($O26=1,$F26,0) -> 0 | AQ26: =IF(AND($O26=1,$T26>0),Pipeline!$T26/$T26,0) -> 0
A27: =21 -> 21 | B27: =IF(Pipeline!$B27<>"",Pipeline!$B27,"") | C27: =SUM(Pipeline!$J27:$M27) -> 0 | D27: =IFERROR(Pipeline!$N27/$C27,0) -> 0 | E27: =IFERROR((Pipeline!$O27+Pipeline!$P27)/Pipeline!$N27,0) -> 0 | F27: =IFERROR(Pipeline!$K27/$C27,0) -> 0 | G27: =IF(NOT(Pipeline!$B27<>""),0,IF(E_MinConn_On=1,IF($C27>=E_MinConn,1,0),1)) -> 0 | H27: =IF(NOT(Pipeline!$B27<>""),0,IF(E_MaxCapexConn_On=1,IF($D27<=E_MaxCapexConn,1,0),1)) -> 0 | I27: =IF(NOT(Pipeline!$B27<>""),0,IF(E_MinRE_On=1,IF(Pipeline!$S27>=E_MinRE,1,0),1)) -> 0 | J27: =IF(NOT(Pipeline!$B27<>""),0,IF(E_MinPrivate_On=1,IF($E27>=E_MinPrivate,1,0),1)) -> 0 | K27: =IF(NOT(Pipeline!$B27<>""),0,IF(E_MinReady_On=1,IF(Pipeline!$F27>=E_MinReady,1,0),1)) -> 0 | L27: =IF(NOT(Pipeline!$B27<>""),0,IF(E_MaxTariff_On=1,IF(Pipeline!$R27<=E_MaxTariff,1,0),1)) -> 0 | M27: =IF(NOT(Pipeline!$B27<>""),0,IF(E_MinPU_On=1,IF($F27>=E_MinPU,1,0),1)) -> 0 | N27: =IF(NOT(Pipeline!$B27<>""),0,IF(E_Country_On=1,IF(IFERROR(INDEX('Fund Parameters'!$B$51:$B$58,MATCH(Pipeline!$C27,'Fund Parameters'!$A$51:$A$58,0))="Y",FALSE()),1,0),1)) -> 0 | O27: =IF(AND(Pipeline!$B27<>"",$G27*$H27*$I27*$J27*$K27*$L27*$M27*$N27=1),1,0) -> 0 | P27: =IF(NOT(Pipeline!$B27<>""),"",IF($O27=1,"Eligible",IF($G27=0,"Too few connections",IF($H27=0,"CAPEX per connection too high",IF($I27=0,"Renewable share too low",IF($J27=0,"Private co-finance too low",IF($K27=0,"Not ready enough",IF($L27=0,"Tariff above cap",IF($M27=0,"Productive use too low",IF($N27=0,"Country not eligible","")))))))))) | Q27: =Pipeline!$J27*RBF_HH+Pipeline!$K27*RBF_PU+Pipeline!$L27*RBF_COM+Pipeline!$M27*RBF_INST -> 0 | R27: =Pipeline!$N27*GrantPct -> 0 | S27: =MAX(0,MIN($Q27+$R27,MaxSupportPct*Pipeline!$N27-Pipeline!$Q27,MaxPerProject,MaxProjShare*Envelope)) -> 0 | T27: =IF($O27=1,IF(Pipeline!$V27>0,MIN(Pipeline!$V27,$S27),$S27),0) -> 0 | U27: =IFERROR($Q27/($Q27+$R27),1) -> 1 | V27: =IFERROR($T27/$C27,0) -> 0 | W27: =IFERROR((Pipeline!$O27+Pipeline!$P27)/$T27,0) -> 0 | X27: =IFERROR(Pipeline!$T27/$T27*1000,0) -> 0 | Y27: =IF($O27=0,"",IF(NOT(ISNUMBER(Pipeline!$U27)),"No viability-gap data",IF(Pipeline!$U27<=0,"No viability-gap data",IF($T27<=Pipeline!$U27*(1+VGFTol),"Within viability gap","Above viability gap")))) | Z27: =IF($O27=1,IFERROR($AN27/MAX($AN$7:$AN$31)*100,0),0) -> 0 | AA27: =IF($O27=1,IFERROR($AO27/MAX($AO$7:$AO$31)*100,0),0) -> 0 | AB27: =IF($O27=1,IFERROR($AP27/MAX($AP$7:$AP$31)*100,0),0) -> 0 | AC27: =IF($O27=1,IFERROR($AQ27/MAX($AQ$7:$AQ$31)*100,0),0) -> 0 | AD27: =IF($O27=1,Pipeline!$F27/5*100,0) -> 0 | AE27: =IF($O27=1,Pipeline!$G27/5*100,0) -> 0 | AF27: =IF($O27=1,(6-Pipeline!$H27)/5*100,0) -> 0 | AG27: =IF($O27=1,IF($Y27="Within viability gap",100,IF($Y27="Above viability gap",0,50)),0) -> 0 | AH27: =$Z27*W_Cost+$AA27*W_Lev+$AB27*W_PU+$AC27*W_CO2+$AD27*W_Ready+$AE27*W_Track+$AF27*W_Risk+$AG27*W_Add -> 0 | AI27: =IF($O27=1,$AH27+(26-$A27)/1000000,-1) -> -1 | AJ27: =IF($O27=1,COUNTIF($AI$7:$AI$31,">"&$AI27)+1,"") | AK27: =SUMIF(Allocation!$B$7:$B$31,21,Allocation!$I$7:$I$31) -> 0 | AL27: =IFERROR($AK27/$T27,0) -> 0 | AM27: =IF($O27=0,"",IF($AL27>=0.999,"Funded",IF($AK27>0,"Partially funded","Not funded"))) | AN27: =IF(AND($O27=1,$V27>0),1/$V27,0) -> 0 | AO27: =IF($O27=1,$W27,0) -> 0 | AP27: =IF($O27=1,$F27,0) -> 0 | AQ27: =IF(AND($O27=1,$T27>0),Pipeline!$T27/$T27,0) -> 0
A28: =22 -> 22 | B28: =IF(Pipeline!$B28<>"",Pipeline!$B28,"") | C28: =SUM(Pipeline!$J28:$M28) -> 0 | D28: =IFERROR(Pipeline!$N28/$C28,0) -> 0 | E28: =IFERROR((Pipeline!$O28+Pipeline!$P28)/Pipeline!$N28,0) -> 0 | F28: =IFERROR(Pipeline!$K28/$C28,0) -> 0 | G28: =IF(NOT(Pipeline!$B28<>""),0,IF(E_MinConn_On=1,IF($C28>=E_MinConn,1,0),1)) -> 0 | H28: =IF(NOT(Pipeline!$B28<>""),0,IF(E_MaxCapexConn_On=1,IF($D28<=E_MaxCapexConn,1,0),1)) -> 0 | I28: =IF(NOT(Pipeline!$B28<>""),0,IF(E_MinRE_On=1,IF(Pipeline!$S28>=E_MinRE,1,0),1)) -> 0 | J28: =IF(NOT(Pipeline!$B28<>""),0,IF(E_MinPrivate_On=1,IF($E28>=E_MinPrivate,1,0),1)) -> 0 | K28: =IF(NOT(Pipeline!$B28<>""),0,IF(E_MinReady_On=1,IF(Pipeline!$F28>=E_MinReady,1,0),1)) -> 0 | L28: =IF(NOT(Pipeline!$B28<>""),0,IF(E_MaxTariff_On=1,IF(Pipeline!$R28<=E_MaxTariff,1,0),1)) -> 0 | M28: =IF(NOT(Pipeline!$B28<>""),0,IF(E_MinPU_On=1,IF($F28>=E_MinPU,1,0),1)) -> 0 | N28: =IF(NOT(Pipeline!$B28<>""),0,IF(E_Country_On=1,IF(IFERROR(INDEX('Fund Parameters'!$B$51:$B$58,MATCH(Pipeline!$C28,'Fund Parameters'!$A$51:$A$58,0))="Y",FALSE()),1,0),1)) -> 0 | O28: =IF(AND(Pipeline!$B28<>"",$G28*$H28*$I28*$J28*$K28*$L28*$M28*$N28=1),1,0) -> 0 | P28: =IF(NOT(Pipeline!$B28<>""),"",IF($O28=1,"Eligible",IF($G28=0,"Too few connections",IF($H28=0,"CAPEX per connection too high",IF($I28=0,"Renewable share too low",IF($J28=0,"Private co-finance too low",IF($K28=0,"Not ready enough",IF($L28=0,"Tariff above cap",IF($M28=0,"Productive use too low",IF($N28=0,"Country not eligible","")))))))))) | Q28: =Pipeline!$J28*RBF_HH+Pipeline!$K28*RBF_PU+Pipeline!$L28*RBF_COM+Pipeline!$M28*RBF_INST -> 0 | R28: =Pipeline!$N28*GrantPct -> 0 | S28: =MAX(0,MIN($Q28+$R28,MaxSupportPct*Pipeline!$N28-Pipeline!$Q28,MaxPerProject,MaxProjShare*Envelope)) -> 0 | T28: =IF($O28=1,IF(Pipeline!$V28>0,MIN(Pipeline!$V28,$S28),$S28),0) -> 0 | U28: =IFERROR($Q28/($Q28+$R28),1) -> 1 | V28: =IFERROR($T28/$C28,0) -> 0 | W28: =IFERROR((Pipeline!$O28+Pipeline!$P28)/$T28,0) -> 0 | X28: =IFERROR(Pipeline!$T28/$T28*1000,0) -> 0 | Y28: =IF($O28=0,"",IF(NOT(ISNUMBER(Pipeline!$U28)),"No viability-gap data",IF(Pipeline!$U28<=0,"No viability-gap data",IF($T28<=Pipeline!$U28*(1+VGFTol),"Within viability gap","Above viability gap")))) | Z28: =IF($O28=1,IFERROR($AN28/MAX($AN$7:$AN$31)*100,0),0) -> 0 | AA28: =IF($O28=1,IFERROR($AO28/MAX($AO$7:$AO$31)*100,0),0) -> 0 | AB28: =IF($O28=1,IFERROR($AP28/MAX($AP$7:$AP$31)*100,0),0) -> 0 | AC28: =IF($O28=1,IFERROR($AQ28/MAX($AQ$7:$AQ$31)*100,0),0) -> 0 | AD28: =IF($O28=1,Pipeline!$F28/5*100,0) -> 0 | AE28: =IF($O28=1,Pipeline!$G28/5*100,0) -> 0 | AF28: =IF($O28=1,(6-Pipeline!$H28)/5*100,0) -> 0 | AG28: =IF($O28=1,IF($Y28="Within viability gap",100,IF($Y28="Above viability gap",0,50)),0) -> 0 | AH28: =$Z28*W_Cost+$AA28*W_Lev+$AB28*W_PU+$AC28*W_CO2+$AD28*W_Ready+$AE28*W_Track+$AF28*W_Risk+$AG28*W_Add -> 0 | AI28: =IF($O28=1,$AH28+(26-$A28)/1000000,-1) -> -1 | AJ28: =IF($O28=1,COUNTIF($AI$7:$AI$31,">"&$AI28)+1,"") | AK28: =SUMIF(Allocation!$B$7:$B$31,22,Allocation!$I$7:$I$31) -> 0 | AL28: =IFERROR($AK28/$T28,0) -> 0 | AM28: =IF($O28=0,"",IF($AL28>=0.999,"Funded",IF($AK28>0,"Partially funded","Not funded"))) | AN28: =IF(AND($O28=1,$V28>0),1/$V28,0) -> 0 | AO28: =IF($O28=1,$W28,0) -> 0 | AP28: =IF($O28=1,$F28,0) -> 0 | AQ28: =IF(AND($O28=1,$T28>0),Pipeline!$T28/$T28,0) -> 0
A29: =23 -> 23 | B29: =IF(Pipeline!$B29<>"",Pipeline!$B29,"") | C29: =SUM(Pipeline!$J29:$M29) -> 0 | D29: =IFERROR(Pipeline!$N29/$C29,0) -> 0 | E29: =IFERROR((Pipeline!$O29+Pipeline!$P29)/Pipeline!$N29,0) -> 0 | F29: =IFERROR(Pipeline!$K29/$C29,0) -> 0 | G29: =IF(NOT(Pipeline!$B29<>""),0,IF(E_MinConn_On=1,IF($C29>=E_MinConn,1,0),1)) -> 0 | H29: =IF(NOT(Pipeline!$B29<>""),0,IF(E_MaxCapexConn_On=1,IF($D29<=E_MaxCapexConn,1,0),1)) -> 0 | I29: =IF(NOT(Pipeline!$B29<>""),0,IF(E_MinRE_On=1,IF(Pipeline!$S29>=E_MinRE,1,0),1)) -> 0 | J29: =IF(NOT(Pipeline!$B29<>""),0,IF(E_MinPrivate_On=1,IF($E29>=E_MinPrivate,1,0),1)) -> 0 | K29: =IF(NOT(Pipeline!$B29<>""),0,IF(E_MinReady_On=1,IF(Pipeline!$F29>=E_MinReady,1,0),1)) -> 0 | L29: =IF(NOT(Pipeline!$B29<>""),0,IF(E_MaxTariff_On=1,IF(Pipeline!$R29<=E_MaxTariff,1,0),1)) -> 0 | M29: =IF(NOT(Pipeline!$B29<>""),0,IF(E_MinPU_On=1,IF($F29>=E_MinPU,1,0),1)) -> 0 | N29: =IF(NOT(Pipeline!$B29<>""),0,IF(E_Country_On=1,IF(IFERROR(INDEX('Fund Parameters'!$B$51:$B$58,MATCH(Pipeline!$C29,'Fund Parameters'!$A$51:$A$58,0))="Y",FALSE()),1,0),1)) -> 0 | O29: =IF(AND(Pipeline!$B29<>"",$G29*$H29*$I29*$J29*$K29*$L29*$M29*$N29=1),1,0) -> 0 | P29: =IF(NOT(Pipeline!$B29<>""),"",IF($O29=1,"Eligible",IF($G29=0,"Too few connections",IF($H29=0,"CAPEX per connection too high",IF($I29=0,"Renewable share too low",IF($J29=0,"Private co-finance too low",IF($K29=0,"Not ready enough",IF($L29=0,"Tariff above cap",IF($M29=0,"Productive use too low",IF($N29=0,"Country not eligible","")))))))))) | Q29: =Pipeline!$J29*RBF_HH+Pipeline!$K29*RBF_PU+Pipeline!$L29*RBF_COM+Pipeline!$M29*RBF_INST -> 0 | R29: =Pipeline!$N29*GrantPct -> 0 | S29: =MAX(0,MIN($Q29+$R29,MaxSupportPct*Pipeline!$N29-Pipeline!$Q29,MaxPerProject,MaxProjShare*Envelope)) -> 0 | T29: =IF($O29=1,IF(Pipeline!$V29>0,MIN(Pipeline!$V29,$S29),$S29),0) -> 0 | U29: =IFERROR($Q29/($Q29+$R29),1) -> 1 | V29: =IFERROR($T29/$C29,0) -> 0 | W29: =IFERROR((Pipeline!$O29+Pipeline!$P29)/$T29,0) -> 0 | X29: =IFERROR(Pipeline!$T29/$T29*1000,0) -> 0 | Y29: =IF($O29=0,"",IF(NOT(ISNUMBER(Pipeline!$U29)),"No viability-gap data",IF(Pipeline!$U29<=0,"No viability-gap data",IF($T29<=Pipeline!$U29*(1+VGFTol),"Within viability gap","Above viability gap")))) | Z29: =IF($O29=1,IFERROR($AN29/MAX($AN$7:$AN$31)*100,0),0) -> 0 | AA29: =IF($O29=1,IFERROR($AO29/MAX($AO$7:$AO$31)*100,0),0) -> 0 | AB29: =IF($O29=1,IFERROR($AP29/MAX($AP$7:$AP$31)*100,0),0) -> 0 | AC29: =IF($O29=1,IFERROR($AQ29/MAX($AQ$7:$AQ$31)*100,0),0) -> 0 | AD29: =IF($O29=1,Pipeline!$F29/5*100,0) -> 0 | AE29: =IF($O29=1,Pipeline!$G29/5*100,0) -> 0 | AF29: =IF($O29=1,(6-Pipeline!$H29)/5*100,0) -> 0 | AG29: =IF($O29=1,IF($Y29="Within viability gap",100,IF($Y29="Above viability gap",0,50)),0) -> 0 | AH29: =$Z29*W_Cost+$AA29*W_Lev+$AB29*W_PU+$AC29*W_CO2+$AD29*W_Ready+$AE29*W_Track+$AF29*W_Risk+$AG29*W_Add -> 0 | AI29: =IF($O29=1,$AH29+(26-$A29)/1000000,-1) -> -1 | AJ29: =IF($O29=1,COUNTIF($AI$7:$AI$31,">"&$AI29)+1,"") | AK29: =SUMIF(Allocation!$B$7:$B$31,23,Allocation!$I$7:$I$31) -> 0 | AL29: =IFERROR($AK29/$T29,0) -> 0 | AM29: =IF($O29=0,"",IF($AL29>=0.999,"Funded",IF($AK29>0,"Partially funded","Not funded"))) | AN29: =IF(AND($O29=1,$V29>0),1/$V29,0) -> 0 | AO29: =IF($O29=1,$W29,0) -> 0 | AP29: =IF($O29=1,$F29,0) -> 0 | AQ29: =IF(AND($O29=1,$T29>0),Pipeline!$T29/$T29,0) -> 0
A30: =24 -> 24 | B30: =IF(Pipeline!$B30<>"",Pipeline!$B30,"") | C30: =SUM(Pipeline!$J30:$M30) -> 0 | D30: =IFERROR(Pipeline!$N30/$C30,0) -> 0 | E30: =IFERROR((Pipeline!$O30+Pipeline!$P30)/Pipeline!$N30,0) -> 0 | F30: =IFERROR(Pipeline!$K30/$C30,0) -> 0 | G30: =IF(NOT(Pipeline!$B30<>""),0,IF(E_MinConn_On=1,IF($C30>=E_MinConn,1,0),1)) -> 0 | H30: =IF(NOT(Pipeline!$B30<>""),0,IF(E_MaxCapexConn_On=1,IF($D30<=E_MaxCapexConn,1,0),1)) -> 0 | I30: =IF(NOT(Pipeline!$B30<>""),0,IF(E_MinRE_On=1,IF(Pipeline!$S30>=E_MinRE,1,0),1)) -> 0 | J30: =IF(NOT(Pipeline!$B30<>""),0,IF(E_MinPrivate_On=1,IF($E30>=E_MinPrivate,1,0),1)) -> 0 | K30: =IF(NOT(Pipeline!$B30<>""),0,IF(E_MinReady_On=1,IF(Pipeline!$F30>=E_MinReady,1,0),1)) -> 0 | L30: =IF(NOT(Pipeline!$B30<>""),0,IF(E_MaxTariff_On=1,IF(Pipeline!$R30<=E_MaxTariff,1,0),1)) -> 0 | M30: =IF(NOT(Pipeline!$B30<>""),0,IF(E_MinPU_On=1,IF($F30>=E_MinPU,1,0),1)) -> 0 | N30: =IF(NOT(Pipeline!$B30<>""),0,IF(E_Country_On=1,IF(IFERROR(INDEX('Fund Parameters'!$B$51:$B$58,MATCH(Pipeline!$C30,'Fund Parameters'!$A$51:$A$58,0))="Y",FALSE()),1,0),1)) -> 0 | O30: =IF(AND(Pipeline!$B30<>"",$G30*$H30*$I30*$J30*$K30*$L30*$M30*$N30=1),1,0) -> 0 | P30: =IF(NOT(Pipeline!$B30<>""),"",IF($O30=1,"Eligible",IF($G30=0,"Too few connections",IF($H30=0,"CAPEX per connection too high",IF($I30=0,"Renewable share too low",IF($J30=0,"Private co-finance too low",IF($K30=0,"Not ready enough",IF($L30=0,"Tariff above cap",IF($M30=0,"Productive use too low",IF($N30=0,"Country not eligible","")))))))))) | Q30: =Pipeline!$J30*RBF_HH+Pipeline!$K30*RBF_PU+Pipeline!$L30*RBF_COM+Pipeline!$M30*RBF_INST -> 0 | R30: =Pipeline!$N30*GrantPct -> 0 | S30: =MAX(0,MIN($Q30+$R30,MaxSupportPct*Pipeline!$N30-Pipeline!$Q30,MaxPerProject,MaxProjShare*Envelope)) -> 0 | T30: =IF($O30=1,IF(Pipeline!$V30>0,MIN(Pipeline!$V30,$S30),$S30),0) -> 0 | U30: =IFERROR($Q30/($Q30+$R30),1) -> 1 | V30: =IFERROR($T30/$C30,0) -> 0 | W30: =IFERROR((Pipeline!$O30+Pipeline!$P30)/$T30,0) -> 0 | X30: =IFERROR(Pipeline!$T30/$T30*1000,0) -> 0 | Y30: =IF($O30=0,"",IF(NOT(ISNUMBER(Pipeline!$U30)),"No viability-gap data",IF(Pipeline!$U30<=0,"No viability-gap data",IF($T30<=Pipeline!$U30*(1+VGFTol),"Within viability gap","Above viability gap")))) | Z30: =IF($O30=1,IFERROR($AN30/MAX($AN$7:$AN$31)*100,0),0) -> 0 | AA30: =IF($O30=1,IFERROR($AO30/MAX($AO$7:$AO$31)*100,0),0) -> 0 | AB30: =IF($O30=1,IFERROR($AP30/MAX($AP$7:$AP$31)*100,0),0) -> 0 | AC30: =IF($O30=1,IFERROR($AQ30/MAX($AQ$7:$AQ$31)*100,0),0) -> 0 | AD30: =IF($O30=1,Pipeline!$F30/5*100,0) -> 0 | AE30: =IF($O30=1,Pipeline!$G30/5*100,0) -> 0 | AF30: =IF($O30=1,(6-Pipeline!$H30)/5*100,0) -> 0 | AG30: =IF($O30=1,IF($Y30="Within viability gap",100,IF($Y30="Above viability gap",0,50)),0) -> 0 | AH30: =$Z30*W_Cost+$AA30*W_Lev+$AB30*W_PU+$AC30*W_CO2+$AD30*W_Ready+$AE30*W_Track+$AF30*W_Risk+$AG30*W_Add -> 0 | AI30: =IF($O30=1,$AH30+(26-$A30)/1000000,-1) -> -1 | AJ30: =IF($O30=1,COUNTIF($AI$7:$AI$31,">"&$AI30)+1,"") | AK30: =SUMIF(Allocation!$B$7:$B$31,24,Allocation!$I$7:$I$31) -> 0 | AL30: =IFERROR($AK30/$T30,0) -> 0 | AM30: =IF($O30=0,"",IF($AL30>=0.999,"Funded",IF($AK30>0,"Partially funded","Not funded"))) | AN30: =IF(AND($O30=1,$V30>0),1/$V30,0) -> 0 | AO30: =IF($O30=1,$W30,0) -> 0 | AP30: =IF($O30=1,$F30,0) -> 0 | AQ30: =IF(AND($O30=1,$T30>0),Pipeline!$T30/$T30,0) -> 0
A31: =25 -> 25 | B31: =IF(Pipeline!$B31<>"",Pipeline!$B31,"") | C31: =SUM(Pipeline!$J31:$M31) -> 0 | D31: =IFERROR(Pipeline!$N31/$C31,0) -> 0 | E31: =IFERROR((Pipeline!$O31+Pipeline!$P31)/Pipeline!$N31,0) -> 0 | F31: =IFERROR(Pipeline!$K31/$C31,0) -> 0 | G31: =IF(NOT(Pipeline!$B31<>""),0,IF(E_MinConn_On=1,IF($C31>=E_MinConn,1,0),1)) -> 0 | H31: =IF(NOT(Pipeline!$B31<>""),0,IF(E_MaxCapexConn_On=1,IF($D31<=E_MaxCapexConn,1,0),1)) -> 0 | I31: =IF(NOT(Pipeline!$B31<>""),0,IF(E_MinRE_On=1,IF(Pipeline!$S31>=E_MinRE,1,0),1)) -> 0 | J31: =IF(NOT(Pipeline!$B31<>""),0,IF(E_MinPrivate_On=1,IF($E31>=E_MinPrivate,1,0),1)) -> 0 | K31: =IF(NOT(Pipeline!$B31<>""),0,IF(E_MinReady_On=1,IF(Pipeline!$F31>=E_MinReady,1,0),1)) -> 0 | L31: =IF(NOT(Pipeline!$B31<>""),0,IF(E_MaxTariff_On=1,IF(Pipeline!$R31<=E_MaxTariff,1,0),1)) -> 0 | M31: =IF(NOT(Pipeline!$B31<>""),0,IF(E_MinPU_On=1,IF($F31>=E_MinPU,1,0),1)) -> 0 | N31: =IF(NOT(Pipeline!$B31<>""),0,IF(E_Country_On=1,IF(IFERROR(INDEX('Fund Parameters'!$B$51:$B$58,MATCH(Pipeline!$C31,'Fund Parameters'!$A$51:$A$58,0))="Y",FALSE()),1,0),1)) -> 0 | O31: =IF(AND(Pipeline!$B31<>"",$G31*$H31*$I31*$J31*$K31*$L31*$M31*$N31=1),1,0) -> 0 | P31: =IF(NOT(Pipeline!$B31<>""),"",IF($O31=1,"Eligible",IF($G31=0,"Too few connections",IF($H31=0,"CAPEX per connection too high",IF($I31=0,"Renewable share too low",IF($J31=0,"Private co-finance too low",IF($K31=0,"Not ready enough",IF($L31=0,"Tariff above cap",IF($M31=0,"Productive use too low",IF($N31=0,"Country not eligible","")))))))))) | Q31: =Pipeline!$J31*RBF_HH+Pipeline!$K31*RBF_PU+Pipeline!$L31*RBF_COM+Pipeline!$M31*RBF_INST -> 0 | R31: =Pipeline!$N31*GrantPct -> 0 | S31: =MAX(0,MIN($Q31+$R31,MaxSupportPct*Pipeline!$N31-Pipeline!$Q31,MaxPerProject,MaxProjShare*Envelope)) -> 0 | T31: =IF($O31=1,IF(Pipeline!$V31>0,MIN(Pipeline!$V31,$S31),$S31),0) -> 0 | U31: =IFERROR($Q31/($Q31+$R31),1) -> 1 | V31: =IFERROR($T31/$C31,0) -> 0 | W31: =IFERROR((Pipeline!$O31+Pipeline!$P31)/$T31,0) -> 0 | X31: =IFERROR(Pipeline!$T31/$T31*1000,0) -> 0 | Y31: =IF($O31=0,"",IF(NOT(ISNUMBER(Pipeline!$U31)),"No viability-gap data",IF(Pipeline!$U31<=0,"No viability-gap data",IF($T31<=Pipeline!$U31*(1+VGFTol),"Within viability gap","Above viability gap")))) | Z31: =IF($O31=1,IFERROR($AN31/MAX($AN$7:$AN$31)*100,0),0) -> 0 | AA31: =IF($O31=1,IFERROR($AO31/MAX($AO$7:$AO$31)*100,0),0) -> 0 | AB31: =IF($O31=1,IFERROR($AP31/MAX($AP$7:$AP$31)*100,0),0) -> 0 | AC31: =IF($O31=1,IFERROR($AQ31/MAX($AQ$7:$AQ$31)*100,0),0) -> 0 | AD31: =IF($O31=1,Pipeline!$F31/5*100,0) -> 0 | AE31: =IF($O31=1,Pipeline!$G31/5*100,0) -> 0 | AF31: =IF($O31=1,(6-Pipeline!$H31)/5*100,0) -> 0 | AG31: =IF($O31=1,IF($Y31="Within viability gap",100,IF($Y31="Above viability gap",0,50)),0) -> 0 | AH31: =$Z31*W_Cost+$AA31*W_Lev+$AB31*W_PU+$AC31*W_CO2+$AD31*W_Ready+$AE31*W_Track+$AF31*W_Risk+$AG31*W_Add -> 0 | AI31: =IF($O31=1,$AH31+(26-$A31)/1000000,-1) -> -1 | AJ31: =IF($O31=1,COUNTIF($AI$7:$AI$31,">"&$AI31)+1,"") | AK31: =SUMIF(Allocation!$B$7:$B$31,25,Allocation!$I$7:$I$31) -> 0 | AL31: =IFERROR($AK31/$T31,0) -> 0 | AM31: =IF($O31=0,"",IF($AL31>=0.999,"Funded",IF($AK31>0,"Partially funded","Not funded"))) | AN31: =IF(AND($O31=1,$V31>0),1/$V31,0) -> 0 | AO31: =IF($O31=1,$W31,0) -> 0 | AP31: =IF($O31=1,$F31,0) -> 0 | AQ31: =IF(AND($O31=1,$T31>0),Pipeline!$T31/$T31,0) -> 0

Sheet Allocation
A1: ALLOCATION (in rank order)
A2: ="Envelope: "&Currency&" "&FIXED(Envelope,0)&" | Partial funding: "&IF(AllowPartial=1,"allowed","not allowed")&" | Max per country: "&FIXED((MaxCountryShare)*100,0)&"%"&" of envelope" -> Envelope: USD 2,550,000 | Partial funding: allowed | Max per country: 50% of envelope
A3: Each row only looks at the rows above it: the envelope and country limits are applied in rank order, without circular references.
A6: Rank | B6: # | C6: Project | D6: Country | E6: Score | F6: Request | G6: Envelope remaining before | H6: Country room remaining | I6: ALLOCATED | J6: Status | K6: Binding constraint
A7: =1 -> 1 | B7: =IFERROR(MATCH(1,'Eligibility & Scoring'!$AJ$7:$AJ$31,0),"") -> 3 | C7: =IF(B7="","",INDEX('Eligibility & Scoring'!$B$7:$B$31,B7)) -> Project C - Northern corridor | D7: =IF(B7="","",INDEX(Pipeline!$C$7:$C$31,B7)) -> Country B | E7: =IF(B7="",0,INDEX('Eligibility & Scoring'!$AH$7:$AH$31,B7)) -> 91.571095 | F7: =IF(B7="",0,INDEX('Eligibility & Scoring'!$T$7:$T$31,B7)) -> 382500 | G7: =IF(B7="","",Envelope) -> 2550000 | H7: =IF(B7="","",MaxCountryShare*Envelope) -> 1275000 | I7: =IF(B7="",0,IF(AllowPartial=1,MAX(0,MIN(F7,G7,H7)),IF(F7<=MIN(G7,H7),F7,0))) -> 382500 | J7: =IF(B7="","",IF(I7>=F7-0.5,"Funded",IF(I7>0,"Partially funded","Not funded"))) -> Funded | K7: =IF(OR(B7="",I7>=F7-0.5),"",IF(H7<G7,"Country limit","Envelope exhausted"))
A8: =2 -> 2 | B8: =IFERROR(MATCH(2,'Eligibility & Scoring'!$AJ$7:$AJ$31,0),"") -> 11 | C8: =IF(B8="","",INDEX('Eligibility & Scoring'!$B$7:$B$31,B8)) -> Project K - Peri-urban extension | D8: =IF(B8="","",INDEX(Pipeline!$C$7:$C$31,B8)) -> Country B | E8: =IF(B8="",0,INDEX('Eligibility & Scoring'!$AH$7:$AH$31,B8)) -> 77.747597 | F8: =IF(B8="",0,INDEX('Eligibility & Scoring'!$T$7:$T$31,B8)) -> 382500 | G8: =IF(B8="","",Envelope-SUM($I$7:I7)) -> 2167500 | H8: =IF(B8="","",MaxCountryShare*Envelope-SUMIF($D$7:D7,D8,$I$7:I7)) -> 892500 | I8: =IF(B8="",0,IF(AllowPartial=1,MAX(0,MIN(F8,G8,H8)),IF(F8<=MIN(G8,H8),F8,0))) -> 382500 | J8: =IF(B8="","",IF(I8>=F8-0.5,"Funded",IF(I8>0,"Partially funded","Not funded"))) -> Funded | K8: =IF(OR(B8="",I8>=F8-0.5),"",IF(H8<G8,"Country limit","Envelope exhausted"))
A9: =3 -> 3 | B9: =IFERROR(MATCH(3,'Eligibility & Scoring'!$AJ$7:$AJ$31,0),"") -> 12 | C9: =IF(B9="","",INDEX('Eligibility & Scoring'!$B$7:$B$31,B9)) -> Project L - Mining belt | D9: =IF(B9="","",INDEX(Pipeline!$C$7:$C$31,B9)) -> Country D | E9: =IF(B9="",0,INDEX('Eligibility & Scoring'!$AH$7:$AH$31,B9)) -> 75.528679 | F9: =IF(B9="",0,INDEX('Eligibility & Scoring'!$T$7:$T$31,B9)) -> 382500 | G9: =IF(B9="","",Envelope-SUM($I$7:I8)) -> 1785000 | H9: =IF(B9="","",MaxCountryShare*Envelope-SUMIF($D$7:D8,D9,$I$7:I8)) -> 1275000 | I9: =IF(B9="",0,IF(AllowPartial=1,MAX(0,MIN(F9,G9,H9)),IF(F9<=MIN(G9,H9),F9,0))) -> 382500 | J9: =IF(B9="","",IF(I9>=F9-0.5,"Funded",IF(I9>0,"Partially funded","Not funded"))) -> Funded | K9: =IF(OR(B9="",I9>=F9-0.5),"",IF(H9<G9,"Country limit","Envelope exhausted"))
A10: =4 -> 4 | B10: =IFERROR(MATCH(4,'Eligibility & Scoring'!$AJ$7:$AJ$31,0),"") -> 8 | C10: =IF(B10="","",INDEX('Eligibility & Scoring'!$B$7:$B$31,B10)) -> Project H - Agro-processing hub | D10: =IF(B10="","",INDEX(Pipeline!$C$7:$C$31,B10)) -> Country B | E10: =IF(B10="",0,INDEX('Eligibility & Scoring'!$AH$7:$AH$31,B10)) -> 70.193796 | F10: =IF(B10="",0,INDEX('Eligibility & Scoring'!$T$7:$T$31,B10)) -> 382500 | G10: =IF(B10="","",Envelope-SUM($I$7:I9)) -> 1402500 | H10: =IF(B10="","",MaxCountryShare*Envelope-SUMIF($D$7:D9,D10,$I$7:I9)) -> 510000 | I10: =IF(B10="",0,IF(AllowPartial=1,MAX(0,MIN(F10,G10,H10)),IF(F10<=MIN(G10,H10),F10,0))) -> 382500 | J10: =IF(B10="","",IF(I10>=F10-0.5,"Funded",IF(I10>0,"Partially funded","Not funded"))) -> Funded | K10: =IF(OR(B10="",I10>=F10-0.5),"",IF(H10<G10,"Country limit","Envelope exhausted"))
A11: =5 -> 5 | B11: =IFERROR(MATCH(5,'Eligibility & Scoring'!$AJ$7:$AJ$31,0),"") -> 1 | C11: =IF(B11="","",INDEX('Eligibility & Scoring'!$B$7:$B$31,B11)) -> Project A - Lake village cluster | D11: =IF(B11="","",INDEX(Pipeline!$C$7:$C$31,B11)) -> Country A | E11: =IF(B11="",0,INDEX('Eligibility & Scoring'!$AH$7:$AH$31,B11)) -> 65.050244 | F11: =IF(B11="",0,INDEX('Eligibility & Scoring'!$T$7:$T$31,B11)) -> 382500 | G11: =IF(B11="","",Envelope-SUM($I$7:I10)) -> 1020000 | H11: =IF(B11="","",MaxCountryShare*Envelope-SUMIF($D$7:D10,D11,$I$7:I10)) -> 1275000 | I11: =IF(B11="",0,IF(AllowPartial=1,MAX(0,MIN(F11,G11,H11)),IF(F11<=MIN(G11,H11),F11,0))) -> 382500 | J11: =IF(B11="","",IF(I11>=F11-0.5,"Funded",IF(I11>0,"Partially funded","Not funded"))) -> Funded | K11: =IF(OR(B11="",I11>=F11-0.5),"",IF(H11<G11,"Country limit","Envelope exhausted"))
A12: =6 -> 6 | B12: =IFERROR(MATCH(6,'Eligibility & Scoring'!$AJ$7:$AJ$31,0),"") -> 14 | C12: =IF(B12="","",INDEX('Eligibility & Scoring'!$B$7:$B$31,B12)) -> Project N - Lakeside expansion | D12: =IF(B12="","",INDEX(Pipeline!$C$7:$C$31,B12)) -> Country B | E12: =IF(B12="",0,INDEX('Eligibility & Scoring'!$AH$7:$AH$31,B12)) -> 63.797502 | F12: =IF(B12="",0,INDEX('Eligibility & Scoring'!$T$7:$T$31,B12)) -> 382500 | G12: =IF(B12="","",Envelope-SUM($I$7:I11)) -> 637500 | H12: =IF(B12="","",MaxCountryShare*Envelope-SUMIF($D$7:D11,D12,$I$7:I11)) -> 127500 | I12: =IF(B12="",0,IF(AllowPartial=1,MAX(0,MIN(F12,G12,H12)),IF(F12<=MIN(G12,H12),F12,0))) -> 127500 | J12: =IF(B12="","",IF(I12>=F12-0.5,"Funded",IF(I12>0,"Partially funded","Not funded"))) -> Partially funded | K12: =IF(OR(B12="",I12>=F12-0.5),"",IF(H12<G12,"Country limit","Envelope exhausted")) -> Country limit
A13: =7 -> 7 | B13: =IFERROR(MATCH(7,'Eligibility & Scoring'!$AJ$7:$AJ$31,0),"") -> 9 | C13: =IF(B13="","",INDEX('Eligibility & Scoring'!$B$7:$B$31,B13)) -> Project I - Fishing communities | D13: =IF(B13="","",INDEX(Pipeline!$C$7:$C$31,B13)) -> Country D | E13: =IF(B13="",0,INDEX('Eligibility & Scoring'!$AH$7:$AH$31,B13)) -> 52.95648 | F13: =IF(B13="",0,INDEX('Eligibility & Scoring'!$T$7:$T$31,B13)) -> 382500 | G13: =IF(B13="","",Envelope-SUM($I$7:I12)) -> 510000 | H13: =IF(B13="","",MaxCountryShare*Envelope-SUMIF($D$7:D12,D13,$I$7:I12)) -> 892500 | I13: =IF(B13="",0,IF(AllowPartial=1,MAX(0,MIN(F13,G13,H13)),IF(F13<=MIN(G13,H13),F13,0))) -> 382500 | J13: =IF(B13="","",IF(I13>=F13-0.5,"Funded",IF(I13>0,"Partially funded","Not funded"))) -> Funded | K13: =IF(OR(B13="",I13>=F13-0.5),"",IF(H13<G13,"Country limit","Envelope exhausted"))
A14: =8 -> 8 | B14: =IFERROR(MATCH(8,'Eligibility & Scoring'!$AJ$7:$AJ$31,0),"") -> 2 | C14: =IF(B14="","",INDEX('Eligibility & Scoring'!$B$7:$B$31,B14)) -> Project B - River towns | D14: =IF(B14="","",INDEX(Pipeline!$C$7:$C$31,B14)) -> Country A | E14: =IF(B14="",0,INDEX('Eligibility & Scoring'!$AH$7:$AH$31,B14)) -> 51.937823 | F14: =IF(B14="",0,INDEX('Eligibility & Scoring'!$T$7:$T$31,B14)) -> 320000 | G14: =IF(B14="","",Envelope-SUM($I$7:I13)) -> 127500 | H14: =IF(B14="","",MaxCountryShare*Envelope-SUMIF($D$7:D13,D14,$I$7:I13)) -> 892500 | I14: =IF(B14="",0,IF(AllowPartial=1,MAX(0,MIN(F14,G14,H14)),IF(F14<=MIN(G14,H14),F14,0))) -> 127500 | J14: =IF(B14="","",IF(I14>=F14-0.5,"Funded",IF(I14>0,"Partially funded","Not funded"))) -> Partially funded | K14: =IF(OR(B14="",I14>=F14-0.5),"",IF(H14<G14,"Country limit","Envelope exhausted")) -> Envelope exhausted
A15: =9 -> 9 | B15: =IFERROR(MATCH(9,'Eligibility & Scoring'!$AJ$7:$AJ$31,0),"") | C15: =IF(B15="","",INDEX('Eligibility & Scoring'!$B$7:$B$31,B15)) | D15: =IF(B15="","",INDEX(Pipeline!$C$7:$C$31,B15)) | E15: =IF(B15="",0,INDEX('Eligibility & Scoring'!$AH$7:$AH$31,B15)) -> 0 | F15: =IF(B15="",0,INDEX('Eligibility & Scoring'!$T$7:$T$31,B15)) -> 0 | G15: =IF(B15="","",Envelope-SUM($I$7:I14)) | H15: =IF(B15="","",MaxCountryShare*Envelope-SUMIF($D$7:D14,D15,$I$7:I14)) | I15: =IF(B15="",0,IF(AllowPartial=1,MAX(0,MIN(F15,G15,H15)),IF(F15<=MIN(G15,H15),F15,0))) -> 0 | J15: =IF(B15="","",IF(I15>=F15-0.5,"Funded",IF(I15>0,"Partially funded","Not funded"))) | K15: =IF(OR(B15="",I15>=F15-0.5),"",IF(H15<G15,"Country limit","Envelope exhausted"))
A16: =10 -> 10 | B16: =IFERROR(MATCH(10,'Eligibility & Scoring'!$AJ$7:$AJ$31,0),"") | C16: =IF(B16="","",INDEX('Eligibility & Scoring'!$B$7:$B$31,B16)) | D16: =IF(B16="","",INDEX(Pipeline!$C$7:$C$31,B16)) | E16: =IF(B16="",0,INDEX('Eligibility & Scoring'!$AH$7:$AH$31,B16)) -> 0 | F16: =IF(B16="",0,INDEX('Eligibility & Scoring'!$T$7:$T$31,B16)) -> 0 | G16: =IF(B16="","",Envelope-SUM($I$7:I15)) | H16: =IF(B16="","",MaxCountryShare*Envelope-SUMIF($D$7:D15,D16,$I$7:I15)) | I16: =IF(B16="",0,IF(AllowPartial=1,MAX(0,MIN(F16,G16,H16)),IF(F16<=MIN(G16,H16),F16,0))) -> 0 | J16: =IF(B16="","",IF(I16>=F16-0.5,"Funded",IF(I16>0,"Partially funded","Not funded"))) | K16: =IF(OR(B16="",I16>=F16-0.5),"",IF(H16<G16,"Country limit","Envelope exhausted"))
A17: =11 -> 11 | B17: =IFERROR(MATCH(11,'Eligibility & Scoring'!$AJ$7:$AJ$31,0),"") | C17: =IF(B17="","",INDEX('Eligibility & Scoring'!$B$7:$B$31,B17)) | D17: =IF(B17="","",INDEX(Pipeline!$C$7:$C$31,B17)) | E17: =IF(B17="",0,INDEX('Eligibility & Scoring'!$AH$7:$AH$31,B17)) -> 0 | F17: =IF(B17="",0,INDEX('Eligibility & Scoring'!$T$7:$T$31,B17)) -> 0 | G17: =IF(B17="","",Envelope-SUM($I$7:I16)) | H17: =IF(B17="","",MaxCountryShare*Envelope-SUMIF($D$7:D16,D17,$I$7:I16)) | I17: =IF(B17="",0,IF(AllowPartial=1,MAX(0,MIN(F17,G17,H17)),IF(F17<=MIN(G17,H17),F17,0))) -> 0 | J17: =IF(B17="","",IF(I17>=F17-0.5,"Funded",IF(I17>0,"Partially funded","Not funded"))) | K17: =IF(OR(B17="",I17>=F17-0.5),"",IF(H17<G17,"Country limit","Envelope exhausted"))
A18: =12 -> 12 | B18: =IFERROR(MATCH(12,'Eligibility & Scoring'!$AJ$7:$AJ$31,0),"") | C18: =IF(B18="","",INDEX('Eligibility & Scoring'!$B$7:$B$31,B18)) | D18: =IF(B18="","",INDEX(Pipeline!$C$7:$C$31,B18)) | E18: =IF(B18="",0,INDEX('Eligibility & Scoring'!$AH$7:$AH$31,B18)) -> 0 | F18: =IF(B18="",0,INDEX('Eligibility & Scoring'!$T$7:$T$31,B18)) -> 0 | G18: =IF(B18="","",Envelope-SUM($I$7:I17)) | H18: =IF(B18="","",MaxCountryShare*Envelope-SUMIF($D$7:D17,D18,$I$7:I17)) | I18: =IF(B18="",0,IF(AllowPartial=1,MAX(0,MIN(F18,G18,H18)),IF(F18<=MIN(G18,H18),F18,0))) -> 0 | J18: =IF(B18="","",IF(I18>=F18-0.5,"Funded",IF(I18>0,"Partially funded","Not funded"))) | K18: =IF(OR(B18="",I18>=F18-0.5),"",IF(H18<G18,"Country limit","Envelope exhausted"))
A19: =13 -> 13 | B19: =IFERROR(MATCH(13,'Eligibility & Scoring'!$AJ$7:$AJ$31,0),"") | C19: =IF(B19="","",INDEX('Eligibility & Scoring'!$B$7:$B$31,B19)) | D19: =IF(B19="","",INDEX(Pipeline!$C$7:$C$31,B19)) | E19: =IF(B19="",0,INDEX('Eligibility & Scoring'!$AH$7:$AH$31,B19)) -> 0 | F19: =IF(B19="",0,INDEX('Eligibility & Scoring'!$T$7:$T$31,B19)) -> 0 | G19: =IF(B19="","",Envelope-SUM($I$7:I18)) | H19: =IF(B19="","",MaxCountryShare*Envelope-SUMIF($D$7:D18,D19,$I$7:I18)) | I19: =IF(B19="",0,IF(AllowPartial=1,MAX(0,MIN(F19,G19,H19)),IF(F19<=MIN(G19,H19),F19,0))) -> 0 | J19: =IF(B19="","",IF(I19>=F19-0.5,"Funded",IF(I19>0,"Partially funded","Not funded"))) | K19: =IF(OR(B19="",I19>=F19-0.5),"",IF(H19<G19,"Country limit","Envelope exhausted"))
A20: =14 -> 14 | B20: =IFERROR(MATCH(14,'Eligibility & Scoring'!$AJ$7:$AJ$31,0),"") | C20: =IF(B20="","",INDEX('Eligibility & Scoring'!$B$7:$B$31,B20)) | D20: =IF(B20="","",INDEX(Pipeline!$C$7:$C$31,B20)) | E20: =IF(B20="",0,INDEX('Eligibility & Scoring'!$AH$7:$AH$31,B20)) -> 0 | F20: =IF(B20="",0,INDEX('Eligibility & Scoring'!$T$7:$T$31,B20)) -> 0 | G20: =IF(B20="","",Envelope-SUM($I$7:I19)) | H20: =IF(B20="","",MaxCountryShare*Envelope-SUMIF($D$7:D19,D20,$I$7:I19)) | I20: =IF(B20="",0,IF(AllowPartial=1,MAX(0,MIN(F20,G20,H20)),IF(F20<=MIN(G20,H20),F20,0))) -> 0 | J20: =IF(B20="","",IF(I20>=F20-0.5,"Funded",IF(I20>0,"Partially funded","Not funded"))) | K20: =IF(OR(B20="",I20>=F20-0.5),"",IF(H20<G20,"Country limit","Envelope exhausted"))
A21: =15 -> 15 | B21: =IFERROR(MATCH(15,'Eligibility & Scoring'!$AJ$7:$AJ$31,0),"") | C21: =IF(B21="","",INDEX('Eligibility & Scoring'!$B$7:$B$31,B21)) | D21: =IF(B21="","",INDEX(Pipeline!$C$7:$C$31,B21)) | E21: =IF(B21="",0,INDEX('Eligibility & Scoring'!$AH$7:$AH$31,B21)) -> 0 | F21: =IF(B21="",0,INDEX('Eligibility & Scoring'!$T$7:$T$31,B21)) -> 0 | G21: =IF(B21="","",Envelope-SUM($I$7:I20)) | H21: =IF(B21="","",MaxCountryShare*Envelope-SUMIF($D$7:D20,D21,$I$7:I20)) | I21: =IF(B21="",0,IF(AllowPartial=1,MAX(0,MIN(F21,G21,H21)),IF(F21<=MIN(G21,H21),F21,0))) -> 0 | J21: =IF(B21="","",IF(I21>=F21-0.5,"Funded",IF(I21>0,"Partially funded","Not funded"))) | K21: =IF(OR(B21="",I21>=F21-0.5),"",IF(H21<G21,"Country limit","Envelope exhausted"))
A22: =16 -> 16 | B22: =IFERROR(MATCH(16,'Eligibility & Scoring'!$AJ$7:$AJ$31,0),"") | C22: =IF(B22="","",INDEX('Eligibility & Scoring'!$B$7:$B$31,B22)) | D22: =IF(B22="","",INDEX(Pipeline!$C$7:$C$31,B22)) | E22: =IF(B22="",0,INDEX('Eligibility & Scoring'!$AH$7:$AH$31,B22)) -> 0 | F22: =IF(B22="",0,INDEX('Eligibility & Scoring'!$T$7:$T$31,B22)) -> 0 | G22: =IF(B22="","",Envelope-SUM($I$7:I21)) | H22: =IF(B22="","",MaxCountryShare*Envelope-SUMIF($D$7:D21,D22,$I$7:I21)) | I22: =IF(B22="",0,IF(AllowPartial=1,MAX(0,MIN(F22,G22,H22)),IF(F22<=MIN(G22,H22),F22,0))) -> 0 | J22: =IF(B22="","",IF(I22>=F22-0.5,"Funded",IF(I22>0,"Partially funded","Not funded"))) | K22: =IF(OR(B22="",I22>=F22-0.5),"",IF(H22<G22,"Country limit","Envelope exhausted"))
A23: =17 -> 17 | B23: =IFERROR(MATCH(17,'Eligibility & Scoring'!$AJ$7:$AJ$31,0),"") | C23: =IF(B23="","",INDEX('Eligibility & Scoring'!$B$7:$B$31,B23)) | D23: =IF(B23="","",INDEX(Pipeline!$C$7:$C$31,B23)) | E23: =IF(B23="",0,INDEX('Eligibility & Scoring'!$AH$7:$AH$31,B23)) -> 0 | F23: =IF(B23="",0,INDEX('Eligibility & Scoring'!$T$7:$T$31,B23)) -> 0 | G23: =IF(B23="","",Envelope-SUM($I$7:I22)) | H23: =IF(B23="","",MaxCountryShare*Envelope-SUMIF($D$7:D22,D23,$I$7:I22)) | I23: =IF(B23="",0,IF(AllowPartial=1,MAX(0,MIN(F23,G23,H23)),IF(F23<=MIN(G23,H23),F23,0))) -> 0 | J23: =IF(B23="","",IF(I23>=F23-0.5,"Funded",IF(I23>0,"Partially funded","Not funded"))) | K23: =IF(OR(B23="",I23>=F23-0.5),"",IF(H23<G23,"Country limit","Envelope exhausted"))
A24: =18 -> 18 | B24: =IFERROR(MATCH(18,'Eligibility & Scoring'!$AJ$7:$AJ$31,0),"") | C24: =IF(B24="","",INDEX('Eligibility & Scoring'!$B$7:$B$31,B24)) | D24: =IF(B24="","",INDEX(Pipeline!$C$7:$C$31,B24)) | E24: =IF(B24="",0,INDEX('Eligibility & Scoring'!$AH$7:$AH$31,B24)) -> 0 | F24: =IF(B24="",0,INDEX('Eligibility & Scoring'!$T$7:$T$31,B24)) -> 0 | G24: =IF(B24="","",Envelope-SUM($I$7:I23)) | H24: =IF(B24="","",MaxCountryShare*Envelope-SUMIF($D$7:D23,D24,$I$7:I23)) | I24: =IF(B24="",0,IF(AllowPartial=1,MAX(0,MIN(F24,G24,H24)),IF(F24<=MIN(G24,H24),F24,0))) -> 0 | J24: =IF(B24="","",IF(I24>=F24-0.5,"Funded",IF(I24>0,"Partially funded","Not funded"))) | K24: =IF(OR(B24="",I24>=F24-0.5),"",IF(H24<G24,"Country limit","Envelope exhausted"))
A25: =19 -> 19 | B25: =IFERROR(MATCH(19,'Eligibility & Scoring'!$AJ$7:$AJ$31,0),"") | C25: =IF(B25="","",INDEX('Eligibility & Scoring'!$B$7:$B$31,B25)) | D25: =IF(B25="","",INDEX(Pipeline!$C$7:$C$31,B25)) | E25: =IF(B25="",0,INDEX('Eligibility & Scoring'!$AH$7:$AH$31,B25)) -> 0 | F25: =IF(B25="",0,INDEX('Eligibility & Scoring'!$T$7:$T$31,B25)) -> 0 | G25: =IF(B25="","",Envelope-SUM($I$7:I24)) | H25: =IF(B25="","",MaxCountryShare*Envelope-SUMIF($D$7:D24,D25,$I$7:I24)) | I25: =IF(B25="",0,IF(AllowPartial=1,MAX(0,MIN(F25,G25,H25)),IF(F25<=MIN(G25,H25),F25,0))) -> 0 | J25: =IF(B25="","",IF(I25>=F25-0.5,"Funded",IF(I25>0,"Partially funded","Not funded"))) | K25: =IF(OR(B25="",I25>=F25-0.5),"",IF(H25<G25,"Country limit","Envelope exhausted"))
A26: =20 -> 20 | B26: =IFERROR(MATCH(20,'Eligibility & Scoring'!$AJ$7:$AJ$31,0),"") | C26: =IF(B26="","",INDEX('Eligibility & Scoring'!$B$7:$B$31,B26)) | D26: =IF(B26="","",INDEX(Pipeline!$C$7:$C$31,B26)) | E26: =IF(B26="",0,INDEX('Eligibility & Scoring'!$AH$7:$AH$31,B26)) -> 0 | F26: =IF(B26="",0,INDEX('Eligibility & Scoring'!$T$7:$T$31,B26)) -> 0 | G26: =IF(B26="","",Envelope-SUM($I$7:I25)) | H26: =IF(B26="","",MaxCountryShare*Envelope-SUMIF($D$7:D25,D26,$I$7:I25)) | I26: =IF(B26="",0,IF(AllowPartial=1,MAX(0,MIN(F26,G26,H26)),IF(F26<=MIN(G26,H26),F26,0))) -> 0 | J26: =IF(B26="","",IF(I26>=F26-0.5,"Funded",IF(I26>0,"Partially funded","Not funded"))) | K26: =IF(OR(B26="",I26>=F26-0.5),"",IF(H26<G26,"Country limit","Envelope exhausted"))
A27: =21 -> 21 | B27: =IFERROR(MATCH(21,'Eligibility & Scoring'!$AJ$7:$AJ$31,0),"") | C27: =IF(B27="","",INDEX('Eligibility & Scoring'!$B$7:$B$31,B27)) | D27: =IF(B27="","",INDEX(Pipeline!$C$7:$C$31,B27)) | E27: =IF(B27="",0,INDEX('Eligibility & Scoring'!$AH$7:$AH$31,B27)) -> 0 | F27: =IF(B27="",0,INDEX('Eligibility & Scoring'!$T$7:$T$31,B27)) -> 0 | G27: =IF(B27="","",Envelope-SUM($I$7:I26)) | H27: =IF(B27="","",MaxCountryShare*Envelope-SUMIF($D$7:D26,D27,$I$7:I26)) | I27: =IF(B27="",0,IF(AllowPartial=1,MAX(0,MIN(F27,G27,H27)),IF(F27<=MIN(G27,H27),F27,0))) -> 0 | J27: =IF(B27="","",IF(I27>=F27-0.5,"Funded",IF(I27>0,"Partially funded","Not funded"))) | K27: =IF(OR(B27="",I27>=F27-0.5),"",IF(H27<G27,"Country limit","Envelope exhausted"))
A28: =22 -> 22 | B28: =IFERROR(MATCH(22,'Eligibility & Scoring'!$AJ$7:$AJ$31,0),"") | C28: =IF(B28="","",INDEX('Eligibility & Scoring'!$B$7:$B$31,B28)) | D28: =IF(B28="","",INDEX(Pipeline!$C$7:$C$31,B28)) | E28: =IF(B28="",0,INDEX('Eligibility & Scoring'!$AH$7:$AH$31,B28)) -> 0 | F28: =IF(B28="",0,INDEX('Eligibility & Scoring'!$T$7:$T$31,B28)) -> 0 | G28: =IF(B28="","",Envelope-SUM($I$7:I27)) | H28: =IF(B28="","",MaxCountryShare*Envelope-SUMIF($D$7:D27,D28,$I$7:I27)) | I28: =IF(B28="",0,IF(AllowPartial=1,MAX(0,MIN(F28,G28,H28)),IF(F28<=MIN(G28,H28),F28,0))) -> 0 | J28: =IF(B28="","",IF(I28>=F28-0.5,"Funded",IF(I28>0,"Partially funded","Not funded"))) | K28: =IF(OR(B28="",I28>=F28-0.5),"",IF(H28<G28,"Country limit","Envelope exhausted"))
A29: =23 -> 23 | B29: =IFERROR(MATCH(23,'Eligibility & Scoring'!$AJ$7:$AJ$31,0),"") | C29: =IF(B29="","",INDEX('Eligibility & Scoring'!$B$7:$B$31,B29)) | D29: =IF(B29="","",INDEX(Pipeline!$C$7:$C$31,B29)) | E29: =IF(B29="",0,INDEX('Eligibility & Scoring'!$AH$7:$AH$31,B29)) -> 0 | F29: =IF(B29="",0,INDEX('Eligibility & Scoring'!$T$7:$T$31,B29)) -> 0 | G29: =IF(B29="","",Envelope-SUM($I$7:I28)) | H29: =IF(B29="","",MaxCountryShare*Envelope-SUMIF($D$7:D28,D29,$I$7:I28)) | I29: =IF(B29="",0,IF(AllowPartial=1,MAX(0,MIN(F29,G29,H29)),IF(F29<=MIN(G29,H29),F29,0))) -> 0 | J29: =IF(B29="","",IF(I29>=F29-0.5,"Funded",IF(I29>0,"Partially funded","Not funded"))) | K29: =IF(OR(B29="",I29>=F29-0.5),"",IF(H29<G29,"Country limit","Envelope exhausted"))
A30: =24 -> 24 | B30: =IFERROR(MATCH(24,'Eligibility & Scoring'!$AJ$7:$AJ$31,0),"") | C30: =IF(B30="","",INDEX('Eligibility & Scoring'!$B$7:$B$31,B30)) | D30: =IF(B30="","",INDEX(Pipeline!$C$7:$C$31,B30)) | E30: =IF(B30="",0,INDEX('Eligibility & Scoring'!$AH$7:$AH$31,B30)) -> 0 | F30: =IF(B30="",0,INDEX('Eligibility & Scoring'!$T$7:$T$31,B30)) -> 0 | G30: =IF(B30="","",Envelope-SUM($I$7:I29)) | H30: =IF(B30="","",MaxCountryShare*Envelope-SUMIF($D$7:D29,D30,$I$7:I29)) | I30: =IF(B30="",0,IF(AllowPartial=1,MAX(0,MIN(F30,G30,H30)),IF(F30<=MIN(G30,H30),F30,0))) -> 0 | J30: =IF(B30="","",IF(I30>=F30-0.5,"Funded",IF(I30>0,"Partially funded","Not funded"))) | K30: =IF(OR(B30="",I30>=F30-0.5),"",IF(H30<G30,"Country limit","Envelope exhausted"))
A31: =25 -> 25 | B31: =IFERROR(MATCH(25,'Eligibility & Scoring'!$AJ$7:$AJ$31,0),"") | C31: =IF(B31="","",INDEX('Eligibility & Scoring'!$B$7:$B$31,B31)) | D31: =IF(B31="","",INDEX(Pipeline!$C$7:$C$31,B31)) | E31: =IF(B31="",0,INDEX('Eligibility & Scoring'!$AH$7:$AH$31,B31)) -> 0 | F31: =IF(B31="",0,INDEX('Eligibility & Scoring'!$T$7:$T$31,B31)) -> 0 | G31: =IF(B31="","",Envelope-SUM($I$7:I30)) | H31: =IF(B31="","",MaxCountryShare*Envelope-SUMIF($D$7:D30,D31,$I$7:I30)) | I31: =IF(B31="",0,IF(AllowPartial=1,MAX(0,MIN(F31,G31,H31)),IF(F31<=MIN(G31,H31),F31,0))) -> 0 | J31: =IF(B31="","",IF(I31>=F31-0.5,"Funded",IF(I31>0,"Partially funded","Not funded"))) | K31: =IF(OR(B31="",I31>=F31-0.5),"",IF(H31<G31,"Country limit","Envelope exhausted"))
C32: TOTAL | F32: =SUM(F7:F31) -> 2997500 | I32: =SUM(I7:I31) -> 2550000

Sheet Disbursements
A1: DISBURSEMENTS (expected, by fund year)
A2: Grant: paid at commissioning. RBF: paid as connections are verified (tranche at verification, balance one year later), scaled by expected delivery.
A4: RBF DISBURSEMENTS
A5: # | B5: Project | C5: Allocated RBF | D5: Allocated grant | E5: Expected delivery | F5: Expected total | G5: =FundStart-1+1 -> 2027 | H5: =FundStart-1+2 -> 2028 | I5: =FundStart-1+3 -> 2029 | J5: =FundStart-1+4 -> 2030 | K5: =FundStart-1+5 -> 2031 | L5: =FundStart-1+6 -> 2032 | M5: =FundStart-1+7 -> 2033 | N5: =FundStart-1+8 -> 2034 | O5: =FundStart-1+9 -> 2035 | P5: =FundStart-1+10 -> 2036 | Q5: Total
A6: 1 | B6: ='Eligibility & Scoring'!$B7 -> Project A - Lake village cluster | C6: ='Eligibility & Scoring'!$AK7*'Eligibility & Scoring'!$U7 -> 110778.69 | D6: ='Eligibility & Scoring'!$AK7-C6 -> 271721.31 | E6: =IF(C6+D6=0,0,IFERROR(INDEX('Fund Parameters'!$B$74:$B$78,Pipeline!$H7),1)) -> 0.95 | F6: =C6*E6 -> 105239.75 | G6: =$C6*$E6*(TrancheA*IF(1-VerifLag=Pipeline!$I7,RampV1,IF(1-VerifLag=Pipeline!$I7+1,RampV2-RampV1,IF(1-VerifLag=Pipeline!$I7+2,1-RampV2,0)))+(1-TrancheA)*IF(1-VerifLag-1=Pipeline!$I7,RampV1,IF(1-VerifLag-1=Pipeline!$I7+1,RampV2-RampV1,IF(1-VerifLag-1=Pipeline!$I7+2,1-RampV2,0)))) -> 44200.697 | H6: =$C6*$E6*(TrancheA*IF(2-VerifLag=Pipeline!$I7,RampV1,IF(2-VerifLag=Pipeline!$I7+1,RampV2-RampV1,IF(2-VerifLag=Pipeline!$I7+2,1-RampV2,0)))+(1-TrancheA)*IF(2-VerifLag-1=Pipeline!$I7,RampV1,IF(2-VerifLag-1=Pipeline!$I7+1,RampV2-RampV1,IF(2-VerifLag-1=Pipeline!$I7+2,1-RampV2,0)))) -> 41043.504 | I6: =$C6*$E6*(TrancheA*IF(3-VerifLag=Pipeline!$I7,RampV1,IF(3-VerifLag=Pipeline!$I7+1,RampV2-RampV1,IF(3-VerifLag=Pipeline!$I7+2,1-RampV2,0)))+(1-TrancheA)*IF(3-VerifLag-1=Pipeline!$I7,RampV1,IF(3-VerifLag-1=Pipeline!$I7+1,RampV2-RampV1,IF(3-VerifLag-1=Pipeline!$I7+2,1-RampV2,0)))) -> 16838.361 | J6: =$C6*$E6*(TrancheA*IF(4-VerifLag=Pipeline!$I7,RampV1,IF(4-VerifLag=Pipeline!$I7+1,RampV2-RampV1,IF(4-VerifLag=Pipeline!$I7+2,1-RampV2,0)))+(1-TrancheA)*IF(4-VerifLag-1=Pipeline!$I7,RampV1,IF(4-VerifLag-1=Pipeline!$I7+1,RampV2-RampV1,IF(4-VerifLag-1=Pipeline!$I7+2,1-RampV2,0)))) -> 3157.1926 | K6: =$C6*$E6*(TrancheA*IF(5-VerifLag=Pipeline!$I7,RampV1,IF(5-VerifLag=Pipeline!$I7+1,RampV2-RampV1,IF(5-VerifLag=Pipeline!$I7+2,1-RampV2,0)))+(1-TrancheA)*IF(5-VerifLag-1=Pipeline!$I7,RampV1,IF(5-VerifLag-1=Pipeline!$I7+1,RampV2-RampV1,IF(5-VerifLag-1=Pipeline!$I7+2,1-RampV2,0)))) -> 0 | L6: =$C6*$E6*(TrancheA*IF(6-VerifLag=Pipeline!$I7,RampV1,IF(6-VerifLag=Pipeline!$I7+1,RampV2-RampV1,IF(6-VerifLag=Pipeline!$I7+2,1-RampV2,0)))+(1-TrancheA)*IF(6-VerifLag-1=Pipeline!$I7,RampV1,IF(6-VerifLag-1=Pipeline!$I7+1,RampV2-RampV1,IF(6-VerifLag-1=Pipeline!$I7+2,1-RampV2,0)))) -> 0 | M6: =$C6*$E6*(TrancheA*IF(7-VerifLag=Pipeline!$I7,RampV1,IF(7-VerifLag=Pipeline!$I7+1,RampV2-RampV1,IF(7-VerifLag=Pipeline!$I7+2,1-RampV2,0)))+(1-TrancheA)*IF(7-VerifLag-1=Pipeline!$I7,RampV1,IF(7-VerifLag-1=Pipeline!$I7+1,RampV2-RampV1,IF(7-VerifLag-1=Pipeline!$I7+2,1-RampV2,0)))) -> 0 | N6: =$C6*$E6*(TrancheA*IF(8-VerifLag=Pipeline!$I7,RampV1,IF(8-VerifLag=Pipeline!$I7+1,RampV2-RampV1,IF(8-VerifLag=Pipeline!$I7+2,1-RampV2,0)))+(1-TrancheA)*IF(8-VerifLag-1=Pipeline!$I7,RampV1,IF(8-VerifLag-1=Pipeline!$I7+1,RampV2-RampV1,IF(8-VerifLag-1=Pipeline!$I7+2,1-RampV2,0)))) -> 0 | O6: =$C6*$E6*(TrancheA*IF(9-VerifLag=Pipeline!$I7,RampV1,IF(9-VerifLag=Pipeline!$I7+1,RampV2-RampV1,IF(9-VerifLag=Pipeline!$I7+2,1-RampV2,0)))+(1-TrancheA)*IF(9-VerifLag-1=Pipeline!$I7,RampV1,IF(9-VerifLag-1=Pipeline!$I7+1,RampV2-RampV1,IF(9-VerifLag-1=Pipeline!$I7+2,1-RampV2,0)))) -> 0 | P6: =$C6*$E6*(TrancheA*IF(10-VerifLag=Pipeline!$I7,RampV1,IF(10-VerifLag=Pipeline!$I7+1,RampV2-RampV1,IF(10-VerifLag=Pipeline!$I7+2,1-RampV2,0)))+(1-TrancheA)*IF(10-VerifLag-1=Pipeline!$I7,RampV1,IF(10-VerifLag-1=Pipeline!$I7+1,RampV2-RampV1,IF(10-VerifLag-1=Pipeline!$I7+2,1-RampV2,0)))) -> 0 | Q6: =SUM(G6:P6) -> 105239.75
A7: 2 | B7: ='Eligibility & Scoring'!$B8 -> Project B - River towns | C7: ='Eligibility & Scoring'!$AK8*'Eligibility & Scoring'!$U8 -> 32871.094 | D7: ='Eligibility & Scoring'!$AK8-C7 -> 94628.906 | E7: =IF(C7+D7=0,0,IFERROR(INDEX('Fund Parameters'!$B$74:$B$78,Pipeline!$H8),1)) -> 0.9 | F7: =C7*E7 -> 29583.984 | G7: =$C7*$E7*(TrancheA*IF(1-VerifLag=Pipeline!$I8,RampV1,IF(1-VerifLag=Pipeline!$I8+1,RampV2-RampV1,IF(1-VerifLag=Pipeline!$I8+2,1-RampV2,0)))+(1-TrancheA)*IF(1-VerifLag-1=Pipeline!$I8,RampV1,IF(1-VerifLag-1=Pipeline!$I8+1,RampV2-RampV1,IF(1-VerifLag-1=Pipeline!$I8+2,1-RampV2,0)))) -> 0 | H7: =$C7*$E7*(TrancheA*IF(2-VerifLag=Pipeline!$I8,RampV1,IF(2-VerifLag=Pipeline!$I8+1,RampV2-RampV1,IF(2-VerifLag=Pipeline!$I8+2,1-RampV2,0)))+(1-TrancheA)*IF(2-VerifLag-1=Pipeline!$I8,RampV1,IF(2-VerifLag-1=Pipeline!$I8+1,RampV2-RampV1,IF(2-VerifLag-1=Pipeline!$I8+2,1-RampV2,0)))) -> 12425.273 | I7: =$C7*$E7*(TrancheA*IF(3-VerifLag=Pipeline!$I8,RampV1,IF(3-VerifLag=Pipeline!$I8+1,RampV2-RampV1,IF(3-VerifLag=Pipeline!$I8+2,1-RampV2,0)))+(1-TrancheA)*IF(3-VerifLag-1=Pipeline!$I8,RampV1,IF(3-VerifLag-1=Pipeline!$I8+1,RampV2-RampV1,IF(3-VerifLag-1=Pipeline!$I8+2,1-RampV2,0)))) -> 11537.754 | J7: =$C7*$E7*(TrancheA*IF(4-VerifLag=Pipeline!$I8,RampV1,IF(4-VerifLag=Pipeline!$I8+1,RampV2-RampV1,IF(4-VerifLag=Pipeline!$I8+2,1-RampV2,0)))+(1-TrancheA)*IF(4-VerifLag-1=Pipeline!$I8,RampV1,IF(4-VerifLag-1=Pipeline!$I8+1,RampV2-RampV1,IF(4-VerifLag-1=Pipeline!$I8+2,1-RampV2,0)))) -> 4733.4375 | K7: =$C7*$E7*(TrancheA*IF(5-VerifLag=Pipeline!$I8,RampV1,IF(5-VerifLag=Pipeline!$I8+1,RampV2-RampV1,IF(5-VerifLag=Pipeline!$I8+2,1-RampV2,0)))+(1-TrancheA)*IF(5-VerifLag-1=Pipeline!$I8,RampV1,IF(5-VerifLag-1=Pipeline!$I8+1,RampV2-RampV1,IF(5-VerifLag-1=Pipeline!$I8+2,1-RampV2,0)))) -> 887.51953 | L7: =$C7*$E7*(TrancheA*IF(6-VerifLag=Pipeline!$I8,RampV1,IF(6-VerifLag=Pipeline!$I8+1,RampV2-RampV1,IF(6-VerifLag=Pipeline!$I8+2,1-RampV2,0)))+(1-TrancheA)*IF(6-VerifLag-1=Pipeline!$I8,RampV1,IF(6-VerifLag-1=Pipeline!$I8+1,RampV2-RampV1,IF(6-VerifLag-1=Pipeline!$I8+2,1-RampV2,0)))) -> 0 | M7: =$C7*$E7*(TrancheA*IF(7-VerifLag=Pipeline!$I8,RampV1,IF(7-VerifLag=Pipeline!$I8+1,RampV2-RampV1,IF(7-VerifLag=Pipeline!$I8+2,1-RampV2,0)))+(1-TrancheA)*IF(7-VerifLag-1=Pipeline!$I8,RampV1,IF(7-VerifLag-1=Pipeline!$I8+1,RampV2-RampV1,IF(7-VerifLag-1=Pipeline!$I8+2,1-RampV2,0)))) -> 0 | N7: =$C7*$E7*(TrancheA*IF(8-VerifLag=Pipeline!$I8,RampV1,IF(8-VerifLag=Pipeline!$I8+1,RampV2-RampV1,IF(8-VerifLag=Pipeline!$I8+2,1-RampV2,0)))+(1-TrancheA)*IF(8-VerifLag-1=Pipeline!$I8,RampV1,IF(8-VerifLag-1=Pipeline!$I8+1,RampV2-RampV1,IF(8-VerifLag-1=Pipeline!$I8+2,1-RampV2,0)))) -> 0 | O7: =$C7*$E7*(TrancheA*IF(9-VerifLag=Pipeline!$I8,RampV1,IF(9-VerifLag=Pipeline!$I8+1,RampV2-RampV1,IF(9-VerifLag=Pipeline!$I8+2,1-RampV2,0)))+(1-TrancheA)*IF(9-VerifLag-1=Pipeline!$I8,RampV1,IF(9-VerifLag-1=Pipeline!$I8+1,RampV2-RampV1,IF(9-VerifLag-1=Pipeline!$I8+2,1-RampV2,0)))) -> 0 | P7: =$C7*$E7*(TrancheA*IF(10-VerifLag=Pipeline!$I8,RampV1,IF(10-VerifLag=Pipeline!$I8+1,RampV2-RampV1,IF(10-VerifLag=Pipeline!$I8+2,1-RampV2,0)))+(1-TrancheA)*IF(10-VerifLag-1=Pipeline!$I8,RampV1,IF(10-VerifLag-1=Pipeline!$I8+1,RampV2-RampV1,IF(10-VerifLag-1=Pipeline!$I8+2,1-RampV2,0)))) -> 0 | Q7: =SUM(G7:P7) -> 29583.984
A8: 3 | B8: ='Eligibility & Scoring'!$B9 -> Project C - Northern corridor | C8: ='Eligibility & Scoring'!$AK9*'Eligibility & Scoring'!$U9 -> 115204.4 | D8: ='Eligibility & Scoring'!$AK9-C8 -> 267295.6 | E8: =IF(C8+D8=0,0,IFERROR(INDEX('Fund Parameters'!$B$74:$B$78,Pipeline!$H9),1)) -> 1 | F8: =C8*E8 -> 115204.4 | G8: =$C8*$E8*(TrancheA*IF(1-VerifLag=Pipeline!$I9,RampV1,IF(1-VerifLag=Pipeline!$I9+1,RampV2-RampV1,IF(1-VerifLag=Pipeline!$I9+2,1-RampV2,0)))+(1-TrancheA)*IF(1-VerifLag-1=Pipeline!$I9,RampV1,IF(1-VerifLag-1=Pipeline!$I9+1,RampV2-RampV1,IF(1-VerifLag-1=Pipeline!$I9+2,1-RampV2,0)))) -> 48385.849 | H8: =$C8*$E8*(TrancheA*IF(2-VerifLag=Pipeline!$I9,RampV1,IF(2-VerifLag=Pipeline!$I9+1,RampV2-RampV1,IF(2-VerifLag=Pipeline!$I9+2,1-RampV2,0)))+(1-TrancheA)*IF(2-VerifLag-1=Pipeline!$I9,RampV1,IF(2-VerifLag-1=Pipeline!$I9+1,RampV2-RampV1,IF(2-VerifLag-1=Pipeline!$I9+2,1-RampV2,0)))) -> 44929.717 | I8: =$C8*$E8*(TrancheA*IF(3-VerifLag=Pipeline!$I9,RampV1,IF(3-VerifLag=Pipeline!$I9+1,RampV2-RampV1,IF(3-VerifLag=Pipeline!$I9+2,1-RampV2,0)))+(1-TrancheA)*IF(3-VerifLag-1=Pipeline!$I9,RampV1,IF(3-VerifLag-1=Pipeline!$I9+1,RampV2-RampV1,IF(3-VerifLag-1=Pipeline!$I9+2,1-RampV2,0)))) -> 18432.704 | J8: =$C8*$E8*(TrancheA*IF(4-VerifLag=Pipeline!$I9,RampV1,IF(4-VerifLag=Pipeline!$I9+1,RampV2-RampV1,IF(4-VerifLag=Pipeline!$I9+2,1-RampV2,0)))+(1-TrancheA)*IF(4-VerifLag-1=Pipeline!$I9,RampV1,IF(4-VerifLag-1=Pipeline!$I9+1,RampV2-RampV1,IF(4-VerifLag-1=Pipeline!$I9+2,1-RampV2,0)))) -> 3456.1321 | K8: =$C8*$E8*(TrancheA*IF(5-VerifLag=Pipeline!$I9,RampV1,IF(5-VerifLag=Pipeline!$I9+1,RampV2-RampV1,IF(5-VerifLag=Pipeline!$I9+2,1-RampV2,0)))+(1-TrancheA)*IF(5-VerifLag-1=Pipeline!$I9,RampV1,IF(5-VerifLag-1=Pipeline!$I9+1,RampV2-RampV1,IF(5-VerifLag-1=Pipeline!$I9+2,1-RampV2,0)))) -> 0 | L8: =$C8*$E8*(TrancheA*IF(6-VerifLag=Pipeline!$I9,RampV1,IF(6-VerifLag=Pipeline!$I9+1,RampV2-RampV1,IF(6-VerifLag=Pipeline!$I9+2,1-RampV2,0)))+(1-TrancheA)*IF(6-VerifLag-1=Pipeline!$I9,RampV1,IF(6-VerifLag-1=Pipeline!$I9+1,RampV2-RampV1,IF(6-VerifLag-1=Pipeline!$I9+2,1-RampV2,0)))) -> 0 | M8: =$C8*$E8*(TrancheA*IF(7-VerifLag=Pipeline!$I9,RampV1,IF(7-VerifLag=Pipeline!$I9+1,RampV2-RampV1,IF(7-VerifLag=Pipeline!$I9+2,1-RampV2,0)))+(1-TrancheA)*IF(7-VerifLag-1=Pipeline!$I9,RampV1,IF(7-VerifLag-1=Pipeline!$I9+1,RampV2-RampV1,IF(7-VerifLag-1=Pipeline!$I9+2,1-RampV2,0)))) -> 0 | N8: =$C8*$E8*(TrancheA*IF(8-VerifLag=Pipeline!$I9,RampV1,IF(8-VerifLag=Pipeline!$I9+1,RampV2-RampV1,IF(8-VerifLag=Pipeline!$I9+2,1-RampV2,0)))+(1-TrancheA)*IF(8-VerifLag-1=Pipeline!$I9,RampV1,IF(8-VerifLag-1=Pipeline!$I9+1,RampV2-RampV1,IF(8-VerifLag-1=Pipeline!$I9+2,1-RampV2,0)))) -> 0 | O8: =$C8*$E8*(TrancheA*IF(9-VerifLag=Pipeline!$I9,RampV1,IF(9-VerifLag=Pipeline!$I9+1,RampV2-RampV1,IF(9-VerifLag=Pipeline!$I9+2,1-RampV2,0)))+(1-TrancheA)*IF(9-VerifLag-1=Pipeline!$I9,RampV1,IF(9-VerifLag-1=Pipeline!$I9+1,RampV2-RampV1,IF(9-VerifLag-1=Pipeline!$I9+2,1-RampV2,0)))) -> 0 | P8: =$C8*$E8*(TrancheA*IF(10-VerifLag=Pipeline!$I9,RampV1,IF(10-VerifLag=Pipeline!$I9+1,RampV2-RampV1,IF(10-VerifLag=Pipeline!$I9+2,1-RampV2,0)))+(1-TrancheA)*IF(10-VerifLag-1=Pipeline!$I9,RampV1,IF(10-VerifLag-1=Pipeline!$I9+1,RampV2-RampV1,IF(10-VerifLag-1=Pipeline!$I9+2,1-RampV2,0)))) -> 0 | Q8: =SUM(G8:P8) -> 115204.4
A9: 4 | B9: ='Eligibility & Scoring'!$B10 -> Project D - Island grids | C9: ='Eligibility & Scoring'!$AK10*'Eligibility & Scoring'!$U10 -> 0 | D9: ='Eligibility & Scoring'!$AK10-C9 -> 0 | E9: =IF(C9+D9=0,0,IFERROR(INDEX('Fund Parameters'!$B$74:$B$78,Pipeline!$H10),1)) -> 0 | F9: =C9*E9 -> 0 | G9: =$C9*$E9*(TrancheA*IF(1-VerifLag=Pipeline!$I10,RampV1,IF(1-VerifLag=Pipeline!$I10+1,RampV2-RampV1,IF(1-VerifLag=Pipeline!$I10+2,1-RampV2,0)))+(1-TrancheA)*IF(1-VerifLag-1=Pipeline!$I10,RampV1,IF(1-VerifLag-1=Pipeline!$I10+1,RampV2-RampV1,IF(1-VerifLag-1=Pipeline!$I10+2,1-RampV2,0)))) -> 0 | H9: =$C9*$E9*(TrancheA*IF(2-VerifLag=Pipeline!$I10,RampV1,IF(2-VerifLag=Pipeline!$I10+1,RampV2-RampV1,IF(2-VerifLag=Pipeline!$I10+2,1-RampV2,0)))+(1-TrancheA)*IF(2-VerifLag-1=Pipeline!$I10,RampV1,IF(2-VerifLag-1=Pipeline!$I10+1,RampV2-RampV1,IF(2-VerifLag-1=Pipeline!$I10+2,1-RampV2,0)))) -> 0 | I9: =$C9*$E9*(TrancheA*IF(3-VerifLag=Pipeline!$I10,RampV1,IF(3-VerifLag=Pipeline!$I10+1,RampV2-RampV1,IF(3-VerifLag=Pipeline!$I10+2,1-RampV2,0)))+(1-TrancheA)*IF(3-VerifLag-1=Pipeline!$I10,RampV1,IF(3-VerifLag-1=Pipeline!$I10+1,RampV2-RampV1,IF(3-VerifLag-1=Pipeline!$I10+2,1-RampV2,0)))) -> 0 | J9: =$C9*$E9*(TrancheA*IF(4-VerifLag=Pipeline!$I10,RampV1,IF(4-VerifLag=Pipeline!$I10+1,RampV2-RampV1,IF(4-VerifLag=Pipeline!$I10+2,1-RampV2,0)))+(1-TrancheA)*IF(4-VerifLag-1=Pipeline!$I10,RampV1,IF(4-VerifLag-1=Pipeline!$I10+1,RampV2-RampV1,IF(4-VerifLag-1=Pipeline!$I10+2,1-RampV2,0)))) -> 0 | K9: =$C9*$E9*(TrancheA*IF(5-VerifLag=Pipeline!$I10,RampV1,IF(5-VerifLag=Pipeline!$I10+1,RampV2-RampV1,IF(5-VerifLag=Pipeline!$I10+2,1-RampV2,0)))+(1-TrancheA)*IF(5-VerifLag-1=Pipeline!$I10,RampV1,IF(5-VerifLag-1=Pipeline!$I10+1,RampV2-RampV1,IF(5-VerifLag-1=Pipeline!$I10+2,1-RampV2,0)))) -> 0 | L9: =$C9*$E9*(TrancheA*IF(6-VerifLag=Pipeline!$I10,RampV1,IF(6-VerifLag=Pipeline!$I10+1,RampV2-RampV1,IF(6-VerifLag=Pipeline!$I10+2,1-RampV2,0)))+(1-TrancheA)*IF(6-VerifLag-1=Pipeline!$I10,RampV1,IF(6-VerifLag-1=Pipeline!$I10+1,RampV2-RampV1,IF(6-VerifLag-1=Pipeline!$I10+2,1-RampV2,0)))) -> 0 | M9: =$C9*$E9*(TrancheA*IF(7-VerifLag=Pipeline!$I10,RampV1,IF(7-VerifLag=Pipeline!$I10+1,RampV2-RampV1,IF(7-VerifLag=Pipeline!$I10+2,1-RampV2,0)))+(1-TrancheA)*IF(7-VerifLag-1=Pipeline!$I10,RampV1,IF(7-VerifLag-1=Pipeline!$I10+1,RampV2-RampV1,IF(7-VerifLag-1=Pipeline!$I10+2,1-RampV2,0)))) -> 0 | N9: =$C9*$E9*(TrancheA*IF(8-VerifLag=Pipeline!$I10,RampV1,IF(8-VerifLag=Pipeline!$I10+1,RampV2-RampV1,IF(8-VerifLag=Pipeline!$I10+2,1-RampV2,0)))+(1-TrancheA)*IF(8-VerifLag-1=Pipeline!$I10,RampV1,IF(8-VerifLag-1=Pipeline!$I10+1,RampV2-RampV1,IF(8-VerifLag-1=Pipeline!$I10+2,1-RampV2,0)))) -> 0 | O9: =$C9*$E9*(TrancheA*IF(9-VerifLag=Pipeline!$I10,RampV1,IF(9-VerifLag=Pipeline!$I10+1,RampV2-RampV1,IF(9-VerifLag=Pipeline!$I10+2,1-RampV2,0)))+(1-TrancheA)*IF(9-VerifLag-1=Pipeline!$I10,RampV1,IF(9-VerifLag-1=Pipeline!$I10+1,RampV2-RampV1,IF(9-VerifLag-1=Pipeline!$I10+2,1-RampV2,0)))) -> 0 | P9: =$C9*$E9*(TrancheA*IF(10-VerifLag=Pipeline!$I10,RampV1,IF(10-VerifLag=Pipeline!$I10+1,RampV2-RampV1,IF(10-VerifLag=Pipeline!$I10+2,1-RampV2,0)))+(1-TrancheA)*IF(10-VerifLag-1=Pipeline!$I10,RampV1,IF(10-VerifLag-1=Pipeline!$I10+1,RampV2-RampV1,IF(10-VerifLag-1=Pipeline!$I10+2,1-RampV2,0)))) -> 0 | Q9: =SUM(G9:P9) -> 0
A10: 5 | B10: ='Eligibility & Scoring'!$B11 -> Project E - Highland villages | C10: ='Eligibility & Scoring'!$AK11*'Eligibility & Scoring'!$U11 -> 0 | D10: ='Eligibility & Scoring'!$AK11-C10 -> 0 | E10: =IF(C10+D10=0,0,IFERROR(INDEX('Fund Parameters'!$B$74:$B$78,Pipeline!$H11),1)) -> 0 | F10: =C10*E10 -> 0 | G10: =$C10*$E10*(TrancheA*IF(1-VerifLag=Pipeline!$I11,RampV1,IF(1-VerifLag=Pipeline!$I11+1,RampV2-RampV1,IF(1-VerifLag=Pipeline!$I11+2,1-RampV2,0)))+(1-TrancheA)*IF(1-VerifLag-1=Pipeline!$I11,RampV1,IF(1-VerifLag-1=Pipeline!$I11+1,RampV2-RampV1,IF(1-VerifLag-1=Pipeline!$I11+2,1-RampV2,0)))) -> 0 | H10: =$C10*$E10*(TrancheA*IF(2-VerifLag=Pipeline!$I11,RampV1,IF(2-VerifLag=Pipeline!$I11+1,RampV2-RampV1,IF(2-VerifLag=Pipeline!$I11+2,1-RampV2,0)))+(1-TrancheA)*IF(2-VerifLag-1=Pipeline!$I11,RampV1,IF(2-VerifLag-1=Pipeline!$I11+1,RampV2-RampV1,IF(2-VerifLag-1=Pipeline!$I11+2,1-RampV2,0)))) -> 0 | I10: =$C10*$E10*(TrancheA*IF(3-VerifLag=Pipeline!$I11,RampV1,IF(3-VerifLag=Pipeline!$I11+1,RampV2-RampV1,IF(3-VerifLag=Pipeline!$I11+2,1-RampV2,0)))+(1-TrancheA)*IF(3-VerifLag-1=Pipeline!$I11,RampV1,IF(3-VerifLag-1=Pipeline!$I11+1,RampV2-RampV1,IF(3-VerifLag-1=Pipeline!$I11+2,1-RampV2,0)))) -> 0 | J10: =$C10*$E10*(TrancheA*IF(4-VerifLag=Pipeline!$I11,RampV1,IF(4-VerifLag=Pipeline!$I11+1,RampV2-RampV1,IF(4-VerifLag=Pipeline!$I11+2,1-RampV2,0)))+(1-TrancheA)*IF(4-VerifLag-1=Pipeline!$I11,RampV1,IF(4-VerifLag-1=Pipeline!$I11+1,RampV2-RampV1,IF(4-VerifLag-1=Pipeline!$I11+2,1-RampV2,0)))) -> 0 | K10: =$C10*$E10*(TrancheA*IF(5-VerifLag=Pipeline!$I11,RampV1,IF(5-VerifLag=Pipeline!$I11+1,RampV2-RampV1,IF(5-VerifLag=Pipeline!$I11+2,1-RampV2,0)))+(1-TrancheA)*IF(5-VerifLag-1=Pipeline!$I11,RampV1,IF(5-VerifLag-1=Pipeline!$I11+1,RampV2-RampV1,IF(5-VerifLag-1=Pipeline!$I11+2,1-RampV2,0)))) -> 0 | L10: =$C10*$E10*(TrancheA*IF(6-VerifLag=Pipeline!$I11,RampV1,IF(6-VerifLag=Pipeline!$I11+1,RampV2-RampV1,IF(6-VerifLag=Pipeline!$I11+2,1-RampV2,0)))+(1-TrancheA)*IF(6-VerifLag-1=Pipeline!$I11,RampV1,IF(6-VerifLag-1=Pipeline!$I11+1,RampV2-RampV1,IF(6-VerifLag-1=Pipeline!$I11+2,1-RampV2,0)))) -> 0 | M10: =$C10*$E10*(TrancheA*IF(7-VerifLag=Pipeline!$I11,RampV1,IF(7-VerifLag=Pipeline!$I11+1,RampV2-RampV1,IF(7-VerifLag=Pipeline!$I11+2,1-RampV2,0)))+(1-TrancheA)*IF(7-VerifLag-1=Pipeline!$I11,RampV1,IF(7-VerifLag-1=Pipeline!$I11+1,RampV2-RampV1,IF(7-VerifLag-1=Pipeline!$I11+2,1-RampV2,0)))) -> 0 | N10: =$C10*$E10*(TrancheA*IF(8-VerifLag=Pipeline!$I11,RampV1,IF(8-VerifLag=Pipeline!$I11+1,RampV2-RampV1,IF(8-VerifLag=Pipeline!$I11+2,1-RampV2,0)))+(1-TrancheA)*IF(8-VerifLag-1=Pipeline!$I11,RampV1,IF(8-VerifLag-1=Pipeline!$I11+1,RampV2-RampV1,IF(8-VerifLag-1=Pipeline!$I11+2,1-RampV2,0)))) -> 0 | O10: =$C10*$E10*(TrancheA*IF(9-VerifLag=Pipeline!$I11,RampV1,IF(9-VerifLag=Pipeline!$I11+1,RampV2-RampV1,IF(9-VerifLag=Pipeline!$I11+2,1-RampV2,0)))+(1-TrancheA)*IF(9-VerifLag-1=Pipeline!$I11,RampV1,IF(9-VerifLag-1=Pipeline!$I11+1,RampV2-RampV1,IF(9-VerifLag-1=Pipeline!$I11+2,1-RampV2,0)))) -> 0 | P10: =$C10*$E10*(TrancheA*IF(10-VerifLag=Pipeline!$I11,RampV1,IF(10-VerifLag=Pipeline!$I11+1,RampV2-RampV1,IF(10-VerifLag=Pipeline!$I11+2,1-RampV2,0)))+(1-TrancheA)*IF(10-VerifLag-1=Pipeline!$I11,RampV1,IF(10-VerifLag-1=Pipeline!$I11+1,RampV2-RampV1,IF(10-VerifLag-1=Pipeline!$I11+2,1-RampV2,0)))) -> 0 | Q10: =SUM(G10:P10) -> 0
A11: 6 | B11: ='Eligibility & Scoring'!$B12 -> Project F - Market towns | C11: ='Eligibility & Scoring'!$AK12*'Eligibility & Scoring'!$U12 -> 0 | D11: ='Eligibility & Scoring'!$AK12-C11 -> 0 | E11: =IF(C11+D11=0,0,IFERROR(INDEX('Fund Parameters'!$B$74:$B$78,Pipeline!$H12),1)) -> 0 | F11: =C11*E11 -> 0 | G11: =$C11*$E11*(TrancheA*IF(1-VerifLag=Pipeline!$I12,RampV1,IF(1-VerifLag=Pipeline!$I12+1,RampV2-RampV1,IF(1-VerifLag=Pipeline!$I12+2,1-RampV2,0)))+(1-TrancheA)*IF(1-VerifLag-1=Pipeline!$I12,RampV1,IF(1-VerifLag-1=Pipeline!$I12+1,RampV2-RampV1,IF(1-VerifLag-1=Pipeline!$I12+2,1-RampV2,0)))) -> 0 | H11: =$C11*$E11*(TrancheA*IF(2-VerifLag=Pipeline!$I12,RampV1,IF(2-VerifLag=Pipeline!$I12+1,RampV2-RampV1,IF(2-VerifLag=Pipeline!$I12+2,1-RampV2,0)))+(1-TrancheA)*IF(2-VerifLag-1=Pipeline!$I12,RampV1,IF(2-VerifLag-1=Pipeline!$I12+1,RampV2-RampV1,IF(2-VerifLag-1=Pipeline!$I12+2,1-RampV2,0)))) -> 0 | I11: =$C11*$E11*(TrancheA*IF(3-VerifLag=Pipeline!$I12,RampV1,IF(3-VerifLag=Pipeline!$I12+1,RampV2-RampV1,IF(3-VerifLag=Pipeline!$I12+2,1-RampV2,0)))+(1-TrancheA)*IF(3-VerifLag-1=Pipeline!$I12,RampV1,IF(3-VerifLag-1=Pipeline!$I12+1,RampV2-RampV1,IF(3-VerifLag-1=Pipeline!$I12+2,1-RampV2,0)))) -> 0 | J11: =$C11*$E11*(TrancheA*IF(4-VerifLag=Pipeline!$I12,RampV1,IF(4-VerifLag=Pipeline!$I12+1,RampV2-RampV1,IF(4-VerifLag=Pipeline!$I12+2,1-RampV2,0)))+(1-TrancheA)*IF(4-VerifLag-1=Pipeline!$I12,RampV1,IF(4-VerifLag-1=Pipeline!$I12+1,RampV2-RampV1,IF(4-VerifLag-1=Pipeline!$I12+2,1-RampV2,0)))) -> 0 | K11: =$C11*$E11*(TrancheA*IF(5-VerifLag=Pipeline!$I12,RampV1,IF(5-VerifLag=Pipeline!$I12+1,RampV2-RampV1,IF(5-VerifLag=Pipeline!$I12+2,1-RampV2,0)))+(1-TrancheA)*IF(5-VerifLag-1=Pipeline!$I12,RampV1,IF(5-VerifLag-1=Pipeline!$I12+1,RampV2-RampV1,IF(5-VerifLag-1=Pipeline!$I12+2,1-RampV2,0)))) -> 0 | L11: =$C11*$E11*(TrancheA*IF(6-VerifLag=Pipeline!$I12,RampV1,IF(6-VerifLag=Pipeline!$I12+1,RampV2-RampV1,IF(6-VerifLag=Pipeline!$I12+2,1-RampV2,0)))+(1-TrancheA)*IF(6-VerifLag-1=Pipeline!$I12,RampV1,IF(6-VerifLag-1=Pipeline!$I12+1,RampV2-RampV1,IF(6-VerifLag-1=Pipeline!$I12+2,1-RampV2,0)))) -> 0 | M11: =$C11*$E11*(TrancheA*IF(7-VerifLag=Pipeline!$I12,RampV1,IF(7-VerifLag=Pipeline!$I12+1,RampV2-RampV1,IF(7-VerifLag=Pipeline!$I12+2,1-RampV2,0)))+(1-TrancheA)*IF(7-VerifLag-1=Pipeline!$I12,RampV1,IF(7-VerifLag-1=Pipeline!$I12+1,RampV2-RampV1,IF(7-VerifLag-1=Pipeline!$I12+2,1-RampV2,0)))) -> 0 | N11: =$C11*$E11*(TrancheA*IF(8-VerifLag=Pipeline!$I12,RampV1,IF(8-VerifLag=Pipeline!$I12+1,RampV2-RampV1,IF(8-VerifLag=Pipeline!$I12+2,1-RampV2,0)))+(1-TrancheA)*IF(8-VerifLag-1=Pipeline!$I12,RampV1,IF(8-VerifLag-1=Pipeline!$I12+1,RampV2-RampV1,IF(8-VerifLag-1=Pipeline!$I12+2,1-RampV2,0)))) -> 0 | O11: =$C11*$E11*(TrancheA*IF(9-VerifLag=Pipeline!$I12,RampV1,IF(9-VerifLag=Pipeline!$I12+1,RampV2-RampV1,IF(9-VerifLag=Pipeline!$I12+2,1-RampV2,0)))+(1-TrancheA)*IF(9-VerifLag-1=Pipeline!$I12,RampV1,IF(9-VerifLag-1=Pipeline!$I12+1,RampV2-RampV1,IF(9-VerifLag-1=Pipeline!$I12+2,1-RampV2,0)))) -> 0 | P11: =$C11*$E11*(TrancheA*IF(10-VerifLag=Pipeline!$I12,RampV1,IF(10-VerifLag=Pipeline!$I12+1,RampV2-RampV1,IF(10-VerifLag=Pipeline!$I12+2,1-RampV2,0)))+(1-TrancheA)*IF(10-VerifLag-1=Pipeline!$I12,RampV1,IF(10-VerifLag-1=Pipeline!$I12+1,RampV2-RampV1,IF(10-VerifLag-1=Pipeline!$I12+2,1-RampV2,0)))) -> 0 | Q11: =SUM(G11:P11) -> 0
A12: 7 | B12: ='Eligibility & Scoring'!$B13 -> Project G - Remote valley | C12: ='Eligibility & Scoring'!$AK13*'Eligibility & Scoring'!$U13 -> 0 | D12: ='Eligibility & Scoring'!$AK13-C12 -> 0 | E12: =IF(C12+D12=0,0,IFERROR(INDEX('Fund Parameters'!$B$74:$B$78,Pipeline!$H13),1)) -> 0 | F12: =C12*E12 -> 0 | G12: =$C12*$E12*(TrancheA*IF(1-VerifLag=Pipeline!$I13,RampV1,IF(1-VerifLag=Pipeline!$I13+1,RampV2-RampV1,IF(1-VerifLag=Pipeline!$I13+2,1-RampV2,0)))+(1-TrancheA)*IF(1-VerifLag-1=Pipeline!$I13,RampV1,IF(1-VerifLag-1=Pipeline!$I13+1,RampV2-RampV1,IF(1-VerifLag-1=Pipeline!$I13+2,1-RampV2,0)))) -> 0 | H12: =$C12*$E12*(TrancheA*IF(2-VerifLag=Pipeline!$I13,RampV1,IF(2-VerifLag=Pipeline!$I13+1,RampV2-RampV1,IF(2-VerifLag=Pipeline!$I13+2,1-RampV2,0)))+(1-TrancheA)*IF(2-VerifLag-1=Pipeline!$I13,RampV1,IF(2-VerifLag-1=Pipeline!$I13+1,RampV2-RampV1,IF(2-VerifLag-1=Pipeline!$I13+2,1-RampV2,0)))) -> 0 | I12: =$C12*$E12*(TrancheA*IF(3-VerifLag=Pipeline!$I13,RampV1,IF(3-VerifLag=Pipeline!$I13+1,RampV2-RampV1,IF(3-VerifLag=Pipeline!$I13+2,1-RampV2,0)))+(1-TrancheA)*IF(3-VerifLag-1=Pipeline!$I13,RampV1,IF(3-VerifLag-1=Pipeline!$I13+1,RampV2-RampV1,IF(3-VerifLag-1=Pipeline!$I13+2,1-RampV2,0)))) -> 0 | J12: =$C12*$E12*(TrancheA*IF(4-VerifLag=Pipeline!$I13,RampV1,IF(4-VerifLag=Pipeline!$I13+1,RampV2-RampV1,IF(4-VerifLag=Pipeline!$I13+2,1-RampV2,0)))+(1-TrancheA)*IF(4-VerifLag-1=Pipeline!$I13,RampV1,IF(4-VerifLag-1=Pipeline!$I13+1,RampV2-RampV1,IF(4-VerifLag-1=Pipeline!$I13+2,1-RampV2,0)))) -> 0 | K12: =$C12*$E12*(TrancheA*IF(5-VerifLag=Pipeline!$I13,RampV1,IF(5-VerifLag=Pipeline!$I13+1,RampV2-RampV1,IF(5-VerifLag=Pipeline!$I13+2,1-RampV2,0)))+(1-TrancheA)*IF(5-VerifLag-1=Pipeline!$I13,RampV1,IF(5-VerifLag-1=Pipeline!$I13+1,RampV2-RampV1,IF(5-VerifLag-1=Pipeline!$I13+2,1-RampV2,0)))) -> 0 | L12: =$C12*$E12*(TrancheA*IF(6-VerifLag=Pipeline!$I13,RampV1,IF(6-VerifLag=Pipeline!$I13+1,RampV2-RampV1,IF(6-VerifLag=Pipeline!$I13+2,1-RampV2,0)))+(1-TrancheA)*IF(6-VerifLag-1=Pipeline!$I13,RampV1,IF(6-VerifLag-1=Pipeline!$I13+1,RampV2-RampV1,IF(6-VerifLag-1=Pipeline!$I13+2,1-RampV2,0)))) -> 0 | M12: =$C12*$E12*(TrancheA*IF(7-VerifLag=Pipeline!$I13,RampV1,IF(7-VerifLag=Pipeline!$I13+1,RampV2-RampV1,IF(7-VerifLag=Pipeline!$I13+2,1-RampV2,0)))+(1-TrancheA)*IF(7-VerifLag-1=Pipeline!$I13,RampV1,IF(7-VerifLag-1=Pipeline!$I13+1,RampV2-RampV1,IF(7-VerifLag-1=Pipeline!$I13+2,1-RampV2,0)))) -> 0 | N12: =$C12*$E12*(TrancheA*IF(8-VerifLag=Pipeline!$I13,RampV1,IF(8-VerifLag=Pipeline!$I13+1,RampV2-RampV1,IF(8-VerifLag=Pipeline!$I13+2,1-RampV2,0)))+(1-TrancheA)*IF(8-VerifLag-1=Pipeline!$I13,RampV1,IF(8-VerifLag-1=Pipeline!$I13+1,RampV2-RampV1,IF(8-VerifLag-1=Pipeline!$I13+2,1-RampV2,0)))) -> 0 | O12: =$C12*$E12*(TrancheA*IF(9-VerifLag=Pipeline!$I13,RampV1,IF(9-VerifLag=Pipeline!$I13+1,RampV2-RampV1,IF(9-VerifLag=Pipeline!$I13+2,1-RampV2,0)))+(1-TrancheA)*IF(9-VerifLag-1=Pipeline!$I13,RampV1,IF(9-VerifLag-1=Pipeline!$I13+1,RampV2-RampV1,IF(9-VerifLag-1=Pipeline!$I13+2,1-RampV2,0)))) -> 0 | P12: =$C12*$E12*(TrancheA*IF(10-VerifLag=Pipeline!$I13,RampV1,IF(10-VerifLag=Pipeline!$I13+1,RampV2-RampV1,IF(10-VerifLag=Pipeline!$I13+2,1-RampV2,0)))+(1-TrancheA)*IF(10-VerifLag-1=Pipeline!$I13,RampV1,IF(10-VerifLag-1=Pipeline!$I13+1,RampV2-RampV1,IF(10-VerifLag-1=Pipeline!$I13+2,1-RampV2,0)))) -> 0 | Q12: =SUM(G12:P12) -> 0
A13: 8 | B13: ='Eligibility & Scoring'!$B14 -> Project H - Agro-processing hub | C13: ='Eligibility & Scoring'!$AK14*'Eligibility & Scoring'!$U14 -> 112181.98 | D13: ='Eligibility & Scoring'!$AK14-C13 -> 270318.02 | E13: =IF(C13+D13=0,0,IFERROR(INDEX('Fund Parameters'!$B$74:$B$78,Pipeline!$H14),1)) -> 0.95 | F13: =C13*E13 -> 106572.88 | G13: =$C13*$E13*(TrancheA*IF(1-VerifLag=Pipeline!$I14,RampV1,IF(1-VerifLag=Pipeline!$I14+1,RampV2-RampV1,IF(1-VerifLag=Pipeline!$I14+2,1-RampV2,0)))+(1-TrancheA)*IF(1-VerifLag-1=Pipeline!$I14,RampV1,IF(1-VerifLag-1=Pipeline!$I14+1,RampV2-RampV1,IF(1-VerifLag-1=Pipeline!$I14+2,1-RampV2,0)))) -> 0 | H13: =$C13*$E13*(TrancheA*IF(2-VerifLag=Pipeline!$I14,RampV1,IF(2-VerifLag=Pipeline!$I14+1,RampV2-RampV1,IF(2-VerifLag=Pipeline!$I14+2,1-RampV2,0)))+(1-TrancheA)*IF(2-VerifLag-1=Pipeline!$I14,RampV1,IF(2-VerifLag-1=Pipeline!$I14+1,RampV2-RampV1,IF(2-VerifLag-1=Pipeline!$I14+2,1-RampV2,0)))) -> 44760.61 | I13: =$C13*$E13*(TrancheA*IF(3-VerifLag=Pipeline!$I14,RampV1,IF(3-VerifLag=Pipeline!$I14+1,RampV2-RampV1,IF(3-VerifLag=Pipeline!$I14+2,1-RampV2,0)))+(1-TrancheA)*IF(3-VerifLag-1=Pipeline!$I14,RampV1,IF(3-VerifLag-1=Pipeline!$I14+1,RampV2-RampV1,IF(3-VerifLag-1=Pipeline!$I14+2,1-RampV2,0)))) -> 41563.423 | J13: =$C13*$E13*(TrancheA*IF(4-VerifLag=Pipeline!$I14,RampV1,IF(4-VerifLag=Pipeline!$I14+1,RampV2-RampV1,IF(4-VerifLag=Pipeline!$I14+2,1-RampV2,0)))+(1-TrancheA)*IF(4-VerifLag-1=Pipeline!$I14,RampV1,IF(4-VerifLag-1=Pipeline!$I14+1,RampV2-RampV1,IF(4-VerifLag-1=Pipeline!$I14+2,1-RampV2,0)))) -> 17051.661 | K13: =$C13*$E13*(TrancheA*IF(5-VerifLag=Pipeline!$I14,RampV1,IF(5-VerifLag=Pipeline!$I14+1,RampV2-RampV1,IF(5-VerifLag=Pipeline!$I14+2,1-RampV2,0)))+(1-TrancheA)*IF(5-VerifLag-1=Pipeline!$I14,RampV1,IF(5-VerifLag-1=Pipeline!$I14+1,RampV2-RampV1,IF(5-VerifLag-1=Pipeline!$I14+2,1-RampV2,0)))) -> 3197.1864 | L13: =$C13*$E13*(TrancheA*IF(6-VerifLag=Pipeline!$I14,RampV1,IF(6-VerifLag=Pipeline!$I14+1,RampV2-RampV1,IF(6-VerifLag=Pipeline!$I14+2,1-RampV2,0)))+(1-TrancheA)*IF(6-VerifLag-1=Pipeline!$I14,RampV1,IF(6-VerifLag-1=Pipeline!$I14+1,RampV2-RampV1,IF(6-VerifLag-1=Pipeline!$I14+2,1-RampV2,0)))) -> 0 | M13: =$C13*$E13*(TrancheA*IF(7-VerifLag=Pipeline!$I14,RampV1,IF(7-VerifLag=Pipeline!$I14+1,RampV2-RampV1,IF(7-VerifLag=Pipeline!$I14+2,1-RampV2,0)))+(1-TrancheA)*IF(7-VerifLag-1=Pipeline!$I14,RampV1,IF(7-VerifLag-1=Pipeline!$I14+1,RampV2-RampV1,IF(7-VerifLag-1=Pipeline!$I14+2,1-RampV2,0)))) -> 0 | N13: =$C13*$E13*(TrancheA*IF(8-VerifLag=Pipeline!$I14,RampV1,IF(8-VerifLag=Pipeline!$I14+1,RampV2-RampV1,IF(8-VerifLag=Pipeline!$I14+2,1-RampV2,0)))+(1-TrancheA)*IF(8-VerifLag-1=Pipeline!$I14,RampV1,IF(8-VerifLag-1=Pipeline!$I14+1,RampV2-RampV1,IF(8-VerifLag-1=Pipeline!$I14+2,1-RampV2,0)))) -> 0 | O13: =$C13*$E13*(TrancheA*IF(9-VerifLag=Pipeline!$I14,RampV1,IF(9-VerifLag=Pipeline!$I14+1,RampV2-RampV1,IF(9-VerifLag=Pipeline!$I14+2,1-RampV2,0)))+(1-TrancheA)*IF(9-VerifLag-1=Pipeline!$I14,RampV1,IF(9-VerifLag-1=Pipeline!$I14+1,RampV2-RampV1,IF(9-VerifLag-1=Pipeline!$I14+2,1-RampV2,0)))) -> 0 | P13: =$C13*$E13*(TrancheA*IF(10-VerifLag=Pipeline!$I14,RampV1,IF(10-VerifLag=Pipeline!$I14+1,RampV2-RampV1,IF(10-VerifLag=Pipeline!$I14+2,1-RampV2,0)))+(1-TrancheA)*IF(10-VerifLag-1=Pipeline!$I14,RampV1,IF(10-VerifLag-1=Pipeline!$I14+1,RampV2-RampV1,IF(10-VerifLag-1=Pipeline!$I14+2,1-RampV2,0)))) -> 0 | Q13: =SUM(G13:P13) -> 106572.88
A14: 9 | B14: ='Eligibility & Scoring'!$B15 -> Project I - Fishing communities | C14: ='Eligibility & Scoring'!$AK15*'Eligibility & Scoring'!$U15 -> 109793.86 | D14: ='Eligibility & Scoring'!$AK15-C14 -> 272706.14 | E14: =IF(C14+D14=0,0,IFERROR(INDEX('Fund Parameters'!$B$74:$B$78,Pipeline!$H15),1)) -> 0.9 | F14: =C14*E14 -> 98814.476 | G14: =$C14*$E14*(TrancheA*IF(1-VerifLag=Pipeline!$I15,RampV1,IF(1-VerifLag=Pipeline!$I15+1,RampV2-RampV1,IF(1-VerifLag=Pipeline!$I15+2,1-RampV2,0)))+(1-TrancheA)*IF(1-VerifLag-1=Pipeline!$I15,RampV1,IF(1-VerifLag-1=Pipeline!$I15+1,RampV2-RampV1,IF(1-VerifLag-1=Pipeline!$I15+2,1-RampV2,0)))) -> 0 | H14: =$C14*$E14*(TrancheA*IF(2-VerifLag=Pipeline!$I15,RampV1,IF(2-VerifLag=Pipeline!$I15+1,RampV2-RampV1,IF(2-VerifLag=Pipeline!$I15+2,1-RampV2,0)))+(1-TrancheA)*IF(2-VerifLag-1=Pipeline!$I15,RampV1,IF(2-VerifLag-1=Pipeline!$I15+1,RampV2-RampV1,IF(2-VerifLag-1=Pipeline!$I15+2,1-RampV2,0)))) -> 41502.08 | I14: =$C14*$E14*(TrancheA*IF(3-VerifLag=Pipeline!$I15,RampV1,IF(3-VerifLag=Pipeline!$I15+1,RampV2-RampV1,IF(3-VerifLag=Pipeline!$I15+2,1-RampV2,0)))+(1-TrancheA)*IF(3-VerifLag-1=Pipeline!$I15,RampV1,IF(3-VerifLag-1=Pipeline!$I15+1,RampV2-RampV1,IF(3-VerifLag-1=Pipeline!$I15+2,1-RampV2,0)))) -> 38537.646 | J14: =$C14*$E14*(TrancheA*IF(4-VerifLag=Pipeline!$I15,RampV1,IF(4-VerifLag=Pipeline!$I15+1,RampV2-RampV1,IF(4-VerifLag=Pipeline!$I15+2,1-RampV2,0)))+(1-TrancheA)*IF(4-VerifLag-1=Pipeline!$I15,RampV1,IF(4-VerifLag-1=Pipeline!$I15+1,RampV2-RampV1,IF(4-VerifLag-1=Pipeline!$I15+2,1-RampV2,0)))) -> 15810.316 | K14: =$C14*$E14*(TrancheA*IF(5-VerifLag=Pipeline!$I15,RampV1,IF(5-VerifLag=Pipeline!$I15+1,RampV2-RampV1,IF(5-VerifLag=Pipeline!$I15+2,1-RampV2,0)))+(1-TrancheA)*IF(5-VerifLag-1=Pipeline!$I15,RampV1,IF(5-VerifLag-1=Pipeline!$I15+1,RampV2-RampV1,IF(5-VerifLag-1=Pipeline!$I15+2,1-RampV2,0)))) -> 2964.4343 | L14: =$C14*$E14*(TrancheA*IF(6-VerifLag=Pipeline!$I15,RampV1,IF(6-VerifLag=Pipeline!$I15+1,RampV2-RampV1,IF(6-VerifLag=Pipeline!$I15+2,1-RampV2,0)))+(1-TrancheA)*IF(6-VerifLag-1=Pipeline!$I15,RampV1,IF(6-VerifLag-1=Pipeline!$I15+1,RampV2-RampV1,IF(6-VerifLag-1=Pipeline!$I15+2,1-RampV2,0)))) -> 0 | M14: =$C14*$E14*(TrancheA*IF(7-VerifLag=Pipeline!$I15,RampV1,IF(7-VerifLag=Pipeline!$I15+1,RampV2-RampV1,IF(7-VerifLag=Pipeline!$I15+2,1-RampV2,0)))+(1-TrancheA)*IF(7-VerifLag-1=Pipeline!$I15,RampV1,IF(7-VerifLag-1=Pipeline!$I15+1,RampV2-RampV1,IF(7-VerifLag-1=Pipeline!$I15+2,1-RampV2,0)))) -> 0 | N14: =$C14*$E14*(TrancheA*IF(8-VerifLag=Pipeline!$I15,RampV1,IF(8-VerifLag=Pipeline!$I15+1,RampV2-RampV1,IF(8-VerifLag=Pipeline!$I15+2,1-RampV2,0)))+(1-TrancheA)*IF(8-VerifLag-1=Pipeline!$I15,RampV1,IF(8-VerifLag-1=Pipeline!$I15+1,RampV2-RampV1,IF(8-VerifLag-1=Pipeline!$I15+2,1-RampV2,0)))) -> 0 | O14: =$C14*$E14*(TrancheA*IF(9-VerifLag=Pipeline!$I15,RampV1,IF(9-VerifLag=Pipeline!$I15+1,RampV2-RampV1,IF(9-VerifLag=Pipeline!$I15+2,1-RampV2,0)))+(1-TrancheA)*IF(9-VerifLag-1=Pipeline!$I15,RampV1,IF(9-VerifLag-1=Pipeline!$I15+1,RampV2-RampV1,IF(9-VerifLag-1=Pipeline!$I15+2,1-RampV2,0)))) -> 0 | P14: =$C14*$E14*(TrancheA*IF(10-VerifLag=Pipeline!$I15,RampV1,IF(10-VerifLag=Pipeline!$I15+1,RampV2-RampV1,IF(10-VerifLag=Pipeline!$I15+2,1-RampV2,0)))+(1-TrancheA)*IF(10-VerifLag-1=Pipeline!$I15,RampV1,IF(10-VerifLag-1=Pipeline!$I15+1,RampV2-RampV1,IF(10-VerifLag-1=Pipeline!$I15+2,1-RampV2,0)))) -> 0 | Q14: =SUM(G14:P14) -> 98814.476
A15: 10 | B15: ='Eligibility & Scoring'!$B16 -> Project J - Health and schools first | C15: ='Eligibility & Scoring'!$AK16*'Eligibility & Scoring'!$U16 -> 0 | D15: ='Eligibility & Scoring'!$AK16-C15 -> 0 | E15: =IF(C15+D15=0,0,IFERROR(INDEX('Fund Parameters'!$B$74:$B$78,Pipeline!$H16),1)) -> 0 | F15: =C15*E15 -> 0 | G15: =$C15*$E15*(TrancheA*IF(1-VerifLag=Pipeline!$I16,RampV1,IF(1-VerifLag=Pipeline!$I16+1,RampV2-RampV1,IF(1-VerifLag=Pipeline!$I16+2,1-RampV2,0)))+(1-TrancheA)*IF(1-VerifLag-1=Pipeline!$I16,RampV1,IF(1-VerifLag-1=Pipeline!$I16+1,RampV2-RampV1,IF(1-VerifLag-1=Pipeline!$I16+2,1-RampV2,0)))) -> 0 | H15: =$C15*$E15*(TrancheA*IF(2-VerifLag=Pipeline!$I16,RampV1,IF(2-VerifLag=Pipeline!$I16+1,RampV2-RampV1,IF(2-VerifLag=Pipeline!$I16+2,1-RampV2,0)))+(1-TrancheA)*IF(2-VerifLag-1=Pipeline!$I16,RampV1,IF(2-VerifLag-1=Pipeline!$I16+1,RampV2-RampV1,IF(2-VerifLag-1=Pipeline!$I16+2,1-RampV2,0)))) -> 0 | I15: =$C15*$E15*(TrancheA*IF(3-VerifLag=Pipeline!$I16,RampV1,IF(3-VerifLag=Pipeline!$I16+1,RampV2-RampV1,IF(3-VerifLag=Pipeline!$I16+2,1-RampV2,0)))+(1-TrancheA)*IF(3-VerifLag-1=Pipeline!$I16,RampV1,IF(3-VerifLag-1=Pipeline!$I16+1,RampV2-RampV1,IF(3-VerifLag-1=Pipeline!$I16+2,1-RampV2,0)))) -> 0 | J15: =$C15*$E15*(TrancheA*IF(4-VerifLag=Pipeline!$I16,RampV1,IF(4-VerifLag=Pipeline!$I16+1,RampV2-RampV1,IF(4-VerifLag=Pipeline!$I16+2,1-RampV2,0)))+(1-TrancheA)*IF(4-VerifLag-1=Pipeline!$I16,RampV1,IF(4-VerifLag-1=Pipeline!$I16+1,RampV2-RampV1,IF(4-VerifLag-1=Pipeline!$I16+2,1-RampV2,0)))) -> 0 | K15: =$C15*$E15*(TrancheA*IF(5-VerifLag=Pipeline!$I16,RampV1,IF(5-VerifLag=Pipeline!$I16+1,RampV2-RampV1,IF(5-VerifLag=Pipeline!$I16+2,1-RampV2,0)))+(1-TrancheA)*IF(5-VerifLag-1=Pipeline!$I16,RampV1,IF(5-VerifLag-1=Pipeline!$I16+1,RampV2-RampV1,IF(5-VerifLag-1=Pipeline!$I16+2,1-RampV2,0)))) -> 0 | L15: =$C15*$E15*(TrancheA*IF(6-VerifLag=Pipeline!$I16,RampV1,IF(6-VerifLag=Pipeline!$I16+1,RampV2-RampV1,IF(6-VerifLag=Pipeline!$I16+2,1-RampV2,0)))+(1-TrancheA)*IF(6-VerifLag-1=Pipeline!$I16,RampV1,IF(6-VerifLag-1=Pipeline!$I16+1,RampV2-RampV1,IF(6-VerifLag-1=Pipeline!$I16+2,1-RampV2,0)))) -> 0 | M15: =$C15*$E15*(TrancheA*IF(7-VerifLag=Pipeline!$I16,RampV1,IF(7-VerifLag=Pipeline!$I16+1,RampV2-RampV1,IF(7-VerifLag=Pipeline!$I16+2,1-RampV2,0)))+(1-TrancheA)*IF(7-VerifLag-1=Pipeline!$I16,RampV1,IF(7-VerifLag-1=Pipeline!$I16+1,RampV2-RampV1,IF(7-VerifLag-1=Pipeline!$I16+2,1-RampV2,0)))) -> 0 | N15: =$C15*$E15*(TrancheA*IF(8-VerifLag=Pipeline!$I16,RampV1,IF(8-VerifLag=Pipeline!$I16+1,RampV2-RampV1,IF(8-VerifLag=Pipeline!$I16+2,1-RampV2,0)))+(1-TrancheA)*IF(8-VerifLag-1=Pipeline!$I16,RampV1,IF(8-VerifLag-1=Pipeline!$I16+1,RampV2-RampV1,IF(8-VerifLag-1=Pipeline!$I16+2,1-RampV2,0)))) -> 0 | O15: =$C15*$E15*(TrancheA*IF(9-VerifLag=Pipeline!$I16,RampV1,IF(9-VerifLag=Pipeline!$I16+1,RampV2-RampV1,IF(9-VerifLag=Pipeline!$I16+2,1-RampV2,0)))+(1-TrancheA)*IF(9-VerifLag-1=Pipeline!$I16,RampV1,IF(9-VerifLag-1=Pipeline!$I16+1,RampV2-RampV1,IF(9-VerifLag-1=Pipeline!$I16+2,1-RampV2,0)))) -> 0 | P15: =$C15*$E15*(TrancheA*IF(10-VerifLag=Pipeline!$I16,RampV1,IF(10-VerifLag=Pipeline!$I16+1,RampV2-RampV1,IF(10-VerifLag=Pipeline!$I16+2,1-RampV2,0)))+(1-TrancheA)*IF(10-VerifLag-1=Pipeline!$I16,RampV1,IF(10-VerifLag-1=Pipeline!$I16+1,RampV2-RampV1,IF(10-VerifLag-1=Pipeline!$I16+2,1-RampV2,0)))) -> 0 | Q15: =SUM(G15:P15) -> 0
A16: 11 | B16: ='Eligibility & Scoring'!$B17 -> Project K - Peri-urban extension | C16: ='Eligibility & Scoring'!$AK17*'Eligibility & Scoring'!$U17 -> 124750.67 | D16: ='Eligibility & Scoring'!$AK17-C16 -> 257749.33 | E16: =IF(C16+D16=0,0,IFERROR(INDEX('Fund Parameters'!$B$74:$B$78,Pipeline!$H17),1)) -> 0.95 | F16: =C16*E16 -> 118513.14 | G16: =$C16*$E16*(TrancheA*IF(1-VerifLag=Pipeline!$I17,RampV1,IF(1-VerifLag=Pipeline!$I17+1,RampV2-RampV1,IF(1-VerifLag=Pipeline!$I17+2,1-RampV2,0)))+(1-TrancheA)*IF(1-VerifLag-1=Pipeline!$I17,RampV1,IF(1-VerifLag-1=Pipeline!$I17+1,RampV2-RampV1,IF(1-VerifLag-1=Pipeline!$I17+2,1-RampV2,0)))) -> 49775.519 | H16: =$C16*$E16*(TrancheA*IF(2-VerifLag=Pipeline!$I17,RampV1,IF(2-VerifLag=Pipeline!$I17+1,RampV2-RampV1,IF(2-VerifLag=Pipeline!$I17+2,1-RampV2,0)))+(1-TrancheA)*IF(2-VerifLag-1=Pipeline!$I17,RampV1,IF(2-VerifLag-1=Pipeline!$I17+1,RampV2-RampV1,IF(2-VerifLag-1=Pipeline!$I17+2,1-RampV2,0)))) -> 46220.125 | I16: =$C16*$E16*(TrancheA*IF(3-VerifLag=Pipeline!$I17,RampV1,IF(3-VerifLag=Pipeline!$I17+1,RampV2-RampV1,IF(3-VerifLag=Pipeline!$I17+2,1-RampV2,0)))+(1-TrancheA)*IF(3-VerifLag-1=Pipeline!$I17,RampV1,IF(3-VerifLag-1=Pipeline!$I17+1,RampV2-RampV1,IF(3-VerifLag-1=Pipeline!$I17+2,1-RampV2,0)))) -> 18962.102 | J16: =$C16*$E16*(TrancheA*IF(4-VerifLag=Pipeline!$I17,RampV1,IF(4-VerifLag=Pipeline!$I17+1,RampV2-RampV1,IF(4-VerifLag=Pipeline!$I17+2,1-RampV2,0)))+(1-TrancheA)*IF(4-VerifLag-1=Pipeline!$I17,RampV1,IF(4-VerifLag-1=Pipeline!$I17+1,RampV2-RampV1,IF(4-VerifLag-1=Pipeline!$I17+2,1-RampV2,0)))) -> 3555.3942 | K16: =$C16*$E16*(TrancheA*IF(5-VerifLag=Pipeline!$I17,RampV1,IF(5-VerifLag=Pipeline!$I17+1,RampV2-RampV1,IF(5-VerifLag=Pipeline!$I17+2,1-RampV2,0)))+(1-TrancheA)*IF(5-VerifLag-1=Pipeline!$I17,RampV1,IF(5-VerifLag-1=Pipeline!$I17+1,RampV2-RampV1,IF(5-VerifLag-1=Pipeline!$I17+2,1-RampV2,0)))) -> 0 | L16: =$C16*$E16*(TrancheA*IF(6-VerifLag=Pipeline!$I17,RampV1,IF(6-VerifLag=Pipeline!$I17+1,RampV2-RampV1,IF(6-VerifLag=Pipeline!$I17+2,1-RampV2,0)))+(1-TrancheA)*IF(6-VerifLag-1=Pipeline!$I17,RampV1,IF(6-VerifLag-1=Pipeline!$I17+1,RampV2-RampV1,IF(6-VerifLag-1=Pipeline!$I17+2,1-RampV2,0)))) -> 0 | M16: =$C16*$E16*(TrancheA*IF(7-VerifLag=Pipeline!$I17,RampV1,IF(7-VerifLag=Pipeline!$I17+1,RampV2-RampV1,IF(7-VerifLag=Pipeline!$I17+2,1-RampV2,0)))+(1-TrancheA)*IF(7-VerifLag-1=Pipeline!$I17,RampV1,IF(7-VerifLag-1=Pipeline!$I17+1,RampV2-RampV1,IF(7-VerifLag-1=Pipeline!$I17+2,1-RampV2,0)))) -> 0 | N16: =$C16*$E16*(TrancheA*IF(8-VerifLag=Pipeline!$I17,RampV1,IF(8-VerifLag=Pipeline!$I17+1,RampV2-RampV1,IF(8-VerifLag=Pipeline!$I17+2,1-RampV2,0)))+(1-TrancheA)*IF(8-VerifLag-1=Pipeline!$I17,RampV1,IF(8-VerifLag-1=Pipeline!$I17+1,RampV2-RampV1,IF(8-VerifLag-1=Pipeline!$I17+2,1-RampV2,0)))) -> 0 | O16: =$C16*$E16*(TrancheA*IF(9-VerifLag=Pipeline!$I17,RampV1,IF(9-VerifLag=Pipeline!$I17+1,RampV2-RampV1,IF(9-VerifLag=Pipeline!$I17+2,1-RampV2,0)))+(1-TrancheA)*IF(9-VerifLag-1=Pipeline!$I17,RampV1,IF(9-VerifLag-1=Pipeline!$I17+1,RampV2-RampV1,IF(9-VerifLag-1=Pipeline!$I17+2,1-RampV2,0)))) -> 0 | P16: =$C16*$E16*(TrancheA*IF(10-VerifLag=Pipeline!$I17,RampV1,IF(10-VerifLag=Pipeline!$I17+1,RampV2-RampV1,IF(10-VerifLag=Pipeline!$I17+2,1-RampV2,0)))+(1-TrancheA)*IF(10-VerifLag-1=Pipeline!$I17,RampV1,IF(10-VerifLag-1=Pipeline!$I17+1,RampV2-RampV1,IF(10-VerifLag-1=Pipeline!$I17+2,1-RampV2,0)))) -> 0 | Q16: =SUM(G16:P16) -> 118513.14
A17: 12 | B17: ='Eligibility & Scoring'!$B18 -> Project L - Mining belt | C17: ='Eligibility & Scoring'!$AK18*'Eligibility & Scoring'!$U18 -> 111562.5 | D17: ='Eligibility & Scoring'!$AK18-C17 -> 270937.5 | E17: =IF(C17+D17=0,0,IFERROR(INDEX('Fund Parameters'!$B$74:$B$78,Pipeline!$H18),1)) -> 0.9 | F17: =C17*E17 -> 100406.25 | G17: =$C17*$E17*(TrancheA*IF(1-VerifLag=Pipeline!$I18,RampV1,IF(1-VerifLag=Pipeline!$I18+1,RampV2-RampV1,IF(1-VerifLag=Pipeline!$I18+2,1-RampV2,0)))+(1-TrancheA)*IF(1-VerifLag-1=Pipeline!$I18,RampV1,IF(1-VerifLag-1=Pipeline!$I18+1,RampV2-RampV1,IF(1-VerifLag-1=Pipeline!$I18+2,1-RampV2,0)))) -> 0 | H17: =$C17*$E17*(TrancheA*IF(2-VerifLag=Pipeline!$I18,RampV1,IF(2-VerifLag=Pipeline!$I18+1,RampV2-RampV1,IF(2-VerifLag=Pipeline!$I18+2,1-RampV2,0)))+(1-TrancheA)*IF(2-VerifLag-1=Pipeline!$I18,RampV1,IF(2-VerifLag-1=Pipeline!$I18+1,RampV2-RampV1,IF(2-VerifLag-1=Pipeline!$I18+2,1-RampV2,0)))) -> 42170.625 | I17: =$C17*$E17*(TrancheA*IF(3-VerifLag=Pipeline!$I18,RampV1,IF(3-VerifLag=Pipeline!$I18+1,RampV2-RampV1,IF(3-VerifLag=Pipeline!$I18+2,1-RampV2,0)))+(1-TrancheA)*IF(3-VerifLag-1=Pipeline!$I18,RampV1,IF(3-VerifLag-1=Pipeline!$I18+1,RampV2-RampV1,IF(3-VerifLag-1=Pipeline!$I18+2,1-RampV2,0)))) -> 39158.438 | J17: =$C17*$E17*(TrancheA*IF(4-VerifLag=Pipeline!$I18,RampV1,IF(4-VerifLag=Pipeline!$I18+1,RampV2-RampV1,IF(4-VerifLag=Pipeline!$I18+2,1-RampV2,0)))+(1-TrancheA)*IF(4-VerifLag-1=Pipeline!$I18,RampV1,IF(4-VerifLag-1=Pipeline!$I18+1,RampV2-RampV1,IF(4-VerifLag-1=Pipeline!$I18+2,1-RampV2,0)))) -> 16065 | K17: =$C17*$E17*(TrancheA*IF(5-VerifLag=Pipeline!$I18,RampV1,IF(5-VerifLag=Pipeline!$I18+1,RampV2-RampV1,IF(5-VerifLag=Pipeline!$I18+2,1-RampV2,0)))+(1-TrancheA)*IF(5-VerifLag-1=Pipeline!$I18,RampV1,IF(5-VerifLag-1=Pipeline!$I18+1,RampV2-RampV1,IF(5-VerifLag-1=Pipeline!$I18+2,1-RampV2,0)))) -> 3012.1875 | L17: =$C17*$E17*(TrancheA*IF(6-VerifLag=Pipeline!$I18,RampV1,IF(6-VerifLag=Pipeline!$I18+1,RampV2-RampV1,IF(6-VerifLag=Pipeline!$I18+2,1-RampV2,0)))+(1-TrancheA)*IF(6-VerifLag-1=Pipeline!$I18,RampV1,IF(6-VerifLag-1=Pipeline!$I18+1,RampV2-RampV1,IF(6-VerifLag-1=Pipeline!$I18+2,1-RampV2,0)))) -> 0 | M17: =$C17*$E17*(TrancheA*IF(7-VerifLag=Pipeline!$I18,RampV1,IF(7-VerifLag=Pipeline!$I18+1,RampV2-RampV1,IF(7-VerifLag=Pipeline!$I18+2,1-RampV2,0)))+(1-TrancheA)*IF(7-VerifLag-1=Pipeline!$I18,RampV1,IF(7-VerifLag-1=Pipeline!$I18+1,RampV2-RampV1,IF(7-VerifLag-1=Pipeline!$I18+2,1-RampV2,0)))) -> 0 | N17: =$C17*$E17*(TrancheA*IF(8-VerifLag=Pipeline!$I18,RampV1,IF(8-VerifLag=Pipeline!$I18+1,RampV2-RampV1,IF(8-VerifLag=Pipeline!$I18+2,1-RampV2,0)))+(1-TrancheA)*IF(8-VerifLag-1=Pipeline!$I18,RampV1,IF(8-VerifLag-1=Pipeline!$I18+1,RampV2-RampV1,IF(8-VerifLag-1=Pipeline!$I18+2,1-RampV2,0)))) -> 0 | O17: =$C17*$E17*(TrancheA*IF(9-VerifLag=Pipeline!$I18,RampV1,IF(9-VerifLag=Pipeline!$I18+1,RampV2-RampV1,IF(9-VerifLag=Pipeline!$I18+2,1-RampV2,0)))+(1-TrancheA)*IF(9-VerifLag-1=Pipeline!$I18,RampV1,IF(9-VerifLag-1=Pipeline!$I18+1,RampV2-RampV1,IF(9-VerifLag-1=Pipeline!$I18+2,1-RampV2,0)))) -> 0 | P17: =$C17*$E17*(TrancheA*IF(10-VerifLag=Pipeline!$I18,RampV1,IF(10-VerifLag=Pipeline!$I18+1,RampV2-RampV1,IF(10-VerifLag=Pipeline!$I18+2,1-RampV2,0)))+(1-TrancheA)*IF(10-VerifLag-1=Pipeline!$I18,RampV1,IF(10-VerifLag-1=Pipeline!$I18+1,RampV2-RampV1,IF(10-VerifLag-1=Pipeline!$I18+2,1-RampV2,0)))) -> 0 | Q17: =SUM(G17:P17) -> 100406.25
... A30: 25 | B30: ='Eligibility & Scoring'!$B31 | C30: ='Eligibility & Scoring'!$AK31*'Eligibility & Scoring'!$U31 -> 0 | D30: ='Eligibility & Scoring'!$AK31-C30 -> 0 | E30: =IF(C30+D30=0,0,IFERROR(INDEX('Fund Parameters'!$B$74:$B$78,Pipeline!$H31),1)) -> 0 | F30: =C30*E30 -> 0 | G30: =$C30*$E30*(TrancheA*IF(1-VerifLag=Pipeline!$I31,RampV1,IF(1-VerifLag=Pipeline!$I31+1,RampV2-RampV1,IF(1-VerifLag=Pipeline!$I31+2,1-RampV2,0)))+(1-TrancheA)*IF(1-VerifLag-1=Pipeline!$I31,RampV1,IF(1-VerifLag-1=Pipeline!$I31+1,RampV2-RampV1,IF(1-VerifLag-1=Pipeline!$I31+2,1-RampV2,0)))) -> 0 | H30: =$C30*$E30*(TrancheA*IF(2-VerifLag=Pipeline!$I31,RampV1,IF(2-VerifLag=Pipeline!$I31+1,RampV2-RampV1,IF(2-VerifLag=Pipeline!$I31+2,1-RampV2,0)))+(1-TrancheA)*IF(2-VerifLag-1=Pipeline!$I31,RampV1,IF(2-VerifLag-1=Pipeline!$I31+1,RampV2-RampV1,IF(2-VerifLag-1=Pipeline!$I31+2,1-RampV2,0)))) -> 0 | I30: =$C30*$E30*(TrancheA*IF(3-VerifLag=Pipeline!$I31,RampV1,IF(3-VerifLag=Pipeline!$I31+1,RampV2-RampV1,IF(3-VerifLag=Pipeline!$I31+2,1-RampV2,0)))+(1-TrancheA)*IF(3-VerifLag-1=Pipeline!$I31,RampV1,IF(3-VerifLag-1=Pipeline!$I31+1,RampV2-RampV1,IF(3-VerifLag-1=Pipeline!$I31+2,1-RampV2,0)))) -> 0 | J30: =$C30*$E30*(TrancheA*IF(4-VerifLag=Pipeline!$I31,RampV1,IF(4-VerifLag=Pipeline!$I31+1,RampV2-RampV1,IF(4-VerifLag=Pipeline!$I31+2,1-RampV2,0)))+(1-TrancheA)*IF(4-VerifLag-1=Pipeline!$I31,RampV1,IF(4-VerifLag-1=Pipeline!$I31+1,RampV2-RampV1,IF(4-VerifLag-1=Pipeline!$I31+2,1-RampV2,0)))) -> 0 | K30: =$C30*$E30*(TrancheA*IF(5-VerifLag=Pipeline!$I31,RampV1,IF(5-VerifLag=Pipeline!$I31+1,RampV2-RampV1,IF(5-VerifLag=Pipeline!$I31+2,1-RampV2,0)))+(1-TrancheA)*IF(5-VerifLag-1=Pipeline!$I31,RampV1,IF(5-VerifLag-1=Pipeline!$I31+1,RampV2-RampV1,IF(5-VerifLag-1=Pipeline!$I31+2,1-RampV2,0)))) -> 0 | L30: =$C30*$E30*(TrancheA*IF(6-VerifLag=Pipeline!$I31,RampV1,IF(6-VerifLag=Pipeline!$I31+1,RampV2-RampV1,IF(6-VerifLag=Pipeline!$I31+2,1-RampV2,0)))+(1-TrancheA)*IF(6-VerifLag-1=Pipeline!$I31,RampV1,IF(6-VerifLag-1=Pipeline!$I31+1,RampV2-RampV1,IF(6-VerifLag-1=Pipeline!$I31+2,1-RampV2,0)))) -> 0 | M30: =$C30*$E30*(TrancheA*IF(7-VerifLag=Pipeline!$I31,RampV1,IF(7-VerifLag=Pipeline!$I31+1,RampV2-RampV1,IF(7-VerifLag=Pipeline!$I31+2,1-RampV2,0)))+(1-TrancheA)*IF(7-VerifLag-1=Pipeline!$I31,RampV1,IF(7-VerifLag-1=Pipeline!$I31+1,RampV2-RampV1,IF(7-VerifLag-1=Pipeline!$I31+2,1-RampV2,0)))) -> 0 | N30: =$C30*$E30*(TrancheA*IF(8-VerifLag=Pipeline!$I31,RampV1,IF(8-VerifLag=Pipeline!$I31+1,RampV2-RampV1,IF(8-VerifLag=Pipeline!$I31+2,1-RampV2,0)))+(1-TrancheA)*IF(8-VerifLag-1=Pipeline!$I31,RampV1,IF(8-VerifLag-1=Pipeline!$I31+1,RampV2-RampV1,IF(8-VerifLag-1=Pipeline!$I31+2,1-RampV2,0)))) -> 0 | O30: =$C30*$E30*(TrancheA*IF(9-VerifLag=Pipeline!$I31,RampV1,IF(9-VerifLag=Pipeline!$I31+1,RampV2-RampV1,IF(9-VerifLag=Pipeline!$I31+2,1-RampV2,0)))+(1-TrancheA)*IF(9-VerifLag-1=Pipeline!$I31,RampV1,IF(9-VerifLag-1=Pipeline!$I31+1,RampV2-RampV1,IF(9-VerifLag-1=Pipeline!$I31+2,1-RampV2,0)))) -> 0 | P30: =$C30*$E30*(TrancheA*IF(10-VerifLag=Pipeline!$I31,RampV1,IF(10-VerifLag=Pipeline!$I31+1,RampV2-RampV1,IF(10-VerifLag=Pipeline!$I31+2,1-RampV2,0)))+(1-TrancheA)*IF(10-VerifLag-1=Pipeline!$I31,RampV1,IF(10-VerifLag-1=Pipeline!$I31+1,RampV2-RampV1,IF(10-VerifLag-1=Pipeline!$I31+2,1-RampV2,0)))) -> 0 | Q30: =SUM(G30:P30) -> 0
B31: TOTAL | C31: =SUM(C6:C30) -> 753310.82 | D31: =SUM(D6:D30) -> 1796689.2 | F31: =SUM(F6:F30) -> 708694.13 | G31: =SUM(G6:G30) -> 142362.06 | H31: =SUM(H6:H30) -> 287482.81 | I31: =SUM(I6:I30) -> 198430.53 | J31: =SUM(J6:J30) -> 69326.612 | K31: =SUM(K6:K30) -> 11092.105 | L31: =SUM(L6:L30) -> 0 | M31: =SUM(M6:M30) -> 0 | ... Q31: =SUM(Q6:Q30) -> 708694.13
A33: GRANT DISBURSEMENTS
A34: # | B34: Project | C34: Allocated RBF | D34: Allocated grant | E34: Expected delivery | F34: Expected total | G34: =FundStart-1+1 -> 2027 | H34: =FundStart-1+2 -> 2028 | I34: =FundStart-1+3 -> 2029 | J34: =FundStart-1+4 -> 2030 | K34: =FundStart-1+5 -> 2031 | L34: =FundStart-1+6 -> 2032 | M34: =FundStart-1+7 -> 2033 | N34: =FundStart-1+8 -> 2034 | O34: =FundStart-1+9 -> 2035 | P34: =FundStart-1+10 -> 2036 | Q34: Total
A35: 1 | B35: ='Eligibility & Scoring'!$B7 -> Project A - Lake village cluster | C35: ='Eligibility & Scoring'!$AK7*'Eligibility & Scoring'!$U7 -> 110778.69 | D35: ='Eligibility & Scoring'!$AK7-C35 -> 271721.31 | E35: =IF(C35+D35=0,0,IFERROR(INDEX('Fund Parameters'!$B$74:$B$78,Pipeline!$H7),1)) -> 0.95 | F35: =D35 -> 271721.31 | G35: =IF(1=Pipeline!$I7,$D35,0) -> 271721.31 | H35: =IF(2=Pipeline!$I7,$D35,0) -> 0 | I35: =IF(3=Pipeline!$I7,$D35,0) -> 0 | J35: =IF(4=Pipeline!$I7,$D35,0) -> 0 | K35: =IF(5=Pipeline!$I7,$D35,0) -> 0 | L35: =IF(6=Pipeline!$I7,$D35,0) -> 0 | M35: =IF(7=Pipeline!$I7,$D35,0) -> 0 | N35: =IF(8=Pipeline!$I7,$D35,0) -> 0 | O35: =IF(9=Pipeline!$I7,$D35,0) -> 0 | P35: =IF(10=Pipeline!$I7,$D35,0) -> 0 | Q35: =SUM(G35:P35) -> 271721.31
A36: 2 | B36: ='Eligibility & Scoring'!$B8 -> Project B - River towns | C36: ='Eligibility & Scoring'!$AK8*'Eligibility & Scoring'!$U8 -> 32871.094 | D36: ='Eligibility & Scoring'!$AK8-C36 -> 94628.906 | E36: =IF(C36+D36=0,0,IFERROR(INDEX('Fund Parameters'!$B$74:$B$78,Pipeline!$H8),1)) -> 0.9 | F36: =D36 -> 94628.906 | G36: =IF(1=Pipeline!$I8,$D36,0) -> 0 | H36: =IF(2=Pipeline!$I8,$D36,0) -> 94628.906 | I36: =IF(3=Pipeline!$I8,$D36,0) -> 0 | J36: =IF(4=Pipeline!$I8,$D36,0) -> 0 | K36: =IF(5=Pipeline!$I8,$D36,0) -> 0 | L36: =IF(6=Pipeline!$I8,$D36,0) -> 0 | M36: =IF(7=Pipeline!$I8,$D36,0) -> 0 | N36: =IF(8=Pipeline!$I8,$D36,0) -> 0 | O36: =IF(9=Pipeline!$I8,$D36,0) -> 0 | P36: =IF(10=Pipeline!$I8,$D36,0) -> 0 | Q36: =SUM(G36:P36) -> 94628.906
A37: 3 | B37: ='Eligibility & Scoring'!$B9 -> Project C - Northern corridor | C37: ='Eligibility & Scoring'!$AK9*'Eligibility & Scoring'!$U9 -> 115204.4 | D37: ='Eligibility & Scoring'!$AK9-C37 -> 267295.6 | E37: =IF(C37+D37=0,0,IFERROR(INDEX('Fund Parameters'!$B$74:$B$78,Pipeline!$H9),1)) -> 1 | F37: =D37 -> 267295.6 | G37: =IF(1=Pipeline!$I9,$D37,0) -> 267295.6 | H37: =IF(2=Pipeline!$I9,$D37,0) -> 0 | I37: =IF(3=Pipeline!$I9,$D37,0) -> 0 | J37: =IF(4=Pipeline!$I9,$D37,0) -> 0 | K37: =IF(5=Pipeline!$I9,$D37,0) -> 0 | L37: =IF(6=Pipeline!$I9,$D37,0) -> 0 | M37: =IF(7=Pipeline!$I9,$D37,0) -> 0 | N37: =IF(8=Pipeline!$I9,$D37,0) -> 0 | O37: =IF(9=Pipeline!$I9,$D37,0) -> 0 | P37: =IF(10=Pipeline!$I9,$D37,0) -> 0 | Q37: =SUM(G37:P37) -> 267295.6
A38: 4 | B38: ='Eligibility & Scoring'!$B10 -> Project D - Island grids | C38: ='Eligibility & Scoring'!$AK10*'Eligibility & Scoring'!$U10 -> 0 | D38: ='Eligibility & Scoring'!$AK10-C38 -> 0 | E38: =IF(C38+D38=0,0,IFERROR(INDEX('Fund Parameters'!$B$74:$B$78,Pipeline!$H10),1)) -> 0 | F38: =D38 -> 0 | G38: =IF(1=Pipeline!$I10,$D38,0) -> 0 | H38: =IF(2=Pipeline!$I10,$D38,0) -> 0 | I38: =IF(3=Pipeline!$I10,$D38,0) -> 0 | J38: =IF(4=Pipeline!$I10,$D38,0) -> 0 | K38: =IF(5=Pipeline!$I10,$D38,0) -> 0 | L38: =IF(6=Pipeline!$I10,$D38,0) -> 0 | M38: =IF(7=Pipeline!$I10,$D38,0) -> 0 | N38: =IF(8=Pipeline!$I10,$D38,0) -> 0 | O38: =IF(9=Pipeline!$I10,$D38,0) -> 0 | P38: =IF(10=Pipeline!$I10,$D38,0) -> 0 | Q38: =SUM(G38:P38) -> 0
A39: 5 | B39: ='Eligibility & Scoring'!$B11 -> Project E - Highland villages | C39: ='Eligibility & Scoring'!$AK11*'Eligibility & Scoring'!$U11 -> 0 | D39: ='Eligibility & Scoring'!$AK11-C39 -> 0 | E39: =IF(C39+D39=0,0,IFERROR(INDEX('Fund Parameters'!$B$74:$B$78,Pipeline!$H11),1)) -> 0 | F39: =D39 -> 0 | G39: =IF(1=Pipeline!$I11,$D39,0) -> 0 | H39: =IF(2=Pipeline!$I11,$D39,0) -> 0 | I39: =IF(3=Pipeline!$I11,$D39,0) -> 0 | J39: =IF(4=Pipeline!$I11,$D39,0) -> 0 | K39: =IF(5=Pipeline!$I11,$D39,0) -> 0 | L39: =IF(6=Pipeline!$I11,$D39,0) -> 0 | M39: =IF(7=Pipeline!$I11,$D39,0) -> 0 | N39: =IF(8=Pipeline!$I11,$D39,0) -> 0 | O39: =IF(9=Pipeline!$I11,$D39,0) -> 0 | P39: =IF(10=Pipeline!$I11,$D39,0) -> 0 | Q39: =SUM(G39:P39) -> 0
A40: 6 | B40: ='Eligibility & Scoring'!$B12 -> Project F - Market towns | C40: ='Eligibility & Scoring'!$AK12*'Eligibility & Scoring'!$U12 -> 0 | D40: ='Eligibility & Scoring'!$AK12-C40 -> 0 | E40: =IF(C40+D40=0,0,IFERROR(INDEX('Fund Parameters'!$B$74:$B$78,Pipeline!$H12),1)) -> 0 | F40: =D40 -> 0 | G40: =IF(1=Pipeline!$I12,$D40,0) -> 0 | H40: =IF(2=Pipeline!$I12,$D40,0) -> 0 | I40: =IF(3=Pipeline!$I12,$D40,0) -> 0 | J40: =IF(4=Pipeline!$I12,$D40,0) -> 0 | K40: =IF(5=Pipeline!$I12,$D40,0) -> 0 | L40: =IF(6=Pipeline!$I12,$D40,0) -> 0 | M40: =IF(7=Pipeline!$I12,$D40,0) -> 0 | N40: =IF(8=Pipeline!$I12,$D40,0) -> 0 | O40: =IF(9=Pipeline!$I12,$D40,0) -> 0 | P40: =IF(10=Pipeline!$I12,$D40,0) -> 0 | Q40: =SUM(G40:P40) -> 0
A41: 7 | B41: ='Eligibility & Scoring'!$B13 -> Project G - Remote valley | C41: ='Eligibility & Scoring'!$AK13*'Eligibility & Scoring'!$U13 -> 0 | D41: ='Eligibility & Scoring'!$AK13-C41 -> 0 | E41: =IF(C41+D41=0,0,IFERROR(INDEX('Fund Parameters'!$B$74:$B$78,Pipeline!$H13),1)) -> 0 | F41: =D41 -> 0 | G41: =IF(1=Pipeline!$I13,$D41,0) -> 0 | H41: =IF(2=Pipeline!$I13,$D41,0) -> 0 | I41: =IF(3=Pipeline!$I13,$D41,0) -> 0 | J41: =IF(4=Pipeline!$I13,$D41,0) -> 0 | K41: =IF(5=Pipeline!$I13,$D41,0) -> 0 | L41: =IF(6=Pipeline!$I13,$D41,0) -> 0 | M41: =IF(7=Pipeline!$I13,$D41,0) -> 0 | N41: =IF(8=Pipeline!$I13,$D41,0) -> 0 | O41: =IF(9=Pipeline!$I13,$D41,0) -> 0 | P41: =IF(10=Pipeline!$I13,$D41,0) -> 0 | Q41: =SUM(G41:P41) -> 0
A42: 8 | B42: ='Eligibility & Scoring'!$B14 -> Project H - Agro-processing hub | C42: ='Eligibility & Scoring'!$AK14*'Eligibility & Scoring'!$U14 -> 112181.98 | D42: ='Eligibility & Scoring'!$AK14-C42 -> 270318.02 | E42: =IF(C42+D42=0,0,IFERROR(INDEX('Fund Parameters'!$B$74:$B$78,Pipeline!$H14),1)) -> 0.95 | F42: =D42 -> 270318.02 | G42: =IF(1=Pipeline!$I14,$D42,0) -> 0 | H42: =IF(2=Pipeline!$I14,$D42,0) -> 270318.02 | I42: =IF(3=Pipeline!$I14,$D42,0) -> 0 | J42: =IF(4=Pipeline!$I14,$D42,0) -> 0 | K42: =IF(5=Pipeline!$I14,$D42,0) -> 0 | L42: =IF(6=Pipeline!$I14,$D42,0) -> 0 | M42: =IF(7=Pipeline!$I14,$D42,0) -> 0 | N42: =IF(8=Pipeline!$I14,$D42,0) -> 0 | O42: =IF(9=Pipeline!$I14,$D42,0) -> 0 | P42: =IF(10=Pipeline!$I14,$D42,0) -> 0 | Q42: =SUM(G42:P42) -> 270318.02
A43: 9 | B43: ='Eligibility & Scoring'!$B15 -> Project I - Fishing communities | C43: ='Eligibility & Scoring'!$AK15*'Eligibility & Scoring'!$U15 -> 109793.86 | D43: ='Eligibility & Scoring'!$AK15-C43 -> 272706.14 | E43: =IF(C43+D43=0,0,IFERROR(INDEX('Fund Parameters'!$B$74:$B$78,Pipeline!$H15),1)) -> 0.9 | F43: =D43 -> 272706.14 | G43: =IF(1=Pipeline!$I15,$D43,0) -> 0 | H43: =IF(2=Pipeline!$I15,$D43,0) -> 272706.14 | I43: =IF(3=Pipeline!$I15,$D43,0) -> 0 | J43: =IF(4=Pipeline!$I15,$D43,0) -> 0 | K43: =IF(5=Pipeline!$I15,$D43,0) -> 0 | L43: =IF(6=Pipeline!$I15,$D43,0) -> 0 | M43: =IF(7=Pipeline!$I15,$D43,0) -> 0 | N43: =IF(8=Pipeline!$I15,$D43,0) -> 0 | O43: =IF(9=Pipeline!$I15,$D43,0) -> 0 | P43: =IF(10=Pipeline!$I15,$D43,0) -> 0 | Q43: =SUM(G43:P43) -> 272706.14
A44: 10 | B44: ='Eligibility & Scoring'!$B16 -> Project J - Health and schools first | C44: ='Eligibility & Scoring'!$AK16*'Eligibility & Scoring'!$U16 -> 0 | D44: ='Eligibility & Scoring'!$AK16-C44 -> 0 | E44: =IF(C44+D44=0,0,IFERROR(INDEX('Fund Parameters'!$B$74:$B$78,Pipeline!$H16),1)) -> 0 | F44: =D44 -> 0 | G44: =IF(1=Pipeline!$I16,$D44,0) -> 0 | H44: =IF(2=Pipeline!$I16,$D44,0) -> 0 | I44: =IF(3=Pipeline!$I16,$D44,0) -> 0 | J44: =IF(4=Pipeline!$I16,$D44,0) -> 0 | K44: =IF(5=Pipeline!$I16,$D44,0) -> 0 | L44: =IF(6=Pipeline!$I16,$D44,0) -> 0 | M44: =IF(7=Pipeline!$I16,$D44,0) -> 0 | N44: =IF(8=Pipeline!$I16,$D44,0) -> 0 | O44: =IF(9=Pipeline!$I16,$D44,0) -> 0 | P44: =IF(10=Pipeline!$I16,$D44,0) -> 0 | Q44: =SUM(G44:P44) -> 0
A45: 11 | B45: ='Eligibility & Scoring'!$B17 -> Project K - Peri-urban extension | C45: ='Eligibility & Scoring'!$AK17*'Eligibility & Scoring'!$U17 -> 124750.67 | D45: ='Eligibility & Scoring'!$AK17-C45 -> 257749.33 | E45: =IF(C45+D45=0,0,IFERROR(INDEX('Fund Parameters'!$B$74:$B$78,Pipeline!$H17),1)) -> 0.95 | F45: =D45 -> 257749.33 | G45: =IF(1=Pipeline!$I17,$D45,0) -> 257749.33 | H45: =IF(2=Pipeline!$I17,$D45,0) -> 0 | I45: =IF(3=Pipeline!$I17,$D45,0) -> 0 | J45: =IF(4=Pipeline!$I17,$D45,0) -> 0 | K45: =IF(5=Pipeline!$I17,$D45,0) -> 0 | L45: =IF(6=Pipeline!$I17,$D45,0) -> 0 | M45: =IF(7=Pipeline!$I17,$D45,0) -> 0 | N45: =IF(8=Pipeline!$I17,$D45,0) -> 0 | O45: =IF(9=Pipeline!$I17,$D45,0) -> 0 | P45: =IF(10=Pipeline!$I17,$D45,0) -> 0 | Q45: =SUM(G45:P45) -> 257749.33
A46: 12 | B46: ='Eligibility & Scoring'!$B18 -> Project L - Mining belt | C46: ='Eligibility & Scoring'!$AK18*'Eligibility & Scoring'!$U18 -> 111562.5 | D46: ='Eligibility & Scoring'!$AK18-C46 -> 270937.5 | E46: =IF(C46+D46=0,0,IFERROR(INDEX('Fund Parameters'!$B$74:$B$78,Pipeline!$H18),1)) -> 0.9 | F46: =D46 -> 270937.5 | G46: =IF(1=Pipeline!$I18,$D46,0) -> 0 | H46: =IF(2=Pipeline!$I18,$D46,0) -> 270937.5 | I46: =IF(3=Pipeline!$I18,$D46,0) -> 0 | J46: =IF(4=Pipeline!$I18,$D46,0) -> 0 | K46: =IF(5=Pipeline!$I18,$D46,0) -> 0 | L46: =IF(6=Pipeline!$I18,$D46,0) -> 0 | M46: =IF(7=Pipeline!$I18,$D46,0) -> 0 | N46: =IF(8=Pipeline!$I18,$D46,0) -> 0 | O46: =IF(9=Pipeline!$I18,$D46,0) -> 0 | P46: =IF(10=Pipeline!$I18,$D46,0) -> 0 | Q46: =SUM(G46:P46) -> 270937.5
... A59: 25 | B59: ='Eligibility & Scoring'!$B31 | C59: ='Eligibility & Scoring'!$AK31*'Eligibility & Scoring'!$U31 -> 0 | D59: ='Eligibility & Scoring'!$AK31-C59 -> 0 | E59: =IF(C59+D59=0,0,IFERROR(INDEX('Fund Parameters'!$B$74:$B$78,Pipeline!$H31),1)) -> 0 | F59: =D59 -> 0 | G59: =IF(1=Pipeline!$I31,$D59,0) -> 0 | H59: =IF(2=Pipeline!$I31,$D59,0) -> 0 | I59: =IF(3=Pipeline!$I31,$D59,0) -> 0 | J59: =IF(4=Pipeline!$I31,$D59,0) -> 0 | K59: =IF(5=Pipeline!$I31,$D59,0) -> 0 | L59: =IF(6=Pipeline!$I31,$D59,0) -> 0 | M59: =IF(7=Pipeline!$I31,$D59,0) -> 0 | N59: =IF(8=Pipeline!$I31,$D59,0) -> 0 | O59: =IF(9=Pipeline!$I31,$D59,0) -> 0 | P59: =IF(10=Pipeline!$I31,$D59,0) -> 0 | Q59: =SUM(G59:P59) -> 0
B60: TOTAL | C60: =SUM(C35:C59) -> 753310.82 | D60: =SUM(D35:D59) -> 1796689.2 | F60: =SUM(F35:F59) -> 1796689.2 | G60: =SUM(G35:G59) -> 796766.24 | H60: =SUM(H35:H59) -> 999922.94 | I60: =SUM(I35:I59) -> 0 | J60: =SUM(J35:J59) -> 0 | K60: =SUM(K35:K59) -> 0 | L60: =SUM(L35:L59) -> 0 | M60: =SUM(M35:M59) -> 0 | ... Q60: =SUM(Q35:Q59) -> 1796689.2
A62: TOTAL DISBURSEMENTS
A63: # | B63: Project | C63: Allocated RBF | D63: Allocated grant | E63: Expected delivery | F63: Expected total | G63: =FundStart-1+1 -> 2027 | H63: =FundStart-1+2 -> 2028 | I63: =FundStart-1+3 -> 2029 | J63: =FundStart-1+4 -> 2030 | K63: =FundStart-1+5 -> 2031 | L63: =FundStart-1+6 -> 2032 | M63: =FundStart-1+7 -> 2033 | N63: =FundStart-1+8 -> 2034 | O63: =FundStart-1+9 -> 2035 | P63: =FundStart-1+10 -> 2036 | Q63: Total
A64: 1 | B64: ='Eligibility & Scoring'!$B7 -> Project A - Lake village cluster | C64: ='Eligibility & Scoring'!$AK7*'Eligibility & Scoring'!$U7 -> 110778.69 | D64: ='Eligibility & Scoring'!$AK7-C64 -> 271721.31 | E64: =IF(C64+D64=0,0,IFERROR(INDEX('Fund Parameters'!$B$74:$B$78,Pipeline!$H7),1)) -> 0.95 | F64: =C64*E64+D64 -> 376961.07 | G64: =G6+G35 -> 315922.01 | H64: =H6+H35 -> 41043.504 | I64: =I6+I35 -> 16838.361 | J64: =J6+J35 -> 3157.1926 | K64: =K6+K35 -> 0 | L64: =L6+L35 -> 0 | M64: =M6+M35 -> 0 | N64: =N6+N35 -> 0 | ... P64: =P6+P35 -> 0 | Q64: =SUM(G64:P64) -> 376961.07
A65: 2 | B65: ='Eligibility & Scoring'!$B8 -> Project B - River towns | C65: ='Eligibility & Scoring'!$AK8*'Eligibility & Scoring'!$U8 -> 32871.094 | D65: ='Eligibility & Scoring'!$AK8-C65 -> 94628.906 | E65: =IF(C65+D65=0,0,IFERROR(INDEX('Fund Parameters'!$B$74:$B$78,Pipeline!$H8),1)) -> 0.9 | F65: =C65*E65+D65 -> 124212.89 | G65: =G7+G36 -> 0 | H65: =H7+H36 -> 107054.18 | I65: =I7+I36 -> 11537.754 | J65: =J7+J36 -> 4733.4375 | K65: =K7+K36 -> 887.51953 | L65: =L7+L36 -> 0 | M65: =M7+M36 -> 0 | N65: =N7+N36 -> 0 | ... P65: =P7+P36 -> 0 | Q65: =SUM(G65:P65) -> 124212.89
A66: 3 | B66: ='Eligibility & Scoring'!$B9 -> Project C - Northern corridor | C66: ='Eligibility & Scoring'!$AK9*'Eligibility & Scoring'!$U9 -> 115204.4 | D66: ='Eligibility & Scoring'!$AK9-C66 -> 267295.6 | E66: =IF(C66+D66=0,0,IFERROR(INDEX('Fund Parameters'!$B$74:$B$78,Pipeline!$H9),1)) -> 1 | F66: =C66*E66+D66 -> 382500 | G66: =G8+G37 -> 315681.45 | H66: =H8+H37 -> 44929.717 | I66: =I8+I37 -> 18432.704 | J66: =J8+J37 -> 3456.1321 | K66: =K8+K37 -> 0 | L66: =L8+L37 -> 0 | M66: =M8+M37 -> 0 | N66: =N8+N37 -> 0 | ... P66: =P8+P37 -> 0 | Q66: =SUM(G66:P66) -> 382500
A67: 4 | B67: ='Eligibility & Scoring'!$B10 -> Project D - Island grids | C67: ='Eligibility & Scoring'!$AK10*'Eligibility & Scoring'!$U10 -> 0 | D67: ='Eligibility & Scoring'!$AK10-C67 -> 0 | E67: =IF(C67+D67=0,0,IFERROR(INDEX('Fund Parameters'!$B$74:$B$78,Pipeline!$H10),1)) -> 0 | F67: =C67*E67+D67 -> 0 | G67: =G9+G38 -> 0 | H67: =H9+H38 -> 0 | I67: =I9+I38 -> 0 | J67: =J9+J38 -> 0 | K67: =K9+K38 -> 0 | L67: =L9+L38 -> 0 | M67: =M9+M38 -> 0 | N67: =N9+N38 -> 0 | ... P67: =P9+P38 -> 0 | Q67: =SUM(G67:P67) -> 0
A68: 5 | B68: ='Eligibility & Scoring'!$B11 -> Project E - Highland villages | C68: ='Eligibility & Scoring'!$AK11*'Eligibility & Scoring'!$U11 -> 0 | D68: ='Eligibility & Scoring'!$AK11-C68 -> 0 | E68: =IF(C68+D68=0,0,IFERROR(INDEX('Fund Parameters'!$B$74:$B$78,Pipeline!$H11),1)) -> 0 | F68: =C68*E68+D68 -> 0 | G68: =G10+G39 -> 0 | H68: =H10+H39 -> 0 | I68: =I10+I39 -> 0 | J68: =J10+J39 -> 0 | K68: =K10+K39 -> 0 | L68: =L10+L39 -> 0 | M68: =M10+M39 -> 0 | N68: =N10+N39 -> 0 | ... P68: =P10+P39 -> 0 | Q68: =SUM(G68:P68) -> 0
A69: 6 | B69: ='Eligibility & Scoring'!$B12 -> Project F - Market towns | C69: ='Eligibility & Scoring'!$AK12*'Eligibility & Scoring'!$U12 -> 0 | D69: ='Eligibility & Scoring'!$AK12-C69 -> 0 | E69: =IF(C69+D69=0,0,IFERROR(INDEX('Fund Parameters'!$B$74:$B$78,Pipeline!$H12),1)) -> 0 | F69: =C69*E69+D69 -> 0 | G69: =G11+G40 -> 0 | H69: =H11+H40 -> 0 | I69: =I11+I40 -> 0 | J69: =J11+J40 -> 0 | K69: =K11+K40 -> 0 | L69: =L11+L40 -> 0 | M69: =M11+M40 -> 0 | N69: =N11+N40 -> 0 | ... P69: =P11+P40 -> 0 | Q69: =SUM(G69:P69) -> 0
A70: 7 | B70: ='Eligibility & Scoring'!$B13 -> Project G - Remote valley | C70: ='Eligibility & Scoring'!$AK13*'Eligibility & Scoring'!$U13 -> 0 | D70: ='Eligibility & Scoring'!$AK13-C70 -> 0 | E70: =IF(C70+D70=0,0,IFERROR(INDEX('Fund Parameters'!$B$74:$B$78,Pipeline!$H13),1)) -> 0 | F70: =C70*E70+D70 -> 0 | G70: =G12+G41 -> 0 | H70: =H12+H41 -> 0 | I70: =I12+I41 -> 0 | J70: =J12+J41 -> 0 | K70: =K12+K41 -> 0 | L70: =L12+L41 -> 0 | M70: =M12+M41 -> 0 | N70: =N12+N41 -> 0 | ... P70: =P12+P41 -> 0 | Q70: =SUM(G70:P70) -> 0
A71: 8 | B71: ='Eligibility & Scoring'!$B14 -> Project H - Agro-processing hub | C71: ='Eligibility & Scoring'!$AK14*'Eligibility & Scoring'!$U14 -> 112181.98 | D71: ='Eligibility & Scoring'!$AK14-C71 -> 270318.02 | E71: =IF(C71+D71=0,0,IFERROR(INDEX('Fund Parameters'!$B$74:$B$78,Pipeline!$H14),1)) -> 0.95 | F71: =C71*E71+D71 -> 376890.9 | G71: =G13+G42 -> 0 | H71: =H13+H42 -> 315078.63 | I71: =I13+I42 -> 41563.423 | J71: =J13+J42 -> 17051.661 | K71: =K13+K42 -> 3197.1864 | L71: =L13+L42 -> 0 | M71: =M13+M42 -> 0 | N71: =N13+N42 -> 0 | ... P71: =P13+P42 -> 0 | Q71: =SUM(G71:P71) -> 376890.9
A72: 9 | B72: ='Eligibility & Scoring'!$B15 -> Project I - Fishing communities | C72: ='Eligibility & Scoring'!$AK15*'Eligibility & Scoring'!$U15 -> 109793.86 | D72: ='Eligibility & Scoring'!$AK15-C72 -> 272706.14 | E72: =IF(C72+D72=0,0,IFERROR(INDEX('Fund Parameters'!$B$74:$B$78,Pipeline!$H15),1)) -> 0.9 | F72: =C72*E72+D72 -> 371520.61 | G72: =G14+G43 -> 0 | H72: =H14+H43 -> 314208.22 | I72: =I14+I43 -> 38537.646 | J72: =J14+J43 -> 15810.316 | K72: =K14+K43 -> 2964.4343 | L72: =L14+L43 -> 0 | M72: =M14+M43 -> 0 | N72: =N14+N43 -> 0 | ... P72: =P14+P43 -> 0 | Q72: =SUM(G72:P72) -> 371520.61
A73: 10 | B73: ='Eligibility & Scoring'!$B16 -> Project J - Health and schools first | C73: ='Eligibility & Scoring'!$AK16*'Eligibility & Scoring'!$U16 -> 0 | D73: ='Eligibility & Scoring'!$AK16-C73 -> 0 | E73: =IF(C73+D73=0,0,IFERROR(INDEX('Fund Parameters'!$B$74:$B$78,Pipeline!$H16),1)) -> 0 | F73: =C73*E73+D73 -> 0 | G73: =G15+G44 -> 0 | H73: =H15+H44 -> 0 | I73: =I15+I44 -> 0 | J73: =J15+J44 -> 0 | K73: =K15+K44 -> 0 | L73: =L15+L44 -> 0 | M73: =M15+M44 -> 0 | N73: =N15+N44 -> 0 | ... P73: =P15+P44 -> 0 | Q73: =SUM(G73:P73) -> 0
A74: 11 | B74: ='Eligibility & Scoring'!$B17 -> Project K - Peri-urban extension | C74: ='Eligibility & Scoring'!$AK17*'Eligibility & Scoring'!$U17 -> 124750.67 | D74: ='Eligibility & Scoring'!$AK17-C74 -> 257749.33 | E74: =IF(C74+D74=0,0,IFERROR(INDEX('Fund Parameters'!$B$74:$B$78,Pipeline!$H17),1)) -> 0.95 | F74: =C74*E74+D74 -> 376262.47 | G74: =G16+G45 -> 307524.85 | H74: =H16+H45 -> 46220.125 | I74: =I16+I45 -> 18962.102 | J74: =J16+J45 -> 3555.3942 | K74: =K16+K45 -> 0 | L74: =L16+L45 -> 0 | M74: =M16+M45 -> 0 | N74: =N16+N45 -> 0 | ... P74: =P16+P45 -> 0 | Q74: =SUM(G74:P74) -> 376262.47
A75: 12 | B75: ='Eligibility & Scoring'!$B18 -> Project L - Mining belt | C75: ='Eligibility & Scoring'!$AK18*'Eligibility & Scoring'!$U18 -> 111562.5 | D75: ='Eligibility & Scoring'!$AK18-C75 -> 270937.5 | E75: =IF(C75+D75=0,0,IFERROR(INDEX('Fund Parameters'!$B$74:$B$78,Pipeline!$H18),1)) -> 0.9 | F75: =C75*E75+D75 -> 371343.75 | G75: =G17+G46 -> 0 | H75: =H17+H46 -> 313108.12 | I75: =I17+I46 -> 39158.438 | J75: =J17+J46 -> 16065 | K75: =K17+K46 -> 3012.1875 | L75: =L17+L46 -> 0 | M75: =M17+M46 -> 0 | N75: =N17+N46 -> 0 | ... P75: =P17+P46 -> 0 | Q75: =SUM(G75:P75) -> 371343.75
... A88: 25 | B88: ='Eligibility & Scoring'!$B31 | C88: ='Eligibility & Scoring'!$AK31*'Eligibility & Scoring'!$U31 -> 0 | D88: ='Eligibility & Scoring'!$AK31-C88 -> 0 | E88: =IF(C88+D88=0,0,IFERROR(INDEX('Fund Parameters'!$B$74:$B$78,Pipeline!$H31),1)) -> 0 | F88: =C88*E88+D88 -> 0 | G88: =G30+G59 -> 0 | H88: =H30+H59 -> 0 | I88: =I30+I59 -> 0 | J88: =J30+J59 -> 0 | K88: =K30+K59 -> 0 | L88: =L30+L59 -> 0 | M88: =M30+M59 -> 0 | N88: =N30+N59 -> 0 | ... P88: =P30+P59 -> 0 | Q88: =SUM(G88:P88) -> 0
B89: TOTAL | C89: =SUM(C64:C88) -> 753310.82 | D89: =SUM(D64:D88) -> 1796689.2 | F89: =SUM(F64:F88) -> 2505383.3 | G89: =SUM(G64:G88) -> 939128.3 | H89: =SUM(H64:H88) -> 1287405.8 | I89: =SUM(I64:I88) -> 198430.53 | J89: =SUM(J64:J88) -> 69326.612 | K89: =SUM(K64:K88) -> 11092.105 | L89: =SUM(L64:L88) -> 0 | M89: =SUM(M64:M88) -> 0 | ... Q89: =SUM(Q64:Q88) -> 2505383.3
A92: FUND CASH POSITION
B93: Expected disbursements | G93: =G89 -> 939128.3 | H93: =H89 -> 1287405.8 | I93: =I89 -> 198430.53 | J93: =J89 -> 69326.612 | K93: =K89 -> 11092.105 | L93: =L89 -> 0 | M93: =M89 -> 0 | N93: =N89 -> 0 | ... P93: =P89 -> 0
B94: Cumulative disbursements | G94: =G93 -> 939128.3 | H94: =G94+H93 -> 2226534.1 | I94: =H94+I93 -> 2424964.6 | J94: =I94+J93 -> 2494291.2 | K94: =J94+K93 -> 2505383.3 | L94: =K94+L93 -> 2505383.3 | M94: =L94+M93 -> 2505383.3 | N94: =M94+N93 -> 2505383.3 | O94: =N94+O93 -> 2505383.3 | P94: =O94+P93 -> 2505383.3
B95: Funds available for projects, remaining | G95: =Available-G94 -> 1610871.7 | H95: =Available-H94 -> 323465.94 | I95: =Available-I94 -> 125035.41 | J95: =Available-J94 -> 55708.799 | K95: =Available-K94 -> 44616.694 | L95: =Available-L94 -> 44616.694 | M95: =Available-M94 -> 44616.694 | N95: =Available-N94 -> 44616.694 | ... P95: =Available-P94 -> 44616.694
B96: Undisbursed commitments | G96: =TotalAllocated-G94 -> 1610871.7 | H96: =TotalAllocated-H94 -> 323465.94 | I96: =TotalAllocated-I94 -> 125035.41 | J96: =TotalAllocated-J94 -> 55708.799 | K96: =TotalAllocated-K94 -> 44616.694 | L96: =TotalAllocated-L94 -> 44616.694 | M96: =TotalAllocated-M94 -> 44616.694 | N96: =TotalAllocated-N94 -> 44616.694 | ... P96: =TotalAllocated-P94 -> 44616.694
B97: Expected decommitment (RBF not earned) | C97: =SUM(C6:C30)-Q31 -> 44616.694
B98: Lowest remaining balance over fund life | C98: =MIN(G95:P95) -> 44616.694

Sheet MRV Tracker
A1: MRV TRACKER
A2: Enter verified connections and RBF paid to date (yellow). Status compares progress with the expected verification profile.
A4: Reporting fund year | D4: 3 | E4: ="= calendar year "&(FundStart-1+RepYear) -> = calendar year 2029
A6: # | B6: Project | C6: Target connections | D6: Allocated RBF | E6: Verified connections to date | F6: Achieved | G6: Expected by now | H6: Status | I6: RBF earned to date (all tranches) | J6: RBF paid to date | K6: Outstanding RBF
A7: 1 | B7: ='Eligibility & Scoring'!$B7 -> Project A - Lake village cluster | C7: ='Eligibility & Scoring'!$C7 -> 1080 | D7: =Disbursements!$C$6 -> 110778.69 | E7: 1048 | F7: =IFERROR(MIN(1,E7/C7),0) -> 0.97037037 | G7: =IF(D7=0,0,IF(RepYear<Pipeline!$I7,0,IF(RepYear=Pipeline!$I7,RampV1,IF(RepYear=Pipeline!$I7+1,RampV2,1)))) -> 1 | H7: =IF(B7="","",IF(D7=0,"Not funded",IF(G7=0,"Not started",IF(F7>=0.9*G7,"On track",IF(F7>=0.6*G7,"Behind","Off track"))))) -> On track | I7: =IFERROR(MIN(D7,E7/C7*D7),0) -> 107496.36 | K7: =MAX(0,I7*TrancheA-J7) -> 75247.45
A8: 2 | B8: ='Eligibility & Scoring'!$B8 -> Project B - River towns | C8: ='Eligibility & Scoring'!$C8 -> 696 | D8: =Disbursements!$C$7 -> 32871.094 | E8: 487 | F8: =IFERROR(MIN(1,E8/C8),0) -> 0.69971264 | G8: =IF(D8=0,0,IF(RepYear<Pipeline!$I8,0,IF(RepYear=Pipeline!$I8,RampV1,IF(RepYear=Pipeline!$I8+1,RampV2,1)))) -> 0.9 | H8: =IF(B8="","",IF(D8=0,"Not funded",IF(G8=0,"Not started",IF(F8>=0.9*G8,"On track",IF(F8>=0.6*G8,"Behind","Off track"))))) -> Behind | I8: =IFERROR(MIN(D8,E8/C8*D8),0) -> 23000.32 | K8: =MAX(0,I8*TrancheA-J8) -> 16100.224
A9: 3 | B9: ='Eligibility & Scoring'!$B9 -> Project C - Northern corridor | C9: ='Eligibility & Scoring'!$C9 -> 1714 | D9: =Disbursements!$C$8 -> 115204.4 | E9: 1371 | F9: =IFERROR(MIN(1,E9/C9),0) -> 0.79988331 | G9: =IF(D9=0,0,IF(RepYear<Pipeline!$I9,0,IF(RepYear=Pipeline!$I9,RampV1,IF(RepYear=Pipeline!$I9+1,RampV2,1)))) -> 1 | H9: =IF(B9="","",IF(D9=0,"Not funded",IF(G9=0,"Not started",IF(F9>=0.9*G9,"On track",IF(F9>=0.6*G9,"Behind","Off track"))))) -> Behind | I9: =IFERROR(MIN(D9,E9/C9*D9),0) -> 92150.079 | K9: =MAX(0,I9*TrancheA-J9) -> 64505.055
A10: 4 | B10: ='Eligibility & Scoring'!$B10 -> Project D - Island grids | C10: ='Eligibility & Scoring'!$C10 -> 595 | D10: =Disbursements!$C$9 -> 0 | E10: 0 | F10: =IFERROR(MIN(1,E10/C10),0) -> 0 | G10: =IF(D10=0,0,IF(RepYear<Pipeline!$I10,0,IF(RepYear=Pipeline!$I10,RampV1,IF(RepYear=Pipeline!$I10+1,RampV2,1)))) -> 0 | H10: =IF(B10="","",IF(D10=0,"Not funded",IF(G10=0,"Not started",IF(F10>=0.9*G10,"On track",IF(F10>=0.6*G10,"Behind","Off track"))))) -> Not funded | I10: =IFERROR(MIN(D10,E10/C10*D10),0) -> 0 | K10: =MAX(0,I10*TrancheA-J10) -> 0
A11: 5 | B11: ='Eligibility & Scoring'!$B11 -> Project E - Highland villages | C11: ='Eligibility & Scoring'!$C11 -> 828 | D11: =Disbursements!$C$10 -> 0 | E11: 0 | F11: =IFERROR(MIN(1,E11/C11),0) -> 0 | G11: =IF(D11=0,0,IF(RepYear<Pipeline!$I11,0,IF(RepYear=Pipeline!$I11,RampV1,IF(RepYear=Pipeline!$I11+1,RampV2,1)))) -> 0 | H11: =IF(B11="","",IF(D11=0,"Not funded",IF(G11=0,"Not started",IF(F11>=0.9*G11,"On track",IF(F11>=0.6*G11,"Behind","Off track"))))) -> Not funded | I11: =IFERROR(MIN(D11,E11/C11*D11),0) -> 0 | K11: =MAX(0,I11*TrancheA-J11) -> 0
A12: 6 | B12: ='Eligibility & Scoring'!$B12 -> Project F - Market towns | C12: ='Eligibility & Scoring'!$C12 -> 988 | D12: =Disbursements!$C$11 -> 0 | E12: 0 | F12: =IFERROR(MIN(1,E12/C12),0) -> 0 | G12: =IF(D12=0,0,IF(RepYear<Pipeline!$I12,0,IF(RepYear=Pipeline!$I12,RampV1,IF(RepYear=Pipeline!$I12+1,RampV2,1)))) -> 0 | H12: =IF(B12="","",IF(D12=0,"Not funded",IF(G12=0,"Not started",IF(F12>=0.9*G12,"On track",IF(F12>=0.6*G12,"Behind","Off track"))))) -> Not funded | I12: =IFERROR(MIN(D12,E12/C12*D12),0) -> 0 | K12: =MAX(0,I12*TrancheA-J12) -> 0
A13: 7 | B13: ='Eligibility & Scoring'!$B13 -> Project G - Remote valley | C13: ='Eligibility & Scoring'!$C13 -> 354 | D13: =Disbursements!$C$12 -> 0 | E13: 0 | F13: =IFERROR(MIN(1,E13/C13),0) -> 0 | G13: =IF(D13=0,0,IF(RepYear<Pipeline!$I13,0,IF(RepYear=Pipeline!$I13,RampV1,IF(RepYear=Pipeline!$I13+1,RampV2,1)))) -> 0 | H13: =IF(B13="","",IF(D13=0,"Not funded",IF(G13=0,"Not started",IF(F13>=0.9*G13,"On track",IF(F13>=0.6*G13,"Behind","Off track"))))) -> Not funded | I13: =IFERROR(MIN(D13,E13/C13*D13),0) -> 0 | K13: =MAX(0,I13*TrancheA-J13) -> 0
A14: 8 | B14: ='Eligibility & Scoring'!$B14 -> Project H - Agro-processing hub | C14: ='Eligibility & Scoring'!$C14 -> 876 | D14: =Disbursements!$C$13 -> 112181.98 | E14: 745 | F14: =IFERROR(MIN(1,E14/C14),0) -> 0.85045662 | G14: =IF(D14=0,0,IF(RepYear<Pipeline!$I14,0,IF(RepYear=Pipeline!$I14,RampV1,IF(RepYear=Pipeline!$I14+1,RampV2,1)))) -> 0.9 | H14: =IF(B14="","",IF(D14=0,"Not funded",IF(G14=0,"Not started",IF(F14>=0.9*G14,"On track",IF(F14>=0.6*G14,"Behind","Off track"))))) -> On track | I14: =IFERROR(MIN(D14,E14/C14*D14),0) -> 95405.907 | K14: =MAX(0,I14*TrancheA-J14) -> 66784.135
A15: 9 | B15: ='Eligibility & Scoring'!$B15 -> Project I - Fishing communities | C15: ='Eligibility & Scoring'!$C15 -> 917 | D15: =Disbursements!$C$14 -> 109793.86 | E15: 367 | F15: =IFERROR(MIN(1,E15/C15),0) -> 0.4002181 | G15: =IF(D15=0,0,IF(RepYear<Pipeline!$I15,0,IF(RepYear=Pipeline!$I15,RampV1,IF(RepYear=Pipeline!$I15+1,RampV2,1)))) -> 0.9 | H15: =IF(B15="","",IF(D15=0,"Not funded",IF(G15=0,"Not started",IF(F15>=0.9*G15,"On track",IF(F15>=0.6*G15,"Behind","Off track"))))) -> Off track | I15: =IFERROR(MIN(D15,E15/C15*D15),0) -> 43941.491 | K15: =MAX(0,I15*TrancheA-J15) -> 30759.044
A16: 10 | B16: ='Eligibility & Scoring'!$B16 -> Project J - Health and schools first | C16: ='Eligibility & Scoring'!$C16 -> 650 | D16: =Disbursements!$C$15 -> 0 | E16: 0 | F16: =IFERROR(MIN(1,E16/C16),0) -> 0 | G16: =IF(D16=0,0,IF(RepYear<Pipeline!$I16,0,IF(RepYear=Pipeline!$I16,RampV1,IF(RepYear=Pipeline!$I16+1,RampV2,1)))) -> 0 | H16: =IF(B16="","",IF(D16=0,"Not funded",IF(G16=0,"Not started",IF(F16>=0.9*G16,"On track",IF(F16>=0.6*G16,"Behind","Off track"))))) -> Not funded | I16: =IFERROR(MIN(D16,E16/C16*D16),0) -> 0 | K16: =MAX(0,I16*TrancheA-J16) -> 0
A17: 11 | B17: ='Eligibility & Scoring'!$B17 -> Project K - Peri-urban extension | C17: ='Eligibility & Scoring'!$C17 -> 1460 | D17: =Disbursements!$C$16 -> 124750.67 | E17: 1460 | F17: =IFERROR(MIN(1,E17/C17),0) -> 1 | G17: =IF(D17=0,0,IF(RepYear<Pipeline!$I17,0,IF(RepYear=Pipeline!$I17,RampV1,IF(RepYear=Pipeline!$I17+1,RampV2,1)))) -> 1 | H17: =IF(B17="","",IF(D17=0,"Not funded",IF(G17=0,"Not started",IF(F17>=0.9*G17,"On track",IF(F17>=0.6*G17,"Behind","Off track"))))) -> On track | I17: =IFERROR(MIN(D17,E17/C17*D17),0) -> 124750.67 | K17: =MAX(0,I17*TrancheA-J17) -> 87325.472
A18: 12 | B18: ='Eligibility & Scoring'!$B18 -> Project L - Mining belt | C18: ='Eligibility & Scoring'!$C18 -> 1298 | D18: =Disbursements!$C$17 -> 111562.5 | E18: 974 | F18: =IFERROR(MIN(1,E18/C18),0) -> 0.75038521 | G18: =IF(D18=0,0,IF(RepYear<Pipeline!$I18,0,IF(RepYear=Pipeline!$I18,RampV1,IF(RepYear=Pipeline!$I18+1,RampV2,1)))) -> 0.9 | H18: =IF(B18="","",IF(D18=0,"Not funded",IF(G18=0,"Not started",IF(F18>=0.9*G18,"On track",IF(F18>=0.6*G18,"Behind","Off track"))))) -> Behind | I18: =IFERROR(MIN(D18,E18/C18*D18),0) -> 83714.85 | K18: =MAX(0,I18*TrancheA-J18) -> 58600.395
A19: 13 | B19: ='Eligibility & Scoring'!$B19 -> Project M - Small pilot | C19: ='Eligibility & Scoring'!$C19 -> 182 | D19: =Disbursements!$C$18 -> 0 | E19: 0 | F19: =IFERROR(MIN(1,E19/C19),0) -> 0 | G19: =IF(D19=0,0,IF(RepYear<Pipeline!$I19,0,IF(RepYear=Pipeline!$I19,RampV1,IF(RepYear=Pipeline!$I19+1,RampV2,1)))) -> 0 | H19: =IF(B19="","",IF(D19=0,"Not funded",IF(G19=0,"Not started",IF(F19>=0.9*G19,"On track",IF(F19>=0.6*G19,"Behind","Off track"))))) -> Not funded | I19: =IFERROR(MIN(D19,E19/C19*D19),0) -> 0 | K19: =MAX(0,I19*TrancheA-J19) -> 0
A20: 14 | B20: ='Eligibility & Scoring'!$B20 -> Project N - Lakeside expansion | C20: ='Eligibility & Scoring'!$C20 -> 1014 | D20: =Disbursements!$C$19 -> 36167.622 | E20: 892 | F20: =IFERROR(MIN(1,E20/C20),0) -> 0.87968442 | G20: =IF(D20=0,0,IF(RepYear<Pipeline!$I20,0,IF(RepYear=Pipeline!$I20,RampV1,IF(RepYear=Pipeline!$I20+1,RampV2,1)))) -> 0.9 | H20: =IF(B20="","",IF(D20=0,"Not funded",IF(G20=0,"Not started",IF(F20>=0.9*G20,"On track",IF(F20>=0.6*G20,"Behind","Off track"))))) -> On track | I20: =IFERROR(MIN(D20,E20/C20*D20),0) -> 31816.093 | K20: =MAX(0,I20*TrancheA-J20) -> 22271.265
A21: 15 | B21: ='Eligibility & Scoring'!$B21 | C21: ='Eligibility & Scoring'!$C21 -> 0 | D21: =Disbursements!$C$20 -> 0 | F21: =IFERROR(MIN(1,E21/C21),0) -> 0 | G21: =IF(D21=0,0,IF(RepYear<Pipeline!$I21,0,IF(RepYear=Pipeline!$I21,RampV1,IF(RepYear=Pipeline!$I21+1,RampV2,1)))) -> 0 | H21: =IF(B21="","",IF(D21=0,"Not funded",IF(G21=0,"Not started",IF(F21>=0.9*G21,"On track",IF(F21>=0.6*G21,"Behind","Off track"))))) | I21: =IFERROR(MIN(D21,E21/C21*D21),0) -> 0 | K21: =MAX(0,I21*TrancheA-J21) -> 0
A22: 16 | B22: ='Eligibility & Scoring'!$B22 | C22: ='Eligibility & Scoring'!$C22 -> 0 | D22: =Disbursements!$C$21 -> 0 | F22: =IFERROR(MIN(1,E22/C22),0) -> 0 | G22: =IF(D22=0,0,IF(RepYear<Pipeline!$I22,0,IF(RepYear=Pipeline!$I22,RampV1,IF(RepYear=Pipeline!$I22+1,RampV2,1)))) -> 0 | H22: =IF(B22="","",IF(D22=0,"Not funded",IF(G22=0,"Not started",IF(F22>=0.9*G22,"On track",IF(F22>=0.6*G22,"Behind","Off track"))))) | I22: =IFERROR(MIN(D22,E22/C22*D22),0) -> 0 | K22: =MAX(0,I22*TrancheA-J22) -> 0
A23: 17 | B23: ='Eligibility & Scoring'!$B23 | C23: ='Eligibility & Scoring'!$C23 -> 0 | D23: =Disbursements!$C$22 -> 0 | F23: =IFERROR(MIN(1,E23/C23),0) -> 0 | G23: =IF(D23=0,0,IF(RepYear<Pipeline!$I23,0,IF(RepYear=Pipeline!$I23,RampV1,IF(RepYear=Pipeline!$I23+1,RampV2,1)))) -> 0 | H23: =IF(B23="","",IF(D23=0,"Not funded",IF(G23=0,"Not started",IF(F23>=0.9*G23,"On track",IF(F23>=0.6*G23,"Behind","Off track"))))) | I23: =IFERROR(MIN(D23,E23/C23*D23),0) -> 0 | K23: =MAX(0,I23*TrancheA-J23) -> 0
A24: 18 | B24: ='Eligibility & Scoring'!$B24 | C24: ='Eligibility & Scoring'!$C24 -> 0 | D24: =Disbursements!$C$23 -> 0 | F24: =IFERROR(MIN(1,E24/C24),0) -> 0 | G24: =IF(D24=0,0,IF(RepYear<Pipeline!$I24,0,IF(RepYear=Pipeline!$I24,RampV1,IF(RepYear=Pipeline!$I24+1,RampV2,1)))) -> 0 | H24: =IF(B24="","",IF(D24=0,"Not funded",IF(G24=0,"Not started",IF(F24>=0.9*G24,"On track",IF(F24>=0.6*G24,"Behind","Off track"))))) | I24: =IFERROR(MIN(D24,E24/C24*D24),0) -> 0 | K24: =MAX(0,I24*TrancheA-J24) -> 0
A25: 19 | B25: ='Eligibility & Scoring'!$B25 | C25: ='Eligibility & Scoring'!$C25 -> 0 | D25: =Disbursements!$C$24 -> 0 | F25: =IFERROR(MIN(1,E25/C25),0) -> 0 | G25: =IF(D25=0,0,IF(RepYear<Pipeline!$I25,0,IF(RepYear=Pipeline!$I25,RampV1,IF(RepYear=Pipeline!$I25+1,RampV2,1)))) -> 0 | H25: =IF(B25="","",IF(D25=0,"Not funded",IF(G25=0,"Not started",IF(F25>=0.9*G25,"On track",IF(F25>=0.6*G25,"Behind","Off track"))))) | I25: =IFERROR(MIN(D25,E25/C25*D25),0) -> 0 | K25: =MAX(0,I25*TrancheA-J25) -> 0
A26: 20 | B26: ='Eligibility & Scoring'!$B26 | C26: ='Eligibility & Scoring'!$C26 -> 0 | D26: =Disbursements!$C$25 -> 0 | F26: =IFERROR(MIN(1,E26/C26),0) -> 0 | G26: =IF(D26=0,0,IF(RepYear<Pipeline!$I26,0,IF(RepYear=Pipeline!$I26,RampV1,IF(RepYear=Pipeline!$I26+1,RampV2,1)))) -> 0 | H26: =IF(B26="","",IF(D26=0,"Not funded",IF(G26=0,"Not started",IF(F26>=0.9*G26,"On track",IF(F26>=0.6*G26,"Behind","Off track"))))) | I26: =IFERROR(MIN(D26,E26/C26*D26),0) -> 0 | K26: =MAX(0,I26*TrancheA-J26) -> 0
A27: 21 | B27: ='Eligibility & Scoring'!$B27 | C27: ='Eligibility & Scoring'!$C27 -> 0 | D27: =Disbursements!$C$26 -> 0 | F27: =IFERROR(MIN(1,E27/C27),0) -> 0 | G27: =IF(D27=0,0,IF(RepYear<Pipeline!$I27,0,IF(RepYear=Pipeline!$I27,RampV1,IF(RepYear=Pipeline!$I27+1,RampV2,1)))) -> 0 | H27: =IF(B27="","",IF(D27=0,"Not funded",IF(G27=0,"Not started",IF(F27>=0.9*G27,"On track",IF(F27>=0.6*G27,"Behind","Off track"))))) | I27: =IFERROR(MIN(D27,E27/C27*D27),0) -> 0 | K27: =MAX(0,I27*TrancheA-J27) -> 0
A28: 22 | B28: ='Eligibility & Scoring'!$B28 | C28: ='Eligibility & Scoring'!$C28 -> 0 | D28: =Disbursements!$C$27 -> 0 | F28: =IFERROR(MIN(1,E28/C28),0) -> 0 | G28: =IF(D28=0,0,IF(RepYear<Pipeline!$I28,0,IF(RepYear=Pipeline!$I28,RampV1,IF(RepYear=Pipeline!$I28+1,RampV2,1)))) -> 0 | H28: =IF(B28="","",IF(D28=0,"Not funded",IF(G28=0,"Not started",IF(F28>=0.9*G28,"On track",IF(F28>=0.6*G28,"Behind","Off track"))))) | I28: =IFERROR(MIN(D28,E28/C28*D28),0) -> 0 | K28: =MAX(0,I28*TrancheA-J28) -> 0
A29: 23 | B29: ='Eligibility & Scoring'!$B29 | C29: ='Eligibility & Scoring'!$C29 -> 0 | D29: =Disbursements!$C$28 -> 0 | F29: =IFERROR(MIN(1,E29/C29),0) -> 0 | G29: =IF(D29=0,0,IF(RepYear<Pipeline!$I29,0,IF(RepYear=Pipeline!$I29,RampV1,IF(RepYear=Pipeline!$I29+1,RampV2,1)))) -> 0 | H29: =IF(B29="","",IF(D29=0,"Not funded",IF(G29=0,"Not started",IF(F29>=0.9*G29,"On track",IF(F29>=0.6*G29,"Behind","Off track"))))) | I29: =IFERROR(MIN(D29,E29/C29*D29),0) -> 0 | K29: =MAX(0,I29*TrancheA-J29) -> 0
A30: 24 | B30: ='Eligibility & Scoring'!$B30 | C30: ='Eligibility & Scoring'!$C30 -> 0 | D30: =Disbursements!$C$29 -> 0 | F30: =IFERROR(MIN(1,E30/C30),0) -> 0 | G30: =IF(D30=0,0,IF(RepYear<Pipeline!$I30,0,IF(RepYear=Pipeline!$I30,RampV1,IF(RepYear=Pipeline!$I30+1,RampV2,1)))) -> 0 | H30: =IF(B30="","",IF(D30=0,"Not funded",IF(G30=0,"Not started",IF(F30>=0.9*G30,"On track",IF(F30>=0.6*G30,"Behind","Off track"))))) | I30: =IFERROR(MIN(D30,E30/C30*D30),0) -> 0 | K30: =MAX(0,I30*TrancheA-J30) -> 0
A31: 25 | B31: ='Eligibility & Scoring'!$B31 | C31: ='Eligibility & Scoring'!$C31 -> 0 | D31: =Disbursements!$C$30 -> 0 | F31: =IFERROR(MIN(1,E31/C31),0) -> 0 | G31: =IF(D31=0,0,IF(RepYear<Pipeline!$I31,0,IF(RepYear=Pipeline!$I31,RampV1,IF(RepYear=Pipeline!$I31+1,RampV2,1)))) -> 0 | H31: =IF(B31="","",IF(D31=0,"Not funded",IF(G31=0,"Not started",IF(F31>=0.9*G31,"On track",IF(F31>=0.6*G31,"Behind","Off track"))))) | I31: =IFERROR(MIN(D31,E31/C31*D31),0) -> 0 | K31: =MAX(0,I31*TrancheA-J31) -> 0
B32: TOTAL | C32: =SUM(C7:C31) -> 12652 | D32: =SUM(D7:D31) -> 753310.82 | E32: =SUM(E7:E31) -> 7344 | I32: =SUM(I7:I31) -> 602275.77 | J32: =SUM(J7:J31) -> 0 | K32: =SUM(K7:K31) -> 421593.04
B34: Outstanding RBF = RBF earned x tranche at verification - RBF paid. The balance tranche falls due after the service-continuity check.

Sheet Portfolio Dashboard
B1: ="PORTFOLIO DASHBOARD - "&FundName -> PORTFOLIO DASHBOARD - Example Energy Access Fund
B2: =FundManager&" | profile: "&ProfileName&" | fund size "&Currency&" "&FIXED(FundSize,0)&" | "&TEXT(FundStart,"0")&"-"&TEXT(FundStart+9,"0") -> Example Fund Manager | profile: Capex grant + RBF | fund size USD 3,000,000 | 2027-2036
E3: ="Model checks: "&ChecksOverall -> Model checks: ALL OK
B5: COMMITMENTS | E5: PIPELINE | H5: ALLOCATION BY COUNTRY
B6: Fund size | C6: =FundSize -> 3000000 | E6: Projects in pipeline | F6: =COUNTIF(Pipeline!$B$7:$B$31,"?*") -> 14 | H6: Country | I6: Allocated | J6: Share of envelope
B7: Available for projects (after management and TA) | C7: =Available -> 2550000 | E7: Eligible projects | F7: =SUM('Eligibility & Scoring'!$O$7:$O$31) -> 8 | H7: =IF('Fund Parameters'!$A$51="","",'Fund Parameters'!$A$51) -> Country A | I7: =IF(H7="",0,SUMIF(Pipeline!$C$7:$C$31,H7,'Eligibility & Scoring'!$AK$7:$AK$31)) -> 510000 | J7: =IFERROR(I7/Envelope,0) -> 0.2
B8: Allocation envelope (with over-commitment) | C8: =Envelope -> 2550000 | E8: Projects funded (fully or partly) | F8: =COUNTIF(Allocation!$I$7:$I$31,">0") -> 8 | H8: =IF('Fund Parameters'!$A$52="","",'Fund Parameters'!$A$52) -> Country B | I8: =IF(H8="",0,SUMIF(Pipeline!$C$7:$C$31,H8,'Eligibility & Scoring'!$AK$7:$AK$31)) -> 1275000 | J8: =IFERROR(I8/Envelope,0) -> 0.5
B9: Requested by eligible projects | C9: =TotalRequested -> 2997500 | E9: Projects fully funded | F9: =COUNTIF('Eligibility & Scoring'!$AM$7:$AM$31,"Funded") -> 6 | H9: =IF('Fund Parameters'!$A$53="","",'Fund Parameters'!$A$53) -> Country C | I9: =IF(H9="",0,SUMIF(Pipeline!$C$7:$C$31,H9,'Eligibility & Scoring'!$AK$7:$AK$31)) -> 0 | J9: =IFERROR(I9/Envelope,0) -> 0
B10: Oversubscription (requested / envelope) | C10: =IFERROR(TotalRequested/Envelope,0) -> 1.1754902 | E10: Eligible projects not funded | F10: =NEligible-NFunded -> 0 | H10: =IF('Fund Parameters'!$A$54="","",'Fund Parameters'!$A$54) -> Country D | I10: =IF(H10="",0,SUMIF(Pipeline!$C$7:$C$31,H10,'Eligibility & Scoring'!$AK$7:$AK$31)) -> 765000 | J10: =IFERROR(I10/Envelope,0) -> 0.3
B11: Allocated | C11: =TotalAllocated -> 2550000 | E11: Projects above their viability gap (funded) | F11: =SUMPRODUCT(('Eligibility & Scoring'!$Y$7:$Y$31="Above viability gap")*('Eligibility & Scoring'!$AK$7:$AK$31>0)) -> 0 | H11: =IF('Fund Parameters'!$A$55="","",'Fund Parameters'!$A$55) | I11: =IF(H11="",0,SUMIF(Pipeline!$C$7:$C$31,H11,'Eligibility & Scoring'!$AK$7:$AK$31)) -> 0 | J11: =IFERROR(I11/Envelope,0) -> 0
B12: of which RBF | C12: =Disbursements!$C$31 -> 753310.82 | E12: Average weighted score of funded projects | F12: =IFERROR(SUMPRODUCT('Eligibility & Scoring'!$AH$7:$AH$31,'Eligibility & Scoring'!$AK$7:$AK$31)/TotalAllocated,0) -> 70.74395 | H12: =IF('Fund Parameters'!$A$56="","",'Fund Parameters'!$A$56) | I12: =IF(H12="",0,SUMIF(Pipeline!$C$7:$C$31,H12,'Eligibility & Scoring'!$AK$7:$AK$31)) -> 0 | J12: =IFERROR(I12/Envelope,0) -> 0
B13: of which CAPEX grants | C13: =Disbursements!$D$31 -> 1796689.2 | H13: =IF('Fund Parameters'!$A$57="","",'Fund Parameters'!$A$57) | I13: =IF(H13="",0,SUMIF(Pipeline!$C$7:$C$31,H13,'Eligibility & Scoring'!$AK$7:$AK$31)) -> 0 | J13: =IFERROR(I13/Envelope,0) -> 0
B14: Envelope used | C14: =IFERROR(TotalAllocated/Envelope,0) -> 1 | H14: =IF('Fund Parameters'!$A$58="","",'Fund Parameters'!$A$58) | I14: =IF(H14="",0,SUMIF(Pipeline!$C$7:$C$31,H14,'Eligibility & Scoring'!$AK$7:$AK$31)) -> 0 | J14: =IFERROR(I14/Envelope,0) -> 0
B15: Expected disbursements (after delivery haircut) | C15: =TotalExpectedDisb -> 2505383.3 | H15: Other / unlisted | I15: =TotalAllocated-SUM(I7:I14) -> 0 | J15: =IFERROR(I15/Envelope,0) -> 0
