Workbook

Sheet Cover
C18: MODEL 2 | BOOK 2, PAYGo SOLAR FINANCE
C20: SOLAR HOME SYSTEMS
C22: PAYGo Company Financial & Investment Model
C24: From business model to investment decision | MTF Tiers 1-5 | Credit, vintage, PERFORM, RBF, FX and benchmark engines
C27: AUTHOR & IDEATION
C28: Emmanuel Boujieka Kamga
C30: Version v0.8-dev | Development build | 03 October 2026
C34: MODEL STATUS
C35: Master check | E35: =Checks!$C$44
C36: Investment readiness | E36: =Investment_Readiness!$B$5
C37: Active case | E37: =Scenarios!$G$13
C38: Credit data | E38: =IF(Credit_Assumptions!$C$5=1,"Proxy (model curves)","Actual (company data)")
C39: Currency | E39: =Inputs!$C$7&" (local), USD for hardware, RBF and term debt"
C41: Start here: Contents > | E41: Investment summary > | H41: Investment readiness >
C43: Decision-support tool. Not investment, legal, tax or accounting advice. Default inputs are illustrative placeholders for a fictional company in a fictional market; market data are graded in Source_Register. This is an analytical modelling treatment and does not constitute a determination of the applicable accounting treatment under IFRS. Readiness is decided on evidence only (see Investment_Readiness).
C47: (c) 2026 Emmanuel Boujieka Kamga. All rights reserved. | Africa Energy Finance: Business & Financial Models

Sheet Start
A1: Start here
A2: What to input, what the model calculates, what the results mean and what an investor should look at.
B4: Master check | C4: =Checks!$C$44
B5: Active case | C5: =Scenarios!$G$13
B6: Credit data | C6: =IF(Credit_Assumptions!$C$5=1,"PROXY (model curves)","ACTUAL (company data)")
B7: Readiness decision | C7: =Investment_Readiness!$C$35&": "&Investment_Readiness!$C$36
A9: 1. WHAT TO INPUT (blue cells; every input carries a provenance label)
A10: 1 | B10: Inputs | C10: Scenario selector, macro and FX, volumes, operating costs, RBF design, working capital, financing, covenants, valuation.
A11: 2 | B11: Products | C11: Five tiers: specification, price plan (cash price, deposit, daily rate, tenor), costs, credit risk, recovery, RBF, advance rate.
A12: 3 | B12: Credit_Assumptions | C12: Default definition, staging thresholds, borrowing-base eligibility, recovery cost, proxy DPD distribution.
A13: 4 | B13: Scenarios | C13: Base, Downside and Severe levers, and which input set is loaded (management or calibrated).
A14: 5 | B14: Consumer_Risk | C14: Affordability review switch and the status of consumer-protection and PERFORM evidence.
A15: 6 | B15: Credit_Input | C15: ACTUAL: monthly portfolio history by tier (DPD buckets, write-offs, unlocks). Set the credit data mode to 2.
A16: 7 | B16: Vintage_Input | C16: ACTUAL: cohort checkpoints (collections and instalments due) and validated ownership at 2x if available.
A17: 8 | B17: PERFORM_2026 | C17: ACTUAL: PAYGo PERFORM 2026 results computed by the company on contract-level data (section C).
A18: 9 | B18: Investment_Readiness | C18: Manual gates: status, where the evidence is held, who signed it off and when.
A20: 2. WHAT THE MODEL CALCULATES
A21: 1 | B21: Curves | C21: Per-unit repayment, default and recovery by account age for each tier.
A22: 2 | B22: Ops | C22: Cohorts by month of sale (Cohort_T1..T5): collections, write-offs, receivables, active accounts, RBF.
A23: 3 | B23: FS | C23: Monthly income statement, balance sheet and cash flow; Annual rolls them up. The balance sheet balances every month (Checks).
A24: 4 | B24: Financing | C24: Receivables facility drawn within the borrowing base, USD term loan, automatic equity top-up to hold minimum cash.
A25: 5 | B25: Credit_Engine | C25: DPD buckets, default, PD and LGD proxies, indicative ECL, borrowing-base eligibility.
A26: 6 | B26: RBF_Engine | C26: RBF under the selected design, and the claim cycle from eligibility to disbursement.
A27: 7 | B27: Valuation | C27: DCF and the investor's USD IRR and MOIC; Covenants tests the facility terms monthly; FX_Exposure isolates FX effects.
A29: 3. WHAT THE RESULTS MEAN (read before quoting any number)
A30: 1 | C30: Revenue is not cash. A PAYGo sale books revenue at once and collects over the tenor: read cash conversion and the funding requirement.
A31: 2 | C31: The operational collection rate is a cash measure. It is not the PAYGo PERFORM Repayment Rate, which only company data can produce.
A32: 3 | C32: ECL, PD and staging are analytical proxies. This is an analytical modelling treatment and does not constitute a determination of the applicable accounting treatment under IFRS.
A33: 4 | C33: Every input is labelled: MODEL ASSUMPTION, COMPANY DATA, EXTERNAL EVIDENCE, CALIBRATED ASSUMPTION or UNVERIFIED (counts below).
A34: 5 | C34: The readiness decision measures the evidence file. GO is never an investment recommendation; STOP on incomplete evidence is not a verdict on the business.
A36: 4. WHAT AN INVESTOR SHOULD LOOK AT, IN THIS ORDER
A37: 1 | B37: Investment_Summary | C37: Trajectory, funding requirement, returns, lender view and unit economics on one page.
A38: 2 | B38: Dashboard | C38: Key metrics by year, labelled and rounded.
A39: 3 | B39: Investment_Readiness | C39: Gates met, missing evidence and the decision with its reason.
A40: 4 | B40: Sensitivity | C40: Downside and Severe, and the single levers that move peak equity and IRR the most.
A41: 5 | B41: Vintage_Dashboard | C41: Cohort behaviour by tier; then PERFORM_2026 for company-reported KPIs.
A42: 6 | B42: Covenants | C42: Months with a breach and the tightest covenant.
A43: 7 | B43: FX_Exposure | C43: Which items sit in USD, the hedge position and the transaction effect on cash.
A44: 8 | B44: Unit_Economics | C44: Lifetime contribution, LTV / CAC and payback by tier.
A45: 9 | B45: Checks | C45: Master check OK and the readiness flags.
A47: 5. PROVENANCE OF INPUTS (count of labelled inputs)
B48: MODEL ASSUMPTION | D48: =COUNTIF(Credit_Assumptions!$E$1:$E$200,"MODEL ASSUMPTION")+COUNTIF(Inputs!$E$1:$E$200,"MODEL ASSUMPTION")+COUNTIF(Products!$I$1:$I$200,"MODEL ASSUMPTION")+COUNTIF(Scenarios!$I$1:$I$200,"MODEL ASSUMPTION")
B49: COMPANY DATA | D49: =COUNTIF(Credit_Assumptions!$E$1:$E$200,"COMPANY DATA")+COUNTIF(Inputs!$E$1:$E$200,"COMPANY DATA")+COUNTIF(Products!$I$1:$I$200,"COMPANY DATA")+COUNTIF(Scenarios!$I$1:$I$200,"COMPANY DATA")
B50: EXTERNAL EVIDENCE | D50: =COUNTIF(Credit_Assumptions!$E$1:$E$200,"EXTERNAL EVIDENCE")+COUNTIF(Inputs!$E$1:$E$200,"EXTERNAL EVIDENCE")+COUNTIF(Products!$I$1:$I$200,"EXTERNAL EVIDENCE")+COUNTIF(Scenarios!$I$1:$I$200,"EXTERNAL EVIDENCE")
B51: CALIBRATED ASSUMPTION | D51: =COUNTIF(Credit_Assumptions!$E$1:$E$200,"CALIBRATED ASSUMPTION")+COUNTIF(Inputs!$E$1:$E$200,"CALIBRATED ASSUMPTION")+COUNTIF(Products!$I$1:$I$200,"CALIBRATED ASSUMPTION")+COUNTIF(Scenarios!$I$1:$I$200,"CALIBRATED ASSUMPTION")
B52: UNVERIFIED | D52: =COUNTIF(Credit_Assumptions!$E$1:$E$200,"UNVERIFIED")+COUNTIF(Inputs!$E$1:$E$200,"UNVERIFIED")+COUNTIF(Products!$I$1:$I$200,"UNVERIFIED")+COUNTIF(Scenarios!$I$1:$I$200,"UNVERIFIED")
C54: Labels describe where a value comes from. Change the label when you replace a value (for example, from MODEL ASSUMPTION to COMPANY DATA).

Sheet Contents
A1: Contents: how to use this model
A2: MODEL 2 | PAYGo Company Financial & Investment Model | Book 2, PAYGo Solar Finance
A4: Model | B4: MODEL 2: PAYGo Company Financial & Investment Model (solar home systems, MTF Tiers 1-5), companion to Book 2, PAYGo Solar Finance
A5: Version | B5: v0.8-dev: development build, generated 2026-10-03
A6: Status | B6: Draft for expert review. Default inputs are illustrative. Readiness and decision: see Investment_Readiness.
A7: Accounting | B7: This is an analytical modelling treatment and does not constitute a determination of the applicable accounting treatment under IFRS.
A8: Currency | B8: Model currency = LCY. Hardware, RBF and term debt in USD, converted at the Timeline FX path (FX_Exposure).
A9: Periodicity | B9: Monthly over 60 months; annual roll-ups on Annual, KPIs and Valuation.
A10: Master check | B10: =Checks!$C$44
A12: How to use
B13: 1. Start: what to input, what the model calculates, what it means and what an investor should look at.
B14: 2. Inputs, Products, Credit_Assumptions, Scenarios (blue cells; yellow = review first; provenance label on every input).
B15: 3. Company history (ACTUAL): Credit_Input, Vintage_Input and PERFORM_2026 section C. Scenario levers never change history.
B16: 4. Read Investment_Summary, Dashboard and Investment_Readiness, then KPIs, Valuation, Covenants, FX_Exposure and Unit_Economics.
B17: 5. Audit trail: FS > Ops > Cohort_T1..T5 > Curves. Every number traces back to an input.
B18: 6. The master check must read OK before any output is used.
A20: Sheet index (tab order)
A21: 01 Cover | B21: Title page and model status
A22: 02 Start | B22: Start here: inputs, calculations, meaning, what to look at
A23: 03 Contents | B23: This page: all sheets in tab order
A24: 04 Investment_Summary | B24: One-page investment committee and lender summary
A25: 05 Investment_Readiness | B25: 23 evidence-based gates and the GO / CONDITIONAL GO / STOP rule
A26: 06 Inputs | B26: Global inputs with provenance labels
A27: 07 Products | B27: Tiers 1-5: specification, price plans, risk, with provenance
A28: 08 Scenarios | B28: Stress levers, input set loaded and the scenario architecture
A29: 09 Credit_Assumptions | B29: DPD buckets, stages, default definition, recovery, eligibility
A30: 10 Consumer_Risk | B30: Affordability, APR, consumer-protection evidence
A31: 11 Dashboard | B31: Key metrics by year, labelled and rounded, with charts
A32: 12 KPIs | B32: Portfolio, financial and lender KPIs
... A67: 47 Checks | B67: Integrity checks and readiness flags
A69: Colour code
A70: 1,000 | B70: Blue = hard-coded input
A71: 1,000 | B71: Yellow fill = key assumption
A72: 1,000 | B72: Black = formula
A73: 1,000 | B73: Green = link from another sheet
A74: MODEL ASSUMPTION | B74: Provenance label (see Start and Glossary)
A75: COMPANY DATA | B75: Provenance label (see Start and Glossary)
A76: EXTERNAL EVIDENCE | B76: Provenance label (see Start and Glossary)
A77: CALIBRATED ASSUMPTION | B77: Provenance label (see Start and Glossary)
A78: UNVERIFIED | B78: Provenance label (see Start and Glossary)
A80: Disclaimer | B80: Decision-support tool. Not investment, legal, tax or accounting advice. Default inputs are illustrative. This is an analytical modelling treatment and does not constitute a determination of the applicable accounting treatment under IFRS. Users are responsible for their inputs and conclusions.

Sheet Investment_Summary
A1: Investment summary
A2: One-page view for investment committees and lenders. Active scenario, LCY unless stated.
A4: Active case | B4: =Scenarios!$G$13 | D4: Model version | E4: v0.8-dev
A5: Master check | B5: =Checks!$C$44 | D5: Currency | E5: =Inputs!$C$7
A6: =Investment_Readiness!$B$5 | D6: Credit data | E6: =IF(Credit_Assumptions!$C$5=1,"PROXY","ACTUAL")
A7: 1. Operating & financial trajectory
A8: Metric | B8: Year 1 | C8: Year 2 | D8: Year 3 | E8: Year 4 | F8: Year 5
A9: Units sold | B9: =KPIs!E14 | C9: =KPIs!F14 | D9: =KPIs!G14 | E9: =KPIs!H14 | F9: =KPIs!I14
A10: Active PAYGo accounts (year end) | B10: =KPIs!E16 | C10: =KPIs!F16 | D10: =KPIs!G16 | E10: =KPIs!H16 | F10: =KPIs!I16
A11: Average cash price per unit (USD) | B11: =KPIs!E15 | C11: =KPIs!F15 | D11: =KPIs!G15 | E11: =KPIs!H15 | F11: =KPIs!I15
A12: Revenue (USD, average FX) | B12: =KPIs!E35 | C12: =KPIs!F35 | D12: =KPIs!G35 | E12: =KPIs!H35 | F12: =KPIs!I35
A13: Gross margin | B13: =KPIs!E36 | C13: =KPIs!F36 | D13: =KPIs!G36 | E13: =KPIs!H36 | F13: =KPIs!I36
A14: EBITDA margin | B14: =KPIs!E38 | C14: =KPIs!F38 | D14: =KPIs!G38 | E14: =KPIs!H38 | F14: =KPIs!I38
A15: Net income (LCY) | B15: =KPIs!E42 | C15: =KPIs!F42 | D15: =KPIs!G42 | E15: =KPIs!H42 | F15: =KPIs!I42
A16: Operational collection rate | B16: =KPIs!E19 | C16: =KPIs!F19 | D16: =KPIs!G19 | E16: =KPIs!H19 | F16: =KPIs!I19
A17: Receivables at risk / gross receivables | B17: =KPIs!E21 | C17: =KPIs!F21 | D17: =KPIs!G21 | E17: =KPIs!H21 | F17: =KPIs!I21
A18: Total debt (LCY, year end) | B18: =KPIs!E47 | C18: =KPIs!F47 | D18: =KPIs!G47 | E18: =KPIs!H47 | F18: =KPIs!I47
A19: DSCR | B19: =KPIs!E50 | C19: =KPIs!F50 | D19: =KPIs!G50 | E19: =KPIs!H50 | F19: =KPIs!I50
A21: 2. Funding requirement
A22: Peak equity requirement (USD, opening FX; includes the initial injection: see KPIs for the additional need) | B22: =KPIs!$C$57
A23: Peak equity requirement (LCY) | B23: =KPIs!$C$56
A24: Peak total debt (LCY) | B24: =KPIs!$C$58
A25: Total RBF received (USD) | B25: =KPIs!$C$59
A26: First month with positive EBITDA | B26: =KPIs!$C$60
A27: Month from which operating cash flow stays positive | B27: =KPIs!$C$61
A29: 3. Valuation & equity returns
A30: DCF enterprise value at start (USD) | B30: =Valuation!$C$28
A31: Terminal value share of EV | B31: =Valuation!$C$29
A32: Exit equity value, 100% (USD, end Year 5) | B32: =Valuation!$C$36
A33: Investor stake | B33: =Valuation!$C$38
A34: Investor IRR (USD) | B34: =Valuation!$C$39
A35: Investor MOIC (USD) | B35: =Valuation!$C$40
A37: 4. Lender view
A38: Lowest trailing-3-month collection rate | B38: =KPIs!$C$62
A39: Highest receivables-at-risk ratio | B39: =KPIs!$C$63
A40: Highest 30+ DPD ratio (projection) | B40: =Covenants!$C$17
A41: Highest 90+ DPD ratio (projection) | B41: =Covenants!$C$19
A42: RBF design mode | B42: =RBF_Engine!$C$8
A43: Receivables financing structure | B43: =IF(Inputs!$C$60=1,"Warehouse facility","Securitisation")
A44: Months with any monthly covenant breach (DSCR is tested annually: next line) | B44: =KPIs!$C$64
A45: Years with DSCR below minimum | B45: =KPIs!$C$65
A46: Peak facility utilisation | B46: =Financing!$C$27
A48: 5. Unit economics by tier
A49: Metric | B49: Tier 1 | C49: Tier 2 | D49: Tier 3 | E49: Tier 4 | F49: Tier 5
A50: Cash price (LCY) | B50: =Unit_Economics!C5 | C50: =Unit_Economics!D5 | D50: =Unit_Economics!E5 | E50: =Unit_Economics!F5 | F50: =Unit_Economics!G5
A51: Implied APR | B51: =Unit_Economics!C7 | C51: =Unit_Economics!D7 | D51: =Unit_Economics!E7 | E51: =Unit_Economics!F7 | F51: =Unit_Economics!G7
A52: Expected loss rate | B52: =Unit_Economics!C11 | C52: =Unit_Economics!D11 | D52: =Unit_Economics!E11 | E52: =Unit_Economics!F11 | F52: =Unit_Economics!G11
A53: LTV / CAC | B53: =Unit_Economics!C21 | C53: =Unit_Economics!D21 | D53: =Unit_Economics!E21 | E53: =Unit_Economics!F21 | F53: =Unit_Economics!G21
A54: Cash payback (months) | B54: =Unit_Economics!C22 | C54: =Unit_Economics!D22 | D54: =Unit_Economics!E22 | E54: =Unit_Economics!F22 | F54: =Unit_Economics!G22
A55: Unit IRR | B55: =Unit_Economics!C23 | C55: =Unit_Economics!D23 | D55: =Unit_Economics!E23 | E55: =Unit_Economics!F23 | F55: =Unit_Economics!G23
A57: 6. Scenario snapshot (static, default inputs: see Sensitivity)
A58: Case | B58: Peak equity (USD m) | C58: Investor IRR | D58: MOIC | E58: Breach months
A59: =IF(Sensitivity!A6="","",Sensitivity!A6) | B59: =IF(Sensitivity!B6="","",Sensitivity!B6) | C59: =IF(Sensitivity!G6="","",Sensitivity!G6) | D59: =IF(Sensitivity!H6="","",Sensitivity!H6) | E59: =IF(Sensitivity!I6="","",Sensitivity!I6)
A60: =IF(Sensitivity!A7="","",Sensitivity!A7) | B60: =IF(Sensitivity!B7="","",Sensitivity!B7) | C60: =IF(Sensitivity!G7="","",Sensitivity!G7) | D60: =IF(Sensitivity!H7="","",Sensitivity!H7) | E60: =IF(Sensitivity!I7="","",Sensitivity!I7)
A61: =IF(Sensitivity!A8="","",Sensitivity!A8) | B61: =IF(Sensitivity!B8="","",Sensitivity!B8) | C61: =IF(Sensitivity!G8="","",Sensitivity!G8) | D61: =IF(Sensitivity!H8="","",Sensitivity!H8) | E61: =IF(Sensitivity!I8="","",Sensitivity!I8)
A63: All default inputs are illustrative. Not investment advice. See Cover for the disclaimer.

Sheet Investment_Readiness
A1: Investment readiness gates and evidence-based decision
A2: Each gate counts only on evidence: automatic gates are computed by the model; a manual gate counts only when marked Met with the place the evidence is held and the person who signed it off. The decision rule below uses these results only. It is not an investment recommendation, a credit rating or an opinion on the company.
B4: Gates met | C4: =SUM(F7:F29) | D4: ="of 23"
B5: ="INVESTMENT READINESS: "&C4&"/23 gates met. Decision: "&Investment_Readiness!$C$35&" ("&Investment_Readiness!$C$36&")"
A6: # | B6: Gate | C6: Type | D6: Manual status | E6: Auto result | F6: Met | G6: Evidence required | H6: Critical | I6: Where the evidence is held | J6: Signed off by | K6: Date | L6: Evidence check
A7: 1 | B7: Model integrity (master check OK) | C7: Auto | E7: =IFERROR(IF(Checks!$C$44="OK","Met","Not met"),"Not met") | F7: =IF(E7="Met",1,0) | G7: Automatic: Checks sheet, master check. | H7: Yes | L7: ="Computed in the model"
A8: 2 | B8: Inputs reviewed and signed off by management | C8: Manual | D8: Not started | F8: =IF(AND(EXACT(D8,"Met"),LEN(TRIM(I8))>1,LEN(TRIM(J8))>1),1,0) | G8: Signed input sheet or board paper approving the plan inputs. | H8: Yes | L8: =IF(D8<>"Met","",IF(F8=1,"Evidenced","Marked Met without evidence location or sign-off: not counted"))
A9: 3 | B9: Product specifications and MTF tier labels verified | C9: Manual | D9: Not started | F9: =IF(AND(EXACT(D9,"Met"),LEN(TRIM(I9))>1,LEN(TRIM(J9))>1),1,0) | G9: Datasheets; ESMAP MTF report (Source_Register E3-01, pending). | H9: No | L9: =IF(D9<>"Met","",IF(F9=1,"Evidenced","Marked Met without evidence location or sign-off: not counted"))
A10: 4 | B10: Pricing, deposits and APR disclosures reviewed | C10: Manual | D10: Not started | F10: =IF(AND(EXACT(D10,"Met"),LEN(TRIM(I10))>1,LEN(TRIM(J10))>1),1,0) | G10: Price list, customer contract and APR disclosure (Consumer_Risk, Products). | H10: No | L10: =IF(D10<>"Met","",IF(F10=1,"Evidenced","Marked Met without evidence location or sign-off: not counted"))
A11: 5 | B11: Sales plan supported by pipeline / channel evidence | C11: Manual | D11: Not started | F11: =IF(AND(EXACT(D11,"Met"),LEN(TRIM(I11))>1,LEN(TRIM(J11))>1),1,0) | G11: Agent network data, sales history, channel contracts. | H11: No | L11: =IF(D11<>"Met","",IF(F11=1,"Evidenced","Marked Met without evidence location or sign-off: not counted"))
A12: 6 | B12: Cost base benchmarked | C12: Manual | D12: Not started | F12: =IF(AND(EXACT(D12,"Met"),LEN(TRIM(I12))>1,LEN(TRIM(J12))>1),1,0) | G12: Management accounts and peer cost data with sources. | H12: No | L12: =IF(D12<>"Met","",IF(F12=1,"Evidenced","Marked Met without evidence location or sign-off: not counted"))
A13: 7 | B13: Stress tests run and documented | C13: Manual | D13: Not started | F13: =IF(AND(EXACT(D13,"Met"),LEN(TRIM(I13))>1,LEN(TRIM(J13))>1),1,0) | G13: Downside and Severe results and the Sensitivity table, reviewed and minuted. | H13: Yes | L13: =IF(D13<>"Met","",IF(F13=1,"Evidenced","Marked Met without evidence location or sign-off: not counted"))
A14: 8 | B14: FX and pass-through assumptions validated | C14: Manual | D14: Not started | F14: =IF(AND(EXACT(D14,"Met"),LEN(TRIM(I14))>1,LEN(TRIM(J14))>1),1,0) | G14: Pricing history after past depreciation; FX_Exposure reviewed. | H14: No | L14: =IF(D14<>"Met","",IF(F14=1,"Evidenced","Marked Met without evidence location or sign-off: not counted"))
A15: 9 | B15: Funding plan supported by term sheets | C15: Manual | D15: Not started | F15: =IF(AND(EXACT(D15,"Met"),LEN(TRIM(I15))>1,LEN(TRIM(J15))>1),1,0) | G15: Signed term sheets or commitment letters for equity and debt. | H15: Yes | L15: =IF(D15<>"Met","",IF(F15=1,"Evidenced","Marked Met without evidence location or sign-off: not counted"))
A16: 10 | B16: No covenant breach in the active scenario (monthly covenants and annual DSCR) | C16: Auto | E16: =IFERROR(IF(AND(KPIs!$C$64=0,KPIs!$C$65=0),"Met","Not met"),"Not met") | F16: =IF(E16="Met",1,0) | G16: Automatic: no month in breach on the Covenants sheet and no year with DSCR below the minimum (KPIs). | H16: Yes | L16: ="Computed in the model"
A17: 11 | B17: Downside survivable without unplanned equity | C17: Manual | D17: Not started | F17: =IF(AND(EXACT(D17,"Met"),LEN(TRIM(I17))>1,LEN(TRIM(J17))>1),1,0) | G17: Downside peak equity compared with committed funding, documented. | H17: Yes | L17: =IF(D17<>"Met","",IF(F17=1,"Evidenced","Marked Met without evidence location or sign-off: not counted"))
A18: 12 | B18: Valuation assumptions reviewed | C18: Manual | D18: Not started | F18: =IF(AND(EXACT(D18,"Met"),LEN(TRIM(I18))>1,LEN(TRIM(J18))>1),1,0) | G18: Discount rate, terminal growth and exit multiple justified in writing. | H18: No | L18: =IF(D18<>"Met","",IF(F18=1,"Evidenced","Marked Met without evidence location or sign-off: not counted"))
A19: 13 | B19: Positive lifetime contribution in every tier | C19: Auto | E19: =IFERROR(IF(MIN(Unit_Economics!C20,Unit_Economics!D20,Unit_Economics!E20,Unit_Economics!F20,Unit_Economics!G20)>0,"Met","Not met"),"Not met") | F19: =IF(E19="Met",1,0) | G19: Automatic: Unit_Economics. | H19: Yes | L19: ="Computed in the model"
A20: 14 | B20: Market data sourced and graded (Source_Register) | C20: Manual | D20: Not started | F20: =IF(AND(EXACT(D20,"Met"),LEN(TRIM(I20))>1,LEN(TRIM(J20))>1),1,0) | G20: Every market figure used has a VERIFIED status (Source_Register). | H20: No | L20: =IF(D20<>"Met","",IF(F20=1,"Evidenced","Marked Met without evidence location or sign-off: not counted"))
A21: 15 | B21: Tax and accounting treatment reviewed | C21: Manual | D21: Not started | F21: =IF(AND(EXACT(D21,"Met"),LEN(TRIM(I21))>1,LEN(TRIM(J21))>1),1,0) | G21: Written review by an accountant of revenue recognition, ECL and tax (the model treatment is not an IFRS determination). | H21: Yes | L21: =IF(D21<>"Met","",IF(F21=1,"Evidenced","Marked Met without evidence location or sign-off: not counted"))
A22: 16 | B22: Legal and regulatory review (consumer credit, data, mobile money) | C22: Manual | D22: Not started | F22: =IF(AND(EXACT(D22,"Met"),LEN(TRIM(I22))>1,LEN(TRIM(J22))>1),1,0) | G22: Legal opinion or regulatory checklist signed by counsel. | H22: Yes | L22: =IF(D22<>"Met","",IF(F22=1,"Evidenced","Marked Met without evidence location or sign-off: not counted"))
A23: 17 | B23: Workbook tested in Microsoft Excel | C23: Manual | D23: Not started | F23: =IF(AND(EXACT(D23,"Met"),LEN(TRIM(I23))>1,LEN(TRIM(J23))>1),1,0) | G23: Test log: opens, recalculates, master check OK, no circular references. | H23: Yes | L23: =IF(D23<>"Met","",IF(F23=1,"Evidenced","Marked Met without evidence location or sign-off: not counted"))
A24: 18 | B24: Credit engine running on actual company data | C24: Auto | E24: =IFERROR(IF(AND(Credit_Assumptions!$C$5=2,Checks!$C$50=0,MAX(COUNT(Credit_Input!$D$8:$D$67),COUNT(Credit_Input!$D$72:$D$131),COUNT(Credit_Input!$D$136:$D$195),COUNT(Credit_Input!$D$200:$D$259),COUNT(Credit_Input!$D$264:$D$323))>=12),"Met","Not met"),"Not met") | F24: =IF(E24="Met",1,0) | G24: Automatic: Actual mode with at least 12 months of Credit_Input history in one tier. | H24: Yes | L24: ="Computed in the model"
A25: 19 | B25: IFRS 9 / ECL validated by auditor or independent reviewer | C25: Manual | D25: Not started | F25: =IF(AND(EXACT(D25,"Met"),LEN(TRIM(I25))>1,LEN(TRIM(J25))>1),1,0) | G25: Auditor's or reviewer's report; indicative ECL and PD proxies are not IFRS 9 measures. | H25: No | L25: =IF(D25<>"Met","",IF(F25=1,"Evidenced","Marked Met without evidence location or sign-off: not counted"))
A26: 20 | B26: Consumer protection evidenced | C26: Auto | E26: =IFERROR(IF(AND(Consumer_Risk!$C$5=1,Checks!$C$49=0,AND(Consumer_Risk!$C$14="Validated",Consumer_Risk!$C$15="Validated",Consumer_Risk!$D$14="Validated",Consumer_Risk!$D$15="Validated",Consumer_Risk!$E$14="Validated",Consumer_Risk!$E$15="Validated",Consumer_Risk!$F$14="Validated",Consumer_Risk!$F$15="Validated",Consumer_Risk!$G$14="Validated",Consumer_Risk!$G$15="Validated"),Checks!$C$53=0),"Met","Not met"),"Not met") | F26: =IF(E26="Met",1,0) | G26: Automatic: affordability reviewed, no flags, PERFORM and consumer-protection evidence validated, PERFORM_2026 results loaded. | H26: Yes | L26: ="Computed in the model"
A27: 21 | B27: Outcome-linked RBF supported by data | C27: Auto | E27: =IFERROR(IF(Vintage_Dashboard!$Q$6=1,"Met","Not met"),"Not met") | F27: =IF(E27="Met",1,0) | G27: Automatic: validated ownership-at-2x data. | H27: No | L27: ="Computed in the model"
A28: 22 | B28: Data reconciliation (actual DPD buckets = gross receivables) | C28: Auto | E28: =IFERROR(IF(AND(Credit_Assumptions!$C$5=2,Checks!$C$50=0,Checks!$C$19=0),"Met","Not met"),"Not met") | F28: =IF(E28="Met",1,0) | G28: Automatic: Actual mode, data supplied, buckets reconcile. | H28: Yes | L28: ="Computed in the model"
A29: 23 | B29: Lender underwriting pack assembled | C29: Manual | D29: Not started | F29: =IF(AND(EXACT(D29,"Met"),LEN(TRIM(I29))>1,LEN(TRIM(J29))>1),1,0) | G29: Cohort tables, PAYGo PERFORM 2026 KPIs (PERFORM_2026), covenant history, borrowing-base reports. | H29: No | L29: =IF(D29<>"Met","",IF(F29=1,"Evidenced","Marked Met without evidence location or sign-off: not counted"))
A31: DECISION RULE (evidence only; no judgement enters these cells)
B32: Critical gates met | C32: =SUMPRODUCT((H7:H29="Yes")*(F7:F29=1))
B33: Critical gates | C33: =13
B34: Failed tests (automatic gates that measure the business or the model) | C34: =IF(F7=0,1,0)+IF(F16=0,1,0)+IF(F19=0,1,0)
B35: Decision | C35: =IF(C34>0,"STOP",IF(C4=23,"GO",IF(C32=C33,"CONDITIONAL GO","STOP")))
B36: Reason | C36: =IF(C34>0,"Failed test: "&LEFT(IF(F7=0,"Model integrity (master check OK); ","")&IF(F16=0,"No covenant breach in the active scenario (monthly covenants and annual DSCR); ","")&IF(F19=0,"Positive lifetime contribution in every tier; ",""),LEN(IF(F7=0,"Model integrity (master check OK); ","")&IF(F16=0,"No covenant breach in the active scenario (monthly covenants and annual DSCR); ","")&IF(F19=0,"Positive lifetime contribution in every tier; ",""))-2),IF(C4=23,"All 23 gates met with evidence",IF(C32=C33,"All critical gates met; open gates to set as conditions: "&(23-C4),"Evidence incomplete: "&(C33-C32)&" of "&C33&" critical gates not met")))
B38: STOP when any failed test exists (master check, a monthly covenant breach or a year with DSCR below the minimum in the active scenario, negative lifetime contribution in a tier).
B39: GO only when all gates are met with evidence. CONDITIONAL GO when every critical gate is met; the open gates become conditions.
B40: Otherwise STOP: evidence incomplete. A STOP on incomplete evidence says the file is not ready for a decision, not that the business fails.
B41: GO is a statement about the completeness of the evidence for an investment committee. It is never an investment recommendation.

Sheet Inputs
A1: Inputs
A2: [ASSUMPTION] Blue = input. Yellow = key assumption to review first. All defaults illustrative.
A3: Input | B3: Unit | C3: Value | D3: Note | E3: Provenance
A4: Scenario & settings
A5: Active scenario (1 = Base, 2 = Downside, 3 = Severe) | B5: # | C5: 1 | D5: Drives the levers on the Scenarios sheet. | E5: MODEL ASSUMPTION
A6: First model month (period end) | B6: date | C6: =DATE(2027,1,31) | D6: Period-end date of month 1. | E6: MODEL ASSUMPTION
A7: Local currency label | B7: text | C7: LCY | D7: Display only. | E7: MODEL ASSUMPTION
A9: Macro
A10: Opening FX rate | B10: LCY per USD | C10: 130 | D10: Illustrative placeholder: replace with company data. | E10: MODEL ASSUMPTION
A11: Local inflation (opex indexation) | B11: % p.a. | C11: 0.06 | D11: Illustrative placeholder: replace with company data. | E11: MODEL ASSUMPTION
A12: Corporate income tax rate | B12: % | C12: 0.3 | D12: Simplified: unlimited loss carry-forward, tax paid in the month it arises. | E12: MODEL ASSUMPTION
A13: Annual price increase on NEW PAYGo contracts | B13: % p.a. | C13: 0.05 | D13: Existing contracts keep their price plan. | E13: MODEL ASSUMPTION
A14: Pass-through of LCY depreciation into new-contract prices | B14: % | C14: 0.5 | D14: Share of cumulative FX depreciation passed into prices of NEW contracts (0% = none, 100% = USD-indexed). | E14: MODEL ASSUMPTION
A16: Sales volume: all tiers (Base, before scenario multiplier; split by Products mix)
A17: Units sold: Year 1 | B17: units | C17: 12000 | D17: Illustrative placeholder: replace with company data. | E17: MODEL ASSUMPTION
A18: Units sold: Year 2 | B18: units | C18: 24000 | D18: Illustrative placeholder: replace with company data. | E18: MODEL ASSUMPTION
A19: Units sold: Year 3 | B19: units | C19: 36000 | D19: Illustrative placeholder: replace with company data. | E19: MODEL ASSUMPTION
A20: Units sold: Year 4 | B20: units | C20: 45000 | D20: Illustrative placeholder: replace with company data. | E20: MODEL ASSUMPTION
A21: Units sold: Year 5 | B21: units | C21: 50000 | D21: Illustrative placeholder: replace with company data. | E21: MODEL ASSUMPTION
A23: Operating costs
A24: Mobile-money / payment processing fees | B24: % of cash collected | C24: 0.02 | D24: Illustrative placeholder: replace with company data. | E24: MODEL ASSUMPTION
A25: Customer service & collections cost | B25: LCY / active account / month | C25: 150 | D25: Illustrative placeholder: replace with company data. | E25: MODEL ASSUMPTION
A26: Staff costs (fixed, month-1 level) | B26: LCY / month | C26: 26000000 | D26: Illustrative placeholder: replace with company data. | E26: MODEL ASSUMPTION
A27: G&A, rent, IT, licences (fixed, month-1 level) | B27: LCY / month | C27: 10400000 | D27: Illustrative placeholder: replace with company data. | E27: MODEL ASSUMPTION
A28: Freight, duty & clearing on hardware | B28: % of USD FOB cost | C28: 0.2 | D28: Illustrative placeholder: replace with company data. | E28: MODEL ASSUMPTION
A30: Repossession & results-based financing (RBF)
A31: Months from default to resale of repossessed unit | B31: months | C31: 3 | D31: Illustrative placeholder: replace with company data. | E31: MODEL ASSUMPTION
A32: RBF programme active (1 = yes, 0 = no) | B32: switch | C32: 1 | D32: RBF per unit is set by tier on Products. Recognised as other income when received (cash basis). | E32: MODEL ASSUMPTION
A33: Months from sale to RBF disbursement (verification lag) | B33: months | C33: 6 | D33: Illustrative placeholder: replace with company data. | E33: MODEL ASSUMPTION
A34: RBF design mode (1 sales, 2 repayment-linked, 3 ownership-linked, 4 hybrid) | B34: # | C34: 1 | D34: See RBF_Engine. Ownership-linked RBF pays nothing until validated ownership-at-2x data exist. | E34: MODEL ASSUMPTION
A35: Repayment rate at verification for 100% of repayment-linked RBF | B35: % | C35: 0.8 | D35: Illustrative placeholder: replace with company data. | E35: MODEL ASSUMPTION
A36: Hybrid weight: sales-based | B36: % | C36: 0.5 | D36: Hybrid weights must sum to 100% (Checks). | E36: MODEL ASSUMPTION
A37: Hybrid weight: repayment-linked | B37: % | C37: 0.5 | D37: Hybrid weights must sum to 100% (Checks). | E37: MODEL ASSUMPTION
A38: Hybrid weight: ownership-linked | B38: % | C38: 0 | D38: Hybrid weights must sum to 100% (Checks). | E38: MODEL ASSUMPTION
A39: Validated ownership-at-2x evidence available (1 = yes) | B39: switch | C39: 0 | D39: Set to 1 ONLY when Vintage_Input holds validated ownership-at-2x data. Never infer this KPI. | E39: MODEL ASSUMPTION
A41: Working capital & capex
A42: Inventory cover | B42: months of hardware COGS | C42: 2 | D42: Illustrative placeholder: replace with company data. | E42: MODEL ASSUMPTION
A43: Supplier credit on hardware | B43: days | C43: 60 | D43: Illustrative placeholder: replace with company data. | E43: MODEL ASSUMPTION
A44: Fixed capex (vehicles, IT, depots, month-1 level) | B44: LCY / month | C44: 900000 | D44: Illustrative placeholder: replace with company data. | E44: MODEL ASSUMPTION
A45: Depreciation life of fixed capex | B45: months | C45: 36 | D45: Illustrative placeholder: replace with company data. | E45: MODEL ASSUMPTION
A46: Minimum operating cash balance | B46: LCY | C46: 100000000 | D46: Any shortfall is covered by an automatic equity top-up = funding requirement. | E46: MODEL ASSUMPTION
A48: Financing
A49: Initial equity (month 1, all shareholders) | B49: LCY | C49: 1300000000 | D49: Illustrative placeholder: replace with company data. | E49: MODEL ASSUMPTION
A50: USD term loan: amount | B50: USD | C50: 5000000 | D50: Illustrative placeholder: replace with company data. | E50: MODEL ASSUMPTION
A51: USD term loan: drawdown month | B51: month # | C51: 6 | D51: Illustrative placeholder: replace with company data. | E51: MODEL ASSUMPTION
A52: USD term loan: interest rate | B52: % p.a. | C52: 0.1 | D52: Illustrative placeholder: replace with company data. | E52: MODEL ASSUMPTION
A53: USD term loan: grace period after drawdown | B53: months | C53: 12 | D53: Illustrative placeholder: replace with company data. | E53: MODEL ASSUMPTION
A54: USD term loan: amortisation period | B54: months | C54: 36 | D54: Illustrative placeholder: replace with company data. | E54: MODEL ASSUMPTION
A55: Receivables facility (LCY): limit | B55: LCY | C55: 6500000000 | D55: Drawn as needed to hold minimum cash (cash sweep), capped at the borrowing base and the limit. Borrowing base = sum over tiers of advance rate x eligible receivables. | E55: MODEL ASSUMPTION
A56: Receivables facility: interest rate | B56: % p.a. | C56: 0.16 | D56: Illustrative placeholder: replace with company data. | E56: MODEL ASSUMPTION
A57: Receivables facility: first available month | B57: month # | C57: 7 | D57: Illustrative placeholder: replace with company data. | E57: MODEL ASSUMPTION
A59: Receivables financing structure
A60: Structure (1 = warehouse facility, 2 = securitisation / term ABS) | B60: # | C60: 1 | D60: Both are modelled on balance sheet. Option 2 applies the rate, advance-rate haircut and upfront fee below. | E60: MODEL ASSUMPTION
A61: Securitisation: all-in interest rate | B61: % p.a. | C61: 0.13 | D61: Illustrative placeholder: replace with company data. | E61: MODEL ASSUMPTION
A62: Securitisation: advance-rate multiplier vs warehouse | B62: x | C62: 0.95 | D62: Illustrative placeholder: replace with company data. | E62: MODEL ASSUMPTION
A63: Securitisation: upfront structuring fee on new drawings | B63: % | C63: 0.02 | D63: Paid the month after the drawing (avoids a circular reference). | E63: MODEL ASSUMPTION
A65: Other revenue streams (digital loans, other services)
A66: Net revenue per active PAYGo account (month-1 level) | B66: LCY / account / month | C66: 0 | D66: Simplification: take-rate revenue only, no on-balance-sheet lending. 0 = switched off. | E66: MODEL ASSUMPTION
A67: Gross margin on other revenue | B67: % | C67: 0.6 | D67: Illustrative placeholder: replace with company data. | E67: MODEL ASSUMPTION
A69: Lender covenants (tested on Covenants sheet)
A70: Minimum trailing-3-month collection rate | B70: % | C70: 0.7 | D70: Illustrative placeholder: replace with company data. | E70: MODEL ASSUMPTION
A71: Maximum receivables at risk / gross receivables | B71: % | C71: 0.15 | D71: Illustrative placeholder: replace with company data. | E71: MODEL ASSUMPTION
A72: Maximum debt / book equity | B72: x | C72: 3 | D72: Illustrative placeholder: replace with company data. | E72: MODEL ASSUMPTION
A73: Minimum annual DSCR (years with debt service) | B73: x | C73: 1.2 | D73: Illustrative placeholder: replace with company data. | E73: MODEL ASSUMPTION
A74: Minimum liquidity: cash before equity top-up | B74: LCY | C74: 50000000 | D74: Illustrative placeholder: replace with company data. | E74: MODEL ASSUMPTION
A75: Maximum 30+ DPD receivables / gross receivables | B75: % | C75: 0.25 | D75: Illustrative placeholder: replace with company data. | E75: MODEL ASSUMPTION
A76: Maximum 90+ DPD receivables / gross receivables | B76: % | C76: 0.18 | D76: Illustrative placeholder: replace with company data. | E76: MODEL ASSUMPTION
A78: Valuation & transaction
A79: Discount rate for DCF (LCY, nominal) | B79: % p.a. | C79: 0.22 | D79: Should reflect LCY risk-free rate, country and company risk premia. | E79: MODEL ASSUMPTION
A80: Terminal growth rate (LCY, nominal) | B80: % p.a. | C80: 0.05 | D80: Illustrative placeholder: replace with company data. | E80: MODEL ASSUMPTION
A81: Investor ticket (part of initial equity) | B81: USD | C81: 4000000 | D81: Illustrative placeholder: replace with company data. | E81: MODEL ASSUMPTION
A82: Pre-money equity valuation | B82: USD | C82: 8000000 | D82: Illustrative placeholder: replace with company data. | E82: MODEL ASSUMPTION
A83: Exit valuation method (1 = EV/EBITDA, 2 = Price/Book) | B83: # | C83: 1 | D83: Illustrative placeholder: replace with company data. | E83: MODEL ASSUMPTION
A84: Exit EV / EBITDA multiple (end of Year 5) | B84: x | C84: 6 | D84: Illustrative placeholder: replace with company data. | E84: MODEL ASSUMPTION
A85: Exit price / book equity multiple (end of Year 5) | B85: x | C85: 1.5 | D85: Illustrative placeholder: replace with company data. | E85: MODEL ASSUMPTION
A87: Covenant definition
A88: DSCR covenant in the facility terms (0 = none, 1 = operating cash flow basis, 2 = cash basis excluding growth in PAYGo receivables) | B88: # | C88: 1 | D88: 1 keeps the test as drafted: operating cash flow absorbs the growth of the receivables book, so a growing PAYGo company fails it. 2 treats the funding of new receivables as investment (financed by the facility). 0 = the facility has no DSCR test. Use the facility's own definition. | E88: MODEL ASSUMPTION

Sheet Products
A1: Product range & PAYGo price plans: MTF Tiers 1-5
A2: [ASSUMPTION] One column per tier. Tier labels follow the MTF capacity attribute only (indicative). Blue = input.
A4: Parameter | B4: Unit | C4: Tier 1 | D4: Tier 2 | E4: Tier 3 | F4: Tier 4 | G4: Tier 5 | H4: Notes | I4: Provenance
A5: Product specification
A6: Product name | B6: text | C6: Tier 1: Pico solar kit | D6: Tier 2: SHS with TV | E6: Tier 3: Large SHS + DC fridge | F6: Tier 4: Solar inverter + lithium (~1.2 kWp / 5 kWh) | G6: Tier 5: Solar inverter + lithium (~3 kWp / 10 kWh) | H6: Illustrative placeholder: replace with company data. | I6: MODEL ASSUMPTION
A7: MTF capacity tier (indicative) | B7: tier | C7: 1 | D7: 2 | E7: 3 | F7: 4 | G7: 5 | H7: Capacity minimums: T1 ≥3 W and ≥12 Wh/day; T2 ≥50 W and ≥200 Wh/day; T3 ≥200 W and ≥1.0 kWh/day; T4 ≥800 W and ≥3.4 kWh/day; T5 ≥2 kW and ≥8.2 kWh/day (ESMAP MTF; to be checked against the framework report). | I7: UNVERIFIED
A8: PV array size | B8: Wp | C8: 10 | D8: 80 | E8: 300 | F8: 1200 | G8: 3000 | H8: Illustrative placeholder: replace with company data. | I8: MODEL ASSUMPTION
A9: Battery capacity | B9: Wh | C9: 40 | D9: 300 | E9: 1500 | F9: 5000 | G9: 10000 | H9: Illustrative placeholder: replace with company data. | I9: MODEL ASSUMPTION
A10: Typical loads / appliances | B10: text | C10: 1-3 lamps, phone charging, radio | D10: 4-6 lamps, radio, phone, 24-32" DC TV | E10: Lighting, TV, DC fridge, fan | F10: AC loads: TV, fridge, fans, small tools | G10: Full household AC loads, freezer, productive-use equipment | H10: Illustrative placeholder: replace with company data. | I10: MODEL ASSUMPTION
A11: Target customer segment | B11: text | C11: Rural, low income, first-time PAYGo | D11: Rural / peri-urban households | E11: Peri-urban households, kiosks | F11: Urban households & SMEs with weak grid | G11: Upper-income households, SMEs, productive use | H11: Illustrative placeholder: replace with company data. | I11: MODEL ASSUMPTION
A12: PAYGo price plan
A13: Cash (list) price | B13: LCY | C13: 6500 | D13: 39000 | E13: 117000 | F13: 390000 | G13: 845000 | H13: Price if paid upfront. Basis of hardware revenue. | I13: MODEL ASSUMPTION
A14: Down payment (deposit) | B14: LCY | C14: 1000 | D14: 4000 | E14: 17550 | F14: 78000 | G14: 211250 | H14: Illustrative placeholder: replace with company data. | I14: MODEL ASSUMPTION
A15: PAYGo daily rate | B15: LCY / day | C15: 25 | D15: 77 | E15: 173 | F15: 445 | G15: 694 | H15: Illustrative placeholder: replace with company data. | I15: MODEL ASSUMPTION
A16: PAYGo tenor | B16: months | C16: 12 | D16: 24 | E16: 30 | F16: 36 | G16: 48 | H16: Maximum 60 months (horizon of the curves). | I16: MODEL ASSUMPTION
A17: Cost to serve & acquisition
A18: Hardware FOB cost | B18: USD / unit | C18: 25 | D18: 150 | E18: 450 | F18: 1400 | G18: 3200 | H18: Illustrative placeholder: replace with company data. | I18: MODEL ASSUMPTION
A19: Installation & last-mile logistics | B19: LCY / unit | C19: 0 | D19: 500 | E19: 2500 | F19: 15000 | G19: 30000 | H19: Indexed to local inflation. | I19: MODEL ASSUMPTION
A20: Agent / installer commission per sale | B20: LCY / unit | C20: 500 | D20: 2000 | E20: 5000 | F20: 12000 | G20: 20000 | H20: Indexed to local inflation. | I20: MODEL ASSUMPTION
A21: Marketing & other acquisition cost per sale | B21: LCY / unit | C21: 300 | D21: 1000 | E21: 2500 | F21: 6000 | G21: 10000 | H21: Indexed to local inflation. | I21: MODEL ASSUMPTION
A22: Warranty & after-sales provision | B22: % of landed HW cost | C22: 0.03 | D22: 0.05 | E22: 0.05 | F22: 0.06 | G22: 0.06 | H22: Illustrative placeholder: replace with company data. | I22: MODEL ASSUMPTION
A23: Sales mix | B23: % of units | C23: 0.3 | D23: 0.35 | E23: 0.2 | F23: 0.1 | G23: 0.05 | H23: Must sum to 100% (see Checks). | I23: MODEL ASSUMPTION
A24: Credit risk & recovery
A25: Base monthly default hazard | B25: % of paying accounts / month | C25: 0.035 | D25: 0.026 | E25: 0.019 | F25: 0.013 | G25: 0.01 | H25: Share of still-paying accounts that stop paying each month. Calibrate to the company's own cohort curves. | I25: MODEL ASSUMPTION
A26: Base collection rate on paying accounts | B26: % of instalment | C26: 0.88 | D26: 0.88 | E26: 0.9 | F26: 0.92 | G26: 0.93 | H26: Captures partial / late payment by accounts that keep paying. | I26: MODEL ASSUMPTION
A27: Repossession rate of defaulted units | B27: % of defaults | C27: 0 | D27: 0.2 | E27: 0.4 | F27: 0.6 | G27: 0.7 | H27: Illustrative placeholder: replace with company data. | I27: MODEL ASSUMPTION
A28: Gross resale value of repossessed unit | B28: % of cash price | C28: 0.2 | D28: 0.25 | E28: 0.35 | F28: 0.45 | G28: 0.5 | H28: Before recovery costs (Credit_Assumptions). Net proceeds are recognised as recoveries against credit losses. | I28: MODEL ASSUMPTION
A29: Subsidy & funding
A30: RBF per unit sold | B30: USD / unit | C30: 5 | D30: 15 | E30: 25 | F30: 0 | G30: 0 | H30: Set to 0 for tiers outside the programme. | I30: MODEL ASSUMPTION
A31: Receivables facility advance rate | B31: % of eligible receivables | C31: 0.5 | D31: 0.7 | E31: 0.7 | F31: 0.75 | G31: 0.75 | H31: Lenders often apply different advance rates by product. | I31: MODEL ASSUMPTION
A32: Derived price-plan metrics (do not edit)
A33: Monthly instalment (daily rate x 365/12) | B33: LCY / month | C33: =Products!$C$15*365/12 | D33: =Products!$D$15*365/12 | E33: =Products!$E$15*365/12 | F33: =Products!$F$15*365/12 | G33: =Products!$G$15*365/12
A34: Total PAYGo contract value | B34: LCY | C34: =Products!$C$14+Products!$C$33*Products!$C$16 | D34: =Products!$D$14+Products!$D$33*Products!$D$16 | E34: =Products!$E$14+Products!$E$33*Products!$E$16 | F34: =Products!$F$14+Products!$F$33*Products!$F$16 | G34: =Products!$G$14+Products!$G$33*Products!$G$16
A35: PAYGo price premium over cash price | B35: LCY | C35: =Products!$C$34-Products!$C$13 | D35: =Products!$D$34-Products!$D$13 | E35: =Products!$E$34-Products!$E$13 | F35: =Products!$F$34-Products!$F$13 | G35: =Products!$G$34-Products!$G$13
A36: PAYGo premium as % of cash price | B36: % | C36: =IF(Products!$C$13=0,0,Products!$C$35/Products!$C$13) | D36: =IF(Products!$D$13=0,0,Products!$D$35/Products!$D$13) | E36: =IF(Products!$E$13=0,0,Products!$E$35/Products!$E$13) | F36: =IF(Products!$F$13=0,0,Products!$F$35/Products!$F$13) | G36: =IF(Products!$G$13=0,0,Products!$G$35/Products!$G$13)
A37: Down payment as % of cash price | B37: % | C37: =IF(Products!$C$13=0,0,Products!$C$14/Products!$C$13) | D37: =IF(Products!$D$13=0,0,Products!$D$14/Products!$D$13) | E37: =IF(Products!$E$13=0,0,Products!$E$14/Products!$E$13) | F37: =IF(Products!$F$13=0,0,Products!$F$14/Products!$F$13) | G37: =IF(Products!$G$13=0,0,Products!$G$14/Products!$G$13)
A38: Amount financed at sale (cash price: deposit) | B38: LCY | C38: =Products!$C$13-Products!$C$14 | D38: =Products!$D$13-Products!$D$14 | E38: =Products!$E$13-Products!$E$14 | F38: =Products!$F$13-Products!$F$14 | G38: =Products!$G$13-Products!$G$14
A39: Implied annual financing rate (nominal APR) | B39: % p.a. | C39: =IFERROR(RATE(Products!$C$16,-Products!$C$33,Products!$C$38)*12,0) | D39: =IFERROR(RATE(Products!$D$16,-Products!$D$33,Products!$D$38)*12,0) | E39: =IFERROR(RATE(Products!$E$16,-Products!$E$33,Products!$E$38)*12,0) | F39: =IFERROR(RATE(Products!$F$16,-Products!$F$33,Products!$F$38)*12,0) | G39: =IFERROR(RATE(Products!$G$16,-Products!$G$33,Products!$G$38)*12,0) | H39: Rate equating the financed amount with the instalment stream (consumer-protection disclosure).
A40: Cash price in USD at opening FX | B40: USD | C40: =Products!$C$13/Inputs!$C$10 | D40: =Products!$D$13/Inputs!$C$10 | E40: =Products!$E$13/Inputs!$C$10 | F40: =Products!$F$13/Inputs!$C$10 | G40: =Products!$G$13/Inputs!$C$10
A41: Scenario monthly default hazard | B41: % | C41: =Products!$C$25*Scenarios!$G$6 | D41: =Products!$D$25*Scenarios!$G$6 | E41: =Products!$E$25*Scenarios!$G$6 | F41: =Products!$F$25*Scenarios!$G$6 | G41: =Products!$G$25*Scenarios!$G$6
A42: Scenario collection rate on paying accounts | B42: % | C42: =MIN(1,Products!$C$26*Scenarios!$G$7) | D42: =MIN(1,Products!$D$26*Scenarios!$G$7) | E42: =MIN(1,Products!$E$26*Scenarios!$G$7) | F42: =MIN(1,Products!$F$26*Scenarios!$G$7) | G42: =MIN(1,Products!$G$26*Scenarios!$G$7)
A43: Landed hardware cost at opening FX (scenario) | B43: LCY / unit | C43: =Products!$C$18*(1+Inputs!$C$28)*Inputs!$C$10*Scenarios!$G$9 | D43: =Products!$D$18*(1+Inputs!$C$28)*Inputs!$C$10*Scenarios!$G$9 | E43: =Products!$E$18*(1+Inputs!$C$28)*Inputs!$C$10*Scenarios!$G$9 | F43: =Products!$F$18*(1+Inputs!$C$28)*Inputs!$C$10*Scenarios!$G$9 | G43: =Products!$G$18*(1+Inputs!$C$28)*Inputs!$C$10*Scenarios!$G$9
A44: Customer acquisition cost (commission + marketing) | B44: LCY / unit | C44: =Products!$C$20+Products!$C$21 | D44: =Products!$D$20+Products!$D$21 | E44: =Products!$E$20+Products!$E$21 | F44: =Products!$F$20+Products!$F$21 | G44: =Products!$G$20+Products!$G$21
A45: PERFORM ownership horizon (2 x tenor) | B45: months | C45: =2*Products!$C$16 | D45: =2*Products!$D$16 | E45: =2*Products!$E$16 | F45: =2*Products!$F$16 | G45: =2*Products!$G$16 | H45: Each tier references its own tenor (avoids the cross-tier reference error found in an earlier workbook).
A46: Hardware gross margin on cash price (month 1) | B46: % | C46: =IF(Products!$C$13=0,0,1-(Products!$C$43+Products!$C$19)/Products!$C$13) | D46: =IF(Products!$D$13=0,0,1-(Products!$D$43+Products!$D$19)/Products!$D$13) | E46: =IF(Products!$E$13=0,0,1-(Products!$E$43+Products!$E$19)/Products!$E$13) | F46: =IF(Products!$F$13=0,0,1-(Products!$F$43+Products!$F$19)/Products!$F$13) | G46: =IF(Products!$G$13=0,0,1-(Products!$G$43+Products!$G$19)/Products!$G$13)

Sheet Scenarios
A1: Scenario levers
A2: [ASSUMPTION] Multipliers / overrides on Base inputs. ACTIVE column follows the selector on Inputs.
A5: Lever | B5: Unit | C5: Base | D5: Downside | E5: Severe | G5: ACTIVE | I5: Provenance
A6: Default hazard multiplier | B6: x | C6: 1 | D6: 1.3 | E6: 1.75 | G6: =CHOOSE(MAX(1,MIN(3,INT(N(Inputs!$C$5)))),C6,D6,E6) | I6: MODEL ASSUMPTION
A7: Collection-rate multiplier (paying accounts) | B7: x | C7: 1 | D7: 0.97 | E7: 0.92 | G7: =CHOOSE(MAX(1,MIN(3,INT(N(Inputs!$C$5)))),C7,D7,E7) | I7: MODEL ASSUMPTION
A8: Sales volume multiplier | B8: x | C8: 1 | D8: 0.9 | E8: 0.75 | G8: =CHOOSE(MAX(1,MIN(3,INT(N(Inputs!$C$5)))),C8,D8,E8) | I8: MODEL ASSUMPTION
A9: Hardware cost multiplier (USD) | B9: x | C9: 1 | D9: 1.05 | E9: 1.1 | G9: =CHOOSE(MAX(1,MIN(3,INT(N(Inputs!$C$5)))),C9,D9,E9) | I9: MODEL ASSUMPTION
A10: LCY depreciation vs USD | B10: % p.a. | C10: 0.05 | D10: 0.12 | E10: 0.25 | G10: =CHOOSE(MAX(1,MIN(3,INT(N(Inputs!$C$5)))),C10,D10,E10) | I10: MODEL ASSUMPTION
A12: Scenario name | C12: Base | D12: Downside | E12: Severe | G12: =IF(IFERROR(AND(ISNUMBER(Inputs!$C$5),Inputs!$C$5=INT(Inputs!$C$5),Inputs!$C$5>=1,Inputs!$C$5<=3),FALSE),CHOOSE(Inputs!$C$5,C12,D12,E12),"INVALID SCENARIO SELECTOR")
A13: Input set loaded on Inputs, Products and Credit_Assumptions | C13: Illustrative (model assumptions) | F13: Active case | G13: =C13&", "&G12
A14: Downside / Severe are illustrative stress settings. Calibrate to the company's cohort history and sector data.
A15: Context: the ESMAP Off-Grid Solar Market Trends Report 2024 is reported to give an average PAYGo collection rate of about 62% for 2021-2023 (Source_Register E1-14, PENDING PRIMARY DOCUMENT). A collection rate, not the PERFORM Repayment Rate.
A18: Scenario architecture: ACTUAL is never changed by levers; ASSUMPTION is the input set; FORECAST is computed
A19: Layer | B19: Type | C19: Where it lives | G19: Status in this workbook
A20: Actual (history) | B20: ACTUAL | C20: Credit_Input, Vintage_Input, PERFORM_2026 section C; read on Credit_Portfolio and Vintage_Dashboard | G20: =IF((COUNT(Credit_Input!$D$8:$D$67)+COUNT(Credit_Input!$D$72:$D$131)+COUNT(Credit_Input!$D$136:$D$195)+COUNT(Credit_Input!$D$200:$D$259)+COUNT(Credit_Input!$D$264:$D$323)+COUNT(Vintage_Input!$C$9:$C$68)+COUNT(Vintage_Input!$C$74:$C$133)+COUNT(Vintage_Input!$C$139:$C$198)+COUNT(Vintage_Input!$C$204:$C$263)+COUNT(Vintage_Input!$C$269:$C$328)+PERFORM_2026!$C$13+PERFORM_2026!$D$13+PERFORM_2026!$E$13+PERFORM_2026!$F$13+PERFORM_2026!$G$13)>0,"Loaded ("&(COUNT(Credit_Input!$D$8:$D$67)+COUNT(Credit_Input!$D$72:$D$131)+COUNT(Credit_Input!$D$136:$D$195)+COUNT(Credit_Input!$D$200:$D$259)+COUNT(Credit_Input!$D$264:$D$323)+COUNT(Vintage_Input!$C$9:$C$68)+COUNT(Vintage_Input!$C$74:$C$133)+COUNT(Vintage_Input!$C$139:$C$198)+COUNT(Vintage_Input!$C$204:$C$263)+COUNT(Vintage_Input!$C$269:$C$328)+PERFORM_2026!$C$13+PERFORM_2026!$D$13+PERFORM_2026!$E$13+PERFORM_2026!$F$13+PERFORM_2026!$G$13)&" records; levers do not apply)","Not loaded")
A21: Management case | B21: ASSUMPTION | C21: Inputs, Products, Credit_Assumptions as submitted by management | G21: =IF(Scenarios!$C$13="Management case","Loaded on the input sheets","Not loaded")
A22: Calibrated case | B22: ASSUMPTION (calibrated) | C22: Same input sheets after re-estimation against actual data and VERIFIED sources (Calibration) | G22: =IF(Scenarios!$C$13="Calibrated case","Loaded on the input sheets","Not loaded")
A23: Base | B23: FORECAST | C23: Loaded input set with Base levers (column C) | G23: =IF(Inputs!$C$5=1,"Active","")
A24: Downside | B24: FORECAST | C24: Loaded input set with Downside levers (column D) | G24: =IF(Inputs!$C$5=2,"Active","")
A25: Severe stress | B25: FORECAST | C25: Loaded input set with Severe levers (column E) | G25: =IF(Inputs!$C$5=3,"Active","")
A27: One input set is loaded at a time. The other set is kept outside the workbook (for the worked case: the case file and the book's comparison table). History is entered on the input templates only and is never overwritten by forecast levers.

Sheet Credit_Assumptions
A1: Credit assumptions: DPD buckets, stages, recovery, eligibility
A2: [ASSUMPTION] Drives Credit_Engine. Proxy = projection from the model's repayment curves; Actual = company data in Credit_Input. This is an analytical modelling treatment and does not constitute a determination of the applicable accounting treatment under IFRS.
A4: Data mode
A5: Credit data mode (1 = Proxy, 2 = Actual) | B5: # | C5: 1 | D5: Actual mode reads Credit_Input (company history) for reporting. Projections and the facility always use the proxy engine. | E5: MODEL ASSUMPTION
A7: Definitions
A8: Default definition | B8: days past due | C8: 180 | D8: Common PAYGo / lender convention; confirm against facility documents. | E8: MODEL ASSUMPTION
A9: Stage 2 threshold (significant increase in credit risk) | B9: DPD | C9: 30 | D9: Indicative IFRS 9-style staging. | E9: MODEL ASSUMPTION
A10: Stage 3 threshold (credit-impaired) | B10: DPD | C10: 90 | D10: Indicative IFRS 9-style staging. | E10: MODEL ASSUMPTION
A11: Borrowing-base eligibility: maximum DPD | B11: DPD | C11: 30 | D11: Receivables in buckets starting above this DPD are ineligible. | E11: MODEL ASSUMPTION
A13: Recovery, cures and ECL
A14: Repossession lag (link to Inputs) | B14: months | C14: =Inputs!$C$31
A15: Recovery cost (retrieval, refurbishment, resale) | B15: % of gross resale | C15: 0.15 | D15: Illustrative placeholder: replace with company data. | E15: MODEL ASSUMPTION
A16: Cure rate of Stage-2 balances (ECL only) | B16: % | C16: 0.3 | D16: The proxy engine assumes accounts that stop paying do not resume; cures enter only the indicative ECL. | E16: MODEL ASSUMPTION
A17: Discount rate for indicative ECL | B17: % p.a. | C17: 0.2 | D17: Illustrative placeholder: replace with company data. | E17: MODEL ASSUMPTION
A19: Proxy DPD distribution
A20: Paying accounts: share of balances current | B20: % | C20: 0.85 | D20: Remainder is 1-30 DPD. | E20: MODEL ASSUMPTION
A21: Receivables at risk: share 31-60 DPD | B21: % | C21: 0.25 | D21: Shares of receivables at risk must sum to 100% (Checks). | E21: MODEL ASSUMPTION
A22: Receivables at risk: share 61-90 DPD | B22: % | C22: 0.2 | D22: Shares of receivables at risk must sum to 100% (Checks). | E22: MODEL ASSUMPTION
A23: Receivables at risk: share 91-180 DPD | B23: % | C23: 0.25 | D23: Shares of receivables at risk must sum to 100% (Checks). | E23: MODEL ASSUMPTION
A24: Receivables at risk: share 180+ DPD | B24: % | C24: 0.3 | D24: Shares of receivables at risk must sum to 100% (Checks). | E24: MODEL ASSUMPTION
A26: Bucket table (derived: do not edit)
A27: DPD bucket | B27: Lower DPD | C27: Upper DPD | D27: Stage | E27: BB eligible | F27: In default | G27: 30+ DPD | H27: 90+ DPD | I27: Proxy share
A28: Current | B28: 0 | C28: 0 | D28: =IF(B28>Credit_Assumptions!$C$10,3,IF(B28>Credit_Assumptions!$C$9,2,1)) | E28: =IF(B28<=Credit_Assumptions!$C$11,1,0) | F28: =IF(B28>Credit_Assumptions!$C$8,1,0) | G28: =IF(B28>30,1,0) | H28: =IF(B28>90,1,0) | I28: =Credit_Assumptions!$C$20
A29: 1-30 | B29: 1 | C29: 30 | D29: =IF(B29>Credit_Assumptions!$C$10,3,IF(B29>Credit_Assumptions!$C$9,2,1)) | E29: =IF(B29<=Credit_Assumptions!$C$11,1,0) | F29: =IF(B29>Credit_Assumptions!$C$8,1,0) | G29: =IF(B29>30,1,0) | H29: =IF(B29>90,1,0) | I29: =1-Credit_Assumptions!$C$20
A30: 31-60 | B30: 31 | C30: 60 | D30: =IF(B30>Credit_Assumptions!$C$10,3,IF(B30>Credit_Assumptions!$C$9,2,1)) | E30: =IF(B30<=Credit_Assumptions!$C$11,1,0) | F30: =IF(B30>Credit_Assumptions!$C$8,1,0) | G30: =IF(B30>30,1,0) | H30: =IF(B30>90,1,0) | I30: =Credit_Assumptions!$C$21
A31: 61-90 | B31: 61 | C31: 90 | D31: =IF(B31>Credit_Assumptions!$C$10,3,IF(B31>Credit_Assumptions!$C$9,2,1)) | E31: =IF(B31<=Credit_Assumptions!$C$11,1,0) | F31: =IF(B31>Credit_Assumptions!$C$8,1,0) | G31: =IF(B31>30,1,0) | H31: =IF(B31>90,1,0) | I31: =Credit_Assumptions!$C$22
A32: 91-180 | B32: 91 | C32: 180 | D32: =IF(B32>Credit_Assumptions!$C$10,3,IF(B32>Credit_Assumptions!$C$9,2,1)) | E32: =IF(B32<=Credit_Assumptions!$C$11,1,0) | F32: =IF(B32>Credit_Assumptions!$C$8,1,0) | G32: =IF(B32>30,1,0) | H32: =IF(B32>90,1,0) | I32: =Credit_Assumptions!$C$23
A33: 180+ | B33: 181 | C33: 9999 | D33: =IF(B33>Credit_Assumptions!$C$10,3,IF(B33>Credit_Assumptions!$C$9,2,1)) | E33: =IF(B33<=Credit_Assumptions!$C$11,1,0) | F33: =IF(B33>Credit_Assumptions!$C$8,1,0) | G33: =IF(B33>30,1,0) | H33: =IF(B33>90,1,0) | I33: =Credit_Assumptions!$C$24
A35: Current and 1-30 shares apply to balances of paying accounts; 31+ shares apply to receivables at risk (accounts that stopped paying). The 30+/90+ flags use fixed market definitions; stage, eligibility and default follow the thresholds above.
A36: The 12-month PD shown by Credit_Engine is a proxy derived from the repayment curve or from observed loss rates. It is NOT an audited IFRS 9 PD.
A37: This is an analytical modelling treatment and does not constitute a determination of the applicable accounting treatment under IFRS.

Sheet Consumer_Risk
A1: Consumer risk: affordability, APR, evidence of consumer protection
A2: [ASSUMPTION] Household incomes are ILLUSTRATIVE: TO BE REPLACED BY COUNTRY / CUSTOMER DATA. Not market data.
A4: Maximum payment burden (instalment / monthly household income) | C4: 0.1 | D4: Illustrative policy threshold: set from the company's credit policy or regulator guidance.
A5: Affordability assumptions reviewed by management (1 = yes) | C5: 0
A7: Metric | B7: Unit | C7: Tier 1 | D7: Tier 2 | E7: Tier 3 | F7: Tier 4 | G7: Tier 5
A8: Household monthly income: ILLUSTRATIVE, TO BE REPLACED | B8: LCY / month | C8: 9000 | D8: 18000 | E8: 40000 | F8: 120000 | G8: 300000
A9: PAYGo monthly instalment | B9: LCY / month | C9: =Products!$C$33 | D9: =Products!$D$33 | E9: =Products!$E$33 | F9: =Products!$F$33 | G9: =Products!$G$33
A10: Payment burden (instalment / income) | B10: % | C10: =IFERROR(C9/C8,0) | D10: =IFERROR(D9/D8,0) | E10: =IFERROR(E9/E8,0) | F10: =IFERROR(F9/F8,0) | G10: =IFERROR(G9/G8,0)
A11: Down payment / monthly income | B11: x | C11: =IFERROR(Products!$C$14/C8,0) | D11: =IFERROR(Products!$D$14/D8,0) | E11: =IFERROR(Products!$E$14/E8,0) | F11: =IFERROR(Products!$F$14/F8,0) | G11: =IFERROR(Products!$G$14/G8,0)
A12: Implied consumer APR | B12: % p.a. | C12: =Products!$C$39 | D12: =Products!$D$39 | E12: =Products!$E$39 | F12: =Products!$F$39 | G12: =Products!$G$39
A13: Affordability flag (burden above threshold) | B13: flag | C13: =IF(C10>Consumer_Risk!$C$4,1,0) | D13: =IF(D10>Consumer_Risk!$C$4,1,0) | E13: =IF(E10>Consumer_Risk!$C$4,1,0) | F13: =IF(F10>Consumer_Risk!$C$4,1,0) | G13: =IF(G10>Consumer_Risk!$C$4,1,0)
A14: PAYGo PERFORM KPI evidence status | B14: status | C14: Not provided | D14: Not provided | E14: Not provided | F14: Not provided | G14: Not provided
A15: Consumer-protection evidence status (pricing disclosure, collections conduct, complaints) | B15: status | C15: Not provided | D15: Not provided | E15: Not provided | F15: Not provided | G15: Not provided
A17: Consumer protection is treated as a financial risk: affordability, collections practices, pricing transparency and ownership outcomes affect repayment, default, reputation, RBF eligibility and investor risk.

Sheet Dashboard
A1: Dashboard: key metrics
A2: [FORECAST] Active case. Each metric is labelled with its unit and source and rounded for reading; full precision stays on the source sheets.
A3: Active case | B3: =Scenarios!$G$13 | D3: Master check | E3: =Checks!$C$44
A5: Metric | B5: Unit | C5: Year 1 | D5: Year 2 | E5: Year 3 | F5: Year 4 | G5: Year 5 | H5: Source / how to read
A6: Scale and customers
A7: New customers (contracts originated in the year) | B7: # | C7: =KPIs!E14 | D7: =KPIs!F14 | E7: =KPIs!G14 | F7: =KPIs!H14 | G7: =KPIs!I14 | H7: KPIs. One unit sold = one contract.
A8: Customers: cumulative contracts originated | B8: # | C8: =SUMIFS(Ops!$E$134:$BL$134,Timeline!$E$4:$BL$4,"<="&12) | D8: =SUMIFS(Ops!$E$134:$BL$134,Timeline!$E$4:$BL$4,"<="&24) | E8: =SUMIFS(Ops!$E$134:$BL$134,Timeline!$E$4:$BL$4,"<="&36) | F8: =SUMIFS(Ops!$E$134:$BL$134,Timeline!$E$4:$BL$4,"<="&48) | G8: =SUMIFS(Ops!$E$134:$BL$134,Timeline!$E$4:$BL$4,"<="&60) | H8: Ops.
A9: Active customers (accounts still paying, year end) | B9: # | C9: =KPIs!E16 | D9: =KPIs!F16 | E9: =KPIs!G16 | F9: =KPIs!H16 | G9: =KPIs!I16 | H9: KPIs.
A10: ARPU: revenue per average active account per month | B10: LCY | C10: =IFERROR(KPIs!E34/((0+KPIs!E16)/2)/12,"n/a") | D10: =IFERROR(KPIs!F34/((KPIs!E16+KPIs!F16)/2)/12,"n/a") | E10: =IFERROR(KPIs!G34/((KPIs!F16+KPIs!G16)/2)/12,"n/a") | F10: =IFERROR(KPIs!H34/((KPIs!G16+KPIs!H16)/2)/12,"n/a") | G10: =IFERROR(KPIs!I34/((KPIs!H16+KPIs!I16)/2)/12,"n/a") | H10: Includes hardware revenue recognised at sale, so it is high in growth years.
A11: Profitability
A12: Revenue | B12: LCY m | C12: =KPIs!E34 | D12: =KPIs!F34 | E12: =KPIs!G34 | F12: =KPIs!H34 | G12: =KPIs!I34 | H12: KPIs. Revenue is not cash: see cash conversion.
A13: Revenue | B13: USD m | C13: =KPIs!E35 | D13: =KPIs!F35 | E13: =KPIs!G35 | F13: =KPIs!H35 | G13: =KPIs!I35 | H13: At average FX (FX_Exposure for translation).
A14: Gross margin | B14: % | C14: =KPIs!E36 | D14: =KPIs!F36 | E14: =KPIs!G36 | F14: =KPIs!H36 | G14: =KPIs!I36 | H14: KPIs.
A15: EBITDA | B15: LCY m | C15: =KPIs!E37 | D15: =KPIs!F37 | E15: =KPIs!G37 | F15: =KPIs!H37 | G15: =KPIs!I37 | H15: KPIs. After expected credit losses and RBF income.
A16: EBITDA margin | B16: % | C16: =KPIs!E38 | D16: =KPIs!F38 | E16: =KPIs!G38 | F16: =KPIs!H38 | G16: =KPIs!I38 | H16: KPIs.
A17: Net income | B17: LCY m | C17: =KPIs!E42 | D17: =KPIs!F42 | E17: =KPIs!G42 | F17: =KPIs!H42 | G17: =KPIs!I42 | H17: KPIs.
A18: Cash and portfolio
A19: Cash balance (year end) | B19: LCY m | C19: =KPIs!E44 | D19: =KPIs!F44 | E19: =KPIs!G44 | F19: =KPIs!H44 | G19: =KPIs!I44 | H19: Held at the minimum by equity top-ups when needed.
A20: PAYGo receivables, gross (year end) | B20: LCY m | C20: =Annual!E32 | D20: =Annual!F32 | E20: =Annual!G32 | F20: =Annual!H32 | G20: =Annual!I32 | H20: Annual.
A21: PAYGo receivables, net of allowance (year end) | B21: LCY m | C21: =Annual!E34 | D21: =Annual!F34 | E21: =Annual!G34 | F21: =Annual!H34 | G21: =Annual!I34 | H21: Annual.
A22: Operational collection rate (not a PERFORM KPI) | B22: % | C22: =KPIs!E19 | D22: =KPIs!F19 | E22: =KPIs!G19 | F22: =KPIs!H19 | G22: =KPIs!I19 | H22: Collected / due, excluding deposits. Never the PERFORM Repayment Rate.
A23: PAYGo PERFORM RR PvP, company-reported (portfolio, latest) | B23: % | C23: =PERFORM_2026!$H$7 | H23: PERFORM_2026. Blank in the model's own forecast; only company results count.
A24: Receivables at risk / gross receivables (year end) | B24: % | C24: =KPIs!E21 | D24: =KPIs!F21 | E24: =KPIs!G21 | F24: =KPIs!H21 | G24: =KPIs!I21 | H24: Proxy; 2021 PERFORM logic (historical).
A25: 30+ DPD / gross receivables (year end) | B25: % | C25: =KPIs!E24 | D25: =KPIs!F24 | E25: =KPIs!G24 | F25: =KPIs!H24 | G25: =KPIs!I24 | H25: Projection (Credit_Engine).
A26: 90+ DPD / gross receivables (year end) | B26: % | C26: =KPIs!E25 | D26: =KPIs!F25 | E26: =KPIs!G25 | F26: =KPIs!H25 | G26: =KPIs!I25 | H26: Projection (Credit_Engine).
A27: Write-off rate (missed / due) | B27: % | C27: =KPIs!E20 | D27: =KPIs!F20 | E27: =KPIs!G20 | F27: =KPIs!H20 | G27: =KPIs!I20 | H27: KPIs.
A28: Write-offs | B28: LCY m | C28: =SUMIFS(Ops!$E$141:$BL$141,Timeline!$E$6:$BL$6,1) | D28: =SUMIFS(Ops!$E$141:$BL$141,Timeline!$E$6:$BL$6,2) | E28: =SUMIFS(Ops!$E$141:$BL$141,Timeline!$E$6:$BL$6,3) | F28: =SUMIFS(Ops!$E$141:$BL$141,Timeline!$E$6:$BL$6,4) | G28: =SUMIFS(Ops!$E$141:$BL$141,Timeline!$E$6:$BL$6,5) | H28: Ops: missed instalments written off.
A29: Cash conversion: operating cash flow / EBITDA | B29: x | C29: =IF(Annual!E19<=0,"n/a",Annual!E55/Annual!E19) | D29: =IF(Annual!F19<=0,"n/a",Annual!F55/Annual!F19) | E29: =IF(Annual!G19<=0,"n/a",Annual!G55/Annual!G19) | F29: =IF(Annual!H19<=0,"n/a",Annual!H55/Annual!H19) | G29: =IF(Annual!I19<=0,"n/a",Annual!I55/Annual!I19) | H29: Below 1x while receivables grow; n/a when EBITDA is not positive.
A30: Funding
A31: Total debt (year end) | B31: LCY m | C31: =KPIs!E47 | D31: =KPIs!F47 | E31: =KPIs!G47 | F31: =KPIs!H47 | G31: =KPIs!I47 | H31: Term loan and receivables facility.
A32: Book equity (year end) | B32: LCY m | C32: =Annual!E44 | D32: =Annual!F44 | E32: =Annual!G44 | F32: =Annual!H44 | G32: =Annual!I44 | H32: Annual.
A33: Cumulative equity invested | B33: LCY m | C33: =KPIs!E45 | D33: =KPIs!F45 | E33: =KPIs!G45 | F33: =KPIs!H45 | G33: =KPIs!I45 | H33: Initial equity plus top-ups.
A34: Funding requirement: equity top-ups in the year | B34: LCY m | C34: =KPIs!E46 | D34: =KPIs!F46 | E34: =KPIs!G46 | F34: =KPIs!H46 | G34: =KPIs!I46 | H34: Automatic top-up to hold minimum cash.
A35: Peak equity requirement | B35: USD m | C35: =KPIs!$C$57 | H35: At opening FX (KPIs).
A36: RBF received | B36: LCY m | C36: =Annual!E15 | D36: =Annual!F15 | E36: =Annual!G15 | F36: =Annual!H15 | G36: =Annual!I15 | H36: RBF_Engine, selected design; claim cycle and working capital gap there.
A37: RBF dependency (RBF income / revenue) | B37: % | C37: =KPIs!E41 | D37: =KPIs!F41 | E37: =KPIs!G41 | F37: =KPIs!H41 | G37: =KPIs!I41 | H37: KPIs.
A38: Returns and timing
A39: Investor IRR (USD) | B39: % | C39: =Valuation!$C$39 | H39: Valuation. Text when no IRR exists.
A40: Investor MOIC (USD) | B40: x | C40: =Valuation!$C$40 | H40: Valuation.
A41: NPV: DCF enterprise value at the discount rate | B41: USD m | C41: =Valuation!$C$28 | H41: Valuation. Check the terminal value share.
A42: Break-even: first month with positive EBITDA | B42: month # | C42: =KPIs!$C$60 | H42: KPIs.
A43: Month from which operating cash flow stays positive | B43: month # | C43: =KPIs!$C$61 | H43: KPIs.
A44: Runway: months before the first equity top-up | B44: months | C44: =IFERROR(MATCH(1,FS!$E$71:$BL$71,0)-1,"No top-up in horizon") | H44: On initial equity and the debt modelled; 0 = top-up in month 1.
A45: FX and readiness
A46: LCY depreciation against USD (active scenario) | B46: % p.a. | C46: =Scenarios!$G$10 | H46: Scenarios.
A47: Share of debt in USD (year end) | B47: % | C47: =FX_Exposure!C22 | D47: =FX_Exposure!D22 | E47: =FX_Exposure!E22 | F47: =FX_Exposure!F22 | G47: =FX_Exposure!G22 | H47: FX_Exposure.
A48: Net FX transaction effect on costs and RBF (before price pass-through) | B48: LCY m | C48: =FX_Exposure!C27*1000000 | D48: =FX_Exposure!D27*1000000 | E48: =FX_Exposure!E27*1000000 | F48: =FX_Exposure!F27*1000000 | G48: =FX_Exposure!G27*1000000 | H48: FX_Exposure. Negative = cost.
A49: Investment readiness: gates met | B49: of 23 | C49: =Investment_Readiness!$C$4 | H49: Investment_Readiness.
A50: Investment readiness: decision (evidence only) | C50: =Investment_Readiness!$C$35 | H50: GO / CONDITIONAL GO / STOP; never a recommendation.
A52: Rounded for reading: money in millions to one decimal, ratios to one decimal place, counts to the unit. Single values (returns, peaks, timing, readiness) are shown under Year 1.
A53: Charts, series order: Revenue, EBITDA | Tier 1..5 | Collection, Write-off | Equity, Debt.

Sheet KPIs
A1: Key performance indicators
A2: [FORECAST] Portfolio, financial and lender KPIs. PAYGo PERFORM 2026 KPIs are on PERFORM_2026.
E5: Year 1 | F5: Year 2 | G5: Year 3 | H5: Year 4 | I5: Year 5
E6: 1 | F6: 2 | G6: 3 | H6: 4 | I6: 5
A8: Sales & customers
A9: Units sold: Tier 1: Pico solar kit | E9: =SUMIFS(Ops!$E$9:$BL$9,Timeline!$E$6:$BL$6,E$6) | F9: =SUMIFS(Ops!$E$9:$BL$9,Timeline!$E$6:$BL$6,F$6) | G9: =SUMIFS(Ops!$E$9:$BL$9,Timeline!$E$6:$BL$6,G$6) | H9: =SUMIFS(Ops!$E$9:$BL$9,Timeline!$E$6:$BL$6,H$6) | I9: =SUMIFS(Ops!$E$9:$BL$9,Timeline!$E$6:$BL$6,I$6)
A10: Units sold: Tier 2: SHS with TV | E10: =SUMIFS(Ops!$E$34:$BL$34,Timeline!$E$6:$BL$6,E$6) | F10: =SUMIFS(Ops!$E$34:$BL$34,Timeline!$E$6:$BL$6,F$6) | G10: =SUMIFS(Ops!$E$34:$BL$34,Timeline!$E$6:$BL$6,G$6) | H10: =SUMIFS(Ops!$E$34:$BL$34,Timeline!$E$6:$BL$6,H$6) | I10: =SUMIFS(Ops!$E$34:$BL$34,Timeline!$E$6:$BL$6,I$6)
A11: Units sold: Tier 3: Large SHS + DC fridge | E11: =SUMIFS(Ops!$E$59:$BL$59,Timeline!$E$6:$BL$6,E$6) | F11: =SUMIFS(Ops!$E$59:$BL$59,Timeline!$E$6:$BL$6,F$6) | G11: =SUMIFS(Ops!$E$59:$BL$59,Timeline!$E$6:$BL$6,G$6) | H11: =SUMIFS(Ops!$E$59:$BL$59,Timeline!$E$6:$BL$6,H$6) | I11: =SUMIFS(Ops!$E$59:$BL$59,Timeline!$E$6:$BL$6,I$6)
A12: Units sold: Tier 4: Solar inverter + lithium (~1.2 kWp / 5 kWh) | E12: =SUMIFS(Ops!$E$84:$BL$84,Timeline!$E$6:$BL$6,E$6) | F12: =SUMIFS(Ops!$E$84:$BL$84,Timeline!$E$6:$BL$6,F$6) | G12: =SUMIFS(Ops!$E$84:$BL$84,Timeline!$E$6:$BL$6,G$6) | H12: =SUMIFS(Ops!$E$84:$BL$84,Timeline!$E$6:$BL$6,H$6) | I12: =SUMIFS(Ops!$E$84:$BL$84,Timeline!$E$6:$BL$6,I$6)
A13: Units sold: Tier 5: Solar inverter + lithium (~3 kWp / 10 kWh) | E13: =SUMIFS(Ops!$E$109:$BL$109,Timeline!$E$6:$BL$6,E$6) | F13: =SUMIFS(Ops!$E$109:$BL$109,Timeline!$E$6:$BL$6,F$6) | G13: =SUMIFS(Ops!$E$109:$BL$109,Timeline!$E$6:$BL$6,G$6) | H13: =SUMIFS(Ops!$E$109:$BL$109,Timeline!$E$6:$BL$6,H$6) | I13: =SUMIFS(Ops!$E$109:$BL$109,Timeline!$E$6:$BL$6,I$6)
A14: Units sold: total | E14: =SUMIFS(Ops!$E$134:$BL$134,Timeline!$E$6:$BL$6,E$6) | F14: =SUMIFS(Ops!$E$134:$BL$134,Timeline!$E$6:$BL$6,F$6) | G14: =SUMIFS(Ops!$E$134:$BL$134,Timeline!$E$6:$BL$6,G$6) | H14: =SUMIFS(Ops!$E$134:$BL$134,Timeline!$E$6:$BL$6,H$6) | I14: =SUMIFS(Ops!$E$134:$BL$134,Timeline!$E$6:$BL$6,I$6)
A15: Average cash price per unit sold (USD, opening FX) | E15: =IFERROR(SUMIFS(Ops!$E$137:$BL$137,Timeline!$E$6:$BL$6,E$6)/SUMIFS(Ops!$E$134:$BL$134,Timeline!$E$6:$BL$6,E$6)/Inputs!$C$10,0) | F15: =IFERROR(SUMIFS(Ops!$E$137:$BL$137,Timeline!$E$6:$BL$6,F$6)/SUMIFS(Ops!$E$134:$BL$134,Timeline!$E$6:$BL$6,F$6)/Inputs!$C$10,0) | G15: =IFERROR(SUMIFS(Ops!$E$137:$BL$137,Timeline!$E$6:$BL$6,G$6)/SUMIFS(Ops!$E$134:$BL$134,Timeline!$E$6:$BL$6,G$6)/Inputs!$C$10,0) | H15: =IFERROR(SUMIFS(Ops!$E$137:$BL$137,Timeline!$E$6:$BL$6,H$6)/SUMIFS(Ops!$E$134:$BL$134,Timeline!$E$6:$BL$6,H$6)/Inputs!$C$10,0) | I15: =IFERROR(SUMIFS(Ops!$E$137:$BL$137,Timeline!$E$6:$BL$6,I$6)/SUMIFS(Ops!$E$134:$BL$134,Timeline!$E$6:$BL$6,I$6)/Inputs!$C$10,0)
A16: Active PAYGo accounts (year end) | E16: =INDEX(Ops!$E$146:$BL$146,1,E$6*12) | F16: =INDEX(Ops!$E$146:$BL$146,1,F$6*12) | G16: =INDEX(Ops!$E$146:$BL$146,1,G$6*12) | H16: =INDEX(Ops!$E$146:$BL$146,1,H$6*12) | I16: =INDEX(Ops!$E$146:$BL$146,1,I$6*12)
A17: Cumulative unlocked accounts (customer ownership) | E17: =INDEX(Ops!$E$158:$BL$158,1,E$6*12) | F17: =INDEX(Ops!$E$158:$BL$158,1,F$6*12) | G17: =INDEX(Ops!$E$158:$BL$158,1,G$6*12) | H17: =INDEX(Ops!$E$158:$BL$158,1,H$6*12) | I17: =INDEX(Ops!$E$158:$BL$158,1,I$6*12)
A18: Portfolio quality
A19: Operational collection rate (collected / due, excl. down payments; not a PERFORM KPI) | E19: =IFERROR(SUMIFS(Ops!$E$140:$BL$140,Timeline!$E$6:$BL$6,E$6)/SUMIFS(Ops!$E$139:$BL$139,Timeline!$E$6:$BL$6,E$6),0) | F19: =IFERROR(SUMIFS(Ops!$E$140:$BL$140,Timeline!$E$6:$BL$6,F$6)/SUMIFS(Ops!$E$139:$BL$139,Timeline!$E$6:$BL$6,F$6),0) | G19: =IFERROR(SUMIFS(Ops!$E$140:$BL$140,Timeline!$E$6:$BL$6,G$6)/SUMIFS(Ops!$E$139:$BL$139,Timeline!$E$6:$BL$6,G$6),0) | H19: =IFERROR(SUMIFS(Ops!$E$140:$BL$140,Timeline!$E$6:$BL$6,H$6)/SUMIFS(Ops!$E$139:$BL$139,Timeline!$E$6:$BL$6,H$6),0) | I19: =IFERROR(SUMIFS(Ops!$E$140:$BL$140,Timeline!$E$6:$BL$6,I$6)/SUMIFS(Ops!$E$139:$BL$139,Timeline!$E$6:$BL$6,I$6),0)
A20: Write-off rate (missed / due) | E20: =IFERROR(SUMIFS(Ops!$E$141:$BL$141,Timeline!$E$6:$BL$6,E$6)/SUMIFS(Ops!$E$139:$BL$139,Timeline!$E$6:$BL$6,E$6),0) | F20: =IFERROR(SUMIFS(Ops!$E$141:$BL$141,Timeline!$E$6:$BL$6,F$6)/SUMIFS(Ops!$E$139:$BL$139,Timeline!$E$6:$BL$6,F$6),0) | G20: =IFERROR(SUMIFS(Ops!$E$141:$BL$141,Timeline!$E$6:$BL$6,G$6)/SUMIFS(Ops!$E$139:$BL$139,Timeline!$E$6:$BL$6,G$6),0) | H20: =IFERROR(SUMIFS(Ops!$E$141:$BL$141,Timeline!$E$6:$BL$6,H$6)/SUMIFS(Ops!$E$139:$BL$139,Timeline!$E$6:$BL$6,H$6),0) | I20: =IFERROR(SUMIFS(Ops!$E$141:$BL$141,Timeline!$E$6:$BL$6,I$6)/SUMIFS(Ops!$E$139:$BL$139,Timeline!$E$6:$BL$6,I$6),0)
A21: Receivables at risk / gross receivables (year end) | E21: =IFERROR(INDEX(Ops!$E$148:$BL$148,1,E$6*12)/INDEX(Ops!$E$149:$BL$149,1,E$6*12),0) | F21: =IFERROR(INDEX(Ops!$E$148:$BL$148,1,F$6*12)/INDEX(Ops!$E$149:$BL$149,1,F$6*12),0) | G21: =IFERROR(INDEX(Ops!$E$148:$BL$148,1,G$6*12)/INDEX(Ops!$E$149:$BL$149,1,G$6*12),0) | H21: =IFERROR(INDEX(Ops!$E$148:$BL$148,1,H$6*12)/INDEX(Ops!$E$149:$BL$149,1,H$6*12),0) | I21: =IFERROR(INDEX(Ops!$E$148:$BL$148,1,I$6*12)/INDEX(Ops!$E$149:$BL$149,1,I$6*12),0)
A22: Loss allowance coverage (allowance / gross receivables) | E22: =IFERROR(-INDEX(FS!$E$35:$BL$35,1,E$6*12)/INDEX(FS!$E$34:$BL$34,1,E$6*12),0) | F22: =IFERROR(-INDEX(FS!$E$35:$BL$35,1,F$6*12)/INDEX(FS!$E$34:$BL$34,1,F$6*12),0) | G22: =IFERROR(-INDEX(FS!$E$35:$BL$35,1,G$6*12)/INDEX(FS!$E$34:$BL$34,1,G$6*12),0) | H22: =IFERROR(-INDEX(FS!$E$35:$BL$35,1,H$6*12)/INDEX(FS!$E$34:$BL$34,1,H$6*12),0) | I22: =IFERROR(-INDEX(FS!$E$35:$BL$35,1,I$6*12)/INDEX(FS!$E$34:$BL$34,1,I$6*12),0)
A23: Net recoveries / write-offs | E23: =IFERROR(SUMIFS(Ops!$E$144:$BL$144,Timeline!$E$6:$BL$6,E$6)/SUMIFS(Ops!$E$141:$BL$141,Timeline!$E$6:$BL$6,E$6),0) | F23: =IFERROR(SUMIFS(Ops!$E$144:$BL$144,Timeline!$E$6:$BL$6,F$6)/SUMIFS(Ops!$E$141:$BL$141,Timeline!$E$6:$BL$6,F$6),0) | G23: =IFERROR(SUMIFS(Ops!$E$144:$BL$144,Timeline!$E$6:$BL$6,G$6)/SUMIFS(Ops!$E$141:$BL$141,Timeline!$E$6:$BL$6,G$6),0) | H23: =IFERROR(SUMIFS(Ops!$E$144:$BL$144,Timeline!$E$6:$BL$6,H$6)/SUMIFS(Ops!$E$141:$BL$141,Timeline!$E$6:$BL$6,H$6),0) | I23: =IFERROR(SUMIFS(Ops!$E$144:$BL$144,Timeline!$E$6:$BL$6,I$6)/SUMIFS(Ops!$E$141:$BL$141,Timeline!$E$6:$BL$6,I$6),0)
A24: 30+ DPD / gross receivables (year end, projection) | E24: =INDEX(Covenants!$E$17:$BL$17,1,E$6*12) | F24: =INDEX(Covenants!$E$17:$BL$17,1,F$6*12) | G24: =INDEX(Covenants!$E$17:$BL$17,1,G$6*12) | H24: =INDEX(Covenants!$E$17:$BL$17,1,H$6*12) | I24: =INDEX(Covenants!$E$17:$BL$17,1,I$6*12)
A25: 90+ DPD / gross receivables (year end, projection) | E25: =INDEX(Covenants!$E$19:$BL$19,1,E$6*12) | F25: =INDEX(Covenants!$E$19:$BL$19,1,F$6*12) | G25: =INDEX(Covenants!$E$19:$BL$19,1,G$6*12) | H25: =INDEX(Covenants!$E$19:$BL$19,1,H$6*12) | I25: =INDEX(Covenants!$E$19:$BL$19,1,I$6*12)
A26: Indicative stage-based ECL / gross receivables (year end) | E26: =INDEX(Covenants!$E$24:$BL$24,1,E$6*12) | F26: =INDEX(Covenants!$E$24:$BL$24,1,F$6*12) | G26: =INDEX(Covenants!$E$24:$BL$24,1,G$6*12) | H26: =INDEX(Covenants!$E$24:$BL$24,1,H$6*12) | I26: =INDEX(Covenants!$E$24:$BL$24,1,I$6*12)
A27: Revenue mix
A28: Revenue share: Tier 1: Pico solar kit | E28: =IFERROR((SUMIFS(Ops!$E$12:$BL$12,Timeline!$E$6:$BL$6,E$6)+SUMIFS(Ops!$E$17:$BL$17,Timeline!$E$6:$BL$6,E$6))/SUMIFS(FS!$E$12:$BL$12,Timeline!$E$6:$BL$6,E$6),0) | F28: =IFERROR((SUMIFS(Ops!$E$12:$BL$12,Timeline!$E$6:$BL$6,F$6)+SUMIFS(Ops!$E$17:$BL$17,Timeline!$E$6:$BL$6,F$6))/SUMIFS(FS!$E$12:$BL$12,Timeline!$E$6:$BL$6,F$6),0) | G28: =IFERROR((SUMIFS(Ops!$E$12:$BL$12,Timeline!$E$6:$BL$6,G$6)+SUMIFS(Ops!$E$17:$BL$17,Timeline!$E$6:$BL$6,G$6))/SUMIFS(FS!$E$12:$BL$12,Timeline!$E$6:$BL$6,G$6),0) | H28: =IFERROR((SUMIFS(Ops!$E$12:$BL$12,Timeline!$E$6:$BL$6,H$6)+SUMIFS(Ops!$E$17:$BL$17,Timeline!$E$6:$BL$6,H$6))/SUMIFS(FS!$E$12:$BL$12,Timeline!$E$6:$BL$6,H$6),0) | I28: =IFERROR((SUMIFS(Ops!$E$12:$BL$12,Timeline!$E$6:$BL$6,I$6)+SUMIFS(Ops!$E$17:$BL$17,Timeline!$E$6:$BL$6,I$6))/SUMIFS(FS!$E$12:$BL$12,Timeline!$E$6:$BL$6,I$6),0)
A29: Revenue share: Tier 2: SHS with TV | E29: =IFERROR((SUMIFS(Ops!$E$37:$BL$37,Timeline!$E$6:$BL$6,E$6)+SUMIFS(Ops!$E$42:$BL$42,Timeline!$E$6:$BL$6,E$6))/SUMIFS(FS!$E$12:$BL$12,Timeline!$E$6:$BL$6,E$6),0) | F29: =IFERROR((SUMIFS(Ops!$E$37:$BL$37,Timeline!$E$6:$BL$6,F$6)+SUMIFS(Ops!$E$42:$BL$42,Timeline!$E$6:$BL$6,F$6))/SUMIFS(FS!$E$12:$BL$12,Timeline!$E$6:$BL$6,F$6),0) | G29: =IFERROR((SUMIFS(Ops!$E$37:$BL$37,Timeline!$E$6:$BL$6,G$6)+SUMIFS(Ops!$E$42:$BL$42,Timeline!$E$6:$BL$6,G$6))/SUMIFS(FS!$E$12:$BL$12,Timeline!$E$6:$BL$6,G$6),0) | H29: =IFERROR((SUMIFS(Ops!$E$37:$BL$37,Timeline!$E$6:$BL$6,H$6)+SUMIFS(Ops!$E$42:$BL$42,Timeline!$E$6:$BL$6,H$6))/SUMIFS(FS!$E$12:$BL$12,Timeline!$E$6:$BL$6,H$6),0) | I29: =IFERROR((SUMIFS(Ops!$E$37:$BL$37,Timeline!$E$6:$BL$6,I$6)+SUMIFS(Ops!$E$42:$BL$42,Timeline!$E$6:$BL$6,I$6))/SUMIFS(FS!$E$12:$BL$12,Timeline!$E$6:$BL$6,I$6),0)
A30: Revenue share: Tier 3: Large SHS + DC fridge | E30: =IFERROR((SUMIFS(Ops!$E$62:$BL$62,Timeline!$E$6:$BL$6,E$6)+SUMIFS(Ops!$E$67:$BL$67,Timeline!$E$6:$BL$6,E$6))/SUMIFS(FS!$E$12:$BL$12,Timeline!$E$6:$BL$6,E$6),0) | F30: =IFERROR((SUMIFS(Ops!$E$62:$BL$62,Timeline!$E$6:$BL$6,F$6)+SUMIFS(Ops!$E$67:$BL$67,Timeline!$E$6:$BL$6,F$6))/SUMIFS(FS!$E$12:$BL$12,Timeline!$E$6:$BL$6,F$6),0) | G30: =IFERROR((SUMIFS(Ops!$E$62:$BL$62,Timeline!$E$6:$BL$6,G$6)+SUMIFS(Ops!$E$67:$BL$67,Timeline!$E$6:$BL$6,G$6))/SUMIFS(FS!$E$12:$BL$12,Timeline!$E$6:$BL$6,G$6),0) | H30: =IFERROR((SUMIFS(Ops!$E$62:$BL$62,Timeline!$E$6:$BL$6,H$6)+SUMIFS(Ops!$E$67:$BL$67,Timeline!$E$6:$BL$6,H$6))/SUMIFS(FS!$E$12:$BL$12,Timeline!$E$6:$BL$6,H$6),0) | I30: =IFERROR((SUMIFS(Ops!$E$62:$BL$62,Timeline!$E$6:$BL$6,I$6)+SUMIFS(Ops!$E$67:$BL$67,Timeline!$E$6:$BL$6,I$6))/SUMIFS(FS!$E$12:$BL$12,Timeline!$E$6:$BL$6,I$6),0)
A31: Revenue share: Tier 4: Solar inverter + lithium (~1.2 kWp / 5 kWh) | E31: =IFERROR((SUMIFS(Ops!$E$87:$BL$87,Timeline!$E$6:$BL$6,E$6)+SUMIFS(Ops!$E$92:$BL$92,Timeline!$E$6:$BL$6,E$6))/SUMIFS(FS!$E$12:$BL$12,Timeline!$E$6:$BL$6,E$6),0) | F31: =IFERROR((SUMIFS(Ops!$E$87:$BL$87,Timeline!$E$6:$BL$6,F$6)+SUMIFS(Ops!$E$92:$BL$92,Timeline!$E$6:$BL$6,F$6))/SUMIFS(FS!$E$12:$BL$12,Timeline!$E$6:$BL$6,F$6),0) | G31: =IFERROR((SUMIFS(Ops!$E$87:$BL$87,Timeline!$E$6:$BL$6,G$6)+SUMIFS(Ops!$E$92:$BL$92,Timeline!$E$6:$BL$6,G$6))/SUMIFS(FS!$E$12:$BL$12,Timeline!$E$6:$BL$6,G$6),0) | H31: =IFERROR((SUMIFS(Ops!$E$87:$BL$87,Timeline!$E$6:$BL$6,H$6)+SUMIFS(Ops!$E$92:$BL$92,Timeline!$E$6:$BL$6,H$6))/SUMIFS(FS!$E$12:$BL$12,Timeline!$E$6:$BL$6,H$6),0) | I31: =IFERROR((SUMIFS(Ops!$E$87:$BL$87,Timeline!$E$6:$BL$6,I$6)+SUMIFS(Ops!$E$92:$BL$92,Timeline!$E$6:$BL$6,I$6))/SUMIFS(FS!$E$12:$BL$12,Timeline!$E$6:$BL$6,I$6),0)
A32: Revenue share: Tier 5: Solar inverter + lithium (~3 kWp / 10 kWh) | E32: =IFERROR((SUMIFS(Ops!$E$112:$BL$112,Timeline!$E$6:$BL$6,E$6)+SUMIFS(Ops!$E$117:$BL$117,Timeline!$E$6:$BL$6,E$6))/SUMIFS(FS!$E$12:$BL$12,Timeline!$E$6:$BL$6,E$6),0) | F32: =IFERROR((SUMIFS(Ops!$E$112:$BL$112,Timeline!$E$6:$BL$6,F$6)+SUMIFS(Ops!$E$117:$BL$117,Timeline!$E$6:$BL$6,F$6))/SUMIFS(FS!$E$12:$BL$12,Timeline!$E$6:$BL$6,F$6),0) | G32: =IFERROR((SUMIFS(Ops!$E$112:$BL$112,Timeline!$E$6:$BL$6,G$6)+SUMIFS(Ops!$E$117:$BL$117,Timeline!$E$6:$BL$6,G$6))/SUMIFS(FS!$E$12:$BL$12,Timeline!$E$6:$BL$6,G$6),0) | H32: =IFERROR((SUMIFS(Ops!$E$112:$BL$112,Timeline!$E$6:$BL$6,H$6)+SUMIFS(Ops!$E$117:$BL$117,Timeline!$E$6:$BL$6,H$6))/SUMIFS(FS!$E$12:$BL$12,Timeline!$E$6:$BL$6,H$6),0) | I32: =IFERROR((SUMIFS(Ops!$E$112:$BL$112,Timeline!$E$6:$BL$6,I$6)+SUMIFS(Ops!$E$117:$BL$117,Timeline!$E$6:$BL$6,I$6))/SUMIFS(FS!$E$12:$BL$12,Timeline!$E$6:$BL$6,I$6),0)
A33: Profitability
A34: Revenue (LCY) | E34: =SUMIFS(FS!$E$12:$BL$12,Timeline!$E$6:$BL$6,E$6) | F34: =SUMIFS(FS!$E$12:$BL$12,Timeline!$E$6:$BL$6,F$6) | G34: =SUMIFS(FS!$E$12:$BL$12,Timeline!$E$6:$BL$6,G$6) | H34: =SUMIFS(FS!$E$12:$BL$12,Timeline!$E$6:$BL$6,H$6) | I34: =SUMIFS(FS!$E$12:$BL$12,Timeline!$E$6:$BL$6,I$6)
A35: Revenue (USD, average FX) | E35: =IFERROR(SUMIFS(FS!$E$12:$BL$12,Timeline!$E$6:$BL$6,E$6)/AVERAGEIFS(Timeline!$E$8:$BL$8,Timeline!$E$6:$BL$6,E$6),0) | F35: =IFERROR(SUMIFS(FS!$E$12:$BL$12,Timeline!$E$6:$BL$6,F$6)/AVERAGEIFS(Timeline!$E$8:$BL$8,Timeline!$E$6:$BL$6,F$6),0) | G35: =IFERROR(SUMIFS(FS!$E$12:$BL$12,Timeline!$E$6:$BL$6,G$6)/AVERAGEIFS(Timeline!$E$8:$BL$8,Timeline!$E$6:$BL$6,G$6),0) | H35: =IFERROR(SUMIFS(FS!$E$12:$BL$12,Timeline!$E$6:$BL$6,H$6)/AVERAGEIFS(Timeline!$E$8:$BL$8,Timeline!$E$6:$BL$6,H$6),0) | I35: =IFERROR(SUMIFS(FS!$E$12:$BL$12,Timeline!$E$6:$BL$6,I$6)/AVERAGEIFS(Timeline!$E$8:$BL$8,Timeline!$E$6:$BL$6,I$6),0)
A36: Gross margin | E36: =IFERROR(SUMIFS(FS!$E$14:$BL$14,Timeline!$E$6:$BL$6,E$6)/SUMIFS(FS!$E$12:$BL$12,Timeline!$E$6:$BL$6,E$6),0) | F36: =IFERROR(SUMIFS(FS!$E$14:$BL$14,Timeline!$E$6:$BL$6,F$6)/SUMIFS(FS!$E$12:$BL$12,Timeline!$E$6:$BL$6,F$6),0) | G36: =IFERROR(SUMIFS(FS!$E$14:$BL$14,Timeline!$E$6:$BL$6,G$6)/SUMIFS(FS!$E$12:$BL$12,Timeline!$E$6:$BL$6,G$6),0) | H36: =IFERROR(SUMIFS(FS!$E$14:$BL$14,Timeline!$E$6:$BL$6,H$6)/SUMIFS(FS!$E$12:$BL$12,Timeline!$E$6:$BL$6,H$6),0) | I36: =IFERROR(SUMIFS(FS!$E$14:$BL$14,Timeline!$E$6:$BL$6,I$6)/SUMIFS(FS!$E$12:$BL$12,Timeline!$E$6:$BL$6,I$6),0)
A37: EBITDA (LCY) | E37: =SUMIFS(FS!$E$19:$BL$19,Timeline!$E$6:$BL$6,E$6) | F37: =SUMIFS(FS!$E$19:$BL$19,Timeline!$E$6:$BL$6,F$6) | G37: =SUMIFS(FS!$E$19:$BL$19,Timeline!$E$6:$BL$6,G$6) | H37: =SUMIFS(FS!$E$19:$BL$19,Timeline!$E$6:$BL$6,H$6) | I37: =SUMIFS(FS!$E$19:$BL$19,Timeline!$E$6:$BL$6,I$6)
A38: EBITDA margin | E38: =IFERROR(SUMIFS(FS!$E$19:$BL$19,Timeline!$E$6:$BL$6,E$6)/SUMIFS(FS!$E$12:$BL$12,Timeline!$E$6:$BL$6,E$6),0) | F38: =IFERROR(SUMIFS(FS!$E$19:$BL$19,Timeline!$E$6:$BL$6,F$6)/SUMIFS(FS!$E$12:$BL$12,Timeline!$E$6:$BL$6,F$6),0) | G38: =IFERROR(SUMIFS(FS!$E$19:$BL$19,Timeline!$E$6:$BL$6,G$6)/SUMIFS(FS!$E$12:$BL$12,Timeline!$E$6:$BL$6,G$6),0) | H38: =IFERROR(SUMIFS(FS!$E$19:$BL$19,Timeline!$E$6:$BL$6,H$6)/SUMIFS(FS!$E$12:$BL$12,Timeline!$E$6:$BL$6,H$6),0) | I38: =IFERROR(SUMIFS(FS!$E$19:$BL$19,Timeline!$E$6:$BL$6,I$6)/SUMIFS(FS!$E$12:$BL$12,Timeline!$E$6:$BL$6,I$6),0)
A39: Net credit losses / revenue | E39: =IFERROR(-(SUMIFS(FS!$E$17:$BL$17,Timeline!$E$6:$BL$6,E$6)+SUMIFS(FS!$E$18:$BL$18,Timeline!$E$6:$BL$6,E$6))/SUMIFS(FS!$E$12:$BL$12,Timeline!$E$6:$BL$6,E$6),0) | F39: =IFERROR(-(SUMIFS(FS!$E$17:$BL$17,Timeline!$E$6:$BL$6,F$6)+SUMIFS(FS!$E$18:$BL$18,Timeline!$E$6:$BL$6,F$6))/SUMIFS(FS!$E$12:$BL$12,Timeline!$E$6:$BL$6,F$6),0) | G39: =IFERROR(-(SUMIFS(FS!$E$17:$BL$17,Timeline!$E$6:$BL$6,G$6)+SUMIFS(FS!$E$18:$BL$18,Timeline!$E$6:$BL$6,G$6))/SUMIFS(FS!$E$12:$BL$12,Timeline!$E$6:$BL$6,G$6),0) | H39: =IFERROR(-(SUMIFS(FS!$E$17:$BL$17,Timeline!$E$6:$BL$6,H$6)+SUMIFS(FS!$E$18:$BL$18,Timeline!$E$6:$BL$6,H$6))/SUMIFS(FS!$E$12:$BL$12,Timeline!$E$6:$BL$6,H$6),0) | I39: =IFERROR(-(SUMIFS(FS!$E$17:$BL$17,Timeline!$E$6:$BL$6,I$6)+SUMIFS(FS!$E$18:$BL$18,Timeline!$E$6:$BL$6,I$6))/SUMIFS(FS!$E$12:$BL$12,Timeline!$E$6:$BL$6,I$6),0)
A40: Other revenue share (digital loans & services) | E40: =IFERROR(SUMIFS(FS!$E$11:$BL$11,Timeline!$E$6:$BL$6,E$6)/SUMIFS(FS!$E$12:$BL$12,Timeline!$E$6:$BL$6,E$6),0) | F40: =IFERROR(SUMIFS(FS!$E$11:$BL$11,Timeline!$E$6:$BL$6,F$6)/SUMIFS(FS!$E$12:$BL$12,Timeline!$E$6:$BL$6,F$6),0) | G40: =IFERROR(SUMIFS(FS!$E$11:$BL$11,Timeline!$E$6:$BL$6,G$6)/SUMIFS(FS!$E$12:$BL$12,Timeline!$E$6:$BL$6,G$6),0) | H40: =IFERROR(SUMIFS(FS!$E$11:$BL$11,Timeline!$E$6:$BL$6,H$6)/SUMIFS(FS!$E$12:$BL$12,Timeline!$E$6:$BL$6,H$6),0) | I40: =IFERROR(SUMIFS(FS!$E$11:$BL$11,Timeline!$E$6:$BL$6,I$6)/SUMIFS(FS!$E$12:$BL$12,Timeline!$E$6:$BL$6,I$6),0)
A41: RBF dependency (RBF income / revenue) | E41: =IFERROR(SUMIFS(FS!$E$15:$BL$15,Timeline!$E$6:$BL$6,E$6)/SUMIFS(FS!$E$12:$BL$12,Timeline!$E$6:$BL$6,E$6),0) | F41: =IFERROR(SUMIFS(FS!$E$15:$BL$15,Timeline!$E$6:$BL$6,F$6)/SUMIFS(FS!$E$12:$BL$12,Timeline!$E$6:$BL$6,F$6),0) | G41: =IFERROR(SUMIFS(FS!$E$15:$BL$15,Timeline!$E$6:$BL$6,G$6)/SUMIFS(FS!$E$12:$BL$12,Timeline!$E$6:$BL$6,G$6),0) | H41: =IFERROR(SUMIFS(FS!$E$15:$BL$15,Timeline!$E$6:$BL$6,H$6)/SUMIFS(FS!$E$12:$BL$12,Timeline!$E$6:$BL$6,H$6),0) | I41: =IFERROR(SUMIFS(FS!$E$15:$BL$15,Timeline!$E$6:$BL$6,I$6)/SUMIFS(FS!$E$12:$BL$12,Timeline!$E$6:$BL$6,I$6),0)
A42: Net income (LCY) | E42: =SUMIFS(FS!$E$30:$BL$30,Timeline!$E$6:$BL$6,E$6) | F42: =SUMIFS(FS!$E$30:$BL$30,Timeline!$E$6:$BL$6,F$6) | G42: =SUMIFS(FS!$E$30:$BL$30,Timeline!$E$6:$BL$6,G$6) | H42: =SUMIFS(FS!$E$30:$BL$30,Timeline!$E$6:$BL$6,H$6) | I42: =SUMIFS(FS!$E$30:$BL$30,Timeline!$E$6:$BL$6,I$6)
A43: Funding, leverage & coverage
A44: Closing cash (LCY) | E44: =INDEX(FS!$E$65:$BL$65,1,E$6*12) | F44: =INDEX(FS!$E$65:$BL$65,1,F$6*12) | G44: =INDEX(FS!$E$65:$BL$65,1,G$6*12) | H44: =INDEX(FS!$E$65:$BL$65,1,H$6*12) | I44: =INDEX(FS!$E$65:$BL$65,1,I$6*12)
A45: Cumulative equity invested (LCY) | E45: =INDEX(Financing!$E$11:$BL$11,1,E$6*12) | F45: =INDEX(Financing!$E$11:$BL$11,1,F$6*12) | G45: =INDEX(Financing!$E$11:$BL$11,1,G$6*12) | H45: =INDEX(Financing!$E$11:$BL$11,1,H$6*12) | I45: =INDEX(Financing!$E$11:$BL$11,1,I$6*12)
A46: Equity top-ups in year (funding gap, LCY) | E46: =SUMIFS(FS!$E$64:$BL$64,Timeline!$E$6:$BL$6,E$6) | F46: =SUMIFS(FS!$E$64:$BL$64,Timeline!$E$6:$BL$6,F$6) | G46: =SUMIFS(FS!$E$64:$BL$64,Timeline!$E$6:$BL$6,G$6) | H46: =SUMIFS(FS!$E$64:$BL$64,Timeline!$E$6:$BL$6,H$6) | I46: =SUMIFS(FS!$E$64:$BL$64,Timeline!$E$6:$BL$6,I$6)
A47: Total debt (year end, LCY) | E47: =INDEX(FS!$E$41:$BL$41,1,E$6*12)+INDEX(FS!$E$42:$BL$42,1,E$6*12) | F47: =INDEX(FS!$E$41:$BL$41,1,F$6*12)+INDEX(FS!$E$42:$BL$42,1,F$6*12) | G47: =INDEX(FS!$E$41:$BL$41,1,G$6*12)+INDEX(FS!$E$42:$BL$42,1,G$6*12) | H47: =INDEX(FS!$E$41:$BL$41,1,H$6*12)+INDEX(FS!$E$42:$BL$42,1,H$6*12) | I47: =INDEX(FS!$E$41:$BL$41,1,I$6*12)+INDEX(FS!$E$42:$BL$42,1,I$6*12)
A48: Debt / book equity | E48: =IFERROR((INDEX(FS!$E$41:$BL$41,1,E$6*12)+INDEX(FS!$E$42:$BL$42,1,E$6*12))/INDEX(FS!$E$46:$BL$46,1,E$6*12),0) | F48: =IFERROR((INDEX(FS!$E$41:$BL$41,1,F$6*12)+INDEX(FS!$E$42:$BL$42,1,F$6*12))/INDEX(FS!$E$46:$BL$46,1,F$6*12),0) | G48: =IFERROR((INDEX(FS!$E$41:$BL$41,1,G$6*12)+INDEX(FS!$E$42:$BL$42,1,G$6*12))/INDEX(FS!$E$46:$BL$46,1,G$6*12),0) | H48: =IFERROR((INDEX(FS!$E$41:$BL$41,1,H$6*12)+INDEX(FS!$E$42:$BL$42,1,H$6*12))/INDEX(FS!$E$46:$BL$46,1,H$6*12),0) | I48: =IFERROR((INDEX(FS!$E$41:$BL$41,1,I$6*12)+INDEX(FS!$E$42:$BL$42,1,I$6*12))/INDEX(FS!$E$46:$BL$46,1,I$6*12),0)
A49: Debt service (interest + term-loan principal, LCY) | E49: =SUMIFS(Financing!$E$16:$BL$16,Timeline!$E$6:$BL$6,E$6)+SUMIFS(Financing!$E$18:$BL$18,Timeline!$E$6:$BL$6,E$6)+SUMIFS(Financing!$E$25:$BL$25,Timeline!$E$6:$BL$6,E$6) | F49: =SUMIFS(Financing!$E$16:$BL$16,Timeline!$E$6:$BL$6,F$6)+SUMIFS(Financing!$E$18:$BL$18,Timeline!$E$6:$BL$6,F$6)+SUMIFS(Financing!$E$25:$BL$25,Timeline!$E$6:$BL$6,F$6) | G49: =SUMIFS(Financing!$E$16:$BL$16,Timeline!$E$6:$BL$6,G$6)+SUMIFS(Financing!$E$18:$BL$18,Timeline!$E$6:$BL$6,G$6)+SUMIFS(Financing!$E$25:$BL$25,Timeline!$E$6:$BL$6,G$6) | H49: =SUMIFS(Financing!$E$16:$BL$16,Timeline!$E$6:$BL$6,H$6)+SUMIFS(Financing!$E$18:$BL$18,Timeline!$E$6:$BL$6,H$6)+SUMIFS(Financing!$E$25:$BL$25,Timeline!$E$6:$BL$6,H$6) | I49: =SUMIFS(Financing!$E$16:$BL$16,Timeline!$E$6:$BL$6,I$6)+SUMIFS(Financing!$E$18:$BL$18,Timeline!$E$6:$BL$6,I$6)+SUMIFS(Financing!$E$25:$BL$25,Timeline!$E$6:$BL$6,I$6)
A50: DSCR ((cash flow + interest) / debt service; basis per Inputs, covenant definition) | E50: =IFERROR((SUMIFS(FS!$E$57:$BL$57,Timeline!$E$6:$BL$6,E$6)-SUMIFS(FS!$E$22:$BL$22,Timeline!$E$6:$BL$6,E$6)-SUMIFS(FS!$E$23:$BL$23,Timeline!$E$6:$BL$6,E$6)-IF(Inputs!$C$88=2,SUMIFS(FS!$E$54:$BL$54,Timeline!$E$6:$BL$6,E$6),0))/E49,0) | F50: =IFERROR((SUMIFS(FS!$E$57:$BL$57,Timeline!$E$6:$BL$6,F$6)-SUMIFS(FS!$E$22:$BL$22,Timeline!$E$6:$BL$6,F$6)-SUMIFS(FS!$E$23:$BL$23,Timeline!$E$6:$BL$6,F$6)-IF(Inputs!$C$88=2,SUMIFS(FS!$E$54:$BL$54,Timeline!$E$6:$BL$6,F$6),0))/F49,0) | G50: =IFERROR((SUMIFS(FS!$E$57:$BL$57,Timeline!$E$6:$BL$6,G$6)-SUMIFS(FS!$E$22:$BL$22,Timeline!$E$6:$BL$6,G$6)-SUMIFS(FS!$E$23:$BL$23,Timeline!$E$6:$BL$6,G$6)-IF(Inputs!$C$88=2,SUMIFS(FS!$E$54:$BL$54,Timeline!$E$6:$BL$6,G$6),0))/G49,0) | H50: =IFERROR((SUMIFS(FS!$E$57:$BL$57,Timeline!$E$6:$BL$6,H$6)-SUMIFS(FS!$E$22:$BL$22,Timeline!$E$6:$BL$6,H$6)-SUMIFS(FS!$E$23:$BL$23,Timeline!$E$6:$BL$6,H$6)-IF(Inputs!$C$88=2,SUMIFS(FS!$E$54:$BL$54,Timeline!$E$6:$BL$6,H$6),0))/H49,0) | I50: =IFERROR((SUMIFS(FS!$E$57:$BL$57,Timeline!$E$6:$BL$6,I$6)-SUMIFS(FS!$E$22:$BL$22,Timeline!$E$6:$BL$6,I$6)-SUMIFS(FS!$E$23:$BL$23,Timeline!$E$6:$BL$6,I$6)-IF(Inputs!$C$88=2,SUMIFS(FS!$E$54:$BL$54,Timeline!$E$6:$BL$6,I$6),0))/I49,0)
A51: Breach: DSCR below minimum (years with debt service; 0 when the facility has no DSCR test) | E51: =IF(AND(Inputs!$C$88>0,E49>0,E50<Inputs!$C$73),1,0) | F51: =IF(AND(Inputs!$C$88>0,F49>0,F50<Inputs!$C$73),1,0) | G51: =IF(AND(Inputs!$C$88>0,G49>0,G50<Inputs!$C$73),1,0) | H51: =IF(AND(Inputs!$C$88>0,H49>0,H50<Inputs!$C$73),1,0) | I51: =IF(AND(Inputs!$C$88>0,I49>0,I50<Inputs!$C$73),1,0)
A52: Months with any monthly covenant breach | E52: =SUMIFS(Covenants!$E$26:$BL$26,Timeline!$E$6:$BL$6,E$6) | F52: =SUMIFS(Covenants!$E$26:$BL$26,Timeline!$E$6:$BL$6,F$6) | G52: =SUMIFS(Covenants!$E$26:$BL$26,Timeline!$E$6:$BL$6,G$6) | H52: =SUMIFS(Covenants!$E$26:$BL$26,Timeline!$E$6:$BL$6,H$6) | I52: =SUMIFS(Covenants!$E$26:$BL$26,Timeline!$E$6:$BL$6,I$6)
A53: FX rate (year end, LCY / USD) | E53: =INDEX(Timeline!$E$8:$BL$8,1,E$6*12) | F53: =INDEX(Timeline!$E$8:$BL$8,1,F$6*12) | G53: =INDEX(Timeline!$E$8:$BL$8,1,G$6*12) | H53: =INDEX(Timeline!$E$8:$BL$8,1,H$6*12) | I53: =INDEX(Timeline!$E$8:$BL$8,1,I$6*12)
A55: Headline metrics
A56: Peak cumulative equity requirement (LCY) | C56: =MAX(Financing!$E$11:$BL$11)
A57: Peak cumulative equity requirement (USD, opening FX) | C57: =C56/Inputs!$C$10
A58: Peak total debt (LCY) | C58: =MAX(Covenants!$E$12:$BL$12)
A59: Total RBF received (USD, opening FX) | C59: =SUM(Ops!$E$145:$BL$145)/Inputs!$C$10
A60: First month with positive EBITDA | C60: =IFERROR(MATCH(1,FS!$E$68:$BL$68,0),"Not reached")
A61: Month from which operating cash flow stays positive | C61: =IFERROR(MATCH(1,FS!$E$70:$BL$70,0),"Not reached")
A62: Lowest trailing-3-month collection rate (from month 3) | C62: =MIN(Covenants!G8:BL8)
A63: Highest receivables-at-risk ratio | C63: =MAX(Ops!$E$161:$BL$161)
A64: Total months with a monthly covenant breach (annual DSCR not included: next row) | C64: =SUM(Covenants!$E$26:$BL$26)
A65: Years with DSCR below minimum | C65: =SUM(E51:I51)
A66: Additional equity required beyond the initial injection (USD, opening FX) | C66: =MAX(0,MAX(Financing!$E$11:$BL$11)-Inputs!$C$49)/Inputs!$C$10
A67: Lowest cash before equity top-up (LCY; negative = funding gap) | C67: =MIN(FS!$E$63:$BL$63)
A69: Receivables at risk follows the logic of the 2021 PAYGo PERFORM guide (historical) with a curve-based proxy. Covenant definitions are illustrative; use those in the actual facility agreement.

Sheet Credit_Portfolio
A1: Credit portfolio dashboard: all tiers (selected data mode)
A2: [FORECAST or ACTUAL (selected data mode)] Proxy = projection; Actual = Credit_Input history. Facility headroom always reflects the projection. This is an analytical modelling treatment and does not constitute a determination of the applicable accounting treatment under IFRS.
A4: Month # | D4: Opening | E4: =Timeline!E4 | F4: =Timeline!F4 | G4: =Timeline!G4 | H4: =Timeline!H4 | I4: =Timeline!I4 | J4: =Timeline!J4 | K4: =Timeline!K4 | L4: =Timeline!L4 | ... BL4: =Timeline!BL4
A5: Period end | E5: =Timeline!E5 | F5: =Timeline!F5 | G5: =Timeline!G5 | H5: =Timeline!H5 | I5: =Timeline!I5 | J5: =Timeline!J5 | K5: =Timeline!K5 | L5: =Timeline!L5 | ... BL5: =Timeline!BL5
A6: Year # | E6: =Timeline!E6 | F6: =Timeline!F6 | G6: =Timeline!G6 | H6: =Timeline!H6 | I6: =Timeline!I6 | J6: =Timeline!J6 | K6: =Timeline!K6 | L6: =Timeline!L6 | ... BL6: =Timeline!BL6
A8: Credit data mode | C8: =IF(Credit_Assumptions!$C$5=1,"PROXY (model curves)","ACTUAL (Credit_Input)")
A9: Period end of the data shown (Actual mode: company observation dates, not model months) | B9: date | E9: =IF(Credit_Assumptions!$C$5=1,Timeline!E$5,IF(ISNUMBER(INDEX(Credit_Input!$B$8:$B$67,E$4)),INDEX(Credit_Input!$B$8:$B$67,E$4),"")) | F9: =IF(Credit_Assumptions!$C$5=1,Timeline!F$5,IF(ISNUMBER(INDEX(Credit_Input!$B$8:$B$67,F$4)),INDEX(Credit_Input!$B$8:$B$67,F$4),"")) | G9: =IF(Credit_Assumptions!$C$5=1,Timeline!G$5,IF(ISNUMBER(INDEX(Credit_Input!$B$8:$B$67,G$4)),INDEX(Credit_Input!$B$8:$B$67,G$4),"")) | H9: =IF(Credit_Assumptions!$C$5=1,Timeline!H$5,IF(ISNUMBER(INDEX(Credit_Input!$B$8:$B$67,H$4)),INDEX(Credit_Input!$B$8:$B$67,H$4),"")) | I9: =IF(Credit_Assumptions!$C$5=1,Timeline!I$5,IF(ISNUMBER(INDEX(Credit_Input!$B$8:$B$67,I$4)),INDEX(Credit_Input!$B$8:$B$67,I$4),"")) | J9: =IF(Credit_Assumptions!$C$5=1,Timeline!J$5,IF(ISNUMBER(INDEX(Credit_Input!$B$8:$B$67,J$4)),INDEX(Credit_Input!$B$8:$B$67,J$4),"")) | K9: =IF(Credit_Assumptions!$C$5=1,Timeline!K$5,IF(ISNUMBER(INDEX(Credit_Input!$B$8:$B$67,K$4)),INDEX(Credit_Input!$B$8:$B$67,K$4),"")) | L9: =IF(Credit_Assumptions!$C$5=1,Timeline!L$5,IF(ISNUMBER(INDEX(Credit_Input!$B$8:$B$67,L$4)),INDEX(Credit_Input!$B$8:$B$67,L$4),"")) | ... BL9: =IF(Credit_Assumptions!$C$5=1,Timeline!BL$5,IF(ISNUMBER(INDEX(Credit_Input!$B$8:$B$67,BL$4)),INDEX(Credit_Input!$B$8:$B$67,BL$4),""))
A10: Gross receivables | C10: =BL10 | E10: =Credit_Engine!E38+Credit_Engine!E94+Credit_Engine!E150+Credit_Engine!E206+Credit_Engine!E262 | F10: =Credit_Engine!F38+Credit_Engine!F94+Credit_Engine!F150+Credit_Engine!F206+Credit_Engine!F262 | G10: =Credit_Engine!G38+Credit_Engine!G94+Credit_Engine!G150+Credit_Engine!G206+Credit_Engine!G262 | H10: =Credit_Engine!H38+Credit_Engine!H94+Credit_Engine!H150+Credit_Engine!H206+Credit_Engine!H262 | I10: =Credit_Engine!I38+Credit_Engine!I94+Credit_Engine!I150+Credit_Engine!I206+Credit_Engine!I262 | J10: =Credit_Engine!J38+Credit_Engine!J94+Credit_Engine!J150+Credit_Engine!J206+Credit_Engine!J262 | K10: =Credit_Engine!K38+Credit_Engine!K94+Credit_Engine!K150+Credit_Engine!K206+Credit_Engine!K262 | L10: =Credit_Engine!L38+Credit_Engine!L94+Credit_Engine!L150+Credit_Engine!L206+Credit_Engine!L262 | ... BL10: =Credit_Engine!BL38+Credit_Engine!BL94+Credit_Engine!BL150+Credit_Engine!BL206+Credit_Engine!BL262
A11: Current | C11: =BL11 | E11: =Credit_Engine!E39+Credit_Engine!E95+Credit_Engine!E151+Credit_Engine!E207+Credit_Engine!E263 | F11: =Credit_Engine!F39+Credit_Engine!F95+Credit_Engine!F151+Credit_Engine!F207+Credit_Engine!F263 | G11: =Credit_Engine!G39+Credit_Engine!G95+Credit_Engine!G151+Credit_Engine!G207+Credit_Engine!G263 | H11: =Credit_Engine!H39+Credit_Engine!H95+Credit_Engine!H151+Credit_Engine!H207+Credit_Engine!H263 | I11: =Credit_Engine!I39+Credit_Engine!I95+Credit_Engine!I151+Credit_Engine!I207+Credit_Engine!I263 | J11: =Credit_Engine!J39+Credit_Engine!J95+Credit_Engine!J151+Credit_Engine!J207+Credit_Engine!J263 | K11: =Credit_Engine!K39+Credit_Engine!K95+Credit_Engine!K151+Credit_Engine!K207+Credit_Engine!K263 | L11: =Credit_Engine!L39+Credit_Engine!L95+Credit_Engine!L151+Credit_Engine!L207+Credit_Engine!L263 | ... BL11: =Credit_Engine!BL39+Credit_Engine!BL95+Credit_Engine!BL151+Credit_Engine!BL207+Credit_Engine!BL263
A12: 1-30 DPD | C12: =BL12 | E12: =Credit_Engine!E40+Credit_Engine!E96+Credit_Engine!E152+Credit_Engine!E208+Credit_Engine!E264 | F12: =Credit_Engine!F40+Credit_Engine!F96+Credit_Engine!F152+Credit_Engine!F208+Credit_Engine!F264 | G12: =Credit_Engine!G40+Credit_Engine!G96+Credit_Engine!G152+Credit_Engine!G208+Credit_Engine!G264 | H12: =Credit_Engine!H40+Credit_Engine!H96+Credit_Engine!H152+Credit_Engine!H208+Credit_Engine!H264 | I12: =Credit_Engine!I40+Credit_Engine!I96+Credit_Engine!I152+Credit_Engine!I208+Credit_Engine!I264 | J12: =Credit_Engine!J40+Credit_Engine!J96+Credit_Engine!J152+Credit_Engine!J208+Credit_Engine!J264 | K12: =Credit_Engine!K40+Credit_Engine!K96+Credit_Engine!K152+Credit_Engine!K208+Credit_Engine!K264 | L12: =Credit_Engine!L40+Credit_Engine!L96+Credit_Engine!L152+Credit_Engine!L208+Credit_Engine!L264 | ... BL12: =Credit_Engine!BL40+Credit_Engine!BL96+Credit_Engine!BL152+Credit_Engine!BL208+Credit_Engine!BL264
A13: 31-60 DPD | C13: =BL13 | E13: =Credit_Engine!E41+Credit_Engine!E97+Credit_Engine!E153+Credit_Engine!E209+Credit_Engine!E265 | F13: =Credit_Engine!F41+Credit_Engine!F97+Credit_Engine!F153+Credit_Engine!F209+Credit_Engine!F265 | G13: =Credit_Engine!G41+Credit_Engine!G97+Credit_Engine!G153+Credit_Engine!G209+Credit_Engine!G265 | H13: =Credit_Engine!H41+Credit_Engine!H97+Credit_Engine!H153+Credit_Engine!H209+Credit_Engine!H265 | I13: =Credit_Engine!I41+Credit_Engine!I97+Credit_Engine!I153+Credit_Engine!I209+Credit_Engine!I265 | J13: =Credit_Engine!J41+Credit_Engine!J97+Credit_Engine!J153+Credit_Engine!J209+Credit_Engine!J265 | K13: =Credit_Engine!K41+Credit_Engine!K97+Credit_Engine!K153+Credit_Engine!K209+Credit_Engine!K265 | L13: =Credit_Engine!L41+Credit_Engine!L97+Credit_Engine!L153+Credit_Engine!L209+Credit_Engine!L265 | ... BL13: =Credit_Engine!BL41+Credit_Engine!BL97+Credit_Engine!BL153+Credit_Engine!BL209+Credit_Engine!BL265
A14: 61-90 DPD | C14: =BL14 | E14: =Credit_Engine!E42+Credit_Engine!E98+Credit_Engine!E154+Credit_Engine!E210+Credit_Engine!E266 | F14: =Credit_Engine!F42+Credit_Engine!F98+Credit_Engine!F154+Credit_Engine!F210+Credit_Engine!F266 | G14: =Credit_Engine!G42+Credit_Engine!G98+Credit_Engine!G154+Credit_Engine!G210+Credit_Engine!G266 | H14: =Credit_Engine!H42+Credit_Engine!H98+Credit_Engine!H154+Credit_Engine!H210+Credit_Engine!H266 | I14: =Credit_Engine!I42+Credit_Engine!I98+Credit_Engine!I154+Credit_Engine!I210+Credit_Engine!I266 | J14: =Credit_Engine!J42+Credit_Engine!J98+Credit_Engine!J154+Credit_Engine!J210+Credit_Engine!J266 | K14: =Credit_Engine!K42+Credit_Engine!K98+Credit_Engine!K154+Credit_Engine!K210+Credit_Engine!K266 | L14: =Credit_Engine!L42+Credit_Engine!L98+Credit_Engine!L154+Credit_Engine!L210+Credit_Engine!L266 | ... BL14: =Credit_Engine!BL42+Credit_Engine!BL98+Credit_Engine!BL154+Credit_Engine!BL210+Credit_Engine!BL266
A15: 91-180 DPD | C15: =BL15 | E15: =Credit_Engine!E43+Credit_Engine!E99+Credit_Engine!E155+Credit_Engine!E211+Credit_Engine!E267 | F15: =Credit_Engine!F43+Credit_Engine!F99+Credit_Engine!F155+Credit_Engine!F211+Credit_Engine!F267 | G15: =Credit_Engine!G43+Credit_Engine!G99+Credit_Engine!G155+Credit_Engine!G211+Credit_Engine!G267 | H15: =Credit_Engine!H43+Credit_Engine!H99+Credit_Engine!H155+Credit_Engine!H211+Credit_Engine!H267 | I15: =Credit_Engine!I43+Credit_Engine!I99+Credit_Engine!I155+Credit_Engine!I211+Credit_Engine!I267 | J15: =Credit_Engine!J43+Credit_Engine!J99+Credit_Engine!J155+Credit_Engine!J211+Credit_Engine!J267 | K15: =Credit_Engine!K43+Credit_Engine!K99+Credit_Engine!K155+Credit_Engine!K211+Credit_Engine!K267 | L15: =Credit_Engine!L43+Credit_Engine!L99+Credit_Engine!L155+Credit_Engine!L211+Credit_Engine!L267 | ... BL15: =Credit_Engine!BL43+Credit_Engine!BL99+Credit_Engine!BL155+Credit_Engine!BL211+Credit_Engine!BL267
A16: 180+ DPD | C16: =BL16 | E16: =Credit_Engine!E44+Credit_Engine!E100+Credit_Engine!E156+Credit_Engine!E212+Credit_Engine!E268 | F16: =Credit_Engine!F44+Credit_Engine!F100+Credit_Engine!F156+Credit_Engine!F212+Credit_Engine!F268 | G16: =Credit_Engine!G44+Credit_Engine!G100+Credit_Engine!G156+Credit_Engine!G212+Credit_Engine!G268 | H16: =Credit_Engine!H44+Credit_Engine!H100+Credit_Engine!H156+Credit_Engine!H212+Credit_Engine!H268 | I16: =Credit_Engine!I44+Credit_Engine!I100+Credit_Engine!I156+Credit_Engine!I212+Credit_Engine!I268 | J16: =Credit_Engine!J44+Credit_Engine!J100+Credit_Engine!J156+Credit_Engine!J212+Credit_Engine!J268 | K16: =Credit_Engine!K44+Credit_Engine!K100+Credit_Engine!K156+Credit_Engine!K212+Credit_Engine!K268 | L16: =Credit_Engine!L44+Credit_Engine!L100+Credit_Engine!L156+Credit_Engine!L212+Credit_Engine!L268 | ... BL16: =Credit_Engine!BL44+Credit_Engine!BL100+Credit_Engine!BL156+Credit_Engine!BL212+Credit_Engine!BL268
A17: Default EAD | C17: =BL17 | E17: =Credit_Engine!E45+Credit_Engine!E101+Credit_Engine!E157+Credit_Engine!E213+Credit_Engine!E269 | F17: =Credit_Engine!F45+Credit_Engine!F101+Credit_Engine!F157+Credit_Engine!F213+Credit_Engine!F269 | G17: =Credit_Engine!G45+Credit_Engine!G101+Credit_Engine!G157+Credit_Engine!G213+Credit_Engine!G269 | H17: =Credit_Engine!H45+Credit_Engine!H101+Credit_Engine!H157+Credit_Engine!H213+Credit_Engine!H269 | I17: =Credit_Engine!I45+Credit_Engine!I101+Credit_Engine!I157+Credit_Engine!I213+Credit_Engine!I269 | J17: =Credit_Engine!J45+Credit_Engine!J101+Credit_Engine!J157+Credit_Engine!J213+Credit_Engine!J269 | K17: =Credit_Engine!K45+Credit_Engine!K101+Credit_Engine!K157+Credit_Engine!K213+Credit_Engine!K269 | L17: =Credit_Engine!L45+Credit_Engine!L101+Credit_Engine!L157+Credit_Engine!L213+Credit_Engine!L269 | ... BL17: =Credit_Engine!BL45+Credit_Engine!BL101+Credit_Engine!BL157+Credit_Engine!BL213+Credit_Engine!BL269
A18: Collections | C18: =BL18 | E18: =Credit_Engine!E53+Credit_Engine!E109+Credit_Engine!E165+Credit_Engine!E221+Credit_Engine!E277 | F18: =Credit_Engine!F53+Credit_Engine!F109+Credit_Engine!F165+Credit_Engine!F221+Credit_Engine!F277 | G18: =Credit_Engine!G53+Credit_Engine!G109+Credit_Engine!G165+Credit_Engine!G221+Credit_Engine!G277 | H18: =Credit_Engine!H53+Credit_Engine!H109+Credit_Engine!H165+Credit_Engine!H221+Credit_Engine!H277 | I18: =Credit_Engine!I53+Credit_Engine!I109+Credit_Engine!I165+Credit_Engine!I221+Credit_Engine!I277 | J18: =Credit_Engine!J53+Credit_Engine!J109+Credit_Engine!J165+Credit_Engine!J221+Credit_Engine!J277 | K18: =Credit_Engine!K53+Credit_Engine!K109+Credit_Engine!K165+Credit_Engine!K221+Credit_Engine!K277 | L18: =Credit_Engine!L53+Credit_Engine!L109+Credit_Engine!L165+Credit_Engine!L221+Credit_Engine!L277 | ... BL18: =Credit_Engine!BL53+Credit_Engine!BL109+Credit_Engine!BL165+Credit_Engine!BL221+Credit_Engine!BL277
A19: Instalments due | C19: =BL19 | E19: =Credit_Engine!E54+Credit_Engine!E110+Credit_Engine!E166+Credit_Engine!E222+Credit_Engine!E278 | F19: =Credit_Engine!F54+Credit_Engine!F110+Credit_Engine!F166+Credit_Engine!F222+Credit_Engine!F278 | G19: =Credit_Engine!G54+Credit_Engine!G110+Credit_Engine!G166+Credit_Engine!G222+Credit_Engine!G278 | H19: =Credit_Engine!H54+Credit_Engine!H110+Credit_Engine!H166+Credit_Engine!H222+Credit_Engine!H278 | I19: =Credit_Engine!I54+Credit_Engine!I110+Credit_Engine!I166+Credit_Engine!I222+Credit_Engine!I278 | J19: =Credit_Engine!J54+Credit_Engine!J110+Credit_Engine!J166+Credit_Engine!J222+Credit_Engine!J278 | K19: =Credit_Engine!K54+Credit_Engine!K110+Credit_Engine!K166+Credit_Engine!K222+Credit_Engine!K278 | L19: =Credit_Engine!L54+Credit_Engine!L110+Credit_Engine!L166+Credit_Engine!L222+Credit_Engine!L278 | ... BL19: =Credit_Engine!BL54+Credit_Engine!BL110+Credit_Engine!BL166+Credit_Engine!BL222+Credit_Engine!BL278
A20: Collection ratio | C20: =BL20 | E20: =IF(E19=0,0,E18/E19) | F20: =IF(F19=0,0,F18/F19) | G20: =IF(G19=0,0,G18/G19) | H20: =IF(H19=0,0,H18/H19) | I20: =IF(I19=0,0,I18/I19) | J20: =IF(J19=0,0,J18/J19) | K20: =IF(K19=0,0,K18/K19) | L20: =IF(L19=0,0,L18/L19) | ... BL20: =IF(BL19=0,0,BL18/BL19)
A21: Weighted 12-month PD proxy (not an IFRS 9 PD) | C21: =BL21 | E21: =IFERROR((Credit_Engine!E57*Credit_Engine!E38+Credit_Engine!E113*Credit_Engine!E94+Credit_Engine!E169*Credit_Engine!E150+Credit_Engine!E225*Credit_Engine!E206+Credit_Engine!E281*Credit_Engine!E262)/E10,0) | F21: =IFERROR((Credit_Engine!F57*Credit_Engine!F38+Credit_Engine!F113*Credit_Engine!F94+Credit_Engine!F169*Credit_Engine!F150+Credit_Engine!F225*Credit_Engine!F206+Credit_Engine!F281*Credit_Engine!F262)/F10,0) | G21: =IFERROR((Credit_Engine!G57*Credit_Engine!G38+Credit_Engine!G113*Credit_Engine!G94+Credit_Engine!G169*Credit_Engine!G150+Credit_Engine!G225*Credit_Engine!G206+Credit_Engine!G281*Credit_Engine!G262)/G10,0) | H21: =IFERROR((Credit_Engine!H57*Credit_Engine!H38+Credit_Engine!H113*Credit_Engine!H94+Credit_Engine!H169*Credit_Engine!H150+Credit_Engine!H225*Credit_Engine!H206+Credit_Engine!H281*Credit_Engine!H262)/H10,0) | I21: =IFERROR((Credit_Engine!I57*Credit_Engine!I38+Credit_Engine!I113*Credit_Engine!I94+Credit_Engine!I169*Credit_Engine!I150+Credit_Engine!I225*Credit_Engine!I206+Credit_Engine!I281*Credit_Engine!I262)/I10,0) | J21: =IFERROR((Credit_Engine!J57*Credit_Engine!J38+Credit_Engine!J113*Credit_Engine!J94+Credit_Engine!J169*Credit_Engine!J150+Credit_Engine!J225*Credit_Engine!J206+Credit_Engine!J281*Credit_Engine!J262)/J10,0) | K21: =IFERROR((Credit_Engine!K57*Credit_Engine!K38+Credit_Engine!K113*Credit_Engine!K94+Credit_Engine!K169*Credit_Engine!K150+Credit_Engine!K225*Credit_Engine!K206+Credit_Engine!K281*Credit_Engine!K262)/K10,0) | L21: =IFERROR((Credit_Engine!L57*Credit_Engine!L38+Credit_Engine!L113*Credit_Engine!L94+Credit_Engine!L169*Credit_Engine!L150+Credit_Engine!L225*Credit_Engine!L206+Credit_Engine!L281*Credit_Engine!L262)/L10,0) | ... BL21: =IFERROR((Credit_Engine!BL57*Credit_Engine!BL38+Credit_Engine!BL113*Credit_Engine!BL94+Credit_Engine!BL169*Credit_Engine!BL150+Credit_Engine!BL225*Credit_Engine!BL206+Credit_Engine!BL281*Credit_Engine!BL262)/BL10,0)
A22: Weighted LGD proxy | C22: =BL22 | E22: =IFERROR((Credit_Engine!E58*Credit_Engine!E38+Credit_Engine!E114*Credit_Engine!E94+Credit_Engine!E170*Credit_Engine!E150+Credit_Engine!E226*Credit_Engine!E206+Credit_Engine!E282*Credit_Engine!E262)/E10,0) | F22: =IFERROR((Credit_Engine!F58*Credit_Engine!F38+Credit_Engine!F114*Credit_Engine!F94+Credit_Engine!F170*Credit_Engine!F150+Credit_Engine!F226*Credit_Engine!F206+Credit_Engine!F282*Credit_Engine!F262)/F10,0) | G22: =IFERROR((Credit_Engine!G58*Credit_Engine!G38+Credit_Engine!G114*Credit_Engine!G94+Credit_Engine!G170*Credit_Engine!G150+Credit_Engine!G226*Credit_Engine!G206+Credit_Engine!G282*Credit_Engine!G262)/G10,0) | H22: =IFERROR((Credit_Engine!H58*Credit_Engine!H38+Credit_Engine!H114*Credit_Engine!H94+Credit_Engine!H170*Credit_Engine!H150+Credit_Engine!H226*Credit_Engine!H206+Credit_Engine!H282*Credit_Engine!H262)/H10,0) | I22: =IFERROR((Credit_Engine!I58*Credit_Engine!I38+Credit_Engine!I114*Credit_Engine!I94+Credit_Engine!I170*Credit_Engine!I150+Credit_Engine!I226*Credit_Engine!I206+Credit_Engine!I282*Credit_Engine!I262)/I10,0) | J22: =IFERROR((Credit_Engine!J58*Credit_Engine!J38+Credit_Engine!J114*Credit_Engine!J94+Credit_Engine!J170*Credit_Engine!J150+Credit_Engine!J226*Credit_Engine!J206+Credit_Engine!J282*Credit_Engine!J262)/J10,0) | K22: =IFERROR((Credit_Engine!K58*Credit_Engine!K38+Credit_Engine!K114*Credit_Engine!K94+Credit_Engine!K170*Credit_Engine!K150+Credit_Engine!K226*Credit_Engine!K206+Credit_Engine!K282*Credit_Engine!K262)/K10,0) | L22: =IFERROR((Credit_Engine!L58*Credit_Engine!L38+Credit_Engine!L114*Credit_Engine!L94+Credit_Engine!L170*Credit_Engine!L150+Credit_Engine!L226*Credit_Engine!L206+Credit_Engine!L282*Credit_Engine!L262)/L10,0) | ... BL22: =IFERROR((Credit_Engine!BL58*Credit_Engine!BL38+Credit_Engine!BL114*Credit_Engine!BL94+Credit_Engine!BL170*Credit_Engine!BL150+Credit_Engine!BL226*Credit_Engine!BL206+Credit_Engine!BL282*Credit_Engine!BL262)/BL10,0)
A23: Indicative ECL (diagnostic) | C23: =BL23 | E23: =Credit_Engine!E59+Credit_Engine!E115+Credit_Engine!E171+Credit_Engine!E227+Credit_Engine!E283 | F23: =Credit_Engine!F59+Credit_Engine!F115+Credit_Engine!F171+Credit_Engine!F227+Credit_Engine!F283 | G23: =Credit_Engine!G59+Credit_Engine!G115+Credit_Engine!G171+Credit_Engine!G227+Credit_Engine!G283 | H23: =Credit_Engine!H59+Credit_Engine!H115+Credit_Engine!H171+Credit_Engine!H227+Credit_Engine!H283 | I23: =Credit_Engine!I59+Credit_Engine!I115+Credit_Engine!I171+Credit_Engine!I227+Credit_Engine!I283 | J23: =Credit_Engine!J59+Credit_Engine!J115+Credit_Engine!J171+Credit_Engine!J227+Credit_Engine!J283 | K23: =Credit_Engine!K59+Credit_Engine!K115+Credit_Engine!K171+Credit_Engine!K227+Credit_Engine!K283 | L23: =Credit_Engine!L59+Credit_Engine!L115+Credit_Engine!L171+Credit_Engine!L227+Credit_Engine!L283 | ... BL23: =Credit_Engine!BL59+Credit_Engine!BL115+Credit_Engine!BL171+Credit_Engine!BL227+Credit_Engine!BL283
A24: Indicative ECL coverage | C24: =BL24 | E24: =IFERROR(E23/E10,0) | F24: =IFERROR(F23/F10,0) | G24: =IFERROR(G23/G10,0) | H24: =IFERROR(H23/H10,0) | I24: =IFERROR(I23/I10,0) | J24: =IFERROR(J23/J10,0) | K24: =IFERROR(K23/K10,0) | L24: =IFERROR(L23/L10,0) | ... BL24: =IFERROR(BL23/BL10,0)
A25: Eligible receivables | C25: =BL25 | E25: =Credit_Engine!E60+Credit_Engine!E116+Credit_Engine!E172+Credit_Engine!E228+Credit_Engine!E284 | F25: =Credit_Engine!F60+Credit_Engine!F116+Credit_Engine!F172+Credit_Engine!F228+Credit_Engine!F284 | G25: =Credit_Engine!G60+Credit_Engine!G116+Credit_Engine!G172+Credit_Engine!G228+Credit_Engine!G284 | H25: =Credit_Engine!H60+Credit_Engine!H116+Credit_Engine!H172+Credit_Engine!H228+Credit_Engine!H284 | I25: =Credit_Engine!I60+Credit_Engine!I116+Credit_Engine!I172+Credit_Engine!I228+Credit_Engine!I284 | J25: =Credit_Engine!J60+Credit_Engine!J116+Credit_Engine!J172+Credit_Engine!J228+Credit_Engine!J284 | K25: =Credit_Engine!K60+Credit_Engine!K116+Credit_Engine!K172+Credit_Engine!K228+Credit_Engine!K284 | L25: =Credit_Engine!L60+Credit_Engine!L116+Credit_Engine!L172+Credit_Engine!L228+Credit_Engine!L284 | ... BL25: =Credit_Engine!BL60+Credit_Engine!BL116+Credit_Engine!BL172+Credit_Engine!BL228+Credit_Engine!BL284
A26: Borrowing-base contribution | C26: =BL26 | E26: =Credit_Engine!E61+Credit_Engine!E117+Credit_Engine!E173+Credit_Engine!E229+Credit_Engine!E285 | F26: =Credit_Engine!F61+Credit_Engine!F117+Credit_Engine!F173+Credit_Engine!F229+Credit_Engine!F285 | G26: =Credit_Engine!G61+Credit_Engine!G117+Credit_Engine!G173+Credit_Engine!G229+Credit_Engine!G285 | H26: =Credit_Engine!H61+Credit_Engine!H117+Credit_Engine!H173+Credit_Engine!H229+Credit_Engine!H285 | I26: =Credit_Engine!I61+Credit_Engine!I117+Credit_Engine!I173+Credit_Engine!I229+Credit_Engine!I285 | J26: =Credit_Engine!J61+Credit_Engine!J117+Credit_Engine!J173+Credit_Engine!J229+Credit_Engine!J285 | K26: =Credit_Engine!K61+Credit_Engine!K117+Credit_Engine!K173+Credit_Engine!K229+Credit_Engine!K285 | L26: =Credit_Engine!L61+Credit_Engine!L117+Credit_Engine!L173+Credit_Engine!L229+Credit_Engine!L285 | ... BL26: =Credit_Engine!BL61+Credit_Engine!BL117+Credit_Engine!BL173+Credit_Engine!BL229+Credit_Engine!BL285
A27: Facility drawn (projection) | C27: =BL27 | E27: =Financing!E$23 | F27: =Financing!F$23 | G27: =Financing!G$23 | H27: =Financing!H$23 | I27: =Financing!I$23 | J27: =Financing!J$23 | K27: =Financing!K$23 | L27: =Financing!L$23 | ... BL27: =Financing!BL$23
A28: Borrowing-base headroom (projection) | C28: =BL28 | E28: =Financing!E$22-E27 | F28: =Financing!F$22-F27 | G28: =Financing!G$22-G27 | H28: =Financing!H$22-H27 | I28: =Financing!I$22-I27 | J28: =Financing!J$22-J27 | K28: =Financing!K$22-K27 | L28: =Financing!L$22-L27 | ... BL28: =Financing!BL$22-BL27
A29: 30+ DPD / gross receivables | C29: =BL29 | E29: =IFERROR((Credit_Engine!E46+Credit_Engine!E102+Credit_Engine!E158+Credit_Engine!E214+Credit_Engine!E270)/E10,0) | F29: =IFERROR((Credit_Engine!F46+Credit_Engine!F102+Credit_Engine!F158+Credit_Engine!F214+Credit_Engine!F270)/F10,0) | G29: =IFERROR((Credit_Engine!G46+Credit_Engine!G102+Credit_Engine!G158+Credit_Engine!G214+Credit_Engine!G270)/G10,0) | H29: =IFERROR((Credit_Engine!H46+Credit_Engine!H102+Credit_Engine!H158+Credit_Engine!H214+Credit_Engine!H270)/H10,0) | I29: =IFERROR((Credit_Engine!I46+Credit_Engine!I102+Credit_Engine!I158+Credit_Engine!I214+Credit_Engine!I270)/I10,0) | J29: =IFERROR((Credit_Engine!J46+Credit_Engine!J102+Credit_Engine!J158+Credit_Engine!J214+Credit_Engine!J270)/J10,0) | K29: =IFERROR((Credit_Engine!K46+Credit_Engine!K102+Credit_Engine!K158+Credit_Engine!K214+Credit_Engine!K270)/K10,0) | L29: =IFERROR((Credit_Engine!L46+Credit_Engine!L102+Credit_Engine!L158+Credit_Engine!L214+Credit_Engine!L270)/L10,0) | ... BL29: =IFERROR((Credit_Engine!BL46+Credit_Engine!BL102+Credit_Engine!BL158+Credit_Engine!BL214+Credit_Engine!BL270)/BL10,0)
A30: 90+ DPD / gross receivables | C30: =BL30 | E30: =IFERROR((Credit_Engine!E47+Credit_Engine!E103+Credit_Engine!E159+Credit_Engine!E215+Credit_Engine!E271)/E10,0) | F30: =IFERROR((Credit_Engine!F47+Credit_Engine!F103+Credit_Engine!F159+Credit_Engine!F215+Credit_Engine!F271)/F10,0) | G30: =IFERROR((Credit_Engine!G47+Credit_Engine!G103+Credit_Engine!G159+Credit_Engine!G215+Credit_Engine!G271)/G10,0) | H30: =IFERROR((Credit_Engine!H47+Credit_Engine!H103+Credit_Engine!H159+Credit_Engine!H215+Credit_Engine!H271)/H10,0) | I30: =IFERROR((Credit_Engine!I47+Credit_Engine!I103+Credit_Engine!I159+Credit_Engine!I215+Credit_Engine!I271)/I10,0) | J30: =IFERROR((Credit_Engine!J47+Credit_Engine!J103+Credit_Engine!J159+Credit_Engine!J215+Credit_Engine!J271)/J10,0) | K30: =IFERROR((Credit_Engine!K47+Credit_Engine!K103+Credit_Engine!K159+Credit_Engine!K215+Credit_Engine!K271)/K10,0) | L30: =IFERROR((Credit_Engine!L47+Credit_Engine!L103+Credit_Engine!L159+Credit_Engine!L215+Credit_Engine!L271)/L10,0) | ... BL30: =IFERROR((Credit_Engine!BL47+Credit_Engine!BL103+Credit_Engine!BL159+Credit_Engine!BL215+Credit_Engine!BL271)/BL10,0)
A31: Credit risk flag (30+ or 90+ above covenant) | C31: =MAX(E31:BL31) | E31: =IF(OR(E29>Inputs!$C$75,E30>Inputs!$C$76),1,0) | F31: =IF(OR(F29>Inputs!$C$75,F30>Inputs!$C$76),1,0) | G31: =IF(OR(G29>Inputs!$C$75,G30>Inputs!$C$76),1,0) | H31: =IF(OR(H29>Inputs!$C$75,H30>Inputs!$C$76),1,0) | I31: =IF(OR(I29>Inputs!$C$75,I30>Inputs!$C$76),1,0) | J31: =IF(OR(J29>Inputs!$C$75,J30>Inputs!$C$76),1,0) | K31: =IF(OR(K29>Inputs!$C$75,K30>Inputs!$C$76),1,0) | L31: =IF(OR(L29>Inputs!$C$75,L30>Inputs!$C$76),1,0) | ... BL31: =IF(OR(BL29>Inputs!$C$75,BL30>Inputs!$C$76),1,0)
A34: COMPANY HISTORY LOADED IN Credit_Input (COMPANY DATA, all tiers; independent of the selected mode)
A35: Months of history with data (longest tier) | C35: =MAX(COUNT(Credit_Input!$R$8:$R$67),COUNT(Credit_Input!$R$72:$R$131),COUNT(Credit_Input!$R$136:$R$195),COUNT(Credit_Input!$R$200:$R$259),COUNT(Credit_Input!$R$264:$R$323))
A36: Operational collection rate, history months 1 to 12 | C36: =IF(C35<12,"n/a: fewer than 12 months",IFERROR((SUM(Credit_Input!$Q$8:$Q$19)+SUM(Credit_Input!$Q$72:$Q$83)+SUM(Credit_Input!$Q$136:$Q$147)+SUM(Credit_Input!$Q$200:$Q$211)+SUM(Credit_Input!$Q$264:$Q$275))/(SUM(Credit_Input!$R$8:$R$19)+SUM(Credit_Input!$R$72:$R$83)+SUM(Credit_Input!$R$136:$R$147)+SUM(Credit_Input!$R$200:$R$211)+SUM(Credit_Input!$R$264:$R$275)),"n/a"))
A37: Operational collection rate, history months 13 to 24 | C37: =IF(C35<24,"n/a: fewer than 24 months",IFERROR((SUM(Credit_Input!$Q$20:$Q$31)+SUM(Credit_Input!$Q$84:$Q$95)+SUM(Credit_Input!$Q$148:$Q$159)+SUM(Credit_Input!$Q$212:$Q$223)+SUM(Credit_Input!$Q$276:$Q$287))/(SUM(Credit_Input!$R$20:$R$31)+SUM(Credit_Input!$R$84:$R$95)+SUM(Credit_Input!$R$148:$R$159)+SUM(Credit_Input!$R$212:$R$223)+SUM(Credit_Input!$R$276:$R$287)),"n/a"))
A38: Operational collection rate, history months 25 to 36 | C38: =IF(C35<36,"n/a: fewer than 36 months",IFERROR((SUM(Credit_Input!$Q$32:$Q$43)+SUM(Credit_Input!$Q$96:$Q$107)+SUM(Credit_Input!$Q$160:$Q$171)+SUM(Credit_Input!$Q$224:$Q$235)+SUM(Credit_Input!$Q$288:$Q$299))/(SUM(Credit_Input!$R$32:$R$43)+SUM(Credit_Input!$R$96:$R$107)+SUM(Credit_Input!$R$160:$R$171)+SUM(Credit_Input!$R$224:$R$235)+SUM(Credit_Input!$R$288:$R$299)),"n/a"))
A39: Operational collection rate, latest 12 months of history | C39: =IF(C35<12,"n/a: fewer than 12 months",IFERROR((SUMPRODUCT(Credit_Input!$Q$8:$Q$67*((ROW(Credit_Input!$Q$8:$Q$67)-8+1)>C35-12)*((ROW(Credit_Input!$Q$8:$Q$67)-8+1)<=C35))+SUMPRODUCT(Credit_Input!$Q$72:$Q$131*((ROW(Credit_Input!$Q$72:$Q$131)-72+1)>C35-12)*((ROW(Credit_Input!$Q$72:$Q$131)-72+1)<=C35))+SUMPRODUCT(Credit_Input!$Q$136:$Q$195*((ROW(Credit_Input!$Q$136:$Q$195)-136+1)>C35-12)*((ROW(Credit_Input!$Q$136:$Q$195)-136+1)<=C35))+SUMPRODUCT(Credit_Input!$Q$200:$Q$259*((ROW(Credit_Input!$Q$200:$Q$259)-200+1)>C35-12)*((ROW(Credit_Input!$Q$200:$Q$259)-200+1)<=C35))+SUMPRODUCT(Credit_Input!$Q$264:$Q$323*((ROW(Credit_Input!$Q$264:$Q$323)-264+1)>C35-12)*((ROW(Credit_Input!$Q$264:$Q$323)-264+1)<=C35)))/(SUMPRODUCT(Credit_Input!$R$8:$R$67*((ROW(Credit_Input!$R$8:$R$67)-8+1)>C35-12)*((ROW(Credit_Input!$R$8:$R$67)-8+1)<=C35))+SUMPRODUCT(Credit_Input!$R$72:$R$131*((ROW(Credit_Input!$R$72:$R$131)-72+1)>C35-12)*((ROW(Credit_Input!$R$72:$R$131)-72+1)<=C35))+SUMPRODUCT(Credit_Input!$R$136:$R$195*((ROW(Credit_Input!$R$136:$R$195)-136+1)>C35-12)*((ROW(Credit_Input!$R$136:$R$195)-136+1)<=C35))+SUMPRODUCT(Credit_Input!$R$200:$R$259*((ROW(Credit_Input!$R$200:$R$259)-200+1)>C35-12)*((ROW(Credit_Input!$R$200:$R$259)-200+1)<=C35))+SUMPRODUCT(Credit_Input!$R$264:$R$323*((ROW(Credit_Input!$R$264:$R$323)-264+1)>C35-12)*((ROW(Credit_Input!$R$264:$R$323)-264+1)<=C35))),"n/a"))
A41: Collected instalments divided by instalments due, deposits excluded, summed over tiers. An operational ratio, not the PAYGo PERFORM 2026 Repayment Rate. Blank Credit_Input gives n/a.

Sheet Vintage_Dashboard
A1: Vintage dashboard
A2: [ACTUAL cohorts and FORECAST proxy] Portfolio data mode, actual cohort coverage, ownership evidence, M12 tier summary, vintage curve.
A4: Cohorts in Actual mode (all tiers) | C4: =COUNTIF(Vintage_Input!$B$9:$B$68,2)+COUNTIF(Vintage_Input!$B$74:$B$133,2)+COUNTIF(Vintage_Input!$B$139:$B$198,2)+COUNTIF(Vintage_Input!$B$204:$B$263,2)+COUNTIF(Vintage_Input!$B$269:$B$328,2) | K4: Readiness flags
A5: Portfolio vintage mode | C5: =IF(C4=0,"PROXY",IF(C4=300,"ACTUAL","MIXED")) | K5: Actual cohort data loaded | Q5: =IF(C4>0,1,0)
A6: Cohorts with ownership-at-2x data | C6: =COUNT(Vintage_Input!$BH$9:$BH$68)+COUNT(Vintage_Input!$BH$74:$BH$133)+COUNT(Vintage_Input!$BH$139:$BH$198)+COUNT(Vintage_Input!$BH$204:$BH$263)+COUNT(Vintage_Input!$BH$269:$BH$328) | K6: Ownership-at-2x evidence validated (switch = 1 and data present) | Q6: =IF(AND(C7=1,C6>0),1,0)
A7: Ownership evidence switch (Inputs) | C7: =Inputs!$C$39 | K7: Conflict: ownership switch = 1 without ownership data | Q7: =IF(AND(C7=1,C6=0),1,0)
A9: Tier summary at M12 | B9: Actual cohorts | C9: Cohort repayment ratio | D9: 30+ DPD / due | E9: 90+ DPD / due | F9: 180+ default / due | G9: Recovery / default | H9: Active share | I9: CAC payback (m)
A10: Tier 1: Pico solar kit | B10: =COUNTIF(Vintage_Input!$B$9:$B$68,2) | C10: =IFERROR(AVERAGE(Vintage_Engine!$F$61:$F$120),"") | D10: =IFERROR(AVERAGE(Vintage_Engine!$N$61:$N$120),"") | E10: =IFERROR(AVERAGE(Vintage_Engine!$V$61:$V$120),"") | F10: =IFERROR(AVERAGE(Vintage_Engine!$AD$61:$AD$120),"") | G10: =IFERROR(AVERAGE(Vintage_Engine!$AL$61:$AL$120),"") | H10: =IFERROR(AVERAGE(Vintage_Engine!$AT$61:$AT$120),"") | I10: =Unit_Economics!C22
A11: Tier 2: SHS with TV | B11: =COUNTIF(Vintage_Input!$B$74:$B$133,2) | C11: =IFERROR(AVERAGE(Vintage_Engine!$F$125:$F$184),"") | D11: =IFERROR(AVERAGE(Vintage_Engine!$N$125:$N$184),"") | E11: =IFERROR(AVERAGE(Vintage_Engine!$V$125:$V$184),"") | F11: =IFERROR(AVERAGE(Vintage_Engine!$AD$125:$AD$184),"") | G11: =IFERROR(AVERAGE(Vintage_Engine!$AL$125:$AL$184),"") | H11: =IFERROR(AVERAGE(Vintage_Engine!$AT$125:$AT$184),"") | I11: =Unit_Economics!D22
A12: Tier 3: Large SHS + DC fridge | B12: =COUNTIF(Vintage_Input!$B$139:$B$198,2) | C12: =IFERROR(AVERAGE(Vintage_Engine!$F$189:$F$248),"") | D12: =IFERROR(AVERAGE(Vintage_Engine!$N$189:$N$248),"") | E12: =IFERROR(AVERAGE(Vintage_Engine!$V$189:$V$248),"") | F12: =IFERROR(AVERAGE(Vintage_Engine!$AD$189:$AD$248),"") | G12: =IFERROR(AVERAGE(Vintage_Engine!$AL$189:$AL$248),"") | H12: =IFERROR(AVERAGE(Vintage_Engine!$AT$189:$AT$248),"") | I12: =Unit_Economics!E22
A13: Tier 4: Solar inverter + lithium (~1.2 kWp / 5 kWh) | B13: =COUNTIF(Vintage_Input!$B$204:$B$263,2) | C13: =IFERROR(AVERAGE(Vintage_Engine!$F$253:$F$312),"") | D13: =IFERROR(AVERAGE(Vintage_Engine!$N$253:$N$312),"") | E13: =IFERROR(AVERAGE(Vintage_Engine!$V$253:$V$312),"") | F13: =IFERROR(AVERAGE(Vintage_Engine!$AD$253:$AD$312),"") | G13: =IFERROR(AVERAGE(Vintage_Engine!$AL$253:$AL$312),"") | H13: =IFERROR(AVERAGE(Vintage_Engine!$AT$253:$AT$312),"") | I13: =Unit_Economics!F22
A14: Tier 5: Solar inverter + lithium (~3 kWp / 10 kWh) | B14: =COUNTIF(Vintage_Input!$B$269:$B$328,2) | C14: =IFERROR(AVERAGE(Vintage_Engine!$F$317:$F$376),"") | D14: =IFERROR(AVERAGE(Vintage_Engine!$N$317:$N$376),"") | E14: =IFERROR(AVERAGE(Vintage_Engine!$V$317:$V$376),"") | F14: =IFERROR(AVERAGE(Vintage_Engine!$AD$317:$AD$376),"") | G14: =IFERROR(AVERAGE(Vintage_Engine!$AL$317:$AL$376),"") | H14: =IFERROR(AVERAGE(Vintage_Engine!$AT$317:$AT$376),"") | I14: =Unit_Economics!G22
A17: Portfolio vintage curve (mix-weighted tier averages) | B17: M3 | C17: M6 | D17: M12 | E17: M18 | F17: M24 | G17: M36 | H17: M48 | I17: M60
A18: Cohort repayment ratio | B18: =Products!$C$23*IFERROR(AVERAGE(Vintage_Engine!$D$61:$D$120),0)+Products!$D$23*IFERROR(AVERAGE(Vintage_Engine!$D$125:$D$184),0)+Products!$E$23*IFERROR(AVERAGE(Vintage_Engine!$D$189:$D$248),0)+Products!$F$23*IFERROR(AVERAGE(Vintage_Engine!$D$253:$D$312),0)+Products!$G$23*IFERROR(AVERAGE(Vintage_Engine!$D$317:$D$376),0) | C18: =Products!$C$23*IFERROR(AVERAGE(Vintage_Engine!$E$61:$E$120),0)+Products!$D$23*IFERROR(AVERAGE(Vintage_Engine!$E$125:$E$184),0)+Products!$E$23*IFERROR(AVERAGE(Vintage_Engine!$E$189:$E$248),0)+Products!$F$23*IFERROR(AVERAGE(Vintage_Engine!$E$253:$E$312),0)+Products!$G$23*IFERROR(AVERAGE(Vintage_Engine!$E$317:$E$376),0) | D18: =Products!$C$23*IFERROR(AVERAGE(Vintage_Engine!$F$61:$F$120),0)+Products!$D$23*IFERROR(AVERAGE(Vintage_Engine!$F$125:$F$184),0)+Products!$E$23*IFERROR(AVERAGE(Vintage_Engine!$F$189:$F$248),0)+Products!$F$23*IFERROR(AVERAGE(Vintage_Engine!$F$253:$F$312),0)+Products!$G$23*IFERROR(AVERAGE(Vintage_Engine!$F$317:$F$376),0) | E18: =Products!$C$23*IFERROR(AVERAGE(Vintage_Engine!$G$61:$G$120),0)+Products!$D$23*IFERROR(AVERAGE(Vintage_Engine!$G$125:$G$184),0)+Products!$E$23*IFERROR(AVERAGE(Vintage_Engine!$G$189:$G$248),0)+Products!$F$23*IFERROR(AVERAGE(Vintage_Engine!$G$253:$G$312),0)+Products!$G$23*IFERROR(AVERAGE(Vintage_Engine!$G$317:$G$376),0) | F18: =Products!$C$23*IFERROR(AVERAGE(Vintage_Engine!$H$61:$H$120),0)+Products!$D$23*IFERROR(AVERAGE(Vintage_Engine!$H$125:$H$184),0)+Products!$E$23*IFERROR(AVERAGE(Vintage_Engine!$H$189:$H$248),0)+Products!$F$23*IFERROR(AVERAGE(Vintage_Engine!$H$253:$H$312),0)+Products!$G$23*IFERROR(AVERAGE(Vintage_Engine!$H$317:$H$376),0) | G18: =Products!$C$23*IFERROR(AVERAGE(Vintage_Engine!$I$61:$I$120),0)+Products!$D$23*IFERROR(AVERAGE(Vintage_Engine!$I$125:$I$184),0)+Products!$E$23*IFERROR(AVERAGE(Vintage_Engine!$I$189:$I$248),0)+Products!$F$23*IFERROR(AVERAGE(Vintage_Engine!$I$253:$I$312),0)+Products!$G$23*IFERROR(AVERAGE(Vintage_Engine!$I$317:$I$376),0) | H18: =Products!$C$23*IFERROR(AVERAGE(Vintage_Engine!$J$61:$J$120),0)+Products!$D$23*IFERROR(AVERAGE(Vintage_Engine!$J$125:$J$184),0)+Products!$E$23*IFERROR(AVERAGE(Vintage_Engine!$J$189:$J$248),0)+Products!$F$23*IFERROR(AVERAGE(Vintage_Engine!$J$253:$J$312),0)+Products!$G$23*IFERROR(AVERAGE(Vintage_Engine!$J$317:$J$376),0) | I18: =Products!$C$23*IFERROR(AVERAGE(Vintage_Engine!$K$61:$K$120),0)+Products!$D$23*IFERROR(AVERAGE(Vintage_Engine!$K$125:$K$184),0)+Products!$E$23*IFERROR(AVERAGE(Vintage_Engine!$K$189:$K$248),0)+Products!$F$23*IFERROR(AVERAGE(Vintage_Engine!$K$253:$K$312),0)+Products!$G$23*IFERROR(AVERAGE(Vintage_Engine!$K$317:$K$376),0)
A19: 30+ DPD / due | B19: =Products!$C$23*IFERROR(AVERAGE(Vintage_Engine!$L$61:$L$120),0)+Products!$D$23*IFERROR(AVERAGE(Vintage_Engine!$L$125:$L$184),0)+Products!$E$23*IFERROR(AVERAGE(Vintage_Engine!$L$189:$L$248),0)+Products!$F$23*IFERROR(AVERAGE(Vintage_Engine!$L$253:$L$312),0)+Products!$G$23*IFERROR(AVERAGE(Vintage_Engine!$L$317:$L$376),0) | C19: =Products!$C$23*IFERROR(AVERAGE(Vintage_Engine!$M$61:$M$120),0)+Products!$D$23*IFERROR(AVERAGE(Vintage_Engine!$M$125:$M$184),0)+Products!$E$23*IFERROR(AVERAGE(Vintage_Engine!$M$189:$M$248),0)+Products!$F$23*IFERROR(AVERAGE(Vintage_Engine!$M$253:$M$312),0)+Products!$G$23*IFERROR(AVERAGE(Vintage_Engine!$M$317:$M$376),0) | D19: =Products!$C$23*IFERROR(AVERAGE(Vintage_Engine!$N$61:$N$120),0)+Products!$D$23*IFERROR(AVERAGE(Vintage_Engine!$N$125:$N$184),0)+Products!$E$23*IFERROR(AVERAGE(Vintage_Engine!$N$189:$N$248),0)+Products!$F$23*IFERROR(AVERAGE(Vintage_Engine!$N$253:$N$312),0)+Products!$G$23*IFERROR(AVERAGE(Vintage_Engine!$N$317:$N$376),0) | E19: =Products!$C$23*IFERROR(AVERAGE(Vintage_Engine!$O$61:$O$120),0)+Products!$D$23*IFERROR(AVERAGE(Vintage_Engine!$O$125:$O$184),0)+Products!$E$23*IFERROR(AVERAGE(Vintage_Engine!$O$189:$O$248),0)+Products!$F$23*IFERROR(AVERAGE(Vintage_Engine!$O$253:$O$312),0)+Products!$G$23*IFERROR(AVERAGE(Vintage_Engine!$O$317:$O$376),0) | F19: =Products!$C$23*IFERROR(AVERAGE(Vintage_Engine!$P$61:$P$120),0)+Products!$D$23*IFERROR(AVERAGE(Vintage_Engine!$P$125:$P$184),0)+Products!$E$23*IFERROR(AVERAGE(Vintage_Engine!$P$189:$P$248),0)+Products!$F$23*IFERROR(AVERAGE(Vintage_Engine!$P$253:$P$312),0)+Products!$G$23*IFERROR(AVERAGE(Vintage_Engine!$P$317:$P$376),0) | G19: =Products!$C$23*IFERROR(AVERAGE(Vintage_Engine!$Q$61:$Q$120),0)+Products!$D$23*IFERROR(AVERAGE(Vintage_Engine!$Q$125:$Q$184),0)+Products!$E$23*IFERROR(AVERAGE(Vintage_Engine!$Q$189:$Q$248),0)+Products!$F$23*IFERROR(AVERAGE(Vintage_Engine!$Q$253:$Q$312),0)+Products!$G$23*IFERROR(AVERAGE(Vintage_Engine!$Q$317:$Q$376),0) | H19: =Products!$C$23*IFERROR(AVERAGE(Vintage_Engine!$R$61:$R$120),0)+Products!$D$23*IFERROR(AVERAGE(Vintage_Engine!$R$125:$R$184),0)+Products!$E$23*IFERROR(AVERAGE(Vintage_Engine!$R$189:$R$248),0)+Products!$F$23*IFERROR(AVERAGE(Vintage_Engine!$R$253:$R$312),0)+Products!$G$23*IFERROR(AVERAGE(Vintage_Engine!$R$317:$R$376),0) | I19: =Products!$C$23*IFERROR(AVERAGE(Vintage_Engine!$S$61:$S$120),0)+Products!$D$23*IFERROR(AVERAGE(Vintage_Engine!$S$125:$S$184),0)+Products!$E$23*IFERROR(AVERAGE(Vintage_Engine!$S$189:$S$248),0)+Products!$F$23*IFERROR(AVERAGE(Vintage_Engine!$S$253:$S$312),0)+Products!$G$23*IFERROR(AVERAGE(Vintage_Engine!$S$317:$S$376),0)
A20: 90+ DPD / due | B20: =Products!$C$23*IFERROR(AVERAGE(Vintage_Engine!$T$61:$T$120),0)+Products!$D$23*IFERROR(AVERAGE(Vintage_Engine!$T$125:$T$184),0)+Products!$E$23*IFERROR(AVERAGE(Vintage_Engine!$T$189:$T$248),0)+Products!$F$23*IFERROR(AVERAGE(Vintage_Engine!$T$253:$T$312),0)+Products!$G$23*IFERROR(AVERAGE(Vintage_Engine!$T$317:$T$376),0) | C20: =Products!$C$23*IFERROR(AVERAGE(Vintage_Engine!$U$61:$U$120),0)+Products!$D$23*IFERROR(AVERAGE(Vintage_Engine!$U$125:$U$184),0)+Products!$E$23*IFERROR(AVERAGE(Vintage_Engine!$U$189:$U$248),0)+Products!$F$23*IFERROR(AVERAGE(Vintage_Engine!$U$253:$U$312),0)+Products!$G$23*IFERROR(AVERAGE(Vintage_Engine!$U$317:$U$376),0) | D20: =Products!$C$23*IFERROR(AVERAGE(Vintage_Engine!$V$61:$V$120),0)+Products!$D$23*IFERROR(AVERAGE(Vintage_Engine!$V$125:$V$184),0)+Products!$E$23*IFERROR(AVERAGE(Vintage_Engine!$V$189:$V$248),0)+Products!$F$23*IFERROR(AVERAGE(Vintage_Engine!$V$253:$V$312),0)+Products!$G$23*IFERROR(AVERAGE(Vintage_Engine!$V$317:$V$376),0) | E20: =Products!$C$23*IFERROR(AVERAGE(Vintage_Engine!$W$61:$W$120),0)+Products!$D$23*IFERROR(AVERAGE(Vintage_Engine!$W$125:$W$184),0)+Products!$E$23*IFERROR(AVERAGE(Vintage_Engine!$W$189:$W$248),0)+Products!$F$23*IFERROR(AVERAGE(Vintage_Engine!$W$253:$W$312),0)+Products!$G$23*IFERROR(AVERAGE(Vintage_Engine!$W$317:$W$376),0) | F20: =Products!$C$23*IFERROR(AVERAGE(Vintage_Engine!$X$61:$X$120),0)+Products!$D$23*IFERROR(AVERAGE(Vintage_Engine!$X$125:$X$184),0)+Products!$E$23*IFERROR(AVERAGE(Vintage_Engine!$X$189:$X$248),0)+Products!$F$23*IFERROR(AVERAGE(Vintage_Engine!$X$253:$X$312),0)+Products!$G$23*IFERROR(AVERAGE(Vintage_Engine!$X$317:$X$376),0) | G20: =Products!$C$23*IFERROR(AVERAGE(Vintage_Engine!$Y$61:$Y$120),0)+Products!$D$23*IFERROR(AVERAGE(Vintage_Engine!$Y$125:$Y$184),0)+Products!$E$23*IFERROR(AVERAGE(Vintage_Engine!$Y$189:$Y$248),0)+Products!$F$23*IFERROR(AVERAGE(Vintage_Engine!$Y$253:$Y$312),0)+Products!$G$23*IFERROR(AVERAGE(Vintage_Engine!$Y$317:$Y$376),0) | H20: =Products!$C$23*IFERROR(AVERAGE(Vintage_Engine!$Z$61:$Z$120),0)+Products!$D$23*IFERROR(AVERAGE(Vintage_Engine!$Z$125:$Z$184),0)+Products!$E$23*IFERROR(AVERAGE(Vintage_Engine!$Z$189:$Z$248),0)+Products!$F$23*IFERROR(AVERAGE(Vintage_Engine!$Z$253:$Z$312),0)+Products!$G$23*IFERROR(AVERAGE(Vintage_Engine!$Z$317:$Z$376),0) | I20: =Products!$C$23*IFERROR(AVERAGE(Vintage_Engine!$AA$61:$AA$120),0)+Products!$D$23*IFERROR(AVERAGE(Vintage_Engine!$AA$125:$AA$184),0)+Products!$E$23*IFERROR(AVERAGE(Vintage_Engine!$AA$189:$AA$248),0)+Products!$F$23*IFERROR(AVERAGE(Vintage_Engine!$AA$253:$AA$312),0)+Products!$G$23*IFERROR(AVERAGE(Vintage_Engine!$AA$317:$AA$376),0)
A22: Proxy cohorts are identical within a tier (same curve). Mixed portfolios average Proxy and Actual cohorts: read with care.

Sheet PERFORM_2026
A1: PAYGo PERFORM KPIs (GOGLA Technical Guide, June 2026)
A2: [ACTUAL (section C) and FORECAST approximations] Company-reported results computed on contract-level data under the 2026 standard, aggregated by summing numerators and denominators. The model does not compute PERFORM KPIs; section B shows labelled approximations only.
A5: A. Company-reported PAYGo PERFORM KPIs (from section C; blank = not provided)
A6: KPI | B6: Type | C6: Tier 1 | D6: Tier 2 | E6: Tier 3 | F6: Tier 4 | G6: Tier 5 | H6: Portfolio | I6: Status
A7: RR, paid vs plan (PvP), to date | B7: Time series | C7: =IF(SUM(PERFORM_2026!$E$43:$E$102)=0,"not provided",SUM(PERFORM_2026!$D$43:$D$102)/SUM(PERFORM_2026!$E$43:$E$102)) | D7: =IF(SUM(PERFORM_2026!$E$108:$E$167)=0,"not provided",SUM(PERFORM_2026!$D$108:$D$167)/SUM(PERFORM_2026!$E$108:$E$167)) | E7: =IF(SUM(PERFORM_2026!$E$173:$E$232)=0,"not provided",SUM(PERFORM_2026!$D$173:$D$232)/SUM(PERFORM_2026!$E$173:$E$232)) | F7: =IF(SUM(PERFORM_2026!$E$238:$E$297)=0,"not provided",SUM(PERFORM_2026!$D$238:$D$297)/SUM(PERFORM_2026!$E$238:$E$297)) | G7: =IF(SUM(PERFORM_2026!$E$303:$E$362)=0,"not provided",SUM(PERFORM_2026!$D$303:$D$362)/SUM(PERFORM_2026!$E$303:$E$362)) | H7: =IF((SUM(PERFORM_2026!$E$43:$E$102)+SUM(PERFORM_2026!$E$108:$E$167)+SUM(PERFORM_2026!$E$173:$E$232)+SUM(PERFORM_2026!$E$238:$E$297)+SUM(PERFORM_2026!$E$303:$E$362))=0,"not provided",(SUM(PERFORM_2026!$D$43:$D$102)+SUM(PERFORM_2026!$D$108:$D$167)+SUM(PERFORM_2026!$D$173:$D$232)+SUM(PERFORM_2026!$D$238:$D$297)+SUM(PERFORM_2026!$D$303:$D$362))/(SUM(PERFORM_2026!$E$43:$E$102)+SUM(PERFORM_2026!$E$108:$E$167)+SUM(PERFORM_2026!$E$173:$E$232)+SUM(PERFORM_2026!$E$238:$E$297)+SUM(PERFORM_2026!$E$303:$E$362))) | I7: =IF(ISNUMBER(H7),"Company reported","Not provided")
A8: RR, paid vs financed (PvFin), to date | B8: Time series | C8: =IF(SUM(PERFORM_2026!$G$43:$G$102)=0,"not provided",SUM(PERFORM_2026!$F$43:$F$102)/SUM(PERFORM_2026!$G$43:$G$102)) | D8: =IF(SUM(PERFORM_2026!$G$108:$G$167)=0,"not provided",SUM(PERFORM_2026!$F$108:$F$167)/SUM(PERFORM_2026!$G$108:$G$167)) | E8: =IF(SUM(PERFORM_2026!$G$173:$G$232)=0,"not provided",SUM(PERFORM_2026!$F$173:$F$232)/SUM(PERFORM_2026!$G$173:$G$232)) | F8: =IF(SUM(PERFORM_2026!$G$238:$G$297)=0,"not provided",SUM(PERFORM_2026!$F$238:$F$297)/SUM(PERFORM_2026!$G$238:$G$297)) | G8: =IF(SUM(PERFORM_2026!$G$303:$G$362)=0,"not provided",SUM(PERFORM_2026!$F$303:$F$362)/SUM(PERFORM_2026!$G$303:$G$362)) | H8: =IF((SUM(PERFORM_2026!$G$43:$G$102)+SUM(PERFORM_2026!$G$108:$G$167)+SUM(PERFORM_2026!$G$173:$G$232)+SUM(PERFORM_2026!$G$238:$G$297)+SUM(PERFORM_2026!$G$303:$G$362))=0,"not provided",(SUM(PERFORM_2026!$F$43:$F$102)+SUM(PERFORM_2026!$F$108:$F$167)+SUM(PERFORM_2026!$F$173:$F$232)+SUM(PERFORM_2026!$F$238:$F$297)+SUM(PERFORM_2026!$F$303:$F$362))/(SUM(PERFORM_2026!$G$43:$G$102)+SUM(PERFORM_2026!$G$108:$G$167)+SUM(PERFORM_2026!$G$173:$G$232)+SUM(PERFORM_2026!$G$238:$G$297)+SUM(PERFORM_2026!$G$303:$G$362))) | I8: =IF(ISNUMBER(H8),"Company reported","Not provided")
A9: RR PvP at 90 days | B9: Cohort milestone | C9: =IF(SUM(PERFORM_2026!$I$43:$I$102)=0,"not provided",SUM(PERFORM_2026!$H$43:$H$102)/SUM(PERFORM_2026!$I$43:$I$102)) | D9: =IF(SUM(PERFORM_2026!$I$108:$I$167)=0,"not provided",SUM(PERFORM_2026!$H$108:$H$167)/SUM(PERFORM_2026!$I$108:$I$167)) | E9: =IF(SUM(PERFORM_2026!$I$173:$I$232)=0,"not provided",SUM(PERFORM_2026!$H$173:$H$232)/SUM(PERFORM_2026!$I$173:$I$232)) | F9: =IF(SUM(PERFORM_2026!$I$238:$I$297)=0,"not provided",SUM(PERFORM_2026!$H$238:$H$297)/SUM(PERFORM_2026!$I$238:$I$297)) | G9: =IF(SUM(PERFORM_2026!$I$303:$I$362)=0,"not provided",SUM(PERFORM_2026!$H$303:$H$362)/SUM(PERFORM_2026!$I$303:$I$362)) | H9: =IF((SUM(PERFORM_2026!$I$43:$I$102)+SUM(PERFORM_2026!$I$108:$I$167)+SUM(PERFORM_2026!$I$173:$I$232)+SUM(PERFORM_2026!$I$238:$I$297)+SUM(PERFORM_2026!$I$303:$I$362))=0,"not provided",(SUM(PERFORM_2026!$H$43:$H$102)+SUM(PERFORM_2026!$H$108:$H$167)+SUM(PERFORM_2026!$H$173:$H$232)+SUM(PERFORM_2026!$H$238:$H$297)+SUM(PERFORM_2026!$H$303:$H$362))/(SUM(PERFORM_2026!$I$43:$I$102)+SUM(PERFORM_2026!$I$108:$I$167)+SUM(PERFORM_2026!$I$173:$I$232)+SUM(PERFORM_2026!$I$238:$I$297)+SUM(PERFORM_2026!$I$303:$I$362))) | I9: =IF(ISNUMBER(H9),"Company reported","Not provided")
A10: RR PvP at 2x contract term | B10: Cohort outcome | C10: =IF(SUM(PERFORM_2026!$K$43:$K$102)=0,"not provided",SUM(PERFORM_2026!$J$43:$J$102)/SUM(PERFORM_2026!$K$43:$K$102)) | D10: =IF(SUM(PERFORM_2026!$K$108:$K$167)=0,"not provided",SUM(PERFORM_2026!$J$108:$J$167)/SUM(PERFORM_2026!$K$108:$K$167)) | E10: =IF(SUM(PERFORM_2026!$K$173:$K$232)=0,"not provided",SUM(PERFORM_2026!$J$173:$J$232)/SUM(PERFORM_2026!$K$173:$K$232)) | F10: =IF(SUM(PERFORM_2026!$K$238:$K$297)=0,"not provided",SUM(PERFORM_2026!$J$238:$J$297)/SUM(PERFORM_2026!$K$238:$K$297)) | G10: =IF(SUM(PERFORM_2026!$K$303:$K$362)=0,"not provided",SUM(PERFORM_2026!$J$303:$J$362)/SUM(PERFORM_2026!$K$303:$K$362)) | H10: =IF((SUM(PERFORM_2026!$K$43:$K$102)+SUM(PERFORM_2026!$K$108:$K$167)+SUM(PERFORM_2026!$K$173:$K$232)+SUM(PERFORM_2026!$K$238:$K$297)+SUM(PERFORM_2026!$K$303:$K$362))=0,"not provided",(SUM(PERFORM_2026!$J$43:$J$102)+SUM(PERFORM_2026!$J$108:$J$167)+SUM(PERFORM_2026!$J$173:$J$232)+SUM(PERFORM_2026!$J$238:$J$297)+SUM(PERFORM_2026!$J$303:$J$362))/(SUM(PERFORM_2026!$K$43:$K$102)+SUM(PERFORM_2026!$K$108:$K$167)+SUM(PERFORM_2026!$K$173:$K$232)+SUM(PERFORM_2026!$K$238:$K$297)+SUM(PERFORM_2026!$K$303:$K$362))) | I10: =IF(ISNUMBER(H10),"Company reported","Not provided")
A11: Ownership rate at 2x contract term (OR @2x) | B11: Cohort outcome | C11: =IF(SUM(PERFORM_2026!$M$43:$M$102)=0,"not provided",SUM(PERFORM_2026!$L$43:$L$102)/SUM(PERFORM_2026!$M$43:$M$102)) | D11: =IF(SUM(PERFORM_2026!$M$108:$M$167)=0,"not provided",SUM(PERFORM_2026!$L$108:$L$167)/SUM(PERFORM_2026!$M$108:$M$167)) | E11: =IF(SUM(PERFORM_2026!$M$173:$M$232)=0,"not provided",SUM(PERFORM_2026!$L$173:$L$232)/SUM(PERFORM_2026!$M$173:$M$232)) | F11: =IF(SUM(PERFORM_2026!$M$238:$M$297)=0,"not provided",SUM(PERFORM_2026!$L$238:$L$297)/SUM(PERFORM_2026!$M$238:$M$297)) | G11: =IF(SUM(PERFORM_2026!$M$303:$M$362)=0,"not provided",SUM(PERFORM_2026!$L$303:$L$362)/SUM(PERFORM_2026!$M$303:$M$362)) | H11: =IF((SUM(PERFORM_2026!$M$43:$M$102)+SUM(PERFORM_2026!$M$108:$M$167)+SUM(PERFORM_2026!$M$173:$M$232)+SUM(PERFORM_2026!$M$238:$M$297)+SUM(PERFORM_2026!$M$303:$M$362))=0,"not provided",(SUM(PERFORM_2026!$L$43:$L$102)+SUM(PERFORM_2026!$L$108:$L$167)+SUM(PERFORM_2026!$L$173:$L$232)+SUM(PERFORM_2026!$L$238:$L$297)+SUM(PERFORM_2026!$L$303:$L$362))/(SUM(PERFORM_2026!$M$43:$M$102)+SUM(PERFORM_2026!$M$108:$M$167)+SUM(PERFORM_2026!$M$173:$M$232)+SUM(PERFORM_2026!$M$238:$M$297)+SUM(PERFORM_2026!$M$303:$M$362))) | I11: =IF(ISNUMBER(H11),"Company reported","Not provided")
A13: Cohorts reported (RR PvP) | C13: =COUNT(PERFORM_2026!$E$43:$E$102) | D13: =COUNT(PERFORM_2026!$E$108:$E$167) | E13: =COUNT(PERFORM_2026!$E$173:$E$232) | F13: =COUNT(PERFORM_2026!$E$238:$E$297) | G13: =COUNT(PERFORM_2026!$E$303:$E$362) | H13: =SUM(C13:G13)
A14: Contracts reported | C14: =SUM(PERFORM_2026!$C$43:$C$102) | D14: =SUM(PERFORM_2026!$C$108:$C$167) | E14: =SUM(PERFORM_2026!$C$173:$C$232) | F14: =SUM(PERFORM_2026!$C$238:$C$297) | G14: =SUM(PERFORM_2026!$C$303:$C$362) | H14: =SUM(C14:G14)
A15: Cohorts with fewer than 100 contracts (the guide recommends at least 100 per monthly cohort) | C15: =COUNTIFS(PERFORM_2026!$C$43:$C$102,">0",PERFORM_2026!$C$43:$C$102,"<100") | D15: =COUNTIFS(PERFORM_2026!$C$108:$C$167,">0",PERFORM_2026!$C$108:$C$167,"<100") | E15: =COUNTIFS(PERFORM_2026!$C$173:$C$232,">0",PERFORM_2026!$C$173:$C$232,"<100") | F15: =COUNTIFS(PERFORM_2026!$C$238:$C$297,">0",PERFORM_2026!$C$238:$C$297,"<100") | G15: =COUNTIFS(PERFORM_2026!$C$303:$C$362,">0",PERFORM_2026!$C$303:$C$362,"<100") | H15: =SUM(C15:G15)
A18: B. Approximations from Vintage_Input monthly checkpoints: NOT PAYGo PERFORM KPIs (monthly, no payment allocation)
A19: Vintage_Input checkpoints (account age, months) | C19: 3 | D19: 6 | E19: 12 | F19: 18 | G19: 24 | H19: 36 | I19: 48 | J19: 60
A20: Approximation | B20: Basis | C20: Tier 1 | D20: Tier 2 | E20: Tier 3 | F20: Tier 4 | G20: Tier 5
A21: Cohort repayment ratio at about 90 days | B21: M3 checkpoint, Actual cohorts | C21: =IF(COUNTIF(Vintage_Input!$B$9:$B$68,2)=0,"not available: proxy data only",IFERROR(SUMPRODUCT((Vintage_Input!$B$9:$B$68=2)*(Vintage_Input!$L$9:$L$68<>"")*(Vintage_Input!$D$9:$D$68<>""),Vintage_Input!$D$9:$D$68)/SUMPRODUCT((Vintage_Input!$B$9:$B$68=2)*(Vintage_Input!$L$9:$L$68<>"")*(Vintage_Input!$D$9:$D$68<>""),Vintage_Input!$L$9:$L$68),"no data at M3")) | D21: =IF(COUNTIF(Vintage_Input!$B$74:$B$133,2)=0,"not available: proxy data only",IFERROR(SUMPRODUCT((Vintage_Input!$B$74:$B$133=2)*(Vintage_Input!$L$74:$L$133<>"")*(Vintage_Input!$D$74:$D$133<>""),Vintage_Input!$D$74:$D$133)/SUMPRODUCT((Vintage_Input!$B$74:$B$133=2)*(Vintage_Input!$L$74:$L$133<>"")*(Vintage_Input!$D$74:$D$133<>""),Vintage_Input!$L$74:$L$133),"no data at M3")) | E21: =IF(COUNTIF(Vintage_Input!$B$139:$B$198,2)=0,"not available: proxy data only",IFERROR(SUMPRODUCT((Vintage_Input!$B$139:$B$198=2)*(Vintage_Input!$L$139:$L$198<>"")*(Vintage_Input!$D$139:$D$198<>""),Vintage_Input!$D$139:$D$198)/SUMPRODUCT((Vintage_Input!$B$139:$B$198=2)*(Vintage_Input!$L$139:$L$198<>"")*(Vintage_Input!$D$139:$D$198<>""),Vintage_Input!$L$139:$L$198),"no data at M3")) | F21: =IF(COUNTIF(Vintage_Input!$B$204:$B$263,2)=0,"not available: proxy data only",IFERROR(SUMPRODUCT((Vintage_Input!$B$204:$B$263=2)*(Vintage_Input!$L$204:$L$263<>"")*(Vintage_Input!$D$204:$D$263<>""),Vintage_Input!$D$204:$D$263)/SUMPRODUCT((Vintage_Input!$B$204:$B$263=2)*(Vintage_Input!$L$204:$L$263<>"")*(Vintage_Input!$D$204:$D$263<>""),Vintage_Input!$L$204:$L$263),"no data at M3")) | G21: =IF(COUNTIF(Vintage_Input!$B$269:$B$328,2)=0,"not available: proxy data only",IFERROR(SUMPRODUCT((Vintage_Input!$B$269:$B$328=2)*(Vintage_Input!$L$269:$L$328<>"")*(Vintage_Input!$D$269:$D$328<>""),Vintage_Input!$D$269:$D$328)/SUMPRODUCT((Vintage_Input!$B$269:$B$328=2)*(Vintage_Input!$L$269:$L$328<>"")*(Vintage_Input!$D$269:$D$328<>""),Vintage_Input!$L$269:$L$328),"no data at M3"))
A22: Cohort repayment ratio at 2x term | B22: Collections at the 2x checkpoint over instalments due over 1x term, Actual cohorts | C22: =IF(COUNTIF(Vintage_Input!$B$9:$B$68,2)=0,"not available: proxy data only",IF(ISNA(MATCH(2*Products!$C$16,PERFORM_2026!$C$19:$J$19,0)),"2x term beyond the input checkpoints",IFERROR(SUMPRODUCT(--(Vintage_Input!$B$9:$B$68=2),CHOOSE(MATCH(2*Products!$C$16,PERFORM_2026!$C$19:$J$19,0),Vintage_Input!$D$9:$D$68,Vintage_Input!$E$9:$E$68,Vintage_Input!$F$9:$F$68,Vintage_Input!$G$9:$G$68,Vintage_Input!$H$9:$H$68,Vintage_Input!$I$9:$I$68,Vintage_Input!$J$9:$J$68,Vintage_Input!$K$9:$K$68))/SUMPRODUCT(--(Vintage_Input!$B$9:$B$68=2),--ISNUMBER(CHOOSE(MATCH(2*Products!$C$16,PERFORM_2026!$C$19:$J$19,0),Vintage_Input!$D$9:$D$68,Vintage_Input!$E$9:$E$68,Vintage_Input!$F$9:$F$68,Vintage_Input!$G$9:$G$68,Vintage_Input!$H$9:$H$68,Vintage_Input!$I$9:$I$68,Vintage_Input!$J$9:$J$68,Vintage_Input!$K$9:$K$68)),CHOOSE(COUNTIF(PERFORM_2026!$C$19:$J$19,"<"&Products!$C$16)+1,Vintage_Input!$L$9:$L$68,Vintage_Input!$M$9:$M$68,Vintage_Input!$N$9:$N$68,Vintage_Input!$O$9:$O$68,Vintage_Input!$P$9:$P$68,Vintage_Input!$Q$9:$Q$68,Vintage_Input!$R$9:$R$68,Vintage_Input!$S$9:$S$68)),"no cohort has reached 2x term"))) | D22: =IF(COUNTIF(Vintage_Input!$B$74:$B$133,2)=0,"not available: proxy data only",IF(ISNA(MATCH(2*Products!$D$16,PERFORM_2026!$C$19:$J$19,0)),"2x term beyond the input checkpoints",IFERROR(SUMPRODUCT(--(Vintage_Input!$B$74:$B$133=2),CHOOSE(MATCH(2*Products!$D$16,PERFORM_2026!$C$19:$J$19,0),Vintage_Input!$D$74:$D$133,Vintage_Input!$E$74:$E$133,Vintage_Input!$F$74:$F$133,Vintage_Input!$G$74:$G$133,Vintage_Input!$H$74:$H$133,Vintage_Input!$I$74:$I$133,Vintage_Input!$J$74:$J$133,Vintage_Input!$K$74:$K$133))/SUMPRODUCT(--(Vintage_Input!$B$74:$B$133=2),--ISNUMBER(CHOOSE(MATCH(2*Products!$D$16,PERFORM_2026!$C$19:$J$19,0),Vintage_Input!$D$74:$D$133,Vintage_Input!$E$74:$E$133,Vintage_Input!$F$74:$F$133,Vintage_Input!$G$74:$G$133,Vintage_Input!$H$74:$H$133,Vintage_Input!$I$74:$I$133,Vintage_Input!$J$74:$J$133,Vintage_Input!$K$74:$K$133)),CHOOSE(COUNTIF(PERFORM_2026!$C$19:$J$19,"<"&Products!$D$16)+1,Vintage_Input!$L$74:$L$133,Vintage_Input!$M$74:$M$133,Vintage_Input!$N$74:$N$133,Vintage_Input!$O$74:$O$133,Vintage_Input!$P$74:$P$133,Vintage_Input!$Q$74:$Q$133,Vintage_Input!$R$74:$R$133,Vintage_Input!$S$74:$S$133)),"no cohort has reached 2x term"))) | E22: =IF(COUNTIF(Vintage_Input!$B$139:$B$198,2)=0,"not available: proxy data only",IF(ISNA(MATCH(2*Products!$E$16,PERFORM_2026!$C$19:$J$19,0)),"2x term beyond the input checkpoints",IFERROR(SUMPRODUCT(--(Vintage_Input!$B$139:$B$198=2),CHOOSE(MATCH(2*Products!$E$16,PERFORM_2026!$C$19:$J$19,0),Vintage_Input!$D$139:$D$198,Vintage_Input!$E$139:$E$198,Vintage_Input!$F$139:$F$198,Vintage_Input!$G$139:$G$198,Vintage_Input!$H$139:$H$198,Vintage_Input!$I$139:$I$198,Vintage_Input!$J$139:$J$198,Vintage_Input!$K$139:$K$198))/SUMPRODUCT(--(Vintage_Input!$B$139:$B$198=2),--ISNUMBER(CHOOSE(MATCH(2*Products!$E$16,PERFORM_2026!$C$19:$J$19,0),Vintage_Input!$D$139:$D$198,Vintage_Input!$E$139:$E$198,Vintage_Input!$F$139:$F$198,Vintage_Input!$G$139:$G$198,Vintage_Input!$H$139:$H$198,Vintage_Input!$I$139:$I$198,Vintage_Input!$J$139:$J$198,Vintage_Input!$K$139:$K$198)),CHOOSE(COUNTIF(PERFORM_2026!$C$19:$J$19,"<"&Products!$E$16)+1,Vintage_Input!$L$139:$L$198,Vintage_Input!$M$139:$M$198,Vintage_Input!$N$139:$N$198,Vintage_Input!$O$139:$O$198,Vintage_Input!$P$139:$P$198,Vintage_Input!$Q$139:$Q$198,Vintage_Input!$R$139:$R$198,Vintage_Input!$S$139:$S$198)),"no cohort has reached 2x term"))) | F22: =IF(COUNTIF(Vintage_Input!$B$204:$B$263,2)=0,"not available: proxy data only",IF(ISNA(MATCH(2*Products!$F$16,PERFORM_2026!$C$19:$J$19,0)),"2x term beyond the input checkpoints",IFERROR(SUMPRODUCT(--(Vintage_Input!$B$204:$B$263=2),CHOOSE(MATCH(2*Products!$F$16,PERFORM_2026!$C$19:$J$19,0),Vintage_Input!$D$204:$D$263,Vintage_Input!$E$204:$E$263,Vintage_Input!$F$204:$F$263,Vintage_Input!$G$204:$G$263,Vintage_Input!$H$204:$H$263,Vintage_Input!$I$204:$I$263,Vintage_Input!$J$204:$J$263,Vintage_Input!$K$204:$K$263))/SUMPRODUCT(--(Vintage_Input!$B$204:$B$263=2),--ISNUMBER(CHOOSE(MATCH(2*Products!$F$16,PERFORM_2026!$C$19:$J$19,0),Vintage_Input!$D$204:$D$263,Vintage_Input!$E$204:$E$263,Vintage_Input!$F$204:$F$263,Vintage_Input!$G$204:$G$263,Vintage_Input!$H$204:$H$263,Vintage_Input!$I$204:$I$263,Vintage_Input!$J$204:$J$263,Vintage_Input!$K$204:$K$263)),CHOOSE(COUNTIF(PERFORM_2026!$C$19:$J$19,"<"&Products!$F$16)+1,Vintage_Input!$L$204:$L$263,Vintage_Input!$M$204:$M$263,Vintage_Input!$N$204:$N$263,Vintage_Input!$O$204:$O$263,Vintage_Input!$P$204:$P$263,Vintage_Input!$Q$204:$Q$263,Vintage_Input!$R$204:$R$263,Vintage_Input!$S$204:$S$263)),"no cohort has reached 2x term"))) | G22: =IF(COUNTIF(Vintage_Input!$B$269:$B$328,2)=0,"not available: proxy data only",IF(ISNA(MATCH(2*Products!$G$16,PERFORM_2026!$C$19:$J$19,0)),"2x term beyond the input checkpoints",IFERROR(SUMPRODUCT(--(Vintage_Input!$B$269:$B$328=2),CHOOSE(MATCH(2*Products!$G$16,PERFORM_2026!$C$19:$J$19,0),Vintage_Input!$D$269:$D$328,Vintage_Input!$E$269:$E$328,Vintage_Input!$F$269:$F$328,Vintage_Input!$G$269:$G$328,Vintage_Input!$H$269:$H$328,Vintage_Input!$I$269:$I$328,Vintage_Input!$J$269:$J$328,Vintage_Input!$K$269:$K$328))/SUMPRODUCT(--(Vintage_Input!$B$269:$B$328=2),--ISNUMBER(CHOOSE(MATCH(2*Products!$G$16,PERFORM_2026!$C$19:$J$19,0),Vintage_Input!$D$269:$D$328,Vintage_Input!$E$269:$E$328,Vintage_Input!$F$269:$F$328,Vintage_Input!$G$269:$G$328,Vintage_Input!$H$269:$H$328,Vintage_Input!$I$269:$I$328,Vintage_Input!$J$269:$J$328,Vintage_Input!$K$269:$K$328)),CHOOSE(COUNTIF(PERFORM_2026!$C$19:$J$19,"<"&Products!$G$16)+1,Vintage_Input!$L$269:$L$328,Vintage_Input!$M$269:$M$328,Vintage_Input!$N$269:$N$328,Vintage_Input!$O$269:$O$328,Vintage_Input!$P$269:$P$328,Vintage_Input!$Q$269:$Q$328,Vintage_Input!$R$269:$R$328,Vintage_Input!$S$269:$S$328)),"no cohort has reached 2x term")))
A23: Ownership at 2x reported in Vintage_Input | B23: Unit weighted, cohorts with ownership data | C23: =IF(COUNT(Vintage_Input!$BH$9:$BH$68)=0,"not reported",SUMPRODUCT(Vintage_Input!$BH$9:$BH$68,Vintage_Input!$C$9:$C$68)/SUMPRODUCT(--ISNUMBER(Vintage_Input!$BH$9:$BH$68),Vintage_Input!$C$9:$C$68)) | D23: =IF(COUNT(Vintage_Input!$BH$74:$BH$133)=0,"not reported",SUMPRODUCT(Vintage_Input!$BH$74:$BH$133,Vintage_Input!$C$74:$C$133)/SUMPRODUCT(--ISNUMBER(Vintage_Input!$BH$74:$BH$133),Vintage_Input!$C$74:$C$133)) | E23: =IF(COUNT(Vintage_Input!$BH$139:$BH$198)=0,"not reported",SUMPRODUCT(Vintage_Input!$BH$139:$BH$198,Vintage_Input!$C$139:$C$198)/SUMPRODUCT(--ISNUMBER(Vintage_Input!$BH$139:$BH$198),Vintage_Input!$C$139:$C$198)) | F23: =IF(COUNT(Vintage_Input!$BH$204:$BH$263)=0,"not reported",SUMPRODUCT(Vintage_Input!$BH$204:$BH$263,Vintage_Input!$C$204:$C$263)/SUMPRODUCT(--ISNUMBER(Vintage_Input!$BH$204:$BH$263),Vintage_Input!$C$204:$C$263)) | G23: =IF(COUNT(Vintage_Input!$BH$269:$BH$328)=0,"not reported",SUMPRODUCT(Vintage_Input!$BH$269:$BH$328,Vintage_Input!$C$269:$C$328)/SUMPRODUCT(--ISNUMBER(Vintage_Input!$BH$269:$BH$328),Vintage_Input!$C$269:$C$328))
A25: Under the 2026 standard a collection rate, days locked or enabled, or self-defined variants may not substitute for the Repayment Rate (Technical Guide, page 10, rule 3A). The operational collection rate on KPIs and Covenants is a cash conversion metric only.
A26: Rules for section C (Technical Guide, pages 8 to 10): exclude deposits, prepayments, penalties, fees and subsidies; include arrears payments and written-off contracts; cumulative from contract start after any free-use period; original contract terms; daily-normalised instalments; payments recognised when applied to due instalments.
A38: C. Company-reported results by monthly cohort (COMPANY DATA: inputs, blank by default)
A41: Tier 1: Pico solar kit
A42: Cohort # | B42: Origination month | C42: Contracts | D42: RR PvP: payments applied to due instalments | E42: RR PvP: instalments due to date | F42: RR PvFin: payments applied to due instalments | G42: RR PvFin: total amount financed | H42: RR @90 days: payments applied | I42: RR @90 days: instalments due by day 90 | J42: RR @2x: payments applied by 2x term | K42: RR @2x: instalments due over 1x term | L42: OR @2x: contracts fully paid by 2x | M42: OR @2x: contracts that reached 2x | N42: Data as of | O42: Notes
A43: 1
A44: 2
A45: 3
A46: 4
A47: 5
A48: 6
A49: 7
A50: 8
A51: 9
A52: 10
A53: 11
A54: 12
... A102: 60
A106: Tier 2: SHS with TV
A107: Cohort # | B107: Origination month | C107: Contracts | D107: RR PvP: payments applied to due instalments | E107: RR PvP: instalments due to date | F107: RR PvFin: payments applied to due instalments | G107: RR PvFin: total amount financed | H107: RR @90 days: payments applied | I107: RR @90 days: instalments due by day 90 | J107: RR @2x: payments applied by 2x term | K107: RR @2x: instalments due over 1x term | L107: OR @2x: contracts fully paid by 2x | M107: OR @2x: contracts that reached 2x | N107: Data as of | O107: Notes
A108: 1
A109: 2
A110: 3
A111: 4
A112: 5
A113: 6
A114: 7
A115: 8
A116: 9
A117: 10
A118: 11
A119: 12
... A167: 60
A171: Tier 3: Large SHS + DC fridge
A172: Cohort # | B172: Origination month | C172: Contracts | D172: RR PvP: payments applied to due instalments | E172: RR PvP: instalments due to date | F172: RR PvFin: payments applied to due instalments | G172: RR PvFin: total amount financed | H172: RR @90 days: payments applied | I172: RR @90 days: instalments due by day 90 | J172: RR @2x: payments applied by 2x term | K172: RR @2x: instalments due over 1x term | L172: OR @2x: contracts fully paid by 2x | M172: OR @2x: contracts that reached 2x | N172: Data as of | O172: Notes
A173: 1
A174: 2
A175: 3
A176: 4
A177: 5
A178: 6
A179: 7
A180: 8
A181: 9
A182: 10
A183: 11
A184: 12
... A232: 60
A236: Tier 4: Solar inverter + lithium (~1.2 kWp / 5 kWh)
A237: Cohort # | B237: Origination month | C237: Contracts | D237: RR PvP: payments applied to due instalments | E237: RR PvP: instalments due to date | F237: RR PvFin: payments applied to due instalments | G237: RR PvFin: total amount financed | H237: RR @90 days: payments applied | I237: RR @90 days: instalments due by day 90 | J237: RR @2x: payments applied by 2x term | K237: RR @2x: instalments due over 1x term | L237: OR @2x: contracts fully paid by 2x | M237: OR @2x: contracts that reached 2x | N237: Data as of | O237: Notes
A238: 1
A239: 2
A240: 3
A241: 4
A242: 5
A243: 6
A244: 7
A245: 8
A246: 9
A247: 10
A248: 11
A249: 12
... A297: 60
A301: Tier 5: Solar inverter + lithium (~3 kWp / 10 kWh)
A302: Cohort # | B302: Origination month | C302: Contracts | D302: RR PvP: payments applied to due instalments | E302: RR PvP: instalments due to date | F302: RR PvFin: payments applied to due instalments | G302: RR PvFin: total amount financed | H302: RR @90 days: payments applied | I302: RR @90 days: instalments due by day 90 | J302: RR @2x: payments applied by 2x term | K302: RR @2x: instalments due over 1x term | L302: OR @2x: contracts fully paid by 2x | M302: OR @2x: contracts that reached 2x | N302: Data as of | O302: Notes
A303: 1
A304: 2
A305: 3
A306: 4
A307: 5
A308: 6
A309: 7
A310: 8
A311: 9
A312: 10
A313: 11
A314: 12
... A362: 60

Sheet Covenants
A1: Lender covenant tests (monthly)
A2: [FORECAST] Flags = 1 when a covenant is breached. Tested only while the relevant debt is outstanding.
A4: Month # | D4: Opening | E4: =Timeline!E4 | F4: =Timeline!F4 | G4: =Timeline!G4 | H4: =Timeline!H4 | I4: =Timeline!I4 | J4: =Timeline!J4 | K4: =Timeline!K4 | L4: =Timeline!L4 | ... BL4: =Timeline!BL4
A5: Period end | E5: =Timeline!E5 | F5: =Timeline!F5 | G5: =Timeline!G5 | H5: =Timeline!H5 | I5: =Timeline!I5 | J5: =Timeline!J5 | K5: =Timeline!K5 | L5: =Timeline!L5 | ... BL5: =Timeline!BL5
A6: Year # | E6: =Timeline!E6 | F6: =Timeline!F6 | G6: =Timeline!G6 | H6: =Timeline!H6 | I6: =Timeline!I6 | J6: =Timeline!J6 | K6: =Timeline!K6 | L6: =Timeline!L6 | ... BL6: =Timeline!BL6
A8: Trailing 3-month collection rate | C8: =MIN(E8:BL8) | E8: =IFERROR(SUM(Ops!E140:E140)/SUM(Ops!E139:E139),0) | F8: =IFERROR(SUM(Ops!E140:F140)/SUM(Ops!E139:F139),0) | G8: =IFERROR(SUM(Ops!E140:G140)/SUM(Ops!E139:G139),0) | H8: =IFERROR(SUM(Ops!F140:H140)/SUM(Ops!F139:H139),0) | I8: =IFERROR(SUM(Ops!G140:I140)/SUM(Ops!G139:I139),0) | J8: =IFERROR(SUM(Ops!H140:J140)/SUM(Ops!H139:J139),0) | K8: =IFERROR(SUM(Ops!I140:K140)/SUM(Ops!I139:K139),0) | L8: =IFERROR(SUM(Ops!J140:L140)/SUM(Ops!J139:L139),0) | M8: =IFERROR(SUM(Ops!K140:M140)/SUM(Ops!K139:M139),0) | N8: =IFERROR(SUM(Ops!L140:N140)/SUM(Ops!L139:N139),0) | ... BL8: =IFERROR(SUM(Ops!BJ140:BL140)/SUM(Ops!BJ139:BL139),0)
A9: Breach: collection rate below minimum | C9: =SUM(E9:BL9) | E9: =IF(AND(Financing!E$23>0,E8<Inputs!$C$70),1,0) | F9: =IF(AND(Financing!F$23>0,F8<Inputs!$C$70),1,0) | G9: =IF(AND(Financing!G$23>0,G8<Inputs!$C$70),1,0) | H9: =IF(AND(Financing!H$23>0,H8<Inputs!$C$70),1,0) | I9: =IF(AND(Financing!I$23>0,I8<Inputs!$C$70),1,0) | J9: =IF(AND(Financing!J$23>0,J8<Inputs!$C$70),1,0) | K9: =IF(AND(Financing!K$23>0,K8<Inputs!$C$70),1,0) | L9: =IF(AND(Financing!L$23>0,L8<Inputs!$C$70),1,0) | ... BL9: =IF(AND(Financing!BL$23>0,BL8<Inputs!$C$70),1,0)
A10: Receivables at risk / gross receivables | C10: =MAX(E10:BL10) | E10: =Ops!E$161 | F10: =Ops!F$161 | G10: =Ops!G$161 | H10: =Ops!H$161 | I10: =Ops!I$161 | J10: =Ops!J$161 | K10: =Ops!K$161 | L10: =Ops!L$161 | ... BL10: =Ops!BL$161
A11: Breach: receivables at risk above maximum | C11: =SUM(E11:BL11) | E11: =IF(AND(Financing!E$23>0,E10>Inputs!$C$71),1,0) | F11: =IF(AND(Financing!F$23>0,F10>Inputs!$C$71),1,0) | G11: =IF(AND(Financing!G$23>0,G10>Inputs!$C$71),1,0) | H11: =IF(AND(Financing!H$23>0,H10>Inputs!$C$71),1,0) | I11: =IF(AND(Financing!I$23>0,I10>Inputs!$C$71),1,0) | J11: =IF(AND(Financing!J$23>0,J10>Inputs!$C$71),1,0) | K11: =IF(AND(Financing!K$23>0,K10>Inputs!$C$71),1,0) | L11: =IF(AND(Financing!L$23>0,L10>Inputs!$C$71),1,0) | ... BL11: =IF(AND(Financing!BL$23>0,BL10>Inputs!$C$71),1,0)
A12: Total financial debt (LCY) | C12: =MAX(E12:BL12) | E12: =FS!E$41+FS!E$42 | F12: =FS!F$41+FS!F$42 | G12: =FS!G$41+FS!G$42 | H12: =FS!H$41+FS!H$42 | I12: =FS!I$41+FS!I$42 | J12: =FS!J$41+FS!J$42 | K12: =FS!K$41+FS!K$42 | L12: =FS!L$41+FS!L$42 | ... BL12: =FS!BL$41+FS!BL$42
A13: Debt / book equity | C13: =MAX(E13:BL13) | E13: =IF(FS!E$46<=0,99,E12/FS!E$46) | F13: =IF(FS!F$46<=0,99,F12/FS!F$46) | G13: =IF(FS!G$46<=0,99,G12/FS!G$46) | H13: =IF(FS!H$46<=0,99,H12/FS!H$46) | I13: =IF(FS!I$46<=0,99,I12/FS!I$46) | J13: =IF(FS!J$46<=0,99,J12/FS!J$46) | K13: =IF(FS!K$46<=0,99,K12/FS!K$46) | L13: =IF(FS!L$46<=0,99,L12/FS!L$46) | ... BL13: =IF(FS!BL$46<=0,99,BL12/FS!BL$46)
A14: Breach: leverage above maximum | C14: =SUM(E14:BL14) | E14: =IF(AND(E12>0,E13>Inputs!$C$72),1,0) | F14: =IF(AND(F12>0,F13>Inputs!$C$72),1,0) | G14: =IF(AND(G12>0,G13>Inputs!$C$72),1,0) | H14: =IF(AND(H12>0,H13>Inputs!$C$72),1,0) | I14: =IF(AND(I12>0,I13>Inputs!$C$72),1,0) | J14: =IF(AND(J12>0,J13>Inputs!$C$72),1,0) | K14: =IF(AND(K12>0,K13>Inputs!$C$72),1,0) | L14: =IF(AND(L12>0,L13>Inputs!$C$72),1,0) | ... BL14: =IF(AND(BL12>0,BL13>Inputs!$C$72),1,0)
A15: Cash before equity top-up (LCY) | C15: =MIN(E15:BL15) | E15: =FS!E$63 | F15: =FS!F$63 | G15: =FS!G$63 | H15: =FS!H$63 | I15: =FS!I$63 | J15: =FS!J$63 | K15: =FS!K$63 | L15: =FS!L$63 | ... BL15: =FS!BL$63
A16: Breach: liquidity below minimum (before new equity) | C16: =SUM(E16:BL16) | E16: =IF(AND(E12>0,E15<Inputs!$C$74),1,0) | F16: =IF(AND(F12>0,F15<Inputs!$C$74),1,0) | G16: =IF(AND(G12>0,G15<Inputs!$C$74),1,0) | H16: =IF(AND(H12>0,H15<Inputs!$C$74),1,0) | I16: =IF(AND(I12>0,I15<Inputs!$C$74),1,0) | J16: =IF(AND(J12>0,J15<Inputs!$C$74),1,0) | K16: =IF(AND(K12>0,K15<Inputs!$C$74),1,0) | L16: =IF(AND(L12>0,L15<Inputs!$C$74),1,0) | ... BL16: =IF(AND(BL12>0,BL15<Inputs!$C$74),1,0)
A17: 30+ DPD receivables / gross receivables (projection) | C17: =MAX(E17:BL17) | E17: =IFERROR((Credit_Engine!E$19+Credit_Engine!E$75+Credit_Engine!E$131+Credit_Engine!E$187+Credit_Engine!E$243)/Ops!E$149,0) | F17: =IFERROR((Credit_Engine!F$19+Credit_Engine!F$75+Credit_Engine!F$131+Credit_Engine!F$187+Credit_Engine!F$243)/Ops!F$149,0) | G17: =IFERROR((Credit_Engine!G$19+Credit_Engine!G$75+Credit_Engine!G$131+Credit_Engine!G$187+Credit_Engine!G$243)/Ops!G$149,0) | H17: =IFERROR((Credit_Engine!H$19+Credit_Engine!H$75+Credit_Engine!H$131+Credit_Engine!H$187+Credit_Engine!H$243)/Ops!H$149,0) | I17: =IFERROR((Credit_Engine!I$19+Credit_Engine!I$75+Credit_Engine!I$131+Credit_Engine!I$187+Credit_Engine!I$243)/Ops!I$149,0) | J17: =IFERROR((Credit_Engine!J$19+Credit_Engine!J$75+Credit_Engine!J$131+Credit_Engine!J$187+Credit_Engine!J$243)/Ops!J$149,0) | K17: =IFERROR((Credit_Engine!K$19+Credit_Engine!K$75+Credit_Engine!K$131+Credit_Engine!K$187+Credit_Engine!K$243)/Ops!K$149,0) | L17: =IFERROR((Credit_Engine!L$19+Credit_Engine!L$75+Credit_Engine!L$131+Credit_Engine!L$187+Credit_Engine!L$243)/Ops!L$149,0) | ... BL17: =IFERROR((Credit_Engine!BL$19+Credit_Engine!BL$75+Credit_Engine!BL$131+Credit_Engine!BL$187+Credit_Engine!BL$243)/Ops!BL$149,0)
A18: Breach: 30+ DPD above maximum | C18: =SUM(E18:BL18) | E18: =IF(AND(Financing!E$23>0,E17>Inputs!$C$75),1,0) | F18: =IF(AND(Financing!F$23>0,F17>Inputs!$C$75),1,0) | G18: =IF(AND(Financing!G$23>0,G17>Inputs!$C$75),1,0) | H18: =IF(AND(Financing!H$23>0,H17>Inputs!$C$75),1,0) | I18: =IF(AND(Financing!I$23>0,I17>Inputs!$C$75),1,0) | J18: =IF(AND(Financing!J$23>0,J17>Inputs!$C$75),1,0) | K18: =IF(AND(Financing!K$23>0,K17>Inputs!$C$75),1,0) | L18: =IF(AND(Financing!L$23>0,L17>Inputs!$C$75),1,0) | ... BL18: =IF(AND(Financing!BL$23>0,BL17>Inputs!$C$75),1,0)
A19: 90+ DPD receivables / gross receivables (projection) | C19: =MAX(E19:BL19) | E19: =IFERROR((Credit_Engine!E$20+Credit_Engine!E$76+Credit_Engine!E$132+Credit_Engine!E$188+Credit_Engine!E$244)/Ops!E$149,0) | F19: =IFERROR((Credit_Engine!F$20+Credit_Engine!F$76+Credit_Engine!F$132+Credit_Engine!F$188+Credit_Engine!F$244)/Ops!F$149,0) | G19: =IFERROR((Credit_Engine!G$20+Credit_Engine!G$76+Credit_Engine!G$132+Credit_Engine!G$188+Credit_Engine!G$244)/Ops!G$149,0) | H19: =IFERROR((Credit_Engine!H$20+Credit_Engine!H$76+Credit_Engine!H$132+Credit_Engine!H$188+Credit_Engine!H$244)/Ops!H$149,0) | I19: =IFERROR((Credit_Engine!I$20+Credit_Engine!I$76+Credit_Engine!I$132+Credit_Engine!I$188+Credit_Engine!I$244)/Ops!I$149,0) | J19: =IFERROR((Credit_Engine!J$20+Credit_Engine!J$76+Credit_Engine!J$132+Credit_Engine!J$188+Credit_Engine!J$244)/Ops!J$149,0) | K19: =IFERROR((Credit_Engine!K$20+Credit_Engine!K$76+Credit_Engine!K$132+Credit_Engine!K$188+Credit_Engine!K$244)/Ops!K$149,0) | L19: =IFERROR((Credit_Engine!L$20+Credit_Engine!L$76+Credit_Engine!L$132+Credit_Engine!L$188+Credit_Engine!L$244)/Ops!L$149,0) | ... BL19: =IFERROR((Credit_Engine!BL$20+Credit_Engine!BL$76+Credit_Engine!BL$132+Credit_Engine!BL$188+Credit_Engine!BL$244)/Ops!BL$149,0)
A20: Breach: 90+ DPD above maximum | C20: =SUM(E20:BL20) | E20: =IF(AND(Financing!E$23>0,E19>Inputs!$C$76),1,0) | F20: =IF(AND(Financing!F$23>0,F19>Inputs!$C$76),1,0) | G20: =IF(AND(Financing!G$23>0,G19>Inputs!$C$76),1,0) | H20: =IF(AND(Financing!H$23>0,H19>Inputs!$C$76),1,0) | I20: =IF(AND(Financing!I$23>0,I19>Inputs!$C$76),1,0) | J20: =IF(AND(Financing!J$23>0,J19>Inputs!$C$76),1,0) | K20: =IF(AND(Financing!K$23>0,K19>Inputs!$C$76),1,0) | L20: =IF(AND(Financing!L$23>0,L19>Inputs!$C$76),1,0) | ... BL20: =IF(AND(Financing!BL$23>0,BL19>Inputs!$C$76),1,0)
A21: Borrowing-base headroom (borrowing base: drawn, LCY) | C21: =MIN(E21:BL21) | E21: =Financing!E$22-Financing!E$23 | F21: =Financing!F$22-Financing!F$23 | G21: =Financing!G$22-Financing!G$23 | H21: =Financing!H$22-Financing!H$23 | I21: =Financing!I$22-Financing!I$23 | J21: =Financing!J$22-Financing!J$23 | K21: =Financing!K$22-Financing!K$23 | L21: =Financing!L$22-Financing!L$23 | ... BL21: =Financing!BL$22-Financing!BL$23
A22: Breach: facility drawn above borrowing base | C22: =SUM(E22:BL22) | E22: =IF(E21<-1,1,0) | F22: =IF(F21<-1,1,0) | G22: =IF(G21<-1,1,0) | H22: =IF(H21<-1,1,0) | I22: =IF(I21<-1,1,0) | J22: =IF(J21<-1,1,0) | K22: =IF(K21<-1,1,0) | L22: =IF(L21<-1,1,0) | ... BL22: =IF(BL21<-1,1,0)
A23: Indicative stage-based ECL (projection, diagnostic) | C23: =MAX(E23:BL23) | E23: =Credit_Engine!E$32+Credit_Engine!E$88+Credit_Engine!E$144+Credit_Engine!E$200+Credit_Engine!E$256 | F23: =Credit_Engine!F$32+Credit_Engine!F$88+Credit_Engine!F$144+Credit_Engine!F$200+Credit_Engine!F$256 | G23: =Credit_Engine!G$32+Credit_Engine!G$88+Credit_Engine!G$144+Credit_Engine!G$200+Credit_Engine!G$256 | H23: =Credit_Engine!H$32+Credit_Engine!H$88+Credit_Engine!H$144+Credit_Engine!H$200+Credit_Engine!H$256 | I23: =Credit_Engine!I$32+Credit_Engine!I$88+Credit_Engine!I$144+Credit_Engine!I$200+Credit_Engine!I$256 | J23: =Credit_Engine!J$32+Credit_Engine!J$88+Credit_Engine!J$144+Credit_Engine!J$200+Credit_Engine!J$256 | K23: =Credit_Engine!K$32+Credit_Engine!K$88+Credit_Engine!K$144+Credit_Engine!K$200+Credit_Engine!K$256 | L23: =Credit_Engine!L$32+Credit_Engine!L$88+Credit_Engine!L$144+Credit_Engine!L$200+Credit_Engine!L$256 | ... BL23: =Credit_Engine!BL$32+Credit_Engine!BL$88+Credit_Engine!BL$144+Credit_Engine!BL$200+Credit_Engine!BL$256
A24: Indicative ECL / gross receivables | C24: =MAX(E24:BL24) | E24: =IFERROR(E23/Ops!E$149,0) | F24: =IFERROR(F23/Ops!F$149,0) | G24: =IFERROR(G23/Ops!G$149,0) | H24: =IFERROR(H23/Ops!H$149,0) | I24: =IFERROR(I23/Ops!I$149,0) | J24: =IFERROR(J23/Ops!J$149,0) | K24: =IFERROR(K23/Ops!K$149,0) | L24: =IFERROR(L23/Ops!L$149,0) | ... BL24: =IFERROR(BL23/Ops!BL$149,0)
A25: Composite credit covenant flag | C25: =SUM(E25:BL25) | E25: =MAX(E9,E11,E18,E20,E22) | F25: =MAX(F9,F11,F18,F20,F22) | G25: =MAX(G9,G11,G18,G20,G22) | H25: =MAX(H9,H11,H18,H20,H22) | I25: =MAX(I9,I11,I18,I20,I22) | J25: =MAX(J9,J11,J18,J20,J22) | K25: =MAX(K9,K11,K18,K20,K22) | L25: =MAX(L9,L11,L18,L20,L22) | ... BL25: =MAX(BL9,BL11,BL18,BL20,BL22)
A26: Any covenant breached in month | C26: =SUM(E26:BL26) | E26: =MAX(E25,E14,E16) | F26: =MAX(F25,F14,F16) | G26: =MAX(G25,G14,G16) | H26: =MAX(H25,H14,H16) | I26: =MAX(I25,I14,I16) | J26: =MAX(J25,J14,J16) | K26: =MAX(K25,K14,K16) | L26: =MAX(L25,L14,L16) | ... BL26: =MAX(BL25,BL14,BL16)

Sheet Valuation
A1: Valuation & investor returns
A2: [FORECAST] DCF of unlevered free cash flow (LCY) and equity investor returns (USD).
D5: Year 0 | E5: Year 1 | F5: Year 2 | G5: Year 3 | H5: Year 4 | I5: Year 5
D6: 0 | E6: 1 | F6: 2 | G6: 3 | H6: 4 | I6: 5
A8: Unlevered free cash flow (LCY)
A9: EBITDA | E9: =SUMIFS(FS!$E$19:$BL$19,Timeline!$E$6:$BL$6,E$6) | F9: =SUMIFS(FS!$E$19:$BL$19,Timeline!$E$6:$BL$6,F$6) | G9: =SUMIFS(FS!$E$19:$BL$19,Timeline!$E$6:$BL$6,G$6) | H9: =SUMIFS(FS!$E$19:$BL$19,Timeline!$E$6:$BL$6,H$6) | I9: =SUMIFS(FS!$E$19:$BL$19,Timeline!$E$6:$BL$6,I$6)
A10: Less: income tax paid (levered tax: simplification) | E10: =SUMIFS(FS!$E$29:$BL$29,Timeline!$E$6:$BL$6,E$6) | F10: =SUMIFS(FS!$E$29:$BL$29,Timeline!$E$6:$BL$6,F$6) | G10: =SUMIFS(FS!$E$29:$BL$29,Timeline!$E$6:$BL$6,G$6) | H10: =SUMIFS(FS!$E$29:$BL$29,Timeline!$E$6:$BL$6,H$6) | I10: =SUMIFS(FS!$E$29:$BL$29,Timeline!$E$6:$BL$6,I$6)
A11: Less: capex | E11: =-SUMIFS(Costs!$E$26:$BL$26,Timeline!$E$6:$BL$6,E$6) | F11: =-SUMIFS(Costs!$E$26:$BL$26,Timeline!$E$6:$BL$6,F$6) | G11: =-SUMIFS(Costs!$E$26:$BL$26,Timeline!$E$6:$BL$6,G$6) | H11: =-SUMIFS(Costs!$E$26:$BL$26,Timeline!$E$6:$BL$6,H$6) | I11: =-SUMIFS(Costs!$E$26:$BL$26,Timeline!$E$6:$BL$6,I$6)
A12: Net working capital (net receivables + inventory: payables), year end | D12: 0 | E12: =INDEX(FS!$E$36:$BL$36,1,E$6*12)+INDEX(FS!$E$37:$BL$37,1,E$6*12)-INDEX(FS!$E$40:$BL$40,1,E$6*12) | F12: =INDEX(FS!$E$36:$BL$36,1,F$6*12)+INDEX(FS!$E$37:$BL$37,1,F$6*12)-INDEX(FS!$E$40:$BL$40,1,F$6*12) | G12: =INDEX(FS!$E$36:$BL$36,1,G$6*12)+INDEX(FS!$E$37:$BL$37,1,G$6*12)-INDEX(FS!$E$40:$BL$40,1,G$6*12) | H12: =INDEX(FS!$E$36:$BL$36,1,H$6*12)+INDEX(FS!$E$37:$BL$37,1,H$6*12)-INDEX(FS!$E$40:$BL$40,1,H$6*12) | I12: =INDEX(FS!$E$36:$BL$36,1,I$6*12)+INDEX(FS!$E$37:$BL$37,1,I$6*12)-INDEX(FS!$E$40:$BL$40,1,I$6*12)
A13: Less: increase in net working capital | E13: =-(E12-D12) | F13: =-(F12-E12) | G13: =-(G12-F12) | H13: =-(H12-G12) | I13: =-(I12-H12)
A14: Unlevered free cash flow (FCFF) | E14: =E9+E10+E11+E13 | F14: =F9+F10+F11+F13 | G14: =G9+G10+G11+G13 | H14: =H9+H10+H11+H13 | I14: =I9+I10+I11+I13
A15: Discount factor (mid-year) | E15: =1/(1+Inputs!$C$79)^(E$6-0.5) | F15: =1/(1+Inputs!$C$79)^(F$6-0.5) | G15: =1/(1+Inputs!$C$79)^(G$6-0.5) | H15: =1/(1+Inputs!$C$79)^(H$6-0.5) | I15: =1/(1+Inputs!$C$79)^(I$6-0.5)
A16: Present value of FCFF | E16: =E14*E15 | F16: =F14*F15 | G16: =G14*G15 | H16: =H14*H15 | I16: =I14*I15
A17: Equity investor (USD)
A18: Equity top-ups in year (LCY) | E18: =SUMIFS(FS!$E$64:$BL$64,Timeline!$E$6:$BL$6,E$6) | F18: =SUMIFS(FS!$E$64:$BL$64,Timeline!$E$6:$BL$6,F$6) | G18: =SUMIFS(FS!$E$64:$BL$64,Timeline!$E$6:$BL$6,G$6) | H18: =SUMIFS(FS!$E$64:$BL$64,Timeline!$E$6:$BL$6,H$6) | I18: =SUMIFS(FS!$E$64:$BL$64,Timeline!$E$6:$BL$6,I$6)
A19: Average FX in year (LCY / USD) | E19: =AVERAGEIFS(Timeline!$E$8:$BL$8,Timeline!$E$6:$BL$6,E$6) | F19: =AVERAGEIFS(Timeline!$E$8:$BL$8,Timeline!$E$6:$BL$6,F$6) | G19: =AVERAGEIFS(Timeline!$E$8:$BL$8,Timeline!$E$6:$BL$6,G$6) | H19: =AVERAGEIFS(Timeline!$E$8:$BL$8,Timeline!$E$6:$BL$6,H$6) | I19: =AVERAGEIFS(Timeline!$E$8:$BL$8,Timeline!$E$6:$BL$6,I$6)
A20: Investor cash flow (USD) | D20: =-Inputs!$C$81 | E20: =-C38*E18/E19 | F20: =-C38*F18/F19 | G20: =-C38*G18/G19 | H20: =-C38*H18/H19 | I20: =-C38*I18/I19+C38*C36
A22: Valuation summary
A23: Sum of PV of FCFF, Years 1-5 (LCY) | C23: =SUM(E16:I16)
A24: Normalised terminal FCFF: (EBITDA: tax: capex)_Y5 x (1+g): g x NWC_Y5 (LCY) | C24: =(I9+I10+I11)*(1+Inputs!$C$80)-Inputs!$C$80*I12
A25: Terminal value at end of Year 5 (Gordon growth on normalised FCFF, LCY) | C25: =IF(Inputs!$C$79>Inputs!$C$80,C24/(Inputs!$C$79-Inputs!$C$80),0)
A26: PV of terminal value (LCY) | C26: =C25/(1+Inputs!$C$79)^5
A27: DCF enterprise value at model start (LCY) | C27: =C23+C26
A28: DCF enterprise value at model start (USD, opening FX) | C28: =C27/Inputs!$C$10
A29: Terminal value share of EV | C29: =IFERROR(C26/C27,0)
A31: Year 5 EBITDA (LCY) | C31: =I9
A32: Net debt at end of Year 5 (LCY) | C32: =INDEX(FS!$E$41:$BL$41,1,I$6*12)+INDEX(FS!$E$42:$BL$42,1,I$6*12)-INDEX(FS!$E$65:$BL$65,1,I$6*12)
A33: Book equity at end of Year 5 (LCY) | C33: =INDEX(FS!$E$46:$BL$46,1,I$6*12)
A34: Exit equity value, 100% (LCY) | C34: =MAX(0,IF(Inputs!$C$83=1,Inputs!$C$84*C31-C32,Inputs!$C$85*C33))
A35: FX at exit (LCY / USD) | C35: =INDEX(Timeline!$E$8:$BL$8,1,60)
A36: Exit equity value, 100% (USD) | C36: =C34/C35
A38: Investor stake (ticket / post-money) | C38: =IFERROR(Inputs!$C$81/(Inputs!$C$82+Inputs!$C$81),0)
A39: Investor IRR (USD) | C39: =IF(OR(COUNTIF(D20:I20,">0")=0,COUNTIF(D20:I20,"<0")=0),"n/a: no sign change",IFERROR(IRR(D20:I20,0.1),IFERROR(IRR(D20:I20,-0.2),IFERROR(IRR(D20:I20,0.5),"n/a: no convergence"))))
A40: Investor MOIC (USD) | C40: =IFERROR(SUMIF(D20:I20,">0")/-SUMIF(D20:I20,"<0"),0)
A42: Investor funds its pro-rata share of any equity top-up and receives no dividends before exit. LCY flows are converted to USD at average FX for the year; exit at year-end FX.
A43: For PAYGo companies, growth of the receivables book is working capital, so FCFF is negative while the book grows. The terminal value therefore uses a normalised FCFF that reinvests only g x NWC (steady-state growth).

Sheet FX_Exposure
A1: FX exposure: currencies, hedging, transaction and translation effects
A2: [FORECAST] Presentation of the model's existing FX calculations. Transaction effects change cash in LCY; translation changes how LCY results look in USD; remeasurement of USD debt is a non-cash accounting entry.
A4: A. Currency map (where each item sits and how the model treats it)
A5: Item | B5: Currency | C5: Treatment in the model | E5: Year 5 (LCY m)
A6: Revenue: hardware and PAYGo financing | B6: LCY | C6: Contract prices in LCY. New contracts are indexed by the pass-through input (Inputs). | E6: =Annual!I12/1000000
A7: Customer collections (mobile money) | B7: LCY | C7: Collected in LCY from the cohort engine. | E7: =SUMIFS(Ops!$E$140:$BL$140,Timeline!$E$6:$BL$6,5)/1000000
A8: PAYGo receivables | B8: LCY | C8: Gross receivables in LCY; no USD indexation of existing contracts. | E8: =Annual!I32/1000000
A9: Hardware (FOB) and freight, duty | B9: USD | C9: Converted at the month's FX rate when units are sold; inventory follows COGS. | E9: =SUMIFS(Costs!$E$8:$BL$8,Timeline!$E$6:$BL$6,5)/1000000
A10: Installation, commissions, opex | B10: LCY | C10: Indexed to local inflation. | E10: =SUMIFS(Costs!$E$20:$BL$20,Timeline!$E$6:$BL$6,5)/1000000
A11: RBF | B11: USD | C11: Set per unit in USD; received in LCY at the FX rate of the payment month. | E11: =Annual!I15/1000000
A12: USD term loan | B12: USD | C12: Remeasured monthly at the closing rate; unrealised FX loss in the income statement. | E12: =Annual!I39/1000000
A13: Receivables facility or securitisation | B13: LCY | C13: Drawn and repaid in LCY against the borrowing base. | E13: =Annual!I40/1000000
A14: Equity | B14: LCY (investor view in USD) | C14: Booked in LCY; the investor's IRR and MOIC are measured in USD on Valuation. | E14: =Annual!I44/1000000
A15: Hedging | B15: None | C15: No forward, swap or option is modelled. The depreciation path is a scenario lever (Scenarios). | E15: =""
A17: B. Exposure and effects by year (active scenario)
A18: Measure | B18: Unit | C18: Year 1 | D18: Year 2 | E18: Year 3 | F18: Year 4 | G18: Year 5 | H18: Total
A19: LCY depreciation against USD (scenario lever) | B19: % p.a. | C19: =Scenarios!$G$10 | D19: =Scenarios!$G$10 | E19: =Scenarios!$G$10 | F19: =Scenarios!$G$10 | G19: =Scenarios!$G$10
A20: FX rate at year end | B20: LCY / USD | C20: =INDEX(Timeline!$E$8:$BL$8,1,12) | D20: =INDEX(Timeline!$E$8:$BL$8,1,24) | E20: =INDEX(Timeline!$E$8:$BL$8,1,36) | F20: =INDEX(Timeline!$E$8:$BL$8,1,48) | G20: =INDEX(Timeline!$E$8:$BL$8,1,60)
A21: Pass-through of depreciation into new-contract prices | B21: % | C21: =Inputs!$C$14 | D21: =Inputs!$C$14 | E21: =Inputs!$C$14 | F21: =Inputs!$C$14 | G21: =Inputs!$C$14
A22: Share of debt in USD at year end | B22: % | C22: =IFERROR(Annual!E39/(Annual!E39+Annual!E40),0) | D22: =IFERROR(Annual!F39/(Annual!F39+Annual!F40),0) | E22: =IFERROR(Annual!G39/(Annual!G39+Annual!G40),0) | F22: =IFERROR(Annual!H39/(Annual!H39+Annual!H40),0) | G22: =IFERROR(Annual!I39/(Annual!I39+Annual!I40),0)
A23: Transaction: extra cost of USD-linked hardware (COGS and warranty) | B23: LCY m | C23: =SUMIFS(Timeline!$E$14:$BL$14,Timeline!$E$6:$BL$6,1)/1000000 | D23: =SUMIFS(Timeline!$E$14:$BL$14,Timeline!$E$6:$BL$6,2)/1000000 | E23: =SUMIFS(Timeline!$E$14:$BL$14,Timeline!$E$6:$BL$6,3)/1000000 | F23: =SUMIFS(Timeline!$E$14:$BL$14,Timeline!$E$6:$BL$6,4)/1000000 | G23: =SUMIFS(Timeline!$E$14:$BL$14,Timeline!$E$6:$BL$6,5)/1000000 | H23: =SUM(C23:G23)
A24: Transaction: extra interest on the USD term loan | B24: LCY m | C24: =SUMIFS(Timeline!$E$15:$BL$15,Timeline!$E$6:$BL$6,1)/1000000 | D24: =SUMIFS(Timeline!$E$15:$BL$15,Timeline!$E$6:$BL$6,2)/1000000 | E24: =SUMIFS(Timeline!$E$15:$BL$15,Timeline!$E$6:$BL$6,3)/1000000 | F24: =SUMIFS(Timeline!$E$15:$BL$15,Timeline!$E$6:$BL$6,4)/1000000 | G24: =SUMIFS(Timeline!$E$15:$BL$15,Timeline!$E$6:$BL$6,5)/1000000 | H24: =SUM(C24:G24)
A25: Transaction: extra LCY to repay USD principal | B25: LCY m | C25: =SUMIFS(Timeline!$E$16:$BL$16,Timeline!$E$6:$BL$6,1)/1000000 | D25: =SUMIFS(Timeline!$E$16:$BL$16,Timeline!$E$6:$BL$6,2)/1000000 | E25: =SUMIFS(Timeline!$E$16:$BL$16,Timeline!$E$6:$BL$6,3)/1000000 | F25: =SUMIFS(Timeline!$E$16:$BL$16,Timeline!$E$6:$BL$6,4)/1000000 | G25: =SUMIFS(Timeline!$E$16:$BL$16,Timeline!$E$6:$BL$6,5)/1000000 | H25: =SUM(C25:G25)
A26: Transaction: extra LCY received on USD-denominated RBF | B26: LCY m | C26: =SUMIFS(Timeline!$E$17:$BL$17,Timeline!$E$6:$BL$6,1)/1000000 | D26: =SUMIFS(Timeline!$E$17:$BL$17,Timeline!$E$6:$BL$6,2)/1000000 | E26: =SUMIFS(Timeline!$E$17:$BL$17,Timeline!$E$6:$BL$6,3)/1000000 | F26: =SUMIFS(Timeline!$E$17:$BL$17,Timeline!$E$6:$BL$6,4)/1000000 | G26: =SUMIFS(Timeline!$E$17:$BL$17,Timeline!$E$6:$BL$6,5)/1000000 | H26: =SUM(C26:G26)
A27: Net transaction effect on costs and RBF, before price pass-through (negative = cost) | B27: LCY m | C27: =SUMIFS(Timeline!$E$18:$BL$18,Timeline!$E$6:$BL$6,1)/1000000 | D27: =SUMIFS(Timeline!$E$18:$BL$18,Timeline!$E$6:$BL$6,2)/1000000 | E27: =SUMIFS(Timeline!$E$18:$BL$18,Timeline!$E$6:$BL$6,3)/1000000 | F27: =SUMIFS(Timeline!$E$18:$BL$18,Timeline!$E$6:$BL$6,4)/1000000 | G27: =SUMIFS(Timeline!$E$18:$BL$18,Timeline!$E$6:$BL$6,5)/1000000 | H27: =SUM(C27:G27)
A28: Remeasurement: unrealised FX loss on USD debt (FS; non-cash) | B28: LCY m | C28: =SUMIFS(Timeline!$E$19:$BL$19,Timeline!$E$6:$BL$6,1)/1000000 | D28: =SUMIFS(Timeline!$E$19:$BL$19,Timeline!$E$6:$BL$6,2)/1000000 | E28: =SUMIFS(Timeline!$E$19:$BL$19,Timeline!$E$6:$BL$6,3)/1000000 | F28: =SUMIFS(Timeline!$E$19:$BL$19,Timeline!$E$6:$BL$6,4)/1000000 | G28: =SUMIFS(Timeline!$E$19:$BL$19,Timeline!$E$6:$BL$6,5)/1000000 | H28: =SUM(C28:G28)
A29: Translation: revenue in USD at the opening rate | B29: USD m | C29: =SUMIFS(Timeline!$E$20:$BL$20,Timeline!$E$6:$BL$6,1)/1000000 | D29: =SUMIFS(Timeline!$E$20:$BL$20,Timeline!$E$6:$BL$6,2)/1000000 | E29: =SUMIFS(Timeline!$E$20:$BL$20,Timeline!$E$6:$BL$6,3)/1000000 | F29: =SUMIFS(Timeline!$E$20:$BL$20,Timeline!$E$6:$BL$6,4)/1000000 | G29: =SUMIFS(Timeline!$E$20:$BL$20,Timeline!$E$6:$BL$6,5)/1000000 | H29: =SUM(C29:G29)
A30: Translation: revenue in USD at the month's rate | B30: USD m | C30: =SUMIFS(Timeline!$E$21:$BL$21,Timeline!$E$6:$BL$6,1)/1000000 | D30: =SUMIFS(Timeline!$E$21:$BL$21,Timeline!$E$6:$BL$6,2)/1000000 | E30: =SUMIFS(Timeline!$E$21:$BL$21,Timeline!$E$6:$BL$6,3)/1000000 | F30: =SUMIFS(Timeline!$E$21:$BL$21,Timeline!$E$6:$BL$6,4)/1000000 | G30: =SUMIFS(Timeline!$E$21:$BL$21,Timeline!$E$6:$BL$6,5)/1000000 | H30: =SUM(C30:G30)
A31: Translation effect on revenue in USD (negative = lower in USD) | B31: USD m | C31: =SUMIFS(Timeline!$E$22:$BL$22,Timeline!$E$6:$BL$6,1)/1000000 | D31: =SUMIFS(Timeline!$E$22:$BL$22,Timeline!$E$6:$BL$6,2)/1000000 | E31: =SUMIFS(Timeline!$E$22:$BL$22,Timeline!$E$6:$BL$6,3)/1000000 | F31: =SUMIFS(Timeline!$E$22:$BL$22,Timeline!$E$6:$BL$6,4)/1000000 | G31: =SUMIFS(Timeline!$E$22:$BL$22,Timeline!$E$6:$BL$6,5)/1000000 | H31: =SUM(C31:G31)
A32: Translation effect on EBITDA in USD | B32: USD m | C32: =SUMIFS(Timeline!$E$23:$BL$23,Timeline!$E$6:$BL$6,1)/1000000 | D32: =SUMIFS(Timeline!$E$23:$BL$23,Timeline!$E$6:$BL$6,2)/1000000 | E32: =SUMIFS(Timeline!$E$23:$BL$23,Timeline!$E$6:$BL$6,3)/1000000 | F32: =SUMIFS(Timeline!$E$23:$BL$23,Timeline!$E$6:$BL$6,4)/1000000 | G32: =SUMIFS(Timeline!$E$23:$BL$23,Timeline!$E$6:$BL$6,5)/1000000 | H32: =SUM(C32:G32)
A33: Memo: hardware revenue added by price pass-through on new contracts (booked at sale, collected over the tenor) | B33: LCY m | C33: =SUMIFS(Timeline!$E$24:$BL$24,Timeline!$E$6:$BL$6,1)/1000000 | D33: =SUMIFS(Timeline!$E$24:$BL$24,Timeline!$E$6:$BL$6,2)/1000000 | E33: =SUMIFS(Timeline!$E$24:$BL$24,Timeline!$E$6:$BL$6,3)/1000000 | F33: =SUMIFS(Timeline!$E$24:$BL$24,Timeline!$E$6:$BL$6,4)/1000000 | G33: =SUMIFS(Timeline!$E$24:$BL$24,Timeline!$E$6:$BL$6,5)/1000000 | H33: =SUM(C33:G33)
A35: Transaction effects compare each LCY amount with what it would have been at the opening rate. They are already inside the statements; this table isolates them. The USD principal effect is the realised counterpart of the remeasurement loss.
A36: The pass-through memo row is the offset on the revenue side: new contracts are priced up by the pass-through share of depreciation. It is booked at sale and collected over the tenor; the effect on financing income of older contracts is not isolated.
A37: Translation does not move LCY cash. It changes how LCY revenue and EBITDA look to a USD investor and drives the USD IRR.
A38: Monthly detail: Timeline, section FX EFFECTS. Stress the path on Scenarios (LCY depreciation) and read the change here and on Valuation.

Sheet Unit_Economics
A1: Unit economics by tier (per unit, month-1 prices, active scenario)
A2: [FORECAST] Lifetime view of one PAYGo customer. Undiscounted unless stated.
A4: Metric | B4: Unit | C4: Tier 1 | D4: Tier 2 | E4: Tier 3 | F4: Tier 4 | G4: Tier 5
A5: Cash price | B5: LCY | C5: =Products!$C$13 | D5: =Products!$D$13 | E5: =Products!$E$13 | F5: =Products!$F$13 | G5: =Products!$G$13
A6: Total PAYGo contract value | B6: LCY | C6: =Products!$C$34 | D6: =Products!$D$34 | E6: =Products!$E$34 | F6: =Products!$F$34 | G6: =Products!$G$34
A7: Implied annual financing rate (nominal APR) | B7: % | C7: =Products!$C$39 | D7: =Products!$D$39 | E7: =Products!$E$39 | F7: =Products!$F$39 | G7: =Products!$G$39
A8: Down payment | B8: LCY | C8: =Products!$C$14 | D8: =Products!$D$14 | E8: =Products!$E$14 | F8: =Products!$F$14 | G8: =Products!$G$14
A9: Expected instalments collected | B9: LCY | C9: =Curves!$D$70 | D9: =Curves!$Q$70 | E9: =Curves!$AD$70 | F9: =Curves!$AQ$70 | G9: =Curves!$BD$70
A10: Expected lifetime customer cash (down payment + instalments) | B10: LCY | C10: =C8+C9 | D10: =D8+D9 | E10: =E8+E9 | F10: =F8+F9 | G10: =G8+G9
A11: Expected loss rate (missed / scheduled instalments) | B11: % | C11: =IFERROR(Curves!$E$70/Curves!$C$70,0) | D11: =IFERROR(Curves!$R$70/Curves!$P$70,0) | E11: =IFERROR(Curves!$AE$70/Curves!$AC$70,0) | F11: =IFERROR(Curves!$AR$70/Curves!$AP$70,0) | G11: =IFERROR(Curves!$BE$70/Curves!$BC$70,0)
A12: Lifetime collection rate (customer cash / contract value) | B12: % | C12: =IFERROR(C10/C6,0) | D12: =IFERROR(D10/D6,0) | E12: =IFERROR(E10/E6,0) | F12: =IFERROR(F10/F6,0) | G12: =IFERROR(G10/G6,0)
A13: Expected recoveries from repossession | B13: LCY | C13: =Curves!$I$70 | D13: =Curves!$V$70 | E13: =Curves!$AI$70 | F13: =Curves!$AV$70 | G13: =Curves!$BI$70
A14: RBF per unit (opening FX) | B14: LCY | C14: =Curves!$J$70 | D14: =Curves!$W$70 | E14: =Curves!$AJ$70 | F14: =Curves!$AW$70 | G14: =Curves!$BJ$70
A15: Landed hardware cost | B15: LCY | C15: =Products!$C$43 | D15: =Products!$D$43 | E15: =Products!$E$43 | F15: =Products!$F$43 | G15: =Products!$G$43
A16: Installation & logistics | B16: LCY | C16: =Products!$C$19 | D16: =Products!$D$19 | E16: =Products!$E$19 | F16: =Products!$F$19 | G16: =Products!$G$19
A17: Warranty provision | B17: LCY | C17: =Products!$C$43*Products!$C$22 | D17: =Products!$D$43*Products!$D$22 | E17: =Products!$E$43*Products!$E$22 | F17: =Products!$F$43*Products!$F$22 | G17: =Products!$G$43*Products!$G$22
A18: Customer acquisition cost (CAC) | B18: LCY | C18: =Products!$C$44 | D18: =Products!$D$44 | E18: =Products!$E$44 | F18: =Products!$F$44 | G18: =Products!$G$44
A19: Payment fees + servicing over life | B19: LCY | C19: =C10*Inputs!$C$24+Inputs!$C$25*(SUM(Curves!$G$8:$G$68)-1) | D19: =D10*Inputs!$C$24+Inputs!$C$25*(SUM(Curves!$T$8:$T$68)-1) | E19: =E10*Inputs!$C$24+Inputs!$C$25*(SUM(Curves!$AG$8:$AG$68)-1) | F19: =F10*Inputs!$C$24+Inputs!$C$25*(SUM(Curves!$AT$8:$AT$68)-1) | G19: =G10*Inputs!$C$24+Inputs!$C$25*(SUM(Curves!$BG$8:$BG$68)-1)
A20: Lifetime contribution per unit | B20: LCY | C20: =C10+C13+C14-C15-C16-C17-C18-C19 | D20: =D10+D13+D14-D15-D16-D17-D18-D19 | E20: =E10+E13+E14-E15-E16-E17-E18-E19 | F20: =F10+F13+F14-F15-F16-F17-F18-F19 | G20: =G10+G13+G14-G15-G16-G17-G18-G19
A21: LTV / CAC (contribution before CAC / CAC) | B21: x | C21: =IFERROR((C20+C18)/C18,0) | D21: =IFERROR((D20+D18)/D18,0) | E21: =IFERROR((E20+E18)/E18,0) | F21: =IFERROR((F20+F18)/F18,0) | G21: =IFERROR((G20+G18)/G18,0)
A22: Cash payback (months after sale) | B22: months | C22: =IF(COUNTIF(Curves!$L$8:$L$68,"<0")>60,"Not paid back",COUNTIF(Curves!$L$8:$L$68,"<0")) | D22: =IF(COUNTIF(Curves!$Y$8:$Y$68,"<0")>60,"Not paid back",COUNTIF(Curves!$Y$8:$Y$68,"<0")) | E22: =IF(COUNTIF(Curves!$AL$8:$AL$68,"<0")>60,"Not paid back",COUNTIF(Curves!$AL$8:$AL$68,"<0")) | F22: =IF(COUNTIF(Curves!$AY$8:$AY$68,"<0")>60,"Not paid back",COUNTIF(Curves!$AY$8:$AY$68,"<0")) | G22: =IF(COUNTIF(Curves!$BL$8:$BL$68,"<0")>60,"Not paid back",COUNTIF(Curves!$BL$8:$BL$68,"<0"))
A23: Unit IRR (annualised, unlevered) | B23: % | C23: =IF(OR(COUNTIF(Curves!$K$8:$K$68,">0")=0,COUNTIF(Curves!$K$8:$K$68,"<0")=0),"n/a: no sign change",IFERROR((1+IRR(Curves!$K$8:$K$68,0.02))^12-1,IFERROR((1+IRR(Curves!$K$8:$K$68,-0.02))^12-1,IFERROR((1+IRR(Curves!$K$8:$K$68,0.1))^12-1,"n/a: no convergence")))) | D23: =IF(OR(COUNTIF(Curves!$X$8:$X$68,">0")=0,COUNTIF(Curves!$X$8:$X$68,"<0")=0),"n/a: no sign change",IFERROR((1+IRR(Curves!$X$8:$X$68,0.02))^12-1,IFERROR((1+IRR(Curves!$X$8:$X$68,-0.02))^12-1,IFERROR((1+IRR(Curves!$X$8:$X$68,0.1))^12-1,"n/a: no convergence")))) | E23: =IF(OR(COUNTIF(Curves!$AK$8:$AK$68,">0")=0,COUNTIF(Curves!$AK$8:$AK$68,"<0")=0),"n/a: no sign change",IFERROR((1+IRR(Curves!$AK$8:$AK$68,0.02))^12-1,IFERROR((1+IRR(Curves!$AK$8:$AK$68,-0.02))^12-1,IFERROR((1+IRR(Curves!$AK$8:$AK$68,0.1))^12-1,"n/a: no convergence")))) | F23: =IF(OR(COUNTIF(Curves!$AX$8:$AX$68,">0")=0,COUNTIF(Curves!$AX$8:$AX$68,"<0")=0),"n/a: no sign change",IFERROR((1+IRR(Curves!$AX$8:$AX$68,0.02))^12-1,IFERROR((1+IRR(Curves!$AX$8:$AX$68,-0.02))^12-1,IFERROR((1+IRR(Curves!$AX$8:$AX$68,0.1))^12-1,"n/a: no convergence")))) | G23: =IF(OR(COUNTIF(Curves!$BK$8:$BK$68,">0")=0,COUNTIF(Curves!$BK$8:$BK$68,"<0")=0),"n/a: no sign change",IFERROR((1+IRR(Curves!$BK$8:$BK$68,0.02))^12-1,IFERROR((1+IRR(Curves!$BK$8:$BK$68,-0.02))^12-1,IFERROR((1+IRR(Curves!$BK$8:$BK$68,0.1))^12-1,"n/a: no convergence"))))
A24: Unit NPV at the DCF discount rate | B24: LCY | C24: =NPV((1+Inputs!$C$79)^(1/12)-1,Curves!$K$8:$K$68)*(1+Inputs!$C$79)^(1/12) | D24: =NPV((1+Inputs!$C$79)^(1/12)-1,Curves!$X$8:$X$68)*(1+Inputs!$C$79)^(1/12) | E24: =NPV((1+Inputs!$C$79)^(1/12)-1,Curves!$AK$8:$AK$68)*(1+Inputs!$C$79)^(1/12) | F24: =NPV((1+Inputs!$C$79)^(1/12)-1,Curves!$AX$8:$AX$68)*(1+Inputs!$C$79)^(1/12) | G24: =NPV((1+Inputs!$C$79)^(1/12)-1,Curves!$BK$8:$BK$68)*(1+Inputs!$C$79)^(1/12)
A26: Servicing counts active months after the sale month. Payback counts months with negative cumulative cash flow (ages 0-60). Unit NPV discounts monthly at the DCF rate; age 0 undiscounted.

Sheet Sensitivity
A1: Scenario & sensitivity table (static, dated) and the live active case
A2: Static rows: computed at DEFAULT inputs and recomputed inside this workbook for every case before release (date below). They do NOT update when inputs change; the LIVE row does.
A5: Case | B5: Peak equity need (USD m) | C5: Year 5 revenue (USD m) | D5: Year 5 EBITDA margin | E5: Year 5 collection rate | F5: DCF EV (USD m) | G5: Investor IRR (USD) | H5: Investor MOIC | I5: Monthly covenant-breach months (excl. annual DSCR)
A6: Base | B6: 10 | C6: 68.45434 | D6: 0.21643258 | E6: 0.7326369 | F6: 15.647635 | G6: 0.46378697 | H6: 6.7203113 | I6: 0
A7: Downside | B7: 10 | C7: 52.677847 | D7: 0.072869343 | E7: 0.67067563 | F7: -9.0285194 | G7: -0.22905023 | H7: 0.2723519 | I7: 44
A8: Severe | B8: 46.602939 | C8: 33.645155 | D8: -0.18380364 | E8: 0.58753459 | F8: -81.922055 | G8: n/a | H8: 0 | I8: 48
A9: Base: default hazard x1.5 | B9: 10 | C9: 68.45434 | D9: 0.15684147 | E9: 0.66126112 | F9: 12.496672 | G9: 0.36128098 | H9: 4.67454 | I9: 40
A10: Base: collection rate x0.95 | B10: 10 | C10: 68.45434 | D10: 0.18294547 | E10: 0.69600506 | F10: 10.88948 | G10: 0.40183546 | H10: 5.413588 | I10: 27
A11: Base: sales volume -20% | B11: 10 | C11: 54.763472 | D11: 0.20368335 | E11: 0.7326369 | F11: 9.358939 | G11: 0.37751469 | H11: 4.9599946 | I11: 0
A12: Base: hardware cost +15% | B12: 10 | C12: 68.45434 | D12: 0.15393617 | E12: 0.7326369 | F12: 7.8227894 | G12: 0.29528045 | H12: 3.6460201 | I12: 38
A13: Base: LCY depreciation 20% p.a. | B13: 10 | C13: 49.519668 | D13: 0.082343289 | E13: 0.73741025 | F13: -7.8171965 | G13: -0.15962037 | H13: 0.41915784 | I13: 41
A14: Base: no price increase on new contracts | B14: 10 | C14: 55.941718 | D14: 0.10414263 | E14: 0.72910543 | F14: -3.322123 | G14: 0.079180627 | H14: 1.4637628 | I14: 35
A15: Base: RBF programme off | B15: 10 | C15: 68.45434 | D15: 0.2082741 | E15: 0.7326369 | F15: 13.969042 | G15: 0.44667965 | H15: 6.3366813 | I15: 0
A16: Base: mix T1 20%, T2 30%, T3 20%, T4 20%, T5 10% | B16: 10 | C16: 111.77093 | D16: 0.24887307 | E16: 0.74586675 | F16: 37.402275 | G16: 0.66611889 | H16: 12.838963 | I16: 0
A17: Base: exit at 4.0x EBITDA | B17: 10 | C17: 68.45434 | D17: 0.21643258 | E17: 0.7326369 | F17: 15.647635 | G17: 0.33906745 | H17: 4.3053878 | I17: 0
A18: Base: repayment-linked RBF (mode 2) | B18: 10 | C18: 68.45434 | D18: 0.21640429 | E18: 0.7326369 | F18: 15.641813 | G18: 0.46372905 | H18: 6.7189817 | I18: 0
A19: Base: securitisation structure | B19: 10 | C19: 68.45434 | D19: 0.21643258 | E19: 0.7326369 | F19: 15.322789 | G19: 0.46494061 | H19: 6.7468351 | I19: 0
A20: Base: borrowing base up to 90 DPD (base does not bind at default) | B20: 10 | C20: 68.45434 | D20: 0.21643258 | E20: 0.7326369 | F20: 15.647635 | G20: 0.46378697 | H20: 6.7203113 | I20: 0
A22: Static table computed on 03 October 2026 at default inputs and recomputed inside this workbook for every case (largest relative difference below one in a billion). To test your own assumptions, read the LIVE row.
A23: LIVE: active case with the current inputs (updates with every change)
A24: =Scenarios!$G$13 | B24: =IF(ISNUMBER(KPIs!$C$57),KPIs!$C$57*1e-06,KPIs!$C$57) | C24: =IF(ISNUMBER(KPIs!$I$35),KPIs!$I$35*1e-06,KPIs!$I$35) | D24: =KPIs!$I$38 | E24: =KPIs!$I$19 | F24: =IF(ISNUMBER(Valuation!$C$28),Valuation!$C$28*1e-06,Valuation!$C$28) | G24: =Valuation!$C$39 | H24: =Valuation!$C$40 | I24: =KPIs!$C$64

Sheet Benchmark_Compare
A1: How does this PAYGo company compare with real companies at scale?
A2: Model (active scenario) vs graded peer records. Peer ranges use grade A-C usable records only; n shows how thin the evidence is.
A5: KPI | B5: Model Y1 | C5: Model Y2 | D5: Model Y3 | E5: Model Y4 | F5: Model Y5 | G5: Peer n | H5: Peer min | I5: Peer median | J5: Peer max | K5: Model Y5 vs peers | L5: Comparability warning
A6: Gross margin | B6: =Benchmark_KPIs!D14 | C6: =Benchmark_KPIs!D15 | D6: =Benchmark_KPIs!D16 | E6: =Benchmark_KPIs!D17 | F6: =Benchmark_KPIs!D18 | G6: =COUNT(Benchmark_KPIs!$D$21:$D$28) | H6: =IF(G6=0,"",MIN(Benchmark_KPIs!$D$21:$D$28)) | I6: =IF(G6=0,"",MEDIAN(Benchmark_KPIs!$D$21:$D$28)) | J6: =IF(G6=0,"",MAX(Benchmark_KPIs!$D$21:$D$28)) | K6: =IF(G6=0,"No graded peer data yet",IF(NOT(ISNUMBER(F6)),"Model value n/a",IF(F6>J6,"Above peer range",IF(F6<H6,"Below peer range","Within peer range")))&IF(G6<3," (n<3: anecdotal)","")) | L6: Cost of sales lines differ (installation, warranty, financing costs).
A7: EBITDA margin | B7: =Benchmark_KPIs!E14 | C7: =Benchmark_KPIs!E15 | D7: =Benchmark_KPIs!E16 | E7: =Benchmark_KPIs!E17 | F7: =Benchmark_KPIs!E18 | G7: =COUNT(Benchmark_KPIs!$E$21:$E$28) | H7: =IF(G7=0,"",MIN(Benchmark_KPIs!$E$21:$E$28)) | I7: =IF(G7=0,"",MEDIAN(Benchmark_KPIs!$E$21:$E$28)) | J7: =IF(G7=0,"",MAX(Benchmark_KPIs!$E$21:$E$28)) | K7: =IF(G7=0,"No graded peer data yet",IF(NOT(ISNUMBER(F7)),"Model value n/a",IF(F7>J7,"Above peer range",IF(F7<H7,"Below peer range","Within peer range")))&IF(G7<3," (n<3: anecdotal)","")) | L7: Companies define EBITDA differently; RBF and credit losses may sit above or below it.
A8: Operating (EBIT) margin | B8: =Benchmark_KPIs!F14 | C8: =Benchmark_KPIs!F15 | D8: =Benchmark_KPIs!F16 | E8: =Benchmark_KPIs!F17 | F8: =Benchmark_KPIs!F18 | G8: =COUNT(Benchmark_KPIs!$F$21:$F$28) | H8: =IF(G8=0,"",MIN(Benchmark_KPIs!$F$21:$F$28)) | I8: =IF(G8=0,"",MEDIAN(Benchmark_KPIs!$F$21:$F$28)) | J8: =IF(G8=0,"",MAX(Benchmark_KPIs!$F$21:$F$28)) | K8: =IF(G8=0,"No graded peer data yet",IF(NOT(ISNUMBER(F8)),"Model value n/a",IF(F8>J8,"Above peer range",IF(F8<H8,"Below peer range","Within peer range")))&IF(G8<3," (n<3: anecdotal)","")) | L8: Check definitions, periods and currency before comparing.
A9: Net margin | B9: =Benchmark_KPIs!G14 | C9: =Benchmark_KPIs!G15 | D9: =Benchmark_KPIs!G16 | E9: =Benchmark_KPIs!G17 | F9: =Benchmark_KPIs!G18 | G9: =COUNT(Benchmark_KPIs!$G$21:$G$28) | H9: =IF(G9=0,"",MIN(Benchmark_KPIs!$G$21:$G$28)) | I9: =IF(G9=0,"",MEDIAN(Benchmark_KPIs!$G$21:$G$28)) | J9: =IF(G9=0,"",MAX(Benchmark_KPIs!$G$21:$G$28)) | K9: =IF(G9=0,"No graded peer data yet",IF(NOT(ISNUMBER(F9)),"Model value n/a",IF(F9>J9,"Above peer range",IF(F9<H9,"Below peer range","Within peer range")))&IF(G9<3," (n<3: anecdotal)","")) | L9: Group accounts include non-PAYGo activities and other currencies.
A10: Revenue growth | B10: =Benchmark_KPIs!H14 | C10: =Benchmark_KPIs!H15 | D10: =Benchmark_KPIs!H16 | E10: =Benchmark_KPIs!H17 | F10: =Benchmark_KPIs!H18 | G10: =COUNT(Benchmark_KPIs!$H$21:$H$28) | H10: =IF(G10=0,"",MIN(Benchmark_KPIs!$H$21:$H$28)) | I10: =IF(G10=0,"",MEDIAN(Benchmark_KPIs!$H$21:$H$28)) | J10: =IF(G10=0,"",MAX(Benchmark_KPIs!$H$21:$H$28)) | K10: =IF(G10=0,"No graded peer data yet",IF(NOT(ISNUMBER(F10)),"Model value n/a",IF(F10>J10,"Above peer range",IF(F10<H10,"Below peer range","Within peer range")))&IF(G10<3," (n<3: anecdotal)","")) | L10: Fiscal years differ from model years; currency of growth matters.
A11: Financing revenue / revenue | B11: =Benchmark_KPIs!I14 | C11: =Benchmark_KPIs!I15 | D11: =Benchmark_KPIs!I16 | E11: =Benchmark_KPIs!I17 | F11: =Benchmark_KPIs!I18 | G11: =COUNT(Benchmark_KPIs!$I$21:$I$28) | H11: =IF(G11=0,"",MIN(Benchmark_KPIs!$I$21:$I$28)) | I11: =IF(G11=0,"",MEDIAN(Benchmark_KPIs!$I$21:$I$28)) | J11: =IF(G11=0,"",MAX(Benchmark_KPIs!$I$21:$I$28)) | K11: =IF(G11=0,"No graded peer data yet",IF(NOT(ISNUMBER(F11)),"Model value n/a",IF(F11>J11,"Above peer range",IF(F11<H11,"Below peer range","Within peer range")))&IF(G11<3," (n<3: anecdotal)","")) | L11: Revenue recognition policies split hardware and financing income differently.
A12: Receivables days | B12: =Benchmark_KPIs!J14 | C12: =Benchmark_KPIs!J15 | D12: =Benchmark_KPIs!J16 | E12: =Benchmark_KPIs!J17 | F12: =Benchmark_KPIs!J18 | G12: =COUNT(Benchmark_KPIs!$J$21:$J$28) | H12: =IF(G12=0,"",MIN(Benchmark_KPIs!$J$21:$J$28)) | I12: =IF(G12=0,"",MEDIAN(Benchmark_KPIs!$J$21:$J$28)) | J12: =IF(G12=0,"",MAX(Benchmark_KPIs!$J$21:$J$28)) | K12: =IF(G12=0,"No graded peer data yet",IF(NOT(ISNUMBER(F12)),"Model value n/a",IF(F12>J12,"Above peer range",IF(F12<H12,"Below peer range","Within peer range")))&IF(G12<3," (n<3: anecdotal)","")) | L12: Gross or net receivables; securitised books may be off balance sheet.
A13: Inventory days | B13: =Benchmark_KPIs!K14 | C13: =Benchmark_KPIs!K15 | D13: =Benchmark_KPIs!K16 | E13: =Benchmark_KPIs!K17 | F13: =Benchmark_KPIs!K18 | G13: =COUNT(Benchmark_KPIs!$K$21:$K$28) | H13: =IF(G13=0,"",MIN(Benchmark_KPIs!$K$21:$K$28)) | I13: =IF(G13=0,"",MEDIAN(Benchmark_KPIs!$K$21:$K$28)) | J13: =IF(G13=0,"",MAX(Benchmark_KPIs!$K$21:$K$28)) | K13: =IF(G13=0,"No graded peer data yet",IF(NOT(ISNUMBER(F13)),"Model value n/a",IF(F13>J13,"Above peer range",IF(F13<H13,"Below peer range","Within peer range")))&IF(G13<3," (n<3: anecdotal)","")) | L13: Check definitions, periods and currency before comparing.
A14: Payables days | B14: =Benchmark_KPIs!L14 | C14: =Benchmark_KPIs!L15 | D14: =Benchmark_KPIs!L16 | E14: =Benchmark_KPIs!L17 | F14: =Benchmark_KPIs!L18 | G14: =COUNT(Benchmark_KPIs!$L$21:$L$28) | H14: =IF(G14=0,"",MIN(Benchmark_KPIs!$L$21:$L$28)) | I14: =IF(G14=0,"",MEDIAN(Benchmark_KPIs!$L$21:$L$28)) | J14: =IF(G14=0,"",MAX(Benchmark_KPIs!$L$21:$L$28)) | K14: =IF(G14=0,"No graded peer data yet",IF(NOT(ISNUMBER(F14)),"Model value n/a",IF(F14>J14,"Above peer range",IF(F14<H14,"Below peer range","Within peer range")))&IF(G14<3," (n<3: anecdotal)","")) | L14: Check definitions, periods and currency before comparing.
A15: Cash conversion cycle (days) | B15: =Benchmark_KPIs!M14 | C15: =Benchmark_KPIs!M15 | D15: =Benchmark_KPIs!M16 | E15: =Benchmark_KPIs!M17 | F15: =Benchmark_KPIs!M18 | G15: =COUNT(Benchmark_KPIs!$M$21:$M$28) | H15: =IF(G15=0,"",MIN(Benchmark_KPIs!$M$21:$M$28)) | I15: =IF(G15=0,"",MEDIAN(Benchmark_KPIs!$M$21:$M$28)) | J15: =IF(G15=0,"",MAX(Benchmark_KPIs!$M$21:$M$28)) | K15: =IF(G15=0,"No graded peer data yet",IF(NOT(ISNUMBER(F15)),"Model value n/a",IF(F15>J15,"Above peer range",IF(F15<H15,"Below peer range","Within peer range")))&IF(G15<3," (n<3: anecdotal)","")) | L15: Check definitions, periods and currency before comparing.
A16: Debt / net receivables | B16: =Benchmark_KPIs!N14 | C16: =Benchmark_KPIs!N15 | D16: =Benchmark_KPIs!N16 | E16: =Benchmark_KPIs!N17 | F16: =Benchmark_KPIs!N18 | G16: =COUNT(Benchmark_KPIs!$N$21:$N$28) | H16: =IF(G16=0,"",MIN(Benchmark_KPIs!$N$21:$N$28)) | I16: =IF(G16=0,"",MEDIAN(Benchmark_KPIs!$N$21:$N$28)) | J16: =IF(G16=0,"",MAX(Benchmark_KPIs!$N$21:$N$28)) | K16: =IF(G16=0,"No graded peer data yet",IF(NOT(ISNUMBER(F16)),"Model value n/a",IF(F16>J16,"Above peer range",IF(F16<H16,"Below peer range","Within peer range")))&IF(G16<3," (n<3: anecdotal)","")) | L16: Check definitions, periods and currency before comparing.
A17: Debt / EBITDA | B17: =Benchmark_KPIs!O14 | C17: =Benchmark_KPIs!O15 | D17: =Benchmark_KPIs!O16 | E17: =Benchmark_KPIs!O17 | F17: =Benchmark_KPIs!O18 | G17: =COUNT(Benchmark_KPIs!$O$21:$O$28) | H17: =IF(G17=0,"",MIN(Benchmark_KPIs!$O$21:$O$28)) | I17: =IF(G17=0,"",MEDIAN(Benchmark_KPIs!$O$21:$O$28)) | J17: =IF(G17=0,"",MAX(Benchmark_KPIs!$O$21:$O$28)) | K17: =IF(G17=0,"No graded peer data yet",IF(NOT(ISNUMBER(F17)),"Model value n/a",IF(F17>J17,"Above peer range",IF(F17<H17,"Below peer range","Within peer range")))&IF(G17<3," (n<3: anecdotal)","")) | L17: Check definitions, periods and currency before comparing.
A18: Total liabilities / total assets | B18: =Benchmark_KPIs!P14 | C18: =Benchmark_KPIs!P15 | D18: =Benchmark_KPIs!P16 | E18: =Benchmark_KPIs!P17 | F18: =Benchmark_KPIs!P18 | G18: =COUNT(Benchmark_KPIs!$P$21:$P$28) | H18: =IF(G18=0,"",MIN(Benchmark_KPIs!$P$21:$P$28)) | I18: =IF(G18=0,"",MEDIAN(Benchmark_KPIs!$P$21:$P$28)) | J18: =IF(G18=0,"",MAX(Benchmark_KPIs!$P$21:$P$28)) | K18: =IF(G18=0,"No graded peer data yet",IF(NOT(ISNUMBER(F18)),"Model value n/a",IF(F18>J18,"Above peer range",IF(F18<H18,"Below peer range","Within peer range")))&IF(G18<3," (n<3: anecdotal)","")) | L18: Check definitions, periods and currency before comparing.
A19: Equity (USD m; derived = assets: liabilities when not reported) | B19: =Benchmark_KPIs!Q14 | C19: =Benchmark_KPIs!Q15 | D19: =Benchmark_KPIs!Q16 | E19: =Benchmark_KPIs!Q17 | F19: =Benchmark_KPIs!Q18 | G19: =COUNT(Benchmark_KPIs!$Q$21:$Q$28) | H19: =IF(G19=0,"",MIN(Benchmark_KPIs!$Q$21:$Q$28)) | I19: =IF(G19=0,"",MEDIAN(Benchmark_KPIs!$Q$21:$Q$28)) | J19: =IF(G19=0,"",MAX(Benchmark_KPIs!$Q$21:$Q$28)) | K19: =IF(G19=0,"No graded peer data yet",IF(NOT(ISNUMBER(F19)),"Model value n/a",IF(F19>J19,"Above peer range",IF(F19<H19,"Below peer range","Within peer range")))&IF(G19<3," (n<3: anecdotal)","")) | L19: Check definitions, periods and currency before comparing.
A20: Return on equity (NI / equity) | B20: =Benchmark_KPIs!R14 | C20: =Benchmark_KPIs!R15 | D20: =Benchmark_KPIs!R16 | E20: =Benchmark_KPIs!R17 | F20: =Benchmark_KPIs!R18 | G20: =COUNT(Benchmark_KPIs!$R$21:$R$28) | H20: =IF(G20=0,"",MIN(Benchmark_KPIs!$R$21:$R$28)) | I20: =IF(G20=0,"",MEDIAN(Benchmark_KPIs!$R$21:$R$28)) | J20: =IF(G20=0,"",MAX(Benchmark_KPIs!$R$21:$R$28)) | K20: =IF(G20=0,"No graded peer data yet",IF(NOT(ISNUMBER(F20)),"Model value n/a",IF(F20>J20,"Above peer range",IF(F20<H20,"Below peer range","Within peer range")))&IF(G20<3," (n<3: anecdotal)","")) | L20: Check definitions, periods and currency before comparing.
A21: ECL / gross receivables | B21: =Benchmark_KPIs!S14 | C21: =Benchmark_KPIs!S15 | D21: =Benchmark_KPIs!S16 | E21: =Benchmark_KPIs!S17 | F21: =Benchmark_KPIs!S18 | G21: =COUNT(Benchmark_KPIs!$S$21:$S$28) | H21: =IF(G21=0,"",MIN(Benchmark_KPIs!$S$21:$S$28)) | I21: =IF(G21=0,"",MEDIAN(Benchmark_KPIs!$S$21:$S$28)) | J21: =IF(G21=0,"",MAX(Benchmark_KPIs!$S$21:$S$28)) | K21: =IF(G21=0,"No graded peer data yet",IF(NOT(ISNUMBER(F21)),"Model value n/a",IF(F21>J21,"Above peer range",IF(F21<H21,"Below peer range","Within peer range")))&IF(G21<3," (n<3: anecdotal)","")) | L21: ECL policies, staging and write-off timing differ between companies.
A22: ECL / revenue | B22: =Benchmark_KPIs!T14 | C22: =Benchmark_KPIs!T15 | D22: =Benchmark_KPIs!T16 | E22: =Benchmark_KPIs!T17 | F22: =Benchmark_KPIs!T18 | G22: =COUNT(Benchmark_KPIs!$T$21:$T$28) | H22: =IF(G22=0,"",MIN(Benchmark_KPIs!$T$21:$T$28)) | I22: =IF(G22=0,"",MEDIAN(Benchmark_KPIs!$T$21:$T$28)) | J22: =IF(G22=0,"",MAX(Benchmark_KPIs!$T$21:$T$28)) | K22: =IF(G22=0,"No graded peer data yet",IF(NOT(ISNUMBER(F22)),"Model value n/a",IF(F22>J22,"Above peer range",IF(F22<H22,"Below peer range","Within peer range")))&IF(G22<3," (n<3: anecdotal)","")) | L22: ECL policies, staging and write-off timing differ between companies.
A23: ECL / financing revenue | B23: =Benchmark_KPIs!U14 | C23: =Benchmark_KPIs!U15 | D23: =Benchmark_KPIs!U16 | E23: =Benchmark_KPIs!U17 | F23: =Benchmark_KPIs!U18 | G23: =COUNT(Benchmark_KPIs!$U$21:$U$28) | H23: =IF(G23=0,"",MIN(Benchmark_KPIs!$U$21:$U$28)) | I23: =IF(G23=0,"",MEDIAN(Benchmark_KPIs!$U$21:$U$28)) | J23: =IF(G23=0,"",MAX(Benchmark_KPIs!$U$21:$U$28)) | K23: =IF(G23=0,"No graded peer data yet",IF(NOT(ISNUMBER(F23)),"Model value n/a",IF(F23>J23,"Above peer range",IF(F23<H23,"Below peer range","Within peer range")))&IF(G23<3," (n<3: anecdotal)","")) | L23: ECL policies, staging and write-off timing differ between companies.
A24: Revenue per active customer (USD) | B24: =Benchmark_KPIs!V14 | C24: =Benchmark_KPIs!V15 | D24: =Benchmark_KPIs!V16 | E24: =Benchmark_KPIs!V17 | F24: =Benchmark_KPIs!V18 | G24: =COUNT(Benchmark_KPIs!$V$21:$V$28) | H24: =IF(G24=0,"",MIN(Benchmark_KPIs!$V$21:$V$28)) | I24: =IF(G24=0,"",MEDIAN(Benchmark_KPIs!$V$21:$V$28)) | J24: =IF(G24=0,"",MAX(Benchmark_KPIs!$V$21:$V$28)) | K24: =IF(G24=0,"No graded peer data yet",IF(NOT(ISNUMBER(F24)),"Model value n/a",IF(F24>J24,"Above peer range",IF(F24<H24,"Below peer range","Within peer range")))&IF(G24<3," (n<3: anecdotal)","")) | L24: Active customer definitions differ (paying accounts, any product, any period).
A25: Net receivables per active customer (USD) | B25: =Benchmark_KPIs!W14 | C25: =Benchmark_KPIs!W15 | D25: =Benchmark_KPIs!W16 | E25: =Benchmark_KPIs!W17 | F25: =Benchmark_KPIs!W18 | G25: =COUNT(Benchmark_KPIs!$W$21:$W$28) | H25: =IF(G25=0,"",MIN(Benchmark_KPIs!$W$21:$W$28)) | I25: =IF(G25=0,"",MEDIAN(Benchmark_KPIs!$W$21:$W$28)) | J25: =IF(G25=0,"",MAX(Benchmark_KPIs!$W$21:$W$28)) | K25: =IF(G25=0,"No graded peer data yet",IF(NOT(ISNUMBER(F25)),"Model value n/a",IF(F25>J25,"Above peer range",IF(F25<H25,"Below peer range","Within peer range")))&IF(G25<3," (n<3: anecdotal)","")) | L25: Active customer definitions differ.
A26: Active / cumulative customers | B26: =Benchmark_KPIs!X14 | C26: =Benchmark_KPIs!X15 | D26: =Benchmark_KPIs!X16 | E26: =Benchmark_KPIs!X17 | F26: =Benchmark_KPIs!X18 | G26: =COUNT(Benchmark_KPIs!$X$21:$X$28) | H26: =IF(G26=0,"",MIN(Benchmark_KPIs!$X$21:$X$28)) | I26: =IF(G26=0,"",MEDIAN(Benchmark_KPIs!$X$21:$X$28)) | J26: =IF(G26=0,"",MAX(Benchmark_KPIs!$X$21:$X$28)) | K26: =IF(G26=0,"No graded peer data yet",IF(NOT(ISNUMBER(F26)),"Model value n/a",IF(F26>J26,"Above peer range",IF(F26<H26,"Below peer range","Within peer range")))&IF(G26<3," (n<3: anecdotal)","")) | L26: Cumulative customers and active customers are defined differently by each company.
A27: Operational collection rate (not PERFORM RR) | B27: =Benchmark_KPIs!Y14 | C27: =Benchmark_KPIs!Y15 | D27: =Benchmark_KPIs!Y16 | E27: =Benchmark_KPIs!Y17 | F27: =Benchmark_KPIs!Y18 | G27: =COUNT(Benchmark_KPIs!$Y$21:$Y$28) | H27: =IF(G27=0,"",MIN(Benchmark_KPIs!$Y$21:$Y$28)) | I27: =IF(G27=0,"",MEDIAN(Benchmark_KPIs!$Y$21:$Y$28)) | J27: =IF(G27=0,"",MAX(Benchmark_KPIs!$Y$21:$Y$28)) | K27: =IF(G27=0,"No graded peer data yet",IF(NOT(ISNUMBER(F27)),"Model value n/a",IF(F27>J27,"Above peer range",IF(F27<H27,"Below peer range","Within peer range")))&IF(G27<3," (n<3: anecdotal)","")) | L27: A company collection rate is not the model's operational collection rate unless deposits, period and denominator match; neither is the PERFORM Repayment Rate.
A28: Customer ownership rate | B28: =Benchmark_KPIs!Z14 | C28: =Benchmark_KPIs!Z15 | D28: =Benchmark_KPIs!Z16 | E28: =Benchmark_KPIs!Z17 | F28: =Benchmark_KPIs!Z18 | G28: =COUNT(Benchmark_KPIs!$Z$21:$Z$28) | H28: =IF(G28=0,"",MIN(Benchmark_KPIs!$Z$21:$Z$28)) | I28: =IF(G28=0,"",MEDIAN(Benchmark_KPIs!$Z$21:$Z$28)) | J28: =IF(G28=0,"",MAX(Benchmark_KPIs!$Z$21:$Z$28)) | K28: =IF(G28=0,"No graded peer data yet",IF(NOT(ISNUMBER(F28)),"Model value n/a",IF(F28>J28,"Above peer range",IF(F28<H28,"Below peer range","Within peer range")))&IF(G28<3," (n<3: anecdotal)","")) | L28: Ownership rate is comparable only on the PAYGo PERFORM 2026 definition (at 2x term).
A31: CAC payback is not disclosed by companies; see Unit_Economics for the model. Watu is an asset-finance comparable (motorcycles / smartphones), not a solar company. Unresolved conflicts (e.g. M-KOPA FY2024 revenue: USD 416m vs USD 253.5m) are excluded until primary filings are read: see Benchmark_DB.

Sheet Benchmark_KPIs
A1: Benchmark KPIs: derived ratios per company-year and for the model
A2: Blank = not computable from usable records. Ratios are diagnostics, not performance norms.
A5: Company | B5: Year | C5: Peer include | D5: Gross margin | E5: EBITDA margin | F5: Operating (EBIT) margin | G5: Net margin | H5: Revenue growth | I5: Financing revenue / revenue | J5: Receivables days | K5: Inventory days | L5: Payables days | M5: Cash conversion cycle (days) | N5: Debt / net receivables | O5: Debt / EBITDA | P5: Total liabilities / total assets | Q5: Equity (USD m; derived = assets: liabilities when not reported) | R5: Return on equity (NI / equity) | S5: ECL / gross receivables | T5: ECL / revenue | U5: ECL / financing revenue | V5: Revenue per active customer (USD) | W5: Net receivables per active customer (USD) | X5: Active / cumulative customers | Y5: Operational collection rate (not PERFORM RR) | Z5: Customer ownership rate
