Workbook

Sheet Guide
A1: AFRICA ENERGY FINANCE | VOLUME 2 | SOLAR HOME SYSTEMS
A2: Loan tape specification and data request
A3: How to use this template
A4: Template T06 | Version 1.0 | Author & ideation: Emmanuel Boujieka Kamga
A6: Purpose
A7: The account level data tape a lender, investor or rating analyst needs to rebuild a PAYGo portfolio, with field definitions, built in validation checks and the standard data request list.
A11: How to use it
A12: Step 1 | B12: Send the Schema and Data_Request sheets to the company at the start of diligence.
A13: Step 2 | B13: Paste the extract into the Tape sheet, one account per row, from row 7 (up to 1,000 rows; extend the formulas for larger books).
A14: Step 3 | B14: Read the Validation sheet: every check should read zero before the tape is used.
A15: Step 4 | B15: Track each data request on Data_Request until it is received and reviewed.
A16: Step 5 | B16: Aggregate the validated tape into monthly and cohort figures for Credit_Input and Vintage_Input in the model, or for Template T05.
A18: Colour code
A19: Input | B19: Blue font on cream: the only cells to edit
A20: Formula | B20: Black font: calculated, do not overwrite
A22: Links to the Volume 2 model and book
A23: Book | B23: Chapter 12 (data tape), Chapter 15 (data request list)
A24: Model | B24: Credit_Input and Vintage_Input are the aggregated form of this tape
A25: Related templates | B25: T02 due diligence checklist; T05 lender KPI report
A27: Decision support material; not investment, legal, tax or accounting advice. Example values are illustrative and refer to the fictional SolaraPay case where data are needed. (c) 2026 Emmanuel Boujieka Kamga.

Sheet Schema
A1: AFRICA ENERGY FINANCE | VOLUME 2 | SOLAR HOME SYSTEMS
A2: Tape field specification
A3: Field, type, definition, mandatory flag and validation rule
A4: Template T06 | Version 1.0 | Author & ideation: Emmanuel Boujieka Kamga
A6: No. | B6: Field | C6: Type | D6: Definition | E6: Mandatory | F6: Validation
A7: 1 | B7: account_id | C7: Text | D7: Unique account identifier | E7: Yes | F7: Unique; not blank
A8: 2 | B8: report_date | C8: Date | D8: Month end date of the extract | E8: Yes | F8: Same for all rows
A9: 3 | B9: tier | C9: Integer | D9: Product tier 1 to 5 as labelled in the model | E9: Yes | F9: 1 to 5
A10: 4 | B10: product_name | C10: Text | D10: Commercial product name | E10: Yes
A11: 5 | B11: origination_date | C11: Date | D11: Date of activation after deposit | E11: Yes | F11: Not after report date
A12: 6 | B12: region | C12: Text | D12: Sales region | E12: Yes
A13: 7 | B13: agent_id | C13: Text | D13: Originating agent | E13: Yes | F13: Links to agent register (T04)
A14: 8 | B14: channel | C14: List | D14: Direct agent, retail partner, other | E14: Yes | F14: From list
A15: 9 | B15: cash_price | C15: Number | D15: Cash selling price, local currency | E15: Yes | F15: Greater than zero
A16: 10 | B16: deposit | C16: Number | D16: Deposit paid at activation | E16: Yes | F16: Not above cash price
A17: 11 | B17: daily_rate | C17: Number | D17: Price of one day of service | E17: Yes | F17: Greater than zero
A18: 12 | B18: tenor_months | C18: Integer | D18: Contractual tenor in months | E18: Yes | F18: Greater than zero
A19: 13 | B19: scheduled_instalments | C19: Number | D19: Daily rate × 365 ÷ 12 × tenor (calculated) | E19: Calc
A20: 14 | B20: cumulative_paid_excl_deposit | C20: Number | D20: Instalments paid to date, deposit excluded | E20: Yes | F20: Not above scheduled instalments
A21: 15 | B21: instalments_due_to_date | C21: Number | D21: Instalments fallen due to date, deposit excluded | E21: Yes
A22: 16 | B22: days_past_due | C22: Integer | D22: Schedule shortfall expressed in days of the daily rate | E22: Yes | F22: Zero or more
A23: 17 | B23: days_without_credit | C23: Integer | D23: Consecutive days the device has been locked | E23: No | F23: Zero or more
A24: 18 | B24: status | C24: List | D24: Active, Paid off, Defaulted, Repossessed, Written off, Restructured | E24: Yes | F24: From list
A25: 19 | B25: restructure_date | C25: Date | D25: Date of the last restructuring, if any | E25: No
A26: 20 | B26: write_off_amount | C26: Number | D26: Amount written off | E26: No
A27: 21 | B27: write_off_date | C27: Date | D27: Date of write off | E27: No
A28: 22 | B28: repossession_date | C28: Date | D28: Date the device was recovered | E28: No
A29: 23 | B29: resale_proceeds | C29: Number | D29: Gross proceeds from resale of the recovered device | E29: No
A30: 24 | B30: recovery_cost | C30: Number | D30: Cost of recovery, refurbishment and resale | E30: No
A31: 25 | B31: unlock_date | C31: Date | D31: Date of permanent unlock | E31: No
A32: 26 | B32: unlock_type | C32: List | D32: Full payment, Settlement, Warranty swap, Goodwill, Other | E32: No | F32: Full payment requires paid = scheduled
A33: 27 | B33: customer_verified | C33: List | D33: Yes or No: verification call or visit completed | E33: Yes | F33: From list

Sheet Tape
A1: AFRICA ENERGY FINANCE | VOLUME 2 | SOLAR HOME SYSTEMS
A2: Loan tape
A3: One row per account; three illustrative rows to be replaced
A4: Template T06 | Version 1.0 | Author & ideation: Emmanuel Boujieka Kamga
A6: account_id | B6: report_date | C6: tier | D6: product_name | E6: origination_date | F6: region | G6: agent_id | H6: channel | I6: cash_price | J6: deposit | K6: daily_rate | L6: tenor_months | M6: scheduled_instalments | N6: cumulative_paid_excl_deposit | O6: instalments_due_to_date | P6: days_past_due | Q6: days_without_credit | R6: status | S6: restructure_date | T6: write_off_amount | U6: write_off_date | V6: repossession_date | W6: resale_proceeds | X6: recovery_cost | Y6: unlock_date | Z6: unlock_type | AA6: customer_verified | AB6: chk_present | AC6: chk_missing | AD6: chk_tier | AE6: chk_status | AF6: chk_deposit | AG6: chk_paid | AH6: chk_origination | AI6: chk_unlock | AJ6: chk_dpd | AK6: chk_duplicate
A7: SP000001 | B7: 46022 | C7: 2 | D7: SHS with TV | E7: 45549 | F7: North | G7: AG007 | H7: Direct agent | I7: 39000 | J7: 4000 | K7: 77 | L7: 24 | M7: =IF(K7="","",K7*365/12*L7) | N7: 29500 | O7: 35130 | P7: 73 | Q7: 12 | R7: Active | AA7: Yes | AB7: =IF(LEN(A7)>0,1,0) | AC7: =IF(LEN(A7)=0,0,(LEN(B7)=0)+(LEN(C7)=0)+(LEN(D7)=0)+(LEN(E7)=0)+(LEN(F7)=0)+(LEN(G7)=0)+(LEN(H7)=0)+(LEN(I7)=0)+(LEN(J7)=0)+(LEN(K7)=0)+(LEN(L7)=0)+(LEN(N7)=0)+(LEN(O7)=0)+(LEN(P7)=0)+(LEN(R7)=0)+(LEN(AA7)=0)) | AD7: =IF(OR(LEN(A7)=0,LEN(C7)=0),0,IF(OR(C7<1,C7>5),1,0)) | AE7: =IF(OR(LEN(A7)=0,LEN(R7)=0),0,IF(OR(R7="Active",R7="Paid off",R7="Defaulted",R7="Repossessed",R7="Written off",R7="Restructured"),0,1)) | AF7: =IF(A7="",0,IF(N(J7)>N(I7),1,0)) | AG7: =IF(A7="",0,IF(N(N7)>N(M7)+1,1,0)) | AH7: =IF(A7="",0,IF(N(E7)>N(B7),1,0)) | AI7: =IF(A7="",0,IF(AND(Z7="Full payment",N(N7)<N(M7)-1),1,0)) | AJ7: =IF(A7="",0,IF(N(P7)<0,1,0)) | AK7: =IF(A7="",0,IF(COUNTIF($A$7:$A$1006,A7)>1,1,0))
A8: SP000002 | B8: 46022 | C8: 1 | D8: Pico solar kit | E8: 45325 | F8: South | G8: AG012 | H8: Retail partner | I8: 6500 | J8: 1000 | K8: 25 | L8: 12 | M8: =IF(K8="","",K8*365/12*L8) | N8: 9125 | O8: 9125 | P8: 0 | Q8: 0 | R8: Paid off | Y8: 45698 | Z8: Full payment | AA8: Yes | AB8: =IF(LEN(A8)>0,1,0) | AC8: =IF(LEN(A8)=0,0,(LEN(B8)=0)+(LEN(C8)=0)+(LEN(D8)=0)+(LEN(E8)=0)+(LEN(F8)=0)+(LEN(G8)=0)+(LEN(H8)=0)+(LEN(I8)=0)+(LEN(J8)=0)+(LEN(K8)=0)+(LEN(L8)=0)+(LEN(N8)=0)+(LEN(O8)=0)+(LEN(P8)=0)+(LEN(R8)=0)+(LEN(AA8)=0)) | AD8: =IF(OR(LEN(A8)=0,LEN(C8)=0),0,IF(OR(C8<1,C8>5),1,0)) | AE8: =IF(OR(LEN(A8)=0,LEN(R8)=0),0,IF(OR(R8="Active",R8="Paid off",R8="Defaulted",R8="Repossessed",R8="Written off",R8="Restructured"),0,1)) | AF8: =IF(A8="",0,IF(N(J8)>N(I8),1,0)) | AG8: =IF(A8="",0,IF(N(N8)>N(M8)+1,1,0)) | AH8: =IF(A8="",0,IF(N(E8)>N(B8),1,0)) | AI8: =IF(A8="",0,IF(AND(Z8="Full payment",N(N8)<N(M8)-1),1,0)) | AJ8: =IF(A8="",0,IF(N(P8)<0,1,0)) | AK8: =IF(A8="",0,IF(COUNTIF($A$7:$A$1006,A8)>1,1,0))
A9: SP000003 | B9: 46022 | C9: 3 | D9: Large SHS with DC fridge | E9: 45432 | F9: East | G9: AG021 | H9: Direct agent | I9: 117000 | J9: 17550 | K9: 173 | L9: 30 | M9: =IF(K9="","",K9*365/12*L9) | N9: 21000 | O9: 99980 | P9: 456 | Q9: 380 | R9: Written off | T9: 136862 | U9: 45838 | V9: 45871 | W9: 18000 | X9: 2700 | AA9: Yes | AB9: =IF(LEN(A9)>0,1,0) | AC9: =IF(LEN(A9)=0,0,(LEN(B9)=0)+(LEN(C9)=0)+(LEN(D9)=0)+(LEN(E9)=0)+(LEN(F9)=0)+(LEN(G9)=0)+(LEN(H9)=0)+(LEN(I9)=0)+(LEN(J9)=0)+(LEN(K9)=0)+(LEN(L9)=0)+(LEN(N9)=0)+(LEN(O9)=0)+(LEN(P9)=0)+(LEN(R9)=0)+(LEN(AA9)=0)) | AD9: =IF(OR(LEN(A9)=0,LEN(C9)=0),0,IF(OR(C9<1,C9>5),1,0)) | AE9: =IF(OR(LEN(A9)=0,LEN(R9)=0),0,IF(OR(R9="Active",R9="Paid off",R9="Defaulted",R9="Repossessed",R9="Written off",R9="Restructured"),0,1)) | AF9: =IF(A9="",0,IF(N(J9)>N(I9),1,0)) | AG9: =IF(A9="",0,IF(N(N9)>N(M9)+1,1,0)) | AH9: =IF(A9="",0,IF(N(E9)>N(B9),1,0)) | AI9: =IF(A9="",0,IF(AND(Z9="Full payment",N(N9)<N(M9)-1),1,0)) | AJ9: =IF(A9="",0,IF(N(P9)<0,1,0)) | AK9: =IF(A9="",0,IF(COUNTIF($A$7:$A$1006,A9)>1,1,0))
M10: =IF(K10="","",K10*365/12*L10) | AB10: =IF(LEN(A10)>0,1,0) | AC10: =IF(LEN(A10)=0,0,(LEN(B10)=0)+(LEN(C10)=0)+(LEN(D10)=0)+(LEN(E10)=0)+(LEN(F10)=0)+(LEN(G10)=0)+(LEN(H10)=0)+(LEN(I10)=0)+(LEN(J10)=0)+(LEN(K10)=0)+(LEN(L10)=0)+(LEN(N10)=0)+(LEN(O10)=0)+(LEN(P10)=0)+(LEN(R10)=0)+(LEN(AA10)=0)) | AD10: =IF(OR(LEN(A10)=0,LEN(C10)=0),0,IF(OR(C10<1,C10>5),1,0)) | AE10: =IF(OR(LEN(A10)=0,LEN(R10)=0),0,IF(OR(R10="Active",R10="Paid off",R10="Defaulted",R10="Repossessed",R10="Written off",R10="Restructured"),0,1)) | AF10: =IF(A10="",0,IF(N(J10)>N(I10),1,0)) | AG10: =IF(A10="",0,IF(N(N10)>N(M10)+1,1,0)) | AH10: =IF(A10="",0,IF(N(E10)>N(B10),1,0)) | AI10: =IF(A10="",0,IF(AND(Z10="Full payment",N(N10)<N(M10)-1),1,0)) | AJ10: =IF(A10="",0,IF(N(P10)<0,1,0)) | AK10: =IF(A10="",0,IF(COUNTIF($A$7:$A$1006,A10)>1,1,0))
M11: =IF(K11="","",K11*365/12*L11) | AB11: =IF(LEN(A11)>0,1,0) | AC11: =IF(LEN(A11)=0,0,(LEN(B11)=0)+(LEN(C11)=0)+(LEN(D11)=0)+(LEN(E11)=0)+(LEN(F11)=0)+(LEN(G11)=0)+(LEN(H11)=0)+(LEN(I11)=0)+(LEN(J11)=0)+(LEN(K11)=0)+(LEN(L11)=0)+(LEN(N11)=0)+(LEN(O11)=0)+(LEN(P11)=0)+(LEN(R11)=0)+(LEN(AA11)=0)) | AD11: =IF(OR(LEN(A11)=0,LEN(C11)=0),0,IF(OR(C11<1,C11>5),1,0)) | AE11: =IF(OR(LEN(A11)=0,LEN(R11)=0),0,IF(OR(R11="Active",R11="Paid off",R11="Defaulted",R11="Repossessed",R11="Written off",R11="Restructured"),0,1)) | AF11: =IF(A11="",0,IF(N(J11)>N(I11),1,0)) | AG11: =IF(A11="",0,IF(N(N11)>N(M11)+1,1,0)) | AH11: =IF(A11="",0,IF(N(E11)>N(B11),1,0)) | AI11: =IF(A11="",0,IF(AND(Z11="Full payment",N(N11)<N(M11)-1),1,0)) | AJ11: =IF(A11="",0,IF(N(P11)<0,1,0)) | AK11: =IF(A11="",0,IF(COUNTIF($A$7:$A$1006,A11)>1,1,0))
M12: =IF(K12="","",K12*365/12*L12) | AB12: =IF(LEN(A12)>0,1,0) | AC12: =IF(LEN(A12)=0,0,(LEN(B12)=0)+(LEN(C12)=0)+(LEN(D12)=0)+(LEN(E12)=0)+(LEN(F12)=0)+(LEN(G12)=0)+(LEN(H12)=0)+(LEN(I12)=0)+(LEN(J12)=0)+(LEN(K12)=0)+(LEN(L12)=0)+(LEN(N12)=0)+(LEN(O12)=0)+(LEN(P12)=0)+(LEN(R12)=0)+(LEN(AA12)=0)) | AD12: =IF(OR(LEN(A12)=0,LEN(C12)=0),0,IF(OR(C12<1,C12>5),1,0)) | AE12: =IF(OR(LEN(A12)=0,LEN(R12)=0),0,IF(OR(R12="Active",R12="Paid off",R12="Defaulted",R12="Repossessed",R12="Written off",R12="Restructured"),0,1)) | AF12: =IF(A12="",0,IF(N(J12)>N(I12),1,0)) | AG12: =IF(A12="",0,IF(N(N12)>N(M12)+1,1,0)) | AH12: =IF(A12="",0,IF(N(E12)>N(B12),1,0)) | AI12: =IF(A12="",0,IF(AND(Z12="Full payment",N(N12)<N(M12)-1),1,0)) | AJ12: =IF(A12="",0,IF(N(P12)<0,1,0)) | AK12: =IF(A12="",0,IF(COUNTIF($A$7:$A$1006,A12)>1,1,0))
M13: =IF(K13="","",K13*365/12*L13) | AB13: =IF(LEN(A13)>0,1,0) | AC13: =IF(LEN(A13)=0,0,(LEN(B13)=0)+(LEN(C13)=0)+(LEN(D13)=0)+(LEN(E13)=0)+(LEN(F13)=0)+(LEN(G13)=0)+(LEN(H13)=0)+(LEN(I13)=0)+(LEN(J13)=0)+(LEN(K13)=0)+(LEN(L13)=0)+(LEN(N13)=0)+(LEN(O13)=0)+(LEN(P13)=0)+(LEN(R13)=0)+(LEN(AA13)=0)) | AD13: =IF(OR(LEN(A13)=0,LEN(C13)=0),0,IF(OR(C13<1,C13>5),1,0)) | AE13: =IF(OR(LEN(A13)=0,LEN(R13)=0),0,IF(OR(R13="Active",R13="Paid off",R13="Defaulted",R13="Repossessed",R13="Written off",R13="Restructured"),0,1)) | AF13: =IF(A13="",0,IF(N(J13)>N(I13),1,0)) | AG13: =IF(A13="",0,IF(N(N13)>N(M13)+1,1,0)) | AH13: =IF(A13="",0,IF(N(E13)>N(B13),1,0)) | AI13: =IF(A13="",0,IF(AND(Z13="Full payment",N(N13)<N(M13)-1),1,0)) | AJ13: =IF(A13="",0,IF(N(P13)<0,1,0)) | AK13: =IF(A13="",0,IF(COUNTIF($A$7:$A$1006,A13)>1,1,0))
M14: =IF(K14="","",K14*365/12*L14) | AB14: =IF(LEN(A14)>0,1,0) | AC14: =IF(LEN(A14)=0,0,(LEN(B14)=0)+(LEN(C14)=0)+(LEN(D14)=0)+(LEN(E14)=0)+(LEN(F14)=0)+(LEN(G14)=0)+(LEN(H14)=0)+(LEN(I14)=0)+(LEN(J14)=0)+(LEN(K14)=0)+(LEN(L14)=0)+(LEN(N14)=0)+(LEN(O14)=0)+(LEN(P14)=0)+(LEN(R14)=0)+(LEN(AA14)=0)) | AD14: =IF(OR(LEN(A14)=0,LEN(C14)=0),0,IF(OR(C14<1,C14>5),1,0)) | AE14: =IF(OR(LEN(A14)=0,LEN(R14)=0),0,IF(OR(R14="Active",R14="Paid off",R14="Defaulted",R14="Repossessed",R14="Written off",R14="Restructured"),0,1)) | AF14: =IF(A14="",0,IF(N(J14)>N(I14),1,0)) | AG14: =IF(A14="",0,IF(N(N14)>N(M14)+1,1,0)) | AH14: =IF(A14="",0,IF(N(E14)>N(B14),1,0)) | AI14: =IF(A14="",0,IF(AND(Z14="Full payment",N(N14)<N(M14)-1),1,0)) | AJ14: =IF(A14="",0,IF(N(P14)<0,1,0)) | AK14: =IF(A14="",0,IF(COUNTIF($A$7:$A$1006,A14)>1,1,0))
M15: =IF(K15="","",K15*365/12*L15) | AB15: =IF(LEN(A15)>0,1,0) | AC15: =IF(LEN(A15)=0,0,(LEN(B15)=0)+(LEN(C15)=0)+(LEN(D15)=0)+(LEN(E15)=0)+(LEN(F15)=0)+(LEN(G15)=0)+(LEN(H15)=0)+(LEN(I15)=0)+(LEN(J15)=0)+(LEN(K15)=0)+(LEN(L15)=0)+(LEN(N15)=0)+(LEN(O15)=0)+(LEN(P15)=0)+(LEN(R15)=0)+(LEN(AA15)=0)) | AD15: =IF(OR(LEN(A15)=0,LEN(C15)=0),0,IF(OR(C15<1,C15>5),1,0)) | AE15: =IF(OR(LEN(A15)=0,LEN(R15)=0),0,IF(OR(R15="Active",R15="Paid off",R15="Defaulted",R15="Repossessed",R15="Written off",R15="Restructured"),0,1)) | AF15: =IF(A15="",0,IF(N(J15)>N(I15),1,0)) | AG15: =IF(A15="",0,IF(N(N15)>N(M15)+1,1,0)) | AH15: =IF(A15="",0,IF(N(E15)>N(B15),1,0)) | AI15: =IF(A15="",0,IF(AND(Z15="Full payment",N(N15)<N(M15)-1),1,0)) | AJ15: =IF(A15="",0,IF(N(P15)<0,1,0)) | AK15: =IF(A15="",0,IF(COUNTIF($A$7:$A$1006,A15)>1,1,0))
M16: =IF(K16="","",K16*365/12*L16) | AB16: =IF(LEN(A16)>0,1,0) | AC16: =IF(LEN(A16)=0,0,(LEN(B16)=0)+(LEN(C16)=0)+(LEN(D16)=0)+(LEN(E16)=0)+(LEN(F16)=0)+(LEN(G16)=0)+(LEN(H16)=0)+(LEN(I16)=0)+(LEN(J16)=0)+(LEN(K16)=0)+(LEN(L16)=0)+(LEN(N16)=0)+(LEN(O16)=0)+(LEN(P16)=0)+(LEN(R16)=0)+(LEN(AA16)=0)) | AD16: =IF(OR(LEN(A16)=0,LEN(C16)=0),0,IF(OR(C16<1,C16>5),1,0)) | AE16: =IF(OR(LEN(A16)=0,LEN(R16)=0),0,IF(OR(R16="Active",R16="Paid off",R16="Defaulted",R16="Repossessed",R16="Written off",R16="Restructured"),0,1)) | AF16: =IF(A16="",0,IF(N(J16)>N(I16),1,0)) | AG16: =IF(A16="",0,IF(N(N16)>N(M16)+1,1,0)) | AH16: =IF(A16="",0,IF(N(E16)>N(B16),1,0)) | AI16: =IF(A16="",0,IF(AND(Z16="Full payment",N(N16)<N(M16)-1),1,0)) | AJ16: =IF(A16="",0,IF(N(P16)<0,1,0)) | AK16: =IF(A16="",0,IF(COUNTIF($A$7:$A$1006,A16)>1,1,0))
M17: =IF(K17="","",K17*365/12*L17) | AB17: =IF(LEN(A17)>0,1,0) | AC17: =IF(LEN(A17)=0,0,(LEN(B17)=0)+(LEN(C17)=0)+(LEN(D17)=0)+(LEN(E17)=0)+(LEN(F17)=0)+(LEN(G17)=0)+(LEN(H17)=0)+(LEN(I17)=0)+(LEN(J17)=0)+(LEN(K17)=0)+(LEN(L17)=0)+(LEN(N17)=0)+(LEN(O17)=0)+(LEN(P17)=0)+(LEN(R17)=0)+(LEN(AA17)=0)) | AD17: =IF(OR(LEN(A17)=0,LEN(C17)=0),0,IF(OR(C17<1,C17>5),1,0)) | AE17: =IF(OR(LEN(A17)=0,LEN(R17)=0),0,IF(OR(R17="Active",R17="Paid off",R17="Defaulted",R17="Repossessed",R17="Written off",R17="Restructured"),0,1)) | AF17: =IF(A17="",0,IF(N(J17)>N(I17),1,0)) | AG17: =IF(A17="",0,IF(N(N17)>N(M17)+1,1,0)) | AH17: =IF(A17="",0,IF(N(E17)>N(B17),1,0)) | AI17: =IF(A17="",0,IF(AND(Z17="Full payment",N(N17)<N(M17)-1),1,0)) | AJ17: =IF(A17="",0,IF(N(P17)<0,1,0)) | AK17: =IF(A17="",0,IF(COUNTIF($A$7:$A$1006,A17)>1,1,0))
M18: =IF(K18="","",K18*365/12*L18) | AB18: =IF(LEN(A18)>0,1,0) | AC18: =IF(LEN(A18)=0,0,(LEN(B18)=0)+(LEN(C18)=0)+(LEN(D18)=0)+(LEN(E18)=0)+(LEN(F18)=0)+(LEN(G18)=0)+(LEN(H18)=0)+(LEN(I18)=0)+(LEN(J18)=0)+(LEN(K18)=0)+(LEN(L18)=0)+(LEN(N18)=0)+(LEN(O18)=0)+(LEN(P18)=0)+(LEN(R18)=0)+(LEN(AA18)=0)) | AD18: =IF(OR(LEN(A18)=0,LEN(C18)=0),0,IF(OR(C18<1,C18>5),1,0)) | AE18: =IF(OR(LEN(A18)=0,LEN(R18)=0),0,IF(OR(R18="Active",R18="Paid off",R18="Defaulted",R18="Repossessed",R18="Written off",R18="Restructured"),0,1)) | AF18: =IF(A18="",0,IF(N(J18)>N(I18),1,0)) | AG18: =IF(A18="",0,IF(N(N18)>N(M18)+1,1,0)) | AH18: =IF(A18="",0,IF(N(E18)>N(B18),1,0)) | AI18: =IF(A18="",0,IF(AND(Z18="Full payment",N(N18)<N(M18)-1),1,0)) | AJ18: =IF(A18="",0,IF(N(P18)<0,1,0)) | AK18: =IF(A18="",0,IF(COUNTIF($A$7:$A$1006,A18)>1,1,0))
M19: =IF(K19="","",K19*365/12*L19) | AB19: =IF(LEN(A19)>0,1,0) | AC19: =IF(LEN(A19)=0,0,(LEN(B19)=0)+(LEN(C19)=0)+(LEN(D19)=0)+(LEN(E19)=0)+(LEN(F19)=0)+(LEN(G19)=0)+(LEN(H19)=0)+(LEN(I19)=0)+(LEN(J19)=0)+(LEN(K19)=0)+(LEN(L19)=0)+(LEN(N19)=0)+(LEN(O19)=0)+(LEN(P19)=0)+(LEN(R19)=0)+(LEN(AA19)=0)) | AD19: =IF(OR(LEN(A19)=0,LEN(C19)=0),0,IF(OR(C19<1,C19>5),1,0)) | AE19: =IF(OR(LEN(A19)=0,LEN(R19)=0),0,IF(OR(R19="Active",R19="Paid off",R19="Defaulted",R19="Repossessed",R19="Written off",R19="Restructured"),0,1)) | AF19: =IF(A19="",0,IF(N(J19)>N(I19),1,0)) | AG19: =IF(A19="",0,IF(N(N19)>N(M19)+1,1,0)) | AH19: =IF(A19="",0,IF(N(E19)>N(B19),1,0)) | AI19: =IF(A19="",0,IF(AND(Z19="Full payment",N(N19)<N(M19)-1),1,0)) | AJ19: =IF(A19="",0,IF(N(P19)<0,1,0)) | AK19: =IF(A19="",0,IF(COUNTIF($A$7:$A$1006,A19)>1,1,0))
M20: =IF(K20="","",K20*365/12*L20) | AB20: =IF(LEN(A20)>0,1,0) | AC20: =IF(LEN(A20)=0,0,(LEN(B20)=0)+(LEN(C20)=0)+(LEN(D20)=0)+(LEN(E20)=0)+(LEN(F20)=0)+(LEN(G20)=0)+(LEN(H20)=0)+(LEN(I20)=0)+(LEN(J20)=0)+(LEN(K20)=0)+(LEN(L20)=0)+(LEN(N20)=0)+(LEN(O20)=0)+(LEN(P20)=0)+(LEN(R20)=0)+(LEN(AA20)=0)) | AD20: =IF(OR(LEN(A20)=0,LEN(C20)=0),0,IF(OR(C20<1,C20>5),1,0)) | AE20: =IF(OR(LEN(A20)=0,LEN(R20)=0),0,IF(OR(R20="Active",R20="Paid off",R20="Defaulted",R20="Repossessed",R20="Written off",R20="Restructured"),0,1)) | AF20: =IF(A20="",0,IF(N(J20)>N(I20),1,0)) | AG20: =IF(A20="",0,IF(N(N20)>N(M20)+1,1,0)) | AH20: =IF(A20="",0,IF(N(E20)>N(B20),1,0)) | AI20: =IF(A20="",0,IF(AND(Z20="Full payment",N(N20)<N(M20)-1),1,0)) | AJ20: =IF(A20="",0,IF(N(P20)<0,1,0)) | AK20: =IF(A20="",0,IF(COUNTIF($A$7:$A$1006,A20)>1,1,0))
M21: =IF(K21="","",K21*365/12*L21) | AB21: =IF(LEN(A21)>0,1,0) | AC21: =IF(LEN(A21)=0,0,(LEN(B21)=0)+(LEN(C21)=0)+(LEN(D21)=0)+(LEN(E21)=0)+(LEN(F21)=0)+(LEN(G21)=0)+(LEN(H21)=0)+(LEN(I21)=0)+(LEN(J21)=0)+(LEN(K21)=0)+(LEN(L21)=0)+(LEN(N21)=0)+(LEN(O21)=0)+(LEN(P21)=0)+(LEN(R21)=0)+(LEN(AA21)=0)) | AD21: =IF(OR(LEN(A21)=0,LEN(C21)=0),0,IF(OR(C21<1,C21>5),1,0)) | AE21: =IF(OR(LEN(A21)=0,LEN(R21)=0),0,IF(OR(R21="Active",R21="Paid off",R21="Defaulted",R21="Repossessed",R21="Written off",R21="Restructured"),0,1)) | AF21: =IF(A21="",0,IF(N(J21)>N(I21),1,0)) | AG21: =IF(A21="",0,IF(N(N21)>N(M21)+1,1,0)) | AH21: =IF(A21="",0,IF(N(E21)>N(B21),1,0)) | AI21: =IF(A21="",0,IF(AND(Z21="Full payment",N(N21)<N(M21)-1),1,0)) | AJ21: =IF(A21="",0,IF(N(P21)<0,1,0)) | AK21: =IF(A21="",0,IF(COUNTIF($A$7:$A$1006,A21)>1,1,0))
... M1006: =IF(K1006="","",K1006*365/12*L1006) | AB1006: =IF(LEN(A1006)>0,1,0) | AC1006: =IF(LEN(A1006)=0,0,(LEN(B1006)=0)+(LEN(C1006)=0)+(LEN(D1006)=0)+(LEN(E1006)=0)+(LEN(F1006)=0)+(LEN(G1006)=0)+(LEN(H1006)=0)+(LEN(I1006)=0)+(LEN(J1006)=0)+(LEN(K1006)=0)+(LEN(L1006)=0)+(LEN(N1006)=0)+(LEN(O1006)=0)+(LEN(P1006)=0)+(LEN(R1006)=0)+(LEN(AA1006)=0)) | AD1006: =IF(OR(LEN(A1006)=0,LEN(C1006)=0),0,IF(OR(C1006<1,C1006>5),1,0)) | AE1006: =IF(OR(LEN(A1006)=0,LEN(R1006)=0),0,IF(OR(R1006="Active",R1006="Paid off",R1006="Defaulted",R1006="Repossessed",R1006="Written off",R1006="Restructured"),0,1)) | AF1006: =IF(A1006="",0,IF(N(J1006)>N(I1006),1,0)) | AG1006: =IF(A1006="",0,IF(N(N1006)>N(M1006)+1,1,0)) | AH1006: =IF(A1006="",0,IF(N(E1006)>N(B1006),1,0)) | AI1006: =IF(A1006="",0,IF(AND(Z1006="Full payment",N(N1006)<N(M1006)-1),1,0)) | AJ1006: =IF(A1006="",0,IF(N(P1006)<0,1,0)) | AK1006: =IF(A1006="",0,IF(COUNTIF($A$7:$A$1006,A1006)>1,1,0))

Sheet Validation
A1: AFRICA ENERGY FINANCE | VOLUME 2 | SOLAR HOME SYSTEMS
A2: Tape validation
A3: Every check should read zero before the tape is used
A4: Template T06 | Version 1.0 | Author & ideation: Emmanuel Boujieka Kamga
A6: Check | B6: Exceptions | C6: Status | D6: Notes
A7: Accounts in tape | B7: =SUM(Tape!$AB$7:$AB$1006)
A8: Rows with a missing mandatory field | B8: =COUNTIF(Tape!$AC$7:$AC$1006,">0") | C8: =IF(B8=0,"OK","Fix")
A9: Missing mandatory values in total | B9: =SUM(Tape!$AC$7:$AC$1006) | C9: =IF(B9=0,"OK","Fix")
A10: Tier outside 1 to 5 | B10: =SUM(Tape!$AD$7:$AD$1006) | C10: =IF(B10=0,"OK","Fix")
A11: Status not in the list | B11: =SUM(Tape!$AE$7:$AE$1006) | C11: =IF(B11=0,"OK","Fix")
A12: Deposit above cash price | B12: =SUM(Tape!$AF$7:$AF$1006) | C12: =IF(B12=0,"OK","Fix")
A13: Paid above scheduled instalments | B13: =SUM(Tape!$AG$7:$AG$1006) | C13: =IF(B13=0,"OK","Fix")
A14: Origination after report date | B14: =SUM(Tape!$AH$7:$AH$1006) | C14: =IF(B14=0,"OK","Fix")
A15: Full payment unlock without full payment | B15: =SUM(Tape!$AI$7:$AI$1006) | C15: =IF(B15=0,"OK","Fix")
A16: Negative days past due | B16: =SUM(Tape!$AJ$7:$AJ$1006) | C16: =IF(B16=0,"OK","Fix")
A17: Duplicate account identifiers (rows) | B17: =SUM(Tape!$AK$7:$AK$1006) | C17: =IF(B17=0,"OK","Fix")
A19: Tape ready for use | B19: =IF(COUNTIF(C8:C17,"Fix")=0,"Yes","No")
A21: Each check is computed per account in the chk columns at the right of the Tape sheet; filter a chk column on 1 to find the rows to fix. The mandatory fields are listed on Schema.

Sheet Data_Request
A1: AFRICA ENERGY FINANCE | VOLUME 2 | SOLAR HOME SYSTEMS
A2: Data request list
A3: Issue at the start of diligence
A4: Template T06 | Version 1.0 | Author & ideation: Emmanuel Boujieka Kamga
A6: Ref | B6: Item | C6: Format | D6: Period | E6: Owner | F6: Requested | G6: Received | H6: Status | I6: Comments
A7: DR01 | B7: Account level loan tape (structure on the Tape sheet) | C7: Excel or CSV | D7: Since launch | H7: Not requested
A8: DR02 | B8: Monthly portfolio data by tier: gross receivables, DPD buckets, default exposure, originations, instalments due, collections, write offs, repossessions, resale proceeds and costs, cures, unlocks | C8: Credit_Input structure | D8: 24 months minimum | H8: Not requested
A9: DR03 | B9: Cohort observations by tier at fixed ages | C9: Vintage_Input structure | D9: All cohorts | H9: Not requested
A10: DR04 | B10: Reconciliation of DPD buckets and gross receivables to the general ledger | C10: Excel | D10: Each month end | H10: Not requested
A11: DR05 | B11: Credit, write off, restructuring and repossession policies, with the dates each version applied | C11: PDF | D11: Current and past versions | H11: Not requested
A12: DR06 | B12: Price plan history by tier, including deposits, daily rates, tenors and promotions | C12: Excel | D12: Since launch | H12: Not requested
A13: DR07 | B13: Agent register, commission schedules, clawback rules and sales by agent | C13: Excel | D13: 24 months | H13: Not requested
A14: DR08 | B14: Unlock logs separated between full payment unlocks and other unlocks | C14: Excel | D14: Since launch | H14: Not requested
A15: DR09 | B15: Audited accounts, monthly management accounts and current budget | C15: PDF and Excel | D15: 3 years | H15: Not requested
A16: DR10 | B16: Financing agreements, compliance certificates, waivers and amendments | C16: PDF | D16: All current | H16: Not requested
A17: DR11 | B17: RBF and grant agreements, verification reports and clawback provisions | C17: PDF | D17: All current | H17: Not requested
A18: DR12 | B18: Customer complaint logs and regulatory correspondence | C18: Excel and PDF | D18: 24 months | H18: Not requested
A19: DR13 | B19: Hardware supply contracts, warranty terms and FX exposure by currency | C19: PDF and Excel | D19: Current | H19: Not requested
