Workbook

Sheet Guide
A1: AFRICA ENERGY FINANCE | BOOK 2 | PAYGO SOLAR FINANCE
A2: Agent economics and fully loaded CAC
A3: How to use this template
A4: Template T04 | Version 0.9 (pre-release) | Author & ideation: Emmanuel Boujieka Kamga
A6: Purpose
A7: Builds the customer acquisition cost of a territory on two definitions, narrow (commission and marketing) and fully loaded (adding the field organisation and fraud controls), ranks agents by the quality of the cohorts they originate, and shows the cost of opening a new territory.
A11: How to use it
A12: Step 1 | B12: Enter the territory inputs on the Inputs sheet (blue cells). Example values are illustrative.
A13: Step 2 | B13: Read the narrow and fully loaded CAC by tier on the CAC sheet, and the ratio between the two.
A14: Step 3 | B14: Paste agent level data into Agent_Ranking: units sold, share current at month 3, repayment at month 6, deposit only accounts.
A15: Step 4 | B15: Use the flags to set commission bands and to decide which agents to retrain or remove.
A16: Step 5 | B16: Use New_Territory to set a budget and stop criteria before opening a new area.
A17: Step 6 | B17: Copy the fully loaded CAC per tier into the commission and marketing lines of the model (Products) if you want the unit view to carry field costs, and remove the same costs from fixed costs on Inputs.
A19: Colour code
A20: Input | B20: Blue font on cream: the only cells to edit
A21: Formula | B21: Black font: calculated, do not overwrite
A23: Links to Book 2 and MODEL 2
A24: Book | B24: Chapter 5 (distribution and customer acquisition); Chapter 9 (unit economics); Annex C
A25: Model | B25: Products (commission, marketing per unit); Inputs (fixed costs); Unit_Economics
A26: Related templates | B26: T03 credit policy (agent override rules)
A28: Decision support material; not investment, legal, tax or accounting advice. Example values are illustrative and refer to the book's worked examples or to the fictional SolaraPay case. (c) 2026 Emmanuel Boujieka Kamga.

Sheet Inputs
A1: AFRICA ENERGY FINANCE | BOOK 2 | PAYGO SOLAR FINANCE
A2: Territory inputs
A3: Monthly figures for one territory, local currency
A4: Template T04 | Version 0.9 (pre-release) | Author & ideation: Emmanuel Boujieka Kamga
A6: Sales force
A7: Active agents | B7: 50 | H7: Agents selling in the month
A8: Sales per agent per month | B8: 6 | H8: All tiers
A9: Monthly agent attrition | B9: 0.08 | H9: Share of agents leaving each month
A10: Recruitment and training cost per new agent | B10: 30000 | H10: Onboarding, training, starter kit
A12: Per tier
A13: Item | B13: Tier 1 | C13: Tier 2 | D13: Tier 3 | E13: Tier 4 | F13: Tier 5 | H13: Notes
A14: Sales mix | B14: 0.3 | C14: 0.35 | D14: 0.2 | E14: 0.1 | F14: 0.05 | H14: Must total 100%
A15: Cash price | B15: 6500 | C15: 39000 | D15: 117000 | E15: 390000 | F15: 845000 | H15: Local currency
A16: Upfront commission per unit | B16: 300 | C16: 1200 | D16: 3000 | E16: 7200 | F16: 12000 | H16: Paid at activation
A17: Deferred commission per unit | B17: 200 | C17: 800 | D17: 2000 | E17: 4800 | F17: 8000 | H17: Paid if the account is current at the checkpoint
A18: Share of accounts qualifying for deferred commission | B18: 0.7 | C18: 0.8 | D18: 0.85 | E18: 0.9 | F18: 0.9 | H18: Credit assumption: current at month 3
A19: Marketing and acquisition per unit | B19: 300 | C19: 1000 | D19: 2500 | E19: 6000 | F19: 10000 | H19: Direct per unit spend
A20: Check: sales mix totals 100% | B20: =IF(ABS(SUM(B14:F14)-1)<0.0001,"OK","ERROR")
A22: Field organisation and controls (per month)
A23: Field supervisors and area managers | B23: 450000 | H23: 5 supervisors at 90,000
A24: Transport and fuel | B24: 210000 | H24: Territory budget
A25: Verification calls and field audits | B25: 60000 | H25: Territory budget
A26: Other field costs | B26: 0 | H26: Demonstration kits, materials
A27: Fraud and ghost sale losses, share of units | B27: 0.01 | H27: From audit sampling; cost valued at upfront commission plus marketing

Sheet CAC
A1: AFRICA ENERGY FINANCE | BOOK 2 | PAYGO SOLAR FINANCE
A2: Customer acquisition cost
A3: Narrow and fully loaded definitions, by tier
A4: Template T04 | Version 0.9 (pre-release) | Author & ideation: Emmanuel Boujieka Kamga
A6: Line | B6: Tier 1 | C6: Tier 2 | D6: Tier 3 | E6: Tier 4 | F6: Tier 5 | G6: Territory total | H6: Notes
A7: Units sold per month | B7: =Inputs!$B$7*Inputs!$B$8*Inputs!B$14 | C7: =Inputs!$B$7*Inputs!$B$8*Inputs!C$14 | D7: =Inputs!$B$7*Inputs!$B$8*Inputs!D$14 | E7: =Inputs!$B$7*Inputs!$B$8*Inputs!E$14 | F7: =Inputs!$B$7*Inputs!$B$8*Inputs!F$14 | G7: =SUM(B7:F7) | H7: Agents x sales per agent x mix
A8: Upfront commission | B8: =Inputs!B$16 | C8: =Inputs!C$16 | D8: =Inputs!D$16 | E8: =Inputs!E$16 | F8: =Inputs!F$16 | G8: =IF($G$7=0,0,SUMPRODUCT(B8:F8,$B$7:$F$7)/$G$7) | H8: Per unit
A9: Expected deferred commission | B9: =Inputs!B$17*Inputs!B$18 | C9: =Inputs!C$17*Inputs!C$18 | D9: =Inputs!D$17*Inputs!D$18 | E9: =Inputs!E$17*Inputs!E$18 | F9: =Inputs!F$17*Inputs!F$18 | G9: =IF($G$7=0,0,SUMPRODUCT(B9:F9,$B$7:$F$7)/$G$7) | H9: Accrued at sale on the expected qualification rate
A10: Marketing and acquisition | B10: =Inputs!B$19 | C10: =Inputs!C$19 | D10: =Inputs!D$19 | E10: =Inputs!E$19 | F10: =Inputs!F$19 | G10: =IF($G$7=0,0,SUMPRODUCT(B10:F10,$B$7:$F$7)/$G$7) | H10: Per unit
A11: Narrow CAC per unit | B11: =SUM(B8:B10) | C11: =SUM(C8:C10) | D11: =SUM(D8:D10) | E11: =SUM(E8:E10) | F11: =SUM(F8:F10) | G11: =IF($G$7=0,0,SUMPRODUCT(B11:F11,$B$7:$F$7)/$G$7) | H11: Commission plus marketing
A12: Field organisation per unit | B12: =IF($G$7=0,0,(Inputs!$B$23+Inputs!$B$24+Inputs!$B$26)/$G$7) | C12: =IF($G$7=0,0,(Inputs!$B$23+Inputs!$B$24+Inputs!$B$26)/$G$7) | D12: =IF($G$7=0,0,(Inputs!$B$23+Inputs!$B$24+Inputs!$B$26)/$G$7) | E12: =IF($G$7=0,0,(Inputs!$B$23+Inputs!$B$24+Inputs!$B$26)/$G$7) | F12: =IF($G$7=0,0,(Inputs!$B$23+Inputs!$B$24+Inputs!$B$26)/$G$7) | G12: =IF($G$7=0,0,SUMPRODUCT(B12:F12,$B$7:$F$7)/$G$7) | H12: Allocated equally per unit
A13: Recruitment and training per unit | B13: =IF($G$7=0,0,Inputs!$B$7*Inputs!$B$9*Inputs!$B$10/$G$7) | C13: =IF($G$7=0,0,Inputs!$B$7*Inputs!$B$9*Inputs!$B$10/$G$7) | D13: =IF($G$7=0,0,Inputs!$B$7*Inputs!$B$9*Inputs!$B$10/$G$7) | E13: =IF($G$7=0,0,Inputs!$B$7*Inputs!$B$9*Inputs!$B$10/$G$7) | F13: =IF($G$7=0,0,Inputs!$B$7*Inputs!$B$9*Inputs!$B$10/$G$7) | G13: =IF($G$7=0,0,SUMPRODUCT(B13:F13,$B$7:$F$7)/$G$7) | H13: Replacing leavers
A14: Verification and audits per unit | B14: =IF($G$7=0,0,Inputs!$B$25/$G$7) | C14: =IF($G$7=0,0,Inputs!$B$25/$G$7) | D14: =IF($G$7=0,0,Inputs!$B$25/$G$7) | E14: =IF($G$7=0,0,Inputs!$B$25/$G$7) | F14: =IF($G$7=0,0,Inputs!$B$25/$G$7) | G14: =IF($G$7=0,0,SUMPRODUCT(B14:F14,$B$7:$F$7)/$G$7) | H14: Allocated equally per unit
A15: Fraud losses per unit | B15: =Inputs!$B$27*(B8+B10) | C15: =Inputs!$B$27*(C8+C10) | D15: =Inputs!$B$27*(D8+D10) | E15: =Inputs!$B$27*(E8+E10) | F15: =Inputs!$B$27*(F8+F10) | G15: =IF($G$7=0,0,SUMPRODUCT(B15:F15,$B$7:$F$7)/$G$7) | H15: Commission and marketing spent on ghost sales
A16: Fully loaded CAC per unit | B16: =B11+SUM(B12:B15) | C16: =C11+SUM(C12:C15) | D16: =D11+SUM(D12:D15) | E16: =E11+SUM(E12:E15) | F16: =F11+SUM(F12:F15) | G16: =IF($G$7=0,0,SUMPRODUCT(B16:F16,$B$7:$F$7)/$G$7)
A17: Fully loaded ÷ narrow | B17: =IF(B11=0,0,B16/B11) | C17: =IF(C11=0,0,C16/C11) | D17: =IF(D11=0,0,D16/D11) | E17: =IF(E11=0,0,E16/E11) | F17: =IF(F11=0,0,F16/F11) | G17: =IF(G11=0,0,G16/G11)
A18: Narrow CAC as share of cash price | B18: =IF(Inputs!B$15=0,0,B11/Inputs!B$15) | C18: =IF(Inputs!C$15=0,0,C11/Inputs!C$15) | D18: =IF(Inputs!D$15=0,0,D11/Inputs!D$15) | E18: =IF(Inputs!E$15=0,0,E11/Inputs!E$15) | F18: =IF(Inputs!F$15=0,0,F11/Inputs!F$15)
A19: Fully loaded CAC as share of cash price | B19: =IF(Inputs!B$15=0,0,B16/Inputs!B$15) | C19: =IF(Inputs!C$15=0,0,C16/Inputs!C$15) | D19: =IF(Inputs!D$15=0,0,D16/Inputs!D$15) | E19: =IF(Inputs!E$15=0,0,E16/Inputs!E$15) | F19: =IF(Inputs!F$15=0,0,F16/Inputs!F$15)
A21: Monthly territory spend, fully loaded | B21: =SUMPRODUCT(B16:F16,B7:F7)
A22: Check: inputs valid | B22: =Inputs!$B$20
A24: Weighted averages in column G use units sold by tier. Field costs are allocated equally per unit; a company that allocates by time spent per tier should change rows 12 to 14.

Sheet Agent_Ranking
A1: AFRICA ENERGY FINANCE | BOOK 2 | PAYGO SOLAR FINANCE
A2: Agent cohort quality ranking
A3: Paste agent level data; thresholds on the right
A4: Template T04 | Version 0.9 (pre-release) | Author & ideation: Emmanuel Boujieka Kamga
A6: Agent ID | B6: Region | C6: Tenure (months) | D6: Units sold, last 6 months | E6: Share current at month 3 | F6: Repayment ratio at month 6 | G6: Deposit only accounts | H6: Deposit only share | I6: Repayment rank | J6: Flag | L6: Thresholds
A7: AG001 | B7: North | C7: 7 | D7: 27 | E7: 0.916 | F7: 0.75 | G7: 3 | H7: =IF(OR(A7="",D7=0),0,G7/D7) | I7: =IF(A7="","",COUNTIFS($F$7:$F$36,">"&F7)+1) | J7: =IF(A7="","",IF(OR(F7<$L$9,H7>$L$12),"Review",IF(F7>=$L$15,"Top band","Standard")))
A8: AG002 | B8: South | C8: 24 | D8: 40 | E8: 0.928 | F8: 0.776 | G8: 3 | H8: =IF(OR(A8="",D8=0),0,G8/D8) | I8: =IF(A8="","",COUNTIFS($F$7:$F$36,">"&F8)+1) | J8: =IF(A8="","",IF(OR(F8<$L$9,H8>$L$12),"Review",IF(F8>=$L$15,"Top band","Standard"))) | L8: Minimum repayment ratio at month 6
A9: AG003 | B9: East | C9: 12 | D9: 35 | E9: 0.819 | F9: 0.796 | G9: 4 | H9: =IF(OR(A9="",D9=0),0,G9/D9) | I9: =IF(A9="","",COUNTIFS($F$7:$F$36,">"&F9)+1) | J9: =IF(A9="","",IF(OR(F9<$L$9,H9>$L$12),"Review",IF(F9>=$L$15,"Top band","Standard"))) | L9: 0.7
A10: AG004 | B10: West | C10: 30 | D10: 35 | E10: 0.703 | F10: 0.831 | G10: 3 | H10: =IF(OR(A10="",D10=0),0,G10/D10) | I10: =IF(A10="","",COUNTIFS($F$7:$F$36,">"&F10)+1) | J10: =IF(A10="","",IF(OR(F10<$L$9,H10>$L$12),"Review",IF(F10>=$L$15,"Top band","Standard")))
A11: AG005 | B11: North | C11: 25 | D11: 31 | E11: 0.772 | F11: 0.744 | G11: 0 | H11: =IF(OR(A11="",D11=0),0,G11/D11) | I11: =IF(A11="","",COUNTIFS($F$7:$F$36,">"&F11)+1) | J11: =IF(A11="","",IF(OR(F11<$L$9,H11>$L$12),"Review",IF(F11>=$L$15,"Top band","Standard"))) | L11: Maximum deposit only share
A12: AG006 | B12: South | C12: 2 | D12: 31 | E12: 0.861 | F12: 0.826 | G12: 1 | H12: =IF(OR(A12="",D12=0),0,G12/D12) | I12: =IF(A12="","",COUNTIFS($F$7:$F$36,">"&F12)+1) | J12: =IF(A12="","",IF(OR(F12<$L$9,H12>$L$12),"Review",IF(F12>=$L$15,"Top band","Standard"))) | L12: 0.1
A13: AG007 | B13: East | C13: 12 | D13: 22 | E13: 0.949 | F13: 0.632 | G13: 0 | H13: =IF(OR(A13="",D13=0),0,G13/D13) | I13: =IF(A13="","",COUNTIFS($F$7:$F$36,">"&F13)+1) | J13: =IF(A13="","",IF(OR(F13<$L$9,H13>$L$12),"Review",IF(F13>=$L$15,"Top band","Standard")))
A14: AG008 | B14: West | C14: 21 | D14: 47 | E14: 0.806 | F14: 0.81 | G14: 3 | H14: =IF(OR(A14="",D14=0),0,G14/D14) | I14: =IF(A14="","",COUNTIFS($F$7:$F$36,">"&F14)+1) | J14: =IF(A14="","",IF(OR(F14<$L$9,H14>$L$12),"Review",IF(F14>=$L$15,"Top band","Standard"))) | L14: Repayment ratio for top commission band
A15: AG009 | B15: North | C15: 20 | D15: 33 | E15: 0.823 | F15: 0.785 | G15: 3 | H15: =IF(OR(A15="",D15=0),0,G15/D15) | I15: =IF(A15="","",COUNTIFS($F$7:$F$36,">"&F15)+1) | J15: =IF(A15="","",IF(OR(F15<$L$9,H15>$L$12),"Review",IF(F15>=$L$15,"Top band","Standard"))) | L15: 0.8
A16: AG010 | B16: South | C16: 7 | D16: 42 | E16: 0.918 | F16: 0.667 | G16: 4 | H16: =IF(OR(A16="",D16=0),0,G16/D16) | I16: =IF(A16="","",COUNTIFS($F$7:$F$36,">"&F16)+1) | J16: =IF(A16="","",IF(OR(F16<$L$9,H16>$L$12),"Review",IF(F16>=$L$15,"Top band","Standard")))
A17: AG011 | B17: East | C17: 27 | D17: 32 | E17: 0.819 | F17: 0.859 | G17: 2 | H17: =IF(OR(A17="",D17=0),0,G17/D17) | I17: =IF(A17="","",COUNTIFS($F$7:$F$36,">"&F17)+1) | J17: =IF(A17="","",IF(OR(F17<$L$9,H17>$L$12),"Review",IF(F17>=$L$15,"Top band","Standard")))
A18: AG012 | B18: West | C18: 30 | D18: 27 | E18: 0.878 | F18: 0.631 | G18: 1 | H18: =IF(OR(A18="",D18=0),0,G18/D18) | I18: =IF(A18="","",COUNTIFS($F$7:$F$36,">"&F18)+1) | J18: =IF(A18="","",IF(OR(F18<$L$9,H18>$L$12),"Review",IF(F18>=$L$15,"Top band","Standard"))) | L18: Agents flagged for review
A19: AG013 | B19: North | C19: 3 | D19: 33 | E19: 0.767 | F19: 0.754 | G19: 2 | H19: =IF(OR(A19="",D19=0),0,G19/D19) | I19: =IF(A19="","",COUNTIFS($F$7:$F$36,">"&F19)+1) | J19: =IF(A19="","",IF(OR(F19<$L$9,H19>$L$12),"Review",IF(F19>=$L$15,"Top band","Standard"))) | L19: =COUNTIFS(J7:J36,"Review")
A20: AG014 | B20: South | C20: 29 | D20: 44 | E20: 0.812 | F20: 0.79 | G20: 5 | H20: =IF(OR(A20="",D20=0),0,G20/D20) | I20: =IF(A20="","",COUNTIFS($F$7:$F$36,">"&F20)+1) | J20: =IF(A20="","",IF(OR(F20<$L$9,H20>$L$12),"Review",IF(F20>=$L$15,"Top band","Standard")))
A21: AG015 | B21: East | C21: 15 | D21: 48 | E21: 0.716 | F21: 0.772 | G21: 0 | H21: =IF(OR(A21="",D21=0),0,G21/D21) | I21: =IF(A21="","",COUNTIFS($F$7:$F$36,">"&F21)+1) | J21: =IF(A21="","",IF(OR(F21<$L$9,H21>$L$12),"Review",IF(F21>=$L$15,"Top band","Standard"))) | L21: Repayment, top half of agents
A22: AG016 | B22: West | C22: 6 | D22: 20 | E22: 0.946 | F22: 0.749 | G22: 0 | H22: =IF(OR(A22="",D22=0),0,G22/D22) | I22: =IF(A22="","",COUNTIFS($F$7:$F$36,">"&F22)+1) | J22: =IF(A22="","",IF(OR(F22<$L$9,H22>$L$12),"Review",IF(F22>=$L$15,"Top band","Standard"))) | L22: =IFERROR(AVERAGEIFS(F7:F36,I7:I36,"<="&COUNT(F7:F36)/2),0)
A23: AG017 | B23: North | C23: 6 | D23: 33 | E23: 0.715 | F23: 0.841 | G23: 0 | H23: =IF(OR(A23="",D23=0),0,G23/D23) | I23: =IF(A23="","",COUNTIFS($F$7:$F$36,">"&F23)+1) | J23: =IF(A23="","",IF(OR(F23<$L$9,H23>$L$12),"Review",IF(F23>=$L$15,"Top band","Standard"))) | L23: Repayment, bottom half of agents
A24: AG018 | B24: South | C24: 25 | D24: 49 | E24: 0.737 | F24: 0.645 | G24: 2 | H24: =IF(OR(A24="",D24=0),0,G24/D24) | I24: =IF(A24="","",COUNTIFS($F$7:$F$36,">"&F24)+1) | J24: =IF(A24="","",IF(OR(F24<$L$9,H24>$L$12),"Review",IF(F24>=$L$15,"Top band","Standard"))) | L24: =IFERROR(AVERAGEIFS(F7:F36,I7:I36,">"&COUNT(F7:F36)/2),0)
A25: AG019 | B25: East | C25: 14 | D25: 47 | E25: 0.92 | F25: 0.629 | G25: 3 | H25: =IF(OR(A25="",D25=0),0,G25/D25) | I25: =IF(A25="","",COUNTIFS($F$7:$F$36,">"&F25)+1) | J25: =IF(A25="","",IF(OR(F25<$L$9,H25>$L$12),"Review",IF(F25>=$L$15,"Top band","Standard")))
A26: AG020 | B26: West | C26: 7 | D26: 57 | E26: 0.855 | F26: 0.662 | G26: 6 | H26: =IF(OR(A26="",D26=0),0,G26/D26) | I26: =IF(A26="","",COUNTIFS($F$7:$F$36,">"&F26)+1) | J26: =IF(A26="","",IF(OR(F26<$L$9,H26>$L$12),"Review",IF(F26>=$L$15,"Top band","Standard"))) | L26: Example rows are random illustrations; replace them with company data. Repayment ratio: cumulative collections ÷ instalments due at month 6 (a cohort ratio, not a PERFORM KPI).
A27: AG021 | B27: North | C27: 14 | D27: 34 | E27: 0.795 | F27: 0.723 | G27: 3 | H27: =IF(OR(A27="",D27=0),0,G27/D27) | I27: =IF(A27="","",COUNTIFS($F$7:$F$36,">"&F27)+1) | J27: =IF(A27="","",IF(OR(F27<$L$9,H27>$L$12),"Review",IF(F27>=$L$15,"Top band","Standard")))
A28: AG022 | B28: South | C28: 15 | D28: 50 | E28: 0.786 | F28: 0.824 | G28: 5 | H28: =IF(OR(A28="",D28=0),0,G28/D28) | I28: =IF(A28="","",COUNTIFS($F$7:$F$36,">"&F28)+1) | J28: =IF(A28="","",IF(OR(F28<$L$9,H28>$L$12),"Review",IF(F28>=$L$15,"Top band","Standard")))
A29: AG023 | B29: East | C29: 29 | D29: 19 | E29: 0.833 | F29: 0.661 | G29: 2 | H29: =IF(OR(A29="",D29=0),0,G29/D29) | I29: =IF(A29="","",COUNTIFS($F$7:$F$36,">"&F29)+1) | J29: =IF(A29="","",IF(OR(F29<$L$9,H29>$L$12),"Review",IF(F29>=$L$15,"Top band","Standard")))
A30: AG024 | B30: West | C30: 17 | D30: 47 | E30: 0.933 | F30: 0.627 | G30: 2 | H30: =IF(OR(A30="",D30=0),0,G30/D30) | I30: =IF(A30="","",COUNTIFS($F$7:$F$36,">"&F30)+1) | J30: =IF(A30="","",IF(OR(F30<$L$9,H30>$L$12),"Review",IF(F30>=$L$15,"Top band","Standard")))
A31: AG025 | B31: North | C31: 9 | D31: 44 | E31: 0.841 | F31: 0.777 | G31: 0 | H31: =IF(OR(A31="",D31=0),0,G31/D31) | I31: =IF(A31="","",COUNTIFS($F$7:$F$36,">"&F31)+1) | J31: =IF(A31="","",IF(OR(F31<$L$9,H31>$L$12),"Review",IF(F31>=$L$15,"Top band","Standard")))
A32: AG026 | B32: South | C32: 24 | D32: 27 | E32: 0.802 | F32: 0.815 | G32: 0 | H32: =IF(OR(A32="",D32=0),0,G32/D32) | I32: =IF(A32="","",COUNTIFS($F$7:$F$36,">"&F32)+1) | J32: =IF(A32="","",IF(OR(F32<$L$9,H32>$L$12),"Review",IF(F32>=$L$15,"Top band","Standard")))
A33: AG027 | B33: East | C33: 29 | D33: 45 | E33: 0.7 | F33: 0.722 | G33: 4 | H33: =IF(OR(A33="",D33=0),0,G33/D33) | I33: =IF(A33="","",COUNTIFS($F$7:$F$36,">"&F33)+1) | J33: =IF(A33="","",IF(OR(F33<$L$9,H33>$L$12),"Review",IF(F33>=$L$15,"Top band","Standard")))
A34: AG028 | B34: West | C34: 24 | D34: 18 | E34: 0.896 | F34: 0.729 | G34: 0 | H34: =IF(OR(A34="",D34=0),0,G34/D34) | I34: =IF(A34="","",COUNTIFS($F$7:$F$36,">"&F34)+1) | J34: =IF(A34="","",IF(OR(F34<$L$9,H34>$L$12),"Review",IF(F34>=$L$15,"Top band","Standard")))
A35: AG029 | B35: North | C35: 11 | D35: 41 | E35: 0.798 | F35: 0.851 | G35: 5 | H35: =IF(OR(A35="",D35=0),0,G35/D35) | I35: =IF(A35="","",COUNTIFS($F$7:$F$36,">"&F35)+1) | J35: =IF(A35="","",IF(OR(F35<$L$9,H35>$L$12),"Review",IF(F35>=$L$15,"Top band","Standard")))
A36: AG030 | B36: South | C36: 28 | D36: 27 | E36: 0.804 | F36: 0.697 | G36: 2 | H36: =IF(OR(A36="",D36=0),0,G36/D36) | I36: =IF(A36="","",COUNTIFS($F$7:$F$36,">"&F36)+1) | J36: =IF(A36="","",IF(OR(F36<$L$9,H36>$L$12),"Review",IF(F36>=$L$15,"Top band","Standard")))

Sheet New_Territory
A1: AFRICA ENERGY FINANCE | BOOK 2 | PAYGO SOLAR FINANCE
A2: New territory ramp
A3: Fixed cost per unit during the first twelve months
A4: Template T04 | Version 0.9 (pre-release) | Author & ideation: Emmanuel Boujieka Kamga
A6: Fixed territory cost per month (depot, manager, vehicles) | B6: 900000
A7: Mature sales per month | B7: 300
A9: Line | B9: M1 | C9: M2 | D9: M3 | E9: M4 | F9: M5 | G9: M6 | H9: M7 | I9: M8 | J9: M9 | K9: M10 | L9: M11 | M9: M12 | N9: Notes
A10: Ramp: share of mature sales | B10: 0.33 | C10: 0.5 | D10: 0.67 | E10: 0.75 | F10: 0.83 | G10: 0.9 | H10: 0.95 | I10: 1 | J10: 1 | K10: 1 | L10: 1 | M10: 1 | N10: Ramp is an input; set it from the last territory opened
A11: Units sold | B11: =$B$7*B10 | C11: =$B$7*C10 | D11: =$B$7*D10 | E11: =$B$7*E10 | F11: =$B$7*F10 | G11: =$B$7*G10 | H11: =$B$7*H10 | I11: =$B$7*I10 | ... M11: =$B$7*M10
A12: Fixed cost per unit | B12: =IF(B11=0,0,$B$6/B11) | C12: =IF(C11=0,0,$B$6/C11) | D12: =IF(D11=0,0,$B$6/D11) | E12: =IF(E11=0,0,$B$6/E11) | F12: =IF(F11=0,0,$B$6/F11) | G12: =IF(G11=0,0,$B$6/G11) | H12: =IF(H11=0,0,$B$6/H11) | I12: =IF(I11=0,0,$B$6/I11) | ... M12: =IF(M11=0,0,$B$6/M11)
A13: Multiple of mature fixed cost per unit | B13: =IF($B$7=0,0,B12/($B$6/$B$7)) | C13: =IF($B$7=0,0,C12/($B$6/$B$7)) | D13: =IF($B$7=0,0,D12/($B$6/$B$7)) | E13: =IF($B$7=0,0,E12/($B$6/$B$7)) | F13: =IF($B$7=0,0,F12/($B$6/$B$7)) | G13: =IF($B$7=0,0,G12/($B$6/$B$7)) | H13: =IF($B$7=0,0,H12/($B$6/$B$7)) | I13: =IF($B$7=0,0,I12/($B$6/$B$7)) | ... M13: =IF($B$7=0,0,M12/($B$6/$B$7))
A15: Stop criteria (set before opening)
A16: Minimum sales per agent per month by month 6 | B16: 4
A17: Maximum gap in repayment at month 3 against established territories (points) | B17: 0.05
A18: Maximum fully loaded CAC multiple of mature figure by month 9 | B18: 1.3
