Workbook

Sheet Guide
A1: AFRICA ENERGY FINANCE | BOOK 2 | PAYGO SOLAR FINANCE
A2: Investor due diligence checklist
A3: How to use this template
A4: Template T02 | Version 0.9 (pre-release) | Author & ideation: Emmanuel Boujieka Kamga
A6: Purpose
A7: A working checklist for a credit led diligence on a PAYGo solar company: eight workstreams, the evidence to request, the red flags to look for, and a summary that shows what remains open before the investment committee.
A11: How to use it
A12: Step 1 | B12: Assign an owner and a due date to every item on the Checklist sheet.
A13: Step 2 | B13: Update the status from the drop down list as evidence arrives; record each finding in plain words.
A14: Step 3 | B14: Mark an item Issue found whenever the red flag is present, and keep it open until the memo explains it.
A15: Step 4 | B15: Read the Summary sheet before each deal team meeting: high priority items still open block the IC date.
A16: Step 5 | B16: Copy every unresolved issue into section 11 of the investment memo (Template T01).
A18: Colour code
A19: Input | B19: Blue font on cream: the only cells to edit
A20: Formula | B20: Black font: calculated, do not overwrite
A22: Links to Book 2 and MODEL 2
A23: Book | B23: Chapter 15 (diligence workstreams, data request, red flags); Annex D
A24: Model | B24: Credit_Input, Vintage_Input, Consumer_Risk, Investment_Readiness
A25: Related templates | B25: T01 investment memo; T06 loan tape and data request
A27: Decision support material; not investment, legal, tax or accounting advice. Example values are illustrative and refer to the book's worked examples or to the fictional SolaraPay case. (c) 2026 Emmanuel Boujieka Kamga.

Sheet Checklist
A1: AFRICA ENERGY FINANCE | BOOK 2 | PAYGO SOLAR FINANCE
A2: Investor due diligence checklist
A3: Status per item; drop down lists in the Priority and Status columns
A4: Template T02 | Version 0.9 (pre-release) | Author & ideation: Emmanuel Boujieka Kamga
A6: Ref | B6: Workstream | C6: Item | D6: Evidence to request | E6: Red flag | F6: Priority | G6: Status | H6: Finding | I6: Owner | J6: Due date | K6: Book chapter
A7: CM01 | B7: Commercial | C7: Market and segment definition by tier | D7: Customer survey; sales by segment and region | E7: Segments defined by product rather than by customer | F7: Medium | G7: Not started | K7: 2
A8: CM02 | B8: Commercial | C8: Sales history by tier, region and channel, 24 months | D8: Monthly sales file reconciled to revenue | E8: Growth driven by deposit waivers or price cuts | F8: High | G8: Not started | K8: 5
A9: CM03 | B9: Commercial | C9: Price plan history | D9: Price lists with effective dates | E9: Frequent promotions not recorded in the system | F9: Medium | G9: Not started | K9: 4
A10: CM04 | B10: Commercial | C10: Competitive position and alternatives | D10: Price comparison with grid, generator and competing systems | E10: No view of competitor pricing | F10: Low | G10: Not started | K10: 2
A11: CM05 | B11: Commercial | C11: Volume plan against distribution capacity | D11: Agent and installer headcount plan | E11: Volume growing faster than the agent network | F11: Medium | G11: Not started | K11: 5
A12: CR01 | B12: Credit and data tape | C12: Account level loan tape | D12: Tape in the Template T06 structure | E12: Tape does not reconcile to the ledger | F12: High | G12: Not started | K12: 15
A13: CR02 | B13: Credit and data tape | C13: Monthly portfolio data by tier, at least 24 months | D13: Data in the Credit_Input structure | E13: Early months missing or restated | F13: High | G13: Not started | K13: 7
A14: CR03 | B14: Credit and data tape | C14: Cohort repayment curves against plan | D14: Data in the Vintage_Input structure | E14: Recent cohorts below older cohorts at the same age | F14: High | G14: Not started | K14: 6
A15: CR04 | B15: Credit and data tape | C15: DPD definition and measurement | D15: Written definition; platform report | E15: Days without credit used instead of schedule shortfall, undisclosed | F15: High | G15: Not started | K15: 6
A16: CR05 | B16: Credit and data tape | C16: DPD buckets reconcile to gross receivables | D16: Monthly reconciliation | E16: Unexplained reconciliation differences | F16: High | G16: Not started | K16: 7
A17: CR06 | B17: Credit and data tape | C17: Collection rate definition (operational metric) | D17: Written definition; deposits excluded from both sides | E17: Deposits included in the numerator, or the collection rate presented as the PERFORM repayment rate | F17: High | G17: Not started | K17: 7
A18: CR07 | B18: Credit and data tape | C18: PAYGo PERFORM 2026 KPIs | D18: RR PvP, RR PvFin, RR PvP at 90 days, RR PvP at 2x term and OR @2x computed on contract data under the GOGLA Technical Guide (June 2026) | E18: KPIs not computed, rebuilt from monthly data, or averaged across cohorts instead of summing numerators and denominators | F18: High | G18: Not started | K18: 7
... A56: MG05 | B56: Management and governance | C56: Related party transactions | D56: Related party register | E56: Undisclosed related party supply | F56: Medium | G56: Not started | K56: 15

Sheet Summary
A1: AFRICA ENERGY FINANCE | BOOK 2 | PAYGO SOLAR FINANCE
A2: Diligence status summary
A3: Counts update from the Checklist sheet
A4: Template T02 | Version 0.9 (pre-release) | Author & ideation: Emmanuel Boujieka Kamga
A6: Workstream | B6: Items | C6: High priority | D6: Closed or N/A | E6: Issues found | F6: High priority open | G6: Share complete | H6: Status
A7: Commercial | B7: =COUNTIFS(Checklist!$B$7:$B$56,A7) | C7: =COUNTIFS(Checklist!$B$7:$B$56,A7,Checklist!$F$7:$F$56,"High") | D7: =COUNTIFS(Checklist!$B$7:$B$56,A7,Checklist!$G$7:$G$56,"Closed")+COUNTIFS(Checklist!$B$7:$B$56,A7,Checklist!$G$7:$G$56,"Not applicable") | E7: =COUNTIFS(Checklist!$B$7:$B$56,A7,Checklist!$G$7:$G$56,"Issue found") | F7: =C7-COUNTIFS(Checklist!$B$7:$B$56,A7,Checklist!$F$7:$F$56,"High",Checklist!$G$7:$G$56,"Closed")-COUNTIFS(Checklist!$B$7:$B$56,A7,Checklist!$F$7:$F$56,"High",Checklist!$G$7:$G$56,"Not applicable") | G7: =IF(B7=0,0,D7/B7) | H7: =IF(E7>0,"Issues open",IF(F7>0,"High items open","Complete"))
A8: Credit and data tape | B8: =COUNTIFS(Checklist!$B$7:$B$56,A8) | C8: =COUNTIFS(Checklist!$B$7:$B$56,A8,Checklist!$F$7:$F$56,"High") | D8: =COUNTIFS(Checklist!$B$7:$B$56,A8,Checklist!$G$7:$G$56,"Closed")+COUNTIFS(Checklist!$B$7:$B$56,A8,Checklist!$G$7:$G$56,"Not applicable") | E8: =COUNTIFS(Checklist!$B$7:$B$56,A8,Checklist!$G$7:$G$56,"Issue found") | F8: =C8-COUNTIFS(Checklist!$B$7:$B$56,A8,Checklist!$F$7:$F$56,"High",Checklist!$G$7:$G$56,"Closed")-COUNTIFS(Checklist!$B$7:$B$56,A8,Checklist!$F$7:$F$56,"High",Checklist!$G$7:$G$56,"Not applicable") | G8: =IF(B8=0,0,D8/B8) | H8: =IF(E8>0,"Issues open",IF(F8>0,"High items open","Complete"))
A9: Operations and agents | B9: =COUNTIFS(Checklist!$B$7:$B$56,A9) | C9: =COUNTIFS(Checklist!$B$7:$B$56,A9,Checklist!$F$7:$F$56,"High") | D9: =COUNTIFS(Checklist!$B$7:$B$56,A9,Checklist!$G$7:$G$56,"Closed")+COUNTIFS(Checklist!$B$7:$B$56,A9,Checklist!$G$7:$G$56,"Not applicable") | E9: =COUNTIFS(Checklist!$B$7:$B$56,A9,Checklist!$G$7:$G$56,"Issue found") | F9: =C9-COUNTIFS(Checklist!$B$7:$B$56,A9,Checklist!$F$7:$F$56,"High",Checklist!$G$7:$G$56,"Closed")-COUNTIFS(Checklist!$B$7:$B$56,A9,Checklist!$F$7:$F$56,"High",Checklist!$G$7:$G$56,"Not applicable") | G9: =IF(B9=0,0,D9/B9) | H9: =IF(E9>0,"Issues open",IF(F9>0,"High items open","Complete"))
A10: Technology and lockout | B10: =COUNTIFS(Checklist!$B$7:$B$56,A10) | C10: =COUNTIFS(Checklist!$B$7:$B$56,A10,Checklist!$F$7:$F$56,"High") | D10: =COUNTIFS(Checklist!$B$7:$B$56,A10,Checklist!$G$7:$G$56,"Closed")+COUNTIFS(Checklist!$B$7:$B$56,A10,Checklist!$G$7:$G$56,"Not applicable") | E10: =COUNTIFS(Checklist!$B$7:$B$56,A10,Checklist!$G$7:$G$56,"Issue found") | F10: =C10-COUNTIFS(Checklist!$B$7:$B$56,A10,Checklist!$F$7:$F$56,"High",Checklist!$G$7:$G$56,"Closed")-COUNTIFS(Checklist!$B$7:$B$56,A10,Checklist!$F$7:$F$56,"High",Checklist!$G$7:$G$56,"Not applicable") | G10: =IF(B10=0,0,D10/B10) | H10: =IF(E10>0,"Issues open",IF(F10>0,"High items open","Complete"))
A11: Finance and accounting | B11: =COUNTIFS(Checklist!$B$7:$B$56,A11) | C11: =COUNTIFS(Checklist!$B$7:$B$56,A11,Checklist!$F$7:$F$56,"High") | D11: =COUNTIFS(Checklist!$B$7:$B$56,A11,Checklist!$G$7:$G$56,"Closed")+COUNTIFS(Checklist!$B$7:$B$56,A11,Checklist!$G$7:$G$56,"Not applicable") | E11: =COUNTIFS(Checklist!$B$7:$B$56,A11,Checklist!$G$7:$G$56,"Issue found") | F11: =C11-COUNTIFS(Checklist!$B$7:$B$56,A11,Checklist!$F$7:$F$56,"High",Checklist!$G$7:$G$56,"Closed")-COUNTIFS(Checklist!$B$7:$B$56,A11,Checklist!$F$7:$F$56,"High",Checklist!$G$7:$G$56,"Not applicable") | G11: =IF(B11=0,0,D11/B11) | H11: =IF(E11>0,"Issues open",IF(F11>0,"High items open","Complete"))
A12: Legal and regulatory | B12: =COUNTIFS(Checklist!$B$7:$B$56,A12) | C12: =COUNTIFS(Checklist!$B$7:$B$56,A12,Checklist!$F$7:$F$56,"High") | D12: =COUNTIFS(Checklist!$B$7:$B$56,A12,Checklist!$G$7:$G$56,"Closed")+COUNTIFS(Checklist!$B$7:$B$56,A12,Checklist!$G$7:$G$56,"Not applicable") | E12: =COUNTIFS(Checklist!$B$7:$B$56,A12,Checklist!$G$7:$G$56,"Issue found") | F12: =C12-COUNTIFS(Checklist!$B$7:$B$56,A12,Checklist!$F$7:$F$56,"High",Checklist!$G$7:$G$56,"Closed")-COUNTIFS(Checklist!$B$7:$B$56,A12,Checklist!$F$7:$F$56,"High",Checklist!$G$7:$G$56,"Not applicable") | G12: =IF(B12=0,0,D12/B12) | H12: =IF(E12>0,"Issues open",IF(F12>0,"High items open","Complete"))
A13: ESG and consumer protection | B13: =COUNTIFS(Checklist!$B$7:$B$56,A13) | C13: =COUNTIFS(Checklist!$B$7:$B$56,A13,Checklist!$F$7:$F$56,"High") | D13: =COUNTIFS(Checklist!$B$7:$B$56,A13,Checklist!$G$7:$G$56,"Closed")+COUNTIFS(Checklist!$B$7:$B$56,A13,Checklist!$G$7:$G$56,"Not applicable") | E13: =COUNTIFS(Checklist!$B$7:$B$56,A13,Checklist!$G$7:$G$56,"Issue found") | F13: =C13-COUNTIFS(Checklist!$B$7:$B$56,A13,Checklist!$F$7:$F$56,"High",Checklist!$G$7:$G$56,"Closed")-COUNTIFS(Checklist!$B$7:$B$56,A13,Checklist!$F$7:$F$56,"High",Checklist!$G$7:$G$56,"Not applicable") | G13: =IF(B13=0,0,D13/B13) | H13: =IF(E13>0,"Issues open",IF(F13>0,"High items open","Complete"))
A14: Management and governance | B14: =COUNTIFS(Checklist!$B$7:$B$56,A14) | C14: =COUNTIFS(Checklist!$B$7:$B$56,A14,Checklist!$F$7:$F$56,"High") | D14: =COUNTIFS(Checklist!$B$7:$B$56,A14,Checklist!$G$7:$G$56,"Closed")+COUNTIFS(Checklist!$B$7:$B$56,A14,Checklist!$G$7:$G$56,"Not applicable") | E14: =COUNTIFS(Checklist!$B$7:$B$56,A14,Checklist!$G$7:$G$56,"Issue found") | F14: =C14-COUNTIFS(Checklist!$B$7:$B$56,A14,Checklist!$F$7:$F$56,"High",Checklist!$G$7:$G$56,"Closed")-COUNTIFS(Checklist!$B$7:$B$56,A14,Checklist!$F$7:$F$56,"High",Checklist!$G$7:$G$56,"Not applicable") | G14: =IF(B14=0,0,D14/B14) | H14: =IF(E14>0,"Issues open",IF(F14>0,"High items open","Complete"))
A15: Total | B15: =SUM(B7:B14) | C15: =SUM(C7:C14) | D15: =SUM(D7:D14) | E15: =SUM(E7:E14) | F15: =SUM(F7:F14) | G15: =IF(B15=0,0,D15/B15) | H15: =IF(E15>0,"Issues open",IF(F15>0,"High items open","Complete"))
A17: Ready for investment committee | B17: =IF(AND(E15=0,F15=0),"Yes","No: resolve open high priority items and issues first")
