Workbook

Sheet Guide
A1: AFRICA ENERGY FINANCE | BOOK 2 | PAYGO SOLAR FINANCE
A2: Lender KPI report
A3: How to use this template
A4: Template T05 | Version 0.9 (pre-release) | Author & ideation: Emmanuel Boujieka Kamga
A6: Purpose
A7: A monthly reporting pack for a PAYGo receivables lender or an investor's portfolio review: the five PAYGo PERFORM 2026 KPIs as reported by the company, operational and lender metrics with their definitions, DPD reconciliation, covenant headroom, cohort repayment against plan and a one page dashboard. The example data are the synthetic 24 month history of the fictional SolaraPay case (Tiers 1 to 3).
A11: How to use it
A12: Step 1 | B12: Replace the example data on Monthly_Input with company data, one column per month (up to 24 months).
A13: Step 2 | B13: Check the reconciliation row on KPIs: the DPD buckets must add up to reported gross receivables every month.
A14: Step 3 | B14: Set covenant thresholds and the blended advance rate on Covenants; the sheet shows headroom and breach flags by month.
A15: Step 4 | B15: Enter cumulative collections and instalments due by cohort on Vintage, with the plan curve, to see cohorts against plan.
A16: Step 5 | B16: Enter the company's PERFORM 2026 numerators and denominators on PERFORM_2026; leave them blank if not computed.
A17: Step 6 | B17: Send the Dashboard page with every monthly report, with the Definitions sheet; the collection rate is an operational metric and never replaces the repayment rate.
A19: Colour code
A20: Input | B20: Blue font on cream: the only cells to edit
A21: Formula | B21: Black font: calculated, do not overwrite
A23: Links to Book 2 and MODEL 2
A24: Book | B24: Chapter 6 (cohorts), Chapter 7 (portfolio KPIs and PERFORM), Chapter 11 (covenants); Annex A
A25: Model | B25: MODEL 2: Credit_Input and Vintage_Input hold the same history; Credit_Portfolio, Covenants, Vintage_Dashboard, PERFORM_2026
A26: Related templates | B26: T06 loan tape; T07 borrowing base certificate
A28: Decision support material; not investment, legal, tax or accounting advice. Example values are illustrative and refer to the book's worked examples or to the fictional SolaraPay case. (c) 2026 Emmanuel Boujieka Kamga.

Sheet Dashboard
A1: AFRICA ENERGY FINANCE | BOOK 2 | PAYGO SOLAR FINANCE
A2: Monthly lender dashboard
A3: Latest month; charts over the reporting period
A4: Template T05 | Version 0.9 (pre-release) | Author & ideation: Emmanuel Boujieka Kamga
A6: KPI | B6: Latest | C6: 3 months earlier | D6: 12 months earlier | E6: Trend | G6: PAYGo PERFORM 2026 KPI (company reported) | J6: Portfolio
A7: Operational collection rate (month) | B7: =IFERROR(INDEX(KPIs!$C$11:$Z$11,MATCH(9.99E+307,KPIs!$C$11:$Z$11)),"") | C7: =IFERROR(INDEX(KPIs!$C$11:$Z$11,MATCH(9.99E+307,KPIs!$C$11:$Z$11)-3),"") | D7: =IFERROR(INDEX(KPIs!$C$11:$Z$11,MATCH(9.99E+307,KPIs!$C$11:$Z$11)-12),"") | E7: =IF(OR(B7="",C7=""),"",IF(B7=C7,"Stable",IF((B7>C7)=TRUE,"Improving","Deteriorating"))) | G7: RR PvP (repayment rate, paid versus plan) | J7: =PERFORM_2026!H14
A8: Operational collection rate (trailing 3 months) | B8: =IFERROR(INDEX(KPIs!$C$12:$Z$12,MATCH(9.99E+307,KPIs!$C$12:$Z$12)),"") | C8: =IFERROR(INDEX(KPIs!$C$12:$Z$12,MATCH(9.99E+307,KPIs!$C$12:$Z$12)-3),"") | D8: =IFERROR(INDEX(KPIs!$C$12:$Z$12,MATCH(9.99E+307,KPIs!$C$12:$Z$12)-12),"") | E8: =IF(OR(B8="",C8=""),"",IF(B8=C8,"Stable",IF((B8>C8)=TRUE,"Improving","Deteriorating"))) | G8: RR PvFin (repayment rate, paid versus financed) | J8: =PERFORM_2026!H19
A9: PAR30 | B9: =IFERROR(INDEX(KPIs!$C$13:$Z$13,MATCH(9.99E+307,KPIs!$C$13:$Z$13)),"") | C9: =IFERROR(INDEX(KPIs!$C$13:$Z$13,MATCH(9.99E+307,KPIs!$C$13:$Z$13)-3),"") | D9: =IFERROR(INDEX(KPIs!$C$13:$Z$13,MATCH(9.99E+307,KPIs!$C$13:$Z$13)-12),"") | E9: =IF(OR(B9="",C9=""),"",IF(B9=C9,"Stable",IF((B9>C9)=FALSE,"Improving","Deteriorating"))) | G9: RR PvP at 90 days | J9: =PERFORM_2026!H24
A10: PAR90 | B10: =IFERROR(INDEX(KPIs!$C$14:$Z$14,MATCH(9.99E+307,KPIs!$C$14:$Z$14)),"") | C10: =IFERROR(INDEX(KPIs!$C$14:$Z$14,MATCH(9.99E+307,KPIs!$C$14:$Z$14)-3),"") | D10: =IFERROR(INDEX(KPIs!$C$14:$Z$14,MATCH(9.99E+307,KPIs!$C$14:$Z$14)-12),"") | E10: =IF(OR(B10="",C10=""),"",IF(B10=C10,"Stable",IF((B10>C10)=FALSE,"Improving","Deteriorating"))) | G10: RR PvP at 2x term | J10: =PERFORM_2026!H29
A11: PAR30 lagged 3 months | B11: =IFERROR(INDEX(KPIs!$C$15:$Z$15,MATCH(9.99E+307,KPIs!$C$15:$Z$15)),"") | C11: =IFERROR(INDEX(KPIs!$C$15:$Z$15,MATCH(9.99E+307,KPIs!$C$15:$Z$15)-3),"") | D11: =IFERROR(INDEX(KPIs!$C$15:$Z$15,MATCH(9.99E+307,KPIs!$C$15:$Z$15)-12),"") | E11: =IF(OR(B11="",C11=""),"",IF(B11=C11,"Stable",IF((B11>C11)=FALSE,"Improving","Deteriorating"))) | G11: OR @2x (ownership rate at 2x term) | J11: =PERFORM_2026!H34
A12: Write off ratio (trailing 12 months, annualised) | B12: =IFERROR(INDEX(KPIs!$C$17:$Z$17,MATCH(9.99E+307,KPIs!$C$17:$Z$17)),"") | C12: =IFERROR(INDEX(KPIs!$C$17:$Z$17,MATCH(9.99E+307,KPIs!$C$17:$Z$17)-3),"") | D12: =IFERROR(INDEX(KPIs!$C$17:$Z$17,MATCH(9.99E+307,KPIs!$C$17:$Z$17)-12),"") | E12: =IF(OR(B12="",C12=""),"",IF(B12=C12,"Stable",IF((B12>C12)=FALSE,"Improving","Deteriorating"))) | G12: Reporting date | J12: =IF(PERFORM_2026!B8="","",PERFORM_2026!B8)
A13: Recovery rate (trailing 12 months) | B13: =IFERROR(INDEX(KPIs!$C$18:$Z$18,MATCH(9.99E+307,KPIs!$C$18:$Z$18)),"") | C13: =IFERROR(INDEX(KPIs!$C$18:$Z$18,MATCH(9.99E+307,KPIs!$C$18:$Z$18)-3),"") | D13: =IFERROR(INDEX(KPIs!$C$18:$Z$18,MATCH(9.99E+307,KPIs!$C$18:$Z$18)-12),"") | E13: =IF(OR(B13="",C13=""),"",IF(B13=C13,"Stable",IF((B13>C13)=TRUE,"Improving","Deteriorating"))) | G13: Rows 7 to 14 on the left are operational and lender metrics, not PERFORM KPIs.
A14: Eligible receivables (to 30 DPD) | B14: =IFERROR(INDEX(KPIs!$C$20:$Z$20,MATCH(9.99E+307,KPIs!$C$20:$Z$20)),"") | C14: =IFERROR(INDEX(KPIs!$C$20:$Z$20,MATCH(9.99E+307,KPIs!$C$20:$Z$20)-3),"") | D14: =IFERROR(INDEX(KPIs!$C$20:$Z$20,MATCH(9.99E+307,KPIs!$C$20:$Z$20)-12),"") | E14: =IF(OR(B14="",C14=""),"",IF(B14=C14,"Stable",IF((B14>C14)=TRUE,"Improving","Deteriorating")))
A16: Reconciliation, latest month | B16: =IFERROR(INDEX(KPIs!$C$10:$Z$10,MATCH("zzz",KPIs!$C$10:$Z$10)),"")
A17: Months with any covenant breach | B17: =Covenants!B22

Sheet Definitions
A1: AFRICA ENERGY FINANCE | BOOK 2 | PAYGO SOLAR FINANCE
A2: KPI definitions
A3: Definitions used in this report
A4: Template T05 | Version 0.9 (pre-release) | Author & ideation: Emmanuel Boujieka Kamga
A6: KPI | B6: Definition | C6: Comment
A7: RR PvP (repayment rate, paid versus plan) [PERFORM 2026 KPI] | B7: Payments applied to due instalments to date ÷ instalments due to date | C7: Company reported (time series); see the PERFORM_2026 sheet
A8: RR PvFin (repayment rate, paid versus financed) [PERFORM 2026 KPI] | B8: Payments applied to due instalments to date ÷ total amount financed | C8: Company reported (time series); see the PERFORM_2026 sheet
A9: RR PvP at 90 days [PERFORM 2026 KPI] | B9: Payments applied to instalments due by day 90 ÷ instalments due by day 90 | C9: Company reported (cohort milestone); see the PERFORM_2026 sheet
A10: RR PvP at 2x term [PERFORM 2026 KPI] | B10: Payments applied to due instalments by 2x the term ÷ instalments due over 1x the term | C10: Company reported (cohort outcome); see the PERFORM_2026 sheet
A11: OR @2x (ownership rate at 2x term) [PERFORM 2026 KPI] | B11: Contracts fully paid by 2x the term ÷ contracts that have reached at least 2x | C11: Company reported (cohort outcome); see the PERFORM_2026 sheet
A12: Operational collection rate (month) | B12: Instalments collected ÷ instalments due in the month, both excluding deposits | C12: Operational metric, not a PERFORM KPI; may not stand in for the repayment rate. Deposits are collected at sale and would flatter the ratio
A13: Operational collection rate (trailing 3 months) | B13: Collections ÷ instalments due over the last three months | C13: Usual covenant measure; operational, not a PERFORM KPI
A14: PAR30 | B14: Gross receivables of accounts more than 30 days past due ÷ gross receivables | C14: Whole balance of late accounts counts
A15: PAR90 | B15: Gross receivables of accounts more than 90 days past due ÷ gross receivables
A16: PAR30 lagged 3 months | B16: Balance more than 30 days past due ÷ gross receivables three months earlier | C16: Corrects for growth in the denominator
A17: Receivables at risk (RaR) | B17: As reported by the company under its stated definition ÷ gross receivables | C17: Lender metric, not a current PERFORM KPI (defined in the 2021 guide, now historical); print the definition beside the figure
A18: Write off ratio (trailing 12 months, annualised) | B18: Write offs ÷ average gross receivables over the same months, scaled to a year | C18: Lender metric (2021 guide definition, historical); depends on the write off policy
A19: Recovery rate (trailing 12 months) | B19: Recoveries net of costs ÷ write offs
A20: Active ratio | B20: Accounts with a payment in the last 30 days ÷ accounts not yet paid off or written off | C20: Optional; leave blank if not reported
A21: Eligible receivables | B21: Current and 1 to 30 DPD balances (eligibility to 30 DPD) | C21: Change the formula if eligibility differs
A22: Borrowing base headroom | B22: Eligible receivables × advance rate less facility drawn
A23: Cohort repayment ratio (not a PERFORM KPI) | B23: Cumulative collections ÷ cumulative instalments due at a given age, monthly | C23: Follows the logic of RR PvP but is not a PERFORM calculation (monthly, no payment allocation); compare cohorts at the same age

Sheet Monthly_Input
A1: AFRICA ENERGY FINANCE | BOOK 2 | PAYGO SOLAR FINANCE
A2: Monthly portfolio input
A3: Local currency; one column per month; month end stocks and monthly flows
A4: Template T05 | Version 0.9 (pre-release) | Author & ideation: Emmanuel Boujieka Kamga
A6: Item | B6: Unit | C6: M1 | D6: M2 | E6: M3 | F6: M4 | G6: M5 | H6: M6 | I6: M7 | J6: M8 | K6: M9 | L6: M10 | M6: M11 | N6: M12 | O6: M13 | P6: M14 | Q6: M15 | R6: M16 | S6: M17 | T6: M18 | U6: M19 | V6: M20 | W6: M21 | X6: M22 | Y6: M23 | Z6: M24
A7: Month end date | B7: date | C7: 45322 | D7: 45351 | E7: 45382 | F7: 45412 | G7: 45443 | H7: 45473 | I7: 45504 | J7: 45535 | K7: 45565 | L7: 45596 | M7: 45626 | N7: 45657 | O7: 45688 | P7: 45716 | Q7: 45747 | R7: 45777 | S7: 45808 | T7: 45838 | U7: 45869 | V7: 45900 | W7: 45930 | X7: 45961 | Y7: 45991 | Z7: 46022
A8: Gross receivables (reported) | B8: LCY | C8: 18461150 | D8: 38420620 | E8: 56840385 | F8: 77055090 | G8: 98707832 | H8: 121500523 | I8: 141344073 | J8: 163691705 | K8: 187223637 | L8: 212382977 | M8: 236055950 | N8: 259723485 | O8: 283064395 | P8: 307163697 | Q8: 330080892 | R8: 352212775 | S8: 374819078 | T8: 398269903 | U8: 424270392 | V8: 447026265 | W8: 469320872 | X8: 493888285 | Y8: 513864362 | Z8: 536043223
A9: Current | B9: LCY | C9: 15876589 | D9: 32591980 | E9: 47537037 | F9: 63651185 | G9: 80606617 | H9: 98158469 | I9: 112800688 | J9: 129321433 | K9: 146554710 | L9: 164889292 | M9: 181649931 | N9: 198177227 | O9: 214238141 | P9: 230770575 | Q9: 246126841 | R9: 260700565 | S9: 275623491 | T9: 291236718 | U9: 309006008 | V9: 323924509 | W9: 338494271 | X9: 355101191 | Y9: 367814951 | Z9: 382613028
A10: 1 to 30 DPD | B10: LCY | C10: 2584561 | D10: 5305671 | E10: 7738587 | F10: 10361821 | G10: 13122007 | H10: 15979286 | I10: 18362903 | J10: 21052326 | K10: 23857744 | L10: 26842443 | M10: 29570919 | N10: 32261409 | O10: 34875976 | P10: 37567303 | Q10: 40067160 | R10: 42439627 | S10: 44868940 | T10: 47410629 | U10: 50303304 | V10: 52731897 | W10: 55103718 | X10: 57807171 | Y10: 59876852 | Z10: 62285842
A11: 31 to 60 DPD | B11: LCY | C11: 0 | D11: 154725 | E11: 290631 | F11: 684193 | G11: 439604 | H11: 2311899 | I11: 1532710 | J11: 2691947 | K11: 3173512 | L11: 3756337 | M11: 4918838 | N11: 5360626 | O11: 6899067 | P11: 9903716 | Q11: 9595264 | R11: 14250956 | S11: 8542448 | T11: 12299315 | U11: 12064344 | V11: 10862364 | W11: 13338398 | X11: 12813022 | Y11: 11743009 | Z11: 18234338
A12: 61 to 90 DPD | B12: LCY | C12: 0 | D12: 145708 | E12: 253627 | F12: 624147 | G12: 775201 | H12: 969055 | I12: 2386818 | J12: 1709197 | K12: 1880842 | L12: 2754214 | M12: 4861658 | N12: 4339816 | O12: 6520400 | P12: 4080594 | Q12: 9169950 | R12: 7121566 | S12: 10635097 | T12: 10341184 | U12: 15982467 | V12: 9715704 | W12: 13301034 | X12: 11094301 | Y12: 11239960 | Z12: 15141867
A13: 91 to 180 DPD | B13: LCY | C13: 0 | D13: 104961 | E13: 527016 | F13: 449567 | G13: 926354 | H13: 1414128 | I13: 1679179 | J13: 3066810 | K13: 4999691 | L13: 4945659 | M13: 5067155 | N13: 7938819 | O13: 6579875 | P13: 10262787 | Q13: 8618951 | R13: 9703177 | S13: 14934420 | T13: 21203346 | U13: 16357430 | V13: 17771514 | W13: 20929363 | X13: 24752048 | Y13: 30095014 | Z13: 23088469
A14: Over 180 DPD | B14: LCY | C14: 0 | D14: 117576 | E14: 493487 | F14: 1284177 | G14: 2838048 | H14: 2667687 | I14: 4581775 | J14: 5849992 | K14: 6757138 | L14: 9195033 | M14: 9987448 | N14: 11645587 | O14: 13950936 | P14: 14578722 | Q14: 16502725 | R14: 17996885 | S14: 20214681 | T14: 15778712 | U14: 20556839 | V14: 32020278 | W14: 28154087 | X14: 32320552 | Y14: 33094575 | Z14: 34679680
A15: Instalments due in month (excluding deposits) | B15: LCY | C15: 0 | D15: 1154799 | E15: 2434155 | F15: 3673999 | G15: 5093727 | H15: 6637008 | I15: 8301317 | J15: 9869813 | K15: 11654176 | L15: 13583962 | M15: 15665557 | N15: 17756794 | O15: 19917381 | P15: 22063611 | Q15: 24314262 | R15: 26580091 | S15: 28860672 | T15: 31227058 | U15: 33742820 | V15: 36488320 | W15: 39153672 | X15: 41852542 | Y15: 44834592 | Z15: 47625109
A16: Instalments collected in month (excluding deposits) | B16: LCY | C16: 0 | D16: 1007013 | E16: 2074572 | F16: 2950068 | G16: 4118571 | H16: 5348943 | I16: 6662015 | J16: 7648116 | K16: 8996222 | L16: 10269182 | M16: 11834787 | N16: 13246472 | O16: 14733873 | P16: 16064161 | Q16: 17710090 | R16: 18866297 | S16: 20490082 | T16: 21825577 | U16: 23489918 | V16: 25023707 | W16: 26868824 | X16: 28372965 | Y16: 29913116 | Z16: 31659766
A17: Deposits collected | B17: LCY | C17: 2761350 | D17: 3142350 | E17: 3044700 | F17: 3368350 | G17: 3813750 | H17: 4148000 | I17: 3802450 | J17: 4304250 | K17: 4671500 | L17: 5109500 | M17: 5049100 | N17: 5316000 | O17: 5379500 | P17: 5750050 | Q17: 5726650 | R17: 5862600 | S17: 6211150 | T17: 6473150 | U17: 7153300 | V17: 6964000 | W17: 7110200 | X17: 7704650 | Y17: 7239550 | Z17: 7788800
A18: Write offs in month | B18: LCY | C18: 0 | D18: 147786 | E18: 359583 | F18: 723931 | G18: 975156 | H18: 1288065 | I18: 1639302 | J18: 2221696 | K18: 2657954 | L18: 3314780 | M18: 3830769 | N18: 4510322 | O18: 5183508 | P18: 5999450 | Q18: 6604172 | R18: 7713793 | S18: 8370590 | T18: 9401481 | U18: 10252903 | V18: 11464613 | W18: 12284848 | X18: 13479577 | Y18: 14921476 | Z18: 15965343
... A20: Units originated | B20: count | C20: 466 | D20: 501 | E20: 498 | F20: 592 | G20: 622 | H20: 657 | I20: 647 | J20: 728 | K20: 793 | L20: 816 | M20: 849 | N20: 869 | O20: 936 | P20: 959 | Q20: 981 | R20: 1001 | S20: 1020 | T20: 1078 | U20: 1146 | V20: 1164 | W20: 1154 | X20: 1287 | Y20: 1210 | Z20: 1307
A21: Receivables at risk (company definition, optional) | B21: LCY
A22: Active accounts (optional) | B22: count
A23: Open accounts, not paid off or written off (optional) | B23: count
A24: Facility drawn | B24: LCY | C24: 0 | D24: 0 | E24: 0 | F24: 0 | G24: 0 | H24: 0 | I24: 0 | J24: 0 | K24: 0 | L24: 0 | M24: 0 | N24: 0 | O24: 0 | P24: 0 | Q24: 0 | R24: 0 | S24: 0 | T24: 0 | U24: 0 | V24: 0 | W24: 0 | X24: 0 | Y24: 0 | Z24: 0
A26: Example: synthetic SolaraPay history, Tiers 1 to 3 combined (fictional). Facility drawn is set to zero because the facility had not been signed in the history period.

Sheet Covenants
A1: AFRICA ENERGY FINANCE | BOOK 2 | PAYGO SOLAR FINANCE
A2: Covenant tests
A3: Thresholds are inputs; headroom and flags by month
A4: Template T05 | Version 0.9 (pre-release) | Author & ideation: Emmanuel Boujieka Kamga
A6: Thresholds
A7: Minimum trailing 3 month operational collection rate | B7: 0.7
A8: Maximum RaR | B8: 0.15
A9: Maximum PAR30 | B9: 0.25
A10: Maximum PAR90 | B10: 0.18
A11: Minimum borrowing base headroom (LCY) | B11: 0
A12: Blended advance rate on eligible receivables | B12: 0.7
A13: Watch list when headroom is below this share of the threshold | B13: 0.1
A15: Test (1 = breach) | C15: M1 | D15: M2 | E15: M3 | F15: M4 | G15: M5 | H15: M6 | I15: M7 | J15: M8 | K15: M9 | L15: M10 | M15: M11 | N15: M12 | O15: M13 | P15: M14 | Q15: M15 | R15: M16 | S15: M17 | T15: M18 | U15: M19 | V15: M20 | W15: M21 | X15: M22 | Y15: M23 | Z15: M24
A16: Trailing 3 month operational collection rate | C16: =IF(KPIs!C12="","",IF(KPIs!C12<$B$7,1,0)) | D16: =IF(KPIs!D12="","",IF(KPIs!D12<$B$7,1,0)) | E16: =IF(KPIs!E12="","",IF(KPIs!E12<$B$7,1,0)) | F16: =IF(KPIs!F12="","",IF(KPIs!F12<$B$7,1,0)) | G16: =IF(KPIs!G12="","",IF(KPIs!G12<$B$7,1,0)) | H16: =IF(KPIs!H12="","",IF(KPIs!H12<$B$7,1,0)) | I16: =IF(KPIs!I12="","",IF(KPIs!I12<$B$7,1,0)) | J16: =IF(KPIs!J12="","",IF(KPIs!J12<$B$7,1,0)) | ... Z16: =IF(KPIs!Z12="","",IF(KPIs!Z12<$B$7,1,0))
A17: RaR | C17: =IF(KPIs!C16="","",IF(KPIs!C16>$B$8,1,0)) | D17: =IF(KPIs!D16="","",IF(KPIs!D16>$B$8,1,0)) | E17: =IF(KPIs!E16="","",IF(KPIs!E16>$B$8,1,0)) | F17: =IF(KPIs!F16="","",IF(KPIs!F16>$B$8,1,0)) | G17: =IF(KPIs!G16="","",IF(KPIs!G16>$B$8,1,0)) | H17: =IF(KPIs!H16="","",IF(KPIs!H16>$B$8,1,0)) | I17: =IF(KPIs!I16="","",IF(KPIs!I16>$B$8,1,0)) | J17: =IF(KPIs!J16="","",IF(KPIs!J16>$B$8,1,0)) | ... Z17: =IF(KPIs!Z16="","",IF(KPIs!Z16>$B$8,1,0))
A18: PAR30 | C18: =IF(KPIs!C13="","",IF(KPIs!C13>$B$9,1,0)) | D18: =IF(KPIs!D13="","",IF(KPIs!D13>$B$9,1,0)) | E18: =IF(KPIs!E13="","",IF(KPIs!E13>$B$9,1,0)) | F18: =IF(KPIs!F13="","",IF(KPIs!F13>$B$9,1,0)) | G18: =IF(KPIs!G13="","",IF(KPIs!G13>$B$9,1,0)) | H18: =IF(KPIs!H13="","",IF(KPIs!H13>$B$9,1,0)) | I18: =IF(KPIs!I13="","",IF(KPIs!I13>$B$9,1,0)) | J18: =IF(KPIs!J13="","",IF(KPIs!J13>$B$9,1,0)) | ... Z18: =IF(KPIs!Z13="","",IF(KPIs!Z13>$B$9,1,0))
A19: PAR90 | C19: =IF(KPIs!C14="","",IF(KPIs!C14>$B$10,1,0)) | D19: =IF(KPIs!D14="","",IF(KPIs!D14>$B$10,1,0)) | E19: =IF(KPIs!E14="","",IF(KPIs!E14>$B$10,1,0)) | F19: =IF(KPIs!F14="","",IF(KPIs!F14>$B$10,1,0)) | G19: =IF(KPIs!G14="","",IF(KPIs!G14>$B$10,1,0)) | H19: =IF(KPIs!H14="","",IF(KPIs!H14>$B$10,1,0)) | I19: =IF(KPIs!I14="","",IF(KPIs!I14>$B$10,1,0)) | J19: =IF(KPIs!J14="","",IF(KPIs!J14>$B$10,1,0)) | ... Z19: =IF(KPIs!Z14="","",IF(KPIs!Z14>$B$10,1,0))
A20: Borrowing base headroom | C20: =IF(N(Monthly_Input!C24)=0,"",IF(KPIs!C22<$B$11,1,0)) | D20: =IF(N(Monthly_Input!D24)=0,"",IF(KPIs!D22<$B$11,1,0)) | E20: =IF(N(Monthly_Input!E24)=0,"",IF(KPIs!E22<$B$11,1,0)) | F20: =IF(N(Monthly_Input!F24)=0,"",IF(KPIs!F22<$B$11,1,0)) | G20: =IF(N(Monthly_Input!G24)=0,"",IF(KPIs!G22<$B$11,1,0)) | H20: =IF(N(Monthly_Input!H24)=0,"",IF(KPIs!H22<$B$11,1,0)) | I20: =IF(N(Monthly_Input!I24)=0,"",IF(KPIs!I22<$B$11,1,0)) | J20: =IF(N(Monthly_Input!J24)=0,"",IF(KPIs!J22<$B$11,1,0)) | ... Z20: =IF(N(Monthly_Input!Z24)=0,"",IF(KPIs!Z22<$B$11,1,0))
A21: Any covenant in breach | C21: =IF(COUNT(C16:C20)=0,"",IF(SUM(C16:C20)>0,1,0)) | D21: =IF(COUNT(D16:D20)=0,"",IF(SUM(D16:D20)>0,1,0)) | E21: =IF(COUNT(E16:E20)=0,"",IF(SUM(E16:E20)>0,1,0)) | F21: =IF(COUNT(F16:F20)=0,"",IF(SUM(F16:F20)>0,1,0)) | G21: =IF(COUNT(G16:G20)=0,"",IF(SUM(G16:G20)>0,1,0)) | H21: =IF(COUNT(H16:H20)=0,"",IF(SUM(H16:H20)>0,1,0)) | I21: =IF(COUNT(I16:I20)=0,"",IF(SUM(I16:I20)>0,1,0)) | J21: =IF(COUNT(J16:J20)=0,"",IF(SUM(J16:J20)>0,1,0)) | ... Z21: =IF(COUNT(Z16:Z20)=0,"",IF(SUM(Z16:Z20)>0,1,0))
A22: Months in breach | B22: =SUM(C21:Z21)
A24: Latest month
A25: Test | B25: Threshold | C25: Actual | D25: Headroom | E25: Status
A26: Trailing 3 month operational collection rate | B26: =B7 | C26: =IFERROR(INDEX(KPIs!$C$12:$Z$12,MATCH(9.99E+307,KPIs!$C$12:$Z$12)),"") | D26: =IF(C26="","",C26-B26) | E26: =IF(C26="",IF(A26="Borrowing base headroom","No facility drawn","No data"),IF(D26<0,"Breach",IF(D26<ABS(B26)*$B$13,"Watch","Compliant")))
A27: RaR | B27: =B8 | C27: =IFERROR(INDEX(KPIs!$C$16:$Z$16,MATCH(9.99E+307,KPIs!$C$16:$Z$16)),"") | D27: =IF(C27="","",B27-C27) | E27: =IF(C27="",IF(A27="Borrowing base headroom","No facility drawn","No data"),IF(D27<0,"Breach",IF(D27<ABS(B27)*$B$13,"Watch","Compliant")))
A28: PAR30 | B28: =B9 | C28: =IFERROR(INDEX(KPIs!$C$13:$Z$13,MATCH(9.99E+307,KPIs!$C$13:$Z$13)),"") | D28: =IF(C28="","",B28-C28) | E28: =IF(C28="",IF(A28="Borrowing base headroom","No facility drawn","No data"),IF(D28<0,"Breach",IF(D28<ABS(B28)*$B$13,"Watch","Compliant")))
A29: PAR90 | B29: =B10 | C29: =IFERROR(INDEX(KPIs!$C$14:$Z$14,MATCH(9.99E+307,KPIs!$C$14:$Z$14)),"") | D29: =IF(C29="","",B29-C29) | E29: =IF(C29="",IF(A29="Borrowing base headroom","No facility drawn","No data"),IF(D29<0,"Breach",IF(D29<ABS(B29)*$B$13,"Watch","Compliant")))
A30: Borrowing base headroom | B30: =B11 | C30: =IF(N(IFERROR(INDEX(Monthly_Input!$C$24:$Z$24,MATCH(9.99E+307,Monthly_Input!$C$24:$Z$24)),0))=0,"",IFERROR(INDEX(KPIs!$C$22:$Z$22,MATCH(9.99E+307,KPIs!$C$22:$Z$22)),"")) | D30: =IF(C30="","",C30-B30) | E30: =IF(C30="",IF(A30="Borrowing base headroom","No facility drawn","No data"),IF(D30<0,"Breach",IF(D30<ABS(B30)*$B$13,"Watch","Compliant")))
A32: Borrowing base headroom is tested only in months with a facility drawn. RaR is tested only when the company reports it.

Sheet KPIs
A1: AFRICA ENERGY FINANCE | BOOK 2 | PAYGO SOLAR FINANCE
A2: Portfolio KPIs
A3: Calculated from Monthly_Input; blank where data are not reported
A4: Template T05 | Version 0.9 (pre-release) | Author & ideation: Emmanuel Boujieka Kamga
A6: KPI | B6: Unit | C6: M1 | D6: M2 | E6: M3 | F6: M4 | G6: M5 | H6: M6 | I6: M7 | J6: M8 | K6: M9 | L6: M10 | M6: M11 | N6: M12 | O6: M13 | P6: M14 | Q6: M15 | R6: M16 | S6: M17 | T6: M18 | U6: M19 | V6: M20 | W6: M21 | X6: M22 | Y6: M23 | Z6: M24
A7: Month end date | B7: date | C7: =Monthly_Input!C7 | D7: =Monthly_Input!D7 | E7: =Monthly_Input!E7 | F7: =Monthly_Input!F7 | G7: =Monthly_Input!G7 | H7: =Monthly_Input!H7 | I7: =Monthly_Input!I7 | J7: =Monthly_Input!J7 | ... Z7: =Monthly_Input!Z7
A8: Sum of DPD buckets | B8: LCY | C8: =SUM(Monthly_Input!C9:C14) | D8: =SUM(Monthly_Input!D9:D14) | E8: =SUM(Monthly_Input!E9:E14) | F8: =SUM(Monthly_Input!F9:F14) | G8: =SUM(Monthly_Input!G9:G14) | H8: =SUM(Monthly_Input!H9:H14) | I8: =SUM(Monthly_Input!I9:I14) | J8: =SUM(Monthly_Input!J9:J14) | ... Z8: =SUM(Monthly_Input!Z9:Z14)
A9: Reconciliation difference | B9: LCY | C9: =C8-Monthly_Input!C8 | D9: =D8-Monthly_Input!D8 | E9: =E8-Monthly_Input!E8 | F9: =F8-Monthly_Input!F8 | G9: =G8-Monthly_Input!G8 | H9: =H8-Monthly_Input!H8 | I9: =I8-Monthly_Input!I8 | J9: =J8-Monthly_Input!J8 | ... Z9: =Z8-Monthly_Input!Z8
A10: Reconciliation check | B10: flag | C10: =IF(Monthly_Input!C8="","",IF(ABS(C9)<=1,"OK","ERROR")) | D10: =IF(Monthly_Input!D8="","",IF(ABS(D9)<=1,"OK","ERROR")) | E10: =IF(Monthly_Input!E8="","",IF(ABS(E9)<=1,"OK","ERROR")) | F10: =IF(Monthly_Input!F8="","",IF(ABS(F9)<=1,"OK","ERROR")) | G10: =IF(Monthly_Input!G8="","",IF(ABS(G9)<=1,"OK","ERROR")) | H10: =IF(Monthly_Input!H8="","",IF(ABS(H9)<=1,"OK","ERROR")) | I10: =IF(Monthly_Input!I8="","",IF(ABS(I9)<=1,"OK","ERROR")) | J10: =IF(Monthly_Input!J8="","",IF(ABS(J9)<=1,"OK","ERROR")) | ... Z10: =IF(Monthly_Input!Z8="","",IF(ABS(Z9)<=1,"OK","ERROR"))
A11: Operational collection rate (month) | B11: % | C11: =IF(N(Monthly_Input!C15)=0,"",Monthly_Input!C16/Monthly_Input!C15) | D11: =IF(N(Monthly_Input!D15)=0,"",Monthly_Input!D16/Monthly_Input!D15) | E11: =IF(N(Monthly_Input!E15)=0,"",Monthly_Input!E16/Monthly_Input!E15) | F11: =IF(N(Monthly_Input!F15)=0,"",Monthly_Input!F16/Monthly_Input!F15) | G11: =IF(N(Monthly_Input!G15)=0,"",Monthly_Input!G16/Monthly_Input!G15) | H11: =IF(N(Monthly_Input!H15)=0,"",Monthly_Input!H16/Monthly_Input!H15) | I11: =IF(N(Monthly_Input!I15)=0,"",Monthly_Input!I16/Monthly_Input!I15) | J11: =IF(N(Monthly_Input!J15)=0,"",Monthly_Input!J16/Monthly_Input!J15) | ... Z11: =IF(N(Monthly_Input!Z15)=0,"",Monthly_Input!Z16/Monthly_Input!Z15)
A12: Operational collection rate (trailing 3 months) | B12: % | E12: =IF(SUM(Monthly_Input!C15:E15)=0,"",SUM(Monthly_Input!C16:E16)/SUM(Monthly_Input!C15:E15)) | F12: =IF(SUM(Monthly_Input!D15:F15)=0,"",SUM(Monthly_Input!D16:F16)/SUM(Monthly_Input!D15:F15)) | G12: =IF(SUM(Monthly_Input!E15:G15)=0,"",SUM(Monthly_Input!E16:G16)/SUM(Monthly_Input!E15:G15)) | H12: =IF(SUM(Monthly_Input!F15:H15)=0,"",SUM(Monthly_Input!F16:H16)/SUM(Monthly_Input!F15:H15)) | I12: =IF(SUM(Monthly_Input!G15:I15)=0,"",SUM(Monthly_Input!G16:I16)/SUM(Monthly_Input!G15:I15)) | J12: =IF(SUM(Monthly_Input!H15:J15)=0,"",SUM(Monthly_Input!H16:J16)/SUM(Monthly_Input!H15:J15)) | K12: =IF(SUM(Monthly_Input!I15:K15)=0,"",SUM(Monthly_Input!I16:K16)/SUM(Monthly_Input!I15:K15)) | L12: =IF(SUM(Monthly_Input!J15:L15)=0,"",SUM(Monthly_Input!J16:L16)/SUM(Monthly_Input!J15:L15)) | ... Z12: =IF(SUM(Monthly_Input!X15:Z15)=0,"",SUM(Monthly_Input!X16:Z16)/SUM(Monthly_Input!X15:Z15))
A13: PAR30 | B13: % | C13: =IF(N(Monthly_Input!C8)=0,"",SUM(Monthly_Input!C11:C14)/Monthly_Input!C8) | D13: =IF(N(Monthly_Input!D8)=0,"",SUM(Monthly_Input!D11:D14)/Monthly_Input!D8) | E13: =IF(N(Monthly_Input!E8)=0,"",SUM(Monthly_Input!E11:E14)/Monthly_Input!E8) | F13: =IF(N(Monthly_Input!F8)=0,"",SUM(Monthly_Input!F11:F14)/Monthly_Input!F8) | G13: =IF(N(Monthly_Input!G8)=0,"",SUM(Monthly_Input!G11:G14)/Monthly_Input!G8) | H13: =IF(N(Monthly_Input!H8)=0,"",SUM(Monthly_Input!H11:H14)/Monthly_Input!H8) | I13: =IF(N(Monthly_Input!I8)=0,"",SUM(Monthly_Input!I11:I14)/Monthly_Input!I8) | J13: =IF(N(Monthly_Input!J8)=0,"",SUM(Monthly_Input!J11:J14)/Monthly_Input!J8) | ... Z13: =IF(N(Monthly_Input!Z8)=0,"",SUM(Monthly_Input!Z11:Z14)/Monthly_Input!Z8)
A14: PAR90 | B14: % | C14: =IF(N(Monthly_Input!C8)=0,"",SUM(Monthly_Input!C13:C14)/Monthly_Input!C8) | D14: =IF(N(Monthly_Input!D8)=0,"",SUM(Monthly_Input!D13:D14)/Monthly_Input!D8) | E14: =IF(N(Monthly_Input!E8)=0,"",SUM(Monthly_Input!E13:E14)/Monthly_Input!E8) | F14: =IF(N(Monthly_Input!F8)=0,"",SUM(Monthly_Input!F13:F14)/Monthly_Input!F8) | G14: =IF(N(Monthly_Input!G8)=0,"",SUM(Monthly_Input!G13:G14)/Monthly_Input!G8) | H14: =IF(N(Monthly_Input!H8)=0,"",SUM(Monthly_Input!H13:H14)/Monthly_Input!H8) | I14: =IF(N(Monthly_Input!I8)=0,"",SUM(Monthly_Input!I13:I14)/Monthly_Input!I8) | J14: =IF(N(Monthly_Input!J8)=0,"",SUM(Monthly_Input!J13:J14)/Monthly_Input!J8) | ... Z14: =IF(N(Monthly_Input!Z8)=0,"",SUM(Monthly_Input!Z13:Z14)/Monthly_Input!Z8)
A15: PAR30 lagged 3 months | B15: % | F15: =IF(N(Monthly_Input!C8)=0,"",SUM(Monthly_Input!F11:F14)/Monthly_Input!C8) | G15: =IF(N(Monthly_Input!D8)=0,"",SUM(Monthly_Input!G11:G14)/Monthly_Input!D8) | H15: =IF(N(Monthly_Input!E8)=0,"",SUM(Monthly_Input!H11:H14)/Monthly_Input!E8) | I15: =IF(N(Monthly_Input!F8)=0,"",SUM(Monthly_Input!I11:I14)/Monthly_Input!F8) | J15: =IF(N(Monthly_Input!G8)=0,"",SUM(Monthly_Input!J11:J14)/Monthly_Input!G8) | K15: =IF(N(Monthly_Input!H8)=0,"",SUM(Monthly_Input!K11:K14)/Monthly_Input!H8) | L15: =IF(N(Monthly_Input!I8)=0,"",SUM(Monthly_Input!L11:L14)/Monthly_Input!I8) | M15: =IF(N(Monthly_Input!J8)=0,"",SUM(Monthly_Input!M11:M14)/Monthly_Input!J8) | ... Z15: =IF(N(Monthly_Input!W8)=0,"",SUM(Monthly_Input!Z11:Z14)/Monthly_Input!W8)
A16: RaR ratio | B16: % | C16: =IF(OR(Monthly_Input!C21="",N(Monthly_Input!C8)=0),"",Monthly_Input!C21/Monthly_Input!C8) | D16: =IF(OR(Monthly_Input!D21="",N(Monthly_Input!D8)=0),"",Monthly_Input!D21/Monthly_Input!D8) | E16: =IF(OR(Monthly_Input!E21="",N(Monthly_Input!E8)=0),"",Monthly_Input!E21/Monthly_Input!E8) | F16: =IF(OR(Monthly_Input!F21="",N(Monthly_Input!F8)=0),"",Monthly_Input!F21/Monthly_Input!F8) | G16: =IF(OR(Monthly_Input!G21="",N(Monthly_Input!G8)=0),"",Monthly_Input!G21/Monthly_Input!G8) | H16: =IF(OR(Monthly_Input!H21="",N(Monthly_Input!H8)=0),"",Monthly_Input!H21/Monthly_Input!H8) | I16: =IF(OR(Monthly_Input!I21="",N(Monthly_Input!I8)=0),"",Monthly_Input!I21/Monthly_Input!I8) | J16: =IF(OR(Monthly_Input!J21="",N(Monthly_Input!J8)=0),"",Monthly_Input!J21/Monthly_Input!J8) | ... Z16: =IF(OR(Monthly_Input!Z21="",N(Monthly_Input!Z8)=0),"",Monthly_Input!Z21/Monthly_Input!Z8)
A17: Write off ratio (trailing 12 months, annualised) | B17: % | C17: =IF(AVERAGE(Monthly_Input!C8:C8)=0,"",SUM(Monthly_Input!C18:C18)/AVERAGE(Monthly_Input!C8:C8)*12/1) | D17: =IF(AVERAGE(Monthly_Input!C8:D8)=0,"",SUM(Monthly_Input!C18:D18)/AVERAGE(Monthly_Input!C8:D8)*12/2) | E17: =IF(AVERAGE(Monthly_Input!C8:E8)=0,"",SUM(Monthly_Input!C18:E18)/AVERAGE(Monthly_Input!C8:E8)*12/3) | F17: =IF(AVERAGE(Monthly_Input!C8:F8)=0,"",SUM(Monthly_Input!C18:F18)/AVERAGE(Monthly_Input!C8:F8)*12/4) | G17: =IF(AVERAGE(Monthly_Input!C8:G8)=0,"",SUM(Monthly_Input!C18:G18)/AVERAGE(Monthly_Input!C8:G8)*12/5) | H17: =IF(AVERAGE(Monthly_Input!C8:H8)=0,"",SUM(Monthly_Input!C18:H18)/AVERAGE(Monthly_Input!C8:H8)*12/6) | I17: =IF(AVERAGE(Monthly_Input!C8:I8)=0,"",SUM(Monthly_Input!C18:I18)/AVERAGE(Monthly_Input!C8:I8)*12/7) | J17: =IF(AVERAGE(Monthly_Input!C8:J8)=0,"",SUM(Monthly_Input!C18:J18)/AVERAGE(Monthly_Input!C8:J8)*12/8) | K17: =IF(AVERAGE(Monthly_Input!C8:K8)=0,"",SUM(Monthly_Input!C18:K18)/AVERAGE(Monthly_Input!C8:K8)*12/9) | L17: =IF(AVERAGE(Monthly_Input!C8:L8)=0,"",SUM(Monthly_Input!C18:L18)/AVERAGE(Monthly_Input!C8:L8)*12/10) | M17: =IF(AVERAGE(Monthly_Input!C8:M8)=0,"",SUM(Monthly_Input!C18:M18)/AVERAGE(Monthly_Input!C8:M8)*12/11) | N17: =IF(AVERAGE(Monthly_Input!C8:N8)=0,"",SUM(Monthly_Input!C18:N18)/AVERAGE(Monthly_Input!C8:N8)*12/12) | O17: =IF(AVERAGE(Monthly_Input!D8:O8)=0,"",SUM(Monthly_Input!D18:O18)/AVERAGE(Monthly_Input!D8:O8)*12/12) | P17: =IF(AVERAGE(Monthly_Input!E8:P8)=0,"",SUM(Monthly_Input!E18:P18)/AVERAGE(Monthly_Input!E8:P8)*12/12) | Q17: =IF(AVERAGE(Monthly_Input!F8:Q8)=0,"",SUM(Monthly_Input!F18:Q18)/AVERAGE(Monthly_Input!F8:Q8)*12/12) | R17: =IF(AVERAGE(Monthly_Input!G8:R8)=0,"",SUM(Monthly_Input!G18:R18)/AVERAGE(Monthly_Input!G8:R8)*12/12) | S17: =IF(AVERAGE(Monthly_Input!H8:S8)=0,"",SUM(Monthly_Input!H18:S18)/AVERAGE(Monthly_Input!H8:S8)*12/12) | T17: =IF(AVERAGE(Monthly_Input!I8:T8)=0,"",SUM(Monthly_Input!I18:T18)/AVERAGE(Monthly_Input!I8:T8)*12/12) | U17: =IF(AVERAGE(Monthly_Input!J8:U8)=0,"",SUM(Monthly_Input!J18:U18)/AVERAGE(Monthly_Input!J8:U8)*12/12) | ... Z17: =IF(AVERAGE(Monthly_Input!O8:Z8)=0,"",SUM(Monthly_Input!O18:Z18)/AVERAGE(Monthly_Input!O8:Z8)*12/12)
A18: Recovery rate (trailing 12 months) | B18: % | C18: =IF(SUM(Monthly_Input!C18:C18)=0,"",SUM(Monthly_Input!C19:C19)/SUM(Monthly_Input!C18:C18)) | D18: =IF(SUM(Monthly_Input!C18:D18)=0,"",SUM(Monthly_Input!C19:D19)/SUM(Monthly_Input!C18:D18)) | E18: =IF(SUM(Monthly_Input!C18:E18)=0,"",SUM(Monthly_Input!C19:E19)/SUM(Monthly_Input!C18:E18)) | F18: =IF(SUM(Monthly_Input!C18:F18)=0,"",SUM(Monthly_Input!C19:F19)/SUM(Monthly_Input!C18:F18)) | G18: =IF(SUM(Monthly_Input!C18:G18)=0,"",SUM(Monthly_Input!C19:G19)/SUM(Monthly_Input!C18:G18)) | H18: =IF(SUM(Monthly_Input!C18:H18)=0,"",SUM(Monthly_Input!C19:H19)/SUM(Monthly_Input!C18:H18)) | I18: =IF(SUM(Monthly_Input!C18:I18)=0,"",SUM(Monthly_Input!C19:I19)/SUM(Monthly_Input!C18:I18)) | J18: =IF(SUM(Monthly_Input!C18:J18)=0,"",SUM(Monthly_Input!C19:J19)/SUM(Monthly_Input!C18:J18)) | K18: =IF(SUM(Monthly_Input!C18:K18)=0,"",SUM(Monthly_Input!C19:K19)/SUM(Monthly_Input!C18:K18)) | L18: =IF(SUM(Monthly_Input!C18:L18)=0,"",SUM(Monthly_Input!C19:L19)/SUM(Monthly_Input!C18:L18)) | M18: =IF(SUM(Monthly_Input!C18:M18)=0,"",SUM(Monthly_Input!C19:M19)/SUM(Monthly_Input!C18:M18)) | N18: =IF(SUM(Monthly_Input!C18:N18)=0,"",SUM(Monthly_Input!C19:N19)/SUM(Monthly_Input!C18:N18)) | O18: =IF(SUM(Monthly_Input!D18:O18)=0,"",SUM(Monthly_Input!D19:O19)/SUM(Monthly_Input!D18:O18)) | P18: =IF(SUM(Monthly_Input!E18:P18)=0,"",SUM(Monthly_Input!E19:P19)/SUM(Monthly_Input!E18:P18)) | Q18: =IF(SUM(Monthly_Input!F18:Q18)=0,"",SUM(Monthly_Input!F19:Q19)/SUM(Monthly_Input!F18:Q18)) | R18: =IF(SUM(Monthly_Input!G18:R18)=0,"",SUM(Monthly_Input!G19:R19)/SUM(Monthly_Input!G18:R18)) | S18: =IF(SUM(Monthly_Input!H18:S18)=0,"",SUM(Monthly_Input!H19:S19)/SUM(Monthly_Input!H18:S18)) | T18: =IF(SUM(Monthly_Input!I18:T18)=0,"",SUM(Monthly_Input!I19:T19)/SUM(Monthly_Input!I18:T18)) | U18: =IF(SUM(Monthly_Input!J18:U18)=0,"",SUM(Monthly_Input!J19:U19)/SUM(Monthly_Input!J18:U18)) | ... Z18: =IF(SUM(Monthly_Input!O18:Z18)=0,"",SUM(Monthly_Input!O19:Z19)/SUM(Monthly_Input!O18:Z18))
A19: Active ratio | B19: % | C19: =IF(OR(Monthly_Input!C22="",N(Monthly_Input!C23)=0),"",Monthly_Input!C22/Monthly_Input!C23) | D19: =IF(OR(Monthly_Input!D22="",N(Monthly_Input!D23)=0),"",Monthly_Input!D22/Monthly_Input!D23) | E19: =IF(OR(Monthly_Input!E22="",N(Monthly_Input!E23)=0),"",Monthly_Input!E22/Monthly_Input!E23) | F19: =IF(OR(Monthly_Input!F22="",N(Monthly_Input!F23)=0),"",Monthly_Input!F22/Monthly_Input!F23) | G19: =IF(OR(Monthly_Input!G22="",N(Monthly_Input!G23)=0),"",Monthly_Input!G22/Monthly_Input!G23) | H19: =IF(OR(Monthly_Input!H22="",N(Monthly_Input!H23)=0),"",Monthly_Input!H22/Monthly_Input!H23) | I19: =IF(OR(Monthly_Input!I22="",N(Monthly_Input!I23)=0),"",Monthly_Input!I22/Monthly_Input!I23) | J19: =IF(OR(Monthly_Input!J22="",N(Monthly_Input!J23)=0),"",Monthly_Input!J22/Monthly_Input!J23) | ... Z19: =IF(OR(Monthly_Input!Z22="",N(Monthly_Input!Z23)=0),"",Monthly_Input!Z22/Monthly_Input!Z23)
A20: Eligible receivables (to 30 DPD) | B20: LCY | C20: =Monthly_Input!C9+Monthly_Input!C10 | D20: =Monthly_Input!D9+Monthly_Input!D10 | E20: =Monthly_Input!E9+Monthly_Input!E10 | F20: =Monthly_Input!F9+Monthly_Input!F10 | G20: =Monthly_Input!G9+Monthly_Input!G10 | H20: =Monthly_Input!H9+Monthly_Input!H10 | I20: =Monthly_Input!I9+Monthly_Input!I10 | J20: =Monthly_Input!J9+Monthly_Input!J10 | ... Z20: =Monthly_Input!Z9+Monthly_Input!Z10
A21: Borrowing base | B21: LCY | C21: =C20*Covenants!$B$12 | D21: =D20*Covenants!$B$12 | E21: =E20*Covenants!$B$12 | F21: =F20*Covenants!$B$12 | G21: =G20*Covenants!$B$12 | H21: =H20*Covenants!$B$12 | I21: =I20*Covenants!$B$12 | J21: =J20*Covenants!$B$12 | ... Z21: =Z20*Covenants!$B$12
A22: Borrowing base headroom | B22: LCY | C22: =C21-N(Monthly_Input!C24) | D22: =D21-N(Monthly_Input!D24) | E22: =E21-N(Monthly_Input!E24) | F22: =F21-N(Monthly_Input!F24) | G22: =G21-N(Monthly_Input!G24) | H22: =H21-N(Monthly_Input!H24) | I22: =I21-N(Monthly_Input!I24) | J22: =J21-N(Monthly_Input!J24) | ... Z22: =Z21-N(Monthly_Input!Z24)

Sheet Vintage
A1: AFRICA ENERGY FINANCE | BOOK 2 | PAYGO SOLAR FINANCE
A2: Cohort repayment against plan
A3: Cumulative collections ÷ instalments due at fixed ages (deposits excluded)
A4: Template T05 | Version 0.9 (pre-release) | Author & ideation: Emmanuel Boujieka Kamga
A6: Tier shown | B6: Tier 2 (example)
A8: Cohort (month of sale) | B8: Collections M3 | C8: Collections M6 | D8: Collections M12 | E8: Collections M18 | F8: Collections M24 | G8: Due M3 | H8: Due M6 | I8: Due M12 | J8: Due M18 | K8: Due M24 | L8: Repayment ratio M3 | M8: Repayment ratio M6 | N8: Repayment ratio M12 | O8: Repayment ratio M18 | P8: Repayment ratio M24
A9: Cohort 01 | B9: 1269302 | C9: 2461017 | D9: 4700071 | E9: 6234914 | G9: 1616038 | H9: 3232075 | I9: 6464150 | J9: 9696225 | L9: =IF(N(G9)=0,"",B9/G9) | M9: =IF(N(H9)=0,"",C9/H9) | N9: =IF(N(I9)=0,"",D9/I9) | O9: =IF(N(J9)=0,"",E9/J9) | P9: =IF(N(K9)=0,"",F9/K9)
A10: Cohort 02 | B10: 1361248 | C10: 2539299 | D10: 4577978 | E10: 6100813 | G10: 1651169 | H10: 3302338 | I10: 6604675 | J10: 9907012 | L10: =IF(N(G10)=0,"",B10/G10) | M10: =IF(N(H10)=0,"",C10/H10) | N10: =IF(N(I10)=0,"",D10/I10) | O10: =IF(N(J10)=0,"",E10/J10) | P10: =IF(N(K10)=0,"",F10/K10)
A11: Cohort 03 | B11: 1259616 | C11: 2387949 | D11: 4174388 | E11: 5845005 | G11: 1545775 | H11: 3091550 | I11: 6183100 | J11: 9274650 | L11: =IF(N(G11)=0,"",B11/G11) | M11: =IF(N(H11)=0,"",C11/H11) | N11: =IF(N(I11)=0,"",D11/I11) | O11: =IF(N(J11)=0,"",E11/J11) | P11: =IF(N(K11)=0,"",F11/K11)
A12: Cohort 04 | B12: 1583676 | C12: 3010345 | D12: 5248696 | E12: 7653815 | G12: 1967350 | H12: 3934700 | I12: 7869400 | J12: 11804100 | L12: =IF(N(G12)=0,"",B12/G12) | M12: =IF(N(H12)=0,"",C12/H12) | N12: =IF(N(I12)=0,"",D12/I12) | O12: =IF(N(J12)=0,"",E12/J12) | P12: =IF(N(K12)=0,"",F12/K12)
A13: Cohort 05 | B13: 1509252 | C13: 2941238 | D13: 5132862 | E13: 6765814 | G13: 1854930 | H13: 3709860 | I13: 7419720 | J13: 11129580 | L13: =IF(N(G13)=0,"",B13/G13) | M13: =IF(N(H13)=0,"",C13/H13) | N13: =IF(N(I13)=0,"",D13/I13) | O13: =IF(N(J13)=0,"",E13/J13) | P13: =IF(N(K13)=0,"",F13/K13)
A14: Cohort 06 | B14: 1572955 | C14: 3078740 | D14: 5608639 | E14: 7822332 | G14: 1974376 | H14: 3948753 | I14: 7897505 | J14: 11846258 | L14: =IF(N(G14)=0,"",B14/G14) | M14: =IF(N(H14)=0,"",C14/H14) | N14: =IF(N(I14)=0,"",D14/I14) | O14: =IF(N(J14)=0,"",E14/J14) | P14: =IF(N(K14)=0,"",F14/K14)
A15: Cohort 07 | B15: 1685997 | C15: 3071153 | D15: 5543835 | G15: 2002481 | H15: 4004962 | I15: 8009925 | L15: =IF(N(G15)=0,"",B15/G15) | M15: =IF(N(H15)=0,"",C15/H15) | N15: =IF(N(I15)=0,"",D15/I15) | O15: =IF(N(J15)=0,"",E15/J15) | P15: =IF(N(K15)=0,"",F15/K15)
A16: Cohort 08 | B16: 1879779 | C16: 3687208 | D16: 6517936 | G16: 2367846 | H16: 4735692 | I16: 9471385 | L16: =IF(N(G16)=0,"",B16/G16) | M16: =IF(N(H16)=0,"",C16/H16) | N16: =IF(N(I16)=0,"",D16/I16) | O16: =IF(N(J16)=0,"",E16/J16) | P16: =IF(N(K16)=0,"",F16/K16)
A17: Cohort 09 | B17: 2090885 | C17: 3842779 | D17: 6889050 | G17: 2494319 | H17: 4988638 | I17: 9977275 | L17: =IF(N(G17)=0,"",B17/G17) | M17: =IF(N(H17)=0,"",C17/H17) | N17: =IF(N(I17)=0,"",D17/I17) | O17: =IF(N(J17)=0,"",E17/J17) | P17: =IF(N(K17)=0,"",F17/K17)
A18: Cohort 10 | B18: 2220937 | C18: 3952852 | D18: 7375792 | G18: 2691054 | H18: 5382108 | I18: 10764215 | L18: =IF(N(G18)=0,"",B18/G18) | M18: =IF(N(H18)=0,"",C18/H18) | N18: =IF(N(I18)=0,"",D18/I18) | O18: =IF(N(J18)=0,"",E18/J18) | P18: =IF(N(K18)=0,"",F18/K18)
A19: Cohort 11 | B19: 2227486 | C19: 4487139 | D19: 7778595 | G19: 2782395 | H19: 5564790 | I19: 11129580 | L19: =IF(N(G19)=0,"",B19/G19) | M19: =IF(N(H19)=0,"",C19/H19) | N19: =IF(N(I19)=0,"",D19/I19) | O19: =IF(N(J19)=0,"",E19/J19) | P19: =IF(N(K19)=0,"",F19/K19)
A20: Cohort 12 | B20: 2169853 | C20: 3992495 | D20: 7566065 | G20: 2662949 | H20: 5325898 | I20: 10651795 | L20: =IF(N(G20)=0,"",B20/G20) | M20: =IF(N(H20)=0,"",C20/H20) | N20: =IF(N(I20)=0,"",D20/I20) | O20: =IF(N(J20)=0,"",E20/J20) | P20: =IF(N(K20)=0,"",F20/K20)
A21: Cohort 13 | B21: 2456167 | C21: 4728542 | G21: 3042366 | H21: 6084732 | L21: =IF(N(G21)=0,"",B21/G21) | M21: =IF(N(H21)=0,"",C21/H21) | N21: =IF(N(I21)=0,"",D21/I21) | O21: =IF(N(J21)=0,"",E21/J21) | P21: =IF(N(K21)=0,"",F21/K21)
A22: Cohort 14 | B22: 2538900 | C22: 4708371 | G22: 3042366 | H22: 6084732 | L22: =IF(N(G22)=0,"",B22/G22) | M22: =IF(N(H22)=0,"",C22/H22) | N22: =IF(N(I22)=0,"",D22/I22) | O22: =IF(N(J22)=0,"",E22/J22) | P22: =IF(N(K22)=0,"",F22/K22)
A23: Cohort 15 | B23: 2651819 | C23: 4951670 | G23: 3246128 | H23: 6492255 | L23: =IF(N(G23)=0,"",B23/G23) | M23: =IF(N(H23)=0,"",C23/H23) | N23: =IF(N(I23)=0,"",D23/I23) | O23: =IF(N(J23)=0,"",E23/J23) | P23: =IF(N(K23)=0,"",F23/K23)
A24: Cohort 16 | B24: 2562093 | C24: 4879779 | G24: 3168839 | H24: 6337678 | L24: =IF(N(G24)=0,"",B24/G24) | M24: =IF(N(H24)=0,"",C24/H24) | N24: =IF(N(I24)=0,"",D24/I24) | O24: =IF(N(J24)=0,"",E24/J24) | P24: =IF(N(K24)=0,"",F24/K24)
A25: Cohort 17 | B25: 2520450 | C25: 4724605 | G25: 3126681 | H25: 6253362 | L25: =IF(N(G25)=0,"",B25/G25) | M25: =IF(N(H25)=0,"",C25/H25) | N25: =IF(N(I25)=0,"",D25/I25) | O25: =IF(N(J25)=0,"",E25/J25) | P25: =IF(N(K25)=0,"",F25/K25)
A26: Cohort 18 | B26: 3001007 | C26: 5469885 | G26: 3604466 | H26: 7208932 | L26: =IF(N(G26)=0,"",B26/G26) | M26: =IF(N(H26)=0,"",C26/H26) | N26: =IF(N(I26)=0,"",D26/I26) | O26: =IF(N(J26)=0,"",E26/J26) | P26: =IF(N(K26)=0,"",F26/K26)
A28: Average observed | L28: =IFERROR(AVERAGE(L9:L26),"") | M28: =IFERROR(AVERAGE(M9:M26),"") | N28: =IFERROR(AVERAGE(N9:N26),"") | O28: =IFERROR(AVERAGE(O9:O26),"") | P28: =IFERROR(AVERAGE(P9:P26),"")
A29: Plan | L29: 0.835 | M29: 0.803 | N29: 0.745 | O29: 0.692 | P29: 0.644
A30: Gap (points) | L30: =IF(L28="","",L28-L29) | M30: =IF(M28="","",M28-M29) | N30: =IF(N28="","",N28-N29) | O30: =IF(O28="","",O28-O29) | P30: =IF(P28="","",P28-P29)
A32: Example: Tier 2 cohorts of the synthetic SolaraPay history (fictional); plan curve from the management plan. Ages beyond the history are left blank, never filled with a proxy. The cohort repayment ratio is monthly and is not a PERFORM calculation.

Sheet PERFORM_2026
A1: AFRICA ENERGY FINANCE | BOOK 2 | PAYGO SOLAR FINANCE
A2: PAYGo PERFORM 2026 KPIs
A3: Company reported on contract data; numerators and denominators by tier
A4: Template T05 | Version 0.9 (pre-release) | Author & ideation: Emmanuel Boujieka Kamga
A6: Company reported, computed on contract data under the GOGLA PAYGo PERFORM KPIs Technical Guide (June 2026): deposits, prepayments, penalties, fees and subsidies excluded; daily normalised; cohort and portfolio results built by summing contract numerators and denominators. This report does not compute them from monthly data.
A8: Reporting date
A10: KPI and line | C10: Tier 1 | D10: Tier 2 | E10: Tier 3 | F10: Tier 4 | G10: Tier 5 | H10: Portfolio | I10: Comment
A11: RR PvP (repayment rate, paid versus plan) | I11: Time series
A12: Numerator | H12: =SUM(C12:G12) | I12: Payments applied to due instalments to date
A13: Denominator | H13: =SUM(C13:G13) | I13: instalments due to date
A14: Result | C14: =IF(N(C13)=0,"not provided",C12/C13) | D14: =IF(N(D13)=0,"not provided",D12/D13) | E14: =IF(N(E13)=0,"not provided",E12/E13) | F14: =IF(N(F13)=0,"not provided",F12/F13) | G14: =IF(N(G13)=0,"not provided",G12/G13) | H14: =IF(N(H13)=0,"not provided",H12/H13)
A16: RR PvFin (repayment rate, paid versus financed) | I16: Time series
A17: Numerator | H17: =SUM(C17:G17) | I17: Payments applied to due instalments to date
A18: Denominator | H18: =SUM(C18:G18) | I18: total amount financed
A19: Result | C19: =IF(N(C18)=0,"not provided",C17/C18) | D19: =IF(N(D18)=0,"not provided",D17/D18) | E19: =IF(N(E18)=0,"not provided",E17/E18) | F19: =IF(N(F18)=0,"not provided",F17/F18) | G19: =IF(N(G18)=0,"not provided",G17/G18) | H19: =IF(N(H18)=0,"not provided",H17/H18)
A21: RR PvP at 90 days | I21: Cohort milestone
A22: Numerator | H22: =SUM(C22:G22) | I22: Payments applied to instalments due by day 90
A23: Denominator | H23: =SUM(C23:G23) | I23: instalments due by day 90
A24: Result | C24: =IF(N(C23)=0,"not provided",C22/C23) | D24: =IF(N(D23)=0,"not provided",D22/D23) | E24: =IF(N(E23)=0,"not provided",E22/E23) | F24: =IF(N(F23)=0,"not provided",F22/F23) | G24: =IF(N(G23)=0,"not provided",G22/G23) | H24: =IF(N(H23)=0,"not provided",H22/H23)
A26: RR PvP at 2x term | I26: Cohort outcome
A27: Numerator | H27: =SUM(C27:G27) | I27: Payments applied to due instalments by 2x the term
A28: Denominator | H28: =SUM(C28:G28) | I28: instalments due over 1x the term
A29: Result | C29: =IF(N(C28)=0,"not provided",C27/C28) | D29: =IF(N(D28)=0,"not provided",D27/D28) | E29: =IF(N(E28)=0,"not provided",E27/E28) | F29: =IF(N(F28)=0,"not provided",F27/F28) | G29: =IF(N(G28)=0,"not provided",G27/G28) | H29: =IF(N(H28)=0,"not provided",H27/H28)
A31: OR @2x (ownership rate at 2x term) | I31: Cohort outcome
A32: Numerator | H32: =SUM(C32:G32) | I32: Contracts fully paid by 2x the term
A33: Denominator | H33: =SUM(C33:G33) | I33: contracts that have reached at least 2x
A34: Result | C34: =IF(N(C33)=0,"not provided",C32/C33) | D34: =IF(N(D33)=0,"not provided",D32/D33) | E34: =IF(N(E33)=0,"not provided",E32/E33) | F34: =IF(N(F33)=0,"not provided",F32/F33) | G34: =IF(N(G33)=0,"not provided",G32/G33) | H34: =IF(N(H33)=0,"not provided",H32/H33)
A36: Contracts in the cohorts reported | H36: =SUM(C36:G36)
A37: Check: numerators within denominators (RR PvP, at 90 days, at 2x; ownership) | H37: =IF(SUM(SUMPRODUCT((C12:G12>C13:G13)*1),SUMPRODUCT((C22:G22>C23:G23)*1),SUMPRODUCT((C27:G27>C28:G28)*1),SUMPRODUCT((C32:G32>C33:G33)*1))=0,"OK","ERROR")
A39: Portfolio results add numerators and denominators across tiers, as the standard requires; they are not averages of tier ratios. A collection rate, or days locked or enabled, may not be entered here as a substitute. Cohorts below 100 contracts should be disclosed. Blank inputs show "not provided".
