Workbook

Sheet LISEZMOI
A1: Modèle financier et tarifaire — électricité (Livrable 2, version de structure)
A2: Étude : Le paradoxe des subventions tarifaires en Afrique — Cameroun, République du Congo et pays dotés d'un pacte national de l'énergie (Mission 300).
A4: STATUT DES DONNÉES
A5: • Feuilles « Cameroun » et « Congo » : AUCUNE donnée saisie. Les cellules jaunes sont à renseigner depuis des sources officielles, avec la source en colonne D.
A6: • Feuille « Exemple_fictif » : valeurs INVENTÉES servant uniquement à vérifier les formules. Ne jamais citer ses résultats.
A8: CODE COULEUR
A9: • Texte bleu : saisie / levier de scénario. • Fond jaune : saisie à documenter. • Texte noir : formule. • Texte vert : lien vers une autre feuille.
A11: STRUCTURE (5 modules de la note de cadrage)
A12: Module 1 Coûts et Module 2 Tarifs : sections 1–2 des feuilles pays (coût efficace et tarif moyen par catégorie, écarts).
A13: Module 3 Équité : feuille Equite_H2 (incidence par quintile) + ligne « ménages sociaux exclus du ciblage ».
A14: Module 4 Industrie : indice du tarif HT, effet sur le coût de production, CE.
A15: Module 5 Réforme : section 3 (S0–S3) et section 4 (trajectoire 2027–2035, CTPT).
... A22: • CI et CE sont des estimations exogènes ; leur méthode doit éviter les doubles comptages.

Sheet Synthese
A1: Synthèse comparative (scénario actif de chaque feuille pays)
A2: Liens verts vers les feuilles pays. Pour comparer les scénarios, changer le scénario actif dans chaque feuille pays et relever les résultats.
A4: Indicateur | B4: Unité | C4: Cameroun | D4: Congo | E4: Exemple_fictif
A5: Scénario actif | C5: =Cameroun!$C$39 -> S0 Statu quo | D5: =Congo!$C$39 -> S0 Statu quo | E5: =Exemple_fictif!$C$39 -> S3 Réforme intégrée
A6: Contrôle : somme des parts de ventes (doit = 100 %) | B6: % | C6: =Cameroun!$C$35 -> 0 | D6: =Congo!$C$35 -> 0 | E6: =Exemple_fictif!$C$35 -> 1
A7: Recettes facturées / coût efficace (base) | B7: % | C7: =IFERROR(Cameroun!C71/Cameroun!C72,0) -> 0 | D7: =IFERROR(Congo!C71/Congo!C72,0) -> 0 | E7: =IFERROR(Exemple_fictif!C71/Exemple_fictif!C72,0) -> 0.84350133
A8: Écart de sous-tarification (base) | B8: Mds FCFA | C8: =Cameroun!C74 -> 0 | D8: =Congo!C74 -> 0 | E8: =Exemple_fictif!C74 -> 56.25
A9: Écart de sur-tarification (base) | B9: Mds FCFA | C9: =Cameroun!C75 -> 0 | D9: =Congo!C75 -> 0 | E9: =Exemple_fictif!C75 -> 12
A10: Résultat d'exploitation opérateur (base) | B10: Mds FCFA | C10: =Cameroun!C86 -> 0 | D10: =Congo!C86 -> 0 | E10: =Exemple_fictif!C86 -> -84.3375
A11: Résultat d'exploitation opérateur (2035) | B11: Mds FCFA | C11: =Cameroun!L86 -> 0 | D11: =Congo!L86 -> 0 | E11: =Exemple_fictif!L86 -> -35.93264
A12: Coût d'inefficience opérateur (2035) | B12: Mds FCFA | C12: =Cameroun!L87 -> 0 | D12: =Congo!L87 -> 0 | E12: =Exemple_fictif!L87 -> 22.64086
A13: SB cumulées 2027–2035 | B13: Mds FCFA | C13: =Cameroun!M90 -> 0 | D13: =Congo!M90 -> 0 | E13: =Exemple_fictif!M90 -> 313.69141
A14: DC cumulé 2027–2035 | B14: Mds FCFA | C14: =Cameroun!M91 -> 0 | D14: =Congo!M91 -> 0 | E14: =Exemple_fictif!M91 -> 238.74379
A15: CTPT cumulé 2027–2035 | B15: Mds FCFA | C15: =Cameroun!M94 -> 0 | D15: =Congo!M94 -> 0 | E15: =Exemple_fictif!M94 -> 1357.4352
A16: CTPT 2035 / CTPT base | B16: % | C16: =IFERROR(Cameroun!L94/Cameroun!C94,0) -> 0 | D16: =IFERROR(Congo!L94/Congo!C94,0) -> 0 | E16: =IFERROR(Exemple_fictif!L94/Exemple_fictif!C94,0) -> 0.59353522
A17: Aide sociale due cumulée 2027–2035 | B17: Mds FCFA | C17: =Cameroun!M79 -> 0 | D17: =Congo!M79 -> 0 | E17: =Exemple_fictif!M79 -> 200.18597
A18: Hausse non compensée des ménages sociaux exclus, cumul | B18: Mds FCFA | C18: =Cameroun!M100 -> 0 | D18: =Congo!M100 -> 0 | E18: =Exemple_fictif!M100 -> 60.874062
A19: Indice tarif industriel HT 2035 (base 100) | B19: indice | C19: =Cameroun!L97 -> 0 | D19: =Congo!L97 -> 0 | E19: =Exemple_fictif!L97 -> 85.714286
A20: Effet sur le coût de production industriel 2035 | B20: % coût | C20: =Cameroun!L98 -> 0 | D20: =Congo!L98 -> 0 | E20: =Exemple_fictif!L98 -> -0.021428571

Sheet Cameroun
A1: Modèle tarifaire électricité — Cameroun
A2: Cellules jaunes à renseigner depuis des sources officielles (régulateur, opérateur, ministère des Finances). Citer la source en colonne D.
A3: Unités : énergie en GWh ; tarifs et coûts en FCFA/kWh ; montants en milliards de FCFA constants de l'année de base (termes réels).
A5: 1. HYPOTHÈSES GÉNÉRALES (année de base)
A6: Paramètre | B6: Unité | C6: Valeur | D6: Source / note
A7: Année de base des données | B7: année | D7: Dernière année avec données vérifiées (période d'analyse 2020–2026).
A8: Énergie injectée dans le réseau | B8: GWh
A9: Croissance annuelle de l'énergie injectée | B9: %/an | D9: Hypothèse de demande ; pas d'élasticité-prix dans cette version.
A10: Pertes techniques | B10: % injectée
A11: Pertes commerciales (non techniques) | B11: % injectée
A12: Pertes totales admises par le régulateur | B12: % injectée | D12: Au-delà : coût d'inefficience, non imputé à la politique tarifaire.
A13: Taux de recouvrement des factures | B13: % facturé
A14: Coût marginal de production / achat | B14: FCFA/kWh | D14: Valorise les pertes excédentaires.
A15: Part de l'écart de sous-tarification que l'État s'engage à compenser | B15: % | D15: Selon textes réglementaires / contrat de concession.
A16: Fiabilité de paiement des engagements budgétaires | B16: % versé | D16: Versé / dû ; s'applique aux compensations, aides sociales et raccordements.
A17: Canal de l'aide sociale (1 = tarif social compensé via la facture ; 0 = transfert direct aux ménages) | B17: 1/0
A18: Ménages bénéficiaires de l'aide ciblée | B18: nombre
A19: Coût administratif du ciblage par bénéficiaire | B19: FCFA/an
A20: Erreur d'inclusion (part de l'aide versée à des non-éligibles) | B20: %
A21: Part de la consommation de la tranche sociale couverte par l'aide | B21: % | D21: Les ménages non couverts (erreur d'exclusion) subissent la hausse.
A22: Subvention par nouveau raccordement | B22: FCFA
A23: CI — coûts indirects liés à la dégradation du service (base) | B23: Mds FCFA | D23: Estimation à documenter ; ne pas inclure ce qui figure déjà dans CE.
A24: CE — surcoûts des entreprises (autoproduction, délestages) (base) | B24: Mds FCFA | D24: Estimation à documenter (enquêtes entreprises).
A25: Part de l'électricité dans les coûts de production industriels | B25: %
A27: 2. CATÉGORIES TARIFAIRES (année de base)
A28: Catégorie | B28: Sociale (1/0) | C28: Part des ventes | D28: Tarif moyen | E28: Coût efficace | F28: Ventes | G28: Recettes | H28: Coût de desserte | I28: Écart tarif–coût | J28: Écart / coût
C29: % ventes | D29: FCFA/kWh | E29: FCFA/kWh | F29: GWh | G29: Mds FCFA | H29: Mds FCFA | I29: Mds FCFA | J29: %
A30: Ménages BT — tranche sociale | B30: 1 | F30: =$C$8*(1-$C$10-$C$11)*C30 -> 0 | G30: =F30*D30/1000 -> 0 | H30: =F30*E30/1000 -> 0 | I30: =G30-H30 -> 0 | J30: =IFERROR(D30/E30-1,0) -> 0
A31: Ménages BT — autres tranches | B31: 0 | F31: =$C$8*(1-$C$10-$C$11)*C31 -> 0 | G31: =F31*D31/1000 -> 0 | H31: =F31*E31/1000 -> 0 | I31: =G31-H31 -> 0 | J31: =IFERROR(D31/E31-1,0) -> 0
A32: Professionnels BT | B32: 0 | F32: =$C$8*(1-$C$10-$C$11)*C32 -> 0 | G32: =F32*D32/1000 -> 0 | H32: =F32*E32/1000 -> 0 | I32: =G32-H32 -> 0 | J32: =IFERROR(D32/E32-1,0) -> 0
A33: Moyenne tension (MT) | B33: 0 | F33: =$C$8*(1-$C$10-$C$11)*C33 -> 0 | G33: =F33*D33/1000 -> 0 | H33: =F33*E33/1000 -> 0 | I33: =G33-H33 -> 0 | J33: =IFERROR(D33/E33-1,0) -> 0
A34: Haute tension — industrie (HT) | B34: 0 | F34: =$C$8*(1-$C$10-$C$11)*C34 -> 0 | G34: =F34*D34/1000 -> 0 | H34: =F34*E34/1000 -> 0 | I34: =G34-H34 -> 0 | J34: =IFERROR(D34/E34-1,0) -> 0
A35: Total / contrôle (la somme des parts doit faire 100 %) | C35: =SUM(C30:C34) -> 0 | F35: =SUM(F30:F34) -> 0 | G35: =SUM(G30:G34) -> 0 | H35: =SUM(H30:H34) -> 0 | I35: =SUM(I30:I34) -> 0 | J35: =IFERROR(G35/H35-1,0) -> 0
A36: Avertissement : un écart positif n'est une subvention croisée que si le coût efficace par catégorie est établi par une étude d'allocation des coûts (tension, pointe, pertes). Sinon, c'est un simple écart non démontré.
A38: 3. SCÉNARIOS DE RÉFORME (paramètres atteints en 2035, trajectoire linéaire)
A39: Scénario actif (choisir dans la liste) | C39: S0 Statu quo
A40: Paramètre | B40: Unité | C40: S0 Statu quo | D40: S1 Tarifs aux coûts | E40: S2 Aides ciblées | F40: S3 Réforme intégrée | G40: Actif
A41: Résorption de l'écart — catégories sous-tarifées non sociales | B41: fraction | C41: 0 | D41: 1 | E41: 1 | F41: 1 | G41: =INDEX(C41:F41,MATCH($C$39,$C$40:$F$40,0)) -> 0
A42: Résorption de l'écart — tranche sociale | B42: fraction | C42: 0 | D42: 1 | E42: 1 | F42: 1 | G42: =INDEX(C42:F42,MATCH($C$39,$C$40:$F$40,0)) -> 0
A43: Résorption de l'écart — catégories sur-tarifées | B43: fraction | C43: 0 | D43: 1 | E43: 1 | F43: 1 | G43: =INDEX(C43:F43,MATCH($C$39,$C$40:$F$40,0)) -> 0
A44: Aide sociale ciblée active | B44: 1/0 | C44: 0 | D44: 0 | E44: 1 | F44: 1 | G44: =INDEX(C44:F44,MATCH($C$39,$C$40:$F$40,0)) -> 0
A45: Pertes techniques en 2035 | B45: % injectée | C45: =$C$10 -> 0 | D45: =$C$10 -> 0 | E45: =$C$10 -> 0 | G45: =INDEX(C45:F45,MATCH($C$39,$C$40:$F$40,0)) -> 0
A46: Pertes commerciales en 2035 | B46: % injectée | C46: =$C$11 -> 0 | D46: =$C$11 -> 0 | E46: =$C$11 -> 0 | G46: =INDEX(C46:F46,MATCH($C$39,$C$40:$F$40,0)) -> 0
A47: Recouvrement en 2035 | B47: % facturé | C47: =$C$13 -> 0 | D47: =$C$13 -> 0 | E47: =$C$13 -> 0 | G47: =INDEX(C47:F47,MATCH($C$39,$C$40:$F$40,0)) -> 0
A48: Raccordements subventionnés par an | B48: nombre | G48: =INDEX(C48:F48,MATCH($C$39,$C$40:$F$40,0)) -> 0
A49: Réduction de CI atteinte en 2035 | B49: % | C49: 0 | D49: 0 | E49: 0 | G49: =INDEX(C49:F49,MATCH($C$39,$C$40:$F$40,0)) -> 0
A50: Réduction de CE atteinte en 2035 | B50: % | C50: 0 | D50: 0 | E50: 0 | G50: =INDEX(C50:F50,MATCH($C$39,$C$40:$F$40,0)) -> 0
A51: Les valeurs 0/1 de résorption et d'aide définissent les scénarios ; elles sont modifiables (ex. S3 : ne résorber que les écarts sans justification de coût). Pertes et recouvrement de S0–S2 = niveau de base (aucune amélioration supposée).
A53: 4. TRAJECTOIRE 2027–2035 (scénario actif)
A54: Indicateur | B54: Unité | C54: Base | D54: 2027 | E54: 2028 | F54: 2029 | G54: 2030 | H54: 2031 | I54: 2032 | J54: 2033 | K54: 2034 | L54: 2035 | M54: Cumul 2027–35
A55: Avancement de la réforme | B55: fraction | C55: =0/9 -> 0 | D55: =1/9 -> 0.11111111 | E55: =2/9 -> 0.22222222 | F55: =3/9 -> 0.33333333 | G55: =4/9 -> 0.44444444 | H55: =5/9 -> 0.55555556 | I55: =6/9 -> 0.66666667 | J55: =7/9 -> 0.77777778 | K55: =8/9 -> 0.88888889 | L55: =9/9 -> 1
A56: Énergie injectée | B56: GWh | C56: =$C$8 -> 0 | D56: =C56*(1+$C$9) -> 0 | E56: =D56*(1+$C$9) -> 0 | F56: =E56*(1+$C$9) -> 0 | G56: =F56*(1+$C$9) -> 0 | H56: =G56*(1+$C$9) -> 0 | I56: =H56*(1+$C$9) -> 0 | J56: =I56*(1+$C$9) -> 0 | K56: =J56*(1+$C$9) -> 0 | L56: =K56*(1+$C$9) -> 0
A57: Pertes techniques | B57: % | C57: =$C$10+($G$45-$C$10)*C$55 -> 0 | D57: =$C$10+($G$45-$C$10)*D$55 -> 0 | E57: =$C$10+($G$45-$C$10)*E$55 -> 0 | F57: =$C$10+($G$45-$C$10)*F$55 -> 0 | G57: =$C$10+($G$45-$C$10)*G$55 -> 0 | H57: =$C$10+($G$45-$C$10)*H$55 -> 0 | I57: =$C$10+($G$45-$C$10)*I$55 -> 0 | J57: =$C$10+($G$45-$C$10)*J$55 -> 0 | ... L57: =$C$10+($G$45-$C$10)*L$55 -> 0
A58: Pertes commerciales | B58: % | C58: =$C$11+($G$46-$C$11)*C$55 -> 0 | D58: =$C$11+($G$46-$C$11)*D$55 -> 0 | E58: =$C$11+($G$46-$C$11)*E$55 -> 0 | F58: =$C$11+($G$46-$C$11)*F$55 -> 0 | G58: =$C$11+($G$46-$C$11)*G$55 -> 0 | H58: =$C$11+($G$46-$C$11)*H$55 -> 0 | I58: =$C$11+($G$46-$C$11)*I$55 -> 0 | J58: =$C$11+($G$46-$C$11)*J$55 -> 0 | ... L58: =$C$11+($G$46-$C$11)*L$55 -> 0
A59: Taux de recouvrement | B59: % | C59: =$C$13+($G$47-$C$13)*C$55 -> 0 | D59: =$C$13+($G$47-$C$13)*D$55 -> 0 | E59: =$C$13+($G$47-$C$13)*E$55 -> 0 | F59: =$C$13+($G$47-$C$13)*F$55 -> 0 | G59: =$C$13+($G$47-$C$13)*G$55 -> 0 | H59: =$C$13+($G$47-$C$13)*H$55 -> 0 | I59: =$C$13+($G$47-$C$13)*I$55 -> 0 | J59: =$C$13+($G$47-$C$13)*J$55 -> 0 | ... L59: =$C$13+($G$47-$C$13)*L$55 -> 0
A60: Ventes facturées | B60: GWh | C60: =C56*(1-C57-C58) -> 0 | D60: =D56*(1-D57-D58) -> 0 | E60: =E56*(1-E57-E58) -> 0 | F60: =F56*(1-F57-F58) -> 0 | G60: =G56*(1-G57-G58) -> 0 | H60: =H56*(1-H57-H58) -> 0 | I60: =I56*(1-I57-I58) -> 0 | J60: =J56*(1-J57-J58) -> 0 | ... L60: =L56*(1-L57-L58) -> 0
A61: Tarif — Ménages BT — tranche sociale | B61: FCFA/kWh | C61: =$D$30+($E$30-$D$30)*IF($B$30=1,$G$42,IF($D$30<$E$30,$G$41,$G$43))*C$55 -> 0 | D61: =$D$30+($E$30-$D$30)*IF($B$30=1,$G$42,IF($D$30<$E$30,$G$41,$G$43))*D$55 -> 0 | E61: =$D$30+($E$30-$D$30)*IF($B$30=1,$G$42,IF($D$30<$E$30,$G$41,$G$43))*E$55 -> 0 | F61: =$D$30+($E$30-$D$30)*IF($B$30=1,$G$42,IF($D$30<$E$30,$G$41,$G$43))*F$55 -> 0 | G61: =$D$30+($E$30-$D$30)*IF($B$30=1,$G$42,IF($D$30<$E$30,$G$41,$G$43))*G$55 -> 0 | H61: =$D$30+($E$30-$D$30)*IF($B$30=1,$G$42,IF($D$30<$E$30,$G$41,$G$43))*H$55 -> 0 | I61: =$D$30+($E$30-$D$30)*IF($B$30=1,$G$42,IF($D$30<$E$30,$G$41,$G$43))*I$55 -> 0 | J61: =$D$30+($E$30-$D$30)*IF($B$30=1,$G$42,IF($D$30<$E$30,$G$41,$G$43))*J$55 -> 0 | ... L61: =$D$30+($E$30-$D$30)*IF($B$30=1,$G$42,IF($D$30<$E$30,$G$41,$G$43))*L$55 -> 0
A62: Tarif — Ménages BT — autres tranches | B62: FCFA/kWh | C62: =$D$31+($E$31-$D$31)*IF($B$31=1,$G$42,IF($D$31<$E$31,$G$41,$G$43))*C$55 -> 0 | D62: =$D$31+($E$31-$D$31)*IF($B$31=1,$G$42,IF($D$31<$E$31,$G$41,$G$43))*D$55 -> 0 | E62: =$D$31+($E$31-$D$31)*IF($B$31=1,$G$42,IF($D$31<$E$31,$G$41,$G$43))*E$55 -> 0 | F62: =$D$31+($E$31-$D$31)*IF($B$31=1,$G$42,IF($D$31<$E$31,$G$41,$G$43))*F$55 -> 0 | G62: =$D$31+($E$31-$D$31)*IF($B$31=1,$G$42,IF($D$31<$E$31,$G$41,$G$43))*G$55 -> 0 | H62: =$D$31+($E$31-$D$31)*IF($B$31=1,$G$42,IF($D$31<$E$31,$G$41,$G$43))*H$55 -> 0 | I62: =$D$31+($E$31-$D$31)*IF($B$31=1,$G$42,IF($D$31<$E$31,$G$41,$G$43))*I$55 -> 0 | J62: =$D$31+($E$31-$D$31)*IF($B$31=1,$G$42,IF($D$31<$E$31,$G$41,$G$43))*J$55 -> 0 | ... L62: =$D$31+($E$31-$D$31)*IF($B$31=1,$G$42,IF($D$31<$E$31,$G$41,$G$43))*L$55 -> 0
A63: Tarif — Professionnels BT | B63: FCFA/kWh | C63: =$D$32+($E$32-$D$32)*IF($B$32=1,$G$42,IF($D$32<$E$32,$G$41,$G$43))*C$55 -> 0 | D63: =$D$32+($E$32-$D$32)*IF($B$32=1,$G$42,IF($D$32<$E$32,$G$41,$G$43))*D$55 -> 0 | E63: =$D$32+($E$32-$D$32)*IF($B$32=1,$G$42,IF($D$32<$E$32,$G$41,$G$43))*E$55 -> 0 | F63: =$D$32+($E$32-$D$32)*IF($B$32=1,$G$42,IF($D$32<$E$32,$G$41,$G$43))*F$55 -> 0 | G63: =$D$32+($E$32-$D$32)*IF($B$32=1,$G$42,IF($D$32<$E$32,$G$41,$G$43))*G$55 -> 0 | H63: =$D$32+($E$32-$D$32)*IF($B$32=1,$G$42,IF($D$32<$E$32,$G$41,$G$43))*H$55 -> 0 | I63: =$D$32+($E$32-$D$32)*IF($B$32=1,$G$42,IF($D$32<$E$32,$G$41,$G$43))*I$55 -> 0 | J63: =$D$32+($E$32-$D$32)*IF($B$32=1,$G$42,IF($D$32<$E$32,$G$41,$G$43))*J$55 -> 0 | ... L63: =$D$32+($E$32-$D$32)*IF($B$32=1,$G$42,IF($D$32<$E$32,$G$41,$G$43))*L$55 -> 0
A64: Tarif — Moyenne tension (MT) | B64: FCFA/kWh | C64: =$D$33+($E$33-$D$33)*IF($B$33=1,$G$42,IF($D$33<$E$33,$G$41,$G$43))*C$55 -> 0 | D64: =$D$33+($E$33-$D$33)*IF($B$33=1,$G$42,IF($D$33<$E$33,$G$41,$G$43))*D$55 -> 0 | E64: =$D$33+($E$33-$D$33)*IF($B$33=1,$G$42,IF($D$33<$E$33,$G$41,$G$43))*E$55 -> 0 | F64: =$D$33+($E$33-$D$33)*IF($B$33=1,$G$42,IF($D$33<$E$33,$G$41,$G$43))*F$55 -> 0 | G64: =$D$33+($E$33-$D$33)*IF($B$33=1,$G$42,IF($D$33<$E$33,$G$41,$G$43))*G$55 -> 0 | H64: =$D$33+($E$33-$D$33)*IF($B$33=1,$G$42,IF($D$33<$E$33,$G$41,$G$43))*H$55 -> 0 | I64: =$D$33+($E$33-$D$33)*IF($B$33=1,$G$42,IF($D$33<$E$33,$G$41,$G$43))*I$55 -> 0 | J64: =$D$33+($E$33-$D$33)*IF($B$33=1,$G$42,IF($D$33<$E$33,$G$41,$G$43))*J$55 -> 0 | ... L64: =$D$33+($E$33-$D$33)*IF($B$33=1,$G$42,IF($D$33<$E$33,$G$41,$G$43))*L$55 -> 0
A65: Tarif — Haute tension — industrie (HT) | B65: FCFA/kWh | C65: =$D$34+($E$34-$D$34)*IF($B$34=1,$G$42,IF($D$34<$E$34,$G$41,$G$43))*C$55 -> 0 | D65: =$D$34+($E$34-$D$34)*IF($B$34=1,$G$42,IF($D$34<$E$34,$G$41,$G$43))*D$55 -> 0 | E65: =$D$34+($E$34-$D$34)*IF($B$34=1,$G$42,IF($D$34<$E$34,$G$41,$G$43))*E$55 -> 0 | F65: =$D$34+($E$34-$D$34)*IF($B$34=1,$G$42,IF($D$34<$E$34,$G$41,$G$43))*F$55 -> 0 | G65: =$D$34+($E$34-$D$34)*IF($B$34=1,$G$42,IF($D$34<$E$34,$G$41,$G$43))*G$55 -> 0 | H65: =$D$34+($E$34-$D$34)*IF($B$34=1,$G$42,IF($D$34<$E$34,$G$41,$G$43))*H$55 -> 0 | I65: =$D$34+($E$34-$D$34)*IF($B$34=1,$G$42,IF($D$34<$E$34,$G$41,$G$43))*I$55 -> 0 | J65: =$D$34+($E$34-$D$34)*IF($B$34=1,$G$42,IF($D$34<$E$34,$G$41,$G$43))*J$55 -> 0 | ... L65: =$D$34+($E$34-$D$34)*IF($B$34=1,$G$42,IF($D$34<$E$34,$G$41,$G$43))*L$55 -> 0
A66: Ventes — Ménages BT — tranche sociale | B66: GWh | C66: =C60*$C$30 -> 0 | D66: =D60*$C$30 -> 0 | E66: =E60*$C$30 -> 0 | F66: =F60*$C$30 -> 0 | G66: =G60*$C$30 -> 0 | H66: =H60*$C$30 -> 0 | I66: =I60*$C$30 -> 0 | J66: =J60*$C$30 -> 0 | ... L66: =L60*$C$30 -> 0
A67: Ventes — Ménages BT — autres tranches | B67: GWh | C67: =C60*$C$31 -> 0 | D67: =D60*$C$31 -> 0 | E67: =E60*$C$31 -> 0 | F67: =F60*$C$31 -> 0 | G67: =G60*$C$31 -> 0 | H67: =H60*$C$31 -> 0 | I67: =I60*$C$31 -> 0 | J67: =J60*$C$31 -> 0 | ... L67: =L60*$C$31 -> 0
A68: Ventes — Professionnels BT | B68: GWh | C68: =C60*$C$32 -> 0 | D68: =D60*$C$32 -> 0 | E68: =E60*$C$32 -> 0 | F68: =F60*$C$32 -> 0 | G68: =G60*$C$32 -> 0 | H68: =H60*$C$32 -> 0 | I68: =I60*$C$32 -> 0 | J68: =J60*$C$32 -> 0 | ... L68: =L60*$C$32 -> 0
A69: Ventes — Moyenne tension (MT) | B69: GWh | C69: =C60*$C$33 -> 0 | D69: =D60*$C$33 -> 0 | E69: =E60*$C$33 -> 0 | F69: =F60*$C$33 -> 0 | G69: =G60*$C$33 -> 0 | H69: =H60*$C$33 -> 0 | I69: =I60*$C$33 -> 0 | J69: =J60*$C$33 -> 0 | ... L69: =L60*$C$33 -> 0
A70: Ventes — Haute tension — industrie (HT) | B70: GWh | C70: =C60*$C$34 -> 0 | D70: =D60*$C$34 -> 0 | E70: =E60*$C$34 -> 0 | F70: =F60*$C$34 -> 0 | G70: =G60*$C$34 -> 0 | H70: =H60*$C$34 -> 0 | I70: =I60*$C$34 -> 0 | J70: =J60*$C$34 -> 0 | ... L70: =L60*$C$34 -> 0
A71: Recettes facturées | B71: Mds FCFA | C71: =(C61*C66+C62*C67+C63*C68+C64*C69+C65*C70)/1000 -> 0 | D71: =(D61*D66+D62*D67+D63*D68+D64*D69+D65*D70)/1000 -> 0 | E71: =(E61*E66+E62*E67+E63*E68+E64*E69+E65*E70)/1000 -> 0 | F71: =(F61*F66+F62*F67+F63*F68+F64*F69+F65*F70)/1000 -> 0 | G71: =(G61*G66+G62*G67+G63*G68+G64*G69+G65*G70)/1000 -> 0 | H71: =(H61*H66+H62*H67+H63*H68+H64*H69+H65*H70)/1000 -> 0 | I71: =(I61*I66+I62*I67+I63*I68+I64*I69+I65*I70)/1000 -> 0 | J71: =(J61*J66+J62*J67+J63*J68+J64*J69+J65*J70)/1000 -> 0 | ... L71: =(L61*L66+L62*L67+L63*L68+L64*L69+L65*L70)/1000 -> 0 | M71: =SUM(D71:L71) -> 0
A72: Coût efficace de desserte | B72: Mds FCFA | C72: =($E$30*C66+$E$31*C67+$E$32*C68+$E$33*C69+$E$34*C70)/1000 -> 0 | D72: =($E$30*D66+$E$31*D67+$E$32*D68+$E$33*D69+$E$34*D70)/1000 -> 0 | E72: =($E$30*E66+$E$31*E67+$E$32*E68+$E$33*E69+$E$34*E70)/1000 -> 0 | F72: =($E$30*F66+$E$31*F67+$E$32*F68+$E$33*F69+$E$34*F70)/1000 -> 0 | G72: =($E$30*G66+$E$31*G67+$E$32*G68+$E$33*G69+$E$34*G70)/1000 -> 0 | H72: =($E$30*H66+$E$31*H67+$E$32*H68+$E$33*H69+$E$34*H70)/1000 -> 0 | I72: =($E$30*I66+$E$31*I67+$E$32*I68+$E$33*I69+$E$34*I70)/1000 -> 0 | J72: =($E$30*J66+$E$31*J67+$E$32*J68+$E$33*J69+$E$34*J70)/1000 -> 0 | ... L72: =($E$30*L66+$E$31*L67+$E$32*L68+$E$33*L69+$E$34*L70)/1000 -> 0 | M72: =SUM(D72:L72) -> 0
A73: Coût des pertes au-delà du niveau admis | B73: Mds FCFA | C73: =C56*MAX(0,C57+C58-$C$12)*$C$14/1000 -> 0 | D73: =D56*MAX(0,D57+D58-$C$12)*$C$14/1000 -> 0 | E73: =E56*MAX(0,E57+E58-$C$12)*$C$14/1000 -> 0 | F73: =F56*MAX(0,F57+F58-$C$12)*$C$14/1000 -> 0 | G73: =G56*MAX(0,G57+G58-$C$12)*$C$14/1000 -> 0 | H73: =H56*MAX(0,H57+H58-$C$12)*$C$14/1000 -> 0 | I73: =I56*MAX(0,I57+I58-$C$12)*$C$14/1000 -> 0 | J73: =J56*MAX(0,J57+J58-$C$12)*$C$14/1000 -> 0 | ... L73: =L56*MAX(0,L57+L58-$C$12)*$C$14/1000 -> 0 | M73: =SUM(D73:L73) -> 0
A74: Écart de sous-tarification (Σ coût > tarif) | B74: Mds FCFA | C74: =(MAX(0,$E$30-C61)*C66+MAX(0,$E$31-C62)*C67+MAX(0,$E$32-C63)*C68+MAX(0,$E$33-C64)*C69+MAX(0,$E$34-C65)*C70)/1000 -> 0 | D74: =(MAX(0,$E$30-D61)*D66+MAX(0,$E$31-D62)*D67+MAX(0,$E$32-D63)*D68+MAX(0,$E$33-D64)*D69+MAX(0,$E$34-D65)*D70)/1000 -> 0 | E74: =(MAX(0,$E$30-E61)*E66+MAX(0,$E$31-E62)*E67+MAX(0,$E$32-E63)*E68+MAX(0,$E$33-E64)*E69+MAX(0,$E$34-E65)*E70)/1000 -> 0 | F74: =(MAX(0,$E$30-F61)*F66+MAX(0,$E$31-F62)*F67+MAX(0,$E$32-F63)*F68+MAX(0,$E$33-F64)*F69+MAX(0,$E$34-F65)*F70)/1000 -> 0 | G74: =(MAX(0,$E$30-G61)*G66+MAX(0,$E$31-G62)*G67+MAX(0,$E$32-G63)*G68+MAX(0,$E$33-G64)*G69+MAX(0,$E$34-G65)*G70)/1000 -> 0 | H74: =(MAX(0,$E$30-H61)*H66+MAX(0,$E$31-H62)*H67+MAX(0,$E$32-H63)*H68+MAX(0,$E$33-H64)*H69+MAX(0,$E$34-H65)*H70)/1000 -> 0 | I74: =(MAX(0,$E$30-I61)*I66+MAX(0,$E$31-I62)*I67+MAX(0,$E$32-I63)*I68+MAX(0,$E$33-I64)*I69+MAX(0,$E$34-I65)*I70)/1000 -> 0 | J74: =(MAX(0,$E$30-J61)*J66+MAX(0,$E$31-J62)*J67+MAX(0,$E$32-J63)*J68+MAX(0,$E$33-J64)*J69+MAX(0,$E$34-J65)*J70)/1000 -> 0 | ... L74: =(MAX(0,$E$30-L61)*L66+MAX(0,$E$31-L62)*L67+MAX(0,$E$32-L63)*L68+MAX(0,$E$33-L64)*L69+MAX(0,$E$34-L65)*L70)/1000 -> 0 | M74: =SUM(D74:L74) -> 0
A75: Écart de sur-tarification (Σ tarif > coût) | B75: Mds FCFA | C75: =(MAX(0,C61-$E$30)*C66+MAX(0,C62-$E$31)*C67+MAX(0,C63-$E$32)*C68+MAX(0,C64-$E$33)*C69+MAX(0,C65-$E$34)*C70)/1000 -> 0 | D75: =(MAX(0,D61-$E$30)*D66+MAX(0,D62-$E$31)*D67+MAX(0,D63-$E$32)*D68+MAX(0,D64-$E$33)*D69+MAX(0,D65-$E$34)*D70)/1000 -> 0 | E75: =(MAX(0,E61-$E$30)*E66+MAX(0,E62-$E$31)*E67+MAX(0,E63-$E$32)*E68+MAX(0,E64-$E$33)*E69+MAX(0,E65-$E$34)*E70)/1000 -> 0 | F75: =(MAX(0,F61-$E$30)*F66+MAX(0,F62-$E$31)*F67+MAX(0,F63-$E$32)*F68+MAX(0,F64-$E$33)*F69+MAX(0,F65-$E$34)*F70)/1000 -> 0 | G75: =(MAX(0,G61-$E$30)*G66+MAX(0,G62-$E$31)*G67+MAX(0,G63-$E$32)*G68+MAX(0,G64-$E$33)*G69+MAX(0,G65-$E$34)*G70)/1000 -> 0 | H75: =(MAX(0,H61-$E$30)*H66+MAX(0,H62-$E$31)*H67+MAX(0,H63-$E$32)*H68+MAX(0,H64-$E$33)*H69+MAX(0,H65-$E$34)*H70)/1000 -> 0 | I75: =(MAX(0,I61-$E$30)*I66+MAX(0,I62-$E$31)*I67+MAX(0,I63-$E$32)*I68+MAX(0,I64-$E$33)*I69+MAX(0,I65-$E$34)*I70)/1000 -> 0 | J75: =(MAX(0,J61-$E$30)*J66+MAX(0,J62-$E$31)*J67+MAX(0,J63-$E$32)*J68+MAX(0,J64-$E$33)*J69+MAX(0,J65-$E$34)*J70)/1000 -> 0 | ... L75: =(MAX(0,L61-$E$30)*L66+MAX(0,L62-$E$31)*L67+MAX(0,L63-$E$32)*L68+MAX(0,L64-$E$33)*L69+MAX(0,L65-$E$34)*L70)/1000 -> 0 | M75: =SUM(D75:L75) -> 0
A76: Aide sociale aux éligibles (hausse du tarif social compensée) | B76: Mds FCFA | C76: =$G$44*$C$21*($B$30*MAX(0,C61-$D$30)*C66+$B$31*MAX(0,C62-$D$31)*C67+$B$32*MAX(0,C63-$D$32)*C68+$B$33*MAX(0,C64-$D$33)*C69+$B$34*MAX(0,C65-$D$34)*C70)/1000 -> 0 | D76: =$G$44*$C$21*($B$30*MAX(0,D61-$D$30)*D66+$B$31*MAX(0,D62-$D$31)*D67+$B$32*MAX(0,D63-$D$32)*D68+$B$33*MAX(0,D64-$D$33)*D69+$B$34*MAX(0,D65-$D$34)*D70)/1000 -> 0 | E76: =$G$44*$C$21*($B$30*MAX(0,E61-$D$30)*E66+$B$31*MAX(0,E62-$D$31)*E67+$B$32*MAX(0,E63-$D$32)*E68+$B$33*MAX(0,E64-$D$33)*E69+$B$34*MAX(0,E65-$D$34)*E70)/1000 -> 0 | F76: =$G$44*$C$21*($B$30*MAX(0,F61-$D$30)*F66+$B$31*MAX(0,F62-$D$31)*F67+$B$32*MAX(0,F63-$D$32)*F68+$B$33*MAX(0,F64-$D$33)*F69+$B$34*MAX(0,F65-$D$34)*F70)/1000 -> 0 | G76: =$G$44*$C$21*($B$30*MAX(0,G61-$D$30)*G66+$B$31*MAX(0,G62-$D$31)*G67+$B$32*MAX(0,G63-$D$32)*G68+$B$33*MAX(0,G64-$D$33)*G69+$B$34*MAX(0,G65-$D$34)*G70)/1000 -> 0 | H76: =$G$44*$C$21*($B$30*MAX(0,H61-$D$30)*H66+$B$31*MAX(0,H62-$D$31)*H67+$B$32*MAX(0,H63-$D$32)*H68+$B$33*MAX(0,H64-$D$33)*H69+$B$34*MAX(0,H65-$D$34)*H70)/1000 -> 0 | I76: =$G$44*$C$21*($B$30*MAX(0,I61-$D$30)*I66+$B$31*MAX(0,I62-$D$31)*I67+$B$32*MAX(0,I63-$D$32)*I68+$B$33*MAX(0,I64-$D$33)*I69+$B$34*MAX(0,I65-$D$34)*I70)/1000 -> 0 | J76: =$G$44*$C$21*($B$30*MAX(0,J61-$D$30)*J66+$B$31*MAX(0,J62-$D$31)*J67+$B$32*MAX(0,J63-$D$32)*J68+$B$33*MAX(0,J64-$D$33)*J69+$B$34*MAX(0,J65-$D$34)*J70)/1000 -> 0 | ... L76: =$G$44*$C$21*($B$30*MAX(0,L61-$D$30)*L66+$B$31*MAX(0,L62-$D$31)*L67+$B$32*MAX(0,L63-$D$32)*L68+$B$33*MAX(0,L64-$D$33)*L69+$B$34*MAX(0,L65-$D$34)*L70)/1000 -> 0 | M76: =SUM(D76:L76) -> 0
A77: Fuites (erreur d'inclusion) | B77: Mds FCFA | C77: =IFERROR(C76*$C$20/(1-$C$20),0) -> 0 | D77: =IFERROR(D76*$C$20/(1-$C$20),0) -> 0 | E77: =IFERROR(E76*$C$20/(1-$C$20),0) -> 0 | F77: =IFERROR(F76*$C$20/(1-$C$20),0) -> 0 | G77: =IFERROR(G76*$C$20/(1-$C$20),0) -> 0 | H77: =IFERROR(H76*$C$20/(1-$C$20),0) -> 0 | I77: =IFERROR(I76*$C$20/(1-$C$20),0) -> 0 | J77: =IFERROR(J76*$C$20/(1-$C$20),0) -> 0 | ... L77: =IFERROR(L76*$C$20/(1-$C$20),0) -> 0 | M77: =SUM(D77:L77) -> 0
A78: Coût administratif du ciblage | B78: Mds FCFA | C78: =IF(0=0,0,$G$44*$C$18*$C$19/1000000000) -> 0 | D78: =IF(1=0,0,$G$44*$C$18*$C$19/1000000000) -> 0 | E78: =IF(2=0,0,$G$44*$C$18*$C$19/1000000000) -> 0 | F78: =IF(3=0,0,$G$44*$C$18*$C$19/1000000000) -> 0 | G78: =IF(4=0,0,$G$44*$C$18*$C$19/1000000000) -> 0 | H78: =IF(5=0,0,$G$44*$C$18*$C$19/1000000000) -> 0 | I78: =IF(6=0,0,$G$44*$C$18*$C$19/1000000000) -> 0 | J78: =IF(7=0,0,$G$44*$C$18*$C$19/1000000000) -> 0 | K78: =IF(8=0,0,$G$44*$C$18*$C$19/1000000000) -> 0 | L78: =IF(9=0,0,$G$44*$C$18*$C$19/1000000000) -> 0 | M78: =SUM(D78:L78) -> 0
A79: Aide sociale due (total) | B79: Mds FCFA | C79: =C76+C77+C78 -> 0 | D79: =D76+D77+D78 -> 0 | E79: =E76+E77+E78 -> 0 | F79: =F76+F77+F78 -> 0 | G79: =G76+G77+G78 -> 0 | H79: =H76+H77+H78 -> 0 | I79: =I76+I77+I78 -> 0 | J79: =J76+J77+J78 -> 0 | ... L79: =L76+L77+L78 -> 0 | M79: =SUM(D79:L79) -> 0
A80: Aide sociale versée | B80: Mds FCFA | C80: =C79*$C$16 -> 0 | D80: =D79*$C$16 -> 0 | E80: =E79*$C$16 -> 0 | F80: =F79*$C$16 -> 0 | G80: =G79*$C$16 -> 0 | H80: =H79*$C$16 -> 0 | I80: =I79*$C$16 -> 0 | J80: =J79*$C$16 -> 0 | ... L80: =L79*$C$16 -> 0 | M80: =SUM(D80:L80) -> 0
A81: Compensation tarifaire due à l'opérateur | B81: Mds FCFA | C81: =C74*$C$15 -> 0 | D81: =D74*$C$15 -> 0 | E81: =E74*$C$15 -> 0 | F81: =F74*$C$15 -> 0 | G81: =G74*$C$15 -> 0 | H81: =H74*$C$15 -> 0 | I81: =I74*$C$15 -> 0 | J81: =J74*$C$15 -> 0 | ... L81: =L74*$C$15 -> 0 | M81: =SUM(D81:L81) -> 0
A82: Compensation tarifaire versée | B82: Mds FCFA | C82: =C81*$C$16 -> 0 | D82: =D81*$C$16 -> 0 | E82: =E81*$C$16 -> 0 | F82: =F81*$C$16 -> 0 | G82: =G81*$C$16 -> 0 | H82: =H81*$C$16 -> 0 | I82: =I81*$C$16 -> 0 | J82: =J81*$C$16 -> 0 | ... L82: =L81*$C$16 -> 0 | M82: =SUM(D82:L82) -> 0
A83: Subventions au raccordement versées | B83: Mds FCFA | C83: =IF(0=0,0,$G$48*$C$22/1000000000*$C$16) -> 0 | D83: =IF(1=0,0,$G$48*$C$22/1000000000*$C$16) -> 0 | E83: =IF(2=0,0,$G$48*$C$22/1000000000*$C$16) -> 0 | F83: =IF(3=0,0,$G$48*$C$22/1000000000*$C$16) -> 0 | G83: =IF(4=0,0,$G$48*$C$22/1000000000*$C$16) -> 0 | H83: =IF(5=0,0,$G$48*$C$22/1000000000*$C$16) -> 0 | I83: =IF(6=0,0,$G$48*$C$22/1000000000*$C$16) -> 0 | J83: =IF(7=0,0,$G$48*$C$22/1000000000*$C$16) -> 0 | K83: =IF(8=0,0,$G$48*$C$22/1000000000*$C$16) -> 0 | L83: =IF(9=0,0,$G$48*$C$22/1000000000*$C$16) -> 0 | M83: =SUM(D83:L83) -> 0
A84: Part de l'aide transitant par la facture | B84: Mds FCFA | C84: =(C76+C77)*$C$17 -> 0 | D84: =(D76+D77)*$C$17 -> 0 | E84: =(E76+E77)*$C$17 -> 0 | F84: =(F76+F77)*$C$17 -> 0 | G84: =(G76+G77)*$C$17 -> 0 | H84: =(H76+H77)*$C$17 -> 0 | I84: =(I76+I77)*$C$17 -> 0 | J84: =(J76+J77)*$C$17 -> 0 | ... L84: =(L76+L77)*$C$17 -> 0 | M84: =SUM(D84:L84) -> 0
A85: Recettes encaissées par l'opérateur (hors compensations) | B85: Mds FCFA | C85: =(C71-C84)*C59+C84*$C$16 -> 0 | D85: =(D71-D84)*D59+D84*$C$16 -> 0 | E85: =(E71-E84)*E59+E84*$C$16 -> 0 | F85: =(F71-F84)*F59+F84*$C$16 -> 0 | G85: =(G71-G84)*G59+G84*$C$16 -> 0 | H85: =(H71-H84)*H59+H84*$C$16 -> 0 | I85: =(I71-I84)*I59+I84*$C$16 -> 0 | J85: =(J71-J84)*J59+J84*$C$16 -> 0 | ... L85: =(L71-L84)*L59+L84*$C$16 -> 0 | M85: =SUM(D85:L85) -> 0
A86: Résultat d'exploitation de l'opérateur | B86: Mds FCFA | C86: =C85+C82-C72-C73 -> 0 | D86: =D85+D82-D72-D73 -> 0 | E86: =E85+E82-E72-E73 -> 0 | F86: =F85+F82-F72-F73 -> 0 | G86: =G85+G82-G72-G73 -> 0 | H86: =H85+H82-H72-H73 -> 0 | I86: =I85+I82-I72-I73 -> 0 | J86: =J85+J82-J72-J73 -> 0 | ... L86: =L85+L82-L72-L73 -> 0 | M86: =SUM(D86:L86) -> 0
A87: dont coût d'inefficience (pertes excédentaires + non-recouvrement) | B87: Mds FCFA | C87: =C73+(C71-C84)*(1-C59) -> 0 | D87: =D73+(D71-D84)*(1-D59) -> 0 | E87: =E73+(E71-E84)*(1-E59) -> 0 | F87: =F73+(F71-F84)*(1-F59) -> 0 | G87: =G73+(G71-G84)*(1-G59) -> 0 | H87: =H73+(H71-H84)*(1-H59) -> 0 | I87: =I73+(I71-I84)*(1-I59) -> 0 | J87: =J73+(J71-J84)*(1-J59) -> 0 | ... L87: =L73+(L71-L84)*(1-L59) -> 0 | M87: =SUM(D87:L87) -> 0
A89: Coût total de la politique tarifaire : CTPT = SB + DC + CI + CE
A90: SB — subventions budgétaires versées | B90: Mds FCFA | C90: =C82+C80+C83 -> 0 | D90: =D82+D80+D83 -> 0 | E90: =E82+E80+E83 -> 0 | F90: =F82+F80+F83 -> 0 | G90: =G82+G80+G83 -> 0 | H90: =H82+H80+H83 -> 0 | I90: =I82+I80+I83 -> 0 | J90: =J82+J80+J83 -> 0 | ... L90: =L82+L80+L83 -> 0 | M90: =SUM(D90:L90) -> 0
A91: DC — déficit de compensation non financé | B91: Mds FCFA | C91: =MAX(0,C74-C82)+(C76+C77)*$C$17*(1-$C$16) -> 0 | D91: =MAX(0,D74-D82)+(D76+D77)*$C$17*(1-$C$16) -> 0 | E91: =MAX(0,E74-E82)+(E76+E77)*$C$17*(1-$C$16) -> 0 | F91: =MAX(0,F74-F82)+(F76+F77)*$C$17*(1-$C$16) -> 0 | G91: =MAX(0,G74-G82)+(G76+G77)*$C$17*(1-$C$16) -> 0 | H91: =MAX(0,H74-H82)+(H76+H77)*$C$17*(1-$C$16) -> 0 | I91: =MAX(0,I74-I82)+(I76+I77)*$C$17*(1-$C$16) -> 0 | J91: =MAX(0,J74-J82)+(J76+J77)*$C$17*(1-$C$16) -> 0 | ... L91: =MAX(0,L74-L82)+(L76+L77)*$C$17*(1-$C$16) -> 0 | M91: =SUM(D91:L91) -> 0
A92: CI — coûts indirects (dégradation du service) | B92: Mds FCFA | C92: =$C$23*(1-$G$49*C$55) -> 0 | D92: =$C$23*(1-$G$49*D$55) -> 0 | E92: =$C$23*(1-$G$49*E$55) -> 0 | F92: =$C$23*(1-$G$49*F$55) -> 0 | G92: =$C$23*(1-$G$49*G$55) -> 0 | H92: =$C$23*(1-$G$49*H$55) -> 0 | I92: =$C$23*(1-$G$49*I$55) -> 0 | J92: =$C$23*(1-$G$49*J$55) -> 0 | ... L92: =$C$23*(1-$G$49*L$55) -> 0 | M92: =SUM(D92:L92) -> 0
A93: CE — surcoûts des entreprises | B93: Mds FCFA | C93: =$C$24*(1-$G$50*C$55) -> 0 | D93: =$C$24*(1-$G$50*D$55) -> 0 | E93: =$C$24*(1-$G$50*E$55) -> 0 | F93: =$C$24*(1-$G$50*F$55) -> 0 | G93: =$C$24*(1-$G$50*G$55) -> 0 | H93: =$C$24*(1-$G$50*H$55) -> 0 | I93: =$C$24*(1-$G$50*I$55) -> 0 | J93: =$C$24*(1-$G$50*J$55) -> 0 | ... L93: =$C$24*(1-$G$50*L$55) -> 0 | M93: =SUM(D93:L93) -> 0
A94: CTPT — coût total de la politique tarifaire | B94: Mds FCFA | C94: =C90+C91+C92+C93 -> 0 | D94: =D90+D91+D92+D93 -> 0 | E94: =E90+E91+E92+E93 -> 0 | F94: =F90+F91+F92+F93 -> 0 | G94: =G90+G91+G92+G93 -> 0 | H94: =H90+H91+H92+H93 -> 0 | I94: =I90+I91+I92+I93 -> 0 | J94: =J90+J91+J92+J93 -> 0 | ... L94: =L90+L91+L92+L93 -> 0 | M94: =SUM(D94:L94) -> 0
A95: Anti-double comptage : DC ne contient que la sous-tarification non compensée et l'aide due non versée. Les pertes excédentaires et le non-recouvrement relèvent de la performance de l'opérateur (ligne « inefficience »), pas du CTPT. CI et CE doivent être estimés sur des périmètres disjoints.
A97: Indice du tarif industriel HT (base = 100) | B97: indice | C97: =IFERROR(C65/$C$65*100,0) -> 0 | D97: =IFERROR(D65/$C$65*100,0) -> 0 | E97: =IFERROR(E65/$C$65*100,0) -> 0 | F97: =IFERROR(F65/$C$65*100,0) -> 0 | G97: =IFERROR(G65/$C$65*100,0) -> 0 | H97: =IFERROR(H65/$C$65*100,0) -> 0 | I97: =IFERROR(I65/$C$65*100,0) -> 0 | J97: =IFERROR(J65/$C$65*100,0) -> 0 | ... L97: =IFERROR(L65/$C$65*100,0) -> 0
A98: Effet sur le coût de production industriel | B98: % coût | C98: =$C$25*(C97/100-1) -> 0 | D98: =$C$25*(D97/100-1) -> 0 | E98: =$C$25*(E97/100-1) -> 0 | F98: =$C$25*(F97/100-1) -> 0 | G98: =$C$25*(G97/100-1) -> 0 | H98: =$C$25*(H97/100-1) -> 0 | I98: =$C$25*(I97/100-1) -> 0 | J98: =$C$25*(J97/100-1) -> 0 | ... L98: =$C$25*(L97/100-1) -> 0
A99: Indice du tarif de la tranche sociale (base = 100) | B99: indice | C99: =IFERROR(C61/$C$61*100,0) -> 0 | D99: =IFERROR(D61/$C$61*100,0) -> 0 | E99: =IFERROR(E61/$C$61*100,0) -> 0 | F99: =IFERROR(F61/$C$61*100,0) -> 0 | G99: =IFERROR(G61/$C$61*100,0) -> 0 | H99: =IFERROR(H61/$C$61*100,0) -> 0 | I99: =IFERROR(I61/$C$61*100,0) -> 0 | J99: =IFERROR(J61/$C$61*100,0) -> 0 | ... L99: =IFERROR(L61/$C$61*100,0) -> 0
A100: Hausse non compensée pour les ménages sociaux exclus du ciblage | B100: Mds FCFA | C100: =(1-$G$44*$C$21)*MAX(0,C61-$D$30)*C66/1000 -> 0 | D100: =(1-$G$44*$C$21)*MAX(0,D61-$D$30)*D66/1000 -> 0 | E100: =(1-$G$44*$C$21)*MAX(0,E61-$D$30)*E66/1000 -> 0 | F100: =(1-$G$44*$C$21)*MAX(0,F61-$D$30)*F66/1000 -> 0 | G100: =(1-$G$44*$C$21)*MAX(0,G61-$D$30)*G66/1000 -> 0 | H100: =(1-$G$44*$C$21)*MAX(0,H61-$D$30)*H66/1000 -> 0 | I100: =(1-$G$44*$C$21)*MAX(0,I61-$D$30)*I66/1000 -> 0 | J100: =(1-$G$44*$C$21)*MAX(0,J61-$D$30)*J66/1000 -> 0 | ... L100: =(1-$G$44*$C$21)*MAX(0,L61-$D$30)*L66/1000 -> 0 | M100: =SUM(D100:L100) -> 0

Sheet Congo
A1: Modèle tarifaire électricité — Congo
A2: Cellules jaunes à renseigner depuis des sources officielles (régulateur, opérateur, ministère des Finances). Citer la source en colonne D.
A3: Unités : énergie en GWh ; tarifs et coûts en FCFA/kWh ; montants en milliards de FCFA constants de l'année de base (termes réels).
A5: 1. HYPOTHÈSES GÉNÉRALES (année de base)
A6: Paramètre | B6: Unité | C6: Valeur | D6: Source / note
A7: Année de base des données | B7: année | D7: Dernière année avec données vérifiées (période d'analyse 2020–2026).
A8: Énergie injectée dans le réseau | B8: GWh
A9: Croissance annuelle de l'énergie injectée | B9: %/an | D9: Hypothèse de demande ; pas d'élasticité-prix dans cette version.
A10: Pertes techniques | B10: % injectée
A11: Pertes commerciales (non techniques) | B11: % injectée
A12: Pertes totales admises par le régulateur | B12: % injectée | D12: Au-delà : coût d'inefficience, non imputé à la politique tarifaire.
A13: Taux de recouvrement des factures | B13: % facturé
A14: Coût marginal de production / achat | B14: FCFA/kWh | D14: Valorise les pertes excédentaires.
A15: Part de l'écart de sous-tarification que l'État s'engage à compenser | B15: % | D15: Selon textes réglementaires / contrat de concession.
A16: Fiabilité de paiement des engagements budgétaires | B16: % versé | D16: Versé / dû ; s'applique aux compensations, aides sociales et raccordements.
A17: Canal de l'aide sociale (1 = tarif social compensé via la facture ; 0 = transfert direct aux ménages) | B17: 1/0
A18: Ménages bénéficiaires de l'aide ciblée | B18: nombre
A19: Coût administratif du ciblage par bénéficiaire | B19: FCFA/an
A20: Erreur d'inclusion (part de l'aide versée à des non-éligibles) | B20: %
A21: Part de la consommation de la tranche sociale couverte par l'aide | B21: % | D21: Les ménages non couverts (erreur d'exclusion) subissent la hausse.
A22: Subvention par nouveau raccordement | B22: FCFA
A23: CI — coûts indirects liés à la dégradation du service (base) | B23: Mds FCFA | D23: Estimation à documenter ; ne pas inclure ce qui figure déjà dans CE.
A24: CE — surcoûts des entreprises (autoproduction, délestages) (base) | B24: Mds FCFA | D24: Estimation à documenter (enquêtes entreprises).
A25: Part de l'électricité dans les coûts de production industriels | B25: %
A27: 2. CATÉGORIES TARIFAIRES (année de base)
A28: Catégorie | B28: Sociale (1/0) | C28: Part des ventes | D28: Tarif moyen | E28: Coût efficace | F28: Ventes | G28: Recettes | H28: Coût de desserte | I28: Écart tarif–coût | J28: Écart / coût
C29: % ventes | D29: FCFA/kWh | E29: FCFA/kWh | F29: GWh | G29: Mds FCFA | H29: Mds FCFA | I29: Mds FCFA | J29: %
A30: Ménages BT — tranche sociale | B30: 1 | F30: =$C$8*(1-$C$10-$C$11)*C30 -> 0 | G30: =F30*D30/1000 -> 0 | H30: =F30*E30/1000 -> 0 | I30: =G30-H30 -> 0 | J30: =IFERROR(D30/E30-1,0) -> 0
A31: Ménages BT — autres tranches | B31: 0 | F31: =$C$8*(1-$C$10-$C$11)*C31 -> 0 | G31: =F31*D31/1000 -> 0 | H31: =F31*E31/1000 -> 0 | I31: =G31-H31 -> 0 | J31: =IFERROR(D31/E31-1,0) -> 0
A32: Professionnels BT | B32: 0 | F32: =$C$8*(1-$C$10-$C$11)*C32 -> 0 | G32: =F32*D32/1000 -> 0 | H32: =F32*E32/1000 -> 0 | I32: =G32-H32 -> 0 | J32: =IFERROR(D32/E32-1,0) -> 0
A33: Moyenne tension (MT) | B33: 0 | F33: =$C$8*(1-$C$10-$C$11)*C33 -> 0 | G33: =F33*D33/1000 -> 0 | H33: =F33*E33/1000 -> 0 | I33: =G33-H33 -> 0 | J33: =IFERROR(D33/E33-1,0) -> 0
A34: Haute tension — industrie (HT) | B34: 0 | F34: =$C$8*(1-$C$10-$C$11)*C34 -> 0 | G34: =F34*D34/1000 -> 0 | H34: =F34*E34/1000 -> 0 | I34: =G34-H34 -> 0 | J34: =IFERROR(D34/E34-1,0) -> 0
A35: Total / contrôle (la somme des parts doit faire 100 %) | C35: =SUM(C30:C34) -> 0 | F35: =SUM(F30:F34) -> 0 | G35: =SUM(G30:G34) -> 0 | H35: =SUM(H30:H34) -> 0 | I35: =SUM(I30:I34) -> 0 | J35: =IFERROR(G35/H35-1,0) -> 0
A36: Avertissement : un écart positif n'est une subvention croisée que si le coût efficace par catégorie est établi par une étude d'allocation des coûts (tension, pointe, pertes). Sinon, c'est un simple écart non démontré.
A38: 3. SCÉNARIOS DE RÉFORME (paramètres atteints en 2035, trajectoire linéaire)
A39: Scénario actif (choisir dans la liste) | C39: S0 Statu quo
A40: Paramètre | B40: Unité | C40: S0 Statu quo | D40: S1 Tarifs aux coûts | E40: S2 Aides ciblées | F40: S3 Réforme intégrée | G40: Actif
A41: Résorption de l'écart — catégories sous-tarifées non sociales | B41: fraction | C41: 0 | D41: 1 | E41: 1 | F41: 1 | G41: =INDEX(C41:F41,MATCH($C$39,$C$40:$F$40,0)) -> 0
A42: Résorption de l'écart — tranche sociale | B42: fraction | C42: 0 | D42: 1 | E42: 1 | F42: 1 | G42: =INDEX(C42:F42,MATCH($C$39,$C$40:$F$40,0)) -> 0
A43: Résorption de l'écart — catégories sur-tarifées | B43: fraction | C43: 0 | D43: 1 | E43: 1 | F43: 1 | G43: =INDEX(C43:F43,MATCH($C$39,$C$40:$F$40,0)) -> 0
A44: Aide sociale ciblée active | B44: 1/0 | C44: 0 | D44: 0 | E44: 1 | F44: 1 | G44: =INDEX(C44:F44,MATCH($C$39,$C$40:$F$40,0)) -> 0
A45: Pertes techniques en 2035 | B45: % injectée | C45: =$C$10 -> 0 | D45: =$C$10 -> 0 | E45: =$C$10 -> 0 | G45: =INDEX(C45:F45,MATCH($C$39,$C$40:$F$40,0)) -> 0
A46: Pertes commerciales en 2035 | B46: % injectée | C46: =$C$11 -> 0 | D46: =$C$11 -> 0 | E46: =$C$11 -> 0 | G46: =INDEX(C46:F46,MATCH($C$39,$C$40:$F$40,0)) -> 0
A47: Recouvrement en 2035 | B47: % facturé | C47: =$C$13 -> 0 | D47: =$C$13 -> 0 | E47: =$C$13 -> 0 | G47: =INDEX(C47:F47,MATCH($C$39,$C$40:$F$40,0)) -> 0
A48: Raccordements subventionnés par an | B48: nombre | G48: =INDEX(C48:F48,MATCH($C$39,$C$40:$F$40,0)) -> 0
A49: Réduction de CI atteinte en 2035 | B49: % | C49: 0 | D49: 0 | E49: 0 | G49: =INDEX(C49:F49,MATCH($C$39,$C$40:$F$40,0)) -> 0
A50: Réduction de CE atteinte en 2035 | B50: % | C50: 0 | D50: 0 | E50: 0 | G50: =INDEX(C50:F50,MATCH($C$39,$C$40:$F$40,0)) -> 0
A51: Les valeurs 0/1 de résorption et d'aide définissent les scénarios ; elles sont modifiables (ex. S3 : ne résorber que les écarts sans justification de coût). Pertes et recouvrement de S0–S2 = niveau de base (aucune amélioration supposée).
A53: 4. TRAJECTOIRE 2027–2035 (scénario actif)
A54: Indicateur | B54: Unité | C54: Base | D54: 2027 | E54: 2028 | F54: 2029 | G54: 2030 | H54: 2031 | I54: 2032 | J54: 2033 | K54: 2034 | L54: 2035 | M54: Cumul 2027–35
A55: Avancement de la réforme | B55: fraction | C55: =0/9 -> 0 | D55: =1/9 -> 0.11111111 | E55: =2/9 -> 0.22222222 | F55: =3/9 -> 0.33333333 | G55: =4/9 -> 0.44444444 | H55: =5/9 -> 0.55555556 | I55: =6/9 -> 0.66666667 | J55: =7/9 -> 0.77777778 | K55: =8/9 -> 0.88888889 | L55: =9/9 -> 1
A56: Énergie injectée | B56: GWh | C56: =$C$8 -> 0 | D56: =C56*(1+$C$9) -> 0 | E56: =D56*(1+$C$9) -> 0 | F56: =E56*(1+$C$9) -> 0 | G56: =F56*(1+$C$9) -> 0 | H56: =G56*(1+$C$9) -> 0 | I56: =H56*(1+$C$9) -> 0 | J56: =I56*(1+$C$9) -> 0 | K56: =J56*(1+$C$9) -> 0 | L56: =K56*(1+$C$9) -> 0
A57: Pertes techniques | B57: % | C57: =$C$10+($G$45-$C$10)*C$55 -> 0 | D57: =$C$10+($G$45-$C$10)*D$55 -> 0 | E57: =$C$10+($G$45-$C$10)*E$55 -> 0 | F57: =$C$10+($G$45-$C$10)*F$55 -> 0 | G57: =$C$10+($G$45-$C$10)*G$55 -> 0 | H57: =$C$10+($G$45-$C$10)*H$55 -> 0 | I57: =$C$10+($G$45-$C$10)*I$55 -> 0 | J57: =$C$10+($G$45-$C$10)*J$55 -> 0 | ... L57: =$C$10+($G$45-$C$10)*L$55 -> 0
A58: Pertes commerciales | B58: % | C58: =$C$11+($G$46-$C$11)*C$55 -> 0 | D58: =$C$11+($G$46-$C$11)*D$55 -> 0 | E58: =$C$11+($G$46-$C$11)*E$55 -> 0 | F58: =$C$11+($G$46-$C$11)*F$55 -> 0 | G58: =$C$11+($G$46-$C$11)*G$55 -> 0 | H58: =$C$11+($G$46-$C$11)*H$55 -> 0 | I58: =$C$11+($G$46-$C$11)*I$55 -> 0 | J58: =$C$11+($G$46-$C$11)*J$55 -> 0 | ... L58: =$C$11+($G$46-$C$11)*L$55 -> 0
A59: Taux de recouvrement | B59: % | C59: =$C$13+($G$47-$C$13)*C$55 -> 0 | D59: =$C$13+($G$47-$C$13)*D$55 -> 0 | E59: =$C$13+($G$47-$C$13)*E$55 -> 0 | F59: =$C$13+($G$47-$C$13)*F$55 -> 0 | G59: =$C$13+($G$47-$C$13)*G$55 -> 0 | H59: =$C$13+($G$47-$C$13)*H$55 -> 0 | I59: =$C$13+($G$47-$C$13)*I$55 -> 0 | J59: =$C$13+($G$47-$C$13)*J$55 -> 0 | ... L59: =$C$13+($G$47-$C$13)*L$55 -> 0
A60: Ventes facturées | B60: GWh | C60: =C56*(1-C57-C58) -> 0 | D60: =D56*(1-D57-D58) -> 0 | E60: =E56*(1-E57-E58) -> 0 | F60: =F56*(1-F57-F58) -> 0 | G60: =G56*(1-G57-G58) -> 0 | H60: =H56*(1-H57-H58) -> 0 | I60: =I56*(1-I57-I58) -> 0 | J60: =J56*(1-J57-J58) -> 0 | ... L60: =L56*(1-L57-L58) -> 0
A61: Tarif — Ménages BT — tranche sociale | B61: FCFA/kWh | C61: =$D$30+($E$30-$D$30)*IF($B$30=1,$G$42,IF($D$30<$E$30,$G$41,$G$43))*C$55 -> 0 | D61: =$D$30+($E$30-$D$30)*IF($B$30=1,$G$42,IF($D$30<$E$30,$G$41,$G$43))*D$55 -> 0 | E61: =$D$30+($E$30-$D$30)*IF($B$30=1,$G$42,IF($D$30<$E$30,$G$41,$G$43))*E$55 -> 0 | F61: =$D$30+($E$30-$D$30)*IF($B$30=1,$G$42,IF($D$30<$E$30,$G$41,$G$43))*F$55 -> 0 | G61: =$D$30+($E$30-$D$30)*IF($B$30=1,$G$42,IF($D$30<$E$30,$G$41,$G$43))*G$55 -> 0 | H61: =$D$30+($E$30-$D$30)*IF($B$30=1,$G$42,IF($D$30<$E$30,$G$41,$G$43))*H$55 -> 0 | I61: =$D$30+($E$30-$D$30)*IF($B$30=1,$G$42,IF($D$30<$E$30,$G$41,$G$43))*I$55 -> 0 | J61: =$D$30+($E$30-$D$30)*IF($B$30=1,$G$42,IF($D$30<$E$30,$G$41,$G$43))*J$55 -> 0 | ... L61: =$D$30+($E$30-$D$30)*IF($B$30=1,$G$42,IF($D$30<$E$30,$G$41,$G$43))*L$55 -> 0
A62: Tarif — Ménages BT — autres tranches | B62: FCFA/kWh | C62: =$D$31+($E$31-$D$31)*IF($B$31=1,$G$42,IF($D$31<$E$31,$G$41,$G$43))*C$55 -> 0 | D62: =$D$31+($E$31-$D$31)*IF($B$31=1,$G$42,IF($D$31<$E$31,$G$41,$G$43))*D$55 -> 0 | E62: =$D$31+($E$31-$D$31)*IF($B$31=1,$G$42,IF($D$31<$E$31,$G$41,$G$43))*E$55 -> 0 | F62: =$D$31+($E$31-$D$31)*IF($B$31=1,$G$42,IF($D$31<$E$31,$G$41,$G$43))*F$55 -> 0 | G62: =$D$31+($E$31-$D$31)*IF($B$31=1,$G$42,IF($D$31<$E$31,$G$41,$G$43))*G$55 -> 0 | H62: =$D$31+($E$31-$D$31)*IF($B$31=1,$G$42,IF($D$31<$E$31,$G$41,$G$43))*H$55 -> 0 | I62: =$D$31+($E$31-$D$31)*IF($B$31=1,$G$42,IF($D$31<$E$31,$G$41,$G$43))*I$55 -> 0 | J62: =$D$31+($E$31-$D$31)*IF($B$31=1,$G$42,IF($D$31<$E$31,$G$41,$G$43))*J$55 -> 0 | ... L62: =$D$31+($E$31-$D$31)*IF($B$31=1,$G$42,IF($D$31<$E$31,$G$41,$G$43))*L$55 -> 0
A63: Tarif — Professionnels BT | B63: FCFA/kWh | C63: =$D$32+($E$32-$D$32)*IF($B$32=1,$G$42,IF($D$32<$E$32,$G$41,$G$43))*C$55 -> 0 | D63: =$D$32+($E$32-$D$32)*IF($B$32=1,$G$42,IF($D$32<$E$32,$G$41,$G$43))*D$55 -> 0 | E63: =$D$32+($E$32-$D$32)*IF($B$32=1,$G$42,IF($D$32<$E$32,$G$41,$G$43))*E$55 -> 0 | F63: =$D$32+($E$32-$D$32)*IF($B$32=1,$G$42,IF($D$32<$E$32,$G$41,$G$43))*F$55 -> 0 | G63: =$D$32+($E$32-$D$32)*IF($B$32=1,$G$42,IF($D$32<$E$32,$G$41,$G$43))*G$55 -> 0 | H63: =$D$32+($E$32-$D$32)*IF($B$32=1,$G$42,IF($D$32<$E$32,$G$41,$G$43))*H$55 -> 0 | I63: =$D$32+($E$32-$D$32)*IF($B$32=1,$G$42,IF($D$32<$E$32,$G$41,$G$43))*I$55 -> 0 | J63: =$D$32+($E$32-$D$32)*IF($B$32=1,$G$42,IF($D$32<$E$32,$G$41,$G$43))*J$55 -> 0 | ... L63: =$D$32+($E$32-$D$32)*IF($B$32=1,$G$42,IF($D$32<$E$32,$G$41,$G$43))*L$55 -> 0
A64: Tarif — Moyenne tension (MT) | B64: FCFA/kWh | C64: =$D$33+($E$33-$D$33)*IF($B$33=1,$G$42,IF($D$33<$E$33,$G$41,$G$43))*C$55 -> 0 | D64: =$D$33+($E$33-$D$33)*IF($B$33=1,$G$42,IF($D$33<$E$33,$G$41,$G$43))*D$55 -> 0 | E64: =$D$33+($E$33-$D$33)*IF($B$33=1,$G$42,IF($D$33<$E$33,$G$41,$G$43))*E$55 -> 0 | F64: =$D$33+($E$33-$D$33)*IF($B$33=1,$G$42,IF($D$33<$E$33,$G$41,$G$43))*F$55 -> 0 | G64: =$D$33+($E$33-$D$33)*IF($B$33=1,$G$42,IF($D$33<$E$33,$G$41,$G$43))*G$55 -> 0 | H64: =$D$33+($E$33-$D$33)*IF($B$33=1,$G$42,IF($D$33<$E$33,$G$41,$G$43))*H$55 -> 0 | I64: =$D$33+($E$33-$D$33)*IF($B$33=1,$G$42,IF($D$33<$E$33,$G$41,$G$43))*I$55 -> 0 | J64: =$D$33+($E$33-$D$33)*IF($B$33=1,$G$42,IF($D$33<$E$33,$G$41,$G$43))*J$55 -> 0 | ... L64: =$D$33+($E$33-$D$33)*IF($B$33=1,$G$42,IF($D$33<$E$33,$G$41,$G$43))*L$55 -> 0
A65: Tarif — Haute tension — industrie (HT) | B65: FCFA/kWh | C65: =$D$34+($E$34-$D$34)*IF($B$34=1,$G$42,IF($D$34<$E$34,$G$41,$G$43))*C$55 -> 0 | D65: =$D$34+($E$34-$D$34)*IF($B$34=1,$G$42,IF($D$34<$E$34,$G$41,$G$43))*D$55 -> 0 | E65: =$D$34+($E$34-$D$34)*IF($B$34=1,$G$42,IF($D$34<$E$34,$G$41,$G$43))*E$55 -> 0 | F65: =$D$34+($E$34-$D$34)*IF($B$34=1,$G$42,IF($D$34<$E$34,$G$41,$G$43))*F$55 -> 0 | G65: =$D$34+($E$34-$D$34)*IF($B$34=1,$G$42,IF($D$34<$E$34,$G$41,$G$43))*G$55 -> 0 | H65: =$D$34+($E$34-$D$34)*IF($B$34=1,$G$42,IF($D$34<$E$34,$G$41,$G$43))*H$55 -> 0 | I65: =$D$34+($E$34-$D$34)*IF($B$34=1,$G$42,IF($D$34<$E$34,$G$41,$G$43))*I$55 -> 0 | J65: =$D$34+($E$34-$D$34)*IF($B$34=1,$G$42,IF($D$34<$E$34,$G$41,$G$43))*J$55 -> 0 | ... L65: =$D$34+($E$34-$D$34)*IF($B$34=1,$G$42,IF($D$34<$E$34,$G$41,$G$43))*L$55 -> 0
A66: Ventes — Ménages BT — tranche sociale | B66: GWh | C66: =C60*$C$30 -> 0 | D66: =D60*$C$30 -> 0 | E66: =E60*$C$30 -> 0 | F66: =F60*$C$30 -> 0 | G66: =G60*$C$30 -> 0 | H66: =H60*$C$30 -> 0 | I66: =I60*$C$30 -> 0 | J66: =J60*$C$30 -> 0 | ... L66: =L60*$C$30 -> 0
A67: Ventes — Ménages BT — autres tranches | B67: GWh | C67: =C60*$C$31 -> 0 | D67: =D60*$C$31 -> 0 | E67: =E60*$C$31 -> 0 | F67: =F60*$C$31 -> 0 | G67: =G60*$C$31 -> 0 | H67: =H60*$C$31 -> 0 | I67: =I60*$C$31 -> 0 | J67: =J60*$C$31 -> 0 | ... L67: =L60*$C$31 -> 0
A68: Ventes — Professionnels BT | B68: GWh | C68: =C60*$C$32 -> 0 | D68: =D60*$C$32 -> 0 | E68: =E60*$C$32 -> 0 | F68: =F60*$C$32 -> 0 | G68: =G60*$C$32 -> 0 | H68: =H60*$C$32 -> 0 | I68: =I60*$C$32 -> 0 | J68: =J60*$C$32 -> 0 | ... L68: =L60*$C$32 -> 0
A69: Ventes — Moyenne tension (MT) | B69: GWh | C69: =C60*$C$33 -> 0 | D69: =D60*$C$33 -> 0 | E69: =E60*$C$33 -> 0 | F69: =F60*$C$33 -> 0 | G69: =G60*$C$33 -> 0 | H69: =H60*$C$33 -> 0 | I69: =I60*$C$33 -> 0 | J69: =J60*$C$33 -> 0 | ... L69: =L60*$C$33 -> 0
A70: Ventes — Haute tension — industrie (HT) | B70: GWh | C70: =C60*$C$34 -> 0 | D70: =D60*$C$34 -> 0 | E70: =E60*$C$34 -> 0 | F70: =F60*$C$34 -> 0 | G70: =G60*$C$34 -> 0 | H70: =H60*$C$34 -> 0 | I70: =I60*$C$34 -> 0 | J70: =J60*$C$34 -> 0 | ... L70: =L60*$C$34 -> 0
A71: Recettes facturées | B71: Mds FCFA | C71: =(C61*C66+C62*C67+C63*C68+C64*C69+C65*C70)/1000 -> 0 | D71: =(D61*D66+D62*D67+D63*D68+D64*D69+D65*D70)/1000 -> 0 | E71: =(E61*E66+E62*E67+E63*E68+E64*E69+E65*E70)/1000 -> 0 | F71: =(F61*F66+F62*F67+F63*F68+F64*F69+F65*F70)/1000 -> 0 | G71: =(G61*G66+G62*G67+G63*G68+G64*G69+G65*G70)/1000 -> 0 | H71: =(H61*H66+H62*H67+H63*H68+H64*H69+H65*H70)/1000 -> 0 | I71: =(I61*I66+I62*I67+I63*I68+I64*I69+I65*I70)/1000 -> 0 | J71: =(J61*J66+J62*J67+J63*J68+J64*J69+J65*J70)/1000 -> 0 | ... L71: =(L61*L66+L62*L67+L63*L68+L64*L69+L65*L70)/1000 -> 0 | M71: =SUM(D71:L71) -> 0
A72: Coût efficace de desserte | B72: Mds FCFA | C72: =($E$30*C66+$E$31*C67+$E$32*C68+$E$33*C69+$E$34*C70)/1000 -> 0 | D72: =($E$30*D66+$E$31*D67+$E$32*D68+$E$33*D69+$E$34*D70)/1000 -> 0 | E72: =($E$30*E66+$E$31*E67+$E$32*E68+$E$33*E69+$E$34*E70)/1000 -> 0 | F72: =($E$30*F66+$E$31*F67+$E$32*F68+$E$33*F69+$E$34*F70)/1000 -> 0 | G72: =($E$30*G66+$E$31*G67+$E$32*G68+$E$33*G69+$E$34*G70)/1000 -> 0 | H72: =($E$30*H66+$E$31*H67+$E$32*H68+$E$33*H69+$E$34*H70)/1000 -> 0 | I72: =($E$30*I66+$E$31*I67+$E$32*I68+$E$33*I69+$E$34*I70)/1000 -> 0 | J72: =($E$30*J66+$E$31*J67+$E$32*J68+$E$33*J69+$E$34*J70)/1000 -> 0 | ... L72: =($E$30*L66+$E$31*L67+$E$32*L68+$E$33*L69+$E$34*L70)/1000 -> 0 | M72: =SUM(D72:L72) -> 0
A73: Coût des pertes au-delà du niveau admis | B73: Mds FCFA | C73: =C56*MAX(0,C57+C58-$C$12)*$C$14/1000 -> 0 | D73: =D56*MAX(0,D57+D58-$C$12)*$C$14/1000 -> 0 | E73: =E56*MAX(0,E57+E58-$C$12)*$C$14/1000 -> 0 | F73: =F56*MAX(0,F57+F58-$C$12)*$C$14/1000 -> 0 | G73: =G56*MAX(0,G57+G58-$C$12)*$C$14/1000 -> 0 | H73: =H56*MAX(0,H57+H58-$C$12)*$C$14/1000 -> 0 | I73: =I56*MAX(0,I57+I58-$C$12)*$C$14/1000 -> 0 | J73: =J56*MAX(0,J57+J58-$C$12)*$C$14/1000 -> 0 | ... L73: =L56*MAX(0,L57+L58-$C$12)*$C$14/1000 -> 0 | M73: =SUM(D73:L73) -> 0
A74: Écart de sous-tarification (Σ coût > tarif) | B74: Mds FCFA | C74: =(MAX(0,$E$30-C61)*C66+MAX(0,$E$31-C62)*C67+MAX(0,$E$32-C63)*C68+MAX(0,$E$33-C64)*C69+MAX(0,$E$34-C65)*C70)/1000 -> 0 | D74: =(MAX(0,$E$30-D61)*D66+MAX(0,$E$31-D62)*D67+MAX(0,$E$32-D63)*D68+MAX(0,$E$33-D64)*D69+MAX(0,$E$34-D65)*D70)/1000 -> 0 | E74: =(MAX(0,$E$30-E61)*E66+MAX(0,$E$31-E62)*E67+MAX(0,$E$32-E63)*E68+MAX(0,$E$33-E64)*E69+MAX(0,$E$34-E65)*E70)/1000 -> 0 | F74: =(MAX(0,$E$30-F61)*F66+MAX(0,$E$31-F62)*F67+MAX(0,$E$32-F63)*F68+MAX(0,$E$33-F64)*F69+MAX(0,$E$34-F65)*F70)/1000 -> 0 | G74: =(MAX(0,$E$30-G61)*G66+MAX(0,$E$31-G62)*G67+MAX(0,$E$32-G63)*G68+MAX(0,$E$33-G64)*G69+MAX(0,$E$34-G65)*G70)/1000 -> 0 | H74: =(MAX(0,$E$30-H61)*H66+MAX(0,$E$31-H62)*H67+MAX(0,$E$32-H63)*H68+MAX(0,$E$33-H64)*H69+MAX(0,$E$34-H65)*H70)/1000 -> 0 | I74: =(MAX(0,$E$30-I61)*I66+MAX(0,$E$31-I62)*I67+MAX(0,$E$32-I63)*I68+MAX(0,$E$33-I64)*I69+MAX(0,$E$34-I65)*I70)/1000 -> 0 | J74: =(MAX(0,$E$30-J61)*J66+MAX(0,$E$31-J62)*J67+MAX(0,$E$32-J63)*J68+MAX(0,$E$33-J64)*J69+MAX(0,$E$34-J65)*J70)/1000 -> 0 | ... L74: =(MAX(0,$E$30-L61)*L66+MAX(0,$E$31-L62)*L67+MAX(0,$E$32-L63)*L68+MAX(0,$E$33-L64)*L69+MAX(0,$E$34-L65)*L70)/1000 -> 0 | M74: =SUM(D74:L74) -> 0
A75: Écart de sur-tarification (Σ tarif > coût) | B75: Mds FCFA | C75: =(MAX(0,C61-$E$30)*C66+MAX(0,C62-$E$31)*C67+MAX(0,C63-$E$32)*C68+MAX(0,C64-$E$33)*C69+MAX(0,C65-$E$34)*C70)/1000 -> 0 | D75: =(MAX(0,D61-$E$30)*D66+MAX(0,D62-$E$31)*D67+MAX(0,D63-$E$32)*D68+MAX(0,D64-$E$33)*D69+MAX(0,D65-$E$34)*D70)/1000 -> 0 | E75: =(MAX(0,E61-$E$30)*E66+MAX(0,E62-$E$31)*E67+MAX(0,E63-$E$32)*E68+MAX(0,E64-$E$33)*E69+MAX(0,E65-$E$34)*E70)/1000 -> 0 | F75: =(MAX(0,F61-$E$30)*F66+MAX(0,F62-$E$31)*F67+MAX(0,F63-$E$32)*F68+MAX(0,F64-$E$33)*F69+MAX(0,F65-$E$34)*F70)/1000 -> 0 | G75: =(MAX(0,G61-$E$30)*G66+MAX(0,G62-$E$31)*G67+MAX(0,G63-$E$32)*G68+MAX(0,G64-$E$33)*G69+MAX(0,G65-$E$34)*G70)/1000 -> 0 | H75: =(MAX(0,H61-$E$30)*H66+MAX(0,H62-$E$31)*H67+MAX(0,H63-$E$32)*H68+MAX(0,H64-$E$33)*H69+MAX(0,H65-$E$34)*H70)/1000 -> 0 | I75: =(MAX(0,I61-$E$30)*I66+MAX(0,I62-$E$31)*I67+MAX(0,I63-$E$32)*I68+MAX(0,I64-$E$33)*I69+MAX(0,I65-$E$34)*I70)/1000 -> 0 | J75: =(MAX(0,J61-$E$30)*J66+MAX(0,J62-$E$31)*J67+MAX(0,J63-$E$32)*J68+MAX(0,J64-$E$33)*J69+MAX(0,J65-$E$34)*J70)/1000 -> 0 | ... L75: =(MAX(0,L61-$E$30)*L66+MAX(0,L62-$E$31)*L67+MAX(0,L63-$E$32)*L68+MAX(0,L64-$E$33)*L69+MAX(0,L65-$E$34)*L70)/1000 -> 0 | M75: =SUM(D75:L75) -> 0
A76: Aide sociale aux éligibles (hausse du tarif social compensée) | B76: Mds FCFA | C76: =$G$44*$C$21*($B$30*MAX(0,C61-$D$30)*C66+$B$31*MAX(0,C62-$D$31)*C67+$B$32*MAX(0,C63-$D$32)*C68+$B$33*MAX(0,C64-$D$33)*C69+$B$34*MAX(0,C65-$D$34)*C70)/1000 -> 0 | D76: =$G$44*$C$21*($B$30*MAX(0,D61-$D$30)*D66+$B$31*MAX(0,D62-$D$31)*D67+$B$32*MAX(0,D63-$D$32)*D68+$B$33*MAX(0,D64-$D$33)*D69+$B$34*MAX(0,D65-$D$34)*D70)/1000 -> 0 | E76: =$G$44*$C$21*($B$30*MAX(0,E61-$D$30)*E66+$B$31*MAX(0,E62-$D$31)*E67+$B$32*MAX(0,E63-$D$32)*E68+$B$33*MAX(0,E64-$D$33)*E69+$B$34*MAX(0,E65-$D$34)*E70)/1000 -> 0 | F76: =$G$44*$C$21*($B$30*MAX(0,F61-$D$30)*F66+$B$31*MAX(0,F62-$D$31)*F67+$B$32*MAX(0,F63-$D$32)*F68+$B$33*MAX(0,F64-$D$33)*F69+$B$34*MAX(0,F65-$D$34)*F70)/1000 -> 0 | G76: =$G$44*$C$21*($B$30*MAX(0,G61-$D$30)*G66+$B$31*MAX(0,G62-$D$31)*G67+$B$32*MAX(0,G63-$D$32)*G68+$B$33*MAX(0,G64-$D$33)*G69+$B$34*MAX(0,G65-$D$34)*G70)/1000 -> 0 | H76: =$G$44*$C$21*($B$30*MAX(0,H61-$D$30)*H66+$B$31*MAX(0,H62-$D$31)*H67+$B$32*MAX(0,H63-$D$32)*H68+$B$33*MAX(0,H64-$D$33)*H69+$B$34*MAX(0,H65-$D$34)*H70)/1000 -> 0 | I76: =$G$44*$C$21*($B$30*MAX(0,I61-$D$30)*I66+$B$31*MAX(0,I62-$D$31)*I67+$B$32*MAX(0,I63-$D$32)*I68+$B$33*MAX(0,I64-$D$33)*I69+$B$34*MAX(0,I65-$D$34)*I70)/1000 -> 0 | J76: =$G$44*$C$21*($B$30*MAX(0,J61-$D$30)*J66+$B$31*MAX(0,J62-$D$31)*J67+$B$32*MAX(0,J63-$D$32)*J68+$B$33*MAX(0,J64-$D$33)*J69+$B$34*MAX(0,J65-$D$34)*J70)/1000 -> 0 | ... L76: =$G$44*$C$21*($B$30*MAX(0,L61-$D$30)*L66+$B$31*MAX(0,L62-$D$31)*L67+$B$32*MAX(0,L63-$D$32)*L68+$B$33*MAX(0,L64-$D$33)*L69+$B$34*MAX(0,L65-$D$34)*L70)/1000 -> 0 | M76: =SUM(D76:L76) -> 0
A77: Fuites (erreur d'inclusion) | B77: Mds FCFA | C77: =IFERROR(C76*$C$20/(1-$C$20),0) -> 0 | D77: =IFERROR(D76*$C$20/(1-$C$20),0) -> 0 | E77: =IFERROR(E76*$C$20/(1-$C$20),0) -> 0 | F77: =IFERROR(F76*$C$20/(1-$C$20),0) -> 0 | G77: =IFERROR(G76*$C$20/(1-$C$20),0) -> 0 | H77: =IFERROR(H76*$C$20/(1-$C$20),0) -> 0 | I77: =IFERROR(I76*$C$20/(1-$C$20),0) -> 0 | J77: =IFERROR(J76*$C$20/(1-$C$20),0) -> 0 | ... L77: =IFERROR(L76*$C$20/(1-$C$20),0) -> 0 | M77: =SUM(D77:L77) -> 0
A78: Coût administratif du ciblage | B78: Mds FCFA | C78: =IF(0=0,0,$G$44*$C$18*$C$19/1000000000) -> 0 | D78: =IF(1=0,0,$G$44*$C$18*$C$19/1000000000) -> 0 | E78: =IF(2=0,0,$G$44*$C$18*$C$19/1000000000) -> 0 | F78: =IF(3=0,0,$G$44*$C$18*$C$19/1000000000) -> 0 | G78: =IF(4=0,0,$G$44*$C$18*$C$19/1000000000) -> 0 | H78: =IF(5=0,0,$G$44*$C$18*$C$19/1000000000) -> 0 | I78: =IF(6=0,0,$G$44*$C$18*$C$19/1000000000) -> 0 | J78: =IF(7=0,0,$G$44*$C$18*$C$19/1000000000) -> 0 | K78: =IF(8=0,0,$G$44*$C$18*$C$19/1000000000) -> 0 | L78: =IF(9=0,0,$G$44*$C$18*$C$19/1000000000) -> 0 | M78: =SUM(D78:L78) -> 0
A79: Aide sociale due (total) | B79: Mds FCFA | C79: =C76+C77+C78 -> 0 | D79: =D76+D77+D78 -> 0 | E79: =E76+E77+E78 -> 0 | F79: =F76+F77+F78 -> 0 | G79: =G76+G77+G78 -> 0 | H79: =H76+H77+H78 -> 0 | I79: =I76+I77+I78 -> 0 | J79: =J76+J77+J78 -> 0 | ... L79: =L76+L77+L78 -> 0 | M79: =SUM(D79:L79) -> 0
A80: Aide sociale versée | B80: Mds FCFA | C80: =C79*$C$16 -> 0 | D80: =D79*$C$16 -> 0 | E80: =E79*$C$16 -> 0 | F80: =F79*$C$16 -> 0 | G80: =G79*$C$16 -> 0 | H80: =H79*$C$16 -> 0 | I80: =I79*$C$16 -> 0 | J80: =J79*$C$16 -> 0 | ... L80: =L79*$C$16 -> 0 | M80: =SUM(D80:L80) -> 0
A81: Compensation tarifaire due à l'opérateur | B81: Mds FCFA | C81: =C74*$C$15 -> 0 | D81: =D74*$C$15 -> 0 | E81: =E74*$C$15 -> 0 | F81: =F74*$C$15 -> 0 | G81: =G74*$C$15 -> 0 | H81: =H74*$C$15 -> 0 | I81: =I74*$C$15 -> 0 | J81: =J74*$C$15 -> 0 | ... L81: =L74*$C$15 -> 0 | M81: =SUM(D81:L81) -> 0
A82: Compensation tarifaire versée | B82: Mds FCFA | C82: =C81*$C$16 -> 0 | D82: =D81*$C$16 -> 0 | E82: =E81*$C$16 -> 0 | F82: =F81*$C$16 -> 0 | G82: =G81*$C$16 -> 0 | H82: =H81*$C$16 -> 0 | I82: =I81*$C$16 -> 0 | J82: =J81*$C$16 -> 0 | ... L82: =L81*$C$16 -> 0 | M82: =SUM(D82:L82) -> 0
A83: Subventions au raccordement versées | B83: Mds FCFA | C83: =IF(0=0,0,$G$48*$C$22/1000000000*$C$16) -> 0 | D83: =IF(1=0,0,$G$48*$C$22/1000000000*$C$16) -> 0 | E83: =IF(2=0,0,$G$48*$C$22/1000000000*$C$16) -> 0 | F83: =IF(3=0,0,$G$48*$C$22/1000000000*$C$16) -> 0 | G83: =IF(4=0,0,$G$48*$C$22/1000000000*$C$16) -> 0 | H83: =IF(5=0,0,$G$48*$C$22/1000000000*$C$16) -> 0 | I83: =IF(6=0,0,$G$48*$C$22/1000000000*$C$16) -> 0 | J83: =IF(7=0,0,$G$48*$C$22/1000000000*$C$16) -> 0 | K83: =IF(8=0,0,$G$48*$C$22/1000000000*$C$16) -> 0 | L83: =IF(9=0,0,$G$48*$C$22/1000000000*$C$16) -> 0 | M83: =SUM(D83:L83) -> 0
A84: Part de l'aide transitant par la facture | B84: Mds FCFA | C84: =(C76+C77)*$C$17 -> 0 | D84: =(D76+D77)*$C$17 -> 0 | E84: =(E76+E77)*$C$17 -> 0 | F84: =(F76+F77)*$C$17 -> 0 | G84: =(G76+G77)*$C$17 -> 0 | H84: =(H76+H77)*$C$17 -> 0 | I84: =(I76+I77)*$C$17 -> 0 | J84: =(J76+J77)*$C$17 -> 0 | ... L84: =(L76+L77)*$C$17 -> 0 | M84: =SUM(D84:L84) -> 0
A85: Recettes encaissées par l'opérateur (hors compensations) | B85: Mds FCFA | C85: =(C71-C84)*C59+C84*$C$16 -> 0 | D85: =(D71-D84)*D59+D84*$C$16 -> 0 | E85: =(E71-E84)*E59+E84*$C$16 -> 0 | F85: =(F71-F84)*F59+F84*$C$16 -> 0 | G85: =(G71-G84)*G59+G84*$C$16 -> 0 | H85: =(H71-H84)*H59+H84*$C$16 -> 0 | I85: =(I71-I84)*I59+I84*$C$16 -> 0 | J85: =(J71-J84)*J59+J84*$C$16 -> 0 | ... L85: =(L71-L84)*L59+L84*$C$16 -> 0 | M85: =SUM(D85:L85) -> 0
A86: Résultat d'exploitation de l'opérateur | B86: Mds FCFA | C86: =C85+C82-C72-C73 -> 0 | D86: =D85+D82-D72-D73 -> 0 | E86: =E85+E82-E72-E73 -> 0 | F86: =F85+F82-F72-F73 -> 0 | G86: =G85+G82-G72-G73 -> 0 | H86: =H85+H82-H72-H73 -> 0 | I86: =I85+I82-I72-I73 -> 0 | J86: =J85+J82-J72-J73 -> 0 | ... L86: =L85+L82-L72-L73 -> 0 | M86: =SUM(D86:L86) -> 0
A87: dont coût d'inefficience (pertes excédentaires + non-recouvrement) | B87: Mds FCFA | C87: =C73+(C71-C84)*(1-C59) -> 0 | D87: =D73+(D71-D84)*(1-D59) -> 0 | E87: =E73+(E71-E84)*(1-E59) -> 0 | F87: =F73+(F71-F84)*(1-F59) -> 0 | G87: =G73+(G71-G84)*(1-G59) -> 0 | H87: =H73+(H71-H84)*(1-H59) -> 0 | I87: =I73+(I71-I84)*(1-I59) -> 0 | J87: =J73+(J71-J84)*(1-J59) -> 0 | ... L87: =L73+(L71-L84)*(1-L59) -> 0 | M87: =SUM(D87:L87) -> 0
A89: Coût total de la politique tarifaire : CTPT = SB + DC + CI + CE
A90: SB — subventions budgétaires versées | B90: Mds FCFA | C90: =C82+C80+C83 -> 0 | D90: =D82+D80+D83 -> 0 | E90: =E82+E80+E83 -> 0 | F90: =F82+F80+F83 -> 0 | G90: =G82+G80+G83 -> 0 | H90: =H82+H80+H83 -> 0 | I90: =I82+I80+I83 -> 0 | J90: =J82+J80+J83 -> 0 | ... L90: =L82+L80+L83 -> 0 | M90: =SUM(D90:L90) -> 0
A91: DC — déficit de compensation non financé | B91: Mds FCFA | C91: =MAX(0,C74-C82)+(C76+C77)*$C$17*(1-$C$16) -> 0 | D91: =MAX(0,D74-D82)+(D76+D77)*$C$17*(1-$C$16) -> 0 | E91: =MAX(0,E74-E82)+(E76+E77)*$C$17*(1-$C$16) -> 0 | F91: =MAX(0,F74-F82)+(F76+F77)*$C$17*(1-$C$16) -> 0 | G91: =MAX(0,G74-G82)+(G76+G77)*$C$17*(1-$C$16) -> 0 | H91: =MAX(0,H74-H82)+(H76+H77)*$C$17*(1-$C$16) -> 0 | I91: =MAX(0,I74-I82)+(I76+I77)*$C$17*(1-$C$16) -> 0 | J91: =MAX(0,J74-J82)+(J76+J77)*$C$17*(1-$C$16) -> 0 | ... L91: =MAX(0,L74-L82)+(L76+L77)*$C$17*(1-$C$16) -> 0 | M91: =SUM(D91:L91) -> 0
A92: CI — coûts indirects (dégradation du service) | B92: Mds FCFA | C92: =$C$23*(1-$G$49*C$55) -> 0 | D92: =$C$23*(1-$G$49*D$55) -> 0 | E92: =$C$23*(1-$G$49*E$55) -> 0 | F92: =$C$23*(1-$G$49*F$55) -> 0 | G92: =$C$23*(1-$G$49*G$55) -> 0 | H92: =$C$23*(1-$G$49*H$55) -> 0 | I92: =$C$23*(1-$G$49*I$55) -> 0 | J92: =$C$23*(1-$G$49*J$55) -> 0 | ... L92: =$C$23*(1-$G$49*L$55) -> 0 | M92: =SUM(D92:L92) -> 0
A93: CE — surcoûts des entreprises | B93: Mds FCFA | C93: =$C$24*(1-$G$50*C$55) -> 0 | D93: =$C$24*(1-$G$50*D$55) -> 0 | E93: =$C$24*(1-$G$50*E$55) -> 0 | F93: =$C$24*(1-$G$50*F$55) -> 0 | G93: =$C$24*(1-$G$50*G$55) -> 0 | H93: =$C$24*(1-$G$50*H$55) -> 0 | I93: =$C$24*(1-$G$50*I$55) -> 0 | J93: =$C$24*(1-$G$50*J$55) -> 0 | ... L93: =$C$24*(1-$G$50*L$55) -> 0 | M93: =SUM(D93:L93) -> 0
A94: CTPT — coût total de la politique tarifaire | B94: Mds FCFA | C94: =C90+C91+C92+C93 -> 0 | D94: =D90+D91+D92+D93 -> 0 | E94: =E90+E91+E92+E93 -> 0 | F94: =F90+F91+F92+F93 -> 0 | G94: =G90+G91+G92+G93 -> 0 | H94: =H90+H91+H92+H93 -> 0 | I94: =I90+I91+I92+I93 -> 0 | J94: =J90+J91+J92+J93 -> 0 | ... L94: =L90+L91+L92+L93 -> 0 | M94: =SUM(D94:L94) -> 0
A95: Anti-double comptage : DC ne contient que la sous-tarification non compensée et l'aide due non versée. Les pertes excédentaires et le non-recouvrement relèvent de la performance de l'opérateur (ligne « inefficience »), pas du CTPT. CI et CE doivent être estimés sur des périmètres disjoints.
A97: Indice du tarif industriel HT (base = 100) | B97: indice | C97: =IFERROR(C65/$C$65*100,0) -> 0 | D97: =IFERROR(D65/$C$65*100,0) -> 0 | E97: =IFERROR(E65/$C$65*100,0) -> 0 | F97: =IFERROR(F65/$C$65*100,0) -> 0 | G97: =IFERROR(G65/$C$65*100,0) -> 0 | H97: =IFERROR(H65/$C$65*100,0) -> 0 | I97: =IFERROR(I65/$C$65*100,0) -> 0 | J97: =IFERROR(J65/$C$65*100,0) -> 0 | ... L97: =IFERROR(L65/$C$65*100,0) -> 0
A98: Effet sur le coût de production industriel | B98: % coût | C98: =$C$25*(C97/100-1) -> 0 | D98: =$C$25*(D97/100-1) -> 0 | E98: =$C$25*(E97/100-1) -> 0 | F98: =$C$25*(F97/100-1) -> 0 | G98: =$C$25*(G97/100-1) -> 0 | H98: =$C$25*(H97/100-1) -> 0 | I98: =$C$25*(I97/100-1) -> 0 | J98: =$C$25*(J97/100-1) -> 0 | ... L98: =$C$25*(L97/100-1) -> 0
A99: Indice du tarif de la tranche sociale (base = 100) | B99: indice | C99: =IFERROR(C61/$C$61*100,0) -> 0 | D99: =IFERROR(D61/$C$61*100,0) -> 0 | E99: =IFERROR(E61/$C$61*100,0) -> 0 | F99: =IFERROR(F61/$C$61*100,0) -> 0 | G99: =IFERROR(G61/$C$61*100,0) -> 0 | H99: =IFERROR(H61/$C$61*100,0) -> 0 | I99: =IFERROR(I61/$C$61*100,0) -> 0 | J99: =IFERROR(J61/$C$61*100,0) -> 0 | ... L99: =IFERROR(L61/$C$61*100,0) -> 0
A100: Hausse non compensée pour les ménages sociaux exclus du ciblage | B100: Mds FCFA | C100: =(1-$G$44*$C$21)*MAX(0,C61-$D$30)*C66/1000 -> 0 | D100: =(1-$G$44*$C$21)*MAX(0,D61-$D$30)*D66/1000 -> 0 | E100: =(1-$G$44*$C$21)*MAX(0,E61-$D$30)*E66/1000 -> 0 | F100: =(1-$G$44*$C$21)*MAX(0,F61-$D$30)*F66/1000 -> 0 | G100: =(1-$G$44*$C$21)*MAX(0,G61-$D$30)*G66/1000 -> 0 | H100: =(1-$G$44*$C$21)*MAX(0,H61-$D$30)*H66/1000 -> 0 | I100: =(1-$G$44*$C$21)*MAX(0,I61-$D$30)*I66/1000 -> 0 | J100: =(1-$G$44*$C$21)*MAX(0,J61-$D$30)*J66/1000 -> 0 | ... L100: =(1-$G$44*$C$21)*MAX(0,L61-$D$30)*L66/1000 -> 0 | M100: =SUM(D100:L100) -> 0

Sheet Exemple_fictif
A1: Modèle tarifaire électricité — Exemple_fictif
A2: VALEURS FICTIVES — test des formules uniquement, aucune donnée réelle.
A3: Unités : énergie en GWh ; tarifs et coûts en FCFA/kWh ; montants en milliards de FCFA constants de l'année de base (termes réels).
A5: 1. HYPOTHÈSES GÉNÉRALES (année de base)
A6: Paramètre | B6: Unité | C6: Valeur | D6: Source / note
A7: Année de base des données | B7: année | C7: 2025 | D7: Dernière année avec données vérifiées (période d'analyse 2020–2026).
A8: Énergie injectée dans le réseau | B8: GWh | C8: 4000
A9: Croissance annuelle de l'énergie injectée | B9: %/an | C9: 0.05 | D9: Hypothèse de demande ; pas d'élasticité-prix dans cette version.
A10: Pertes techniques | B10: % injectée | C10: 0.12
A11: Pertes commerciales (non techniques) | B11: % injectée | C11: 0.13
A12: Pertes totales admises par le régulateur | B12: % injectée | C12: 0.15 | D12: Au-delà : coût d'inefficience, non imputé à la politique tarifaire.
A13: Taux de recouvrement des factures | B13: % facturé | C13: 0.85
A14: Coût marginal de production / achat | B14: FCFA/kWh | C14: 60 | D14: Valorise les pertes excédentaires.
A15: Part de l'écart de sous-tarification que l'État s'engage à compenser | B15: % | C15: 0.5 | D15: Selon textes réglementaires / contrat de concession.
A16: Fiabilité de paiement des engagements budgétaires | B16: % versé | C16: 0.7 | D16: Versé / dû ; s'applique aux compensations, aides sociales et raccordements.
A17: Canal de l'aide sociale (1 = tarif social compensé via la facture ; 0 = transfert direct aux ménages) | B17: 1/0 | C17: 1
A18: Ménages bénéficiaires de l'aide ciblée | B18: nombre | C18: 400000
A19: Coût administratif du ciblage par bénéficiaire | B19: FCFA/an | C19: 3000
A20: Erreur d'inclusion (part de l'aide versée à des non-éligibles) | B20: % | C20: 0.25
A21: Part de la consommation de la tranche sociale couverte par l'aide | B21: % | C21: 0.7 | D21: Les ménages non couverts (erreur d'exclusion) subissent la hausse.
A22: Subvention par nouveau raccordement | B22: FCFA | C22: 150000
A23: CI — coûts indirects liés à la dégradation du service (base) | B23: Mds FCFA | C23: 50 | D23: Estimation à documenter ; ne pas inclure ce qui figure déjà dans CE.
A24: CE — surcoûts des entreprises (autoproduction, délestages) (base) | B24: Mds FCFA | C24: 80 | D24: Estimation à documenter (enquêtes entreprises).
A25: Part de l'électricité dans les coûts de production industriels | B25: % | C25: 0.15
A27: 2. CATÉGORIES TARIFAIRES (année de base)
A28: Catégorie | B28: Sociale (1/0) | C28: Part des ventes | D28: Tarif moyen | E28: Coût efficace | F28: Ventes | G28: Recettes | H28: Coût de desserte | I28: Écart tarif–coût | J28: Écart / coût
C29: % ventes | D29: FCFA/kWh | E29: FCFA/kWh | F29: GWh | G29: Mds FCFA | H29: Mds FCFA | I29: Mds FCFA | J29: %
A30: Ménages BT — tranche sociale | B30: 1 | C30: 0.15 | D30: 50 | E30: 110 | F30: =$C$8*(1-$C$10-$C$11)*C30 -> 450 | G30: =F30*D30/1000 -> 22.5 | H30: =F30*E30/1000 -> 49.5 | I30: =G30-H30 -> -27 | J30: =IFERROR(D30/E30-1,0) -> -0.54545455
A31: Ménages BT — autres tranches | B31: 0 | C31: 0.3 | D31: 80 | E31: 110 | F31: =$C$8*(1-$C$10-$C$11)*C31 -> 900 | G31: =F31*D31/1000 -> 72 | H31: =F31*E31/1000 -> 99 | I31: =G31-H31 -> -27 | J31: =IFERROR(D31/E31-1,0) -> -0.27272727
A32: Professionnels BT | B32: 0 | C32: 0.15 | D32: 100 | E32: 105 | F32: =$C$8*(1-$C$10-$C$11)*C32 -> 450 | G32: =F32*D32/1000 -> 45 | H32: =F32*E32/1000 -> 47.25 | I32: =G32-H32 -> -2.25 | J32: =IFERROR(D32/E32-1,0) -> -0.047619048
A33: Moyenne tension (MT) | B33: 0 | C33: 0.2 | D33: 95 | E33: 85 | F33: =$C$8*(1-$C$10-$C$11)*C33 -> 600 | G33: =F33*D33/1000 -> 57 | H33: =F33*E33/1000 -> 51 | I33: =G33-H33 -> 6 | J33: =IFERROR(D33/E33-1,0) -> 0.11764706
A34: Haute tension — industrie (HT) | B34: 0 | C34: 0.2 | D34: 70 | E34: 60 | F34: =$C$8*(1-$C$10-$C$11)*C34 -> 600 | G34: =F34*D34/1000 -> 42 | H34: =F34*E34/1000 -> 36 | I34: =G34-H34 -> 6 | J34: =IFERROR(D34/E34-1,0) -> 0.16666667
A35: Total / contrôle (la somme des parts doit faire 100 %) | C35: =SUM(C30:C34) -> 1 | F35: =SUM(F30:F34) -> 3000 | G35: =SUM(G30:G34) -> 238.5 | H35: =SUM(H30:H34) -> 282.75 | I35: =SUM(I30:I34) -> -44.25 | J35: =IFERROR(G35/H35-1,0) -> -0.15649867
A36: Avertissement : un écart positif n'est une subvention croisée que si le coût efficace par catégorie est établi par une étude d'allocation des coûts (tension, pointe, pertes). Sinon, c'est un simple écart non démontré.
A38: 3. SCÉNARIOS DE RÉFORME (paramètres atteints en 2035, trajectoire linéaire)
A39: Scénario actif (choisir dans la liste) | C39: S3 Réforme intégrée
A40: Paramètre | B40: Unité | C40: S0 Statu quo | D40: S1 Tarifs aux coûts | E40: S2 Aides ciblées | F40: S3 Réforme intégrée | G40: Actif
A41: Résorption de l'écart — catégories sous-tarifées non sociales | B41: fraction | C41: 0 | D41: 1 | E41: 1 | F41: 1 | G41: =INDEX(C41:F41,MATCH($C$39,$C$40:$F$40,0)) -> 1
A42: Résorption de l'écart — tranche sociale | B42: fraction | C42: 0 | D42: 1 | E42: 1 | F42: 1 | G42: =INDEX(C42:F42,MATCH($C$39,$C$40:$F$40,0)) -> 1
A43: Résorption de l'écart — catégories sur-tarifées | B43: fraction | C43: 0 | D43: 1 | E43: 1 | F43: 1 | G43: =INDEX(C43:F43,MATCH($C$39,$C$40:$F$40,0)) -> 1
A44: Aide sociale ciblée active | B44: 1/0 | C44: 0 | D44: 0 | E44: 1 | F44: 1 | G44: =INDEX(C44:F44,MATCH($C$39,$C$40:$F$40,0)) -> 1
A45: Pertes techniques en 2035 | B45: % injectée | C45: =$C$10 -> 0.12 | D45: =$C$10 -> 0.12 | E45: =$C$10 -> 0.12 | F45: 0.09 | G45: =INDEX(C45:F45,MATCH($C$39,$C$40:$F$40,0)) -> 0.09
A46: Pertes commerciales en 2035 | B46: % injectée | C46: =$C$11 -> 0.13 | D46: =$C$11 -> 0.13 | E46: =$C$11 -> 0.13 | F46: 0.06 | G46: =INDEX(C46:F46,MATCH($C$39,$C$40:$F$40,0)) -> 0.06
A47: Recouvrement en 2035 | B47: % facturé | C47: =$C$13 -> 0.85 | D47: =$C$13 -> 0.85 | E47: =$C$13 -> 0.85 | F47: 0.95 | G47: =INDEX(C47:F47,MATCH($C$39,$C$40:$F$40,0)) -> 0.95
A48: Raccordements subventionnés par an | B48: nombre | C48: 20000 | D48: 0 | E48: 50000 | F48: 80000 | G48: =INDEX(C48:F48,MATCH($C$39,$C$40:$F$40,0)) -> 80000
A49: Réduction de CI atteinte en 2035 | B49: % | C49: 0 | D49: 0 | E49: 0 | F49: 0.5 | G49: =INDEX(C49:F49,MATCH($C$39,$C$40:$F$40,0)) -> 0.5
A50: Réduction de CE atteinte en 2035 | B50: % | C50: 0 | D50: 0 | E50: 0 | F50: 0.6 | G50: =INDEX(C50:F50,MATCH($C$39,$C$40:$F$40,0)) -> 0.6
A51: Les valeurs 0/1 de résorption et d'aide définissent les scénarios ; elles sont modifiables (ex. S3 : ne résorber que les écarts sans justification de coût). Pertes et recouvrement de S0–S2 = niveau de base (aucune amélioration supposée).
A53: 4. TRAJECTOIRE 2027–2035 (scénario actif)
A54: Indicateur | B54: Unité | C54: Base | D54: 2027 | E54: 2028 | F54: 2029 | G54: 2030 | H54: 2031 | I54: 2032 | J54: 2033 | K54: 2034 | L54: 2035 | M54: Cumul 2027–35
A55: Avancement de la réforme | B55: fraction | C55: =0/9 -> 0 | D55: =1/9 -> 0.11111111 | E55: =2/9 -> 0.22222222 | F55: =3/9 -> 0.33333333 | G55: =4/9 -> 0.44444444 | H55: =5/9 -> 0.55555556 | I55: =6/9 -> 0.66666667 | J55: =7/9 -> 0.77777778 | K55: =8/9 -> 0.88888889 | L55: =9/9 -> 1
A56: Énergie injectée | B56: GWh | C56: =$C$8 -> 4000 | D56: =C56*(1+$C$9) -> 4200 | E56: =D56*(1+$C$9) -> 4410 | F56: =E56*(1+$C$9) -> 4630.5 | G56: =F56*(1+$C$9) -> 4862.025 | H56: =G56*(1+$C$9) -> 5105.1263 | I56: =H56*(1+$C$9) -> 5360.3826 | J56: =I56*(1+$C$9) -> 5628.4017 | K56: =J56*(1+$C$9) -> 5909.8218 | L56: =K56*(1+$C$9) -> 6205.3129
A57: Pertes techniques | B57: % | C57: =$C$10+($G$45-$C$10)*C$55 -> 0.12 | D57: =$C$10+($G$45-$C$10)*D$55 -> 0.11666667 | E57: =$C$10+($G$45-$C$10)*E$55 -> 0.11333333 | F57: =$C$10+($G$45-$C$10)*F$55 -> 0.11 | G57: =$C$10+($G$45-$C$10)*G$55 -> 0.10666667 | H57: =$C$10+($G$45-$C$10)*H$55 -> 0.10333333 | I57: =$C$10+($G$45-$C$10)*I$55 -> 0.1 | J57: =$C$10+($G$45-$C$10)*J$55 -> 0.096666667 | ... L57: =$C$10+($G$45-$C$10)*L$55 -> 0.09
A58: Pertes commerciales | B58: % | C58: =$C$11+($G$46-$C$11)*C$55 -> 0.13 | D58: =$C$11+($G$46-$C$11)*D$55 -> 0.12222222 | E58: =$C$11+($G$46-$C$11)*E$55 -> 0.11444444 | F58: =$C$11+($G$46-$C$11)*F$55 -> 0.10666667 | G58: =$C$11+($G$46-$C$11)*G$55 -> 0.098888889 | H58: =$C$11+($G$46-$C$11)*H$55 -> 0.091111111 | I58: =$C$11+($G$46-$C$11)*I$55 -> 0.083333333 | J58: =$C$11+($G$46-$C$11)*J$55 -> 0.075555556 | ... L58: =$C$11+($G$46-$C$11)*L$55 -> 0.06
A59: Taux de recouvrement | B59: % | C59: =$C$13+($G$47-$C$13)*C$55 -> 0.85 | D59: =$C$13+($G$47-$C$13)*D$55 -> 0.86111111 | E59: =$C$13+($G$47-$C$13)*E$55 -> 0.87222222 | F59: =$C$13+($G$47-$C$13)*F$55 -> 0.88333333 | G59: =$C$13+($G$47-$C$13)*G$55 -> 0.89444444 | H59: =$C$13+($G$47-$C$13)*H$55 -> 0.90555556 | I59: =$C$13+($G$47-$C$13)*I$55 -> 0.91666667 | J59: =$C$13+($G$47-$C$13)*J$55 -> 0.92777778 | ... L59: =$C$13+($G$47-$C$13)*L$55 -> 0.95
A60: Ventes facturées | B60: GWh | C60: =C56*(1-C57-C58) -> 3000 | D60: =D56*(1-D57-D58) -> 3196.6667 | E60: =E56*(1-E57-E58) -> 3405.5 | F60: =F56*(1-F57-F58) -> 3627.225 | G60: =G56*(1-G57-G58) -> 3862.6087 | H60: =H56*(1-H57-H58) -> 4112.4628 | I60: =I56*(1-I57-I58) -> 4377.6458 | J60: =J56*(1-J57-J58) -> 4659.0658 | ... L60: =L56*(1-L57-L58) -> 5274.5159
A61: Tarif — Ménages BT — tranche sociale | B61: FCFA/kWh | C61: =$D$30+($E$30-$D$30)*IF($B$30=1,$G$42,IF($D$30<$E$30,$G$41,$G$43))*C$55 -> 50 | D61: =$D$30+($E$30-$D$30)*IF($B$30=1,$G$42,IF($D$30<$E$30,$G$41,$G$43))*D$55 -> 56.666667 | E61: =$D$30+($E$30-$D$30)*IF($B$30=1,$G$42,IF($D$30<$E$30,$G$41,$G$43))*E$55 -> 63.333333 | F61: =$D$30+($E$30-$D$30)*IF($B$30=1,$G$42,IF($D$30<$E$30,$G$41,$G$43))*F$55 -> 70 | G61: =$D$30+($E$30-$D$30)*IF($B$30=1,$G$42,IF($D$30<$E$30,$G$41,$G$43))*G$55 -> 76.666667 | H61: =$D$30+($E$30-$D$30)*IF($B$30=1,$G$42,IF($D$30<$E$30,$G$41,$G$43))*H$55 -> 83.333333 | I61: =$D$30+($E$30-$D$30)*IF($B$30=1,$G$42,IF($D$30<$E$30,$G$41,$G$43))*I$55 -> 90 | J61: =$D$30+($E$30-$D$30)*IF($B$30=1,$G$42,IF($D$30<$E$30,$G$41,$G$43))*J$55 -> 96.666667 | ... L61: =$D$30+($E$30-$D$30)*IF($B$30=1,$G$42,IF($D$30<$E$30,$G$41,$G$43))*L$55 -> 110
A62: Tarif — Ménages BT — autres tranches | B62: FCFA/kWh | C62: =$D$31+($E$31-$D$31)*IF($B$31=1,$G$42,IF($D$31<$E$31,$G$41,$G$43))*C$55 -> 80 | D62: =$D$31+($E$31-$D$31)*IF($B$31=1,$G$42,IF($D$31<$E$31,$G$41,$G$43))*D$55 -> 83.333333 | E62: =$D$31+($E$31-$D$31)*IF($B$31=1,$G$42,IF($D$31<$E$31,$G$41,$G$43))*E$55 -> 86.666667 | F62: =$D$31+($E$31-$D$31)*IF($B$31=1,$G$42,IF($D$31<$E$31,$G$41,$G$43))*F$55 -> 90 | G62: =$D$31+($E$31-$D$31)*IF($B$31=1,$G$42,IF($D$31<$E$31,$G$41,$G$43))*G$55 -> 93.333333 | H62: =$D$31+($E$31-$D$31)*IF($B$31=1,$G$42,IF($D$31<$E$31,$G$41,$G$43))*H$55 -> 96.666667 | I62: =$D$31+($E$31-$D$31)*IF($B$31=1,$G$42,IF($D$31<$E$31,$G$41,$G$43))*I$55 -> 100 | J62: =$D$31+($E$31-$D$31)*IF($B$31=1,$G$42,IF($D$31<$E$31,$G$41,$G$43))*J$55 -> 103.33333 | ... L62: =$D$31+($E$31-$D$31)*IF($B$31=1,$G$42,IF($D$31<$E$31,$G$41,$G$43))*L$55 -> 110
A63: Tarif — Professionnels BT | B63: FCFA/kWh | C63: =$D$32+($E$32-$D$32)*IF($B$32=1,$G$42,IF($D$32<$E$32,$G$41,$G$43))*C$55 -> 100 | D63: =$D$32+($E$32-$D$32)*IF($B$32=1,$G$42,IF($D$32<$E$32,$G$41,$G$43))*D$55 -> 100.55556 | E63: =$D$32+($E$32-$D$32)*IF($B$32=1,$G$42,IF($D$32<$E$32,$G$41,$G$43))*E$55 -> 101.11111 | F63: =$D$32+($E$32-$D$32)*IF($B$32=1,$G$42,IF($D$32<$E$32,$G$41,$G$43))*F$55 -> 101.66667 | G63: =$D$32+($E$32-$D$32)*IF($B$32=1,$G$42,IF($D$32<$E$32,$G$41,$G$43))*G$55 -> 102.22222 | H63: =$D$32+($E$32-$D$32)*IF($B$32=1,$G$42,IF($D$32<$E$32,$G$41,$G$43))*H$55 -> 102.77778 | I63: =$D$32+($E$32-$D$32)*IF($B$32=1,$G$42,IF($D$32<$E$32,$G$41,$G$43))*I$55 -> 103.33333 | J63: =$D$32+($E$32-$D$32)*IF($B$32=1,$G$42,IF($D$32<$E$32,$G$41,$G$43))*J$55 -> 103.88889 | ... L63: =$D$32+($E$32-$D$32)*IF($B$32=1,$G$42,IF($D$32<$E$32,$G$41,$G$43))*L$55 -> 105
A64: Tarif — Moyenne tension (MT) | B64: FCFA/kWh | C64: =$D$33+($E$33-$D$33)*IF($B$33=1,$G$42,IF($D$33<$E$33,$G$41,$G$43))*C$55 -> 95 | D64: =$D$33+($E$33-$D$33)*IF($B$33=1,$G$42,IF($D$33<$E$33,$G$41,$G$43))*D$55 -> 93.888889 | E64: =$D$33+($E$33-$D$33)*IF($B$33=1,$G$42,IF($D$33<$E$33,$G$41,$G$43))*E$55 -> 92.777778 | F64: =$D$33+($E$33-$D$33)*IF($B$33=1,$G$42,IF($D$33<$E$33,$G$41,$G$43))*F$55 -> 91.666667 | G64: =$D$33+($E$33-$D$33)*IF($B$33=1,$G$42,IF($D$33<$E$33,$G$41,$G$43))*G$55 -> 90.555556 | H64: =$D$33+($E$33-$D$33)*IF($B$33=1,$G$42,IF($D$33<$E$33,$G$41,$G$43))*H$55 -> 89.444444 | I64: =$D$33+($E$33-$D$33)*IF($B$33=1,$G$42,IF($D$33<$E$33,$G$41,$G$43))*I$55 -> 88.333333 | J64: =$D$33+($E$33-$D$33)*IF($B$33=1,$G$42,IF($D$33<$E$33,$G$41,$G$43))*J$55 -> 87.222222 | ... L64: =$D$33+($E$33-$D$33)*IF($B$33=1,$G$42,IF($D$33<$E$33,$G$41,$G$43))*L$55 -> 85
A65: Tarif — Haute tension — industrie (HT) | B65: FCFA/kWh | C65: =$D$34+($E$34-$D$34)*IF($B$34=1,$G$42,IF($D$34<$E$34,$G$41,$G$43))*C$55 -> 70 | D65: =$D$34+($E$34-$D$34)*IF($B$34=1,$G$42,IF($D$34<$E$34,$G$41,$G$43))*D$55 -> 68.888889 | E65: =$D$34+($E$34-$D$34)*IF($B$34=1,$G$42,IF($D$34<$E$34,$G$41,$G$43))*E$55 -> 67.777778 | F65: =$D$34+($E$34-$D$34)*IF($B$34=1,$G$42,IF($D$34<$E$34,$G$41,$G$43))*F$55 -> 66.666667 | G65: =$D$34+($E$34-$D$34)*IF($B$34=1,$G$42,IF($D$34<$E$34,$G$41,$G$43))*G$55 -> 65.555556 | H65: =$D$34+($E$34-$D$34)*IF($B$34=1,$G$42,IF($D$34<$E$34,$G$41,$G$43))*H$55 -> 64.444444 | I65: =$D$34+($E$34-$D$34)*IF($B$34=1,$G$42,IF($D$34<$E$34,$G$41,$G$43))*I$55 -> 63.333333 | J65: =$D$34+($E$34-$D$34)*IF($B$34=1,$G$42,IF($D$34<$E$34,$G$41,$G$43))*J$55 -> 62.222222 | ... L65: =$D$34+($E$34-$D$34)*IF($B$34=1,$G$42,IF($D$34<$E$34,$G$41,$G$43))*L$55 -> 60
A66: Ventes — Ménages BT — tranche sociale | B66: GWh | C66: =C60*$C$30 -> 450 | D66: =D60*$C$30 -> 479.5 | E66: =E60*$C$30 -> 510.825 | F66: =F60*$C$30 -> 544.08375 | G66: =G60*$C$30 -> 579.39131 | H66: =H60*$C$30 -> 616.86942 | I66: =I60*$C$30 -> 656.64686 | J66: =J60*$C$30 -> 698.85988 | ... L66: =L60*$C$30 -> 791.17739
A67: Ventes — Ménages BT — autres tranches | B67: GWh | C67: =C60*$C$31 -> 900 | D67: =D60*$C$31 -> 959 | E67: =E60*$C$31 -> 1021.65 | F67: =F60*$C$31 -> 1088.1675 | G67: =G60*$C$31 -> 1158.7826 | H67: =H60*$C$31 -> 1233.7388 | I67: =I60*$C$31 -> 1313.2937 | J67: =J60*$C$31 -> 1397.7198 | ... L67: =L60*$C$31 -> 1582.3548
A68: Ventes — Professionnels BT | B68: GWh | C68: =C60*$C$32 -> 450 | D68: =D60*$C$32 -> 479.5 | E68: =E60*$C$32 -> 510.825 | F68: =F60*$C$32 -> 544.08375 | G68: =G60*$C$32 -> 579.39131 | H68: =H60*$C$32 -> 616.86942 | I68: =I60*$C$32 -> 656.64686 | J68: =J60*$C$32 -> 698.85988 | ... L68: =L60*$C$32 -> 791.17739
A69: Ventes — Moyenne tension (MT) | B69: GWh | C69: =C60*$C$33 -> 600 | D69: =D60*$C$33 -> 639.33333 | E69: =E60*$C$33 -> 681.1 | F69: =F60*$C$33 -> 725.445 | G69: =G60*$C$33 -> 772.52175 | H69: =H60*$C$33 -> 822.49256 | I69: =I60*$C$33 -> 875.52915 | J69: =J60*$C$33 -> 931.81317 | ... L69: =L60*$C$33 -> 1054.9032
A70: Ventes — Haute tension — industrie (HT) | B70: GWh | C70: =C60*$C$34 -> 600 | D70: =D60*$C$34 -> 639.33333 | E70: =E60*$C$34 -> 681.1 | F70: =F60*$C$34 -> 725.445 | G70: =G60*$C$34 -> 772.52175 | H70: =H60*$C$34 -> 822.49256 | I70: =I60*$C$34 -> 875.52915 | J70: =J60*$C$34 -> 931.81317 | ... L70: =L60*$C$34 -> 1054.9032
A71: Recettes facturées | B71: Mds FCFA | C71: =(C61*C66+C62*C67+C63*C68+C64*C69+C65*C70)/1000 -> 238.5 | D71: =(D61*D66+D62*D67+D63*D68+D64*D69+D65*D70)/1000 -> 259.37398 | E71: =(E61*E66+E62*E67+E63*E68+E64*E69+E65*E70)/1000 -> 281.89972 | F71: =(F61*F66+F62*F67+F63*F68+F64*F69+F65*F70)/1000 -> 306.19824 | G71: =(G61*G66+G62*G67+G63*G68+G64*G69+G65*G70)/1000 -> 332.39894 | H71: =(H61*H66+H62*H67+H63*H68+H64*H69+H65*H70)/1000 -> 360.64014 | I71: =(I61*I66+I62*I67+I63*I68+I64*I69+I65*I70)/1000 -> 391.06969 | J71: =(J61*J66+J62*J67+J63*J68+J64*J69+J65*J70)/1000 -> 423.84557 | ... L71: =(L61*L66+L62*L67+L63*L68+L64*L69+L65*L70)/1000 -> 497.12313 | M71: =SUM(D71:L71) -> 3311.686
A72: Coût efficace de desserte | B72: Mds FCFA | C72: =($E$30*C66+$E$31*C67+$E$32*C68+$E$33*C69+$E$34*C70)/1000 -> 282.75 | D72: =($E$30*D66+$E$31*D67+$E$32*D68+$E$33*D69+$E$34*D70)/1000 -> 301.28583 | E72: =($E$30*E66+$E$31*E67+$E$32*E68+$E$33*E69+$E$34*E70)/1000 -> 320.96837 | F72: =($E$30*F66+$E$31*F67+$E$32*F68+$E$33*F69+$E$34*F70)/1000 -> 341.86596 | G72: =($E$30*G66+$E$31*G67+$E$32*G68+$E$33*G69+$E$34*G70)/1000 -> 364.05087 | H72: =($E$30*H66+$E$31*H67+$E$32*H68+$E$33*H69+$E$34*H70)/1000 -> 387.59962 | I72: =($E$30*I66+$E$31*I67+$E$32*I68+$E$33*I69+$E$34*I70)/1000 -> 412.59311 | J72: =($E$30*J66+$E$31*J67+$E$32*J68+$E$33*J69+$E$34*J70)/1000 -> 439.11696 | ... L72: =($E$30*L66+$E$31*L67+$E$32*L68+$E$33*L69+$E$34*L70)/1000 -> 497.12313 | M72: =SUM(D72:L72) -> 3531.8656
A73: Coût des pertes au-delà du niveau admis | B73: Mds FCFA | C73: =C56*MAX(0,C57+C58-$C$12)*$C$14/1000 -> 24 | D73: =D56*MAX(0,D57+D58-$C$12)*$C$14/1000 -> 22.4 | E73: =E56*MAX(0,E57+E58-$C$12)*$C$14/1000 -> 20.58 | F73: =F56*MAX(0,F57+F58-$C$12)*$C$14/1000 -> 18.522 | G73: =G56*MAX(0,G57+G58-$C$12)*$C$14/1000 -> 16.20675 | H73: =H56*MAX(0,H57+H58-$C$12)*$C$14/1000 -> 13.61367 | I73: =I56*MAX(0,I57+I58-$C$12)*$C$14/1000 -> 10.720765 | J73: =J56*MAX(0,J57+J58-$C$12)*$C$14/1000 -> 7.5045356 | ... L73: =L56*MAX(0,L57+L58-$C$12)*$C$14/1000 -> 0 | M73: =SUM(D73:L73) -> 113.4876
A74: Écart de sous-tarification (Σ coût > tarif) | B74: Mds FCFA | C74: =(MAX(0,$E$30-C61)*C66+MAX(0,$E$31-C62)*C67+MAX(0,$E$32-C63)*C68+MAX(0,$E$33-C64)*C69+MAX(0,$E$34-C65)*C70)/1000 -> 56.25 | D74: =(MAX(0,$E$30-D61)*D66+MAX(0,$E$31-D62)*D67+MAX(0,$E$32-D63)*D68+MAX(0,$E$33-D64)*D69+MAX(0,$E$34-D65)*D70)/1000 -> 53.277778 | E74: =(MAX(0,$E$30-E61)*E66+MAX(0,$E$31-E62)*E67+MAX(0,$E$32-E63)*E68+MAX(0,$E$33-E64)*E69+MAX(0,$E$34-E65)*E70)/1000 -> 49.663542 | F74: =(MAX(0,$E$30-F61)*F66+MAX(0,$E$31-F62)*F67+MAX(0,$E$32-F63)*F68+MAX(0,$E$33-F64)*F69+MAX(0,$E$34-F65)*F70)/1000 -> 45.340313 | G74: =(MAX(0,$E$30-G61)*G66+MAX(0,$E$31-G62)*G67+MAX(0,$E$32-G63)*G68+MAX(0,$E$33-G64)*G69+MAX(0,$E$34-G65)*G70)/1000 -> 40.235508 | H74: =(MAX(0,$E$30-H61)*H66+MAX(0,$E$31-H62)*H67+MAX(0,$E$32-H63)*H68+MAX(0,$E$33-H64)*H69+MAX(0,$E$34-H65)*H70)/1000 -> 34.270523 | I74: =(MAX(0,$E$30-I61)*I66+MAX(0,$E$31-I62)*I67+MAX(0,$E$32-I63)*I68+MAX(0,$E$33-I64)*I69+MAX(0,$E$34-I65)*I70)/1000 -> 27.360286 | J74: =(MAX(0,$E$30-J61)*J66+MAX(0,$E$31-J62)*J67+MAX(0,$E$32-J63)*J68+MAX(0,$E$33-J64)*J69+MAX(0,$E$34-J65)*J70)/1000 -> 19.412774 | ... L74: =(MAX(0,$E$30-L61)*L66+MAX(0,$E$31-L62)*L67+MAX(0,$E$32-L63)*L68+MAX(0,$E$33-L64)*L69+MAX(0,$E$34-L65)*L70)/1000 -> 0 | M74: =SUM(D74:L74) -> 279.88923
A75: Écart de sur-tarification (Σ tarif > coût) | B75: Mds FCFA | C75: =(MAX(0,C61-$E$30)*C66+MAX(0,C62-$E$31)*C67+MAX(0,C63-$E$32)*C68+MAX(0,C64-$E$33)*C69+MAX(0,C65-$E$34)*C70)/1000 -> 12 | D75: =(MAX(0,D61-$E$30)*D66+MAX(0,D62-$E$31)*D67+MAX(0,D63-$E$32)*D68+MAX(0,D64-$E$33)*D69+MAX(0,D65-$E$34)*D70)/1000 -> 11.365926 | E75: =(MAX(0,E61-$E$30)*E66+MAX(0,E62-$E$31)*E67+MAX(0,E63-$E$32)*E68+MAX(0,E64-$E$33)*E69+MAX(0,E65-$E$34)*E70)/1000 -> 10.594889 | F75: =(MAX(0,F61-$E$30)*F66+MAX(0,F62-$E$31)*F67+MAX(0,F63-$E$32)*F68+MAX(0,F64-$E$33)*F69+MAX(0,F65-$E$34)*F70)/1000 -> 9.6726 | G75: =(MAX(0,G61-$E$30)*G66+MAX(0,G62-$E$31)*G67+MAX(0,G63-$E$32)*G68+MAX(0,G64-$E$33)*G69+MAX(0,G65-$E$34)*G70)/1000 -> 8.583575 | H75: =(MAX(0,H61-$E$30)*H66+MAX(0,H62-$E$31)*H67+MAX(0,H63-$E$32)*H68+MAX(0,H64-$E$33)*H69+MAX(0,H65-$E$34)*H70)/1000 -> 7.311045 | I75: =(MAX(0,I61-$E$30)*I66+MAX(0,I62-$E$31)*I67+MAX(0,I63-$E$32)*I68+MAX(0,I64-$E$33)*I69+MAX(0,I65-$E$34)*I70)/1000 -> 5.836861 | J75: =(MAX(0,J61-$E$30)*J66+MAX(0,J62-$E$31)*J67+MAX(0,J63-$E$32)*J68+MAX(0,J64-$E$33)*J69+MAX(0,J65-$E$34)*J70)/1000 -> 4.1413919 | ... L75: =(MAX(0,L61-$E$30)*L66+MAX(0,L62-$E$31)*L67+MAX(0,L63-$E$32)*L68+MAX(0,L64-$E$33)*L69+MAX(0,L65-$E$34)*L70)/1000 -> 0 | M75: =SUM(D75:L75) -> 59.709703
A76: Aide sociale aux éligibles (hausse du tarif social compensée) | B76: Mds FCFA | C76: =$G$44*$C$21*($B$30*MAX(0,C61-$D$30)*C66+$B$31*MAX(0,C62-$D$31)*C67+$B$32*MAX(0,C63-$D$32)*C68+$B$33*MAX(0,C64-$D$33)*C69+$B$34*MAX(0,C65-$D$34)*C70)/1000 -> 0 | D76: =$G$44*$C$21*($B$30*MAX(0,D61-$D$30)*D66+$B$31*MAX(0,D62-$D$31)*D67+$B$32*MAX(0,D63-$D$32)*D68+$B$33*MAX(0,D64-$D$33)*D69+$B$34*MAX(0,D65-$D$34)*D70)/1000 -> 2.2376667 | E76: =$G$44*$C$21*($B$30*MAX(0,E61-$D$30)*E66+$B$31*MAX(0,E62-$D$31)*E67+$B$32*MAX(0,E63-$D$32)*E68+$B$33*MAX(0,E64-$D$33)*E69+$B$34*MAX(0,E65-$D$34)*E70)/1000 -> 4.7677 | F76: =$G$44*$C$21*($B$30*MAX(0,F61-$D$30)*F66+$B$31*MAX(0,F62-$D$31)*F67+$B$32*MAX(0,F63-$D$32)*F68+$B$33*MAX(0,F64-$D$33)*F69+$B$34*MAX(0,F65-$D$34)*F70)/1000 -> 7.6171725 | G76: =$G$44*$C$21*($B$30*MAX(0,G61-$D$30)*G66+$B$31*MAX(0,G62-$D$31)*G67+$B$32*MAX(0,G63-$D$32)*G68+$B$33*MAX(0,G64-$D$33)*G69+$B$34*MAX(0,G65-$D$34)*G70)/1000 -> 10.815304 | H76: =$G$44*$C$21*($B$30*MAX(0,H61-$D$30)*H66+$B$31*MAX(0,H62-$D$31)*H67+$B$32*MAX(0,H63-$D$32)*H68+$B$33*MAX(0,H64-$D$33)*H69+$B$34*MAX(0,H65-$D$34)*H70)/1000 -> 14.39362 | I76: =$G$44*$C$21*($B$30*MAX(0,I61-$D$30)*I66+$B$31*MAX(0,I62-$D$31)*I67+$B$32*MAX(0,I63-$D$32)*I68+$B$33*MAX(0,I64-$D$33)*I69+$B$34*MAX(0,I65-$D$34)*I70)/1000 -> 18.386112 | J76: =$G$44*$C$21*($B$30*MAX(0,J61-$D$30)*J66+$B$31*MAX(0,J62-$D$31)*J67+$B$32*MAX(0,J63-$D$32)*J68+$B$33*MAX(0,J64-$D$33)*J69+$B$34*MAX(0,J65-$D$34)*J70)/1000 -> 22.829423 | ... L76: =$G$44*$C$21*($B$30*MAX(0,L61-$D$30)*L66+$B$31*MAX(0,L62-$D$31)*L67+$B$32*MAX(0,L63-$D$32)*L68+$B$33*MAX(0,L64-$D$33)*L69+$B$34*MAX(0,L65-$D$34)*L70)/1000 -> 33.22945 | M76: =SUM(D76:L76) -> 142.03948
A77: Fuites (erreur d'inclusion) | B77: Mds FCFA | C77: =IFERROR(C76*$C$20/(1-$C$20),0) -> 0 | D77: =IFERROR(D76*$C$20/(1-$C$20),0) -> 0.74588889 | E77: =IFERROR(E76*$C$20/(1-$C$20),0) -> 1.5892333 | F77: =IFERROR(F76*$C$20/(1-$C$20),0) -> 2.5390575 | G77: =IFERROR(G76*$C$20/(1-$C$20),0) -> 3.6051015 | H77: =IFERROR(H76*$C$20/(1-$C$20),0) -> 4.7978733 | I77: =IFERROR(I76*$C$20/(1-$C$20),0) -> 6.1287041 | J77: =IFERROR(J76*$C$20/(1-$C$20),0) -> 7.6098075 | ... L77: =IFERROR(L76*$C$20/(1-$C$20),0) -> 11.076483 | M77: =SUM(D77:L77) -> 47.346493
A78: Coût administratif du ciblage | B78: Mds FCFA | C78: =IF(0=0,0,$G$44*$C$18*$C$19/1000000000) -> 0 | D78: =IF(1=0,0,$G$44*$C$18*$C$19/1000000000) -> 1.2 | E78: =IF(2=0,0,$G$44*$C$18*$C$19/1000000000) -> 1.2 | F78: =IF(3=0,0,$G$44*$C$18*$C$19/1000000000) -> 1.2 | G78: =IF(4=0,0,$G$44*$C$18*$C$19/1000000000) -> 1.2 | H78: =IF(5=0,0,$G$44*$C$18*$C$19/1000000000) -> 1.2 | I78: =IF(6=0,0,$G$44*$C$18*$C$19/1000000000) -> 1.2 | J78: =IF(7=0,0,$G$44*$C$18*$C$19/1000000000) -> 1.2 | K78: =IF(8=0,0,$G$44*$C$18*$C$19/1000000000) -> 1.2 | L78: =IF(9=0,0,$G$44*$C$18*$C$19/1000000000) -> 1.2 | M78: =SUM(D78:L78) -> 10.8
A79: Aide sociale due (total) | B79: Mds FCFA | C79: =C76+C77+C78 -> 0 | D79: =D76+D77+D78 -> 4.1835556 | E79: =E76+E77+E78 -> 7.5569333 | F79: =F76+F77+F78 -> 11.35623 | G79: =G76+G77+G78 -> 15.620406 | H79: =H76+H77+H78 -> 20.391493 | I79: =I76+I77+I78 -> 25.714816 | J79: =J76+J77+J78 -> 31.63923 | ... L79: =L76+L77+L78 -> 45.505934 | M79: =SUM(D79:L79) -> 200.18597
A80: Aide sociale versée | B80: Mds FCFA | C80: =C79*$C$16 -> 0 | D80: =D79*$C$16 -> 2.9284889 | E80: =E79*$C$16 -> 5.2898533 | F80: =F79*$C$16 -> 7.949361 | G80: =G79*$C$16 -> 10.934284 | H80: =H79*$C$16 -> 14.274045 | I80: =I79*$C$16 -> 18.000371 | J80: =J79*$C$16 -> 22.147461 | ... L80: =L79*$C$16 -> 31.854154 | M80: =SUM(D80:L80) -> 140.13018
A81: Compensation tarifaire due à l'opérateur | B81: Mds FCFA | C81: =C74*$C$15 -> 28.125 | D81: =D74*$C$15 -> 26.638889 | E81: =E74*$C$15 -> 24.831771 | F81: =F74*$C$15 -> 22.670156 | G81: =G74*$C$15 -> 20.117754 | H81: =H74*$C$15 -> 17.135262 | I81: =I74*$C$15 -> 13.680143 | J81: =J74*$C$15 -> 9.7063872 | ... L81: =L74*$C$15 -> 0 | M81: =SUM(D81:L81) -> 139.94462
A82: Compensation tarifaire versée | B82: Mds FCFA | C82: =C81*$C$16 -> 19.6875 | D82: =D81*$C$16 -> 18.647222 | E82: =E81*$C$16 -> 17.38224 | F82: =F81*$C$16 -> 15.869109 | G82: =G81*$C$16 -> 14.082428 | H82: =H81*$C$16 -> 11.994683 | I82: =I81*$C$16 -> 9.5761001 | J82: =J81*$C$16 -> 6.794471 | ... L82: =L81*$C$16 -> 0 | M82: =SUM(D82:L82) -> 97.961231
A83: Subventions au raccordement versées | B83: Mds FCFA | C83: =IF(0=0,0,$G$48*$C$22/1000000000*$C$16) -> 0 | D83: =IF(1=0,0,$G$48*$C$22/1000000000*$C$16) -> 8.4 | E83: =IF(2=0,0,$G$48*$C$22/1000000000*$C$16) -> 8.4 | F83: =IF(3=0,0,$G$48*$C$22/1000000000*$C$16) -> 8.4 | G83: =IF(4=0,0,$G$48*$C$22/1000000000*$C$16) -> 8.4 | H83: =IF(5=0,0,$G$48*$C$22/1000000000*$C$16) -> 8.4 | I83: =IF(6=0,0,$G$48*$C$22/1000000000*$C$16) -> 8.4 | J83: =IF(7=0,0,$G$48*$C$22/1000000000*$C$16) -> 8.4 | K83: =IF(8=0,0,$G$48*$C$22/1000000000*$C$16) -> 8.4 | L83: =IF(9=0,0,$G$48*$C$22/1000000000*$C$16) -> 8.4 | M83: =SUM(D83:L83) -> 75.6
A84: Part de l'aide transitant par la facture | B84: Mds FCFA | C84: =(C76+C77)*$C$17 -> 0 | D84: =(D76+D77)*$C$17 -> 2.9835556 | E84: =(E76+E77)*$C$17 -> 6.3569333 | F84: =(F76+F77)*$C$17 -> 10.15623 | G84: =(G76+G77)*$C$17 -> 14.420406 | H84: =(H76+H77)*$C$17 -> 19.191493 | I84: =(I76+I77)*$C$17 -> 24.514816 | J84: =(J76+J77)*$C$17 -> 30.43923 | ... L84: =(L76+L77)*$C$17 -> 44.305934 | M84: =SUM(D84:L84) -> 189.38597
A85: Recettes encaissées par l'opérateur (hors compensations) | B85: Mds FCFA | C85: =(C71-C84)*C59+C84*$C$16 -> 202.725 | D85: =(D71-D84)*D59+D84*$C$16 -> 222.86913 | E85: =(E71-E84)*E59+E84*$C$16 -> 244.7844 | F85: =(F71-F84)*F59+F84*$C$16 -> 268.61314 | G85: =(G71-G84)*G59+G84*$C$16 -> 294.50842 | H85: =(H71-H84)*H59+H84*$C$16 -> 322.63477 | I85: =(I71-I84)*I59+I84*$C$16 -> 353.169 | J85: =(J71-J84)*J59+J84*$C$16 -> 386.30112 | ... L85: =(L71-L84)*L59+L84*$C$16 -> 461.19049 | M85: =SUM(D85:L85) -> 2976.3057
A86: Résultat d'exploitation de l'opérateur | B86: Mds FCFA | C86: =C85+C82-C72-C73 -> -84.3375 | D86: =D85+D82-D72-D73 -> -82.169478 | E86: =E85+E82-E72-E73 -> -79.381738 | F86: =F85+F82-F72-F73 -> -75.905707 | G86: =G85+G82-G72-G73 -> -71.666778 | H86: =H85+H82-H72-H73 -> -66.583841 | I86: =I85+I82-I72-I73 -> -60.568774 | J86: =J85+J82-J72-J73 -> -53.525896 | ... L86: =L85+L82-L72-L73 -> -35.93264 | M86: =SUM(D86:L86) -> -571.08624
A87: dont coût d'inefficience (pertes excédentaires + non-recouvrement) | B87: Mds FCFA | C87: =C73+(C71-C84)*(1-C59) -> 59.775 | D87: =D73+(D71-D84)*(1-D59) -> 58.009781 | E87: =E73+(E71-E84)*(1-E59) -> 55.788245 | F87: =F73+(F71-F84)*(1-F59) -> 53.060235 | G87: =G73+(G71-G84)*(1-G59) -> 49.771151 | H87: =H73+(H71-H84)*(1-H59) -> 45.861598 | I87: =I73+(I71-I84)*(1-I59) -> 41.267004 | J87: =J73+(J71-J84)*(1-J59) -> 35.917216 | ... L87: =L73+(L71-L84)*(1-L59) -> 22.64086 | M87: =SUM(D87:L87) -> 392.05215
A89: Coût total de la politique tarifaire : CTPT = SB + DC + CI + CE
A90: SB — subventions budgétaires versées | B90: Mds FCFA | C90: =C82+C80+C83 -> 19.6875 | D90: =D82+D80+D83 -> 29.975711 | E90: =E82+E80+E83 -> 31.072093 | F90: =F82+F80+F83 -> 32.21847 | G90: =G82+G80+G83 -> 33.416712 | H90: =H82+H80+H83 -> 34.668728 | I90: =I82+I80+I83 -> 35.976471 | J90: =J82+J80+J83 -> 37.341932 | ... L90: =L82+L80+L83 -> 40.254154 | M90: =SUM(D90:L90) -> 313.69141
A91: DC — déficit de compensation non financé | B91: Mds FCFA | C91: =MAX(0,C74-C82)+(C76+C77)*$C$17*(1-$C$16) -> 36.5625 | D91: =MAX(0,D74-D82)+(D76+D77)*$C$17*(1-$C$16) -> 35.525622 | E91: =MAX(0,E74-E82)+(E76+E77)*$C$17*(1-$C$16) -> 34.188382 | F91: =MAX(0,F74-F82)+(F76+F77)*$C$17*(1-$C$16) -> 32.518072 | G91: =MAX(0,G74-G82)+(G76+G77)*$C$17*(1-$C$16) -> 30.479202 | H91: =MAX(0,H74-H82)+(H76+H77)*$C$17*(1-$C$16) -> 28.033288 | I91: =MAX(0,I74-I82)+(I76+I77)*$C$17*(1-$C$16) -> 25.138631 | J91: =MAX(0,J74-J82)+(J76+J77)*$C$17*(1-$C$16) -> 21.750072 | ... L91: =MAX(0,L74-L82)+(L76+L77)*$C$17*(1-$C$16) -> 13.29178 | M91: =SUM(D91:L91) -> 238.74379
A92: CI — coûts indirects (dégradation du service) | B92: Mds FCFA | C92: =$C$23*(1-$G$49*C$55) -> 50 | D92: =$C$23*(1-$G$49*D$55) -> 47.222222 | E92: =$C$23*(1-$G$49*E$55) -> 44.444444 | F92: =$C$23*(1-$G$49*F$55) -> 41.666667 | G92: =$C$23*(1-$G$49*G$55) -> 38.888889 | H92: =$C$23*(1-$G$49*H$55) -> 36.111111 | I92: =$C$23*(1-$G$49*I$55) -> 33.333333 | J92: =$C$23*(1-$G$49*J$55) -> 30.555556 | ... L92: =$C$23*(1-$G$49*L$55) -> 25 | M92: =SUM(D92:L92) -> 325
A93: CE — surcoûts des entreprises | B93: Mds FCFA | C93: =$C$24*(1-$G$50*C$55) -> 80 | D93: =$C$24*(1-$G$50*D$55) -> 74.666667 | E93: =$C$24*(1-$G$50*E$55) -> 69.333333 | F93: =$C$24*(1-$G$50*F$55) -> 64 | G93: =$C$24*(1-$G$50*G$55) -> 58.666667 | H93: =$C$24*(1-$G$50*H$55) -> 53.333333 | I93: =$C$24*(1-$G$50*I$55) -> 48 | J93: =$C$24*(1-$G$50*J$55) -> 42.666667 | ... L93: =$C$24*(1-$G$50*L$55) -> 32 | M93: =SUM(D93:L93) -> 480
A94: CTPT — coût total de la politique tarifaire | B94: Mds FCFA | C94: =C90+C91+C92+C93 -> 186.25 | D94: =D90+D91+D92+D93 -> 187.39022 | E94: =E90+E91+E92+E93 -> 179.03825 | F94: =F90+F91+F92+F93 -> 170.40321 | G94: =G90+G91+G92+G93 -> 161.45147 | H94: =H90+H91+H92+H93 -> 152.14646 | I94: =I90+I91+I92+I93 -> 142.44844 | J94: =J90+J91+J92+J93 -> 132.31423 | ... L94: =L90+L91+L92+L93 -> 110.54593 | M94: =SUM(D94:L94) -> 1357.4352
A95: Anti-double comptage : DC ne contient que la sous-tarification non compensée et l'aide due non versée. Les pertes excédentaires et le non-recouvrement relèvent de la performance de l'opérateur (ligne « inefficience »), pas du CTPT. CI et CE doivent être estimés sur des périmètres disjoints.
A97: Indice du tarif industriel HT (base = 100) | B97: indice | C97: =IFERROR(C65/$C$65*100,0) -> 100 | D97: =IFERROR(D65/$C$65*100,0) -> 98.412698 | E97: =IFERROR(E65/$C$65*100,0) -> 96.825397 | F97: =IFERROR(F65/$C$65*100,0) -> 95.238095 | G97: =IFERROR(G65/$C$65*100,0) -> 93.650794 | H97: =IFERROR(H65/$C$65*100,0) -> 92.063492 | I97: =IFERROR(I65/$C$65*100,0) -> 90.47619 | J97: =IFERROR(J65/$C$65*100,0) -> 88.888889 | ... L97: =IFERROR(L65/$C$65*100,0) -> 85.714286
A98: Effet sur le coût de production industriel | B98: % coût | C98: =$C$25*(C97/100-1) -> 0 | D98: =$C$25*(D97/100-1) -> -0.0023809524 | E98: =$C$25*(E97/100-1) -> -0.0047619048 | F98: =$C$25*(F97/100-1) -> -0.0071428571 | G98: =$C$25*(G97/100-1) -> -0.0095238095 | H98: =$C$25*(H97/100-1) -> -0.011904762 | I98: =$C$25*(I97/100-1) -> -0.014285714 | J98: =$C$25*(J97/100-1) -> -0.016666667 | ... L98: =$C$25*(L97/100-1) -> -0.021428571
A99: Indice du tarif de la tranche sociale (base = 100) | B99: indice | C99: =IFERROR(C61/$C$61*100,0) -> 100 | D99: =IFERROR(D61/$C$61*100,0) -> 113.33333 | E99: =IFERROR(E61/$C$61*100,0) -> 126.66667 | F99: =IFERROR(F61/$C$61*100,0) -> 140 | G99: =IFERROR(G61/$C$61*100,0) -> 153.33333 | H99: =IFERROR(H61/$C$61*100,0) -> 166.66667 | I99: =IFERROR(I61/$C$61*100,0) -> 180 | J99: =IFERROR(J61/$C$61*100,0) -> 193.33333 | ... L99: =IFERROR(L61/$C$61*100,0) -> 220
A100: Hausse non compensée pour les ménages sociaux exclus du ciblage | B100: Mds FCFA | C100: =(1-$G$44*$C$21)*MAX(0,C61-$D$30)*C66/1000 -> 0 | D100: =(1-$G$44*$C$21)*MAX(0,D61-$D$30)*D66/1000 -> 0.959 | E100: =(1-$G$44*$C$21)*MAX(0,E61-$D$30)*E66/1000 -> 2.0433 | F100: =(1-$G$44*$C$21)*MAX(0,F61-$D$30)*F66/1000 -> 3.2645025 | G100: =(1-$G$44*$C$21)*MAX(0,G61-$D$30)*G66/1000 -> 4.6351305 | H100: =(1-$G$44*$C$21)*MAX(0,H61-$D$30)*H66/1000 -> 6.1686942 | I100: =(1-$G$44*$C$21)*MAX(0,I61-$D$30)*I66/1000 -> 7.8797624 | J100: =(1-$G$44*$C$21)*MAX(0,J61-$D$30)*J66/1000 -> 9.7840383 | ... L100: =(1-$G$44*$C$21)*MAX(0,L61-$D$30)*L66/1000 -> 14.241193 | M100: =SUM(D100:L100) -> 60.874062

Sheet Equite_H2
A1: Incidence distributive de la subvention résidentielle (test de H2)
A2: Source attendue : enquête ménages représentative (consommation, raccordement, quintile de revenu ou de dépenses). Les ménages non raccordés reçoivent 0.
A5: Cameroun
A6: Seuil de la tranche sociale | B6: kWh/mois
A7: Structure (1 = progressive : chacun paie la 1re tranche au tarif social ; 0 = tarif social seulement si conso ≤ seuil)
A8: Tarif social / tarif autres tranches / coût BT résidentiel | B8: FCFA/kWh | C8: =Cameroun!$D$30 -> 0 | D8: =Cameroun!$D$31 -> 0 | E8: =Cameroun!$E$31 -> 0 | F8: Liés à la feuille pays (base).
A9: Quintile | B9: Ménages | C9: Taux de raccordement | D9: Conso. raccordés (kWh/mois) | E9: Subvention / ménage raccordé (FCFA/an) | F9: Subvention totale (Mds FCFA) | G9: Part de la subvention | H9: Part des ménages
A10: Q1 (plus pauvres) | E10: =12*IF($C$7=1,MIN(D10,$C$6)*($E$8-$C$8)+MAX(0,D10-$C$6)*($E$8-$D$8),IF(D10<=$C$6,D10*($E$8-$C$8),D10*($E$8-$D$8))) -> 0 | F10: =B10*C10*E10/1000000000 -> 0 | G10: =IFERROR(F10/SUM($F$10:$F$14),0) -> 0 | H10: =IFERROR(B10/SUM($B$10:$B$14),0) -> 0
A11: Q2 | E11: =12*IF($C$7=1,MIN(D11,$C$6)*($E$8-$C$8)+MAX(0,D11-$C$6)*($E$8-$D$8),IF(D11<=$C$6,D11*($E$8-$C$8),D11*($E$8-$D$8))) -> 0 | F11: =B11*C11*E11/1000000000 -> 0 | G11: =IFERROR(F11/SUM($F$10:$F$14),0) -> 0 | H11: =IFERROR(B11/SUM($B$10:$B$14),0) -> 0
A12: Q3 | E12: =12*IF($C$7=1,MIN(D12,$C$6)*($E$8-$C$8)+MAX(0,D12-$C$6)*($E$8-$D$8),IF(D12<=$C$6,D12*($E$8-$C$8),D12*($E$8-$D$8))) -> 0 | F12: =B12*C12*E12/1000000000 -> 0 | G12: =IFERROR(F12/SUM($F$10:$F$14),0) -> 0 | H12: =IFERROR(B12/SUM($B$10:$B$14),0) -> 0
A13: Q4 | E13: =12*IF($C$7=1,MIN(D13,$C$6)*($E$8-$C$8)+MAX(0,D13-$C$6)*($E$8-$D$8),IF(D13<=$C$6,D13*($E$8-$C$8),D13*($E$8-$D$8))) -> 0 | F13: =B13*C13*E13/1000000000 -> 0 | G13: =IFERROR(F13/SUM($F$10:$F$14),0) -> 0 | H13: =IFERROR(B13/SUM($B$10:$B$14),0) -> 0
A14: Q5 (plus riches) | E14: =12*IF($C$7=1,MIN(D14,$C$6)*($E$8-$C$8)+MAX(0,D14-$C$6)*($E$8-$D$8),IF(D14<=$C$6,D14*($E$8-$C$8),D14*($E$8-$D$8))) -> 0 | F14: =B14*C14*E14/1000000000 -> 0 | G14: =IFERROR(F14/SUM($F$10:$F$14),0) -> 0 | H14: =IFERROR(B14/SUM($B$10:$B$14),0) -> 0
A15: Total | B15: =SUM(B10:B14) -> 0 | F15: =SUM(F10:F14) -> 0
A16: Part de la subvention captée par Q1+Q2 (40 % les plus pauvres) | C16: =G10+G11 -> 0
A17: Part captée par Q5 (20 % les plus riches) | C17: =G14 -> 0
A18: H2 soutenue si la part de Q5 dépasse celle de Q1+Q2 (1 = oui) | C18: =IF(F15=0,"n.d.",IF(G14>G10+G11,1,0)) -> n.d.
A19: Lecture : subvention négative = la catégorie paie plus que le coût BT retenu. Test indicatif, à compléter par des intervalles de confiance d'enquête.
A21: Congo
A22: Seuil de la tranche sociale | B22: kWh/mois
A23: Structure (1 = progressive : chacun paie la 1re tranche au tarif social ; 0 = tarif social seulement si conso ≤ seuil)
A24: Tarif social / tarif autres tranches / coût BT résidentiel | B24: FCFA/kWh | C24: =Congo!$D$30 -> 0 | D24: =Congo!$D$31 -> 0 | E24: =Congo!$E$31 -> 0 | F24: Liés à la feuille pays (base).
A25: Quintile | B25: Ménages | C25: Taux de raccordement | D25: Conso. raccordés (kWh/mois) | E25: Subvention / ménage raccordé (FCFA/an) | F25: Subvention totale (Mds FCFA) | G25: Part de la subvention | H25: Part des ménages
A26: Q1 (plus pauvres) | E26: =12*IF($C$23=1,MIN(D26,$C$22)*($E$24-$C$24)+MAX(0,D26-$C$22)*($E$24-$D$24),IF(D26<=$C$22,D26*($E$24-$C$24),D26*($E$24-$D$24))) -> 0 | F26: =B26*C26*E26/1000000000 -> 0 | G26: =IFERROR(F26/SUM($F$26:$F$30),0) -> 0 | H26: =IFERROR(B26/SUM($B$26:$B$30),0) -> 0
A27: Q2 | E27: =12*IF($C$23=1,MIN(D27,$C$22)*($E$24-$C$24)+MAX(0,D27-$C$22)*($E$24-$D$24),IF(D27<=$C$22,D27*($E$24-$C$24),D27*($E$24-$D$24))) -> 0 | F27: =B27*C27*E27/1000000000 -> 0 | G27: =IFERROR(F27/SUM($F$26:$F$30),0) -> 0 | H27: =IFERROR(B27/SUM($B$26:$B$30),0) -> 0
A28: Q3 | E28: =12*IF($C$23=1,MIN(D28,$C$22)*($E$24-$C$24)+MAX(0,D28-$C$22)*($E$24-$D$24),IF(D28<=$C$22,D28*($E$24-$C$24),D28*($E$24-$D$24))) -> 0 | F28: =B28*C28*E28/1000000000 -> 0 | G28: =IFERROR(F28/SUM($F$26:$F$30),0) -> 0 | H28: =IFERROR(B28/SUM($B$26:$B$30),0) -> 0
A29: Q4 | E29: =12*IF($C$23=1,MIN(D29,$C$22)*($E$24-$C$24)+MAX(0,D29-$C$22)*($E$24-$D$24),IF(D29<=$C$22,D29*($E$24-$C$24),D29*($E$24-$D$24))) -> 0 | F29: =B29*C29*E29/1000000000 -> 0 | G29: =IFERROR(F29/SUM($F$26:$F$30),0) -> 0 | H29: =IFERROR(B29/SUM($B$26:$B$30),0) -> 0
A30: Q5 (plus riches) | E30: =12*IF($C$23=1,MIN(D30,$C$22)*($E$24-$C$24)+MAX(0,D30-$C$22)*($E$24-$D$24),IF(D30<=$C$22,D30*($E$24-$C$24),D30*($E$24-$D$24))) -> 0 | F30: =B30*C30*E30/1000000000 -> 0 | G30: =IFERROR(F30/SUM($F$26:$F$30),0) -> 0 | H30: =IFERROR(B30/SUM($B$26:$B$30),0) -> 0
A31: Total | B31: =SUM(B26:B30) -> 0 | F31: =SUM(F26:F30) -> 0
A32: Part de la subvention captée par Q1+Q2 (40 % les plus pauvres) | C32: =G26+G27 -> 0
A33: Part captée par Q5 (20 % les plus riches) | C33: =G30 -> 0
A34: H2 soutenue si la part de Q5 dépasse celle de Q1+Q2 (1 = oui) | C34: =IF(F31=0,"n.d.",IF(G30>G26+G27,1,0)) -> n.d.
A35: Lecture : subvention négative = la catégorie paie plus que le coût BT retenu. Test indicatif, à compléter par des intervalles de confiance d'enquête.
A37: Exemple_fictif
A38: Seuil de la tranche sociale | B38: kWh/mois | C38: 100
A39: Structure (1 = progressive : chacun paie la 1re tranche au tarif social ; 0 = tarif social seulement si conso ≤ seuil) | C39: 1
A40: Tarif social / tarif autres tranches / coût BT résidentiel | B40: FCFA/kWh | C40: =Exemple_fictif!$D$30 -> 50 | D40: =Exemple_fictif!$D$31 -> 80 | E40: =Exemple_fictif!$E$31 -> 110 | F40: Liés à la feuille pays (base).
A41: Quintile | B41: Ménages | C41: Taux de raccordement | D41: Conso. raccordés (kWh/mois) | E41: Subvention / ménage raccordé (FCFA/an) | F41: Subvention totale (Mds FCFA) | G41: Part de la subvention | H41: Part des ménages
A42: Q1 (plus pauvres) | B42: 600000 | C42: 0.2 | D42: 40 | E42: =12*IF($C$39=1,MIN(D42,$C$38)*($E$40-$C$40)+MAX(0,D42-$C$38)*($E$40-$D$40),IF(D42<=$C$38,D42*($E$40-$C$40),D42*($E$40-$D$40))) -> 28800 | F42: =B42*C42*E42/1000000000 -> 3.456 | G42: =IFERROR(F42/SUM($F$42:$F$46),0) -> 0.021276596 | H42: =IFERROR(B42/SUM($B$42:$B$46),0) -> 0.2
A43: Q2 | B43: 600000 | C43: 0.4 | D43: 60 | E43: =12*IF($C$39=1,MIN(D43,$C$38)*($E$40-$C$40)+MAX(0,D43-$C$38)*($E$40-$D$40),IF(D43<=$C$38,D43*($E$40-$C$40),D43*($E$40-$D$40))) -> 43200 | F43: =B43*C43*E43/1000000000 -> 10.368 | G43: =IFERROR(F43/SUM($F$42:$F$46),0) -> 0.063829787 | H43: =IFERROR(B43/SUM($B$42:$B$46),0) -> 0.2
A44: Q3 | B44: 600000 | C44: 0.6 | D44: 90 | E44: =12*IF($C$39=1,MIN(D44,$C$38)*($E$40-$C$40)+MAX(0,D44-$C$38)*($E$40-$D$40),IF(D44<=$C$38,D44*($E$40-$C$40),D44*($E$40-$D$40))) -> 64800 | F44: =B44*C44*E44/1000000000 -> 23.328 | G44: =IFERROR(F44/SUM($F$42:$F$46),0) -> 0.14361702 | H44: =IFERROR(B44/SUM($B$42:$B$46),0) -> 0.2
A45: Q4 | B45: 600000 | C45: 0.8 | D45: 150 | E45: =12*IF($C$39=1,MIN(D45,$C$38)*($E$40-$C$40)+MAX(0,D45-$C$38)*($E$40-$D$40),IF(D45<=$C$38,D45*($E$40-$C$40),D45*($E$40-$D$40))) -> 90000 | F45: =B45*C45*E45/1000000000 -> 43.2 | G45: =IFERROR(F45/SUM($F$42:$F$46),0) -> 0.26595745 | H45: =IFERROR(B45/SUM($B$42:$B$46),0) -> 0.2
A46: Q5 (plus riches) | B46: 600000 | C46: 0.95 | D46: 300 | E46: =12*IF($C$39=1,MIN(D46,$C$38)*($E$40-$C$40)+MAX(0,D46-$C$38)*($E$40-$D$40),IF(D46<=$C$38,D46*($E$40-$C$40),D46*($E$40-$D$40))) -> 144000 | F46: =B46*C46*E46/1000000000 -> 82.08 | G46: =IFERROR(F46/SUM($F$42:$F$46),0) -> 0.50531915 | H46: =IFERROR(B46/SUM($B$42:$B$46),0) -> 0.2
A47: Total | B47: =SUM(B42:B46) -> 3000000 | F47: =SUM(F42:F46) -> 162.432
A48: Part de la subvention captée par Q1+Q2 (40 % les plus pauvres) | C48: =G42+G43 -> 0.085106383
A49: Part captée par Q5 (20 % les plus riches) | C49: =G46 -> 0.50531915
A50: H2 soutenue si la part de Q5 dépasse celle de Q1+Q2 (1 = oui) | C50: =IF(F47=0,"n.d.",IF(G46>G42+G43,1,0)) -> 1
A51: Lecture : subvention négative = la catégorie paie plus que le coût BT retenu. Test indicatif, à compléter par des intervalles de confiance d'enquête.
