Workbook

Sheet Guide
A1: AFRICA ENERGY FINANCE | BOOK 2 | PAYGO SOLAR FINANCE
A2: Unit economics calculator
A3: How to use this template
A4: Decision tool D2 | Version 0.9 (pre-release) | Author & ideation: Emmanuel Boujieka Kamga
A6: Purpose
A7: Builds the expected lifetime cash flow of one PAYGo sale month by month from the repayment curve, and derives expected loss, contribution, LTV to CAC, cash payback, peak funding, unit IRR and unit NPV, with a sensitivity grid on default hazard and collection rate. A second sheet compares the five default tiers in closed form.
A11: How to use it
A12: Step 1 | B12: Enter the price plan, credit behaviour, recovery and cost inputs on Inputs (blue cells).
A13: Step 2 | B13: Read Results: contribution and LTV to CAC, but also payback, peak funding and unit IRR, which carry the timing.
A14: Step 3 | B14: Use the sensitivity grid to see how contribution moves with the default hazard and the collection rate.
A15: Step 4 | B15: Check that the closed form check on Results reads zero difference; it confirms the monthly table.
A16: Step 5 | B16: Use Tier_Dashboard to compare tiers; replace the default tier inputs with the company's own.
A18: Colour code
A19: Input | B19: Blue font on cream: the only cells to edit
A20: Formula | B20: Black font: calculated, do not overwrite
A22: Links to Book 2 and MODEL 2
A23: Book | B23: Chapter 1 (one Tier 2 sale), Chapter 6 (survival curve), Chapter 9 (unit economics)
A24: Model | B24: Curves, Unit_Economics
A25: Default inputs | B25: Reproduce the worked example of Chapter 1: expected collections LCY 33,832, payback in month 14 and lifetime cash of LCY 11,832, with servicing, fees and recoveries set to zero. Add them for a full view.
A27: Decision support material; not investment, legal, tax or accounting advice. Example values are illustrative and refer to the book's worked examples or to the fictional SolaraPay case. (c) 2026 Emmanuel Boujieka Kamga.

Sheet Inputs
A1: AFRICA ENERGY FINANCE | BOOK 2 | PAYGO SOLAR FINANCE
A2: Unit inputs
A3: One product, local currency
A4: Decision tool D2 | Version 0.9 (pre-release) | Author & ideation: Emmanuel Boujieka Kamga
A6: Inputs
A7: Cash price | B7: 40000
A8: Deposit | B8: 4000
A9: Daily rate | B9: 72
A10: Tenor (months) | B10: 24 | D10: Up to 48 months
A11: Monthly default hazard | B11: 0.026 | D11: Share of paying accounts that stop for good each month
A12: Collection rate on paying accounts | B12: 0.88
A13: Repossession rate of defaulted units | B13: 0 | D13: Chapter 1 example: no recoveries
A14: Repossession lag (months) | B14: 3
A15: Resale value as share of cash price | B15: 0.25
A16: Recovery cost as share of resale proceeds | B16: 0.15
A17: Landed hardware cost | B17: 22000
A18: Installation | B18: 0
A19: Warranty provision, share of landed cost | B19: 0
A20: Customer acquisition cost (commission and marketing) | B20: 4000
A21: Servicing cost per active account per month | B21: 0 | D21: Model default 150
A22: Payment fees, share of cash collected | B22: 0 | D22: Model default 2%
A23: RBF per unit (local currency) | B23: 0
A24: Month RBF is received | B24: 6
A25: Discount rate (annual) for unit NPV | B25: 0.25
A27: Derived
A28: Monthly instalment | B28: ='Inputs'!$B$9*365/12
A29: Scheduled instalments | B29: ='Inputs'!$B$28*'Inputs'!$B$10
A30: Day one outlay (hardware, installation, warranty, CAC) | B30: ='Inputs'!$B$17*(1+'Inputs'!$B$19)+'Inputs'!$B$18+'Inputs'!$B$20
A31: Check: tenor plus repossession lag within 60 months | B31: =IF('Inputs'!$B$10+'Inputs'!$B$14<=60,"OK","Reduce tenor or lag")

Sheet Results
A1: AFRICA ENERGY FINANCE | BOOK 2 | PAYGO SOLAR FINANCE
A2: Unit economics results
A3: Expected values per unit sold
A4: Decision tool D2 | Version 0.9 (pre-release) | Author & ideation: Emmanuel Boujieka Kamga
A7: Expected instalments collected | B7: =SUM(Unit_Cash_Flow!$D$7:$D$67)
A8: Expected loss rate (missed ÷ scheduled instalments) | B8: =IF('Inputs'!$B$29=0,0,1-SUM(Unit_Cash_Flow!$D$7:$D$67)/'Inputs'!$B$29)
A9: Expected recoveries | B9: =SUM(Unit_Cash_Flow!$G$7:$G$67)
A10: Lifetime contribution (undiscounted) | B10: =SUM(Unit_Cash_Flow!$L$7:$L$67)
A11: Customer acquisition cost | B11: ='Inputs'!$B$20
A12: LTV (contribution before CAC) | B12: =B10+B11
A13: LTV to CAC | B13: =IF(B11=0,"",B12/B11)
A14: Cash payback (month) | B14: =IFERROR(INDEX(Unit_Cash_Flow!$A$7:$A$67,MATCH(1,Unit_Cash_Flow!$P$7:$P$67,0)),"Not within 60 months")
A15: Peak funding per unit | B15: =-MIN(Unit_Cash_Flow!$M$7:$M$67)
A16: Unit IRR (annualised) | B16: =IFERROR((1+IRR(Unit_Cash_Flow!$L$7:$L$67))^12-1,"")
A17: Unit NPV at the discount rate | B17: =SUM(Unit_Cash_Flow!$O$7:$O$67)
A19: Closed form contribution (check) | B19: =('Inputs'!$B$8+'Inputs'!$B$28*MIN(1,'Inputs'!$B$12*1)*(1-'Inputs'!$B$11*1)*(1-(1-'Inputs'!$B$11*1)^'Inputs'!$B$10)/('Inputs'!$B$11*1)+(1-(1-'Inputs'!$B$11*1)^'Inputs'!$B$10)*'Inputs'!$B$13*'Inputs'!$B$15*'Inputs'!$B$7*(1-'Inputs'!$B$16))*(1-'Inputs'!$B$22)-'Inputs'!$B$21*(1-'Inputs'!$B$11*1)*(1-(1-'Inputs'!$B$11*1)^'Inputs'!$B$10)/('Inputs'!$B$11*1)+'Inputs'!$B$23-'Inputs'!$B$30
A20: Difference with the monthly table | B20: =IF(ABS(B19-B10)<1,"OK: "&TEXT(B19-B10,"0.00"),"Check inputs: "&TEXT(B19-B10,"0"))
A22: Sensitivity: lifetime contribution
A23: Default hazard multiplier (rows) × collection rate multiplier (columns)
A24: Hazard multiplier | B24: Monthly hazard | D24: 0.9 | E24: 0.95 | F24: 1
A25: 0.5 | B25: ='Inputs'!$B$11*A25 | D25: =('Inputs'!$B$8+'Inputs'!$B$28*MIN(1,'Inputs'!$B$12*D$24)*(1-'Inputs'!$B$11*$A25)*(1-(1-'Inputs'!$B$11*$A25)^'Inputs'!$B$10)/('Inputs'!$B$11*$A25)+(1-(1-'Inputs'!$B$11*$A25)^'Inputs'!$B$10)*'Inputs'!$B$13*'Inputs'!$B$15*'Inputs'!$B$7*(1-'Inputs'!$B$16))*(1-'Inputs'!$B$22)-'Inputs'!$B$21*(1-'Inputs'!$B$11*$A25)*(1-(1-'Inputs'!$B$11*$A25)^'Inputs'!$B$10)/('Inputs'!$B$11*$A25)+'Inputs'!$B$23-'Inputs'!$B$30 | E25: =('Inputs'!$B$8+'Inputs'!$B$28*MIN(1,'Inputs'!$B$12*E$24)*(1-'Inputs'!$B$11*$A25)*(1-(1-'Inputs'!$B$11*$A25)^'Inputs'!$B$10)/('Inputs'!$B$11*$A25)+(1-(1-'Inputs'!$B$11*$A25)^'Inputs'!$B$10)*'Inputs'!$B$13*'Inputs'!$B$15*'Inputs'!$B$7*(1-'Inputs'!$B$16))*(1-'Inputs'!$B$22)-'Inputs'!$B$21*(1-'Inputs'!$B$11*$A25)*(1-(1-'Inputs'!$B$11*$A25)^'Inputs'!$B$10)/('Inputs'!$B$11*$A25)+'Inputs'!$B$23-'Inputs'!$B$30 | F25: =('Inputs'!$B$8+'Inputs'!$B$28*MIN(1,'Inputs'!$B$12*F$24)*(1-'Inputs'!$B$11*$A25)*(1-(1-'Inputs'!$B$11*$A25)^'Inputs'!$B$10)/('Inputs'!$B$11*$A25)+(1-(1-'Inputs'!$B$11*$A25)^'Inputs'!$B$10)*'Inputs'!$B$13*'Inputs'!$B$15*'Inputs'!$B$7*(1-'Inputs'!$B$16))*(1-'Inputs'!$B$22)-'Inputs'!$B$21*(1-'Inputs'!$B$11*$A25)*(1-(1-'Inputs'!$B$11*$A25)^'Inputs'!$B$10)/('Inputs'!$B$11*$A25)+'Inputs'!$B$23-'Inputs'!$B$30
A26: 0.75 | B26: ='Inputs'!$B$11*A26 | D26: =('Inputs'!$B$8+'Inputs'!$B$28*MIN(1,'Inputs'!$B$12*D$24)*(1-'Inputs'!$B$11*$A26)*(1-(1-'Inputs'!$B$11*$A26)^'Inputs'!$B$10)/('Inputs'!$B$11*$A26)+(1-(1-'Inputs'!$B$11*$A26)^'Inputs'!$B$10)*'Inputs'!$B$13*'Inputs'!$B$15*'Inputs'!$B$7*(1-'Inputs'!$B$16))*(1-'Inputs'!$B$22)-'Inputs'!$B$21*(1-'Inputs'!$B$11*$A26)*(1-(1-'Inputs'!$B$11*$A26)^'Inputs'!$B$10)/('Inputs'!$B$11*$A26)+'Inputs'!$B$23-'Inputs'!$B$30 | E26: =('Inputs'!$B$8+'Inputs'!$B$28*MIN(1,'Inputs'!$B$12*E$24)*(1-'Inputs'!$B$11*$A26)*(1-(1-'Inputs'!$B$11*$A26)^'Inputs'!$B$10)/('Inputs'!$B$11*$A26)+(1-(1-'Inputs'!$B$11*$A26)^'Inputs'!$B$10)*'Inputs'!$B$13*'Inputs'!$B$15*'Inputs'!$B$7*(1-'Inputs'!$B$16))*(1-'Inputs'!$B$22)-'Inputs'!$B$21*(1-'Inputs'!$B$11*$A26)*(1-(1-'Inputs'!$B$11*$A26)^'Inputs'!$B$10)/('Inputs'!$B$11*$A26)+'Inputs'!$B$23-'Inputs'!$B$30 | F26: =('Inputs'!$B$8+'Inputs'!$B$28*MIN(1,'Inputs'!$B$12*F$24)*(1-'Inputs'!$B$11*$A26)*(1-(1-'Inputs'!$B$11*$A26)^'Inputs'!$B$10)/('Inputs'!$B$11*$A26)+(1-(1-'Inputs'!$B$11*$A26)^'Inputs'!$B$10)*'Inputs'!$B$13*'Inputs'!$B$15*'Inputs'!$B$7*(1-'Inputs'!$B$16))*(1-'Inputs'!$B$22)-'Inputs'!$B$21*(1-'Inputs'!$B$11*$A26)*(1-(1-'Inputs'!$B$11*$A26)^'Inputs'!$B$10)/('Inputs'!$B$11*$A26)+'Inputs'!$B$23-'Inputs'!$B$30
A27: 1 | B27: ='Inputs'!$B$11*A27 | D27: =('Inputs'!$B$8+'Inputs'!$B$28*MIN(1,'Inputs'!$B$12*D$24)*(1-'Inputs'!$B$11*$A27)*(1-(1-'Inputs'!$B$11*$A27)^'Inputs'!$B$10)/('Inputs'!$B$11*$A27)+(1-(1-'Inputs'!$B$11*$A27)^'Inputs'!$B$10)*'Inputs'!$B$13*'Inputs'!$B$15*'Inputs'!$B$7*(1-'Inputs'!$B$16))*(1-'Inputs'!$B$22)-'Inputs'!$B$21*(1-'Inputs'!$B$11*$A27)*(1-(1-'Inputs'!$B$11*$A27)^'Inputs'!$B$10)/('Inputs'!$B$11*$A27)+'Inputs'!$B$23-'Inputs'!$B$30 | E27: =('Inputs'!$B$8+'Inputs'!$B$28*MIN(1,'Inputs'!$B$12*E$24)*(1-'Inputs'!$B$11*$A27)*(1-(1-'Inputs'!$B$11*$A27)^'Inputs'!$B$10)/('Inputs'!$B$11*$A27)+(1-(1-'Inputs'!$B$11*$A27)^'Inputs'!$B$10)*'Inputs'!$B$13*'Inputs'!$B$15*'Inputs'!$B$7*(1-'Inputs'!$B$16))*(1-'Inputs'!$B$22)-'Inputs'!$B$21*(1-'Inputs'!$B$11*$A27)*(1-(1-'Inputs'!$B$11*$A27)^'Inputs'!$B$10)/('Inputs'!$B$11*$A27)+'Inputs'!$B$23-'Inputs'!$B$30 | F27: =('Inputs'!$B$8+'Inputs'!$B$28*MIN(1,'Inputs'!$B$12*F$24)*(1-'Inputs'!$B$11*$A27)*(1-(1-'Inputs'!$B$11*$A27)^'Inputs'!$B$10)/('Inputs'!$B$11*$A27)+(1-(1-'Inputs'!$B$11*$A27)^'Inputs'!$B$10)*'Inputs'!$B$13*'Inputs'!$B$15*'Inputs'!$B$7*(1-'Inputs'!$B$16))*(1-'Inputs'!$B$22)-'Inputs'!$B$21*(1-'Inputs'!$B$11*$A27)*(1-(1-'Inputs'!$B$11*$A27)^'Inputs'!$B$10)/('Inputs'!$B$11*$A27)+'Inputs'!$B$23-'Inputs'!$B$30
A28: 1.3 | B28: ='Inputs'!$B$11*A28 | D28: =('Inputs'!$B$8+'Inputs'!$B$28*MIN(1,'Inputs'!$B$12*D$24)*(1-'Inputs'!$B$11*$A28)*(1-(1-'Inputs'!$B$11*$A28)^'Inputs'!$B$10)/('Inputs'!$B$11*$A28)+(1-(1-'Inputs'!$B$11*$A28)^'Inputs'!$B$10)*'Inputs'!$B$13*'Inputs'!$B$15*'Inputs'!$B$7*(1-'Inputs'!$B$16))*(1-'Inputs'!$B$22)-'Inputs'!$B$21*(1-'Inputs'!$B$11*$A28)*(1-(1-'Inputs'!$B$11*$A28)^'Inputs'!$B$10)/('Inputs'!$B$11*$A28)+'Inputs'!$B$23-'Inputs'!$B$30 | E28: =('Inputs'!$B$8+'Inputs'!$B$28*MIN(1,'Inputs'!$B$12*E$24)*(1-'Inputs'!$B$11*$A28)*(1-(1-'Inputs'!$B$11*$A28)^'Inputs'!$B$10)/('Inputs'!$B$11*$A28)+(1-(1-'Inputs'!$B$11*$A28)^'Inputs'!$B$10)*'Inputs'!$B$13*'Inputs'!$B$15*'Inputs'!$B$7*(1-'Inputs'!$B$16))*(1-'Inputs'!$B$22)-'Inputs'!$B$21*(1-'Inputs'!$B$11*$A28)*(1-(1-'Inputs'!$B$11*$A28)^'Inputs'!$B$10)/('Inputs'!$B$11*$A28)+'Inputs'!$B$23-'Inputs'!$B$30 | F28: =('Inputs'!$B$8+'Inputs'!$B$28*MIN(1,'Inputs'!$B$12*F$24)*(1-'Inputs'!$B$11*$A28)*(1-(1-'Inputs'!$B$11*$A28)^'Inputs'!$B$10)/('Inputs'!$B$11*$A28)+(1-(1-'Inputs'!$B$11*$A28)^'Inputs'!$B$10)*'Inputs'!$B$13*'Inputs'!$B$15*'Inputs'!$B$7*(1-'Inputs'!$B$16))*(1-'Inputs'!$B$22)-'Inputs'!$B$21*(1-'Inputs'!$B$11*$A28)*(1-(1-'Inputs'!$B$11*$A28)^'Inputs'!$B$10)/('Inputs'!$B$11*$A28)+'Inputs'!$B$23-'Inputs'!$B$30
A29: 1.5 | B29: ='Inputs'!$B$11*A29 | D29: =('Inputs'!$B$8+'Inputs'!$B$28*MIN(1,'Inputs'!$B$12*D$24)*(1-'Inputs'!$B$11*$A29)*(1-(1-'Inputs'!$B$11*$A29)^'Inputs'!$B$10)/('Inputs'!$B$11*$A29)+(1-(1-'Inputs'!$B$11*$A29)^'Inputs'!$B$10)*'Inputs'!$B$13*'Inputs'!$B$15*'Inputs'!$B$7*(1-'Inputs'!$B$16))*(1-'Inputs'!$B$22)-'Inputs'!$B$21*(1-'Inputs'!$B$11*$A29)*(1-(1-'Inputs'!$B$11*$A29)^'Inputs'!$B$10)/('Inputs'!$B$11*$A29)+'Inputs'!$B$23-'Inputs'!$B$30 | E29: =('Inputs'!$B$8+'Inputs'!$B$28*MIN(1,'Inputs'!$B$12*E$24)*(1-'Inputs'!$B$11*$A29)*(1-(1-'Inputs'!$B$11*$A29)^'Inputs'!$B$10)/('Inputs'!$B$11*$A29)+(1-(1-'Inputs'!$B$11*$A29)^'Inputs'!$B$10)*'Inputs'!$B$13*'Inputs'!$B$15*'Inputs'!$B$7*(1-'Inputs'!$B$16))*(1-'Inputs'!$B$22)-'Inputs'!$B$21*(1-'Inputs'!$B$11*$A29)*(1-(1-'Inputs'!$B$11*$A29)^'Inputs'!$B$10)/('Inputs'!$B$11*$A29)+'Inputs'!$B$23-'Inputs'!$B$30 | F29: =('Inputs'!$B$8+'Inputs'!$B$28*MIN(1,'Inputs'!$B$12*F$24)*(1-'Inputs'!$B$11*$A29)*(1-(1-'Inputs'!$B$11*$A29)^'Inputs'!$B$10)/('Inputs'!$B$11*$A29)+(1-(1-'Inputs'!$B$11*$A29)^'Inputs'!$B$10)*'Inputs'!$B$13*'Inputs'!$B$15*'Inputs'!$B$7*(1-'Inputs'!$B$16))*(1-'Inputs'!$B$22)-'Inputs'!$B$21*(1-'Inputs'!$B$11*$A29)*(1-(1-'Inputs'!$B$11*$A29)^'Inputs'!$B$10)/('Inputs'!$B$11*$A29)+'Inputs'!$B$23-'Inputs'!$B$30
A30: 2 | B30: ='Inputs'!$B$11*A30 | D30: =('Inputs'!$B$8+'Inputs'!$B$28*MIN(1,'Inputs'!$B$12*D$24)*(1-'Inputs'!$B$11*$A30)*(1-(1-'Inputs'!$B$11*$A30)^'Inputs'!$B$10)/('Inputs'!$B$11*$A30)+(1-(1-'Inputs'!$B$11*$A30)^'Inputs'!$B$10)*'Inputs'!$B$13*'Inputs'!$B$15*'Inputs'!$B$7*(1-'Inputs'!$B$16))*(1-'Inputs'!$B$22)-'Inputs'!$B$21*(1-'Inputs'!$B$11*$A30)*(1-(1-'Inputs'!$B$11*$A30)^'Inputs'!$B$10)/('Inputs'!$B$11*$A30)+'Inputs'!$B$23-'Inputs'!$B$30 | E30: =('Inputs'!$B$8+'Inputs'!$B$28*MIN(1,'Inputs'!$B$12*E$24)*(1-'Inputs'!$B$11*$A30)*(1-(1-'Inputs'!$B$11*$A30)^'Inputs'!$B$10)/('Inputs'!$B$11*$A30)+(1-(1-'Inputs'!$B$11*$A30)^'Inputs'!$B$10)*'Inputs'!$B$13*'Inputs'!$B$15*'Inputs'!$B$7*(1-'Inputs'!$B$16))*(1-'Inputs'!$B$22)-'Inputs'!$B$21*(1-'Inputs'!$B$11*$A30)*(1-(1-'Inputs'!$B$11*$A30)^'Inputs'!$B$10)/('Inputs'!$B$11*$A30)+'Inputs'!$B$23-'Inputs'!$B$30 | F30: =('Inputs'!$B$8+'Inputs'!$B$28*MIN(1,'Inputs'!$B$12*F$24)*(1-'Inputs'!$B$11*$A30)*(1-(1-'Inputs'!$B$11*$A30)^'Inputs'!$B$10)/('Inputs'!$B$11*$A30)+(1-(1-'Inputs'!$B$11*$A30)^'Inputs'!$B$10)*'Inputs'!$B$13*'Inputs'!$B$15*'Inputs'!$B$7*(1-'Inputs'!$B$16))*(1-'Inputs'!$B$22)-'Inputs'!$B$21*(1-'Inputs'!$B$11*$A30)*(1-(1-'Inputs'!$B$11*$A30)^'Inputs'!$B$10)/('Inputs'!$B$11*$A30)+'Inputs'!$B$23-'Inputs'!$B$30
A32: The grid uses the closed form, which matches the monthly table when the check above reads OK. The Downside scenario of the model raises the hazard by 1.30 times and lowers collections by 0.97 times.

Sheet Unit_Cash_Flow
A1: AFRICA ENERGY FINANCE | BOOK 2 | PAYGO SOLAR FINANCE
A2: Expected cash flow of one unit
A3: Months since sale; expected values
A4: Decision tool D2 | Version 0.9 (pre-release) | Author & ideation: Emmanuel Boujieka Kamga
A6: Month | B6: Share still paying | C6: Instalment due | D6: Collected | E6: Deposit | F6: Defaults in month | G6: Recoveries | H6: Servicing | I6: Payment fees | J6: RBF | K6: Day one outlay | L6: Net cash | M6: Cumulative | N6: Discount factor | O6: Present value | P6: Cumulative positive
A7: 0 | B7: =(1-'Inputs'!$B$11)^A7 | C7: =IF(AND(A7>=1,A7<='Inputs'!$B$10),'Inputs'!$B$28,0) | D7: =IF(AND(A7>=1,A7<='Inputs'!$B$10),'Inputs'!$B$28*'Inputs'!$B$12*B7,0) | E7: =IF(A7=0,'Inputs'!$B$8,0) | F7: =0 | G7: =IF(A7-'Inputs'!$B$14>=1,INDEX($F$7:$F$67,A7-'Inputs'!$B$14+1)*'Inputs'!$B$13*'Inputs'!$B$15*'Inputs'!$B$7*(1-'Inputs'!$B$16),0) | H7: =-IF(AND(A7>=1,A7<='Inputs'!$B$10),'Inputs'!$B$21*B7,0) | I7: =-'Inputs'!$B$22*(D7+E7+G7) | J7: =IF(A7='Inputs'!$B$24,'Inputs'!$B$23,0) | K7: =IF(A7=0,-'Inputs'!$B$30,0) | L7: =SUM(D7:K7)-F7 | M7: =L7 | N7: =(1+'Inputs'!$B$25)^(-A7/12) | O7: =L7*N7 | P7: =IF(AND(A7>=1,M7>=0),1,0)
A8: 1 | B8: =(1-'Inputs'!$B$11)^A8 | C8: =IF(AND(A8>=1,A8<='Inputs'!$B$10),'Inputs'!$B$28,0) | D8: =IF(AND(A8>=1,A8<='Inputs'!$B$10),'Inputs'!$B$28*'Inputs'!$B$12*B8,0) | E8: =IF(A8=0,'Inputs'!$B$8,0) | F8: =IF(AND(A8>=1,A8<='Inputs'!$B$10),B7-B8,0) | G8: =IF(A8-'Inputs'!$B$14>=1,INDEX($F$7:$F$67,A8-'Inputs'!$B$14+1)*'Inputs'!$B$13*'Inputs'!$B$15*'Inputs'!$B$7*(1-'Inputs'!$B$16),0) | H8: =-IF(AND(A8>=1,A8<='Inputs'!$B$10),'Inputs'!$B$21*B8,0) | I8: =-'Inputs'!$B$22*(D8+E8+G8) | J8: =IF(A8='Inputs'!$B$24,'Inputs'!$B$23,0) | K8: =IF(A8=0,-'Inputs'!$B$30,0) | L8: =SUM(D8:K8)-F8 | M8: =M7+L8 | N8: =(1+'Inputs'!$B$25)^(-A8/12) | O8: =L8*N8 | P8: =IF(AND(A8>=1,M8>=0),1,0)
A9: 2 | B9: =(1-'Inputs'!$B$11)^A9 | C9: =IF(AND(A9>=1,A9<='Inputs'!$B$10),'Inputs'!$B$28,0) | D9: =IF(AND(A9>=1,A9<='Inputs'!$B$10),'Inputs'!$B$28*'Inputs'!$B$12*B9,0) | E9: =IF(A9=0,'Inputs'!$B$8,0) | F9: =IF(AND(A9>=1,A9<='Inputs'!$B$10),B8-B9,0) | G9: =IF(A9-'Inputs'!$B$14>=1,INDEX($F$7:$F$67,A9-'Inputs'!$B$14+1)*'Inputs'!$B$13*'Inputs'!$B$15*'Inputs'!$B$7*(1-'Inputs'!$B$16),0) | H9: =-IF(AND(A9>=1,A9<='Inputs'!$B$10),'Inputs'!$B$21*B9,0) | I9: =-'Inputs'!$B$22*(D9+E9+G9) | J9: =IF(A9='Inputs'!$B$24,'Inputs'!$B$23,0) | K9: =IF(A9=0,-'Inputs'!$B$30,0) | L9: =SUM(D9:K9)-F9 | M9: =M8+L9 | N9: =(1+'Inputs'!$B$25)^(-A9/12) | O9: =L9*N9 | P9: =IF(AND(A9>=1,M9>=0),1,0)
A10: 3 | B10: =(1-'Inputs'!$B$11)^A10 | C10: =IF(AND(A10>=1,A10<='Inputs'!$B$10),'Inputs'!$B$28,0) | D10: =IF(AND(A10>=1,A10<='Inputs'!$B$10),'Inputs'!$B$28*'Inputs'!$B$12*B10,0) | E10: =IF(A10=0,'Inputs'!$B$8,0) | F10: =IF(AND(A10>=1,A10<='Inputs'!$B$10),B9-B10,0) | G10: =IF(A10-'Inputs'!$B$14>=1,INDEX($F$7:$F$67,A10-'Inputs'!$B$14+1)*'Inputs'!$B$13*'Inputs'!$B$15*'Inputs'!$B$7*(1-'Inputs'!$B$16),0) | H10: =-IF(AND(A10>=1,A10<='Inputs'!$B$10),'Inputs'!$B$21*B10,0) | I10: =-'Inputs'!$B$22*(D10+E10+G10) | J10: =IF(A10='Inputs'!$B$24,'Inputs'!$B$23,0) | K10: =IF(A10=0,-'Inputs'!$B$30,0) | L10: =SUM(D10:K10)-F10 | M10: =M9+L10 | N10: =(1+'Inputs'!$B$25)^(-A10/12) | O10: =L10*N10 | P10: =IF(AND(A10>=1,M10>=0),1,0)
A11: 4 | B11: =(1-'Inputs'!$B$11)^A11 | C11: =IF(AND(A11>=1,A11<='Inputs'!$B$10),'Inputs'!$B$28,0) | D11: =IF(AND(A11>=1,A11<='Inputs'!$B$10),'Inputs'!$B$28*'Inputs'!$B$12*B11,0) | E11: =IF(A11=0,'Inputs'!$B$8,0) | F11: =IF(AND(A11>=1,A11<='Inputs'!$B$10),B10-B11,0) | G11: =IF(A11-'Inputs'!$B$14>=1,INDEX($F$7:$F$67,A11-'Inputs'!$B$14+1)*'Inputs'!$B$13*'Inputs'!$B$15*'Inputs'!$B$7*(1-'Inputs'!$B$16),0) | H11: =-IF(AND(A11>=1,A11<='Inputs'!$B$10),'Inputs'!$B$21*B11,0) | I11: =-'Inputs'!$B$22*(D11+E11+G11) | J11: =IF(A11='Inputs'!$B$24,'Inputs'!$B$23,0) | K11: =IF(A11=0,-'Inputs'!$B$30,0) | L11: =SUM(D11:K11)-F11 | M11: =M10+L11 | N11: =(1+'Inputs'!$B$25)^(-A11/12) | O11: =L11*N11 | P11: =IF(AND(A11>=1,M11>=0),1,0)
A12: 5 | B12: =(1-'Inputs'!$B$11)^A12 | C12: =IF(AND(A12>=1,A12<='Inputs'!$B$10),'Inputs'!$B$28,0) | D12: =IF(AND(A12>=1,A12<='Inputs'!$B$10),'Inputs'!$B$28*'Inputs'!$B$12*B12,0) | E12: =IF(A12=0,'Inputs'!$B$8,0) | F12: =IF(AND(A12>=1,A12<='Inputs'!$B$10),B11-B12,0) | G12: =IF(A12-'Inputs'!$B$14>=1,INDEX($F$7:$F$67,A12-'Inputs'!$B$14+1)*'Inputs'!$B$13*'Inputs'!$B$15*'Inputs'!$B$7*(1-'Inputs'!$B$16),0) | H12: =-IF(AND(A12>=1,A12<='Inputs'!$B$10),'Inputs'!$B$21*B12,0) | I12: =-'Inputs'!$B$22*(D12+E12+G12) | J12: =IF(A12='Inputs'!$B$24,'Inputs'!$B$23,0) | K12: =IF(A12=0,-'Inputs'!$B$30,0) | L12: =SUM(D12:K12)-F12 | M12: =M11+L12 | N12: =(1+'Inputs'!$B$25)^(-A12/12) | O12: =L12*N12 | P12: =IF(AND(A12>=1,M12>=0),1,0)
A13: 6 | B13: =(1-'Inputs'!$B$11)^A13 | C13: =IF(AND(A13>=1,A13<='Inputs'!$B$10),'Inputs'!$B$28,0) | D13: =IF(AND(A13>=1,A13<='Inputs'!$B$10),'Inputs'!$B$28*'Inputs'!$B$12*B13,0) | E13: =IF(A13=0,'Inputs'!$B$8,0) | F13: =IF(AND(A13>=1,A13<='Inputs'!$B$10),B12-B13,0) | G13: =IF(A13-'Inputs'!$B$14>=1,INDEX($F$7:$F$67,A13-'Inputs'!$B$14+1)*'Inputs'!$B$13*'Inputs'!$B$15*'Inputs'!$B$7*(1-'Inputs'!$B$16),0) | H13: =-IF(AND(A13>=1,A13<='Inputs'!$B$10),'Inputs'!$B$21*B13,0) | I13: =-'Inputs'!$B$22*(D13+E13+G13) | J13: =IF(A13='Inputs'!$B$24,'Inputs'!$B$23,0) | K13: =IF(A13=0,-'Inputs'!$B$30,0) | L13: =SUM(D13:K13)-F13 | M13: =M12+L13 | N13: =(1+'Inputs'!$B$25)^(-A13/12) | O13: =L13*N13 | P13: =IF(AND(A13>=1,M13>=0),1,0)
A14: 7 | B14: =(1-'Inputs'!$B$11)^A14 | C14: =IF(AND(A14>=1,A14<='Inputs'!$B$10),'Inputs'!$B$28,0) | D14: =IF(AND(A14>=1,A14<='Inputs'!$B$10),'Inputs'!$B$28*'Inputs'!$B$12*B14,0) | E14: =IF(A14=0,'Inputs'!$B$8,0) | F14: =IF(AND(A14>=1,A14<='Inputs'!$B$10),B13-B14,0) | G14: =IF(A14-'Inputs'!$B$14>=1,INDEX($F$7:$F$67,A14-'Inputs'!$B$14+1)*'Inputs'!$B$13*'Inputs'!$B$15*'Inputs'!$B$7*(1-'Inputs'!$B$16),0) | H14: =-IF(AND(A14>=1,A14<='Inputs'!$B$10),'Inputs'!$B$21*B14,0) | I14: =-'Inputs'!$B$22*(D14+E14+G14) | J14: =IF(A14='Inputs'!$B$24,'Inputs'!$B$23,0) | K14: =IF(A14=0,-'Inputs'!$B$30,0) | L14: =SUM(D14:K14)-F14 | M14: =M13+L14 | N14: =(1+'Inputs'!$B$25)^(-A14/12) | O14: =L14*N14 | P14: =IF(AND(A14>=1,M14>=0),1,0)
A15: 8 | B15: =(1-'Inputs'!$B$11)^A15 | C15: =IF(AND(A15>=1,A15<='Inputs'!$B$10),'Inputs'!$B$28,0) | D15: =IF(AND(A15>=1,A15<='Inputs'!$B$10),'Inputs'!$B$28*'Inputs'!$B$12*B15,0) | E15: =IF(A15=0,'Inputs'!$B$8,0) | F15: =IF(AND(A15>=1,A15<='Inputs'!$B$10),B14-B15,0) | G15: =IF(A15-'Inputs'!$B$14>=1,INDEX($F$7:$F$67,A15-'Inputs'!$B$14+1)*'Inputs'!$B$13*'Inputs'!$B$15*'Inputs'!$B$7*(1-'Inputs'!$B$16),0) | H15: =-IF(AND(A15>=1,A15<='Inputs'!$B$10),'Inputs'!$B$21*B15,0) | I15: =-'Inputs'!$B$22*(D15+E15+G15) | J15: =IF(A15='Inputs'!$B$24,'Inputs'!$B$23,0) | K15: =IF(A15=0,-'Inputs'!$B$30,0) | L15: =SUM(D15:K15)-F15 | M15: =M14+L15 | N15: =(1+'Inputs'!$B$25)^(-A15/12) | O15: =L15*N15 | P15: =IF(AND(A15>=1,M15>=0),1,0)
A16: 9 | B16: =(1-'Inputs'!$B$11)^A16 | C16: =IF(AND(A16>=1,A16<='Inputs'!$B$10),'Inputs'!$B$28,0) | D16: =IF(AND(A16>=1,A16<='Inputs'!$B$10),'Inputs'!$B$28*'Inputs'!$B$12*B16,0) | E16: =IF(A16=0,'Inputs'!$B$8,0) | F16: =IF(AND(A16>=1,A16<='Inputs'!$B$10),B15-B16,0) | G16: =IF(A16-'Inputs'!$B$14>=1,INDEX($F$7:$F$67,A16-'Inputs'!$B$14+1)*'Inputs'!$B$13*'Inputs'!$B$15*'Inputs'!$B$7*(1-'Inputs'!$B$16),0) | H16: =-IF(AND(A16>=1,A16<='Inputs'!$B$10),'Inputs'!$B$21*B16,0) | I16: =-'Inputs'!$B$22*(D16+E16+G16) | J16: =IF(A16='Inputs'!$B$24,'Inputs'!$B$23,0) | K16: =IF(A16=0,-'Inputs'!$B$30,0) | L16: =SUM(D16:K16)-F16 | M16: =M15+L16 | N16: =(1+'Inputs'!$B$25)^(-A16/12) | O16: =L16*N16 | P16: =IF(AND(A16>=1,M16>=0),1,0)
A17: 10 | B17: =(1-'Inputs'!$B$11)^A17 | C17: =IF(AND(A17>=1,A17<='Inputs'!$B$10),'Inputs'!$B$28,0) | D17: =IF(AND(A17>=1,A17<='Inputs'!$B$10),'Inputs'!$B$28*'Inputs'!$B$12*B17,0) | E17: =IF(A17=0,'Inputs'!$B$8,0) | F17: =IF(AND(A17>=1,A17<='Inputs'!$B$10),B16-B17,0) | G17: =IF(A17-'Inputs'!$B$14>=1,INDEX($F$7:$F$67,A17-'Inputs'!$B$14+1)*'Inputs'!$B$13*'Inputs'!$B$15*'Inputs'!$B$7*(1-'Inputs'!$B$16),0) | H17: =-IF(AND(A17>=1,A17<='Inputs'!$B$10),'Inputs'!$B$21*B17,0) | I17: =-'Inputs'!$B$22*(D17+E17+G17) | J17: =IF(A17='Inputs'!$B$24,'Inputs'!$B$23,0) | K17: =IF(A17=0,-'Inputs'!$B$30,0) | L17: =SUM(D17:K17)-F17 | M17: =M16+L17 | N17: =(1+'Inputs'!$B$25)^(-A17/12) | O17: =L17*N17 | P17: =IF(AND(A17>=1,M17>=0),1,0)
A18: 11 | B18: =(1-'Inputs'!$B$11)^A18 | C18: =IF(AND(A18>=1,A18<='Inputs'!$B$10),'Inputs'!$B$28,0) | D18: =IF(AND(A18>=1,A18<='Inputs'!$B$10),'Inputs'!$B$28*'Inputs'!$B$12*B18,0) | E18: =IF(A18=0,'Inputs'!$B$8,0) | F18: =IF(AND(A18>=1,A18<='Inputs'!$B$10),B17-B18,0) | G18: =IF(A18-'Inputs'!$B$14>=1,INDEX($F$7:$F$67,A18-'Inputs'!$B$14+1)*'Inputs'!$B$13*'Inputs'!$B$15*'Inputs'!$B$7*(1-'Inputs'!$B$16),0) | H18: =-IF(AND(A18>=1,A18<='Inputs'!$B$10),'Inputs'!$B$21*B18,0) | I18: =-'Inputs'!$B$22*(D18+E18+G18) | J18: =IF(A18='Inputs'!$B$24,'Inputs'!$B$23,0) | K18: =IF(A18=0,-'Inputs'!$B$30,0) | L18: =SUM(D18:K18)-F18 | M18: =M17+L18 | N18: =(1+'Inputs'!$B$25)^(-A18/12) | O18: =L18*N18 | P18: =IF(AND(A18>=1,M18>=0),1,0)
A19: 12 | B19: =(1-'Inputs'!$B$11)^A19 | C19: =IF(AND(A19>=1,A19<='Inputs'!$B$10),'Inputs'!$B$28,0) | D19: =IF(AND(A19>=1,A19<='Inputs'!$B$10),'Inputs'!$B$28*'Inputs'!$B$12*B19,0) | E19: =IF(A19=0,'Inputs'!$B$8,0) | F19: =IF(AND(A19>=1,A19<='Inputs'!$B$10),B18-B19,0) | G19: =IF(A19-'Inputs'!$B$14>=1,INDEX($F$7:$F$67,A19-'Inputs'!$B$14+1)*'Inputs'!$B$13*'Inputs'!$B$15*'Inputs'!$B$7*(1-'Inputs'!$B$16),0) | H19: =-IF(AND(A19>=1,A19<='Inputs'!$B$10),'Inputs'!$B$21*B19,0) | I19: =-'Inputs'!$B$22*(D19+E19+G19) | J19: =IF(A19='Inputs'!$B$24,'Inputs'!$B$23,0) | K19: =IF(A19=0,-'Inputs'!$B$30,0) | L19: =SUM(D19:K19)-F19 | M19: =M18+L19 | N19: =(1+'Inputs'!$B$25)^(-A19/12) | O19: =L19*N19 | P19: =IF(AND(A19>=1,M19>=0),1,0)
... A67: 60 | B67: =(1-'Inputs'!$B$11)^A67 | C67: =IF(AND(A67>=1,A67<='Inputs'!$B$10),'Inputs'!$B$28,0) | D67: =IF(AND(A67>=1,A67<='Inputs'!$B$10),'Inputs'!$B$28*'Inputs'!$B$12*B67,0) | E67: =IF(A67=0,'Inputs'!$B$8,0) | F67: =IF(AND(A67>=1,A67<='Inputs'!$B$10),B66-B67,0) | G67: =IF(A67-'Inputs'!$B$14>=1,INDEX($F$7:$F$67,A67-'Inputs'!$B$14+1)*'Inputs'!$B$13*'Inputs'!$B$15*'Inputs'!$B$7*(1-'Inputs'!$B$16),0) | H67: =-IF(AND(A67>=1,A67<='Inputs'!$B$10),'Inputs'!$B$21*B67,0) | I67: =-'Inputs'!$B$22*(D67+E67+G67) | J67: =IF(A67='Inputs'!$B$24,'Inputs'!$B$23,0) | K67: =IF(A67=0,-'Inputs'!$B$30,0) | L67: =SUM(D67:K67)-F67 | M67: =M66+L67 | N67: =(1+'Inputs'!$B$25)^(-A67/12) | O67: =L67*N67 | P67: =IF(AND(A67>=1,M67>=0),1,0)
A69: Net cash excludes the defaults column, which counts accounts (a share of one unit), not money.

Sheet Tier_Dashboard
A1: AFRICA ENERGY FINANCE | BOOK 2 | PAYGO SOLAR FINANCE
A2: LTV to CAC by tier
A3: Closed form on the model's default tiers; replace the blue inputs with company data
A4: Decision tool D2 | Version 0.9 (pre-release) | Author & ideation: Emmanuel Boujieka Kamga
A6: Item | B6: Tier 1 | C6: Tier 2 | D6: Tier 3 | E6: Tier 4 | F6: Tier 5 | H6: Notes
A7: Cash price | B7: 6500 | C7: 39000 | D7: 117000 | E7: 390000 | F7: 845000
A8: Deposit | B8: 1000 | C8: 4000 | D8: 17550 | E8: 78000 | F8: 211250
A9: Daily rate | B9: 25 | C9: 77 | D9: 173 | E9: 445 | F9: 694
A10: Tenor (months) | B10: 12 | C10: 24 | D10: 30 | E10: 36 | F10: 48
A11: Monthly default hazard | B11: 0.035 | C11: 0.026 | D11: 0.019 | E11: 0.013 | F11: 0.01
A12: Collection rate on paying accounts | B12: 0.88 | C12: 0.88 | D12: 0.9 | E12: 0.92 | F12: 0.93
A13: Repossession rate | B13: 0 | C13: 0.2 | D13: 0.4 | E13: 0.6 | F13: 0.7
A14: Resale value, share of cash price | B14: 0.2 | C14: 0.25 | D14: 0.35 | E14: 0.45 | F14: 0.5
A15: Landed hardware cost | B15: 3900 | C15: 23400 | D15: 70200 | E15: 218400 | F15: 499200 | H15: USD cost × 130 × (1 + 20% freight and duty)
A16: Installation | B16: 0 | C16: 500 | D16: 2500 | E16: 15000 | F16: 30000
A17: Warranty, share of landed cost | B17: 0.03 | C17: 0.05 | D17: 0.05 | E17: 0.06 | F17: 0.06
A18: CAC (commission and marketing) | B18: 800 | C18: 3000 | D18: 7500 | E18: 18000 | F18: 30000
A19: RBF per unit (local currency) | B19: 650 | C19: 1950 | D19: 3250 | E19: 0 | F19: 0 | H19: USD per unit × opening FX rate
A20: Servicing cost per active account per month | B20: 150
A21: Payment fees, share of cash collected | B21: 0.02
A22: Recovery cost, share of resale proceeds | B22: 0.15
A24: Results
A25: Monthly instalment | B25: =B$9*365/12 | C25: =C$9*365/12 | D25: =D$9*365/12 | E25: =E$9*365/12 | F25: =F$9*365/12
A26: Sum of survival over the tenor | B26: =(1-B$11)*(1-(1-B$11)^B$10)/B$11 | C26: =(1-C$11)*(1-(1-C$11)^C$10)/C$11 | D26: =(1-D$11)*(1-(1-D$11)^D$10)/D$11 | E26: =(1-E$11)*(1-(1-E$11)^E$10)/E$11 | F26: =(1-F$11)*(1-(1-F$11)^F$10)/F$11
A27: Expected instalments collected | B27: =B25*B$12*B26 | C27: =C25*C$12*C26 | D27: =D25*D$12*D26 | E27: =E25*E$12*E26 | F27: =F25*F$12*F26
A28: Expected loss rate | B28: =1-B27/(B25*B$10) | C28: =1-C27/(C25*C$10) | D28: =1-D27/(D25*D$10) | E28: =1-E27/(E25*E$10) | F28: =1-F27/(F25*F$10)
A29: Expected recoveries | B29: =(1-(1-B$11)^B$10)*B$13*B$14*B$7*(1-$B$22) | C29: =(1-(1-C$11)^C$10)*C$13*C$14*C$7*(1-$B$22) | D29: =(1-(1-D$11)^D$10)*D$13*D$14*D$7*(1-$B$22) | E29: =(1-(1-E$11)^E$10)*E$13*E$14*E$7*(1-$B$22) | F29: =(1-(1-F$11)^F$10)*F$13*F$14*F$7*(1-$B$22)
A30: Servicing and payment fees | B30: =-$B$20*B26-$B$21*(B$8+B27+B29) | C30: =-$B$20*C26-$B$21*(C$8+C27+C29) | D30: =-$B$20*D26-$B$21*(D$8+D27+D29) | E30: =-$B$20*E26-$B$21*(E$8+E27+E29) | F30: =-$B$20*F26-$B$21*(F$8+F27+F29)
A31: Day one outlay excluding CAC | B31: =B$15*(1+B$17)+B$16 | C31: =C$15*(1+C$17)+C$16 | D31: =D$15*(1+D$17)+D$16 | E31: =E$15*(1+E$17)+E$16 | F31: =F$15*(1+F$17)+F$16
A32: LTV (contribution before CAC) | B32: =B$8+B27+B29+B30+B$19-B31 | C32: =C$8+C27+C29+C30+C$19-C31 | D32: =D$8+D27+D29+D30+D$19-D31 | E32: =E$8+E27+E29+E30+E$19-E31 | F32: =F$8+F27+F29+F30+F$19-F31
A33: CAC | B33: =B$18 | C33: =C$18 | D33: =D$18 | E33: =E$18 | F33: =F$18
A34: Lifetime contribution | B34: =B32-B33 | C34: =C32-C33 | D34: =D32-D33 | E34: =E32-E33 | F34: =F32-F33
A35: LTV to CAC | B35: =IF(B33=0,"",B32/B33) | C35: =IF(C33=0,"",C32/C33) | D35: =IF(D33=0,"",D32/D33) | E35: =IF(E33=0,"",E32/E33) | F35: =IF(F33=0,"",F32/F33)
A36: Months of collections to recover the day one outlay | B36: =IFERROR(IF(1-(B31+B33-B$8)*B$11/(B25*B$12*(1-B$11))<=0,"Beyond tenor",IF(LN(1-(B31+B33-B$8)*B$11/(B25*B$12*(1-B$11)))/LN(1-B$11)>B$10,"Beyond tenor",LN(1-(B31+B33-B$8)*B$11/(B25*B$12*(1-B$11)))/LN(1-B$11))),"") | C36: =IFERROR(IF(1-(C31+C33-C$8)*C$11/(C25*C$12*(1-C$11))<=0,"Beyond tenor",IF(LN(1-(C31+C33-C$8)*C$11/(C25*C$12*(1-C$11)))/LN(1-C$11)>C$10,"Beyond tenor",LN(1-(C31+C33-C$8)*C$11/(C25*C$12*(1-C$11)))/LN(1-C$11))),"") | D36: =IFERROR(IF(1-(D31+D33-D$8)*D$11/(D25*D$12*(1-D$11))<=0,"Beyond tenor",IF(LN(1-(D31+D33-D$8)*D$11/(D25*D$12*(1-D$11)))/LN(1-D$11)>D$10,"Beyond tenor",LN(1-(D31+D33-D$8)*D$11/(D25*D$12*(1-D$11)))/LN(1-D$11))),"") | E36: =IFERROR(IF(1-(E31+E33-E$8)*E$11/(E25*E$12*(1-E$11))<=0,"Beyond tenor",IF(LN(1-(E31+E33-E$8)*E$11/(E25*E$12*(1-E$11)))/LN(1-E$11)>E$10,"Beyond tenor",LN(1-(E31+E33-E$8)*E$11/(E25*E$12*(1-E$11)))/LN(1-E$11))),"") | F36: =IFERROR(IF(1-(F31+F33-F$8)*F$11/(F25*F$12*(1-F$11))<=0,"Beyond tenor",IF(LN(1-(F31+F33-F$8)*F$11/(F25*F$12*(1-F$11)))/LN(1-F$11)>F$10,"Beyond tenor",LN(1-(F31+F33-F$8)*F$11/(F25*F$12*(1-F$11)))/LN(1-F$11))),"") | H36: Before servicing and fees; deposit counted at sale
A38: Closed form on the model's default inputs, without price indexation or timing of recoveries; the model's Unit_Economics sheet remains the reference. The default tiers have no company history behind them.
