Workbook

Sheet Guide
A1: AFRICA ENERGY FINANCE | VOLUME 2 | SOLAR HOME SYSTEMS
A2: Receivables financing calculator
A3: How to use this template
A4: Decision tool D4 | Version 1.0 | Author & ideation: Emmanuel Boujieka Kamga
A6: Purpose
A7: Shows how much cash a sales plan consumes before it returns any, how much of that the receivables facility can carry, and how much must be equity; and compares local currency and hard currency debt.
A11: How to use it
A12: Step 1 | B12: Enter units sold per year, the price plan, credit behaviour, the day one outlay per unit and the facility terms.
A13: Step 2 | B13: Read the monthly funding path on Funding and the year end summary on Summary.
A14: Step 3 | B14: Peak equity is the most the plan needs from shareholders to fund the book and central costs, before interest, tax and capex.
A15: Step 4 | B15: Use Currency to compare a local currency facility with dollar debt plus expected depreciation.
A16: Step 5 | B16: For a full plan with overheads, tax and interest, use the AEF SHS PAYGo model.
A18: Colour code
A19: Input | B19: Blue font on cream: the only cells to edit
A20: Formula | B20: Black font: calculated, do not overwrite
A22: Links to the Volume 2 model and book
A23: Book | B23: Chapter 10 (working capital and FX), Chapter 11 (funding the book)
A24: Model | B24: Financing, FS, Credit_Portfolio, Investment_Summary
A25: Default inputs | B25: The default Tier 2 product of the model, sold at 10,000, 20,000, 35,000, 50,000 and 50,000 units a year (the volumes of Chapter 10).
A27: Decision support material; not investment, legal, tax or accounting advice. Example values are illustrative and refer to the book's worked examples or to the fictional SolaraPay case. (c) 2026 Emmanuel Boujieka Kamga.

Sheet Inputs
A1: AFRICA ENERGY FINANCE | VOLUME 2 | SOLAR HOME SYSTEMS
A2: Financing inputs
A3: Single product; local currency
A4: Decision tool D4 | Version 1.0 | Author & ideation: Emmanuel Boujieka Kamga
A6: Inputs
A7: Units sold, Year 1 | B7: 10000
A8: Units sold, Year 2 | B8: 20000
A9: Units sold, Year 3 | B9: 35000
A10: Units sold, Year 4 | B10: 50000
A11: Units sold, Year 5 | B11: 50000
A12: Cash price | B12: 39000
A13: Deposit | B13: 4000
A14: Daily rate | B14: 77
A15: Tenor (months) | B15: 24
A16: Monthly default hazard | B16: 0.026
A17: Collection rate on paying accounts | B17: 0.88
A18: Day one outlay per unit (hardware, installation, CAC) | B18: 26900 | D18: Landed 23,400 + installation 500 + CAC 3,000
A19: Advance rate on eligible receivables | B19: 0.7
A20: Eligible share of paying account balances | B20: 1 | D20: Paying accounts are current or 1 to 30 DPD in the model's proxy
A21: Facility limit | B21: 3000000000
A22: Facility available from month | B22: 7 | D22: Model default
A23: Central costs per month (staff, G&A) | B23: 36400000 | D23: Model default; set to zero to isolate the book
A24: Exchange rate (local per USD) for the USD summary | B24: 130
A26: Monthly instalment | B26: ='Inputs'!$B$14*365/12
A27: PAYGo premium per unit | B27: ='Inputs'!$B$13+'Inputs'!$B$26*'Inputs'!$B$15-'Inputs'!$B$12

Sheet Per_Unit
A1: AFRICA ENERGY FINANCE | VOLUME 2 | SOLAR HOME SYSTEMS
A2: Per unit curve
A3: Expected collections and balance of one unit by age
A4: Decision tool D4 | Version 1.0 | Author & ideation: Emmanuel Boujieka Kamga
A6: Age | B6: Share still paying | C6: Collection | D6: Carrying amount of paying accounts
A7: 0 | B7: =(1-'Inputs'!$B$16)^A7 | C7: =IF(AND(A7>=1,A7<='Inputs'!$B$15),'Inputs'!$B$26*'Inputs'!$B$17*B7,0) | D7: =IF(A7<='Inputs'!$B$15,('Inputs'!$B$15-A7)*('Inputs'!$B$26-'Inputs'!$B$27/'Inputs'!$B$15)*B7,0)
A8: 1 | B8: =(1-'Inputs'!$B$16)^A8 | C8: =IF(AND(A8>=1,A8<='Inputs'!$B$15),'Inputs'!$B$26*'Inputs'!$B$17*B8,0) | D8: =IF(A8<='Inputs'!$B$15,('Inputs'!$B$15-A8)*('Inputs'!$B$26-'Inputs'!$B$27/'Inputs'!$B$15)*B8,0)
A9: 2 | B9: =(1-'Inputs'!$B$16)^A9 | C9: =IF(AND(A9>=1,A9<='Inputs'!$B$15),'Inputs'!$B$26*'Inputs'!$B$17*B9,0) | D9: =IF(A9<='Inputs'!$B$15,('Inputs'!$B$15-A9)*('Inputs'!$B$26-'Inputs'!$B$27/'Inputs'!$B$15)*B9,0)
A10: 3 | B10: =(1-'Inputs'!$B$16)^A10 | C10: =IF(AND(A10>=1,A10<='Inputs'!$B$15),'Inputs'!$B$26*'Inputs'!$B$17*B10,0) | D10: =IF(A10<='Inputs'!$B$15,('Inputs'!$B$15-A10)*('Inputs'!$B$26-'Inputs'!$B$27/'Inputs'!$B$15)*B10,0)
A11: 4 | B11: =(1-'Inputs'!$B$16)^A11 | C11: =IF(AND(A11>=1,A11<='Inputs'!$B$15),'Inputs'!$B$26*'Inputs'!$B$17*B11,0) | D11: =IF(A11<='Inputs'!$B$15,('Inputs'!$B$15-A11)*('Inputs'!$B$26-'Inputs'!$B$27/'Inputs'!$B$15)*B11,0)
A12: 5 | B12: =(1-'Inputs'!$B$16)^A12 | C12: =IF(AND(A12>=1,A12<='Inputs'!$B$15),'Inputs'!$B$26*'Inputs'!$B$17*B12,0) | D12: =IF(A12<='Inputs'!$B$15,('Inputs'!$B$15-A12)*('Inputs'!$B$26-'Inputs'!$B$27/'Inputs'!$B$15)*B12,0)
A13: 6 | B13: =(1-'Inputs'!$B$16)^A13 | C13: =IF(AND(A13>=1,A13<='Inputs'!$B$15),'Inputs'!$B$26*'Inputs'!$B$17*B13,0) | D13: =IF(A13<='Inputs'!$B$15,('Inputs'!$B$15-A13)*('Inputs'!$B$26-'Inputs'!$B$27/'Inputs'!$B$15)*B13,0)
A14: 7 | B14: =(1-'Inputs'!$B$16)^A14 | C14: =IF(AND(A14>=1,A14<='Inputs'!$B$15),'Inputs'!$B$26*'Inputs'!$B$17*B14,0) | D14: =IF(A14<='Inputs'!$B$15,('Inputs'!$B$15-A14)*('Inputs'!$B$26-'Inputs'!$B$27/'Inputs'!$B$15)*B14,0)
A15: 8 | B15: =(1-'Inputs'!$B$16)^A15 | C15: =IF(AND(A15>=1,A15<='Inputs'!$B$15),'Inputs'!$B$26*'Inputs'!$B$17*B15,0) | D15: =IF(A15<='Inputs'!$B$15,('Inputs'!$B$15-A15)*('Inputs'!$B$26-'Inputs'!$B$27/'Inputs'!$B$15)*B15,0)
A16: 9 | B16: =(1-'Inputs'!$B$16)^A16 | C16: =IF(AND(A16>=1,A16<='Inputs'!$B$15),'Inputs'!$B$26*'Inputs'!$B$17*B16,0) | D16: =IF(A16<='Inputs'!$B$15,('Inputs'!$B$15-A16)*('Inputs'!$B$26-'Inputs'!$B$27/'Inputs'!$B$15)*B16,0)
A17: 10 | B17: =(1-'Inputs'!$B$16)^A17 | C17: =IF(AND(A17>=1,A17<='Inputs'!$B$15),'Inputs'!$B$26*'Inputs'!$B$17*B17,0) | D17: =IF(A17<='Inputs'!$B$15,('Inputs'!$B$15-A17)*('Inputs'!$B$26-'Inputs'!$B$27/'Inputs'!$B$15)*B17,0)
A18: 11 | B18: =(1-'Inputs'!$B$16)^A18 | C18: =IF(AND(A18>=1,A18<='Inputs'!$B$15),'Inputs'!$B$26*'Inputs'!$B$17*B18,0) | D18: =IF(A18<='Inputs'!$B$15,('Inputs'!$B$15-A18)*('Inputs'!$B$26-'Inputs'!$B$27/'Inputs'!$B$15)*B18,0)
... A67: 60 | B67: =(1-'Inputs'!$B$16)^A67 | C67: =IF(AND(A67>=1,A67<='Inputs'!$B$15),'Inputs'!$B$26*'Inputs'!$B$17*B67,0) | D67: =IF(A67<='Inputs'!$B$15,('Inputs'!$B$15-A67)*('Inputs'!$B$26-'Inputs'!$B$27/'Inputs'!$B$15)*B67,0)

Sheet Cohorts
A1: AFRICA ENERGY FINANCE | VOLUME 2 | SOLAR HOME SYSTEMS
A2: Cohort matrix
A3: Rows: calendar month; columns: month of sale. Upper block balances, lower block collections
A4: Decision tool D4 | Version 1.0 | Author & ideation: Emmanuel Boujieka Kamga
A6: Month of sale | B6: 1 | C6: 2 | D6: 3 | E6: 4 | F6: 5 | G6: 6 | H6: 7 | I6: 8 | J6: 9 | K6: 10 | L6: 11 | M6: 12 | N6: 13 | O6: 14 | P6: 15 | Q6: 16 | R6: 17 | S6: 18 | T6: 19 | U6: 20 | V6: 21 | W6: 22 | X6: 23 | Y6: 24 | Z6: 25 | AA6: 26 | AB6: 27 | AC6: 28 | AD6: 29 | AE6: 30 | AF6: 31 | AG6: 32 | AH6: 33 | AI6: 34 | AJ6: 35 | AK6: 36 | AL6: 37 | AM6: 38 | AN6: 39 | AO6: 40 | AP6: 41 | AQ6: 42 | AR6: 43 | AS6: 44 | AT6: 45 | AU6: 46 | AV6: 47 | AW6: 48 | AX6: 49 | AY6: 50 | AZ6: 51 | BA6: 52 | BB6: 53 | BC6: 54 | BD6: 55 | BE6: 56 | BF6: 57 | BG6: 58 | BH6: 59 | BI6: 60
A7: Units sold | B7: =CHOOSE(ROUNDUP(B6/12,0),'Inputs'!$B$7,'Inputs'!$B$8,'Inputs'!$B$9,'Inputs'!$B$10,'Inputs'!$B$11)/12 | C7: =CHOOSE(ROUNDUP(C6/12,0),'Inputs'!$B$7,'Inputs'!$B$8,'Inputs'!$B$9,'Inputs'!$B$10,'Inputs'!$B$11)/12 | D7: =CHOOSE(ROUNDUP(D6/12,0),'Inputs'!$B$7,'Inputs'!$B$8,'Inputs'!$B$9,'Inputs'!$B$10,'Inputs'!$B$11)/12 | E7: =CHOOSE(ROUNDUP(E6/12,0),'Inputs'!$B$7,'Inputs'!$B$8,'Inputs'!$B$9,'Inputs'!$B$10,'Inputs'!$B$11)/12 | F7: =CHOOSE(ROUNDUP(F6/12,0),'Inputs'!$B$7,'Inputs'!$B$8,'Inputs'!$B$9,'Inputs'!$B$10,'Inputs'!$B$11)/12 | G7: =CHOOSE(ROUNDUP(G6/12,0),'Inputs'!$B$7,'Inputs'!$B$8,'Inputs'!$B$9,'Inputs'!$B$10,'Inputs'!$B$11)/12 | H7: =CHOOSE(ROUNDUP(H6/12,0),'Inputs'!$B$7,'Inputs'!$B$8,'Inputs'!$B$9,'Inputs'!$B$10,'Inputs'!$B$11)/12 | I7: =CHOOSE(ROUNDUP(I6/12,0),'Inputs'!$B$7,'Inputs'!$B$8,'Inputs'!$B$9,'Inputs'!$B$10,'Inputs'!$B$11)/12 | ... BI7: =CHOOSE(ROUNDUP(BI6/12,0),'Inputs'!$B$7,'Inputs'!$B$8,'Inputs'!$B$9,'Inputs'!$B$10,'Inputs'!$B$11)/12
A9: Balances
A10: 1 | B10: =B$7*Per_Unit!$D$7
A11: 2 | B11: =B$7*Per_Unit!$D$8 | C11: =C$7*Per_Unit!$D$7
A12: 3 | B12: =B$7*Per_Unit!$D$9 | C12: =C$7*Per_Unit!$D$8 | D12: =D$7*Per_Unit!$D$7
A13: 4 | B13: =B$7*Per_Unit!$D$10 | C13: =C$7*Per_Unit!$D$9 | D13: =D$7*Per_Unit!$D$8 | E13: =E$7*Per_Unit!$D$7
A14: 5 | B14: =B$7*Per_Unit!$D$11 | C14: =C$7*Per_Unit!$D$10 | D14: =D$7*Per_Unit!$D$9 | E14: =E$7*Per_Unit!$D$8 | F14: =F$7*Per_Unit!$D$7
A15: 6 | B15: =B$7*Per_Unit!$D$12 | C15: =C$7*Per_Unit!$D$11 | D15: =D$7*Per_Unit!$D$10 | E15: =E$7*Per_Unit!$D$9 | F15: =F$7*Per_Unit!$D$8 | G15: =G$7*Per_Unit!$D$7
A16: 7 | B16: =B$7*Per_Unit!$D$13 | C16: =C$7*Per_Unit!$D$12 | D16: =D$7*Per_Unit!$D$11 | E16: =E$7*Per_Unit!$D$10 | F16: =F$7*Per_Unit!$D$9 | G16: =G$7*Per_Unit!$D$8 | H16: =H$7*Per_Unit!$D$7
A17: 8 | B17: =B$7*Per_Unit!$D$14 | C17: =C$7*Per_Unit!$D$13 | D17: =D$7*Per_Unit!$D$12 | E17: =E$7*Per_Unit!$D$11 | F17: =F$7*Per_Unit!$D$10 | G17: =G$7*Per_Unit!$D$9 | H17: =H$7*Per_Unit!$D$8 | I17: =I$7*Per_Unit!$D$7
A18: 9 | B18: =B$7*Per_Unit!$D$15 | C18: =C$7*Per_Unit!$D$14 | D18: =D$7*Per_Unit!$D$13 | E18: =E$7*Per_Unit!$D$12 | F18: =F$7*Per_Unit!$D$11 | G18: =G$7*Per_Unit!$D$10 | H18: =H$7*Per_Unit!$D$9 | I18: =I$7*Per_Unit!$D$8 | J18: =J$7*Per_Unit!$D$7
A19: 10 | B19: =B$7*Per_Unit!$D$16 | C19: =C$7*Per_Unit!$D$15 | D19: =D$7*Per_Unit!$D$14 | E19: =E$7*Per_Unit!$D$13 | F19: =F$7*Per_Unit!$D$12 | G19: =G$7*Per_Unit!$D$11 | H19: =H$7*Per_Unit!$D$10 | I19: =I$7*Per_Unit!$D$9 | J19: =J$7*Per_Unit!$D$8 | K19: =K$7*Per_Unit!$D$7
A20: 11 | B20: =B$7*Per_Unit!$D$17 | C20: =C$7*Per_Unit!$D$16 | D20: =D$7*Per_Unit!$D$15 | E20: =E$7*Per_Unit!$D$14 | F20: =F$7*Per_Unit!$D$13 | G20: =G$7*Per_Unit!$D$12 | H20: =H$7*Per_Unit!$D$11 | I20: =I$7*Per_Unit!$D$10 | J20: =J$7*Per_Unit!$D$9 | K20: =K$7*Per_Unit!$D$8 | L20: =L$7*Per_Unit!$D$7
A21: 12 | B21: =B$7*Per_Unit!$D$18 | C21: =C$7*Per_Unit!$D$17 | D21: =D$7*Per_Unit!$D$16 | E21: =E$7*Per_Unit!$D$15 | F21: =F$7*Per_Unit!$D$14 | G21: =G$7*Per_Unit!$D$13 | H21: =H$7*Per_Unit!$D$12 | I21: =I$7*Per_Unit!$D$11 | J21: =J$7*Per_Unit!$D$10 | K21: =K$7*Per_Unit!$D$9 | L21: =L$7*Per_Unit!$D$8 | M21: =M$7*Per_Unit!$D$7
A22: 13 | B22: =B$7*Per_Unit!$D$19 | C22: =C$7*Per_Unit!$D$18 | D22: =D$7*Per_Unit!$D$17 | E22: =E$7*Per_Unit!$D$16 | F22: =F$7*Per_Unit!$D$15 | G22: =G$7*Per_Unit!$D$14 | H22: =H$7*Per_Unit!$D$13 | I22: =I$7*Per_Unit!$D$12 | J22: =J$7*Per_Unit!$D$11 | K22: =K$7*Per_Unit!$D$10 | L22: =L$7*Per_Unit!$D$9 | M22: =M$7*Per_Unit!$D$8 | N22: =N$7*Per_Unit!$D$7
A23: 14 | B23: =B$7*Per_Unit!$D$20 | C23: =C$7*Per_Unit!$D$19 | D23: =D$7*Per_Unit!$D$18 | E23: =E$7*Per_Unit!$D$17 | F23: =F$7*Per_Unit!$D$16 | G23: =G$7*Per_Unit!$D$15 | H23: =H$7*Per_Unit!$D$14 | I23: =I$7*Per_Unit!$D$13 | J23: =J$7*Per_Unit!$D$12 | K23: =K$7*Per_Unit!$D$11 | L23: =L$7*Per_Unit!$D$10 | M23: =M$7*Per_Unit!$D$9 | N23: =N$7*Per_Unit!$D$8 | O23: =O$7*Per_Unit!$D$7
A24: 15 | B24: =B$7*Per_Unit!$D$21 | C24: =C$7*Per_Unit!$D$20 | D24: =D$7*Per_Unit!$D$19 | E24: =E$7*Per_Unit!$D$18 | F24: =F$7*Per_Unit!$D$17 | G24: =G$7*Per_Unit!$D$16 | H24: =H$7*Per_Unit!$D$15 | I24: =I$7*Per_Unit!$D$14 | J24: =J$7*Per_Unit!$D$13 | K24: =K$7*Per_Unit!$D$12 | L24: =L$7*Per_Unit!$D$11 | M24: =M$7*Per_Unit!$D$10 | N24: =N$7*Per_Unit!$D$9 | O24: =O$7*Per_Unit!$D$8 | P24: =P$7*Per_Unit!$D$7
A25: 16 | B25: =B$7*Per_Unit!$D$22 | C25: =C$7*Per_Unit!$D$21 | D25: =D$7*Per_Unit!$D$20 | E25: =E$7*Per_Unit!$D$19 | F25: =F$7*Per_Unit!$D$18 | G25: =G$7*Per_Unit!$D$17 | H25: =H$7*Per_Unit!$D$16 | I25: =I$7*Per_Unit!$D$15 | J25: =J$7*Per_Unit!$D$14 | K25: =K$7*Per_Unit!$D$13 | L25: =L$7*Per_Unit!$D$12 | M25: =M$7*Per_Unit!$D$11 | N25: =N$7*Per_Unit!$D$10 | O25: =O$7*Per_Unit!$D$9 | P25: =P$7*Per_Unit!$D$8 | Q25: =Q$7*Per_Unit!$D$7
A26: 17 | B26: =B$7*Per_Unit!$D$23 | C26: =C$7*Per_Unit!$D$22 | D26: =D$7*Per_Unit!$D$21 | E26: =E$7*Per_Unit!$D$20 | F26: =F$7*Per_Unit!$D$19 | G26: =G$7*Per_Unit!$D$18 | H26: =H$7*Per_Unit!$D$17 | I26: =I$7*Per_Unit!$D$16 | J26: =J$7*Per_Unit!$D$15 | K26: =K$7*Per_Unit!$D$14 | L26: =L$7*Per_Unit!$D$13 | M26: =M$7*Per_Unit!$D$12 | N26: =N$7*Per_Unit!$D$11 | O26: =O$7*Per_Unit!$D$10 | P26: =P$7*Per_Unit!$D$9 | Q26: =Q$7*Per_Unit!$D$8 | R26: =R$7*Per_Unit!$D$7
A27: 18 | B27: =B$7*Per_Unit!$D$24 | C27: =C$7*Per_Unit!$D$23 | D27: =D$7*Per_Unit!$D$22 | E27: =E$7*Per_Unit!$D$21 | F27: =F$7*Per_Unit!$D$20 | G27: =G$7*Per_Unit!$D$19 | H27: =H$7*Per_Unit!$D$18 | I27: =I$7*Per_Unit!$D$17 | J27: =J$7*Per_Unit!$D$16 | K27: =K$7*Per_Unit!$D$15 | L27: =L$7*Per_Unit!$D$14 | M27: =M$7*Per_Unit!$D$13 | N27: =N$7*Per_Unit!$D$12 | O27: =O$7*Per_Unit!$D$11 | P27: =P$7*Per_Unit!$D$10 | Q27: =Q$7*Per_Unit!$D$9 | R27: =R$7*Per_Unit!$D$8 | S27: =S$7*Per_Unit!$D$7
A28: 19 | B28: =B$7*Per_Unit!$D$25 | C28: =C$7*Per_Unit!$D$24 | D28: =D$7*Per_Unit!$D$23 | E28: =E$7*Per_Unit!$D$22 | F28: =F$7*Per_Unit!$D$21 | G28: =G$7*Per_Unit!$D$20 | H28: =H$7*Per_Unit!$D$19 | I28: =I$7*Per_Unit!$D$18 | J28: =J$7*Per_Unit!$D$17 | K28: =K$7*Per_Unit!$D$16 | L28: =L$7*Per_Unit!$D$15 | M28: =M$7*Per_Unit!$D$14 | N28: =N$7*Per_Unit!$D$13 | O28: =O$7*Per_Unit!$D$12 | P28: =P$7*Per_Unit!$D$11 | Q28: =Q$7*Per_Unit!$D$10 | R28: =R$7*Per_Unit!$D$9 | S28: =S$7*Per_Unit!$D$8 | T28: =T$7*Per_Unit!$D$7
A29: 20 | B29: =B$7*Per_Unit!$D$26 | C29: =C$7*Per_Unit!$D$25 | D29: =D$7*Per_Unit!$D$24 | E29: =E$7*Per_Unit!$D$23 | F29: =F$7*Per_Unit!$D$22 | G29: =G$7*Per_Unit!$D$21 | H29: =H$7*Per_Unit!$D$20 | I29: =I$7*Per_Unit!$D$19 | J29: =J$7*Per_Unit!$D$18 | K29: =K$7*Per_Unit!$D$17 | L29: =L$7*Per_Unit!$D$16 | M29: =M$7*Per_Unit!$D$15 | N29: =N$7*Per_Unit!$D$14 | O29: =O$7*Per_Unit!$D$13 | P29: =P$7*Per_Unit!$D$12 | Q29: =Q$7*Per_Unit!$D$11 | R29: =R$7*Per_Unit!$D$10 | S29: =S$7*Per_Unit!$D$9 | T29: =T$7*Per_Unit!$D$8 | U29: =U$7*Per_Unit!$D$7
A30: 21 | B30: =B$7*Per_Unit!$D$27 | C30: =C$7*Per_Unit!$D$26 | D30: =D$7*Per_Unit!$D$25 | E30: =E$7*Per_Unit!$D$24 | F30: =F$7*Per_Unit!$D$23 | G30: =G$7*Per_Unit!$D$22 | H30: =H$7*Per_Unit!$D$21 | I30: =I$7*Per_Unit!$D$20 | J30: =J$7*Per_Unit!$D$19 | K30: =K$7*Per_Unit!$D$18 | L30: =L$7*Per_Unit!$D$17 | M30: =M$7*Per_Unit!$D$16 | N30: =N$7*Per_Unit!$D$15 | O30: =O$7*Per_Unit!$D$14 | P30: =P$7*Per_Unit!$D$13 | Q30: =Q$7*Per_Unit!$D$12 | R30: =R$7*Per_Unit!$D$11 | S30: =S$7*Per_Unit!$D$10 | T30: =T$7*Per_Unit!$D$9 | U30: =U$7*Per_Unit!$D$8 | V30: =V$7*Per_Unit!$D$7
A31: 22 | B31: =B$7*Per_Unit!$D$28 | C31: =C$7*Per_Unit!$D$27 | D31: =D$7*Per_Unit!$D$26 | E31: =E$7*Per_Unit!$D$25 | F31: =F$7*Per_Unit!$D$24 | G31: =G$7*Per_Unit!$D$23 | H31: =H$7*Per_Unit!$D$22 | I31: =I$7*Per_Unit!$D$21 | J31: =J$7*Per_Unit!$D$20 | K31: =K$7*Per_Unit!$D$19 | L31: =L$7*Per_Unit!$D$18 | M31: =M$7*Per_Unit!$D$17 | N31: =N$7*Per_Unit!$D$16 | O31: =O$7*Per_Unit!$D$15 | P31: =P$7*Per_Unit!$D$14 | Q31: =Q$7*Per_Unit!$D$13 | R31: =R$7*Per_Unit!$D$12 | S31: =S$7*Per_Unit!$D$11 | T31: =T$7*Per_Unit!$D$10 | U31: =U$7*Per_Unit!$D$9 | V31: =V$7*Per_Unit!$D$8 | W31: =W$7*Per_Unit!$D$7
A32: 23 | B32: =B$7*Per_Unit!$D$29 | C32: =C$7*Per_Unit!$D$28 | D32: =D$7*Per_Unit!$D$27 | E32: =E$7*Per_Unit!$D$26 | F32: =F$7*Per_Unit!$D$25 | G32: =G$7*Per_Unit!$D$24 | H32: =H$7*Per_Unit!$D$23 | I32: =I$7*Per_Unit!$D$22 | J32: =J$7*Per_Unit!$D$21 | K32: =K$7*Per_Unit!$D$20 | L32: =L$7*Per_Unit!$D$19 | M32: =M$7*Per_Unit!$D$18 | N32: =N$7*Per_Unit!$D$17 | O32: =O$7*Per_Unit!$D$16 | P32: =P$7*Per_Unit!$D$15 | Q32: =Q$7*Per_Unit!$D$14 | R32: =R$7*Per_Unit!$D$13 | S32: =S$7*Per_Unit!$D$12 | T32: =T$7*Per_Unit!$D$11 | U32: =U$7*Per_Unit!$D$10 | V32: =V$7*Per_Unit!$D$9 | W32: =W$7*Per_Unit!$D$8 | X32: =X$7*Per_Unit!$D$7
A33: 24 | B33: =B$7*Per_Unit!$D$30 | C33: =C$7*Per_Unit!$D$29 | D33: =D$7*Per_Unit!$D$28 | E33: =E$7*Per_Unit!$D$27 | F33: =F$7*Per_Unit!$D$26 | G33: =G$7*Per_Unit!$D$25 | H33: =H$7*Per_Unit!$D$24 | I33: =I$7*Per_Unit!$D$23 | J33: =J$7*Per_Unit!$D$22 | K33: =K$7*Per_Unit!$D$21 | L33: =L$7*Per_Unit!$D$20 | M33: =M$7*Per_Unit!$D$19 | N33: =N$7*Per_Unit!$D$18 | O33: =O$7*Per_Unit!$D$17 | P33: =P$7*Per_Unit!$D$16 | Q33: =Q$7*Per_Unit!$D$15 | R33: =R$7*Per_Unit!$D$14 | S33: =S$7*Per_Unit!$D$13 | T33: =T$7*Per_Unit!$D$12 | U33: =U$7*Per_Unit!$D$11 | V33: =V$7*Per_Unit!$D$10 | W33: =W$7*Per_Unit!$D$9 | X33: =X$7*Per_Unit!$D$8 | Y33: =Y$7*Per_Unit!$D$7
A34: 25 | B34: =B$7*Per_Unit!$D$31 | C34: =C$7*Per_Unit!$D$30 | D34: =D$7*Per_Unit!$D$29 | E34: =E$7*Per_Unit!$D$28 | F34: =F$7*Per_Unit!$D$27 | G34: =G$7*Per_Unit!$D$26 | H34: =H$7*Per_Unit!$D$25 | I34: =I$7*Per_Unit!$D$24 | J34: =J$7*Per_Unit!$D$23 | K34: =K$7*Per_Unit!$D$22 | L34: =L$7*Per_Unit!$D$21 | M34: =M$7*Per_Unit!$D$20 | N34: =N$7*Per_Unit!$D$19 | O34: =O$7*Per_Unit!$D$18 | P34: =P$7*Per_Unit!$D$17 | Q34: =Q$7*Per_Unit!$D$16 | R34: =R$7*Per_Unit!$D$15 | S34: =S$7*Per_Unit!$D$14 | T34: =T$7*Per_Unit!$D$13 | U34: =U$7*Per_Unit!$D$12 | V34: =V$7*Per_Unit!$D$11 | W34: =W$7*Per_Unit!$D$10 | X34: =X$7*Per_Unit!$D$9 | Y34: =Y$7*Per_Unit!$D$8 | Z34: =Z$7*Per_Unit!$D$7
A35: 26 | B35: =B$7*Per_Unit!$D$32 | C35: =C$7*Per_Unit!$D$31 | D35: =D$7*Per_Unit!$D$30 | E35: =E$7*Per_Unit!$D$29 | F35: =F$7*Per_Unit!$D$28 | G35: =G$7*Per_Unit!$D$27 | H35: =H$7*Per_Unit!$D$26 | I35: =I$7*Per_Unit!$D$25 | J35: =J$7*Per_Unit!$D$24 | K35: =K$7*Per_Unit!$D$23 | L35: =L$7*Per_Unit!$D$22 | M35: =M$7*Per_Unit!$D$21 | N35: =N$7*Per_Unit!$D$20 | O35: =O$7*Per_Unit!$D$19 | P35: =P$7*Per_Unit!$D$18 | Q35: =Q$7*Per_Unit!$D$17 | R35: =R$7*Per_Unit!$D$16 | S35: =S$7*Per_Unit!$D$15 | T35: =T$7*Per_Unit!$D$14 | U35: =U$7*Per_Unit!$D$13 | V35: =V$7*Per_Unit!$D$12 | W35: =W$7*Per_Unit!$D$11 | X35: =X$7*Per_Unit!$D$10 | Y35: =Y$7*Per_Unit!$D$9 | Z35: =Z$7*Per_Unit!$D$8 | AA35: =AA$7*Per_Unit!$D$7
A36: 27 | B36: =B$7*Per_Unit!$D$33 | C36: =C$7*Per_Unit!$D$32 | D36: =D$7*Per_Unit!$D$31 | E36: =E$7*Per_Unit!$D$30 | F36: =F$7*Per_Unit!$D$29 | G36: =G$7*Per_Unit!$D$28 | H36: =H$7*Per_Unit!$D$27 | I36: =I$7*Per_Unit!$D$26 | J36: =J$7*Per_Unit!$D$25 | K36: =K$7*Per_Unit!$D$24 | L36: =L$7*Per_Unit!$D$23 | M36: =M$7*Per_Unit!$D$22 | N36: =N$7*Per_Unit!$D$21 | O36: =O$7*Per_Unit!$D$20 | P36: =P$7*Per_Unit!$D$19 | Q36: =Q$7*Per_Unit!$D$18 | R36: =R$7*Per_Unit!$D$17 | S36: =S$7*Per_Unit!$D$16 | T36: =T$7*Per_Unit!$D$15 | U36: =U$7*Per_Unit!$D$14 | V36: =V$7*Per_Unit!$D$13 | W36: =W$7*Per_Unit!$D$12 | X36: =X$7*Per_Unit!$D$11 | Y36: =Y$7*Per_Unit!$D$10 | Z36: =Z$7*Per_Unit!$D$9 | AA36: =AA$7*Per_Unit!$D$8 | AB36: =AB$7*Per_Unit!$D$7
A37: 28 | B37: =B$7*Per_Unit!$D$34 | C37: =C$7*Per_Unit!$D$33 | D37: =D$7*Per_Unit!$D$32 | E37: =E$7*Per_Unit!$D$31 | F37: =F$7*Per_Unit!$D$30 | G37: =G$7*Per_Unit!$D$29 | H37: =H$7*Per_Unit!$D$28 | I37: =I$7*Per_Unit!$D$27 | J37: =J$7*Per_Unit!$D$26 | K37: =K$7*Per_Unit!$D$25 | L37: =L$7*Per_Unit!$D$24 | M37: =M$7*Per_Unit!$D$23 | N37: =N$7*Per_Unit!$D$22 | O37: =O$7*Per_Unit!$D$21 | P37: =P$7*Per_Unit!$D$20 | Q37: =Q$7*Per_Unit!$D$19 | R37: =R$7*Per_Unit!$D$18 | S37: =S$7*Per_Unit!$D$17 | T37: =T$7*Per_Unit!$D$16 | U37: =U$7*Per_Unit!$D$15 | V37: =V$7*Per_Unit!$D$14 | W37: =W$7*Per_Unit!$D$13 | X37: =X$7*Per_Unit!$D$12 | Y37: =Y$7*Per_Unit!$D$11 | Z37: =Z$7*Per_Unit!$D$10 | AA37: =AA$7*Per_Unit!$D$9 | AB37: =AB$7*Per_Unit!$D$8 | AC37: =AC$7*Per_Unit!$D$7
A38: 29 | B38: =B$7*Per_Unit!$D$35 | C38: =C$7*Per_Unit!$D$34 | D38: =D$7*Per_Unit!$D$33 | E38: =E$7*Per_Unit!$D$32 | F38: =F$7*Per_Unit!$D$31 | G38: =G$7*Per_Unit!$D$30 | H38: =H$7*Per_Unit!$D$29 | I38: =I$7*Per_Unit!$D$28 | J38: =J$7*Per_Unit!$D$27 | K38: =K$7*Per_Unit!$D$26 | L38: =L$7*Per_Unit!$D$25 | M38: =M$7*Per_Unit!$D$24 | N38: =N$7*Per_Unit!$D$23 | O38: =O$7*Per_Unit!$D$22 | P38: =P$7*Per_Unit!$D$21 | Q38: =Q$7*Per_Unit!$D$20 | R38: =R$7*Per_Unit!$D$19 | S38: =S$7*Per_Unit!$D$18 | T38: =T$7*Per_Unit!$D$17 | U38: =U$7*Per_Unit!$D$16 | V38: =V$7*Per_Unit!$D$15 | W38: =W$7*Per_Unit!$D$14 | X38: =X$7*Per_Unit!$D$13 | Y38: =Y$7*Per_Unit!$D$12 | Z38: =Z$7*Per_Unit!$D$11 | AA38: =AA$7*Per_Unit!$D$10 | AB38: =AB$7*Per_Unit!$D$9 | AC38: =AC$7*Per_Unit!$D$8 | AD38: =AD$7*Per_Unit!$D$7
A39: 30 | B39: =B$7*Per_Unit!$D$36 | C39: =C$7*Per_Unit!$D$35 | D39: =D$7*Per_Unit!$D$34 | E39: =E$7*Per_Unit!$D$33 | F39: =F$7*Per_Unit!$D$32 | G39: =G$7*Per_Unit!$D$31 | H39: =H$7*Per_Unit!$D$30 | I39: =I$7*Per_Unit!$D$29 | J39: =J$7*Per_Unit!$D$28 | K39: =K$7*Per_Unit!$D$27 | L39: =L$7*Per_Unit!$D$26 | M39: =M$7*Per_Unit!$D$25 | N39: =N$7*Per_Unit!$D$24 | O39: =O$7*Per_Unit!$D$23 | P39: =P$7*Per_Unit!$D$22 | Q39: =Q$7*Per_Unit!$D$21 | R39: =R$7*Per_Unit!$D$20 | S39: =S$7*Per_Unit!$D$19 | T39: =T$7*Per_Unit!$D$18 | U39: =U$7*Per_Unit!$D$17 | V39: =V$7*Per_Unit!$D$16 | W39: =W$7*Per_Unit!$D$15 | X39: =X$7*Per_Unit!$D$14 | Y39: =Y$7*Per_Unit!$D$13 | Z39: =Z$7*Per_Unit!$D$12 | AA39: =AA$7*Per_Unit!$D$11 | AB39: =AB$7*Per_Unit!$D$10 | AC39: =AC$7*Per_Unit!$D$9 | AD39: =AD$7*Per_Unit!$D$8 | AE39: =AE$7*Per_Unit!$D$7
A40: 31 | B40: =B$7*Per_Unit!$D$37 | C40: =C$7*Per_Unit!$D$36 | D40: =D$7*Per_Unit!$D$35 | E40: =E$7*Per_Unit!$D$34 | F40: =F$7*Per_Unit!$D$33 | G40: =G$7*Per_Unit!$D$32 | H40: =H$7*Per_Unit!$D$31 | I40: =I$7*Per_Unit!$D$30 | J40: =J$7*Per_Unit!$D$29 | K40: =K$7*Per_Unit!$D$28 | L40: =L$7*Per_Unit!$D$27 | M40: =M$7*Per_Unit!$D$26 | N40: =N$7*Per_Unit!$D$25 | O40: =O$7*Per_Unit!$D$24 | P40: =P$7*Per_Unit!$D$23 | Q40: =Q$7*Per_Unit!$D$22 | R40: =R$7*Per_Unit!$D$21 | S40: =S$7*Per_Unit!$D$20 | T40: =T$7*Per_Unit!$D$19 | U40: =U$7*Per_Unit!$D$18 | V40: =V$7*Per_Unit!$D$17 | W40: =W$7*Per_Unit!$D$16 | X40: =X$7*Per_Unit!$D$15 | Y40: =Y$7*Per_Unit!$D$14 | Z40: =Z$7*Per_Unit!$D$13 | AA40: =AA$7*Per_Unit!$D$12 | AB40: =AB$7*Per_Unit!$D$11 | AC40: =AC$7*Per_Unit!$D$10 | AD40: =AD$7*Per_Unit!$D$9 | AE40: =AE$7*Per_Unit!$D$8 | AF40: =AF$7*Per_Unit!$D$7
A41: 32 | B41: =B$7*Per_Unit!$D$38 | C41: =C$7*Per_Unit!$D$37 | D41: =D$7*Per_Unit!$D$36 | E41: =E$7*Per_Unit!$D$35 | F41: =F$7*Per_Unit!$D$34 | G41: =G$7*Per_Unit!$D$33 | H41: =H$7*Per_Unit!$D$32 | I41: =I$7*Per_Unit!$D$31 | J41: =J$7*Per_Unit!$D$30 | K41: =K$7*Per_Unit!$D$29 | L41: =L$7*Per_Unit!$D$28 | M41: =M$7*Per_Unit!$D$27 | N41: =N$7*Per_Unit!$D$26 | O41: =O$7*Per_Unit!$D$25 | P41: =P$7*Per_Unit!$D$24 | Q41: =Q$7*Per_Unit!$D$23 | R41: =R$7*Per_Unit!$D$22 | S41: =S$7*Per_Unit!$D$21 | T41: =T$7*Per_Unit!$D$20 | U41: =U$7*Per_Unit!$D$19 | V41: =V$7*Per_Unit!$D$18 | W41: =W$7*Per_Unit!$D$17 | X41: =X$7*Per_Unit!$D$16 | Y41: =Y$7*Per_Unit!$D$15 | Z41: =Z$7*Per_Unit!$D$14 | AA41: =AA$7*Per_Unit!$D$13 | AB41: =AB$7*Per_Unit!$D$12 | AC41: =AC$7*Per_Unit!$D$11 | AD41: =AD$7*Per_Unit!$D$10 | AE41: =AE$7*Per_Unit!$D$9 | AF41: =AF$7*Per_Unit!$D$8 | AG41: =AG$7*Per_Unit!$D$7
A42: 33 | B42: =B$7*Per_Unit!$D$39 | C42: =C$7*Per_Unit!$D$38 | D42: =D$7*Per_Unit!$D$37 | E42: =E$7*Per_Unit!$D$36 | F42: =F$7*Per_Unit!$D$35 | G42: =G$7*Per_Unit!$D$34 | H42: =H$7*Per_Unit!$D$33 | I42: =I$7*Per_Unit!$D$32 | J42: =J$7*Per_Unit!$D$31 | K42: =K$7*Per_Unit!$D$30 | L42: =L$7*Per_Unit!$D$29 | M42: =M$7*Per_Unit!$D$28 | N42: =N$7*Per_Unit!$D$27 | O42: =O$7*Per_Unit!$D$26 | P42: =P$7*Per_Unit!$D$25 | Q42: =Q$7*Per_Unit!$D$24 | R42: =R$7*Per_Unit!$D$23 | S42: =S$7*Per_Unit!$D$22 | T42: =T$7*Per_Unit!$D$21 | U42: =U$7*Per_Unit!$D$20 | V42: =V$7*Per_Unit!$D$19 | W42: =W$7*Per_Unit!$D$18 | X42: =X$7*Per_Unit!$D$17 | Y42: =Y$7*Per_Unit!$D$16 | Z42: =Z$7*Per_Unit!$D$15 | AA42: =AA$7*Per_Unit!$D$14 | AB42: =AB$7*Per_Unit!$D$13 | AC42: =AC$7*Per_Unit!$D$12 | AD42: =AD$7*Per_Unit!$D$11 | AE42: =AE$7*Per_Unit!$D$10 | AF42: =AF$7*Per_Unit!$D$9 | AG42: =AG$7*Per_Unit!$D$8 | AH42: =AH$7*Per_Unit!$D$7
A43: 34 | B43: =B$7*Per_Unit!$D$40 | C43: =C$7*Per_Unit!$D$39 | D43: =D$7*Per_Unit!$D$38 | E43: =E$7*Per_Unit!$D$37 | F43: =F$7*Per_Unit!$D$36 | G43: =G$7*Per_Unit!$D$35 | H43: =H$7*Per_Unit!$D$34 | I43: =I$7*Per_Unit!$D$33 | J43: =J$7*Per_Unit!$D$32 | K43: =K$7*Per_Unit!$D$31 | L43: =L$7*Per_Unit!$D$30 | M43: =M$7*Per_Unit!$D$29 | N43: =N$7*Per_Unit!$D$28 | O43: =O$7*Per_Unit!$D$27 | P43: =P$7*Per_Unit!$D$26 | Q43: =Q$7*Per_Unit!$D$25 | R43: =R$7*Per_Unit!$D$24 | S43: =S$7*Per_Unit!$D$23 | T43: =T$7*Per_Unit!$D$22 | U43: =U$7*Per_Unit!$D$21 | V43: =V$7*Per_Unit!$D$20 | W43: =W$7*Per_Unit!$D$19 | X43: =X$7*Per_Unit!$D$18 | Y43: =Y$7*Per_Unit!$D$17 | Z43: =Z$7*Per_Unit!$D$16 | AA43: =AA$7*Per_Unit!$D$15 | AB43: =AB$7*Per_Unit!$D$14 | AC43: =AC$7*Per_Unit!$D$13 | AD43: =AD$7*Per_Unit!$D$12 | AE43: =AE$7*Per_Unit!$D$11 | AF43: =AF$7*Per_Unit!$D$10 | AG43: =AG$7*Per_Unit!$D$9 | AH43: =AH$7*Per_Unit!$D$8 | AI43: =AI$7*Per_Unit!$D$7
A44: 35 | B44: =B$7*Per_Unit!$D$41 | C44: =C$7*Per_Unit!$D$40 | D44: =D$7*Per_Unit!$D$39 | E44: =E$7*Per_Unit!$D$38 | F44: =F$7*Per_Unit!$D$37 | G44: =G$7*Per_Unit!$D$36 | H44: =H$7*Per_Unit!$D$35 | I44: =I$7*Per_Unit!$D$34 | J44: =J$7*Per_Unit!$D$33 | K44: =K$7*Per_Unit!$D$32 | L44: =L$7*Per_Unit!$D$31 | M44: =M$7*Per_Unit!$D$30 | N44: =N$7*Per_Unit!$D$29 | O44: =O$7*Per_Unit!$D$28 | P44: =P$7*Per_Unit!$D$27 | Q44: =Q$7*Per_Unit!$D$26 | R44: =R$7*Per_Unit!$D$25 | S44: =S$7*Per_Unit!$D$24 | T44: =T$7*Per_Unit!$D$23 | U44: =U$7*Per_Unit!$D$22 | V44: =V$7*Per_Unit!$D$21 | W44: =W$7*Per_Unit!$D$20 | X44: =X$7*Per_Unit!$D$19 | Y44: =Y$7*Per_Unit!$D$18 | Z44: =Z$7*Per_Unit!$D$17 | AA44: =AA$7*Per_Unit!$D$16 | AB44: =AB$7*Per_Unit!$D$15 | AC44: =AC$7*Per_Unit!$D$14 | AD44: =AD$7*Per_Unit!$D$13 | AE44: =AE$7*Per_Unit!$D$12 | AF44: =AF$7*Per_Unit!$D$11 | AG44: =AG$7*Per_Unit!$D$10 | AH44: =AH$7*Per_Unit!$D$9 | AI44: =AI$7*Per_Unit!$D$8 | AJ44: =AJ$7*Per_Unit!$D$7
A45: 36 | B45: =B$7*Per_Unit!$D$42 | C45: =C$7*Per_Unit!$D$41 | D45: =D$7*Per_Unit!$D$40 | E45: =E$7*Per_Unit!$D$39 | F45: =F$7*Per_Unit!$D$38 | G45: =G$7*Per_Unit!$D$37 | H45: =H$7*Per_Unit!$D$36 | I45: =I$7*Per_Unit!$D$35 | J45: =J$7*Per_Unit!$D$34 | K45: =K$7*Per_Unit!$D$33 | L45: =L$7*Per_Unit!$D$32 | M45: =M$7*Per_Unit!$D$31 | N45: =N$7*Per_Unit!$D$30 | O45: =O$7*Per_Unit!$D$29 | P45: =P$7*Per_Unit!$D$28 | Q45: =Q$7*Per_Unit!$D$27 | R45: =R$7*Per_Unit!$D$26 | S45: =S$7*Per_Unit!$D$25 | T45: =T$7*Per_Unit!$D$24 | U45: =U$7*Per_Unit!$D$23 | V45: =V$7*Per_Unit!$D$22 | W45: =W$7*Per_Unit!$D$21 | X45: =X$7*Per_Unit!$D$20 | Y45: =Y$7*Per_Unit!$D$19 | Z45: =Z$7*Per_Unit!$D$18 | AA45: =AA$7*Per_Unit!$D$17 | AB45: =AB$7*Per_Unit!$D$16 | AC45: =AC$7*Per_Unit!$D$15 | AD45: =AD$7*Per_Unit!$D$14 | AE45: =AE$7*Per_Unit!$D$13 | AF45: =AF$7*Per_Unit!$D$12 | AG45: =AG$7*Per_Unit!$D$11 | AH45: =AH$7*Per_Unit!$D$10 | AI45: =AI$7*Per_Unit!$D$9 | AJ45: =AJ$7*Per_Unit!$D$8 | AK45: =AK$7*Per_Unit!$D$7
A46: 37 | B46: =B$7*Per_Unit!$D$43 | C46: =C$7*Per_Unit!$D$42 | D46: =D$7*Per_Unit!$D$41 | E46: =E$7*Per_Unit!$D$40 | F46: =F$7*Per_Unit!$D$39 | G46: =G$7*Per_Unit!$D$38 | H46: =H$7*Per_Unit!$D$37 | I46: =I$7*Per_Unit!$D$36 | J46: =J$7*Per_Unit!$D$35 | K46: =K$7*Per_Unit!$D$34 | L46: =L$7*Per_Unit!$D$33 | M46: =M$7*Per_Unit!$D$32 | N46: =N$7*Per_Unit!$D$31 | O46: =O$7*Per_Unit!$D$30 | P46: =P$7*Per_Unit!$D$29 | Q46: =Q$7*Per_Unit!$D$28 | R46: =R$7*Per_Unit!$D$27 | S46: =S$7*Per_Unit!$D$26 | T46: =T$7*Per_Unit!$D$25 | U46: =U$7*Per_Unit!$D$24 | V46: =V$7*Per_Unit!$D$23 | W46: =W$7*Per_Unit!$D$22 | X46: =X$7*Per_Unit!$D$21 | Y46: =Y$7*Per_Unit!$D$20 | Z46: =Z$7*Per_Unit!$D$19 | AA46: =AA$7*Per_Unit!$D$18 | AB46: =AB$7*Per_Unit!$D$17 | AC46: =AC$7*Per_Unit!$D$16 | AD46: =AD$7*Per_Unit!$D$15 | AE46: =AE$7*Per_Unit!$D$14 | AF46: =AF$7*Per_Unit!$D$13 | AG46: =AG$7*Per_Unit!$D$12 | AH46: =AH$7*Per_Unit!$D$11 | AI46: =AI$7*Per_Unit!$D$10 | AJ46: =AJ$7*Per_Unit!$D$9 | AK46: =AK$7*Per_Unit!$D$8 | AL46: =AL$7*Per_Unit!$D$7
A47: 38 | B47: =B$7*Per_Unit!$D$44 | C47: =C$7*Per_Unit!$D$43 | D47: =D$7*Per_Unit!$D$42 | E47: =E$7*Per_Unit!$D$41 | F47: =F$7*Per_Unit!$D$40 | G47: =G$7*Per_Unit!$D$39 | H47: =H$7*Per_Unit!$D$38 | I47: =I$7*Per_Unit!$D$37 | J47: =J$7*Per_Unit!$D$36 | K47: =K$7*Per_Unit!$D$35 | L47: =L$7*Per_Unit!$D$34 | M47: =M$7*Per_Unit!$D$33 | N47: =N$7*Per_Unit!$D$32 | O47: =O$7*Per_Unit!$D$31 | P47: =P$7*Per_Unit!$D$30 | Q47: =Q$7*Per_Unit!$D$29 | R47: =R$7*Per_Unit!$D$28 | S47: =S$7*Per_Unit!$D$27 | T47: =T$7*Per_Unit!$D$26 | U47: =U$7*Per_Unit!$D$25 | V47: =V$7*Per_Unit!$D$24 | W47: =W$7*Per_Unit!$D$23 | X47: =X$7*Per_Unit!$D$22 | Y47: =Y$7*Per_Unit!$D$21 | Z47: =Z$7*Per_Unit!$D$20 | AA47: =AA$7*Per_Unit!$D$19 | AB47: =AB$7*Per_Unit!$D$18 | AC47: =AC$7*Per_Unit!$D$17 | AD47: =AD$7*Per_Unit!$D$16 | AE47: =AE$7*Per_Unit!$D$15 | AF47: =AF$7*Per_Unit!$D$14 | AG47: =AG$7*Per_Unit!$D$13 | AH47: =AH$7*Per_Unit!$D$12 | AI47: =AI$7*Per_Unit!$D$11 | AJ47: =AJ$7*Per_Unit!$D$10 | AK47: =AK$7*Per_Unit!$D$9 | AL47: =AL$7*Per_Unit!$D$8 | AM47: =AM$7*Per_Unit!$D$7
A48: 39 | B48: =B$7*Per_Unit!$D$45 | C48: =C$7*Per_Unit!$D$44 | D48: =D$7*Per_Unit!$D$43 | E48: =E$7*Per_Unit!$D$42 | F48: =F$7*Per_Unit!$D$41 | G48: =G$7*Per_Unit!$D$40 | H48: =H$7*Per_Unit!$D$39 | I48: =I$7*Per_Unit!$D$38 | J48: =J$7*Per_Unit!$D$37 | K48: =K$7*Per_Unit!$D$36 | L48: =L$7*Per_Unit!$D$35 | M48: =M$7*Per_Unit!$D$34 | N48: =N$7*Per_Unit!$D$33 | O48: =O$7*Per_Unit!$D$32 | P48: =P$7*Per_Unit!$D$31 | Q48: =Q$7*Per_Unit!$D$30 | R48: =R$7*Per_Unit!$D$29 | S48: =S$7*Per_Unit!$D$28 | T48: =T$7*Per_Unit!$D$27 | U48: =U$7*Per_Unit!$D$26 | V48: =V$7*Per_Unit!$D$25 | W48: =W$7*Per_Unit!$D$24 | X48: =X$7*Per_Unit!$D$23 | Y48: =Y$7*Per_Unit!$D$22 | Z48: =Z$7*Per_Unit!$D$21 | AA48: =AA$7*Per_Unit!$D$20 | AB48: =AB$7*Per_Unit!$D$19 | AC48: =AC$7*Per_Unit!$D$18 | AD48: =AD$7*Per_Unit!$D$17 | AE48: =AE$7*Per_Unit!$D$16 | AF48: =AF$7*Per_Unit!$D$15 | AG48: =AG$7*Per_Unit!$D$14 | AH48: =AH$7*Per_Unit!$D$13 | AI48: =AI$7*Per_Unit!$D$12 | AJ48: =AJ$7*Per_Unit!$D$11 | AK48: =AK$7*Per_Unit!$D$10 | AL48: =AL$7*Per_Unit!$D$9 | AM48: =AM$7*Per_Unit!$D$8 | AN48: =AN$7*Per_Unit!$D$7
A49: 40 | B49: =B$7*Per_Unit!$D$46 | C49: =C$7*Per_Unit!$D$45 | D49: =D$7*Per_Unit!$D$44 | E49: =E$7*Per_Unit!$D$43 | F49: =F$7*Per_Unit!$D$42 | G49: =G$7*Per_Unit!$D$41 | H49: =H$7*Per_Unit!$D$40 | I49: =I$7*Per_Unit!$D$39 | J49: =J$7*Per_Unit!$D$38 | K49: =K$7*Per_Unit!$D$37 | L49: =L$7*Per_Unit!$D$36 | M49: =M$7*Per_Unit!$D$35 | N49: =N$7*Per_Unit!$D$34 | O49: =O$7*Per_Unit!$D$33 | P49: =P$7*Per_Unit!$D$32 | Q49: =Q$7*Per_Unit!$D$31 | R49: =R$7*Per_Unit!$D$30 | S49: =S$7*Per_Unit!$D$29 | T49: =T$7*Per_Unit!$D$28 | U49: =U$7*Per_Unit!$D$27 | V49: =V$7*Per_Unit!$D$26 | W49: =W$7*Per_Unit!$D$25 | X49: =X$7*Per_Unit!$D$24 | Y49: =Y$7*Per_Unit!$D$23 | Z49: =Z$7*Per_Unit!$D$22 | AA49: =AA$7*Per_Unit!$D$21 | AB49: =AB$7*Per_Unit!$D$20 | AC49: =AC$7*Per_Unit!$D$19 | AD49: =AD$7*Per_Unit!$D$18 | AE49: =AE$7*Per_Unit!$D$17 | AF49: =AF$7*Per_Unit!$D$16 | AG49: =AG$7*Per_Unit!$D$15 | AH49: =AH$7*Per_Unit!$D$14 | AI49: =AI$7*Per_Unit!$D$13 | AJ49: =AJ$7*Per_Unit!$D$12 | AK49: =AK$7*Per_Unit!$D$11 | AL49: =AL$7*Per_Unit!$D$10 | AM49: =AM$7*Per_Unit!$D$9 | AN49: =AN$7*Per_Unit!$D$8 | AO49: =AO$7*Per_Unit!$D$7
A50: 41 | B50: =B$7*Per_Unit!$D$47 | C50: =C$7*Per_Unit!$D$46 | D50: =D$7*Per_Unit!$D$45 | E50: =E$7*Per_Unit!$D$44 | F50: =F$7*Per_Unit!$D$43 | G50: =G$7*Per_Unit!$D$42 | H50: =H$7*Per_Unit!$D$41 | I50: =I$7*Per_Unit!$D$40 | J50: =J$7*Per_Unit!$D$39 | K50: =K$7*Per_Unit!$D$38 | L50: =L$7*Per_Unit!$D$37 | M50: =M$7*Per_Unit!$D$36 | N50: =N$7*Per_Unit!$D$35 | O50: =O$7*Per_Unit!$D$34 | P50: =P$7*Per_Unit!$D$33 | Q50: =Q$7*Per_Unit!$D$32 | R50: =R$7*Per_Unit!$D$31 | S50: =S$7*Per_Unit!$D$30 | T50: =T$7*Per_Unit!$D$29 | U50: =U$7*Per_Unit!$D$28 | V50: =V$7*Per_Unit!$D$27 | W50: =W$7*Per_Unit!$D$26 | X50: =X$7*Per_Unit!$D$25 | Y50: =Y$7*Per_Unit!$D$24 | Z50: =Z$7*Per_Unit!$D$23 | AA50: =AA$7*Per_Unit!$D$22 | AB50: =AB$7*Per_Unit!$D$21 | AC50: =AC$7*Per_Unit!$D$20 | AD50: =AD$7*Per_Unit!$D$19 | AE50: =AE$7*Per_Unit!$D$18 | AF50: =AF$7*Per_Unit!$D$17 | AG50: =AG$7*Per_Unit!$D$16 | AH50: =AH$7*Per_Unit!$D$15 | AI50: =AI$7*Per_Unit!$D$14 | AJ50: =AJ$7*Per_Unit!$D$13 | AK50: =AK$7*Per_Unit!$D$12 | AL50: =AL$7*Per_Unit!$D$11 | AM50: =AM$7*Per_Unit!$D$10 | AN50: =AN$7*Per_Unit!$D$9 | AO50: =AO$7*Per_Unit!$D$8 | AP50: =AP$7*Per_Unit!$D$7
A51: 42 | B51: =B$7*Per_Unit!$D$48 | C51: =C$7*Per_Unit!$D$47 | D51: =D$7*Per_Unit!$D$46 | E51: =E$7*Per_Unit!$D$45 | F51: =F$7*Per_Unit!$D$44 | G51: =G$7*Per_Unit!$D$43 | H51: =H$7*Per_Unit!$D$42 | I51: =I$7*Per_Unit!$D$41 | J51: =J$7*Per_Unit!$D$40 | K51: =K$7*Per_Unit!$D$39 | L51: =L$7*Per_Unit!$D$38 | M51: =M$7*Per_Unit!$D$37 | N51: =N$7*Per_Unit!$D$36 | O51: =O$7*Per_Unit!$D$35 | P51: =P$7*Per_Unit!$D$34 | Q51: =Q$7*Per_Unit!$D$33 | R51: =R$7*Per_Unit!$D$32 | S51: =S$7*Per_Unit!$D$31 | T51: =T$7*Per_Unit!$D$30 | U51: =U$7*Per_Unit!$D$29 | V51: =V$7*Per_Unit!$D$28 | W51: =W$7*Per_Unit!$D$27 | X51: =X$7*Per_Unit!$D$26 | Y51: =Y$7*Per_Unit!$D$25 | Z51: =Z$7*Per_Unit!$D$24 | AA51: =AA$7*Per_Unit!$D$23 | AB51: =AB$7*Per_Unit!$D$22 | AC51: =AC$7*Per_Unit!$D$21 | AD51: =AD$7*Per_Unit!$D$20 | AE51: =AE$7*Per_Unit!$D$19 | AF51: =AF$7*Per_Unit!$D$18 | AG51: =AG$7*Per_Unit!$D$17 | AH51: =AH$7*Per_Unit!$D$16 | AI51: =AI$7*Per_Unit!$D$15 | AJ51: =AJ$7*Per_Unit!$D$14 | AK51: =AK$7*Per_Unit!$D$13 | AL51: =AL$7*Per_Unit!$D$12 | AM51: =AM$7*Per_Unit!$D$11 | AN51: =AN$7*Per_Unit!$D$10 | AO51: =AO$7*Per_Unit!$D$9 | AP51: =AP$7*Per_Unit!$D$8 | AQ51: =AQ$7*Per_Unit!$D$7
A52: 43 | B52: =B$7*Per_Unit!$D$49 | C52: =C$7*Per_Unit!$D$48 | D52: =D$7*Per_Unit!$D$47 | E52: =E$7*Per_Unit!$D$46 | F52: =F$7*Per_Unit!$D$45 | G52: =G$7*Per_Unit!$D$44 | H52: =H$7*Per_Unit!$D$43 | I52: =I$7*Per_Unit!$D$42 | J52: =J$7*Per_Unit!$D$41 | K52: =K$7*Per_Unit!$D$40 | L52: =L$7*Per_Unit!$D$39 | M52: =M$7*Per_Unit!$D$38 | N52: =N$7*Per_Unit!$D$37 | O52: =O$7*Per_Unit!$D$36 | P52: =P$7*Per_Unit!$D$35 | Q52: =Q$7*Per_Unit!$D$34 | R52: =R$7*Per_Unit!$D$33 | S52: =S$7*Per_Unit!$D$32 | T52: =T$7*Per_Unit!$D$31 | U52: =U$7*Per_Unit!$D$30 | V52: =V$7*Per_Unit!$D$29 | W52: =W$7*Per_Unit!$D$28 | X52: =X$7*Per_Unit!$D$27 | Y52: =Y$7*Per_Unit!$D$26 | Z52: =Z$7*Per_Unit!$D$25 | AA52: =AA$7*Per_Unit!$D$24 | AB52: =AB$7*Per_Unit!$D$23 | AC52: =AC$7*Per_Unit!$D$22 | AD52: =AD$7*Per_Unit!$D$21 | AE52: =AE$7*Per_Unit!$D$20 | AF52: =AF$7*Per_Unit!$D$19 | AG52: =AG$7*Per_Unit!$D$18 | AH52: =AH$7*Per_Unit!$D$17 | AI52: =AI$7*Per_Unit!$D$16 | AJ52: =AJ$7*Per_Unit!$D$15 | AK52: =AK$7*Per_Unit!$D$14 | AL52: =AL$7*Per_Unit!$D$13 | AM52: =AM$7*Per_Unit!$D$12 | AN52: =AN$7*Per_Unit!$D$11 | AO52: =AO$7*Per_Unit!$D$10 | AP52: =AP$7*Per_Unit!$D$9 | AQ52: =AQ$7*Per_Unit!$D$8 | AR52: =AR$7*Per_Unit!$D$7
A53: 44 | B53: =B$7*Per_Unit!$D$50 | C53: =C$7*Per_Unit!$D$49 | D53: =D$7*Per_Unit!$D$48 | E53: =E$7*Per_Unit!$D$47 | F53: =F$7*Per_Unit!$D$46 | G53: =G$7*Per_Unit!$D$45 | H53: =H$7*Per_Unit!$D$44 | I53: =I$7*Per_Unit!$D$43 | J53: =J$7*Per_Unit!$D$42 | K53: =K$7*Per_Unit!$D$41 | L53: =L$7*Per_Unit!$D$40 | M53: =M$7*Per_Unit!$D$39 | N53: =N$7*Per_Unit!$D$38 | O53: =O$7*Per_Unit!$D$37 | P53: =P$7*Per_Unit!$D$36 | Q53: =Q$7*Per_Unit!$D$35 | R53: =R$7*Per_Unit!$D$34 | S53: =S$7*Per_Unit!$D$33 | T53: =T$7*Per_Unit!$D$32 | U53: =U$7*Per_Unit!$D$31 | V53: =V$7*Per_Unit!$D$30 | W53: =W$7*Per_Unit!$D$29 | X53: =X$7*Per_Unit!$D$28 | Y53: =Y$7*Per_Unit!$D$27 | Z53: =Z$7*Per_Unit!$D$26 | AA53: =AA$7*Per_Unit!$D$25 | AB53: =AB$7*Per_Unit!$D$24 | AC53: =AC$7*Per_Unit!$D$23 | AD53: =AD$7*Per_Unit!$D$22 | AE53: =AE$7*Per_Unit!$D$21 | AF53: =AF$7*Per_Unit!$D$20 | AG53: =AG$7*Per_Unit!$D$19 | AH53: =AH$7*Per_Unit!$D$18 | AI53: =AI$7*Per_Unit!$D$17 | AJ53: =AJ$7*Per_Unit!$D$16 | AK53: =AK$7*Per_Unit!$D$15 | AL53: =AL$7*Per_Unit!$D$14 | AM53: =AM$7*Per_Unit!$D$13 | AN53: =AN$7*Per_Unit!$D$12 | AO53: =AO$7*Per_Unit!$D$11 | AP53: =AP$7*Per_Unit!$D$10 | AQ53: =AQ$7*Per_Unit!$D$9 | AR53: =AR$7*Per_Unit!$D$8 | AS53: =AS$7*Per_Unit!$D$7
A54: 45 | B54: =B$7*Per_Unit!$D$51 | C54: =C$7*Per_Unit!$D$50 | D54: =D$7*Per_Unit!$D$49 | E54: =E$7*Per_Unit!$D$48 | F54: =F$7*Per_Unit!$D$47 | G54: =G$7*Per_Unit!$D$46 | H54: =H$7*Per_Unit!$D$45 | I54: =I$7*Per_Unit!$D$44 | J54: =J$7*Per_Unit!$D$43 | K54: =K$7*Per_Unit!$D$42 | L54: =L$7*Per_Unit!$D$41 | M54: =M$7*Per_Unit!$D$40 | N54: =N$7*Per_Unit!$D$39 | O54: =O$7*Per_Unit!$D$38 | P54: =P$7*Per_Unit!$D$37 | Q54: =Q$7*Per_Unit!$D$36 | R54: =R$7*Per_Unit!$D$35 | S54: =S$7*Per_Unit!$D$34 | T54: =T$7*Per_Unit!$D$33 | U54: =U$7*Per_Unit!$D$32 | V54: =V$7*Per_Unit!$D$31 | W54: =W$7*Per_Unit!$D$30 | X54: =X$7*Per_Unit!$D$29 | Y54: =Y$7*Per_Unit!$D$28 | Z54: =Z$7*Per_Unit!$D$27 | AA54: =AA$7*Per_Unit!$D$26 | AB54: =AB$7*Per_Unit!$D$25 | AC54: =AC$7*Per_Unit!$D$24 | AD54: =AD$7*Per_Unit!$D$23 | AE54: =AE$7*Per_Unit!$D$22 | AF54: =AF$7*Per_Unit!$D$21 | AG54: =AG$7*Per_Unit!$D$20 | AH54: =AH$7*Per_Unit!$D$19 | AI54: =AI$7*Per_Unit!$D$18 | AJ54: =AJ$7*Per_Unit!$D$17 | AK54: =AK$7*Per_Unit!$D$16 | AL54: =AL$7*Per_Unit!$D$15 | AM54: =AM$7*Per_Unit!$D$14 | AN54: =AN$7*Per_Unit!$D$13 | AO54: =AO$7*Per_Unit!$D$12 | AP54: =AP$7*Per_Unit!$D$11 | AQ54: =AQ$7*Per_Unit!$D$10 | AR54: =AR$7*Per_Unit!$D$9 | AS54: =AS$7*Per_Unit!$D$8 | AT54: =AT$7*Per_Unit!$D$7
A55: 46 | B55: =B$7*Per_Unit!$D$52 | C55: =C$7*Per_Unit!$D$51 | D55: =D$7*Per_Unit!$D$50 | E55: =E$7*Per_Unit!$D$49 | F55: =F$7*Per_Unit!$D$48 | G55: =G$7*Per_Unit!$D$47 | H55: =H$7*Per_Unit!$D$46 | I55: =I$7*Per_Unit!$D$45 | J55: =J$7*Per_Unit!$D$44 | K55: =K$7*Per_Unit!$D$43 | L55: =L$7*Per_Unit!$D$42 | M55: =M$7*Per_Unit!$D$41 | N55: =N$7*Per_Unit!$D$40 | O55: =O$7*Per_Unit!$D$39 | P55: =P$7*Per_Unit!$D$38 | Q55: =Q$7*Per_Unit!$D$37 | R55: =R$7*Per_Unit!$D$36 | S55: =S$7*Per_Unit!$D$35 | T55: =T$7*Per_Unit!$D$34 | U55: =U$7*Per_Unit!$D$33 | V55: =V$7*Per_Unit!$D$32 | W55: =W$7*Per_Unit!$D$31 | X55: =X$7*Per_Unit!$D$30 | Y55: =Y$7*Per_Unit!$D$29 | Z55: =Z$7*Per_Unit!$D$28 | AA55: =AA$7*Per_Unit!$D$27 | AB55: =AB$7*Per_Unit!$D$26 | AC55: =AC$7*Per_Unit!$D$25 | AD55: =AD$7*Per_Unit!$D$24 | AE55: =AE$7*Per_Unit!$D$23 | AF55: =AF$7*Per_Unit!$D$22 | AG55: =AG$7*Per_Unit!$D$21 | AH55: =AH$7*Per_Unit!$D$20 | AI55: =AI$7*Per_Unit!$D$19 | AJ55: =AJ$7*Per_Unit!$D$18 | AK55: =AK$7*Per_Unit!$D$17 | AL55: =AL$7*Per_Unit!$D$16 | AM55: =AM$7*Per_Unit!$D$15 | AN55: =AN$7*Per_Unit!$D$14 | AO55: =AO$7*Per_Unit!$D$13 | AP55: =AP$7*Per_Unit!$D$12 | AQ55: =AQ$7*Per_Unit!$D$11 | AR55: =AR$7*Per_Unit!$D$10 | AS55: =AS$7*Per_Unit!$D$9 | AT55: =AT$7*Per_Unit!$D$8 | AU55: =AU$7*Per_Unit!$D$7
A56: 47 | B56: =B$7*Per_Unit!$D$53 | C56: =C$7*Per_Unit!$D$52 | D56: =D$7*Per_Unit!$D$51 | E56: =E$7*Per_Unit!$D$50 | F56: =F$7*Per_Unit!$D$49 | G56: =G$7*Per_Unit!$D$48 | H56: =H$7*Per_Unit!$D$47 | I56: =I$7*Per_Unit!$D$46 | J56: =J$7*Per_Unit!$D$45 | K56: =K$7*Per_Unit!$D$44 | L56: =L$7*Per_Unit!$D$43 | M56: =M$7*Per_Unit!$D$42 | N56: =N$7*Per_Unit!$D$41 | O56: =O$7*Per_Unit!$D$40 | P56: =P$7*Per_Unit!$D$39 | Q56: =Q$7*Per_Unit!$D$38 | R56: =R$7*Per_Unit!$D$37 | S56: =S$7*Per_Unit!$D$36 | T56: =T$7*Per_Unit!$D$35 | U56: =U$7*Per_Unit!$D$34 | V56: =V$7*Per_Unit!$D$33 | W56: =W$7*Per_Unit!$D$32 | X56: =X$7*Per_Unit!$D$31 | Y56: =Y$7*Per_Unit!$D$30 | Z56: =Z$7*Per_Unit!$D$29 | AA56: =AA$7*Per_Unit!$D$28 | AB56: =AB$7*Per_Unit!$D$27 | AC56: =AC$7*Per_Unit!$D$26 | AD56: =AD$7*Per_Unit!$D$25 | AE56: =AE$7*Per_Unit!$D$24 | AF56: =AF$7*Per_Unit!$D$23 | AG56: =AG$7*Per_Unit!$D$22 | AH56: =AH$7*Per_Unit!$D$21 | AI56: =AI$7*Per_Unit!$D$20 | AJ56: =AJ$7*Per_Unit!$D$19 | AK56: =AK$7*Per_Unit!$D$18 | AL56: =AL$7*Per_Unit!$D$17 | AM56: =AM$7*Per_Unit!$D$16 | AN56: =AN$7*Per_Unit!$D$15 | AO56: =AO$7*Per_Unit!$D$14 | AP56: =AP$7*Per_Unit!$D$13 | AQ56: =AQ$7*Per_Unit!$D$12 | AR56: =AR$7*Per_Unit!$D$11 | AS56: =AS$7*Per_Unit!$D$10 | AT56: =AT$7*Per_Unit!$D$9 | AU56: =AU$7*Per_Unit!$D$8 | AV56: =AV$7*Per_Unit!$D$7
A57: 48 | B57: =B$7*Per_Unit!$D$54 | C57: =C$7*Per_Unit!$D$53 | D57: =D$7*Per_Unit!$D$52 | E57: =E$7*Per_Unit!$D$51 | F57: =F$7*Per_Unit!$D$50 | G57: =G$7*Per_Unit!$D$49 | H57: =H$7*Per_Unit!$D$48 | I57: =I$7*Per_Unit!$D$47 | J57: =J$7*Per_Unit!$D$46 | K57: =K$7*Per_Unit!$D$45 | L57: =L$7*Per_Unit!$D$44 | M57: =M$7*Per_Unit!$D$43 | N57: =N$7*Per_Unit!$D$42 | O57: =O$7*Per_Unit!$D$41 | P57: =P$7*Per_Unit!$D$40 | Q57: =Q$7*Per_Unit!$D$39 | R57: =R$7*Per_Unit!$D$38 | S57: =S$7*Per_Unit!$D$37 | T57: =T$7*Per_Unit!$D$36 | U57: =U$7*Per_Unit!$D$35 | V57: =V$7*Per_Unit!$D$34 | W57: =W$7*Per_Unit!$D$33 | X57: =X$7*Per_Unit!$D$32 | Y57: =Y$7*Per_Unit!$D$31 | Z57: =Z$7*Per_Unit!$D$30 | AA57: =AA$7*Per_Unit!$D$29 | AB57: =AB$7*Per_Unit!$D$28 | AC57: =AC$7*Per_Unit!$D$27 | AD57: =AD$7*Per_Unit!$D$26 | AE57: =AE$7*Per_Unit!$D$25 | AF57: =AF$7*Per_Unit!$D$24 | AG57: =AG$7*Per_Unit!$D$23 | AH57: =AH$7*Per_Unit!$D$22 | AI57: =AI$7*Per_Unit!$D$21 | AJ57: =AJ$7*Per_Unit!$D$20 | AK57: =AK$7*Per_Unit!$D$19 | AL57: =AL$7*Per_Unit!$D$18 | AM57: =AM$7*Per_Unit!$D$17 | AN57: =AN$7*Per_Unit!$D$16 | AO57: =AO$7*Per_Unit!$D$15 | AP57: =AP$7*Per_Unit!$D$14 | AQ57: =AQ$7*Per_Unit!$D$13 | AR57: =AR$7*Per_Unit!$D$12 | AS57: =AS$7*Per_Unit!$D$11 | AT57: =AT$7*Per_Unit!$D$10 | AU57: =AU$7*Per_Unit!$D$9 | AV57: =AV$7*Per_Unit!$D$8 | AW57: =AW$7*Per_Unit!$D$7
A58: 49 | B58: =B$7*Per_Unit!$D$55 | C58: =C$7*Per_Unit!$D$54 | D58: =D$7*Per_Unit!$D$53 | E58: =E$7*Per_Unit!$D$52 | F58: =F$7*Per_Unit!$D$51 | G58: =G$7*Per_Unit!$D$50 | H58: =H$7*Per_Unit!$D$49 | I58: =I$7*Per_Unit!$D$48 | J58: =J$7*Per_Unit!$D$47 | K58: =K$7*Per_Unit!$D$46 | L58: =L$7*Per_Unit!$D$45 | M58: =M$7*Per_Unit!$D$44 | N58: =N$7*Per_Unit!$D$43 | O58: =O$7*Per_Unit!$D$42 | P58: =P$7*Per_Unit!$D$41 | Q58: =Q$7*Per_Unit!$D$40 | R58: =R$7*Per_Unit!$D$39 | S58: =S$7*Per_Unit!$D$38 | T58: =T$7*Per_Unit!$D$37 | U58: =U$7*Per_Unit!$D$36 | V58: =V$7*Per_Unit!$D$35 | W58: =W$7*Per_Unit!$D$34 | X58: =X$7*Per_Unit!$D$33 | Y58: =Y$7*Per_Unit!$D$32 | Z58: =Z$7*Per_Unit!$D$31 | AA58: =AA$7*Per_Unit!$D$30 | AB58: =AB$7*Per_Unit!$D$29 | AC58: =AC$7*Per_Unit!$D$28 | AD58: =AD$7*Per_Unit!$D$27 | AE58: =AE$7*Per_Unit!$D$26 | AF58: =AF$7*Per_Unit!$D$25 | AG58: =AG$7*Per_Unit!$D$24 | AH58: =AH$7*Per_Unit!$D$23 | AI58: =AI$7*Per_Unit!$D$22 | AJ58: =AJ$7*Per_Unit!$D$21 | AK58: =AK$7*Per_Unit!$D$20 | AL58: =AL$7*Per_Unit!$D$19 | AM58: =AM$7*Per_Unit!$D$18 | AN58: =AN$7*Per_Unit!$D$17 | AO58: =AO$7*Per_Unit!$D$16 | AP58: =AP$7*Per_Unit!$D$15 | AQ58: =AQ$7*Per_Unit!$D$14 | AR58: =AR$7*Per_Unit!$D$13 | AS58: =AS$7*Per_Unit!$D$12 | AT58: =AT$7*Per_Unit!$D$11 | AU58: =AU$7*Per_Unit!$D$10 | AV58: =AV$7*Per_Unit!$D$9 | AW58: =AW$7*Per_Unit!$D$8 | AX58: =AX$7*Per_Unit!$D$7
A59: 50 | B59: =B$7*Per_Unit!$D$56 | C59: =C$7*Per_Unit!$D$55 | D59: =D$7*Per_Unit!$D$54 | E59: =E$7*Per_Unit!$D$53 | F59: =F$7*Per_Unit!$D$52 | G59: =G$7*Per_Unit!$D$51 | H59: =H$7*Per_Unit!$D$50 | I59: =I$7*Per_Unit!$D$49 | J59: =J$7*Per_Unit!$D$48 | K59: =K$7*Per_Unit!$D$47 | L59: =L$7*Per_Unit!$D$46 | M59: =M$7*Per_Unit!$D$45 | N59: =N$7*Per_Unit!$D$44 | O59: =O$7*Per_Unit!$D$43 | P59: =P$7*Per_Unit!$D$42 | Q59: =Q$7*Per_Unit!$D$41 | R59: =R$7*Per_Unit!$D$40 | S59: =S$7*Per_Unit!$D$39 | T59: =T$7*Per_Unit!$D$38 | U59: =U$7*Per_Unit!$D$37 | V59: =V$7*Per_Unit!$D$36 | W59: =W$7*Per_Unit!$D$35 | X59: =X$7*Per_Unit!$D$34 | Y59: =Y$7*Per_Unit!$D$33 | Z59: =Z$7*Per_Unit!$D$32 | AA59: =AA$7*Per_Unit!$D$31 | AB59: =AB$7*Per_Unit!$D$30 | AC59: =AC$7*Per_Unit!$D$29 | AD59: =AD$7*Per_Unit!$D$28 | AE59: =AE$7*Per_Unit!$D$27 | AF59: =AF$7*Per_Unit!$D$26 | AG59: =AG$7*Per_Unit!$D$25 | AH59: =AH$7*Per_Unit!$D$24 | AI59: =AI$7*Per_Unit!$D$23 | AJ59: =AJ$7*Per_Unit!$D$22 | AK59: =AK$7*Per_Unit!$D$21 | AL59: =AL$7*Per_Unit!$D$20 | AM59: =AM$7*Per_Unit!$D$19 | AN59: =AN$7*Per_Unit!$D$18 | AO59: =AO$7*Per_Unit!$D$17 | AP59: =AP$7*Per_Unit!$D$16 | AQ59: =AQ$7*Per_Unit!$D$15 | AR59: =AR$7*Per_Unit!$D$14 | AS59: =AS$7*Per_Unit!$D$13 | AT59: =AT$7*Per_Unit!$D$12 | AU59: =AU$7*Per_Unit!$D$11 | AV59: =AV$7*Per_Unit!$D$10 | AW59: =AW$7*Per_Unit!$D$9 | AX59: =AX$7*Per_Unit!$D$8 | AY59: =AY$7*Per_Unit!$D$7
A60: 51 | B60: =B$7*Per_Unit!$D$57 | C60: =C$7*Per_Unit!$D$56 | D60: =D$7*Per_Unit!$D$55 | E60: =E$7*Per_Unit!$D$54 | F60: =F$7*Per_Unit!$D$53 | G60: =G$7*Per_Unit!$D$52 | H60: =H$7*Per_Unit!$D$51 | I60: =I$7*Per_Unit!$D$50 | J60: =J$7*Per_Unit!$D$49 | K60: =K$7*Per_Unit!$D$48 | L60: =L$7*Per_Unit!$D$47 | M60: =M$7*Per_Unit!$D$46 | N60: =N$7*Per_Unit!$D$45 | O60: =O$7*Per_Unit!$D$44 | P60: =P$7*Per_Unit!$D$43 | Q60: =Q$7*Per_Unit!$D$42 | R60: =R$7*Per_Unit!$D$41 | S60: =S$7*Per_Unit!$D$40 | T60: =T$7*Per_Unit!$D$39 | U60: =U$7*Per_Unit!$D$38 | V60: =V$7*Per_Unit!$D$37 | W60: =W$7*Per_Unit!$D$36 | X60: =X$7*Per_Unit!$D$35 | Y60: =Y$7*Per_Unit!$D$34 | Z60: =Z$7*Per_Unit!$D$33 | AA60: =AA$7*Per_Unit!$D$32 | AB60: =AB$7*Per_Unit!$D$31 | AC60: =AC$7*Per_Unit!$D$30 | AD60: =AD$7*Per_Unit!$D$29 | AE60: =AE$7*Per_Unit!$D$28 | AF60: =AF$7*Per_Unit!$D$27 | AG60: =AG$7*Per_Unit!$D$26 | AH60: =AH$7*Per_Unit!$D$25 | AI60: =AI$7*Per_Unit!$D$24 | AJ60: =AJ$7*Per_Unit!$D$23 | AK60: =AK$7*Per_Unit!$D$22 | AL60: =AL$7*Per_Unit!$D$21 | AM60: =AM$7*Per_Unit!$D$20 | AN60: =AN$7*Per_Unit!$D$19 | AO60: =AO$7*Per_Unit!$D$18 | AP60: =AP$7*Per_Unit!$D$17 | AQ60: =AQ$7*Per_Unit!$D$16 | AR60: =AR$7*Per_Unit!$D$15 | AS60: =AS$7*Per_Unit!$D$14 | AT60: =AT$7*Per_Unit!$D$13 | AU60: =AU$7*Per_Unit!$D$12 | AV60: =AV$7*Per_Unit!$D$11 | AW60: =AW$7*Per_Unit!$D$10 | AX60: =AX$7*Per_Unit!$D$9 | AY60: =AY$7*Per_Unit!$D$8 | AZ60: =AZ$7*Per_Unit!$D$7
A61: 52 | B61: =B$7*Per_Unit!$D$58 | C61: =C$7*Per_Unit!$D$57 | D61: =D$7*Per_Unit!$D$56 | E61: =E$7*Per_Unit!$D$55 | F61: =F$7*Per_Unit!$D$54 | G61: =G$7*Per_Unit!$D$53 | H61: =H$7*Per_Unit!$D$52 | I61: =I$7*Per_Unit!$D$51 | J61: =J$7*Per_Unit!$D$50 | K61: =K$7*Per_Unit!$D$49 | L61: =L$7*Per_Unit!$D$48 | M61: =M$7*Per_Unit!$D$47 | N61: =N$7*Per_Unit!$D$46 | O61: =O$7*Per_Unit!$D$45 | P61: =P$7*Per_Unit!$D$44 | Q61: =Q$7*Per_Unit!$D$43 | R61: =R$7*Per_Unit!$D$42 | S61: =S$7*Per_Unit!$D$41 | T61: =T$7*Per_Unit!$D$40 | U61: =U$7*Per_Unit!$D$39 | V61: =V$7*Per_Unit!$D$38 | W61: =W$7*Per_Unit!$D$37 | X61: =X$7*Per_Unit!$D$36 | Y61: =Y$7*Per_Unit!$D$35 | Z61: =Z$7*Per_Unit!$D$34 | AA61: =AA$7*Per_Unit!$D$33 | AB61: =AB$7*Per_Unit!$D$32 | AC61: =AC$7*Per_Unit!$D$31 | AD61: =AD$7*Per_Unit!$D$30 | AE61: =AE$7*Per_Unit!$D$29 | AF61: =AF$7*Per_Unit!$D$28 | AG61: =AG$7*Per_Unit!$D$27 | AH61: =AH$7*Per_Unit!$D$26 | AI61: =AI$7*Per_Unit!$D$25 | AJ61: =AJ$7*Per_Unit!$D$24 | AK61: =AK$7*Per_Unit!$D$23 | AL61: =AL$7*Per_Unit!$D$22 | AM61: =AM$7*Per_Unit!$D$21 | AN61: =AN$7*Per_Unit!$D$20 | AO61: =AO$7*Per_Unit!$D$19 | AP61: =AP$7*Per_Unit!$D$18 | AQ61: =AQ$7*Per_Unit!$D$17 | AR61: =AR$7*Per_Unit!$D$16 | AS61: =AS$7*Per_Unit!$D$15 | AT61: =AT$7*Per_Unit!$D$14 | AU61: =AU$7*Per_Unit!$D$13 | AV61: =AV$7*Per_Unit!$D$12 | AW61: =AW$7*Per_Unit!$D$11 | AX61: =AX$7*Per_Unit!$D$10 | AY61: =AY$7*Per_Unit!$D$9 | AZ61: =AZ$7*Per_Unit!$D$8 | BA61: =BA$7*Per_Unit!$D$7
A62: 53 | B62: =B$7*Per_Unit!$D$59 | C62: =C$7*Per_Unit!$D$58 | D62: =D$7*Per_Unit!$D$57 | E62: =E$7*Per_Unit!$D$56 | F62: =F$7*Per_Unit!$D$55 | G62: =G$7*Per_Unit!$D$54 | H62: =H$7*Per_Unit!$D$53 | I62: =I$7*Per_Unit!$D$52 | J62: =J$7*Per_Unit!$D$51 | K62: =K$7*Per_Unit!$D$50 | L62: =L$7*Per_Unit!$D$49 | M62: =M$7*Per_Unit!$D$48 | N62: =N$7*Per_Unit!$D$47 | O62: =O$7*Per_Unit!$D$46 | P62: =P$7*Per_Unit!$D$45 | Q62: =Q$7*Per_Unit!$D$44 | R62: =R$7*Per_Unit!$D$43 | S62: =S$7*Per_Unit!$D$42 | T62: =T$7*Per_Unit!$D$41 | U62: =U$7*Per_Unit!$D$40 | V62: =V$7*Per_Unit!$D$39 | W62: =W$7*Per_Unit!$D$38 | X62: =X$7*Per_Unit!$D$37 | Y62: =Y$7*Per_Unit!$D$36 | Z62: =Z$7*Per_Unit!$D$35 | AA62: =AA$7*Per_Unit!$D$34 | AB62: =AB$7*Per_Unit!$D$33 | AC62: =AC$7*Per_Unit!$D$32 | AD62: =AD$7*Per_Unit!$D$31 | AE62: =AE$7*Per_Unit!$D$30 | AF62: =AF$7*Per_Unit!$D$29 | AG62: =AG$7*Per_Unit!$D$28 | AH62: =AH$7*Per_Unit!$D$27 | AI62: =AI$7*Per_Unit!$D$26 | AJ62: =AJ$7*Per_Unit!$D$25 | AK62: =AK$7*Per_Unit!$D$24 | AL62: =AL$7*Per_Unit!$D$23 | AM62: =AM$7*Per_Unit!$D$22 | AN62: =AN$7*Per_Unit!$D$21 | AO62: =AO$7*Per_Unit!$D$20 | AP62: =AP$7*Per_Unit!$D$19 | AQ62: =AQ$7*Per_Unit!$D$18 | AR62: =AR$7*Per_Unit!$D$17 | AS62: =AS$7*Per_Unit!$D$16 | AT62: =AT$7*Per_Unit!$D$15 | AU62: =AU$7*Per_Unit!$D$14 | AV62: =AV$7*Per_Unit!$D$13 | AW62: =AW$7*Per_Unit!$D$12 | AX62: =AX$7*Per_Unit!$D$11 | AY62: =AY$7*Per_Unit!$D$10 | AZ62: =AZ$7*Per_Unit!$D$9 | BA62: =BA$7*Per_Unit!$D$8 | BB62: =BB$7*Per_Unit!$D$7
A63: 54 | B63: =B$7*Per_Unit!$D$60 | C63: =C$7*Per_Unit!$D$59 | D63: =D$7*Per_Unit!$D$58 | E63: =E$7*Per_Unit!$D$57 | F63: =F$7*Per_Unit!$D$56 | G63: =G$7*Per_Unit!$D$55 | H63: =H$7*Per_Unit!$D$54 | I63: =I$7*Per_Unit!$D$53 | J63: =J$7*Per_Unit!$D$52 | K63: =K$7*Per_Unit!$D$51 | L63: =L$7*Per_Unit!$D$50 | M63: =M$7*Per_Unit!$D$49 | N63: =N$7*Per_Unit!$D$48 | O63: =O$7*Per_Unit!$D$47 | P63: =P$7*Per_Unit!$D$46 | Q63: =Q$7*Per_Unit!$D$45 | R63: =R$7*Per_Unit!$D$44 | S63: =S$7*Per_Unit!$D$43 | T63: =T$7*Per_Unit!$D$42 | U63: =U$7*Per_Unit!$D$41 | V63: =V$7*Per_Unit!$D$40 | W63: =W$7*Per_Unit!$D$39 | X63: =X$7*Per_Unit!$D$38 | Y63: =Y$7*Per_Unit!$D$37 | Z63: =Z$7*Per_Unit!$D$36 | AA63: =AA$7*Per_Unit!$D$35 | AB63: =AB$7*Per_Unit!$D$34 | AC63: =AC$7*Per_Unit!$D$33 | AD63: =AD$7*Per_Unit!$D$32 | AE63: =AE$7*Per_Unit!$D$31 | AF63: =AF$7*Per_Unit!$D$30 | AG63: =AG$7*Per_Unit!$D$29 | AH63: =AH$7*Per_Unit!$D$28 | AI63: =AI$7*Per_Unit!$D$27 | AJ63: =AJ$7*Per_Unit!$D$26 | AK63: =AK$7*Per_Unit!$D$25 | AL63: =AL$7*Per_Unit!$D$24 | AM63: =AM$7*Per_Unit!$D$23 | AN63: =AN$7*Per_Unit!$D$22 | AO63: =AO$7*Per_Unit!$D$21 | AP63: =AP$7*Per_Unit!$D$20 | AQ63: =AQ$7*Per_Unit!$D$19 | AR63: =AR$7*Per_Unit!$D$18 | AS63: =AS$7*Per_Unit!$D$17 | AT63: =AT$7*Per_Unit!$D$16 | AU63: =AU$7*Per_Unit!$D$15 | AV63: =AV$7*Per_Unit!$D$14 | AW63: =AW$7*Per_Unit!$D$13 | AX63: =AX$7*Per_Unit!$D$12 | AY63: =AY$7*Per_Unit!$D$11 | AZ63: =AZ$7*Per_Unit!$D$10 | BA63: =BA$7*Per_Unit!$D$9 | BB63: =BB$7*Per_Unit!$D$8 | BC63: =BC$7*Per_Unit!$D$7
A64: 55 | B64: =B$7*Per_Unit!$D$61 | C64: =C$7*Per_Unit!$D$60 | D64: =D$7*Per_Unit!$D$59 | E64: =E$7*Per_Unit!$D$58 | F64: =F$7*Per_Unit!$D$57 | G64: =G$7*Per_Unit!$D$56 | H64: =H$7*Per_Unit!$D$55 | I64: =I$7*Per_Unit!$D$54 | J64: =J$7*Per_Unit!$D$53 | K64: =K$7*Per_Unit!$D$52 | L64: =L$7*Per_Unit!$D$51 | M64: =M$7*Per_Unit!$D$50 | N64: =N$7*Per_Unit!$D$49 | O64: =O$7*Per_Unit!$D$48 | P64: =P$7*Per_Unit!$D$47 | Q64: =Q$7*Per_Unit!$D$46 | R64: =R$7*Per_Unit!$D$45 | S64: =S$7*Per_Unit!$D$44 | T64: =T$7*Per_Unit!$D$43 | U64: =U$7*Per_Unit!$D$42 | V64: =V$7*Per_Unit!$D$41 | W64: =W$7*Per_Unit!$D$40 | X64: =X$7*Per_Unit!$D$39 | Y64: =Y$7*Per_Unit!$D$38 | Z64: =Z$7*Per_Unit!$D$37 | AA64: =AA$7*Per_Unit!$D$36 | AB64: =AB$7*Per_Unit!$D$35 | AC64: =AC$7*Per_Unit!$D$34 | AD64: =AD$7*Per_Unit!$D$33 | AE64: =AE$7*Per_Unit!$D$32 | AF64: =AF$7*Per_Unit!$D$31 | AG64: =AG$7*Per_Unit!$D$30 | AH64: =AH$7*Per_Unit!$D$29 | AI64: =AI$7*Per_Unit!$D$28 | AJ64: =AJ$7*Per_Unit!$D$27 | AK64: =AK$7*Per_Unit!$D$26 | AL64: =AL$7*Per_Unit!$D$25 | AM64: =AM$7*Per_Unit!$D$24 | AN64: =AN$7*Per_Unit!$D$23 | AO64: =AO$7*Per_Unit!$D$22 | AP64: =AP$7*Per_Unit!$D$21 | AQ64: =AQ$7*Per_Unit!$D$20 | AR64: =AR$7*Per_Unit!$D$19 | AS64: =AS$7*Per_Unit!$D$18 | AT64: =AT$7*Per_Unit!$D$17 | AU64: =AU$7*Per_Unit!$D$16 | AV64: =AV$7*Per_Unit!$D$15 | AW64: =AW$7*Per_Unit!$D$14 | AX64: =AX$7*Per_Unit!$D$13 | AY64: =AY$7*Per_Unit!$D$12 | AZ64: =AZ$7*Per_Unit!$D$11 | BA64: =BA$7*Per_Unit!$D$10 | BB64: =BB$7*Per_Unit!$D$9 | BC64: =BC$7*Per_Unit!$D$8 | BD64: =BD$7*Per_Unit!$D$7
A65: 56 | B65: =B$7*Per_Unit!$D$62 | C65: =C$7*Per_Unit!$D$61 | D65: =D$7*Per_Unit!$D$60 | E65: =E$7*Per_Unit!$D$59 | F65: =F$7*Per_Unit!$D$58 | G65: =G$7*Per_Unit!$D$57 | H65: =H$7*Per_Unit!$D$56 | I65: =I$7*Per_Unit!$D$55 | J65: =J$7*Per_Unit!$D$54 | K65: =K$7*Per_Unit!$D$53 | L65: =L$7*Per_Unit!$D$52 | M65: =M$7*Per_Unit!$D$51 | N65: =N$7*Per_Unit!$D$50 | O65: =O$7*Per_Unit!$D$49 | P65: =P$7*Per_Unit!$D$48 | Q65: =Q$7*Per_Unit!$D$47 | R65: =R$7*Per_Unit!$D$46 | S65: =S$7*Per_Unit!$D$45 | T65: =T$7*Per_Unit!$D$44 | U65: =U$7*Per_Unit!$D$43 | V65: =V$7*Per_Unit!$D$42 | W65: =W$7*Per_Unit!$D$41 | X65: =X$7*Per_Unit!$D$40 | Y65: =Y$7*Per_Unit!$D$39 | Z65: =Z$7*Per_Unit!$D$38 | AA65: =AA$7*Per_Unit!$D$37 | AB65: =AB$7*Per_Unit!$D$36 | AC65: =AC$7*Per_Unit!$D$35 | AD65: =AD$7*Per_Unit!$D$34 | AE65: =AE$7*Per_Unit!$D$33 | AF65: =AF$7*Per_Unit!$D$32 | AG65: =AG$7*Per_Unit!$D$31 | AH65: =AH$7*Per_Unit!$D$30 | AI65: =AI$7*Per_Unit!$D$29 | AJ65: =AJ$7*Per_Unit!$D$28 | AK65: =AK$7*Per_Unit!$D$27 | AL65: =AL$7*Per_Unit!$D$26 | AM65: =AM$7*Per_Unit!$D$25 | AN65: =AN$7*Per_Unit!$D$24 | AO65: =AO$7*Per_Unit!$D$23 | AP65: =AP$7*Per_Unit!$D$22 | AQ65: =AQ$7*Per_Unit!$D$21 | AR65: =AR$7*Per_Unit!$D$20 | AS65: =AS$7*Per_Unit!$D$19 | AT65: =AT$7*Per_Unit!$D$18 | AU65: =AU$7*Per_Unit!$D$17 | AV65: =AV$7*Per_Unit!$D$16 | AW65: =AW$7*Per_Unit!$D$15 | AX65: =AX$7*Per_Unit!$D$14 | AY65: =AY$7*Per_Unit!$D$13 | AZ65: =AZ$7*Per_Unit!$D$12 | BA65: =BA$7*Per_Unit!$D$11 | BB65: =BB$7*Per_Unit!$D$10 | BC65: =BC$7*Per_Unit!$D$9 | BD65: =BD$7*Per_Unit!$D$8 | BE65: =BE$7*Per_Unit!$D$7
A66: 57 | B66: =B$7*Per_Unit!$D$63 | C66: =C$7*Per_Unit!$D$62 | D66: =D$7*Per_Unit!$D$61 | E66: =E$7*Per_Unit!$D$60 | F66: =F$7*Per_Unit!$D$59 | G66: =G$7*Per_Unit!$D$58 | H66: =H$7*Per_Unit!$D$57 | I66: =I$7*Per_Unit!$D$56 | J66: =J$7*Per_Unit!$D$55 | K66: =K$7*Per_Unit!$D$54 | L66: =L$7*Per_Unit!$D$53 | M66: =M$7*Per_Unit!$D$52 | N66: =N$7*Per_Unit!$D$51 | O66: =O$7*Per_Unit!$D$50 | P66: =P$7*Per_Unit!$D$49 | Q66: =Q$7*Per_Unit!$D$48 | R66: =R$7*Per_Unit!$D$47 | S66: =S$7*Per_Unit!$D$46 | T66: =T$7*Per_Unit!$D$45 | U66: =U$7*Per_Unit!$D$44 | V66: =V$7*Per_Unit!$D$43 | W66: =W$7*Per_Unit!$D$42 | X66: =X$7*Per_Unit!$D$41 | Y66: =Y$7*Per_Unit!$D$40 | Z66: =Z$7*Per_Unit!$D$39 | AA66: =AA$7*Per_Unit!$D$38 | AB66: =AB$7*Per_Unit!$D$37 | AC66: =AC$7*Per_Unit!$D$36 | AD66: =AD$7*Per_Unit!$D$35 | AE66: =AE$7*Per_Unit!$D$34 | AF66: =AF$7*Per_Unit!$D$33 | AG66: =AG$7*Per_Unit!$D$32 | AH66: =AH$7*Per_Unit!$D$31 | AI66: =AI$7*Per_Unit!$D$30 | AJ66: =AJ$7*Per_Unit!$D$29 | AK66: =AK$7*Per_Unit!$D$28 | AL66: =AL$7*Per_Unit!$D$27 | AM66: =AM$7*Per_Unit!$D$26 | AN66: =AN$7*Per_Unit!$D$25 | AO66: =AO$7*Per_Unit!$D$24 | AP66: =AP$7*Per_Unit!$D$23 | AQ66: =AQ$7*Per_Unit!$D$22 | AR66: =AR$7*Per_Unit!$D$21 | AS66: =AS$7*Per_Unit!$D$20 | AT66: =AT$7*Per_Unit!$D$19 | AU66: =AU$7*Per_Unit!$D$18 | AV66: =AV$7*Per_Unit!$D$17 | AW66: =AW$7*Per_Unit!$D$16 | AX66: =AX$7*Per_Unit!$D$15 | AY66: =AY$7*Per_Unit!$D$14 | AZ66: =AZ$7*Per_Unit!$D$13 | BA66: =BA$7*Per_Unit!$D$12 | BB66: =BB$7*Per_Unit!$D$11 | BC66: =BC$7*Per_Unit!$D$10 | BD66: =BD$7*Per_Unit!$D$9 | BE66: =BE$7*Per_Unit!$D$8 | BF66: =BF$7*Per_Unit!$D$7
A67: 58 | B67: =B$7*Per_Unit!$D$64 | C67: =C$7*Per_Unit!$D$63 | D67: =D$7*Per_Unit!$D$62 | E67: =E$7*Per_Unit!$D$61 | F67: =F$7*Per_Unit!$D$60 | G67: =G$7*Per_Unit!$D$59 | H67: =H$7*Per_Unit!$D$58 | I67: =I$7*Per_Unit!$D$57 | J67: =J$7*Per_Unit!$D$56 | K67: =K$7*Per_Unit!$D$55 | L67: =L$7*Per_Unit!$D$54 | M67: =M$7*Per_Unit!$D$53 | N67: =N$7*Per_Unit!$D$52 | O67: =O$7*Per_Unit!$D$51 | P67: =P$7*Per_Unit!$D$50 | Q67: =Q$7*Per_Unit!$D$49 | R67: =R$7*Per_Unit!$D$48 | S67: =S$7*Per_Unit!$D$47 | T67: =T$7*Per_Unit!$D$46 | U67: =U$7*Per_Unit!$D$45 | V67: =V$7*Per_Unit!$D$44 | W67: =W$7*Per_Unit!$D$43 | X67: =X$7*Per_Unit!$D$42 | Y67: =Y$7*Per_Unit!$D$41 | Z67: =Z$7*Per_Unit!$D$40 | AA67: =AA$7*Per_Unit!$D$39 | AB67: =AB$7*Per_Unit!$D$38 | AC67: =AC$7*Per_Unit!$D$37 | AD67: =AD$7*Per_Unit!$D$36 | AE67: =AE$7*Per_Unit!$D$35 | AF67: =AF$7*Per_Unit!$D$34 | AG67: =AG$7*Per_Unit!$D$33 | AH67: =AH$7*Per_Unit!$D$32 | AI67: =AI$7*Per_Unit!$D$31 | AJ67: =AJ$7*Per_Unit!$D$30 | AK67: =AK$7*Per_Unit!$D$29 | AL67: =AL$7*Per_Unit!$D$28 | AM67: =AM$7*Per_Unit!$D$27 | AN67: =AN$7*Per_Unit!$D$26 | AO67: =AO$7*Per_Unit!$D$25 | AP67: =AP$7*Per_Unit!$D$24 | AQ67: =AQ$7*Per_Unit!$D$23 | AR67: =AR$7*Per_Unit!$D$22 | AS67: =AS$7*Per_Unit!$D$21 | AT67: =AT$7*Per_Unit!$D$20 | AU67: =AU$7*Per_Unit!$D$19 | AV67: =AV$7*Per_Unit!$D$18 | AW67: =AW$7*Per_Unit!$D$17 | AX67: =AX$7*Per_Unit!$D$16 | AY67: =AY$7*Per_Unit!$D$15 | AZ67: =AZ$7*Per_Unit!$D$14 | BA67: =BA$7*Per_Unit!$D$13 | BB67: =BB$7*Per_Unit!$D$12 | BC67: =BC$7*Per_Unit!$D$11 | BD67: =BD$7*Per_Unit!$D$10 | BE67: =BE$7*Per_Unit!$D$9 | BF67: =BF$7*Per_Unit!$D$8 | BG67: =BG$7*Per_Unit!$D$7
A68: 59 | B68: =B$7*Per_Unit!$D$65 | C68: =C$7*Per_Unit!$D$64 | D68: =D$7*Per_Unit!$D$63 | E68: =E$7*Per_Unit!$D$62 | F68: =F$7*Per_Unit!$D$61 | G68: =G$7*Per_Unit!$D$60 | H68: =H$7*Per_Unit!$D$59 | I68: =I$7*Per_Unit!$D$58 | J68: =J$7*Per_Unit!$D$57 | K68: =K$7*Per_Unit!$D$56 | L68: =L$7*Per_Unit!$D$55 | M68: =M$7*Per_Unit!$D$54 | N68: =N$7*Per_Unit!$D$53 | O68: =O$7*Per_Unit!$D$52 | P68: =P$7*Per_Unit!$D$51 | Q68: =Q$7*Per_Unit!$D$50 | R68: =R$7*Per_Unit!$D$49 | S68: =S$7*Per_Unit!$D$48 | T68: =T$7*Per_Unit!$D$47 | U68: =U$7*Per_Unit!$D$46 | V68: =V$7*Per_Unit!$D$45 | W68: =W$7*Per_Unit!$D$44 | X68: =X$7*Per_Unit!$D$43 | Y68: =Y$7*Per_Unit!$D$42 | Z68: =Z$7*Per_Unit!$D$41 | AA68: =AA$7*Per_Unit!$D$40 | AB68: =AB$7*Per_Unit!$D$39 | AC68: =AC$7*Per_Unit!$D$38 | AD68: =AD$7*Per_Unit!$D$37 | AE68: =AE$7*Per_Unit!$D$36 | AF68: =AF$7*Per_Unit!$D$35 | AG68: =AG$7*Per_Unit!$D$34 | AH68: =AH$7*Per_Unit!$D$33 | AI68: =AI$7*Per_Unit!$D$32 | AJ68: =AJ$7*Per_Unit!$D$31 | AK68: =AK$7*Per_Unit!$D$30 | AL68: =AL$7*Per_Unit!$D$29 | AM68: =AM$7*Per_Unit!$D$28 | AN68: =AN$7*Per_Unit!$D$27 | AO68: =AO$7*Per_Unit!$D$26 | AP68: =AP$7*Per_Unit!$D$25 | AQ68: =AQ$7*Per_Unit!$D$24 | AR68: =AR$7*Per_Unit!$D$23 | AS68: =AS$7*Per_Unit!$D$22 | AT68: =AT$7*Per_Unit!$D$21 | AU68: =AU$7*Per_Unit!$D$20 | AV68: =AV$7*Per_Unit!$D$19 | AW68: =AW$7*Per_Unit!$D$18 | AX68: =AX$7*Per_Unit!$D$17 | AY68: =AY$7*Per_Unit!$D$16 | AZ68: =AZ$7*Per_Unit!$D$15 | BA68: =BA$7*Per_Unit!$D$14 | BB68: =BB$7*Per_Unit!$D$13 | BC68: =BC$7*Per_Unit!$D$12 | BD68: =BD$7*Per_Unit!$D$11 | BE68: =BE$7*Per_Unit!$D$10 | BF68: =BF$7*Per_Unit!$D$9 | BG68: =BG$7*Per_Unit!$D$8 | BH68: =BH$7*Per_Unit!$D$7
A69: 60 | B69: =B$7*Per_Unit!$D$66 | C69: =C$7*Per_Unit!$D$65 | D69: =D$7*Per_Unit!$D$64 | E69: =E$7*Per_Unit!$D$63 | F69: =F$7*Per_Unit!$D$62 | G69: =G$7*Per_Unit!$D$61 | H69: =H$7*Per_Unit!$D$60 | I69: =I$7*Per_Unit!$D$59 | J69: =J$7*Per_Unit!$D$58 | K69: =K$7*Per_Unit!$D$57 | L69: =L$7*Per_Unit!$D$56 | M69: =M$7*Per_Unit!$D$55 | N69: =N$7*Per_Unit!$D$54 | O69: =O$7*Per_Unit!$D$53 | P69: =P$7*Per_Unit!$D$52 | Q69: =Q$7*Per_Unit!$D$51 | R69: =R$7*Per_Unit!$D$50 | S69: =S$7*Per_Unit!$D$49 | T69: =T$7*Per_Unit!$D$48 | U69: =U$7*Per_Unit!$D$47 | V69: =V$7*Per_Unit!$D$46 | W69: =W$7*Per_Unit!$D$45 | X69: =X$7*Per_Unit!$D$44 | Y69: =Y$7*Per_Unit!$D$43 | Z69: =Z$7*Per_Unit!$D$42 | AA69: =AA$7*Per_Unit!$D$41 | AB69: =AB$7*Per_Unit!$D$40 | AC69: =AC$7*Per_Unit!$D$39 | AD69: =AD$7*Per_Unit!$D$38 | AE69: =AE$7*Per_Unit!$D$37 | AF69: =AF$7*Per_Unit!$D$36 | AG69: =AG$7*Per_Unit!$D$35 | AH69: =AH$7*Per_Unit!$D$34 | AI69: =AI$7*Per_Unit!$D$33 | AJ69: =AJ$7*Per_Unit!$D$32 | AK69: =AK$7*Per_Unit!$D$31 | AL69: =AL$7*Per_Unit!$D$30 | AM69: =AM$7*Per_Unit!$D$29 | AN69: =AN$7*Per_Unit!$D$28 | AO69: =AO$7*Per_Unit!$D$27 | AP69: =AP$7*Per_Unit!$D$26 | AQ69: =AQ$7*Per_Unit!$D$25 | AR69: =AR$7*Per_Unit!$D$24 | AS69: =AS$7*Per_Unit!$D$23 | AT69: =AT$7*Per_Unit!$D$22 | AU69: =AU$7*Per_Unit!$D$21 | AV69: =AV$7*Per_Unit!$D$20 | AW69: =AW$7*Per_Unit!$D$19 | AX69: =AX$7*Per_Unit!$D$18 | AY69: =AY$7*Per_Unit!$D$17 | AZ69: =AZ$7*Per_Unit!$D$16 | BA69: =BA$7*Per_Unit!$D$15 | BB69: =BB$7*Per_Unit!$D$14 | BC69: =BC$7*Per_Unit!$D$13 | BD69: =BD$7*Per_Unit!$D$12 | BE69: =BE$7*Per_Unit!$D$11 | BF69: =BF$7*Per_Unit!$D$10 | BG69: =BG$7*Per_Unit!$D$9 | BH69: =BH$7*Per_Unit!$D$8 | BI69: =BI$7*Per_Unit!$D$7
A71: Collections
A72: 1 | B72: =B$7*Per_Unit!$C$7
A73: 2 | B73: =B$7*Per_Unit!$C$8 | C73: =C$7*Per_Unit!$C$7
A74: 3 | B74: =B$7*Per_Unit!$C$9 | C74: =C$7*Per_Unit!$C$8 | D74: =D$7*Per_Unit!$C$7
A75: 4 | B75: =B$7*Per_Unit!$C$10 | C75: =C$7*Per_Unit!$C$9 | D75: =D$7*Per_Unit!$C$8 | E75: =E$7*Per_Unit!$C$7
A76: 5 | B76: =B$7*Per_Unit!$C$11 | C76: =C$7*Per_Unit!$C$10 | D76: =D$7*Per_Unit!$C$9 | E76: =E$7*Per_Unit!$C$8 | F76: =F$7*Per_Unit!$C$7
A77: 6 | B77: =B$7*Per_Unit!$C$12 | C77: =C$7*Per_Unit!$C$11 | D77: =D$7*Per_Unit!$C$10 | E77: =E$7*Per_Unit!$C$9 | F77: =F$7*Per_Unit!$C$8 | G77: =G$7*Per_Unit!$C$7
A78: 7 | B78: =B$7*Per_Unit!$C$13 | C78: =C$7*Per_Unit!$C$12 | D78: =D$7*Per_Unit!$C$11 | E78: =E$7*Per_Unit!$C$10 | F78: =F$7*Per_Unit!$C$9 | G78: =G$7*Per_Unit!$C$8 | H78: =H$7*Per_Unit!$C$7
A79: 8 | B79: =B$7*Per_Unit!$C$14 | C79: =C$7*Per_Unit!$C$13 | D79: =D$7*Per_Unit!$C$12 | E79: =E$7*Per_Unit!$C$11 | F79: =F$7*Per_Unit!$C$10 | G79: =G$7*Per_Unit!$C$9 | H79: =H$7*Per_Unit!$C$8 | I79: =I$7*Per_Unit!$C$7
A80: 9 | B80: =B$7*Per_Unit!$C$15 | C80: =C$7*Per_Unit!$C$14 | D80: =D$7*Per_Unit!$C$13 | E80: =E$7*Per_Unit!$C$12 | F80: =F$7*Per_Unit!$C$11 | G80: =G$7*Per_Unit!$C$10 | H80: =H$7*Per_Unit!$C$9 | I80: =I$7*Per_Unit!$C$8 | J80: =J$7*Per_Unit!$C$7
A81: 10 | B81: =B$7*Per_Unit!$C$16 | C81: =C$7*Per_Unit!$C$15 | D81: =D$7*Per_Unit!$C$14 | E81: =E$7*Per_Unit!$C$13 | F81: =F$7*Per_Unit!$C$12 | G81: =G$7*Per_Unit!$C$11 | H81: =H$7*Per_Unit!$C$10 | I81: =I$7*Per_Unit!$C$9 | J81: =J$7*Per_Unit!$C$8 | K81: =K$7*Per_Unit!$C$7
A82: 11 | B82: =B$7*Per_Unit!$C$17 | C82: =C$7*Per_Unit!$C$16 | D82: =D$7*Per_Unit!$C$15 | E82: =E$7*Per_Unit!$C$14 | F82: =F$7*Per_Unit!$C$13 | G82: =G$7*Per_Unit!$C$12 | H82: =H$7*Per_Unit!$C$11 | I82: =I$7*Per_Unit!$C$10 | J82: =J$7*Per_Unit!$C$9 | K82: =K$7*Per_Unit!$C$8 | L82: =L$7*Per_Unit!$C$7
A83: 12 | B83: =B$7*Per_Unit!$C$18 | C83: =C$7*Per_Unit!$C$17 | D83: =D$7*Per_Unit!$C$16 | E83: =E$7*Per_Unit!$C$15 | F83: =F$7*Per_Unit!$C$14 | G83: =G$7*Per_Unit!$C$13 | H83: =H$7*Per_Unit!$C$12 | I83: =I$7*Per_Unit!$C$11 | J83: =J$7*Per_Unit!$C$10 | K83: =K$7*Per_Unit!$C$9 | L83: =L$7*Per_Unit!$C$8 | M83: =M$7*Per_Unit!$C$7
A84: 13 | B84: =B$7*Per_Unit!$C$19 | C84: =C$7*Per_Unit!$C$18 | D84: =D$7*Per_Unit!$C$17 | E84: =E$7*Per_Unit!$C$16 | F84: =F$7*Per_Unit!$C$15 | G84: =G$7*Per_Unit!$C$14 | H84: =H$7*Per_Unit!$C$13 | I84: =I$7*Per_Unit!$C$12 | J84: =J$7*Per_Unit!$C$11 | K84: =K$7*Per_Unit!$C$10 | L84: =L$7*Per_Unit!$C$9 | M84: =M$7*Per_Unit!$C$8 | N84: =N$7*Per_Unit!$C$7
A85: 14 | B85: =B$7*Per_Unit!$C$20 | C85: =C$7*Per_Unit!$C$19 | D85: =D$7*Per_Unit!$C$18 | E85: =E$7*Per_Unit!$C$17 | F85: =F$7*Per_Unit!$C$16 | G85: =G$7*Per_Unit!$C$15 | H85: =H$7*Per_Unit!$C$14 | I85: =I$7*Per_Unit!$C$13 | J85: =J$7*Per_Unit!$C$12 | K85: =K$7*Per_Unit!$C$11 | L85: =L$7*Per_Unit!$C$10 | M85: =M$7*Per_Unit!$C$9 | N85: =N$7*Per_Unit!$C$8 | O85: =O$7*Per_Unit!$C$7
A86: 15 | B86: =B$7*Per_Unit!$C$21 | C86: =C$7*Per_Unit!$C$20 | D86: =D$7*Per_Unit!$C$19 | E86: =E$7*Per_Unit!$C$18 | F86: =F$7*Per_Unit!$C$17 | G86: =G$7*Per_Unit!$C$16 | H86: =H$7*Per_Unit!$C$15 | I86: =I$7*Per_Unit!$C$14 | J86: =J$7*Per_Unit!$C$13 | K86: =K$7*Per_Unit!$C$12 | L86: =L$7*Per_Unit!$C$11 | M86: =M$7*Per_Unit!$C$10 | N86: =N$7*Per_Unit!$C$9 | O86: =O$7*Per_Unit!$C$8 | P86: =P$7*Per_Unit!$C$7
A87: 16 | B87: =B$7*Per_Unit!$C$22 | C87: =C$7*Per_Unit!$C$21 | D87: =D$7*Per_Unit!$C$20 | E87: =E$7*Per_Unit!$C$19 | F87: =F$7*Per_Unit!$C$18 | G87: =G$7*Per_Unit!$C$17 | H87: =H$7*Per_Unit!$C$16 | I87: =I$7*Per_Unit!$C$15 | J87: =J$7*Per_Unit!$C$14 | K87: =K$7*Per_Unit!$C$13 | L87: =L$7*Per_Unit!$C$12 | M87: =M$7*Per_Unit!$C$11 | N87: =N$7*Per_Unit!$C$10 | O87: =O$7*Per_Unit!$C$9 | P87: =P$7*Per_Unit!$C$8 | Q87: =Q$7*Per_Unit!$C$7
A88: 17 | B88: =B$7*Per_Unit!$C$23 | C88: =C$7*Per_Unit!$C$22 | D88: =D$7*Per_Unit!$C$21 | E88: =E$7*Per_Unit!$C$20 | F88: =F$7*Per_Unit!$C$19 | G88: =G$7*Per_Unit!$C$18 | H88: =H$7*Per_Unit!$C$17 | I88: =I$7*Per_Unit!$C$16 | J88: =J$7*Per_Unit!$C$15 | K88: =K$7*Per_Unit!$C$14 | L88: =L$7*Per_Unit!$C$13 | M88: =M$7*Per_Unit!$C$12 | N88: =N$7*Per_Unit!$C$11 | O88: =O$7*Per_Unit!$C$10 | P88: =P$7*Per_Unit!$C$9 | Q88: =Q$7*Per_Unit!$C$8 | R88: =R$7*Per_Unit!$C$7
A89: 18 | B89: =B$7*Per_Unit!$C$24 | C89: =C$7*Per_Unit!$C$23 | D89: =D$7*Per_Unit!$C$22 | E89: =E$7*Per_Unit!$C$21 | F89: =F$7*Per_Unit!$C$20 | G89: =G$7*Per_Unit!$C$19 | H89: =H$7*Per_Unit!$C$18 | I89: =I$7*Per_Unit!$C$17 | J89: =J$7*Per_Unit!$C$16 | K89: =K$7*Per_Unit!$C$15 | L89: =L$7*Per_Unit!$C$14 | M89: =M$7*Per_Unit!$C$13 | N89: =N$7*Per_Unit!$C$12 | O89: =O$7*Per_Unit!$C$11 | P89: =P$7*Per_Unit!$C$10 | Q89: =Q$7*Per_Unit!$C$9 | R89: =R$7*Per_Unit!$C$8 | S89: =S$7*Per_Unit!$C$7
A90: 19 | B90: =B$7*Per_Unit!$C$25 | C90: =C$7*Per_Unit!$C$24 | D90: =D$7*Per_Unit!$C$23 | E90: =E$7*Per_Unit!$C$22 | F90: =F$7*Per_Unit!$C$21 | G90: =G$7*Per_Unit!$C$20 | H90: =H$7*Per_Unit!$C$19 | I90: =I$7*Per_Unit!$C$18 | J90: =J$7*Per_Unit!$C$17 | K90: =K$7*Per_Unit!$C$16 | L90: =L$7*Per_Unit!$C$15 | M90: =M$7*Per_Unit!$C$14 | N90: =N$7*Per_Unit!$C$13 | O90: =O$7*Per_Unit!$C$12 | P90: =P$7*Per_Unit!$C$11 | Q90: =Q$7*Per_Unit!$C$10 | R90: =R$7*Per_Unit!$C$9 | S90: =S$7*Per_Unit!$C$8 | T90: =T$7*Per_Unit!$C$7
A91: 20 | B91: =B$7*Per_Unit!$C$26 | C91: =C$7*Per_Unit!$C$25 | D91: =D$7*Per_Unit!$C$24 | E91: =E$7*Per_Unit!$C$23 | F91: =F$7*Per_Unit!$C$22 | G91: =G$7*Per_Unit!$C$21 | H91: =H$7*Per_Unit!$C$20 | I91: =I$7*Per_Unit!$C$19 | J91: =J$7*Per_Unit!$C$18 | K91: =K$7*Per_Unit!$C$17 | L91: =L$7*Per_Unit!$C$16 | M91: =M$7*Per_Unit!$C$15 | N91: =N$7*Per_Unit!$C$14 | O91: =O$7*Per_Unit!$C$13 | P91: =P$7*Per_Unit!$C$12 | Q91: =Q$7*Per_Unit!$C$11 | R91: =R$7*Per_Unit!$C$10 | S91: =S$7*Per_Unit!$C$9 | T91: =T$7*Per_Unit!$C$8 | U91: =U$7*Per_Unit!$C$7
A92: 21 | B92: =B$7*Per_Unit!$C$27 | C92: =C$7*Per_Unit!$C$26 | D92: =D$7*Per_Unit!$C$25 | E92: =E$7*Per_Unit!$C$24 | F92: =F$7*Per_Unit!$C$23 | G92: =G$7*Per_Unit!$C$22 | H92: =H$7*Per_Unit!$C$21 | I92: =I$7*Per_Unit!$C$20 | J92: =J$7*Per_Unit!$C$19 | K92: =K$7*Per_Unit!$C$18 | L92: =L$7*Per_Unit!$C$17 | M92: =M$7*Per_Unit!$C$16 | N92: =N$7*Per_Unit!$C$15 | O92: =O$7*Per_Unit!$C$14 | P92: =P$7*Per_Unit!$C$13 | Q92: =Q$7*Per_Unit!$C$12 | R92: =R$7*Per_Unit!$C$11 | S92: =S$7*Per_Unit!$C$10 | T92: =T$7*Per_Unit!$C$9 | U92: =U$7*Per_Unit!$C$8 | V92: =V$7*Per_Unit!$C$7
A93: 22 | B93: =B$7*Per_Unit!$C$28 | C93: =C$7*Per_Unit!$C$27 | D93: =D$7*Per_Unit!$C$26 | E93: =E$7*Per_Unit!$C$25 | F93: =F$7*Per_Unit!$C$24 | G93: =G$7*Per_Unit!$C$23 | H93: =H$7*Per_Unit!$C$22 | I93: =I$7*Per_Unit!$C$21 | J93: =J$7*Per_Unit!$C$20 | K93: =K$7*Per_Unit!$C$19 | L93: =L$7*Per_Unit!$C$18 | M93: =M$7*Per_Unit!$C$17 | N93: =N$7*Per_Unit!$C$16 | O93: =O$7*Per_Unit!$C$15 | P93: =P$7*Per_Unit!$C$14 | Q93: =Q$7*Per_Unit!$C$13 | R93: =R$7*Per_Unit!$C$12 | S93: =S$7*Per_Unit!$C$11 | T93: =T$7*Per_Unit!$C$10 | U93: =U$7*Per_Unit!$C$9 | V93: =V$7*Per_Unit!$C$8 | W93: =W$7*Per_Unit!$C$7
A94: 23 | B94: =B$7*Per_Unit!$C$29 | C94: =C$7*Per_Unit!$C$28 | D94: =D$7*Per_Unit!$C$27 | E94: =E$7*Per_Unit!$C$26 | F94: =F$7*Per_Unit!$C$25 | G94: =G$7*Per_Unit!$C$24 | H94: =H$7*Per_Unit!$C$23 | I94: =I$7*Per_Unit!$C$22 | J94: =J$7*Per_Unit!$C$21 | K94: =K$7*Per_Unit!$C$20 | L94: =L$7*Per_Unit!$C$19 | M94: =M$7*Per_Unit!$C$18 | N94: =N$7*Per_Unit!$C$17 | O94: =O$7*Per_Unit!$C$16 | P94: =P$7*Per_Unit!$C$15 | Q94: =Q$7*Per_Unit!$C$14 | R94: =R$7*Per_Unit!$C$13 | S94: =S$7*Per_Unit!$C$12 | T94: =T$7*Per_Unit!$C$11 | U94: =U$7*Per_Unit!$C$10 | V94: =V$7*Per_Unit!$C$9 | W94: =W$7*Per_Unit!$C$8 | X94: =X$7*Per_Unit!$C$7
A95: 24 | B95: =B$7*Per_Unit!$C$30 | C95: =C$7*Per_Unit!$C$29 | D95: =D$7*Per_Unit!$C$28 | E95: =E$7*Per_Unit!$C$27 | F95: =F$7*Per_Unit!$C$26 | G95: =G$7*Per_Unit!$C$25 | H95: =H$7*Per_Unit!$C$24 | I95: =I$7*Per_Unit!$C$23 | J95: =J$7*Per_Unit!$C$22 | K95: =K$7*Per_Unit!$C$21 | L95: =L$7*Per_Unit!$C$20 | M95: =M$7*Per_Unit!$C$19 | N95: =N$7*Per_Unit!$C$18 | O95: =O$7*Per_Unit!$C$17 | P95: =P$7*Per_Unit!$C$16 | Q95: =Q$7*Per_Unit!$C$15 | R95: =R$7*Per_Unit!$C$14 | S95: =S$7*Per_Unit!$C$13 | T95: =T$7*Per_Unit!$C$12 | U95: =U$7*Per_Unit!$C$11 | V95: =V$7*Per_Unit!$C$10 | W95: =W$7*Per_Unit!$C$9 | X95: =X$7*Per_Unit!$C$8 | Y95: =Y$7*Per_Unit!$C$7
A96: 25 | B96: =B$7*Per_Unit!$C$31 | C96: =C$7*Per_Unit!$C$30 | D96: =D$7*Per_Unit!$C$29 | E96: =E$7*Per_Unit!$C$28 | F96: =F$7*Per_Unit!$C$27 | G96: =G$7*Per_Unit!$C$26 | H96: =H$7*Per_Unit!$C$25 | I96: =I$7*Per_Unit!$C$24 | J96: =J$7*Per_Unit!$C$23 | K96: =K$7*Per_Unit!$C$22 | L96: =L$7*Per_Unit!$C$21 | M96: =M$7*Per_Unit!$C$20 | N96: =N$7*Per_Unit!$C$19 | O96: =O$7*Per_Unit!$C$18 | P96: =P$7*Per_Unit!$C$17 | Q96: =Q$7*Per_Unit!$C$16 | R96: =R$7*Per_Unit!$C$15 | S96: =S$7*Per_Unit!$C$14 | T96: =T$7*Per_Unit!$C$13 | U96: =U$7*Per_Unit!$C$12 | V96: =V$7*Per_Unit!$C$11 | W96: =W$7*Per_Unit!$C$10 | X96: =X$7*Per_Unit!$C$9 | Y96: =Y$7*Per_Unit!$C$8 | Z96: =Z$7*Per_Unit!$C$7
A97: 26 | B97: =B$7*Per_Unit!$C$32 | C97: =C$7*Per_Unit!$C$31 | D97: =D$7*Per_Unit!$C$30 | E97: =E$7*Per_Unit!$C$29 | F97: =F$7*Per_Unit!$C$28 | G97: =G$7*Per_Unit!$C$27 | H97: =H$7*Per_Unit!$C$26 | I97: =I$7*Per_Unit!$C$25 | J97: =J$7*Per_Unit!$C$24 | K97: =K$7*Per_Unit!$C$23 | L97: =L$7*Per_Unit!$C$22 | M97: =M$7*Per_Unit!$C$21 | N97: =N$7*Per_Unit!$C$20 | O97: =O$7*Per_Unit!$C$19 | P97: =P$7*Per_Unit!$C$18 | Q97: =Q$7*Per_Unit!$C$17 | R97: =R$7*Per_Unit!$C$16 | S97: =S$7*Per_Unit!$C$15 | T97: =T$7*Per_Unit!$C$14 | U97: =U$7*Per_Unit!$C$13 | V97: =V$7*Per_Unit!$C$12 | W97: =W$7*Per_Unit!$C$11 | X97: =X$7*Per_Unit!$C$10 | Y97: =Y$7*Per_Unit!$C$9 | Z97: =Z$7*Per_Unit!$C$8 | AA97: =AA$7*Per_Unit!$C$7
A98: 27 | B98: =B$7*Per_Unit!$C$33 | C98: =C$7*Per_Unit!$C$32 | D98: =D$7*Per_Unit!$C$31 | E98: =E$7*Per_Unit!$C$30 | F98: =F$7*Per_Unit!$C$29 | G98: =G$7*Per_Unit!$C$28 | H98: =H$7*Per_Unit!$C$27 | I98: =I$7*Per_Unit!$C$26 | J98: =J$7*Per_Unit!$C$25 | K98: =K$7*Per_Unit!$C$24 | L98: =L$7*Per_Unit!$C$23 | M98: =M$7*Per_Unit!$C$22 | N98: =N$7*Per_Unit!$C$21 | O98: =O$7*Per_Unit!$C$20 | P98: =P$7*Per_Unit!$C$19 | Q98: =Q$7*Per_Unit!$C$18 | R98: =R$7*Per_Unit!$C$17 | S98: =S$7*Per_Unit!$C$16 | T98: =T$7*Per_Unit!$C$15 | U98: =U$7*Per_Unit!$C$14 | V98: =V$7*Per_Unit!$C$13 | W98: =W$7*Per_Unit!$C$12 | X98: =X$7*Per_Unit!$C$11 | Y98: =Y$7*Per_Unit!$C$10 | Z98: =Z$7*Per_Unit!$C$9 | AA98: =AA$7*Per_Unit!$C$8 | AB98: =AB$7*Per_Unit!$C$7
A99: 28 | B99: =B$7*Per_Unit!$C$34 | C99: =C$7*Per_Unit!$C$33 | D99: =D$7*Per_Unit!$C$32 | E99: =E$7*Per_Unit!$C$31 | F99: =F$7*Per_Unit!$C$30 | G99: =G$7*Per_Unit!$C$29 | H99: =H$7*Per_Unit!$C$28 | I99: =I$7*Per_Unit!$C$27 | J99: =J$7*Per_Unit!$C$26 | K99: =K$7*Per_Unit!$C$25 | L99: =L$7*Per_Unit!$C$24 | M99: =M$7*Per_Unit!$C$23 | N99: =N$7*Per_Unit!$C$22 | O99: =O$7*Per_Unit!$C$21 | P99: =P$7*Per_Unit!$C$20 | Q99: =Q$7*Per_Unit!$C$19 | R99: =R$7*Per_Unit!$C$18 | S99: =S$7*Per_Unit!$C$17 | T99: =T$7*Per_Unit!$C$16 | U99: =U$7*Per_Unit!$C$15 | V99: =V$7*Per_Unit!$C$14 | W99: =W$7*Per_Unit!$C$13 | X99: =X$7*Per_Unit!$C$12 | Y99: =Y$7*Per_Unit!$C$11 | Z99: =Z$7*Per_Unit!$C$10 | AA99: =AA$7*Per_Unit!$C$9 | AB99: =AB$7*Per_Unit!$C$8 | AC99: =AC$7*Per_Unit!$C$7
A100: 29 | B100: =B$7*Per_Unit!$C$35 | C100: =C$7*Per_Unit!$C$34 | D100: =D$7*Per_Unit!$C$33 | E100: =E$7*Per_Unit!$C$32 | F100: =F$7*Per_Unit!$C$31 | G100: =G$7*Per_Unit!$C$30 | H100: =H$7*Per_Unit!$C$29 | I100: =I$7*Per_Unit!$C$28 | J100: =J$7*Per_Unit!$C$27 | K100: =K$7*Per_Unit!$C$26 | L100: =L$7*Per_Unit!$C$25 | M100: =M$7*Per_Unit!$C$24 | N100: =N$7*Per_Unit!$C$23 | O100: =O$7*Per_Unit!$C$22 | P100: =P$7*Per_Unit!$C$21 | Q100: =Q$7*Per_Unit!$C$20 | R100: =R$7*Per_Unit!$C$19 | S100: =S$7*Per_Unit!$C$18 | T100: =T$7*Per_Unit!$C$17 | U100: =U$7*Per_Unit!$C$16 | V100: =V$7*Per_Unit!$C$15 | W100: =W$7*Per_Unit!$C$14 | X100: =X$7*Per_Unit!$C$13 | Y100: =Y$7*Per_Unit!$C$12 | Z100: =Z$7*Per_Unit!$C$11 | AA100: =AA$7*Per_Unit!$C$10 | AB100: =AB$7*Per_Unit!$C$9 | AC100: =AC$7*Per_Unit!$C$8 | AD100: =AD$7*Per_Unit!$C$7
A101: 30 | B101: =B$7*Per_Unit!$C$36 | C101: =C$7*Per_Unit!$C$35 | D101: =D$7*Per_Unit!$C$34 | E101: =E$7*Per_Unit!$C$33 | F101: =F$7*Per_Unit!$C$32 | G101: =G$7*Per_Unit!$C$31 | H101: =H$7*Per_Unit!$C$30 | I101: =I$7*Per_Unit!$C$29 | J101: =J$7*Per_Unit!$C$28 | K101: =K$7*Per_Unit!$C$27 | L101: =L$7*Per_Unit!$C$26 | M101: =M$7*Per_Unit!$C$25 | N101: =N$7*Per_Unit!$C$24 | O101: =O$7*Per_Unit!$C$23 | P101: =P$7*Per_Unit!$C$22 | Q101: =Q$7*Per_Unit!$C$21 | R101: =R$7*Per_Unit!$C$20 | S101: =S$7*Per_Unit!$C$19 | T101: =T$7*Per_Unit!$C$18 | U101: =U$7*Per_Unit!$C$17 | V101: =V$7*Per_Unit!$C$16 | W101: =W$7*Per_Unit!$C$15 | X101: =X$7*Per_Unit!$C$14 | Y101: =Y$7*Per_Unit!$C$13 | Z101: =Z$7*Per_Unit!$C$12 | AA101: =AA$7*Per_Unit!$C$11 | AB101: =AB$7*Per_Unit!$C$10 | AC101: =AC$7*Per_Unit!$C$9 | AD101: =AD$7*Per_Unit!$C$8 | AE101: =AE$7*Per_Unit!$C$7
A102: 31 | B102: =B$7*Per_Unit!$C$37 | C102: =C$7*Per_Unit!$C$36 | D102: =D$7*Per_Unit!$C$35 | E102: =E$7*Per_Unit!$C$34 | F102: =F$7*Per_Unit!$C$33 | G102: =G$7*Per_Unit!$C$32 | H102: =H$7*Per_Unit!$C$31 | I102: =I$7*Per_Unit!$C$30 | J102: =J$7*Per_Unit!$C$29 | K102: =K$7*Per_Unit!$C$28 | L102: =L$7*Per_Unit!$C$27 | M102: =M$7*Per_Unit!$C$26 | N102: =N$7*Per_Unit!$C$25 | O102: =O$7*Per_Unit!$C$24 | P102: =P$7*Per_Unit!$C$23 | Q102: =Q$7*Per_Unit!$C$22 | R102: =R$7*Per_Unit!$C$21 | S102: =S$7*Per_Unit!$C$20 | T102: =T$7*Per_Unit!$C$19 | U102: =U$7*Per_Unit!$C$18 | V102: =V$7*Per_Unit!$C$17 | W102: =W$7*Per_Unit!$C$16 | X102: =X$7*Per_Unit!$C$15 | Y102: =Y$7*Per_Unit!$C$14 | Z102: =Z$7*Per_Unit!$C$13 | AA102: =AA$7*Per_Unit!$C$12 | AB102: =AB$7*Per_Unit!$C$11 | AC102: =AC$7*Per_Unit!$C$10 | AD102: =AD$7*Per_Unit!$C$9 | AE102: =AE$7*Per_Unit!$C$8 | AF102: =AF$7*Per_Unit!$C$7
A103: 32 | B103: =B$7*Per_Unit!$C$38 | C103: =C$7*Per_Unit!$C$37 | D103: =D$7*Per_Unit!$C$36 | E103: =E$7*Per_Unit!$C$35 | F103: =F$7*Per_Unit!$C$34 | G103: =G$7*Per_Unit!$C$33 | H103: =H$7*Per_Unit!$C$32 | I103: =I$7*Per_Unit!$C$31 | J103: =J$7*Per_Unit!$C$30 | K103: =K$7*Per_Unit!$C$29 | L103: =L$7*Per_Unit!$C$28 | M103: =M$7*Per_Unit!$C$27 | N103: =N$7*Per_Unit!$C$26 | O103: =O$7*Per_Unit!$C$25 | P103: =P$7*Per_Unit!$C$24 | Q103: =Q$7*Per_Unit!$C$23 | R103: =R$7*Per_Unit!$C$22 | S103: =S$7*Per_Unit!$C$21 | T103: =T$7*Per_Unit!$C$20 | U103: =U$7*Per_Unit!$C$19 | V103: =V$7*Per_Unit!$C$18 | W103: =W$7*Per_Unit!$C$17 | X103: =X$7*Per_Unit!$C$16 | Y103: =Y$7*Per_Unit!$C$15 | Z103: =Z$7*Per_Unit!$C$14 | AA103: =AA$7*Per_Unit!$C$13 | AB103: =AB$7*Per_Unit!$C$12 | AC103: =AC$7*Per_Unit!$C$11 | AD103: =AD$7*Per_Unit!$C$10 | AE103: =AE$7*Per_Unit!$C$9 | AF103: =AF$7*Per_Unit!$C$8 | AG103: =AG$7*Per_Unit!$C$7
...

Sheet Funding
A1: AFRICA ENERGY FINANCE | VOLUME 2 | SOLAR HOME SYSTEMS
A2: Monthly funding path
A3: Funding of the receivables book and central costs, before tax, interest and capex
A4: Decision tool D4 | Version 1.0 | Author & ideation: Emmanuel Boujieka Kamga
A6: Month | B6: Units sold | C6: Collections | D6: Deposits | E6: Day one outlay and central costs | F6: Net cash | G6: Cumulative net cash | H6: Receivables, carrying amount | I6: Facility capacity | J6: Funding need | K6: Facility drawn | L6: Equity required
A7: 1 | B7: =INDEX(Cohorts!$B$7:$BI$7,A7) | C7: =SUM(Cohorts!B72:BI72) | D7: =B7*'Inputs'!$B$13 | E7: =-B7*'Inputs'!$B$18-'Inputs'!$B$23 | F7: =C7+D7+E7 | G7: =F7 | H7: =SUM(Cohorts!B10:BI10) | I7: =IF(A7<'Inputs'!$B$22,0,MIN('Inputs'!$B$21,H7*'Inputs'!$B$20*'Inputs'!$B$19)) | J7: =MAX(0,-G7) | K7: =MIN(I7,J7) | L7: =J7-K7
A8: 2 | B8: =INDEX(Cohorts!$B$7:$BI$7,A8) | C8: =SUM(Cohorts!B73:BI73) | D8: =B8*'Inputs'!$B$13 | E8: =-B8*'Inputs'!$B$18-'Inputs'!$B$23 | F8: =C8+D8+E8 | G8: =G7+F8 | H8: =SUM(Cohorts!B11:BI11) | I8: =IF(A8<'Inputs'!$B$22,0,MIN('Inputs'!$B$21,H8*'Inputs'!$B$20*'Inputs'!$B$19)) | J8: =MAX(0,-G8) | K8: =MIN(I8,J8) | L8: =J8-K8
A9: 3 | B9: =INDEX(Cohorts!$B$7:$BI$7,A9) | C9: =SUM(Cohorts!B74:BI74) | D9: =B9*'Inputs'!$B$13 | E9: =-B9*'Inputs'!$B$18-'Inputs'!$B$23 | F9: =C9+D9+E9 | G9: =G8+F9 | H9: =SUM(Cohorts!B12:BI12) | I9: =IF(A9<'Inputs'!$B$22,0,MIN('Inputs'!$B$21,H9*'Inputs'!$B$20*'Inputs'!$B$19)) | J9: =MAX(0,-G9) | K9: =MIN(I9,J9) | L9: =J9-K9
A10: 4 | B10: =INDEX(Cohorts!$B$7:$BI$7,A10) | C10: =SUM(Cohorts!B75:BI75) | D10: =B10*'Inputs'!$B$13 | E10: =-B10*'Inputs'!$B$18-'Inputs'!$B$23 | F10: =C10+D10+E10 | G10: =G9+F10 | H10: =SUM(Cohorts!B13:BI13) | I10: =IF(A10<'Inputs'!$B$22,0,MIN('Inputs'!$B$21,H10*'Inputs'!$B$20*'Inputs'!$B$19)) | J10: =MAX(0,-G10) | K10: =MIN(I10,J10) | L10: =J10-K10
A11: 5 | B11: =INDEX(Cohorts!$B$7:$BI$7,A11) | C11: =SUM(Cohorts!B76:BI76) | D11: =B11*'Inputs'!$B$13 | E11: =-B11*'Inputs'!$B$18-'Inputs'!$B$23 | F11: =C11+D11+E11 | G11: =G10+F11 | H11: =SUM(Cohorts!B14:BI14) | I11: =IF(A11<'Inputs'!$B$22,0,MIN('Inputs'!$B$21,H11*'Inputs'!$B$20*'Inputs'!$B$19)) | J11: =MAX(0,-G11) | K11: =MIN(I11,J11) | L11: =J11-K11
A12: 6 | B12: =INDEX(Cohorts!$B$7:$BI$7,A12) | C12: =SUM(Cohorts!B77:BI77) | D12: =B12*'Inputs'!$B$13 | E12: =-B12*'Inputs'!$B$18-'Inputs'!$B$23 | F12: =C12+D12+E12 | G12: =G11+F12 | H12: =SUM(Cohorts!B15:BI15) | I12: =IF(A12<'Inputs'!$B$22,0,MIN('Inputs'!$B$21,H12*'Inputs'!$B$20*'Inputs'!$B$19)) | J12: =MAX(0,-G12) | K12: =MIN(I12,J12) | L12: =J12-K12
A13: 7 | B13: =INDEX(Cohorts!$B$7:$BI$7,A13) | C13: =SUM(Cohorts!B78:BI78) | D13: =B13*'Inputs'!$B$13 | E13: =-B13*'Inputs'!$B$18-'Inputs'!$B$23 | F13: =C13+D13+E13 | G13: =G12+F13 | H13: =SUM(Cohorts!B16:BI16) | I13: =IF(A13<'Inputs'!$B$22,0,MIN('Inputs'!$B$21,H13*'Inputs'!$B$20*'Inputs'!$B$19)) | J13: =MAX(0,-G13) | K13: =MIN(I13,J13) | L13: =J13-K13
A14: 8 | B14: =INDEX(Cohorts!$B$7:$BI$7,A14) | C14: =SUM(Cohorts!B79:BI79) | D14: =B14*'Inputs'!$B$13 | E14: =-B14*'Inputs'!$B$18-'Inputs'!$B$23 | F14: =C14+D14+E14 | G14: =G13+F14 | H14: =SUM(Cohorts!B17:BI17) | I14: =IF(A14<'Inputs'!$B$22,0,MIN('Inputs'!$B$21,H14*'Inputs'!$B$20*'Inputs'!$B$19)) | J14: =MAX(0,-G14) | K14: =MIN(I14,J14) | L14: =J14-K14
A15: 9 | B15: =INDEX(Cohorts!$B$7:$BI$7,A15) | C15: =SUM(Cohorts!B80:BI80) | D15: =B15*'Inputs'!$B$13 | E15: =-B15*'Inputs'!$B$18-'Inputs'!$B$23 | F15: =C15+D15+E15 | G15: =G14+F15 | H15: =SUM(Cohorts!B18:BI18) | I15: =IF(A15<'Inputs'!$B$22,0,MIN('Inputs'!$B$21,H15*'Inputs'!$B$20*'Inputs'!$B$19)) | J15: =MAX(0,-G15) | K15: =MIN(I15,J15) | L15: =J15-K15
A16: 10 | B16: =INDEX(Cohorts!$B$7:$BI$7,A16) | C16: =SUM(Cohorts!B81:BI81) | D16: =B16*'Inputs'!$B$13 | E16: =-B16*'Inputs'!$B$18-'Inputs'!$B$23 | F16: =C16+D16+E16 | G16: =G15+F16 | H16: =SUM(Cohorts!B19:BI19) | I16: =IF(A16<'Inputs'!$B$22,0,MIN('Inputs'!$B$21,H16*'Inputs'!$B$20*'Inputs'!$B$19)) | J16: =MAX(0,-G16) | K16: =MIN(I16,J16) | L16: =J16-K16
A17: 11 | B17: =INDEX(Cohorts!$B$7:$BI$7,A17) | C17: =SUM(Cohorts!B82:BI82) | D17: =B17*'Inputs'!$B$13 | E17: =-B17*'Inputs'!$B$18-'Inputs'!$B$23 | F17: =C17+D17+E17 | G17: =G16+F17 | H17: =SUM(Cohorts!B20:BI20) | I17: =IF(A17<'Inputs'!$B$22,0,MIN('Inputs'!$B$21,H17*'Inputs'!$B$20*'Inputs'!$B$19)) | J17: =MAX(0,-G17) | K17: =MIN(I17,J17) | L17: =J17-K17
A18: 12 | B18: =INDEX(Cohorts!$B$7:$BI$7,A18) | C18: =SUM(Cohorts!B83:BI83) | D18: =B18*'Inputs'!$B$13 | E18: =-B18*'Inputs'!$B$18-'Inputs'!$B$23 | F18: =C18+D18+E18 | G18: =G17+F18 | H18: =SUM(Cohorts!B21:BI21) | I18: =IF(A18<'Inputs'!$B$22,0,MIN('Inputs'!$B$21,H18*'Inputs'!$B$20*'Inputs'!$B$19)) | J18: =MAX(0,-G18) | K18: =MIN(I18,J18) | L18: =J18-K18
A19: 13 | B19: =INDEX(Cohorts!$B$7:$BI$7,A19) | C19: =SUM(Cohorts!B84:BI84) | D19: =B19*'Inputs'!$B$13 | E19: =-B19*'Inputs'!$B$18-'Inputs'!$B$23 | F19: =C19+D19+E19 | G19: =G18+F19 | H19: =SUM(Cohorts!B22:BI22) | I19: =IF(A19<'Inputs'!$B$22,0,MIN('Inputs'!$B$21,H19*'Inputs'!$B$20*'Inputs'!$B$19)) | J19: =MAX(0,-G19) | K19: =MIN(I19,J19) | L19: =J19-K19
... A66: 60 | B66: =INDEX(Cohorts!$B$7:$BI$7,A66) | C66: =SUM(Cohorts!B131:BI131) | D66: =B66*'Inputs'!$B$13 | E66: =-B66*'Inputs'!$B$18-'Inputs'!$B$23 | F66: =C66+D66+E66 | G66: =G65+F66 | H66: =SUM(Cohorts!B69:BI69) | I66: =IF(A66<'Inputs'!$B$22,0,MIN('Inputs'!$B$21,H66*'Inputs'!$B$20*'Inputs'!$B$19)) | J66: =MAX(0,-G66) | K66: =MIN(I66,J66) | L66: =J66-K66

Sheet Summary
A1: AFRICA ENERGY FINANCE | VOLUME 2 | SOLAR HOME SYSTEMS
A2: Funding summary
A3: Year end and peak values
A4: Decision tool D4 | Version 1.0 | Author & ideation: Emmanuel Boujieka Kamga
A6: Item | B6: Year 1 | C6: Year 2 | D6: Year 3 | E6: Year 4 | F6: Year 5
A7: Receivables, carrying amount (year end) | B7: =Funding!H18 | C7: =Funding!H30 | D7: =Funding!H42 | E7: =Funding!H54 | F7: =Funding!H66
A8: Facility drawn (year end) | B8: =Funding!K18 | C8: =Funding!K30 | D8: =Funding!K42 | E8: =Funding!K54 | F8: =Funding!K66
A9: Equity required (year end) | B9: =Funding!L18 | C9: =Funding!L30 | D9: =Funding!L42 | E9: =Funding!L54 | F9: =Funding!L66
A10: Cumulative net cash (year end) | B10: =Funding!G18 | C10: =Funding!G30 | D10: =Funding!G42 | E10: =Funding!G54 | F10: =Funding!G66
A12: Peak funding need | B12: =MAX(Funding!J7:J66)
A13: Peak facility drawn | B13: =MAX(Funding!K7:K66)
A14: Peak equity required | B14: =MAX(Funding!L7:L66)
A15: Month of peak equity | B15: =MATCH(B14,Funding!L7:L66,0)
A16: Peak equity required (USD) | B16: =B14/'Inputs'!$B$24
A18: Receivables are the carrying amount of paying accounts (remaining instalments less unearned premium), the basis on which the facility advances. Defaulted balances are written off as they fall due. Interest, tax and capex are excluded.

Sheet Currency
A1: AFRICA ENERGY FINANCE | VOLUME 2 | SOLAR HOME SYSTEMS
A2: Local currency or dollar debt
A3: Cost of dollar debt in local currency terms
A4: Decision tool D4 | Version 1.0 | Author & ideation: Emmanuel Boujieka Kamga
A6: Dollar interest rate | B6: 0.1
A7: Local currency facility rate | B7: 0.16
A8: Break even depreciation of the local currency, per year | B8: =(1+B7)/(1+B6)-1
A10: Depreciation scenario | B10: Depreciation per year | C10: Dollar debt cost in local currency | D10: Cheaper
A11: Base | B11: 0.05 | C11: =(1+$B$6)*(1+B11)-1 | D11: =IF(C11>$B$7,"Local currency","Dollar debt")
A12: Downside | B12: 0.12 | C12: =(1+$B$6)*(1+B12)-1 | D12: =IF(C12>$B$7,"Local currency","Dollar debt")
A13: Severe | B13: 0.25 | C13: =(1+$B$6)*(1+B13)-1 | D13: =IF(C13>$B$7,"Local currency","Dollar debt")
A15: The comparison covers the expected cost only. Dollar debt also carries the volatility of the exchange rate and the translation loss on the principal, which local currency debt does not (Chapter 10).
