Workbook

Sheet Guide
A1: AFRICA ENERGY FINANCE | BOOK 2 | PAYGO SOLAR FINANCE
A2: Investor returns calculator
A3: How to use this template
A4: Decision tool D6 | Version 0.9 (pre-release) | Author & ideation: Emmanuel Boujieka Kamga
A6: Purpose
A7: Translates an entry price and an exit case into the investor's stake, multiple and IRR in US dollars, including the effect of currency depreciation and of follow on equity; solves for the highest pre money valuation that meets a target IRR; and tabulates the IRR across exit multiples and depreciation rates.
A11: How to use it
A12: Step 1 | B12: Enter the ticket, the pre money valuation, the exit year and the exit case in local currency.
A13: Step 2 | B13: Enter expected depreciation and any follow on equity calls the investor must fund pro rata.
A14: Step 3 | B14: Read stake, exit proceeds, multiple and IRR; then the maximum pre money valuation for the target IRR.
A15: Step 4 | B15: Use the grid to see how much of the return depends on the exit multiple and on the currency.
A17: Colour code
A18: Input | B18: Blue font on cream: the only cells to edit
A19: Formula | B19: Black font: calculated, do not overwrite
A21: Links to Book 2 and MODEL 2
A22: Book | B22: Chapter 15 (valuation, IRR and multiple in USD), Chapter 16 (SolaraPay returns)
A23: Model | B23: Valuation, Investment_Summary
A24: Default inputs | B24: SolaraPay calibrated Base: USD 4.0m at USD 8.0m pre money, Year 5 EBITDA KVS 1,418m at 6x, net debt KVS 1,122m, KVS 135 per USD and 5% depreciation a year. The tool returns the case's 29.0% IRR and 3.6x multiple.
A26: Decision support material; not investment, legal, tax or accounting advice. Example values are illustrative and refer to the book's worked examples or to the fictional SolaraPay case. (c) 2026 Emmanuel Boujieka Kamga.

Sheet Returns
A1: AFRICA ENERGY FINANCE | BOOK 2 | PAYGO SOLAR FINANCE
A2: Investor returns
A3: US dollar returns on a local currency exit
A4: Decision tool D6 | Version 0.9 (pre-release) | Author & ideation: Emmanuel Boujieka Kamga
A6: Inputs
A7: Investment (USD) | B7: 4000000
A8: Pre money valuation (USD) | B8: 8000000
A9: Exit year (1 to 7) | B9: 5
A10: Exit year EBITDA (local currency) | B10: 1418022460
A11: Exit multiple of EBITDA | B11: 6
A12: Net debt at exit (local currency) | B12: 1121735060
A13: Exchange rate at entry (local per USD) | B13: 135
A14: Depreciation of the local currency, per year | B14: 0.05
A15: Target IRR | B15: 0.25
A17: Follow on equity calls, total company (USD)
C18: Year 1 | D18: Year 2 | E18: Year 3 | F18: Year 4 | G18: Year 5 | H18: Year 6 | I18: Year 7
A19: Equity called from shareholders | C19: 0 | D19: 0 | E19: 0 | F19: 0 | G19: 0 | H19: 0 | I19: 0
A21: Results
A22: Stake | B22: ='Returns'!$B$7/('Returns'!$B$8+'Returns'!$B$7)
A23: Exit enterprise value (local currency) | B23: ='Returns'!$B$10*'Returns'!$B$11
A24: Exit equity value, 100% (local currency) | B24: =MAX(0,B23-'Returns'!$B$12)
A25: Exchange rate at exit | B25: ='Returns'!$B$13*(1+'Returns'!$B$14)^'Returns'!$B$9
A26: Exit equity value, 100% (USD) | B26: =B24/B25
A27: Investor proceeds at exit (USD) | B27: =B22*B26
A28: Investor follow on equity (USD) | B28: =B22*(IF(1<='Returns'!$B$9,C19,0)+IF(2<='Returns'!$B$9,D19,0)+IF(3<='Returns'!$B$9,E19,0)+IF(4<='Returns'!$B$9,F19,0)+IF(5<='Returns'!$B$9,G19,0)+IF(6<='Returns'!$B$9,H19,0)+IF(7<='Returns'!$B$9,I19,0))
A29: Multiple on invested capital | B29: =IF((B7+B28)=0,"",B27/('Returns'!$B$7+B28))
A30: IRR (USD) | B30: =IFERROR(IRR(C33:J33),"Total loss")
A31: Maximum pre money valuation for the target IRR, no follow on (USD) | B31: =IF(B26<=0,"No value at exit",MAX(0,B26*'Returns'!$B$7/('Returns'!$B$7*(1+'Returns'!$B$15)^'Returns'!$B$9)-'Returns'!$B$7))
C32: 0 | D32: 1 | E32: 2 | F32: 3 | G32: 4 | H32: 5 | I32: 6 | J32: 7
A33: Investor cash flows (USD), year 0 to year 7 | C33: =-'Returns'!$B$7 | D33: =IF(1<='Returns'!$B$9,-$B$22*C19,0)+IF(1='Returns'!$B$9,$B$27,0) | E33: =IF(2<='Returns'!$B$9,-$B$22*D19,0)+IF(2='Returns'!$B$9,$B$27,0) | F33: =IF(3<='Returns'!$B$9,-$B$22*E19,0)+IF(3='Returns'!$B$9,$B$27,0) | G33: =IF(4<='Returns'!$B$9,-$B$22*F19,0)+IF(4='Returns'!$B$9,$B$27,0) | H33: =IF(5<='Returns'!$B$9,-$B$22*G19,0)+IF(5='Returns'!$B$9,$B$27,0) | I33: =IF(6<='Returns'!$B$9,-$B$22*H19,0)+IF(6='Returns'!$B$9,$B$27,0) | J33: =IF(7<='Returns'!$B$9,-$B$22*I19,0)+IF(7='Returns'!$B$9,$B$27,0)
A34: Follow on calls after the exit year are ignored.
A36: IRR by exit multiple and depreciation (no follow on equity)
A37: Exit multiple (rows) × depreciation per year (columns) | B37: 0 | C37: 0.05 | D37: 0.12 | E37: 0.2 | F37: 0.25
A38: 4 | B38: =IF(MAX(0,'Returns'!$B$10*$A38-'Returns'!$B$12)/('Returns'!$B$13*(1+B$37)^'Returns'!$B$9)<=0,"Total loss",($B$22*MAX(0,'Returns'!$B$10*$A38-'Returns'!$B$12)/('Returns'!$B$13*(1+B$37)^'Returns'!$B$9)/'Returns'!$B$7)^(1/'Returns'!$B$9)-1) | C38: =IF(MAX(0,'Returns'!$B$10*$A38-'Returns'!$B$12)/('Returns'!$B$13*(1+C$37)^'Returns'!$B$9)<=0,"Total loss",($B$22*MAX(0,'Returns'!$B$10*$A38-'Returns'!$B$12)/('Returns'!$B$13*(1+C$37)^'Returns'!$B$9)/'Returns'!$B$7)^(1/'Returns'!$B$9)-1) | D38: =IF(MAX(0,'Returns'!$B$10*$A38-'Returns'!$B$12)/('Returns'!$B$13*(1+D$37)^'Returns'!$B$9)<=0,"Total loss",($B$22*MAX(0,'Returns'!$B$10*$A38-'Returns'!$B$12)/('Returns'!$B$13*(1+D$37)^'Returns'!$B$9)/'Returns'!$B$7)^(1/'Returns'!$B$9)-1) | E38: =IF(MAX(0,'Returns'!$B$10*$A38-'Returns'!$B$12)/('Returns'!$B$13*(1+E$37)^'Returns'!$B$9)<=0,"Total loss",($B$22*MAX(0,'Returns'!$B$10*$A38-'Returns'!$B$12)/('Returns'!$B$13*(1+E$37)^'Returns'!$B$9)/'Returns'!$B$7)^(1/'Returns'!$B$9)-1) | F38: =IF(MAX(0,'Returns'!$B$10*$A38-'Returns'!$B$12)/('Returns'!$B$13*(1+F$37)^'Returns'!$B$9)<=0,"Total loss",($B$22*MAX(0,'Returns'!$B$10*$A38-'Returns'!$B$12)/('Returns'!$B$13*(1+F$37)^'Returns'!$B$9)/'Returns'!$B$7)^(1/'Returns'!$B$9)-1)
A39: 5 | B39: =IF(MAX(0,'Returns'!$B$10*$A39-'Returns'!$B$12)/('Returns'!$B$13*(1+B$37)^'Returns'!$B$9)<=0,"Total loss",($B$22*MAX(0,'Returns'!$B$10*$A39-'Returns'!$B$12)/('Returns'!$B$13*(1+B$37)^'Returns'!$B$9)/'Returns'!$B$7)^(1/'Returns'!$B$9)-1) | C39: =IF(MAX(0,'Returns'!$B$10*$A39-'Returns'!$B$12)/('Returns'!$B$13*(1+C$37)^'Returns'!$B$9)<=0,"Total loss",($B$22*MAX(0,'Returns'!$B$10*$A39-'Returns'!$B$12)/('Returns'!$B$13*(1+C$37)^'Returns'!$B$9)/'Returns'!$B$7)^(1/'Returns'!$B$9)-1) | D39: =IF(MAX(0,'Returns'!$B$10*$A39-'Returns'!$B$12)/('Returns'!$B$13*(1+D$37)^'Returns'!$B$9)<=0,"Total loss",($B$22*MAX(0,'Returns'!$B$10*$A39-'Returns'!$B$12)/('Returns'!$B$13*(1+D$37)^'Returns'!$B$9)/'Returns'!$B$7)^(1/'Returns'!$B$9)-1) | E39: =IF(MAX(0,'Returns'!$B$10*$A39-'Returns'!$B$12)/('Returns'!$B$13*(1+E$37)^'Returns'!$B$9)<=0,"Total loss",($B$22*MAX(0,'Returns'!$B$10*$A39-'Returns'!$B$12)/('Returns'!$B$13*(1+E$37)^'Returns'!$B$9)/'Returns'!$B$7)^(1/'Returns'!$B$9)-1) | F39: =IF(MAX(0,'Returns'!$B$10*$A39-'Returns'!$B$12)/('Returns'!$B$13*(1+F$37)^'Returns'!$B$9)<=0,"Total loss",($B$22*MAX(0,'Returns'!$B$10*$A39-'Returns'!$B$12)/('Returns'!$B$13*(1+F$37)^'Returns'!$B$9)/'Returns'!$B$7)^(1/'Returns'!$B$9)-1)
A40: 6 | B40: =IF(MAX(0,'Returns'!$B$10*$A40-'Returns'!$B$12)/('Returns'!$B$13*(1+B$37)^'Returns'!$B$9)<=0,"Total loss",($B$22*MAX(0,'Returns'!$B$10*$A40-'Returns'!$B$12)/('Returns'!$B$13*(1+B$37)^'Returns'!$B$9)/'Returns'!$B$7)^(1/'Returns'!$B$9)-1) | C40: =IF(MAX(0,'Returns'!$B$10*$A40-'Returns'!$B$12)/('Returns'!$B$13*(1+C$37)^'Returns'!$B$9)<=0,"Total loss",($B$22*MAX(0,'Returns'!$B$10*$A40-'Returns'!$B$12)/('Returns'!$B$13*(1+C$37)^'Returns'!$B$9)/'Returns'!$B$7)^(1/'Returns'!$B$9)-1) | D40: =IF(MAX(0,'Returns'!$B$10*$A40-'Returns'!$B$12)/('Returns'!$B$13*(1+D$37)^'Returns'!$B$9)<=0,"Total loss",($B$22*MAX(0,'Returns'!$B$10*$A40-'Returns'!$B$12)/('Returns'!$B$13*(1+D$37)^'Returns'!$B$9)/'Returns'!$B$7)^(1/'Returns'!$B$9)-1) | E40: =IF(MAX(0,'Returns'!$B$10*$A40-'Returns'!$B$12)/('Returns'!$B$13*(1+E$37)^'Returns'!$B$9)<=0,"Total loss",($B$22*MAX(0,'Returns'!$B$10*$A40-'Returns'!$B$12)/('Returns'!$B$13*(1+E$37)^'Returns'!$B$9)/'Returns'!$B$7)^(1/'Returns'!$B$9)-1) | F40: =IF(MAX(0,'Returns'!$B$10*$A40-'Returns'!$B$12)/('Returns'!$B$13*(1+F$37)^'Returns'!$B$9)<=0,"Total loss",($B$22*MAX(0,'Returns'!$B$10*$A40-'Returns'!$B$12)/('Returns'!$B$13*(1+F$37)^'Returns'!$B$9)/'Returns'!$B$7)^(1/'Returns'!$B$9)-1)
A41: 7 | B41: =IF(MAX(0,'Returns'!$B$10*$A41-'Returns'!$B$12)/('Returns'!$B$13*(1+B$37)^'Returns'!$B$9)<=0,"Total loss",($B$22*MAX(0,'Returns'!$B$10*$A41-'Returns'!$B$12)/('Returns'!$B$13*(1+B$37)^'Returns'!$B$9)/'Returns'!$B$7)^(1/'Returns'!$B$9)-1) | C41: =IF(MAX(0,'Returns'!$B$10*$A41-'Returns'!$B$12)/('Returns'!$B$13*(1+C$37)^'Returns'!$B$9)<=0,"Total loss",($B$22*MAX(0,'Returns'!$B$10*$A41-'Returns'!$B$12)/('Returns'!$B$13*(1+C$37)^'Returns'!$B$9)/'Returns'!$B$7)^(1/'Returns'!$B$9)-1) | D41: =IF(MAX(0,'Returns'!$B$10*$A41-'Returns'!$B$12)/('Returns'!$B$13*(1+D$37)^'Returns'!$B$9)<=0,"Total loss",($B$22*MAX(0,'Returns'!$B$10*$A41-'Returns'!$B$12)/('Returns'!$B$13*(1+D$37)^'Returns'!$B$9)/'Returns'!$B$7)^(1/'Returns'!$B$9)-1) | E41: =IF(MAX(0,'Returns'!$B$10*$A41-'Returns'!$B$12)/('Returns'!$B$13*(1+E$37)^'Returns'!$B$9)<=0,"Total loss",($B$22*MAX(0,'Returns'!$B$10*$A41-'Returns'!$B$12)/('Returns'!$B$13*(1+E$37)^'Returns'!$B$9)/'Returns'!$B$7)^(1/'Returns'!$B$9)-1) | F41: =IF(MAX(0,'Returns'!$B$10*$A41-'Returns'!$B$12)/('Returns'!$B$13*(1+F$37)^'Returns'!$B$9)<=0,"Total loss",($B$22*MAX(0,'Returns'!$B$10*$A41-'Returns'!$B$12)/('Returns'!$B$13*(1+F$37)^'Returns'!$B$9)/'Returns'!$B$7)^(1/'Returns'!$B$9)-1)
A42: 8 | B42: =IF(MAX(0,'Returns'!$B$10*$A42-'Returns'!$B$12)/('Returns'!$B$13*(1+B$37)^'Returns'!$B$9)<=0,"Total loss",($B$22*MAX(0,'Returns'!$B$10*$A42-'Returns'!$B$12)/('Returns'!$B$13*(1+B$37)^'Returns'!$B$9)/'Returns'!$B$7)^(1/'Returns'!$B$9)-1) | C42: =IF(MAX(0,'Returns'!$B$10*$A42-'Returns'!$B$12)/('Returns'!$B$13*(1+C$37)^'Returns'!$B$9)<=0,"Total loss",($B$22*MAX(0,'Returns'!$B$10*$A42-'Returns'!$B$12)/('Returns'!$B$13*(1+C$37)^'Returns'!$B$9)/'Returns'!$B$7)^(1/'Returns'!$B$9)-1) | D42: =IF(MAX(0,'Returns'!$B$10*$A42-'Returns'!$B$12)/('Returns'!$B$13*(1+D$37)^'Returns'!$B$9)<=0,"Total loss",($B$22*MAX(0,'Returns'!$B$10*$A42-'Returns'!$B$12)/('Returns'!$B$13*(1+D$37)^'Returns'!$B$9)/'Returns'!$B$7)^(1/'Returns'!$B$9)-1) | E42: =IF(MAX(0,'Returns'!$B$10*$A42-'Returns'!$B$12)/('Returns'!$B$13*(1+E$37)^'Returns'!$B$9)<=0,"Total loss",($B$22*MAX(0,'Returns'!$B$10*$A42-'Returns'!$B$12)/('Returns'!$B$13*(1+E$37)^'Returns'!$B$9)/'Returns'!$B$7)^(1/'Returns'!$B$9)-1) | F42: =IF(MAX(0,'Returns'!$B$10*$A42-'Returns'!$B$12)/('Returns'!$B$13*(1+F$37)^'Returns'!$B$9)<=0,"Total loss",($B$22*MAX(0,'Returns'!$B$10*$A42-'Returns'!$B$12)/('Returns'!$B$13*(1+F$37)^'Returns'!$B$9)/'Returns'!$B$7)^(1/'Returns'!$B$9)-1)
A44: Exit equity is floored at zero: when net debt exceeds the exit enterprise value, the stake is worth nothing.
