Workbook

Sheet Cover
A1: AFRICA ENERGY FINANCE - Business & Financial Models
A2: Volume 2 - Solar Home Systems: PAYGo Company Financial Model
A4: Model | B4: SHS / PAYGo Company Financial Model
A5: Version | B5: v0.1 (development build - not for sale)
A6: Status | B6: Draft for expert review. Default inputs are illustrative, not benchmarks.
A7: Currency | B7: Model currency = LCY (local currency). Hardware and term debt in USD, converted at the Timeline FX rate.
A8: Periodicity | B8: Monthly, 60 months; annual summaries on 'Annual' and 'KPIs'.
A9: Master check | B9: =Checks!C15
A12: How to use
B13: 1. Inputs: set scenario, macro, volumes, opex, financing (blue cells; yellow = key assumptions).
B14: 2. Products: set price plan, hardware cost, CAC and credit-risk parameters per product.
B15: 3. Scenarios: review Base / Downside / Severe levers.
B16: 4. Review Curves (per-unit repayment behaviour) and Unit_Economics (LTV/CAC, payback, unit IRR).
B17: 5. Review FS (monthly statements), Annual, KPIs and Dashboard.
B18: 6. Confirm the master check on this sheet reads OK before using any output.
A20: Sheet map
A21: Inputs | B21: Scenario selector, macro, volumes, opex, working capital, financing
A22: Products | B22: Product catalogue, PAYGo price plans, CAC, credit-risk parameters
A23: Scenarios | B23: Base / Downside / Severe levers and the active values
A24: Timeline | B24: Dates, years, FX path, inflation and price indices
A25: Curves | B25: Per-unit repayment, default and cash-flow curves by account age
A26: Cohort_P1..P3 | B26: Monthly vintage (cohort) matrices: collections, active accounts, balance at risk
A27: Ops | B27: Units, deposits, instalments due, collections, write-offs, ECL, receivables drivers
A28: Costs | B28: COGS, opex, inventory, payables, capex and depreciation
A29: Financing | B29: Equity, USD term loan (with FX), receivables-backed facility
A30: FS | B30: Monthly P&L, balance sheet, cash flow
A31: Annual | B31: Annual statements
A32: KPIs | B32: PAYGo portfolio KPIs (PERFORM-style) and financial KPIs
... A35: Checks | B35: Integrity checks
A37: Colour code
A38: 1,000 | B38: Blue = hard-coded input
A39: 1,000 | B39: Yellow fill = key assumption to review first
A40: 1,000 | B40: Black = formula
A41: 1,000 | B41: Green = link from another sheet
A43: Disclaimer | B43: This model is a decision-support tool. It is not investment, legal, tax or accounting advice. Simplifications are documented in the user manual (revenue recognition, IFRS 9 provisioning, tax). Users are responsible for their inputs and conclusions.

Sheet Inputs
A1: Inputs
A2: Blue = input. Yellow = key assumption. All defaults illustrative.
A4: Scenario & model settings
A5: Active scenario (1 = Base, 2 = Downside, 3 = Severe) | B5: # | C5: 1 | D5: Drives the levers on the Scenarios sheet.
A6: First model month (period end) | B6: date | C6: =DATE(2027,1,31) | D6: Enter as a date (period end of month 1).
A7: Local currency label | B7: text | C7: LCY | D7: Display label only.
A9: Macro
A10: Opening FX rate | B10: LCY per USD | C10: 130 | D10: Illustrative placeholder - replace with company data.
A11: Local inflation (opex indexation) | B11: % p.a. | C11: 0.06 | D11: Illustrative placeholder - replace with company data.
A12: Corporate income tax rate | B12: % | C12: 0.3 | D12: Simplified: tax losses carried forward indefinitely, tax paid in the month incurred.
A13: Annual price increase on NEW contracts | B13: % p.a. | C13: 0.05 | D13: Applies to new cohorts only; existing contracts keep their price plan.
A15: Sales volume (Base, before scenario multiplier)
A16: Units sold - Year 1 | B16: units | C16: 12000 | D16: Illustrative placeholder - replace with company data.
A17: Units sold - Year 2 | B17: units | C17: 24000 | D17: Illustrative placeholder - replace with company data.
A18: Units sold - Year 3 | B18: units | C18: 36000 | D18: Illustrative placeholder - replace with company data.
A19: Units sold - Year 4 | B19: units | C19: 45000 | D19: Illustrative placeholder - replace with company data.
A20: Units sold - Year 5 | B20: units | C20: 50000 | D20: Illustrative placeholder - replace with company data.
A22: Operating costs
A23: Mobile-money / payment fees | B23: % of cash collected | C23: 0.02 | D23: Illustrative placeholder - replace with company data.
A24: Customer service & collections cost | B24: LCY / active account / month | C24: 60 | D24: Illustrative placeholder - replace with company data.
A25: Staff costs (fixed, month 1 level) | B25: LCY / month | C25: 6500000 | D25: Illustrative placeholder - replace with company data.
A26: G&A, rent, IT (fixed, month 1 level) | B26: LCY / month | C26: 2600000 | D26: Illustrative placeholder - replace with company data.
A27: Warranty & after-sales provision | B27: % of landed HW cost | C27: 0.05 | D27: Illustrative placeholder - replace with company data.
A28: Freight, duty & clearing | B28: % of USD FOB cost | C28: 0.2 | D28: Illustrative placeholder - replace with company data.
A30: Working capital & capex
A31: Inventory cover | B31: months of COGS | C31: 2 | D31: Illustrative placeholder - replace with company data.
A32: Supplier credit on hardware | B32: days | C32: 60 | D32: Illustrative placeholder - replace with company data.
A33: Fixed capex (vehicles, IT, depots) | B33: LCY / month | C33: 650000 | D33: Illustrative placeholder - replace with company data.
A34: Depreciation life of fixed capex | B34: months | C34: 36 | D34: Illustrative placeholder - replace with company data.
A35: Minimum cash balance | B35: LCY | C35: 65000000 | D35: Shortfalls below this level are covered by an automatic equity injection (funding requirement).
A37: Financing
A38: Initial equity (month 1) | B38: LCY | C38: 390000000 | D38: Illustrative placeholder - replace with company data.
A39: USD term loan - amount | B39: USD | C39: 2000000 | D39: Illustrative placeholder - replace with company data.
A40: USD term loan - drawdown month | B40: month # | C40: 6 | D40: Illustrative placeholder - replace with company data.
A41: USD term loan - interest rate | B41: % p.a. | C41: 0.1 | D41: Illustrative placeholder - replace with company data.
A42: USD term loan - grace period after drawdown | B42: months | C42: 12 | D42: Illustrative placeholder - replace with company data.
A43: USD term loan - amortisation period | B43: months | C43: 36 | D43: Illustrative placeholder - replace with company data.
A44: Receivables facility (LCY) - limit | B44: LCY | C44: 1300000000 | D44: Illustrative placeholder - replace with company data.
A45: Receivables facility - advance rate | B45: % of eligible receivables | C45: 0.7 | D45: Illustrative placeholder - replace with company data.
A46: Receivables facility - interest rate | B46: % p.a. | C46: 0.16 | D46: Illustrative placeholder - replace with company data.
A47: Receivables facility - first available month | B47: month # | C47: 7 | D47: Illustrative placeholder - replace with company data.

Sheet Products
A1: Product catalogue & PAYGo price plans
A2: One column per product. Blue = input. Derived values in black.
A4: Parameter | B4: Unit | C4: P1 Solar lantern kit (Tier 1) | D4: P2 SHS lights+radio (Tier 2) | E4: P3 SHS with TV (Tier 3) | F4: Notes
A5: Product name | B5: text | C5: P1 Solar lantern kit (Tier 1) | D5: P2 SHS lights+radio (Tier 2) | E5: P3 SHS with TV (Tier 3) | F5: Illustrative placeholder - replace with company data.
A6: Cash (list) price | B6: LCY | C6: 6500 | D6: 26000 | E6: 65000 | F6: Price if paid upfront. Basis of hardware revenue.
A7: PAYGo deposit | B7: LCY | C7: 1000 | D7: 3000 | E7: 6500 | F7: Illustrative placeholder - replace with company data.
A8: PAYGo daily rate | B8: LCY / day | C8: 25 | D8: 60 | E8: 130 | F8: Illustrative placeholder - replace with company data.
A9: PAYGo tenor | B9: months | C9: 12 | D9: 18 | E9: 24 | F9: Max 60.
A10: Hardware FOB cost | B10: USD / unit | C10: 25 | D10: 90 | E10: 260 | F10: Illustrative placeholder - replace with company data.
A11: Agent commission per sale | B11: LCY / unit | C11: 500 | D11: 1500 | E11: 3000 | F11: Illustrative placeholder - replace with company data.
A12: Marketing & acquisition cost per sale | B12: LCY / unit | C12: 300 | D12: 800 | E12: 1500 | F12: Illustrative placeholder - replace with company data.
A13: Sales mix | B13: % of units | C13: 0.4 | D13: 0.4 | E13: 0.2 | F13: Must sum to 100% (see Checks).
A14: Base monthly default hazard | B14: % of performing accounts / month | C14: 0.025 | D14: 0.02 | E14: 0.015 | F14: Share of still-paying accounts that stop paying each month. Scenario multiplier applied.
A15: Base collection rate on performing accounts | B15: % of instalment | C15: 0.92 | D15: 0.9 | E15: 0.9 | F15: Partial / late payment of performing accounts. Scenario multiplier applied, capped at 100%.
A17: Derived price-plan metrics
A18: Monthly instalment (daily rate x 30.42) | B18: LCY / month | C18: =Products!$C$8*365/12 | D18: =Products!$D$8*365/12 | E18: =Products!$E$8*365/12
A19: Total PAYGo contract value | B19: LCY | C19: =Products!$C$7+Products!$C$18*Products!$C$9 | D19: =Products!$D$7+Products!$D$18*Products!$D$9 | E19: =Products!$E$7+Products!$E$18*Products!$E$9
A20: PAYGo financing mark-up over cash price | B20: LCY | C20: =Products!$C$19-Products!$C$6 | D20: =Products!$D$19-Products!$D$6 | E20: =Products!$E$19-Products!$E$6
A21: Mark-up as % of cash price | B21: % | C21: =IF(Products!$C$6=0,0,Products!$C$20/Products!$C$6) | D21: =IF(Products!$D$6=0,0,Products!$D$20/Products!$D$6) | E21: =IF(Products!$E$6=0,0,Products!$E$20/Products!$E$6)
A22: Amount financed at sale (cash price - deposit) | B22: LCY | C22: =Products!$C$6-Products!$C$7 | D22: =Products!$D$6-Products!$D$7 | E22: =Products!$E$6-Products!$E$7
A23: Scenario monthly default hazard | B23: % | C23: =Products!$C$14*Scenarios!$G$6 | D23: =Products!$D$14*Scenarios!$G$6 | E23: =Products!$E$14*Scenarios!$G$6
A24: Scenario collection rate on performing | B24: % | C24: =MIN(1,Products!$C$15*Scenarios!$G$7) | D24: =MIN(1,Products!$D$15*Scenarios!$G$7) | E24: =MIN(1,Products!$E$15*Scenarios!$G$7)
A25: Landed hardware cost at opening FX (scenario) | B25: LCY / unit | C25: =Products!$C$10*(1+Inputs!$C$28)*Inputs!$C$10*Scenarios!$G$9 | D25: =Products!$D$10*(1+Inputs!$C$28)*Inputs!$C$10*Scenarios!$G$9 | E25: =Products!$E$10*(1+Inputs!$C$28)*Inputs!$C$10*Scenarios!$G$9
A26: Customer acquisition cost (commission + marketing) | B26: LCY / unit | C26: =Products!$C$11+Products!$C$12 | D26: =Products!$D$11+Products!$D$12 | E26: =Products!$E$11+Products!$E$12

Sheet Scenarios
A1: Scenario levers
A2: Multipliers / overrides applied to Base inputs. Active column follows Inputs!C5.
A5: Lever | B5: Unit | C5: Base | D5: Downside | E5: Severe | G5: ACTIVE
A6: Default hazard multiplier | B6: x | C6: 1 | D6: 1.5 | E6: 2 | G6: =CHOOSE(Inputs!$C$5,C6,D6,E6)
A7: Collection-rate multiplier (performing accounts) | B7: x | C7: 1 | D7: 0.95 | E7: 0.88 | G7: =CHOOSE(Inputs!$C$5,C7,D7,E7)
A8: Sales volume multiplier | B8: x | C8: 1 | D8: 0.85 | E8: 0.7 | G8: =CHOOSE(Inputs!$C$5,C8,D8,E8)
A9: Hardware cost multiplier (USD) | B9: x | C9: 1 | D9: 1.05 | E9: 1.1 | G9: =CHOOSE(Inputs!$C$5,C9,D9,E9)
A10: LCY depreciation vs USD | B10: % p.a. | C10: 0.05 | D10: 0.15 | E10: 0.3 | G10: =CHOOSE(Inputs!$C$5,C10,D10,E10)
A12: Scenario names | C12: Base | D12: Downside | E12: Severe | G12: =CHOOSE(Inputs!$C$5,C12,D12,E12)
A14: Downside/Severe levers are illustrative stress settings. Calibrate them to the company's own cohort history and to sector data before use.
A15: Context: ESMAP Off-Grid Solar Market Trends Report 2024 reports a sector PAYGo collection rate of about 62% (2023) - see sources/source-register.md.

Sheet Dashboard
A1: Dashboard
A2: Active scenario shown in Scenarios!G12. Charts read from Annual / KPIs.
A4: Active scenario | B4: =Scenarios!G12
A5: Peak equity requirement (LCY) | B5: =KPIs!$C$30
A6: Peak equity requirement (USD at opening FX) | B6: =KPIs!$C$30/Inputs!$C$10
A7: Master check | B7: =Checks!C15
A10: Chart series order: bar = Revenue, EBITDA; line 1 = Collection rate, Write-off rate; line 2 = Cumulative equity, Total debt.

Sheet KPIs
A1: Key performance indicators
A2: Portfolio KPIs follow PAYGo PERFORM-style definitions where noted (simplified, see manual).
E5: Year 1 | F5: Year 2 | G5: Year 3 | H5: Year 4 | I5: Year 5
E6: 1 | F6: 2 | G6: 3 | H6: 4 | I6: 5
A8: Portfolio
A9: Units sold | E9: =SUMIFS(Ops!$E$54:$BL$54,Timeline!$E$6:$BL$6,E$6) | F9: =SUMIFS(Ops!$E$54:$BL$54,Timeline!$E$6:$BL$6,F$6) | G9: =SUMIFS(Ops!$E$54:$BL$54,Timeline!$E$6:$BL$6,G$6) | H9: =SUMIFS(Ops!$E$54:$BL$54,Timeline!$E$6:$BL$6,H$6) | I9: =SUMIFS(Ops!$E$54:$BL$54,Timeline!$E$6:$BL$6,I$6)
A10: Active accounts (year end) | E10: =INDEX(Ops!$E$64:$BL$64,1,E$6*12) | F10: =INDEX(Ops!$E$64:$BL$64,1,F$6*12) | G10: =INDEX(Ops!$E$64:$BL$64,1,G$6*12) | H10: =INDEX(Ops!$E$64:$BL$64,1,H$6*12) | I10: =INDEX(Ops!$E$64:$BL$64,1,I$6*12)
A11: Collection rate (collected / due, excl. deposits) | E11: =IFERROR(SUMIFS(Ops!$E$60:$BL$60,Timeline!$E$6:$BL$6,E$6)/SUMIFS(Ops!$E$59:$BL$59,Timeline!$E$6:$BL$6,E$6),0) | F11: =IFERROR(SUMIFS(Ops!$E$60:$BL$60,Timeline!$E$6:$BL$6,F$6)/SUMIFS(Ops!$E$59:$BL$59,Timeline!$E$6:$BL$6,F$6),0) | G11: =IFERROR(SUMIFS(Ops!$E$60:$BL$60,Timeline!$E$6:$BL$6,G$6)/SUMIFS(Ops!$E$59:$BL$59,Timeline!$E$6:$BL$6,G$6),0) | H11: =IFERROR(SUMIFS(Ops!$E$60:$BL$60,Timeline!$E$6:$BL$6,H$6)/SUMIFS(Ops!$E$59:$BL$59,Timeline!$E$6:$BL$6,H$6),0) | I11: =IFERROR(SUMIFS(Ops!$E$60:$BL$60,Timeline!$E$6:$BL$6,I$6)/SUMIFS(Ops!$E$59:$BL$59,Timeline!$E$6:$BL$6,I$6),0)
A12: Write-off rate (missed / due) | E12: =IFERROR(SUMIFS(Ops!$E$61:$BL$61,Timeline!$E$6:$BL$6,E$6)/SUMIFS(Ops!$E$59:$BL$59,Timeline!$E$6:$BL$6,E$6),0) | F12: =IFERROR(SUMIFS(Ops!$E$61:$BL$61,Timeline!$E$6:$BL$6,F$6)/SUMIFS(Ops!$E$59:$BL$59,Timeline!$E$6:$BL$6,F$6),0) | G12: =IFERROR(SUMIFS(Ops!$E$61:$BL$61,Timeline!$E$6:$BL$6,G$6)/SUMIFS(Ops!$E$59:$BL$59,Timeline!$E$6:$BL$6,G$6),0) | H12: =IFERROR(SUMIFS(Ops!$E$61:$BL$61,Timeline!$E$6:$BL$6,H$6)/SUMIFS(Ops!$E$59:$BL$59,Timeline!$E$6:$BL$6,H$6),0) | I12: =IFERROR(SUMIFS(Ops!$E$61:$BL$61,Timeline!$E$6:$BL$6,I$6)/SUMIFS(Ops!$E$59:$BL$59,Timeline!$E$6:$BL$6,I$6),0)
A13: Receivables at risk / gross receivables (year end) | E13: =IFERROR(INDEX(Ops!$E$65:$BL$65,1,E$6*12)/INDEX(FS!$E$30:$BL$30,1,E$6*12),0) | F13: =IFERROR(INDEX(Ops!$E$65:$BL$65,1,F$6*12)/INDEX(FS!$E$30:$BL$30,1,F$6*12),0) | G13: =IFERROR(INDEX(Ops!$E$65:$BL$65,1,G$6*12)/INDEX(FS!$E$30:$BL$30,1,G$6*12),0) | H13: =IFERROR(INDEX(Ops!$E$65:$BL$65,1,H$6*12)/INDEX(FS!$E$30:$BL$30,1,H$6*12),0) | I13: =IFERROR(INDEX(Ops!$E$65:$BL$65,1,I$6*12)/INDEX(FS!$E$30:$BL$30,1,I$6*12),0)
A14: Loss allowance coverage (allowance / gross receivables) | E14: =IFERROR(-INDEX(FS!$E$31:$BL$31,1,E$6*12)/INDEX(FS!$E$30:$BL$30,1,E$6*12),0) | F14: =IFERROR(-INDEX(FS!$E$31:$BL$31,1,F$6*12)/INDEX(FS!$E$30:$BL$30,1,F$6*12),0) | G14: =IFERROR(-INDEX(FS!$E$31:$BL$31,1,G$6*12)/INDEX(FS!$E$30:$BL$30,1,G$6*12),0) | H14: =IFERROR(-INDEX(FS!$E$31:$BL$31,1,H$6*12)/INDEX(FS!$E$30:$BL$30,1,H$6*12),0) | I14: =IFERROR(-INDEX(FS!$E$31:$BL$31,1,I$6*12)/INDEX(FS!$E$30:$BL$30,1,I$6*12),0)
A15: Profitability
A16: Revenue (LCY) | E16: =SUMIFS(FS!$E$11:$BL$11,Timeline!$E$6:$BL$6,E$6) | F16: =SUMIFS(FS!$E$11:$BL$11,Timeline!$E$6:$BL$6,F$6) | G16: =SUMIFS(FS!$E$11:$BL$11,Timeline!$E$6:$BL$6,G$6) | H16: =SUMIFS(FS!$E$11:$BL$11,Timeline!$E$6:$BL$6,H$6) | I16: =SUMIFS(FS!$E$11:$BL$11,Timeline!$E$6:$BL$6,I$6)
A17: Gross margin | E17: =IFERROR(SUMIFS(FS!$E$13:$BL$13,Timeline!$E$6:$BL$6,E$6)/SUMIFS(FS!$E$11:$BL$11,Timeline!$E$6:$BL$6,E$6),0) | F17: =IFERROR(SUMIFS(FS!$E$13:$BL$13,Timeline!$E$6:$BL$6,F$6)/SUMIFS(FS!$E$11:$BL$11,Timeline!$E$6:$BL$6,F$6),0) | G17: =IFERROR(SUMIFS(FS!$E$13:$BL$13,Timeline!$E$6:$BL$6,G$6)/SUMIFS(FS!$E$11:$BL$11,Timeline!$E$6:$BL$6,G$6),0) | H17: =IFERROR(SUMIFS(FS!$E$13:$BL$13,Timeline!$E$6:$BL$6,H$6)/SUMIFS(FS!$E$11:$BL$11,Timeline!$E$6:$BL$6,H$6),0) | I17: =IFERROR(SUMIFS(FS!$E$13:$BL$13,Timeline!$E$6:$BL$6,I$6)/SUMIFS(FS!$E$11:$BL$11,Timeline!$E$6:$BL$6,I$6),0)
A18: EBITDA margin | E18: =IFERROR(SUMIFS(FS!$E$16:$BL$16,Timeline!$E$6:$BL$6,E$6)/SUMIFS(FS!$E$11:$BL$11,Timeline!$E$6:$BL$6,E$6),0) | F18: =IFERROR(SUMIFS(FS!$E$16:$BL$16,Timeline!$E$6:$BL$6,F$6)/SUMIFS(FS!$E$11:$BL$11,Timeline!$E$6:$BL$6,F$6),0) | G18: =IFERROR(SUMIFS(FS!$E$16:$BL$16,Timeline!$E$6:$BL$6,G$6)/SUMIFS(FS!$E$11:$BL$11,Timeline!$E$6:$BL$6,G$6),0) | H18: =IFERROR(SUMIFS(FS!$E$16:$BL$16,Timeline!$E$6:$BL$6,H$6)/SUMIFS(FS!$E$11:$BL$11,Timeline!$E$6:$BL$6,H$6),0) | I18: =IFERROR(SUMIFS(FS!$E$16:$BL$16,Timeline!$E$6:$BL$6,I$6)/SUMIFS(FS!$E$11:$BL$11,Timeline!$E$6:$BL$6,I$6),0)
A19: Net income (LCY) | E19: =SUMIFS(FS!$E$26:$BL$26,Timeline!$E$6:$BL$6,E$6) | F19: =SUMIFS(FS!$E$26:$BL$26,Timeline!$E$6:$BL$6,F$6) | G19: =SUMIFS(FS!$E$26:$BL$26,Timeline!$E$6:$BL$6,G$6) | H19: =SUMIFS(FS!$E$26:$BL$26,Timeline!$E$6:$BL$6,H$6) | I19: =SUMIFS(FS!$E$26:$BL$26,Timeline!$E$6:$BL$6,I$6)
A20: Revenue (USD, at average FX) | E20: =IFERROR(SUMIFS(FS!$E$11:$BL$11,Timeline!$E$6:$BL$6,E$6)/AVERAGEIFS(Timeline!$E$8:$BL$8,Timeline!$E$6:$BL$6,E$6),0) | F20: =IFERROR(SUMIFS(FS!$E$11:$BL$11,Timeline!$E$6:$BL$6,F$6)/AVERAGEIFS(Timeline!$E$8:$BL$8,Timeline!$E$6:$BL$6,F$6),0) | G20: =IFERROR(SUMIFS(FS!$E$11:$BL$11,Timeline!$E$6:$BL$6,G$6)/AVERAGEIFS(Timeline!$E$8:$BL$8,Timeline!$E$6:$BL$6,G$6),0) | H20: =IFERROR(SUMIFS(FS!$E$11:$BL$11,Timeline!$E$6:$BL$6,H$6)/AVERAGEIFS(Timeline!$E$8:$BL$8,Timeline!$E$6:$BL$6,H$6),0) | I20: =IFERROR(SUMIFS(FS!$E$11:$BL$11,Timeline!$E$6:$BL$6,I$6)/AVERAGEIFS(Timeline!$E$8:$BL$8,Timeline!$E$6:$BL$6,I$6),0)
A21: Funding & leverage
A22: Closing cash (LCY) | E22: =INDEX(FS!$E$60:$BL$60,1,E$6*12) | F22: =INDEX(FS!$E$60:$BL$60,1,F$6*12) | G22: =INDEX(FS!$E$60:$BL$60,1,G$6*12) | H22: =INDEX(FS!$E$60:$BL$60,1,H$6*12) | I22: =INDEX(FS!$E$60:$BL$60,1,I$6*12)
A23: Cumulative equity invested (LCY) | E23: =INDEX(Financing!$E$11:$BL$11,1,E$6*12) | F23: =INDEX(Financing!$E$11:$BL$11,1,F$6*12) | G23: =INDEX(Financing!$E$11:$BL$11,1,G$6*12) | H23: =INDEX(Financing!$E$11:$BL$11,1,H$6*12) | I23: =INDEX(Financing!$E$11:$BL$11,1,I$6*12)
A24: Equity top-ups in year (funding gap, LCY) | E24: =SUMIFS(FS!$E$59:$BL$59,Timeline!$E$6:$BL$6,E$6) | F24: =SUMIFS(FS!$E$59:$BL$59,Timeline!$E$6:$BL$6,F$6) | G24: =SUMIFS(FS!$E$59:$BL$59,Timeline!$E$6:$BL$6,G$6) | H24: =SUMIFS(FS!$E$59:$BL$59,Timeline!$E$6:$BL$6,H$6) | I24: =SUMIFS(FS!$E$59:$BL$59,Timeline!$E$6:$BL$6,I$6)
A25: Total debt (year end, LCY) | E25: =INDEX(FS!$E$37:$BL$37,1,E$6*12)+INDEX(FS!$E$38:$BL$38,1,E$6*12) | F25: =INDEX(FS!$E$37:$BL$37,1,F$6*12)+INDEX(FS!$E$38:$BL$38,1,F$6*12) | G25: =INDEX(FS!$E$37:$BL$37,1,G$6*12)+INDEX(FS!$E$38:$BL$38,1,G$6*12) | H25: =INDEX(FS!$E$37:$BL$37,1,H$6*12)+INDEX(FS!$E$38:$BL$38,1,H$6*12) | I25: =INDEX(FS!$E$37:$BL$37,1,I$6*12)+INDEX(FS!$E$38:$BL$38,1,I$6*12)
A26: Debt / equity (book) | E26: =IFERROR((INDEX(FS!$E$37:$BL$37,1,E$6*12)+INDEX(FS!$E$38:$BL$38,1,E$6*12))/INDEX(FS!$E$42:$BL$42,1,E$6*12),0) | F26: =IFERROR((INDEX(FS!$E$37:$BL$37,1,F$6*12)+INDEX(FS!$E$38:$BL$38,1,F$6*12))/INDEX(FS!$E$42:$BL$42,1,F$6*12),0) | G26: =IFERROR((INDEX(FS!$E$37:$BL$37,1,G$6*12)+INDEX(FS!$E$38:$BL$38,1,G$6*12))/INDEX(FS!$E$42:$BL$42,1,G$6*12),0) | H26: =IFERROR((INDEX(FS!$E$37:$BL$37,1,H$6*12)+INDEX(FS!$E$38:$BL$38,1,H$6*12))/INDEX(FS!$E$42:$BL$42,1,H$6*12),0) | I26: =IFERROR((INDEX(FS!$E$37:$BL$37,1,I$6*12)+INDEX(FS!$E$38:$BL$38,1,I$6*12))/INDEX(FS!$E$42:$BL$42,1,I$6*12),0)
A27: Debt service coverage ((CFO + interest) / (interest + term-loan principal)) | E27: =IFERROR((SUMIFS(FS!$E$53:$BL$53,Timeline!$E$6:$BL$6,E$6)-SUMIFS(FS!$E$19:$BL$19,Timeline!$E$6:$BL$6,E$6)-SUMIFS(FS!$E$20:$BL$20,Timeline!$E$6:$BL$6,E$6))/(SUMIFS(Financing!$E$16:$BL$16,Timeline!$E$6:$BL$6,E$6)+SUMIFS(Financing!$E$18:$BL$18,Timeline!$E$6:$BL$6,E$6)+SUMIFS(Financing!$E$26:$BL$26,Timeline!$E$6:$BL$6,E$6)),0) | F27: =IFERROR((SUMIFS(FS!$E$53:$BL$53,Timeline!$E$6:$BL$6,F$6)-SUMIFS(FS!$E$19:$BL$19,Timeline!$E$6:$BL$6,F$6)-SUMIFS(FS!$E$20:$BL$20,Timeline!$E$6:$BL$6,F$6))/(SUMIFS(Financing!$E$16:$BL$16,Timeline!$E$6:$BL$6,F$6)+SUMIFS(Financing!$E$18:$BL$18,Timeline!$E$6:$BL$6,F$6)+SUMIFS(Financing!$E$26:$BL$26,Timeline!$E$6:$BL$6,F$6)),0) | G27: =IFERROR((SUMIFS(FS!$E$53:$BL$53,Timeline!$E$6:$BL$6,G$6)-SUMIFS(FS!$E$19:$BL$19,Timeline!$E$6:$BL$6,G$6)-SUMIFS(FS!$E$20:$BL$20,Timeline!$E$6:$BL$6,G$6))/(SUMIFS(Financing!$E$16:$BL$16,Timeline!$E$6:$BL$6,G$6)+SUMIFS(Financing!$E$18:$BL$18,Timeline!$E$6:$BL$6,G$6)+SUMIFS(Financing!$E$26:$BL$26,Timeline!$E$6:$BL$6,G$6)),0) | H27: =IFERROR((SUMIFS(FS!$E$53:$BL$53,Timeline!$E$6:$BL$6,H$6)-SUMIFS(FS!$E$19:$BL$19,Timeline!$E$6:$BL$6,H$6)-SUMIFS(FS!$E$20:$BL$20,Timeline!$E$6:$BL$6,H$6))/(SUMIFS(Financing!$E$16:$BL$16,Timeline!$E$6:$BL$6,H$6)+SUMIFS(Financing!$E$18:$BL$18,Timeline!$E$6:$BL$6,H$6)+SUMIFS(Financing!$E$26:$BL$26,Timeline!$E$6:$BL$6,H$6)),0) | I27: =IFERROR((SUMIFS(FS!$E$53:$BL$53,Timeline!$E$6:$BL$6,I$6)-SUMIFS(FS!$E$19:$BL$19,Timeline!$E$6:$BL$6,I$6)-SUMIFS(FS!$E$20:$BL$20,Timeline!$E$6:$BL$6,I$6))/(SUMIFS(Financing!$E$16:$BL$16,Timeline!$E$6:$BL$6,I$6)+SUMIFS(Financing!$E$18:$BL$18,Timeline!$E$6:$BL$6,I$6)+SUMIFS(Financing!$E$26:$BL$26,Timeline!$E$6:$BL$6,I$6)),0)
A28: FX rate (year end, LCY/USD) | E28: =INDEX(Timeline!$E$8:$BL$8,1,E$6*12) | F28: =INDEX(Timeline!$E$8:$BL$8,1,F$6*12) | G28: =INDEX(Timeline!$E$8:$BL$8,1,G$6*12) | H28: =INDEX(Timeline!$E$8:$BL$8,1,H$6*12) | I28: =INDEX(Timeline!$E$8:$BL$8,1,I$6*12)
A30: Peak cumulative equity requirement (LCY) | C30: =MAX(Financing!$E$11:$BL$11)
A31: Peak cumulative equity requirement (USD, at opening FX) | C31: =C30/Inputs!$C$10
A33: DSCR is shown for information; covenant definitions vary by lender. Balance-at-risk is a model approximation of PERFORM 'Receivables at Risk' (accounts that have stopped paying).

Sheet Annual
A1: Annual summary
A2: Flows summed by financial year; balances at year end. LCY.
A5: LCY | E5: Year 1 | F5: Year 2 | G5: Year 3 | H5: Year 4 | I5: Year 5
E6: 1 | F6: 2 | G6: 3 | H6: 4 | I6: 5
A8: INCOME STATEMENT
A9: Hardware revenue (cash price) | E9: =SUMIFS(FS!$E$9:$BL$9,Timeline!$E$6:$BL$6,E$6) | F9: =SUMIFS(FS!$E$9:$BL$9,Timeline!$E$6:$BL$6,F$6) | G9: =SUMIFS(FS!$E$9:$BL$9,Timeline!$E$6:$BL$6,G$6) | H9: =SUMIFS(FS!$E$9:$BL$9,Timeline!$E$6:$BL$6,H$6) | I9: =SUMIFS(FS!$E$9:$BL$9,Timeline!$E$6:$BL$6,I$6)
A10: PAYGo financing income | E10: =SUMIFS(FS!$E$10:$BL$10,Timeline!$E$6:$BL$6,E$6) | F10: =SUMIFS(FS!$E$10:$BL$10,Timeline!$E$6:$BL$6,F$6) | G10: =SUMIFS(FS!$E$10:$BL$10,Timeline!$E$6:$BL$6,G$6) | H10: =SUMIFS(FS!$E$10:$BL$10,Timeline!$E$6:$BL$6,H$6) | I10: =SUMIFS(FS!$E$10:$BL$10,Timeline!$E$6:$BL$6,I$6)
A11: Total revenue | E11: =SUMIFS(FS!$E$11:$BL$11,Timeline!$E$6:$BL$6,E$6) | F11: =SUMIFS(FS!$E$11:$BL$11,Timeline!$E$6:$BL$6,F$6) | G11: =SUMIFS(FS!$E$11:$BL$11,Timeline!$E$6:$BL$6,G$6) | H11: =SUMIFS(FS!$E$11:$BL$11,Timeline!$E$6:$BL$6,H$6) | I11: =SUMIFS(FS!$E$11:$BL$11,Timeline!$E$6:$BL$6,I$6)
A12: Cost of goods sold | E12: =SUMIFS(FS!$E$12:$BL$12,Timeline!$E$6:$BL$6,E$6) | F12: =SUMIFS(FS!$E$12:$BL$12,Timeline!$E$6:$BL$6,F$6) | G12: =SUMIFS(FS!$E$12:$BL$12,Timeline!$E$6:$BL$6,G$6) | H12: =SUMIFS(FS!$E$12:$BL$12,Timeline!$E$6:$BL$6,H$6) | I12: =SUMIFS(FS!$E$12:$BL$12,Timeline!$E$6:$BL$6,I$6)
A13: Gross profit | E13: =SUMIFS(FS!$E$13:$BL$13,Timeline!$E$6:$BL$6,E$6) | F13: =SUMIFS(FS!$E$13:$BL$13,Timeline!$E$6:$BL$6,F$6) | G13: =SUMIFS(FS!$E$13:$BL$13,Timeline!$E$6:$BL$6,G$6) | H13: =SUMIFS(FS!$E$13:$BL$13,Timeline!$E$6:$BL$6,H$6) | I13: =SUMIFS(FS!$E$13:$BL$13,Timeline!$E$6:$BL$6,I$6)
A14: Operating expenses | E14: =SUMIFS(FS!$E$14:$BL$14,Timeline!$E$6:$BL$6,E$6) | F14: =SUMIFS(FS!$E$14:$BL$14,Timeline!$E$6:$BL$6,F$6) | G14: =SUMIFS(FS!$E$14:$BL$14,Timeline!$E$6:$BL$6,G$6) | H14: =SUMIFS(FS!$E$14:$BL$14,Timeline!$E$6:$BL$6,H$6) | I14: =SUMIFS(FS!$E$14:$BL$14,Timeline!$E$6:$BL$6,I$6)
A15: Credit loss expense (ECL) | E15: =SUMIFS(FS!$E$15:$BL$15,Timeline!$E$6:$BL$6,E$6) | F15: =SUMIFS(FS!$E$15:$BL$15,Timeline!$E$6:$BL$6,F$6) | G15: =SUMIFS(FS!$E$15:$BL$15,Timeline!$E$6:$BL$6,G$6) | H15: =SUMIFS(FS!$E$15:$BL$15,Timeline!$E$6:$BL$6,H$6) | I15: =SUMIFS(FS!$E$15:$BL$15,Timeline!$E$6:$BL$6,I$6)
A16: EBITDA | E16: =SUMIFS(FS!$E$16:$BL$16,Timeline!$E$6:$BL$6,E$6) | F16: =SUMIFS(FS!$E$16:$BL$16,Timeline!$E$6:$BL$6,F$6) | G16: =SUMIFS(FS!$E$16:$BL$16,Timeline!$E$6:$BL$6,G$6) | H16: =SUMIFS(FS!$E$16:$BL$16,Timeline!$E$6:$BL$6,H$6) | I16: =SUMIFS(FS!$E$16:$BL$16,Timeline!$E$6:$BL$6,I$6)
A17: Depreciation | E17: =SUMIFS(FS!$E$17:$BL$17,Timeline!$E$6:$BL$6,E$6) | F17: =SUMIFS(FS!$E$17:$BL$17,Timeline!$E$6:$BL$6,F$6) | G17: =SUMIFS(FS!$E$17:$BL$17,Timeline!$E$6:$BL$6,G$6) | H17: =SUMIFS(FS!$E$17:$BL$17,Timeline!$E$6:$BL$6,H$6) | I17: =SUMIFS(FS!$E$17:$BL$17,Timeline!$E$6:$BL$6,I$6)
A18: EBIT | E18: =SUMIFS(FS!$E$18:$BL$18,Timeline!$E$6:$BL$6,E$6) | F18: =SUMIFS(FS!$E$18:$BL$18,Timeline!$E$6:$BL$6,F$6) | G18: =SUMIFS(FS!$E$18:$BL$18,Timeline!$E$6:$BL$6,G$6) | H18: =SUMIFS(FS!$E$18:$BL$18,Timeline!$E$6:$BL$6,H$6) | I18: =SUMIFS(FS!$E$18:$BL$18,Timeline!$E$6:$BL$6,I$6)
A19: Interest - USD term loan | E19: =SUMIFS(FS!$E$19:$BL$19,Timeline!$E$6:$BL$6,E$6) | F19: =SUMIFS(FS!$E$19:$BL$19,Timeline!$E$6:$BL$6,F$6) | G19: =SUMIFS(FS!$E$19:$BL$19,Timeline!$E$6:$BL$6,G$6) | H19: =SUMIFS(FS!$E$19:$BL$19,Timeline!$E$6:$BL$6,H$6) | I19: =SUMIFS(FS!$E$19:$BL$19,Timeline!$E$6:$BL$6,I$6)
A20: Interest - receivables facility | E20: =SUMIFS(FS!$E$20:$BL$20,Timeline!$E$6:$BL$6,E$6) | F20: =SUMIFS(FS!$E$20:$BL$20,Timeline!$E$6:$BL$6,F$6) | G20: =SUMIFS(FS!$E$20:$BL$20,Timeline!$E$6:$BL$6,G$6) | H20: =SUMIFS(FS!$E$20:$BL$20,Timeline!$E$6:$BL$6,H$6) | I20: =SUMIFS(FS!$E$20:$BL$20,Timeline!$E$6:$BL$6,I$6)
A21: FX (loss) / gain on USD debt | E21: =SUMIFS(FS!$E$21:$BL$21,Timeline!$E$6:$BL$6,E$6) | F21: =SUMIFS(FS!$E$21:$BL$21,Timeline!$E$6:$BL$6,F$6) | G21: =SUMIFS(FS!$E$21:$BL$21,Timeline!$E$6:$BL$6,G$6) | H21: =SUMIFS(FS!$E$21:$BL$21,Timeline!$E$6:$BL$6,H$6) | I21: =SUMIFS(FS!$E$21:$BL$21,Timeline!$E$6:$BL$6,I$6)
A22: Profit before tax | E22: =SUMIFS(FS!$E$22:$BL$22,Timeline!$E$6:$BL$6,E$6) | F22: =SUMIFS(FS!$E$22:$BL$22,Timeline!$E$6:$BL$6,F$6) | G22: =SUMIFS(FS!$E$22:$BL$22,Timeline!$E$6:$BL$6,G$6) | H22: =SUMIFS(FS!$E$22:$BL$22,Timeline!$E$6:$BL$6,H$6) | I22: =SUMIFS(FS!$E$22:$BL$22,Timeline!$E$6:$BL$6,I$6)
A23: Income tax | E23: =SUMIFS(FS!$E$25:$BL$25,Timeline!$E$6:$BL$6,E$6) | F23: =SUMIFS(FS!$E$25:$BL$25,Timeline!$E$6:$BL$6,F$6) | G23: =SUMIFS(FS!$E$25:$BL$25,Timeline!$E$6:$BL$6,G$6) | H23: =SUMIFS(FS!$E$25:$BL$25,Timeline!$E$6:$BL$6,H$6) | I23: =SUMIFS(FS!$E$25:$BL$25,Timeline!$E$6:$BL$6,I$6)
A24: Net income | E24: =SUMIFS(FS!$E$26:$BL$26,Timeline!$E$6:$BL$6,E$6) | F24: =SUMIFS(FS!$E$26:$BL$26,Timeline!$E$6:$BL$6,F$6) | G24: =SUMIFS(FS!$E$26:$BL$26,Timeline!$E$6:$BL$6,G$6) | H24: =SUMIFS(FS!$E$26:$BL$26,Timeline!$E$6:$BL$6,H$6) | I24: =SUMIFS(FS!$E$26:$BL$26,Timeline!$E$6:$BL$6,I$6)
A26: BALANCE SHEET
A27: Cash | E27: =INDEX(FS!$E$29:$BL$29,1,E$6*12) | F27: =INDEX(FS!$E$29:$BL$29,1,F$6*12) | G27: =INDEX(FS!$E$29:$BL$29,1,G$6*12) | H27: =INDEX(FS!$E$29:$BL$29,1,H$6*12) | I27: =INDEX(FS!$E$29:$BL$29,1,I$6*12)
A28: PAYGo receivables - gross | E28: =INDEX(FS!$E$30:$BL$30,1,E$6*12) | F28: =INDEX(FS!$E$30:$BL$30,1,F$6*12) | G28: =INDEX(FS!$E$30:$BL$30,1,G$6*12) | H28: =INDEX(FS!$E$30:$BL$30,1,H$6*12) | I28: =INDEX(FS!$E$30:$BL$30,1,I$6*12)
A29: Loss allowance (ECL provision) | E29: =INDEX(FS!$E$31:$BL$31,1,E$6*12) | F29: =INDEX(FS!$E$31:$BL$31,1,F$6*12) | G29: =INDEX(FS!$E$31:$BL$31,1,G$6*12) | H29: =INDEX(FS!$E$31:$BL$31,1,H$6*12) | I29: =INDEX(FS!$E$31:$BL$31,1,I$6*12)
A30: PAYGo receivables - net | E30: =INDEX(FS!$E$32:$BL$32,1,E$6*12) | F30: =INDEX(FS!$E$32:$BL$32,1,F$6*12) | G30: =INDEX(FS!$E$32:$BL$32,1,G$6*12) | H30: =INDEX(FS!$E$32:$BL$32,1,H$6*12) | I30: =INDEX(FS!$E$32:$BL$32,1,I$6*12)
A31: Inventory | E31: =INDEX(FS!$E$33:$BL$33,1,E$6*12) | F31: =INDEX(FS!$E$33:$BL$33,1,F$6*12) | G31: =INDEX(FS!$E$33:$BL$33,1,G$6*12) | H31: =INDEX(FS!$E$33:$BL$33,1,H$6*12) | I31: =INDEX(FS!$E$33:$BL$33,1,I$6*12)
A32: Net fixed assets | E32: =INDEX(FS!$E$34:$BL$34,1,E$6*12) | F32: =INDEX(FS!$E$34:$BL$34,1,F$6*12) | G32: =INDEX(FS!$E$34:$BL$34,1,G$6*12) | H32: =INDEX(FS!$E$34:$BL$34,1,H$6*12) | I32: =INDEX(FS!$E$34:$BL$34,1,I$6*12)
A33: Total assets | E33: =INDEX(FS!$E$35:$BL$35,1,E$6*12) | F33: =INDEX(FS!$E$35:$BL$35,1,F$6*12) | G33: =INDEX(FS!$E$35:$BL$35,1,G$6*12) | H33: =INDEX(FS!$E$35:$BL$35,1,H$6*12) | I33: =INDEX(FS!$E$35:$BL$35,1,I$6*12)
A34: Supplier payables | E34: =INDEX(FS!$E$36:$BL$36,1,E$6*12) | F34: =INDEX(FS!$E$36:$BL$36,1,F$6*12) | G34: =INDEX(FS!$E$36:$BL$36,1,G$6*12) | H34: =INDEX(FS!$E$36:$BL$36,1,H$6*12) | I34: =INDEX(FS!$E$36:$BL$36,1,I$6*12)
A35: USD term loan (in LCY) | E35: =INDEX(FS!$E$37:$BL$37,1,E$6*12) | F35: =INDEX(FS!$E$37:$BL$37,1,F$6*12) | G35: =INDEX(FS!$E$37:$BL$37,1,G$6*12) | H35: =INDEX(FS!$E$37:$BL$37,1,H$6*12) | I35: =INDEX(FS!$E$37:$BL$37,1,I$6*12)
A36: Receivables facility | E36: =INDEX(FS!$E$38:$BL$38,1,E$6*12) | F36: =INDEX(FS!$E$38:$BL$38,1,F$6*12) | G36: =INDEX(FS!$E$38:$BL$38,1,G$6*12) | H36: =INDEX(FS!$E$38:$BL$38,1,H$6*12) | I36: =INDEX(FS!$E$38:$BL$38,1,I$6*12)
A37: Total liabilities | E37: =INDEX(FS!$E$39:$BL$39,1,E$6*12) | F37: =INDEX(FS!$E$39:$BL$39,1,F$6*12) | G37: =INDEX(FS!$E$39:$BL$39,1,G$6*12) | H37: =INDEX(FS!$E$39:$BL$39,1,H$6*12) | I37: =INDEX(FS!$E$39:$BL$39,1,I$6*12)
A38: Share capital | E38: =INDEX(FS!$E$40:$BL$40,1,E$6*12) | F38: =INDEX(FS!$E$40:$BL$40,1,F$6*12) | G38: =INDEX(FS!$E$40:$BL$40,1,G$6*12) | H38: =INDEX(FS!$E$40:$BL$40,1,H$6*12) | I38: =INDEX(FS!$E$40:$BL$40,1,I$6*12)
A39: Retained earnings | E39: =INDEX(FS!$E$41:$BL$41,1,E$6*12) | F39: =INDEX(FS!$E$41:$BL$41,1,F$6*12) | G39: =INDEX(FS!$E$41:$BL$41,1,G$6*12) | H39: =INDEX(FS!$E$41:$BL$41,1,H$6*12) | I39: =INDEX(FS!$E$41:$BL$41,1,I$6*12)
A40: Total equity | E40: =INDEX(FS!$E$42:$BL$42,1,E$6*12) | F40: =INDEX(FS!$E$42:$BL$42,1,F$6*12) | G40: =INDEX(FS!$E$42:$BL$42,1,G$6*12) | H40: =INDEX(FS!$E$42:$BL$42,1,H$6*12) | I40: =INDEX(FS!$E$42:$BL$42,1,I$6*12)
A41: Total liabilities & equity | E41: =INDEX(FS!$E$43:$BL$43,1,E$6*12) | F41: =INDEX(FS!$E$43:$BL$43,1,F$6*12) | G41: =INDEX(FS!$E$43:$BL$43,1,G$6*12) | H41: =INDEX(FS!$E$43:$BL$43,1,H$6*12) | I41: =INDEX(FS!$E$43:$BL$43,1,I$6*12)
A42: Balance check (should be 0) | E42: =INDEX(FS!$E$44:$BL$44,1,E$6*12) | F42: =INDEX(FS!$E$44:$BL$44,1,F$6*12) | G42: =INDEX(FS!$E$44:$BL$44,1,G$6*12) | H42: =INDEX(FS!$E$44:$BL$44,1,H$6*12) | I42: =INDEX(FS!$E$44:$BL$44,1,I$6*12)
A44: CASH FLOW STATEMENT
A45: Net income | E45: =SUMIFS(FS!$E$47:$BL$47,Timeline!$E$6:$BL$6,E$6) | F45: =SUMIFS(FS!$E$47:$BL$47,Timeline!$E$6:$BL$6,F$6) | G45: =SUMIFS(FS!$E$47:$BL$47,Timeline!$E$6:$BL$6,G$6) | H45: =SUMIFS(FS!$E$47:$BL$47,Timeline!$E$6:$BL$6,H$6) | I45: =SUMIFS(FS!$E$47:$BL$47,Timeline!$E$6:$BL$6,I$6)
A46: Add back: depreciation | E46: =SUMIFS(FS!$E$48:$BL$48,Timeline!$E$6:$BL$6,E$6) | F46: =SUMIFS(FS!$E$48:$BL$48,Timeline!$E$6:$BL$6,F$6) | G46: =SUMIFS(FS!$E$48:$BL$48,Timeline!$E$6:$BL$6,G$6) | H46: =SUMIFS(FS!$E$48:$BL$48,Timeline!$E$6:$BL$6,H$6) | I46: =SUMIFS(FS!$E$48:$BL$48,Timeline!$E$6:$BL$6,I$6)
A47: Add back: unrealised FX loss | E47: =SUMIFS(FS!$E$49:$BL$49,Timeline!$E$6:$BL$6,E$6) | F47: =SUMIFS(FS!$E$49:$BL$49,Timeline!$E$6:$BL$6,F$6) | G47: =SUMIFS(FS!$E$49:$BL$49,Timeline!$E$6:$BL$6,G$6) | H47: =SUMIFS(FS!$E$49:$BL$49,Timeline!$E$6:$BL$6,H$6) | I47: =SUMIFS(FS!$E$49:$BL$49,Timeline!$E$6:$BL$6,I$6)
A48: (Increase) / decrease in net receivables | E48: =SUMIFS(FS!$E$50:$BL$50,Timeline!$E$6:$BL$6,E$6) | F48: =SUMIFS(FS!$E$50:$BL$50,Timeline!$E$6:$BL$6,F$6) | G48: =SUMIFS(FS!$E$50:$BL$50,Timeline!$E$6:$BL$6,G$6) | H48: =SUMIFS(FS!$E$50:$BL$50,Timeline!$E$6:$BL$6,H$6) | I48: =SUMIFS(FS!$E$50:$BL$50,Timeline!$E$6:$BL$6,I$6)
A49: (Increase) / decrease in inventory | E49: =SUMIFS(FS!$E$51:$BL$51,Timeline!$E$6:$BL$6,E$6) | F49: =SUMIFS(FS!$E$51:$BL$51,Timeline!$E$6:$BL$6,F$6) | G49: =SUMIFS(FS!$E$51:$BL$51,Timeline!$E$6:$BL$6,G$6) | H49: =SUMIFS(FS!$E$51:$BL$51,Timeline!$E$6:$BL$6,H$6) | I49: =SUMIFS(FS!$E$51:$BL$51,Timeline!$E$6:$BL$6,I$6)
A50: Increase / (decrease) in payables | E50: =SUMIFS(FS!$E$52:$BL$52,Timeline!$E$6:$BL$6,E$6) | F50: =SUMIFS(FS!$E$52:$BL$52,Timeline!$E$6:$BL$6,F$6) | G50: =SUMIFS(FS!$E$52:$BL$52,Timeline!$E$6:$BL$6,G$6) | H50: =SUMIFS(FS!$E$52:$BL$52,Timeline!$E$6:$BL$6,H$6) | I50: =SUMIFS(FS!$E$52:$BL$52,Timeline!$E$6:$BL$6,I$6)
A51: Cash flow from operations | E51: =SUMIFS(FS!$E$53:$BL$53,Timeline!$E$6:$BL$6,E$6) | F51: =SUMIFS(FS!$E$53:$BL$53,Timeline!$E$6:$BL$6,F$6) | G51: =SUMIFS(FS!$E$53:$BL$53,Timeline!$E$6:$BL$6,G$6) | H51: =SUMIFS(FS!$E$53:$BL$53,Timeline!$E$6:$BL$6,H$6) | I51: =SUMIFS(FS!$E$53:$BL$53,Timeline!$E$6:$BL$6,I$6)
A52: Cash flow from investing (capex) | E52: =SUMIFS(FS!$E$54:$BL$54,Timeline!$E$6:$BL$6,E$6) | F52: =SUMIFS(FS!$E$54:$BL$54,Timeline!$E$6:$BL$6,F$6) | G52: =SUMIFS(FS!$E$54:$BL$54,Timeline!$E$6:$BL$6,G$6) | H52: =SUMIFS(FS!$E$54:$BL$54,Timeline!$E$6:$BL$6,H$6) | I52: =SUMIFS(FS!$E$54:$BL$54,Timeline!$E$6:$BL$6,I$6)
A53: Term loan drawdown / (repayment) | E53: =SUMIFS(FS!$E$55:$BL$55,Timeline!$E$6:$BL$6,E$6) | F53: =SUMIFS(FS!$E$55:$BL$55,Timeline!$E$6:$BL$6,F$6) | G53: =SUMIFS(FS!$E$55:$BL$55,Timeline!$E$6:$BL$6,G$6) | H53: =SUMIFS(FS!$E$55:$BL$55,Timeline!$E$6:$BL$6,H$6) | I53: =SUMIFS(FS!$E$55:$BL$55,Timeline!$E$6:$BL$6,I$6)
A54: Receivables facility drawdown / (repayment) | E54: =SUMIFS(FS!$E$56:$BL$56,Timeline!$E$6:$BL$6,E$6) | F54: =SUMIFS(FS!$E$56:$BL$56,Timeline!$E$6:$BL$6,F$6) | G54: =SUMIFS(FS!$E$56:$BL$56,Timeline!$E$6:$BL$6,G$6) | H54: =SUMIFS(FS!$E$56:$BL$56,Timeline!$E$6:$BL$6,H$6) | I54: =SUMIFS(FS!$E$56:$BL$56,Timeline!$E$6:$BL$6,I$6)
A55: Equity - initial / scheduled | E55: =SUMIFS(FS!$E$57:$BL$57,Timeline!$E$6:$BL$6,E$6) | F55: =SUMIFS(FS!$E$57:$BL$57,Timeline!$E$6:$BL$6,F$6) | G55: =SUMIFS(FS!$E$57:$BL$57,Timeline!$E$6:$BL$6,G$6) | H55: =SUMIFS(FS!$E$57:$BL$57,Timeline!$E$6:$BL$6,H$6) | I55: =SUMIFS(FS!$E$57:$BL$57,Timeline!$E$6:$BL$6,I$6)
A56: Cash before equity top-up | E56: =INDEX(FS!$E$58:$BL$58,1,E$6*12) | F56: =INDEX(FS!$E$58:$BL$58,1,F$6*12) | G56: =INDEX(FS!$E$58:$BL$58,1,G$6*12) | H56: =INDEX(FS!$E$58:$BL$58,1,H$6*12) | I56: =INDEX(FS!$E$58:$BL$58,1,I$6*12)
A57: Equity top-up to maintain minimum cash | E57: =SUMIFS(FS!$E$59:$BL$59,Timeline!$E$6:$BL$6,E$6) | F57: =SUMIFS(FS!$E$59:$BL$59,Timeline!$E$6:$BL$6,F$6) | G57: =SUMIFS(FS!$E$59:$BL$59,Timeline!$E$6:$BL$6,G$6) | H57: =SUMIFS(FS!$E$59:$BL$59,Timeline!$E$6:$BL$6,H$6) | I57: =SUMIFS(FS!$E$59:$BL$59,Timeline!$E$6:$BL$6,I$6)
A58: Closing cash | E58: =INDEX(FS!$E$60:$BL$60,1,E$6*12) | F58: =INDEX(FS!$E$60:$BL$60,1,F$6*12) | G58: =INDEX(FS!$E$60:$BL$60,1,G$6*12) | H58: =INDEX(FS!$E$60:$BL$60,1,H$6*12) | I58: =INDEX(FS!$E$60:$BL$60,1,I$6*12)

Sheet Unit_Economics
A1: Unit economics (per unit, month-1 prices, active scenario)
A2: Lifetime view of one PAYGo customer per product.
A4: Metric | B4: Unit | C4: P1 Solar lantern kit (Tier 1) | D4: P2 SHS lights+radio (Tier 2) | E4: P3 SHS with TV (Tier 3)
A5: Cash price | B5: LCY | C5: =Products!$C$6 | D5: =Products!$D$6 | E5: =Products!$E$6
A6: Total contract value | B6: LCY | C6: =Products!$C$19 | D6: =Products!$D$19 | E6: =Products!$E$19
A7: Deposit | B7: LCY | C7: =Products!$C$7 | D7: =Products!$D$7 | E7: =Products!$E$7
A8: Expected instalments collected | B8: LCY | C8: =Curves!$D$70 | D8: =Curves!$M$70 | E8: =Curves!$V$70
A9: Expected lifetime cash collected (deposit + instalments) | B9: LCY | C9: =C7+C8 | D9: =D7+D8 | E9: =E7+E8
A10: Expected loss rate (missed / scheduled instalments) | B10: % | C10: =IFERROR(Curves!$E$70/Curves!$C$70,0) | D10: =IFERROR(Curves!$N$70/Curves!$L$70,0) | E10: =IFERROR(Curves!$W$70/Curves!$U$70,0)
A11: Lifetime collection rate (collected / contract value) | B11: % | C11: =IFERROR(C9/C6,0) | D11: =IFERROR(D9/D6,0) | E11: =IFERROR(E9/E6,0)
A12: Landed hardware cost | B12: LCY | C12: =Products!$C$25 | D12: =Products!$D$25 | E12: =Products!$E$25
A13: Warranty provision | B13: LCY | C13: =Products!$C$25*Inputs!$C$27 | D13: =Products!$D$25*Inputs!$C$27 | E13: =Products!$E$25*Inputs!$C$27
A14: Customer acquisition cost (CAC) | B14: LCY | C14: =Products!$C$26 | D14: =Products!$D$26 | E14: =Products!$E$26
A15: Payment fees + servicing over life | B15: LCY | C15: =C9*Inputs!$C$23+Inputs!$C$24*SUM(Curves!$G$8:$G$68)-Inputs!$C$24 | D15: =D9*Inputs!$C$23+Inputs!$C$24*SUM(Curves!$P$8:$P$68)-Inputs!$C$24 | E15: =E9*Inputs!$C$23+Inputs!$C$24*SUM(Curves!$Y$8:$Y$68)-Inputs!$C$24
A16: Contribution per unit (lifetime, undiscounted) | B16: LCY | C16: =C9-C12-C13-C14-C15 | D16: =D9-D12-D13-D14-D15 | E16: =E9-E12-E13-E14-E15
A17: LTV / CAC (lifetime gross profit after credit losses / CAC) | B17: x | C17: =IFERROR((C9-C12-C13-C15)/C14,0) | D17: =IFERROR((D9-D12-D13-D15)/D14,0) | E17: =IFERROR((E9-E12-E13-E15)/E14,0)
A18: Cash payback (months after sale) | B18: months | C18: =IF(COUNTIF(Curves!$I$8:$I$68,"<0")>60,"Not paid back",COUNTIF(Curves!$I$8:$I$68,"<0")) | D18: =IF(COUNTIF(Curves!$R$8:$R$68,"<0")>60,"Not paid back",COUNTIF(Curves!$R$8:$R$68,"<0")) | E18: =IF(COUNTIF(Curves!$AA$8:$AA$68,"<0")>60,"Not paid back",COUNTIF(Curves!$AA$8:$AA$68,"<0"))
A19: Unit IRR (annualised, unlevered) | B19: % | C19: =IFERROR((1+IRR(Curves!$H$8:$H$68,0.02))^12-1,"n/a") | D19: =IFERROR((1+IRR(Curves!$Q$8:$Q$68,0.02))^12-1,"n/a") | E19: =IFERROR((1+IRR(Curves!$Z$8:$Z$68,0.02))^12-1,"n/a")
A22: Note: the active-account servicing cost excludes age 0 (sale month). Payback counts months with negative cumulative cash flow, ages 0..60. Values in month-1 prices; later cohorts scale with the price index.

Sheet FS
A1: Financial statements (monthly)
A2: LCY. Simplified IFRS-style presentation; see manual for accounting simplifications.
A4: Month # | D4: Opening | E4: =Timeline!E4 | F4: =Timeline!F4 | G4: =Timeline!G4 | H4: =Timeline!H4 | I4: =Timeline!I4 | J4: =Timeline!J4 | K4: =Timeline!K4 | L4: =Timeline!L4 | ... BL4: =Timeline!BL4
A5: Period end | E5: =Timeline!E5 | F5: =Timeline!F5 | G5: =Timeline!G5 | H5: =Timeline!H5 | I5: =Timeline!I5 | J5: =Timeline!J5 | K5: =Timeline!K5 | L5: =Timeline!L5 | ... BL5: =Timeline!BL5
A6: Year # | E6: =Timeline!E6 | F6: =Timeline!F6 | G6: =Timeline!G6 | H6: =Timeline!H6 | I6: =Timeline!I6 | J6: =Timeline!J6 | K6: =Timeline!K6 | L6: =Timeline!L6 | ... BL6: =Timeline!BL6
A8: INCOME STATEMENT
A9: Hardware revenue (cash price) | B9: LCY | C9: =SUM(E9:BL9) | E9: =Ops!E$57 | F9: =Ops!F$57 | G9: =Ops!G$57 | H9: =Ops!H$57 | I9: =Ops!I$57 | J9: =Ops!J$57 | K9: =Ops!K$57 | L9: =Ops!L$57 | ... BL9: =Ops!BL$57
A10: PAYGo financing income | B10: LCY | C10: =SUM(E10:BL10) | E10: =Ops!E$62 | F10: =Ops!F$62 | G10: =Ops!G$62 | H10: =Ops!H$62 | I10: =Ops!I$62 | J10: =Ops!J$62 | K10: =Ops!K$62 | L10: =Ops!L$62 | ... BL10: =Ops!BL$62
A11: Total revenue | B11: LCY | C11: =SUM(E11:BL11) | E11: =E9+E10 | F11: =F9+F10 | G11: =G9+G10 | H11: =H9+H10 | I11: =I9+I10 | J11: =J9+J10 | K11: =K9+K10 | L11: =L9+L10 | ... BL11: =BL9+BL10
A12: Cost of goods sold | B12: LCY | C12: =SUM(E12:BL12) | E12: =-Costs!E$8 | F12: =-Costs!F$8 | G12: =-Costs!G$8 | H12: =-Costs!H$8 | I12: =-Costs!I$8 | J12: =-Costs!J$8 | K12: =-Costs!K$8 | L12: =-Costs!L$8 | ... BL12: =-Costs!BL$8
A13: Gross profit | B13: LCY | C13: =SUM(E13:BL13) | E13: =E11+E12 | F13: =F11+F12 | G13: =G11+G12 | H13: =H11+H12 | I13: =I11+I12 | J13: =J11+J12 | K13: =K11+K12 | L13: =L11+L12 | ... BL13: =BL11+BL12
A14: Operating expenses | B14: LCY | C14: =SUM(E14:BL14) | E14: =-Costs!E$16 | F14: =-Costs!F$16 | G14: =-Costs!G$16 | H14: =-Costs!H$16 | I14: =-Costs!I$16 | J14: =-Costs!J$16 | K14: =-Costs!K$16 | L14: =-Costs!L$16 | ... BL14: =-Costs!BL$16
A15: Credit loss expense (ECL) | B15: LCY | C15: =SUM(E15:BL15) | E15: =-Ops!E$63 | F15: =-Ops!F$63 | G15: =-Ops!G$63 | H15: =-Ops!H$63 | I15: =-Ops!I$63 | J15: =-Ops!J$63 | K15: =-Ops!K$63 | L15: =-Ops!L$63 | ... BL15: =-Ops!BL$63
A16: EBITDA | B16: LCY | C16: =SUM(E16:BL16) | E16: =E13+E14+E15 | F16: =F13+F14+F15 | G16: =G13+G14+G15 | H16: =H13+H14+H15 | I16: =I13+I14+I15 | J16: =J13+J14+J15 | K16: =K13+K14+K15 | L16: =L13+L14+L15 | ... BL16: =BL13+BL14+BL15
A17: Depreciation | B17: LCY | C17: =SUM(E17:BL17) | E17: =-Costs!E$23 | F17: =-Costs!F$23 | G17: =-Costs!G$23 | H17: =-Costs!H$23 | I17: =-Costs!I$23 | J17: =-Costs!J$23 | K17: =-Costs!K$23 | L17: =-Costs!L$23 | ... BL17: =-Costs!BL$23
A18: EBIT | B18: LCY | C18: =SUM(E18:BL18) | E18: =E16+E17 | F18: =F16+F17 | G18: =G16+G17 | H18: =H16+H17 | I18: =I16+I17 | J18: =J16+J17 | K18: =K16+K17 | L18: =L16+L17 | ... BL18: =BL16+BL17
A19: Interest - USD term loan | B19: LCY | C19: =SUM(E19:BL19) | E19: =-Financing!E$16 | F19: =-Financing!F$16 | G19: =-Financing!G$16 | H19: =-Financing!H$16 | I19: =-Financing!I$16 | J19: =-Financing!J$16 | K19: =-Financing!K$16 | L19: =-Financing!L$16 | ... BL19: =-Financing!BL$16
A20: Interest - receivables facility | B20: LCY | C20: =SUM(E20:BL20) | E20: =-Financing!E$26 | F20: =-Financing!F$26 | G20: =-Financing!G$26 | H20: =-Financing!H$26 | I20: =-Financing!I$26 | J20: =-Financing!J$26 | K20: =-Financing!K$26 | L20: =-Financing!L$26 | ... BL20: =-Financing!BL$26
A21: FX (loss) / gain on USD debt | B21: LCY | C21: =SUM(E21:BL21) | E21: =-Financing!E$20 | F21: =-Financing!F$20 | G21: =-Financing!G$20 | H21: =-Financing!H$20 | I21: =-Financing!I$20 | J21: =-Financing!J$20 | K21: =-Financing!K$20 | L21: =-Financing!L$20 | ... BL21: =-Financing!BL$20
A22: Profit before tax | B22: LCY | C22: =SUM(E22:BL22) | E22: =E18+E19+E20+E21 | F22: =F18+F19+F20+F21 | G22: =G18+G19+G20+G21 | H22: =H18+H19+H20+H21 | I22: =I18+I19+I20+I21 | J22: =J18+J19+J20+J21 | K22: =K18+K19+K20+K21 | L22: =L18+L19+L20+L21 | ... BL22: =BL18+BL19+BL20+BL21
A23: memo: cumulative PBT | B23: LCY | C23: =BL23 | E23: =D23+E22 | F23: =E23+F22 | G23: =F23+G22 | H23: =G23+H22 | I23: =H23+I22 | J23: =I23+J22 | K23: =J23+K22 | L23: =K23+L22 | ... BL23: =BK23+BL22
A24: memo: running max of cumulative PBT | B24: LCY | C24: =BL24 | E24: =MAX(D24,E23) | F24: =MAX(E24,F23) | G24: =MAX(F24,G23) | H24: =MAX(G24,H23) | I24: =MAX(H24,I23) | J24: =MAX(I24,J23) | K24: =MAX(J24,K23) | L24: =MAX(K24,L23) | ... BL24: =MAX(BK24,BL23)
A25: Income tax | B25: LCY | C25: =SUM(E25:BL25) | E25: =-Inputs!$C$12*(MAX(0,E24)-MAX(0,D24)) | F25: =-Inputs!$C$12*(MAX(0,F24)-MAX(0,E24)) | G25: =-Inputs!$C$12*(MAX(0,G24)-MAX(0,F24)) | H25: =-Inputs!$C$12*(MAX(0,H24)-MAX(0,G24)) | I25: =-Inputs!$C$12*(MAX(0,I24)-MAX(0,H24)) | J25: =-Inputs!$C$12*(MAX(0,J24)-MAX(0,I24)) | K25: =-Inputs!$C$12*(MAX(0,K24)-MAX(0,J24)) | L25: =-Inputs!$C$12*(MAX(0,L24)-MAX(0,K24)) | ... BL25: =-Inputs!$C$12*(MAX(0,BL24)-MAX(0,BK24))
A26: Net income | B26: LCY | C26: =SUM(E26:BL26) | E26: =E22+E25 | F26: =F22+F25 | G26: =G22+G25 | H26: =H22+H25 | I26: =I22+I25 | J26: =J22+J25 | K26: =K22+K25 | L26: =L22+L25 | ... BL26: =BL22+BL25
A28: BALANCE SHEET
A29: Cash | B29: LCY | C29: =BL29 | E29: =E60 | F29: =F60 | G29: =G60 | H29: =H60 | I29: =I60 | J29: =J60 | K29: =K60 | L29: =L60 | ... BL29: =BL60
A30: PAYGo receivables - gross | B30: LCY | C30: =BL30 | E30: =D30+Ops!E$58+Ops!E$62-Ops!E$60-Ops!E$61 | F30: =E30+Ops!F$58+Ops!F$62-Ops!F$60-Ops!F$61 | G30: =F30+Ops!G$58+Ops!G$62-Ops!G$60-Ops!G$61 | H30: =G30+Ops!H$58+Ops!H$62-Ops!H$60-Ops!H$61 | I30: =H30+Ops!I$58+Ops!I$62-Ops!I$60-Ops!I$61 | J30: =I30+Ops!J$58+Ops!J$62-Ops!J$60-Ops!J$61 | K30: =J30+Ops!K$58+Ops!K$62-Ops!K$60-Ops!K$61 | L30: =K30+Ops!L$58+Ops!L$62-Ops!L$60-Ops!L$61 | ... BL30: =BK30+Ops!BL$58+Ops!BL$62-Ops!BL$60-Ops!BL$61
A31: Loss allowance (ECL provision) | B31: LCY | C31: =BL31 | E31: =D31-Ops!E$63+Ops!E$61 | F31: =E31-Ops!F$63+Ops!F$61 | G31: =F31-Ops!G$63+Ops!G$61 | H31: =G31-Ops!H$63+Ops!H$61 | I31: =H31-Ops!I$63+Ops!I$61 | J31: =I31-Ops!J$63+Ops!J$61 | K31: =J31-Ops!K$63+Ops!K$61 | L31: =K31-Ops!L$63+Ops!L$61 | ... BL31: =BK31-Ops!BL$63+Ops!BL$61
A32: PAYGo receivables - net | B32: LCY | C32: =BL32 | E32: =E30+E31 | F32: =F30+F31 | G32: =G30+G31 | H32: =H30+H31 | I32: =I30+I31 | J32: =J30+J31 | K32: =K30+K31 | L32: =L30+L31 | ... BL32: =BL30+BL31
A33: Inventory | B33: LCY | C33: =BL33 | E33: =Costs!E$18 | F33: =Costs!F$18 | G33: =Costs!G$18 | H33: =Costs!H$18 | I33: =Costs!I$18 | J33: =Costs!J$18 | K33: =Costs!K$18 | L33: =Costs!L$18 | ... BL33: =Costs!BL$18
A34: Net fixed assets | B34: LCY | C34: =BL34 | E34: =Costs!E$24 | F34: =Costs!F$24 | G34: =Costs!G$24 | H34: =Costs!H$24 | I34: =Costs!I$24 | J34: =Costs!J$24 | K34: =Costs!K$24 | L34: =Costs!L$24 | ... BL34: =Costs!BL$24
A35: Total assets | B35: LCY | C35: =BL35 | E35: =E29+E32+E33+E34 | F35: =F29+F32+F33+F34 | G35: =G29+G32+G33+G34 | H35: =H29+H32+H33+H34 | I35: =I29+I32+I33+I34 | J35: =J29+J32+J33+J34 | K35: =K29+K32+K33+K34 | L35: =L29+L32+L33+L34 | ... BL35: =BL29+BL32+BL33+BL34
A36: Supplier payables | B36: LCY | C36: =BL36 | E36: =Costs!E$20 | F36: =Costs!F$20 | G36: =Costs!G$20 | H36: =Costs!H$20 | I36: =Costs!I$20 | J36: =Costs!J$20 | K36: =Costs!K$20 | L36: =Costs!L$20 | ... BL36: =Costs!BL$20
A37: USD term loan (in LCY) | B37: LCY | C37: =BL37 | E37: =Financing!E$19 | F37: =Financing!F$19 | G37: =Financing!G$19 | H37: =Financing!H$19 | I37: =Financing!I$19 | J37: =Financing!J$19 | K37: =Financing!K$19 | L37: =Financing!L$19 | ... BL37: =Financing!BL$19
A38: Receivables facility | B38: LCY | C38: =BL38 | E38: =Financing!E$24 | F38: =Financing!F$24 | G38: =Financing!G$24 | H38: =Financing!H$24 | I38: =Financing!I$24 | J38: =Financing!J$24 | K38: =Financing!K$24 | L38: =Financing!L$24 | ... BL38: =Financing!BL$24
A39: Total liabilities | B39: LCY | C39: =BL39 | E39: =E36+E37+E38 | F39: =F36+F37+F38 | G39: =G36+G37+G38 | H39: =H36+H37+H38 | I39: =I36+I37+I38 | J39: =J36+J37+J38 | K39: =K36+K37+K38 | L39: =L36+L37+L38 | ... BL39: =BL36+BL37+BL38
A40: Share capital | B40: LCY | C40: =BL40 | E40: =Financing!E$11 | F40: =Financing!F$11 | G40: =Financing!G$11 | H40: =Financing!H$11 | I40: =Financing!I$11 | J40: =Financing!J$11 | K40: =Financing!K$11 | L40: =Financing!L$11 | ... BL40: =Financing!BL$11
A41: Retained earnings | B41: LCY | C41: =BL41 | E41: =D41+E26 | F41: =E41+F26 | G41: =F41+G26 | H41: =G41+H26 | I41: =H41+I26 | J41: =I41+J26 | K41: =J41+K26 | L41: =K41+L26 | ... BL41: =BK41+BL26
A42: Total equity | B42: LCY | C42: =BL42 | E42: =E40+E41 | F42: =F40+F41 | G42: =G40+G41 | H42: =H40+H41 | I42: =I40+I41 | J42: =J40+J41 | K42: =K40+K41 | L42: =L40+L41 | ... BL42: =BL40+BL41
A43: Total liabilities & equity | B43: LCY | C43: =BL43 | E43: =E39+E42 | F43: =F39+F42 | G43: =G39+G42 | H43: =H39+H42 | I43: =I39+I42 | J43: =J39+J42 | K43: =K39+K42 | L43: =L39+L42 | ... BL43: =BL39+BL42
A44: Balance check (should be 0) | B44: LCY | C44: =MAX(E44:BL44) | E44: =ROUND(E35-E43,0) | F44: =ROUND(F35-F43,0) | G44: =ROUND(G35-G43,0) | H44: =ROUND(H35-H43,0) | I44: =ROUND(I35-I43,0) | J44: =ROUND(J35-J43,0) | K44: =ROUND(K35-K43,0) | L44: =ROUND(L35-L43,0) | ... BL44: =ROUND(BL35-BL43,0)
A46: CASH FLOW STATEMENT
A47: Net income | B47: LCY | C47: =SUM(E47:BL47) | E47: =E26 | F47: =F26 | G47: =G26 | H47: =H26 | I47: =I26 | J47: =J26 | K47: =K26 | L47: =L26 | ... BL47: =BL26
A48: Add back: depreciation | B48: LCY | C48: =SUM(E48:BL48) | E48: =-E17 | F48: =-F17 | G48: =-G17 | H48: =-H17 | I48: =-I17 | J48: =-J17 | K48: =-K17 | L48: =-L17 | ... BL48: =-BL17
A49: Add back: unrealised FX loss | B49: LCY | C49: =SUM(E49:BL49) | E49: =-E21 | F49: =-F21 | G49: =-G21 | H49: =-H21 | I49: =-I21 | J49: =-J21 | K49: =-K21 | L49: =-L21 | ... BL49: =-BL21
A50: (Increase) / decrease in net receivables | B50: LCY | C50: =SUM(E50:BL50) | E50: =-(E32-D32) | F50: =-(F32-E32) | G50: =-(G32-F32) | H50: =-(H32-G32) | I50: =-(I32-H32) | J50: =-(J32-I32) | K50: =-(K32-J32) | L50: =-(L32-K32) | ... BL50: =-(BL32-BK32)
A51: (Increase) / decrease in inventory | B51: LCY | C51: =SUM(E51:BL51) | E51: =-(E33-D33) | F51: =-(F33-E33) | G51: =-(G33-F33) | H51: =-(H33-G33) | I51: =-(I33-H33) | J51: =-(J33-I33) | K51: =-(K33-J33) | L51: =-(L33-K33) | ... BL51: =-(BL33-BK33)
A52: Increase / (decrease) in payables | B52: LCY | C52: =SUM(E52:BL52) | E52: =E36-D36 | F52: =F36-E36 | G52: =G36-F36 | H52: =H36-G36 | I52: =I36-H36 | J52: =J36-I36 | K52: =K36-J36 | L52: =L36-K36 | ... BL52: =BL36-BK36
A53: Cash flow from operations | B53: LCY | C53: =SUM(E53:BL53) | E53: =SUM(E47:E52) | F53: =SUM(F47:F52) | G53: =SUM(G47:G52) | H53: =SUM(H47:H52) | I53: =SUM(I47:I52) | J53: =SUM(J47:J52) | K53: =SUM(K47:K52) | L53: =SUM(L47:L52) | ... BL53: =SUM(BL47:BL52)
A54: Cash flow from investing (capex) | B54: LCY | C54: =SUM(E54:BL54) | E54: =-Costs!E$22 | F54: =-Costs!F$22 | G54: =-Costs!G$22 | H54: =-Costs!H$22 | I54: =-Costs!I$22 | J54: =-Costs!J$22 | K54: =-Costs!K$22 | L54: =-Costs!L$22 | ... BL54: =-Costs!BL$22
A55: Term loan drawdown / (repayment) | B55: LCY | C55: =SUM(E55:BL55) | E55: =Financing!E$17-Financing!E$18 | F55: =Financing!F$17-Financing!F$18 | G55: =Financing!G$17-Financing!G$18 | H55: =Financing!H$17-Financing!H$18 | I55: =Financing!I$17-Financing!I$18 | J55: =Financing!J$17-Financing!J$18 | K55: =Financing!K$17-Financing!K$18 | L55: =Financing!L$17-Financing!L$18 | ... BL55: =Financing!BL$17-Financing!BL$18
A56: Receivables facility drawdown / (repayment) | B56: LCY | C56: =SUM(E56:BL56) | E56: =Financing!E$25 | F56: =Financing!F$25 | G56: =Financing!G$25 | H56: =Financing!H$25 | I56: =Financing!I$25 | J56: =Financing!J$25 | K56: =Financing!K$25 | L56: =Financing!L$25 | ... BL56: =Financing!BL$25
A57: Equity - initial / scheduled | B57: LCY | C57: =SUM(E57:BL57) | E57: =Financing!E$9 | F57: =Financing!F$9 | G57: =Financing!G$9 | H57: =Financing!H$9 | I57: =Financing!I$9 | J57: =Financing!J$9 | K57: =Financing!K$9 | L57: =Financing!L$9 | ... BL57: =Financing!BL$9
A58: Cash before equity top-up | B58: LCY | C58: =BL58 | E58: =D60+E53+E54+E55+E56+E57 | F58: =E60+F53+F54+F55+F56+F57 | G58: =F60+G53+G54+G55+G56+G57 | H58: =G60+H53+H54+H55+H56+H57 | I58: =H60+I53+I54+I55+I56+I57 | J58: =I60+J53+J54+J55+J56+J57 | K58: =J60+K53+K54+K55+K56+K57 | L58: =K60+L53+L54+L55+L56+L57 | ... BL58: =BK60+BL53+BL54+BL55+BL56+BL57
A59: Equity top-up to maintain minimum cash | B59: LCY | C59: =SUM(E59:BL59) | E59: =MAX(0,Inputs!$C$35-E58) | F59: =MAX(0,Inputs!$C$35-F58) | G59: =MAX(0,Inputs!$C$35-G58) | H59: =MAX(0,Inputs!$C$35-H58) | I59: =MAX(0,Inputs!$C$35-I58) | J59: =MAX(0,Inputs!$C$35-J58) | K59: =MAX(0,Inputs!$C$35-K58) | L59: =MAX(0,Inputs!$C$35-L58) | ... BL59: =MAX(0,Inputs!$C$35-BL58)
A60: Closing cash | B60: LCY | C60: =BL60 | E60: =E58+E59 | F60: =F58+F59 | G60: =G58+G59 | H60: =H58+H59 | I60: =I58+I59 | J60: =J58+J59 | K60: =K58+K59 | L60: =L58+L59 | ... BL60: =BL58+BL59

Sheet Ops
A1: Operations & portfolio
A2: Per product, then totals. LCY unless stated.
A4: Month # | D4: Opening | E4: =Timeline!E4 | F4: =Timeline!F4 | G4: =Timeline!G4 | H4: =Timeline!H4 | I4: =Timeline!I4 | J4: =Timeline!J4 | K4: =Timeline!K4 | L4: =Timeline!L4 | ... BL4: =Timeline!BL4
A5: Period end | E5: =Timeline!E5 | F5: =Timeline!F5 | G5: =Timeline!G5 | H5: =Timeline!H5 | I5: =Timeline!I5 | J5: =Timeline!J5 | K5: =Timeline!K5 | L5: =Timeline!L5 | ... BL5: =Timeline!BL5
A6: Year # | E6: =Timeline!E6 | F6: =Timeline!F6 | G6: =Timeline!G6 | H6: =Timeline!H6 | I6: =Timeline!I6 | J6: =Timeline!J6 | K6: =Timeline!K6 | L6: =Timeline!L6 | ... BL6: =Timeline!BL6
A8: =Products!$C$5
A9: Units sold | B9: units | C9: =SUM(E9:BL9) | E9: =Timeline!E$11*Products!$C$13 | F9: =Timeline!F$11*Products!$C$13 | G9: =Timeline!G$11*Products!$C$13 | H9: =Timeline!H$11*Products!$C$13 | I9: =Timeline!I$11*Products!$C$13 | J9: =Timeline!J$11*Products!$C$13 | K9: =Timeline!K$11*Products!$C$13 | L9: =Timeline!L$11*Products!$C$13 | ... BL9: =Timeline!BL$11*Products!$C$13
A10: Price-indexed units (units x price index) | B10: units | C10: =SUM(E10:BL10) | E10: =E$9*Timeline!E$10 | F10: =F$9*Timeline!F$10 | G10: =G$9*Timeline!G$10 | H10: =H$9*Timeline!H$10 | I10: =I$9*Timeline!I$10 | J10: =J$9*Timeline!J$10 | K10: =K$9*Timeline!K$10 | L10: =L$9*Timeline!L$10 | ... BL10: =BL$9*Timeline!BL$10
A11: Deposits collected | B11: LCY | C11: =SUM(E11:BL11) | E11: =E$10*Products!$C$7 | F11: =F$10*Products!$C$7 | G11: =G$10*Products!$C$7 | H11: =H$10*Products!$C$7 | I11: =I$10*Products!$C$7 | J11: =J$10*Products!$C$7 | K11: =K$10*Products!$C$7 | L11: =L$10*Products!$C$7 | ... BL11: =BL$10*Products!$C$7
A12: Hardware revenue (cash price) | B12: LCY | C12: =SUM(E12:BL12) | E12: =E$10*Products!$C$6 | F12: =F$10*Products!$C$6 | G12: =G$10*Products!$C$6 | H12: =H$10*Products!$C$6 | I12: =I$10*Products!$C$6 | J12: =J$10*Products!$C$6 | K12: =K$10*Products!$C$6 | L12: =L$10*Products!$C$6 | ... BL12: =BL$10*Products!$C$6
A13: New receivables originated (cash price - deposit) | B13: LCY | C13: =SUM(E13:BL13) | E13: =E$10*Products!$C$22 | F13: =F$10*Products!$C$22 | G13: =G$10*Products!$C$22 | H13: =H$10*Products!$C$22 | I13: =I$10*Products!$C$22 | J13: =J$10*Products!$C$22 | K13: =K$10*Products!$C$22 | L13: =L$10*Products!$C$22 | ... BL13: =BL$10*Products!$C$22
A14: Instalments due | B14: LCY | C14: =SUM(E14:BL14) | E14: =Products!$C$18*SUMIFS($E$10:$BL$10,Timeline!$E$4:$BL$4,">="&(E$4-Products!$C$9),Timeline!$E$4:$BL$4,"<="&(E$4-1)) | F14: =Products!$C$18*SUMIFS($E$10:$BL$10,Timeline!$E$4:$BL$4,">="&(F$4-Products!$C$9),Timeline!$E$4:$BL$4,"<="&(F$4-1)) | G14: =Products!$C$18*SUMIFS($E$10:$BL$10,Timeline!$E$4:$BL$4,">="&(G$4-Products!$C$9),Timeline!$E$4:$BL$4,"<="&(G$4-1)) | H14: =Products!$C$18*SUMIFS($E$10:$BL$10,Timeline!$E$4:$BL$4,">="&(H$4-Products!$C$9),Timeline!$E$4:$BL$4,"<="&(H$4-1)) | I14: =Products!$C$18*SUMIFS($E$10:$BL$10,Timeline!$E$4:$BL$4,">="&(I$4-Products!$C$9),Timeline!$E$4:$BL$4,"<="&(I$4-1)) | J14: =Products!$C$18*SUMIFS($E$10:$BL$10,Timeline!$E$4:$BL$4,">="&(J$4-Products!$C$9),Timeline!$E$4:$BL$4,"<="&(J$4-1)) | K14: =Products!$C$18*SUMIFS($E$10:$BL$10,Timeline!$E$4:$BL$4,">="&(K$4-Products!$C$9),Timeline!$E$4:$BL$4,"<="&(K$4-1)) | L14: =Products!$C$18*SUMIFS($E$10:$BL$10,Timeline!$E$4:$BL$4,">="&(L$4-Products!$C$9),Timeline!$E$4:$BL$4,"<="&(L$4-1)) | ... BL14: =Products!$C$18*SUMIFS($E$10:$BL$10,Timeline!$E$4:$BL$4,">="&(BL$4-Products!$C$9),Timeline!$E$4:$BL$4,"<="&(BL$4-1))
A15: Instalments collected | B15: LCY | C15: =SUM(E15:BL15) | E15: =Cohort_P1!E$9 | F15: =Cohort_P1!F$9 | G15: =Cohort_P1!G$9 | H15: =Cohort_P1!H$9 | I15: =Cohort_P1!I$9 | J15: =Cohort_P1!J$9 | K15: =Cohort_P1!K$9 | L15: =Cohort_P1!L$9 | ... BL15: =Cohort_P1!BL$9
A16: Missed instalments written off | B16: LCY | C16: =SUM(E16:BL16) | E16: =E$14-E$15 | F16: =F$14-F$15 | G16: =G$14-G$15 | H16: =H$14-H$15 | I16: =I$14-I$15 | J16: =J$14-J$15 | K16: =K$14-K$15 | L16: =L$14-L$15 | ... BL16: =BL$14-BL$15
A17: PAYGo financing income (straight-line over tenor) | B17: LCY | C17: =SUM(E17:BL17) | E17: =IF(Products!$C$9=0,0,Products!$C$20/Products!$C$9*SUMIFS($E$10:$BL$10,Timeline!$E$4:$BL$4,">="&(E$4-Products!$C$9),Timeline!$E$4:$BL$4,"<="&(E$4-1))) | F17: =IF(Products!$C$9=0,0,Products!$C$20/Products!$C$9*SUMIFS($E$10:$BL$10,Timeline!$E$4:$BL$4,">="&(F$4-Products!$C$9),Timeline!$E$4:$BL$4,"<="&(F$4-1))) | G17: =IF(Products!$C$9=0,0,Products!$C$20/Products!$C$9*SUMIFS($E$10:$BL$10,Timeline!$E$4:$BL$4,">="&(G$4-Products!$C$9),Timeline!$E$4:$BL$4,"<="&(G$4-1))) | H17: =IF(Products!$C$9=0,0,Products!$C$20/Products!$C$9*SUMIFS($E$10:$BL$10,Timeline!$E$4:$BL$4,">="&(H$4-Products!$C$9),Timeline!$E$4:$BL$4,"<="&(H$4-1))) | I17: =IF(Products!$C$9=0,0,Products!$C$20/Products!$C$9*SUMIFS($E$10:$BL$10,Timeline!$E$4:$BL$4,">="&(I$4-Products!$C$9),Timeline!$E$4:$BL$4,"<="&(I$4-1))) | J17: =IF(Products!$C$9=0,0,Products!$C$20/Products!$C$9*SUMIFS($E$10:$BL$10,Timeline!$E$4:$BL$4,">="&(J$4-Products!$C$9),Timeline!$E$4:$BL$4,"<="&(J$4-1))) | K17: =IF(Products!$C$9=0,0,Products!$C$20/Products!$C$9*SUMIFS($E$10:$BL$10,Timeline!$E$4:$BL$4,">="&(K$4-Products!$C$9),Timeline!$E$4:$BL$4,"<="&(K$4-1))) | L17: =IF(Products!$C$9=0,0,Products!$C$20/Products!$C$9*SUMIFS($E$10:$BL$10,Timeline!$E$4:$BL$4,">="&(L$4-Products!$C$9),Timeline!$E$4:$BL$4,"<="&(L$4-1))) | ... BL17: =IF(Products!$C$9=0,0,Products!$C$20/Products!$C$9*SUMIFS($E$10:$BL$10,Timeline!$E$4:$BL$4,">="&(BL$4-Products!$C$9),Timeline!$E$4:$BL$4,"<="&(BL$4-1)))
A18: Expected credit loss charge at origination | B18: LCY | C18: =SUM(E18:BL18) | E18: =E$10*Curves!$E$70 | F18: =F$10*Curves!$E$70 | G18: =G$10*Curves!$E$70 | H18: =H$10*Curves!$E$70 | I18: =I$10*Curves!$E$70 | J18: =J$10*Curves!$E$70 | K18: =K$10*Curves!$E$70 | L18: =L$10*Curves!$E$70 | ... BL18: =BL$10*Curves!$E$70
A19: Active (paying, in-tenor) accounts | B19: accounts | C19: =BL19 | E19: =Cohort_P1!E$72 | F19: =Cohort_P1!F$72 | G19: =Cohort_P1!G$72 | H19: =Cohort_P1!H$72 | I19: =Cohort_P1!I$72 | J19: =Cohort_P1!J$72 | K19: =Cohort_P1!K$72 | L19: =Cohort_P1!L$72 | ... BL19: =Cohort_P1!BL$72
A20: Receivables at risk (carrying amount of accounts that stopped paying) | B20: LCY | C20: =BL20 | E20: =Cohort_P1!E$135 | F20: =Cohort_P1!F$135 | G20: =Cohort_P1!G$135 | H20: =Cohort_P1!H$135 | I20: =Cohort_P1!I$135 | J20: =Cohort_P1!J$135 | K20: =Cohort_P1!K$135 | L20: =Cohort_P1!L$135 | ... BL20: =Cohort_P1!BL$135
A21: Landed hardware cost of units sold | B21: LCY | C21: =SUM(E21:BL21) | E21: =E$9*Products!$C$10*(1+Inputs!$C$28)*Timeline!E$8*Scenarios!$G$9 | F21: =F$9*Products!$C$10*(1+Inputs!$C$28)*Timeline!F$8*Scenarios!$G$9 | G21: =G$9*Products!$C$10*(1+Inputs!$C$28)*Timeline!G$8*Scenarios!$G$9 | H21: =H$9*Products!$C$10*(1+Inputs!$C$28)*Timeline!H$8*Scenarios!$G$9 | I21: =I$9*Products!$C$10*(1+Inputs!$C$28)*Timeline!I$8*Scenarios!$G$9 | J21: =J$9*Products!$C$10*(1+Inputs!$C$28)*Timeline!J$8*Scenarios!$G$9 | K21: =K$9*Products!$C$10*(1+Inputs!$C$28)*Timeline!K$8*Scenarios!$G$9 | L21: =L$9*Products!$C$10*(1+Inputs!$C$28)*Timeline!L$8*Scenarios!$G$9 | ... BL21: =BL$9*Products!$C$10*(1+Inputs!$C$28)*Timeline!BL$8*Scenarios!$G$9
A23: =Products!$D$5
A24: Units sold | B24: units | C24: =SUM(E24:BL24) | E24: =Timeline!E$11*Products!$D$13 | F24: =Timeline!F$11*Products!$D$13 | G24: =Timeline!G$11*Products!$D$13 | H24: =Timeline!H$11*Products!$D$13 | I24: =Timeline!I$11*Products!$D$13 | J24: =Timeline!J$11*Products!$D$13 | K24: =Timeline!K$11*Products!$D$13 | L24: =Timeline!L$11*Products!$D$13 | ... BL24: =Timeline!BL$11*Products!$D$13
A25: Price-indexed units (units x price index) | B25: units | C25: =SUM(E25:BL25) | E25: =E$24*Timeline!E$10 | F25: =F$24*Timeline!F$10 | G25: =G$24*Timeline!G$10 | H25: =H$24*Timeline!H$10 | I25: =I$24*Timeline!I$10 | J25: =J$24*Timeline!J$10 | K25: =K$24*Timeline!K$10 | L25: =L$24*Timeline!L$10 | ... BL25: =BL$24*Timeline!BL$10
A26: Deposits collected | B26: LCY | C26: =SUM(E26:BL26) | E26: =E$25*Products!$D$7 | F26: =F$25*Products!$D$7 | G26: =G$25*Products!$D$7 | H26: =H$25*Products!$D$7 | I26: =I$25*Products!$D$7 | J26: =J$25*Products!$D$7 | K26: =K$25*Products!$D$7 | L26: =L$25*Products!$D$7 | ... BL26: =BL$25*Products!$D$7
A27: Hardware revenue (cash price) | B27: LCY | C27: =SUM(E27:BL27) | E27: =E$25*Products!$D$6 | F27: =F$25*Products!$D$6 | G27: =G$25*Products!$D$6 | H27: =H$25*Products!$D$6 | I27: =I$25*Products!$D$6 | J27: =J$25*Products!$D$6 | K27: =K$25*Products!$D$6 | L27: =L$25*Products!$D$6 | ... BL27: =BL$25*Products!$D$6
A28: New receivables originated (cash price - deposit) | B28: LCY | C28: =SUM(E28:BL28) | E28: =E$25*Products!$D$22 | F28: =F$25*Products!$D$22 | G28: =G$25*Products!$D$22 | H28: =H$25*Products!$D$22 | I28: =I$25*Products!$D$22 | J28: =J$25*Products!$D$22 | K28: =K$25*Products!$D$22 | L28: =L$25*Products!$D$22 | ... BL28: =BL$25*Products!$D$22
A29: Instalments due | B29: LCY | C29: =SUM(E29:BL29) | E29: =Products!$D$18*SUMIFS($E$25:$BL$25,Timeline!$E$4:$BL$4,">="&(E$4-Products!$D$9),Timeline!$E$4:$BL$4,"<="&(E$4-1)) | F29: =Products!$D$18*SUMIFS($E$25:$BL$25,Timeline!$E$4:$BL$4,">="&(F$4-Products!$D$9),Timeline!$E$4:$BL$4,"<="&(F$4-1)) | G29: =Products!$D$18*SUMIFS($E$25:$BL$25,Timeline!$E$4:$BL$4,">="&(G$4-Products!$D$9),Timeline!$E$4:$BL$4,"<="&(G$4-1)) | H29: =Products!$D$18*SUMIFS($E$25:$BL$25,Timeline!$E$4:$BL$4,">="&(H$4-Products!$D$9),Timeline!$E$4:$BL$4,"<="&(H$4-1)) | I29: =Products!$D$18*SUMIFS($E$25:$BL$25,Timeline!$E$4:$BL$4,">="&(I$4-Products!$D$9),Timeline!$E$4:$BL$4,"<="&(I$4-1)) | J29: =Products!$D$18*SUMIFS($E$25:$BL$25,Timeline!$E$4:$BL$4,">="&(J$4-Products!$D$9),Timeline!$E$4:$BL$4,"<="&(J$4-1)) | K29: =Products!$D$18*SUMIFS($E$25:$BL$25,Timeline!$E$4:$BL$4,">="&(K$4-Products!$D$9),Timeline!$E$4:$BL$4,"<="&(K$4-1)) | L29: =Products!$D$18*SUMIFS($E$25:$BL$25,Timeline!$E$4:$BL$4,">="&(L$4-Products!$D$9),Timeline!$E$4:$BL$4,"<="&(L$4-1)) | ... BL29: =Products!$D$18*SUMIFS($E$25:$BL$25,Timeline!$E$4:$BL$4,">="&(BL$4-Products!$D$9),Timeline!$E$4:$BL$4,"<="&(BL$4-1))
A30: Instalments collected | B30: LCY | C30: =SUM(E30:BL30) | E30: =Cohort_P2!E$9 | F30: =Cohort_P2!F$9 | G30: =Cohort_P2!G$9 | H30: =Cohort_P2!H$9 | I30: =Cohort_P2!I$9 | J30: =Cohort_P2!J$9 | K30: =Cohort_P2!K$9 | L30: =Cohort_P2!L$9 | ... BL30: =Cohort_P2!BL$9
A31: Missed instalments written off | B31: LCY | C31: =SUM(E31:BL31) | E31: =E$29-E$30 | F31: =F$29-F$30 | G31: =G$29-G$30 | H31: =H$29-H$30 | I31: =I$29-I$30 | J31: =J$29-J$30 | K31: =K$29-K$30 | L31: =L$29-L$30 | ... BL31: =BL$29-BL$30
A32: PAYGo financing income (straight-line over tenor) | B32: LCY | C32: =SUM(E32:BL32) | E32: =IF(Products!$D$9=0,0,Products!$D$20/Products!$D$9*SUMIFS($E$25:$BL$25,Timeline!$E$4:$BL$4,">="&(E$4-Products!$D$9),Timeline!$E$4:$BL$4,"<="&(E$4-1))) | F32: =IF(Products!$D$9=0,0,Products!$D$20/Products!$D$9*SUMIFS($E$25:$BL$25,Timeline!$E$4:$BL$4,">="&(F$4-Products!$D$9),Timeline!$E$4:$BL$4,"<="&(F$4-1))) | G32: =IF(Products!$D$9=0,0,Products!$D$20/Products!$D$9*SUMIFS($E$25:$BL$25,Timeline!$E$4:$BL$4,">="&(G$4-Products!$D$9),Timeline!$E$4:$BL$4,"<="&(G$4-1))) | H32: =IF(Products!$D$9=0,0,Products!$D$20/Products!$D$9*SUMIFS($E$25:$BL$25,Timeline!$E$4:$BL$4,">="&(H$4-Products!$D$9),Timeline!$E$4:$BL$4,"<="&(H$4-1))) | I32: =IF(Products!$D$9=0,0,Products!$D$20/Products!$D$9*SUMIFS($E$25:$BL$25,Timeline!$E$4:$BL$4,">="&(I$4-Products!$D$9),Timeline!$E$4:$BL$4,"<="&(I$4-1))) | J32: =IF(Products!$D$9=0,0,Products!$D$20/Products!$D$9*SUMIFS($E$25:$BL$25,Timeline!$E$4:$BL$4,">="&(J$4-Products!$D$9),Timeline!$E$4:$BL$4,"<="&(J$4-1))) | K32: =IF(Products!$D$9=0,0,Products!$D$20/Products!$D$9*SUMIFS($E$25:$BL$25,Timeline!$E$4:$BL$4,">="&(K$4-Products!$D$9),Timeline!$E$4:$BL$4,"<="&(K$4-1))) | L32: =IF(Products!$D$9=0,0,Products!$D$20/Products!$D$9*SUMIFS($E$25:$BL$25,Timeline!$E$4:$BL$4,">="&(L$4-Products!$D$9),Timeline!$E$4:$BL$4,"<="&(L$4-1))) | ... BL32: =IF(Products!$D$9=0,0,Products!$D$20/Products!$D$9*SUMIFS($E$25:$BL$25,Timeline!$E$4:$BL$4,">="&(BL$4-Products!$D$9),Timeline!$E$4:$BL$4,"<="&(BL$4-1)))
A33: Expected credit loss charge at origination | B33: LCY | C33: =SUM(E33:BL33) | E33: =E$25*Curves!$N$70 | F33: =F$25*Curves!$N$70 | G33: =G$25*Curves!$N$70 | H33: =H$25*Curves!$N$70 | I33: =I$25*Curves!$N$70 | J33: =J$25*Curves!$N$70 | K33: =K$25*Curves!$N$70 | L33: =L$25*Curves!$N$70 | ... BL33: =BL$25*Curves!$N$70
A34: Active (paying, in-tenor) accounts | B34: accounts | C34: =BL34 | E34: =Cohort_P2!E$72 | F34: =Cohort_P2!F$72 | G34: =Cohort_P2!G$72 | H34: =Cohort_P2!H$72 | I34: =Cohort_P2!I$72 | J34: =Cohort_P2!J$72 | K34: =Cohort_P2!K$72 | L34: =Cohort_P2!L$72 | ... BL34: =Cohort_P2!BL$72
A35: Receivables at risk (carrying amount of accounts that stopped paying) | B35: LCY | C35: =BL35 | E35: =Cohort_P2!E$135 | F35: =Cohort_P2!F$135 | G35: =Cohort_P2!G$135 | H35: =Cohort_P2!H$135 | I35: =Cohort_P2!I$135 | J35: =Cohort_P2!J$135 | K35: =Cohort_P2!K$135 | L35: =Cohort_P2!L$135 | ... BL35: =Cohort_P2!BL$135
A36: Landed hardware cost of units sold | B36: LCY | C36: =SUM(E36:BL36) | E36: =E$24*Products!$D$10*(1+Inputs!$C$28)*Timeline!E$8*Scenarios!$G$9 | F36: =F$24*Products!$D$10*(1+Inputs!$C$28)*Timeline!F$8*Scenarios!$G$9 | G36: =G$24*Products!$D$10*(1+Inputs!$C$28)*Timeline!G$8*Scenarios!$G$9 | H36: =H$24*Products!$D$10*(1+Inputs!$C$28)*Timeline!H$8*Scenarios!$G$9 | I36: =I$24*Products!$D$10*(1+Inputs!$C$28)*Timeline!I$8*Scenarios!$G$9 | J36: =J$24*Products!$D$10*(1+Inputs!$C$28)*Timeline!J$8*Scenarios!$G$9 | K36: =K$24*Products!$D$10*(1+Inputs!$C$28)*Timeline!K$8*Scenarios!$G$9 | L36: =L$24*Products!$D$10*(1+Inputs!$C$28)*Timeline!L$8*Scenarios!$G$9 | ... BL36: =BL$24*Products!$D$10*(1+Inputs!$C$28)*Timeline!BL$8*Scenarios!$G$9
A38: =Products!$E$5
A39: Units sold | B39: units | C39: =SUM(E39:BL39) | E39: =Timeline!E$11*Products!$E$13 | F39: =Timeline!F$11*Products!$E$13 | G39: =Timeline!G$11*Products!$E$13 | H39: =Timeline!H$11*Products!$E$13 | I39: =Timeline!I$11*Products!$E$13 | J39: =Timeline!J$11*Products!$E$13 | K39: =Timeline!K$11*Products!$E$13 | L39: =Timeline!L$11*Products!$E$13 | ... BL39: =Timeline!BL$11*Products!$E$13
A40: Price-indexed units (units x price index) | B40: units | C40: =SUM(E40:BL40) | E40: =E$39*Timeline!E$10 | F40: =F$39*Timeline!F$10 | G40: =G$39*Timeline!G$10 | H40: =H$39*Timeline!H$10 | I40: =I$39*Timeline!I$10 | J40: =J$39*Timeline!J$10 | K40: =K$39*Timeline!K$10 | L40: =L$39*Timeline!L$10 | ... BL40: =BL$39*Timeline!BL$10
A41: Deposits collected | B41: LCY | C41: =SUM(E41:BL41) | E41: =E$40*Products!$E$7 | F41: =F$40*Products!$E$7 | G41: =G$40*Products!$E$7 | H41: =H$40*Products!$E$7 | I41: =I$40*Products!$E$7 | J41: =J$40*Products!$E$7 | K41: =K$40*Products!$E$7 | L41: =L$40*Products!$E$7 | ... BL41: =BL$40*Products!$E$7
A42: Hardware revenue (cash price) | B42: LCY | C42: =SUM(E42:BL42) | E42: =E$40*Products!$E$6 | F42: =F$40*Products!$E$6 | G42: =G$40*Products!$E$6 | H42: =H$40*Products!$E$6 | I42: =I$40*Products!$E$6 | J42: =J$40*Products!$E$6 | K42: =K$40*Products!$E$6 | L42: =L$40*Products!$E$6 | ... BL42: =BL$40*Products!$E$6
A43: New receivables originated (cash price - deposit) | B43: LCY | C43: =SUM(E43:BL43) | E43: =E$40*Products!$E$22 | F43: =F$40*Products!$E$22 | G43: =G$40*Products!$E$22 | H43: =H$40*Products!$E$22 | I43: =I$40*Products!$E$22 | J43: =J$40*Products!$E$22 | K43: =K$40*Products!$E$22 | L43: =L$40*Products!$E$22 | ... BL43: =BL$40*Products!$E$22
A44: Instalments due | B44: LCY | C44: =SUM(E44:BL44) | E44: =Products!$E$18*SUMIFS($E$40:$BL$40,Timeline!$E$4:$BL$4,">="&(E$4-Products!$E$9),Timeline!$E$4:$BL$4,"<="&(E$4-1)) | F44: =Products!$E$18*SUMIFS($E$40:$BL$40,Timeline!$E$4:$BL$4,">="&(F$4-Products!$E$9),Timeline!$E$4:$BL$4,"<="&(F$4-1)) | G44: =Products!$E$18*SUMIFS($E$40:$BL$40,Timeline!$E$4:$BL$4,">="&(G$4-Products!$E$9),Timeline!$E$4:$BL$4,"<="&(G$4-1)) | H44: =Products!$E$18*SUMIFS($E$40:$BL$40,Timeline!$E$4:$BL$4,">="&(H$4-Products!$E$9),Timeline!$E$4:$BL$4,"<="&(H$4-1)) | I44: =Products!$E$18*SUMIFS($E$40:$BL$40,Timeline!$E$4:$BL$4,">="&(I$4-Products!$E$9),Timeline!$E$4:$BL$4,"<="&(I$4-1)) | J44: =Products!$E$18*SUMIFS($E$40:$BL$40,Timeline!$E$4:$BL$4,">="&(J$4-Products!$E$9),Timeline!$E$4:$BL$4,"<="&(J$4-1)) | K44: =Products!$E$18*SUMIFS($E$40:$BL$40,Timeline!$E$4:$BL$4,">="&(K$4-Products!$E$9),Timeline!$E$4:$BL$4,"<="&(K$4-1)) | L44: =Products!$E$18*SUMIFS($E$40:$BL$40,Timeline!$E$4:$BL$4,">="&(L$4-Products!$E$9),Timeline!$E$4:$BL$4,"<="&(L$4-1)) | ... BL44: =Products!$E$18*SUMIFS($E$40:$BL$40,Timeline!$E$4:$BL$4,">="&(BL$4-Products!$E$9),Timeline!$E$4:$BL$4,"<="&(BL$4-1))
A45: Instalments collected | B45: LCY | C45: =SUM(E45:BL45) | E45: =Cohort_P3!E$9 | F45: =Cohort_P3!F$9 | G45: =Cohort_P3!G$9 | H45: =Cohort_P3!H$9 | I45: =Cohort_P3!I$9 | J45: =Cohort_P3!J$9 | K45: =Cohort_P3!K$9 | L45: =Cohort_P3!L$9 | ... BL45: =Cohort_P3!BL$9
A46: Missed instalments written off | B46: LCY | C46: =SUM(E46:BL46) | E46: =E$44-E$45 | F46: =F$44-F$45 | G46: =G$44-G$45 | H46: =H$44-H$45 | I46: =I$44-I$45 | J46: =J$44-J$45 | K46: =K$44-K$45 | L46: =L$44-L$45 | ... BL46: =BL$44-BL$45
A47: PAYGo financing income (straight-line over tenor) | B47: LCY | C47: =SUM(E47:BL47) | E47: =IF(Products!$E$9=0,0,Products!$E$20/Products!$E$9*SUMIFS($E$40:$BL$40,Timeline!$E$4:$BL$4,">="&(E$4-Products!$E$9),Timeline!$E$4:$BL$4,"<="&(E$4-1))) | F47: =IF(Products!$E$9=0,0,Products!$E$20/Products!$E$9*SUMIFS($E$40:$BL$40,Timeline!$E$4:$BL$4,">="&(F$4-Products!$E$9),Timeline!$E$4:$BL$4,"<="&(F$4-1))) | G47: =IF(Products!$E$9=0,0,Products!$E$20/Products!$E$9*SUMIFS($E$40:$BL$40,Timeline!$E$4:$BL$4,">="&(G$4-Products!$E$9),Timeline!$E$4:$BL$4,"<="&(G$4-1))) | H47: =IF(Products!$E$9=0,0,Products!$E$20/Products!$E$9*SUMIFS($E$40:$BL$40,Timeline!$E$4:$BL$4,">="&(H$4-Products!$E$9),Timeline!$E$4:$BL$4,"<="&(H$4-1))) | I47: =IF(Products!$E$9=0,0,Products!$E$20/Products!$E$9*SUMIFS($E$40:$BL$40,Timeline!$E$4:$BL$4,">="&(I$4-Products!$E$9),Timeline!$E$4:$BL$4,"<="&(I$4-1))) | J47: =IF(Products!$E$9=0,0,Products!$E$20/Products!$E$9*SUMIFS($E$40:$BL$40,Timeline!$E$4:$BL$4,">="&(J$4-Products!$E$9),Timeline!$E$4:$BL$4,"<="&(J$4-1))) | K47: =IF(Products!$E$9=0,0,Products!$E$20/Products!$E$9*SUMIFS($E$40:$BL$40,Timeline!$E$4:$BL$4,">="&(K$4-Products!$E$9),Timeline!$E$4:$BL$4,"<="&(K$4-1))) | L47: =IF(Products!$E$9=0,0,Products!$E$20/Products!$E$9*SUMIFS($E$40:$BL$40,Timeline!$E$4:$BL$4,">="&(L$4-Products!$E$9),Timeline!$E$4:$BL$4,"<="&(L$4-1))) | ... BL47: =IF(Products!$E$9=0,0,Products!$E$20/Products!$E$9*SUMIFS($E$40:$BL$40,Timeline!$E$4:$BL$4,">="&(BL$4-Products!$E$9),Timeline!$E$4:$BL$4,"<="&(BL$4-1)))
A48: Expected credit loss charge at origination | B48: LCY | C48: =SUM(E48:BL48) | E48: =E$40*Curves!$W$70 | F48: =F$40*Curves!$W$70 | G48: =G$40*Curves!$W$70 | H48: =H$40*Curves!$W$70 | I48: =I$40*Curves!$W$70 | J48: =J$40*Curves!$W$70 | K48: =K$40*Curves!$W$70 | L48: =L$40*Curves!$W$70 | ... BL48: =BL$40*Curves!$W$70
A49: Active (paying, in-tenor) accounts | B49: accounts | C49: =BL49 | E49: =Cohort_P3!E$72 | F49: =Cohort_P3!F$72 | G49: =Cohort_P3!G$72 | H49: =Cohort_P3!H$72 | I49: =Cohort_P3!I$72 | J49: =Cohort_P3!J$72 | K49: =Cohort_P3!K$72 | L49: =Cohort_P3!L$72 | ... BL49: =Cohort_P3!BL$72
A50: Receivables at risk (carrying amount of accounts that stopped paying) | B50: LCY | C50: =BL50 | E50: =Cohort_P3!E$135 | F50: =Cohort_P3!F$135 | G50: =Cohort_P3!G$135 | H50: =Cohort_P3!H$135 | I50: =Cohort_P3!I$135 | J50: =Cohort_P3!J$135 | K50: =Cohort_P3!K$135 | L50: =Cohort_P3!L$135 | ... BL50: =Cohort_P3!BL$135
A51: Landed hardware cost of units sold | B51: LCY | C51: =SUM(E51:BL51) | E51: =E$39*Products!$E$10*(1+Inputs!$C$28)*Timeline!E$8*Scenarios!$G$9 | F51: =F$39*Products!$E$10*(1+Inputs!$C$28)*Timeline!F$8*Scenarios!$G$9 | G51: =G$39*Products!$E$10*(1+Inputs!$C$28)*Timeline!G$8*Scenarios!$G$9 | H51: =H$39*Products!$E$10*(1+Inputs!$C$28)*Timeline!H$8*Scenarios!$G$9 | I51: =I$39*Products!$E$10*(1+Inputs!$C$28)*Timeline!I$8*Scenarios!$G$9 | J51: =J$39*Products!$E$10*(1+Inputs!$C$28)*Timeline!J$8*Scenarios!$G$9 | K51: =K$39*Products!$E$10*(1+Inputs!$C$28)*Timeline!K$8*Scenarios!$G$9 | L51: =L$39*Products!$E$10*(1+Inputs!$C$28)*Timeline!L$8*Scenarios!$G$9 | ... BL51: =BL$39*Products!$E$10*(1+Inputs!$C$28)*Timeline!BL$8*Scenarios!$G$9
A53: TOTAL - all products
A54: Units sold | B54: units | C54: =SUM(E54:BL54) | E54: =E$9+E$24+E$39 | F54: =F$9+F$24+F$39 | G54: =G$9+G$24+G$39 | H54: =H$9+H$24+H$39 | I54: =I$9+I$24+I$39 | J54: =J$9+J$24+J$39 | K54: =K$9+K$24+K$39 | L54: =L$9+L$24+L$39 | ... BL54: =BL$9+BL$24+BL$39
A55: Price-indexed units (units x price index) | B55: units | C55: =SUM(E55:BL55) | E55: =E$10+E$25+E$40 | F55: =F$10+F$25+F$40 | G55: =G$10+G$25+G$40 | H55: =H$10+H$25+H$40 | I55: =I$10+I$25+I$40 | J55: =J$10+J$25+J$40 | K55: =K$10+K$25+K$40 | L55: =L$10+L$25+L$40 | ... BL55: =BL$10+BL$25+BL$40
A56: Deposits collected | B56: LCY | C56: =SUM(E56:BL56) | E56: =E$11+E$26+E$41 | F56: =F$11+F$26+F$41 | G56: =G$11+G$26+G$41 | H56: =H$11+H$26+H$41 | I56: =I$11+I$26+I$41 | J56: =J$11+J$26+J$41 | K56: =K$11+K$26+K$41 | L56: =L$11+L$26+L$41 | ... BL56: =BL$11+BL$26+BL$41
A57: Hardware revenue (cash price) | B57: LCY | C57: =SUM(E57:BL57) | E57: =E$12+E$27+E$42 | F57: =F$12+F$27+F$42 | G57: =G$12+G$27+G$42 | H57: =H$12+H$27+H$42 | I57: =I$12+I$27+I$42 | J57: =J$12+J$27+J$42 | K57: =K$12+K$27+K$42 | L57: =L$12+L$27+L$42 | ... BL57: =BL$12+BL$27+BL$42
A58: New receivables originated (cash price - deposit) | B58: LCY | C58: =SUM(E58:BL58) | E58: =E$13+E$28+E$43 | F58: =F$13+F$28+F$43 | G58: =G$13+G$28+G$43 | H58: =H$13+H$28+H$43 | I58: =I$13+I$28+I$43 | J58: =J$13+J$28+J$43 | K58: =K$13+K$28+K$43 | L58: =L$13+L$28+L$43 | ... BL58: =BL$13+BL$28+BL$43
A59: Instalments due | B59: LCY | C59: =SUM(E59:BL59) | E59: =E$14+E$29+E$44 | F59: =F$14+F$29+F$44 | G59: =G$14+G$29+G$44 | H59: =H$14+H$29+H$44 | I59: =I$14+I$29+I$44 | J59: =J$14+J$29+J$44 | K59: =K$14+K$29+K$44 | L59: =L$14+L$29+L$44 | ... BL59: =BL$14+BL$29+BL$44
A60: Instalments collected | B60: LCY | C60: =SUM(E60:BL60) | E60: =E$15+E$30+E$45 | F60: =F$15+F$30+F$45 | G60: =G$15+G$30+G$45 | H60: =H$15+H$30+H$45 | I60: =I$15+I$30+I$45 | J60: =J$15+J$30+J$45 | K60: =K$15+K$30+K$45 | L60: =L$15+L$30+L$45 | ... BL60: =BL$15+BL$30+BL$45
A61: Missed instalments written off | B61: LCY | C61: =SUM(E61:BL61) | E61: =E$16+E$31+E$46 | F61: =F$16+F$31+F$46 | G61: =G$16+G$31+G$46 | H61: =H$16+H$31+H$46 | I61: =I$16+I$31+I$46 | J61: =J$16+J$31+J$46 | K61: =K$16+K$31+K$46 | L61: =L$16+L$31+L$46 | ... BL61: =BL$16+BL$31+BL$46
A62: PAYGo financing income (straight-line over tenor) | B62: LCY | C62: =SUM(E62:BL62) | E62: =E$17+E$32+E$47 | F62: =F$17+F$32+F$47 | G62: =G$17+G$32+G$47 | H62: =H$17+H$32+H$47 | I62: =I$17+I$32+I$47 | J62: =J$17+J$32+J$47 | K62: =K$17+K$32+K$47 | L62: =L$17+L$32+L$47 | ... BL62: =BL$17+BL$32+BL$47
A63: Expected credit loss charge at origination | B63: LCY | C63: =SUM(E63:BL63) | E63: =E$18+E$33+E$48 | F63: =F$18+F$33+F$48 | G63: =G$18+G$33+G$48 | H63: =H$18+H$33+H$48 | I63: =I$18+I$33+I$48 | J63: =J$18+J$33+J$48 | K63: =K$18+K$33+K$48 | L63: =L$18+L$33+L$48 | ... BL63: =BL$18+BL$33+BL$48
A64: Active (paying, in-tenor) accounts | B64: accounts | C64: =BL64 | E64: =E$19+E$34+E$49 | F64: =F$19+F$34+F$49 | G64: =G$19+G$34+G$49 | H64: =H$19+H$34+H$49 | I64: =I$19+I$34+I$49 | J64: =J$19+J$34+J$49 | K64: =K$19+K$34+K$49 | L64: =L$19+L$34+L$49 | ... BL64: =BL$19+BL$34+BL$49
A65: Receivables at risk (carrying amount of accounts that stopped paying) | B65: LCY | C65: =BL65 | E65: =E$20+E$35+E$50 | F65: =F$20+F$35+F$50 | G65: =G$20+G$35+G$50 | H65: =H$20+H$35+H$50 | I65: =I$20+I$35+I$50 | J65: =J$20+J$35+J$50 | K65: =K$20+K$35+K$50 | L65: =L$20+L$35+L$50 | ... BL65: =BL$20+BL$35+BL$50
A66: Landed hardware cost of units sold | B66: LCY | C66: =SUM(E66:BL66) | E66: =E$21+E$36+E$51 | F66: =F$21+F$36+F$51 | G66: =G$21+G$36+G$51 | H66: =H$21+H$36+H$51 | I66: =I$21+I$36+I$51 | J66: =J$21+J$36+J$51 | K66: =K$21+K$36+K$51 | L66: =L$21+L$36+L$51 | ... BL66: =BL$21+BL$36+BL$51
A68: Portfolio collection rate (collected / due, excl. deposits) | B68: % | E68: =IF(E$59=0,0,E$60/E$59) | F68: =IF(F$59=0,0,F$60/F$59) | G68: =IF(G$59=0,0,G$60/G$59) | H68: =IF(H$59=0,0,H$60/H$59) | I68: =IF(I$59=0,0,I$60/I$59) | J68: =IF(J$59=0,0,J$60/J$59) | K68: =IF(K$59=0,0,K$60/K$59) | L68: =IF(L$59=0,0,L$60/L$59) | ... BL68: =IF(BL$59=0,0,BL$60/BL$59)
A69: Write-off rate (missed / due) | B69: % | E69: =IF(E$59=0,0,E$61/E$59) | F69: =IF(F$59=0,0,F$61/F$59) | G69: =IF(G$59=0,0,G$61/G$59) | H69: =IF(H$59=0,0,H$61/H$59) | I69: =IF(I$59=0,0,I$61/I$59) | J69: =IF(J$59=0,0,J$61/J$59) | K69: =IF(K$59=0,0,K$61/K$59) | L69: =IF(L$59=0,0,L$61/L$59) | ... BL69: =IF(BL$59=0,0,BL$61/BL$59)

Sheet Costs
A1: Operating costs, working capital & capex
A2: LCY
A4: Month # | D4: Opening | E4: =Timeline!E4 | F4: =Timeline!F4 | G4: =Timeline!G4 | H4: =Timeline!H4 | I4: =Timeline!I4 | J4: =Timeline!J4 | K4: =Timeline!K4 | L4: =Timeline!L4 | ... BL4: =Timeline!BL4
A5: Period end | E5: =Timeline!E5 | F5: =Timeline!F5 | G5: =Timeline!G5 | H5: =Timeline!H5 | I5: =Timeline!I5 | J5: =Timeline!J5 | K5: =Timeline!K5 | L5: =Timeline!L5 | ... BL5: =Timeline!BL5
A6: Year # | E6: =Timeline!E6 | F6: =Timeline!F6 | G6: =Timeline!G6 | H6: =Timeline!H6 | I6: =Timeline!I6 | J6: =Timeline!J6 | K6: =Timeline!K6 | L6: =Timeline!L6 | ... BL6: =Timeline!BL6
A8: Cost of goods sold (landed hardware) | B8: LCY | C8: =SUM(E8:BL8) | E8: =Ops!E$66 | F8: =Ops!F$66 | G8: =Ops!G$66 | H8: =Ops!H$66 | I8: =Ops!I$66 | J8: =Ops!J$66 | K8: =Ops!K$66 | L8: =Ops!L$66 | ... BL8: =Ops!BL$66
A9: Warranty & after-sales | B9: LCY | C9: =SUM(E9:BL9) | E9: =E8*Inputs!$C$27 | F9: =F8*Inputs!$C$27 | G9: =G8*Inputs!$C$27 | H9: =H8*Inputs!$C$27 | I9: =I8*Inputs!$C$27 | J9: =J8*Inputs!$C$27 | K9: =K8*Inputs!$C$27 | L9: =L8*Inputs!$C$27 | ... BL9: =BL8*Inputs!$C$27
A10: Agent commissions | B10: LCY | C10: =SUM(E10:BL10) | E10: =Ops!E$9*Products!$C$11*Timeline!E$9+Ops!E$24*Products!$D$11*Timeline!E$9+Ops!E$39*Products!$E$11*Timeline!E$9 | F10: =Ops!F$9*Products!$C$11*Timeline!F$9+Ops!F$24*Products!$D$11*Timeline!F$9+Ops!F$39*Products!$E$11*Timeline!F$9 | G10: =Ops!G$9*Products!$C$11*Timeline!G$9+Ops!G$24*Products!$D$11*Timeline!G$9+Ops!G$39*Products!$E$11*Timeline!G$9 | H10: =Ops!H$9*Products!$C$11*Timeline!H$9+Ops!H$24*Products!$D$11*Timeline!H$9+Ops!H$39*Products!$E$11*Timeline!H$9 | I10: =Ops!I$9*Products!$C$11*Timeline!I$9+Ops!I$24*Products!$D$11*Timeline!I$9+Ops!I$39*Products!$E$11*Timeline!I$9 | J10: =Ops!J$9*Products!$C$11*Timeline!J$9+Ops!J$24*Products!$D$11*Timeline!J$9+Ops!J$39*Products!$E$11*Timeline!J$9 | K10: =Ops!K$9*Products!$C$11*Timeline!K$9+Ops!K$24*Products!$D$11*Timeline!K$9+Ops!K$39*Products!$E$11*Timeline!K$9 | L10: =Ops!L$9*Products!$C$11*Timeline!L$9+Ops!L$24*Products!$D$11*Timeline!L$9+Ops!L$39*Products!$E$11*Timeline!L$9 | ... BL10: =Ops!BL$9*Products!$C$11*Timeline!BL$9+Ops!BL$24*Products!$D$11*Timeline!BL$9+Ops!BL$39*Products!$E$11*Timeline!BL$9
A11: Marketing & acquisition | B11: LCY | C11: =SUM(E11:BL11) | E11: =Ops!E$9*Products!$C$12*Timeline!E$9+Ops!E$24*Products!$D$12*Timeline!E$9+Ops!E$39*Products!$E$12*Timeline!E$9 | F11: =Ops!F$9*Products!$C$12*Timeline!F$9+Ops!F$24*Products!$D$12*Timeline!F$9+Ops!F$39*Products!$E$12*Timeline!F$9 | G11: =Ops!G$9*Products!$C$12*Timeline!G$9+Ops!G$24*Products!$D$12*Timeline!G$9+Ops!G$39*Products!$E$12*Timeline!G$9 | H11: =Ops!H$9*Products!$C$12*Timeline!H$9+Ops!H$24*Products!$D$12*Timeline!H$9+Ops!H$39*Products!$E$12*Timeline!H$9 | I11: =Ops!I$9*Products!$C$12*Timeline!I$9+Ops!I$24*Products!$D$12*Timeline!I$9+Ops!I$39*Products!$E$12*Timeline!I$9 | J11: =Ops!J$9*Products!$C$12*Timeline!J$9+Ops!J$24*Products!$D$12*Timeline!J$9+Ops!J$39*Products!$E$12*Timeline!J$9 | K11: =Ops!K$9*Products!$C$12*Timeline!K$9+Ops!K$24*Products!$D$12*Timeline!K$9+Ops!K$39*Products!$E$12*Timeline!K$9 | L11: =Ops!L$9*Products!$C$12*Timeline!L$9+Ops!L$24*Products!$D$12*Timeline!L$9+Ops!L$39*Products!$E$12*Timeline!L$9 | ... BL11: =Ops!BL$9*Products!$C$12*Timeline!BL$9+Ops!BL$24*Products!$D$12*Timeline!BL$9+Ops!BL$39*Products!$E$12*Timeline!BL$9
A12: Mobile-money / payment fees | B12: LCY | C12: =SUM(E12:BL12) | E12: =(Ops!E$56+Ops!E$60)*Inputs!$C$23 | F12: =(Ops!F$56+Ops!F$60)*Inputs!$C$23 | G12: =(Ops!G$56+Ops!G$60)*Inputs!$C$23 | H12: =(Ops!H$56+Ops!H$60)*Inputs!$C$23 | I12: =(Ops!I$56+Ops!I$60)*Inputs!$C$23 | J12: =(Ops!J$56+Ops!J$60)*Inputs!$C$23 | K12: =(Ops!K$56+Ops!K$60)*Inputs!$C$23 | L12: =(Ops!L$56+Ops!L$60)*Inputs!$C$23 | ... BL12: =(Ops!BL$56+Ops!BL$60)*Inputs!$C$23
A13: Customer service & collections | B13: LCY | C13: =SUM(E13:BL13) | E13: =Ops!E$64*Inputs!$C$24*Timeline!E$9 | F13: =Ops!F$64*Inputs!$C$24*Timeline!F$9 | G13: =Ops!G$64*Inputs!$C$24*Timeline!G$9 | H13: =Ops!H$64*Inputs!$C$24*Timeline!H$9 | I13: =Ops!I$64*Inputs!$C$24*Timeline!I$9 | J13: =Ops!J$64*Inputs!$C$24*Timeline!J$9 | K13: =Ops!K$64*Inputs!$C$24*Timeline!K$9 | L13: =Ops!L$64*Inputs!$C$24*Timeline!L$9 | ... BL13: =Ops!BL$64*Inputs!$C$24*Timeline!BL$9
A14: Staff | B14: LCY | C14: =SUM(E14:BL14) | E14: =Inputs!$C$25*Timeline!E$9 | F14: =Inputs!$C$25*Timeline!F$9 | G14: =Inputs!$C$25*Timeline!G$9 | H14: =Inputs!$C$25*Timeline!H$9 | I14: =Inputs!$C$25*Timeline!I$9 | J14: =Inputs!$C$25*Timeline!J$9 | K14: =Inputs!$C$25*Timeline!K$9 | L14: =Inputs!$C$25*Timeline!L$9 | ... BL14: =Inputs!$C$25*Timeline!BL$9
A15: G&A, rent, IT | B15: LCY | C15: =SUM(E15:BL15) | E15: =Inputs!$C$26*Timeline!E$9 | F15: =Inputs!$C$26*Timeline!F$9 | G15: =Inputs!$C$26*Timeline!G$9 | H15: =Inputs!$C$26*Timeline!H$9 | I15: =Inputs!$C$26*Timeline!I$9 | J15: =Inputs!$C$26*Timeline!J$9 | K15: =Inputs!$C$26*Timeline!K$9 | L15: =Inputs!$C$26*Timeline!L$9 | ... BL15: =Inputs!$C$26*Timeline!BL$9
A16: Total operating expenses (excl. COGS, ECL) | B16: LCY | C16: =SUM(E16:BL16) | E16: =SUM(E9:E15) | F16: =SUM(F9:F15) | G16: =SUM(G9:G15) | H16: =SUM(H9:H15) | I16: =SUM(I9:I15) | J16: =SUM(J9:J15) | K16: =SUM(K9:K15) | L16: =SUM(L9:L15) | ... BL16: =SUM(BL9:BL15)
A18: Inventory (closing) | B18: LCY | C18: =BL18 | E18: =E8*Inputs!$C$31 | F18: =F8*Inputs!$C$31 | G18: =G8*Inputs!$C$31 | H18: =H8*Inputs!$C$31 | I18: =I8*Inputs!$C$31 | J18: =J8*Inputs!$C$31 | K18: =K8*Inputs!$C$31 | L18: =L8*Inputs!$C$31 | ... BL18: =BL8*Inputs!$C$31
A19: Hardware purchases | B19: LCY | C19: =SUM(E19:BL19) | E19: =E8+E18-D18 | F19: =F8+F18-E18 | G19: =G8+G18-F18 | H19: =H8+H18-G18 | I19: =I8+I18-H18 | J19: =J8+J18-I18 | K19: =K8+K18-J18 | L19: =L8+L18-K18 | ... BL19: =BL8+BL18-BK18
A20: Supplier payables (closing) | B20: LCY | C20: =BL20 | E20: =E19*Inputs!$C$32/(365/12) | F20: =F19*Inputs!$C$32/(365/12) | G20: =G19*Inputs!$C$32/(365/12) | H20: =H19*Inputs!$C$32/(365/12) | I20: =I19*Inputs!$C$32/(365/12) | J20: =J19*Inputs!$C$32/(365/12) | K20: =K19*Inputs!$C$32/(365/12) | L20: =L19*Inputs!$C$32/(365/12) | ... BL20: =BL19*Inputs!$C$32/(365/12)
A22: Fixed capex | B22: LCY | C22: =SUM(E22:BL22) | E22: =Inputs!$C$33*Timeline!E$9 | F22: =Inputs!$C$33*Timeline!F$9 | G22: =Inputs!$C$33*Timeline!G$9 | H22: =Inputs!$C$33*Timeline!H$9 | I22: =Inputs!$C$33*Timeline!I$9 | J22: =Inputs!$C$33*Timeline!J$9 | K22: =Inputs!$C$33*Timeline!K$9 | L22: =Inputs!$C$33*Timeline!L$9 | ... BL22: =Inputs!$C$33*Timeline!BL$9
A23: Depreciation (straight-line, by vintage) | B23: LCY | C23: =SUM(E23:BL23) | E23: =SUMIFS($E22:E22,$E$4:E$4,">"&(E$4-Inputs!$C$34))/Inputs!$C$34 | F23: =SUMIFS($E22:F22,$E$4:F$4,">"&(F$4-Inputs!$C$34))/Inputs!$C$34 | G23: =SUMIFS($E22:G22,$E$4:G$4,">"&(G$4-Inputs!$C$34))/Inputs!$C$34 | H23: =SUMIFS($E22:H22,$E$4:H$4,">"&(H$4-Inputs!$C$34))/Inputs!$C$34 | I23: =SUMIFS($E22:I22,$E$4:I$4,">"&(I$4-Inputs!$C$34))/Inputs!$C$34 | J23: =SUMIFS($E22:J22,$E$4:J$4,">"&(J$4-Inputs!$C$34))/Inputs!$C$34 | K23: =SUMIFS($E22:K22,$E$4:K$4,">"&(K$4-Inputs!$C$34))/Inputs!$C$34 | L23: =SUMIFS($E22:L22,$E$4:L$4,">"&(L$4-Inputs!$C$34))/Inputs!$C$34 | ... BL23: =SUMIFS($E22:BL22,$E$4:BL$4,">"&(BL$4-Inputs!$C$34))/Inputs!$C$34
A24: Net fixed assets (closing) | B24: LCY | C24: =BL24 | E24: =D24+E22-E23 | F24: =E24+F22-F23 | G24: =F24+G22-G23 | H24: =G24+H22-H23 | I24: =H24+I22-I23 | J24: =I24+J22-J23 | K24: =J24+K22-K23 | L24: =K24+L22-L23 | ... BL24: =BK24+BL22-BL23

Sheet Financing
A1: Financing
A2: Equity, USD term loan (with FX translation), receivables-backed facility
A4: Month # | D4: Opening | E4: =Timeline!E4 | F4: =Timeline!F4 | G4: =Timeline!G4 | H4: =Timeline!H4 | I4: =Timeline!I4 | J4: =Timeline!J4 | K4: =Timeline!K4 | L4: =Timeline!L4 | ... BL4: =Timeline!BL4
A5: Period end | E5: =Timeline!E5 | F5: =Timeline!F5 | G5: =Timeline!G5 | H5: =Timeline!H5 | I5: =Timeline!I5 | J5: =Timeline!J5 | K5: =Timeline!K5 | L5: =Timeline!L5 | ... BL5: =Timeline!BL5
A6: Year # | E6: =Timeline!E6 | F6: =Timeline!F6 | G6: =Timeline!G6 | H6: =Timeline!H6 | I6: =Timeline!I6 | J6: =Timeline!J6 | K6: =Timeline!K6 | L6: =Timeline!L6 | ... BL6: =Timeline!BL6
A8: EQUITY
A9: Initial equity injection | B9: LCY | C9: =SUM(E9:BL9) | E9: =IF(E$4=1,Inputs!$C$38,0) | F9: =IF(F$4=1,Inputs!$C$38,0) | G9: =IF(G$4=1,Inputs!$C$38,0) | H9: =IF(H$4=1,Inputs!$C$38,0) | I9: =IF(I$4=1,Inputs!$C$38,0) | J9: =IF(J$4=1,Inputs!$C$38,0) | K9: =IF(K$4=1,Inputs!$C$38,0) | L9: =IF(L$4=1,Inputs!$C$38,0) | ... BL9: =IF(BL$4=1,Inputs!$C$38,0)
A10: Automatic equity top-up (funding requirement) | B10: LCY | C10: =SUM(E10:BL10) | E10: =FS!E$59 | F10: =FS!F$59 | G10: =FS!G$59 | H10: =FS!H$59 | I10: =FS!I$59 | J10: =FS!J$59 | K10: =FS!K$59 | L10: =FS!L$59 | ... BL10: =FS!BL$59
A11: Cumulative equity invested | B11: LCY | C11: =BL11 | E11: =D11+E9+E10 | F11: =E11+F9+F10 | G11: =F11+G9+G10 | H11: =G11+H9+H10 | I11: =H11+I9+I10 | J11: =I11+J9+J10 | K11: =J11+K9+K10 | L11: =K11+L9+L10 | ... BL11: =BK11+BL9+BL10
A12: USD TERM LOAN
A13: Drawdown (USD) | B13: USD | C13: =SUM(E13:BL13) | E13: =IF(E$4=Inputs!$C$40,Inputs!$C$39,0) | F13: =IF(F$4=Inputs!$C$40,Inputs!$C$39,0) | G13: =IF(G$4=Inputs!$C$40,Inputs!$C$39,0) | H13: =IF(H$4=Inputs!$C$40,Inputs!$C$39,0) | I13: =IF(I$4=Inputs!$C$40,Inputs!$C$39,0) | J13: =IF(J$4=Inputs!$C$40,Inputs!$C$39,0) | K13: =IF(K$4=Inputs!$C$40,Inputs!$C$39,0) | L13: =IF(L$4=Inputs!$C$40,Inputs!$C$39,0) | ... BL13: =IF(BL$4=Inputs!$C$40,Inputs!$C$39,0)
A14: Repayment (USD) | B14: USD | C14: =SUM(E14:BL14) | E14: =IF(AND(E$4>Inputs!$C$40+Inputs!$C$42,E$4<=Inputs!$C$40+Inputs!$C$42+Inputs!$C$43),MIN(D15,Inputs!$C$39/Inputs!$C$43),0) | F14: =IF(AND(F$4>Inputs!$C$40+Inputs!$C$42,F$4<=Inputs!$C$40+Inputs!$C$42+Inputs!$C$43),MIN(E15,Inputs!$C$39/Inputs!$C$43),0) | G14: =IF(AND(G$4>Inputs!$C$40+Inputs!$C$42,G$4<=Inputs!$C$40+Inputs!$C$42+Inputs!$C$43),MIN(F15,Inputs!$C$39/Inputs!$C$43),0) | H14: =IF(AND(H$4>Inputs!$C$40+Inputs!$C$42,H$4<=Inputs!$C$40+Inputs!$C$42+Inputs!$C$43),MIN(G15,Inputs!$C$39/Inputs!$C$43),0) | I14: =IF(AND(I$4>Inputs!$C$40+Inputs!$C$42,I$4<=Inputs!$C$40+Inputs!$C$42+Inputs!$C$43),MIN(H15,Inputs!$C$39/Inputs!$C$43),0) | J14: =IF(AND(J$4>Inputs!$C$40+Inputs!$C$42,J$4<=Inputs!$C$40+Inputs!$C$42+Inputs!$C$43),MIN(I15,Inputs!$C$39/Inputs!$C$43),0) | K14: =IF(AND(K$4>Inputs!$C$40+Inputs!$C$42,K$4<=Inputs!$C$40+Inputs!$C$42+Inputs!$C$43),MIN(J15,Inputs!$C$39/Inputs!$C$43),0) | L14: =IF(AND(L$4>Inputs!$C$40+Inputs!$C$42,L$4<=Inputs!$C$40+Inputs!$C$42+Inputs!$C$43),MIN(K15,Inputs!$C$39/Inputs!$C$43),0) | ... BL14: =IF(AND(BL$4>Inputs!$C$40+Inputs!$C$42,BL$4<=Inputs!$C$40+Inputs!$C$42+Inputs!$C$43),MIN(BK15,Inputs!$C$39/Inputs!$C$43),0)
A15: Closing balance (USD) | B15: USD | C15: =BL15 | E15: =D15+E13-E14 | F15: =E15+F13-F14 | G15: =F15+G13-G14 | H15: =G15+H13-H14 | I15: =H15+I13-I14 | J15: =I15+J13-J14 | K15: =J15+K13-K14 | L15: =K15+L13-L14 | ... BL15: =BK15+BL13-BL14
A16: Interest (LCY) | B16: LCY | C16: =SUM(E16:BL16) | E16: =D15*Inputs!$C$41/12*Timeline!E$8 | F16: =E15*Inputs!$C$41/12*Timeline!F$8 | G16: =F15*Inputs!$C$41/12*Timeline!G$8 | H16: =G15*Inputs!$C$41/12*Timeline!H$8 | I16: =H15*Inputs!$C$41/12*Timeline!I$8 | J16: =I15*Inputs!$C$41/12*Timeline!J$8 | K16: =J15*Inputs!$C$41/12*Timeline!K$8 | L16: =K15*Inputs!$C$41/12*Timeline!L$8 | ... BL16: =BK15*Inputs!$C$41/12*Timeline!BL$8
A17: Drawdown (LCY) | B17: LCY | C17: =SUM(E17:BL17) | E17: =E13*Timeline!E$8 | F17: =F13*Timeline!F$8 | G17: =G13*Timeline!G$8 | H17: =H13*Timeline!H$8 | I17: =I13*Timeline!I$8 | J17: =J13*Timeline!J$8 | K17: =K13*Timeline!K$8 | L17: =L13*Timeline!L$8 | ... BL17: =BL13*Timeline!BL$8
A18: Repayment (LCY) | B18: LCY | C18: =SUM(E18:BL18) | E18: =E14*Timeline!E$8 | F18: =F14*Timeline!F$8 | G18: =G14*Timeline!G$8 | H18: =H14*Timeline!H$8 | I18: =I14*Timeline!I$8 | J18: =J14*Timeline!J$8 | K18: =K14*Timeline!K$8 | L18: =L14*Timeline!L$8 | ... BL18: =BL14*Timeline!BL$8
A19: Closing balance (LCY) | B19: LCY | C19: =BL19 | E19: =E15*Timeline!E$8 | F19: =F15*Timeline!F$8 | G19: =G15*Timeline!G$8 | H19: =H15*Timeline!H$8 | I19: =I15*Timeline!I$8 | J19: =J15*Timeline!J$8 | K19: =K15*Timeline!K$8 | L19: =L15*Timeline!L$8 | ... BL19: =BL15*Timeline!BL$8
A20: Unrealised FX loss / (gain) on USD debt (LCY) | B20: LCY | C20: =SUM(E20:BL20) | E20: =D15*(Timeline!E$8-Timeline!D$8) | F20: =E15*(Timeline!F$8-Timeline!E$8) | G20: =F15*(Timeline!G$8-Timeline!F$8) | H20: =G15*(Timeline!H$8-Timeline!G$8) | I20: =H15*(Timeline!I$8-Timeline!H$8) | J20: =I15*(Timeline!J$8-Timeline!I$8) | K20: =J15*(Timeline!K$8-Timeline!J$8) | L20: =K15*(Timeline!L$8-Timeline!K$8) | ... BL20: =BK15*(Timeline!BL$8-Timeline!BK$8)
A21: RECEIVABLES FACILITY (LCY)
A22: Eligible receivables (gross receivables - receivables at risk) | B22: LCY | C22: =BL22 | E22: =MAX(0,FS!E$30-Ops!E$65) | F22: =MAX(0,FS!F$30-Ops!F$65) | G22: =MAX(0,FS!G$30-Ops!G$65) | H22: =MAX(0,FS!H$30-Ops!H$65) | I22: =MAX(0,FS!I$30-Ops!I$65) | J22: =MAX(0,FS!J$30-Ops!J$65) | K22: =MAX(0,FS!K$30-Ops!K$65) | L22: =MAX(0,FS!L$30-Ops!L$65) | ... BL22: =MAX(0,FS!BL$30-Ops!BL$65)
A23: Borrowing base (advance rate x eligible) | B23: LCY | C23: =BL23 | E23: =E22*Inputs!$C$45 | F23: =F22*Inputs!$C$45 | G23: =G22*Inputs!$C$45 | H23: =H22*Inputs!$C$45 | I23: =I22*Inputs!$C$45 | J23: =J22*Inputs!$C$45 | K23: =K22*Inputs!$C$45 | L23: =L22*Inputs!$C$45 | ... BL23: =BL22*Inputs!$C$45
A24: Facility drawn (closing) | B24: LCY | C24: =BL24 | E24: =IF(E$4>=Inputs!$C$47,MIN(Inputs!$C$44,E23),0) | F24: =IF(F$4>=Inputs!$C$47,MIN(Inputs!$C$44,F23),0) | G24: =IF(G$4>=Inputs!$C$47,MIN(Inputs!$C$44,G23),0) | H24: =IF(H$4>=Inputs!$C$47,MIN(Inputs!$C$44,H23),0) | I24: =IF(I$4>=Inputs!$C$47,MIN(Inputs!$C$44,I23),0) | J24: =IF(J$4>=Inputs!$C$47,MIN(Inputs!$C$44,J23),0) | K24: =IF(K$4>=Inputs!$C$47,MIN(Inputs!$C$44,K23),0) | L24: =IF(L$4>=Inputs!$C$47,MIN(Inputs!$C$44,L23),0) | ... BL24: =IF(BL$4>=Inputs!$C$47,MIN(Inputs!$C$44,BL23),0)
A25: Net drawdown / (repayment) | B25: LCY | C25: =SUM(E25:BL25) | E25: =E24-D24 | F25: =F24-E24 | G25: =G24-F24 | H25: =H24-G24 | I25: =I24-H24 | J25: =J24-I24 | K25: =K24-J24 | L25: =L24-K24 | ... BL25: =BL24-BK24
A26: Interest | B26: LCY | C26: =SUM(E26:BL26) | E26: =D24*Inputs!$C$46/12 | F26: =E24*Inputs!$C$46/12 | G26: =F24*Inputs!$C$46/12 | H26: =G24*Inputs!$C$46/12 | I26: =H24*Inputs!$C$46/12 | J26: =I24*Inputs!$C$46/12 | K26: =J24*Inputs!$C$46/12 | L26: =K24*Inputs!$C$46/12 | ... BL26: =BK24*Inputs!$C$46/12
A27: Utilisation of limit | B27: % | C27: =MAX(E27:BL27) | E27: =IF(Inputs!$C$44=0,0,E24/Inputs!$C$44) | F27: =IF(Inputs!$C$44=0,0,F24/Inputs!$C$44) | G27: =IF(Inputs!$C$44=0,0,G24/Inputs!$C$44) | H27: =IF(Inputs!$C$44=0,0,H24/Inputs!$C$44) | I27: =IF(Inputs!$C$44=0,0,I24/Inputs!$C$44) | J27: =IF(Inputs!$C$44=0,0,J24/Inputs!$C$44) | K27: =IF(Inputs!$C$44=0,0,K24/Inputs!$C$44) | L27: =IF(Inputs!$C$44=0,0,L24/Inputs!$C$44) | ... BL27: =IF(Inputs!$C$44=0,0,BL24/Inputs!$C$44)

Sheet Curves
A1: Per-unit repayment curves by account age
A2: Age 0 = month of sale. One block per product. Values are per unit, in month-1 prices (cohorts are scaled by the price index).
B5: P1 Solar lantern kit (Tier 1) | K5: P2 SHS lights+radio (Tier 2) | T5: P3 SHS with TV (Tier 3)
A6: Age (m) | B6: Survival (still paying) | C6: Instalment due | D6: Collected | E6: Missed (written off) | F6: Receivable at risk | G6: Active account | H6: Net cash flow / unit | I6: Cumulative cash flow | K6: Survival (still paying) | L6: Instalment due | M6: Collected | N6: Missed (written off) | O6: Receivable at risk | P6: Active account | Q6: Net cash flow / unit | R6: Cumulative cash flow | T6: Survival (still paying) | U6: Instalment due | V6: Collected | W6: Missed (written off) | X6: Receivable at risk | Y6: Active account | Z6: Net cash flow / unit | AA6: Cumulative cash flow
A8: 0 | B8: =1 | C8: =IF(AND($A8>=1,$A8<=Products!$C$9),Products!$C$18,0) | D8: =C8*Products!$C$24*B8 | E8: =C8-D8 | F8: =(1-B8)*MAX(0,Products!$C$9-$A8)*(Products!$C$18-Products!$C$20/Products!$C$9) | G8: =IF($A8<=Products!$C$9,B8,0) | H8: =Products!$C$7*(1-Inputs!$C$23)-Products!$C$25*(1+Inputs!$C$27)-Products!$C$26 | I8: =H8 | K8: =1 | L8: =IF(AND($A8>=1,$A8<=Products!$D$9),Products!$D$18,0) | M8: =L8*Products!$D$24*K8 | N8: =L8-M8 | O8: =(1-K8)*MAX(0,Products!$D$9-$A8)*(Products!$D$18-Products!$D$20/Products!$D$9) | P8: =IF($A8<=Products!$D$9,K8,0) | Q8: =Products!$D$7*(1-Inputs!$C$23)-Products!$D$25*(1+Inputs!$C$27)-Products!$D$26 | R8: =Q8 | T8: =1 | U8: =IF(AND($A8>=1,$A8<=Products!$E$9),Products!$E$18,0) | V8: =U8*Products!$E$24*T8 | W8: =U8-V8 | X8: =(1-T8)*MAX(0,Products!$E$9-$A8)*(Products!$E$18-Products!$E$20/Products!$E$9) | Y8: =IF($A8<=Products!$E$9,T8,0) | Z8: =Products!$E$7*(1-Inputs!$C$23)-Products!$E$25*(1+Inputs!$C$27)-Products!$E$26 | AA8: =Z8
A9: 1 | B9: =(1-Products!$C$23)^$A9 | C9: =IF(AND($A9>=1,$A9<=Products!$C$9),Products!$C$18,0) | D9: =C9*Products!$C$24*B9 | E9: =C9-D9 | F9: =(1-B9)*MAX(0,Products!$C$9-$A9)*(Products!$C$18-Products!$C$20/Products!$C$9) | G9: =IF($A9<=Products!$C$9,B9,0) | H9: =D9*(1-Inputs!$C$23)-Inputs!$C$24*G9 | I9: =I8+H9 | K9: =(1-Products!$D$23)^$A9 | L9: =IF(AND($A9>=1,$A9<=Products!$D$9),Products!$D$18,0) | M9: =L9*Products!$D$24*K9 | N9: =L9-M9 | O9: =(1-K9)*MAX(0,Products!$D$9-$A9)*(Products!$D$18-Products!$D$20/Products!$D$9) | P9: =IF($A9<=Products!$D$9,K9,0) | Q9: =M9*(1-Inputs!$C$23)-Inputs!$C$24*P9 | R9: =R8+Q9 | T9: =(1-Products!$E$23)^$A9 | U9: =IF(AND($A9>=1,$A9<=Products!$E$9),Products!$E$18,0) | V9: =U9*Products!$E$24*T9 | W9: =U9-V9 | X9: =(1-T9)*MAX(0,Products!$E$9-$A9)*(Products!$E$18-Products!$E$20/Products!$E$9) | Y9: =IF($A9<=Products!$E$9,T9,0) | Z9: =V9*(1-Inputs!$C$23)-Inputs!$C$24*Y9 | AA9: =AA8+Z9
A10: 2 | B10: =(1-Products!$C$23)^$A10 | C10: =IF(AND($A10>=1,$A10<=Products!$C$9),Products!$C$18,0) | D10: =C10*Products!$C$24*B10 | E10: =C10-D10 | F10: =(1-B10)*MAX(0,Products!$C$9-$A10)*(Products!$C$18-Products!$C$20/Products!$C$9) | G10: =IF($A10<=Products!$C$9,B10,0) | H10: =D10*(1-Inputs!$C$23)-Inputs!$C$24*G10 | I10: =I9+H10 | K10: =(1-Products!$D$23)^$A10 | L10: =IF(AND($A10>=1,$A10<=Products!$D$9),Products!$D$18,0) | M10: =L10*Products!$D$24*K10 | N10: =L10-M10 | O10: =(1-K10)*MAX(0,Products!$D$9-$A10)*(Products!$D$18-Products!$D$20/Products!$D$9) | P10: =IF($A10<=Products!$D$9,K10,0) | Q10: =M10*(1-Inputs!$C$23)-Inputs!$C$24*P10 | R10: =R9+Q10 | T10: =(1-Products!$E$23)^$A10 | U10: =IF(AND($A10>=1,$A10<=Products!$E$9),Products!$E$18,0) | V10: =U10*Products!$E$24*T10 | W10: =U10-V10 | X10: =(1-T10)*MAX(0,Products!$E$9-$A10)*(Products!$E$18-Products!$E$20/Products!$E$9) | Y10: =IF($A10<=Products!$E$9,T10,0) | Z10: =V10*(1-Inputs!$C$23)-Inputs!$C$24*Y10 | AA10: =AA9+Z10
A11: 3 | B11: =(1-Products!$C$23)^$A11 | C11: =IF(AND($A11>=1,$A11<=Products!$C$9),Products!$C$18,0) | D11: =C11*Products!$C$24*B11 | E11: =C11-D11 | F11: =(1-B11)*MAX(0,Products!$C$9-$A11)*(Products!$C$18-Products!$C$20/Products!$C$9) | G11: =IF($A11<=Products!$C$9,B11,0) | H11: =D11*(1-Inputs!$C$23)-Inputs!$C$24*G11 | I11: =I10+H11 | K11: =(1-Products!$D$23)^$A11 | L11: =IF(AND($A11>=1,$A11<=Products!$D$9),Products!$D$18,0) | M11: =L11*Products!$D$24*K11 | N11: =L11-M11 | O11: =(1-K11)*MAX(0,Products!$D$9-$A11)*(Products!$D$18-Products!$D$20/Products!$D$9) | P11: =IF($A11<=Products!$D$9,K11,0) | Q11: =M11*(1-Inputs!$C$23)-Inputs!$C$24*P11 | R11: =R10+Q11 | T11: =(1-Products!$E$23)^$A11 | U11: =IF(AND($A11>=1,$A11<=Products!$E$9),Products!$E$18,0) | V11: =U11*Products!$E$24*T11 | W11: =U11-V11 | X11: =(1-T11)*MAX(0,Products!$E$9-$A11)*(Products!$E$18-Products!$E$20/Products!$E$9) | Y11: =IF($A11<=Products!$E$9,T11,0) | Z11: =V11*(1-Inputs!$C$23)-Inputs!$C$24*Y11 | AA11: =AA10+Z11
A12: 4 | B12: =(1-Products!$C$23)^$A12 | C12: =IF(AND($A12>=1,$A12<=Products!$C$9),Products!$C$18,0) | D12: =C12*Products!$C$24*B12 | E12: =C12-D12 | F12: =(1-B12)*MAX(0,Products!$C$9-$A12)*(Products!$C$18-Products!$C$20/Products!$C$9) | G12: =IF($A12<=Products!$C$9,B12,0) | H12: =D12*(1-Inputs!$C$23)-Inputs!$C$24*G12 | I12: =I11+H12 | K12: =(1-Products!$D$23)^$A12 | L12: =IF(AND($A12>=1,$A12<=Products!$D$9),Products!$D$18,0) | M12: =L12*Products!$D$24*K12 | N12: =L12-M12 | O12: =(1-K12)*MAX(0,Products!$D$9-$A12)*(Products!$D$18-Products!$D$20/Products!$D$9) | P12: =IF($A12<=Products!$D$9,K12,0) | Q12: =M12*(1-Inputs!$C$23)-Inputs!$C$24*P12 | R12: =R11+Q12 | T12: =(1-Products!$E$23)^$A12 | U12: =IF(AND($A12>=1,$A12<=Products!$E$9),Products!$E$18,0) | V12: =U12*Products!$E$24*T12 | W12: =U12-V12 | X12: =(1-T12)*MAX(0,Products!$E$9-$A12)*(Products!$E$18-Products!$E$20/Products!$E$9) | Y12: =IF($A12<=Products!$E$9,T12,0) | Z12: =V12*(1-Inputs!$C$23)-Inputs!$C$24*Y12 | AA12: =AA11+Z12
A13: 5 | B13: =(1-Products!$C$23)^$A13 | C13: =IF(AND($A13>=1,$A13<=Products!$C$9),Products!$C$18,0) | D13: =C13*Products!$C$24*B13 | E13: =C13-D13 | F13: =(1-B13)*MAX(0,Products!$C$9-$A13)*(Products!$C$18-Products!$C$20/Products!$C$9) | G13: =IF($A13<=Products!$C$9,B13,0) | H13: =D13*(1-Inputs!$C$23)-Inputs!$C$24*G13 | I13: =I12+H13 | K13: =(1-Products!$D$23)^$A13 | L13: =IF(AND($A13>=1,$A13<=Products!$D$9),Products!$D$18,0) | M13: =L13*Products!$D$24*K13 | N13: =L13-M13 | O13: =(1-K13)*MAX(0,Products!$D$9-$A13)*(Products!$D$18-Products!$D$20/Products!$D$9) | P13: =IF($A13<=Products!$D$9,K13,0) | Q13: =M13*(1-Inputs!$C$23)-Inputs!$C$24*P13 | R13: =R12+Q13 | T13: =(1-Products!$E$23)^$A13 | U13: =IF(AND($A13>=1,$A13<=Products!$E$9),Products!$E$18,0) | V13: =U13*Products!$E$24*T13 | W13: =U13-V13 | X13: =(1-T13)*MAX(0,Products!$E$9-$A13)*(Products!$E$18-Products!$E$20/Products!$E$9) | Y13: =IF($A13<=Products!$E$9,T13,0) | Z13: =V13*(1-Inputs!$C$23)-Inputs!$C$24*Y13 | AA13: =AA12+Z13
A14: 6 | B14: =(1-Products!$C$23)^$A14 | C14: =IF(AND($A14>=1,$A14<=Products!$C$9),Products!$C$18,0) | D14: =C14*Products!$C$24*B14 | E14: =C14-D14 | F14: =(1-B14)*MAX(0,Products!$C$9-$A14)*(Products!$C$18-Products!$C$20/Products!$C$9) | G14: =IF($A14<=Products!$C$9,B14,0) | H14: =D14*(1-Inputs!$C$23)-Inputs!$C$24*G14 | I14: =I13+H14 | K14: =(1-Products!$D$23)^$A14 | L14: =IF(AND($A14>=1,$A14<=Products!$D$9),Products!$D$18,0) | M14: =L14*Products!$D$24*K14 | N14: =L14-M14 | O14: =(1-K14)*MAX(0,Products!$D$9-$A14)*(Products!$D$18-Products!$D$20/Products!$D$9) | P14: =IF($A14<=Products!$D$9,K14,0) | Q14: =M14*(1-Inputs!$C$23)-Inputs!$C$24*P14 | R14: =R13+Q14 | T14: =(1-Products!$E$23)^$A14 | U14: =IF(AND($A14>=1,$A14<=Products!$E$9),Products!$E$18,0) | V14: =U14*Products!$E$24*T14 | W14: =U14-V14 | X14: =(1-T14)*MAX(0,Products!$E$9-$A14)*(Products!$E$18-Products!$E$20/Products!$E$9) | Y14: =IF($A14<=Products!$E$9,T14,0) | Z14: =V14*(1-Inputs!$C$23)-Inputs!$C$24*Y14 | AA14: =AA13+Z14
A15: 7 | B15: =(1-Products!$C$23)^$A15 | C15: =IF(AND($A15>=1,$A15<=Products!$C$9),Products!$C$18,0) | D15: =C15*Products!$C$24*B15 | E15: =C15-D15 | F15: =(1-B15)*MAX(0,Products!$C$9-$A15)*(Products!$C$18-Products!$C$20/Products!$C$9) | G15: =IF($A15<=Products!$C$9,B15,0) | H15: =D15*(1-Inputs!$C$23)-Inputs!$C$24*G15 | I15: =I14+H15 | K15: =(1-Products!$D$23)^$A15 | L15: =IF(AND($A15>=1,$A15<=Products!$D$9),Products!$D$18,0) | M15: =L15*Products!$D$24*K15 | N15: =L15-M15 | O15: =(1-K15)*MAX(0,Products!$D$9-$A15)*(Products!$D$18-Products!$D$20/Products!$D$9) | P15: =IF($A15<=Products!$D$9,K15,0) | Q15: =M15*(1-Inputs!$C$23)-Inputs!$C$24*P15 | R15: =R14+Q15 | T15: =(1-Products!$E$23)^$A15 | U15: =IF(AND($A15>=1,$A15<=Products!$E$9),Products!$E$18,0) | V15: =U15*Products!$E$24*T15 | W15: =U15-V15 | X15: =(1-T15)*MAX(0,Products!$E$9-$A15)*(Products!$E$18-Products!$E$20/Products!$E$9) | Y15: =IF($A15<=Products!$E$9,T15,0) | Z15: =V15*(1-Inputs!$C$23)-Inputs!$C$24*Y15 | AA15: =AA14+Z15
A16: 8 | B16: =(1-Products!$C$23)^$A16 | C16: =IF(AND($A16>=1,$A16<=Products!$C$9),Products!$C$18,0) | D16: =C16*Products!$C$24*B16 | E16: =C16-D16 | F16: =(1-B16)*MAX(0,Products!$C$9-$A16)*(Products!$C$18-Products!$C$20/Products!$C$9) | G16: =IF($A16<=Products!$C$9,B16,0) | H16: =D16*(1-Inputs!$C$23)-Inputs!$C$24*G16 | I16: =I15+H16 | K16: =(1-Products!$D$23)^$A16 | L16: =IF(AND($A16>=1,$A16<=Products!$D$9),Products!$D$18,0) | M16: =L16*Products!$D$24*K16 | N16: =L16-M16 | O16: =(1-K16)*MAX(0,Products!$D$9-$A16)*(Products!$D$18-Products!$D$20/Products!$D$9) | P16: =IF($A16<=Products!$D$9,K16,0) | Q16: =M16*(1-Inputs!$C$23)-Inputs!$C$24*P16 | R16: =R15+Q16 | T16: =(1-Products!$E$23)^$A16 | U16: =IF(AND($A16>=1,$A16<=Products!$E$9),Products!$E$18,0) | V16: =U16*Products!$E$24*T16 | W16: =U16-V16 | X16: =(1-T16)*MAX(0,Products!$E$9-$A16)*(Products!$E$18-Products!$E$20/Products!$E$9) | Y16: =IF($A16<=Products!$E$9,T16,0) | Z16: =V16*(1-Inputs!$C$23)-Inputs!$C$24*Y16 | AA16: =AA15+Z16
A17: 9 | B17: =(1-Products!$C$23)^$A17 | C17: =IF(AND($A17>=1,$A17<=Products!$C$9),Products!$C$18,0) | D17: =C17*Products!$C$24*B17 | E17: =C17-D17 | F17: =(1-B17)*MAX(0,Products!$C$9-$A17)*(Products!$C$18-Products!$C$20/Products!$C$9) | G17: =IF($A17<=Products!$C$9,B17,0) | H17: =D17*(1-Inputs!$C$23)-Inputs!$C$24*G17 | I17: =I16+H17 | K17: =(1-Products!$D$23)^$A17 | L17: =IF(AND($A17>=1,$A17<=Products!$D$9),Products!$D$18,0) | M17: =L17*Products!$D$24*K17 | N17: =L17-M17 | O17: =(1-K17)*MAX(0,Products!$D$9-$A17)*(Products!$D$18-Products!$D$20/Products!$D$9) | P17: =IF($A17<=Products!$D$9,K17,0) | Q17: =M17*(1-Inputs!$C$23)-Inputs!$C$24*P17 | R17: =R16+Q17 | T17: =(1-Products!$E$23)^$A17 | U17: =IF(AND($A17>=1,$A17<=Products!$E$9),Products!$E$18,0) | V17: =U17*Products!$E$24*T17 | W17: =U17-V17 | X17: =(1-T17)*MAX(0,Products!$E$9-$A17)*(Products!$E$18-Products!$E$20/Products!$E$9) | Y17: =IF($A17<=Products!$E$9,T17,0) | Z17: =V17*(1-Inputs!$C$23)-Inputs!$C$24*Y17 | AA17: =AA16+Z17
A18: 10 | B18: =(1-Products!$C$23)^$A18 | C18: =IF(AND($A18>=1,$A18<=Products!$C$9),Products!$C$18,0) | D18: =C18*Products!$C$24*B18 | E18: =C18-D18 | F18: =(1-B18)*MAX(0,Products!$C$9-$A18)*(Products!$C$18-Products!$C$20/Products!$C$9) | G18: =IF($A18<=Products!$C$9,B18,0) | H18: =D18*(1-Inputs!$C$23)-Inputs!$C$24*G18 | I18: =I17+H18 | K18: =(1-Products!$D$23)^$A18 | L18: =IF(AND($A18>=1,$A18<=Products!$D$9),Products!$D$18,0) | M18: =L18*Products!$D$24*K18 | N18: =L18-M18 | O18: =(1-K18)*MAX(0,Products!$D$9-$A18)*(Products!$D$18-Products!$D$20/Products!$D$9) | P18: =IF($A18<=Products!$D$9,K18,0) | Q18: =M18*(1-Inputs!$C$23)-Inputs!$C$24*P18 | R18: =R17+Q18 | T18: =(1-Products!$E$23)^$A18 | U18: =IF(AND($A18>=1,$A18<=Products!$E$9),Products!$E$18,0) | V18: =U18*Products!$E$24*T18 | W18: =U18-V18 | X18: =(1-T18)*MAX(0,Products!$E$9-$A18)*(Products!$E$18-Products!$E$20/Products!$E$9) | Y18: =IF($A18<=Products!$E$9,T18,0) | Z18: =V18*(1-Inputs!$C$23)-Inputs!$C$24*Y18 | AA18: =AA17+Z18
A19: 11 | B19: =(1-Products!$C$23)^$A19 | C19: =IF(AND($A19>=1,$A19<=Products!$C$9),Products!$C$18,0) | D19: =C19*Products!$C$24*B19 | E19: =C19-D19 | F19: =(1-B19)*MAX(0,Products!$C$9-$A19)*(Products!$C$18-Products!$C$20/Products!$C$9) | G19: =IF($A19<=Products!$C$9,B19,0) | H19: =D19*(1-Inputs!$C$23)-Inputs!$C$24*G19 | I19: =I18+H19 | K19: =(1-Products!$D$23)^$A19 | L19: =IF(AND($A19>=1,$A19<=Products!$D$9),Products!$D$18,0) | M19: =L19*Products!$D$24*K19 | N19: =L19-M19 | O19: =(1-K19)*MAX(0,Products!$D$9-$A19)*(Products!$D$18-Products!$D$20/Products!$D$9) | P19: =IF($A19<=Products!$D$9,K19,0) | Q19: =M19*(1-Inputs!$C$23)-Inputs!$C$24*P19 | R19: =R18+Q19 | T19: =(1-Products!$E$23)^$A19 | U19: =IF(AND($A19>=1,$A19<=Products!$E$9),Products!$E$18,0) | V19: =U19*Products!$E$24*T19 | W19: =U19-V19 | X19: =(1-T19)*MAX(0,Products!$E$9-$A19)*(Products!$E$18-Products!$E$20/Products!$E$9) | Y19: =IF($A19<=Products!$E$9,T19,0) | Z19: =V19*(1-Inputs!$C$23)-Inputs!$C$24*Y19 | AA19: =AA18+Z19
A20: 12 | B20: =(1-Products!$C$23)^$A20 | C20: =IF(AND($A20>=1,$A20<=Products!$C$9),Products!$C$18,0) | D20: =C20*Products!$C$24*B20 | E20: =C20-D20 | F20: =(1-B20)*MAX(0,Products!$C$9-$A20)*(Products!$C$18-Products!$C$20/Products!$C$9) | G20: =IF($A20<=Products!$C$9,B20,0) | H20: =D20*(1-Inputs!$C$23)-Inputs!$C$24*G20 | I20: =I19+H20 | K20: =(1-Products!$D$23)^$A20 | L20: =IF(AND($A20>=1,$A20<=Products!$D$9),Products!$D$18,0) | M20: =L20*Products!$D$24*K20 | N20: =L20-M20 | O20: =(1-K20)*MAX(0,Products!$D$9-$A20)*(Products!$D$18-Products!$D$20/Products!$D$9) | P20: =IF($A20<=Products!$D$9,K20,0) | Q20: =M20*(1-Inputs!$C$23)-Inputs!$C$24*P20 | R20: =R19+Q20 | T20: =(1-Products!$E$23)^$A20 | U20: =IF(AND($A20>=1,$A20<=Products!$E$9),Products!$E$18,0) | V20: =U20*Products!$E$24*T20 | W20: =U20-V20 | X20: =(1-T20)*MAX(0,Products!$E$9-$A20)*(Products!$E$18-Products!$E$20/Products!$E$9) | Y20: =IF($A20<=Products!$E$9,T20,0) | Z20: =V20*(1-Inputs!$C$23)-Inputs!$C$24*Y20 | AA20: =AA19+Z20
... A68: 60 | B68: =(1-Products!$C$23)^$A68 | C68: =IF(AND($A68>=1,$A68<=Products!$C$9),Products!$C$18,0) | D68: =C68*Products!$C$24*B68 | E68: =C68-D68 | F68: =(1-B68)*MAX(0,Products!$C$9-$A68)*(Products!$C$18-Products!$C$20/Products!$C$9) | G68: =IF($A68<=Products!$C$9,B68,0) | H68: =D68*(1-Inputs!$C$23)-Inputs!$C$24*G68 | I68: =I67+H68 | K68: =(1-Products!$D$23)^$A68 | L68: =IF(AND($A68>=1,$A68<=Products!$D$9),Products!$D$18,0) | M68: =L68*Products!$D$24*K68 | N68: =L68-M68 | O68: =(1-K68)*MAX(0,Products!$D$9-$A68)*(Products!$D$18-Products!$D$20/Products!$D$9) | P68: =IF($A68<=Products!$D$9,K68,0) | Q68: =M68*(1-Inputs!$C$23)-Inputs!$C$24*P68 | R68: =R67+Q68 | T68: =(1-Products!$E$23)^$A68 | U68: =IF(AND($A68>=1,$A68<=Products!$E$9),Products!$E$18,0) | V68: =U68*Products!$E$24*T68 | W68: =U68-V68 | X68: =(1-T68)*MAX(0,Products!$E$9-$A68)*(Products!$E$18-Products!$E$20/Products!$E$9) | Y68: =IF($A68<=Products!$E$9,T68,0) | Z68: =V68*(1-Inputs!$C$23)-Inputs!$C$24*Y68 | AA68: =AA67+Z68
A70: Totals per unit (month-1 prices) | C70: =SUM(C8:C68) | D70: =SUM(D8:D68) | E70: =SUM(E8:E68) | L70: =SUM(L8:L68) | M70: =SUM(M8:M68) | N70: =SUM(N8:N68) | U70: =SUM(U8:U68) | V70: =SUM(V8:V68) | W70: =SUM(W8:W68)

Sheet Cohort_P1
A1: Cohort (vintage) matrix - P1 Solar lantern kit (Tier 1)
A2: Rows = sales cohort (month of sale); columns = calendar month. Cohort size in column C.
A4: Month # | D4: Opening | E4: =Timeline!E4 | F4: =Timeline!F4 | G4: =Timeline!G4 | H4: =Timeline!H4 | I4: =Timeline!I4 | J4: =Timeline!J4 | K4: =Timeline!K4 | L4: =Timeline!L4 | ... BL4: =Timeline!BL4
A5: Period end | E5: =Timeline!E5 | F5: =Timeline!F5 | G5: =Timeline!G5 | H5: =Timeline!H5 | I5: =Timeline!I5 | J5: =Timeline!J5 | K5: =Timeline!K5 | L5: =Timeline!L5 | ... BL5: =Timeline!BL5
A6: Year # | E6: =Timeline!E6 | F6: =Timeline!F6 | G6: =Timeline!G6 | H6: =Timeline!H6 | I6: =Timeline!I6 | J6: =Timeline!J6 | K6: =Timeline!K6 | L6: =Timeline!L6 | ... BL6: =Timeline!BL6
A8: Instalments collected by cohort (LCY)
A9: Total | E9: =SUM(E10:E69) | F9: =SUM(F10:F69) | G9: =SUM(G10:G69) | H9: =SUM(H10:H69) | I9: =SUM(I10:I69) | J9: =SUM(J10:J69) | K9: =SUM(K10:K69) | L9: =SUM(L10:L69) | ... BL9: =SUM(BL10:BL69)
A10: Cohort month 1 | B10: 1 | C10: =INDEX(Ops!$E$10:$BL$10,1,$B10) | F10: =$C10*INDEX(Curves!$D$8:$D$68,F$4-$B10+1) | G10: =$C10*INDEX(Curves!$D$8:$D$68,G$4-$B10+1) | H10: =$C10*INDEX(Curves!$D$8:$D$68,H$4-$B10+1) | I10: =$C10*INDEX(Curves!$D$8:$D$68,I$4-$B10+1) | J10: =$C10*INDEX(Curves!$D$8:$D$68,J$4-$B10+1) | K10: =$C10*INDEX(Curves!$D$8:$D$68,K$4-$B10+1) | L10: =$C10*INDEX(Curves!$D$8:$D$68,L$4-$B10+1) | M10: =$C10*INDEX(Curves!$D$8:$D$68,M$4-$B10+1) | ... BL10: =$C10*INDEX(Curves!$D$8:$D$68,BL$4-$B10+1)
A11: Cohort month 2 | B11: 2 | C11: =INDEX(Ops!$E$10:$BL$10,1,$B11) | G11: =$C11*INDEX(Curves!$D$8:$D$68,G$4-$B11+1) | H11: =$C11*INDEX(Curves!$D$8:$D$68,H$4-$B11+1) | I11: =$C11*INDEX(Curves!$D$8:$D$68,I$4-$B11+1) | J11: =$C11*INDEX(Curves!$D$8:$D$68,J$4-$B11+1) | K11: =$C11*INDEX(Curves!$D$8:$D$68,K$4-$B11+1) | L11: =$C11*INDEX(Curves!$D$8:$D$68,L$4-$B11+1) | M11: =$C11*INDEX(Curves!$D$8:$D$68,M$4-$B11+1) | N11: =$C11*INDEX(Curves!$D$8:$D$68,N$4-$B11+1) | ... BL11: =$C11*INDEX(Curves!$D$8:$D$68,BL$4-$B11+1)
A12: Cohort month 3 | B12: 3 | C12: =INDEX(Ops!$E$10:$BL$10,1,$B12) | H12: =$C12*INDEX(Curves!$D$8:$D$68,H$4-$B12+1) | I12: =$C12*INDEX(Curves!$D$8:$D$68,I$4-$B12+1) | J12: =$C12*INDEX(Curves!$D$8:$D$68,J$4-$B12+1) | K12: =$C12*INDEX(Curves!$D$8:$D$68,K$4-$B12+1) | L12: =$C12*INDEX(Curves!$D$8:$D$68,L$4-$B12+1) | M12: =$C12*INDEX(Curves!$D$8:$D$68,M$4-$B12+1) | N12: =$C12*INDEX(Curves!$D$8:$D$68,N$4-$B12+1) | O12: =$C12*INDEX(Curves!$D$8:$D$68,O$4-$B12+1) | ... BL12: =$C12*INDEX(Curves!$D$8:$D$68,BL$4-$B12+1)
A13: Cohort month 4 | B13: 4 | C13: =INDEX(Ops!$E$10:$BL$10,1,$B13) | I13: =$C13*INDEX(Curves!$D$8:$D$68,I$4-$B13+1) | J13: =$C13*INDEX(Curves!$D$8:$D$68,J$4-$B13+1) | K13: =$C13*INDEX(Curves!$D$8:$D$68,K$4-$B13+1) | L13: =$C13*INDEX(Curves!$D$8:$D$68,L$4-$B13+1) | M13: =$C13*INDEX(Curves!$D$8:$D$68,M$4-$B13+1) | N13: =$C13*INDEX(Curves!$D$8:$D$68,N$4-$B13+1) | O13: =$C13*INDEX(Curves!$D$8:$D$68,O$4-$B13+1) | P13: =$C13*INDEX(Curves!$D$8:$D$68,P$4-$B13+1) | ... BL13: =$C13*INDEX(Curves!$D$8:$D$68,BL$4-$B13+1)
A14: Cohort month 5 | B14: 5 | C14: =INDEX(Ops!$E$10:$BL$10,1,$B14) | J14: =$C14*INDEX(Curves!$D$8:$D$68,J$4-$B14+1) | K14: =$C14*INDEX(Curves!$D$8:$D$68,K$4-$B14+1) | L14: =$C14*INDEX(Curves!$D$8:$D$68,L$4-$B14+1) | M14: =$C14*INDEX(Curves!$D$8:$D$68,M$4-$B14+1) | N14: =$C14*INDEX(Curves!$D$8:$D$68,N$4-$B14+1) | O14: =$C14*INDEX(Curves!$D$8:$D$68,O$4-$B14+1) | P14: =$C14*INDEX(Curves!$D$8:$D$68,P$4-$B14+1) | Q14: =$C14*INDEX(Curves!$D$8:$D$68,Q$4-$B14+1) | ... BL14: =$C14*INDEX(Curves!$D$8:$D$68,BL$4-$B14+1)
A15: Cohort month 6 | B15: 6 | C15: =INDEX(Ops!$E$10:$BL$10,1,$B15) | K15: =$C15*INDEX(Curves!$D$8:$D$68,K$4-$B15+1) | L15: =$C15*INDEX(Curves!$D$8:$D$68,L$4-$B15+1) | M15: =$C15*INDEX(Curves!$D$8:$D$68,M$4-$B15+1) | N15: =$C15*INDEX(Curves!$D$8:$D$68,N$4-$B15+1) | O15: =$C15*INDEX(Curves!$D$8:$D$68,O$4-$B15+1) | P15: =$C15*INDEX(Curves!$D$8:$D$68,P$4-$B15+1) | Q15: =$C15*INDEX(Curves!$D$8:$D$68,Q$4-$B15+1) | R15: =$C15*INDEX(Curves!$D$8:$D$68,R$4-$B15+1) | ... BL15: =$C15*INDEX(Curves!$D$8:$D$68,BL$4-$B15+1)
A16: Cohort month 7 | B16: 7 | C16: =INDEX(Ops!$E$10:$BL$10,1,$B16) | L16: =$C16*INDEX(Curves!$D$8:$D$68,L$4-$B16+1) | M16: =$C16*INDEX(Curves!$D$8:$D$68,M$4-$B16+1) | N16: =$C16*INDEX(Curves!$D$8:$D$68,N$4-$B16+1) | O16: =$C16*INDEX(Curves!$D$8:$D$68,O$4-$B16+1) | P16: =$C16*INDEX(Curves!$D$8:$D$68,P$4-$B16+1) | Q16: =$C16*INDEX(Curves!$D$8:$D$68,Q$4-$B16+1) | R16: =$C16*INDEX(Curves!$D$8:$D$68,R$4-$B16+1) | S16: =$C16*INDEX(Curves!$D$8:$D$68,S$4-$B16+1) | ... BL16: =$C16*INDEX(Curves!$D$8:$D$68,BL$4-$B16+1)
A17: Cohort month 8 | B17: 8 | C17: =INDEX(Ops!$E$10:$BL$10,1,$B17) | M17: =$C17*INDEX(Curves!$D$8:$D$68,M$4-$B17+1) | N17: =$C17*INDEX(Curves!$D$8:$D$68,N$4-$B17+1) | O17: =$C17*INDEX(Curves!$D$8:$D$68,O$4-$B17+1) | P17: =$C17*INDEX(Curves!$D$8:$D$68,P$4-$B17+1) | Q17: =$C17*INDEX(Curves!$D$8:$D$68,Q$4-$B17+1) | R17: =$C17*INDEX(Curves!$D$8:$D$68,R$4-$B17+1) | S17: =$C17*INDEX(Curves!$D$8:$D$68,S$4-$B17+1) | T17: =$C17*INDEX(Curves!$D$8:$D$68,T$4-$B17+1) | ... BL17: =$C17*INDEX(Curves!$D$8:$D$68,BL$4-$B17+1)
A18: Cohort month 9 | B18: 9 | C18: =INDEX(Ops!$E$10:$BL$10,1,$B18) | N18: =$C18*INDEX(Curves!$D$8:$D$68,N$4-$B18+1) | O18: =$C18*INDEX(Curves!$D$8:$D$68,O$4-$B18+1) | P18: =$C18*INDEX(Curves!$D$8:$D$68,P$4-$B18+1) | Q18: =$C18*INDEX(Curves!$D$8:$D$68,Q$4-$B18+1) | R18: =$C18*INDEX(Curves!$D$8:$D$68,R$4-$B18+1) | S18: =$C18*INDEX(Curves!$D$8:$D$68,S$4-$B18+1) | T18: =$C18*INDEX(Curves!$D$8:$D$68,T$4-$B18+1) | U18: =$C18*INDEX(Curves!$D$8:$D$68,U$4-$B18+1) | ... BL18: =$C18*INDEX(Curves!$D$8:$D$68,BL$4-$B18+1)
A19: Cohort month 10 | B19: 10 | C19: =INDEX(Ops!$E$10:$BL$10,1,$B19) | O19: =$C19*INDEX(Curves!$D$8:$D$68,O$4-$B19+1) | P19: =$C19*INDEX(Curves!$D$8:$D$68,P$4-$B19+1) | Q19: =$C19*INDEX(Curves!$D$8:$D$68,Q$4-$B19+1) | R19: =$C19*INDEX(Curves!$D$8:$D$68,R$4-$B19+1) | S19: =$C19*INDEX(Curves!$D$8:$D$68,S$4-$B19+1) | T19: =$C19*INDEX(Curves!$D$8:$D$68,T$4-$B19+1) | U19: =$C19*INDEX(Curves!$D$8:$D$68,U$4-$B19+1) | V19: =$C19*INDEX(Curves!$D$8:$D$68,V$4-$B19+1) | ... BL19: =$C19*INDEX(Curves!$D$8:$D$68,BL$4-$B19+1)
A20: Cohort month 11 | B20: 11 | C20: =INDEX(Ops!$E$10:$BL$10,1,$B20) | P20: =$C20*INDEX(Curves!$D$8:$D$68,P$4-$B20+1) | Q20: =$C20*INDEX(Curves!$D$8:$D$68,Q$4-$B20+1) | R20: =$C20*INDEX(Curves!$D$8:$D$68,R$4-$B20+1) | S20: =$C20*INDEX(Curves!$D$8:$D$68,S$4-$B20+1) | T20: =$C20*INDEX(Curves!$D$8:$D$68,T$4-$B20+1) | U20: =$C20*INDEX(Curves!$D$8:$D$68,U$4-$B20+1) | V20: =$C20*INDEX(Curves!$D$8:$D$68,V$4-$B20+1) | W20: =$C20*INDEX(Curves!$D$8:$D$68,W$4-$B20+1) | ... BL20: =$C20*INDEX(Curves!$D$8:$D$68,BL$4-$B20+1)
A21: Cohort month 12 | B21: 12 | C21: =INDEX(Ops!$E$10:$BL$10,1,$B21) | Q21: =$C21*INDEX(Curves!$D$8:$D$68,Q$4-$B21+1) | R21: =$C21*INDEX(Curves!$D$8:$D$68,R$4-$B21+1) | S21: =$C21*INDEX(Curves!$D$8:$D$68,S$4-$B21+1) | T21: =$C21*INDEX(Curves!$D$8:$D$68,T$4-$B21+1) | U21: =$C21*INDEX(Curves!$D$8:$D$68,U$4-$B21+1) | V21: =$C21*INDEX(Curves!$D$8:$D$68,V$4-$B21+1) | W21: =$C21*INDEX(Curves!$D$8:$D$68,W$4-$B21+1) | X21: =$C21*INDEX(Curves!$D$8:$D$68,X$4-$B21+1) | ... BL21: =$C21*INDEX(Curves!$D$8:$D$68,BL$4-$B21+1)
A22: Cohort month 13 | B22: 13 | C22: =INDEX(Ops!$E$10:$BL$10,1,$B22) | R22: =$C22*INDEX(Curves!$D$8:$D$68,R$4-$B22+1) | S22: =$C22*INDEX(Curves!$D$8:$D$68,S$4-$B22+1) | T22: =$C22*INDEX(Curves!$D$8:$D$68,T$4-$B22+1) | U22: =$C22*INDEX(Curves!$D$8:$D$68,U$4-$B22+1) | V22: =$C22*INDEX(Curves!$D$8:$D$68,V$4-$B22+1) | W22: =$C22*INDEX(Curves!$D$8:$D$68,W$4-$B22+1) | X22: =$C22*INDEX(Curves!$D$8:$D$68,X$4-$B22+1) | Y22: =$C22*INDEX(Curves!$D$8:$D$68,Y$4-$B22+1) | ... BL22: =$C22*INDEX(Curves!$D$8:$D$68,BL$4-$B22+1)
A23: Cohort month 14 | B23: 14 | C23: =INDEX(Ops!$E$10:$BL$10,1,$B23) | S23: =$C23*INDEX(Curves!$D$8:$D$68,S$4-$B23+1) | T23: =$C23*INDEX(Curves!$D$8:$D$68,T$4-$B23+1) | U23: =$C23*INDEX(Curves!$D$8:$D$68,U$4-$B23+1) | V23: =$C23*INDEX(Curves!$D$8:$D$68,V$4-$B23+1) | W23: =$C23*INDEX(Curves!$D$8:$D$68,W$4-$B23+1) | X23: =$C23*INDEX(Curves!$D$8:$D$68,X$4-$B23+1) | Y23: =$C23*INDEX(Curves!$D$8:$D$68,Y$4-$B23+1) | Z23: =$C23*INDEX(Curves!$D$8:$D$68,Z$4-$B23+1) | ... BL23: =$C23*INDEX(Curves!$D$8:$D$68,BL$4-$B23+1)
A24: Cohort month 15 | B24: 15 | C24: =INDEX(Ops!$E$10:$BL$10,1,$B24) | T24: =$C24*INDEX(Curves!$D$8:$D$68,T$4-$B24+1) | U24: =$C24*INDEX(Curves!$D$8:$D$68,U$4-$B24+1) | V24: =$C24*INDEX(Curves!$D$8:$D$68,V$4-$B24+1) | W24: =$C24*INDEX(Curves!$D$8:$D$68,W$4-$B24+1) | X24: =$C24*INDEX(Curves!$D$8:$D$68,X$4-$B24+1) | Y24: =$C24*INDEX(Curves!$D$8:$D$68,Y$4-$B24+1) | Z24: =$C24*INDEX(Curves!$D$8:$D$68,Z$4-$B24+1) | AA24: =$C24*INDEX(Curves!$D$8:$D$68,AA$4-$B24+1) | ... BL24: =$C24*INDEX(Curves!$D$8:$D$68,BL$4-$B24+1)
A25: Cohort month 16 | B25: 16 | C25: =INDEX(Ops!$E$10:$BL$10,1,$B25) | U25: =$C25*INDEX(Curves!$D$8:$D$68,U$4-$B25+1) | V25: =$C25*INDEX(Curves!$D$8:$D$68,V$4-$B25+1) | W25: =$C25*INDEX(Curves!$D$8:$D$68,W$4-$B25+1) | X25: =$C25*INDEX(Curves!$D$8:$D$68,X$4-$B25+1) | Y25: =$C25*INDEX(Curves!$D$8:$D$68,Y$4-$B25+1) | Z25: =$C25*INDEX(Curves!$D$8:$D$68,Z$4-$B25+1) | AA25: =$C25*INDEX(Curves!$D$8:$D$68,AA$4-$B25+1) | AB25: =$C25*INDEX(Curves!$D$8:$D$68,AB$4-$B25+1) | ... BL25: =$C25*INDEX(Curves!$D$8:$D$68,BL$4-$B25+1)
A26: Cohort month 17 | B26: 17 | C26: =INDEX(Ops!$E$10:$BL$10,1,$B26) | V26: =$C26*INDEX(Curves!$D$8:$D$68,V$4-$B26+1) | W26: =$C26*INDEX(Curves!$D$8:$D$68,W$4-$B26+1) | X26: =$C26*INDEX(Curves!$D$8:$D$68,X$4-$B26+1) | Y26: =$C26*INDEX(Curves!$D$8:$D$68,Y$4-$B26+1) | Z26: =$C26*INDEX(Curves!$D$8:$D$68,Z$4-$B26+1) | AA26: =$C26*INDEX(Curves!$D$8:$D$68,AA$4-$B26+1) | AB26: =$C26*INDEX(Curves!$D$8:$D$68,AB$4-$B26+1) | AC26: =$C26*INDEX(Curves!$D$8:$D$68,AC$4-$B26+1) | ... BL26: =$C26*INDEX(Curves!$D$8:$D$68,BL$4-$B26+1)
A27: Cohort month 18 | B27: 18 | C27: =INDEX(Ops!$E$10:$BL$10,1,$B27) | W27: =$C27*INDEX(Curves!$D$8:$D$68,W$4-$B27+1) | X27: =$C27*INDEX(Curves!$D$8:$D$68,X$4-$B27+1) | Y27: =$C27*INDEX(Curves!$D$8:$D$68,Y$4-$B27+1) | Z27: =$C27*INDEX(Curves!$D$8:$D$68,Z$4-$B27+1) | AA27: =$C27*INDEX(Curves!$D$8:$D$68,AA$4-$B27+1) | AB27: =$C27*INDEX(Curves!$D$8:$D$68,AB$4-$B27+1) | AC27: =$C27*INDEX(Curves!$D$8:$D$68,AC$4-$B27+1) | AD27: =$C27*INDEX(Curves!$D$8:$D$68,AD$4-$B27+1) | ... BL27: =$C27*INDEX(Curves!$D$8:$D$68,BL$4-$B27+1)
A28: Cohort month 19 | B28: 19 | C28: =INDEX(Ops!$E$10:$BL$10,1,$B28) | X28: =$C28*INDEX(Curves!$D$8:$D$68,X$4-$B28+1) | Y28: =$C28*INDEX(Curves!$D$8:$D$68,Y$4-$B28+1) | Z28: =$C28*INDEX(Curves!$D$8:$D$68,Z$4-$B28+1) | AA28: =$C28*INDEX(Curves!$D$8:$D$68,AA$4-$B28+1) | AB28: =$C28*INDEX(Curves!$D$8:$D$68,AB$4-$B28+1) | AC28: =$C28*INDEX(Curves!$D$8:$D$68,AC$4-$B28+1) | AD28: =$C28*INDEX(Curves!$D$8:$D$68,AD$4-$B28+1) | AE28: =$C28*INDEX(Curves!$D$8:$D$68,AE$4-$B28+1) | ... BL28: =$C28*INDEX(Curves!$D$8:$D$68,BL$4-$B28+1)
A29: Cohort month 20 | B29: 20 | C29: =INDEX(Ops!$E$10:$BL$10,1,$B29) | Y29: =$C29*INDEX(Curves!$D$8:$D$68,Y$4-$B29+1) | Z29: =$C29*INDEX(Curves!$D$8:$D$68,Z$4-$B29+1) | AA29: =$C29*INDEX(Curves!$D$8:$D$68,AA$4-$B29+1) | AB29: =$C29*INDEX(Curves!$D$8:$D$68,AB$4-$B29+1) | AC29: =$C29*INDEX(Curves!$D$8:$D$68,AC$4-$B29+1) | AD29: =$C29*INDEX(Curves!$D$8:$D$68,AD$4-$B29+1) | AE29: =$C29*INDEX(Curves!$D$8:$D$68,AE$4-$B29+1) | AF29: =$C29*INDEX(Curves!$D$8:$D$68,AF$4-$B29+1) | ... BL29: =$C29*INDEX(Curves!$D$8:$D$68,BL$4-$B29+1)
A30: Cohort month 21 | B30: 21 | C30: =INDEX(Ops!$E$10:$BL$10,1,$B30) | Z30: =$C30*INDEX(Curves!$D$8:$D$68,Z$4-$B30+1) | AA30: =$C30*INDEX(Curves!$D$8:$D$68,AA$4-$B30+1) | AB30: =$C30*INDEX(Curves!$D$8:$D$68,AB$4-$B30+1) | AC30: =$C30*INDEX(Curves!$D$8:$D$68,AC$4-$B30+1) | AD30: =$C30*INDEX(Curves!$D$8:$D$68,AD$4-$B30+1) | AE30: =$C30*INDEX(Curves!$D$8:$D$68,AE$4-$B30+1) | AF30: =$C30*INDEX(Curves!$D$8:$D$68,AF$4-$B30+1) | AG30: =$C30*INDEX(Curves!$D$8:$D$68,AG$4-$B30+1) | ... BL30: =$C30*INDEX(Curves!$D$8:$D$68,BL$4-$B30+1)
A31: Cohort month 22 | B31: 22 | C31: =INDEX(Ops!$E$10:$BL$10,1,$B31) | AA31: =$C31*INDEX(Curves!$D$8:$D$68,AA$4-$B31+1) | AB31: =$C31*INDEX(Curves!$D$8:$D$68,AB$4-$B31+1) | AC31: =$C31*INDEX(Curves!$D$8:$D$68,AC$4-$B31+1) | AD31: =$C31*INDEX(Curves!$D$8:$D$68,AD$4-$B31+1) | AE31: =$C31*INDEX(Curves!$D$8:$D$68,AE$4-$B31+1) | AF31: =$C31*INDEX(Curves!$D$8:$D$68,AF$4-$B31+1) | AG31: =$C31*INDEX(Curves!$D$8:$D$68,AG$4-$B31+1) | AH31: =$C31*INDEX(Curves!$D$8:$D$68,AH$4-$B31+1) | ... BL31: =$C31*INDEX(Curves!$D$8:$D$68,BL$4-$B31+1)
A32: Cohort month 23 | B32: 23 | C32: =INDEX(Ops!$E$10:$BL$10,1,$B32) | AB32: =$C32*INDEX(Curves!$D$8:$D$68,AB$4-$B32+1) | AC32: =$C32*INDEX(Curves!$D$8:$D$68,AC$4-$B32+1) | AD32: =$C32*INDEX(Curves!$D$8:$D$68,AD$4-$B32+1) | AE32: =$C32*INDEX(Curves!$D$8:$D$68,AE$4-$B32+1) | AF32: =$C32*INDEX(Curves!$D$8:$D$68,AF$4-$B32+1) | AG32: =$C32*INDEX(Curves!$D$8:$D$68,AG$4-$B32+1) | AH32: =$C32*INDEX(Curves!$D$8:$D$68,AH$4-$B32+1) | AI32: =$C32*INDEX(Curves!$D$8:$D$68,AI$4-$B32+1) | ... BL32: =$C32*INDEX(Curves!$D$8:$D$68,BL$4-$B32+1)
A33: Cohort month 24 | B33: 24 | C33: =INDEX(Ops!$E$10:$BL$10,1,$B33) | AC33: =$C33*INDEX(Curves!$D$8:$D$68,AC$4-$B33+1) | AD33: =$C33*INDEX(Curves!$D$8:$D$68,AD$4-$B33+1) | AE33: =$C33*INDEX(Curves!$D$8:$D$68,AE$4-$B33+1) | AF33: =$C33*INDEX(Curves!$D$8:$D$68,AF$4-$B33+1) | AG33: =$C33*INDEX(Curves!$D$8:$D$68,AG$4-$B33+1) | AH33: =$C33*INDEX(Curves!$D$8:$D$68,AH$4-$B33+1) | AI33: =$C33*INDEX(Curves!$D$8:$D$68,AI$4-$B33+1) | AJ33: =$C33*INDEX(Curves!$D$8:$D$68,AJ$4-$B33+1) | ... BL33: =$C33*INDEX(Curves!$D$8:$D$68,BL$4-$B33+1)
A34: Cohort month 25 | B34: 25 | C34: =INDEX(Ops!$E$10:$BL$10,1,$B34) | AD34: =$C34*INDEX(Curves!$D$8:$D$68,AD$4-$B34+1) | AE34: =$C34*INDEX(Curves!$D$8:$D$68,AE$4-$B34+1) | AF34: =$C34*INDEX(Curves!$D$8:$D$68,AF$4-$B34+1) | AG34: =$C34*INDEX(Curves!$D$8:$D$68,AG$4-$B34+1) | AH34: =$C34*INDEX(Curves!$D$8:$D$68,AH$4-$B34+1) | AI34: =$C34*INDEX(Curves!$D$8:$D$68,AI$4-$B34+1) | AJ34: =$C34*INDEX(Curves!$D$8:$D$68,AJ$4-$B34+1) | AK34: =$C34*INDEX(Curves!$D$8:$D$68,AK$4-$B34+1) | ... BL34: =$C34*INDEX(Curves!$D$8:$D$68,BL$4-$B34+1)
A35: Cohort month 26 | B35: 26 | C35: =INDEX(Ops!$E$10:$BL$10,1,$B35) | AE35: =$C35*INDEX(Curves!$D$8:$D$68,AE$4-$B35+1) | AF35: =$C35*INDEX(Curves!$D$8:$D$68,AF$4-$B35+1) | AG35: =$C35*INDEX(Curves!$D$8:$D$68,AG$4-$B35+1) | AH35: =$C35*INDEX(Curves!$D$8:$D$68,AH$4-$B35+1) | AI35: =$C35*INDEX(Curves!$D$8:$D$68,AI$4-$B35+1) | AJ35: =$C35*INDEX(Curves!$D$8:$D$68,AJ$4-$B35+1) | AK35: =$C35*INDEX(Curves!$D$8:$D$68,AK$4-$B35+1) | AL35: =$C35*INDEX(Curves!$D$8:$D$68,AL$4-$B35+1) | ... BL35: =$C35*INDEX(Curves!$D$8:$D$68,BL$4-$B35+1)
A36: Cohort month 27 | B36: 27 | C36: =INDEX(Ops!$E$10:$BL$10,1,$B36) | AF36: =$C36*INDEX(Curves!$D$8:$D$68,AF$4-$B36+1) | AG36: =$C36*INDEX(Curves!$D$8:$D$68,AG$4-$B36+1) | AH36: =$C36*INDEX(Curves!$D$8:$D$68,AH$4-$B36+1) | AI36: =$C36*INDEX(Curves!$D$8:$D$68,AI$4-$B36+1) | AJ36: =$C36*INDEX(Curves!$D$8:$D$68,AJ$4-$B36+1) | AK36: =$C36*INDEX(Curves!$D$8:$D$68,AK$4-$B36+1) | AL36: =$C36*INDEX(Curves!$D$8:$D$68,AL$4-$B36+1) | AM36: =$C36*INDEX(Curves!$D$8:$D$68,AM$4-$B36+1) | ... BL36: =$C36*INDEX(Curves!$D$8:$D$68,BL$4-$B36+1)
A37: Cohort month 28 | B37: 28 | C37: =INDEX(Ops!$E$10:$BL$10,1,$B37) | AG37: =$C37*INDEX(Curves!$D$8:$D$68,AG$4-$B37+1) | AH37: =$C37*INDEX(Curves!$D$8:$D$68,AH$4-$B37+1) | AI37: =$C37*INDEX(Curves!$D$8:$D$68,AI$4-$B37+1) | AJ37: =$C37*INDEX(Curves!$D$8:$D$68,AJ$4-$B37+1) | AK37: =$C37*INDEX(Curves!$D$8:$D$68,AK$4-$B37+1) | AL37: =$C37*INDEX(Curves!$D$8:$D$68,AL$4-$B37+1) | AM37: =$C37*INDEX(Curves!$D$8:$D$68,AM$4-$B37+1) | AN37: =$C37*INDEX(Curves!$D$8:$D$68,AN$4-$B37+1) | ... BL37: =$C37*INDEX(Curves!$D$8:$D$68,BL$4-$B37+1)
A38: Cohort month 29 | B38: 29 | C38: =INDEX(Ops!$E$10:$BL$10,1,$B38) | AH38: =$C38*INDEX(Curves!$D$8:$D$68,AH$4-$B38+1) | AI38: =$C38*INDEX(Curves!$D$8:$D$68,AI$4-$B38+1) | AJ38: =$C38*INDEX(Curves!$D$8:$D$68,AJ$4-$B38+1) | AK38: =$C38*INDEX(Curves!$D$8:$D$68,AK$4-$B38+1) | AL38: =$C38*INDEX(Curves!$D$8:$D$68,AL$4-$B38+1) | AM38: =$C38*INDEX(Curves!$D$8:$D$68,AM$4-$B38+1) | AN38: =$C38*INDEX(Curves!$D$8:$D$68,AN$4-$B38+1) | AO38: =$C38*INDEX(Curves!$D$8:$D$68,AO$4-$B38+1) | ... BL38: =$C38*INDEX(Curves!$D$8:$D$68,BL$4-$B38+1)
A39: Cohort month 30 | B39: 30 | C39: =INDEX(Ops!$E$10:$BL$10,1,$B39) | AI39: =$C39*INDEX(Curves!$D$8:$D$68,AI$4-$B39+1) | AJ39: =$C39*INDEX(Curves!$D$8:$D$68,AJ$4-$B39+1) | AK39: =$C39*INDEX(Curves!$D$8:$D$68,AK$4-$B39+1) | AL39: =$C39*INDEX(Curves!$D$8:$D$68,AL$4-$B39+1) | AM39: =$C39*INDEX(Curves!$D$8:$D$68,AM$4-$B39+1) | AN39: =$C39*INDEX(Curves!$D$8:$D$68,AN$4-$B39+1) | AO39: =$C39*INDEX(Curves!$D$8:$D$68,AO$4-$B39+1) | AP39: =$C39*INDEX(Curves!$D$8:$D$68,AP$4-$B39+1) | ... BL39: =$C39*INDEX(Curves!$D$8:$D$68,BL$4-$B39+1)
A40: Cohort month 31 | B40: 31 | C40: =INDEX(Ops!$E$10:$BL$10,1,$B40) | AJ40: =$C40*INDEX(Curves!$D$8:$D$68,AJ$4-$B40+1) | AK40: =$C40*INDEX(Curves!$D$8:$D$68,AK$4-$B40+1) | AL40: =$C40*INDEX(Curves!$D$8:$D$68,AL$4-$B40+1) | AM40: =$C40*INDEX(Curves!$D$8:$D$68,AM$4-$B40+1) | AN40: =$C40*INDEX(Curves!$D$8:$D$68,AN$4-$B40+1) | AO40: =$C40*INDEX(Curves!$D$8:$D$68,AO$4-$B40+1) | AP40: =$C40*INDEX(Curves!$D$8:$D$68,AP$4-$B40+1) | AQ40: =$C40*INDEX(Curves!$D$8:$D$68,AQ$4-$B40+1) | ... BL40: =$C40*INDEX(Curves!$D$8:$D$68,BL$4-$B40+1)
A41: Cohort month 32 | B41: 32 | C41: =INDEX(Ops!$E$10:$BL$10,1,$B41) | AK41: =$C41*INDEX(Curves!$D$8:$D$68,AK$4-$B41+1) | AL41: =$C41*INDEX(Curves!$D$8:$D$68,AL$4-$B41+1) | AM41: =$C41*INDEX(Curves!$D$8:$D$68,AM$4-$B41+1) | AN41: =$C41*INDEX(Curves!$D$8:$D$68,AN$4-$B41+1) | AO41: =$C41*INDEX(Curves!$D$8:$D$68,AO$4-$B41+1) | AP41: =$C41*INDEX(Curves!$D$8:$D$68,AP$4-$B41+1) | AQ41: =$C41*INDEX(Curves!$D$8:$D$68,AQ$4-$B41+1) | AR41: =$C41*INDEX(Curves!$D$8:$D$68,AR$4-$B41+1) | ... BL41: =$C41*INDEX(Curves!$D$8:$D$68,BL$4-$B41+1)
A42: Cohort month 33 | B42: 33 | C42: =INDEX(Ops!$E$10:$BL$10,1,$B42) | AL42: =$C42*INDEX(Curves!$D$8:$D$68,AL$4-$B42+1) | AM42: =$C42*INDEX(Curves!$D$8:$D$68,AM$4-$B42+1) | AN42: =$C42*INDEX(Curves!$D$8:$D$68,AN$4-$B42+1) | AO42: =$C42*INDEX(Curves!$D$8:$D$68,AO$4-$B42+1) | AP42: =$C42*INDEX(Curves!$D$8:$D$68,AP$4-$B42+1) | AQ42: =$C42*INDEX(Curves!$D$8:$D$68,AQ$4-$B42+1) | AR42: =$C42*INDEX(Curves!$D$8:$D$68,AR$4-$B42+1) | AS42: =$C42*INDEX(Curves!$D$8:$D$68,AS$4-$B42+1) | ... BL42: =$C42*INDEX(Curves!$D$8:$D$68,BL$4-$B42+1)
A43: Cohort month 34 | B43: 34 | C43: =INDEX(Ops!$E$10:$BL$10,1,$B43) | AM43: =$C43*INDEX(Curves!$D$8:$D$68,AM$4-$B43+1) | AN43: =$C43*INDEX(Curves!$D$8:$D$68,AN$4-$B43+1) | AO43: =$C43*INDEX(Curves!$D$8:$D$68,AO$4-$B43+1) | AP43: =$C43*INDEX(Curves!$D$8:$D$68,AP$4-$B43+1) | AQ43: =$C43*INDEX(Curves!$D$8:$D$68,AQ$4-$B43+1) | AR43: =$C43*INDEX(Curves!$D$8:$D$68,AR$4-$B43+1) | AS43: =$C43*INDEX(Curves!$D$8:$D$68,AS$4-$B43+1) | AT43: =$C43*INDEX(Curves!$D$8:$D$68,AT$4-$B43+1) | ... BL43: =$C43*INDEX(Curves!$D$8:$D$68,BL$4-$B43+1)
A44: Cohort month 35 | B44: 35 | C44: =INDEX(Ops!$E$10:$BL$10,1,$B44) | AN44: =$C44*INDEX(Curves!$D$8:$D$68,AN$4-$B44+1) | AO44: =$C44*INDEX(Curves!$D$8:$D$68,AO$4-$B44+1) | AP44: =$C44*INDEX(Curves!$D$8:$D$68,AP$4-$B44+1) | AQ44: =$C44*INDEX(Curves!$D$8:$D$68,AQ$4-$B44+1) | AR44: =$C44*INDEX(Curves!$D$8:$D$68,AR$4-$B44+1) | AS44: =$C44*INDEX(Curves!$D$8:$D$68,AS$4-$B44+1) | AT44: =$C44*INDEX(Curves!$D$8:$D$68,AT$4-$B44+1) | AU44: =$C44*INDEX(Curves!$D$8:$D$68,AU$4-$B44+1) | ... BL44: =$C44*INDEX(Curves!$D$8:$D$68,BL$4-$B44+1)
A45: Cohort month 36 | B45: 36 | C45: =INDEX(Ops!$E$10:$BL$10,1,$B45) | AO45: =$C45*INDEX(Curves!$D$8:$D$68,AO$4-$B45+1) | AP45: =$C45*INDEX(Curves!$D$8:$D$68,AP$4-$B45+1) | AQ45: =$C45*INDEX(Curves!$D$8:$D$68,AQ$4-$B45+1) | AR45: =$C45*INDEX(Curves!$D$8:$D$68,AR$4-$B45+1) | AS45: =$C45*INDEX(Curves!$D$8:$D$68,AS$4-$B45+1) | AT45: =$C45*INDEX(Curves!$D$8:$D$68,AT$4-$B45+1) | AU45: =$C45*INDEX(Curves!$D$8:$D$68,AU$4-$B45+1) | AV45: =$C45*INDEX(Curves!$D$8:$D$68,AV$4-$B45+1) | ... BL45: =$C45*INDEX(Curves!$D$8:$D$68,BL$4-$B45+1)
A46: Cohort month 37 | B46: 37 | C46: =INDEX(Ops!$E$10:$BL$10,1,$B46) | AP46: =$C46*INDEX(Curves!$D$8:$D$68,AP$4-$B46+1) | AQ46: =$C46*INDEX(Curves!$D$8:$D$68,AQ$4-$B46+1) | AR46: =$C46*INDEX(Curves!$D$8:$D$68,AR$4-$B46+1) | AS46: =$C46*INDEX(Curves!$D$8:$D$68,AS$4-$B46+1) | AT46: =$C46*INDEX(Curves!$D$8:$D$68,AT$4-$B46+1) | AU46: =$C46*INDEX(Curves!$D$8:$D$68,AU$4-$B46+1) | AV46: =$C46*INDEX(Curves!$D$8:$D$68,AV$4-$B46+1) | AW46: =$C46*INDEX(Curves!$D$8:$D$68,AW$4-$B46+1) | ... BL46: =$C46*INDEX(Curves!$D$8:$D$68,BL$4-$B46+1)
A47: Cohort month 38 | B47: 38 | C47: =INDEX(Ops!$E$10:$BL$10,1,$B47) | AQ47: =$C47*INDEX(Curves!$D$8:$D$68,AQ$4-$B47+1) | AR47: =$C47*INDEX(Curves!$D$8:$D$68,AR$4-$B47+1) | AS47: =$C47*INDEX(Curves!$D$8:$D$68,AS$4-$B47+1) | AT47: =$C47*INDEX(Curves!$D$8:$D$68,AT$4-$B47+1) | AU47: =$C47*INDEX(Curves!$D$8:$D$68,AU$4-$B47+1) | AV47: =$C47*INDEX(Curves!$D$8:$D$68,AV$4-$B47+1) | AW47: =$C47*INDEX(Curves!$D$8:$D$68,AW$4-$B47+1) | AX47: =$C47*INDEX(Curves!$D$8:$D$68,AX$4-$B47+1) | ... BL47: =$C47*INDEX(Curves!$D$8:$D$68,BL$4-$B47+1)
A48: Cohort month 39 | B48: 39 | C48: =INDEX(Ops!$E$10:$BL$10,1,$B48) | AR48: =$C48*INDEX(Curves!$D$8:$D$68,AR$4-$B48+1) | AS48: =$C48*INDEX(Curves!$D$8:$D$68,AS$4-$B48+1) | AT48: =$C48*INDEX(Curves!$D$8:$D$68,AT$4-$B48+1) | AU48: =$C48*INDEX(Curves!$D$8:$D$68,AU$4-$B48+1) | AV48: =$C48*INDEX(Curves!$D$8:$D$68,AV$4-$B48+1) | AW48: =$C48*INDEX(Curves!$D$8:$D$68,AW$4-$B48+1) | AX48: =$C48*INDEX(Curves!$D$8:$D$68,AX$4-$B48+1) | AY48: =$C48*INDEX(Curves!$D$8:$D$68,AY$4-$B48+1) | ... BL48: =$C48*INDEX(Curves!$D$8:$D$68,BL$4-$B48+1)
A49: Cohort month 40 | B49: 40 | C49: =INDEX(Ops!$E$10:$BL$10,1,$B49) | AS49: =$C49*INDEX(Curves!$D$8:$D$68,AS$4-$B49+1) | AT49: =$C49*INDEX(Curves!$D$8:$D$68,AT$4-$B49+1) | AU49: =$C49*INDEX(Curves!$D$8:$D$68,AU$4-$B49+1) | AV49: =$C49*INDEX(Curves!$D$8:$D$68,AV$4-$B49+1) | AW49: =$C49*INDEX(Curves!$D$8:$D$68,AW$4-$B49+1) | AX49: =$C49*INDEX(Curves!$D$8:$D$68,AX$4-$B49+1) | AY49: =$C49*INDEX(Curves!$D$8:$D$68,AY$4-$B49+1) | AZ49: =$C49*INDEX(Curves!$D$8:$D$68,AZ$4-$B49+1) | ... BL49: =$C49*INDEX(Curves!$D$8:$D$68,BL$4-$B49+1)
A50: Cohort month 41 | B50: 41 | C50: =INDEX(Ops!$E$10:$BL$10,1,$B50) | AT50: =$C50*INDEX(Curves!$D$8:$D$68,AT$4-$B50+1) | AU50: =$C50*INDEX(Curves!$D$8:$D$68,AU$4-$B50+1) | AV50: =$C50*INDEX(Curves!$D$8:$D$68,AV$4-$B50+1) | AW50: =$C50*INDEX(Curves!$D$8:$D$68,AW$4-$B50+1) | AX50: =$C50*INDEX(Curves!$D$8:$D$68,AX$4-$B50+1) | AY50: =$C50*INDEX(Curves!$D$8:$D$68,AY$4-$B50+1) | AZ50: =$C50*INDEX(Curves!$D$8:$D$68,AZ$4-$B50+1) | BA50: =$C50*INDEX(Curves!$D$8:$D$68,BA$4-$B50+1) | ... BL50: =$C50*INDEX(Curves!$D$8:$D$68,BL$4-$B50+1)
A51: Cohort month 42 | B51: 42 | C51: =INDEX(Ops!$E$10:$BL$10,1,$B51) | AU51: =$C51*INDEX(Curves!$D$8:$D$68,AU$4-$B51+1) | AV51: =$C51*INDEX(Curves!$D$8:$D$68,AV$4-$B51+1) | AW51: =$C51*INDEX(Curves!$D$8:$D$68,AW$4-$B51+1) | AX51: =$C51*INDEX(Curves!$D$8:$D$68,AX$4-$B51+1) | AY51: =$C51*INDEX(Curves!$D$8:$D$68,AY$4-$B51+1) | AZ51: =$C51*INDEX(Curves!$D$8:$D$68,AZ$4-$B51+1) | BA51: =$C51*INDEX(Curves!$D$8:$D$68,BA$4-$B51+1) | BB51: =$C51*INDEX(Curves!$D$8:$D$68,BB$4-$B51+1) | ... BL51: =$C51*INDEX(Curves!$D$8:$D$68,BL$4-$B51+1)
A52: Cohort month 43 | B52: 43 | C52: =INDEX(Ops!$E$10:$BL$10,1,$B52) | AV52: =$C52*INDEX(Curves!$D$8:$D$68,AV$4-$B52+1) | AW52: =$C52*INDEX(Curves!$D$8:$D$68,AW$4-$B52+1) | AX52: =$C52*INDEX(Curves!$D$8:$D$68,AX$4-$B52+1) | AY52: =$C52*INDEX(Curves!$D$8:$D$68,AY$4-$B52+1) | AZ52: =$C52*INDEX(Curves!$D$8:$D$68,AZ$4-$B52+1) | BA52: =$C52*INDEX(Curves!$D$8:$D$68,BA$4-$B52+1) | BB52: =$C52*INDEX(Curves!$D$8:$D$68,BB$4-$B52+1) | BC52: =$C52*INDEX(Curves!$D$8:$D$68,BC$4-$B52+1) | ... BL52: =$C52*INDEX(Curves!$D$8:$D$68,BL$4-$B52+1)
A53: Cohort month 44 | B53: 44 | C53: =INDEX(Ops!$E$10:$BL$10,1,$B53) | AW53: =$C53*INDEX(Curves!$D$8:$D$68,AW$4-$B53+1) | AX53: =$C53*INDEX(Curves!$D$8:$D$68,AX$4-$B53+1) | AY53: =$C53*INDEX(Curves!$D$8:$D$68,AY$4-$B53+1) | AZ53: =$C53*INDEX(Curves!$D$8:$D$68,AZ$4-$B53+1) | BA53: =$C53*INDEX(Curves!$D$8:$D$68,BA$4-$B53+1) | BB53: =$C53*INDEX(Curves!$D$8:$D$68,BB$4-$B53+1) | BC53: =$C53*INDEX(Curves!$D$8:$D$68,BC$4-$B53+1) | BD53: =$C53*INDEX(Curves!$D$8:$D$68,BD$4-$B53+1) | ... BL53: =$C53*INDEX(Curves!$D$8:$D$68,BL$4-$B53+1)
A54: Cohort month 45 | B54: 45 | C54: =INDEX(Ops!$E$10:$BL$10,1,$B54) | AX54: =$C54*INDEX(Curves!$D$8:$D$68,AX$4-$B54+1) | AY54: =$C54*INDEX(Curves!$D$8:$D$68,AY$4-$B54+1) | AZ54: =$C54*INDEX(Curves!$D$8:$D$68,AZ$4-$B54+1) | BA54: =$C54*INDEX(Curves!$D$8:$D$68,BA$4-$B54+1) | BB54: =$C54*INDEX(Curves!$D$8:$D$68,BB$4-$B54+1) | BC54: =$C54*INDEX(Curves!$D$8:$D$68,BC$4-$B54+1) | BD54: =$C54*INDEX(Curves!$D$8:$D$68,BD$4-$B54+1) | BE54: =$C54*INDEX(Curves!$D$8:$D$68,BE$4-$B54+1) | ... BL54: =$C54*INDEX(Curves!$D$8:$D$68,BL$4-$B54+1)
A55: Cohort month 46 | B55: 46 | C55: =INDEX(Ops!$E$10:$BL$10,1,$B55) | AY55: =$C55*INDEX(Curves!$D$8:$D$68,AY$4-$B55+1) | AZ55: =$C55*INDEX(Curves!$D$8:$D$68,AZ$4-$B55+1) | BA55: =$C55*INDEX(Curves!$D$8:$D$68,BA$4-$B55+1) | BB55: =$C55*INDEX(Curves!$D$8:$D$68,BB$4-$B55+1) | BC55: =$C55*INDEX(Curves!$D$8:$D$68,BC$4-$B55+1) | BD55: =$C55*INDEX(Curves!$D$8:$D$68,BD$4-$B55+1) | BE55: =$C55*INDEX(Curves!$D$8:$D$68,BE$4-$B55+1) | BF55: =$C55*INDEX(Curves!$D$8:$D$68,BF$4-$B55+1) | ... BL55: =$C55*INDEX(Curves!$D$8:$D$68,BL$4-$B55+1)
A56: Cohort month 47 | B56: 47 | C56: =INDEX(Ops!$E$10:$BL$10,1,$B56) | AZ56: =$C56*INDEX(Curves!$D$8:$D$68,AZ$4-$B56+1) | BA56: =$C56*INDEX(Curves!$D$8:$D$68,BA$4-$B56+1) | BB56: =$C56*INDEX(Curves!$D$8:$D$68,BB$4-$B56+1) | BC56: =$C56*INDEX(Curves!$D$8:$D$68,BC$4-$B56+1) | BD56: =$C56*INDEX(Curves!$D$8:$D$68,BD$4-$B56+1) | BE56: =$C56*INDEX(Curves!$D$8:$D$68,BE$4-$B56+1) | BF56: =$C56*INDEX(Curves!$D$8:$D$68,BF$4-$B56+1) | BG56: =$C56*INDEX(Curves!$D$8:$D$68,BG$4-$B56+1) | ... BL56: =$C56*INDEX(Curves!$D$8:$D$68,BL$4-$B56+1)
A57: Cohort month 48 | B57: 48 | C57: =INDEX(Ops!$E$10:$BL$10,1,$B57) | BA57: =$C57*INDEX(Curves!$D$8:$D$68,BA$4-$B57+1) | BB57: =$C57*INDEX(Curves!$D$8:$D$68,BB$4-$B57+1) | BC57: =$C57*INDEX(Curves!$D$8:$D$68,BC$4-$B57+1) | BD57: =$C57*INDEX(Curves!$D$8:$D$68,BD$4-$B57+1) | BE57: =$C57*INDEX(Curves!$D$8:$D$68,BE$4-$B57+1) | BF57: =$C57*INDEX(Curves!$D$8:$D$68,BF$4-$B57+1) | BG57: =$C57*INDEX(Curves!$D$8:$D$68,BG$4-$B57+1) | BH57: =$C57*INDEX(Curves!$D$8:$D$68,BH$4-$B57+1) | ... BL57: =$C57*INDEX(Curves!$D$8:$D$68,BL$4-$B57+1)
A58: Cohort month 49 | B58: 49 | C58: =INDEX(Ops!$E$10:$BL$10,1,$B58) | BB58: =$C58*INDEX(Curves!$D$8:$D$68,BB$4-$B58+1) | BC58: =$C58*INDEX(Curves!$D$8:$D$68,BC$4-$B58+1) | BD58: =$C58*INDEX(Curves!$D$8:$D$68,BD$4-$B58+1) | BE58: =$C58*INDEX(Curves!$D$8:$D$68,BE$4-$B58+1) | BF58: =$C58*INDEX(Curves!$D$8:$D$68,BF$4-$B58+1) | BG58: =$C58*INDEX(Curves!$D$8:$D$68,BG$4-$B58+1) | BH58: =$C58*INDEX(Curves!$D$8:$D$68,BH$4-$B58+1) | BI58: =$C58*INDEX(Curves!$D$8:$D$68,BI$4-$B58+1) | ... BL58: =$C58*INDEX(Curves!$D$8:$D$68,BL$4-$B58+1)
A59: Cohort month 50 | B59: 50 | C59: =INDEX(Ops!$E$10:$BL$10,1,$B59) | BC59: =$C59*INDEX(Curves!$D$8:$D$68,BC$4-$B59+1) | BD59: =$C59*INDEX(Curves!$D$8:$D$68,BD$4-$B59+1) | BE59: =$C59*INDEX(Curves!$D$8:$D$68,BE$4-$B59+1) | BF59: =$C59*INDEX(Curves!$D$8:$D$68,BF$4-$B59+1) | BG59: =$C59*INDEX(Curves!$D$8:$D$68,BG$4-$B59+1) | BH59: =$C59*INDEX(Curves!$D$8:$D$68,BH$4-$B59+1) | BI59: =$C59*INDEX(Curves!$D$8:$D$68,BI$4-$B59+1) | BJ59: =$C59*INDEX(Curves!$D$8:$D$68,BJ$4-$B59+1) | ... BL59: =$C59*INDEX(Curves!$D$8:$D$68,BL$4-$B59+1)
A60: Cohort month 51 | B60: 51 | C60: =INDEX(Ops!$E$10:$BL$10,1,$B60) | BD60: =$C60*INDEX(Curves!$D$8:$D$68,BD$4-$B60+1) | BE60: =$C60*INDEX(Curves!$D$8:$D$68,BE$4-$B60+1) | BF60: =$C60*INDEX(Curves!$D$8:$D$68,BF$4-$B60+1) | BG60: =$C60*INDEX(Curves!$D$8:$D$68,BG$4-$B60+1) | BH60: =$C60*INDEX(Curves!$D$8:$D$68,BH$4-$B60+1) | BI60: =$C60*INDEX(Curves!$D$8:$D$68,BI$4-$B60+1) | BJ60: =$C60*INDEX(Curves!$D$8:$D$68,BJ$4-$B60+1) | BK60: =$C60*INDEX(Curves!$D$8:$D$68,BK$4-$B60+1) | BL60: =$C60*INDEX(Curves!$D$8:$D$68,BL$4-$B60+1)
A61: Cohort month 52 | B61: 52 | C61: =INDEX(Ops!$E$10:$BL$10,1,$B61) | BE61: =$C61*INDEX(Curves!$D$8:$D$68,BE$4-$B61+1) | BF61: =$C61*INDEX(Curves!$D$8:$D$68,BF$4-$B61+1) | BG61: =$C61*INDEX(Curves!$D$8:$D$68,BG$4-$B61+1) | BH61: =$C61*INDEX(Curves!$D$8:$D$68,BH$4-$B61+1) | BI61: =$C61*INDEX(Curves!$D$8:$D$68,BI$4-$B61+1) | BJ61: =$C61*INDEX(Curves!$D$8:$D$68,BJ$4-$B61+1) | BK61: =$C61*INDEX(Curves!$D$8:$D$68,BK$4-$B61+1) | BL61: =$C61*INDEX(Curves!$D$8:$D$68,BL$4-$B61+1)
A62: Cohort month 53 | B62: 53 | C62: =INDEX(Ops!$E$10:$BL$10,1,$B62) | BF62: =$C62*INDEX(Curves!$D$8:$D$68,BF$4-$B62+1) | BG62: =$C62*INDEX(Curves!$D$8:$D$68,BG$4-$B62+1) | BH62: =$C62*INDEX(Curves!$D$8:$D$68,BH$4-$B62+1) | BI62: =$C62*INDEX(Curves!$D$8:$D$68,BI$4-$B62+1) | BJ62: =$C62*INDEX(Curves!$D$8:$D$68,BJ$4-$B62+1) | BK62: =$C62*INDEX(Curves!$D$8:$D$68,BK$4-$B62+1) | BL62: =$C62*INDEX(Curves!$D$8:$D$68,BL$4-$B62+1)
A63: Cohort month 54 | B63: 54 | C63: =INDEX(Ops!$E$10:$BL$10,1,$B63) | BG63: =$C63*INDEX(Curves!$D$8:$D$68,BG$4-$B63+1) | BH63: =$C63*INDEX(Curves!$D$8:$D$68,BH$4-$B63+1) | BI63: =$C63*INDEX(Curves!$D$8:$D$68,BI$4-$B63+1) | BJ63: =$C63*INDEX(Curves!$D$8:$D$68,BJ$4-$B63+1) | BK63: =$C63*INDEX(Curves!$D$8:$D$68,BK$4-$B63+1) | BL63: =$C63*INDEX(Curves!$D$8:$D$68,BL$4-$B63+1)
A64: Cohort month 55 | B64: 55 | C64: =INDEX(Ops!$E$10:$BL$10,1,$B64) | BH64: =$C64*INDEX(Curves!$D$8:$D$68,BH$4-$B64+1) | BI64: =$C64*INDEX(Curves!$D$8:$D$68,BI$4-$B64+1) | BJ64: =$C64*INDEX(Curves!$D$8:$D$68,BJ$4-$B64+1) | BK64: =$C64*INDEX(Curves!$D$8:$D$68,BK$4-$B64+1) | BL64: =$C64*INDEX(Curves!$D$8:$D$68,BL$4-$B64+1)
A65: Cohort month 56 | B65: 56 | C65: =INDEX(Ops!$E$10:$BL$10,1,$B65) | BI65: =$C65*INDEX(Curves!$D$8:$D$68,BI$4-$B65+1) | BJ65: =$C65*INDEX(Curves!$D$8:$D$68,BJ$4-$B65+1) | BK65: =$C65*INDEX(Curves!$D$8:$D$68,BK$4-$B65+1) | BL65: =$C65*INDEX(Curves!$D$8:$D$68,BL$4-$B65+1)
A66: Cohort month 57 | B66: 57 | C66: =INDEX(Ops!$E$10:$BL$10,1,$B66) | BJ66: =$C66*INDEX(Curves!$D$8:$D$68,BJ$4-$B66+1) | BK66: =$C66*INDEX(Curves!$D$8:$D$68,BK$4-$B66+1) | BL66: =$C66*INDEX(Curves!$D$8:$D$68,BL$4-$B66+1)
A67: Cohort month 58 | B67: 58 | C67: =INDEX(Ops!$E$10:$BL$10,1,$B67) | BK67: =$C67*INDEX(Curves!$D$8:$D$68,BK$4-$B67+1) | BL67: =$C67*INDEX(Curves!$D$8:$D$68,BL$4-$B67+1)
A68: Cohort month 59 | B68: 59 | C68: =INDEX(Ops!$E$10:$BL$10,1,$B68) | BL68: =$C68*INDEX(Curves!$D$8:$D$68,BL$4-$B68+1)
A69: Cohort month 60 | B69: 60 | C69: =INDEX(Ops!$E$10:$BL$10,1,$B69)
A71: Active accounts by cohort
A72: Total | E72: =SUM(E73:E132) | F72: =SUM(F73:F132) | G72: =SUM(G73:G132) | H72: =SUM(H73:H132) | I72: =SUM(I73:I132) | J72: =SUM(J73:J132) | K72: =SUM(K73:K132) | L72: =SUM(L73:L132) | ... BL72: =SUM(BL73:BL132)
A73: Cohort month 1 | B73: 1 | C73: =INDEX(Ops!$E$9:$BL$9,1,$B73) | F73: =$C73*INDEX(Curves!$G$8:$G$68,F$4-$B73+1) | G73: =$C73*INDEX(Curves!$G$8:$G$68,G$4-$B73+1) | H73: =$C73*INDEX(Curves!$G$8:$G$68,H$4-$B73+1) | I73: =$C73*INDEX(Curves!$G$8:$G$68,I$4-$B73+1) | J73: =$C73*INDEX(Curves!$G$8:$G$68,J$4-$B73+1) | K73: =$C73*INDEX(Curves!$G$8:$G$68,K$4-$B73+1) | L73: =$C73*INDEX(Curves!$G$8:$G$68,L$4-$B73+1) | M73: =$C73*INDEX(Curves!$G$8:$G$68,M$4-$B73+1) | ... BL73: =$C73*INDEX(Curves!$G$8:$G$68,BL$4-$B73+1)
A74: Cohort month 2 | B74: 2 | C74: =INDEX(Ops!$E$9:$BL$9,1,$B74) | G74: =$C74*INDEX(Curves!$G$8:$G$68,G$4-$B74+1) | H74: =$C74*INDEX(Curves!$G$8:$G$68,H$4-$B74+1) | I74: =$C74*INDEX(Curves!$G$8:$G$68,I$4-$B74+1) | J74: =$C74*INDEX(Curves!$G$8:$G$68,J$4-$B74+1) | K74: =$C74*INDEX(Curves!$G$8:$G$68,K$4-$B74+1) | L74: =$C74*INDEX(Curves!$G$8:$G$68,L$4-$B74+1) | M74: =$C74*INDEX(Curves!$G$8:$G$68,M$4-$B74+1) | N74: =$C74*INDEX(Curves!$G$8:$G$68,N$4-$B74+1) | ... BL74: =$C74*INDEX(Curves!$G$8:$G$68,BL$4-$B74+1)
A75: Cohort month 3 | B75: 3 | C75: =INDEX(Ops!$E$9:$BL$9,1,$B75) | H75: =$C75*INDEX(Curves!$G$8:$G$68,H$4-$B75+1) | I75: =$C75*INDEX(Curves!$G$8:$G$68,I$4-$B75+1) | J75: =$C75*INDEX(Curves!$G$8:$G$68,J$4-$B75+1) | K75: =$C75*INDEX(Curves!$G$8:$G$68,K$4-$B75+1) | L75: =$C75*INDEX(Curves!$G$8:$G$68,L$4-$B75+1) | M75: =$C75*INDEX(Curves!$G$8:$G$68,M$4-$B75+1) | N75: =$C75*INDEX(Curves!$G$8:$G$68,N$4-$B75+1) | O75: =$C75*INDEX(Curves!$G$8:$G$68,O$4-$B75+1) | ... BL75: =$C75*INDEX(Curves!$G$8:$G$68,BL$4-$B75+1)
A76: Cohort month 4 | B76: 4 | C76: =INDEX(Ops!$E$9:$BL$9,1,$B76) | I76: =$C76*INDEX(Curves!$G$8:$G$68,I$4-$B76+1) | J76: =$C76*INDEX(Curves!$G$8:$G$68,J$4-$B76+1) | K76: =$C76*INDEX(Curves!$G$8:$G$68,K$4-$B76+1) | L76: =$C76*INDEX(Curves!$G$8:$G$68,L$4-$B76+1) | M76: =$C76*INDEX(Curves!$G$8:$G$68,M$4-$B76+1) | N76: =$C76*INDEX(Curves!$G$8:$G$68,N$4-$B76+1) | O76: =$C76*INDEX(Curves!$G$8:$G$68,O$4-$B76+1) | P76: =$C76*INDEX(Curves!$G$8:$G$68,P$4-$B76+1) | ... BL76: =$C76*INDEX(Curves!$G$8:$G$68,BL$4-$B76+1)
A77: Cohort month 5 | B77: 5 | C77: =INDEX(Ops!$E$9:$BL$9,1,$B77) | J77: =$C77*INDEX(Curves!$G$8:$G$68,J$4-$B77+1) | K77: =$C77*INDEX(Curves!$G$8:$G$68,K$4-$B77+1) | L77: =$C77*INDEX(Curves!$G$8:$G$68,L$4-$B77+1) | M77: =$C77*INDEX(Curves!$G$8:$G$68,M$4-$B77+1) | N77: =$C77*INDEX(Curves!$G$8:$G$68,N$4-$B77+1) | O77: =$C77*INDEX(Curves!$G$8:$G$68,O$4-$B77+1) | P77: =$C77*INDEX(Curves!$G$8:$G$68,P$4-$B77+1) | Q77: =$C77*INDEX(Curves!$G$8:$G$68,Q$4-$B77+1) | ... BL77: =$C77*INDEX(Curves!$G$8:$G$68,BL$4-$B77+1)
A78: Cohort month 6 | B78: 6 | C78: =INDEX(Ops!$E$9:$BL$9,1,$B78) | K78: =$C78*INDEX(Curves!$G$8:$G$68,K$4-$B78+1) | L78: =$C78*INDEX(Curves!$G$8:$G$68,L$4-$B78+1) | M78: =$C78*INDEX(Curves!$G$8:$G$68,M$4-$B78+1) | N78: =$C78*INDEX(Curves!$G$8:$G$68,N$4-$B78+1) | O78: =$C78*INDEX(Curves!$G$8:$G$68,O$4-$B78+1) | P78: =$C78*INDEX(Curves!$G$8:$G$68,P$4-$B78+1) | Q78: =$C78*INDEX(Curves!$G$8:$G$68,Q$4-$B78+1) | R78: =$C78*INDEX(Curves!$G$8:$G$68,R$4-$B78+1) | ... BL78: =$C78*INDEX(Curves!$G$8:$G$68,BL$4-$B78+1)
A79: Cohort month 7 | B79: 7 | C79: =INDEX(Ops!$E$9:$BL$9,1,$B79) | L79: =$C79*INDEX(Curves!$G$8:$G$68,L$4-$B79+1) | M79: =$C79*INDEX(Curves!$G$8:$G$68,M$4-$B79+1) | N79: =$C79*INDEX(Curves!$G$8:$G$68,N$4-$B79+1) | O79: =$C79*INDEX(Curves!$G$8:$G$68,O$4-$B79+1) | P79: =$C79*INDEX(Curves!$G$8:$G$68,P$4-$B79+1) | Q79: =$C79*INDEX(Curves!$G$8:$G$68,Q$4-$B79+1) | R79: =$C79*INDEX(Curves!$G$8:$G$68,R$4-$B79+1) | S79: =$C79*INDEX(Curves!$G$8:$G$68,S$4-$B79+1) | ... BL79: =$C79*INDEX(Curves!$G$8:$G$68,BL$4-$B79+1)
A80: Cohort month 8 | B80: 8 | C80: =INDEX(Ops!$E$9:$BL$9,1,$B80) | M80: =$C80*INDEX(Curves!$G$8:$G$68,M$4-$B80+1) | N80: =$C80*INDEX(Curves!$G$8:$G$68,N$4-$B80+1) | O80: =$C80*INDEX(Curves!$G$8:$G$68,O$4-$B80+1) | P80: =$C80*INDEX(Curves!$G$8:$G$68,P$4-$B80+1) | Q80: =$C80*INDEX(Curves!$G$8:$G$68,Q$4-$B80+1) | R80: =$C80*INDEX(Curves!$G$8:$G$68,R$4-$B80+1) | S80: =$C80*INDEX(Curves!$G$8:$G$68,S$4-$B80+1) | T80: =$C80*INDEX(Curves!$G$8:$G$68,T$4-$B80+1) | ... BL80: =$C80*INDEX(Curves!$G$8:$G$68,BL$4-$B80+1)
A81: Cohort month 9 | B81: 9 | C81: =INDEX(Ops!$E$9:$BL$9,1,$B81) | N81: =$C81*INDEX(Curves!$G$8:$G$68,N$4-$B81+1) | O81: =$C81*INDEX(Curves!$G$8:$G$68,O$4-$B81+1) | P81: =$C81*INDEX(Curves!$G$8:$G$68,P$4-$B81+1) | Q81: =$C81*INDEX(Curves!$G$8:$G$68,Q$4-$B81+1) | R81: =$C81*INDEX(Curves!$G$8:$G$68,R$4-$B81+1) | S81: =$C81*INDEX(Curves!$G$8:$G$68,S$4-$B81+1) | T81: =$C81*INDEX(Curves!$G$8:$G$68,T$4-$B81+1) | U81: =$C81*INDEX(Curves!$G$8:$G$68,U$4-$B81+1) | ... BL81: =$C81*INDEX(Curves!$G$8:$G$68,BL$4-$B81+1)
A82: Cohort month 10 | B82: 10 | C82: =INDEX(Ops!$E$9:$BL$9,1,$B82) | O82: =$C82*INDEX(Curves!$G$8:$G$68,O$4-$B82+1) | P82: =$C82*INDEX(Curves!$G$8:$G$68,P$4-$B82+1) | Q82: =$C82*INDEX(Curves!$G$8:$G$68,Q$4-$B82+1) | R82: =$C82*INDEX(Curves!$G$8:$G$68,R$4-$B82+1) | S82: =$C82*INDEX(Curves!$G$8:$G$68,S$4-$B82+1) | T82: =$C82*INDEX(Curves!$G$8:$G$68,T$4-$B82+1) | U82: =$C82*INDEX(Curves!$G$8:$G$68,U$4-$B82+1) | V82: =$C82*INDEX(Curves!$G$8:$G$68,V$4-$B82+1) | ... BL82: =$C82*INDEX(Curves!$G$8:$G$68,BL$4-$B82+1)
A83: Cohort month 11 | B83: 11 | C83: =INDEX(Ops!$E$9:$BL$9,1,$B83) | P83: =$C83*INDEX(Curves!$G$8:$G$68,P$4-$B83+1) | Q83: =$C83*INDEX(Curves!$G$8:$G$68,Q$4-$B83+1) | R83: =$C83*INDEX(Curves!$G$8:$G$68,R$4-$B83+1) | S83: =$C83*INDEX(Curves!$G$8:$G$68,S$4-$B83+1) | T83: =$C83*INDEX(Curves!$G$8:$G$68,T$4-$B83+1) | U83: =$C83*INDEX(Curves!$G$8:$G$68,U$4-$B83+1) | V83: =$C83*INDEX(Curves!$G$8:$G$68,V$4-$B83+1) | W83: =$C83*INDEX(Curves!$G$8:$G$68,W$4-$B83+1) | ... BL83: =$C83*INDEX(Curves!$G$8:$G$68,BL$4-$B83+1)
A84: Cohort month 12 | B84: 12 | C84: =INDEX(Ops!$E$9:$BL$9,1,$B84) | Q84: =$C84*INDEX(Curves!$G$8:$G$68,Q$4-$B84+1) | R84: =$C84*INDEX(Curves!$G$8:$G$68,R$4-$B84+1) | S84: =$C84*INDEX(Curves!$G$8:$G$68,S$4-$B84+1) | T84: =$C84*INDEX(Curves!$G$8:$G$68,T$4-$B84+1) | U84: =$C84*INDEX(Curves!$G$8:$G$68,U$4-$B84+1) | V84: =$C84*INDEX(Curves!$G$8:$G$68,V$4-$B84+1) | W84: =$C84*INDEX(Curves!$G$8:$G$68,W$4-$B84+1) | X84: =$C84*INDEX(Curves!$G$8:$G$68,X$4-$B84+1) | ... BL84: =$C84*INDEX(Curves!$G$8:$G$68,BL$4-$B84+1)
A85: Cohort month 13 | B85: 13 | C85: =INDEX(Ops!$E$9:$BL$9,1,$B85) | R85: =$C85*INDEX(Curves!$G$8:$G$68,R$4-$B85+1) | S85: =$C85*INDEX(Curves!$G$8:$G$68,S$4-$B85+1) | T85: =$C85*INDEX(Curves!$G$8:$G$68,T$4-$B85+1) | U85: =$C85*INDEX(Curves!$G$8:$G$68,U$4-$B85+1) | V85: =$C85*INDEX(Curves!$G$8:$G$68,V$4-$B85+1) | W85: =$C85*INDEX(Curves!$G$8:$G$68,W$4-$B85+1) | X85: =$C85*INDEX(Curves!$G$8:$G$68,X$4-$B85+1) | Y85: =$C85*INDEX(Curves!$G$8:$G$68,Y$4-$B85+1) | ... BL85: =$C85*INDEX(Curves!$G$8:$G$68,BL$4-$B85+1)
A86: Cohort month 14 | B86: 14 | C86: =INDEX(Ops!$E$9:$BL$9,1,$B86) | S86: =$C86*INDEX(Curves!$G$8:$G$68,S$4-$B86+1) | T86: =$C86*INDEX(Curves!$G$8:$G$68,T$4-$B86+1) | U86: =$C86*INDEX(Curves!$G$8:$G$68,U$4-$B86+1) | V86: =$C86*INDEX(Curves!$G$8:$G$68,V$4-$B86+1) | W86: =$C86*INDEX(Curves!$G$8:$G$68,W$4-$B86+1) | X86: =$C86*INDEX(Curves!$G$8:$G$68,X$4-$B86+1) | Y86: =$C86*INDEX(Curves!$G$8:$G$68,Y$4-$B86+1) | Z86: =$C86*INDEX(Curves!$G$8:$G$68,Z$4-$B86+1) | ... BL86: =$C86*INDEX(Curves!$G$8:$G$68,BL$4-$B86+1)
A87: Cohort month 15 | B87: 15 | C87: =INDEX(Ops!$E$9:$BL$9,1,$B87) | T87: =$C87*INDEX(Curves!$G$8:$G$68,T$4-$B87+1) | U87: =$C87*INDEX(Curves!$G$8:$G$68,U$4-$B87+1) | V87: =$C87*INDEX(Curves!$G$8:$G$68,V$4-$B87+1) | W87: =$C87*INDEX(Curves!$G$8:$G$68,W$4-$B87+1) | X87: =$C87*INDEX(Curves!$G$8:$G$68,X$4-$B87+1) | Y87: =$C87*INDEX(Curves!$G$8:$G$68,Y$4-$B87+1) | Z87: =$C87*INDEX(Curves!$G$8:$G$68,Z$4-$B87+1) | AA87: =$C87*INDEX(Curves!$G$8:$G$68,AA$4-$B87+1) | ... BL87: =$C87*INDEX(Curves!$G$8:$G$68,BL$4-$B87+1)
A88: Cohort month 16 | B88: 16 | C88: =INDEX(Ops!$E$9:$BL$9,1,$B88) | U88: =$C88*INDEX(Curves!$G$8:$G$68,U$4-$B88+1) | V88: =$C88*INDEX(Curves!$G$8:$G$68,V$4-$B88+1) | W88: =$C88*INDEX(Curves!$G$8:$G$68,W$4-$B88+1) | X88: =$C88*INDEX(Curves!$G$8:$G$68,X$4-$B88+1) | Y88: =$C88*INDEX(Curves!$G$8:$G$68,Y$4-$B88+1) | Z88: =$C88*INDEX(Curves!$G$8:$G$68,Z$4-$B88+1) | AA88: =$C88*INDEX(Curves!$G$8:$G$68,AA$4-$B88+1) | AB88: =$C88*INDEX(Curves!$G$8:$G$68,AB$4-$B88+1) | ... BL88: =$C88*INDEX(Curves!$G$8:$G$68,BL$4-$B88+1)
A89: Cohort month 17 | B89: 17 | C89: =INDEX(Ops!$E$9:$BL$9,1,$B89) | V89: =$C89*INDEX(Curves!$G$8:$G$68,V$4-$B89+1) | W89: =$C89*INDEX(Curves!$G$8:$G$68,W$4-$B89+1) | X89: =$C89*INDEX(Curves!$G$8:$G$68,X$4-$B89+1) | Y89: =$C89*INDEX(Curves!$G$8:$G$68,Y$4-$B89+1) | Z89: =$C89*INDEX(Curves!$G$8:$G$68,Z$4-$B89+1) | AA89: =$C89*INDEX(Curves!$G$8:$G$68,AA$4-$B89+1) | AB89: =$C89*INDEX(Curves!$G$8:$G$68,AB$4-$B89+1) | AC89: =$C89*INDEX(Curves!$G$8:$G$68,AC$4-$B89+1) | ... BL89: =$C89*INDEX(Curves!$G$8:$G$68,BL$4-$B89+1)
A90: Cohort month 18 | B90: 18 | C90: =INDEX(Ops!$E$9:$BL$9,1,$B90) | W90: =$C90*INDEX(Curves!$G$8:$G$68,W$4-$B90+1) | X90: =$C90*INDEX(Curves!$G$8:$G$68,X$4-$B90+1) | Y90: =$C90*INDEX(Curves!$G$8:$G$68,Y$4-$B90+1) | Z90: =$C90*INDEX(Curves!$G$8:$G$68,Z$4-$B90+1) | AA90: =$C90*INDEX(Curves!$G$8:$G$68,AA$4-$B90+1) | AB90: =$C90*INDEX(Curves!$G$8:$G$68,AB$4-$B90+1) | AC90: =$C90*INDEX(Curves!$G$8:$G$68,AC$4-$B90+1) | AD90: =$C90*INDEX(Curves!$G$8:$G$68,AD$4-$B90+1) | ... BL90: =$C90*INDEX(Curves!$G$8:$G$68,BL$4-$B90+1)
A91: Cohort month 19 | B91: 19 | C91: =INDEX(Ops!$E$9:$BL$9,1,$B91) | X91: =$C91*INDEX(Curves!$G$8:$G$68,X$4-$B91+1) | Y91: =$C91*INDEX(Curves!$G$8:$G$68,Y$4-$B91+1) | Z91: =$C91*INDEX(Curves!$G$8:$G$68,Z$4-$B91+1) | AA91: =$C91*INDEX(Curves!$G$8:$G$68,AA$4-$B91+1) | AB91: =$C91*INDEX(Curves!$G$8:$G$68,AB$4-$B91+1) | AC91: =$C91*INDEX(Curves!$G$8:$G$68,AC$4-$B91+1) | AD91: =$C91*INDEX(Curves!$G$8:$G$68,AD$4-$B91+1) | AE91: =$C91*INDEX(Curves!$G$8:$G$68,AE$4-$B91+1) | ... BL91: =$C91*INDEX(Curves!$G$8:$G$68,BL$4-$B91+1)
A92: Cohort month 20 | B92: 20 | C92: =INDEX(Ops!$E$9:$BL$9,1,$B92) | Y92: =$C92*INDEX(Curves!$G$8:$G$68,Y$4-$B92+1) | Z92: =$C92*INDEX(Curves!$G$8:$G$68,Z$4-$B92+1) | AA92: =$C92*INDEX(Curves!$G$8:$G$68,AA$4-$B92+1) | AB92: =$C92*INDEX(Curves!$G$8:$G$68,AB$4-$B92+1) | AC92: =$C92*INDEX(Curves!$G$8:$G$68,AC$4-$B92+1) | AD92: =$C92*INDEX(Curves!$G$8:$G$68,AD$4-$B92+1) | AE92: =$C92*INDEX(Curves!$G$8:$G$68,AE$4-$B92+1) | AF92: =$C92*INDEX(Curves!$G$8:$G$68,AF$4-$B92+1) | ... BL92: =$C92*INDEX(Curves!$G$8:$G$68,BL$4-$B92+1)
A93: Cohort month 21 | B93: 21 | C93: =INDEX(Ops!$E$9:$BL$9,1,$B93) | Z93: =$C93*INDEX(Curves!$G$8:$G$68,Z$4-$B93+1) | AA93: =$C93*INDEX(Curves!$G$8:$G$68,AA$4-$B93+1) | AB93: =$C93*INDEX(Curves!$G$8:$G$68,AB$4-$B93+1) | AC93: =$C93*INDEX(Curves!$G$8:$G$68,AC$4-$B93+1) | AD93: =$C93*INDEX(Curves!$G$8:$G$68,AD$4-$B93+1) | AE93: =$C93*INDEX(Curves!$G$8:$G$68,AE$4-$B93+1) | AF93: =$C93*INDEX(Curves!$G$8:$G$68,AF$4-$B93+1) | AG93: =$C93*INDEX(Curves!$G$8:$G$68,AG$4-$B93+1) | ... BL93: =$C93*INDEX(Curves!$G$8:$G$68,BL$4-$B93+1)
A94: Cohort month 22 | B94: 22 | C94: =INDEX(Ops!$E$9:$BL$9,1,$B94) | AA94: =$C94*INDEX(Curves!$G$8:$G$68,AA$4-$B94+1) | AB94: =$C94*INDEX(Curves!$G$8:$G$68,AB$4-$B94+1) | AC94: =$C94*INDEX(Curves!$G$8:$G$68,AC$4-$B94+1) | AD94: =$C94*INDEX(Curves!$G$8:$G$68,AD$4-$B94+1) | AE94: =$C94*INDEX(Curves!$G$8:$G$68,AE$4-$B94+1) | AF94: =$C94*INDEX(Curves!$G$8:$G$68,AF$4-$B94+1) | AG94: =$C94*INDEX(Curves!$G$8:$G$68,AG$4-$B94+1) | AH94: =$C94*INDEX(Curves!$G$8:$G$68,AH$4-$B94+1) | ... BL94: =$C94*INDEX(Curves!$G$8:$G$68,BL$4-$B94+1)
A95: Cohort month 23 | B95: 23 | C95: =INDEX(Ops!$E$9:$BL$9,1,$B95) | AB95: =$C95*INDEX(Curves!$G$8:$G$68,AB$4-$B95+1) | AC95: =$C95*INDEX(Curves!$G$8:$G$68,AC$4-$B95+1) | AD95: =$C95*INDEX(Curves!$G$8:$G$68,AD$4-$B95+1) | AE95: =$C95*INDEX(Curves!$G$8:$G$68,AE$4-$B95+1) | AF95: =$C95*INDEX(Curves!$G$8:$G$68,AF$4-$B95+1) | AG95: =$C95*INDEX(Curves!$G$8:$G$68,AG$4-$B95+1) | AH95: =$C95*INDEX(Curves!$G$8:$G$68,AH$4-$B95+1) | AI95: =$C95*INDEX(Curves!$G$8:$G$68,AI$4-$B95+1) | ... BL95: =$C95*INDEX(Curves!$G$8:$G$68,BL$4-$B95+1)
A96: Cohort month 24 | B96: 24 | C96: =INDEX(Ops!$E$9:$BL$9,1,$B96) | AC96: =$C96*INDEX(Curves!$G$8:$G$68,AC$4-$B96+1) | AD96: =$C96*INDEX(Curves!$G$8:$G$68,AD$4-$B96+1) | AE96: =$C96*INDEX(Curves!$G$8:$G$68,AE$4-$B96+1) | AF96: =$C96*INDEX(Curves!$G$8:$G$68,AF$4-$B96+1) | AG96: =$C96*INDEX(Curves!$G$8:$G$68,AG$4-$B96+1) | AH96: =$C96*INDEX(Curves!$G$8:$G$68,AH$4-$B96+1) | AI96: =$C96*INDEX(Curves!$G$8:$G$68,AI$4-$B96+1) | AJ96: =$C96*INDEX(Curves!$G$8:$G$68,AJ$4-$B96+1) | ... BL96: =$C96*INDEX(Curves!$G$8:$G$68,BL$4-$B96+1)
A97: Cohort month 25 | B97: 25 | C97: =INDEX(Ops!$E$9:$BL$9,1,$B97) | AD97: =$C97*INDEX(Curves!$G$8:$G$68,AD$4-$B97+1) | AE97: =$C97*INDEX(Curves!$G$8:$G$68,AE$4-$B97+1) | AF97: =$C97*INDEX(Curves!$G$8:$G$68,AF$4-$B97+1) | AG97: =$C97*INDEX(Curves!$G$8:$G$68,AG$4-$B97+1) | AH97: =$C97*INDEX(Curves!$G$8:$G$68,AH$4-$B97+1) | AI97: =$C97*INDEX(Curves!$G$8:$G$68,AI$4-$B97+1) | AJ97: =$C97*INDEX(Curves!$G$8:$G$68,AJ$4-$B97+1) | AK97: =$C97*INDEX(Curves!$G$8:$G$68,AK$4-$B97+1) | ... BL97: =$C97*INDEX(Curves!$G$8:$G$68,BL$4-$B97+1)
A98: Cohort month 26 | B98: 26 | C98: =INDEX(Ops!$E$9:$BL$9,1,$B98) | AE98: =$C98*INDEX(Curves!$G$8:$G$68,AE$4-$B98+1) | AF98: =$C98*INDEX(Curves!$G$8:$G$68,AF$4-$B98+1) | AG98: =$C98*INDEX(Curves!$G$8:$G$68,AG$4-$B98+1) | AH98: =$C98*INDEX(Curves!$G$8:$G$68,AH$4-$B98+1) | AI98: =$C98*INDEX(Curves!$G$8:$G$68,AI$4-$B98+1) | AJ98: =$C98*INDEX(Curves!$G$8:$G$68,AJ$4-$B98+1) | AK98: =$C98*INDEX(Curves!$G$8:$G$68,AK$4-$B98+1) | AL98: =$C98*INDEX(Curves!$G$8:$G$68,AL$4-$B98+1) | ... BL98: =$C98*INDEX(Curves!$G$8:$G$68,BL$4-$B98+1)
A99: Cohort month 27 | B99: 27 | C99: =INDEX(Ops!$E$9:$BL$9,1,$B99) | AF99: =$C99*INDEX(Curves!$G$8:$G$68,AF$4-$B99+1) | AG99: =$C99*INDEX(Curves!$G$8:$G$68,AG$4-$B99+1) | AH99: =$C99*INDEX(Curves!$G$8:$G$68,AH$4-$B99+1) | AI99: =$C99*INDEX(Curves!$G$8:$G$68,AI$4-$B99+1) | AJ99: =$C99*INDEX(Curves!$G$8:$G$68,AJ$4-$B99+1) | AK99: =$C99*INDEX(Curves!$G$8:$G$68,AK$4-$B99+1) | AL99: =$C99*INDEX(Curves!$G$8:$G$68,AL$4-$B99+1) | AM99: =$C99*INDEX(Curves!$G$8:$G$68,AM$4-$B99+1) | ... BL99: =$C99*INDEX(Curves!$G$8:$G$68,BL$4-$B99+1)
A100: Cohort month 28 | B100: 28 | C100: =INDEX(Ops!$E$9:$BL$9,1,$B100) | AG100: =$C100*INDEX(Curves!$G$8:$G$68,AG$4-$B100+1) | AH100: =$C100*INDEX(Curves!$G$8:$G$68,AH$4-$B100+1) | AI100: =$C100*INDEX(Curves!$G$8:$G$68,AI$4-$B100+1) | AJ100: =$C100*INDEX(Curves!$G$8:$G$68,AJ$4-$B100+1) | AK100: =$C100*INDEX(Curves!$G$8:$G$68,AK$4-$B100+1) | AL100: =$C100*INDEX(Curves!$G$8:$G$68,AL$4-$B100+1) | AM100: =$C100*INDEX(Curves!$G$8:$G$68,AM$4-$B100+1) | AN100: =$C100*INDEX(Curves!$G$8:$G$68,AN$4-$B100+1) | ... BL100: =$C100*INDEX(Curves!$G$8:$G$68,BL$4-$B100+1)
A101: Cohort month 29 | B101: 29 | C101: =INDEX(Ops!$E$9:$BL$9,1,$B101) | AH101: =$C101*INDEX(Curves!$G$8:$G$68,AH$4-$B101+1) | AI101: =$C101*INDEX(Curves!$G$8:$G$68,AI$4-$B101+1) | AJ101: =$C101*INDEX(Curves!$G$8:$G$68,AJ$4-$B101+1) | AK101: =$C101*INDEX(Curves!$G$8:$G$68,AK$4-$B101+1) | AL101: =$C101*INDEX(Curves!$G$8:$G$68,AL$4-$B101+1) | AM101: =$C101*INDEX(Curves!$G$8:$G$68,AM$4-$B101+1) | AN101: =$C101*INDEX(Curves!$G$8:$G$68,AN$4-$B101+1) | AO101: =$C101*INDEX(Curves!$G$8:$G$68,AO$4-$B101+1) | ... BL101: =$C101*INDEX(Curves!$G$8:$G$68,BL$4-$B101+1)
A102: Cohort month 30 | B102: 30 | C102: =INDEX(Ops!$E$9:$BL$9,1,$B102) | AI102: =$C102*INDEX(Curves!$G$8:$G$68,AI$4-$B102+1) | AJ102: =$C102*INDEX(Curves!$G$8:$G$68,AJ$4-$B102+1) | AK102: =$C102*INDEX(Curves!$G$8:$G$68,AK$4-$B102+1) | AL102: =$C102*INDEX(Curves!$G$8:$G$68,AL$4-$B102+1) | AM102: =$C102*INDEX(Curves!$G$8:$G$68,AM$4-$B102+1) | AN102: =$C102*INDEX(Curves!$G$8:$G$68,AN$4-$B102+1) | AO102: =$C102*INDEX(Curves!$G$8:$G$68,AO$4-$B102+1) | AP102: =$C102*INDEX(Curves!$G$8:$G$68,AP$4-$B102+1) | ... BL102: =$C102*INDEX(Curves!$G$8:$G$68,BL$4-$B102+1)
A103: Cohort month 31 | B103: 31 | C103: =INDEX(Ops!$E$9:$BL$9,1,$B103) | AJ103: =$C103*INDEX(Curves!$G$8:$G$68,AJ$4-$B103+1) | AK103: =$C103*INDEX(Curves!$G$8:$G$68,AK$4-$B103+1) | AL103: =$C103*INDEX(Curves!$G$8:$G$68,AL$4-$B103+1) | AM103: =$C103*INDEX(Curves!$G$8:$G$68,AM$4-$B103+1) | AN103: =$C103*INDEX(Curves!$G$8:$G$68,AN$4-$B103+1) | AO103: =$C103*INDEX(Curves!$G$8:$G$68,AO$4-$B103+1) | AP103: =$C103*INDEX(Curves!$G$8:$G$68,AP$4-$B103+1) | AQ103: =$C103*INDEX(Curves!$G$8:$G$68,AQ$4-$B103+1) | ... BL103: =$C103*INDEX(Curves!$G$8:$G$68,BL$4-$B103+1)
...

Sheet Cohort_P2
A1: Cohort (vintage) matrix - P2 SHS lights+radio (Tier 2)
A2: Rows = sales cohort (month of sale); columns = calendar month. Cohort size in column C.
A4: Month # | D4: Opening | E4: =Timeline!E4 | F4: =Timeline!F4 | G4: =Timeline!G4 | H4: =Timeline!H4 | I4: =Timeline!I4 | J4: =Timeline!J4 | K4: =Timeline!K4 | L4: =Timeline!L4 | ... BL4: =Timeline!BL4
A5: Period end | E5: =Timeline!E5 | F5: =Timeline!F5 | G5: =Timeline!G5 | H5: =Timeline!H5 | I5: =Timeline!I5 | J5: =Timeline!J5 | K5: =Timeline!K5 | L5: =Timeline!L5 | ... BL5: =Timeline!BL5
A6: Year # | E6: =Timeline!E6 | F6: =Timeline!F6 | G6: =Timeline!G6 | H6: =Timeline!H6 | I6: =Timeline!I6 | J6: =Timeline!J6 | K6: =Timeline!K6 | L6: =Timeline!L6 | ... BL6: =Timeline!BL6
A8: Instalments collected by cohort (LCY)
A9: Total | E9: =SUM(E10:E69) | F9: =SUM(F10:F69) | G9: =SUM(G10:G69) | H9: =SUM(H10:H69) | I9: =SUM(I10:I69) | J9: =SUM(J10:J69) | K9: =SUM(K10:K69) | L9: =SUM(L10:L69) | ... BL9: =SUM(BL10:BL69)
A10: Cohort month 1 | B10: 1 | C10: =INDEX(Ops!$E$25:$BL$25,1,$B10) | F10: =$C10*INDEX(Curves!$M$8:$M$68,F$4-$B10+1) | G10: =$C10*INDEX(Curves!$M$8:$M$68,G$4-$B10+1) | H10: =$C10*INDEX(Curves!$M$8:$M$68,H$4-$B10+1) | I10: =$C10*INDEX(Curves!$M$8:$M$68,I$4-$B10+1) | J10: =$C10*INDEX(Curves!$M$8:$M$68,J$4-$B10+1) | K10: =$C10*INDEX(Curves!$M$8:$M$68,K$4-$B10+1) | L10: =$C10*INDEX(Curves!$M$8:$M$68,L$4-$B10+1) | M10: =$C10*INDEX(Curves!$M$8:$M$68,M$4-$B10+1) | ... BL10: =$C10*INDEX(Curves!$M$8:$M$68,BL$4-$B10+1)
A11: Cohort month 2 | B11: 2 | C11: =INDEX(Ops!$E$25:$BL$25,1,$B11) | G11: =$C11*INDEX(Curves!$M$8:$M$68,G$4-$B11+1) | H11: =$C11*INDEX(Curves!$M$8:$M$68,H$4-$B11+1) | I11: =$C11*INDEX(Curves!$M$8:$M$68,I$4-$B11+1) | J11: =$C11*INDEX(Curves!$M$8:$M$68,J$4-$B11+1) | K11: =$C11*INDEX(Curves!$M$8:$M$68,K$4-$B11+1) | L11: =$C11*INDEX(Curves!$M$8:$M$68,L$4-$B11+1) | M11: =$C11*INDEX(Curves!$M$8:$M$68,M$4-$B11+1) | N11: =$C11*INDEX(Curves!$M$8:$M$68,N$4-$B11+1) | ... BL11: =$C11*INDEX(Curves!$M$8:$M$68,BL$4-$B11+1)
A12: Cohort month 3 | B12: 3 | C12: =INDEX(Ops!$E$25:$BL$25,1,$B12) | H12: =$C12*INDEX(Curves!$M$8:$M$68,H$4-$B12+1) | I12: =$C12*INDEX(Curves!$M$8:$M$68,I$4-$B12+1) | J12: =$C12*INDEX(Curves!$M$8:$M$68,J$4-$B12+1) | K12: =$C12*INDEX(Curves!$M$8:$M$68,K$4-$B12+1) | L12: =$C12*INDEX(Curves!$M$8:$M$68,L$4-$B12+1) | M12: =$C12*INDEX(Curves!$M$8:$M$68,M$4-$B12+1) | N12: =$C12*INDEX(Curves!$M$8:$M$68,N$4-$B12+1) | O12: =$C12*INDEX(Curves!$M$8:$M$68,O$4-$B12+1) | ... BL12: =$C12*INDEX(Curves!$M$8:$M$68,BL$4-$B12+1)
A13: Cohort month 4 | B13: 4 | C13: =INDEX(Ops!$E$25:$BL$25,1,$B13) | I13: =$C13*INDEX(Curves!$M$8:$M$68,I$4-$B13+1) | J13: =$C13*INDEX(Curves!$M$8:$M$68,J$4-$B13+1) | K13: =$C13*INDEX(Curves!$M$8:$M$68,K$4-$B13+1) | L13: =$C13*INDEX(Curves!$M$8:$M$68,L$4-$B13+1) | M13: =$C13*INDEX(Curves!$M$8:$M$68,M$4-$B13+1) | N13: =$C13*INDEX(Curves!$M$8:$M$68,N$4-$B13+1) | O13: =$C13*INDEX(Curves!$M$8:$M$68,O$4-$B13+1) | P13: =$C13*INDEX(Curves!$M$8:$M$68,P$4-$B13+1) | ... BL13: =$C13*INDEX(Curves!$M$8:$M$68,BL$4-$B13+1)
A14: Cohort month 5 | B14: 5 | C14: =INDEX(Ops!$E$25:$BL$25,1,$B14) | J14: =$C14*INDEX(Curves!$M$8:$M$68,J$4-$B14+1) | K14: =$C14*INDEX(Curves!$M$8:$M$68,K$4-$B14+1) | L14: =$C14*INDEX(Curves!$M$8:$M$68,L$4-$B14+1) | M14: =$C14*INDEX(Curves!$M$8:$M$68,M$4-$B14+1) | N14: =$C14*INDEX(Curves!$M$8:$M$68,N$4-$B14+1) | O14: =$C14*INDEX(Curves!$M$8:$M$68,O$4-$B14+1) | P14: =$C14*INDEX(Curves!$M$8:$M$68,P$4-$B14+1) | Q14: =$C14*INDEX(Curves!$M$8:$M$68,Q$4-$B14+1) | ... BL14: =$C14*INDEX(Curves!$M$8:$M$68,BL$4-$B14+1)
A15: Cohort month 6 | B15: 6 | C15: =INDEX(Ops!$E$25:$BL$25,1,$B15) | K15: =$C15*INDEX(Curves!$M$8:$M$68,K$4-$B15+1) | L15: =$C15*INDEX(Curves!$M$8:$M$68,L$4-$B15+1) | M15: =$C15*INDEX(Curves!$M$8:$M$68,M$4-$B15+1) | N15: =$C15*INDEX(Curves!$M$8:$M$68,N$4-$B15+1) | O15: =$C15*INDEX(Curves!$M$8:$M$68,O$4-$B15+1) | P15: =$C15*INDEX(Curves!$M$8:$M$68,P$4-$B15+1) | Q15: =$C15*INDEX(Curves!$M$8:$M$68,Q$4-$B15+1) | R15: =$C15*INDEX(Curves!$M$8:$M$68,R$4-$B15+1) | ... BL15: =$C15*INDEX(Curves!$M$8:$M$68,BL$4-$B15+1)
A16: Cohort month 7 | B16: 7 | C16: =INDEX(Ops!$E$25:$BL$25,1,$B16) | L16: =$C16*INDEX(Curves!$M$8:$M$68,L$4-$B16+1) | M16: =$C16*INDEX(Curves!$M$8:$M$68,M$4-$B16+1) | N16: =$C16*INDEX(Curves!$M$8:$M$68,N$4-$B16+1) | O16: =$C16*INDEX(Curves!$M$8:$M$68,O$4-$B16+1) | P16: =$C16*INDEX(Curves!$M$8:$M$68,P$4-$B16+1) | Q16: =$C16*INDEX(Curves!$M$8:$M$68,Q$4-$B16+1) | R16: =$C16*INDEX(Curves!$M$8:$M$68,R$4-$B16+1) | S16: =$C16*INDEX(Curves!$M$8:$M$68,S$4-$B16+1) | ... BL16: =$C16*INDEX(Curves!$M$8:$M$68,BL$4-$B16+1)
A17: Cohort month 8 | B17: 8 | C17: =INDEX(Ops!$E$25:$BL$25,1,$B17) | M17: =$C17*INDEX(Curves!$M$8:$M$68,M$4-$B17+1) | N17: =$C17*INDEX(Curves!$M$8:$M$68,N$4-$B17+1) | O17: =$C17*INDEX(Curves!$M$8:$M$68,O$4-$B17+1) | P17: =$C17*INDEX(Curves!$M$8:$M$68,P$4-$B17+1) | Q17: =$C17*INDEX(Curves!$M$8:$M$68,Q$4-$B17+1) | R17: =$C17*INDEX(Curves!$M$8:$M$68,R$4-$B17+1) | S17: =$C17*INDEX(Curves!$M$8:$M$68,S$4-$B17+1) | T17: =$C17*INDEX(Curves!$M$8:$M$68,T$4-$B17+1) | ... BL17: =$C17*INDEX(Curves!$M$8:$M$68,BL$4-$B17+1)
A18: Cohort month 9 | B18: 9 | C18: =INDEX(Ops!$E$25:$BL$25,1,$B18) | N18: =$C18*INDEX(Curves!$M$8:$M$68,N$4-$B18+1) | O18: =$C18*INDEX(Curves!$M$8:$M$68,O$4-$B18+1) | P18: =$C18*INDEX(Curves!$M$8:$M$68,P$4-$B18+1) | Q18: =$C18*INDEX(Curves!$M$8:$M$68,Q$4-$B18+1) | R18: =$C18*INDEX(Curves!$M$8:$M$68,R$4-$B18+1) | S18: =$C18*INDEX(Curves!$M$8:$M$68,S$4-$B18+1) | T18: =$C18*INDEX(Curves!$M$8:$M$68,T$4-$B18+1) | U18: =$C18*INDEX(Curves!$M$8:$M$68,U$4-$B18+1) | ... BL18: =$C18*INDEX(Curves!$M$8:$M$68,BL$4-$B18+1)
A19: Cohort month 10 | B19: 10 | C19: =INDEX(Ops!$E$25:$BL$25,1,$B19) | O19: =$C19*INDEX(Curves!$M$8:$M$68,O$4-$B19+1) | P19: =$C19*INDEX(Curves!$M$8:$M$68,P$4-$B19+1) | Q19: =$C19*INDEX(Curves!$M$8:$M$68,Q$4-$B19+1) | R19: =$C19*INDEX(Curves!$M$8:$M$68,R$4-$B19+1) | S19: =$C19*INDEX(Curves!$M$8:$M$68,S$4-$B19+1) | T19: =$C19*INDEX(Curves!$M$8:$M$68,T$4-$B19+1) | U19: =$C19*INDEX(Curves!$M$8:$M$68,U$4-$B19+1) | V19: =$C19*INDEX(Curves!$M$8:$M$68,V$4-$B19+1) | ... BL19: =$C19*INDEX(Curves!$M$8:$M$68,BL$4-$B19+1)
A20: Cohort month 11 | B20: 11 | C20: =INDEX(Ops!$E$25:$BL$25,1,$B20) | P20: =$C20*INDEX(Curves!$M$8:$M$68,P$4-$B20+1) | Q20: =$C20*INDEX(Curves!$M$8:$M$68,Q$4-$B20+1) | R20: =$C20*INDEX(Curves!$M$8:$M$68,R$4-$B20+1) | S20: =$C20*INDEX(Curves!$M$8:$M$68,S$4-$B20+1) | T20: =$C20*INDEX(Curves!$M$8:$M$68,T$4-$B20+1) | U20: =$C20*INDEX(Curves!$M$8:$M$68,U$4-$B20+1) | V20: =$C20*INDEX(Curves!$M$8:$M$68,V$4-$B20+1) | W20: =$C20*INDEX(Curves!$M$8:$M$68,W$4-$B20+1) | ... BL20: =$C20*INDEX(Curves!$M$8:$M$68,BL$4-$B20+1)
A21: Cohort month 12 | B21: 12 | C21: =INDEX(Ops!$E$25:$BL$25,1,$B21) | Q21: =$C21*INDEX(Curves!$M$8:$M$68,Q$4-$B21+1) | R21: =$C21*INDEX(Curves!$M$8:$M$68,R$4-$B21+1) | S21: =$C21*INDEX(Curves!$M$8:$M$68,S$4-$B21+1) | T21: =$C21*INDEX(Curves!$M$8:$M$68,T$4-$B21+1) | U21: =$C21*INDEX(Curves!$M$8:$M$68,U$4-$B21+1) | V21: =$C21*INDEX(Curves!$M$8:$M$68,V$4-$B21+1) | W21: =$C21*INDEX(Curves!$M$8:$M$68,W$4-$B21+1) | X21: =$C21*INDEX(Curves!$M$8:$M$68,X$4-$B21+1) | ... BL21: =$C21*INDEX(Curves!$M$8:$M$68,BL$4-$B21+1)
A22: Cohort month 13 | B22: 13 | C22: =INDEX(Ops!$E$25:$BL$25,1,$B22) | R22: =$C22*INDEX(Curves!$M$8:$M$68,R$4-$B22+1) | S22: =$C22*INDEX(Curves!$M$8:$M$68,S$4-$B22+1) | T22: =$C22*INDEX(Curves!$M$8:$M$68,T$4-$B22+1) | U22: =$C22*INDEX(Curves!$M$8:$M$68,U$4-$B22+1) | V22: =$C22*INDEX(Curves!$M$8:$M$68,V$4-$B22+1) | W22: =$C22*INDEX(Curves!$M$8:$M$68,W$4-$B22+1) | X22: =$C22*INDEX(Curves!$M$8:$M$68,X$4-$B22+1) | Y22: =$C22*INDEX(Curves!$M$8:$M$68,Y$4-$B22+1) | ... BL22: =$C22*INDEX(Curves!$M$8:$M$68,BL$4-$B22+1)
A23: Cohort month 14 | B23: 14 | C23: =INDEX(Ops!$E$25:$BL$25,1,$B23) | S23: =$C23*INDEX(Curves!$M$8:$M$68,S$4-$B23+1) | T23: =$C23*INDEX(Curves!$M$8:$M$68,T$4-$B23+1) | U23: =$C23*INDEX(Curves!$M$8:$M$68,U$4-$B23+1) | V23: =$C23*INDEX(Curves!$M$8:$M$68,V$4-$B23+1) | W23: =$C23*INDEX(Curves!$M$8:$M$68,W$4-$B23+1) | X23: =$C23*INDEX(Curves!$M$8:$M$68,X$4-$B23+1) | Y23: =$C23*INDEX(Curves!$M$8:$M$68,Y$4-$B23+1) | Z23: =$C23*INDEX(Curves!$M$8:$M$68,Z$4-$B23+1) | ... BL23: =$C23*INDEX(Curves!$M$8:$M$68,BL$4-$B23+1)
A24: Cohort month 15 | B24: 15 | C24: =INDEX(Ops!$E$25:$BL$25,1,$B24) | T24: =$C24*INDEX(Curves!$M$8:$M$68,T$4-$B24+1) | U24: =$C24*INDEX(Curves!$M$8:$M$68,U$4-$B24+1) | V24: =$C24*INDEX(Curves!$M$8:$M$68,V$4-$B24+1) | W24: =$C24*INDEX(Curves!$M$8:$M$68,W$4-$B24+1) | X24: =$C24*INDEX(Curves!$M$8:$M$68,X$4-$B24+1) | Y24: =$C24*INDEX(Curves!$M$8:$M$68,Y$4-$B24+1) | Z24: =$C24*INDEX(Curves!$M$8:$M$68,Z$4-$B24+1) | AA24: =$C24*INDEX(Curves!$M$8:$M$68,AA$4-$B24+1) | ... BL24: =$C24*INDEX(Curves!$M$8:$M$68,BL$4-$B24+1)
A25: Cohort month 16 | B25: 16 | C25: =INDEX(Ops!$E$25:$BL$25,1,$B25) | U25: =$C25*INDEX(Curves!$M$8:$M$68,U$4-$B25+1) | V25: =$C25*INDEX(Curves!$M$8:$M$68,V$4-$B25+1) | W25: =$C25*INDEX(Curves!$M$8:$M$68,W$4-$B25+1) | X25: =$C25*INDEX(Curves!$M$8:$M$68,X$4-$B25+1) | Y25: =$C25*INDEX(Curves!$M$8:$M$68,Y$4-$B25+1) | Z25: =$C25*INDEX(Curves!$M$8:$M$68,Z$4-$B25+1) | AA25: =$C25*INDEX(Curves!$M$8:$M$68,AA$4-$B25+1) | AB25: =$C25*INDEX(Curves!$M$8:$M$68,AB$4-$B25+1) | ... BL25: =$C25*INDEX(Curves!$M$8:$M$68,BL$4-$B25+1)
A26: Cohort month 17 | B26: 17 | C26: =INDEX(Ops!$E$25:$BL$25,1,$B26) | V26: =$C26*INDEX(Curves!$M$8:$M$68,V$4-$B26+1) | W26: =$C26*INDEX(Curves!$M$8:$M$68,W$4-$B26+1) | X26: =$C26*INDEX(Curves!$M$8:$M$68,X$4-$B26+1) | Y26: =$C26*INDEX(Curves!$M$8:$M$68,Y$4-$B26+1) | Z26: =$C26*INDEX(Curves!$M$8:$M$68,Z$4-$B26+1) | AA26: =$C26*INDEX(Curves!$M$8:$M$68,AA$4-$B26+1) | AB26: =$C26*INDEX(Curves!$M$8:$M$68,AB$4-$B26+1) | AC26: =$C26*INDEX(Curves!$M$8:$M$68,AC$4-$B26+1) | ... BL26: =$C26*INDEX(Curves!$M$8:$M$68,BL$4-$B26+1)
A27: Cohort month 18 | B27: 18 | C27: =INDEX(Ops!$E$25:$BL$25,1,$B27) | W27: =$C27*INDEX(Curves!$M$8:$M$68,W$4-$B27+1) | X27: =$C27*INDEX(Curves!$M$8:$M$68,X$4-$B27+1) | Y27: =$C27*INDEX(Curves!$M$8:$M$68,Y$4-$B27+1) | Z27: =$C27*INDEX(Curves!$M$8:$M$68,Z$4-$B27+1) | AA27: =$C27*INDEX(Curves!$M$8:$M$68,AA$4-$B27+1) | AB27: =$C27*INDEX(Curves!$M$8:$M$68,AB$4-$B27+1) | AC27: =$C27*INDEX(Curves!$M$8:$M$68,AC$4-$B27+1) | AD27: =$C27*INDEX(Curves!$M$8:$M$68,AD$4-$B27+1) | ... BL27: =$C27*INDEX(Curves!$M$8:$M$68,BL$4-$B27+1)
A28: Cohort month 19 | B28: 19 | C28: =INDEX(Ops!$E$25:$BL$25,1,$B28) | X28: =$C28*INDEX(Curves!$M$8:$M$68,X$4-$B28+1) | Y28: =$C28*INDEX(Curves!$M$8:$M$68,Y$4-$B28+1) | Z28: =$C28*INDEX(Curves!$M$8:$M$68,Z$4-$B28+1) | AA28: =$C28*INDEX(Curves!$M$8:$M$68,AA$4-$B28+1) | AB28: =$C28*INDEX(Curves!$M$8:$M$68,AB$4-$B28+1) | AC28: =$C28*INDEX(Curves!$M$8:$M$68,AC$4-$B28+1) | AD28: =$C28*INDEX(Curves!$M$8:$M$68,AD$4-$B28+1) | AE28: =$C28*INDEX(Curves!$M$8:$M$68,AE$4-$B28+1) | ... BL28: =$C28*INDEX(Curves!$M$8:$M$68,BL$4-$B28+1)
A29: Cohort month 20 | B29: 20 | C29: =INDEX(Ops!$E$25:$BL$25,1,$B29) | Y29: =$C29*INDEX(Curves!$M$8:$M$68,Y$4-$B29+1) | Z29: =$C29*INDEX(Curves!$M$8:$M$68,Z$4-$B29+1) | AA29: =$C29*INDEX(Curves!$M$8:$M$68,AA$4-$B29+1) | AB29: =$C29*INDEX(Curves!$M$8:$M$68,AB$4-$B29+1) | AC29: =$C29*INDEX(Curves!$M$8:$M$68,AC$4-$B29+1) | AD29: =$C29*INDEX(Curves!$M$8:$M$68,AD$4-$B29+1) | AE29: =$C29*INDEX(Curves!$M$8:$M$68,AE$4-$B29+1) | AF29: =$C29*INDEX(Curves!$M$8:$M$68,AF$4-$B29+1) | ... BL29: =$C29*INDEX(Curves!$M$8:$M$68,BL$4-$B29+1)
A30: Cohort month 21 | B30: 21 | C30: =INDEX(Ops!$E$25:$BL$25,1,$B30) | Z30: =$C30*INDEX(Curves!$M$8:$M$68,Z$4-$B30+1) | AA30: =$C30*INDEX(Curves!$M$8:$M$68,AA$4-$B30+1) | AB30: =$C30*INDEX(Curves!$M$8:$M$68,AB$4-$B30+1) | AC30: =$C30*INDEX(Curves!$M$8:$M$68,AC$4-$B30+1) | AD30: =$C30*INDEX(Curves!$M$8:$M$68,AD$4-$B30+1) | AE30: =$C30*INDEX(Curves!$M$8:$M$68,AE$4-$B30+1) | AF30: =$C30*INDEX(Curves!$M$8:$M$68,AF$4-$B30+1) | AG30: =$C30*INDEX(Curves!$M$8:$M$68,AG$4-$B30+1) | ... BL30: =$C30*INDEX(Curves!$M$8:$M$68,BL$4-$B30+1)
A31: Cohort month 22 | B31: 22 | C31: =INDEX(Ops!$E$25:$BL$25,1,$B31) | AA31: =$C31*INDEX(Curves!$M$8:$M$68,AA$4-$B31+1) | AB31: =$C31*INDEX(Curves!$M$8:$M$68,AB$4-$B31+1) | AC31: =$C31*INDEX(Curves!$M$8:$M$68,AC$4-$B31+1) | AD31: =$C31*INDEX(Curves!$M$8:$M$68,AD$4-$B31+1) | AE31: =$C31*INDEX(Curves!$M$8:$M$68,AE$4-$B31+1) | AF31: =$C31*INDEX(Curves!$M$8:$M$68,AF$4-$B31+1) | AG31: =$C31*INDEX(Curves!$M$8:$M$68,AG$4-$B31+1) | AH31: =$C31*INDEX(Curves!$M$8:$M$68,AH$4-$B31+1) | ... BL31: =$C31*INDEX(Curves!$M$8:$M$68,BL$4-$B31+1)
A32: Cohort month 23 | B32: 23 | C32: =INDEX(Ops!$E$25:$BL$25,1,$B32) | AB32: =$C32*INDEX(Curves!$M$8:$M$68,AB$4-$B32+1) | AC32: =$C32*INDEX(Curves!$M$8:$M$68,AC$4-$B32+1) | AD32: =$C32*INDEX(Curves!$M$8:$M$68,AD$4-$B32+1) | AE32: =$C32*INDEX(Curves!$M$8:$M$68,AE$4-$B32+1) | AF32: =$C32*INDEX(Curves!$M$8:$M$68,AF$4-$B32+1) | AG32: =$C32*INDEX(Curves!$M$8:$M$68,AG$4-$B32+1) | AH32: =$C32*INDEX(Curves!$M$8:$M$68,AH$4-$B32+1) | AI32: =$C32*INDEX(Curves!$M$8:$M$68,AI$4-$B32+1) | ... BL32: =$C32*INDEX(Curves!$M$8:$M$68,BL$4-$B32+1)
A33: Cohort month 24 | B33: 24 | C33: =INDEX(Ops!$E$25:$BL$25,1,$B33) | AC33: =$C33*INDEX(Curves!$M$8:$M$68,AC$4-$B33+1) | AD33: =$C33*INDEX(Curves!$M$8:$M$68,AD$4-$B33+1) | AE33: =$C33*INDEX(Curves!$M$8:$M$68,AE$4-$B33+1) | AF33: =$C33*INDEX(Curves!$M$8:$M$68,AF$4-$B33+1) | AG33: =$C33*INDEX(Curves!$M$8:$M$68,AG$4-$B33+1) | AH33: =$C33*INDEX(Curves!$M$8:$M$68,AH$4-$B33+1) | AI33: =$C33*INDEX(Curves!$M$8:$M$68,AI$4-$B33+1) | AJ33: =$C33*INDEX(Curves!$M$8:$M$68,AJ$4-$B33+1) | ... BL33: =$C33*INDEX(Curves!$M$8:$M$68,BL$4-$B33+1)
A34: Cohort month 25 | B34: 25 | C34: =INDEX(Ops!$E$25:$BL$25,1,$B34) | AD34: =$C34*INDEX(Curves!$M$8:$M$68,AD$4-$B34+1) | AE34: =$C34*INDEX(Curves!$M$8:$M$68,AE$4-$B34+1) | AF34: =$C34*INDEX(Curves!$M$8:$M$68,AF$4-$B34+1) | AG34: =$C34*INDEX(Curves!$M$8:$M$68,AG$4-$B34+1) | AH34: =$C34*INDEX(Curves!$M$8:$M$68,AH$4-$B34+1) | AI34: =$C34*INDEX(Curves!$M$8:$M$68,AI$4-$B34+1) | AJ34: =$C34*INDEX(Curves!$M$8:$M$68,AJ$4-$B34+1) | AK34: =$C34*INDEX(Curves!$M$8:$M$68,AK$4-$B34+1) | ... BL34: =$C34*INDEX(Curves!$M$8:$M$68,BL$4-$B34+1)
A35: Cohort month 26 | B35: 26 | C35: =INDEX(Ops!$E$25:$BL$25,1,$B35) | AE35: =$C35*INDEX(Curves!$M$8:$M$68,AE$4-$B35+1) | AF35: =$C35*INDEX(Curves!$M$8:$M$68,AF$4-$B35+1) | AG35: =$C35*INDEX(Curves!$M$8:$M$68,AG$4-$B35+1) | AH35: =$C35*INDEX(Curves!$M$8:$M$68,AH$4-$B35+1) | AI35: =$C35*INDEX(Curves!$M$8:$M$68,AI$4-$B35+1) | AJ35: =$C35*INDEX(Curves!$M$8:$M$68,AJ$4-$B35+1) | AK35: =$C35*INDEX(Curves!$M$8:$M$68,AK$4-$B35+1) | AL35: =$C35*INDEX(Curves!$M$8:$M$68,AL$4-$B35+1) | ... BL35: =$C35*INDEX(Curves!$M$8:$M$68,BL$4-$B35+1)
A36: Cohort month 27 | B36: 27 | C36: =INDEX(Ops!$E$25:$BL$25,1,$B36) | AF36: =$C36*INDEX(Curves!$M$8:$M$68,AF$4-$B36+1) | AG36: =$C36*INDEX(Curves!$M$8:$M$68,AG$4-$B36+1) | AH36: =$C36*INDEX(Curves!$M$8:$M$68,AH$4-$B36+1) | AI36: =$C36*INDEX(Curves!$M$8:$M$68,AI$4-$B36+1) | AJ36: =$C36*INDEX(Curves!$M$8:$M$68,AJ$4-$B36+1) | AK36: =$C36*INDEX(Curves!$M$8:$M$68,AK$4-$B36+1) | AL36: =$C36*INDEX(Curves!$M$8:$M$68,AL$4-$B36+1) | AM36: =$C36*INDEX(Curves!$M$8:$M$68,AM$4-$B36+1) | ... BL36: =$C36*INDEX(Curves!$M$8:$M$68,BL$4-$B36+1)
A37: Cohort month 28 | B37: 28 | C37: =INDEX(Ops!$E$25:$BL$25,1,$B37) | AG37: =$C37*INDEX(Curves!$M$8:$M$68,AG$4-$B37+1) | AH37: =$C37*INDEX(Curves!$M$8:$M$68,AH$4-$B37+1) | AI37: =$C37*INDEX(Curves!$M$8:$M$68,AI$4-$B37+1) | AJ37: =$C37*INDEX(Curves!$M$8:$M$68,AJ$4-$B37+1) | AK37: =$C37*INDEX(Curves!$M$8:$M$68,AK$4-$B37+1) | AL37: =$C37*INDEX(Curves!$M$8:$M$68,AL$4-$B37+1) | AM37: =$C37*INDEX(Curves!$M$8:$M$68,AM$4-$B37+1) | AN37: =$C37*INDEX(Curves!$M$8:$M$68,AN$4-$B37+1) | ... BL37: =$C37*INDEX(Curves!$M$8:$M$68,BL$4-$B37+1)
A38: Cohort month 29 | B38: 29 | C38: =INDEX(Ops!$E$25:$BL$25,1,$B38) | AH38: =$C38*INDEX(Curves!$M$8:$M$68,AH$4-$B38+1) | AI38: =$C38*INDEX(Curves!$M$8:$M$68,AI$4-$B38+1) | AJ38: =$C38*INDEX(Curves!$M$8:$M$68,AJ$4-$B38+1) | AK38: =$C38*INDEX(Curves!$M$8:$M$68,AK$4-$B38+1) | AL38: =$C38*INDEX(Curves!$M$8:$M$68,AL$4-$B38+1) | AM38: =$C38*INDEX(Curves!$M$8:$M$68,AM$4-$B38+1) | AN38: =$C38*INDEX(Curves!$M$8:$M$68,AN$4-$B38+1) | AO38: =$C38*INDEX(Curves!$M$8:$M$68,AO$4-$B38+1) | ... BL38: =$C38*INDEX(Curves!$M$8:$M$68,BL$4-$B38+1)
A39: Cohort month 30 | B39: 30 | C39: =INDEX(Ops!$E$25:$BL$25,1,$B39) | AI39: =$C39*INDEX(Curves!$M$8:$M$68,AI$4-$B39+1) | AJ39: =$C39*INDEX(Curves!$M$8:$M$68,AJ$4-$B39+1) | AK39: =$C39*INDEX(Curves!$M$8:$M$68,AK$4-$B39+1) | AL39: =$C39*INDEX(Curves!$M$8:$M$68,AL$4-$B39+1) | AM39: =$C39*INDEX(Curves!$M$8:$M$68,AM$4-$B39+1) | AN39: =$C39*INDEX(Curves!$M$8:$M$68,AN$4-$B39+1) | AO39: =$C39*INDEX(Curves!$M$8:$M$68,AO$4-$B39+1) | AP39: =$C39*INDEX(Curves!$M$8:$M$68,AP$4-$B39+1) | ... BL39: =$C39*INDEX(Curves!$M$8:$M$68,BL$4-$B39+1)
A40: Cohort month 31 | B40: 31 | C40: =INDEX(Ops!$E$25:$BL$25,1,$B40) | AJ40: =$C40*INDEX(Curves!$M$8:$M$68,AJ$4-$B40+1) | AK40: =$C40*INDEX(Curves!$M$8:$M$68,AK$4-$B40+1) | AL40: =$C40*INDEX(Curves!$M$8:$M$68,AL$4-$B40+1) | AM40: =$C40*INDEX(Curves!$M$8:$M$68,AM$4-$B40+1) | AN40: =$C40*INDEX(Curves!$M$8:$M$68,AN$4-$B40+1) | AO40: =$C40*INDEX(Curves!$M$8:$M$68,AO$4-$B40+1) | AP40: =$C40*INDEX(Curves!$M$8:$M$68,AP$4-$B40+1) | AQ40: =$C40*INDEX(Curves!$M$8:$M$68,AQ$4-$B40+1) | ... BL40: =$C40*INDEX(Curves!$M$8:$M$68,BL$4-$B40+1)
A41: Cohort month 32 | B41: 32 | C41: =INDEX(Ops!$E$25:$BL$25,1,$B41) | AK41: =$C41*INDEX(Curves!$M$8:$M$68,AK$4-$B41+1) | AL41: =$C41*INDEX(Curves!$M$8:$M$68,AL$4-$B41+1) | AM41: =$C41*INDEX(Curves!$M$8:$M$68,AM$4-$B41+1) | AN41: =$C41*INDEX(Curves!$M$8:$M$68,AN$4-$B41+1) | AO41: =$C41*INDEX(Curves!$M$8:$M$68,AO$4-$B41+1) | AP41: =$C41*INDEX(Curves!$M$8:$M$68,AP$4-$B41+1) | AQ41: =$C41*INDEX(Curves!$M$8:$M$68,AQ$4-$B41+1) | AR41: =$C41*INDEX(Curves!$M$8:$M$68,AR$4-$B41+1) | ... BL41: =$C41*INDEX(Curves!$M$8:$M$68,BL$4-$B41+1)
A42: Cohort month 33 | B42: 33 | C42: =INDEX(Ops!$E$25:$BL$25,1,$B42) | AL42: =$C42*INDEX(Curves!$M$8:$M$68,AL$4-$B42+1) | AM42: =$C42*INDEX(Curves!$M$8:$M$68,AM$4-$B42+1) | AN42: =$C42*INDEX(Curves!$M$8:$M$68,AN$4-$B42+1) | AO42: =$C42*INDEX(Curves!$M$8:$M$68,AO$4-$B42+1) | AP42: =$C42*INDEX(Curves!$M$8:$M$68,AP$4-$B42+1) | AQ42: =$C42*INDEX(Curves!$M$8:$M$68,AQ$4-$B42+1) | AR42: =$C42*INDEX(Curves!$M$8:$M$68,AR$4-$B42+1) | AS42: =$C42*INDEX(Curves!$M$8:$M$68,AS$4-$B42+1) | ... BL42: =$C42*INDEX(Curves!$M$8:$M$68,BL$4-$B42+1)
A43: Cohort month 34 | B43: 34 | C43: =INDEX(Ops!$E$25:$BL$25,1,$B43) | AM43: =$C43*INDEX(Curves!$M$8:$M$68,AM$4-$B43+1) | AN43: =$C43*INDEX(Curves!$M$8:$M$68,AN$4-$B43+1) | AO43: =$C43*INDEX(Curves!$M$8:$M$68,AO$4-$B43+1) | AP43: =$C43*INDEX(Curves!$M$8:$M$68,AP$4-$B43+1) | AQ43: =$C43*INDEX(Curves!$M$8:$M$68,AQ$4-$B43+1) | AR43: =$C43*INDEX(Curves!$M$8:$M$68,AR$4-$B43+1) | AS43: =$C43*INDEX(Curves!$M$8:$M$68,AS$4-$B43+1) | AT43: =$C43*INDEX(Curves!$M$8:$M$68,AT$4-$B43+1) | ... BL43: =$C43*INDEX(Curves!$M$8:$M$68,BL$4-$B43+1)
A44: Cohort month 35 | B44: 35 | C44: =INDEX(Ops!$E$25:$BL$25,1,$B44) | AN44: =$C44*INDEX(Curves!$M$8:$M$68,AN$4-$B44+1) | AO44: =$C44*INDEX(Curves!$M$8:$M$68,AO$4-$B44+1) | AP44: =$C44*INDEX(Curves!$M$8:$M$68,AP$4-$B44+1) | AQ44: =$C44*INDEX(Curves!$M$8:$M$68,AQ$4-$B44+1) | AR44: =$C44*INDEX(Curves!$M$8:$M$68,AR$4-$B44+1) | AS44: =$C44*INDEX(Curves!$M$8:$M$68,AS$4-$B44+1) | AT44: =$C44*INDEX(Curves!$M$8:$M$68,AT$4-$B44+1) | AU44: =$C44*INDEX(Curves!$M$8:$M$68,AU$4-$B44+1) | ... BL44: =$C44*INDEX(Curves!$M$8:$M$68,BL$4-$B44+1)
A45: Cohort month 36 | B45: 36 | C45: =INDEX(Ops!$E$25:$BL$25,1,$B45) | AO45: =$C45*INDEX(Curves!$M$8:$M$68,AO$4-$B45+1) | AP45: =$C45*INDEX(Curves!$M$8:$M$68,AP$4-$B45+1) | AQ45: =$C45*INDEX(Curves!$M$8:$M$68,AQ$4-$B45+1) | AR45: =$C45*INDEX(Curves!$M$8:$M$68,AR$4-$B45+1) | AS45: =$C45*INDEX(Curves!$M$8:$M$68,AS$4-$B45+1) | AT45: =$C45*INDEX(Curves!$M$8:$M$68,AT$4-$B45+1) | AU45: =$C45*INDEX(Curves!$M$8:$M$68,AU$4-$B45+1) | AV45: =$C45*INDEX(Curves!$M$8:$M$68,AV$4-$B45+1) | ... BL45: =$C45*INDEX(Curves!$M$8:$M$68,BL$4-$B45+1)
A46: Cohort month 37 | B46: 37 | C46: =INDEX(Ops!$E$25:$BL$25,1,$B46) | AP46: =$C46*INDEX(Curves!$M$8:$M$68,AP$4-$B46+1) | AQ46: =$C46*INDEX(Curves!$M$8:$M$68,AQ$4-$B46+1) | AR46: =$C46*INDEX(Curves!$M$8:$M$68,AR$4-$B46+1) | AS46: =$C46*INDEX(Curves!$M$8:$M$68,AS$4-$B46+1) | AT46: =$C46*INDEX(Curves!$M$8:$M$68,AT$4-$B46+1) | AU46: =$C46*INDEX(Curves!$M$8:$M$68,AU$4-$B46+1) | AV46: =$C46*INDEX(Curves!$M$8:$M$68,AV$4-$B46+1) | AW46: =$C46*INDEX(Curves!$M$8:$M$68,AW$4-$B46+1) | ... BL46: =$C46*INDEX(Curves!$M$8:$M$68,BL$4-$B46+1)
A47: Cohort month 38 | B47: 38 | C47: =INDEX(Ops!$E$25:$BL$25,1,$B47) | AQ47: =$C47*INDEX(Curves!$M$8:$M$68,AQ$4-$B47+1) | AR47: =$C47*INDEX(Curves!$M$8:$M$68,AR$4-$B47+1) | AS47: =$C47*INDEX(Curves!$M$8:$M$68,AS$4-$B47+1) | AT47: =$C47*INDEX(Curves!$M$8:$M$68,AT$4-$B47+1) | AU47: =$C47*INDEX(Curves!$M$8:$M$68,AU$4-$B47+1) | AV47: =$C47*INDEX(Curves!$M$8:$M$68,AV$4-$B47+1) | AW47: =$C47*INDEX(Curves!$M$8:$M$68,AW$4-$B47+1) | AX47: =$C47*INDEX(Curves!$M$8:$M$68,AX$4-$B47+1) | ... BL47: =$C47*INDEX(Curves!$M$8:$M$68,BL$4-$B47+1)
A48: Cohort month 39 | B48: 39 | C48: =INDEX(Ops!$E$25:$BL$25,1,$B48) | AR48: =$C48*INDEX(Curves!$M$8:$M$68,AR$4-$B48+1) | AS48: =$C48*INDEX(Curves!$M$8:$M$68,AS$4-$B48+1) | AT48: =$C48*INDEX(Curves!$M$8:$M$68,AT$4-$B48+1) | AU48: =$C48*INDEX(Curves!$M$8:$M$68,AU$4-$B48+1) | AV48: =$C48*INDEX(Curves!$M$8:$M$68,AV$4-$B48+1) | AW48: =$C48*INDEX(Curves!$M$8:$M$68,AW$4-$B48+1) | AX48: =$C48*INDEX(Curves!$M$8:$M$68,AX$4-$B48+1) | AY48: =$C48*INDEX(Curves!$M$8:$M$68,AY$4-$B48+1) | ... BL48: =$C48*INDEX(Curves!$M$8:$M$68,BL$4-$B48+1)
A49: Cohort month 40 | B49: 40 | C49: =INDEX(Ops!$E$25:$BL$25,1,$B49) | AS49: =$C49*INDEX(Curves!$M$8:$M$68,AS$4-$B49+1) | AT49: =$C49*INDEX(Curves!$M$8:$M$68,AT$4-$B49+1) | AU49: =$C49*INDEX(Curves!$M$8:$M$68,AU$4-$B49+1) | AV49: =$C49*INDEX(Curves!$M$8:$M$68,AV$4-$B49+1) | AW49: =$C49*INDEX(Curves!$M$8:$M$68,AW$4-$B49+1) | AX49: =$C49*INDEX(Curves!$M$8:$M$68,AX$4-$B49+1) | AY49: =$C49*INDEX(Curves!$M$8:$M$68,AY$4-$B49+1) | AZ49: =$C49*INDEX(Curves!$M$8:$M$68,AZ$4-$B49+1) | ... BL49: =$C49*INDEX(Curves!$M$8:$M$68,BL$4-$B49+1)
A50: Cohort month 41 | B50: 41 | C50: =INDEX(Ops!$E$25:$BL$25,1,$B50) | AT50: =$C50*INDEX(Curves!$M$8:$M$68,AT$4-$B50+1) | AU50: =$C50*INDEX(Curves!$M$8:$M$68,AU$4-$B50+1) | AV50: =$C50*INDEX(Curves!$M$8:$M$68,AV$4-$B50+1) | AW50: =$C50*INDEX(Curves!$M$8:$M$68,AW$4-$B50+1) | AX50: =$C50*INDEX(Curves!$M$8:$M$68,AX$4-$B50+1) | AY50: =$C50*INDEX(Curves!$M$8:$M$68,AY$4-$B50+1) | AZ50: =$C50*INDEX(Curves!$M$8:$M$68,AZ$4-$B50+1) | BA50: =$C50*INDEX(Curves!$M$8:$M$68,BA$4-$B50+1) | ... BL50: =$C50*INDEX(Curves!$M$8:$M$68,BL$4-$B50+1)
A51: Cohort month 42 | B51: 42 | C51: =INDEX(Ops!$E$25:$BL$25,1,$B51) | AU51: =$C51*INDEX(Curves!$M$8:$M$68,AU$4-$B51+1) | AV51: =$C51*INDEX(Curves!$M$8:$M$68,AV$4-$B51+1) | AW51: =$C51*INDEX(Curves!$M$8:$M$68,AW$4-$B51+1) | AX51: =$C51*INDEX(Curves!$M$8:$M$68,AX$4-$B51+1) | AY51: =$C51*INDEX(Curves!$M$8:$M$68,AY$4-$B51+1) | AZ51: =$C51*INDEX(Curves!$M$8:$M$68,AZ$4-$B51+1) | BA51: =$C51*INDEX(Curves!$M$8:$M$68,BA$4-$B51+1) | BB51: =$C51*INDEX(Curves!$M$8:$M$68,BB$4-$B51+1) | ... BL51: =$C51*INDEX(Curves!$M$8:$M$68,BL$4-$B51+1)
A52: Cohort month 43 | B52: 43 | C52: =INDEX(Ops!$E$25:$BL$25,1,$B52) | AV52: =$C52*INDEX(Curves!$M$8:$M$68,AV$4-$B52+1) | AW52: =$C52*INDEX(Curves!$M$8:$M$68,AW$4-$B52+1) | AX52: =$C52*INDEX(Curves!$M$8:$M$68,AX$4-$B52+1) | AY52: =$C52*INDEX(Curves!$M$8:$M$68,AY$4-$B52+1) | AZ52: =$C52*INDEX(Curves!$M$8:$M$68,AZ$4-$B52+1) | BA52: =$C52*INDEX(Curves!$M$8:$M$68,BA$4-$B52+1) | BB52: =$C52*INDEX(Curves!$M$8:$M$68,BB$4-$B52+1) | BC52: =$C52*INDEX(Curves!$M$8:$M$68,BC$4-$B52+1) | ... BL52: =$C52*INDEX(Curves!$M$8:$M$68,BL$4-$B52+1)
A53: Cohort month 44 | B53: 44 | C53: =INDEX(Ops!$E$25:$BL$25,1,$B53) | AW53: =$C53*INDEX(Curves!$M$8:$M$68,AW$4-$B53+1) | AX53: =$C53*INDEX(Curves!$M$8:$M$68,AX$4-$B53+1) | AY53: =$C53*INDEX(Curves!$M$8:$M$68,AY$4-$B53+1) | AZ53: =$C53*INDEX(Curves!$M$8:$M$68,AZ$4-$B53+1) | BA53: =$C53*INDEX(Curves!$M$8:$M$68,BA$4-$B53+1) | BB53: =$C53*INDEX(Curves!$M$8:$M$68,BB$4-$B53+1) | BC53: =$C53*INDEX(Curves!$M$8:$M$68,BC$4-$B53+1) | BD53: =$C53*INDEX(Curves!$M$8:$M$68,BD$4-$B53+1) | ... BL53: =$C53*INDEX(Curves!$M$8:$M$68,BL$4-$B53+1)
A54: Cohort month 45 | B54: 45 | C54: =INDEX(Ops!$E$25:$BL$25,1,$B54) | AX54: =$C54*INDEX(Curves!$M$8:$M$68,AX$4-$B54+1) | AY54: =$C54*INDEX(Curves!$M$8:$M$68,AY$4-$B54+1) | AZ54: =$C54*INDEX(Curves!$M$8:$M$68,AZ$4-$B54+1) | BA54: =$C54*INDEX(Curves!$M$8:$M$68,BA$4-$B54+1) | BB54: =$C54*INDEX(Curves!$M$8:$M$68,BB$4-$B54+1) | BC54: =$C54*INDEX(Curves!$M$8:$M$68,BC$4-$B54+1) | BD54: =$C54*INDEX(Curves!$M$8:$M$68,BD$4-$B54+1) | BE54: =$C54*INDEX(Curves!$M$8:$M$68,BE$4-$B54+1) | ... BL54: =$C54*INDEX(Curves!$M$8:$M$68,BL$4-$B54+1)
A55: Cohort month 46 | B55: 46 | C55: =INDEX(Ops!$E$25:$BL$25,1,$B55) | AY55: =$C55*INDEX(Curves!$M$8:$M$68,AY$4-$B55+1) | AZ55: =$C55*INDEX(Curves!$M$8:$M$68,AZ$4-$B55+1) | BA55: =$C55*INDEX(Curves!$M$8:$M$68,BA$4-$B55+1) | BB55: =$C55*INDEX(Curves!$M$8:$M$68,BB$4-$B55+1) | BC55: =$C55*INDEX(Curves!$M$8:$M$68,BC$4-$B55+1) | BD55: =$C55*INDEX(Curves!$M$8:$M$68,BD$4-$B55+1) | BE55: =$C55*INDEX(Curves!$M$8:$M$68,BE$4-$B55+1) | BF55: =$C55*INDEX(Curves!$M$8:$M$68,BF$4-$B55+1) | ... BL55: =$C55*INDEX(Curves!$M$8:$M$68,BL$4-$B55+1)
A56: Cohort month 47 | B56: 47 | C56: =INDEX(Ops!$E$25:$BL$25,1,$B56) | AZ56: =$C56*INDEX(Curves!$M$8:$M$68,AZ$4-$B56+1) | BA56: =$C56*INDEX(Curves!$M$8:$M$68,BA$4-$B56+1) | BB56: =$C56*INDEX(Curves!$M$8:$M$68,BB$4-$B56+1) | BC56: =$C56*INDEX(Curves!$M$8:$M$68,BC$4-$B56+1) | BD56: =$C56*INDEX(Curves!$M$8:$M$68,BD$4-$B56+1) | BE56: =$C56*INDEX(Curves!$M$8:$M$68,BE$4-$B56+1) | BF56: =$C56*INDEX(Curves!$M$8:$M$68,BF$4-$B56+1) | BG56: =$C56*INDEX(Curves!$M$8:$M$68,BG$4-$B56+1) | ... BL56: =$C56*INDEX(Curves!$M$8:$M$68,BL$4-$B56+1)
A57: Cohort month 48 | B57: 48 | C57: =INDEX(Ops!$E$25:$BL$25,1,$B57) | BA57: =$C57*INDEX(Curves!$M$8:$M$68,BA$4-$B57+1) | BB57: =$C57*INDEX(Curves!$M$8:$M$68,BB$4-$B57+1) | BC57: =$C57*INDEX(Curves!$M$8:$M$68,BC$4-$B57+1) | BD57: =$C57*INDEX(Curves!$M$8:$M$68,BD$4-$B57+1) | BE57: =$C57*INDEX(Curves!$M$8:$M$68,BE$4-$B57+1) | BF57: =$C57*INDEX(Curves!$M$8:$M$68,BF$4-$B57+1) | BG57: =$C57*INDEX(Curves!$M$8:$M$68,BG$4-$B57+1) | BH57: =$C57*INDEX(Curves!$M$8:$M$68,BH$4-$B57+1) | ... BL57: =$C57*INDEX(Curves!$M$8:$M$68,BL$4-$B57+1)
A58: Cohort month 49 | B58: 49 | C58: =INDEX(Ops!$E$25:$BL$25,1,$B58) | BB58: =$C58*INDEX(Curves!$M$8:$M$68,BB$4-$B58+1) | BC58: =$C58*INDEX(Curves!$M$8:$M$68,BC$4-$B58+1) | BD58: =$C58*INDEX(Curves!$M$8:$M$68,BD$4-$B58+1) | BE58: =$C58*INDEX(Curves!$M$8:$M$68,BE$4-$B58+1) | BF58: =$C58*INDEX(Curves!$M$8:$M$68,BF$4-$B58+1) | BG58: =$C58*INDEX(Curves!$M$8:$M$68,BG$4-$B58+1) | BH58: =$C58*INDEX(Curves!$M$8:$M$68,BH$4-$B58+1) | BI58: =$C58*INDEX(Curves!$M$8:$M$68,BI$4-$B58+1) | ... BL58: =$C58*INDEX(Curves!$M$8:$M$68,BL$4-$B58+1)
A59: Cohort month 50 | B59: 50 | C59: =INDEX(Ops!$E$25:$BL$25,1,$B59) | BC59: =$C59*INDEX(Curves!$M$8:$M$68,BC$4-$B59+1) | BD59: =$C59*INDEX(Curves!$M$8:$M$68,BD$4-$B59+1) | BE59: =$C59*INDEX(Curves!$M$8:$M$68,BE$4-$B59+1) | BF59: =$C59*INDEX(Curves!$M$8:$M$68,BF$4-$B59+1) | BG59: =$C59*INDEX(Curves!$M$8:$M$68,BG$4-$B59+1) | BH59: =$C59*INDEX(Curves!$M$8:$M$68,BH$4-$B59+1) | BI59: =$C59*INDEX(Curves!$M$8:$M$68,BI$4-$B59+1) | BJ59: =$C59*INDEX(Curves!$M$8:$M$68,BJ$4-$B59+1) | ... BL59: =$C59*INDEX(Curves!$M$8:$M$68,BL$4-$B59+1)
A60: Cohort month 51 | B60: 51 | C60: =INDEX(Ops!$E$25:$BL$25,1,$B60) | BD60: =$C60*INDEX(Curves!$M$8:$M$68,BD$4-$B60+1) | BE60: =$C60*INDEX(Curves!$M$8:$M$68,BE$4-$B60+1) | BF60: =$C60*INDEX(Curves!$M$8:$M$68,BF$4-$B60+1) | BG60: =$C60*INDEX(Curves!$M$8:$M$68,BG$4-$B60+1) | BH60: =$C60*INDEX(Curves!$M$8:$M$68,BH$4-$B60+1) | BI60: =$C60*INDEX(Curves!$M$8:$M$68,BI$4-$B60+1) | BJ60: =$C60*INDEX(Curves!$M$8:$M$68,BJ$4-$B60+1) | BK60: =$C60*INDEX(Curves!$M$8:$M$68,BK$4-$B60+1) | BL60: =$C60*INDEX(Curves!$M$8:$M$68,BL$4-$B60+1)
A61: Cohort month 52 | B61: 52 | C61: =INDEX(Ops!$E$25:$BL$25,1,$B61) | BE61: =$C61*INDEX(Curves!$M$8:$M$68,BE$4-$B61+1) | BF61: =$C61*INDEX(Curves!$M$8:$M$68,BF$4-$B61+1) | BG61: =$C61*INDEX(Curves!$M$8:$M$68,BG$4-$B61+1) | BH61: =$C61*INDEX(Curves!$M$8:$M$68,BH$4-$B61+1) | BI61: =$C61*INDEX(Curves!$M$8:$M$68,BI$4-$B61+1) | BJ61: =$C61*INDEX(Curves!$M$8:$M$68,BJ$4-$B61+1) | BK61: =$C61*INDEX(Curves!$M$8:$M$68,BK$4-$B61+1) | BL61: =$C61*INDEX(Curves!$M$8:$M$68,BL$4-$B61+1)
A62: Cohort month 53 | B62: 53 | C62: =INDEX(Ops!$E$25:$BL$25,1,$B62) | BF62: =$C62*INDEX(Curves!$M$8:$M$68,BF$4-$B62+1) | BG62: =$C62*INDEX(Curves!$M$8:$M$68,BG$4-$B62+1) | BH62: =$C62*INDEX(Curves!$M$8:$M$68,BH$4-$B62+1) | BI62: =$C62*INDEX(Curves!$M$8:$M$68,BI$4-$B62+1) | BJ62: =$C62*INDEX(Curves!$M$8:$M$68,BJ$4-$B62+1) | BK62: =$C62*INDEX(Curves!$M$8:$M$68,BK$4-$B62+1) | BL62: =$C62*INDEX(Curves!$M$8:$M$68,BL$4-$B62+1)
A63: Cohort month 54 | B63: 54 | C63: =INDEX(Ops!$E$25:$BL$25,1,$B63) | BG63: =$C63*INDEX(Curves!$M$8:$M$68,BG$4-$B63+1) | BH63: =$C63*INDEX(Curves!$M$8:$M$68,BH$4-$B63+1) | BI63: =$C63*INDEX(Curves!$M$8:$M$68,BI$4-$B63+1) | BJ63: =$C63*INDEX(Curves!$M$8:$M$68,BJ$4-$B63+1) | BK63: =$C63*INDEX(Curves!$M$8:$M$68,BK$4-$B63+1) | BL63: =$C63*INDEX(Curves!$M$8:$M$68,BL$4-$B63+1)
A64: Cohort month 55 | B64: 55 | C64: =INDEX(Ops!$E$25:$BL$25,1,$B64) | BH64: =$C64*INDEX(Curves!$M$8:$M$68,BH$4-$B64+1) | BI64: =$C64*INDEX(Curves!$M$8:$M$68,BI$4-$B64+1) | BJ64: =$C64*INDEX(Curves!$M$8:$M$68,BJ$4-$B64+1) | BK64: =$C64*INDEX(Curves!$M$8:$M$68,BK$4-$B64+1) | BL64: =$C64*INDEX(Curves!$M$8:$M$68,BL$4-$B64+1)
A65: Cohort month 56 | B65: 56 | C65: =INDEX(Ops!$E$25:$BL$25,1,$B65) | BI65: =$C65*INDEX(Curves!$M$8:$M$68,BI$4-$B65+1) | BJ65: =$C65*INDEX(Curves!$M$8:$M$68,BJ$4-$B65+1) | BK65: =$C65*INDEX(Curves!$M$8:$M$68,BK$4-$B65+1) | BL65: =$C65*INDEX(Curves!$M$8:$M$68,BL$4-$B65+1)
A66: Cohort month 57 | B66: 57 | C66: =INDEX(Ops!$E$25:$BL$25,1,$B66) | BJ66: =$C66*INDEX(Curves!$M$8:$M$68,BJ$4-$B66+1) | BK66: =$C66*INDEX(Curves!$M$8:$M$68,BK$4-$B66+1) | BL66: =$C66*INDEX(Curves!$M$8:$M$68,BL$4-$B66+1)
A67: Cohort month 58 | B67: 58 | C67: =INDEX(Ops!$E$25:$BL$25,1,$B67) | BK67: =$C67*INDEX(Curves!$M$8:$M$68,BK$4-$B67+1) | BL67: =$C67*INDEX(Curves!$M$8:$M$68,BL$4-$B67+1)
A68: Cohort month 59 | B68: 59 | C68: =INDEX(Ops!$E$25:$BL$25,1,$B68) | BL68: =$C68*INDEX(Curves!$M$8:$M$68,BL$4-$B68+1)
A69: Cohort month 60 | B69: 60 | C69: =INDEX(Ops!$E$25:$BL$25,1,$B69)
A71: Active accounts by cohort
A72: Total | E72: =SUM(E73:E132) | F72: =SUM(F73:F132) | G72: =SUM(G73:G132) | H72: =SUM(H73:H132) | I72: =SUM(I73:I132) | J72: =SUM(J73:J132) | K72: =SUM(K73:K132) | L72: =SUM(L73:L132) | ... BL72: =SUM(BL73:BL132)
A73: Cohort month 1 | B73: 1 | C73: =INDEX(Ops!$E$24:$BL$24,1,$B73) | F73: =$C73*INDEX(Curves!$P$8:$P$68,F$4-$B73+1) | G73: =$C73*INDEX(Curves!$P$8:$P$68,G$4-$B73+1) | H73: =$C73*INDEX(Curves!$P$8:$P$68,H$4-$B73+1) | I73: =$C73*INDEX(Curves!$P$8:$P$68,I$4-$B73+1) | J73: =$C73*INDEX(Curves!$P$8:$P$68,J$4-$B73+1) | K73: =$C73*INDEX(Curves!$P$8:$P$68,K$4-$B73+1) | L73: =$C73*INDEX(Curves!$P$8:$P$68,L$4-$B73+1) | M73: =$C73*INDEX(Curves!$P$8:$P$68,M$4-$B73+1) | ... BL73: =$C73*INDEX(Curves!$P$8:$P$68,BL$4-$B73+1)
A74: Cohort month 2 | B74: 2 | C74: =INDEX(Ops!$E$24:$BL$24,1,$B74) | G74: =$C74*INDEX(Curves!$P$8:$P$68,G$4-$B74+1) | H74: =$C74*INDEX(Curves!$P$8:$P$68,H$4-$B74+1) | I74: =$C74*INDEX(Curves!$P$8:$P$68,I$4-$B74+1) | J74: =$C74*INDEX(Curves!$P$8:$P$68,J$4-$B74+1) | K74: =$C74*INDEX(Curves!$P$8:$P$68,K$4-$B74+1) | L74: =$C74*INDEX(Curves!$P$8:$P$68,L$4-$B74+1) | M74: =$C74*INDEX(Curves!$P$8:$P$68,M$4-$B74+1) | N74: =$C74*INDEX(Curves!$P$8:$P$68,N$4-$B74+1) | ... BL74: =$C74*INDEX(Curves!$P$8:$P$68,BL$4-$B74+1)
A75: Cohort month 3 | B75: 3 | C75: =INDEX(Ops!$E$24:$BL$24,1,$B75) | H75: =$C75*INDEX(Curves!$P$8:$P$68,H$4-$B75+1) | I75: =$C75*INDEX(Curves!$P$8:$P$68,I$4-$B75+1) | J75: =$C75*INDEX(Curves!$P$8:$P$68,J$4-$B75+1) | K75: =$C75*INDEX(Curves!$P$8:$P$68,K$4-$B75+1) | L75: =$C75*INDEX(Curves!$P$8:$P$68,L$4-$B75+1) | M75: =$C75*INDEX(Curves!$P$8:$P$68,M$4-$B75+1) | N75: =$C75*INDEX(Curves!$P$8:$P$68,N$4-$B75+1) | O75: =$C75*INDEX(Curves!$P$8:$P$68,O$4-$B75+1) | ... BL75: =$C75*INDEX(Curves!$P$8:$P$68,BL$4-$B75+1)
A76: Cohort month 4 | B76: 4 | C76: =INDEX(Ops!$E$24:$BL$24,1,$B76) | I76: =$C76*INDEX(Curves!$P$8:$P$68,I$4-$B76+1) | J76: =$C76*INDEX(Curves!$P$8:$P$68,J$4-$B76+1) | K76: =$C76*INDEX(Curves!$P$8:$P$68,K$4-$B76+1) | L76: =$C76*INDEX(Curves!$P$8:$P$68,L$4-$B76+1) | M76: =$C76*INDEX(Curves!$P$8:$P$68,M$4-$B76+1) | N76: =$C76*INDEX(Curves!$P$8:$P$68,N$4-$B76+1) | O76: =$C76*INDEX(Curves!$P$8:$P$68,O$4-$B76+1) | P76: =$C76*INDEX(Curves!$P$8:$P$68,P$4-$B76+1) | ... BL76: =$C76*INDEX(Curves!$P$8:$P$68,BL$4-$B76+1)
A77: Cohort month 5 | B77: 5 | C77: =INDEX(Ops!$E$24:$BL$24,1,$B77) | J77: =$C77*INDEX(Curves!$P$8:$P$68,J$4-$B77+1) | K77: =$C77*INDEX(Curves!$P$8:$P$68,K$4-$B77+1) | L77: =$C77*INDEX(Curves!$P$8:$P$68,L$4-$B77+1) | M77: =$C77*INDEX(Curves!$P$8:$P$68,M$4-$B77+1) | N77: =$C77*INDEX(Curves!$P$8:$P$68,N$4-$B77+1) | O77: =$C77*INDEX(Curves!$P$8:$P$68,O$4-$B77+1) | P77: =$C77*INDEX(Curves!$P$8:$P$68,P$4-$B77+1) | Q77: =$C77*INDEX(Curves!$P$8:$P$68,Q$4-$B77+1) | ... BL77: =$C77*INDEX(Curves!$P$8:$P$68,BL$4-$B77+1)
A78: Cohort month 6 | B78: 6 | C78: =INDEX(Ops!$E$24:$BL$24,1,$B78) | K78: =$C78*INDEX(Curves!$P$8:$P$68,K$4-$B78+1) | L78: =$C78*INDEX(Curves!$P$8:$P$68,L$4-$B78+1) | M78: =$C78*INDEX(Curves!$P$8:$P$68,M$4-$B78+1) | N78: =$C78*INDEX(Curves!$P$8:$P$68,N$4-$B78+1) | O78: =$C78*INDEX(Curves!$P$8:$P$68,O$4-$B78+1) | P78: =$C78*INDEX(Curves!$P$8:$P$68,P$4-$B78+1) | Q78: =$C78*INDEX(Curves!$P$8:$P$68,Q$4-$B78+1) | R78: =$C78*INDEX(Curves!$P$8:$P$68,R$4-$B78+1) | ... BL78: =$C78*INDEX(Curves!$P$8:$P$68,BL$4-$B78+1)
A79: Cohort month 7 | B79: 7 | C79: =INDEX(Ops!$E$24:$BL$24,1,$B79) | L79: =$C79*INDEX(Curves!$P$8:$P$68,L$4-$B79+1) | M79: =$C79*INDEX(Curves!$P$8:$P$68,M$4-$B79+1) | N79: =$C79*INDEX(Curves!$P$8:$P$68,N$4-$B79+1) | O79: =$C79*INDEX(Curves!$P$8:$P$68,O$4-$B79+1) | P79: =$C79*INDEX(Curves!$P$8:$P$68,P$4-$B79+1) | Q79: =$C79*INDEX(Curves!$P$8:$P$68,Q$4-$B79+1) | R79: =$C79*INDEX(Curves!$P$8:$P$68,R$4-$B79+1) | S79: =$C79*INDEX(Curves!$P$8:$P$68,S$4-$B79+1) | ... BL79: =$C79*INDEX(Curves!$P$8:$P$68,BL$4-$B79+1)
A80: Cohort month 8 | B80: 8 | C80: =INDEX(Ops!$E$24:$BL$24,1,$B80) | M80: =$C80*INDEX(Curves!$P$8:$P$68,M$4-$B80+1) | N80: =$C80*INDEX(Curves!$P$8:$P$68,N$4-$B80+1) | O80: =$C80*INDEX(Curves!$P$8:$P$68,O$4-$B80+1) | P80: =$C80*INDEX(Curves!$P$8:$P$68,P$4-$B80+1) | Q80: =$C80*INDEX(Curves!$P$8:$P$68,Q$4-$B80+1) | R80: =$C80*INDEX(Curves!$P$8:$P$68,R$4-$B80+1) | S80: =$C80*INDEX(Curves!$P$8:$P$68,S$4-$B80+1) | T80: =$C80*INDEX(Curves!$P$8:$P$68,T$4-$B80+1) | ... BL80: =$C80*INDEX(Curves!$P$8:$P$68,BL$4-$B80+1)
A81: Cohort month 9 | B81: 9 | C81: =INDEX(Ops!$E$24:$BL$24,1,$B81) | N81: =$C81*INDEX(Curves!$P$8:$P$68,N$4-$B81+1) | O81: =$C81*INDEX(Curves!$P$8:$P$68,O$4-$B81+1) | P81: =$C81*INDEX(Curves!$P$8:$P$68,P$4-$B81+1) | Q81: =$C81*INDEX(Curves!$P$8:$P$68,Q$4-$B81+1) | R81: =$C81*INDEX(Curves!$P$8:$P$68,R$4-$B81+1) | S81: =$C81*INDEX(Curves!$P$8:$P$68,S$4-$B81+1) | T81: =$C81*INDEX(Curves!$P$8:$P$68,T$4-$B81+1) | U81: =$C81*INDEX(Curves!$P$8:$P$68,U$4-$B81+1) | ... BL81: =$C81*INDEX(Curves!$P$8:$P$68,BL$4-$B81+1)
A82: Cohort month 10 | B82: 10 | C82: =INDEX(Ops!$E$24:$BL$24,1,$B82) | O82: =$C82*INDEX(Curves!$P$8:$P$68,O$4-$B82+1) | P82: =$C82*INDEX(Curves!$P$8:$P$68,P$4-$B82+1) | Q82: =$C82*INDEX(Curves!$P$8:$P$68,Q$4-$B82+1) | R82: =$C82*INDEX(Curves!$P$8:$P$68,R$4-$B82+1) | S82: =$C82*INDEX(Curves!$P$8:$P$68,S$4-$B82+1) | T82: =$C82*INDEX(Curves!$P$8:$P$68,T$4-$B82+1) | U82: =$C82*INDEX(Curves!$P$8:$P$68,U$4-$B82+1) | V82: =$C82*INDEX(Curves!$P$8:$P$68,V$4-$B82+1) | ... BL82: =$C82*INDEX(Curves!$P$8:$P$68,BL$4-$B82+1)
A83: Cohort month 11 | B83: 11 | C83: =INDEX(Ops!$E$24:$BL$24,1,$B83) | P83: =$C83*INDEX(Curves!$P$8:$P$68,P$4-$B83+1) | Q83: =$C83*INDEX(Curves!$P$8:$P$68,Q$4-$B83+1) | R83: =$C83*INDEX(Curves!$P$8:$P$68,R$4-$B83+1) | S83: =$C83*INDEX(Curves!$P$8:$P$68,S$4-$B83+1) | T83: =$C83*INDEX(Curves!$P$8:$P$68,T$4-$B83+1) | U83: =$C83*INDEX(Curves!$P$8:$P$68,U$4-$B83+1) | V83: =$C83*INDEX(Curves!$P$8:$P$68,V$4-$B83+1) | W83: =$C83*INDEX(Curves!$P$8:$P$68,W$4-$B83+1) | ... BL83: =$C83*INDEX(Curves!$P$8:$P$68,BL$4-$B83+1)
A84: Cohort month 12 | B84: 12 | C84: =INDEX(Ops!$E$24:$BL$24,1,$B84) | Q84: =$C84*INDEX(Curves!$P$8:$P$68,Q$4-$B84+1) | R84: =$C84*INDEX(Curves!$P$8:$P$68,R$4-$B84+1) | S84: =$C84*INDEX(Curves!$P$8:$P$68,S$4-$B84+1) | T84: =$C84*INDEX(Curves!$P$8:$P$68,T$4-$B84+1) | U84: =$C84*INDEX(Curves!$P$8:$P$68,U$4-$B84+1) | V84: =$C84*INDEX(Curves!$P$8:$P$68,V$4-$B84+1) | W84: =$C84*INDEX(Curves!$P$8:$P$68,W$4-$B84+1) | X84: =$C84*INDEX(Curves!$P$8:$P$68,X$4-$B84+1) | ... BL84: =$C84*INDEX(Curves!$P$8:$P$68,BL$4-$B84+1)
A85: Cohort month 13 | B85: 13 | C85: =INDEX(Ops!$E$24:$BL$24,1,$B85) | R85: =$C85*INDEX(Curves!$P$8:$P$68,R$4-$B85+1) | S85: =$C85*INDEX(Curves!$P$8:$P$68,S$4-$B85+1) | T85: =$C85*INDEX(Curves!$P$8:$P$68,T$4-$B85+1) | U85: =$C85*INDEX(Curves!$P$8:$P$68,U$4-$B85+1) | V85: =$C85*INDEX(Curves!$P$8:$P$68,V$4-$B85+1) | W85: =$C85*INDEX(Curves!$P$8:$P$68,W$4-$B85+1) | X85: =$C85*INDEX(Curves!$P$8:$P$68,X$4-$B85+1) | Y85: =$C85*INDEX(Curves!$P$8:$P$68,Y$4-$B85+1) | ... BL85: =$C85*INDEX(Curves!$P$8:$P$68,BL$4-$B85+1)
A86: Cohort month 14 | B86: 14 | C86: =INDEX(Ops!$E$24:$BL$24,1,$B86) | S86: =$C86*INDEX(Curves!$P$8:$P$68,S$4-$B86+1) | T86: =$C86*INDEX(Curves!$P$8:$P$68,T$4-$B86+1) | U86: =$C86*INDEX(Curves!$P$8:$P$68,U$4-$B86+1) | V86: =$C86*INDEX(Curves!$P$8:$P$68,V$4-$B86+1) | W86: =$C86*INDEX(Curves!$P$8:$P$68,W$4-$B86+1) | X86: =$C86*INDEX(Curves!$P$8:$P$68,X$4-$B86+1) | Y86: =$C86*INDEX(Curves!$P$8:$P$68,Y$4-$B86+1) | Z86: =$C86*INDEX(Curves!$P$8:$P$68,Z$4-$B86+1) | ... BL86: =$C86*INDEX(Curves!$P$8:$P$68,BL$4-$B86+1)
A87: Cohort month 15 | B87: 15 | C87: =INDEX(Ops!$E$24:$BL$24,1,$B87) | T87: =$C87*INDEX(Curves!$P$8:$P$68,T$4-$B87+1) | U87: =$C87*INDEX(Curves!$P$8:$P$68,U$4-$B87+1) | V87: =$C87*INDEX(Curves!$P$8:$P$68,V$4-$B87+1) | W87: =$C87*INDEX(Curves!$P$8:$P$68,W$4-$B87+1) | X87: =$C87*INDEX(Curves!$P$8:$P$68,X$4-$B87+1) | Y87: =$C87*INDEX(Curves!$P$8:$P$68,Y$4-$B87+1) | Z87: =$C87*INDEX(Curves!$P$8:$P$68,Z$4-$B87+1) | AA87: =$C87*INDEX(Curves!$P$8:$P$68,AA$4-$B87+1) | ... BL87: =$C87*INDEX(Curves!$P$8:$P$68,BL$4-$B87+1)
A88: Cohort month 16 | B88: 16 | C88: =INDEX(Ops!$E$24:$BL$24,1,$B88) | U88: =$C88*INDEX(Curves!$P$8:$P$68,U$4-$B88+1) | V88: =$C88*INDEX(Curves!$P$8:$P$68,V$4-$B88+1) | W88: =$C88*INDEX(Curves!$P$8:$P$68,W$4-$B88+1) | X88: =$C88*INDEX(Curves!$P$8:$P$68,X$4-$B88+1) | Y88: =$C88*INDEX(Curves!$P$8:$P$68,Y$4-$B88+1) | Z88: =$C88*INDEX(Curves!$P$8:$P$68,Z$4-$B88+1) | AA88: =$C88*INDEX(Curves!$P$8:$P$68,AA$4-$B88+1) | AB88: =$C88*INDEX(Curves!$P$8:$P$68,AB$4-$B88+1) | ... BL88: =$C88*INDEX(Curves!$P$8:$P$68,BL$4-$B88+1)
A89: Cohort month 17 | B89: 17 | C89: =INDEX(Ops!$E$24:$BL$24,1,$B89) | V89: =$C89*INDEX(Curves!$P$8:$P$68,V$4-$B89+1) | W89: =$C89*INDEX(Curves!$P$8:$P$68,W$4-$B89+1) | X89: =$C89*INDEX(Curves!$P$8:$P$68,X$4-$B89+1) | Y89: =$C89*INDEX(Curves!$P$8:$P$68,Y$4-$B89+1) | Z89: =$C89*INDEX(Curves!$P$8:$P$68,Z$4-$B89+1) | AA89: =$C89*INDEX(Curves!$P$8:$P$68,AA$4-$B89+1) | AB89: =$C89*INDEX(Curves!$P$8:$P$68,AB$4-$B89+1) | AC89: =$C89*INDEX(Curves!$P$8:$P$68,AC$4-$B89+1) | ... BL89: =$C89*INDEX(Curves!$P$8:$P$68,BL$4-$B89+1)
A90: Cohort month 18 | B90: 18 | C90: =INDEX(Ops!$E$24:$BL$24,1,$B90) | W90: =$C90*INDEX(Curves!$P$8:$P$68,W$4-$B90+1) | X90: =$C90*INDEX(Curves!$P$8:$P$68,X$4-$B90+1) | Y90: =$C90*INDEX(Curves!$P$8:$P$68,Y$4-$B90+1) | Z90: =$C90*INDEX(Curves!$P$8:$P$68,Z$4-$B90+1) | AA90: =$C90*INDEX(Curves!$P$8:$P$68,AA$4-$B90+1) | AB90: =$C90*INDEX(Curves!$P$8:$P$68,AB$4-$B90+1) | AC90: =$C90*INDEX(Curves!$P$8:$P$68,AC$4-$B90+1) | AD90: =$C90*INDEX(Curves!$P$8:$P$68,AD$4-$B90+1) | ... BL90: =$C90*INDEX(Curves!$P$8:$P$68,BL$4-$B90+1)
A91: Cohort month 19 | B91: 19 | C91: =INDEX(Ops!$E$24:$BL$24,1,$B91) | X91: =$C91*INDEX(Curves!$P$8:$P$68,X$4-$B91+1) | Y91: =$C91*INDEX(Curves!$P$8:$P$68,Y$4-$B91+1) | Z91: =$C91*INDEX(Curves!$P$8:$P$68,Z$4-$B91+1) | AA91: =$C91*INDEX(Curves!$P$8:$P$68,AA$4-$B91+1) | AB91: =$C91*INDEX(Curves!$P$8:$P$68,AB$4-$B91+1) | AC91: =$C91*INDEX(Curves!$P$8:$P$68,AC$4-$B91+1) | AD91: =$C91*INDEX(Curves!$P$8:$P$68,AD$4-$B91+1) | AE91: =$C91*INDEX(Curves!$P$8:$P$68,AE$4-$B91+1) | ... BL91: =$C91*INDEX(Curves!$P$8:$P$68,BL$4-$B91+1)
A92: Cohort month 20 | B92: 20 | C92: =INDEX(Ops!$E$24:$BL$24,1,$B92) | Y92: =$C92*INDEX(Curves!$P$8:$P$68,Y$4-$B92+1) | Z92: =$C92*INDEX(Curves!$P$8:$P$68,Z$4-$B92+1) | AA92: =$C92*INDEX(Curves!$P$8:$P$68,AA$4-$B92+1) | AB92: =$C92*INDEX(Curves!$P$8:$P$68,AB$4-$B92+1) | AC92: =$C92*INDEX(Curves!$P$8:$P$68,AC$4-$B92+1) | AD92: =$C92*INDEX(Curves!$P$8:$P$68,AD$4-$B92+1) | AE92: =$C92*INDEX(Curves!$P$8:$P$68,AE$4-$B92+1) | AF92: =$C92*INDEX(Curves!$P$8:$P$68,AF$4-$B92+1) | ... BL92: =$C92*INDEX(Curves!$P$8:$P$68,BL$4-$B92+1)
A93: Cohort month 21 | B93: 21 | C93: =INDEX(Ops!$E$24:$BL$24,1,$B93) | Z93: =$C93*INDEX(Curves!$P$8:$P$68,Z$4-$B93+1) | AA93: =$C93*INDEX(Curves!$P$8:$P$68,AA$4-$B93+1) | AB93: =$C93*INDEX(Curves!$P$8:$P$68,AB$4-$B93+1) | AC93: =$C93*INDEX(Curves!$P$8:$P$68,AC$4-$B93+1) | AD93: =$C93*INDEX(Curves!$P$8:$P$68,AD$4-$B93+1) | AE93: =$C93*INDEX(Curves!$P$8:$P$68,AE$4-$B93+1) | AF93: =$C93*INDEX(Curves!$P$8:$P$68,AF$4-$B93+1) | AG93: =$C93*INDEX(Curves!$P$8:$P$68,AG$4-$B93+1) | ... BL93: =$C93*INDEX(Curves!$P$8:$P$68,BL$4-$B93+1)
A94: Cohort month 22 | B94: 22 | C94: =INDEX(Ops!$E$24:$BL$24,1,$B94) | AA94: =$C94*INDEX(Curves!$P$8:$P$68,AA$4-$B94+1) | AB94: =$C94*INDEX(Curves!$P$8:$P$68,AB$4-$B94+1) | AC94: =$C94*INDEX(Curves!$P$8:$P$68,AC$4-$B94+1) | AD94: =$C94*INDEX(Curves!$P$8:$P$68,AD$4-$B94+1) | AE94: =$C94*INDEX(Curves!$P$8:$P$68,AE$4-$B94+1) | AF94: =$C94*INDEX(Curves!$P$8:$P$68,AF$4-$B94+1) | AG94: =$C94*INDEX(Curves!$P$8:$P$68,AG$4-$B94+1) | AH94: =$C94*INDEX(Curves!$P$8:$P$68,AH$4-$B94+1) | ... BL94: =$C94*INDEX(Curves!$P$8:$P$68,BL$4-$B94+1)
A95: Cohort month 23 | B95: 23 | C95: =INDEX(Ops!$E$24:$BL$24,1,$B95) | AB95: =$C95*INDEX(Curves!$P$8:$P$68,AB$4-$B95+1) | AC95: =$C95*INDEX(Curves!$P$8:$P$68,AC$4-$B95+1) | AD95: =$C95*INDEX(Curves!$P$8:$P$68,AD$4-$B95+1) | AE95: =$C95*INDEX(Curves!$P$8:$P$68,AE$4-$B95+1) | AF95: =$C95*INDEX(Curves!$P$8:$P$68,AF$4-$B95+1) | AG95: =$C95*INDEX(Curves!$P$8:$P$68,AG$4-$B95+1) | AH95: =$C95*INDEX(Curves!$P$8:$P$68,AH$4-$B95+1) | AI95: =$C95*INDEX(Curves!$P$8:$P$68,AI$4-$B95+1) | ... BL95: =$C95*INDEX(Curves!$P$8:$P$68,BL$4-$B95+1)
A96: Cohort month 24 | B96: 24 | C96: =INDEX(Ops!$E$24:$BL$24,1,$B96) | AC96: =$C96*INDEX(Curves!$P$8:$P$68,AC$4-$B96+1) | AD96: =$C96*INDEX(Curves!$P$8:$P$68,AD$4-$B96+1) | AE96: =$C96*INDEX(Curves!$P$8:$P$68,AE$4-$B96+1) | AF96: =$C96*INDEX(Curves!$P$8:$P$68,AF$4-$B96+1) | AG96: =$C96*INDEX(Curves!$P$8:$P$68,AG$4-$B96+1) | AH96: =$C96*INDEX(Curves!$P$8:$P$68,AH$4-$B96+1) | AI96: =$C96*INDEX(Curves!$P$8:$P$68,AI$4-$B96+1) | AJ96: =$C96*INDEX(Curves!$P$8:$P$68,AJ$4-$B96+1) | ... BL96: =$C96*INDEX(Curves!$P$8:$P$68,BL$4-$B96+1)
A97: Cohort month 25 | B97: 25 | C97: =INDEX(Ops!$E$24:$BL$24,1,$B97) | AD97: =$C97*INDEX(Curves!$P$8:$P$68,AD$4-$B97+1) | AE97: =$C97*INDEX(Curves!$P$8:$P$68,AE$4-$B97+1) | AF97: =$C97*INDEX(Curves!$P$8:$P$68,AF$4-$B97+1) | AG97: =$C97*INDEX(Curves!$P$8:$P$68,AG$4-$B97+1) | AH97: =$C97*INDEX(Curves!$P$8:$P$68,AH$4-$B97+1) | AI97: =$C97*INDEX(Curves!$P$8:$P$68,AI$4-$B97+1) | AJ97: =$C97*INDEX(Curves!$P$8:$P$68,AJ$4-$B97+1) | AK97: =$C97*INDEX(Curves!$P$8:$P$68,AK$4-$B97+1) | ... BL97: =$C97*INDEX(Curves!$P$8:$P$68,BL$4-$B97+1)
A98: Cohort month 26 | B98: 26 | C98: =INDEX(Ops!$E$24:$BL$24,1,$B98) | AE98: =$C98*INDEX(Curves!$P$8:$P$68,AE$4-$B98+1) | AF98: =$C98*INDEX(Curves!$P$8:$P$68,AF$4-$B98+1) | AG98: =$C98*INDEX(Curves!$P$8:$P$68,AG$4-$B98+1) | AH98: =$C98*INDEX(Curves!$P$8:$P$68,AH$4-$B98+1) | AI98: =$C98*INDEX(Curves!$P$8:$P$68,AI$4-$B98+1) | AJ98: =$C98*INDEX(Curves!$P$8:$P$68,AJ$4-$B98+1) | AK98: =$C98*INDEX(Curves!$P$8:$P$68,AK$4-$B98+1) | AL98: =$C98*INDEX(Curves!$P$8:$P$68,AL$4-$B98+1) | ... BL98: =$C98*INDEX(Curves!$P$8:$P$68,BL$4-$B98+1)
A99: Cohort month 27 | B99: 27 | C99: =INDEX(Ops!$E$24:$BL$24,1,$B99) | AF99: =$C99*INDEX(Curves!$P$8:$P$68,AF$4-$B99+1) | AG99: =$C99*INDEX(Curves!$P$8:$P$68,AG$4-$B99+1) | AH99: =$C99*INDEX(Curves!$P$8:$P$68,AH$4-$B99+1) | AI99: =$C99*INDEX(Curves!$P$8:$P$68,AI$4-$B99+1) | AJ99: =$C99*INDEX(Curves!$P$8:$P$68,AJ$4-$B99+1) | AK99: =$C99*INDEX(Curves!$P$8:$P$68,AK$4-$B99+1) | AL99: =$C99*INDEX(Curves!$P$8:$P$68,AL$4-$B99+1) | AM99: =$C99*INDEX(Curves!$P$8:$P$68,AM$4-$B99+1) | ... BL99: =$C99*INDEX(Curves!$P$8:$P$68,BL$4-$B99+1)
A100: Cohort month 28 | B100: 28 | C100: =INDEX(Ops!$E$24:$BL$24,1,$B100) | AG100: =$C100*INDEX(Curves!$P$8:$P$68,AG$4-$B100+1) | AH100: =$C100*INDEX(Curves!$P$8:$P$68,AH$4-$B100+1) | AI100: =$C100*INDEX(Curves!$P$8:$P$68,AI$4-$B100+1) | AJ100: =$C100*INDEX(Curves!$P$8:$P$68,AJ$4-$B100+1) | AK100: =$C100*INDEX(Curves!$P$8:$P$68,AK$4-$B100+1) | AL100: =$C100*INDEX(Curves!$P$8:$P$68,AL$4-$B100+1) | AM100: =$C100*INDEX(Curves!$P$8:$P$68,AM$4-$B100+1) | AN100: =$C100*INDEX(Curves!$P$8:$P$68,AN$4-$B100+1) | ... BL100: =$C100*INDEX(Curves!$P$8:$P$68,BL$4-$B100+1)
A101: Cohort month 29 | B101: 29 | C101: =INDEX(Ops!$E$24:$BL$24,1,$B101) | AH101: =$C101*INDEX(Curves!$P$8:$P$68,AH$4-$B101+1) | AI101: =$C101*INDEX(Curves!$P$8:$P$68,AI$4-$B101+1) | AJ101: =$C101*INDEX(Curves!$P$8:$P$68,AJ$4-$B101+1) | AK101: =$C101*INDEX(Curves!$P$8:$P$68,AK$4-$B101+1) | AL101: =$C101*INDEX(Curves!$P$8:$P$68,AL$4-$B101+1) | AM101: =$C101*INDEX(Curves!$P$8:$P$68,AM$4-$B101+1) | AN101: =$C101*INDEX(Curves!$P$8:$P$68,AN$4-$B101+1) | AO101: =$C101*INDEX(Curves!$P$8:$P$68,AO$4-$B101+1) | ... BL101: =$C101*INDEX(Curves!$P$8:$P$68,BL$4-$B101+1)
A102: Cohort month 30 | B102: 30 | C102: =INDEX(Ops!$E$24:$BL$24,1,$B102) | AI102: =$C102*INDEX(Curves!$P$8:$P$68,AI$4-$B102+1) | AJ102: =$C102*INDEX(Curves!$P$8:$P$68,AJ$4-$B102+1) | AK102: =$C102*INDEX(Curves!$P$8:$P$68,AK$4-$B102+1) | AL102: =$C102*INDEX(Curves!$P$8:$P$68,AL$4-$B102+1) | AM102: =$C102*INDEX(Curves!$P$8:$P$68,AM$4-$B102+1) | AN102: =$C102*INDEX(Curves!$P$8:$P$68,AN$4-$B102+1) | AO102: =$C102*INDEX(Curves!$P$8:$P$68,AO$4-$B102+1) | AP102: =$C102*INDEX(Curves!$P$8:$P$68,AP$4-$B102+1) | ... BL102: =$C102*INDEX(Curves!$P$8:$P$68,BL$4-$B102+1)
A103: Cohort month 31 | B103: 31 | C103: =INDEX(Ops!$E$24:$BL$24,1,$B103) | AJ103: =$C103*INDEX(Curves!$P$8:$P$68,AJ$4-$B103+1) | AK103: =$C103*INDEX(Curves!$P$8:$P$68,AK$4-$B103+1) | AL103: =$C103*INDEX(Curves!$P$8:$P$68,AL$4-$B103+1) | AM103: =$C103*INDEX(Curves!$P$8:$P$68,AM$4-$B103+1) | AN103: =$C103*INDEX(Curves!$P$8:$P$68,AN$4-$B103+1) | AO103: =$C103*INDEX(Curves!$P$8:$P$68,AO$4-$B103+1) | AP103: =$C103*INDEX(Curves!$P$8:$P$68,AP$4-$B103+1) | AQ103: =$C103*INDEX(Curves!$P$8:$P$68,AQ$4-$B103+1) | ... BL103: =$C103*INDEX(Curves!$P$8:$P$68,BL$4-$B103+1)
...

Sheet Cohort_P3
A1: Cohort (vintage) matrix - P3 SHS with TV (Tier 3)
A2: Rows = sales cohort (month of sale); columns = calendar month. Cohort size in column C.
A4: Month # | D4: Opening | E4: =Timeline!E4 | F4: =Timeline!F4 | G4: =Timeline!G4 | H4: =Timeline!H4 | I4: =Timeline!I4 | J4: =Timeline!J4 | K4: =Timeline!K4 | L4: =Timeline!L4 | ... BL4: =Timeline!BL4
A5: Period end | E5: =Timeline!E5 | F5: =Timeline!F5 | G5: =Timeline!G5 | H5: =Timeline!H5 | I5: =Timeline!I5 | J5: =Timeline!J5 | K5: =Timeline!K5 | L5: =Timeline!L5 | ... BL5: =Timeline!BL5
A6: Year # | E6: =Timeline!E6 | F6: =Timeline!F6 | G6: =Timeline!G6 | H6: =Timeline!H6 | I6: =Timeline!I6 | J6: =Timeline!J6 | K6: =Timeline!K6 | L6: =Timeline!L6 | ... BL6: =Timeline!BL6
A8: Instalments collected by cohort (LCY)
